Workbook

Sheet Enterprise
D2: =TEXT(D4, "mmm-yy") -> Apr-26 | E2: =TEXT(E4, "mmm-yy") -> May-26 | F2: =TEXT(F4, "mmm-yy") -> Jun-26 | G2: =TEXT(G4, "mmm-yy") -> Jul-26 | H2: =TEXT(H4, "mmm-yy") -> Aug-26 | I2: =TEXT(I4, "mmm-yy") -> Sep-26 | J2: =TEXT(J4, "mmm-yy") -> Oct-26 | K2: =TEXT(K4, "mmm-yy") -> Nov-26 | ... O2: =TEXT(O4, "mmm-yy") -> Mar-27
D3: 30 | E3: 31 | F3: 30 | G3: 0 | H3: 0 | I3: 0 | J3: 0 | K3: 0 | L3: 0 | M3: 0 | N3: 0 | O3: 0 | P3: =SUM(D3:O3) -> 91
C4: Marketplace (Enterprise) | D4: 46113 | E4: 46143 | F4: 46174 | G4: 46204 | H4: 46235 | I4: 46266 | J4: 46296 | K4: 46327 | L4: 46357 | M4: 46388 | N4: 46419 | O4: 46447 | P4: FY 2026-27 | W4: Apr | X4: May
C5: Quantity (MT) | D5: 202.396 | E5: 162.374 | F5: 213.291 | G5: =SUMIFS(Details!$BB$4:$BB$243,Details!$C$4:$C$243,Enterprise!G$4)/1000 -> 0 | H5: =SUMIFS(Details!$BB$4:$BB$243,Details!$C$4:$C$243,Enterprise!H$4)/1000 -> 0 | I5: =SUMIFS(Details!$BB$4:$BB$243,Details!$C$4:$C$243,Enterprise!I$4)/1000 -> 0 | J5: =SUMIFS(Details!$BB$4:$BB$243,Details!$C$4:$C$243,Enterprise!J$4)/1000 -> 0 | K5: =SUMIFS(Details!$BB$4:$BB$243,Details!$C$4:$C$243,Enterprise!K$4)/1000 -> 0 | L5: =SUMIFS(Details!$BB$4:$BB$243,Details!$C$4:$C$243,Enterprise!L$4)/1000 -> 0 | M5: =SUMIFS(Details!$BB$4:$BB$243,Details!$C$4:$C$243,Enterprise!M$4)/1000 -> 0 | N5: =SUMIFS(Details!$BB$4:$BB$243,Details!$C$4:$C$243,Enterprise!N$4)/1000 -> 0 | O5: =SUMIFS(Details!$BB$4:$BB$243,Details!$C$4:$C$243,Enterprise!O$4)/1000 -> 0 | P5: =SUM(D5:O5) -> 578.061 | Q5: =Details!BB244/1000 -> 578.061 | R5: =P5-Q5 -> 0 | W5: 128151 | X5: 124831
C6: Sales | D6: 3212253.5 | E6: 2824375 | F6: 4640707 | G6: =SUMIFS(Details!$BO$4:$BO$243,Details!$C$4:$C$243,Enterprise!G$4)-G47 -> 0 | H6: =SUMIFS(Details!$BO$4:$BO$243,Details!$C$4:$C$243,Enterprise!H$4)-H47 -> 0 | I6: =SUMIFS(Details!$BO$4:$BO$243,Details!$C$4:$C$243,Enterprise!I$4)-I47 -> 0 | J6: =SUMIFS(Details!$BO$4:$BO$243,Details!$C$4:$C$243,Enterprise!J$4)-J47 -> 0 | K6: =SUMIFS(Details!$BO$4:$BO$243,Details!$C$4:$C$243,Enterprise!K$4)-K47 -> 0 | L6: =SUMIFS(Details!$BO$4:$BO$243,Details!$C$4:$C$243,Enterprise!L$4)-L47 -> 0 | M6: =SUMIFS(Details!$BO$4:$BO$243,Details!$C$4:$C$243,Enterprise!M$4)-M47 -> 0 | N6: =SUMIFS(Details!$BO$4:$BO$243,Details!$C$4:$C$243,Enterprise!N$4)-N47 -> 0 | O6: =SUMIFS(Details!$BO$4:$BO$243,Details!$C$4:$C$243,Enterprise!O$4)-O47 -> 0 | P6: =SUM(D6:O6) -> 10677336 | Q6: =Details!BO244 -> 10677336 | R6: =P6-Q6 -> 0 | W6: 120737 | X6: 111891
C7: Purchases | D7: 2748791 | E7: 2420732 | F7: 4175968 | G7: =SUMIFS(Details!$AM$4:$AM$243,Details!$C$4:$C$243,Enterprise!G$4)-SUMIFS(Details!$AB$4:$AB$243,Details!$C$4:$C$243,Enterprise!G$4) -> 0 | H7: =SUMIFS(Details!$AM$4:$AM$243,Details!$C$4:$C$243,Enterprise!H$4)-SUMIFS(Details!$AB$4:$AB$243,Details!$C$4:$C$243,Enterprise!H$4) -> 0 | I7: =SUMIFS(Details!$AM$4:$AM$243,Details!$C$4:$C$243,Enterprise!I$4)-SUMIFS(Details!$AB$4:$AB$243,Details!$C$4:$C$243,Enterprise!I$4) -> 0 | J7: =SUMIFS(Details!$AM$4:$AM$243,Details!$C$4:$C$243,Enterprise!J$4)-SUMIFS(Details!$AB$4:$AB$243,Details!$C$4:$C$243,Enterprise!J$4) -> 0 | K7: =SUMIFS(Details!$AM$4:$AM$243,Details!$C$4:$C$243,Enterprise!K$4)-SUMIFS(Details!$AB$4:$AB$243,Details!$C$4:$C$243,Enterprise!K$4) -> 0 | L7: =SUMIFS(Details!$AM$4:$AM$243,Details!$C$4:$C$243,Enterprise!L$4)-SUMIFS(Details!$AB$4:$AB$243,Details!$C$4:$C$243,Enterprise!L$4) -> 0 | M7: =SUMIFS(Details!$AM$4:$AM$243,Details!$C$4:$C$243,Enterprise!M$4)-SUMIFS(Details!$AB$4:$AB$243,Details!$C$4:$C$243,Enterprise!M$4) -> 0 | N7: =SUMIFS(Details!$AM$4:$AM$243,Details!$C$4:$C$243,Enterprise!N$4)-SUMIFS(Details!$AB$4:$AB$243,Details!$C$4:$C$243,Enterprise!N$4) -> 0 | O7: =SUMIFS(Details!$AM$4:$AM$243,Details!$C$4:$C$243,Enterprise!O$4)-SUMIFS(Details!$AB$4:$AB$243,Details!$C$4:$C$243,Enterprise!O$4) -> 0 | P7: =SUM(D7:O7) -> 9345491 | Q7: =Details!P245 -> 9345491 | R7: =P7-Q7 -> 0 | W7: 13200 | X7: 10800
C8: Gross Margin | D8: =D6-D7 -> 463462.5 | E8: =E6-E7 -> 403643 | F8: =F6-F7 -> 464739 | G8: =G6-G7 -> 0 | H8: =H6-H7 -> 0 | I8: =I6-I7 -> 0 | J8: =J6-J7 -> 0 | K8: =K6-K7 -> 0 | ... O8: =O6-O7 -> 0 | P8: =SUM(D8:O8) -> 1331844.5 | Y8: 10725 | Z8: 18150
C9: Gross Margin (%) | D9: =IFERROR((D8/D6),0) -> 0.14427955 | E9: =IFERROR((E8/E6),0) -> 0.1429141 | F9: =IFERROR((F8/F6),0) -> 0.10014401 | G9: =IFERROR((G8/G6),0) -> 0 | H9: =IFERROR((H8/H6),0) -> 0 | I9: =IFERROR((I8/I6),0) -> 0 | J9: =IFERROR((J8/J6),0) -> 0 | K9: =IFERROR((K8/K6),0) -> 0 | ... P9: =IFERROR((P8/P6),0) -> 0.12473566 | Y9: 13527 | Z9: 1100
C10: Transportation Charges | D10: =SUMIFS(Details!$AB$4:$AB$243,Details!$C$4:$C$243,Enterprise!D$4) -> 0 | E10: =SUMIFS(Details!$AB$4:$AB$243,Details!$C$4:$C$243,Enterprise!E$4) -> 0 | F10: =SUMIFS(Details!$AB$4:$AB$243,Details!$C$4:$C$243,Enterprise!F$4) -> 0 | G10: =SUMIFS(Details!$AB$4:$AB$243,Details!$C$4:$C$243,Enterprise!G$4) -> 0 | H10: =SUMIFS(Details!$AB$4:$AB$243,Details!$C$4:$C$243,Enterprise!H$4) -> 0 | I10: =SUMIFS(Details!$AB$4:$AB$243,Details!$C$4:$C$243,Enterprise!I$4) -> 0 | J10: =SUMIFS(Details!$AB$4:$AB$243,Details!$C$4:$C$243,Enterprise!J$4) -> 0 | K10: =SUMIFS(Details!$AB$4:$AB$243,Details!$C$4:$C$243,Enterprise!K$4) -> 0 | ... O10: =SUMIFS(Details!$AB$4:$AB$243,Details!$C$4:$C$243,Enterprise!O$4) -> 0 | P10: =SUM(D10:O10) -> 0 | Q10: =Details!AB244 -> 0 | R10: =P10-Q10 -> 0 | W10: =SUM(W5:W9) -> 262088 | X10: =SUM(X5:X9) -> 247522
C11: Operational Cost | D11: =SUMIFS(Details!$AC:$AC,Details!$C:$C,Enterprise!D$4) -> 249453.07 | E11: =SUMIFS(Details!$AC:$AC,Details!$C:$C,Enterprise!E$4) -> 200125.95 | F11: =SUMIFS(Details!$AC:$AC,Details!$C:$C,Enterprise!F$4) -> 336776.48 | G11: =SUMIFS(Details!$AC:$AC,Details!$C:$C,Enterprise!G$4) -> 0 | H11: =SUMIFS(Details!$AC:$AC,Details!$C:$C,Enterprise!H$4) -> 0 | I11: =SUMIFS(Details!$AC:$AC,Details!$C:$C,Enterprise!I$4) -> 0 | J11: =SUMIFS(Details!$AC:$AC,Details!$C:$C,Enterprise!J$4) -> 0 | K11: =SUMIFS(Details!$AC:$AC,Details!$C:$C,Enterprise!K$4) -> 0 | ... O11: =SUMIFS(Details!$AC:$AC,Details!$C:$C,Enterprise!O$4) -> 0 | P11: =SUM(D11:O11) -> 786355.5 | W11: =W10-D11 -> 12634.93 | X11: =X10-E11 -> 47396.045
C12: Net Margin | D12: =D6-D7-D10-D11 -> 214009.43 | E12: =E6-E7-E10-E11 -> 203517.05 | F12: =F6-F7-F10-F11 -> 127962.52 | G12: =G6-G7-G10-G11 -> 0 | H12: =H6-H7-H10-H11 -> 0 | I12: =I6-I7-I10-I11 -> 0 | J12: =J6-J7-J10-J11 -> 0 | K12: =K6-K7-K10-K11 -> 0 | ... O12: =O6-O7-O10-O11 -> 0 | P12: =SUM(D12:O12) -> 545489
C13: Net Margin (%) | D13: =IFERROR((D12/D6),0) -> 0.066622833 | E13: =IFERROR((E12/E6),0) -> 0.072057374 | F13: =IFERROR((F12/F6),0) -> 0.027573929 | G13: =IFERROR((G12/G6),0) -> 0 | H13: =IFERROR((H12/H6),0) -> 0 | I13: =IFERROR((I12/I6),0) -> 0 | J13: =IFERROR((J12/J6),0) -> 0 | K13: =IFERROR((K12/K6),0) -> 0 | ... P13: =IFERROR((P12/P6),0) -> 0.051088495
C14: Other Income | D14: 0 | E14: 0 | F14: 0 | G14: 0 | H14: 0 | I14: 0 | J14: 0 | K14: 0 | L14: 0 | M14: 0 | N14: 0 | O14: 0 | P14: =SUM(D14:O14) -> 0
C15: Transport Charges (%) | D15: =IFERROR((D10/D6),0) -> 0 | E15: =IFERROR((E10/E6),0) -> 0 | F15: =IFERROR((F10/F6),0) -> 0 | G15: =IFERROR((G10/G6),0) -> 0 | H15: =IFERROR((H10/H6),0) -> 0 | I15: =IFERROR((I10/I6),0) -> 0 | J15: =IFERROR((J10/J6),0) -> 0 | K15: =IFERROR((K10/K6),0) -> 0 | ... P15: =IFERROR((P10/P6),0) -> 0
C16: Revenue Per Kg | D16: =+D6/(D5*1000) -> 15.871131 | E16: =+E6/(E5*1000) -> 17.394256 | F16: =+F6/(F5*1000) -> 21.757632 | G16: =+G6/(G5*1000) -> #DIV/0! | H16: =+H6/(H5*1000) -> #DIV/0! | I16: =+I6/(I5*1000) -> #DIV/0! | J16: =+J6/(J5*1000) -> #DIV/0! | K16: =+K6/(K5*1000) -> #DIV/0! | ... P16: =+P6/(P5*1000) -> 18.470949
C17: Purchase Cost Per Kg | D17: =+D7/(D5*1000) -> 13.581252 | E17: =+E7/(E5*1000) -> 14.908372 | F17: =+F7/(F5*1000) -> 19.578735 | G17: =+G7/(G5*1000) -> #DIV/0! | H17: =+H7/(H5*1000) -> #DIV/0! | I17: =+I7/(I5*1000) -> #DIV/0! | J17: =+J7/(J5*1000) -> #DIV/0! | K17: =+K7/(K5*1000) -> #DIV/0! | ... P17: =+P7/(P5*1000) -> 16.166963
C18: Transportation Charges Per Kg | D18: =D10/(D5*1000) -> 0 | E18: =E10/(E5*1000) -> 0 | F18: =F10/(F5*1000) -> 0 | G18: =G10/(G5*1000) -> #DIV/0! | H18: =H10/(H5*1000) -> #DIV/0! | I18: =I10/(I5*1000) -> #DIV/0! | J18: =J10/(J5*1000) -> #DIV/0! | K18: =K10/(K5*1000) -> #DIV/0! | ... P18: =P10/(P5*1000) -> 0
C19: No. of Transactions | D19: {=IFERROR(ROWS(_xlfn.UNIQUE(_xlfn._xlws.FILTER(Details!$AO$5:$AO$243, (Details!$C$5:$C$243)=Enterprise!D$2))),0)} -> 65 | E19: {=IFERROR(ROWS(_xlfn.UNIQUE(_xlfn._xlws.FILTER(Details!$AO$5:$AO$243, (Details!$C$5:$C$243)=Enterprise!E$2))),0)} -> 46 | F19: {=IFERROR(ROWS(_xlfn.UNIQUE(_xlfn._xlws.FILTER(Details!$AO$5:$AO$243, (Details!$C$5:$C$243)=Enterprise!F$2))),0)} -> 56 | G19: {=IFERROR(ROWS(_xlfn.UNIQUE(_xlfn._xlws.FILTER(Details!$AO$5:$AO$243, (Details!$C$5:$C$243)=Enterprise!G$2))),0)} -> 0 | H19: {=IFERROR(ROWS(_xlfn.UNIQUE(_xlfn._xlws.FILTER(Details!$AO$5:$AO$243, (Details!$C$5:$C$243)=Enterprise!H$2))),0)} -> 0 | I19: {=IFERROR(ROWS(_xlfn.UNIQUE(_xlfn._xlws.FILTER(Details!$AO$5:$AO$243, (Details!$C$5:$C$243)=Enterprise!I$2))),0)} -> 0 | J19: {=IFERROR(ROWS(_xlfn.UNIQUE(_xlfn._xlws.FILTER(Details!$AO$5:$AO$243, (Details!$C$5:$C$243)=Enterprise!J$2))),0)} -> 0 | K19: {=IFERROR(ROWS(_xlfn.UNIQUE(_xlfn._xlws.FILTER(Details!$AO$5:$AO$243, (Details!$C$5:$C$243)=Enterprise!K$2))),0)} -> 0 | ... O19: {=IFERROR(ROWS(_xlfn.UNIQUE(_xlfn._xlws.FILTER(Details!$AO$5:$AO$243, (Details!$C$5:$C$243)=Enterprise!O$2))),0)} -> 0 | P19: =SUM(D19:O19) -> 167
C20: No. of Sellers (Aggregators) | D20: {=IFERROR(ROWS(_xlfn.UNIQUE(_xlfn._xlws.FILTER(MID(Details!$G$5:$G$243,3,10), (Details!$C$5:$C$243)=Enterprise!D$2))),0)} -> 1 | E20: {=IFERROR(ROWS(_xlfn.UNIQUE(_xlfn._xlws.FILTER(MID(Details!$G$5:$G$243,3,10), (Details!$C$5:$C$243)=Enterprise!E$2))),0)} -> 2 | F20: {=IFERROR(ROWS(_xlfn.UNIQUE(_xlfn._xlws.FILTER(MID(Details!$G$5:$G$243,3,10), (Details!$C$5:$C$243)=Enterprise!F$2))),0)} -> 3 | G20: {=IFERROR(ROWS(_xlfn.UNIQUE(_xlfn._xlws.FILTER(MID(Details!$G$5:$G$243,3,10), (Details!$C$5:$C$243)=Enterprise!G$2))),0)} -> 0 | H20: {=IFERROR(ROWS(_xlfn.UNIQUE(_xlfn._xlws.FILTER(MID(Details!$G$5:$G$243,3,10), (Details!$C$5:$C$243)=Enterprise!H$2))),0)} -> 0 | I20: {=IFERROR(ROWS(_xlfn.UNIQUE(_xlfn._xlws.FILTER(MID(Details!$G$5:$G$243,3,10), (Details!$C$5:$C$243)=Enterprise!I$2))),0)} -> 0 | J20: {=IFERROR(ROWS(_xlfn.UNIQUE(_xlfn._xlws.FILTER(MID(Details!$G$5:$G$243,3,10), (Details!$C$5:$C$243)=Enterprise!J$2))),0)} -> 0 | K20: {=IFERROR(ROWS(_xlfn.UNIQUE(_xlfn._xlws.FILTER(MID(Details!$G$5:$G$243,3,10), (Details!$C$5:$C$243)=Enterprise!K$2))),0)} -> 0 | ... O20: {=IFERROR(ROWS(_xlfn.UNIQUE(_xlfn._xlws.FILTER(MID(Details!$G$5:$G$243,3,10), (Details!$C$5:$C$243)=Enterprise!O$2))),0)} -> 0 | P20: ='AP & AR'!B2 -> 23
C21: No. of Buyers (Recyclers) | D21: {=IFERROR(ROWS(_xlfn.UNIQUE(_xlfn._xlws.FILTER(MID(Details!$AR$5:$AR$243,3,10), (Details!$C$5:$C$243)=Enterprise!D$2))),0)} -> 5 | E21: {=IFERROR(ROWS(_xlfn.UNIQUE(_xlfn._xlws.FILTER(MID(Details!$AR$5:$AR$243,3,10), (Details!$C$5:$C$243)=Enterprise!E$2))),0)} -> 3 | F21: {=IFERROR(ROWS(_xlfn.UNIQUE(_xlfn._xlws.FILTER(MID(Details!$AR$5:$AR$243,3,10), (Details!$C$5:$C$243)=Enterprise!F$2))),0)} -> 4 | G21: {=IFERROR(ROWS(_xlfn.UNIQUE(_xlfn._xlws.FILTER(MID(Details!$AR$5:$AR$243,3,10), (Details!$C$5:$C$243)=Enterprise!G$2))),0)} -> 0 | H21: {=IFERROR(ROWS(_xlfn.UNIQUE(_xlfn._xlws.FILTER(MID(Details!$AR$5:$AR$243,3,10), (Details!$C$5:$C$243)=Enterprise!H$2))),0)} -> 0 | I21: {=IFERROR(ROWS(_xlfn.UNIQUE(_xlfn._xlws.FILTER(MID(Details!$AR$5:$AR$243,3,10), (Details!$C$5:$C$243)=Enterprise!I$2))),0)} -> 0 | J21: {=IFERROR(ROWS(_xlfn.UNIQUE(_xlfn._xlws.FILTER(MID(Details!$AR$5:$AR$243,3,10), (Details!$C$5:$C$243)=Enterprise!J$2))),0)} -> 0 | K21: {=IFERROR(ROWS(_xlfn.UNIQUE(_xlfn._xlws.FILTER(MID(Details!$AR$5:$AR$243,3,10), (Details!$C$5:$C$243)=Enterprise!K$2))),0)} -> 0 | ... O21: {=IFERROR(ROWS(_xlfn.UNIQUE(_xlfn._xlws.FILTER(MID(Details!$AR$5:$AR$243,3,10), (Details!$C$5:$C$243)=Enterprise!O$2))),0)} -> 0 | P21: ='AP & AR'!G2 -> 7
C22: Full Sales Returns (Nos) | D22: 0 | E22: 0 | F22: 0 | G22: 0 | H22: 0 | I22: 0 | J22: 0 | K22: 0 | L22: 0 | M22: 0 | N22: 0 | O22: 0 | P22: =SUM(D22:O22) -> 0
C23: Receivable | D23: 2546227 | E23: 2029170 | F23: 1674994.1 | P23: =F23 -> 1674994.1
C24: DSO (Days) | D24: =IFERROR(((D23/(D6*1.18))*D3),0) -> 20.15239 | E24: =IFERROR(((E23/(E6*1.18))*E3),0) -> 18.874513 | F24: =IFERROR(((F23/(F6*1.18))*F3),0) -> 9.1763165 | G24: =IFERROR(((G23/(G6*1.18))*G3),0) -> 0 | H24: =IFERROR(((H23/(H6*1.18))*H3),0) -> 0 | I24: =IFERROR(((I23/(I6*1.18))*I3),0) -> 0 | J24: =IFERROR(((J23/(J6*1.18))*J3),0) -> 0 | K24: =IFERROR(((K23/(K6*1.18))*K3),0) -> 0 | ... O24: =IFERROR(((O23/(O6*1.18))*O3),0) -> 0 | P24: =IFERROR(((P23)/(P6*1.18)*P3),0) -> 12.097894
C25: Processing Cost | D25: 0 | E25: 0 | F25: 0 | G25: 0 | H25: 0 | I25: 0 | J25: 0 | K25: 0 | L25: 0 | M25: 0 | N25: 0 | O25: 0 | P25: =SUM(D25:O25) -> 0
C26: Finance Cost | D26: 0 | E26: 0 | F26: 0 | G26: 0 | H26: 0 | I26: 0 | J26: 0 | K26: 0 | L26: 0 | M26: 0 | N26: 0 | O26: 0 | P26: =SUM(D26:O26) -> 0
C27: Indirect Expences | D27: 0 | E27: 0 | F27: 0 | G27: 0 | H27: 0 | I27: 0 | J27: 0 | K27: 0 | L27: 0 | M27: 0 | N27: 0 | O27: 0 | P27: =SUM(D27:O27) -> 0
C28: Margin after Opex & Finance Cost | D28: =D12-D27 -> 214009.43 | E28: =E12-E27 -> 203517.05 | F28: =F12-F27 -> 127962.52 | G28: =G12-G27 -> 0 | H28: =H12-H27 -> 0 | I28: =I12-I27 -> 0 | J28: =J12-J27 -> 0 | K28: =K12-K27 -> 0 | ... P28: =P12-P27 -> 545489
C29: CM % | D29: =D28/D6 -> 0.066622833 | E29: =E28/E6 -> 0.072057374 | F29: =F28/F6 -> 0.027573929 | G29: =G28/G6 -> #DIV/0! | H29: =H28/H6 -> #DIV/0! | I29: =I28/I6 -> #DIV/0! | J29: =J28/J6 -> #DIV/0! | K29: =K28/K6 -> #DIV/0! | ... P29: =P28/P6 -> 0.051088495

Sheet IB
C3: =Enterprise!D3 -> 30 | D3: 31 | E3: =Enterprise!F3 -> 30 | F3: =Enterprise!G3 -> 0 | G3: =Enterprise!H3 -> 0 | H3: =Enterprise!I3 -> 0 | I3: =Enterprise!J3 -> 0 | J3: =Enterprise!K3 -> 0 | K3: =Enterprise!L3 -> 0 | L3: =Enterprise!M3 -> 0 | ... N3: =Enterprise!O3 -> 0 | O3: =SUM(C3:N3) -> 91
B4: IB(B2B & Warehouse) | C4: 46113 | D4: 46143 | E4: 46174 | F4: 46204 | G4: 46235 | H4: 46266 | I4: 46296 | J4: 46327 | K4: 46357 | L4: 46388 | M4: 46419 | N4: 46447 | O4: FY 2026-27
B5: Quantity (MT) | C5: =Enterprise!D5+'Processing Centre'!AA5 -> 217.213 | D5: =Enterprise!E5+'Processing Centre'!AB5 -> 319.474 | E5: =Enterprise!F5+'Processing Centre'!AC5 -> 267.056 | O5: =SUM(C5:N5) -> 803.743
B6: Sales | C6: =Enterprise!D6+'Processing Centre'!AA6 -> 4092280.5 | D6: =Enterprise!E6+'Processing Centre'!AB6 -> 7861789.7 | E6: =Enterprise!F6+'Processing Centre'!AC6 -> 6384823 | O6: =SUM(C6:N6) -> 18338893
B7: Purchases | C7: =Enterprise!D7+'Processing Centre'!AA7 -> 3558699.2 | D7: =Enterprise!E7+'Processing Centre'!AB7 -> 7174755.9 | E7: =Enterprise!F7+'Processing Centre'!AC7 -> 5652950.9 | O7: =SUM(C7:N7) -> 16386406
B8: Gross Margin | C8: =C6-C7 -> 533581.29 | D8: =D6-D7 -> 687033.75 | E8: =E6-E7 -> 731872.12 | O8: =SUM(C8:N8) -> 1952487.2
B9: Gross Margin (%) | C9: =IFERROR((C8/C6),0) -> 0.13038727 | D9: =IFERROR((D8/D6),0) -> 0.087388976 | E9: =IFERROR((E8/E6),0) -> 0.11462685 | O9: =IFERROR((O8/O6),0) -> 0.10646701
B10: Transportation Charges | C10: ='Processing Centre'!AA10+Enterprise!D10 -> 0 | D10: ='Processing Centre'!AB10+Enterprise!E10 -> 0 | E10: ='Processing Centre'!AC10+Enterprise!F10 -> 0 | O10: =SUM(C10:N10) -> 0
B11: Operational Cost | C11: ='Processing Centre'!AA11+Enterprise!D11 -> 653123.07 | D11: ='Processing Centre'!AB11+Enterprise!E11 -> 413045.95 | E11: ='Processing Centre'!AC11+Enterprise!F11 -> 853956.48 | O11: =SUM(C11:N11) -> 1920125.5
B12: Net Margin | C12: =C6-C7-C10-C11 -> -119541.78 | D12: =D6-D7-D10-D11 -> 273987.8 | E12: =E6-E7-E10-E11 -> -122084.35 | O12: =SUM(C12:N12) -> 32361.663
B13: Net Margin (%) | C13: =IFERROR((C12/C6),0) -> -0.029211531 | D13: =IFERROR((D12/D6),0) -> 0.034850563 | E13: =IFERROR((E12/E6),0) -> -0.019121024 | O13: =IFERROR((O12/O6),0) -> 0.0017646464
B14: Other Income | C14: =Enterprise!D14+'Processing Centre'!AA14 -> 0 | D14: =Enterprise!E14+'Processing Centre'!AB14 -> 0 | E14: =Enterprise!F14+'Processing Centre'!AC14 -> 0 | O14: =SUM(C14:N14) -> 0
B15: Transport Charges (%) | C15: =IFERROR((C10/C6),0) -> 0 | D15: =IFERROR((D10/D6),0) -> 0 | E15: =IFERROR((E10/E6),0) -> 0 | O15: =IFERROR((O10/O6),0) -> 0
B16: Revenue Per Kg | C16: =+C6/(C5*1000) -> 18.839943 | D16: =+D6/(D5*1000) -> 24.608543 | E16: =+E6/(E5*1000) -> 23.90818 | O16: =+O6/(O5*1000) -> 22.816862
B17: Purchase Cost Per Kg | C17: =+C7/(C5*1000) -> 16.383454 | D17: =+D7/(D5*1000) -> 22.458028 | E17: =+E7/(E5*1000) -> 21.167661 | O17: =+O7/(O5*1000) -> 20.387619
B18: Transportation Charges Per Kg | C18: =C10/(C5*1000) -> 0 | D18: =D10/(D5*1000) -> 0 | E18: =E10/(E5*1000) -> 0 | O18: =O10/(O5*1000) -> 0
B19: No. of Transactions | C19: ='Processing Centre'!AA19+Enterprise!D19 -> 69 | D19: ='Processing Centre'!AB19+Enterprise!E19 -> 49 | E19: ='Processing Centre'!AC19+Enterprise!F19 -> 56 | O19: =SUM(C19:N19) -> 174
B20: No. of Sellers (Aggregators) | C20: ='Processing Centre'!AA20+Enterprise!D20 -> 4 | D20: ='Processing Centre'!AB20+Enterprise!E20 -> 4 | E20: ='Processing Centre'!AC20+Enterprise!F20 -> 3 | O20: ='AP & AR'!C22 -> 20
B21: No. of Buyers (Recyclers) | C21: ='Processing Centre'!AA21+Enterprise!D21 -> 8 | D21: ='Processing Centre'!AB21+Enterprise!E21 -> 5 | E21: ='Processing Centre'!AC21+Enterprise!F21 -> 4 | O21: ='AP & AR'!B22 -> 7
B22: Full Sales Returns (Nos) | C22: ='Processing Centre'!AA22+Enterprise!D22 -> 0 | D22: ='Processing Centre'!AB22+Enterprise!E22 -> 0 | E22: ='Processing Centre'!AC22+Enterprise!F22 -> 0 | O22: =SUM(C22:N22) -> 0
B23: Receivable | C23: =Enterprise!D23+'Processing Centre'!AA23 -> 6579198.9 | D23: 6008355.5 | E23: 3653279.7 | O23: =E23 -> 3653279.7
B24: DSO (Days) | C24: =IFERROR(((C23/(C6*1.18))*C3),0) -> 40.873974 | D24: =IFERROR(((D23/(D6*1.18))*D3),0) -> 20.077697 | E24: =IFERROR(((E23/(E6*1.18))*E3),0) -> 14.546996 | O24: =IFERROR(((O23/(O6*1.18))*O3),0) -> 15.362758
B25: Finance Cost | C25: ='Processing Centre'!AA25 -> 17250.437 | D25: ='Processing Centre'!AB25 -> 21592.228 | E25: ='Processing Centre'!AC25 -> 6891.7351 | O25: =SUM(C25:N25) -> 45734.4
B26: Indirect Expences | C26: ='Processing Centre'!AA26 -> 254388.13 | D26: ='Processing Centre'!AB26 -> 312234.81 | E26: ='Processing Centre'!AC26 -> 161501.44 | O26: =SUM(C26:N26) -> 728124.38
B27: Margin after Opex & Finance Cost | C27: ='Processing Centre'!AA27 -> -605189.77 | D27: ='Processing Centre'!AB27 -> -263356.29 | E27: ='Processing Centre'!AC27 -> -418440.06 | O27: =SUM(C27:N27) -> -1286986.1
B28: CM % | C28: =C27/C6 -> -0.1478857 | D28: =D27/D6 -> -0.033498262 | E28: =E27/E6 -> -0.065536673 | O28: =O27/O6 -> -0.070177961

Sheet Processing Centre
C3: 0 | D3: 0 | E3: 0 | F3: 0 | G3: 0 | H3: 0 | I3: 0 | J3: 0 | K3: 30 | L3: 31 | M3: 28 | N3: 31 | O3: 30 | P3: 31 | Q3: 30 | R3: 31 | S3: 31 | T3: 30 | U3: 31 | V3: 30 | W3: 31 | X3: 31 | Y3: 28 | Z3: 31 | AA3: 30 | AB3: 31 | AC3: 30 | AD3: =SUM(C3:AC3) -> 576 | AE3: =SUM(C3:N3) -> 120 | AF3: =SUM(O3:Z3) -> 365 | AG3: =SUM(AA3:AC3) -> 91
B4: Marketplace Warehouse(IB) | C4: Apr-24 | D4: May-24 | E4: Jun-24 | F4: Jul-24 | G4: Aug-24 | H4: Sep-24 | I4: Oct-24 | J4: Nov-24 | K4: Dec-24 | L4: Jan-25 | M4: Feb-25 | N4: 45717 | O4: Apr-25 | P4: May-25 | Q4: Jun-25 | R4: Jul-25 | S4: Aug-25 | T4: Sep-25 | U4: Oct-25 | V4: Nov-25 | W4: Dec-25 | X4: Jan-26 | Y4: Feb-26 | Z4: Mar-26 | AA4: Apr-26 | AB4: May-26 | AC4: 46174 | AD4: Till Date | AE4: FY 2024-25 | AF4: FY 2025-26 | AG4: FY 2026-27
B5: Quantity (MT) | C5: =SUMIFS('Details PC'!$AE$7:$AE$421,'Details PC'!$W$7:$W$421,'Processing Centre'!C$4)/1000 -> 0 | D5: =SUMIFS('Details PC'!$AE$7:$AE$421,'Details PC'!$W$7:$W$421,'Processing Centre'!D$4)/1000 -> 0 | E5: =SUMIFS('Details PC'!$AE$7:$AE$421,'Details PC'!$W$7:$W$421,'Processing Centre'!E$4)/1000 -> 0 | F5: =SUMIFS('Details PC'!$AE$7:$AE$421,'Details PC'!$W$7:$W$421,'Processing Centre'!F$4)/1000 -> 0 | G5: =SUMIFS('Details PC'!$AE$7:$AE$421,'Details PC'!$W$7:$W$421,'Processing Centre'!G$4)/1000 -> 0 | H5: =SUMIFS('Details PC'!$AE$7:$AE$421,'Details PC'!$W$7:$W$421,'Processing Centre'!H$4)/1000 -> 0 | I5: =SUMIFS('Details PC'!$AE$7:$AE$421,'Details PC'!$W$7:$W$421,'Processing Centre'!I$4)/1000 -> 0 | J5: =SUMIFS('Details PC'!$AE$7:$AE$421,'Details PC'!$W$7:$W$421,'Processing Centre'!J$4)/1000 -> 0 | K5: =SUMIFS('Details PC'!$AK$5:$AK$421,'Details PC'!$W$5:$W$421,'Processing Centre'!K$4)/1000 -> 70.8 | L5: =SUMIFS('Details PC'!$AK$5:$AK$421,'Details PC'!$W$5:$W$421,'Processing Centre'!L$4)/1000 -> 51.56 | M5: =SUMIFS('Details PC'!$AK$5:$AK$421,'Details PC'!$W$5:$W$421,'Processing Centre'!M$4)/1000 -> 82.5237 | N5: =SUMIFS('Details PC'!$AK$5:$AK$421,'Details PC'!$W$5:$W$421,'Processing Centre'!N$4)/1000 -> 205.41 | O5: =SUMIFS('Details PC'!$AK$5:$AK$421,'Details PC'!$W$5:$W$421,'Processing Centre'!O$4)/1000 -> 240.65 | P5: =SUMIFS('Details PC'!$AK$5:$AK$421,'Details PC'!$W$5:$W$421,'Processing Centre'!P$4)/1000 -> 77.855 | Q5: =SUMIFS('Details PC'!$AK$5:$AK$421,'Details PC'!$W$5:$W$421,'Processing Centre'!Q$4)/1000 -> 263.19 | R5: =SUMIFS('Details PC'!$AK$5:$AK$421,'Details PC'!$W$5:$W$421,'Processing Centre'!R$4)/1000 -> 291.8 | ... Z5: =SUMIFS('Details PC'!$AK$5:$AK$421,'Details PC'!$W$5:$W$421,'Processing Centre'!Z$4)/1000 -> 148.3172 | AA5: 14.817 | AB5: 157.1 | AC5: 53.765 | AD5: =SUM(C5:AB5) -> 4644.5129 | AE5: =SUM(C5:N5) -> 410.2937 | AF5: =SUM(O5:Z5) -> 4062.3022 | AG5: =SUM(AA5:AC5) -> 225.682
B6: Sales | C6: =SUMIFS('Details PC'!$AG$5:$AG$421,'Details PC'!$W$5:$W$421,'Processing Centre'!C$4)+SUMIFS('Details PC'!$AH$5:$AH$421,'Details PC'!$W$5:$W$421,'Processing Centre'!C$4) -> 0 | D6: =SUMIFS('Details PC'!$AG$5:$AG$421,'Details PC'!$W$5:$W$421,'Processing Centre'!D$4)+SUMIFS('Details PC'!$AH$5:$AH$421,'Details PC'!$W$5:$W$421,'Processing Centre'!D$4) -> 0 | E6: =SUMIFS('Details PC'!$AG$5:$AG$421,'Details PC'!$W$5:$W$421,'Processing Centre'!E$4)+SUMIFS('Details PC'!$AH$5:$AH$421,'Details PC'!$W$5:$W$421,'Processing Centre'!E$4) -> 0 | F6: =SUMIFS('Details PC'!$AG$5:$AG$421,'Details PC'!$W$5:$W$421,'Processing Centre'!F$4)+SUMIFS('Details PC'!$AH$5:$AH$421,'Details PC'!$W$5:$W$421,'Processing Centre'!F$4) -> 0 | G6: =SUMIFS('Details PC'!$AG$5:$AG$421,'Details PC'!$W$5:$W$421,'Processing Centre'!G$4)+SUMIFS('Details PC'!$AH$5:$AH$421,'Details PC'!$W$5:$W$421,'Processing Centre'!G$4) -> 0 | H6: =SUMIFS('Details PC'!$AG$5:$AG$421,'Details PC'!$W$5:$W$421,'Processing Centre'!H$4)+SUMIFS('Details PC'!$AH$5:$AH$421,'Details PC'!$W$5:$W$421,'Processing Centre'!H$4) -> 0 | I6: =SUMIFS('Details PC'!$AG$5:$AG$421,'Details PC'!$W$5:$W$421,'Processing Centre'!I$4)+SUMIFS('Details PC'!$AH$5:$AH$421,'Details PC'!$W$5:$W$421,'Processing Centre'!I$4) -> 0 | J6: =SUMIFS('Details PC'!$AG$5:$AG$421,'Details PC'!$W$5:$W$421,'Processing Centre'!J$4)+SUMIFS('Details PC'!$AH$5:$AH$421,'Details PC'!$W$5:$W$421,'Processing Centre'!J$4) -> 0 | ... Z6: =SUMIFS('Details PC'!$AG$5:$AG$421,'Details PC'!$W$5:$W$421,'Processing Centre'!Z$4)+SUMIFS('Details PC'!$AH$5:$AH$421,'Details PC'!$W$5:$W$421,'Processing Centre'!Z$4) -> 5118069.8 | AA6: 880027 | AB6: 5037414.7 | AC6: 1744116 | AD6: =SUM(C6:AB6) -> 1.6688297e+08 | AE6: =SUM(C6:N6) -> 15977724 | AF6: =SUM(O6:Z6) -> 1.449878e+08 | AG6: =SUM(AA6:AC6) -> 7661557.7
B7: Purchases | C7: =SUMIFS('Details PC'!$AL$5:$AL$421,'Details PC'!$W$5:$W$421,'Processing Centre'!C$4) -> 0 | D7: =SUMIFS('Details PC'!$AL$5:$AL$421,'Details PC'!$W$5:$W$421,'Processing Centre'!D$4) -> 0 | E7: =SUMIFS('Details PC'!$AL$5:$AL$421,'Details PC'!$W$5:$W$421,'Processing Centre'!E$4) -> 0 | F7: =SUMIFS('Details PC'!$AL$5:$AL$421,'Details PC'!$W$5:$W$421,'Processing Centre'!F$4) -> 0 | G7: =SUMIFS('Details PC'!$AL$5:$AL$421,'Details PC'!$W$5:$W$421,'Processing Centre'!G$4) -> 0 | H7: =SUMIFS('Details PC'!$AL$5:$AL$421,'Details PC'!$W$5:$W$421,'Processing Centre'!H$4) -> 0 | I7: =SUMIFS('Details PC'!$AL$5:$AL$421,'Details PC'!$W$5:$W$421,'Processing Centre'!I$4) -> 0 | J7: =SUMIFS('Details PC'!$AL$5:$AL$421,'Details PC'!$W$5:$W$421,'Processing Centre'!J$4) -> 0 | ... Z7: =SUMIFS('Details PC'!$AL$5:$AL$421,'Details PC'!$W$5:$W$421,'Processing Centre'!Z$4) -> 4889984.8 | AA7: 809908.21 | AB7: 4754023.9 | AC7: 1476982.9 | AD7: =SUM(C7:AB7) -> 1.5833101e+08 | AE7: =SUM(C7:N7) -> 13550583 | AF7: =SUM(O7:Z7) -> 1.392165e+08 | AG7: =SUM(AA7:AC7) -> 7040915
B8: Gross Margin | C8: =IFERROR((C6-C7),0) -> 0 | D8: =IFERROR((D6-D7),0) -> 0 | E8: =IFERROR((E6-E7),0) -> 0 | F8: =IFERROR((F6-F7),0) -> 0 | G8: =IFERROR((G6-G7),0) -> 0 | H8: =IFERROR((H6-H7),0) -> 0 | I8: =IFERROR((I6-I7),0) -> 0 | J8: =IFERROR((J6-J7),0) -> 0 | ... AC8: =IFERROR((AC6-AC7),0) -> 267133.12 | AD8: =SUM(C8:AB8) -> 8551954.3 | AE8: =IFERROR((AE6-AE7),0) -> 2427141.5 | AF8: =AF6-AF7 -> 5771303.2 | AG8: =SUM(AA8:AC8) -> 620642.66
B9: Gross Margin (%) | C9: =IFERROR((C8/C6),0) -> 0 | D9: =IFERROR((D8/D6),0) -> 0 | E9: =IFERROR((E8/E6),0) -> 0 | F9: =IFERROR((F8/F6),0) -> 0 | G9: =IFERROR((G8/G6),0) -> 0 | H9: =IFERROR((H8/H6),0) -> 0 | I9: =IFERROR((I8/I6),0) -> 0 | J9: =IFERROR((J8/J6),0) -> 0 | ... AG9: =IFERROR((AG8/AG6),0) -> 0.081007373
B10: Transportation Charges | C10: 0 | D10: 0 | E10: 0 | F10: 0 | G10: 0 | H10: 0 | I10: 0 | J10: 0 | K10: 0 | L10: 0 | M10: 0 | N10: 0 | O10: 0 | P10: 0 | Q10: 0 | R10: 0 | S10: 0 | T10: 0 | U10: 0 | V10: 0 | W10: 0 | X10: 0 | Y10: 0 | Z10: 0 | AA10: 0 | AB10: 0 | AC10: 0 | AD10: =SUM(C10:AA10) -> 0 | AE10: =SUM(K10:N10) -> 0 | AF10: =SUM(O10:Z10) -> 0 | AG10: =AA10 -> 0
B11: Processing Cost | K11: =SUMIFS('Details PC'!$T:$T,'Details PC'!$D:$D,'Processing Centre'!K4,'Details PC'!$E:$E,"Operational Cost") -> 200000 | L11: =SUMIFS('Details PC'!$T:$T,'Details PC'!$D:$D,'Processing Centre'!L4,'Details PC'!$E:$E,"Operational Cost") -> 750000 | M11: =SUMIFS('Details PC'!$T:$T,'Details PC'!$D:$D,'Processing Centre'!M4,'Details PC'!$E:$E,"Operational Cost") -> 43000 | N11: =SUMIFS('Details PC'!$T:$T,'Details PC'!$D:$D,'Processing Centre'!N4,'Details PC'!$E:$E,"Operational Cost") -> 112605 | O11: =SUMIFS('Details PC'!$T:$T,'Details PC'!$D:$D,'Processing Centre'!O4,'Details PC'!$E:$E,"Operational Cost") -> 5700 | P11: =SUMIFS('Details PC'!$T:$T,'Details PC'!$D:$D,'Processing Centre'!P4,'Details PC'!$E:$E,"Operational Cost") -> 636817 | Q11: =SUMIFS('Details PC'!$T:$T,'Details PC'!$D:$D,'Processing Centre'!Q4,'Details PC'!$E:$E,"Operational Cost") -> 544481 | R11: =SUMIFS('Details PC'!$T:$T,'Details PC'!$D:$D,'Processing Centre'!R4,'Details PC'!$E:$E,"Operational Cost") -> 1264704 | ... AC11: =SUMIFS('Details PC'!$T:$T,'Details PC'!$D:$D,'Processing Centre'!AC4,'Details PC'!$E:$E,"Operational Cost") -> 517180 | AD11: =SUM(C11:AB11) -> 14637341 | AE11: =SUM(C11:N11) -> 1105605 | AF11: =SUM(O11:Z11) -> 12915146 | AG11: =SUM(AA11:AC11) -> 1133770
B12: Net Margin | C12: =C8-C11 -> 0 | D12: =D8-D11 -> 0 | E12: =E8-E11 -> 0 | F12: =F8-F11 -> 0 | G12: =G8-G11 -> 0 | H12: =H8-H11 -> 0 | I12: =I8-I11 -> 0 | J12: =J8-J11 -> 0 | ... AC12: =AC8-AC11 -> -250046.88 | AD12: =SUM(C12:AB12) -> -6085387.2 | AE12: =AE8-AE11 -> 1321536.5 | AF12: =AF8-AF11 -> -7143843.2 | AG12: =SUM(AA12:AC12) -> -513127.34
B13: Net Margin (%) | C13: =IFERROR((C12/C6),0) -> 0 | D13: =IFERROR((D12/D6),0) -> 0 | E13: =IFERROR((E12/E6),0) -> 0 | F13: =IFERROR((F12/F6),0) -> 0 | G13: =IFERROR((G12/G6),0) -> 0 | H13: =IFERROR((H12/H6),0) -> 0 | I13: =IFERROR((I12/I6),0) -> 0 | J13: =IFERROR((J12/J6),0) -> 0 | ... AG13: =IFERROR((AG12/AG6),0) -> -0.066974284
B14: Other Income | C14: 0 | D14: 0 | E14: 0 | F14: 0 | G14: 0 | H14: 0 | I14: 0 | J14: 0 | K14: 0 | L14: 0 | M14: 0 | N14: 0 | O14: 0 | P14: 0 | Q14: 0 | R14: 0 | S14: 0 | T14: 0 | U14: 0 | V14: 0 | W14: 0 | X14: 0 | Y14: 0 | Z14: 0 | AA14: 0 | AB14: 0 | AC14: 0 | AD14: 0 | AE14: 0 | AF14: 0 | AG14: =AA14 -> 0
B15: Transport Charges (%) | C15: =IFERROR((C10/C6),0) -> 0 | D15: =IFERROR((D10/D6),0) -> 0 | E15: =IFERROR((E10/E6),0) -> 0 | F15: =IFERROR((F10/F6),0) -> 0 | G15: =IFERROR((G10/G6),0) -> 0 | H15: =IFERROR((H10/H6),0) -> 0 | I15: =IFERROR((I10/I6),0) -> 0 | J15: =IFERROR((J10/J6),0) -> 0 | ... AF15: =IFERROR((AF10/AF6),0) -> 0 | AG15: =AA15 -> 0
B16: Revenue Per Kg | C16: =IFERROR(+C6/(C5*1000),0) -> 0 | D16: =IFERROR(+D6/(D5*1000),0) -> 0 | E16: =IFERROR(+E6/(E5*1000),0) -> 0 | F16: =IFERROR(+F6/(F5*1000),0) -> 0 | G16: =IFERROR(+G6/(G5*1000),0) -> 0 | H16: =IFERROR(+H6/(H5*1000),0) -> 0 | I16: =IFERROR(+I6/(I5*1000),0) -> 0 | J16: =IFERROR(+J6/(J5*1000),0) -> 0 | ... AF16: =IFERROR(+AF6/(AF5*1000),0) -> 35.691043 | AG16: =+AG6/(AG5*1000) -> 33.948466
B17: Purchase Cost Per Kg | C17: =IFERROR(+C7/(C5*1000),0) -> 0 | D17: =IFERROR(+D7/(D5*1000),0) -> 0 | E17: =IFERROR(+E7/(E5*1000),0) -> 0 | F17: =IFERROR(+F7/(F5*1000),0) -> 0 | G17: =IFERROR(+G7/(G5*1000),0) -> 0 | H17: =IFERROR(+H7/(H5*1000),0) -> 0 | I17: =IFERROR(+I7/(I5*1000),0) -> 0 | J17: =IFERROR(+J7/(J5*1000),0) -> 0 | ... AF17: =IFERROR(+AF7/(AF5*1000),0) -> 34.270345 | AG17: =+AG7/(AG5*1000) -> 31.19839
B18: Transportation Charges Per Kg | C18: =IFERROR(C10/(C5*1000),0) -> 0 | D18: =IFERROR(D10/(D5*1000),0) -> 0 | E18: =IFERROR(E10/(E5*1000),0) -> 0 | F18: =IFERROR(F10/(F5*1000),0) -> 0 | G18: =IFERROR(G10/(G5*1000),0) -> 0 | H18: =IFERROR(H10/(H5*1000),0) -> 0 | I18: =IFERROR(I10/(I5*1000),0) -> 0 | J18: =IFERROR(J10/(J5*1000),0) -> 0 | ... AF18: =IFERROR(AF10/(AF5*1000),0) -> 0 | AG18: =AA18 -> 0
B19: No. of Transactions | C19: {=IFERROR(ROWS(_xlfn.UNIQUE(_xlfn._xlws.FILTER('Details PC'!$AA$5:$AA$421,'Details PC'!$W$5:$W$421='Processing Centre'!C$4))),0)} -> 0 | D19: {=IFERROR(ROWS(_xlfn.UNIQUE(_xlfn._xlws.FILTER('Details PC'!$AA$5:$AA$421,'Details PC'!$W$5:$W$421='Processing Centre'!D$4))),0)} -> 0 | E19: {=IFERROR(ROWS(_xlfn.UNIQUE(_xlfn._xlws.FILTER('Details PC'!$AA$5:$AA$421,'Details PC'!$W$5:$W$421='Processing Centre'!E$4))),0)} -> 0 | F19: {=IFERROR(ROWS(_xlfn.UNIQUE(_xlfn._xlws.FILTER('Details PC'!$AA$5:$AA$421,'Details PC'!$W$5:$W$421='Processing Centre'!F$4))),0)} -> 0 | G19: {=IFERROR(ROWS(_xlfn.UNIQUE(_xlfn._xlws.FILTER('Details PC'!$AA$5:$AA$421,'Details PC'!$W$5:$W$421='Processing Centre'!G$4))),0)} -> 0 | H19: {=IFERROR(ROWS(_xlfn.UNIQUE(_xlfn._xlws.FILTER('Details PC'!$AA$5:$AA$421,'Details PC'!$W$5:$W$421='Processing Centre'!H$4))),0)} -> 0 | I19: {=IFERROR(ROWS(_xlfn.UNIQUE(_xlfn._xlws.FILTER('Details PC'!$AA$5:$AA$421,'Details PC'!$W$5:$W$421='Processing Centre'!I$4))),0)} -> 0 | J19: {=IFERROR(ROWS(_xlfn.UNIQUE(_xlfn._xlws.FILTER('Details PC'!$AA$5:$AA$421,'Details PC'!$W$5:$W$421='Processing Centre'!J$4))),0)} -> 0 | ... Z19: {=IFERROR(ROWS(_xlfn.UNIQUE(_xlfn._xlws.FILTER('Details PC'!$AA$5:$AA$421,'Details PC'!$W$5:$W$421='Processing Centre'!Z$4))),0)} -> 12 | AA19: {=IFERROR(ROWS(_xlfn.UNIQUE(_xlfn._xlws.FILTER('Details PC'!$AA$5:$AA$522,'Details PC'!$W$5:$W$522='Processing Centre'!AA$4))),0)} -> 4 | AB19: {=IFERROR(ROWS(_xlfn.UNIQUE(_xlfn._xlws.FILTER('Details PC'!$AA$5:$AA$522,'Details PC'!$W$5:$W$522='Processing Centre'!AB$4))),0)} -> 3 | AC19: {=IFERROR(ROWS(_xlfn.UNIQUE(_xlfn._xlws.FILTER('Details PC'!$AA$5:$AA$522,'Details PC'!$W$5:$W$522='Processing Centre'!AC$4))),0)} -> 0 | AD19: =SUM(C19:AB19) -> 219 | AE19: =SUM(C19:N19) -> 11 | AF19: =SUM(O19:Z19) -> 201 | AG19: =SUM(AA19:AC19) -> 7
B20: No. of Sellers (Aggregators) | C20: {=IFERROR(ROWS(_xlfn.UNIQUE(_xlfn._xlws.FILTER('Details PC'!$H$5:$H$421,'Details PC'!$W$5:$W$421='Processing Centre'!C$4))),0)} -> 0 | D20: {=IFERROR(ROWS(_xlfn.UNIQUE(_xlfn._xlws.FILTER('Details PC'!$H$5:$H$421,'Details PC'!$W$5:$W$421='Processing Centre'!D$4))),0)} -> 0 | E20: {=IFERROR(ROWS(_xlfn.UNIQUE(_xlfn._xlws.FILTER('Details PC'!$H$5:$H$421,'Details PC'!$W$5:$W$421='Processing Centre'!E$4))),0)} -> 0 | F20: {=IFERROR(ROWS(_xlfn.UNIQUE(_xlfn._xlws.FILTER('Details PC'!$H$5:$H$421,'Details PC'!$W$5:$W$421='Processing Centre'!F$4))),0)} -> 0 | G20: {=IFERROR(ROWS(_xlfn.UNIQUE(_xlfn._xlws.FILTER('Details PC'!$H$5:$H$421,'Details PC'!$W$5:$W$421='Processing Centre'!G$4))),0)} -> 0 | H20: {=IFERROR(ROWS(_xlfn.UNIQUE(_xlfn._xlws.FILTER('Details PC'!$H$5:$H$421,'Details PC'!$W$5:$W$421='Processing Centre'!H$4))),0)} -> 0 | I20: {=IFERROR(ROWS(_xlfn.UNIQUE(_xlfn._xlws.FILTER('Details PC'!$H$5:$H$421,'Details PC'!$W$5:$W$421='Processing Centre'!I$4))),0)} -> 0 | J20: {=IFERROR(ROWS(_xlfn.UNIQUE(_xlfn._xlws.FILTER('Details PC'!$H$5:$H$421,'Details PC'!$W$5:$W$421='Processing Centre'!J$4))),0)} -> 0 | ... AC20: {=IFERROR(ROWS(_xlfn.UNIQUE(_xlfn._xlws.FILTER('Details PC'!$H$5:$H$421,'Details PC'!$W$5:$W$421='Processing Centre'!AC$4))),0)} -> 0 | AD20: =ROWS(_xlfn.UNIQUE('Details PC'!H5:H421))-1 -> 16 | AE20: {=IFERROR(ROWS(_xlfn.UNIQUE(_xlfn._xlws.FILTER('Details PC'!$H$5:$H$421,'Details PC'!$C$5:$C$421=AE4))),0)} -> 4 | AF20: {=IFERROR(ROWS(_xlfn.UNIQUE(_xlfn._xlws.FILTER('Details PC'!$H$5:$H$421,'Details PC'!$C$5:$C$421=AF4))),0)} -> 14 | AG20: =SUM(AA20:AC20) -> 5
B21: No. of Buyers (Recyclers) | C21: {=IFERROR(ROWS(_xlfn.UNIQUE(_xlfn._xlws.FILTER('Details PC'!$AB$5:$AB$421,'Details PC'!$W$5:$W$421='Processing Centre'!C$4))),0)} -> 0 | D21: {=IFERROR(ROWS(_xlfn.UNIQUE(_xlfn._xlws.FILTER('Details PC'!$AB$5:$AB$421,'Details PC'!$W$5:$W$421='Processing Centre'!D$4))),0)} -> 0 | E21: {=IFERROR(ROWS(_xlfn.UNIQUE(_xlfn._xlws.FILTER('Details PC'!$AB$5:$AB$421,'Details PC'!$W$5:$W$421='Processing Centre'!E$4))),0)} -> 0 | F21: {=IFERROR(ROWS(_xlfn.UNIQUE(_xlfn._xlws.FILTER('Details PC'!$AB$5:$AB$421,'Details PC'!$W$5:$W$421='Processing Centre'!F$4))),0)} -> 0 | G21: {=IFERROR(ROWS(_xlfn.UNIQUE(_xlfn._xlws.FILTER('Details PC'!$AB$5:$AB$421,'Details PC'!$W$5:$W$421='Processing Centre'!G$4))),0)} -> 0 | H21: {=IFERROR(ROWS(_xlfn.UNIQUE(_xlfn._xlws.FILTER('Details PC'!$AB$5:$AB$421,'Details PC'!$W$5:$W$421='Processing Centre'!H$4))),0)} -> 0 | I21: {=IFERROR(ROWS(_xlfn.UNIQUE(_xlfn._xlws.FILTER('Details PC'!$AB$5:$AB$421,'Details PC'!$W$5:$W$421='Processing Centre'!I$4))),0)} -> 0 | J21: {=IFERROR(ROWS(_xlfn.UNIQUE(_xlfn._xlws.FILTER('Details PC'!$AB$5:$AB$421,'Details PC'!$W$5:$W$421='Processing Centre'!J$4))),0)} -> 0 | ... AC21: {=IFERROR(ROWS(_xlfn.UNIQUE(_xlfn._xlws.FILTER('Details PC'!$AB$5:$AB$421,'Details PC'!$W$5:$W$421='Processing Centre'!AC$4))),0)} -> 0 | AD21: =ROWS(_xlfn.UNIQUE('Details PC'!AB5:AB421))-1 -> 23 | AE21: {=IFERROR(ROWS(_xlfn.UNIQUE(_xlfn._xlws.FILTER('Details PC'!$AB$5:$AB$421,'Details PC'!$V$5:$V$421='Processing Centre'!AE$4))),0)} -> 7 | AF21: {=IFERROR(ROWS(_xlfn.UNIQUE(_xlfn._xlws.FILTER('Details PC'!$AB$5:$AB$421,'Details PC'!$V$5:$V$421='Processing Centre'!AF$4))),0)} -> 19 | AG21: =SUM(AA21:AC21) -> 5
B22: Full Sales Returns (Nos) | C22: 0 | D22: 0 | E22: 0 | F22: 0 | G22: 0 | H22: 0 | I22: 0 | J22: 0 | K22: 0 | L22: 0 | M22: 0 | N22: 0 | O22: 0 | P22: 0 | Q22: 0 | R22: 0 | S22: 0 | T22: 0 | U22: 0 | V22: 0 | W22: 0 | X22: 0 | Y22: 0 | Z22: 0 | AA22: 0 | AB22: 0 | AC22: 0 | AD22: =SUM(C22:AB22) -> 0 | AE22: =SUM(D22:N22) -> 0 | AF22: =SUM(O22:Z22) -> 0 | AG22: =AA22 -> 0
B23: Receivable | C23: 0 | D23: 0 | E23: 0 | F23: 0 | G23: 0 | H23: 0 | I23: 0 | J23: 0 | K23: 0 | L23: 3684158 | M23: 4840740 | N23: 5071174 | O23: 9109058 | P23: 9064031.6 | Q23: 14603523 | R23: 20048166 | S23: 20753319 | T23: 27967133 | U23: 10286916 | V23: 15585783 | W23: 17202350 | X23: 19983005 | Y23: 22412228 | Z23: 5596657.2 | AA23: 4032971.9 | AB23: 4781142.7 | AC23: 1978285.6 | AD23: =AVERAGE(L23:AB23) -> 12648374 | AE23: =AVERAGE(K23:N23) -> 3399018 | AF23: =AVERAGE(O23:Z23) -> 16051014 | AG23: =AC23 -> 1978285.6
B24: DSO (Days) | C24: =IFERROR(((C23/(C6*1.18))*C3),0) -> 0 | D24: =IFERROR(((D23/(D6*1.18))*D3),0) -> 0 | E24: =IFERROR(((E23/(E6*1.18))*E3),0) -> 0 | F24: =IFERROR(((F23/(F6*1.18))*F3),0) -> 0 | G24: =IFERROR(((G23/(G6*1.18))*G3),0) -> 0 | H24: =IFERROR(((H23/(H6*1.18))*H3),0) -> 0 | I24: =IFERROR(((I23/(I6*1.18))*I3),0) -> 0 | J24: =IFERROR(((J23/(J6*1.18))*J3),0) -> 0 | ... AC24: =IFERROR(((AC23/(AC6*1.18))*AC3),0) -> 28.837186 | AD24: =IFERROR(((AD23)/(AD6*1.18)*AD3),0) -> 36.996715 | AE24: =IFERROR(((AE23)/(AE6*1.18)*AE3),0) -> 21.634047 | AF24: =IFERROR(((AF23)/(AF6*1.18)*AF3),0) -> 34.243794 | AG24: =IFERROR(((AG23)/(AG6*1.18)*AG3),0) -> 19.912753
B25: Finance Cost | C25: =SUMIFS('Details PC'!$AQ$5:$AQ$421,'Details PC'!$W$5:$W$421,'Processing Centre'!C$4) -> 0 | D25: =SUMIFS('Details PC'!$AQ$5:$AQ$421,'Details PC'!$W$5:$W$421,'Processing Centre'!D$4) -> 0 | E25: =SUMIFS('Details PC'!$AQ$5:$AQ$421,'Details PC'!$W$5:$W$421,'Processing Centre'!E$4) -> 0 | F25: =SUMIFS('Details PC'!$AQ$5:$AQ$421,'Details PC'!$W$5:$W$421,'Processing Centre'!F$4) -> 0 | G25: =SUMIFS('Details PC'!$AQ$5:$AQ$421,'Details PC'!$W$5:$W$421,'Processing Centre'!G$4) -> 0 | H25: =SUMIFS('Details PC'!$AQ$5:$AQ$421,'Details PC'!$W$5:$W$421,'Processing Centre'!H$4) -> 0 | I25: =SUMIFS('Details PC'!$AQ$5:$AQ$421,'Details PC'!$W$5:$W$421,'Processing Centre'!I$4) -> 0 | J25: =SUMIFS('Details PC'!$AQ$5:$AQ$421,'Details PC'!$W$5:$W$421,'Processing Centre'!J$4) -> 0 | ... AC25: =SUMIFS('Details PC'!$AQ$5:$AQ$421,'Details PC'!$W$5:$W$421,'Processing Centre'!AC$4) -> 6891.7351 | AD25: =SUM(C25:AB25) -> 2884762.6 | AE25: =SUM(C25:N25) -> 360975.95 | AF25: =SUM(O25:Z25) -> 2484944 | AG25: =SUM(AA25:AC25) -> 45734.4
B26: Indirect Expences | C26: =SUMIFS('Opex & Capex Detail'!$I:$I,'Opex & Capex Detail'!$C:$C,'Processing Centre'!C$4) -> 95641 | D26: =SUMIFS('Opex & Capex Detail'!$I:$I,'Opex & Capex Detail'!$C:$C,'Processing Centre'!D$4) -> 180281 | E26: =SUMIFS('Opex & Capex Detail'!$I:$I,'Opex & Capex Detail'!$C:$C,'Processing Centre'!E$4) -> 165624 | F26: =SUMIFS('Opex & Capex Detail'!$I:$I,'Opex & Capex Detail'!$C:$C,'Processing Centre'!F$4) -> 152871.7 | G26: =SUMIFS('Opex & Capex Detail'!$I:$I,'Opex & Capex Detail'!$C:$C,'Processing Centre'!G$4) -> 117600.5 | H26: =SUMIFS('Opex & Capex Detail'!$I:$I,'Opex & Capex Detail'!$C:$C,'Processing Centre'!H$4) -> 106651.3 | I26: =SUMIFS('Opex & Capex Detail'!$I:$I,'Opex & Capex Detail'!$C:$C,'Processing Centre'!I$4) -> 90985.44 | J26: =SUMIFS('Opex & Capex Detail'!$I:$I,'Opex & Capex Detail'!$C:$C,'Processing Centre'!J$4) -> 241504 | ... AB26: =SUMIFS('Opex & Capex Detail'!$I:$I,'Opex & Capex Detail'!$C:$C,'Processing Centre'!AB$4) -> 312234.81 | AC26: =AB26*AC5/AB5+'Opex & Capex Detail'!I676 -> 161501.44 | AD26: =SUM(C26:AB26) -> 11991990 | AE26: =SUM(C26:N26) -> 3286831.9 | AF26: =SUM(O26:Z26) -> 8138535.7 | AG26: =SUM(AA26:AC26) -> 728124.38
B27: Margin after Opex & Finance Cost | K27: =K12-K26-K25 -> 65856.895 | L27: =L12-L26-L25 -> -1024049.7 | M27: =M12-M26-M25 -> -154831.09 | N27: =N12-N26-N25 -> -62088.484 | O27: =O12-O26-O25 -> 638651.15 | P27: =P12-P26-P25 -> -1509100.9 | Q27: =Q12-Q26-Q25 -> -138203.67 | R27: =R12-R26-R25 -> -662931.28 | ... AF27: =AF12-AF26-AF25 -> -17767323 | AG27: =SUM(AA27:AC27) -> -1286986.1
B28: CM % | K28: =K27/K6 -> 0.022838746 | L28: =L27/L6 -> -0.49794304 | M28: =M27/M6 -> -0.045104985 | N28: =N27/N6 -> -0.0081642499 | O28: =O27/O6 -> 0.067003278 | P28: =P27/P6 -> -0.4768242 | Q28: =Q27/Q6 -> -0.01390735 | R28: =R27/R6 -> -0.06312914 | ... AG28: =AG27/AG6 -> -0.1679797
B30: Inventory Details(MT) | C30: =C4 -> Apr-24 | D30: =D4 -> May-24 | E30: =E4 -> Jun-24 | F30: =F4 -> Jul-24 | G30: =G4 -> Aug-24 | H30: =H4 -> Sep-24 | I30: =I4 -> Oct-24 | J30: =J4 -> Nov-24 | ... Z30: =Z4 -> Mar-26 | AA30: 46113 | AB30: 46143 | AC30: 46174 | AD30: Till Date
B31: Opening Qty | C31: 0 | D31: =C34 -> 0 | E31: =D34 -> 0 | F31: =E34 -> 0 | G31: =F34 -> 0 | H31: =G34 -> 0 | I31: =H34 -> 0 | J31: =I34 -> 0 | K31: =J34 -> 0 | ... Z31: =Y34 -> 318440.3 | AA31: =Z34-52206 -> 138714.1 | AB31: =AA34-52206 -> 87221.1 | AC31: =AB34-52206 -> -73544.9 | AD31: 0
B32: Purchase Qty | C32: =SUMIFS('Details PC'!$R$5:$R$421,'Details PC'!$D$5:$D$421,'Processing Centre'!C$30)/1000 -> 0 | D32: =SUMIFS('Details PC'!$R$5:$R$421,'Details PC'!$D$5:$D$421,'Processing Centre'!D$30)/1000 -> 0 | E32: =SUMIFS('Details PC'!$R$5:$R$421,'Details PC'!$D$5:$D$421,'Processing Centre'!E$30)/1000 -> 0 | F32: =SUMIFS('Details PC'!$R$5:$R$421,'Details PC'!$D$5:$D$421,'Processing Centre'!F$30)/1000 -> 0 | G32: =SUMIFS('Details PC'!$R$5:$R$421,'Details PC'!$D$5:$D$421,'Processing Centre'!G$30)/1000 -> 0 | H32: =SUMIFS('Details PC'!$R$5:$R$421,'Details PC'!$D$5:$D$421,'Processing Centre'!H$30)/1000 -> 0 | I32: =SUMIFS('Details PC'!$R$5:$R$421,'Details PC'!$D$5:$D$421,'Processing Centre'!I$30)/1000 -> 0 | J32: =SUMIFS('Details PC'!$R$5:$R$421,'Details PC'!$D$5:$D$421,'Processing Centre'!J$30)/1000 -> 0 | K32: =SUMIFS('Details PC'!$R$5:$R$421,'Details PC'!$D$5:$D$421,'Processing Centre'!K$30) -> 800270 | L32: =SUMIFS('Details PC'!$R$5:$R$421,'Details PC'!$D$5:$D$421,'Processing Centre'!L$30) -> 91800 | M32: =SUMIFS('Details PC'!$R$5:$R$421,'Details PC'!$D$5:$D$421,'Processing Centre'!M$30) -> 35640 | N32: =SUMIFS('Details PC'!$R$5:$R$421,'Details PC'!$D$5:$D$421,'Processing Centre'!N$30) -> 13040 | O32: =SUMIFS('Details PC'!$R$5:$R$421,'Details PC'!$D$5:$D$421,'Processing Centre'!O$30) -> 181330 | P32: =SUMIFS('Details PC'!$R$5:$R$421,'Details PC'!$D$5:$D$421,'Processing Centre'!P$30) -> 79660 | Q32: =SUMIFS('Details PC'!$R$5:$R$421,'Details PC'!$D$5:$D$421,'Processing Centre'!Q$30) -> 851400 | R32: =SUMIFS('Details PC'!$R$5:$R$421,'Details PC'!$D$5:$D$421,'Processing Centre'!R$30) -> 335580 | ... AC32: =SUMIFS('Details PC'!$R$5:$R$421,'Details PC'!$D$5:$D$421,'Processing Centre'!AC$30) -> 91562 | AD32: =SUM(C32:AA32) -> 4679046
B33: Sale Qty | C33: =C5 -> 0 | D33: =D5 -> 0 | E33: =E5 -> 0 | F33: =F5 -> 0 | G33: =G5 -> 0 | H33: =H5 -> 0 | I33: =I5 -> 0 | J33: =J5 -> 0 | K33: =SUMIFS('Details PC'!$AK$5:$AK$421,'Details PC'!$W$5:$W$421,'Processing Centre'!K$4) -> 70800 | L33: =SUMIFS('Details PC'!$AK$5:$AK$421,'Details PC'!$W$5:$W$421,'Processing Centre'!L$4) -> 51560 | M33: =SUMIFS('Details PC'!$AK$5:$AK$421,'Details PC'!$W$5:$W$421,'Processing Centre'!M$4) -> 82523.7 | N33: =SUMIFS('Details PC'!$AK$5:$AK$421,'Details PC'!$W$5:$W$421,'Processing Centre'!N$4) -> 205410 | O33: =SUMIFS('Details PC'!$AK$5:$AK$421,'Details PC'!$W$5:$W$421,'Processing Centre'!O$4) -> 240650 | P33: =SUMIFS('Details PC'!$AK$5:$AK$421,'Details PC'!$W$5:$W$421,'Processing Centre'!P$4) -> 77855 | Q33: =SUMIFS('Details PC'!$AK$5:$AK$421,'Details PC'!$W$5:$W$421,'Processing Centre'!Q$4) -> 263190 | R33: =SUMIFS('Details PC'!$AK$5:$AK$421,'Details PC'!$W$5:$W$421,'Processing Centre'!R$4) -> 291800 | ... AC33: =SUMIFS('Details PC'!$AK$5:$AK$421,'Details PC'!$W$5:$W$421,'Processing Centre'!AC$4) -> 53765 | AD33: =SUM(C33:AA33) -> 4487412.9
B34: Closing Qty | C34: =C31+C32-C33 -> 0 | D34: =D31+D32-D33 -> 0 | E34: =E31+E32-E33 -> 0 | F34: =F31+F32-F33 -> 0 | G34: =G31+G32-G33 -> 0 | H34: =H31+H32-H33 -> 0 | I34: =I31+I32-I33 -> 0 | J34: =J31+J32-J33 -> 0 | ... AD34: =AD31+AD32-AD33 -> 191633.1

Sheet Details PC
O1: =R3-AE3 -> 13505.1 | AI1: =AI3-AJ1 -> 1.6688873e+08 | AJ1: 1738352.2 | AL1: =AL2/(AG3+AH3) -> 0.052299353
AL2: =(AG3+AH3)-AL3 -> 8819087.4
R3: =SUBTOTAL(9,R5:R421) -> 4819148 | T3: =SUBTOTAL(9,T5:T421) -> 1.6020377e+08 | AE3: =SUBTOTAL(9,AE5:AE421) -> 4805642.9 | AG3: =SUBTOTAL(9,AG5:AG421) -> 1.7291257e+08 | AH3: =SUBTOTAL(9,AH5:AH421) -> -4285489.1 | AI3: =SUBTOTAL(9,AI5:AI421) -> 1.6862708e+08 | AJ3: =SUBTOTAL(9,AJ5:AJ421) -> 107365 | AK3: =SUBTOTAL(9,AK5:AK421) -> 4698277.9 | AL3: =SUBTOTAL(9,AL5:AL421) -> 1.59808e+08 | AM3: =SUBTOTAL(9,AM5:AM421) -> 8819087.4 | AN3: =AM3/(AG3+AH3) -> 0.052299353 | AO3: =SUBTOTAL(9,AO5:AO421) -> 1.6034225e+08 | AQ3: =SUBTOTAL(9,AQ5:AQ421) -> 2891654.4 | AR3: =SUBTOTAL(9,AR5:AR421) -> 5927433 | AS3: =AR3/(AG3+AH3) -> 0.035151133
A4: z | B4: SI No | C4: Financial Year | D4: Month | E4: Order Type | F4: Bill Date | G4: CF.SO Number | H4: Vendor Name | I4: GST Identification Number (GSTIN) | J4: Bill Number | K4: CF.Supplier Invoice Date | L4: CF.Purchase | M4: CF.Voucher Date | N4: Source of Supply | O4: CF.Vehicle No | P4: Material_Generic | Q4: Item Name | R4: Purchase Qty | S4: Rate | T4: Taxable Value/Basic Cost | U4: Classification | V4: Financial Year | W4: Month | X4: LOT No | Y4: SO Number | Z4: Sale Date | AA4: Sale Invoice No | AB4: Buyer Name | AC4: Material_Generic | AD4: Material Name | AE4: Qty | AF4: Rate | AG4: Sale Taxable Value | AH4: CN Amount | AI4: Net Sale | AJ4: Return Qty | AK4: Net Qty | AL4: Purchases Angst Sale | AM4: Gross Margin | AN4: % | AO4: Purchases(Inc Inward Cost) | AP4: Days | AQ4: Finance Cost | AR4: Final Margin | AS4: (%)
B5: 1 | C5: FY 2024-25 | D5: =TEXT(F5,"mmm-yy") -> Dec-24 | E5: Regular | F5: 45628 | G5: 002 | H5: Tata Motors Passenger Vehicle Ltd | I5: 27AAHCT8301P1ZT | J5: MH6100765970 | K5: 45628 | L5: 24-25/PUR/11922 | M5: 45638 | N5: MH | O5: MH12EQ8475 | P5: MS Scrap | Q5: Scrap Dismantled & in cut size structural steel | R5: 8840 | S5: 33.121 | T5: =R5*S5 -> 292789.64 | U5: Regular | V5: Fy 2024-25 | W5: =TEXT(Z5,"mmm-yy") -> Dec-24 | X5: B1244K | Y5: MPPUNE/001 | Z5: 45641 | AA5: 25/MPPIB/INV0314 | AB5: Prajapati Foundry Private Limited | AC5: MS Scrap | AD5: MS Scrap (Casting) | AE5: 22510 | AF5: 38 | AG5: =AE5*AF5 -> 855380 | AH5: 0 | AI5: =AG5+AH5 -> 855380 | AJ5: 0 | AK5: =AE5-AJ5 -> 22510 | AL5: =AE5*S5 -> 745553.71 | AM5: =(AG5+AH5)-AL5 -> 109826.29 | AN5: =IFERROR(AM5/(AG5+AH5),0) -> 0.12839474 | AO5: =AE5*S5 -> 745553.71 | AP5: =(Z5-K5) -> 13 | AQ5: =T5*9.35%*AP5/365 -> 975.02961 | AR5: =AM5-AQ5 -> 108851.26 | AS5: =AR5/(AG5+AH5) -> 0.12725486
B6: =B5+1 -> 2 | C6: FY 2024-25 | D6: =TEXT(F6,"mmm-yy") -> Dec-24 | E6: Regular | F6: 45637 | G6: SH12241108 | H6: Tata Motors Passenger Vehicle Ltd | I6: 27AAHCT8301P1ZT | J6: MH6100797898 | K6: 45637 | L6: 24-25/PUR/11888 | M6: 45637 | N6: MH | O6: MH16AY3962 | P6: MS Scrap | Q6: Used/Scrapped/Defaced Dies and Fixtures | R6: 29550 | S6: 32.3 | T6: =R6*S6 -> 954465 | U6: Regular | V6: Fy 2024-25 | W6: =TEXT(Z6,"mmm-yy") -> Dec-24 | X6: B1244K | Y6: MPPUNE/002 | Z6: 45649 | AA6: 25/MPPIB/INV0322 | AB6: Kalyani Foundry Works | AC6: MS Scrap | AD6: MS Scrap (Casting) | AE6: 22790 | AF6: 42 | AG6: =AE6*AF6 -> 957180 | AH6: 0 | AI6: =AG6+AH6 -> 957180 | AJ6: 0 | AK6: =AE6-AJ6 -> 22790 | AL6: =AE6*S6 -> 736117 | AM6: =(AG6+AH6)-AL6 -> 221063 | AN6: =IFERROR(AM6/(AG6+AH6),0) -> 0.23095238 | AO6: =AE6*S6 -> 736117 | AP6: =(Z6-K6) -> 12 | AQ6: =T6*9.35%*AP6/365 -> 2933.9993 | AR6: =AM6-AQ6 -> 218129 | AS6: =AR6/(AG6+AH6) -> 0.22788713
B7: =B6+1 -> 3 | C7: FY 2024-25 | D7: =TEXT(F7,"mmm-yy") -> Dec-24 | E7: Regular | F7: 45637 | G7: SH12241106 | H7: Tata Motors Passenger Vehicle Ltd | I7: 27AAHCT8301P1ZT | J7: MH6100797313 | K7: 45637 | L7: 24-25/PUR/11879 | M7: 45637 | N7: MH | O7: MH25U7780 | P7: MS Scrap | Q7: Used/Scrapped/Defaced Dies and Fixtures | R7: 22390 | S7: 32.3 | T7: =R7*S7 -> 723197 | U7: Regular | V7: Fy 2024-25 | W7: =TEXT(Z7,"mmm-yy") -> Dec-24 | X7: B1244K | Y7: MPPUNE/003 | Z7: 45657 | AA7: 25/MPPIB/INV0331 | AB7: Kalyani Foundry Works | AC7: MS Scrap | AD7: MS Scrap (Casting) | AE7: 25500 | AF7: 42 | AG7: =AE7*AF7 -> 1071000 | AH7: 0 | AI7: =AG7+AH7 -> 1071000 | AJ7: 0 | AK7: =AE7-AJ7 -> 25500 | AL7: =AE7*S7 -> 823650 | AM7: =(AG7+AH7)-AL7 -> 247350 | AN7: =IFERROR(AM7/(AG7+AH7),0) -> 0.23095238 | AO7: =AE7*S7 -> 823650 | AP7: =(Z7-K7) -> 20 | AQ7: =T7*9.35%*AP7/365 -> 3705.1463 | AR7: =AM7-AQ7 -> 243644.85 | AS7: =AR7/(AG7+AH7) -> 0.22749286
B8: =B7+1 -> 4 | C8: FY 2024-25 | D8: =TEXT(F8,"mmm-yy") -> Dec-24 | E8: Regular | F8: 45638 | G8: 004 | H8: Tata Motors Passenger Vehicle Ltd | I8: 27AAHCT8301P1ZT | J8: MH6100696842 | K8: 45609 | L8: 24-25/PUR/11925 | M8: 45638 | N8: MH | O8: MH12EQ8475 | P8: MS Scrap | Q8: Scrap Dismantled & in cut size structural steel | R8: 9050 | S8: 33.121 | T8: =R8*S8 -> 299745.05 | U8: Regular | V8: Fy 2024-25 | W8: =TEXT(Z8,"mmm-yy") -> Jan-25 | X8: B1244K | Y8: MPPUNE/004 | Z8: 45667 | AA8: 25/MPPIB/INV0338 | AB8: Prajapati Foundry Private Limited | AC8: MS Scrap | AD8: MS Scrap (Casting) | AE8: 25910 | AF8: 38 | AG8: =AE8*AF8 -> 984580 | AH8: -5320 | AI8: =AG8+AH8 -> 979260 | AJ8: 0 | AK8: =AE8-AJ8 -> 25910 | AL8: =AE8*S8 -> 858165.11 | AM8: =(AG8+AH8)-AL8 -> 121094.89 | AN8: =IFERROR(AM8/(AG8+AH8),0) -> 0.12365959 | AO8: =AE8*S8 -> 858165.11 | AP8: =(Z8-K8) -> 58 | AQ8: =T8*9.35%*AP8/365 -> 4453.4723 | AR8: =AM8-AQ8 -> 116641.42 | AS8: =AR8/(AG8+AH8) -> 0.1191118
B9: =B8+1 -> 5 | C9: FY 2024-25 | D9: =TEXT(F9,"mmm-yy") -> Dec-24 | E9: Regular | F9: 45638 | G9: 015 | H9: Tata Motors Passenger Vehicle Ltd | I9: 27AAHCT8301P1ZT | J9: MH6100675953 | K9: 45602 | L9: 24-25/PUR/11940 | M9: 45638 | N9: MH | O9: MH48T2266 | P9: MS Scrap | Q9: Used/Scrapped/Defaced Dies and Fixtures | R9: 25040 | S9: 33.521 | T9: =R9*S9 -> 839365.84 | U9: Regular | V9: Fy 2024-25 | W9: =TEXT(Z9,"mmm-yy") -> Jan-25 | X9: B1244K | Y9: MPPUNE/005 | Z9: 45676 | AA9: 25/MPPIB/INV0339 | AB9: Kalyani Foundry Works | AC9: MS Scrap | AD9: MS Scrap (Casting) | AE9: 25650 | AF9: 42 | AG9: =AE9*AF9 -> 1077300 | AH9: 0 | AI9: =AG9+AH9 -> 1077300 | AJ9: 0 | AK9: =AE9-AJ9 -> 25650 | AL9: =AE9*S9 -> 859813.65 | AM9: =(AG9+AH9)-AL9 -> 217486.35 | AN9: =IFERROR(AM9/(AG9+AH9),0) -> 0.20188095 | AO9: =AE9*S9 -> 859813.65 | AP9: =(Z9-K9) -> 74 | AQ9: =T9*9.35%*AP9/365 -> 15911.157 | AR9: =AM9-AQ9 -> 201575.19 | AS9: =AR9/(AG9+AH9) -> 0.18711148
B10: =B9+1 -> 6 | C10: FY 2024-25 | D10: =TEXT(F10,"mmm-yy") -> Dec-24 | E10: Regular | F10: 45638 | G10: 014 | H10: Tata Motors Passenger Vehicle Ltd | I10: 27AAHCT8301P1ZT | J10: MH6100675959 | K10: 45602 | L10: 24-25/PUR/11937 | M10: 45638 | N10: MH | O10: MH04HD3353 | P10: MS Scrap | Q10: Used/Scrapped/Defaced Dies and Fixtures | R10: 25820 | S10: 33.521 | T10: =R10*S10 -> 865512.22 | U10: Regular | V10: Fy 2024-25 | W10: =TEXT(Z10,"mmm-yy") -> Feb-25 | X10: B1244K | Y10: MPPUNE/006 | Z10: 45696 | AA10: 25/MPPIB/INV0364 | AB10: Shree Balaji Metal Trading Company | AC10: CRC | AD10: Brass Scrap | AE10: 433.7 | AF10: 485 | AG10: =AE10*AF10 -> 210344.5 | AH10: -9700 | AI10: =AG10+AH10 -> 200644.5 | AJ10: 0 | AK10: =AE10-AJ10 -> 433.7 | AL10: =AE10*S10 -> 14538.058 | AM10: =(AG10+AH10)-AL10 -> 186106.44 | AN10: =IFERROR(AM10/(AG10+AH10),0) -> 0.9275432 | AO10: =AE10*S10 -> 14538.058 | AP10: =(Z10-K10) -> 94 | AQ10: =T10*9.35%*AP10/365 -> 20841.06 | AR10: =AM10-AQ10 -> 165265.38 | AS10: =AR10/(AG10+AH10) -> 0.82367263
B11: =B10+1 -> 7 | C11: FY 2024-25 | D11: =TEXT(F11,"mmm-yy") -> Dec-24 | E11: Regular | F11: 45638 | G11: 010 | H11: Tata Motors Passenger Vehicle Ltd | I11: 27AAHCT8301P1ZT | J11: MH6100679115 | K11: 45603 | L11: 24-25/PUR/11932 | M11: 45638 | N11: MH | O11: MH12MV6966 | P11: MS Scrap | Q11: Used/Scrapped/Defaced Dies and Fixtures | R11: 25190 | S11: 33.521 | T11: =R11*S11 -> 844393.99 | U11: Regular | V11: Fy 2024-25 | W11: =TEXT(Z11,"mmm-yy") -> Feb-25 | X11: B1244K | Y11: MPPUNE/007 | Z11: 45698 | AA11: 25/MPPIB/INV0367 | AB11: Affan Tools | AC11: CRC | AD11: MS Scrap (D2) | AE11: 1050 | AF11: 52 | AG11: =AE11*AF11 -> 54600 | AH11: 0 | AI11: =AG11+AH11 -> 54600 | AJ11: 0 | AK11: =AE11-AJ11 -> 1050 | AL11: =AE11*S11 -> 35197.05 | AM11: =(AG11+AH11)-AL11 -> 19402.95 | AN11: =IFERROR(AM11/(AG11+AH11),0) -> 0.35536538 | AO11: =AE11*S11 -> 35197.05 | AP11: =(Z11-K11) -> 95 | AQ11: =T11*9.35%*AP11/365 -> 20548.848 | AR11: =AM11-AQ11 -> -1145.8983 | AS11: =AR11/(AG11+AH11) -> -0.020987148
B12: =B11+1 -> 8 | C12: FY 2024-25 | D12: =TEXT(F12,"mmm-yy") -> Dec-24 | E12: Regular | F12: 45638 | G12: 011 | H12: Tata Motors Passenger Vehicle Ltd | I12: 27AAHCT8301P1ZT | J12: MH6100679114 | K12: 45603 | L12: 24-25/PUR/11933 | M12: 45638 | N12: MH | O12: MH48T2266 | P12: MS Scrap | Q12: Used/Scrapped/Defaced Dies and Fixtures | R12: 20280 | S12: 33.521 | T12: =R12*S12 -> 679805.88 | U12: Regular | V12: Fy 2024-25 | W12: =TEXT(Z12,"mmm-yy") -> Feb-25 | X12: B1244K | Y12: MPPUNE/008 | Z12: 45705 | AA12: 25/MPPIB/INV0378 | AB12: Kalyani Foundry Works | AC12: MS Scrap | AD12: MS Scrap (Casting) | AE12: 22170 | AF12: 42 | AG12: =AE12*AF12 -> 931140 | AH12: 0 | AI12: =AG12+AH12 -> 931140 | AJ12: 0 | AK12: =AE12-AJ12 -> 22170 | AL12: =AE12*S12 -> 743160.57 | AM12: =(AG12+AH12)-AL12 -> 187979.43 | AN12: =IFERROR(AM12/(AG12+AH12),0) -> 0.20188095 | AO12: =AE12*S12 -> 743160.57 | AP12: =(Z12-K12) -> 102 | AQ12: =T12*9.35%*AP12/365 -> 17762.49 | AR12: =AM12-AQ12 -> 170216.94 | AS12: =AR12/(AG12+AH12) -> 0.18280488
B13: =B12+1 -> 9 | C13: FY 2024-25 | D13: =TEXT(F13,"mmm-yy") -> Dec-24 | E13: Regular | F13: 45638 | G13: 013 | H13: Tata Motors Passenger Vehicle Ltd | I13: 27AAHCT8301P1ZT | J13: MH6100679113 | K13: 45603 | L13: 24-25/PUR/11936 | M13: 45638 | N13: MH | O13: MH04HD3714 | P13: MS Scrap | Q13: Used/Scrapped/Defaced Dies and Fixtures | R13: 17620 | S13: 33.521 | T13: =R13*S13 -> 590640.02 | U13: Regular | V13: Fy 2024-25 | W13: =TEXT(Z13,"mmm-yy") -> Feb-25 | X13: B1244K | Y13: MPPUNE/009 | Z13: 45711 | AA13: 25/MPPIB/INV0388 | AB13: Kalyani Foundry Works | AC13: MS Scrap | AD13: MS Scrap (Casting) | AE13: 24330 | AF13: 42 | AG13: =AE13*AF13 -> 1021860 | AH13: 0 | AI13: =AG13+AH13 -> 1021860 | AJ13: 0 | AK13: =AE13-AJ13 -> 24330 | AL13: =AE13*S13 -> 815565.93 | AM13: =(AG13+AH13)-AL13 -> 206294.07 | AN13: =IFERROR(AM13/(AG13+AH13),0) -> 0.20188095 | AO13: =AE13*S13 -> 815565.93 | AP13: =(Z13-K13) -> 108 | AQ13: =T13*9.35%*AP13/365 -> 16340.501 | AR13: =AM13-AQ13 -> 189953.57 | AS13: =AR13/(AG13+AH13) -> 0.18589001
B14: =B13+1 -> 10 | C14: FY 2024-25 | D14: =TEXT(F14,"mmm-yy") -> Dec-24 | E14: Regular | F14: 45638 | G14: 012 | H14: Tata Motors Passenger Vehicle Ltd | I14: 27AAHCT8301P1ZT | J14: MH6100679069 | K14: 45603 | L14: 24-25/PUR/11934 | M14: 45638 | N14: MH | O14: MH04HD3353 | P14: MS Scrap | Q14: Used/Scrapped/Defaced Dies and Fixtures | R14: 21200 | S14: 33.521 | T14: =R14*S14 -> 710645.2 | U14: Regular | V14: Fy 2024-25 | W14: =TEXT(Z14,"mmm-yy") -> Feb-25 | X14: M&M | Y14: MPPUNE/010 | Z14: 45714 | AA14: 25/MPPIB/INV0392 | AB14: Yash Enterprises | AC14: CRC | AD14: Defaced Light & Heavy metallic Auto components | AE14: 12940 | AF14: 35.7 | AG14: =AE14*AF14 -> 461958 | AH14: 0 | AI14: =AG14+AH14 -> 461958 | AJ14: 0 | AK14: =AE14-AJ14 -> 12940 | AL14: =AE14*S14 -> 433761.74 | AM14: =(AG14+AH14)-AL14 -> 28196.26 | AN14: =IFERROR(AM14/(AG14+AH14),0) -> 0.061036415 | AO14: =AE14*S14 -> 433761.74 | AP14: =(Z14-K14) -> 111 | AQ14: =T14*9.35%*AP14/365 -> 20206.661 | AR14: =AM14-AQ14 -> 7989.5992 | AS14: =AR14/(AG14+AH14) -> 0.017295077
B15: =B14+1 -> 11 | C15: FY 2024-25 | D15: =TEXT(F15,"mmm-yy") -> Dec-24 | E15: Regular | F15: 45638 | G15: 007 | H15: Tata Motors Passenger Vehicle Ltd | I15: 27AAHCT8301P1ZT | J15: MH6100682260 | K15: 45604 | L15: 24-25/PUR/11929 | M15: 45638 | N15: MH | O15: MH04HD3714 | P15: MS Scrap | Q15: Used/Scrapped/Defaced Dies and Fixtures | R15: 29120 | S15: 33.521 | T15: =R15*S15 -> 976131.52 | U15: Regular | V15: Fy 2024-25 | W15: =TEXT(Z15,"mmm-yy") -> Feb-25 | X15: A13K | Y15: MPPUNE/011 | Z15: 45716 | AA15: 25/MPPIB/INV0396 | AB15: Yash Enterprises | AC15: CRC | AD15: Scrap Dismantled & in cut size structural steel | AE15: 21600 | AF15: 35.3 | AG15: =AE15*AF15 -> 762480 | AH15: 0 | AI15: =AG15+AH15 -> 762480 | AJ15: 0 | AK15: =AE15-AJ15 -> 21600 | AL15: =AE15*S15 -> 724053.6 | AM15: =(AG15+AH15)-AL15 -> 38426.4 | AN15: =IFERROR(AM15/(AG15+AH15),0) -> 0.050396601 | AO15: =AE15*S15 -> 724053.6 | AP15: =(Z15-K15) -> 112 | AQ15: =T15*9.35%*AP15/365 -> 28005.614 | AR15: =AM15-AQ15 -> 10420.786 | AS15: =AR15/(AG15+AH15) -> 0.013666962
B16: =B15+1 -> 12 | C16: FY 2024-25 | D16: =TEXT(F16,"mmm-yy") -> Dec-24 | E16: Regular | F16: 45638 | G16: 009 | H16: Tata Motors Passenger Vehicle Ltd | I16: 27AAHCT8301P1ZT | J16: MH6100681729 | K16: 45604 | L16: 24-25/PUR/11931 | M16: 45638 | N16: MH | O16: MH04HD3353 | P16: MS Scrap | Q16: Used/Scrapped/Defaced Dies and Fixtures | R16: 26990 | S16: 33.521 | T16: =R16*S16 -> 904731.79 | U16: Regular | V16: Fy 2024-25 | W16: =TEXT(Z16,"mmm-yy") -> Mar-25 | X16: B1244K | Y16: MPPUNE/012 | Z16: 45719 | AA16: 25/MPPIB/INV0404 | AB16: Prajapati Casting Foundry Private Limited | AC16: MS Scrap | AD16: MS Scrap (Casting) | AE16: 20900 | AF16: 38.5 | AG16: =AE16*AF16 -> 804650 | AH16: 0 | AI16: =AG16+AH16 -> 804650 | AJ16: 0 | AK16: =AE16-AJ16 -> 20900 | AL16: =AE16*S16 -> 700588.9 | AM16: =(AG16+AH16)-AL16 -> 104061.1 | AN16: =IFERROR(AM16/(AG16+AH16),0) -> 0.12932468 | AO16: =AE16*S16 -> 700588.9 | AP16: =(Z16-K16) -> 115 | AQ16: =T16*9.35%*AP16/365 -> 26652.407 | AR16: =AM16-AQ16 -> 77408.693 | AS16: =AR16/(AG16+AH16) -> 0.096201694
B17: =B16+1 -> 13 | C17: FY 2024-25 | D17: =TEXT(F17,"mmm-yy") -> Dec-24 | E17: Regular | F17: 45638 | G17: 008 | H17: Tata Motors Passenger Vehicle Ltd | I17: 27AAHCT8301P1ZT | J17: MH6100683932 | K17: 45605 | L17: 24-25/PUR/11930 | M17: 45638 | N17: MH | O17: MH12MV6966 | P17: MS Scrap | Q17: Used/Scrapped/Defaced Dies and Fixtures | R17: 29550 | S17: 33.521 | T17: =R17*S17 -> 990545.55 | U17: Regular | V17: Fy 2024-25 | W17: =TEXT(Z17,"mmm-yy") -> Mar-25 | X17: B1244K | Y17: MPPUNE/013 | Z17: 45719 | AA17: 25/MPPIB/INV0402 | AB17: Madhuban Trade Steels Private Limited | AC17: MS Scrap | AD17: MS Scrap (Casting) | AE17: 22860 | AF17: 36.5 | AG17: =AE17*AF17 -> 834390 | AH17: 0 | AI17: =AG17+AH17 -> 834390 | AJ17: 0 | AK17: =AE17-AJ17 -> 22860 | AL17: =AE17*S17 -> 766290.06 | AM17: =(AG17+AH17)-AL17 -> 68099.94 | AN17: =IFERROR(AM17/(AG17+AH17),0) -> 0.081616438 | AO17: =AE17*S17 -> 766290.06 | AP17: =(Z17-K17) -> 114 | AQ17: =T17*9.35%*AP17/365 -> 28926.644 | AR17: =AM17-AQ17 -> 39173.296 | AS17: =AR17/(AG17+AH17) -> 0.046948425
... B41: =B40+1 -> 37 | C41: FY 2024-25 | D41: =TEXT(F41,"mmm-yy") -> Jan-25 | E41: Regular | F41: 45673 | G41: 020 | H41: Tata Motors Ltd | I41: 27AAACT2727Q1ZW | J41: MH0100935797 | K41: 45673 | L41: 24-25/PUR/13395 | M41: 45675 | N41: MH | O41: MH12KP9590 | P41: MS Scrap | Q41: Scrap Dismantled & in cut size structural steel | R41: 6800 | S41: 32.121 | T41: =R41*S41 -> 218422.8 | U41: Regular | V41: Fy 2025-26 | W41: =TEXT(Z41,"mmm-yy") -> Apr-25 | X41: B514CA | Y41: MPPUNE/0037 | Z41: 45772 | AA41: 26/MPPIB/INV0068 | AB41: Yash Enterprises | AC41: MS Scrap | AD41: Scrap steel forging | AE41: 11660 | AF41: 34.8 | AG41: =AE41*AF41 -> 405768 | AH41: 0 | AI41: =AG41+AH41 -> 405768 | AJ41: 0 | AK41: =AE41-AJ41 -> 11660 | AL41: =AE41*S41 -> 374530.86 | AM41: =(AG41+AH41)-AL41 -> 31237.14 | AN41: =IFERROR(AM41/(AG41+AH41),0) -> 0.076982759 | AO41: =AE41*S41 -> 374530.86 | AP41: =(Z41-K41) -> 99 | AQ41: =T41*9.35%*AP41/365 -> 5539.262 | AR41: =AM41-AQ41 -> 25697.878 | AS41: =AR41/(AG41+AH41) -> 0.063331455
B42: =B41+1 -> 38 | C42: FY 2024-25 | D42: =TEXT(F42,"mmm-yy") -> Jan-25 | E42: Regular | F42: 45675 | G42: 021 | H42: Tata Motors Passenger Vehicle Ltd | I42: 27AAHCT8301P1ZT | J42: MH6100933162 | K42: 45675 | L42: 24-25/PUR/13441 | M42: 45677 | N42: MH | O42: MH12KP9590 | P42: Commercial | Q42: Scrap Gascut Aluminium | R42: 2760 | S42: 84.521 | T42: =R42*S42 -> 233277.96 | U42: Regular | V42: Fy 2025-26 | W42: =TEXT(Z42,"mmm-yy") -> May-25 | X42: Suyash | Y42: MPPUNE/0038 | Z42: 45785 | AA42: 26/MPPIB/INV0096 | AB42: Prajapati Foundry Private Limited | AC42: CRC | AD42: MS Scrap (CRC) | AE42: 7550 | AF42: 40 | AG42: =AE42*AF42 -> 302000 | AH42: -302000 | AI42: =AG42+AH42 -> 0 | AJ42: 7550 | AK42: =AE42-AJ42 -> 0 | AL42: =AE42*S42 -> 638133.55 | AM42: =(AG42+AH42)-AL42 -> -638133.55 | AN42: =IFERROR(AM42/(AG42+AH42),0) -> 0 | AO42: =AE42*S42 -> 638133.55 | AR42: =AM42-AQ42 -> -638133.55
B43: =B42+1 -> 39 | C43: FY 2024-25 | D43: =TEXT(F43,"mmm-yy") -> Jan-25 | E43: Regular | F43: 45681 | G43: 022 | H43: Tata Motors Ltd | I43: 27AAACT2727Q1ZW | J43: MH0100963482 | K43: 45681 | L43: 24-25/PUR/13690 | M43: 45681 | N43: MH | O43: MH04CG3578 | P43: MS Scrap | Q43: Heavy Metal scrap | R43: 7440 | S43: 35.111 | T43: =R43*S43 -> 261225.84 | U43: Regular | V43: Fy 2025-26 | W43: =TEXT(Z43,"mmm-yy") -> May-25 | X43: A18K | Y43: MPPUNE/0039 | Z43: 45799 | AA43: 26/MPPIB/INV0126 | AB43: S S R ENTERPRISES | AC43: CRC | AD43: MS Scrap (CRC) | AE43: 24720 | AF43: 38 | AG43: =AE43*AF43 -> 939360 | AH43: 0 | AI43: =AG43+AH43 -> 939360 | AJ43: 0 | AK43: =AE43-AJ43 -> 24720 | AL43: =AE43*S43 -> 867943.92 | AM43: =(AG43+AH43)-AL43 -> 71416.08 | AN43: =IFERROR(AM43/(AG43+AH43),0) -> 0.076026316 | AO43: =AE43*S43 -> 867943.92 | AP43: =(Z43-K43) -> 118 | AQ43: =T43*9.35%*AP43/365 -> 7896.1772 | AR43: =AM43-AQ43 -> 63519.903 | AS43: =AR43/(AG43+AH43) -> 0.067620404
B44: =B43+1 -> 40 | C44: FY 2024-25 | D44: =TEXT(F44,"mmm-yy") -> Jan-25 | E44: Regular | F44: 45684 | G44: 023 | H44: Tata Motors Ltd | I44: 27AAACT2727Q1ZW | J44: MH0100971251 | K44: 45684 | L44: 24-25/PUR/13921 | M44: 45686 | N44: MH | O44: MH04CG3578 | P44: MS Scrap | Q44: Heavy Metal scrap | R44: 8920 | S44: 35.111 | T44: =R44*S44 -> 313190.12 | U44: Regular | V44: Fy 2025-26 | W44: =TEXT(Z44,"mmm-yy") -> May-25 | X44: M7472K | Y44: MPPUNE/0041 | Z44: 45800 | AA44: 26/MPPIB/INV0130 | AB44: Kalyani Foundry Works | AC44: MS Scrap | AD44: MS Scrap (Casting) | AE44: 10280 | AF44: 42 | AG44: =AE44*AF44 -> 431760 | AH44: 0 | AI44: =AG44+AH44 -> 431760 | AJ44: 0 | AK44: =AE44-AJ44 -> 10280 | AL44: =AE44*S44 -> 360941.08 | AM44: =(AG44+AH44)-AL44 -> 70818.92 | AN44: =IFERROR(AM44/(AG44+AH44),0) -> 0.16402381 | AO44: =AE44*S44 -> 360941.08 | AP44: =(Z44-K44) -> 116 | AQ44: =T44*9.35%*AP44/365 -> 9306.4659 | AR44: =AM44-AQ44 -> 61512.454 | AS44: =AR44/(AG44+AH44) -> 0.14246909
B45: =B44+1 -> 41 | C45: FY 2024-25 | D45: =TEXT(F45,"mmm-yy") -> Jan-25 | E45: Regular | F45: 45685 | G45: 024 | H45: Tata Motors Ltd | I45: 27AAACT2727Q1ZW | J45: MH0100976626 | K45: 45685 | L45: 24-25/PUR/13922 | M45: 45686 | N45: MH | O45: MH04CG3578 | P45: MS Scrap | Q45: Heavy Metal scrap | R45: 7940 | S45: 35.111 | T45: =R45*S45 -> 278781.34 | U45: Regular | V45: Fy 2025-26 | W45: =TEXT(Z45,"mmm-yy") -> May-25 | X45: M7472K | Y45: MPPUNE/0040 | Z45: 45800 | AA45: 26/MPPIB/INV0129 | AB45: Kalyani Foundry Works | AC45: MS Scrap | AD45: MS Scrap (Casting) | AE45: 9600 | AF45: 42 | AG45: =AE45*AF45 -> 403200 | AH45: 0 | AI45: =AG45+AH45 -> 403200 | AJ45: 0 | AK45: =AE45-AJ45 -> 9600 | AL45: =AE45*S45 -> 337065.6 | AM45: =(AG45+AH45)-AL45 -> 66134.4 | AN45: =IFERROR(AM45/(AG45+AH45),0) -> 0.16402381 | AO45: =AE45*S45 -> 337065.6 | AP45: =(Z45-K45) -> 115 | AQ45: =T45*9.35%*AP45/365 -> 8212.5928 | AR45: =AM45-AQ45 -> 57921.807 | AS45: =AR45/(AG45+AH45) -> 0.14365528
B46: =B45+1 -> 42 | C46: FY 2024-25 | D46: =TEXT(F46,"mmm-yy") -> Jan-25 | E46: Regular | F46: 45686 | G46: 025 | H46: Tata Motors Ltd | I46: 27AAACT2727Q1ZW | J46: MH0100981769 | K46: 45686 | L46: 24-25/PUR/13951 | M46: 45687 | N46: MH | O46: MH04CG3578 | P46: MS Scrap | Q46: Heavy Metal scrap | R46: 10240 | S46: 35.111 | T46: =R46*S46 -> 359536.64 | U46: Regular | V46: Fy 2025-26 | W46: =TEXT(Z46,"mmm-yy") -> May-25 | X46: M7472K | Y46: MPPUNE/0042 | Z46: 45801 | AA46: 26/MPPIB/INV0131 | AB46: Kalyani Foundry Works | AC46: MS Scrap | AD46: MS Scrap (Casting) | AE46: 5600 | AF46: 42 | AG46: =AE46*AF46 -> 235200 | AH46: 0 | AI46: =AG46+AH46 -> 235200 | AJ46: 0 | AK46: =AE46-AJ46 -> 5600 | AL46: =AE46*S46 -> 196621.6 | AM46: =(AG46+AH46)-AL46 -> 38578.4 | AN46: =IFERROR(AM46/(AG46+AH46),0) -> 0.16402381 | AO46: =AE46*S46 -> 196621.6 | AP46: =(Z46-K46) -> 115 | AQ46: =T46*9.35%*AP46/365 -> 10591.555 | AR46: =AM46-AQ46 -> 27986.845 | AS46: =AR46/(AG46+AH46) -> 0.11899169
B47: =B46+1 -> 43 | C47: FY 2024-25 | D47: =TEXT(F47,"mmm-yy") -> Jan-25 | E47: Regular | F47: 45687 | G47: 027 | H47: Tata Motors Ltd | I47: 27AAACT2727Q1ZW | J47: MH0100986998 | K47: 45687 | L47: 24-25/PUR/13997 | M47: 45688 | N47: MH | O47: MH04CG3578 | P47: MS Scrap | Q47: Heavy Metal scrap | R47: 7240 | S47: 35.111 | T47: =R47*S47 -> 254203.64 | U47: Regular | V47: Fy 2025-26 | W47: =TEXT(Z47,"mmm-yy") -> May-25 | X47: M7472K | Y47: MPPUNE/0043 | Z47: 45805 | AA47: 26/MPPIB/INV0141 | AB47: Kalyani Foundry Works | AC47: MS Scrap | AD47: MS Scrap (Casting) | AE47: 11630 | AF47: 42 | AG47: =AE47*AF47 -> 488460 | AH47: 0 | AI47: =AG47+AH47 -> 488460 | AJ47: 0 | AK47: =AE47-AJ47 -> 11630 | AL47: =AE47*S47 -> 408340.93 | AM47: =(AG47+AH47)-AL47 -> 80119.07 | AN47: =IFERROR(AM47/(AG47+AH47),0) -> 0.16402381 | AO47: =AE47*S47 -> 408340.93 | AP47: =(Z47-K47) -> 118 | AQ47: =T47*9.35%*AP47/365 -> 7683.9144 | AR47: =AM47-AQ47 -> 72435.156 | AS47: =AR47/(AG47+AH47) -> 0.14829291
B48: =B47+1 -> 44 | C48: FY 2024-25 | D48: =TEXT(F48,"mmm-yy") -> Jan-25 | E48: Regular | F48: 45687 | G48: 026 | H48: Tata Motors Ltd | I48: 27AAACT2727Q1ZW | J48: MH0100986561 | K48: 45687 | L48: 24-25/PUR/13995 | M48: 45688 | N48: MH | O48: MH04DS3172 | P48: MS Scrap | Q48: Scrap Dismantled & in cut size structural steel | R48: 7400 | S48: 32.121 | T48: =R48*S48 -> 237695.4 | U48: Regular | V48: Fy 2025-26 | W48: =TEXT(Z48,"mmm-yy") -> May-25 | X48: M7472K | Y48: MPPUNE/0044 | Z48: 45806 | AA48: 26/MPPIB/INV0145 | AB48: Kalyani Foundry Works | AC48: MS Scrap | AD48: MS Scrap (Casting) | AE48: 12960 | AF48: 42 | AG48: =AE48*AF48 -> 544320 | AH48: 0 | AI48: =AG48+AH48 -> 544320 | AJ48: 0 | AK48: =AE48-AJ48 -> 12960 | AL48: =AE48*S48 -> 416288.16 | AM48: =(AG48+AH48)-AL48 -> 128031.84 | AN48: =IFERROR(AM48/(AG48+AH48),0) -> 0.23521429 | AO48: =AE48*S48 -> 416288.16 | AP48: =(Z48-K48) -> 119 | AQ48: =T48*9.35%*AP48/365 -> 7245.8024 | AR48: =AM48-AQ48 -> 120786.04 | AS48: =AR48/(AG48+AH48) -> 0.22190263
B49: =B48+1 -> 45 | C49: FY 2024-25 | D49: =TEXT(F49,"mmm-yy") -> Jan-25 | E49: Regular | F49: 45688 | G49: 029 | H49: Tata Motors Ltd | I49: 27AAACT2727Q1ZW | J49: MH0100994937 | K49: 45688 | L49: 24-25/PUR/14083 | M49: 45691 | N49: MH | O49: MH04DS3172 | P49: MS Scrap | Q49: Heavy Metal scrap | R49: 8460 | S49: 35.111 | T49: =R49*S49 -> 297039.06 | U49: Regular | V49: Fy 2025-26 | W49: =TEXT(Z49,"mmm-yy") -> May-25 | X49: Suyash | Y49: MPPUNE/0045 | Z49: 45808 | AA49: 26/MPPIB/INV0148 | AB49: Prajapati Foundry Private Limited | AC49: CRC | AD49: MS Scrap (CRC) | AE49: 3065 | AF49: 40 | AG49: =AE49*AF49 -> 122600 | AH49: 0 | AI49: =AG49+AH49 -> 122600 | AJ49: 0 | AK49: =AE49-AJ49 -> 3065 | AL49: =AE49*S49 -> 107615.21 | AM49: =(AG49+AH49)-AL49 -> 14984.785 | AN49: =IFERROR(AM49/(AG49+AH49),0) -> 0.122225 | AO49: =AE49*S49 -> 107615.21 | AP49: =(Z49-K49) -> 120 | AQ49: =T49*9.35%*AP49/365 -> 9130.8993 | AR49: =AM49-AQ49 -> 5853.8857 | AS49: =AR49/(AG49+AH49) -> 0.047747844
B50: =B49+1 -> 46 | C50: FY 2024-25 | D50: =TEXT(F50,"mmm-yy") -> Jan-25 | E50: Regular | F50: 45688 | G50: 028 | H50: Tata Motors Ltd | I50: 27AAACT2727Q1ZW | J50: MH0100994936 | K50: 45688 | L50: 24-25/PUR/14078 | M50: 45691 | N50: MH | O50: MH04CG3578 | P50: MS Scrap | Q50: Scrap Dismantled & in cut size structural steel | R50: 6240 | S50: 32.121 | T50: =R50*S50 -> 200435.04 | U50: Regular | V50: Fy 2025-26 | W50: =TEXT(Z50,"mmm-yy") -> Jun-25 | X50: M7472K | Y50: MPPUNE/0047 | Z50: 45809 | AA50: 26/MPPIB/INV0153 | AB50: Kalyani Foundry Works | AC50: MS Scrap | AD50: MS Scrap (Casting) | AE50: 13840 | AF50: 42 | AG50: =AE50*AF50 -> 581280 | AH50: 0 | AI50: =AG50+AH50 -> 581280 | AJ50: 0 | AK50: =AE50-AJ50 -> 13840 | AL50: =AE50*S50 -> 444554.64 | AM50: =(AG50+AH50)-AL50 -> 136725.36 | AN50: =IFERROR(AM50/(AG50+AH50),0) -> 0.23521429 | AO50: =AE50*S50 -> 444554.64 | AP50: =(Z50-K50) -> 121 | AQ50: =T50*9.35%*AP50/365 -> 6212.6625 | AR50: =AM50-AQ50 -> 130512.7 | AS50: =AR50/(AG50+AH50) -> 0.22452639
B51: =B50+1 -> 47 | C51: FY 2024-25 | D51: =TEXT(F51,"mmm-yy") -> Feb-25 | E51: Regular | F51: 45706 | G51: 030 | H51: Mahindra & Mahindra Limited Automotive Division | I51: 27AAACM3025E1ZZ | J51: IN01252703032292 | K51: 45706 | L51: 24-25/PUR/15044 | M51: 45710 | N51: MH | O51: MH12EQ8475 | P51: CRC | Q51: Defaced Light & Heavy metallic Auto components | R51: 18370 | S51: 34.1 | T51: =R51*S51 -> 626417 | U51: Regular | V51: Fy 2025-26 | W51: =TEXT(Z51,"mmm-yy") -> Jun-25 | X51: A18K | Y51: MPPUNE/0046 | Z51: 45809 | AA51: 26/MPPIB/INV0152 | AB51: Yash Enterprises | AC51: MS Scrap | AD51: MS Scrap | AE51: 12090 | AF51: 33 | AG51: =AE51*AF51 -> 398970 | AH51: 0 | AI51: =AG51+AH51 -> 398970 | AJ51: 0 | AK51: =AE51-AJ51 -> 12090 | AL51: =AE51*S51 -> 412269 | AM51: =(AG51+AH51)-AL51 -> -13299 | AN51: =IFERROR(AM51/(AG51+AH51),0) -> -0.033333333 | AO51: =AE51*S51 -> 412269 | AP51: =(Z51-K51) -> 103 | AQ51: =T51*9.35%*AP51/365 -> 16527.97 | AR51: =AM51-AQ51 -> -29826.97 | AS51: =AR51/(AG51+AH51) -> -0.074759931
B52: =B51+1 -> 48 | C52: FY 2024-25 | D52: =TEXT(F52,"mmm-yy") -> Feb-25 | E52: Regular | F52: 45709 | G52: 031 | H52: Tata Motors Passenger Vehicle Ltd | I52: 27AAHCT8301P1ZT | J52: MH6101047235 | K52: 45709 | L52: 24-25/PUR/15075 | M52: 45712 | N52: MH | O52: MH27BX0052 | P52: MS Scrap | Q52: Used Fastner Items | R52: 17270 | S52: 34.521 | T52: =R52*S52 -> 596177.67 | U52: Regular | V52: Fy 2025-26 | W52: =TEXT(Z52,"mmm-yy") -> Jun-25 | X52: A18K | Y52: MPPUNE/0048 | Z52: 45810 | AA52: 26/MPPIB/INV0155 | AB52: Yash Enterprises | AC52: MS Scrap | AD52: MS Scrap | AE52: 8510 | AF52: 33 | AG52: =AE52*AF52 -> 280830 | AH52: 0 | AI52: =AG52+AH52 -> 280830 | AJ52: 0 | AK52: =AE52-AJ52 -> 8510 | AL52: =AE52*S52 -> 293773.71 | AM52: =(AG52+AH52)-AL52 -> -12943.71 | AN52: =IFERROR(AM52/(AG52+AH52),0) -> -0.046090909 | AO52: =AE52*S52 -> 293773.71 | AP52: =(Z52-K52) -> 101 | AQ52: =T52*9.35%*AP52/365 -> 15424.668 | AR52: =AM52-AQ52 -> -28368.378 | AS52: =AR52/(AG52+AH52) -> -0.10101619
B53: =B52+1 -> 49 | C53: FY 2024-25 | D53: =TEXT(F53,"mmm-yy") -> Mar-25 | E53: Regular | F53: 45741 | G53: 032 | H53: Mother Stamping | I53: 27CTGPK8680K1ZZ | J53: 2024-25/187 | K53: 45741 | L53: 24-25/PUR/16433 | M53: 45741 | N53: MH | O53: MH12KP9590 | P53: CRC | Q53: Steel Scrap Loose (CRC) | R53: 13040 | S53: 34 | T53: =R53*S53 -> 443360 | U53: Regular | V53: Fy 2025-26 | W53: =TEXT(Z53,"mmm-yy") -> Jun-25 | X53: A18K | Y53: MPPUNE/0049 | Z53: 45812 | AA53: 26/MPPIB/INV0162 | AB53: Yash Enterprises | AC53: MS Scrap | AD53: MS Scrap | AE53: 4460 | AF53: 33 | AG53: =AE53*AF53 -> 147180 | AH53: 0 | AI53: =AG53+AH53 -> 147180 | AJ53: 0 | AK53: =AE53-AJ53 -> 4460 | AL53: =AE53*S53 -> 151640 | AM53: =(AG53+AH53)-AL53 -> -4460 | AN53: =IFERROR(AM53/(AG53+AH53),0) -> -0.03030303 | AO53: =AE53*S53 -> 151640 | AP53: =(Z53-K53) -> 71 | AQ53: =T53*9.35%*AP53/365 -> 8063.6859 | AR53: =AM53-AQ53 -> -12523.686 | AS53: =AR53/(AG53+AH53) -> -0.085090949
B54: =B53+1 -> 50 | C54: FY 2025-26 | D54: =TEXT(F54,"mmm-yy") -> Apr-25 | E54: Regular | F54: 45759 | G54: MHPV003 | H54: Tata Motors Passenger Vehicle Ltd | I54: 27AAHCT8301P1ZT | J54: MH6100032867 | K54: 45759 | L54: 25-26/PUR/000387 | M54: 45759 | N54: MH | O54: MH04BU8943 | P54: CRC | Q54: Scrap Sheet Metal Components of M V Parts | R54: 2380 | S54: 31.121 | T54: =R54*S54 -> 74067.98 | U54: Regular | V54: Fy 2025-26 | W54: =TEXT(Z54,"mmm-yy") -> Jun-25 | X54: A18K | Y54: MPPUNE/0051 | Z54: 45816 | AA54: 26/MPPIB/INV0178 | AB54: Yash Enterprises | AC54: MS Scrap | AD54: MS Scrap | AE54: 6630 | AF54: 33 | AG54: =AE54*AF54 -> 218790 | AH54: 0 | AI54: =AG54+AH54 -> 218790 | AJ54: 0 | AK54: =AE54-AJ54 -> 6630 | AL54: =AE54*S54 -> 206332.23 | AM54: =(AG54+AH54)-AL54 -> 12457.77 | AN54: =IFERROR(AM54/(AG54+AH54),0) -> 0.056939394 | AO54: =AE54*S54 -> 206332.23 | AP54: =(Z54-K54) -> 57 | AQ54: =T54*9.35%*AP54/365 -> 1081.494 | AR54: =AM54-AQ54 -> 11376.276 | AS54: =AR54/(AG54+AH54) -> 0.051996325
... B78: =B77+1 -> 74 | C78: FY 2025-26 | D78: =TEXT(F78,"mmm-yy") -> May-25 | E78: Regular | F78: 45780 | G78: MHPV025 | H78: Tata Motors Passenger Vehicle Ltd | I78: 27AAHCT8301P1ZT | J78: MH6100102937 | K78: 45780 | L78: 25-26/PUR/001274 | M78: 45780 | N78: MH | O78: MH04BU8943 | P78: CRC | Q78: Scrap Sheet Metal Components of M V Parts | R78: 2970 | S78: 31.121 | T78: =R78*S78 -> 92429.37 | U78: Regular | V78: Fy 2025-26 | W78: =TEXT(Z78,"mmm-yy") -> Jul-25 | X78: Ultra | Y78: MPPUNE/0074 | Z78: 45864 | AA78: 27/MPIB/26IN0018 | AB78: SAARLOHA ADVANCED MATERIALS PRIVATE LIMITED | AC78: MS Scrap | AD78: MS Scrap | AE78: 25920 | AF78: 35.05 | AG78: =AE78*AF78 -> 908496 | AH78: 0 | AI78: =AG78+AH78 -> 908496 | AJ78: 0 | AK78: =AE78-AJ78 -> 25920 | AL78: =AE78*S78 -> 806656.32 | AM78: =(AG78+AH78)-AL78 -> 101839.68 | AN78: =IFERROR(AM78/(AG78+AH78),0) -> 0.112097 | AO78: =AE78*S78 -> 806656.32 | AP78: =(Z78-K78) -> 84 | AQ78: =T78*9.35%*AP78/365 -> 1988.8775 | AR78: =AM78-AQ78 -> 99850.803 | AS78: =AR78/(AG78+AH78) -> 0.10990781
B79: =B78+1 -> 75 | C79: FY 2025-26 | D79: =TEXT(F79,"mmm-yy") -> May-25 | E79: Regular | F79: 45782 | G79: MHPV026 | H79: SUYASH INDUSTRIES | I79: 27ABFFS1168K1ZV | J79: 594 | K79: 45782 | L79: 25-26/PUR/001424 | M79: 45783 | N79: MH | O79: MH43E8288 | P79: CRC | Q79: MS scrap (CRC) | R79: 7470 | S79: 36 | T79: =R79*S79 -> 268920 | U79: Regular | V79: Fy 2025-26 | W79: =TEXT(Z79,"mmm-yy") -> Jul-25 | X79: Ultra | Y79: MPPUNE/0075 | Z79: 45865 | AA79: 27/MPIB/26IN0019 | AB79: SAARLOHA ADVANCED MATERIALS PRIVATE LIMITED | AC79: MS Scrap | AD79: MS Scrap | AE79: 30750 | AF79: 35.05 | AG79: =AE79*AF79 -> 1077787.5 | AH79: -3505 | AI79: =AG79+AH79 -> 1074282.5 | AJ79: 0 | AK79: =AE79-AJ79 -> 30750 | AL79: =AE79*S79 -> 1107000 | AM79: =(AG79+AH79)-AL79 -> -32717.5 | AN79: =IFERROR(AM79/(AG79+AH79),0) -> -0.030455211 | AO79: =AE79*S79 -> 1107000 | AP79: =(Z79-K79) -> 83 | AQ79: =T79*9.35%*AP79/365 -> 5717.6813 | AR79: =AM79-AQ79 -> -38435.181 | AS79: =AR79/(AG79+AH79) -> -0.035777536
B80: =B79+1 -> 76 | C80: FY 2025-26 | D80: =TEXT(F80,"mmm-yy") -> May-25 | E80: Regular | F80: 45783 | G80: MHPV027 | H80: Tata Motors Passenger Vehicle Ltd | I80: 27AAHCT8301P1ZT | J80: MH6100109888 | K80: 45783 | L80: 25-26/PUR/001437 | M80: 45783 | N80: MH | O80: MH04BU8943 | P80: CRC | Q80: Scrap Sheet Metal Components of M V Parts | R80: 3110 | S80: 31.121 | T80: =R80*S80 -> 96786.31 | U80: Regular | V80: Fy 2025-26 | W80: =TEXT(Z80,"mmm-yy") -> Jul-25 | X80: M7483K | Y80: MPPUNE/0076 | Z80: 45866 | AA80: 27/MPIB/26IN0020 | AB80: Sona Foundry | AC80: MS Scrap | AD80: MS Scrap (Casting) | AE80: 12750 | AF80: 37.5 | AG80: =AE80*AF80 -> 478125 | AH80: -750 | AI80: =AG80+AH80 -> 477375 | AJ80: 0 | AK80: =AE80-AJ80 -> 12750 | AL80: =AE80*S80 -> 396792.75 | AM80: =(AG80+AH80)-AL80 -> 80582.25 | AN80: =IFERROR(AM80/(AG80+AH80),0) -> 0.16880283 | AO80: =AE80*S80 -> 396792.75 | AP80: =(Z80-K80) -> 83 | AQ80: =T80*9.35%*AP80/365 -> 2057.8361 | AR80: =AM80-AQ80 -> 78524.414 | AS80: =AR80/(AG80+AH80) -> 0.1644921
B81: =B80+1 -> 77 | C81: FY 2025-26 | D81: =TEXT(F81,"mmm-yy") -> May-25 | E81: Regular | F81: 45783 | G81: MHPV028 | H81: Tata Motors Passenger Vehicle Ltd | I81: 27AAHCT8301P1ZT | J81: MH6100110459 | K81: 45783 | L81: 25-26/PUR/001447 | M81: 45783 | N81: MH | O81: MH12KP9590 | P81: CRC | Q81: Scrap Sheet Metal Components of M V Parts | R81: 4160 | S81: 31.121 | T81: =R81*S81 -> 129463.36 | U81: Regular | V81: Fy 2025-26 | W81: =TEXT(Z81,"mmm-yy") -> Jul-25 | X81: Ultra | Y81: MPPUNE/0077 | Z81: 45867 | AA81: 27/MPIB/26IN0021 | AB81: SAARLOHA ADVANCED MATERIALS PRIVATE LIMITED | AC81: MS Scrap | AD81: MS Scrap | AE81: 28890 | AF81: 35.05 | AG81: =AE81*AF81 -> 1012594.5 | AH81: 0 | AI81: =AG81+AH81 -> 1012594.5 | AJ81: 0 | AK81: =AE81-AJ81 -> 28890 | AL81: =AE81*S81 -> 899085.69 | AM81: =(AG81+AH81)-AL81 -> 113508.81 | AN81: =IFERROR(AM81/(AG81+AH81),0) -> 0.112097 | AO81: =AE81*S81 -> 899085.69 | AP81: =(Z81-K81) -> 84 | AQ81: =T81*9.35%*AP81/365 -> 2785.7678 | AR81: =AM81-AQ81 -> 110723.04 | AS81: =AR81/(AG81+AH81) -> 0.10934589
B82: =B81+1 -> 78 | C82: FY 2025-26 | D82: =TEXT(F82,"mmm-yy") -> May-25 | E82: Regular | F82: 45785 | G82: MHPV029 | H82: Tata Motors Passenger Vehicle Ltd | I82: 27AAHCT8301P1ZT | J82: MH6100117271 | K82: 45785 | L82: 25-26/PUR/001573 | M82: 45785 | N82: MH | O82: MH12KP9590 | P82: CRC | Q82: Scrap Sheet Metal Components of M V Parts | R82: 2320 | S82: 31.121 | T82: =R82*S82 -> 72200.72 | U82: Regular | V82: Fy 2025-26 | W82: =TEXT(Z82,"mmm-yy") -> Aug-25 | X82: CRC | Y82: MPPUNE/0078 | Z82: 45871 | AA82: 27/MPIB/26IN0023 | AB82: Sound Castings Private Limited - U5 | AC82: CRC | AD82: MS Scrap (CRC) | AE82: 31170 | AF82: 35.9 | AG82: =AE82*AF82 -> 1119003 | AH82: -14001 | AI82: =AG82+AH82 -> 1105002 | AJ82: 0 | AK82: =AE82-AJ82 -> 31170 | AL82: =AE82*S82 -> 970041.57 | AM82: =(AG82+AH82)-AL82 -> 134960.43 | AN82: =IFERROR(AM82/(AG82+AH82),0) -> 0.12213591 | AO82: =AE82*S82 -> 970041.57 | AP82: =(Z82-K82) -> 86 | AQ82: =T82*9.35%*AP82/365 -> 1590.5918 | AR82: =AM82-AQ82 -> 133369.84 | AS82: =AR82/(AG82+AH82) -> 0.12069647
B83: =B82+1 -> 79 | C83: FY 2025-26 | D83: =TEXT(F83,"mmm-yy") -> May-25 | E83: Regular | F83: 45786 | G83: MHPV030 | H83: Tata Motors Ltd | I83: 27AAACT2727Q1ZW | J83: MH0100114662 | K83: 45786 | L83: 25-26/PUR/001637 | M83: 45786 | N83: MH | O83: MH12KP9590 | P83: CRC | Q83: Scrap Sheet Metal Components of M V Parts | R83: 4560 | S83: 30.151 | T83: =R83*S83 -> 137488.56 | U83: Regular | V83: Fy 2025-26 | W83: =TEXT(Z83,"mmm-yy") -> Aug-25 | X83: Ultra | Y83: MPPUNE/0079 | Z83: 45871 | AA83: 27/MPIB/26IN0024 | AB83: Sound Castings Private Limited - U5 | AC83: MS Scrap | AD83: MS Scrap | AE83: 5420 | AF83: 35.7 | AG83: =AE83*AF83 -> 193494 | AH83: =-2142-1631 -> -3773 | AI83: =AG83+AH83 -> 189721 | AJ83: 0 | AK83: =AE83-AJ83 -> 5420 | AL83: =AE83*S83 -> 163418.42 | AM83: =(AG83+AH83)-AL83 -> 26302.58 | AN83: =IFERROR(AM83/(AG83+AH83),0) -> 0.13863821 | AO83: =AE83*S83 -> 163418.42 | AP83: =(Z83-K83) -> 85 | AQ83: =T83*9.35%*AP83/365 -> 2993.6721 | AR83: =AM83-AQ83 -> 23308.908 | AS83: =AR83/(AG83+AH83) -> 0.12285887
B84: =B83+1 -> 80 | C84: FY 2025-26 | D84: =TEXT(F84,"mmm-yy") -> May-25 | E84: Regular | F84: 45791 | G84: MHPV031 | H84: Tata Motors Passenger Vehicle Ltd | I84: 27AAHCT8301P1ZT | J84: MH6100135639 | K84: 45791 | L84: 25-26/PUR/001778 | M84: 45791 | N84: MH | O84: MH14BJ3188 | P84: CRC | Q84: Scrap Sheet Metal Components of M V Parts | R84: 2520 | S84: 31.121 | T84: =R84*S84 -> 78424.92 | U84: Regular | V84: Fy 2025-26 | W84: =TEXT(Z84,"mmm-yy") -> Aug-25 | X84: Ultra | Y84: MPPUNE/0079 | Z84: 45874 | AA84: 27/MPIB/26IN0025 | AB84: Sound Castings Private Limited - U5 | AC84: MS Scrap | AD84: MS Scrap | AE84: 20390 | AF84: 35.7 | AG84: =AE84*AF84 -> 727923 | AH84: 0 | AI84: =AG84+AH84 -> 727923 | AJ84: 0 | AK84: =AE84-AJ84 -> 20390 | AL84: =AE84*S84 -> 634557.19 | AM84: =(AG84+AH84)-AL84 -> 93365.81 | AN84: =IFERROR(AM84/(AG84+AH84),0) -> 0.12826331 | AO84: =AE84*S84 -> 634557.19 | AP84: =(Z84-K84) -> 83 | AQ84: =T84*9.35%*AP84/365 -> 1667.4427 | AR84: =AM84-AQ84 -> 91698.367 | AS84: =AR84/(AG84+AH84) -> 0.12597262
B85: =B84+1 -> 81 | C85: FY 2025-26 | D85: =TEXT(F85,"mmm-yy") -> May-25 | E85: Regular | F85: 45791 | G85: MHPV032 | H85: Tata Motors Passenger Vehicle Ltd | I85: 27AAHCT8301P1ZT | J85: MH6100135881 | K85: 45791 | L85: 25-26/PUR/001790 | M85: 45791 | N85: MH | O85: MH04BU8943 | P85: CRC | Q85: Scrap Sheet Metal Components of M V Parts | R85: 2450 | S85: 31.121 | T85: =R85*S85 -> 76246.45 | U85: Regular | V85: Fy 2025-26 | W85: =TEXT(Z85,"mmm-yy") -> Aug-25 | X85: CRC | Y85: MPPUNE/0080 | Z85: 45875 | AA85: 27/MPIB/26IN0026 | AB85: Sound Castings Private Limited - U5 | AC85: CRC | AD85: MS Scrap (CRC) | AE85: 23950 | AF85: 35.9 | AG85: =AE85*AF85 -> 859805 | AH85: =-6462-1916 -> -8378 | AI85: =AG85+AH85 -> 851427 | AJ85: 0 | AK85: =AE85-AJ85 -> 23950 | AL85: =AE85*S85 -> 745347.95 | AM85: =(AG85+AH85)-AL85 -> 106079.05 | AN85: =IFERROR(AM85/(AG85+AH85),0) -> 0.12458972 | AO85: =AE85*S85 -> 745347.95 | AP85: =(Z85-K85) -> 84 | AQ85: =T85*9.35%*AP85/365 -> 1640.6565 | AR85: =AM85-AQ85 -> 104438.39 | AS85: =AR85/(AG85+AH85) -> 0.12266277
B86: =B85+1 -> 82 | C86: FY 2025-26 | D86: =TEXT(F86,"mmm-yy") -> May-25 | E86: Regular | F86: 45793 | G86: MHPV034 | H86: Tata Motors Passenger Vehicle Ltd | I86: 27AAHCT8301P1ZT | J86: MH6100143150 | K86: 45793 | L86: 25-26/PUR/001870 | M86: 45793 | N86: MH | O86: MH14DM7761 | P86: CRC | Q86: Scrap Sheet Metal Components of M V Parts | R86: 3060 | S86: 31.121 | T86: =R86*S86 -> 95230.26 | U86: Regular | V86: Fy 2025-26 | W86: =TEXT(Z86,"mmm-yy") -> Aug-25 | X86: Ultra | Y86: MPPUNE/0081 | Z86: 45876 | AA86: 27/MPIB/26IN0027 | AB86: SAARLOHA ADVANCED MATERIALS PRIVATE LIMITED | AC86: MS Scrap | AD86: MS Scrap | AE86: 25465 | AF86: 35.7 | AG86: =AE86*AF86 -> 909100.5 | AH86: 0 | AI86: =AG86+AH86 -> 909100.5 | AJ86: 0 | AK86: =AE86-AJ86 -> 25465 | AL86: =AE86*S86 -> 792496.27 | AM86: =(AG86+AH86)-AL86 -> 116604.24 | AN86: =IFERROR(AM86/(AG86+AH86),0) -> 0.12826331 | AO86: =AE86*S86 -> 792496.27 | AP86: =(Z86-K86) -> 83 | AQ86: =T86*9.35%*AP86/365 -> 2024.7519 | AR86: =AM86-AQ86 -> 114579.48 | AS86: =AR86/(AG86+AH86) -> 0.1260361
B87: =B86+1 -> 83 | C87: FY 2025-26 | D87: =TEXT(F87,"mmm-yy") -> May-25 | E87: Regular | F87: 45793 | G87: MHPV033 | H87: Tata Motors Passenger Vehicle Ltd | I87: 27AAHCT8301P1ZT | J87: MH6100142704 | K87: 45793 | L87: 25-26/PUR/001858 | M87: 45793 | N87: MH | O87: MH04BU8943 | P87: CRC | Q87: Scrap Sheet Metal Components of M V Parts | R87: 2650 | S87: 31.121 | T87: =R87*S87 -> 82470.65 | U87: Regular | V87: Fy 2025-26 | W87: =TEXT(Z87,"mmm-yy") -> Aug-25 | X87: Ultra | Y87: MPPUNE/0082 | Z87: 45877 | AA87: 27/MPIB/26IN0028 | AB87: SAARLOHA ADVANCED MATERIALS PRIVATE LIMITED | AC87: MS Scrap | AD87: MS Scrap | AE87: 26665 | AF87: 35.7 | AG87: =AE87*AF87 -> 951940.5 | AH87: 0 | AI87: =AG87+AH87 -> 951940.5 | AJ87: 0 | AK87: =AE87-AJ87 -> 26665 | AL87: =AE87*S87 -> 829841.46 | AM87: =(AG87+AH87)-AL87 -> 122099.04 | AN87: =IFERROR(AM87/(AG87+AH87),0) -> 0.12826331 | AO87: =AE87*S87 -> 829841.46 | AP87: =(Z87-K87) -> 84 | AQ87: =T87*9.35%*AP87/365 -> 1774.5876 | AR87: =AM87-AQ87 -> 120324.45 | AS87: =IFERROR(AR87/(AG87+AH87),0) -> 0.12639913
B88: =B87+1 -> 84 | C88: FY 2025-26 | D88: =TEXT(F88,"mmm-yy") -> May-25 | E88: Regular | F88: 45794 | G88: MHPV035 | H88: Tata Motors Ltd | I88: 27AAACT2727Q1ZW | J88: MH0100138293 | K88: 45794 | L88: 25-26/PUR/001893 | M88: 45794 | N88: MH | O88: MH04BU8943 | P88: CRC | Q88: Scrap Sheet Metal Components of M V Parts | R88: 5060 | S88: 30.151 | T88: =R88*S88 -> 152564.06 | U88: Regular | V88: Fy 2025-26 | W88: =TEXT(Z88,"mmm-yy") -> Aug-25 | X88: CRC | Y88: MPPUNE/0083 | Z88: 45878 | AA88: 27/MPIB/26IN0029 | AB88: S S R ENTERPRISES | AC88: CRC | AD88: MS Scrap (CRC) | AE88: 31310 | AF88: 33 | AG88: =AE88*AF88 -> 1033230 | AH88: -31310 | AI88: =AG88+AH88 -> 1001920 | AJ88: 0 | AK88: =AE88-AJ88 -> 31310 | AL88: =AE88*S88 -> 944027.81 | AM88: =(AG88+AH88)-AL88 -> 57892.19 | AN88: =IFERROR(AM88/(AG88+AH88),0) -> 0.05778125 | AO88: =AE88*S88 -> 944027.81 | AP88: =(Z88-K88) -> 84 | AQ88: =T88*9.35%*AP88/365 -> 3282.8442 | AR88: =AM88-AQ88 -> 54609.346 | AS88: =IFERROR(AR88/(AG88+AH88),0) -> 0.054504697
B89: =B88+1 -> 85 | C89: FY 2025-26 | D89: =TEXT(F89,"mmm-yy") -> May-25 | E89: Regular | F89: 45796 | G89: MHPV036 | H89: Tata Motors Passenger Vehicle Ltd | I89: 27AAHCT8301P1ZT | J89: MH6100151811 | K89: 45796 | L89: 25-26/PUR/001958 | M89: 45796 | N89: MH | O89: MH04BU8943 | P89: CRC | Q89: Scrap Sheet Metal Components of M V Parts | R89: 2260 | S89: 31.121 | T89: =R89*S89 -> 70333.46 | U89: Regular | V89: Fy 2025-26 | W89: =TEXT(Z89,"mmm-yy") -> Aug-25 | X89: Ultra | Y89: MPPUNE/0085 | Z89: 45878 | AA89: 27/MPIB/26IN0031 | AB89: SAARLOHA ADVANCED MATERIALS PRIVATE LIMITED | AC89: MS Scrap | AD89: MS Scrap | AE89: 29575 | AF89: 35.7 | AG89: =AE89*AF89 -> 1055827.5 | AH89: 0 | AI89: =AG89+AH89 -> 1055827.5 | AJ89: 0 | AK89: =AE89-AJ89 -> 29575 | AL89: =AE89*S89 -> 920403.57 | AM89: =(AG89+AH89)-AL89 -> 135423.93 | AN89: =IFERROR(AM89/(AG89+AH89),0) -> 0.12826331 | AO89: =AE89*S89 -> 920403.57 | AP89: =(Z89-K89) -> 82 | AQ89: =T89*9.35%*AP89/365 -> 1477.388 | AR89: =AM89-AQ89 -> 133946.54 | AS89: =IFERROR(AR89/(AG89+AH89),0) -> 0.12686404
B90: =B89+1 -> 86 | C90: FY 2025-26 | D90: =TEXT(F90,"mmm-yy") -> May-25 | E90: Regular | F90: 45799 | G90: MHPV037 | H90: Tata Motors Passenger Vehicle Ltd | I90: 27AAHCT8301P1ZT | J90: MH6100162608 | K90: 45799 | L90: 25-26/PUR/002088 | M90: 45799 | N90: MH | O90: MH14DM7761 | P90: CRC | Q90: Scrap Sheet Metal Components of M V Parts | R90: 3610 | S90: 31.121 | T90: =R90*S90 -> 112346.81 | U90: Regular | V90: Fy 2025-26 | W90: =TEXT(Z90,"mmm-yy") -> Aug-25 | X90: Ultra | Y90: MPPUNE/0084 | Z90: 45878 | AA90: 27/MPIB/26IN0030 | AB90: SAARLOHA ADVANCED MATERIALS PRIVATE LIMITED | AC90: MS Scrap | AD90: MS Scrap | AE90: 14340 | AF90: 33.75 | AG90: =AE90*AF90 -> 483975 | AH90: 0 | AI90: =AG90+AH90 -> 483975 | AJ90: 0 | AK90: =AE90-AJ90 -> 14340 | AL90: =AE90*S90 -> 446275.14 | AM90: =(AG90+AH90)-AL90 -> 37699.86 | AN90: =IFERROR(AM90/(AG90+AH90),0) -> 0.077896296 | AO90: =AE90*S90 -> 446275.14 | AP90: =(Z90-K90) -> 79 | AQ90: =T90*9.35%*AP90/365 -> 2273.5609 | AR90: =AM90-AQ90 -> 35426.299 | AS90: =IFERROR(AR90/(AG90+AH90),0) -> 0.073198614
B91: =B90+1 -> 87 | C91: FY 2025-26 | D91: =TEXT(F91,"mmm-yy") -> May-25 | E91: Regular | F91: 45800 | G91: MHPV038 | H91: Tata Motors Passenger Vehicle Ltd | I91: 27AAHCT8301P1ZT | J91: MH6100165666 | K91: 45800 | L91: 25-26/PUR/002136 | M91: 45800 | N91: MH | O91: MH04BU8943 | P91: CRC | Q91: Scrap Sheet Metal Components of M V Parts | R91: 2520 | S91: 31.121 | T91: =R91*S91 -> 78424.92 | U91: Regular | V91: Fy 2025-26 | W91: =TEXT(Z91,"mmm-yy") -> Aug-25 | X91: Ultra | Y91: MPPUNE/0086 | Z91: 45879 | AA91: 27/MPIB/26IN0032 | AB91: SAARLOHA ADVANCED MATERIALS PRIVATE LIMITED | AC91: MS Scrap | AD91: MS Scrap | AE91: 18430 | AF91: 35.7 | AG91: =AE91*AF91 -> 657951 | AH91: 0 | AI91: =AG91+AH91 -> 657951 | AJ91: 0 | AK91: =AE91-AJ91 -> 18430 | AL91: =AE91*S91 -> 573560.03 | AM91: =(AG91+AH91)-AL91 -> 84390.97 | AN91: =IFERROR(AM91/(AG91+AH91),0) -> 0.12826331 | AO91: =AE91*S91 -> 573560.03 | AP91: =(Z91-K91) -> 79 | AQ91: =T91*9.35%*AP91/365 -> 1587.084 | AR91: =AM91-AQ91 -> 82803.886 | AS91: =IFERROR(AR91/(AG91+AH91),0) -> 0.12585114
B92: =B91+1 -> 88 | C92: FY 2025-26 | D92: =TEXT(F92,"mmm-yy") -> May-25 | E92: Regular | F92: 45800 | G92: MHPV039 | H92: Tata Motors Passenger Vehicle Ltd | I92: 27AAHCT8301P1ZT | J92: MH6100166138 | K92: 45800 | L92: 25-26/PUR/002137 | M92: 45800 | N92: MH | O92: MH14CP7057 | P92: CRC | Q92: Scrap Sheet Metal Components of M V Parts | R92: 3410 | S92: 31.121 | T92: =R92*S92 -> 106122.61 | U92: Regular | V92: Fy 2025-26 | W92: =TEXT(Z92,"mmm-yy") -> Aug-25 | X92: Ultra | Y92: MPPUNE/0087 | Z92: 45879 | AA92: 27/MPIB/26IN0033 | AB92: SAARLOHA ADVANCED MATERIALS PRIVATE LIMITED | AC92: MS Scrap | AD92: MS Scrap | AE92: 18580 | AF92: 33.75 | AG92: =AE92*AF92 -> 627075 | AH92: -2025 | AI92: =AG92+AH92 -> 625050 | AJ92: 0 | AK92: =AE92-AJ92 -> 18580 | AL92: =AE92*S92 -> 578228.18 | AM92: =(AG92+AH92)-AL92 -> 46821.82 | AN92: =IFERROR(AM92/(AG92+AH92),0) -> 0.074908919 | AO92: =AE92*S92 -> 578228.18 | AP92: =(Z92-K92) -> 79 | AQ92: =T92*9.35%*AP92/365 -> 2147.6018 | AR92: =AM92-AQ92 -> 44674.218 | AS92: =IFERROR(AR92/(AG92+AH92),0) -> 0.071473031
B93: =B92+1 -> 89 | C93: FY 2025-26 | D93: =TEXT(F93,"mmm-yy") -> May-25 | E93: Regular | F93: 45803 | G93: MHPV040 | H93: Tata Motors Passenger Vehicle Ltd | I93: 27AAHCT8301P1ZT | J93: MH6100174335 | K93: 45803 | L93: 25-26/PUR/002246 | M93: 45803 | N93: MH | O93: MH12FZ7432 | P93: CRC | Q93: Scrap Sheet Metal Components of M V Parts | R93: 3290 | S93: 31.121 | T93: =R93*S93 -> 102388.09 | U93: Regular | V93: Fy 2025-26 | W93: =TEXT(Z93,"mmm-yy") -> Aug-25 | X93: Ultra | Y93: MPPUNE/0088 | Z93: 45880 | AA93: 27/MPIB/26IN0034 | AB93: SAARLOHA ADVANCED MATERIALS PRIVATE LIMITED | AC93: MS Scrap | AD93: MS Scrap | AE93: 17935 | AF93: 33.75 | AG93: =AE93*AF93 -> 605306.25 | AH93: 0 | AI93: =AG93+AH93 -> 605306.25 | AJ93: 0 | AK93: =AE93-AJ93 -> 17935 | AL93: =AE93*S93 -> 558155.14 | AM93: =(AG93+AH93)-AL93 -> 47151.115 | AN93: =IFERROR(AM93/(AG93+AH93),0) -> 0.077896296 | AO93: =AE93*S93 -> 558155.14 | AP93: =(Z93-K93) -> 77 | AQ93: =T93*9.35%*AP93/365 -> 2019.57 | AR93: =AM93-AQ93 -> 45131.545 | AS93: =IFERROR(AR93/(AG93+AH93),0) -> 0.074559853
B94: =B93+1 -> 90 | C94: FY 2025-26 | D94: =TEXT(F94,"mmm-yy") -> May-25 | E94: Regular | F94: 45806 | G94: MHPV042 | H94: Tata Motors Passenger Vehicle Ltd | I94: 27AAHCT8301P1ZT | J94: MH6100185373 | K94: 45806 | L94: 25-26/PUR/002376 | M94: 45806 | N94: MH | O94: MH04BU8943 | P94: CRC | Q94: Scrap Sheet Metal Components of M V Parts | R94: 2800 | S94: 31.121 | T94: =R94*S94 -> 87138.8 | U94: Regular | V94: Fy 2025-26 | W94: =TEXT(Z94,"mmm-yy") -> Aug-25 | X94: CRC | Y94: MPPUNE/0089 | Z94: 45881 | AA94: 27/MPIB/26IN0035 | AB94: S S R ENTERPRISES | AC94: CRC | AD94: MS Scrap (CRC) | AE94: 25320 | AF94: 33 | AG94: =AE94*AF94 -> 835560 | AH94: -25320 | AI94: =AG94+AH94 -> 810240 | AJ94: 0 | AK94: =AE94-AJ94 -> 25320 | AL94: =AE94*S94 -> 787983.72 | AM94: =(AG94+AH94)-AL94 -> 22256.28 | AN94: =IFERROR(AM94/(AG94+AH94),0) -> 0.02746875 | AO94: =AE94*S94 -> 787983.72 | AP94: =(Z94-K94) -> 75 | AQ94: =T94*9.35%*AP94/365 -> 1674.1393 | AR94: =AM94-AQ94 -> 20582.141 | AS94: =IFERROR(AR94/(AG94+AH94),0) -> 0.025402524
B95: =B94+1 -> 91 | C95: FY 2025-26 | D95: =TEXT(F95,"mmm-yy") -> May-25 | E95: Regular | F95: 45806 | G95: MHPV041 | H95: Tata Motors Passenger Vehicle Ltd | I95: 27AAHCT8301P1ZT | J95: MH6100185544 | K95: 45806 | L95: 25-26/PUR/002377 | M95: 45806 | N95: MH | O95: MH04FJ7949 | P95: CRC | Q95: Scrap Sheet Metal Components of M V Parts | R95: 2600 | S95: 31.121 | T95: =R95*S95 -> 80914.6 | U95: Regular | V95: Fy 2025-26 | W95: =TEXT(Z95,"mmm-yy") -> Aug-25 | X95: Ultra | Y95: MPPUNE/0090 | Z95: 45882 | AA95: 27/MPIB/26IN0036 | AB95: Sound Castings Private Limited - U2 | AC95: MS Scrap | AD95: MS Scrap | AE95: 25480 | AF95: 35.7 | AG95: =AE95*AF95 -> 909636 | AH95: -3927 | AI95: =AG95+AH95 -> 905709 | AJ95: 0 | AK95: =AE95-AJ95 -> 25480 | AL95: =AE95*S95 -> 792963.08 | AM95: =(AG95+AH95)-AL95 -> 112745.92 | AN95: =IFERROR(AM95/(AG95+AH95),0) -> 0.1244836 | AO95: =AE95*S95 -> 792963.08 | AP95: =(Z95-K95) -> 76 | AQ95: =T95*9.35%*AP95/365 -> 1575.2853 | AR95: =AM95-AQ95 -> 111170.63 | AS95: =IFERROR(AR95/(AG95+AH95),0) -> 0.12274432
B96: =B95+1 -> 92 | C96: FY 2025-26 | D96: =TEXT(F96,"mmm-yy") -> May-25 | E96: Regular | F96: 45807 | G96: MHPV044 | H96: Tata Motors Ltd | I96: 27AAACT2727Q1ZW | J96: MH0100189081 | K96: 45807 | L96: 25-26/PUR/002414 | M96: 45807 | N96: MH | O96: MH04BU8943 | P96: CRC | Q96: Scrap Sheet Metal Components of M V Parts | R96: 3320 | S96: 30.151 | T96: =R96*S96 -> 100101.32 | U96: Regular | V96: Fy 2025-26 | W96: =TEXT(Z96,"mmm-yy") -> Aug-25 | X96: Ultra | Y96: MPPUNE/0091 | Z96: 45888 | AA96: 27/MPIB/26IN0037 | AB96: Sound Castings Private Limited - U2 | AC96: MS Scrap | AD96: MS Scrap | AE96: 25670 | AF96: 35.7 | AG96: =AE96*AF96 -> 916419 | AH96: -4641 | AI96: =AG96+AH96 -> 911778 | AJ96: 0 | AK96: =AE96-AJ96 -> 25670 | AL96: =AE96*S96 -> 773976.17 | AM96: =(AG96+AH96)-AL96 -> 137801.83 | AN96: =IFERROR(AM96/(AG96+AH96),0) -> 0.15113529 | AO96: =AE96*S96 -> 773976.17 | AP96: =(Z96-K96) -> 81 | AQ96: =T96*9.35%*AP96/365 -> 2077.0338 | AR96: =AM96-AQ96 -> 135724.8 | AS96: =IFERROR(AR96/(AG96+AH96),0) -> 0.14885728
B97: =B96+1 -> 93 | C97: FY 2025-26 | D97: =TEXT(F97,"mmm-yy") -> May-25 | E97: Regular | F97: 45807 | G97: MHPV043 | H97: Tata Motors Ltd | I97: 27AAACT2727Q1ZW | J97: MH0100190160 | K97: 45807 | L97: 25-26/PUR/002413 | M97: 45807 | N97: MH | O97: MH04FJ7949 | P97: CRC | Q97: Scrap Sheet Metal Components of M V Parts | R97: 4240 | S97: 30.151 | T97: =R97*S97 -> 127840.24 | U97: Regular | V97: Fy 2025-26 | W97: =TEXT(Z97,"mmm-yy") -> Aug-25 | X97: A18K | Y97: MPPUNE/0095 | Z97: 45890 | AA97: 27/MPIB/26IN0041 | AB97: Yash Enterprises | AC97: MS Scrap | AD97: MS Scrap | AE97: 6070 | AF97: 28 | AG97: =AE97*AF97 -> 169960 | AH97: 0 | AI97: =AG97+AH97 -> 169960 | AJ97: 0 | AK97: =AE97-AJ97 -> 6070 | AL97: =AE97*S97 -> 183016.57 | AM97: =(AG97+AH97)-AL97 -> -13056.57 | AN97: =IFERROR(AM97/(AG97+AH97),0) -> -0.076821429 | AO97: =AE97*S97 -> 183016.57 | AP97: =(Z97-K97) -> 83 | AQ97: =T97*9.35%*AP97/365 -> 2718.0937 | AR97: =AM97-AQ97 -> -15774.664 | AS97: =IFERROR(AR97/(AG97+AH97),0) -> -0.092813978
B98: =B97+1 -> 94 | C98: FY 2025-26 | D98: =TEXT(F98,"mmm-yy") -> Jun-25 | E98: Regular | F98: 45811 | G98: MHPV047 | H98: AUTOCOMP CORPORATION PANSE PVT LTD | I98: 27AAFCA6224N1ZG | J98: 6122503531 | K98: 45811 | L98: 25-26/PUR/002589 | M98: 45812 | N98: MH | O98: MH04BU8943 | P98: CRC | Q98: MS scrap (CRC) | R98: 8540 | S98: 34.2 | T98: =R98*S98 -> 292068 | U98: Regular | V98: Fy 2025-26 | W98: =TEXT(Z98,"mmm-yy") -> Aug-25 | X98: A18K | Y98: MPPUNE/0092 | Z98: 45890 | AA98: 27/MPIB/26IN0038 | AB98: Yash Enterprises | AC98: MS Scrap | AD98: MS Scrap | AE98: 4210 | AF98: 28 | AG98: =AE98*AF98 -> 117880 | AH98: 0 | AI98: =AG98+AH98 -> 117880 | AJ98: 0 | AK98: =AE98-AJ98 -> 4210 | AL98: =AE98*S98 -> 143982 | AM98: =(AG98+AH98)-AL98 -> -26102 | AN98: =IFERROR(AM98/(AG98+AH98),0) -> -0.22142857 | AO98: =AE98*S98 -> 143982 | AP98: =(Z98-K98) -> 79 | AQ98: =T98*9.35%*AP98/365 -> 5910.5761 | AR98: =AM98-AQ98 -> -32012.576 | AS98: =IFERROR(AR98/(AG98+AH98),0) -> -0.27156919
B99: =B98+1 -> 95 | C99: FY 2025-26 | D99: =TEXT(F99,"mmm-yy") -> Jun-25 | E99: Regular | F99: 45811 | G99: MHPV045 | H99: AUTOCOMP CORPORATION PANSE PVT LTD | I99: 27AAFCA6224N1ZG | J99: 6122503525 | K99: 45811 | L99: 25-26/PUR/002575 | M99: 45812 | N99: MH | O99: MH12KP9590 | P99: CRC | Q99: MS scrap (CRC) | R99: 7535 | S99: 34.2 | T99: =R99*S99 -> 257697 | U99: Regular | V99: Fy 2025-26 | W99: =TEXT(Z99,"mmm-yy") -> Aug-25 | X99: A18K | Y99: MPPUNE/0093 | Z99: 45890 | AA99: 27/MPIB/26IN0039 | AB99: Yash Enterprises | AC99: MS Scrap | AD99: MS Scrap | AE99: 4300 | AF99: 28 | AG99: =AE99*AF99 -> 120400 | AH99: 0 | AI99: =AG99+AH99 -> 120400 | AJ99: 0 | AK99: =AE99-AJ99 -> 4300 | AL99: =AE99*S99 -> 147060 | AM99: =(AG99+AH99)-AL99 -> -26660 | AN99: =IFERROR(AM99/(AG99+AH99),0) -> -0.22142857 | AO99: =AE99*S99 -> 147060 | AP99: =(Z99-K99) -> 79 | AQ99: =T99*9.35%*AP99/365 -> 5215.0107 | AR99: =AM99-AQ99 -> -31875.011 | AS99: =IFERROR(AR99/(AG99+AH99),0) -> -0.26474261
B100: =B99+1 -> 96 | C100: FY 2025-26 | D100: =TEXT(F100,"mmm-yy") -> Jun-25 | E100: Regular | F100: 45811 | G100: MHPV046 | H100: AUTOCOMP CORPORATION PANSE PVT LTD | I100: 27AAFCA6224N1ZG | J100: 6122503528 | K100: 45811 | L100: 25-26/PUR/002577 | M100: 45812 | N100: MH | O100: MH04FJ7949 | P100: CRC | Q100: MS scrap (CRC) | R100: 7810 | S100: 34.2 | T100: =R100*S100 -> 267102 | U100: Regular | V100: Fy 2025-26 | W100: =TEXT(Z100,"mmm-yy") -> Aug-25 | X100: A18K | Y100: MPPUNE/0094 | Z100: 45890 | AA100: 27/MPIB/26IN0040 | AB100: Yash Enterprises | AC100: MS Scrap | AD100: MS Scrap | AE100: 4030 | AF100: 28 | AG100: =AE100*AF100 -> 112840 | AH100: 0 | AI100: =AG100+AH100 -> 112840 | AJ100: 0 | AK100: =AE100-AJ100 -> 4030 | AL100: =AE100*S100 -> 137826 | AM100: =(AG100+AH100)-AL100 -> -24986 | AN100: =IFERROR(AM100/(AG100+AH100),0) -> -0.22142857 | AO100: =AE100*S100 -> 137826 | AP100: =(Z100-K100) -> 79 | AQ100: =T100*9.35%*AP100/365 -> 5405.3395 | AR100: =AM100-AQ100 -> -30391.34 | AS100: =IFERROR(AR100/(AG100+AH100),0) -> -0.26933126
B101: =B100+1 -> 97 | C101: FY 2025-26 | D101: =TEXT(F101,"mmm-yy") -> Jun-25 | E101: Regular | F101: 45812 | G101: MHPV048 | H101: AUTOCOMP CORPORATION PANSE PVT LTD | I101: 27AAFCA6224N1ZG | J101: 6122503572 | K101: 45812 | L101: 25-26/PUR/002590 | M101: 45812 | N101: MH | O101: MH43E8288 | P101: CRC | Q101: MS scrap (CRC) | R101: 10970 | S101: 34.2 | T101: =R101*S101 -> 375174 | U101: Regular | V101: Fy 2025-26 | W101: =TEXT(Z101,"mmm-yy") -> Aug-25 | X101: Ultra | Y101: MPPUNE/0098 | Z101: 45892 | AA101: 27/MPIB/26IN0044 | AB101: Sound Castings Private Limited - U2 | AC101: MS Scrap | AD101: MS Scrap | AE101: 24295 | AF101: 35.7 | AG101: =AE101*AF101 -> 867331.5 | AH101: 0 | AI101: =AG101+AH101 -> 867331.5 | AJ101: 0 | AK101: =AE101-AJ101 -> 24295 | AL101: =AE101*S101 -> 830889 | AM101: =(AG101+AH101)-AL101 -> 36442.5 | AN101: =IFERROR(AM101/(AG101+AH101),0) -> 0.042016807 | AO101: =AE101*S101 -> 830889 | AP101: =(Z101-K101) -> 80 | AQ101: =T101*9.35%*AP101/365 -> 7688.4973 | AR101: =AM101-AQ101 -> 28754.003 | AS101: =IFERROR(AR101/(AG101+AH101),0) -> 0.033152264
B102: =B101+1 -> 98 | C102: FY 2025-26 | D102: =TEXT(F102,"mmm-yy") -> Jun-25 | E102: Regular | F102: 45812 | G102: MHPV049 | H102: AUTOCOMP CORPORATION PANSE PVT LTD | I102: 27AAFCA6224N1ZG | J102: 6122503579 | K102: 45812 | L102: 25-26/PUR/002602 | M102: 45812 | N102: MH | O102: MH27BX0052 | P102: CRC | Q102: MS scrap (CRC) | R102: 7995 | S102: 34.2 | T102: =R102*S102 -> 273429 | U102: Regular | V102: Fy 2025-26 | W102: =TEXT(Z102,"mmm-yy") -> Aug-25 | X102: A18K | Y102: MPPUNE/0096 | Z102: 45892 | AA102: 27/MPIB/26IN0042 | AB102: Yash Enterprises | AC102: MS Scrap | AD102: MS Scrap | AE102: 3290 | AF102: 28 | AG102: =AE102*AF102 -> 92120 | AH102: 0 | AI102: =AG102+AH102 -> 92120 | AJ102: 0 | AK102: =AE102-AJ102 -> 3290 | AL102: =AE102*S102 -> 112518 | AM102: =(AG102+AH102)-AL102 -> -20398 | AN102: =IFERROR(AM102/(AG102+AH102),0) -> -0.22142857 | AO102: =AE102*S102 -> 112518 | AP102: =(Z102-K102) -> 80 | AQ102: =T102*9.35%*AP102/365 -> 5603.4217 | AR102: =AM102-AQ102 -> -26001.422 | AS102: =IFERROR(AR102/(AG102+AH102),0) -> -0.28225599
B103: =B102+1 -> 99 | C103: FY 2025-26 | D103: =TEXT(F103,"mmm-yy") -> Jun-25 | E103: Regular | F103: 45812 | G103: MHPV050 | H103: AUTOCOMP CORPORATION PANSE PVT LTD | I103: 27AAFCA6224N1ZG | J103: 6122503583 | K103: 45812 | L103: 25-26/PUR/002635 | M103: 45813 | N103: MH | O103: MH04BU8943 | P103: CRC | Q103: MS scrap (CRC) | R103: 5990 | S103: 34.2 | T103: =R103*S103 -> 204858 | U103: Regular | V103: Fy 2025-26 | W103: =TEXT(Z103,"mmm-yy") -> Aug-25 | X103: A18K | Y103: MPPUNE/0097 | Z103: 45892 | AA103: 27/MPIB/26IN0043 | AB103: Yash Enterprises | AC103: MS Scrap | AD103: MS Scrap | AE103: 3280 | AF103: 28 | AG103: =AE103*AF103 -> 91840 | AH103: 0 | AI103: =AG103+AH103 -> 91840 | AJ103: 0 | AK103: =AE103-AJ103 -> 3280 | AL103: =AE103*S103 -> 112176 | AM103: =(AG103+AH103)-AL103 -> -20336 | AN103: =IFERROR(AM103/(AG103+AH103),0) -> -0.22142857 | AO103: =AE103*S103 -> 112176 | AP103: =(Z103-K103) -> 80 | AQ103: =T103*9.35%*AP103/365 -> 4198.1859 | AR103: =AM103-AQ103 -> -24534.186 | AS103: =IFERROR(AR103/(AG103+AH103),0) -> -0.26714053
B104: =B103+1 -> 100 | C104: FY 2025-26 | D104: =TEXT(F104,"mmm-yy") -> Jun-25 | E104: Regular | F104: 45813 | G104: MHPV051 | H104: AUTOCOMP CORPORATION PANSE PVT LTD | I104: 27AAFCA6224N1ZG | J104: 6122503641 | K104: 45813 | L104: 25-26/PUR/002655 | M104: 45814 | N104: MH | O104: MH12KP9590 | P104: CRC | Q104: MS scrap (CRC) | R104: 9180 | S104: 34.2 | T104: =R104*S104 -> 313956 | U104: Regular | V104: Fy 2025-26 | W104: =TEXT(Z104,"mmm-yy") -> Aug-25 | X104: A18K | Y104: MPPUNE/0099 | Z104: 45892 | AA104: 27/MPIB/26IN0045 | AB104: Yash Enterprises | AC104: MS Scrap | AD104: MS Scrap | AE104: 2890 | AF104: 28 | AG104: =AE104*AF104 -> 80920 | AH104: 0 | AI104: =AG104+AH104 -> 80920 | AJ104: 0 | AK104: =AE104-AJ104 -> 2890 | AL104: =AE104*S104 -> 98838 | AM104: =(AG104+AH104)-AL104 -> -17918 | AN104: =IFERROR(AM104/(AG104+AH104),0) -> -0.22142857 | AO104: =AE104*S104 -> 98838 | AP104: =(Z104-K104) -> 79 | AQ104: =T104*9.35%*AP104/365 -> 6353.5233 | AR104: =AM104-AQ104 -> -24271.523 | AS104: =IFERROR(AR104/(AG104+AH104),0) -> -0.29994468
B105: =B104+1 -> 101 | C105: FY 2025-26 | D105: =TEXT(F105,"mmm-yy") -> Jun-25 | E105: Regular | F105: 45813 | G105: MHPV052 | H105: AUTOCOMP CORPORATION PANSE PVT LTD | I105: 27AAFCA6224N1ZG | J105: 6122503640 | K105: 45813 | L105: 25-26/PUR/002654 | M105: 45814 | N105: MH | O105: MH04BU8943 | P105: CRC | Q105: MS scrap (CRC) | R105: 6930 | S105: 34.2 | T105: =R105*S105 -> 237006 | U105: Regular | V105: Fy 2025-26 | W105: =TEXT(Z105,"mmm-yy") -> Aug-25 | X105: Ultra & A60K | Y105: MPPUNE/0100 | Z105: 45895 | AA105: 27/MPIB/26IN0046 | AB105: SAARLOHA ADVANCED MATERIALS PRIVATE LIMITED | AC105: MS Scrap | AD105: MS Scrap | AE105: 23490 | AF105: 33.75 | AG105: =AE105*AF105 -> 792787.5 | AH105: 0 | AI105: =AG105+AH105 -> 792787.5 | AJ105: 0 | AK105: =AE105-AJ105 -> 23490 | AL105: =AE105*S105 -> 803358 | AM105: =(AG105+AH105)-AL105 -> -10570.5 | AN105: =IFERROR(AM105/(AG105+AH105),0) -> -0.013333333 | AO105: =AE105*S105 -> 803358 | AP105: =(Z105-K105) -> 82 | AQ105: =T105*9.35%*AP105/365 -> 4978.4247 | AR105: =AM105-AQ105 -> -15548.925 | AS105: =IFERROR(AR105/(AG105+AH105),0) -> -0.019612979
B106: =B105+1 -> 102 | C106: FY 2025-26 | D106: =TEXT(F106,"mmm-yy") -> Jun-25 | E106: Regular | F106: 45814 | G106: MHPV053 | H106: AUTOCOMP CORPORATION PANSE PVT LTD | I106: 27AAFCA6224N1ZG | J106: 6122503688 | K106: 45814 | L106: 25-26/PUR/002772 | M106: 45815 | N106: MH | O106: MH12FZ7432 | P106: CRC | Q106: MS scrap (CRC) | R106: 7545 | S106: 34.2 | T106: =R106*S106 -> 258039 | U106: Regular | V106: Fy 2025-26 | W106: =TEXT(Z106,"mmm-yy") -> Aug-25 | X106: B47K | Y106: MPPUNE/0101 | Z106: 45895 | AA106: 27/MPIB/26IN0047 | AB106: Yash Enterprises | AC106: CRC | AD106: SCRAP GAS CUT ALUMINIUM | AE106: 2870 | AF106: 90 | AG106: =AE106*AF106 -> 258300 | AH106: 0 | AI106: =AG106+AH106 -> 258300 | AJ106: 0 | AK106: =AE106-AJ106 -> 2870 | AL106: =AE106*S106 -> 98154 | AM106: =(AG106+AH106)-AL106 -> 160146 | AN106: =IFERROR(AM106/(AG106+AH106),0) -> 0.62 | AO106: =AE106*S106 -> 98154 | AP106: =(Z106-K106) -> 81 | AQ106: =T106*9.35%*AP106/365 -> 5354.1325 | AR106: =AM106-AQ106 -> 154791.87 | AS106: =IFERROR(AR106/(AG106+AH106),0) -> 0.59927165
B107: =B106+1 -> 103 | C107: FY 2025-26 | D107: =TEXT(F107,"mmm-yy") -> Jun-25 | E107: Regular | F107: 45814 | G107: MHPV054 | H107: AUTOCOMP CORPORATION PANSE PVT LTD | I107: 27AAFCA6224N1ZG | J107: 6122503689 | K107: 45814 | L107: 25-26/PUR/002774 | M107: 45815 | N107: MH | O107: MH27BX0052 | P107: CRC | Q107: MS scrap (CRC) | R107: 7750 | S107: 34.2 | T107: =R107*S107 -> 265050 | U107: Regular | V107: Fy 2025-26 | W107: =TEXT(Z107,"mmm-yy") -> Aug-25 | X107: Ultra | Y107: MPPUNE/0102 | Z107: 45896 | AA107: 27/MPIB/26IN0048 | AB107: SAARLOHA ADVANCED MATERIALS PRIVATE LIMITED | AC107: MS Scrap | AD107: MS Scrap | AE107: 21510 | AF107: 33.75 | AG107: =AE107*AF107 -> 725962.5 | AH107: 0 | AI107: =AG107+AH107 -> 725962.5 | AJ107: 0 | AK107: =AE107-AJ107 -> 21510 | AL107: =AE107*S107 -> 735642 | AM107: =(AG107+AH107)-AL107 -> -9679.5 | AN107: =IFERROR(AM107/(AG107+AH107),0) -> -0.013333333 | AO107: =AE107*S107 -> 735642 | AP107: =(Z107-K107) -> 82 | AQ107: =T107*9.35%*AP107/365 -> 5567.5023 | AR107: =AM107-AQ107 -> -15247.002 | AS107: =IFERROR(AR107/(AG107+AH107),0) -> -0.021002465
B108: =B107+1 -> 104 | C108: FY 2025-26 | D108: =TEXT(F108,"mmm-yy") -> Jun-25 | E108: Regular | F108: 45815 | G108: MHPV056 | H108: AUTOCOMP CORPORATION PANSE PVT LTD | I108: 27AAFCA6224N1ZG | J108: 6122503738 | K108: 45815 | L108: 25-26/PUR/002797 | M108: 45816 | N108: MH | O108: MH12FZ7432 | P108: CRC | Q108: MS scrap (CRC) | R108: 6285 | S108: 34.2 | T108: =R108*S108 -> 214947 | U108: Regular | V108: Fy 2025-26 | W108: =TEXT(Z108,"mmm-yy") -> Sep-25 | X108: CRC | Y108: MPPUNE/0103 | Z108: 45906 | AA108: 27/MPIB/26IN0049 | AB108: Sound Castings Private Limited - U5 | AC108: CRC | AD108: MS Scrap (CRC) | AE108: 30730 | AF108: 35.9 | AG108: =AE108*AF108 -> 1103207 | AH108: -2458 | AI108: =AG108+AH108 -> 1100749 | AJ108: 0 | AK108: =AE108-AJ108 -> 30730 | AL108: =AE108*S108 -> 1050966 | AM108: =(AG108+AH108)-AL108 -> 49783 | AN108: =IFERROR(AM108/(AG108+AH108),0) -> 0.045226478 | AO108: =AE108*S108 -> 1050966 | AP108: =(Z108-K108) -> 91 | AQ108: =T108*9.35%*AP108/365 -> 5010.6207 | AR108: =AM108-AQ108 -> 44772.379 | AS108: =IFERROR(AR108/(AG108+AH108),0) -> 0.040674467
B109: =B108+1 -> 105 | C109: FY 2025-26 | D109: =TEXT(F109,"mmm-yy") -> Jun-25 | E109: Regular | F109: 45815 | G109: MHPV055 | H109: AUTOCOMP CORPORATION PANSE PVT LTD | I109: 27AAFCA6224N1ZG | J109: 6122503743 | K109: 45815 | L109: 25-26/PUR/002798 | M109: 45816 | N109: MH | O109: MH27BX0052 | P109: CRC | Q109: MS scrap (CRC) | R109: 9635 | S109: 34.2 | T109: =R109*S109 -> 329517 | U109: Regular | V109: Fy 2025-26 | W109: =TEXT(Z109,"mmm-yy") -> Sep-25 | X109: Ultra | Y109: MPPUNE/0105 | Z109: 45907 | AA109: 27/MPIB/26IN0051 | AB109: Sound Castings Private Limited - U2 | AC109: MS Scrap | AD109: MS Scrap | AE109: 30870 | AF109: 35.7 | AG109: =AE109*AF109 -> 1102059 | AH109: -3570 | AI109: =AG109+AH109 -> 1098489 | AJ109: 0 | AK109: =AE109-AJ109 -> 30870 | AL109: =AE109*S109 -> 1055754 | AM109: =(AG109+AH109)-AL109 -> 42735 | AN109: =IFERROR(AM109/(AG109+AH109),0) -> 0.038903439 | AO109: =AE109*S109 -> 1055754 | AP109: =(Z109-K109) -> 92 | AQ109: =T109*9.35%*AP109/365 -> 7765.7678 | AR109: =AM109-AQ109 -> 34969.232 | AS109: =IFERROR(AR109/(AG109+AH109),0) -> 0.031833939
B110: =B109+1 -> 106 | C110: FY 2025-26 | D110: =TEXT(F110,"mmm-yy") -> Jun-25 | E110: Regular | F110: 45817 | G110: MHPV124 | H110: AUTOCOMP CORPORATION PANSE PVT LTD | I110: 27AAFCA6224N1ZG | J110: 6122503823 | K110: 45817 | L110: 25-26/PUR/004265 | M110: 45840 | N110: MH | O110: MH14BJ3188 | P110: CRC | Q110: MS scrap (CRC) | R110: 6640 | S110: 34.2 | T110: =R110*S110 -> 227088 | U110: Regular | V110: Fy 2025-26 | W110: =TEXT(Z110,"mmm-yy") -> Sep-25 | X110: CRC | Y110: MPPUNE/0104 | Z110: 45907 | AA110: 27/MPIB/26IN0050 | AB110: Sound Castings Private Limited - U5 | AC110: CRC | AD110: MS Scrap (CRC) | AE110: 25060 | AF110: 35.9 | AG110: =AE110*AF110 -> 899654 | AH110: =-1753-359 -> -2112 | AI110: =AG110+AH110 -> 897542 | AJ110: 0 | AK110: =AE110-AJ110 -> 25060 | AL110: =AE110*S110 -> 857052 | AM110: =(AG110+AH110)-AL110 -> 40490 | AN110: =IFERROR(AM110/(AG110+AH110),0) -> 0.045112095 | AO110: =AE110*S110 -> 857052 | AP110: =(Z110-K110) -> 90 | AQ110: =T110*9.35%*AP110/365 -> 5235.4672 | AR110: =AM110-AQ110 -> 35254.533 | AS110: =IFERROR(AR110/(AG110+AH110),0) -> 0.039278978
B111: =B110+1 -> 107 | C111: FY 2025-26 | D111: =TEXT(F111,"mmm-yy") -> Jun-25 | E111: Regular | F111: 45818 | G111: MHPV057 | H111: AUTOCOMP CORPORATION PANSE PVT LTD | I111: 27AAFCA6224N1ZG | J111: 6122503882 | K111: 45818 | L111: 25-26/PUR/002903 | M111: 45818 | N111: MH | O111: MH04BU8943 | P111: CRC | Q111: MS scrap (CRC) | R111: 6115 | S111: 34.2 | T111: =R111*S111 -> 209133 | U111: Regular | V111: Fy 2025-26 | W111: =TEXT(Z111,"mmm-yy") -> Sep-25 | X111: CRC | Y111: MPPUNE/0114 | Z111: 45907 | AA111: 27/MPIB/26IN0060 | AB111: Sound Castings Private Limited - U5 | AC111: CRC | AD111: MS Scrap (CRC) | AE111: 25415 | AF111: 35.9 | AG111: =AE111*AF111 -> 912398.5 | AH111: -2692.5 | AI111: =AG111+AH111 -> 909706 | AJ111: 0 | AK111: =AE111-AJ111 -> 25415 | AL111: =AE111*S111 -> 869193 | AM111: =(AG111+AH111)-AL111 -> 40513 | AN111: =IFERROR(AM111/(AG111+AH111),0) -> 0.044534168 | AO111: =AE111*S111 -> 869193 | AP111: =(Z111-K111) -> 89 | AQ111: =T111*9.35%*AP111/365 -> 4767.9459 | AR111: =AM111-AQ111 -> 35745.054 | AS111: =IFERROR(AR111/(AG111+AH111),0) -> 0.039292974
B112: =B111+1 -> 108 | C112: FY 2025-26 | D112: =TEXT(F112,"mmm-yy") -> Jun-25 | E112: Regular | F112: 45819 | G112: MHPV058 | H112: Tata Motors Ltd | I112: 27AAACT2727Q1ZW | J112: MH0100229812 | K112: 45819 | L112: 25-26/PUR/002959 | M112: 45819 | N112: MH | O112: MH04BU8943 | P112: CRC | Q112: Scrap Sheet Metal Components of M V Parts | R112: 3140 | S112: 30.151 | T112: =R112*S112 -> 94674.14 | U112: Regular | V112: Fy 2025-26 | W112: =TEXT(Z112,"mmm-yy") -> Sep-25 | X112: Ultra | Y112: MPPUNE/0106 | Z112: 45909 | AA112: 27/MPIB/26IN0052 | AB112: Sound Castings Private Limited - U2 | AC112: MS Scrap | AD112: MS Scrap | AE112: 30260 | AF112: 35.5 | AG112: =AE112*AF112 -> 1074230 | AH112: 0 | AI112: =AG112+AH112 -> 1074230 | AJ112: 0 | AK112: =AE112-AJ112 -> 30260 | AL112: =AE112*S112 -> 912369.26 | AM112: =(AG112+AH112)-AL112 -> 161860.74 | AN112: =IFERROR(AM112/(AG112+AH112),0) -> 0.15067606 | AO112: =AE112*S112 -> 912369.26 | AP112: =(Z112-K112) -> 90 | AQ112: =T112*9.35%*AP112/365 -> 2182.6928 | AR112: =AM112-AQ112 -> 159678.05 | AS112: =IFERROR(AR112/(AG112+AH112),0) -> 0.14864419
B113: =B112+1 -> 109 | C113: FY 2025-26 | D113: =TEXT(F113,"mmm-yy") -> Jun-25 | E113: Regular | F113: 45819 | G113: MHPV059 | H113: AUTOCOMP CORPORATION PANSE PVT LTD | I113: 27AAFCA6224N1ZG | J113: 6122503943 | K113: 45819 | L113: 25-26/PUR/002962 | M113: 45819 | N113: MH | O113: MH12KP9590 | P113: CRC | Q113: MS scrap (CRC) | R113: 11350 | S113: 34.2 | T113: =R113*S113 -> 388170 | U113: Regular | V113: Fy 2025-26 | W113: =TEXT(Z113,"mmm-yy") -> Sep-25 | X113: Ultra | Y113: MPPUNE/0113 | Z113: 45909 | AA113: 27/MPIB/26IN0059 | AB113: Sound Castings Private Limited - U2 | AC113: MS Scrap | AD113: MS Scrap | AE113: 23885 | AF113: 35.5 | AG113: =AE113*AF113 -> 847917.5 | AH113: -3727.5 | AI113: =AG113+AH113 -> 844190 | AJ113: 0 | AK113: =AE113-AJ113 -> 23885 | AL113: =AE113*S113 -> 816867 | AM113: =(AG113+AH113)-AL113 -> 27323 | AN113: =IFERROR(AM113/(AG113+AH113),0) -> 0.032365937 | AO113: =AE113*S113 -> 816867 | AP113: =(Z113-K113) -> 90 | AQ113: =T113*9.35%*AP113/365 -> 8949.1796 | AR113: =AM113-AQ113 -> 18373.82 | AS113: =IFERROR(AR113/(AG113+AH113),0) -> 0.02176503
B114: =B113+1 -> 110 | C114: FY 2025-26 | D114: =TEXT(F114,"mmm-yy") -> Jun-25 | E114: Regular | F114: 45819 | G114: MHPV060 | H114: AUTOCOMP CORPORATION PANSE PVT LTD | I114: 27AAFCA6224N1ZG | J114: 6122503949 | K114: 45819 | L114: 25-26/PUR/002963 | M114: 45819 | N114: MH | O114: MH14BJ3188 | P114: CRC | Q114: MS scrap (CRC) | R114: 6615 | S114: 34.2 | T114: =R114*S114 -> 226233 | U114: Regular | V114: Fy 2025-26 | W114: =TEXT(Z114,"mmm-yy") -> Sep-25 | X114: M7483K | Y114: MPPUNE/0107 | Z114: 45910 | AA114: 27/MPIB/26IN0053 | AB114: Yash Enterprises | AC114: MS Scrap | AD114: MS Scrap | AE114: 31340 | AF114: 28 | AG114: =AE114*AF114 -> 877520 | AH114: 0 | AI114: =AG114+AH114 -> 877520 | AJ114: 0 | AK114: =AE114-AJ114 -> 31340 | AL114: =AE114*S114 -> 1071828 | AM114: =(AG114+AH114)-AL114 -> -194308 | AN114: =IFERROR(AM114/(AG114+AH114),0) -> -0.22142857 | AO114: =AE114*S114 -> 1071828 | AP114: =(Z114-K114) -> 91 | AQ114: =T114*9.35%*AP114/365 -> 5273.7082 | AR114: =AM114-AQ114 -> -199581.71 | AS114: =IFERROR(AR114/(AG114+AH114),0) -> -0.22743836
B115: =B114+1 -> 111 | C115: FY 2025-26 | D115: =TEXT(F115,"mmm-yy") -> Jun-25 | E115: Regular | F115: 45819 | G115: MHPV061 | H115: AUTOCOMP CORPORATION PANSE PVT LTD | I115: 27AAFCA6224N1ZG | J115: 6122503965 | K115: 45819 | L115: 25-26/PUR/002964 | M115: 45819 | N115: MH | O115: MH27BX0052 | P115: CRC | Q115: MS scrap (CRC) | R115: 9765 | S115: 34.2 | T115: =R115*S115 -> 333963 | U115: Regular | V115: Fy 2025-26 | W115: =TEXT(Z115,"mmm-yy") -> Sep-25 | X115: Ultra | Y115: MPPUNE/0109 | Z115: 45912 | AA115: 27/MPIB/26IN0054 | AB115: SAARLOHA ADVANCED MATERIALS PRIVATE LIMITED | AC115: MS Scrap | AD115: MS Scrap | AE115: 28075 | AF115: 35.45 | AG115: =AE115*AF115 -> 995258.75 | AH115: 0 | AI115: =AG115+AH115 -> 995258.75 | AJ115: 0 | AK115: =AE115-AJ115 -> 28075 | AL115: =AE115*S115 -> 960165 | AM115: =(AG115+AH115)-AL115 -> 35093.75 | AN115: =IFERROR(AM115/(AG115+AH115),0) -> 0.035260931 | AO115: =AE115*S115 -> 960165 | AP115: =(Z115-K115) -> 93 | AQ115: =T115*9.35%*AP115/365 -> 7956.0966 | AR115: =AM115-AQ115 -> 27137.653 | AS115: =IFERROR(AR115/(AG115+AH115),0) -> 0.027266933
B116: =B115+1 -> 112 | C116: FY 2025-26 | D116: =TEXT(F116,"mmm-yy") -> Jun-25 | E116: Regular | F116: 45820 | G116: MHPV069 | H116: Tata Motors Passenger Vehicle Ltd | I116: 27AAHCT8301P1ZT | J116: MH6100232271 | K116: 45820 | L116: 25-26/PUR/002993 | M116: 45820 | N116: MH | O116: MH43Y5101 | P116: CRC | Q116: Scrap Sheet Metal Components of M V Parts | R116: 2870 | S116: 31.121 | T116: =R116*S116 -> 89317.27 | U116: Regular | V116: Fy 2025-26 | W116: =TEXT(Z116,"mmm-yy") -> Sep-25 | X116: Ultra | Y116: MPPUNE/0108 | Z116: 45912 | AA116: 27/MPIB/26IN0055 | AB116: SAARLOHA ADVANCED MATERIALS PRIVATE LIMITED | AC116: MS Scrap | AD116: MS Scrap | AE116: 24670 | AF116: 35.45 | AG116: =AE116*AF116 -> 874551.5 | AH116: -2836 | AI116: =AG116+AH116 -> 871715.5 | AJ116: 0 | AK116: =AE116-AJ116 -> 24670 | AL116: =AE116*S116 -> 767755.07 | AM116: =(AG116+AH116)-AL116 -> 103960.43 | AN116: =IFERROR(AM116/(AG116+AH116),0) -> 0.11925959 | AO116: =AE116*S116 -> 767755.07 | AP116: =(Z116-K116) -> 92 | AQ116: =T116*9.35%*AP116/365 -> 2104.9511 | AR116: =AM116-AQ116 -> 101855.48 | AS116: =IFERROR(AR116/(AG116+AH116),0) -> 0.11684486
B117: =B116+1 -> 113 | C117: FY 2025-26 | D117: =TEXT(F117,"mmm-yy") -> Jun-25 | E117: Regular | F117: 45820 | G117: MHPV063 | H117: Yash Enterprises | I117: 27DIBPM1991J1ZX | J117: GST/25-26/020 | K117: 45785 | L117: 25-26/PUR/002973 | M117: 45820 | N117: MH | O117: MH14BJ2933 | P117: CRC | Q117: MS scrap (CRC) | R117: 4710 | S117: 36.5 | T117: =R117*S117 -> 171915 | U117: Regular | V117: Fy 2025-26 | W117: =TEXT(Z117,"mmm-yy") -> Sep-25 | X117: Ultra | Y117: MPPUNE/0110 | Z117: 45912 | AA117: 27/MPIB/26IN0056 | AB117: SAARLOHA ADVANCED MATERIALS PRIVATE LIMITED | AC117: MS Scrap | AD117: MS Scrap | AE117: 28125 | AF117: 35.45 | AG117: =AE117*AF117 -> 997031.25 | AH117: 0 | AI117: =AG117+AH117 -> 997031.25 | AJ117: 0 | AK117: =AE117-AJ117 -> 28125 | AL117: =AE117*S117 -> 1026562.5 | AM117: =(AG117+AH117)-AL117 -> -29531.25 | AN117: =IFERROR(AM117/(AG117+AH117),0) -> -0.029619182 | AO117: =AE117*S117 -> 1026562.5 | AP117: =(Z117-K117) -> 127 | AQ117: =T117*9.35%*AP117/365 -> 5592.8895 | AR117: =AM117-AQ117 -> -35124.139 | AS117: =AR117/(AG117+AH117) -> -0.035228725
B118: =B117+1 -> 114 | C118: FY 2025-26 | D118: =TEXT(F118,"mmm-yy") -> Jun-25 | E118: Regular | F118: 45820 | G118: MHPV064 | H118: Yash Enterprises | I118: 27DIBPM1991J1ZX | J118: GST/25-26/021 | K118: 45787 | L118: 25-26/PUR/002979 | M118: 45820 | N118: MH | O118: MH14BJ2933 | P118: CRC | Q118: MS scrap (CRC) | R118: 3960 | S118: 36.5 | T118: =R118*S118 -> 144540 | U118: Regular | V118: Fy 2025-26 | W118: =TEXT(Z118,"mmm-yy") -> Sep-25 | X118: Ultra | Y118: MPPUNE/0111 | Z118: 45912 | AA118: 27/MPIB/26IN0057 | AB118: Sound Castings Private Limited - U3 | AC118: MS Scrap | AD118: MS Scrap | AE118: 24460 | AF118: 35.5 | AG118: =AE118*AF118 -> 868330 | AH118: 0 | AI118: =AG118+AH118 -> 868330 | AJ118: 0 | AK118: =AE118-AJ118 -> 24460 | AL118: =AE118*S118 -> 892790 | AM118: =(AG118+AH118)-AL118 -> -24460 | AN118: =IFERROR(AM118/(AG118+AH118),0) -> -0.028169014 | AO118: =AE118*S118 -> 892790 | AP118: =(Z118-K118) -> 125 | AQ118: =T118*9.35%*AP118/365 -> 4628.25 | AR118: =AM118-AQ118 -> -29088.25 | AS118: =AR118/(AG118+AH118) -> -0.033499073
B119: =B118+1 -> 115 | C119: FY 2025-26 | D119: =TEXT(F119,"mmm-yy") -> Jun-25 | E119: Regular | F119: 45820 | G119: MHPV065 | H119: Yash Enterprises | I119: 27DIBPM1991J1ZX | J119: GST/25-26/022 | K119: 45787 | L119: 25-26/PUR/002980 | M119: 45820 | N119: MH | O119: MH04FJ8427 | P119: CRC | Q119: MS scrap (CRC) | R119: 3900 | S119: 36.5 | T119: =R119*S119 -> 142350 | U119: Regular | V119: Fy 2025-26 | W119: =TEXT(Z119,"mmm-yy") -> Sep-25 | X119: Ultra | Y119: MPPUNE/0116 | Z119: 45912 | AA119: 27/MPIB/26IN0062 | AB119: SAARLOHA ADVANCED MATERIALS PRIVATE LIMITED | AC119: MS Scrap | AD119: MS Scrap | AE119: 25485 | AF119: 35.45 | AG119: =AE119*AF119 -> 903443.25 | AH119: 0 | AI119: =AG119+AH119 -> 903443.25 | AJ119: 0 | AK119: =AE119-AJ119 -> 25485 | AL119: =AE119*S119 -> 930202.5 | AM119: =(AG119+AH119)-AL119 -> -26759.25 | AN119: =IFERROR(AM119/(AG119+AH119),0) -> -0.029619182 | AO119: =AE119*S119 -> 930202.5 | AP119: =(Z119-K119) -> 125 | AQ119: =T119*9.35%*AP119/365 -> 4558.125 | AR119: =AM119-AQ119 -> -31317.375 | AS119: =AR119/(AG119+AH119) -> -0.034664463
B120: =B119+1 -> 116 | C120: FY 2025-26 | D120: =TEXT(F120,"mmm-yy") -> Jun-25 | E120: Regular | F120: 45820 | G120: MHPV067 | H120: Yash Enterprises | I120: 27DIBPM1991J1ZX | J120: GST/25-26/025 | K120: 45789 | L120: 25-26/PUR/002983 | M120: 45820 | N120: MH | O120: MH14FT2009 | P120: CRC | Q120: MS scrap (CRC) | R120: 6360 | S120: 36.5 | T120: =R120*S120 -> 232140 | U120: Regular | V120: Fy 2025-26 | W120: =TEXT(Z120,"mmm-yy") -> Sep-25 | X120: Ultra | Y120: MPPUNE/0115 | Z120: 45912 | AA120: 27/MPIB/26IN0061 | AB120: SAARLOHA ADVANCED MATERIALS PRIVATE LIMITED | AC120: MS Scrap | AD120: MS Scrap | AE120: 24425 | AF120: 35.45 | AG120: =AE120*AF120 -> 865866.25 | AH120: -3367.75 | AI120: =AG120+AH120 -> 862498.5 | AJ120: 0 | AK120: =AE120-AJ120 -> 24425 | AL120: =AE120*S120 -> 891512.5 | AM120: =(AG120+AH120)-AL120 -> -29014 | AN120: =IFERROR(AM120/(AG120+AH120),0) -> -0.033639479 | AO120: =AE120*S120 -> 891512.5 | AP120: =(Z120-K120) -> 123 | AQ120: =T120*9.35%*AP120/365 -> 7314.318 | AR120: =AM120-AQ120 -> -36328.318 | AS120: =AR120/(AG120+AH120) -> -0.042119862
B121: =B120+1 -> 117 | C121: FY 2025-26 | D121: =TEXT(F121,"mmm-yy") -> Jun-25 | E121: Regular | F121: 45820 | G121: MHPV062 | H121: Yash Enterprises | I121: 27DIBPM1991J1ZX | J121: GST/25-26/024 | K121: 45789 | L121: 25-26/PUR/002972 | M121: 45820 | N121: MH | O121: MH14BJ2933 | P121: CRC | Q121: MS scrap (CRC) | R121: 3960 | S121: 36.5 | T121: =R121*S121 -> 144540 | U121: Regular | V121: Fy 2025-26 | W121: =TEXT(Z121,"mmm-yy") -> Sep-25 | X121: Ultra | Y121: MPPUNE/0112 | Z121: 45915 | AA121: 27/MPIB/26IN0058 | AB121: SAARLOHA ADVANCED MATERIALS PRIVATE LIMITED | AC121: MS Scrap | AD121: MS Scrap | AE121: 31510 | AF121: 35.45 | AG121: =AE121*AF121 -> 1117029.5 | AH121: -4254 | AI121: =AG121+AH121 -> 1112775.5 | AJ121: 0 | AK121: =AE121-AJ121 -> 31510 | AL121: =AE121*S121 -> 1150115 | AM121: =(AG121+AH121)-AL121 -> -37339.5 | AN121: =IFERROR(AM121/(AG121+AH121),0) -> -0.033555286 | AO121: =AE121*S121 -> 1150115 | AP121: =(Z121-K121) -> 126 | AQ121: =T121*9.35%*AP121/365 -> 4665.276 | AR121: =AM121-AQ121 -> -42004.776 | AS121: =AR121/(AG121+AH121) -> -0.037747754
B122: =B121+1 -> 118 | C122: FY 2025-26 | D122: =TEXT(F122,"mmm-yy") -> Jun-25 | E122: Regular | F122: 45820 | G122: MHPV068 | H122: Yash Enterprises | I122: 27DIBPM1991J1ZX | J122: GST/25-26/026 | K122: 45789 | L122: 25-26/PUR/002984 | M122: 45820 | N122: MH | O122: UP32UN8579 | P122: CRC | Q122: MS scrap (CRC) | R122: 8960 | S122: 36.5 | T122: =R122*S122 -> 327040 | U122: Regular | V122: Fy 2025-26 | W122: =TEXT(Z122,"mmm-yy") -> Sep-25 | X122: Ultra | Y122: MPPUNE/0117 | Z122: 45919 | AA122: 27/MPIB/26IN0063 | AB122: SAARLOHA ADVANCED MATERIALS PRIVATE LIMITED | AC122: MS Scrap | AD122: MS Scrap | AE122: 37280 | AF122: 33.6 | AG122: =AE122*AF122 -> 1252608 | AH122: 0 | AI122: =AG122+AH122 -> 1252608 | AJ122: 0 | AK122: =AE122-AJ122 -> 37280 | AL122: =AE122*S122 -> 1360720 | AM122: =(AG122+AH122)-AL122 -> -108112 | AN122: =IFERROR(AM122/(AG122+AH122),0) -> -0.086309524 | AO122: =AE122*S122 -> 1360720 | AP122: =(Z122-K122) -> 130 | AQ122: =T122*9.35%*AP122/365 -> 10890.88 | AR122: =AM122-AQ122 -> -119002.88 | AS122: =AR122/(AG122+AH122) -> -0.095004087
B123: =B122+1 -> 119 | C123: FY 2025-26 | D123: =TEXT(F123,"mmm-yy") -> Jun-25 | E123: Regular | F123: 45820 | G123: MHPV066 | H123: Yash Enterprises | I123: 27DIBPM1991J1ZX | J123: GST/25-26/023 | K123: 45789 | L123: 25-26/PUR/002981 | M123: 45820 | N123: MH | O123: MH14FT2009 | P123: CRC | Q123: MS scrap (CRC) | R123: 7590 | S123: 36.5 | T123: =R123*S123 -> 277035 | U123: Regular | V123: Fy 2025-26 | W123: =TEXT(Z123,"mmm-yy") -> Sep-25 | X123: Ultra | Y123: MPPUNE/0118 | Z123: 45919 | AA123: 27/MPIB/26IN0064 | AB123: Sound Castings Private Limited - U3 | AC123: MS Scrap | AD123: MS Scrap | AE123: 24815 | AF123: 35.5 | AG123: =AE123*AF123 -> 880932.5 | AH123: 0 | AI123: =AG123+AH123 -> 880932.5 | AJ123: 0 | AK123: =AE123-AJ123 -> 24815 | AL123: =AE123*S123 -> 905747.5 | AM123: =(AG123+AH123)-AL123 -> -24815 | AN123: =IFERROR(AM123/(AG123+AH123),0) -> -0.028169014 | AO123: =AE123*S123 -> 905747.5 | AP123: =(Z123-K123) -> 130 | AQ123: =T123*9.35%*AP123/365 -> 9225.645 | AR123: =AM123-AQ123 -> -34040.645 | AS123: =AR123/(AG123+AH123) -> -0.038641604
B124: =B123+1 -> 120 | C124: FY 2025-26 | D124: =TEXT(F124,"mmm-yy") -> Jun-25 | E124: Regular | F124: 45820 | G124: MHPV071 | H124: AUTOCOMP CORPORATION PANSE PVT LTD | I124: 27AAFCA6224N1ZG | J124: 6122504028 | K124: 45820 | L124: 25-26/PUR/002996 | M124: 45820 | N124: MH | O124: MH04BU8943 | P124: CRC | Q124: MS scrap (CRC) | R124: 6550 | S124: 34.2 | T124: =R124*S124 -> 224010 | U124: Regular | V124: Fy 2025-26 | W124: =TEXT(Z124,"mmm-yy") -> Sep-25 | X124: Ultra | Y124: MPPUNE/0119 | Z124: 45921 | AA124: 27/MPIB/26IN0065 | AB124: SAARLOHA ADVANCED MATERIALS PRIVATE LIMITED | AC124: MS Scrap | AD124: MS Scrap | AE124: 24000 | AF124: 35.45 | AG124: =AE124*AF124 -> 850800 | AH124: 0 | AI124: =AG124+AH124 -> 850800 | AJ124: 0 | AK124: =AE124-AJ124 -> 24000 | AL124: =AE124*S124 -> 820800 | AM124: =(AG124+AH124)-AL124 -> 30000 | AN124: =IFERROR(AM124/(AG124+AH124),0) -> 0.035260931 | AO124: =AE124*S124 -> 820800 | AP124: =(Z124-K124) -> 101 | AQ124: =T124*9.35%*AP124/365 -> 5795.7217 | AR124: =AM124-AQ124 -> 24204.278 | AS124: =IFERROR(AR124/(AG124+AH124),0) -> 0.028448846
B125: =B124+1 -> 121 | C125: FY 2025-26 | D125: =TEXT(F125,"mmm-yy") -> Jun-25 | E125: Regular | F125: 45820 | G125: MHPV070 | H125: AUTOCOMP CORPORATION PANSE PVT LTD | I125: 27AAFCA6224N1ZG | J125: 6122504025 | K125: 45820 | L125: 25-26/PUR/002995 | M125: 45820 | N125: MH | O125: MH12KP9590 | P125: CRC | Q125: MS scrap (CRC) | R125: 9310 | S125: 34.2 | T125: =R125*S125 -> 318402 | U125: Regular | V125: Fy 2025-26 | W125: =TEXT(Z125,"mmm-yy") -> Sep-25 | X125: Ultra | Y125: MPPUNE/0120 | Z125: 45922 | AA125: 27/MPIB/26IN0066 | AB125: SAARLOHA ADVANCED MATERIALS PRIVATE LIMITED | AC125: MS Scrap | AD125: MS Scrap | AE125: 22100 | AF125: 35.45 | AG125: =AE125*AF125 -> 783445 | AH125: 0 | AI125: =AG125+AH125 -> 783445 | AJ125: 0 | AK125: =AE125-AJ125 -> 22100 | AL125: =AE125*S125 -> 755820 | AM125: =(AG125+AH125)-AL125 -> 27625 | AN125: =IFERROR(AM125/(AG125+AH125),0) -> 0.035260931 | AO125: =AE125*S125 -> 755820 | AP125: =(Z125-K125) -> 102 | AQ125: =T125*9.35%*AP125/365 -> 8319.4517 | AR125: =AM125-AQ125 -> 19305.548 | AS125: =IFERROR(AR125/(AG125+AH125),0) -> 0.024641868
B126: =B125+1 -> 122 | C126: FY 2025-26 | D126: =TEXT(F126,"mmm-yy") -> Jun-25 | E126: Regular | F126: 45821 | G126: MHPV072 | H126: AUTOCOMP CORPORATION PANSE PVT LTD | I126: 27AAFCA6224N1ZG | J126: 6122504103 | K126: 45821 | L126: 25-26/PUR/003060 | M126: 45821 | N126: MH | O126: MH04BU8943 | P126: CRC | Q126: MS scrap (CRC) | R126: 6540 | S126: 34.2 | T126: =R126*S126 -> 223668 | U126: Regular | V126: Fy 2025-26 | W126: =TEXT(Z126,"mmm-yy") -> Sep-25 | X126: Ultra | Y126: MPPUNE/0121 | Z126: 45923 | AA126: 27/MPIB/26IN0067 | AB126: Sound Castings Private Limited - U2 | AC126: MS Scrap | AD126: MS Scrap | AE126: 28850 | AF126: 35.5 | AG126: =AE126*AF126 -> 1024175 | AH126: -1775 | AI126: =AG126+AH126 -> 1022400 | AJ126: 0 | AK126: =AE126-AJ126 -> 28850 | AL126: =AE126*S126 -> 986670 | AM126: =(AG126+AH126)-AL126 -> 35730 | AN126: =IFERROR(AM126/(AG126+AH126),0) -> 0.034947183 | AO126: =AE126*S126 -> 986670 | AP126: =(Z126-K126) -> 102 | AQ126: =T126*9.35%*AP126/365 -> 5844.1691 | AR126: =AM126-AQ126 -> 29885.831 | AS126: =IFERROR(AR126/(AG126+AH126),0) -> 0.029231055
B127: =B126+1 -> 123 | C127: FY 2025-26 | D127: =TEXT(F127,"mmm-yy") -> Jun-25 | E127: Regular | F127: 45821 | G127: MHPV073 | H127: AUTOCOMP CORPORATION PANSE PVT LTD | I127: 27AAFCA6224N1ZG | J127: 6122504099 | K127: 45821 | L127: 25-26/PUR/003073 | M127: 45821 | N127: MH | O127: MH27BX0052 | P127: CRC | Q127: MS scrap (CRC) | R127: 6285 | S127: 34.2 | T127: =R127*S127 -> 214947 | U127: Regular | V127: Fy 2025-26 | W127: =TEXT(Z127,"mmm-yy") -> Sep-25 | X127: Ultra | Y127: MPPUNE/0122 | Z127: 45925 | AA127: 27/MPIB/26IN0068 | AB127: SAARLOHA ADVANCED MATERIALS PRIVATE LIMITED | AC127: MS Scrap | AD127: MS Scrap | AE127: 17250 | AF127: 35.45 | AG127: =AE127*AF127 -> 611512.5 | AH127: 0 | AI127: =AG127+AH127 -> 611512.5 | AJ127: 0 | AK127: =AE127-AJ127 -> 17250 | AL127: =AE127*S127 -> 589950 | AM127: =(AG127+AH127)-AL127 -> 21562.5 | AN127: =IFERROR(AM127/(AG127+AH127),0) -> 0.035260931 | AO127: =AE127*S127 -> 589950 | AP127: =(Z127-K127) -> 104 | AQ127: =T127*9.35%*AP127/365 -> 5726.4236 | AR127: =AM127-AQ127 -> 15836.076 | AS127: =IFERROR(AR127/(AG127+AH127),0) -> 0.02589657
B128: =B127+1 -> 124 | C128: FY 2025-26 | D128: =TEXT(F128,"mmm-yy") -> Jun-25 | E128: Regular | F128: 45822 | G128: MHPV074 | H128: AUTOCOMP CORPORATION PANSE PVT LTD | I128: 27AAFCA6224N1ZG | J128: 6122504158 | K128: 45822 | L128: 25-26/PUR/003105 | M128: 45822 | N128: MH | O128: MH04BU8943 | P128: CRC | Q128: MS scrap (CRC) | R128: 7805 | S128: 34.2 | T128: =R128*S128 -> 266931 | U128: Regular | V128: Fy 2025-26 | W128: =TEXT(Z128,"mmm-yy") -> Sep-25 | X128: Ultra | Y128: MPPUNE/0123 | Z128: 45926 | AA128: 27/MPIB/26IN0069 | AB128: Sound Castings Private Limited - U2 | AC128: MS Scrap | AD128: MS Scrap | AE128: 25445 | AF128: 35.5 | AG128: =AE128*AF128 -> 903297.5 | AH128: 0 | AI128: =AG128+AH128 -> 903297.5 | AJ128: 0 | AK128: =AE128-AJ128 -> 25445 | AL128: =AE128*S128 -> 870219 | AM128: =(AG128+AH128)-AL128 -> 33078.5 | AN128: =IFERROR(AM128/(AG128+AH128),0) -> 0.036619718 | AO128: =AE128*S128 -> 870219 | AP128: =(Z128-K128) -> 104 | AQ128: =T128*9.35%*AP128/365 -> 7111.3344 | AR128: =AM128-AQ128 -> 25967.166 | AS128: =IFERROR(AR128/(AG128+AH128),0) -> 0.02874708
B129: =B128+1 -> 125 | C129: FY 2025-26 | D129: =TEXT(F129,"mmm-yy") -> Jun-25 | E129: Regular | F129: 45823 | G129: MHPV075 | H129: Ultra Corpotech Pvt Ltd | I129: 27AADCP6808R1ZP | J129: 8252000562 | K129: 45823 | L129: 25-26/PUR/003126 | M129: 45824 | N129: MH | O129: MH12MV7637 | P129: MS Scrap | Q129: MS Melting scrap | R129: 31700 | S129: 34.3 | T129: =R129*S129 -> 1087310 | U129: Regular | V129: Fy 2025-26 | W129: =TEXT(Z129,"mmm-yy") -> Sep-25 | X129: Ultra | Y129: MPPUNE/0124 | Z129: 45927 | AA129: 27/MPIB/26IN0070 | AB129: Sound Castings Private Limited - U5 | AC129: MS Scrap | AD129: MS Scrap | AE129: 23265 | AF129: 35.5 | AG129: =AE129*AF129 -> 825907.5 | AH129: -1861 | AI129: =AG129+AH129 -> 824046.5 | AJ129: 0 | AK129: =AE129-AJ129 -> 23265 | AL129: =AE129*S129 -> 797989.5 | AM129: =(AG129+AH129)-AL129 -> 26057 | AN129: =IFERROR(AM129/(AG129+AH129),0) -> 0.031620788 | AO129: =AE129*S129 -> 797989.5 | AP129: =(Z129-K129) -> 104 | AQ129: =T129*9.35%*AP129/365 -> 28967.13 | AR129: =AM129-AQ129 -> -2910.13 | AS129: =IFERROR(AR129/(AG129+AH129),0) -> -0.0035315118
B130: =B129+1 -> 126 | C130: FY 2025-26 | D130: =TEXT(F130,"mmm-yy") -> Jun-25 | E130: Regular | F130: 45823 | G130: MHPV076 | H130: Ultra Corpotech Pvt Ltd | I130: 27AADCP6808R1ZP | J130: 5252000373 | K130: 45823 | L130: 25-26/PUR/003125 | M130: 45824 | N130: MH | O130: MH27BX0052 | P130: MS Scrap | Q130: MS Melting scrap | R130: 11820 | S130: 34.3 | T130: =R130*S130 -> 405426 | U130: Regular | V130: Fy 2025-26 | W130: =TEXT(Z130,"mmm-yy") -> Sep-25 | X130: Ultra | Y130: MPPUNE/0125 | Z130: 45927 | AA130: 27/MPIB/26IN0074 | AB130: SAARLOHA ADVANCED MATERIALS PRIVATE LIMITED | AC130: MS Scrap | AD130: MS Scrap | AE130: 25490 | AF130: 33.5 | AG130: =AE130*AF130 -> 853915 | AH130: -3015 | AI130: =AG130+AH130 -> 850900 | AJ130: 0 | AK130: =AE130-AJ130 -> 25490 | AL130: =AE130*S130 -> 874307 | AM130: =(AG130+AH130)-AL130 -> -23407 | AN130: =IFERROR(AM130/(AG130+AH130),0) -> -0.02750852 | AO130: =AE130*S130 -> 874307 | AP130: =(Z130-K130) -> 104 | AQ130: =T130*9.35%*AP130/365 -> 10800.993 | AR130: =AM130-AQ130 -> -34207.993 | AS130: =IFERROR(AR130/(AG130+AH130),0) -> -0.040202131
B131: =B130+1 -> 127 | C131: FY 2025-26 | D131: =TEXT(F131,"mmm-yy") -> Jun-25 | E131: Regular | F131: 45824 | G131: MHPV077 | H131: Tata Motors Passenger Vehicle Ltd | I131: 27AAHCT8301P1ZT | J131: MH6100244471 | K131: 45824 | L131: 25-26/PUR/003143 | M131: 45824 | N131: MH | O131: MH04BU8943 | P131: CRC | Q131: Scrap Sheet Metal Components of M V Parts | R131: 2980 | S131: 31.121 | T131: =R131*S131 -> 92740.58 | U131: Regular | V131: Fy 2025-26 | W131: =TEXT(Z131,"mmm-yy") -> Sep-25 | X131: Ultra | Y131: MPPUNE/0126 | Z131: 45927 | AA131: 27/MPIB/26IN0075 | AB131: SAARLOHA ADVANCED MATERIALS PRIVATE LIMITED | AC131: MS Scrap | AD131: MS Scrap | AE131: 28750 | AF131: 33.5 | AG131: =AE131*AF131 -> 963125 | AH131: 0 | AI131: =AG131+AH131 -> 963125 | AJ131: 0 | AK131: =AE131-AJ131 -> 28750 | AL131: =AE131*S131 -> 894728.75 | AM131: =(AG131+AH131)-AL131 -> 68396.25 | AN131: =IFERROR(AM131/(AG131+AH131),0) -> 0.071014925 | AO131: =AE131*S131 -> 894728.75 | AP131: =(Z131-K131) -> 103 | AQ131: =T131*9.35%*AP131/365 -> 2446.9539 | AR131: =AM131-AQ131 -> 65949.296 | AS131: =IFERROR(AR131/(AG131+AH131),0) -> 0.068474285
B132: =B131+1 -> 128 | C132: FY 2025-26 | D132: =TEXT(F132,"mmm-yy") -> Jun-25 | E132: Regular | F132: 45824 | G132: MHPV078 | H132: AUTOCOMP CORPORATION PANSE PVT LTD | I132: 27AAFCA6224N1ZG | J132: 6122504218 | K132: 45824 | L132: 25-26/PUR/003144 | M132: 45824 | N132: MH | O132: MH14BJ3188 | P132: CRC | Q132: MS scrap (CRC) | R132: 8940 | S132: 34.2 | T132: =R132*S132 -> 305748 | U132: Regular | V132: Fy 2025-26 | W132: =TEXT(Z132,"mmm-yy") -> Sep-25 | X132: Ultra | Y132: MPPUNE/0127 | Z132: 45928 | AA132: 27/MPIB/26IN0078 | AB132: SAARLOHA ADVANCED MATERIALS PRIVATE LIMITED | AC132: MS Scrap | AD132: MS Scrap | AE132: 34235 | AF132: 35.45 | AG132: =AE132*AF132 -> 1213630.8 | AH132: 0 | AI132: =AG132+AH132 -> 1213630.8 | AJ132: 0 | AK132: =AE132-AJ132 -> 34235 | AL132: =AE132*S132 -> 1170837 | AM132: =(AG132+AH132)-AL132 -> 42793.75 | AN132: =IFERROR(AM132/(AG132+AH132),0) -> 0.035260931 | AO132: =AE132*S132 -> 1170837 | AP132: =(Z132-K132) -> 104 | AQ132: =T132*9.35%*AP132/365 -> 8145.4618 | AR132: =AM132-AQ132 -> 34648.288 | AS132: =IFERROR(AR132/(AG132+AH132),0) -> 0.028549283
B133: =B132+1 -> 129 | C133: FY 2025-26 | D133: =TEXT(F133,"mmm-yy") -> Jun-25 | E133: Regular | F133: 45824 | G133: MHPV081 | H133: Ultra Corpotech Pvt Ltd | I133: 27AADCP6808R1ZP | J133: 8252000579 | K133: 45824 | L133: 25-26/PUR/003244 | M133: 45825 | N133: MH | O133: MH12MV7637 | P133: MS Scrap | Q133: MS Melting scrap | R133: 30390 | S133: 34.3 | T133: =R133*S133 -> 1042377 | U133: Regular | V133: Fy 2025-26 | W133: =TEXT(Z133,"mmm-yy") -> Sep-25 | X133: Ultra | Y133: MPPUNE/0128 | Z133: 45928 | AA133: 27/MPIB/26IN0079 | AB133: SAARLOHA ADVANCED MATERIALS PRIVATE LIMITED | AC133: MS Scrap | AD133: MS Scrap | AE133: 19370 | AF133: 33.5 | AG133: =AE133*AF133 -> 648895 | AH133: 0 | AI133: =AG133+AH133 -> 648895 | AJ133: 0 | AK133: =AE133-AJ133 -> 19370 | AL133: =AE133*S133 -> 664391 | AM133: =(AG133+AH133)-AL133 -> -15496 | AN133: =IFERROR(AM133/(AG133+AH133),0) -> -0.023880597 | AO133: =AE133*S133 -> 664391 | AP133: =(Z133-K133) -> 104 | AQ133: =T133*9.35%*AP133/365 -> 27770.066 | AR133: =AM133-AQ133 -> -43266.066 | AS133: =IFERROR(AR133/(AG133+AH133),0) -> -0.066676528
B134: =B133+1 -> 130 | C134: FY 2025-26 | D134: =TEXT(F134,"mmm-yy") -> Jun-25 | E134: Regular | F134: 45824 | G134: MHPV082 | H134: Ultra Corpotech Pvt Ltd | I134: 27AADCP6808R1ZP | J134: 8252000577 | K134: 45824 | L134: 25-26/PUR/003237 | M134: 45825 | N134: MH | O134: MH12FZ7432 | P134: MS Scrap | Q134: MS Melting scrap | R134: 21080 | S134: 34.3 | T134: =R134*S134 -> 723044 | U134: Regular | V134: Fy 2025-26 | W134: =TEXT(Z134,"mmm-yy") -> Sep-25 | X134: Ultra | Y134: MPPUNE/0129 | Z134: 45930 | AA134: 27/MPIB/26IN0082 | AB134: SAARLOHA ADVANCED MATERIALS PRIVATE LIMITED | AC134: MS Scrap | AD134: MS Scrap | AE134: 29195 | AF134: 35.45 | AG134: =AE134*AF134 -> 1034962.8 | AH134: -3013.25 | AI134: =AG134+AH134 -> 1031949.5 | AJ134: 0 | AK134: =AE134-AJ134 -> 29195 | AL134: =AE134*S134 -> 1001388.5 | AM134: =(AG134+AH134)-AL134 -> 30561 | AN134: =IFERROR(AM134/(AG134+AH134),0) -> 0.029614821 | AO134: =AE134*S134 -> 1001388.5 | AP134: =(Z134-K134) -> 106 | AQ134: =T134*9.35%*AP134/365 -> 19633.121 | AR134: =AM134-AQ134 -> 10927.879 | AS134: =IFERROR(AR134/(AG134+AH134),0) -> 0.010589548
B135: =B134+1 -> 131 | C135: FY 2025-26 | D135: =TEXT(F135,"mmm-yy") -> Jun-25 | E135: Regular | F135: 45825 | G135: MHPV079 | H135: AUTOCOMP CORPORATION PANSE PVT LTD | I135: 27AAFCA6224N1ZG | J135: 6122504268 | K135: 45825 | L135: 25-26/PUR/003243 | M135: 45825 | N135: MH | O135: MH27BX0052 | P135: CRC | Q135: MS scrap (CRC) | R135: 5360 | S135: 34.2 | T135: =R135*S135 -> 183312 | U135: Regular | V135: Fy 2025-26 | W135: =TEXT(Z135,"mmm-yy") -> Oct-25 | X135: Ultra | Y135: MPPUNE/0130 | Z135: 45931 | AA135: 27/MPIB/26IN0086 | AB135: SAARLOHA ADVANCED MATERIALS PRIVATE LIMITED | AC135: MS Scrap | AD135: MS Scrap | AE135: 16755 | AF135: 33.5 | AG135: =AE135*AF135 -> 561292.5 | AH135: 0 | AI135: =AG135+AH135 -> 561292.5 | AJ135: 0 | AK135: =AE135-AJ135 -> 16755 | AL135: =AE135*S135 -> 573021 | AM135: =(AG135+AH135)-AL135 -> -11728.5 | AN135: =IFERROR(AM135/(AG135+AH135),0) -> -0.020895522 | AO135: =AE135*S135 -> 573021 | AP135: =(Z135-K135) -> 106 | AQ135: =T135*9.35%*AP135/365 -> 4977.5486 | AR135: =AM135-AQ135 -> -16706.049 | AS135: =IFERROR(AR135/(AG135+AH135),0) -> -0.029763534
B136: =B135+1 -> 132 | C136: FY 2025-26 | D136: =TEXT(F136,"mmm-yy") -> Jun-25 | E136: Regular | F136: 45825 | G136: MHPV080 | H136: AUTOCOMP CORPORATION PANSE PVT LTD | I136: 27AAFCA6224N1ZG | J136: 6122504275 | K136: 45825 | L136: 25-26/PUR/003236 | M136: 45825 | N136: MH | O136: MH04BU8943 | P136: CRC | Q136: MS scrap (CRC) | R136: 4835 | S136: 34.2 | T136: =R136*S136 -> 165357 | U136: Regular | V136: Fy 2025-26 | W136: =TEXT(Z136,"mmm-yy") -> Oct-25 | X136: Ultra | Y136: MPPUNE/0131 | Z136: 45932 | AA136: 27/MPIB/26IN0087 | AB136: SAARLOHA ADVANCED MATERIALS PRIVATE LIMITED | AC136: MS Scrap | AD136: MS Scrap | AE136: 15460 | AF136: 33.5 | AG136: =AE136*AF136 -> 517910 | AH136: -5695 | AI136: =AG136+AH136 -> 512215 | AJ136: 0 | AK136: =AE136-AJ136 -> 15460 | AL136: =AE136*S136 -> 528732 | AM136: =(AG136+AH136)-AL136 -> -16517 | AN136: =IFERROR(AM136/(AG136+AH136),0) -> -0.032246225 | AO136: =AE136*S136 -> 528732 | AP136: =(Z136-K136) -> 107 | AQ136: =T136*9.35%*AP136/365 -> 4532.3674 | AR136: =AM136-AQ136 -> -21049.367 | AS136: =IFERROR(AR136/(AG136+AH136),0) -> -0.041094789
B137: =B136+1 -> 133 | C137: FY 2025-26 | D137: =TEXT(F137,"mmm-yy") -> Jun-25 | E137: Regular | F137: 45825 | G137: MHPV083 | H137: ULTRA CORPOTECH PRIVATE LIMITED | I137: 27AADCP6808R1ZP | J137: 5252000385 | K137: 45825 | L137: 25-26/PUR/003242 | M137: 45826 | N137: MH | O137: MH04EL5352 | P137: MS Scrap | Q137: M S Scrap | R137: 15990 | S137: 34.3 | T137: =R137*S137 -> 548457 | U137: Regular | V137: Fy 2025-26 | W137: =TEXT(Z137,"mmm-yy") -> Oct-25 | X137: Ultra | Y137: MPPUNE/0132 | Z137: 45933 | AA137: 27/MPIB/26IN0088 | AB137: Sound Castings Private Limited - U5 | AC137: MS Scrap | AD137: MS Scrap | AE137: 25990 | AF137: 35.5 | AG137: =AE137*AF137 -> 922645 | AH137: -710 | AI137: =AG137+AH137 -> 921935 | AJ137: 0 | AK137: =AE137-AJ137 -> 25990 | AL137: =AE137*S137 -> 891457 | AM137: =(AG137+AH137)-AL137 -> 30478 | AN137: =IFERROR(AM137/(AG137+AH137),0) -> 0.03305873 | AO137: =AE137*S137 -> 891457 | AP137: =(Z137-K137) -> 108 | AQ137: =T137*9.35%*AP137/365 -> 15173.476 | AR137: =AM137-AQ137 -> 15304.524 | AS137: =IFERROR(AR137/(AG137+AH137),0) -> 0.016600437
B138: =B137+1 -> 134 | C138: FY 2025-26 | D138: =TEXT(F138,"mmm-yy") -> Jun-25 | E138: Regular | F138: 45825 | G138: MHPV084 | H138: Ultra Corpotech Pvt Ltd | I138: 27AADCP6808R1ZP | J138: 8252000585 | K138: 45825 | L138: 25-26/PUR/003302 | M138: 45826 | N138: MH | O138: MH12NX4313 | P138: MS Scrap | Q138: MS Melting scrap | R138: 34510 | S138: 34.3 | T138: =R138*S138 -> 1183693 | U138: Regular | V138: Fy 2025-26 | W138: =TEXT(Z138,"mmm-yy") -> Oct-25 | X138: Ultra | Y138: MPPUNE/0133 | Z138: 45933 | AA138: 27/MPIB/26IN0089 | AB138: Sound Castings Private Limited - U3 | AC138: MS Scrap | AD138: MS Scrap | AE138: 30475 | AF138: 35.5 | AG138: =AE138*AF138 -> 1081862.5 | AH138: -3372 | AI138: =AG138+AH138 -> 1078490.5 | AJ138: 0 | AK138: =AE138-AJ138 -> 30475 | AL138: =AE138*S138 -> 1045292.5 | AM138: =(AG138+AH138)-AL138 -> 33198 | AN138: =IFERROR(AM138/(AG138+AH138),0) -> 0.030781912 | AO138: =AE138*S138 -> 1045292.5 | AP138: =(Z138-K138) -> 108 | AQ138: =T138*9.35%*AP138/365 -> 32747.759 | AR138: =AM138-AQ138 -> 450.24133 | AS138: =IFERROR(AR138/(AG138+AH138),0) -> 0.00041747362
B139: =B138+1 -> 135 | C139: FY 2025-26 | D139: =TEXT(F139,"mmm-yy") -> Jun-25 | E139: Regular | F139: 45826 | G139: MHPV085 | H139: Ultra Corpotech Pvt Ltd | I139: 27AADCP6808R1ZP | J139: 8252000595 | K139: 45826 | L139: 25-26/PUR/003339 | M139: 45827 | N139: MH | O139: MH12MV7637 | P139: MS Scrap | Q139: MS Melting scrap | R139: 29760 | S139: 34.3 | T139: =R139*S139 -> 1020768 | U139: Regular | V139: Fy 2025-26 | W139: =TEXT(Z139,"mmm-yy") -> Oct-25 | X139: Ultra | Y139: MPPUNE/0134 | Z139: 45934 | AA139: 27/MPIB/26IN0091 | AB139: SAARLOHA ADVANCED MATERIALS PRIVATE LIMITED | AC139: MS Scrap | AD139: MS Scrap | AE139: 14410 | AF139: 33.5 | AG139: =AE139*AF139 -> 482735 | AH139: -2680 | AI139: =AG139+AH139 -> 480055 | AJ139: 0 | AK139: =AE139-AJ139 -> 14410 | AL139: =AE139*S139 -> 494263 | AM139: =(AG139+AH139)-AL139 -> -14208 | AN139: =IFERROR(AM139/(AG139+AH139),0) -> -0.029596609 | AO139: =AE139*S139 -> 494263 | AP139: =(Z139-K139) -> 108 | AQ139: =T139*9.35%*AP139/365 -> 28240.316 | AR139: =AM139-AQ139 -> -42448.316 | AS139: =IFERROR(AR139/(AG139+AH139),0) -> -0.088423859
B140: =B139+1 -> 136 | C140: FY 2025-26 | D140: =TEXT(F140,"mmm-yy") -> Jun-25 | E140: Regular | F140: 45828 | G140: MHPV087 | H140: Tata Motors Passenger Vehicle Ltd | I140: 27AAHCT8301P1ZT | J140: MH6100261361 | K140: 45828 | L140: 25-26/PUR/003422 | M140: 45828 | N140: MH | O140: MH12EQ8475 | P140: CRC | Q140: Scrap Sheet Metal Components of M V Parts | R140: 5070 | S140: 31.121 | T140: =R140*S140 -> 157783.47 | U140: Regular | V140: Fy 2025-26 | W140: =TEXT(Z140,"mmm-yy") -> Oct-25 | X140: Ultra | Y140: MPPUNE/0135 | Z140: 45936 | AA140: 27/MPIB/26IN0092 | AB140: Sound Castings Private Limited - U5 | AC140: MS Scrap | AD140: MS Scrap | AE140: 25840 | AF140: 35.5 | AG140: =AE140*AF140 -> 917320 | AH140: -2485 | AI140: =AG140+AH140 -> 914835 | AJ140: 0 | AK140: =AE140-AJ140 -> 25840 | AL140: =AE140*S140 -> 804166.64 | AM140: =(AG140+AH140)-AL140 -> 110668.36 | AN140: =IFERROR(AM140/(AG140+AH140),0) -> 0.12097084 | AO140: =AE140*S140 -> 804166.64 | AP140: =(Z140-K140) -> 108 | AQ140: =T140*9.35%*AP140/365 -> 4365.1986 | AR140: =AM140-AQ140 -> 106303.16 | AS140: =IFERROR(AR140/(AG140+AH140),0) -> 0.11619927
B141: =B140+1 -> 137 | C141: FY 2025-26 | D141: =TEXT(F141,"mmm-yy") -> Jun-25 | E141: Regular | F141: 45828 | G141: MHPV088 | H141: Tata Motors Passenger Vehicle Ltd | I141: 27AAHCT8301P1ZT | J141: MH6100262168 | K141: 45828 | L141: 25-26/PUR/003424 | M141: 45828 | N141: MH | O141: MH12FZ7432 | P141: CRC | Q141: Scrap Sheet Metal Components of M V Parts | R141: 2740 | S141: 31.121 | T141: =R141*S141 -> 85271.54 | U141: Regular | V141: Fy 2025-26 | W141: =TEXT(Z141,"mmm-yy") -> Oct-25 | X141: Ultra | Y141: MPPUNE/0136 | Z141: 45936 | AA141: 27/MPIB/26IN0093 | AB141: SAARLOHA ADVANCED MATERIALS PRIVATE LIMITED | AC141: MS Scrap | AD141: MS Scrap | AE141: 20270 | AF141: 33.5 | AG141: =AE141*AF141 -> 679045 | AH141: 0 | AI141: =AG141+AH141 -> 679045 | AJ141: 0 | AK141: =AE141-AJ141 -> 20270 | AL141: =AE141*S141 -> 630822.67 | AM141: =(AG141+AH141)-AL141 -> 48222.33 | AN141: =IFERROR(AM141/(AG141+AH141),0) -> 0.071014925 | AO141: =AE141*S141 -> 630822.67 | AP141: =(Z141-K141) -> 108 | AQ141: =T141*9.35%*AP141/365 -> 2359.1014 | AR141: =AM141-AQ141 -> 45863.229 | AS141: =IFERROR(AR141/(AG141+AH141),0) -> 0.067540779
B142: =B141+1 -> 138 | C142: FY 2025-26 | D142: =TEXT(F142,"mmm-yy") -> Jun-25 | E142: Regular | F142: 45828 | G142: MHPV091 | H142: AUTOCOMP CORPORATION PANSE PVT LTD | I142: 27AAFCA6224N1ZG | J142: 6122504467 | K142: 45828 | L142: 25-26/PUR/003450 | M142: 45830 | N142: MH | O142: MH04BU8943 | P142: CRC | Q142: MS scrap (CRC) | R142: 9115 | S142: 34.2 | T142: =R142*S142 -> 311733 | U142: Regular | V142: Fy 2025-26 | W142: =TEXT(Z142,"mmm-yy") -> Oct-25 | X142: Ultra | Y142: MPPUNE/0137 | Z142: 45939 | AA142: 27/MPIB/26IN0098 | AB142: SAARLOHA ADVANCED MATERIALS PRIVATE LIMITED | AC142: MS Scrap | AD142: MS Scrap | AE142: 22900 | AF142: 33.5 | AG142: =AE142*AF142 -> 767150 | AH142: -2680 | AI142: =AG142+AH142 -> 764470 | AJ142: 0 | AK142: =AE142-AJ142 -> 22900 | AL142: =AE142*S142 -> 783180 | AM142: =(AG142+AH142)-AL142 -> -18710 | AN142: =IFERROR(AM142/(AG142+AH142),0) -> -0.024474473 | AO142: =AE142*S142 -> 783180 | AP142: =(Z142-K142) -> 111 | AQ142: =T142*9.35%*AP142/365 -> 8863.893 | AR142: =AM142-AQ142 -> -27573.893 | AS142: =IFERROR(AR142/(AG142+AH142),0) -> -0.036069294
B143: =B142+1 -> 139 | C143: FY 2025-26 | D143: =TEXT(F143,"mmm-yy") -> Jun-25 | E143: Regular | F143: 45828 | G143: MHPV089 | H143: AUTOCOMP CORPORATION PANSE PVT LTD | I143: 27AAFCA6224N1ZG | J143: 6122504485 | K143: 45828 | L143: 25-26/PUR/003447 | M143: 45829 | N143: MH | O143: MH12KP9590 | P143: CRC | Q143: MS scrap (CRC) | R143: 7995 | S143: 34.2 | T143: =R143*S143 -> 273429 | U143: Regular | V143: Fy 2025-26 | W143: =TEXT(Z143,"mmm-yy") -> Oct-25 | X143: Ultra | Y143: MPPUNE/0138 | Z143: 45939 | AA143: 27/MPIB/26IN0099 | AB143: Sound Castings Private Limited - U5 | AC143: MS Scrap | AD143: MS Scrap | AE143: 30725 | AF143: 35.5 | AG143: =AE143*AF143 -> 1090737.5 | AH143: -6232.5 | AI143: =AG143+AH143 -> 1084505 | AJ143: 0 | AK143: =AE143-AJ143 -> 30725 | AL143: =AE143*S143 -> 1050795 | AM143: =(AG143+AH143)-AL143 -> 33710 | AN143: =IFERROR(AM143/(AG143+AH143),0) -> 0.031083305 | AO143: =AE143*S143 -> 1050795 | AP143: =(Z143-K143) -> 111 | AQ143: =T143*9.35%*AP143/365 -> 7774.7476 | AR143: =AM143-AQ143 -> 25935.252 | AS143: =IFERROR(AR143/(AG143+AH143),0) -> 0.023914369
B144: =B143+1 -> 140 | C144: FY 2025-26 | D144: =TEXT(F144,"mmm-yy") -> Jun-25 | E144: Regular | F144: 45828 | G144: MHPV086 | H144: Ultra Corpotech Pvt Ltd | I144: 27AADCP6808R1ZP | J144: 8252000610 | K144: 45828 | L144: 25-26/PUR/003423 | M144: 45828 | N144: MH | O144: MH27BX0052 | P144: MS Scrap | Q144: MS Melting scrap | R144: 16250 | S144: 34.3 | T144: =R144*S144 -> 557375 | U144: Regular | V144: Fy 2025-26 | W144: =TEXT(Z144,"mmm-yy") -> Oct-25 | X144: DP | Y144: MPPUNE/0139 | Z144: 45942 | AA144: 27/MPIB/26IN0103 | AB144: Prajapati Casting Foundry Private Limited | AC144: CRC | AD144: MS Scrap (CRC) | AE144: 12190 | AF144: 41.5 | AG144: =AE144*AF144 -> 505885 | AH144: 0 | AI144: =AG144+AH144 -> 505885 | AJ144: 0 | AK144: =AE144-AJ144 -> 12190 | AL144: =AE144*S144 -> 418117 | AM144: =(AG144+AH144)-AL144 -> 87768 | AN144: =IFERROR(AM144/(AG144+AH144),0) -> 0.17349398 | AO144: =AE144*S144 -> 418117 | AP144: =(Z144-K144) -> 114 | AQ144: =T144*9.35%*AP144/365 -> 16276.877 | AR144: =AM144-AQ144 -> 71491.123 | AS144: =IFERROR(AR144/(AG144+AH144),0) -> 0.14131892
B145: =B144+1 -> 141 | C145: FY 2025-26 | D145: =TEXT(F145,"mmm-yy") -> Jun-25 | E145: Regular | F145: 45829 | G145: MHPV090 | H145: Tata Motors Ltd | I145: 27AAACT2727Q1ZW | J145: MH0100261957 | K145: 45829 | L145: 25-26/PUR/003448 | M145: 45829 | N145: MH | O145: MH27BX0052 | P145: CRC | Q145: Scrap Sheet Metal Components of M V Parts | R145: 3240 | S145: 30.151 | T145: =R145*S145 -> 97689.24 | U145: Regular | V145: Fy 2025-26 | W145: =TEXT(Z145,"mmm-yy") -> Oct-25 | X145: Ultra | Y145: MPPUNE/0140 | Z145: 45942 | AA145: 27/MPIB/26IN0104 | AB145: SAARLOHA ADVANCED MATERIALS PRIVATE LIMITED | AC145: MS Scrap | AD145: MS Scrap | AE145: 18380 | AF145: 33.5 | AG145: =AE145*AF145 -> 615730 | AH145: 0 | AI145: =AG145+AH145 -> 615730 | AJ145: 0 | AK145: =AE145-AJ145 -> 18380 | AL145: =AE145*S145 -> 554175.38 | AM145: =(AG145+AH145)-AL145 -> 61554.62 | AN145: =IFERROR(AM145/(AG145+AH145),0) -> 0.099970149 | AO145: =AE145*S145 -> 554175.38 | AP145: =(Z145-K145) -> 113 | AQ145: =T145*9.35%*AP145/365 -> 2827.7689 | AR145: =AM145-AQ145 -> 58726.851 | AS145: =IFERROR(AR145/(AG145+AH145),0) -> 0.095377602
B146: =B145+1 -> 142 | C146: FY 2025-26 | D146: =TEXT(F146,"mmm-yy") -> Jun-25 | E146: Regular | F146: 45830 | G146: MHPV092 | H146: Ultra Corpotech Pvt Ltd | I146: 27AADCP6808R1ZP | J146: 5252000413 | K146: 45830 | L146: 25-26/PUR/003467 | M146: 45830 | N146: MH | O146: MH12FZ7432 | P146: MS Scrap | Q146: MS Melting scrap | R146: 13150 | S146: 34.3 | T146: =R146*S146 -> 451045 | U146: Regular | V146: Fy 2025-26 | W146: =TEXT(Z146,"mmm-yy") -> Oct-25 | X146: Ultra | Y146: MPPUNE/0142 | Z146: 45945 | AA146: 27/MPIB/26IN0114 | AB146: SAARLOHA ADVANCED MATERIALS PRIVATE LIMITED | AC146: MS Scrap | AD146: MS Scrap | AE146: 16665 | AF146: 33.5 | AG146: =AE146*AF146 -> 558277.5 | AH146: 0 | AI146: =AG146+AH146 -> 558277.5 | AJ146: 0 | AK146: =AE146-AJ146 -> 16665 | AL146: =AE146*S146 -> 571609.5 | AM146: =(AG146+AH146)-AL146 -> -13332 | AN146: =IFERROR(AM146/(AG146+AH146),0) -> -0.023880597 | AO146: =AE146*S146 -> 571609.5 | AP146: =(Z146-K146) -> 115 | AQ146: =T146*9.35%*AP146/365 -> 13287.291 | AR146: =AM146-AQ146 -> -26619.291 | AS146: =IFERROR(AR146/(AG146+AH146),0) -> -0.047681111
...

Sheet Pune MIS
G1: =H2*I2 -> 0 | AT1: 4847684.7
H2: =SUBTOTAL(9,H4:H495) -> 4067983 | J2: =SUBTOTAL(9,J4:J495) -> 1.3501279e+08 | K2: =SUBTOTAL(9,K4:K495) -> -741438 | L2: =SUBTOTAL(9,L4:L495) -> 1.3427135e+08 | T2: =SUBTOTAL(9,T4:T493) -> 4493887.2 | V2: =SUBTOTAL(9,V4:V493) -> 1.606522e+08 | W2: =SUBTOTAL(9,W4:W493) -> -7777762.4 | X2: =SUBTOTAL(9,X4:X493) -> 1.5287444e+08 | AP2: =SUBTOTAL(9,AP4:AP496) -> 8935562.2 | AQ2: =SUBTOTAL(9,AQ4:AQ496) -> 63867.51 | AR2: =SUBTOTAL(9,AR4:AR496) -> 8871694.7 | AT2: Vendor | AU2: Type of Service
A3: Remarks | B3: Calssification | C3: Financial Year | D3: Month | E3: Bill Date | F3: CF.SO Number | G3: Vendor Name | H3: Quantity | I3: Rate | J3: Item Total | K3: DN to Vendor | L3: Net Cost | N3: CF.SO Number | O3: Sale Type | P3: Financial Year | Q3: Invoice Date | R3: Invoice Number | S3: Customer Name | T3: Quantity | U3: Item Price | V3: Total | W3: Crecit Note | X3: Net Sale | Y3: Check | AA3: Financial Year | AB3: Month | AC3: Bill Date | AD3: CF.SO Number | AE3: Vendor Name | AF3: GST Identification Number (GSTIN) | AG3: Bill Number | AH3: CF.Supplier Invoice Date | AI3: CF.Purchase | AJ3: CF.Voucher Date | AK3: Source of Supply | AL3: CF.Vehicle No | AM3: Item_Name | AN3: Purchase Qty | AO3: Rate | AP3: Cost | AQ3: DN | AR3: Net | AT3: MOHIT KANAUGIYA | AU3: Labour, Crane & Logistics
B4: Processing Cost | C4: FY 2025-26 | D4: =TEXT(E4,"mmm-yy") -> Apr-25 | E4: 45748 | G4: BHAIRAVNATH ENTERPRISES | H4: 1 | I4: 5700 | J4: =H4*I4 -> 5700 | K4: 0 | L4: =J4+K4 -> 5700 | N4: MPPUNE/0023 | O4: Warehouse | P4: FY 2025-26 | Q4: 45750 | R4: 26/MPPIB/INV0007 | S4: KALYANI FOUNDRY WORKS | T4: 22290 | U4: 42 | V4: =U4*T4 -> 936180 | W4: 0 | X4: =V4+W4 -> 936180 | Y4: =_xlfn.XLOOKUP(R4,'Details PC'!AA:AA,'Details PC'!AI:AI)-X4 -> 0 | AA4: FY 2025-26 | AB4: =TEXT(AC4,"mmm-yy") -> May-25 | AC4: 45782 | AE4: MOHIT KANAUGIYA | AG4: 10 | AI4: 25-26/PUR/001308 | AN4: 1 | AO4: 3000 | AP4: =AN4*AO4 -> 3000 | AQ4: 0 | AR4: =AP4-AQ4 -> 3000 | AT4: YASH ENTERPRISES | AU4: Labour, Seller, Buyer
B5: Material Cost | C5: FY 2025-26 | D5: =TEXT(E5,"mmm-yy") -> Apr-25 | E5: 45759 | F5: MHPV001 | G5: TATA MOTORS PASSENGER VEHICLES LIMITED | H5: 2900 | I5: 31.121 | J5: =H5*I5 -> 90250.9 | K5: 0 | L5: =J5+K5 -> 90250.9 | N5: MPPUNE/0024 | O5: Warehouse | P5: FY 2025-26 | Q5: 45751 | R5: 26/MPPIB/INV0011 | S5: SNEHA FOUNDRY WORKS | T5: 21360 | U5: 42 | V5: =U5*T5 -> 897120 | W5: 0 | X5: =V5+W5 -> 897120 | Y5: =_xlfn.XLOOKUP(R5,'Details PC'!AA:AA,'Details PC'!AI:AI)-X5 -> 0 | AA5: FY 2025-26 | AB5: =TEXT(AC5,"mmm-yy") -> May-25 | AC5: 45782 | AE5: MOHIT KANAUGIYA | AG5: 10 | AI5: 25-26/PUR/001308 | AN5: 1 | AO5: 3606 | AP5: =AN5*AO5 -> 3606 | AQ5: 0 | AR5: =AP5-AQ5 -> 3606 | AT5: Shivshambho Logistics | AU5: Logistics
B6: Material Cost | C6: FY 2025-26 | D6: =TEXT(E6,"mmm-yy") -> Apr-25 | E6: 45759 | F6: MHPV002 | G6: TATA MOTORS PASSENGER VEHICLES LIMITED | H6: 2490 | I6: 31.121 | J6: =H6*I6 -> 77491.29 | K6: 0 | L6: =J6+K6 -> 77491.29 | N6: MPPUNE/0025 | O6: Warehouse | P6: FY 2025-26 | Q6: 45751 | R6: 26/MPPIB/INV0012 | S6: SNEHA FOUNDRY WORKS | T6: 23850 | U6: 42 | V6: =U6*T6 -> 1001700 | W6: 0 | X6: =V6+W6 -> 1001700 | Y6: =_xlfn.XLOOKUP(R6,'Details PC'!AA:AA,'Details PC'!AI:AI)-X6 -> 0 | AA6: FY 2025-26 | AB6: =TEXT(AC6,"mmm-yy") -> May-25 | AC6: 45782 | AE6: MOHIT KANAUGIYA | AG6: 10 | AI6: 25-26/PUR/001308 | AN6: 1 | AO6: 3000 | AP6: =AN6*AO6 -> 3000 | AQ6: 0 | AR6: =AP6-AQ6 -> 3000 | AT6: VIKAS ENTERPRISES | AU6: Labour & Logistics
B7: Material Cost | C7: FY 2025-26 | D7: =TEXT(E7,"mmm-yy") -> Apr-25 | E7: 45759 | F7: MHPV003 | G7: TATA MOTORS PASSENGER VEHICLES LIMITED | H7: 2380 | I7: 31.121 | J7: =H7*I7 -> 74067.98 | K7: 0 | L7: =J7+K7 -> 74067.98 | N7: MPPUNE/0026 | O7: Warehouse | P7: FY 2025-26 | Q7: 45752 | R7: 26/MPPIB/INV0015 | S7: PRAJAPATI FOUNDRY PRIVATE LIMITED | T7: 24190 | U7: 37.5 | V7: =U7*T7 -> 907125 | W7: -3187.5 | X7: =V7+W7 -> 903937.5 | Y7: =_xlfn.XLOOKUP(R7,'Details PC'!AA:AA,'Details PC'!AI:AI)-X7 -> 0 | AA7: FY 2025-26 | AB7: =TEXT(AC7,"mmm-yy") -> May-25 | AC7: 45782 | AE7: MOHIT KANAUGIYA | AG7: 11 | AI7: 25-26/PUR/001309 | AN7: 1 | AO7: 3000 | AP7: =AN7*AO7 -> 3000 | AQ7: 0 | AR7: =AP7-AQ7 -> 3000 | AT7: BHAIRAVNATH ENTERPRISES | AU7: Crane
B8: Material Cost | C8: FY 2025-26 | D8: =TEXT(E8,"mmm-yy") -> Apr-25 | E8: 45761 | F8: MHPV004 | G8: TATA MOTORS PASSENGER VEHICLES LIMITED | H8: 18010 | I8: 32.221 | J8: =H8*I8 -> 580300.21 | K8: 0 | L8: =J8+K8 -> 580300.21 | N8: MPPUNE/0027 | O8: Warehouse | P8: FY 2025-26 | Q8: 45753 | R8: 26/MPPIB/INV0017 | S8: PRAJAPATI CASTING FOUNDRY PRIVATE LIMITED | T8: 23460 | U8: 39.5 | V8: =U8*T8 -> 926670 | W8: 0 | X8: =V8+W8 -> 926670 | Y8: =_xlfn.XLOOKUP(R8,'Details PC'!AA:AA,'Details PC'!AI:AI)-X8 -> 0 | AA8: FY 2025-26 | AB8: =TEXT(AC8,"mmm-yy") -> May-25 | AC8: 45782 | AE8: MOHIT KANAUGIYA | AG8: 11 | AI8: 25-26/PUR/001309 | AN8: 1 | AO8: 3000 | AP8: =AN8*AO8 -> 3000 | AQ8: 0 | AR8: =AP8-AQ8 -> 3000 | AT8: RAJENDRA SHYAMLAL | AU8: Labour
B9: Material Cost | C9: FY 2025-26 | D9: =TEXT(E9,"mmm-yy") -> Apr-25 | E9: 45761 | F9: MHPV005 | G9: TATA MOTORS PASSENGER VEHICLES LIMITED | H9: 20960 | I9: 32.221 | J9: =H9*I9 -> 675352.16 | K9: 0 | L9: =J9+K9 -> 675352.16 | N9: MPPUNE/0029 | O9: Warehouse | P9: FY 2025-26 | Q9: 45754 | R9: 26/MPPIB/INV0020 | S9: SONA FOUNDRY | T9: 22300 | U9: 37.5 | V9: =U9*T9 -> 836250 | W9: 0 | X9: =V9+W9 -> 836250 | Y9: =_xlfn.XLOOKUP(R9,'Details PC'!AA:AA,'Details PC'!AI:AI)-X9 -> 0 | AA9: FY 2025-26 | AB9: =TEXT(AC9,"mmm-yy") -> May-25 | AC9: 45782 | AE9: MOHIT KANAUGIYA | AG9: 11 | AI9: 25-26/PUR/001309 | AN9: 1 | AO9: 3000 | AP9: =AN9*AO9 -> 3000 | AQ9: 0 | AR9: =AP9-AQ9 -> 3000 | AT9: YASH GASES | AU9: Consumables
B10: Material Cost | C10: FY 2025-26 | D10: =TEXT(E10,"mmm-yy") -> Apr-25 | E10: 45761 | F10: MHPV006 | G10: TATA MOTORS PASSENGER VEHICLES LIMITED | H10: 22880 | I10: 32.221 | J10: =H10*I10 -> 737216.48 | K10: 0 | L10: =J10+K10 -> 737216.48 | N10: MPPUNE/0028 | O10: Warehouse | P10: FY 2025-26 | Q10: 45754 | R10: 26/MPPIB/INV0021 | S10: SONA FOUNDRY | T10: 22270 | U10: 37.5 | V10: =U10*T10 -> 835125 | W10: 0 | X10: =V10+W10 -> 835125 | Y10: =_xlfn.XLOOKUP(R10,'Details PC'!AA:AA,'Details PC'!AI:AI)-X10 -> 0 | AA10: FY 2025-26 | AB10: =TEXT(AC10,"mmm-yy") -> May-25 | AC10: 45782 | AE10: MOHIT KANAUGIYA | AG10: 11 | AI10: 25-26/PUR/001309 | AN10: 1 | AO10: 3000 | AP10: =AN10*AO10 -> 3000 | AQ10: 0 | AR10: =AP10-AQ10 -> 3000 | AT10: Shubhangi Enterprises | AU10: Logistics
B11: Material Cost | C11: FY 2025-26 | D11: =TEXT(E11,"mmm-yy") -> Apr-25 | E11: 45761 | F11: MHPV007 | G11: TATA MOTORS PASSENGER VEHICLES LIMITED | H11: 14110 | I11: 32.221 | J11: =H11*I11 -> 454638.31 | K11: 0 | L11: =J11+K11 -> 454638.31 | N11: MPPUNE/0030 | O11: Warehouse | P11: FY 2025-26 | Q11: 45761 | R11: 26/MPPIB/INV0033 | S11: SNEHA FOUNDRY WORKS | T11: 21590 | U11: 42 | V11: =U11*T11 -> 906780 | W11: 0 | X11: =V11+W11 -> 906780 | Y11: =_xlfn.XLOOKUP(R11,'Details PC'!AA:AA,'Details PC'!AI:AI)-X11 -> 0 | AA11: FY 2025-26 | AB11: =TEXT(AC11,"mmm-yy") -> May-25 | AC11: 45782 | AE11: MOHIT KANAUGIYA | AG11: 14 | AI11: 25-26/PUR/001316 | AN11: 1 | AO11: 3500 | AP11: =AN11*AO11 -> 3500 | AQ11: 0 | AR11: =AP11-AQ11 -> 3500 | AT11: GURUDATTA CRANE SERVICE | AU11: Crane
B12: Material Cost | C12: FY 2025-26 | D12: =TEXT(E12,"mmm-yy") -> Apr-25 | E12: 45763 | F12: MHPV008 | G12: TATA MOTORS LIMITED | H12: 5020 | I12: 30.151 | J12: =H12*I12 -> 151358.02 | K12: 0 | L12: =J12+K12 -> 151358.02 | N12: MPPUNE/0032 | O12: Warehouse | P12: FY 2025-26 | Q12: 45763 | R12: 26/MPPIB/INV0041 | S12: KALYANI FOUNDRY WORKS | T12: 15830 | U12: 42 | V12: =U12*T12 -> 664860 | W12: 0 | X12: =V12+W12 -> 664860 | Y12: =_xlfn.XLOOKUP(R12,'Details PC'!AA:AA,'Details PC'!AI:AI)-X12 -> 0 | AA12: FY 2025-26 | AB12: =TEXT(AC12,"mmm-yy") -> May-25 | AC12: 45782 | AE12: MOHIT KANAUGIYA | AG12: 16 | AI12: 25-26/PUR/001317 | AN12: 1 | AO12: 6270 | AP12: =AN12*AO12 -> 6270 | AQ12: 0 | AR12: =AP12-AQ12 -> 6270 | AT12: SHARIFUNANISA ABDUL GAFFAR SHAH | AU12: Labour
B13: Material Cost | C13: FY 2025-26 | D13: =TEXT(E13,"mmm-yy") -> Apr-25 | E13: 45763 | F13: MHPV009 | G13: TATA MOTORS LIMITED | H13: 5200 | I13: 30.151 | J13: =H13*I13 -> 156785.2 | K13: 0 | L13: =J13+K13 -> 156785.2 | N13: MPPUNE/0031 | O13: Warehouse | P13: FY 2025-26 | Q13: 45763 | R13: 26/MPPIB/INV0040 | S13: PRAJAPATI FOUNDRY PRIVATE LIMITED | T13: 2660 | U13: 39 | V13: =U13*T13 -> 103740 | W13: 0 | X13: =V13+W13 -> 103740 | Y13: =_xlfn.XLOOKUP(R13,'Details PC'!AA:AA,'Details PC'!AI:AI)-X13 -> 0 | AA13: FY 2025-26 | AB13: =TEXT(AC13,"mmm-yy") -> May-25 | AC13: 45782 | AE13: MOHIT KANAUGIYA | AG13: 16 | AI13: 25-26/PUR/001317 | AN13: 1 | AO13: 4896 | AP13: =AN13*AO13 -> 4896 | AQ13: 0 | AR13: =AP13-AQ13 -> 4896
B14: Material Cost | C14: FY 2025-26 | D14: =TEXT(E14,"mmm-yy") -> Apr-25 | E14: 45765 | F14: MHPV010 | G14: TATA MOTORS PASSENGER VEHICLES LIMITED | H14: 24180 | I14: 32.221 | J14: =H14*I14 -> 779103.78 | K14: 0 | L14: =J14+K14 -> 779103.78 | N14: MPPUNE/0033 | O14: Warehouse | P14: FY 2025-26 | Q14: 45764 | R14: 26/MPPIB/INV0042 | S14: AFFAN TOOLS | T14: 3820 | U14: 38 | V14: =U14*T14 -> 145160 | W14: 0 | X14: =V14+W14 -> 145160 | Y14: =_xlfn.XLOOKUP(R14,'Details PC'!AA:AA,'Details PC'!AI:AI)-X14 -> 0 | AA14: FY 2025-26 | AB14: =TEXT(AC14,"mmm-yy") -> May-25 | AC14: 45782 | AE14: MOHIT KANAUGIYA | AG14: 16 | AI14: 25-26/PUR/001317 | AN14: 1 | AO14: 5412 | AP14: =AN14*AO14 -> 5412 | AQ14: 0 | AR14: =AP14-AQ14 -> 5412
B15: Material Cost | C15: FY 2025-26 | D15: =TEXT(E15,"mmm-yy") -> Apr-25 | E15: 45765 | F15: MHPV011 | G15: TATA MOTORS PASSENGER VEHICLES LIMITED | H15: 25150 | I15: 32.221 | J15: =H15*I15 -> 810358.15 | K15: 0 | L15: =J15+K15 -> 810358.15 | N15: MPPUNE/0035 | O15: Warehouse | P15: FY 2025-26 | Q15: 45772 | R15: 26/MPPIB/INV0066 | S15: YASH ENTERPRISES | T15: 7600 | U15: 37 | V15: =U15*T15 -> 281200 | W15: 0 | X15: =V15+W15 -> 281200 | Y15: =_xlfn.XLOOKUP(R15,'Details PC'!AA:AA,'Details PC'!AI:AI)-X15 -> 0 | AA15: FY 2025-26 | AB15: =TEXT(AC15,"mmm-yy") -> May-25 | AC15: 45782 | AE15: MOHIT KANAUGIYA | AG15: 12 | AI15: 25-26/PUR/001319 | AN15: 1 | AO15: 5628 | AP15: =AN15*AO15 -> 5628 | AQ15: 0 | AR15: =AP15-AQ15 -> 5628
B16: Material Cost | C16: FY 2025-26 | D16: =TEXT(E16,"mmm-yy") -> Apr-25 | E16: 45765 | F16: MHPV012 | G16: TATA MOTORS PASSENGER VEHICLES LIMITED | H16: 10770 | I16: 32.221 | J16: =H16*I16 -> 347020.17 | K16: 0 | L16: =J16+K16 -> 347020.17 | N16: MPPUNE/0034 | O16: Warehouse | P16: FY 2025-26 | Q16: 45766 | R16: 26/MPPIB/INV0050 | S16: PRAJAPATI CASTING FOUNDRY PRIVATE LIMITED | T16: 12270 | U16: 40 | V16: =U16*T16 -> 490800 | W16: 0 | X16: =V16+W16 -> 490800 | Y16: =_xlfn.XLOOKUP(R16,'Details PC'!AA:AA,'Details PC'!AI:AI)-X16 -> 0 | AA16: FY 2025-26 | AB16: =TEXT(AC16,"mmm-yy") -> May-25 | AC16: 45782 | AE16: MOHIT KANAUGIYA | AG16: 12 | AI16: 25-26/PUR/001319 | AN16: 1 | AO16: 5629 | AP16: =AN16*AO16 -> 5629 | AQ16: 0 | AR16: =AP16-AQ16 -> 5629
B17: Material Cost | C17: FY 2025-26 | D17: =TEXT(E17,"mmm-yy") -> Apr-25 | E17: 45766 | F17: MHPV013 | G17: TATA MOTORS PASSENGER VEHICLES LIMITED | H17: 2920 | I17: 31.121 | J17: =H17*I17 -> 90873.32 | K17: 0 | L17: =J17+K17 -> 90873.32 | N17: MPPUNE/0036 | O17: Warehouse | P17: FY 2025-26 | Q17: 45772 | R17: 26/MPPIB/INV0067 | S17: YASH ENTERPRISES | T17: 5500 | U17: 35.7 | V17: =U17*T17 -> 196350 | W17: 0 | X17: =V17+W17 -> 196350 | Y17: =_xlfn.XLOOKUP(R17,'Details PC'!AA:AA,'Details PC'!AI:AI)-X17 -> 0 | AA17: FY 2025-26 | AB17: =TEXT(AC17,"mmm-yy") -> May-25 | AC17: 45782 | AE17: MOHIT KANAUGIYA | AG17: 12 | AI17: 25-26/PUR/001319 | AN17: 1 | AO17: 5698 | AP17: =AN17*AO17 -> 5698 | AQ17: 0 | AR17: =AP17-AQ17 -> 5698
B18: Material Cost | C18: FY 2025-26 | D18: =TEXT(E18,"mmm-yy") -> Apr-25 | E18: 45766 | F18: MHPV014 | G18: TATA MOTORS PASSENGER VEHICLES LIMITED | H18: 3040 | I18: 31.121 | J18: =H18*I18 -> 94607.84 | K18: 0 | L18: =J18+K18 -> 94607.84 | N18: MPPUNE/0037 | O18: Warehouse | P18: FY 2025-26 | Q18: 45772 | R18: 26/MPPIB/INV0068 | S18: YASH ENTERPRISES | T18: 11660 | U18: 34.8 | V18: =U18*T18 -> 405768 | W18: 0 | X18: =V18+W18 -> 405768 | Y18: =_xlfn.XLOOKUP(R18,'Details PC'!AA:AA,'Details PC'!AI:AI)-X18 -> 0 | AA18: FY 2025-26 | AB18: =TEXT(AC18,"mmm-yy") -> May-25 | AC18: 45782 | AE18: MOHIT KANAUGIYA | AG18: 12 | AI18: 25-26/PUR/001319 | AN18: 1 | AO18: 6375 | AP18: =AN18*AO18 -> 6375 | AQ18: 0 | AR18: =AP18-AQ18 -> 6375
B19: Material Cost | C19: FY 2025-26 | D19: =TEXT(E19,"mmm-yy") -> Apr-25 | E19: 45768 | F19: MHPV015 | G19: TATA MOTORS PASSENGER VEHICLES LIMITED | H19: 3260 | I19: 31.121 | J19: =H19*I19 -> 101454.46 | K19: 0 | L19: =J19+K19 -> 101454.46 | N19: MPPUNE/0038 | O19: Warehouse | P19: FY 2025-26 | Q19: 45785 | R19: 26/MPPIB/INV0096 | S19: PRAJAPATI FOUNDRY PRIVATE LIMITED | T19: 7550 | U19: 40 | V19: =U19*T19 -> 302000 | W19: -302000 | X19: =V19+W19 -> 0 | Y19: =_xlfn.XLOOKUP(R19,'Details PC'!AA:AA,'Details PC'!AI:AI)-X19 -> 0 | AA19: FY 2025-26 | AB19: =TEXT(AC19,"mmm-yy") -> May-25 | AC19: 45782 | AE19: MOHIT KANAUGIYA | AG19: 13 | AI19: 25-26/PUR/001321 | AN19: 1 | AO19: 6478 | AP19: =AN19*AO19 -> 6478 | AQ19: 0 | AR19: =AP19-AQ19 -> 6478
B20: Material Cost | C20: FY 2025-26 | D20: =TEXT(E20,"mmm-yy") -> Apr-25 | E20: 45768 | F20: MHPV016 | G20: TATA MOTORS PASSENGER VEHICLES LIMITED | H20: 3250 | I20: 31.121 | J20: =H20*I20 -> 101143.25 | K20: 0 | L20: =J20+K20 -> 101143.25 | N20: MPPUNE/0039 | O20: Warehouse | P20: FY 2025-26 | Q20: 45799 | R20: 26/MPPIB/INV0126 | S20: S S R ENTERPRISES | T20: 24720 | U20: 38 | V20: =U20*T20 -> 939360 | W20: 0 | X20: =V20+W20 -> 939360 | Y20: =_xlfn.XLOOKUP(R20,'Details PC'!AA:AA,'Details PC'!AI:AI)-X20 -> 0 | AA20: FY 2025-26 | AB20: =TEXT(AC20,"mmm-yy") -> May-25 | AC20: 45782 | AE20: MOHIT KANAUGIYA | AG20: 13 | AI20: 25-26/PUR/001321 | AN20: 1 | AO20: 6413 | AP20: =AN20*AO20 -> 6413 | AQ20: 0 | AR20: =AP20-AQ20 -> 6413
B21: Material Cost | C21: FY 2025-26 | D21: =TEXT(E21,"mmm-yy") -> Apr-25 | E21: 45775 | F21: MHPV017 | G21: TATA MOTORS PASSENGER VEHICLES LIMITED | H21: 2580 | I21: 31.121 | J21: =H21*I21 -> 80292.18 | K21: 0 | L21: =J21+K21 -> 80292.18 | N21: MPPUNE/0041 | O21: Warehouse | P21: FY 2025-26 | Q21: 45800 | R21: 26/MPPIB/INV0130 | S21: KALYANI FOUNDRY WORKS | T21: 10280 | U21: 42 | V21: =U21*T21 -> 431760 | W21: 0 | X21: =V21+W21 -> 431760 | Y21: =_xlfn.XLOOKUP(R21,'Details PC'!AA:AA,'Details PC'!AI:AI)-X21 -> 0 | AA21: FY 2025-26 | AB21: =TEXT(AC21,"mmm-yy") -> May-25 | AC21: 45782 | AE21: MOHIT KANAUGIYA | AG21: 13 | AI21: 25-26/PUR/001321 | AN21: 1 | AO21: 3000 | AP21: =AN21*AO21 -> 3000 | AQ21: 0 | AR21: =AP21-AQ21 -> 3000
B22: Material Cost | C22: FY 2025-26 | D22: =TEXT(E22,"mmm-yy") -> Apr-25 | E22: 45775 | F22: MHPV018 | G22: TATA MOTORS PASSENGER VEHICLES LIMITED | H22: 3330 | I22: 31.121 | J22: =H22*I22 -> 103632.93 | K22: 0 | L22: =J22+K22 -> 103632.93 | N22: MPPUNE/0040 | O22: Warehouse | P22: FY 2025-26 | Q22: 45800 | R22: 26/MPPIB/INV0129 | S22: KALYANI FOUNDRY WORKS | T22: 9600 | U22: 42 | V22: =U22*T22 -> 403200 | W22: 0 | X22: =V22+W22 -> 403200 | Y22: =_xlfn.XLOOKUP(R22,'Details PC'!AA:AA,'Details PC'!AI:AI)-X22 -> 0 | AA22: FY 2025-26 | AB22: =TEXT(AC22,"mmm-yy") -> May-25 | AC22: 45782 | AE22: MOHIT KANAUGIYA | AG22: 13 | AI22: 25-26/PUR/001321 | AN22: 1 | AO22: 3000 | AP22: =AN22*AO22 -> 3000 | AQ22: 0 | AR22: =AP22-AQ22 -> 3000
B23: Material Cost | C23: FY 2025-26 | D23: =TEXT(E23,"mmm-yy") -> Apr-25 | E23: 45776 | F23: MHPV019 | G23: TATA MOTORS LIMITED | H23: 4260 | I23: 30.151 | J23: =H23*I23 -> 128443.26 | K23: 0 | L23: =J23+K23 -> 128443.26 | N23: MPPUNE/0042 | O23: Warehouse | P23: FY 2025-26 | Q23: 45801 | R23: 26/MPPIB/INV0131 | S23: KALYANI FOUNDRY WORKS | T23: 5600 | U23: 42 | V23: =U23*T23 -> 235200 | W23: 0 | X23: =V23+W23 -> 235200 | Y23: =_xlfn.XLOOKUP(R23,'Details PC'!AA:AA,'Details PC'!AI:AI)-X23 -> 0 | AA23: FY 2025-26 | AB23: =TEXT(AC23,"mmm-yy") -> May-25 | AC23: 45782 | AE23: MOHIT KANAUGIYA | AG23: 13 | AI23: 25-26/PUR/001321 | AN23: 1 | AO23: 3000 | AP23: =AN23*AO23 -> 3000 | AQ23: 0 | AR23: =AP23-AQ23 -> 3000
B24: Material Cost | C24: FY 2025-26 | D24: =TEXT(E24,"mmm-yy") -> Apr-25 | E24: 45776 | F24: MHPV020 | G24: TATA MOTORS LIMITED | H24: 4640 | I24: 30.151 | J24: =H24*I24 -> 139900.64 | K24: 0 | L24: =J24+K24 -> 139900.64 | N24: MPPUNE/0043 | O24: Warehouse | P24: FY 2025-26 | Q24: 45805 | R24: 26/MPPIB/INV0141 | S24: KALYANI FOUNDRY WORKS | T24: 11630 | U24: 42 | V24: =U24*T24 -> 488460 | W24: 0 | X24: =V24+W24 -> 488460 | Y24: =_xlfn.XLOOKUP(R24,'Details PC'!AA:AA,'Details PC'!AI:AI)-X24 -> 0 | AA24: FY 2025-26 | AB24: =TEXT(AC24,"mmm-yy") -> May-25 | AC24: 45782 | AE24: MOHIT KANAUGIYA | AG24: 13 | AI24: 25-26/PUR/001321 | AN24: 1 | AO24: 3000 | AP24: =AN24*AO24 -> 3000 | AQ24: 0 | AR24: =AP24-AQ24 -> 3000
... B30: Material Cost | C30: FY 2025-26 | D30: =TEXT(E30,"mmm-yy") -> May-25 | E30: 45782 | F30: MHPV026 | G30: SUYASH INDUSTRIES | H30: 7470 | I30: 36 | J30: =H30*I30 -> 268920 | K30: 0 | L30: =J30+K30 -> 268920 | N30: MPPUNE/0053 | O30: Warehouse | P30: FY 2025-26 | Q30: 45818 | R30: 26/MPPIB/INV0187 | S30: KALYANI FOUNDRY WORKS | T30: 21210 | U30: 42 | V30: =U30*T30 -> 890820 | W30: 0 | X30: =V30+W30 -> 890820 | Y30: =_xlfn.XLOOKUP(R30,'Details PC'!AA:AA,'Details PC'!AI:AI)-X30 -> 0 | AA30: FY 2025-26 | AB30: =TEXT(AC30,"mmm-yy") -> May-25 | AC30: 45782 | AE30: MOHIT KANAUGIYA | AG30: 15 | AI30: 25-26/PUR/001323 | AN30: 1 | AO30: 5181 | AP30: =AN30*AO30 -> 5181 | AQ30: 0 | AR30: =AP30-AQ30 -> 5181
B31: Processing Cost | C31: FY 2025-26 | D31: =TEXT(E31,"mmm-yy") -> May-25 | E31: 45782 | G31: BHAIRAVNATH ENTERPRISES | H31: 1 | I31: 26950 | J31: =H31*I31 -> 26950 | K31: 0 | L31: =J31+K31 -> 26950 | N31: MPPUNE/0054 | O31: Warehouse | P31: FY 2025-26 | Q31: 45819 | R31: 26/MPPIB/INV0188 | S31: YASH ENTERPRISES | T31: 11690 | U31: 33 | V31: =U31*T31 -> 385770 | W31: 0 | X31: =V31+W31 -> 385770 | Y31: =_xlfn.XLOOKUP(R31,'Details PC'!AA:AA,'Details PC'!AI:AI)-X31 -> 0 | AA31: FY 2025-26 | AB31: =TEXT(AC31,"mmm-yy") -> May-25 | AC31: 45782 | AE31: MOHIT KANAUGIYA | AG31: 17 | AI31: 25-26/PUR/001325 | AN31: 1 | AO31: 39050 | AP31: =AN31*AO31 -> 39050 | AQ31: 0 | AR31: =AP31-AQ31 -> 39050
B32: Material Cost | C32: FY 2025-26 | D32: =TEXT(E32,"mmm-yy") -> May-25 | E32: 45783 | F32: MHPV027 | G32: TATA MOTORS PASSENGER VEHICLES LIMITED | H32: 3110 | I32: 31.121 | J32: =H32*I32 -> 96786.31 | K32: 0 | L32: =J32+K32 -> 96786.31 | N32: MPPUNE/0048 | O32: Warehouse | P32: FY 2025-26 | Q32: 45810 | R32: 26/MPPIB/INV0155 | S32: YASH ENTERPRISES | T32: 8510 | U32: 33 | V32: =U32*T32 -> 280830 | W32: 0 | X32: =V32+W32 -> 280830 | Y32: =_xlfn.XLOOKUP(R32,'Details PC'!AA:AA,'Details PC'!AI:AI)-X32 -> 0 | AA32: FY 2025-26 | AB32: =TEXT(AC32,"mmm-yy") -> May-25 | AC32: 45782 | AE32: MOHIT KANAUGIYA | AG32: 13 | AI32: 25-26/PUR/001321 | AN32: 1 | AO32: 3000 | AP32: =AN32*AO32 -> 3000 | AQ32: 0 | AR32: =AP32-AQ32 -> 3000
B33: Material Cost | C33: FY 2025-26 | D33: =TEXT(E33,"mmm-yy") -> May-25 | E33: 45783 | F33: MHPV028 | G33: TATA MOTORS PASSENGER VEHICLES LIMITED | H33: 4160 | I33: 31.121 | J33: =H33*I33 -> 129463.36 | K33: 0 | L33: =J33+K33 -> 129463.36 | N33: MPPUNE/0049 | O33: Warehouse | P33: FY 2025-26 | Q33: 45812 | R33: 26/MPPIB/INV0162 | S33: YASH ENTERPRISES | T33: 4460 | U33: 33 | V33: =U33*T33 -> 147180 | W33: 0 | X33: =V33+W33 -> 147180 | Y33: =_xlfn.XLOOKUP(R33,'Details PC'!AA:AA,'Details PC'!AI:AI)-X33 -> 0 | AA33: FY 2025-26 | AB33: =TEXT(AC33,"mmm-yy") -> May-25 | AC33: 45782 | AE33: MOHIT KANAUGIYA | AG33: 15 | AI33: 25-26/PUR/001323 | AN33: 1 | AO33: 5511 | AP33: =AN33*AO33 -> 5511 | AQ33: 0 | AR33: =AP33-AQ33 -> 5511
B34: Material Cost | C34: FY 2025-26 | D34: =TEXT(E34,"mmm-yy") -> May-25 | E34: 45785 | F34: MHPV029 | G34: TATA MOTORS PASSENGER VEHICLES LIMITED | H34: 2320 | I34: 31.121 | J34: =H34*I34 -> 72200.72 | K34: 0 | L34: =J34+K34 -> 72200.72 | N34: MPPUNE/0051 | O34: Warehouse | P34: FY 2025-26 | Q34: 45816 | R34: 26/MPPIB/INV0178 | S34: YASH ENTERPRISES | T34: 6630 | U34: 33 | V34: =U34*T34 -> 218790 | W34: 0 | X34: =V34+W34 -> 218790 | Y34: =_xlfn.XLOOKUP(R34,'Details PC'!AA:AA,'Details PC'!AI:AI)-X34 -> 0 | AA34: FY 2025-26 | AB34: =TEXT(AC34,"mmm-yy") -> May-25 | AC34: 45782 | AE34: MOHIT KANAUGIYA | AG34: 15 | AI34: 25-26/PUR/001323 | AN34: 1 | AO34: 6651 | AP34: =AN34*AO34 -> 6651 | AQ34: 0 | AR34: =AP34-AQ34 -> 6651
B35: Material Cost | C35: FY 2025-26 | D35: =TEXT(E35,"mmm-yy") -> May-25 | E35: 45786 | F35: MHPV030 | G35: TATA MOTORS LIMITED | H35: 4560 | I35: 30.151 | J35: =H35*I35 -> 137488.56 | K35: 0 | L35: =J35+K35 -> 137488.56 | N35: MPPUNE/0052 | O35: Warehouse | P35: FY 2025-26 | Q35: 45817 | R35: 26/MPPIB/INV0179 | S35: S S R ENTERPRISES | T35: 23940 | U35: 38 | V35: =U35*T35 -> 909720 | W35: 0 | X35: =V35+W35 -> 909720 | Y35: =_xlfn.XLOOKUP(R35,'Details PC'!AA:AA,'Details PC'!AI:AI)-X35 -> 0 | AA35: FY 2025-26 | AB35: =TEXT(AC35,"mmm-yy") -> May-25 | AC35: 45782 | AE35: MOHIT KANAUGIYA | AG35: 15 | AI35: 25-26/PUR/001323 | AN35: 1 | AO35: 7299 | AP35: =AN35*AO35 -> 7299 | AQ35: 0 | AR35: =AP35-AQ35 -> 7299
B36: Material Cost | C36: FY 2025-26 | D36: =TEXT(E36,"mmm-yy") -> May-25 | E36: 45791 | F36: MHPV031 | G36: TATA MOTORS PASSENGER VEHICLES LIMITED | H36: 2520 | I36: 31.121 | J36: =H36*I36 -> 78424.92 | K36: 0 | L36: =J36+K36 -> 78424.92 | N36: MPPUNE/0056 | O36: Warehouse | P36: FY 2025-26 | Q36: 45825 | R36: 26/MPPIB/INV0209 | S36: S S R ENTERPRISES | T36: 24580 | U36: 38 | V36: =U36*T36 -> 934040 | W36: -24580 | X36: =V36+W36 -> 909460 | Y36: =_xlfn.XLOOKUP(R36,'Details PC'!AA:AA,'Details PC'!AI:AI)-X36 -> 0 | AA36: FY 2025-26 | AB36: =TEXT(AC36,"mmm-yy") -> May-25 | AC36: 45782 | AE36: YASH ENTERPRISES | AG36: GST/25-26/016 | AI36: 25-26/PUR/001347 | AN36: 1 | AO36: 110009 | AP36: =AN36*AO36 -> 110009 | AQ36: 0 | AR36: =AP36-AQ36 -> 110009
B37: Material Cost | C37: FY 2025-26 | D37: =TEXT(E37,"mmm-yy") -> May-25 | E37: 45791 | F37: MHPV032 | G37: TATA MOTORS PASSENGER VEHICLES LIMITED | H37: 2450 | I37: 31.121 | J37: =H37*I37 -> 76246.45 | K37: 0 | L37: =J37+K37 -> 76246.45 | N37: MPPUNE/0055 | O37: Warehouse | P37: FY 2025-26 | Q37: 45820 | R37: 26/MPPIB/INV0192 | S37: KALYANI FOUNDRY WORKS | T37: 10470 | U37: 42 | V37: =U37*T37 -> 439740 | W37: 0 | X37: =V37+W37 -> 439740 | Y37: =_xlfn.XLOOKUP(R37,'Details PC'!AA:AA,'Details PC'!AI:AI)-X37 -> 0 | AA37: FY 2025-26 | AB37: =TEXT(AC37,"mmm-yy") -> May-25 | AC37: 45782 | AE37: MOHIT KANAUGIYA | AG37: 18 | AI37: 25-26/PUR/001328 | AN37: 1 | AO37: 7000 | AP37: =AN37*AO37 -> 7000 | AQ37: 0 | AR37: =AP37-AQ37 -> 7000
B38: Material Cost | C38: FY 2025-26 | D38: =TEXT(E38,"mmm-yy") -> May-25 | E38: 45793 | F38: MHPV033 | G38: TATA MOTORS PASSENGER VEHICLES LIMITED | H38: 2650 | I38: 31.121 | J38: =H38*I38 -> 82470.65 | K38: 0 | L38: =J38+K38 -> 82470.65 | N38: MPPUNE/0057 | O38: Warehouse | P38: FY 2025-26 | Q38: 45830 | R38: 27/MPIB/26IN0001 | S38: PRAJAPATI FOUNDRY PRIVATE LIMITED | T38: 18950 | U38: 36.5 | V38: =U38*T38 -> 691675 | W38: -2555 | X38: =V38+W38 -> 689120 | Y38: =_xlfn.XLOOKUP(R38,'Details PC'!AA:AA,'Details PC'!AI:AI)-X38 -> 0 | AA38: FY 2025-26 | AB38: =TEXT(AC38,"mmm-yy") -> May-25 | AC38: 45805 | AE38: MOHIT KANAUGIYA | AG38: 20 | AI38: 25-26/PUR/002316 | AN38: 1 | AO38: 7254 | AP38: =AN38*AO38 -> 7254 | AQ38: 0 | AR38: =AP38-AQ38 -> 7254
B39: Material Cost | C39: FY 2025-26 | D39: =TEXT(E39,"mmm-yy") -> May-25 | E39: 45793 | F39: MHPV034 | G39: TATA MOTORS PASSENGER VEHICLES LIMITED | H39: 3060 | I39: 31.121 | J39: =H39*I39 -> 95230.26 | K39: 0 | L39: =J39+K39 -> 95230.26 | N39: MPPUNE/0058 | O39: Warehouse | P39: FY 2025-26 | Q39: 45832 | R39: 27/MPIB/26IN0002 | S39: S S R ENTERPRISES | T39: 11940 | U39: 35 | V39: =U39*T39 -> 417900 | W39: 0 | X39: =V39+W39 -> 417900 | Y39: =_xlfn.XLOOKUP(R39,'Details PC'!AA:AA,'Details PC'!AI:AI)-X39 -> 0 | AA39: FY 2025-26 | AB39: =TEXT(AC39,"mmm-yy") -> May-25 | AC39: 45805 | AE39: MOHIT KANAUGIYA | AG39: 20 | AI39: 25-26/PUR/002316 | AN39: 1 | AO39: 7545 | AP39: =AN39*AO39 -> 7545 | AQ39: 0 | AR39: =AP39-AQ39 -> 7545
B40: Material Cost | C40: FY 2025-26 | D40: =TEXT(E40,"mmm-yy") -> May-25 | E40: 45794 | F40: MHPV035 | G40: TATA MOTORS LIMITED | H40: 5060 | I40: 30.151 | J40: =H40*I40 -> 152564.06 | K40: 0 | L40: =J40+K40 -> 152564.06 | N40: MPPUNE/0059 | O40: Warehouse | P40: FY 2025-26 | Q40: 45832 | R40: 27/MPIB/26IN0003 | S40: S S R ENTERPRISES | T40: 11640 | U40: 35 | V40: =U40*T40 -> 407400 | W40: -2910 | X40: =V40+W40 -> 404490 | Y40: =_xlfn.XLOOKUP(R40,'Details PC'!AA:AA,'Details PC'!AI:AI)-X40 -> 0 | AA40: FY 2025-26 | AB40: =TEXT(AC40,"mmm-yy") -> May-25 | AC40: 45805 | AE40: MOHIT KANAUGIYA | AG40: 21 | AI40: 25-26/PUR/002317 | AN40: 1 | AO40: 88697 | AP40: =AN40*AO40 -> 88697 | AQ40: 0 | AR40: =AP40-AQ40 -> 88697
B41: Material Cost | C41: FY 2025-26 | D41: =TEXT(E41,"mmm-yy") -> May-25 | E41: 45796 | F41: MHPV036 | G41: TATA MOTORS PASSENGER VEHICLES LIMITED | H41: 2260 | I41: 31.121 | J41: =H41*I41 -> 70333.46 | K41: 0 | L41: =J41+K41 -> 70333.46 | N41: MPPUNE/0060 | O41: Warehouse | P41: FY 2025-26 | Q41: 45833 | R41: 27/MPIB/26IN0004 | S41: PRAJAPATI CASTING FOUNDRY PRIVATE LIMITED | T41: 22110 | U41: 40.5 | V41: =U41*T41 -> 895455 | W41: 0 | X41: =V41+W41 -> 895455 | Y41: =_xlfn.XLOOKUP(R41,'Details PC'!AA:AA,'Details PC'!AI:AI)-X41 -> 0 | AA41: FY 2025-26 | AB41: =TEXT(AC41,"mmm-yy") -> May-25 | AC41: 45805 | AE41: MOHIT KANAUGIYA | AG41: 22 | AI41: 25-26/PUR/002318 | AN41: 1 | AO41: 44145 | AP41: =AN41*AO41 -> 44145 | AQ41: 0 | AR41: =AP41-AQ41 -> 44145
B42: Material Cost | C42: FY 2025-26 | D42: =TEXT(E42,"mmm-yy") -> May-25 | E42: 45799 | F42: MHPV037 | G42: TATA MOTORS PASSENGER VEHICLES LIMITED | H42: 3610 | I42: 31.121 | J42: =H42*I42 -> 112346.81 | K42: 0 | L42: =J42+K42 -> 112346.81 | N42: MPPUNE/0061 | O42: Warehouse | P42: FY 2025-26 | Q42: 45837 | R42: 27/MPIB/26IN0005 | S42: KALYANI FOUNDRY WORKS | T42: 20420 | U42: 42 | V42: =U42*T42 -> 857640 | W42: 0 | X42: =V42+W42 -> 857640 | Y42: =_xlfn.XLOOKUP(R42,'Details PC'!AA:AA,'Details PC'!AI:AI)-X42 -> 0 | AA42: FY 2025-26 | AB42: =TEXT(AC42,"mmm-yy") -> May-25 | AC42: 45805 | AE42: MOHIT KANAUGIYA | AG42: 23 | AI42: 25-26/PUR/002319 | AN42: 1 | AO42: 67100 | AP42: =AN42*AO42 -> 67100 | AQ42: 0 | AR42: =AP42-AQ42 -> 67100
B43: Material Cost | C43: FY 2025-26 | D43: =TEXT(E43,"mmm-yy") -> May-25 | E43: 45800 | F43: MHPV038 | G43: TATA MOTORS PASSENGER VEHICLES LIMITED | H43: 2520 | I43: 31.121 | J43: =H43*I43 -> 78424.92 | K43: 0 | L43: =J43+K43 -> 78424.92 | N43: MPPUNE/0062 | O43: Warehouse | P43: FY 2025-26 | Q43: 45837 | R43: 27/MPIB/26IN0006 | S43: S S R ENTERPRISES | T43: 22680 | U43: 38 | V43: =U43*T43 -> 861840 | W43: -45360 | X43: =V43+W43 -> 816480 | Y43: =_xlfn.XLOOKUP(R43,'Details PC'!AA:AA,'Details PC'!AI:AI)-X43 -> 0 | AA43: FY 2025-26 | AB43: =TEXT(AC43,"mmm-yy") -> May-25 | AC43: 45805 | AE43: MOHIT KANAUGIYA | AG43: 19 | AI43: 25-26/PUR/002321 | AN43: 1 | AO43: 6520 | AP43: =AN43*AO43 -> 6520 | AQ43: 0 | AR43: =AP43-AQ43 -> 6520
... B45: Material Cost | C45: FY 2025-26 | D45: =TEXT(E45,"mmm-yy") -> May-25 | E45: 45803 | F45: MHPV040 | G45: TATA MOTORS PASSENGER VEHICLES LIMITED | H45: 3290 | I45: 31.121 | J45: =H45*I45 -> 102388.09 | K45: 0 | L45: =J45+K45 -> 102388.09 | N45: MPPUNE/0064 | O45: Warehouse | P45: FY 2025-26 | Q45: 45839 | R45: 27/MPIB/26IN0008 | S45: YASH ENTERPRISES | T45: 13060 | U45: 33 | V45: =U45*T45 -> 430980 | W45: 0 | X45: =V45+W45 -> 430980 | Y45: =_xlfn.XLOOKUP(R45,'Details PC'!AA:AA,'Details PC'!AI:AI)-X45 -> 0 | AA45: FY 2025-26 | AB45: =TEXT(AC45,"mmm-yy") -> Jun-25 | AC45: 45828 | AE45: MOHIT KANAUGIYA | AG45: 24 | AI45: 25-26/PUR/003381 | AN45: 58.5 | AO45: 1100 | AP45: =AN45*AO45 -> 64350 | AQ45: 0 | AR45: =AP45-AQ45 -> 64350
B46: Processing Cost | C46: FY 2025-26 | D46: =TEXT(E46,"mmm-yy") -> May-25 | E46: 45804 | G46: RAJENDRA SHYAMLAL | H46: 1 | I46: 100000 | J46: =H46*I46 -> 100000 | K46: 0 | L46: =J46+K46 -> 100000 | N46: MPPUNE/0065 | O46: Warehouse | P46: FY 2025-26 | Q46: 45840 | R46: 27/MPIB/26IN0009 | S46: PRAJAPATI FOUNDRY PRIVATE LIMITED | T46: 15540 | U46: 36.5 | V46: =U46*T46 -> 567210 | W46: -2372.5 | X46: =V46+W46 -> 564837.5 | Y46: =_xlfn.XLOOKUP(R46,'Details PC'!AA:AA,'Details PC'!AI:AI)-X46 -> 0 | AA46: FY 2025-26 | AB46: =TEXT(AC46,"mmm-yy") -> Jun-25 | AC46: 45828 | AE46: MOHIT KANAUGIYA | AG46: 29 | AI46: 25-26/PUR/003391 | AN46: 1 | AO46: 9000 | AP46: =AN46*AO46 -> 9000 | AQ46: 0 | AR46: =AP46-AQ46 -> 9000
B47: Material Cost | C47: FY 2025-26 | D47: =TEXT(E47,"mmm-yy") -> May-25 | E47: 45806 | F47: MHPV041 | G47: TATA MOTORS PASSENGER VEHICLES LIMITED | H47: 2600 | I47: 31.121 | J47: =H47*I47 -> 80914.6 | K47: 0 | L47: =J47+K47 -> 80914.6 | N47: MPPUNE/0066 | O47: Warehouse | P47: FY 2025-26 | Q47: 45844 | R47: 27/MPIB/26IN0010 | S47: SONA FOUNDRY | T47: 17580 | U47: 37.5 | V47: =U47*T47 -> 659250 | W47: -2250 | X47: =V47+W47 -> 657000 | Y47: =_xlfn.XLOOKUP(R47,'Details PC'!AA:AA,'Details PC'!AI:AI)-X47 -> 0 | AA47: FY 2025-26 | AB47: =TEXT(AC47,"mmm-yy") -> Jun-25 | AC47: 45828 | AE47: MOHIT KANAUGIYA | AG47: 26 | AI47: 25-26/PUR/003383 | AN47: 1 | AO47: 8300 | AP47: =AN47*AO47 -> 8300 | AQ47: 0 | AR47: =AP47-AQ47 -> 8300
B48: Material Cost | C48: FY 2025-26 | D48: =TEXT(E48,"mmm-yy") -> May-25 | E48: 45806 | F48: MHPV042 | G48: TATA MOTORS PASSENGER VEHICLES LIMITED | H48: 2800 | I48: 31.121 | J48: =H48*I48 -> 87138.8 | K48: 0 | L48: =J48+K48 -> 87138.8 | N48: MPPUNE/0067 | O48: Warehouse | P48: FY 2025-26 | Q48: 45844 | R48: 27/MPIB/26IN0011 | S48: S S R ENTERPRISES | T48: 12950 | U48: 35.7 | V48: =U48*T48 -> 462315 | W48: -2590 | X48: =V48+W48 -> 459725 | Y48: =_xlfn.XLOOKUP(R48,'Details PC'!AA:AA,'Details PC'!AI:AI)-X48 -> 0 | AA48: FY 2025-26 | AB48: =TEXT(AC48,"mmm-yy") -> Jun-25 | AC48: 45828 | AE48: MOHIT KANAUGIYA | AG48: 25 | AI48: 25-26/PUR/003382 | AN48: 16 | AO48: 1100 | AP48: =AN48*AO48 -> 17600 | AQ48: 0 | AR48: =AP48-AQ48 -> 17600
B49: Material Cost | C49: FY 2025-26 | D49: =TEXT(E49,"mmm-yy") -> May-25 | E49: 45807 | F49: MHPV043 | G49: TATA MOTORS LIMITED | H49: 4240 | I49: 30.151 | J49: =H49*I49 -> 127840.24 | K49: 0 | L49: =J49+K49 -> 127840.24 | N49: MPPUNE/0068 | O49: Warehouse | P49: FY 2025-26 | Q49: 45844 | R49: 27/MPIB/26IN0012 | S49: S S R ENTERPRISES | T49: 12980 | U49: 35.7 | V49: =U49*T49 -> 463386 | W49: -2596 | X49: =V49+W49 -> 460790 | Y49: =_xlfn.XLOOKUP(R49,'Details PC'!AA:AA,'Details PC'!AI:AI)-X49 -> 0 | AA49: FY 2025-26 | AB49: =TEXT(AC49,"mmm-yy") -> Jun-25 | AC49: 45828 | AE49: MOHIT KANAUGIYA | AG49: 27 | AI49: 25-26/PUR/003384 | AN49: 1 | AO49: 104249 | AP49: =AN49*AO49 -> 104249 | AQ49: 0 | AR49: =AP49-AQ49 -> 104249
B50: Material Cost | C50: FY 2025-26 | D50: =TEXT(E50,"mmm-yy") -> May-25 | E50: 45807 | F50: MHPV044 | G50: TATA MOTORS LIMITED | H50: 3320 | I50: 30.151 | J50: =H50*I50 -> 100101.32 | K50: 0 | L50: =J50+K50 -> 100101.32 | N50: MPPUNE/0069 | O50: Warehouse | P50: FY 2025-26 | Q50: 45847 | R50: 27/MPIB/26IN0013 | S50: SONA FOUNDRY | T50: 17960 | U50: 37.5 | V50: =U50*T50 -> 673500 | W50: -1500 | X50: =V50+W50 -> 672000 | Y50: =_xlfn.XLOOKUP(R50,'Details PC'!AA:AA,'Details PC'!AI:AI)-X50 -> 0 | AA50: FY 2025-26 | AB50: =TEXT(AC50,"mmm-yy") -> Jun-25 | AC50: 45828 | AE50: MOHIT KANAUGIYA | AG50: 28 | AI50: 25-26/PUR/003389 | AN50: 1 | AO50: 30072 | AP50: =AN50*AO50 -> 30072 | AQ50: 0 | AR50: =AP50-AQ50 -> 30072
B51: Material Cost | C51: FY 2025-26 | D51: =TEXT(E51,"mmm-yy") -> Jun-25 | E51: 45811 | F51: MHPV045 | G51: AUTOCOMP CORPORATION PANSE PRIVATE LIMITED | H51: 7535 | I51: 34.2 | J51: =H51*I51 -> 257697 | K51: 0 | L51: =J51+K51 -> 257697 | N51: MPPUNE/0070 | O51: Warehouse | P51: FY 2025-26 | Q51: 45851 | R51: 27/MPIB/26IN0014 | S51: SONA FOUNDRY | T51: 26060 | U51: 37.5 | V51: =U51*T51 -> 977250 | W51: -3375 | X51: =V51+W51 -> 973875 | Y51: =_xlfn.XLOOKUP(R51,'Details PC'!AA:AA,'Details PC'!AI:AI)-X51 -> 0 | AA51: FY 2025-26 | AB51: =TEXT(AC51,"mmm-yy") -> Jul-25 | AC51: 45840 | AE51: MOHIT KANAUGIYA | AG51: 30 | AI51: 25-26/PUR/004324 | AN51: 26 | AO51: 6000 | AP51: =AN51*AO51 -> 156000 | AQ51: 0 | AR51: =AP51-AQ51 -> 156000
B52: Material Cost | C52: FY 2025-26 | D52: =TEXT(E52,"mmm-yy") -> Jun-25 | E52: 45811 | F52: MHPV046 | G52: AUTOCOMP CORPORATION PANSE PRIVATE LIMITED | H52: 7810 | I52: 34.2 | J52: =H52*I52 -> 267102 | K52: 0 | L52: =J52+K52 -> 267102 | N52: MPPUNE/0071 | O52: Warehouse | P52: FY 2025-26 | Q52: 45859 | R52: 27/MPIB/26IN0015 | S52: SONA FOUNDRY | T52: 25480 | U52: 37.5 | V52: =U52*T52 -> 955500 | W52: -750 | X52: =V52+W52 -> 954750 | Y52: =_xlfn.XLOOKUP(R52,'Details PC'!AA:AA,'Details PC'!AI:AI)-X52 -> 0 | AA52: FY 2025-26 | AB52: =TEXT(AC52,"mmm-yy") -> Jul-25 | AC52: 45840 | AE52: MOHIT KANAUGIYA | AG52: 30 | AI52: 25-26/PUR/004324 | AN52: 7 | AO52: 1000 | AP52: =AN52*AO52 -> 7000 | AQ52: 0 | AR52: =AP52-AQ52 -> 7000
B53: Material Cost | C53: FY 2025-26 | D53: =TEXT(E53,"mmm-yy") -> Jun-25 | E53: 45811 | F53: MHPV047 | G53: AUTOCOMP CORPORATION PANSE PRIVATE LIMITED | H53: 8540 | I53: 34.2 | J53: =H53*I53 -> 292068 | K53: 0 | L53: =J53+K53 -> 292068 | N53: MPPUNE/0072 | O53: Warehouse | P53: FY 2025-26 | Q53: 45861 | R53: 27/MPIB/26IN0016 | S53: PRAJAPATI FOUNDRY PRIVATE LIMITED | T53: 19390 | U53: 37.5 | V53: =U53*T53 -> 727125 | W53: -3000 | X53: =V53+W53 -> 724125 | Y53: =_xlfn.XLOOKUP(R53,'Details PC'!AA:AA,'Details PC'!AI:AI)-X53 -> 0 | AA53: FY 2025-26 | AB53: =TEXT(AC53,"mmm-yy") -> Jul-25 | AC53: 45840 | AE53: MOHIT KANAUGIYA | AG53: 31 | AI53: 25-26/PUR/004327 | AN53: 19 | AO53: 6000 | AP53: =AN53*AO53 -> 114000 | AQ53: 0 | AR53: =AP53-AQ53 -> 114000
B54: Processing Cost | C54: FY 2025-26 | D54: =TEXT(E54,"mmm-yy") -> Jun-25 | E54: 45811 | G54: RAJENDRA SHYAMLAL | H54: 1 | I54: 100000 | J54: =H54*I54 -> 100000 | K54: 0 | L54: =J54+K54 -> 100000 | N54: MPPUNE/0073 | O54: Warehouse | P54: FY 2025-26 | Q54: 45863 | R54: 27/MPIB/26IN0017 | S54: SAARLOHA ADVANCED MATERIALS PRIVATE LIMITED | T54: 32490 | U54: 35.05 | V54: =U54*T54 -> 1138774.5 | W54: -8412 | X54: =V54+W54 -> 1130362.5 | Y54: =_xlfn.XLOOKUP(R54,'Details PC'!AA:AA,'Details PC'!AI:AI)-X54 -> 0 | AA54: FY 2025-26 | AB54: =TEXT(AC54,"mmm-yy") -> Jul-25 | AC54: 45840 | AE54: MOHIT KANAUGIYA | AG54: 31 | AI54: 25-26/PUR/004327 | AN54: 6 | AO54: 1000 | AP54: =AN54*AO54 -> 6000 | AQ54: 0 | AR54: =AP54-AQ54 -> 6000
B55: Material Cost | C55: FY 2025-26 | D55: =TEXT(E55,"mmm-yy") -> Jun-25 | E55: 45812 | F55: MHPV048 | G55: AUTOCOMP CORPORATION PANSE PRIVATE LIMITED | H55: 10970 | I55: 34.2 | J55: =H55*I55 -> 375174 | K55: 0 | L55: =J55+K55 -> 375174 | N55: MPPUNE/0074 | O55: Warehouse | P55: FY 2025-26 | Q55: 45864 | R55: 27/MPIB/26IN0018 | S55: SAARLOHA ADVANCED MATERIALS PRIVATE LIMITED | T55: 25920 | U55: 35.05 | V55: =U55*T55 -> 908496 | W55: 0 | X55: =V55+W55 -> 908496 | Y55: =_xlfn.XLOOKUP(R55,'Details PC'!AA:AA,'Details PC'!AI:AI)-X55 -> 0 | AA55: FY 2025-26 | AB55: =TEXT(AC55,"mmm-yy") -> Jul-25 | AC55: 45841 | AE55: MOHIT KANAUGIYA | AG55: 32 | AI55: 25-26/PUR/004379 | AN55: 32 | AO55: 3000 | AP55: =AN55*AO55 -> 96000 | AQ55: 0 | AR55: =AP55-AQ55 -> 96000
B56: Material Cost | C56: FY 2025-26 | D56: =TEXT(E56,"mmm-yy") -> Jun-25 | E56: 45812 | F56: MHPV049 | G56: AUTOCOMP CORPORATION PANSE PRIVATE LIMITED | H56: 7995 | I56: 34.2 | J56: =H56*I56 -> 273429 | K56: 0 | L56: =J56+K56 -> 273429 | N56: MPPUNE/0075 | O56: Warehouse | P56: FY 2025-26 | Q56: 45865 | R56: 27/MPIB/26IN0019 | S56: SAARLOHA ADVANCED MATERIALS PRIVATE LIMITED | T56: 30750 | U56: 35.05 | V56: =U56*T56 -> 1077787.5 | W56: -3505 | X56: =V56+W56 -> 1074282.5 | Y56: =_xlfn.XLOOKUP(R56,'Details PC'!AA:AA,'Details PC'!AI:AI)-X56 -> 0 | AA56: FY 2025-26 | AB56: =TEXT(AC56,"mmm-yy") -> Jul-25 | AC56: 45847 | AE56: Shivshambho Logistics | AG56: 50 | AI56: 25-26/PUR/004700 | AN56: 1 | AO56: 103568 | AP56: =AN56*AO56 -> 103568 | AQ56: 0 | AR56: =AP56-AQ56 -> 103568
B57: Material Cost | C57: FY 2025-26 | D57: =TEXT(E57,"mmm-yy") -> Jun-25 | E57: 45812 | F57: MHPV050 | G57: AUTOCOMP CORPORATION PANSE PRIVATE LIMITED | H57: 5990 | I57: 34.2 | J57: =H57*I57 -> 204858 | K57: 0 | L57: =J57+K57 -> 204858 | N57: MPPUNE/0076 | O57: Warehouse | P57: FY 2025-26 | Q57: 45866 | R57: 27/MPIB/26IN0020 | S57: SONA FOUNDRY | T57: 12750 | U57: 37.5 | V57: =U57*T57 -> 478125 | W57: -750 | X57: =V57+W57 -> 477375 | Y57: =_xlfn.XLOOKUP(R57,'Details PC'!AA:AA,'Details PC'!AI:AI)-X57 -> 0 | AA57: FY 2025-26 | AB57: =TEXT(AC57,"mmm-yy") -> Jul-25 | AC57: 45862 | AE57: YASH ENTERPRISES | AG57: GST/25-26/084 | AI57: 25-26/PUR/005820 | AN57: 1 | AO57: 90500 | AP57: =AN57*AO57 -> 90500 | AQ57: 0 | AR57: =AP57-AQ57 -> 90500
B58: Processing Cost | C58: FY 2025-26 | D58: =TEXT(E58,"mmm-yy") -> Jun-25 | E58: 45812 | G58: BHAIRAVNATH ENTERPRISES | H58: 1 | I58: 40950 | J58: =H58*I58 -> 40950 | K58: 0 | L58: =J58+K58 -> 40950 | N58: MPPUNE/0077 | O58: Warehouse | P58: FY 2025-26 | Q58: 45867 | R58: 27/MPIB/26IN0021 | S58: SAARLOHA ADVANCED MATERIALS PRIVATE LIMITED | T58: 28890 | U58: 35.05 | V58: =U58*T58 -> 1012594.5 | W58: 0 | X58: =V58+W58 -> 1012594.5 | Y58: =_xlfn.XLOOKUP(R58,'Details PC'!AA:AA,'Details PC'!AI:AI)-X58 -> 0 | AA58: FY 2025-26 | AB58: =TEXT(AC58,"mmm-yy") -> Jul-25 | AC58: 45868 | AE58: MOHIT KANAUGIYA | AG58: 33 | AI58: 25-26/PUR/006251 | AN58: 1 | AO58: 6500 | AP58: =AN58*AO58 -> 6500 | AQ58: 0 | AR58: =AP58-AQ58 -> 6500
B59: Material Cost | C59: FY 2025-26 | D59: =TEXT(E59,"mmm-yy") -> Jun-25 | E59: 45813 | F59: MHPV051 | G59: AUTOCOMP CORPORATION PANSE PRIVATE LIMITED | H59: 9180 | I59: 34.2 | J59: =H59*I59 -> 313956 | K59: 0 | L59: =J59+K59 -> 313956 | N59: MPPUNE/0078 | O59: Warehouse | P59: FY 2025-26 | Q59: 45869 | R59: 27/MPIB/26IN0022 | S59: SOUND CASTINGS PRIVATE LIMITED | T59: 31170 | U59: 36.2 | V59: =U59*T59 -> 1128354 | W59: -1128354 | X59: =V59+W59 -> 0 | Y59: =_xlfn.XLOOKUP(R59,'Details PC'!AA:AA,'Details PC'!AI:AI)-X59 -> #N/A | AA59: FY 2025-26 | AB59: =TEXT(AC59,"mmm-yy") -> Jul-25 | AC59: 45868 | AE59: MOHIT KANAUGIYA | AG59: 34 | AI59: 25-26/PUR/006259 | AN59: 1 | AO59: 54336 | AP59: =AN59*AO59 -> 54336 | AQ59: 0 | AR59: =AP59-AQ59 -> 54336
B60: Material Cost | C60: FY 2025-26 | D60: =TEXT(E60,"mmm-yy") -> Jun-25 | E60: 45813 | F60: MHPV052 | G60: AUTOCOMP CORPORATION PANSE PRIVATE LIMITED | H60: 6930 | I60: 34.2 | J60: =H60*I60 -> 237006 | K60: 0 | L60: =J60+K60 -> 237006 | N60: MPPUNE/0078 | O60: Warehouse | P60: FY 2025-26 | Q60: 45871 | R60: 27/MPIB/26IN0023 | S60: SOUND CASTINGS PRIVATE LIMITED | T60: 31170 | U60: 35.9 | V60: =U60*T60 -> 1119003 | W60: -14001 | X60: =V60+W60 -> 1105002 | Y60: =_xlfn.XLOOKUP(R60,'Details PC'!AA:AA,'Details PC'!AI:AI)-X60 -> 0 | AA60: FY 2025-26 | AB60: =TEXT(AC60,"mmm-yy") -> Jul-25 | AC60: 45868 | AE60: MOHIT KANAUGIYA | AG60: 35 | AI60: 25-26/PUR/006267 | AN60: 1 | AO60: 72104 | AP60: =AN60*AO60 -> 72104 | AQ60: 0 | AR60: =AP60-AQ60 -> 72104
B61: Material Cost | C61: FY 2025-26 | D61: =TEXT(E61,"mmm-yy") -> Jun-25 | E61: 45814 | F61: MHPV053 | G61: AUTOCOMP CORPORATION PANSE PRIVATE LIMITED | H61: 7545 | I61: 34.2 | J61: =H61*I61 -> 258039 | K61: 0 | L61: =J61+K61 -> 258039 | N61: MPPUNE/0079 | O61: Warehouse | P61: FY 2025-26 | Q61: 45871 | R61: 27/MPIB/26IN0024 | S61: SOUND CASTINGS PRIVATE LIMITED | T61: 25810 | U61: 35.7 | V61: =U61*T61 -> 921417 | W61: =-727923-2142-1631 -> -731696 | X61: =V61+W61 -> 189721 | Y61: =_xlfn.XLOOKUP(R61,'Details PC'!AA:AA,'Details PC'!AI:AI)-X61 -> 0 | AA61: FY 2025-26 | AB61: =TEXT(AC61,"mmm-yy") -> Jul-25 | AC61: 45868 | AE61: MOHIT KANAUGIYA | AG61: 35 | AI61: 25-26/PUR/006267 | AN61: 1 | AO61: 4500 | AP61: =AN61*AO61 -> 4500 | AQ61: 0 | AR61: =AP61-AQ61 -> 4500
B62: Material Cost | C62: FY 2025-26 | D62: =TEXT(E62,"mmm-yy") -> Jun-25 | E62: 45814 | F62: MHPV054 | G62: AUTOCOMP CORPORATION PANSE PRIVATE LIMITED | H62: 7750 | I62: 34.2 | J62: =H62*I62 -> 265050 | K62: 0 | L62: =J62+K62 -> 265050 | N62: MPPUNE/0079 | O62: Warehouse | P62: FY 2025-26 | Q62: 45874 | R62: 27/MPIB/26IN0025 | S62: SOUND CASTINGS PRIVATE LIMITED | T62: 20390 | U62: 35.7 | V62: =U62*T62 -> 727923 | W62: 0 | X62: =V62+W62 -> 727923 | Y62: =_xlfn.XLOOKUP(R62,'Details PC'!AA:AA,'Details PC'!AI:AI)-X62 -> 0 | AA62: FY 2025-26 | AB62: =TEXT(AC62,"mmm-yy") -> Jul-25 | AC62: 45868 | AE62: MOHIT KANAUGIYA | AG62: 35 | AI62: 25-26/PUR/006267 | AN62: 1 | AO62: 4000 | AP62: =AN62*AO62 -> 4000 | AQ62: 0 | AR62: =AP62-AQ62 -> 4000
B63: Material Cost | C63: FY 2025-26 | D63: =TEXT(E63,"mmm-yy") -> Jun-25 | E63: 45815 | F63: MHPV055 | G63: AUTOCOMP CORPORATION PANSE PRIVATE LIMITED | H63: 9635 | I63: 34.2 | J63: =H63*I63 -> 329517 | K63: 0 | L63: =J63+K63 -> 329517 | N63: MPPUNE/0080 | O63: Warehouse | P63: FY 2025-26 | Q63: 45875 | R63: 27/MPIB/26IN0026 | S63: SOUND CASTINGS PRIVATE LIMITED | T63: 23950 | U63: 35.9 | V63: =U63*T63 -> 859805 | W63: =-6462-1916 -> -8378 | X63: =V63+W63 -> 851427 | Y63: =_xlfn.XLOOKUP(R63,'Details PC'!AA:AA,'Details PC'!AI:AI)-X63 -> 0 | AA63: FY 2025-26 | AB63: =TEXT(AC63,"mmm-yy") -> Aug-25 | AC63: 45877 | AE63: Shivshambho Logistics | AG63: 64 | AI63: 25-26/PUR/007300 | AN63: 1 | AO63: =258301.5-12908 -> 245393.5 | AP63: =AN63*AO63 -> 245393.5 | AQ63: 0 | AR63: =AP63-AQ63 -> 245393.5
B64: Material Cost | C64: FY 2025-26 | D64: =TEXT(E64,"mmm-yy") -> Jun-25 | E64: 45815 | F64: MHPV056 | G64: AUTOCOMP CORPORATION PANSE PRIVATE LIMITED | H64: 6285 | I64: 34.2 | J64: =H64*I64 -> 214947 | K64: 0 | L64: =J64+K64 -> 214947 | N64: MPPUNE/0081 | O64: Warehouse | P64: FY 2025-26 | Q64: 45876 | R64: 27/MPIB/26IN0027 | S64: SAARLOHA ADVANCED MATERIALS PRIVATE LIMITED | T64: 25465 | U64: 35.7 | V64: =U64*T64 -> 909100.5 | W64: 0 | X64: =V64+W64 -> 909100.5 | Y64: =_xlfn.XLOOKUP(R64,'Details PC'!AA:AA,'Details PC'!AI:AI)-X64 -> 0 | AA64: FY 2025-26 | AB64: =TEXT(AC64,"mmm-yy") -> Aug-25 | AC64: 45877 | AE64: MOHIT KANAUGIYA | AG64: 37 | AI64: 25-26/PUR/007361 | AN64: 1 | AO64: 49532 | AP64: =AN64*AO64 -> 49532 | AQ64: 0 | AR64: =AP64-AQ64 -> 49532
B65: Material Cost | C65: FY 2025-26 | D65: =TEXT(E65,"mmm-yy") -> Jun-25 | E65: 45817 | F65: MHPV124 | G65: AUTOCOMP CORPORATION PANSE PRIVATE LIMITED | H65: 6640 | I65: 34.2 | J65: =H65*I65 -> 227088 | K65: 0 | L65: =J65+K65 -> 227088 | N65: MPPUNE/0082 | O65: Warehouse | P65: FY 2025-26 | Q65: 45877 | R65: 27/MPIB/26IN0028 | S65: SAARLOHA ADVANCED MATERIALS PRIVATE LIMITED | T65: 26665 | U65: 35.7 | V65: =U65*T65 -> 951940.5 | W65: 0 | X65: =V65+W65 -> 951940.5 | Y65: =_xlfn.XLOOKUP(R65,'Details PC'!AA:AA,'Details PC'!AI:AI)-X65 -> 0 | AA65: FY 2025-26 | AB65: =TEXT(AC65,"mmm-yy") -> Aug-25 | AC65: 45877 | AE65: MOHIT KANAUGIYA | AG65: 38 | AI65: 25-26/PUR/007364 | AN65: 1 | AO65: 117000 | AP65: =AN65*AO65 -> 117000 | AQ65: 0 | AR65: =AP65-AQ65 -> 117000
B66: Material Cost | C66: FY 2025-26 | D66: =TEXT(E66,"mmm-yy") -> Jun-25 | E66: 45818 | F66: MHPV057 | G66: AUTOCOMP CORPORATION PANSE PRIVATE LIMITED | H66: 6115 | I66: 34.2 | J66: =H66*I66 -> 209133 | K66: 0 | L66: =J66+K66 -> 209133 | N66: MPPUNE/0083 | O66: Warehouse | P66: FY 2025-26 | Q66: 45878 | R66: 27/MPIB/26IN0029 | S66: S S R ENTERPRISES | T66: 31310 | U66: 33 | V66: =U66*T66 -> 1033230 | W66: -31310 | X66: =V66+W66 -> 1001920 | Y66: =_xlfn.XLOOKUP(R66,'Details PC'!AA:AA,'Details PC'!AI:AI)-X66 -> 0 | AA66: FY 2025-26 | AB66: =TEXT(AC66,"mmm-yy") -> Aug-25 | AC66: 45877 | AE66: MOHIT KANAUGIYA | AG66: 39 | AI66: 25-26/PUR/007365 | AN66: 1 | AO66: 86042 | AP66: =AN66*AO66 -> 86042 | AQ66: 0 | AR66: =AP66-AQ66 -> 86042
B67: Material Cost | C67: FY 2025-26 | D67: =TEXT(E67,"mmm-yy") -> Jun-25 | E67: 45819 | F67: MHPV058 | G67: TATA MOTORS LIMITED | H67: 3140 | I67: 30.151 | J67: =H67*I67 -> 94674.14 | K67: 0 | L67: =J67+K67 -> 94674.14 | N67: MPPUNE/0084 | O67: Warehouse | P67: FY 2025-26 | Q67: 45878 | R67: 27/MPIB/26IN0030 | S67: SAARLOHA ADVANCED MATERIALS PRIVATE LIMITED | T67: 14340 | U67: 33.75 | V67: =U67*T67 -> 483975 | W67: 0 | X67: =V67+W67 -> 483975 | Y67: =_xlfn.XLOOKUP(R67,'Details PC'!AA:AA,'Details PC'!AI:AI)-X67 -> 0 | AA67: FY 2025-26 | AB67: =TEXT(AC67,"mmm-yy") -> Aug-25 | AC67: 45878 | AE67: MOHIT KANAUGIYA | AG67: 36 | AI67: 25-26/PUR/007360 | AN67: 1 | AO67: 32000 | AP67: =AN67*AO67 -> 32000 | AQ67: 0 | AR67: =AP67-AQ67 -> 32000
B68: Material Cost | C68: FY 2025-26 | D68: =TEXT(E68,"mmm-yy") -> Jun-25 | E68: 45819 | F68: MHPV059 | G68: AUTOCOMP CORPORATION PANSE PRIVATE LIMITED | H68: 11350 | I68: 34.2 | J68: =H68*I68 -> 388170 | K68: 0 | L68: =J68+K68 -> 388170 | N68: MPPUNE/0085 | O68: Warehouse | P68: FY 2025-26 | Q68: 45878 | R68: 27/MPIB/26IN0031 | S68: SAARLOHA ADVANCED MATERIALS PRIVATE LIMITED | T68: 29575 | U68: 35.7 | V68: =U68*T68 -> 1055827.5 | W68: 0 | X68: =V68+W68 -> 1055827.5 | Y68: =_xlfn.XLOOKUP(R68,'Details PC'!AA:AA,'Details PC'!AI:AI)-X68 -> 0 | AA68: FY 2025-26 | AB68: =TEXT(AC68,"mmm-yy") -> Aug-25 | AC68: 45882 | AE68: VIKAS ENTERPRISES | AG68: 115/25-26 | AI68: 25-26/PUR/007627 | AN68: 1 | AO68: 29316.41 | AP68: =AN68*AO68 -> 29316.41 | AQ68: 0 | AR68: =AP68-AQ68 -> 29316.41
B69: Material Cost | C69: FY 2025-26 | D69: =TEXT(E69,"mmm-yy") -> Jun-25 | E69: 45819 | F69: MHPV060 | G69: AUTOCOMP CORPORATION PANSE PRIVATE LIMITED | H69: 6615 | I69: 34.2 | J69: =H69*I69 -> 226233 | K69: 0 | L69: =J69+K69 -> 226233 | N69: MPPUNE/0086 | O69: Warehouse | P69: FY 2025-26 | Q69: 45879 | R69: 27/MPIB/26IN0032 | S69: SAARLOHA ADVANCED MATERIALS PRIVATE LIMITED | T69: 18430 | U69: 35.7 | V69: =U69*T69 -> 657951 | W69: 0 | X69: =V69+W69 -> 657951 | Y69: =_xlfn.XLOOKUP(R69,'Details PC'!AA:AA,'Details PC'!AI:AI)-X69 -> 0 | AA69: FY 2025-26 | AB69: =TEXT(AC69,"mmm-yy") -> Aug-25 | AC69: 45882 | AE69: VIKAS ENTERPRISES | AG69: 78/25-26 | AI69: 25-26/PUR/007628 | AN69: 1 | AO69: 22634.75 | AP69: =AN69*AO69 -> 22634.75 | AQ69: 0 | AR69: =AP69-AQ69 -> 22634.75
B70: Material Cost | C70: FY 2025-26 | D70: =TEXT(E70,"mmm-yy") -> Jun-25 | E70: 45819 | F70: MHPV061 | G70: AUTOCOMP CORPORATION PANSE PRIVATE LIMITED | H70: 9765 | I70: 34.2 | J70: =H70*I70 -> 333963 | K70: 0 | L70: =J70+K70 -> 333963 | N70: MPPUNE/0087 | O70: Warehouse | P70: FY 2025-26 | Q70: 45879 | R70: 27/MPIB/26IN0033 | S70: SAARLOHA ADVANCED MATERIALS PRIVATE LIMITED | T70: 18580 | U70: 33.75 | V70: =U70*T70 -> 627075 | W70: -2025 | X70: =V70+W70 -> 625050 | Y70: =_xlfn.XLOOKUP(R70,'Details PC'!AA:AA,'Details PC'!AI:AI)-X70 -> 0 | AA70: FY 2025-26 | AB70: =TEXT(AC70,"mmm-yy") -> Aug-25 | AC70: 45882 | AE70: VIKAS ENTERPRISES | AG70: 166/25-26 | AI70: 25-26/PUR/007630 | AN70: 1 | AO70: 37834.19 | AP70: =AN70*AO70 -> 37834.19 | AQ70: 0 | AR70: =AP70-AQ70 -> 37834.19
B71: Material Cost | C71: FY 2025-26 | D71: =TEXT(E71,"mmm-yy") -> Jun-25 | E71: 45820 | F71: MHPV062 | G71: YASH ENTERPRISES | H71: 3960 | I71: 36.5 | J71: =H71*I71 -> 144540 | K71: 0 | L71: =J71+K71 -> 144540 | N71: MPPUNE/0088 | O71: Warehouse | P71: FY 2025-26 | Q71: 45880 | R71: 27/MPIB/26IN0034 | S71: SAARLOHA ADVANCED MATERIALS PRIVATE LIMITED | T71: 17935 | U71: 33.75 | V71: =U71*T71 -> 605306.25 | W71: 0 | X71: =V71+W71 -> 605306.25 | Y71: =_xlfn.XLOOKUP(R71,'Details PC'!AA:AA,'Details PC'!AI:AI)-X71 -> 0 | AA71: FY 2025-26 | AB71: =TEXT(AC71,"mmm-yy") -> Aug-25 | AC71: 45874 | AE71: VIKAS ENTERPRISES | AG71: 188/25-26 | AI71: 25-26/PUR/007629 | AN71: 1 | AO71: 30154.02 | AP71: =AN71*AO71 -> 30154.02 | AQ71: 0 | AR71: =AP71-AQ71 -> 30154.02
B72: Material Cost | C72: FY 2025-26 | D72: =TEXT(E72,"mmm-yy") -> Jun-25 | E72: 45820 | F72: MHPV063 | G72: YASH ENTERPRISES | H72: 4710 | I72: 36.5 | J72: =H72*I72 -> 171915 | K72: 0 | L72: =J72+K72 -> 171915 | N72: MPPUNE/0089 | O72: Warehouse | P72: FY 2025-26 | Q72: 45881 | R72: 27/MPIB/26IN0035 | S72: S S R ENTERPRISES | T72: 25320 | U72: 33 | V72: =U72*T72 -> 835560 | W72: -25320 | X72: =V72+W72 -> 810240 | Y72: =_xlfn.XLOOKUP(R72,'Details PC'!AA:AA,'Details PC'!AI:AI)-X72 -> 0 | AA72: FY 2025-26 | AB72: =TEXT(AC72,"mmm-yy") -> Aug-25 | AC72: 45875 | AE72: YASH ENTERPRISES | AG72: GST/25-26/096 | AI72: 25-26/PUR/007227 | AN72: 1 | AO72: 21991 | AP72: =AN72*AO72 -> 21991 | AQ72: 0 | AR72: =AP72-AQ72 -> 21991
B73: Material Cost | C73: FY 2025-26 | D73: =TEXT(E73,"mmm-yy") -> Jun-25 | E73: 45820 | F73: MHPV064 | G73: YASH ENTERPRISES | H73: 3960 | I73: 36.5 | J73: =H73*I73 -> 144540 | K73: 0 | L73: =J73+K73 -> 144540 | N73: MPPUNE/0090 | O73: Warehouse | P73: FY 2025-26 | Q73: 45882 | R73: 27/MPIB/26IN0036 | S73: SOUND CASTINGS PRIVATE LIMITED | T73: 25480 | U73: 35.7 | V73: =U73*T73 -> 909636 | W73: -3927 | X73: =V73+W73 -> 905709 | Y73: =_xlfn.XLOOKUP(R73,'Details PC'!AA:AA,'Details PC'!AI:AI)-X73 -> 0 | AA73: FY 2025-26 | AB73: =TEXT(AC73,"mmm-yy") -> Sep-25 | AC73: 45901 | AE73: MOHIT KANAUGIYA | AG73: 40 | AI73: 25-26/PUR/008922 | AN73: 1 | AO73: 131232 | AP73: =AN73*AO73 -> 131232 | AQ73: 0 | AR73: =AP73-AQ73 -> 131232
B74: Material Cost | C74: FY 2025-26 | D74: =TEXT(E74,"mmm-yy") -> Jun-25 | E74: 45820 | F74: MHPV065 | G74: YASH ENTERPRISES | H74: 3900 | I74: 36.5 | J74: =H74*I74 -> 142350 | K74: 0 | L74: =J74+K74 -> 142350 | N74: MPPUNE/0091 | O74: Warehouse | P74: FY 2025-26 | Q74: 45888 | R74: 27/MPIB/26IN0037 | S74: SOUND CASTINGS PRIVATE LIMITED | T74: 25670 | U74: 35.7 | V74: =U74*T74 -> 916419 | W74: -4641 | X74: =V74+W74 -> 911778 | Y74: =_xlfn.XLOOKUP(R74,'Details PC'!AA:AA,'Details PC'!AI:AI)-X74 -> 0 | AA74: FY 2025-26 | AB74: =TEXT(AC74,"mmm-yy") -> Sep-25 | AC74: 45901 | AE74: MOHIT KANAUGIYA | AG74: 41 | AI74: 25-26/PUR/008923 | AN74: 1 | AO74: 96096 | AP74: =AN74*AO74 -> 96096 | AQ74: 0 | AR74: =AP74-AQ74 -> 96096
B75: Material Cost | C75: FY 2025-26 | D75: =TEXT(E75,"mmm-yy") -> Jun-25 | E75: 45820 | F75: MHPV066 | G75: YASH ENTERPRISES | H75: 7590 | I75: 36.5 | J75: =H75*I75 -> 277035 | K75: 0 | L75: =J75+K75 -> 277035 | N75: MPPUNE/0092 | O75: Warehouse | P75: FY 2025-26 | Q75: 45890 | R75: 27/MPIB/26IN0038 | S75: YASH ENTERPRISES | T75: 4210 | U75: 28 | V75: =U75*T75 -> 117880 | W75: 0 | X75: =V75+W75 -> 117880 | Y75: =_xlfn.XLOOKUP(R75,'Details PC'!AA:AA,'Details PC'!AI:AI)-X75 -> 0 | AA75: FY 2025-26 | AB75: =TEXT(AC75,"mmm-yy") -> Sep-25 | AC75: 45901 | AE75: YASH ENTERPRISES | AG75: GST/25-26/135 | AI75: 25-26/PUR/009031 | AN75: 1 | AO75: 54751 | AP75: =AN75*AO75 -> 54751 | AQ75: 0 | AR75: =AP75-AQ75 -> 54751
... B82: Material Cost | C82: FY 2025-26 | D82: =TEXT(E82,"mmm-yy") -> Jun-25 | E82: 45821 | F82: MHPV073 | G82: AUTOCOMP CORPORATION PANSE PRIVATE LIMITED | H82: 6285 | I82: 34.2 | J82: =H82*I82 -> 214947 | K82: 0 | L82: =J82+K82 -> 214947 | N82: MPPUNE/0099 | O82: Warehouse | P82: FY 2025-26 | Q82: 45892 | R82: 27/MPIB/26IN0045 | S82: YASH ENTERPRISES | T82: 2890 | U82: 28 | V82: =U82*T82 -> 80920 | W82: 0 | X82: =V82+W82 -> 80920 | Y82: =_xlfn.XLOOKUP(R82,'Details PC'!AA:AA,'Details PC'!AI:AI)-X82 -> 0 | AA82: FY 2025-26 | AB82: =TEXT(AC82,"mmm-yy") -> Sep-25 | AC82: 45926 | AE82: MOHIT KANAUGIYA | AG82: 46 | AI82: 25-26/PUR/010940 | AN82: 1 | AO82: 58210 | AP82: =AN82*AO82 -> 58210 | AQ82: 0 | AR82: =AP82-AQ82 -> 58210
B83: Processing Cost | C83: FY 2025-26 | D83: =TEXT(E83,"mmm-yy") -> Jun-25 | E83: 45821 | G83: YASH GASES | H83: 19 | I83: 190 | J83: =H83*I83 -> 3610 | K83: 0 | L83: =J83+K83 -> 3610 | N83: MPPUNE/0100 | O83: Warehouse | P83: FY 2025-26 | Q83: 45895 | R83: 27/MPIB/26IN0046 | S83: SAARLOHA ADVANCED MATERIALS PRIVATE LIMITED | T83: 23490 | U83: 33.75 | V83: =U83*T83 -> 792787.5 | W83: 0 | X83: =V83+W83 -> 792787.5 | Y83: =_xlfn.XLOOKUP(R83,'Details PC'!AA:AA,'Details PC'!AI:AI)-X83 -> 0 | AA83: FY 2025-26 | AB83: =TEXT(AC83,"mmm-yy") -> Oct-25 | AC83: 45931 | AE83: Shivshambho Logistics | AG83: 96 | AI83: 25-26/PUR/011615 | AN83: 1 | AO83: 392128.75 | AP83: =AN83*AO83 -> 392128.75 | AQ83: 0 | AR83: =AP83-AQ83 -> 392128.75
B84: Processing Cost | C84: FY 2025-26 | D84: =TEXT(E84,"mmm-yy") -> Jun-25 | E84: 45821 | G84: YASH GASES | H84: 1 | I84: 1850 | J84: =H84*I84 -> 1850 | K84: 0 | L84: =J84+K84 -> 1850 | N84: MPPUNE/0101 | O84: Warehouse | P84: FY 2025-26 | Q84: 45895 | R84: 27/MPIB/26IN0047 | S84: YASH ENTERPRISES | T84: 2870 | U84: 90 | V84: =U84*T84 -> 258300 | W84: 0 | X84: =V84+W84 -> 258300 | Y84: =_xlfn.XLOOKUP(R84,'Details PC'!AA:AA,'Details PC'!AI:AI)-X84 -> 0 | AA84: FY 2025-26 | AB84: =TEXT(AC84,"mmm-yy") -> Oct-25 | AC84: 45931 | AE84: Shivshambho Logistics | AG84: 97 | AI84: 25-26/PUR/011616 | AN84: 1 | AO84: 296282.75 | AP84: =AN84*AO84 -> 296282.75 | AQ84: 0 | AR84: =AP84-AQ84 -> 296282.75
B85: Material Cost | C85: FY 2025-26 | D85: =TEXT(E85,"mmm-yy") -> Jun-25 | E85: 45822 | F85: MHPV074 | G85: AUTOCOMP CORPORATION PANSE PRIVATE LIMITED | H85: 7805 | I85: 34.2 | J85: =H85*I85 -> 266931 | K85: 0 | L85: =J85+K85 -> 266931 | N85: MPPUNE/0102 | O85: Warehouse | P85: FY 2025-26 | Q85: 45896 | R85: 27/MPIB/26IN0048 | S85: SAARLOHA ADVANCED MATERIALS PRIVATE LIMITED | T85: 21510 | U85: 33.75 | V85: =U85*T85 -> 725962.5 | W85: 0 | X85: =V85+W85 -> 725962.5 | Y85: =_xlfn.XLOOKUP(R85,'Details PC'!AA:AA,'Details PC'!AI:AI)-X85 -> 0 | AA85: FY 2025-26 | AB85: =TEXT(AC85,"mmm-yy") -> Oct-25 | AC85: 45943 | AE85: YASH ENTERPRISES | AG85: GST/25-26/205 | AI85: 25-26/PUR/012250 | AN85: 1 | AO85: 286838 | AP85: =AN85*AO85 -> 286838 | AQ85: 0 | AR85: =AP85-AQ85 -> 286838
B86: Material Cost | C86: FY 2025-26 | D86: =TEXT(E86,"mmm-yy") -> Jun-25 | E86: 45823 | F86: MHPV075 | G86: ULTRA CORPOTECH PRIVATE LIMITED | H86: 31700 | I86: 34.3 | J86: =H86*I86 -> 1087310 | K86: 0 | L86: =J86+K86 -> 1087310 | N86: MPPUNE/0103 | O86: Warehouse | P86: FY 2025-26 | Q86: 45906 | R86: 27/MPIB/26IN0049 | S86: SOUND CASTINGS PRIVATE LIMITED | T86: 30730 | U86: 35.9 | V86: =U86*T86 -> 1103207 | W86: -2458 | X86: =V86+W86 -> 1100749 | Y86: =_xlfn.XLOOKUP(R86,'Details PC'!AA:AA,'Details PC'!AI:AI)-X86 -> 0 | AA86: FY 2025-26 | AB86: =TEXT(AC86,"mmm-yy") -> Oct-25 | AC86: 45943 | AE86: MOHIT KANAUGIYA | AG86: 47 | AI86: 25-26/PUR/012264 | AN86: 1 | AO86: 38570 | AP86: =AN86*AO86 -> 38570 | AQ86: 0 | AR86: =AP86-AQ86 -> 38570
