Workbook

Sheet Summary
B1: D
D2: =TEXT(D4, "mmm-yy") -> Apr-26 | E2: =TEXT(E4, "mmm-yy") -> May-26 | F2: =TEXT(F4, "mmm-yy") -> Jun-26 | G2: =TEXT(G4, "mmm-yy") -> Jul-26 | H2: =TEXT(H4, "mmm-yy") -> Aug-26 | I2: =TEXT(I4, "mmm-yy") -> Sep-26 | J2: =TEXT(J4, "mmm-yy") -> Oct-26 | K2: =TEXT(K4, "mmm-yy") -> Nov-26 | ... O2: =TEXT(O4, "mmm-yy") -> Mar-27
D3: 30 | E3: 31 | F3: 30 | G3: 0 | H3: 0 | I3: 0 | J3: 0 | K3: 0 | L3: 0 | M3: 0 | N3: 0 | O3: 0 | P3: =SUM(D3:O3) -> 91
C4: Marketplace (ITAD) | D4: 46113 | E4: 46143 | F4: 46174 | G4: 46204 | H4: 46235 | I4: 46266 | J4: 46296 | K4: 46327 | L4: 46357 | M4: 46388 | N4: 46419 | O4: 46447 | P4: FY 2026-27
C5: Quantity (units) | D5: 6453.55 | E5: 1326 | F5: 3549.26 | G5: =SUMIFS(Details!$BB$4:$BB$160,Details!$C$4:$C$160,Summary!G$4) -> 0 | H5: =SUMIFS(Details!$BB$4:$BB$160,Details!$C$4:$C$160,Summary!H$4) -> 0 | I5: =SUMIFS(Details!$BB$4:$BB$160,Details!$C$4:$C$160,Summary!I$4) -> 0 | J5: =SUMIFS(Details!$BB$4:$BB$160,Details!$C$4:$C$160,Summary!J$4) -> 0 | K5: =SUMIFS(Details!$BB$4:$BB$160,Details!$C$4:$C$160,Summary!K$4) -> 0 | L5: =SUMIFS(Details!$BB$4:$BB$160,Details!$C$4:$C$160,Summary!L$4) -> 0 | M5: =SUMIFS(Details!$BB$4:$BB$160,Details!$C$4:$C$160,Summary!M$4) -> 0 | N5: =SUMIFS(Details!$BB$4:$BB$160,Details!$C$4:$C$160,Summary!N$4) -> 0 | O5: =SUMIFS(Details!$BB$4:$BB$160,Details!$C$4:$C$160,Summary!O$4) -> 0 | P5: =SUM(D5:O5) -> 11328.81 | Q5: =Details!BB161 -> 11328.81 | R5: =P5-Q5 -> 0
C6: Sales | D6: 2227828.8 | E6: 1333242.9 | F6: 3099918.1 | G6: =SUMIFS(Details!$BO$4:$BO$160,Details!$C$4:$C$160,Summary!G$4) -> 0 | H6: =SUMIFS(Details!$BO$4:$BO$160,Details!$C$4:$C$160,Summary!H$4) -> 0 | I6: =SUMIFS(Details!$BO$4:$BO$160,Details!$C$4:$C$160,Summary!I$4) -> 0 | J6: =SUMIFS(Details!$BO$4:$BO$160,Details!$C$4:$C$160,Summary!J$4) -> 0 | K6: =SUMIFS(Details!$BO$4:$BO$160,Details!$C$4:$C$160,Summary!K$4) -> 0 | L6: =SUMIFS(Details!$BO$4:$BO$160,Details!$C$4:$C$160,Summary!L$4) -> 0 | M6: =SUMIFS(Details!$BO$4:$BO$160,Details!$C$4:$C$160,Summary!M$4) -> 0 | N6: =SUMIFS(Details!$BO$4:$BO$160,Details!$C$4:$C$160,Summary!N$4) -> 0 | O6: =SUMIFS(Details!$BO$4:$BO$160,Details!$C$4:$C$160,Summary!O$4) -> 0 | P6: =SUM(D6:O6) -> 6660989.7 | Q6: =Details!BO161 -> 6660989.7 | R6: =P6-Q6+P74 -> 0
C7: Purchases | D7: 1570805.1 | E7: 1206184 | F7: 2827776.9 | G7: =SUMIFS(Details!$AM$4:$AM$160,Details!$C$4:$C$160,Summary!G$4)-SUMIFS(Details!$AB$4:$AB$160,Details!$C$4:$C$160,Summary!G$4) -> 0 | H7: =SUMIFS(Details!$AM$4:$AM$160,Details!$C$4:$C$160,Summary!H$4)-SUMIFS(Details!$AB$4:$AB$160,Details!$C$4:$C$160,Summary!H$4) -> 0 | I7: =SUMIFS(Details!$AM$4:$AM$160,Details!$C$4:$C$160,Summary!I$4)-SUMIFS(Details!$AB$4:$AB$160,Details!$C$4:$C$160,Summary!I$4) -> 0 | J7: =SUMIFS(Details!$AM$4:$AM$160,Details!$C$4:$C$160,Summary!J$4)-SUMIFS(Details!$AB$4:$AB$160,Details!$C$4:$C$160,Summary!J$4) -> 0 | K7: =SUMIFS(Details!$AM$4:$AM$160,Details!$C$4:$C$160,Summary!K$4)-SUMIFS(Details!$AB$4:$AB$160,Details!$C$4:$C$160,Summary!K$4) -> 0 | L7: =SUMIFS(Details!$AM$4:$AM$160,Details!$C$4:$C$160,Summary!L$4)-SUMIFS(Details!$AB$4:$AB$160,Details!$C$4:$C$160,Summary!L$4) -> 0 | M7: =SUMIFS(Details!$AM$4:$AM$160,Details!$C$4:$C$160,Summary!M$4)-SUMIFS(Details!$AB$4:$AB$160,Details!$C$4:$C$160,Summary!M$4) -> 0 | N7: =SUMIFS(Details!$AM$4:$AM$160,Details!$C$4:$C$160,Summary!N$4)-SUMIFS(Details!$AB$4:$AB$160,Details!$C$4:$C$160,Summary!N$4) -> 0 | O7: =SUMIFS(Details!$AM$4:$AM$160,Details!$C$4:$C$160,Summary!O$4)-SUMIFS(Details!$AB$4:$AB$160,Details!$C$4:$C$160,Summary!O$4) -> 0 | P7: =SUM(D7:O7) -> 5604766 | Q7: =Details!P162 -> 5604766 | R7: =P7-Q7 -> 0
C8: Gross Margin | D8: =D6-D7 -> 657023.68 | E8: =E6-E7 -> 127058.89 | F8: =F6-F7 -> 272141.13 | G8: =G6-G7 -> 0 | H8: =H6-H7 -> 0 | I8: =I6-I7 -> 0 | J8: =J6-J7 -> 0 | K8: =K6-K7 -> 0 | ... O8: =O6-O7 -> 0 | P8: =SUM(D8:O8) -> 1056223.7
C9: Gross Margin (%) | D9: =IFERROR((D8/D6),0) -> 0.2949166 | E9: =IFERROR((E8/E6),0) -> 0.095300631 | F9: =IFERROR((F8/F6),0) -> 0.087789782 | G9: =IFERROR((G8/G6),0) -> 0 | H9: =IFERROR((H8/H6),0) -> 0 | I9: =IFERROR((I8/I6),0) -> 0 | J9: =IFERROR((J8/J6),0) -> 0 | K9: =IFERROR((K8/K6),0) -> 0 | ... P9: =IFERROR((P8/P6),0) -> 0.15856858
C10: Transportation Charges | D10: =SUMIFS(Details!$AB$4:$AB$160,Details!$C$4:$C$160,Summary!D$4) -> 0 | E10: =SUMIFS(Details!$AB$4:$AB$160,Details!$C$4:$C$160,Summary!E$4) -> 0 | F10: =SUMIFS(Details!$AB$4:$AB$160,Details!$C$4:$C$160,Summary!F$4) -> 0 | G10: =SUMIFS(Details!$AB$4:$AB$160,Details!$C$4:$C$160,Summary!G$4) -> 0 | H10: =SUMIFS(Details!$AB$4:$AB$160,Details!$C$4:$C$160,Summary!H$4) -> 0 | I10: =SUMIFS(Details!$AB$4:$AB$160,Details!$C$4:$C$160,Summary!I$4) -> 0 | J10: =SUMIFS(Details!$AB$4:$AB$160,Details!$C$4:$C$160,Summary!J$4) -> 0 | K10: =SUMIFS(Details!$AB$4:$AB$160,Details!$C$4:$C$160,Summary!K$4) -> 0 | ... O10: =SUMIFS(Details!$AB$4:$AB$160,Details!$C$4:$C$160,Summary!O$4) -> 0 | P10: =SUM(D10:O10) -> 0 | Q10: =Details!AB161 -> 0 | R10: =P10-Q10 -> 0
C11: Operational Cost | D11: =SUMIFS(Details!$AC$4:$AC$160,Details!$C$4:$C$160,Summary!D$4) -> 0 | E11: =SUMIFS(Details!$AC$4:$AC$160,Details!$C$4:$C$160,Summary!E$4) -> 0 | F11: =SUMIFS(Details!$AC$4:$AC$160,Details!$C$4:$C$160,Summary!F$4) -> 0 | G11: =SUMIFS(Details!$AC$4:$AC$160,Details!$C$4:$C$160,Summary!G$4) -> 0 | H11: =SUMIFS(Details!$AC$4:$AC$160,Details!$C$4:$C$160,Summary!H$4) -> 0 | I11: =SUMIFS(Details!$AC$4:$AC$160,Details!$C$4:$C$160,Summary!I$4) -> 0 | J11: =SUMIFS(Details!$AC$4:$AC$160,Details!$C$4:$C$160,Summary!J$4) -> 0 | K11: =SUMIFS(Details!$AC$4:$AC$160,Details!$C$4:$C$160,Summary!K$4) -> 0 | ... O11: =SUMIFS(Details!$AC$4:$AC$160,Details!$C$4:$C$160,Summary!O$4) -> 0 | P11: =SUM(D11:O11) -> 0
C12: Net Margin | D12: =D6-D7-D10-D11 -> 657023.68 | E12: =E6-E7-E10-E11 -> 127058.89 | F12: =F6-F7-F10-F11 -> 272141.13 | G12: =G6-G7-G10-G11 -> 0 | H12: =H6-H7-H10-H11 -> 0 | I12: =I6-I7-I10-I11 -> 0 | J12: =J6-J7-J10-J11 -> 0 | K12: =K6-K7-K10-K11 -> 0 | ... O12: =O6-O7-O10-O11 -> 0 | P12: =SUM(D12:O12) -> 1056223.7
C13: Net Margin (%) | D13: =IFERROR((D12/D6),0) -> 0.2949166 | E13: =IFERROR((E12/E6),0) -> 0.095300631 | F13: =IFERROR((F12/F6),0) -> 0.087789782 | G13: =IFERROR((G12/G6),0) -> 0 | H13: =IFERROR((H12/H6),0) -> 0 | I13: =IFERROR((I12/I6),0) -> 0 | J13: =IFERROR((J12/J6),0) -> 0 | K13: =IFERROR((K12/K6),0) -> 0 | ... P13: =IFERROR((P12/P6),0) -> 0.15856858
C14: Other Income | D14: 0 | E14: 0 | F14: 0 | G14: 0 | H14: 0 | I14: 0 | J14: 0 | K14: 0 | L14: 0 | M14: 0 | N14: 0 | O14: 0 | P14: =SUM(D14:O14) -> 0
C15: Transport Charges (%) | D15: =IFERROR((D10/D6),0) -> 0 | E15: =IFERROR((E10/E6),0) -> 0 | F15: =IFERROR((F10/F6),0) -> 0 | G15: =IFERROR((G10/G6),0) -> 0 | H15: =IFERROR((H10/H6),0) -> 0 | I15: =IFERROR((I10/I6),0) -> 0 | J15: =IFERROR((J10/J6),0) -> 0 | K15: =IFERROR((K10/K6),0) -> 0 | ... P15: =IFERROR((P10/P6),0) -> 0
C16: Revenue Per unit | D16: =IFERROR(D6/(D5*1000),0) -> 0.34520981 | E16: =IFERROR(E6/(E5*1000),0) -> 1.0054622 | F16: =IFERROR(F6/(F5*1000),0) -> 0.87339842 | G16: =IFERROR(G6/(G5*1000),0) -> 0 | H16: =IFERROR(H6/(H5*1000),0) -> 0 | I16: =IFERROR(I6/(I5*1000),0) -> 0 | J16: =IFERROR(J6/(J5*1000),0) -> 0 | K16: =IFERROR(K6/(K5*1000),0) -> 0 | ... O16: =IFERROR(O6/(O5*1000),0) -> 0 | P16: =+P6/(P5*1000) -> 0.58796906
C17: Purchase Cost Per unit | D17: =IFERROR(D7/(D5*1000),0) -> 0.24340171 | E17: =IFERROR(E7/(E5*1000),0) -> 0.90964104 | F17: =IFERROR(F7/(F5*1000),0) -> 0.79672296 | G17: =IFERROR(G7/(G5*1000),0) -> 0 | H17: =IFERROR(H7/(H5*1000),0) -> 0 | I17: =IFERROR(I7/(I5*1000),0) -> 0 | J17: =IFERROR(J7/(J5*1000),0) -> 0 | K17: =IFERROR(K7/(K5*1000),0) -> 0 | ... O17: =IFERROR(O7/(O5*1000),0) -> 0 | P17: =+P7/(P5*1000) -> 0.49473564
C18: Transportation Charges Per unit | D18: =IFERROR(D10/(D5*1000),0) -> 0 | E18: =IFERROR(E10/(E5*1000),0) -> 0 | F18: =IFERROR(F10/(F5*1000),0) -> 0 | G18: =IFERROR(G10/(G5*1000),0) -> 0 | H18: =IFERROR(H10/(H5*1000),0) -> 0 | I18: =IFERROR(I10/(I5*1000),0) -> 0 | J18: =IFERROR(J10/(J5*1000),0) -> 0 | K18: =IFERROR(K10/(K5*1000),0) -> 0 | ... O18: =IFERROR(O10/(O5*1000),0) -> 0 | P18: =P10/(P5*1000) -> 0
C19: No. of Transactions | D19: {=IFERROR(ROWS(_xlfn.UNIQUE(_xlfn._xlws.FILTER(Details!$AO$5:$AO$160, (Details!$C$5:$C$160)=Summary!D$2))),0)} -> 17 | E19: {=IFERROR(ROWS(_xlfn.UNIQUE(_xlfn._xlws.FILTER(Details!$AO$5:$AO$160, (Details!$C$5:$C$160)=Summary!E$2))),0)} -> 9 | F19: {=IFERROR(ROWS(_xlfn.UNIQUE(_xlfn._xlws.FILTER(Details!$AO$5:$AO$160, (Details!$C$5:$C$160)=Summary!F$2))),0)} -> 14 | G19: {=IFERROR(ROWS(_xlfn.UNIQUE(_xlfn._xlws.FILTER(Details!$AO$5:$AO$160, (Details!$C$5:$C$160)=Summary!G$2))),0)} -> 0 | H19: {=IFERROR(ROWS(_xlfn.UNIQUE(_xlfn._xlws.FILTER(Details!$AO$5:$AO$160, (Details!$C$5:$C$160)=Summary!H$2))),0)} -> 0 | I19: {=IFERROR(ROWS(_xlfn.UNIQUE(_xlfn._xlws.FILTER(Details!$AO$5:$AO$160, (Details!$C$5:$C$160)=Summary!I$2))),0)} -> 0 | J19: {=IFERROR(ROWS(_xlfn.UNIQUE(_xlfn._xlws.FILTER(Details!$AO$5:$AO$160, (Details!$C$5:$C$160)=Summary!J$2))),0)} -> 0 | K19: {=IFERROR(ROWS(_xlfn.UNIQUE(_xlfn._xlws.FILTER(Details!$AO$5:$AO$160, (Details!$C$5:$C$160)=Summary!K$2))),0)} -> 0 | ... O19: {=IFERROR(ROWS(_xlfn.UNIQUE(_xlfn._xlws.FILTER(Details!$AO$5:$AO$160, (Details!$C$5:$C$160)=Summary!O$2))),0)} -> 0 | P19: =SUM(D19:O19) -> 40
C20: No. of Sellers (Aggregators) | D20: {=IFERROR(ROWS(_xlfn.UNIQUE(_xlfn._xlws.FILTER(MID(Details!$G$5:$G$160,3,10), (Details!$C$5:$C$160)=Summary!D$2))),0)} -> 10 | E20: {=IFERROR(ROWS(_xlfn.UNIQUE(_xlfn._xlws.FILTER(MID(Details!$G$5:$G$160,3,10), (Details!$C$5:$C$160)=Summary!E$2))),0)-1} -> 5 | F20: {=IFERROR(ROWS(_xlfn.UNIQUE(_xlfn._xlws.FILTER(MID(Details!$G$5:$G$160,3,10), (Details!$C$5:$C$160)=Summary!F$2))),0)-1} -> 9 | G20: {=IFERROR(ROWS(_xlfn.UNIQUE(_xlfn._xlws.FILTER(MID(Details!$G$5:$G$160,3,10), (Details!$C$5:$C$160)=Summary!G$2))),0)} -> 0 | H20: {=IFERROR(ROWS(_xlfn.UNIQUE(_xlfn._xlws.FILTER(MID(Details!$G$5:$G$160,3,10), (Details!$C$5:$C$160)=Summary!H$2))),0)} -> 0 | I20: {=IFERROR(ROWS(_xlfn.UNIQUE(_xlfn._xlws.FILTER(MID(Details!$G$5:$G$160,3,10), (Details!$C$5:$C$160)=Summary!I$2))),0)} -> 0 | J20: {=IFERROR(ROWS(_xlfn.UNIQUE(_xlfn._xlws.FILTER(MID(Details!$G$5:$G$160,3,10), (Details!$C$5:$C$160)=Summary!J$2))),0)} -> 0 | K20: {=IFERROR(ROWS(_xlfn.UNIQUE(_xlfn._xlws.FILTER(MID(Details!$G$5:$G$160,3,10), (Details!$C$5:$C$160)=Summary!K$2))),0)} -> 0 | L20: {=IFERROR(ROWS(_xlfn.UNIQUE(_xlfn._xlws.FILTER(MID(Details!$G$5:$G$160,3,10), (Details!$C$5:$C$160)=Summary!L$2))),0)} -> 0 | M20: {=IFERROR(ROWS(_xlfn.UNIQUE(_xlfn._xlws.FILTER(MID(Details!$G$5:$G$160,3,10), (Details!$C$5:$C$160)=Summary!M$2))),0)} -> 0 | N20: {=IFERROR(ROWS(_xlfn.UNIQUE(_xlfn._xlws.FILTER(MID(Details!$G$5:$G$160,3,10), (Details!$C$5:$C$160)=Summary!N$2))),0)} -> 0 | O20: {=IFERROR(ROWS(_xlfn.UNIQUE(_xlfn._xlws.FILTER(MID(Details!$G$5:$G$160,3,10), (Details!$C$5:$C$160)=Summary!O$2))),0)} -> 0 | P20: ='Supplier Metrics'!E2 -> 22
C21: No. of Buyers (Recyclers) | D21: {=IFERROR(ROWS(_xlfn.UNIQUE(_xlfn._xlws.FILTER(MID(Details!$AR$5:$AR$160,3,10), (Details!$C$5:$C$160)=Summary!D$2))),0)} -> 7 | E21: {=IFERROR(ROWS(_xlfn.UNIQUE(_xlfn._xlws.FILTER(MID(Details!$AR$5:$AR$160,3,10), (Details!$C$5:$C$160)=Summary!E$2))),0)} -> 4 | F21: {=IFERROR(ROWS(_xlfn.UNIQUE(_xlfn._xlws.FILTER(MID(Details!$AR$5:$AR$160,3,10), (Details!$C$5:$C$160)=Summary!F$2))),0)} -> 9 | G21: {=IFERROR(ROWS(_xlfn.UNIQUE(_xlfn._xlws.FILTER(MID(Details!$AR$5:$AR$160,3,10), (Details!$C$5:$C$160)=Summary!G$2))),0)} -> 0 | H21: {=IFERROR(ROWS(_xlfn.UNIQUE(_xlfn._xlws.FILTER(MID(Details!$AR$5:$AR$160,3,10), (Details!$C$5:$C$160)=Summary!H$2))),0)} -> 0 | I21: {=IFERROR(ROWS(_xlfn.UNIQUE(_xlfn._xlws.FILTER(MID(Details!$AR$5:$AR$160,3,10), (Details!$C$5:$C$160)=Summary!I$2))),0)} -> 0 | J21: {=IFERROR(ROWS(_xlfn.UNIQUE(_xlfn._xlws.FILTER(MID(Details!$AR$5:$AR$160,3,10), (Details!$C$5:$C$160)=Summary!J$2))),0)} -> 0 | K21: {=IFERROR(ROWS(_xlfn.UNIQUE(_xlfn._xlws.FILTER(MID(Details!$AR$5:$AR$160,3,10), (Details!$C$5:$C$160)=Summary!K$2))),0)} -> 0 | ... O21: {=IFERROR(ROWS(_xlfn.UNIQUE(_xlfn._xlws.FILTER(MID(Details!$AR$5:$AR$160,3,10), (Details!$C$5:$C$160)=Summary!O$2))),0)} -> 0 | P21: ='Buyer Metrics'!C3 -> 14
C22: Full Rejection | D22: {=IFERROR(ROWS(_xlfn.UNIQUE(_xlfn._xlws.FILTER(Details!$E$5:$E$160,(Details!$C$5:$C$160=Summary!D$2)*(Details!$BR$5:$BR$160=Summary!$C$22)))),0)} -> 0 | E22: {=IFERROR(ROWS(_xlfn.UNIQUE(_xlfn._xlws.FILTER(Details!$E$5:$E$160,(Details!$C$5:$C$160=Summary!E$2)*(Details!$BR$5:$BR$160=Summary!$C$22)))),0)} -> 0 | F22: {=IFERROR(ROWS(_xlfn.UNIQUE(_xlfn._xlws.FILTER(Details!$E$5:$E$160,(Details!$C$5:$C$160=Summary!F$2)*(Details!$BR$5:$BR$160=Summary!$C$22)))),0)} -> 0 | G22: {=IFERROR(ROWS(_xlfn.UNIQUE(_xlfn._xlws.FILTER(Details!$E$5:$E$160,(Details!$C$5:$C$160=Summary!G$2)*(Details!$BR$5:$BR$160=Summary!$C$22)))),0)} -> 0 | H22: {=IFERROR(ROWS(_xlfn.UNIQUE(_xlfn._xlws.FILTER(Details!$E$5:$E$160,(Details!$C$5:$C$160=Summary!H$2)*(Details!$BR$5:$BR$160=Summary!$C$22)))),0)} -> 0 | I22: {=IFERROR(ROWS(_xlfn.UNIQUE(_xlfn._xlws.FILTER(Details!$E$5:$E$160,(Details!$C$5:$C$160=Summary!I$2)*(Details!$BR$5:$BR$160=Summary!$C$22)))),0)} -> 0 | J22: {=IFERROR(ROWS(_xlfn.UNIQUE(_xlfn._xlws.FILTER(Details!$E$5:$E$160,(Details!$C$5:$C$160=Summary!J$2)*(Details!$BR$5:$BR$160=Summary!$C$22)))),0)} -> 0 | K22: {=IFERROR(ROWS(_xlfn.UNIQUE(_xlfn._xlws.FILTER(Details!$E$5:$E$160,(Details!$C$5:$C$160=Summary!K$2)*(Details!$BR$5:$BR$160=Summary!$C$22)))),0)} -> 0 | ... O22: {=IFERROR(ROWS(_xlfn.UNIQUE(_xlfn._xlws.FILTER(Details!$E$5:$E$160,(Details!$C$5:$C$160=Summary!O$2)*(Details!$BR$5:$BR$160=Summary!$C$22)))),0)} -> 0 | P22: =SUM(D22:O22) -> 0
C23: Receivable | D23: 1423815.6 | E23: 1121048.3 | F23: 1389959.4 | G23: 0 | H23: 0 | I23: 0 | J23: 0 | K23: 0 | L23: 0 | M23: 0 | N23: 0 | O23: 0 | P23: =F23 -> 1389959.4
C24: DSO (Days) | D24: =IFERROR(((D23/(D6*1.18))*D3),0) -> 16.248422 | E24: =IFERROR(((E23/(E6*1.18))*E3),0) -> 22.089949 | F24: =IFERROR(((F23/(F6*1.18))*F3),0) -> 11.399641 | G24: =IFERROR(((G23/(G6*1.18))*G3),0) -> 0 | H24: =IFERROR(((H23/(H6*1.18))*H3),0) -> 0 | I24: =IFERROR(((I23/(I6*1.18))*I3),0) -> 0 | J24: =IFERROR(((J23/(J6*1.18))*J3),0) -> 0 | K24: =IFERROR(((K23/(K6*1.18))*K3),0) -> 0 | ... O24: =IFERROR(((O23/(O6*1.18))*O3),0) -> 0 | P24: =IFERROR(((P23)/(P6*1.18)*P3),0) -> 16.092471
C25: Payable | D25: 665050.13 | E25: 1299425.5 | F25: 1730327.6 | G25: 0 | H25: 0 | I25: 0 | J25: 0 | K25: 0 | L25: 0 | M25: 0 | N25: 0 | O25: 0 | P25: =F25 -> 1730327.6
C26: DPO (Days) | D26: =IFERROR(((D25/(D7*1.18))*D3),0) -> 10.763942 | E26: =IFERROR(((E25/(E7*1.18))*E3),0) -> 28.302025 | F26: =IFERROR(((F25/(F7*1.18))*F3),0) -> 15.556878 | G26: =IFERROR(((G25/(G7*1.18))*G3),0) -> 0 | H26: =IFERROR(((H25/(H7*1.18))*H3),0) -> 0 | I26: =IFERROR(((I25/(I7*1.18))*I3),0) -> 0 | J26: =IFERROR(((J25/(J7*1.18))*J3),0) -> 0 | K26: =IFERROR(((K25/(K7*1.18))*K3),0) -> 0 | ... P26: =IFERROR(((P25/(P7*1.18))*P3),0) -> 23.808402
C27: Working Capital Days | D27: =D24-D26 -> 5.4844803 | E27: =E24-E26 -> -6.2120757 | F27: =F24-F26 -> -4.1572375 | G27: =G24-G26 -> 0 | H27: =H24-H26 -> 0 | I27: =I24-I26 -> 0 | J27: =J24-J26 -> 0 | K27: =K24-K26 -> 0 | ... P27: =P24-P26 -> -7.7159305
C28: Credit Notes (Value - Incl. Prov) | D28: 0 | E28: =-SUMIFS(Details!$BW$4:$BW$160,Details!$C$4:$C$160,Summary!E4) -> 0 | F28: =-SUMIFS(Details!$BW$4:$BW$160,Details!$C$4:$C$160,Summary!F4) -> 0 | G28: =-SUMIFS(Details!$BW$4:$BW$160,Details!$C$4:$C$160,Summary!G4) -> 0 | H28: =-SUMIFS(Details!$BW$4:$BW$160,Details!$C$4:$C$160,Summary!H4) -> 0 | I28: =-SUMIFS(Details!$BW$4:$BW$160,Details!$C$4:$C$160,Summary!I4) -> 0 | J28: =-SUMIFS(Details!$BW$4:$BW$160,Details!$C$4:$C$160,Summary!J4) -> 0 | K28: =-SUMIFS(Details!$BW$4:$BW$160,Details!$C$4:$C$160,Summary!K4) -> 0 | L28: =-SUMIFS(Details!$BW$4:$BW$160,Details!$C$4:$C$160,Summary!L4) -> 0 | ... O28: =-SUMIFS(Details!$BW$4:$BW$160,Details!$C$4:$C$160,Summary!O4) -> 0 | P28: =SUM(D28:O28) -> 0 | Q28: =(-Details!BM161-Details!BN161) -> 0 | R28: =P28-Q28 -> 0
C29: Credit Notes (% to Revenue) | D29: =IFERROR((D28/D6),0) -> 0 | E29: =IFERROR((E28/E6),0) -> 0 | F29: =IFERROR((F28/F6),0) -> 0 | G29: =IFERROR((G28/G6),0) -> 0 | H29: =IFERROR((H28/H6),0) -> 0 | I29: =IFERROR((I28/I6),0) -> 0 | J29: =IFERROR((J28/J6),0) -> 0 | K29: =IFERROR((K28/K6),0) -> 0 | ... O29: =IFERROR((O28/O6),0) -> 0 | P29: =+P28/P6 -> 0
C30: Debit Notes (Value - Incl. Prov) | D30: 0 | E30: =-SUMIFS(Details!$BX$4:$BX$160,Details!$C$4:$C$160,Summary!E4) -> 0 | F30: =-SUMIFS(Details!$BX$4:$BX$160,Details!$C$4:$C$160,Summary!F4) -> 0 | G30: =-SUMIFS(Details!$BX$4:$BX$160,Details!$C$4:$C$160,Summary!G4) -> 0 | H30: =-SUMIFS(Details!$BX$4:$BX$160,Details!$C$4:$C$160,Summary!H4) -> 0 | I30: =-SUMIFS(Details!$BX$4:$BX$160,Details!$C$4:$C$160,Summary!I4) -> 0 | J30: =-SUMIFS(Details!$BX$4:$BX$160,Details!$C$4:$C$160,Summary!J4) -> 0 | K30: =-SUMIFS(Details!$BX$4:$BX$160,Details!$C$4:$C$160,Summary!K4) -> 0 | L30: =-SUMIFS(Details!$BX$4:$BX$160,Details!$C$4:$C$160,Summary!L4) -> 0 | ... O30: =-SUMIFS(Details!$BX$4:$BX$160,Details!$C$4:$C$160,Summary!O4) -> 0 | P30: =SUM(D30:O30) -> 0 | Q30: =(-Details!AK161-Details!AL161) -> 0 | R30: =P30-Q30 -> 0
C31: Debit Notes (% to Purchase) | D31: =IFERROR((D30/D7),0) -> 0 | E31: =IFERROR((E30/E7),0) -> 0 | F31: =IFERROR((F30/F7),0) -> 0 | G31: =IFERROR((G30/G7),0) -> 0 | H31: =IFERROR((H30/H7),0) -> 0 | I31: =IFERROR((I30/I7),0) -> 0 | J31: =IFERROR((J30/J7),0) -> 0 | K31: =IFERROR((K30/K7),0) -> 0 | ... O31: =IFERROR((O30/O7),0) -> 0 | P31: =(P30/(P7+P10)) -> 0
C33: KPI's without Provisions | D33: =D4 -> 46113 | E33: =E4 -> 46143 | F33: =F4 -> 46174 | G33: =G4 -> 46204 | H33: =H4 -> 46235 | I33: =I4 -> 46266 | J33: =J4 -> 46296 | K33: =K4 -> 46327 | ... P33: =P4 -> FY 2026-27
C34: Sales without Provision | D34: =D6-D53 -> 2227828.8 | E34: =E6+E53 -> 1333242.9 | F34: =F6+F53 -> 3099918.1 | G34: =G6+G53 -> 0 | H34: =H6+H53 -> 0 | I34: =I6+I53 -> 0 | J34: =J6+J53 -> 0 | K34: =K6+K53 -> 0 | L34: =L6+L53 -> 0 | ... O34: =O6+O53 -> 0 | P34: =SUM(D34:O34) -> 6660989.7
C35: Purchases without Provision | D35: =D7+D10-D52 -> 1570805.1 | E35: =E7+E10+E52 -> 1206184 | F35: =F7+F10+F52 -> 2827776.9 | G35: =G7+G10+G52 -> 0 | H35: =H7+H10+H52 -> 0 | I35: =I7+I10+I52 -> 0 | J35: =J7+J10+J52 -> 0 | K35: =K7+K10+K52 -> 0 | L35: =L7+L10+L52 -> 0 | ... O35: =O7+O10+O52 -> 0 | P35: =SUM(D35:O35) -> 5604766
C36: Contribution without Provision | D36: =D34-D35 -> 657023.68 | E36: =E34-E35 -> 127058.89 | F36: =F34-F35 -> 272141.13 | G36: =G34-G35 -> 0 | H36: =H34-H35 -> 0 | I36: =I34-I35 -> 0 | J36: =J34-J35 -> 0 | K36: =K34-K35 -> 0 | ... P36: =P34-P35 -> 1056223.7
C37: Contribution (%) | D37: =D36/D34 -> 0.2949166 | E37: =E36/E34 -> 0.095300631 | F37: =F36/F34 -> 0.087789782 | G37: =G36/G34 -> #DIV/0! | H37: =H36/H34 -> #DIV/0! | I37: =I36/I34 -> #DIV/0! | J37: =J36/J34 -> #DIV/0! | K37: =K36/K34 -> #DIV/0! | ... P37: =P36/P34 -> 0.15856858
C39: Business Trends | D39: =D4 -> 46113 | E39: =E4 -> 46143 | F39: =F4 -> 46174 | G39: =G4 -> 46204 | H39: =H4 -> 46235 | I39: =I4 -> 46266 | J39: =J4 -> 46296 | K39: =K4 -> 46327 | ... P39: =P4 -> FY 2026-27
C40: Sales-Revenue (MoM) | D40: =IFERROR(((D6/C6)-1),0) -> 0 | E40: =IFERROR(((E6/D6)-1),0) -> -0.40155055 | F40: =IFERROR(((F6/E6)-1),0) -> 1.3250962 | G40: =IFERROR(((G6/F6)-1),0) -> -1 | H40: =IFERROR(((H6/G6)-1),0) -> 0 | I40: =IFERROR(((I6/H6)-1),0) -> 0 | J40: =IFERROR(((J6/I6)-1),0) -> 0 | K40: =IFERROR(((K6/J6)-1),0) -> 0 | ... O40: =IFERROR(((O6/N6)-1),0) -> 0 | P40: 0
C41: Sales-Volume (MoM) | D41: =IFERROR(((D5/C5)-1),0) -> 0 | E41: =IFERROR(((E5/D5)-1),0) -> -0.79453169 | F41: =IFERROR(((F5/E5)-1),0) -> 1.6766667 | G41: =IFERROR(((G5/F5)-1),0) -> -1 | H41: =IFERROR(((H5/G5)-1),0) -> 0 | I41: =IFERROR(((I5/H5)-1),0) -> 0 | J41: =IFERROR(((J5/I5)-1),0) -> 0 | K41: =IFERROR(((K5/J5)-1),0) -> 0 | ... O41: =IFERROR(((O5/N5)-1),0) -> 0 | P41: 0
C42: Sales-Transactions (MoM) | D42: =IFERROR(((D19/C19)-1),0) -> 0 | E42: =IFERROR(((E19/D19)-1),0) -> -0.47058824 | F42: =IFERROR(((F19/E19)-1),0) -> 0.55555556 | G42: =IFERROR(((G19/F19)-1),0) -> -1 | H42: =IFERROR(((#REF!/G19)-1),0) -> 0 | I42: =IFERROR(((I19/#REF!)-1),0) -> 0 | J42: =IFERROR(((J19/I19)-1),0) -> 0 | K42: =IFERROR(((K19/J19)-1),0) -> 0 | L42: =IFERROR(((L19/K19)-1),0) -> 0 | M42: =IFERROR(((M19/L19)-1),0) -> 0 | N42: =IFERROR(((N19/M19)-1),0) -> 0 | O42: =IFERROR(((O19/N19)-1),0) -> 0 | P42: 0
C44: Loss Making Transactions | D44: =D39 -> 46113 | E44: =E39 -> 46143 | F44: =F39 -> 46174 | G44: =G39 -> 46204 | H44: =H39 -> 46235 | I44: =I39 -> 46266 | J44: =J39 -> 46296 | K44: =K39 -> 46327 | ... P44: =P39 -> FY 2026-27
C45: No of LMT @ Inception | D45: 0 | E45: 1 | F45: 0 | G45: 0 | H45: 0 | I45: 0 | J45: 0 | K45: 0 | L45: 0 | M45: 0 | N45: 0 | O45: 0 | P45: =SUM(D45:O45) -> 1
C46: Value of LMT @ Inception | D46: 0 | E46: -331839 | F46: 0 | G46: -36291 | H46: 0 | I46: 0 | J46: 0 | K46: 0 | L46: 0 | M46: 0 | N46: 0 | O46: 0 | P46: =SUM(D46:O46) -> -368130
C47: No of LMT | D47: 0 | E47: 1 | F47: 0 | G47: 0 | H47: 0 | I47: 0 | J47: 0 | K47: 0 | L47: 0 | M47: 0 | N47: 0 | O47: 0 | P47: =SUM(D47:O47) -> 1
C48: % of LMT | D48: =IFERROR(D47/D19,0) -> 0 | E48: =IFERROR(E47/E19,0) -> 0.11111111 | F48: =IFERROR(F47/F19,0) -> 0 | G48: =IFERROR(G47/G19,0) -> 0 | H48: =IFERROR(H47/#REF!,0) -> 0 | I48: =IFERROR(I47/I19,0) -> 0 | J48: =IFERROR(J47/J19,0) -> 0 | K48: =IFERROR(K47/K19,0) -> 0 | L48: =IFERROR(L47/L19,0) -> 0 | M48: =IFERROR(M47/M19,0) -> 0 | N48: =IFERROR(N47/N19,0) -> 0 | O48: =IFERROR(O47/O19,0) -> 0 | P48: =IFERROR(P47/P19,0) -> 0.025
C49: Value of LMT | D49: 0 | E49: -331839 | F49: 0 | G49: -36291 | H49: 0 | I49: 0 | J49: 0 | K49: 0 | L49: 0 | M49: 0 | N49: 0 | O49: 0 | P49: =SUM(D49:O49) -> -368130
C51: CN & DN Provisions | D51: =D44 -> 46113 | E51: =E44 -> 46143 | F51: =F44 -> 46174 | G51: =G44 -> 46204 | H51: =H44 -> 46235 | I51: =I44 -> 46266 | J51: =J44 -> 46296 | K51: =K44 -> 46327 | ... P51: =P44 -> FY 2026-27 | Q51: =ROUND(Q52-Q53,2)+ROUND(P36-P12,2) -> 0
C52: DN Provision | D52: =-SUMIFS(Details!$AL$4:$AL$160,Details!$C$4:$C$160,Summary!D51) -> 0 | E52: =-SUMIFS(Details!$AL$4:$AL$160,Details!$C$4:$C$160,Summary!E51) -> 0 | F52: =-SUMIFS(Details!$AL$4:$AL$160,Details!$C$4:$C$160,Summary!F51) -> 0 | G52: =-SUMIFS(Details!$AL$4:$AL$160,Details!$C$4:$C$160,Summary!G51) -> 0 | H52: =-SUMIFS(Details!$AL$4:$AL$160,Details!$C$4:$C$160,Summary!H51) -> 0 | I52: =-SUMIFS(Details!$AL$4:$AL$160,Details!$C$4:$C$160,Summary!I51) -> 0 | J52: =-SUMIFS(Details!$AL$4:$AL$160,Details!$C$4:$C$160,Summary!J51) -> 0 | K52: =-SUMIFS(Details!$AL$4:$AL$160,Details!$C$4:$C$160,Summary!K51) -> 0 | ... O52: =-SUMIFS(Details!$AL$4:$AL$160,Details!$C$4:$C$160,Summary!O51) -> 0 | P52: =SUM(D52:O52) -> 0 | Q52: =Details!AL161 -> 0 | R52: =Q52+P52 -> 0
C53: CN Provision | D53: =-SUMIFS(Details!$BN$4:$BN$160,Details!$C$4:$C$160,Summary!D51) -> 0 | E53: =-SUMIFS(Details!$BN$4:$BN$160,Details!$C$4:$C$160,Summary!E51) -> 0 | F53: =-SUMIFS(Details!$BN$4:$BN$160,Details!$C$4:$C$160,Summary!F51) -> 0 | G53: =-SUMIFS(Details!$BN$4:$BN$160,Details!$C$4:$C$160,Summary!G51) -> 0 | H53: =-SUMIFS(Details!$BN$4:$BN$160,Details!$C$4:$C$160,Summary!H51) -> 0 | I53: =-SUMIFS(Details!$BN$4:$BN$160,Details!$C$4:$C$160,Summary!I51) -> 0 | J53: =-SUMIFS(Details!$BN$4:$BN$160,Details!$C$4:$C$160,Summary!J51) -> 0 | K53: =-SUMIFS(Details!$BN$4:$BN$160,Details!$C$4:$C$160,Summary!K51) -> 0 | ... O53: =-SUMIFS(Details!$BN$4:$BN$160,Details!$C$4:$C$160,Summary!O51) -> 0 | P53: =SUM(D53:O53) -> 0 | Q53: =Details!BN161 -> 0 | R53: =Q53+P53 -> 0
C55: Qty Returned | D55: =D51 -> 46113 | E55: =E51 -> 46143 | F55: =F51 -> 46174 | G55: =G51 -> 46204 | H55: =H51 -> 46235 | I55: =I51 -> 46266 | J55: =J51 -> 46296 | K55: =K51 -> 46327 | ... P55: =P51 -> FY 2026-27
D56: =SUMIFS(Details!$R$4:$R$160,Details!$C$4:$C$160,Summary!D55) -> 0 | E56: =SUMIFS(Details!$R$4:$R$160,Details!$C$4:$C$160,Summary!E55) -> 0 | F56: =SUMIFS(Details!$R$4:$R$160,Details!$C$4:$C$160,Summary!F55) -> 0 | G56: =SUMIFS(Details!$R$4:$R$160,Details!$C$4:$C$160,Summary!G55) -> 0 | H56: =SUMIFS(Details!$R$4:$R$160,Details!$C$4:$C$160,Summary!H55) -> 0 | I56: =SUMIFS(Details!$R$4:$R$160,Details!$C$4:$C$160,Summary!I55) -> 0 | J56: =SUMIFS(Details!$R$4:$R$160,Details!$C$4:$C$160,Summary!J55) -> 0 | K56: =SUMIFS(Details!$R$4:$R$160,Details!$C$4:$C$160,Summary!K55) -> 0 | ... O56: =SUMIFS(Details!$R$4:$R$160,Details!$C$4:$C$160,Summary!O55) -> 0 | P56: =SUM(D56:O56) -> 0
C58: Margins | D58: 45748 | E58: 45778 | F58: 45809 | G58: 45839 | H58: 45870 | I58: 45901 | J58: 45931 | K58: 45962 | L58: 45992 | M58: 46023 | N58: 46054 | O58: 46082 | P58: FY 2025-26
C59: Gross Margin | D59: =SUMIFS(Details!$CK$5:$CK$160,Details!$C$5:$C$160,Summary!D$58) -> 0 | E59: =SUMIFS(Details!$CK$5:$CK$160,Details!$C$5:$C$160,Summary!E$58) -> 0 | F59: =SUMIFS(Details!$CK$5:$CK$160,Details!$C$5:$C$160,Summary!F$58) -> 0 | G59: =SUMIFS(Details!$CK$5:$CK$160,Details!$C$5:$C$160,Summary!G$58) -> 0 | H59: =SUMIFS(Details!$CK$5:$CK$160,Details!$C$5:$C$160,Summary!H$58) -> 0 | I59: =SUMIFS(Details!$CK$5:$CK$160,Details!$C$5:$C$160,Summary!I$58) -> 0 | J59: =SUMIFS(Details!$CK$5:$CK$160,Details!$C$5:$C$160,Summary!J$58) -> 0 | K59: =SUMIFS(Details!$CK$5:$CK$160,Details!$C$5:$C$160,Summary!K$58) -> 0 | ... O59: =SUMIFS(Details!$CK$5:$CK$160,Details!$C$5:$C$160,Summary!O$58) -> 0 | P59: =SUM(D59:O59) -> 0
C60: Recykal Margin | D60: =SUMIFS(Details!$CL$5:$CL$160,Details!$C$5:$C$160,Summary!D$58) -> 0 | E60: =SUMIFS(Details!$CL$5:$CL$160,Details!$C$5:$C$160,Summary!E$58) -> 0 | F60: =SUMIFS(Details!$CL$5:$CL$160,Details!$C$5:$C$160,Summary!F$58) -> 0 | G60: =SUMIFS(Details!$CL$5:$CL$160,Details!$C$5:$C$160,Summary!G$58) -> 0 | H60: =SUMIFS(Details!$CL$5:$CL$160,Details!$C$5:$C$160,Summary!H$58) -> 0 | I60: =SUMIFS(Details!$CL$5:$CL$160,Details!$C$5:$C$160,Summary!I$58) -> 0 | J60: =SUMIFS(Details!$CL$5:$CL$160,Details!$C$5:$C$160,Summary!J$58) -> 0 | K60: =SUMIFS(Details!$CL$5:$CL$160,Details!$C$5:$C$160,Summary!K$58) -> 0 | ... O60: =SUMIFS(Details!$CL$5:$CL$160,Details!$C$5:$C$160,Summary!O$58) -> 0 | P60: =SUM(D60:O60) -> 0
C61: Net Margin | D61: =SUMIFS(Details!$CM$5:$CM$160,Details!$C$5:$C$160,Summary!D$58) -> 0 | E61: =SUMIFS(Details!$CM$5:$CM$160,Details!$C$5:$C$160,Summary!E$58) -> 0 | F61: =SUMIFS(Details!$CM$5:$CM$160,Details!$C$5:$C$160,Summary!F$58) -> 0 | G61: =SUMIFS(Details!$CM$5:$CM$160,Details!$C$5:$C$160,Summary!G$58) -> 0 | H61: =SUMIFS(Details!$CM$5:$CM$160,Details!$C$5:$C$160,Summary!H$58) -> 0 | I61: =SUMIFS(Details!$CM$5:$CM$160,Details!$C$5:$C$160,Summary!I$58) -> 0 | J61: =SUMIFS(Details!$CM$5:$CM$160,Details!$C$5:$C$160,Summary!J$58) -> 0 | K61: =SUMIFS(Details!$CM$5:$CM$160,Details!$C$5:$C$160,Summary!K$58) -> 0 | ... O61: =SUMIFS(Details!$CM$5:$CM$160,Details!$C$5:$C$160,Summary!O$58) -> 0 | P61: =SUM(D61:O61) -> 0
C63: Financial with GST | D63: Sales | E63: Purchases
C64: =Details!P167 -> 46203 | D64: =SUMIFS(Details!$BO$5:$BO$160,Details!$D$5:$D$160,Summary!$C64)*118% -> 0 | E64: =SUMIFS(Details!$AM$5:$AM$160,Details!$D$5:$D$160,Summary!$C64)*118% -> 0
C65: =TEXT(C64,"mmm-yy") -> Jun-26 | D65: =SUMIFS(Details!$BO$5:$BO$160,Details!$C$5:$C$160,Summary!$C65)*118% -> 3657903.3 | E65: =SUMIFS(Details!$AM$5:$AM$160,Details!$C$5:$C$160,Summary!$C65)*118% -> 3336776.8
C66: Fy 2025-26 | D66: =Details!BO161*118% -> 7859967.9 | E66: =Details!AM161*118% -> 6613623.9

Sheet Details
B3: Raw Data -ITAD | F3: Purchase Details | U3: Logistic Details of the transaction | AF3: Debit Notes to Suppliers | AM3: Sales Details | BD3: DN to Customer | BH3: Credit Notes from Customers | BM3: 0 | BV3: CN & DN Checks | CE3: Without Provisions | CJ3: Margin Buckets | CM3: Financials with GST
B4: Quarter | C4: Month | D4: Date | E4: Shipment ID | F4: Supplier Name | G4: GST Reg No. | H4: Vendor Invoice No. | I4: Vendor Invoice Date | J4: P V No. | K4: P V Date | L4: State (Origin) | M4: Vehicle No. | N4: Material | O4: Qty (Kg) | P4: Price/unit | Q4: Purchase Price | R4: Return Qty | S4: Net Qty | T4: Basic Customs Duty/Discount | U4: Transporter Name | V4: LR NO/BILL NO | W4: J V No. | X4: JV Date | Y4: Logistics cost | Z4: Debit note on logistic cost | AA4: Logistics Provision | AB4: Total Logistics Cost | AC4: Operational Cost | AD4: Cost/Kg. | AE4: Divertion/Internal | AF4: Debit Note No. | AG4: Debit Note Date. | AH4: Debit Note No. 2 | AI4: Debit Note Date. 2 | AJ4: Full Debit Note | AK4: Actual Debit Note | AL4: Provision for DN | AM4: Total Cost | AN4: Inv. Date | AO4: Inv. No. | AP4: Customer ID | AQ4: Buyer Name | AR4: Buyer GST Number | AS4: Location (Origin) | AT4: Location (Destination) | AU4: State (Destination) | AV4: E-WayBill Number | AW4: Qty(Kg) | AX4: Price/unit | AY4: Amount | AZ4: Qty Check | BA4: Return Qty | BB4: Net Qty | BC4: Divertion/Internal | BD4: Return Type | BE4: Date : DN to Buyer | BF4: DN to Buyer | BG4: Amount | BH4: Credit Note No:1 | BI4: CN Date. No:1 | BJ4: Credit Note No:2 | BK4: CN Date. No:2 | BL4: Full Credit Notes | BM4: Actual Credit Note | BN4: Provision for CN | BO4: Net Revenue | BP4: Margin | BQ4: Reamrks - Margin | BR4: Remarks | BS4: LMI @ Inception | BT4: Remarks @ Inception | BU4: Margin (%) | BV4: Margin Bucket | BW4: Total CN(Inc.Provisions) | BX4: Total DN(Inc.Provisions) | BY4: Check | BZ4: Actaul CN | CA4: Actual DN | CB4: Check | CC4: Material-Short Form | CD4: Supplier Type | CE4: Cost | CF4: Revenue | CG4: Week No: | CH4: Category (Material) | CI4: Broad Category | CJ4: POC Name | CK4: Gross Margin | CL4: Recykal Margin | CM4: Net Margin | CN4: Sales | CO4: Purchases | CP4: Credit Note | CQ4: Debit Note | CR4: Margin | CS4: Bill Branch | CT4: Inv Branch | CU4: Vendor PAN No | CV4: Customer PAN No
B5: ="Q" & IF(ROUNDUP(MONTH(D5)/3,0)-1=0,4,ROUNDUP(MONTH(D5)/3,0)-1) -> Q1 | C5: =TEXT(AN5,"mmm-yy") -> Apr-26 | D5: 46115 | E5: SH04260204 | F5: CHAITANYA INDIA FIN CREDIT PRIVATE LIMITED | G5: 33AADCC6184H1ZP | H5: 2026290000000088 | I5: 46094 | J5: 25-26/PUR/027030 | K5: 46115 | L5: TN | N5: ITAD Mixed E Waste | O5: 26 | P5: 1576 | Q5: =O5*P5 -> 40976 | R5: 0 | S5: =O5-R5 -> 26 | T5: 0 | U5: 0 | V5: 0 | W5: 0 | X5: 0 | Y5: 0 | Z5: 0 | AA5: 0 | AB5: =Y5+AA5+Z5 -> 0 | AC5: 0 | AD5: 0 | AE5: 0 | AF5: 0 | AG5: 0 | AH5: 0 | AI5: 0 | AJ5: 0 | AK5: 0 | AL5: =(BN5*P5/AX5)+AB5/O5*(BN5/AX5) -> 0 | AM5: =Q5+AB5+AL5+AK5+AJ5+T5+AE5 -> 40976 | AN5: 46115 | AO5: 29/IAD/27IN00002 | AP5: 832139000046796207 | AQ5: TRADEWIND BUSINESS SOLUTIONS LLP | AR5: 07AARFT3586D1ZR | AS5: Alamelupuram Tamil Nadu 636905 | AT5: New Delhi | AU5: Delhi | AW5: 26 | AX5: 1733.9 | AY5: =AW5*AX5 -> 45081.4 | AZ5: =AW5=O5 -> TRUE | BA5: 0 | BB5: =AW5-BA5 -> 26 | BC5: 0 | BD5: Regular | BE5: 0 | BF5: 0 | BG5: 0 | BH5: 0 | BI5: 0 | BJ5: 0 | BK5: 0 | BL5: 0 | BM5: 0 | BN5: =AY5*$BM$3 -> 0 | BO5: =AY5+BL5+BM5+BN5+BC5+BG5 -> 45081.4 | BP5: =BO5-AM5 -> 4105.4 | BQ5: =IF(BP5>=0,"Positive Margin","Negative Margin") -> Positive Margin | BR5: No Provision | BS5: =AY5-Y5-Q5-AA5-T5+BC5 -> 4105.4 | BT5: =IF(BS5<0, "Negative Margin at Inception", "Positive Margin at Inception") -> Positive Margin at Inception | BU5: =IFERROR(BP5/BO5,"0") -> 0.091066382 | BV5: =IF(BU5<1%,"Less Than 1%",IF(BU5>2%,"More than 2%",IF(BU5>=1%,"1% - 2%"))) -> More than 2% | BW5: =BM5+BN5 -> 0 | BX5: =AL5+AK5 -> 0 | BY5: =BW5-BX5 -> 0 | BZ5: =BM5 -> 0 | CA5: =AK5 -> 0 | CB5: =BZ5-CA5 -> 0 | CC5: Marketplace (IT Assets Disposition) | CD5: 0 | CE5: =AM5-AL5-AA5 -> 40976 | CF5: =BO5-BN5 -> 45081.4 | CG5: =INT((D5- IF(MONTH(D5) >= 4, DATE(YEAR(D5), 4, 1), DATE(YEAR(D5)-1, 4, 1))) / 7) + 1 -> 1 | CH5: 0 | CI5: 0 | CJ5: =_xlfn.XLOOKUP(AP5,POC!B:B,POC!D:D) -> #N/A | CK5: =AY5-Q5 -> 4105.4 | CL5: =CK5-Y5+Z5 -> 4105.4 | CM5: =BO5-AM5 -> 4105.4 | CN5: =AY5*118% -> 53196.052 | CO5: =-Q5*118% -> -48351.68 | CP5: =-BZ5*118% -> 0 | CQ5: =-CA5*118% -> 0 | CR5: =SUM(CN5:CQ5) -> 4844.372 | CS5: Telangana - HO | CT5: Telangana - HO | CU5: =MID(G5,3,10) -> AADCC6184H | CV5: =MID(AR5,3,10) -> AARFT3586D | CW5: =H5&F5 -> 2026290000000088CHAITANYA INDIA FIN CREDIT PRIVATE LIMITED
B6: ="Q" & IF(ROUNDUP(MONTH(D6)/3,0)-1=0,4,ROUNDUP(MONTH(D6)/3,0)-1) -> Q1 | C6: =TEXT(AN6,"mmm-yy") -> Apr-26 | D6: 46115 | E6: SH04260204 | F6: CHAITANYA INDIA FIN CREDIT PRIVATE LIMITED | G6: 33AADCC6184H1ZP | H6: 2026290000000088 | I6: 46094 | J6: 25-26/PUR/027030 | K6: 46115 | L6: TN | N6: ITAD Mixed E Waste | O6: 1 | P6: 85 | Q6: =O6*P6 -> 85 | R6: 0 | S6: =O6-R6 -> 1 | T6: 0 | U6: 0 | V6: 0 | W6: 0 | X6: 0 | Y6: 0 | Z6: 0 | AA6: 0 | AB6: =Y6+AA6+Z6 -> 0 | AC6: 0 | AD6: 0 | AE6: 0 | AF6: 0 | AG6: 0 | AH6: 0 | AI6: 0 | AJ6: 0 | AK6: 0 | AL6: =(BN6*P6/AX6)+AB6/O6*(BN6/AX6) -> 0 | AM6: =Q6+AB6+AL6+AK6+AJ6+T6+AE6 -> 85 | AN6: 46115 | AO6: 29/IAD/27IN00002 | AP6: 832139000046796207 | AQ6: TRADEWIND BUSINESS SOLUTIONS LLP | AR6: 07AARFT3586D1ZR | AS6: Alamelupuram Tamil Nadu 636905 | AT6: New Delhi | AU6: Delhi | AW6: 1 | AX6: 93.22 | AY6: =AW6*AX6 -> 93.22 | AZ6: =AW6=O6 -> TRUE | BA6: 0 | BB6: =AW6-BA6 -> 1 | BC6: 0 | BD6: Regular | BE6: 0 | BF6: 0 | BG6: 0 | BH6: 0 | BI6: 0 | BJ6: 0 | BK6: 0 | BL6: 0 | BM6: 0 | BN6: =AY6*$BM$3 -> 0 | BO6: =AY6+BL6+BM6+BN6+BC6+BG6 -> 93.22 | BP6: =BO6-AM6 -> 8.22 | BQ6: =IF(BP6>=0,"Positive Margin","Negative Margin") -> Positive Margin | BR6: No Provision | BS6: =AY6-Y6-Q6-AA6-T6+BC6 -> 8.22 | BT6: =IF(BS6<0, "Negative Margin at Inception", "Positive Margin at Inception") -> Positive Margin at Inception | BU6: =IFERROR(BP6/BO6,"0") -> 0.088178502 | BV6: =IF(BU6<1%,"Less Than 1%",IF(BU6>2%,"More than 2%",IF(BU6>=1%,"1% - 2%"))) -> More than 2% | BW6: =BM6+BN6 -> 0 | BX6: =AL6+AK6 -> 0 | BY6: =BW6-BX6 -> 0 | BZ6: =BM6 -> 0 | CA6: =AK6 -> 0 | CB6: =BZ6-CA6 -> 0 | CC6: Marketplace (IT Assets Disposition) | CD6: 0 | CE6: =AM6-AL6-AA6 -> 85 | CF6: =BO6-BN6 -> 93.22 | CG6: =INT((D6- IF(MONTH(D6) >= 4, DATE(YEAR(D6), 4, 1), DATE(YEAR(D6)-1, 4, 1))) / 7) + 1 -> 1 | CH6: 0 | CI6: 0 | CJ6: =_xlfn.XLOOKUP(AP6,POC!B:B,POC!D:D) -> #N/A | CK6: =AY6-Q6 -> 8.22 | CL6: =CK6-Y6+Z6 -> 8.22 | CM6: =BO6-AM6 -> 8.22 | CN6: =AY6*118% -> 109.9996 | CO6: =-Q6*118% -> -100.3 | CP6: =-BZ6*118% -> 0 | CQ6: =-CA6*118% -> 0 | CR6: =SUM(CN6:CQ6) -> 9.6996 | CS6: Telangana - HO | CT6: Telangana - HO | CU6: =MID(G6,3,10) -> AADCC6184H | CV6: =MID(AR6,3,10) -> AARFT3586D | CW6: =H6&F6 -> 2026290000000088CHAITANYA INDIA FIN CREDIT PRIVATE LIMITED
B7: ="Q" & IF(ROUNDUP(MONTH(D7)/3,0)-1=0,4,ROUNDUP(MONTH(D7)/3,0)-1) -> Q1 | C7: =TEXT(AN7,"mmm-yy") -> Apr-26 | D7: 46115 | E7: SH04260204 | F7: CHAITANYA INDIA FIN CREDIT PRIVATE LIMITED | G7: 33AADCC6184H1ZP | H7: 2026290000000088 | I7: 46094 | J7: 25-26/PUR/027030 | K7: 46115 | L7: TN | N7: ITAD Mixed E Waste | O7: 1 | P7: 85 | Q7: =O7*P7 -> 85 | R7: 0 | S7: =O7-R7 -> 1 | T7: 0 | U7: 0 | V7: 0 | W7: 0 | X7: 0 | Y7: 0 | Z7: 0 | AA7: 0 | AB7: =Y7+AA7+Z7 -> 0 | AC7: 0 | AD7: 0 | AE7: 0 | AF7: 0 | AG7: 0 | AH7: 0 | AI7: 0 | AJ7: 0 | AK7: 0 | AL7: =(BN7*P7/AX7)+AB7/O7*(BN7/AX7) -> 0 | AM7: =Q7+AB7+AL7+AK7+AJ7+T7+AE7 -> 85 | AN7: 46115 | AO7: 29/IAD/27IN00002 | AP7: 832139000046796207 | AQ7: TRADEWIND BUSINESS SOLUTIONS LLP | AR7: 07AARFT3586D1ZR | AS7: Alamelupuram Tamil Nadu 636905 | AT7: New Delhi | AU7: Delhi | AW7: 1 | AX7: 93.22 | AY7: =AW7*AX7 -> 93.22 | AZ7: =AW7=O7 -> TRUE | BA7: 0 | BB7: =AW7-BA7 -> 1 | BC7: 0 | BD7: Regular | BE7: 0 | BF7: 0 | BG7: 0 | BH7: 0 | BI7: 0 | BJ7: 0 | BK7: 0 | BL7: 0 | BM7: 0 | BN7: =AY7*$BM$3 -> 0 | BO7: =AY7+BL7+BM7+BN7+BC7+BG7 -> 93.22 | BP7: =BO7-AM7 -> 8.22 | BQ7: =IF(BP7>=0,"Positive Margin","Negative Margin") -> Positive Margin | BR7: No Provision | BS7: =AY7-Y7-Q7-AA7-T7+BC7 -> 8.22 | BT7: =IF(BS7<0, "Negative Margin at Inception", "Positive Margin at Inception") -> Positive Margin at Inception | BU7: =IFERROR(BP7/BO7,"0") -> 0.088178502 | BV7: =IF(BU7<1%,"Less Than 1%",IF(BU7>2%,"More than 2%",IF(BU7>=1%,"1% - 2%"))) -> More than 2% | BW7: =BM7+BN7 -> 0 | BX7: =AL7+AK7 -> 0 | BY7: =BW7-BX7 -> 0 | BZ7: =BM7 -> 0 | CA7: =AK7 -> 0 | CB7: =BZ7-CA7 -> 0 | CC7: Marketplace (IT Assets Disposition) | CD7: 0 | CE7: =AM7-AL7-AA7 -> 85 | CF7: =BO7-BN7 -> 93.22 | CG7: =INT((D7- IF(MONTH(D7) >= 4, DATE(YEAR(D7), 4, 1), DATE(YEAR(D7)-1, 4, 1))) / 7) + 1 -> 1 | CH7: 0 | CI7: 0 | CJ7: =_xlfn.XLOOKUP(AP7,POC!B:B,POC!D:D) -> #N/A | CK7: =AY7-Q7 -> 8.22 | CL7: =CK7-Y7+Z7 -> 8.22 | CM7: =BO7-AM7 -> 8.22 | CN7: =AY7*118% -> 109.9996 | CO7: =-Q7*118% -> -100.3 | CP7: =-BZ7*118% -> 0 | CQ7: =-CA7*118% -> 0 | CR7: =SUM(CN7:CQ7) -> 9.6996 | CS7: Telangana - HO | CT7: Telangana - HO | CU7: =MID(G7,3,10) -> AADCC6184H | CV7: =MID(AR7,3,10) -> AARFT3586D | CW7: =H7&F7 -> 2026290000000088CHAITANYA INDIA FIN CREDIT PRIVATE LIMITED
B8: ="Q" & IF(ROUNDUP(MONTH(D8)/3,0)-1=0,4,ROUNDUP(MONTH(D8)/3,0)-1) -> Q1 | C8: =TEXT(AN8,"mmm-yy") -> Apr-26 | D8: 46115 | E8: SH04260203 | F8: CHAITANYA INDIA FIN CREDIT PRIVATE LIMITED | G8: 08AADCC6184H1ZI | H8: 2026290000000087 | I8: 46094 | J8: 25-26/PUR/027028 | K8: 46115 | L8: RJ | N8: ITAD Mixed E Waste | O8: 15 | P8: 1576 | Q8: =O8*P8 -> 23640 | R8: 0 | S8: =O8-R8 -> 15 | T8: 0 | U8: 0 | V8: 0 | W8: 0 | X8: 0 | Y8: 0 | Z8: 0 | AA8: 0 | AB8: =Y8+AA8+Z8 -> 0 | AC8: 0 | AD8: 0 | AE8: 0 | AF8: 0 | AG8: 0 | AH8: 0 | AI8: 0 | AJ8: 0 | AK8: 0 | AL8: =(BN8*P8/AX8)+AB8/O8*(BN8/AX8) -> 0 | AM8: =Q8+AB8+AL8+AK8+AJ8+T8+AE8 -> 23640 | AN8: 46115 | AO8: 29/IAD/27IN00001 | AP8: 832139000046796207 | AQ8: TRADEWIND BUSINESS SOLUTIONS LLP | AR8: 07AARFT3586D1ZR | AS8: Jaipur Rajasthan 302020 | AT8: New Delhi | AU8: Delhi | AW8: 15 | AX8: 1733.9 | AY8: =AW8*AX8 -> 26008.5 | AZ8: =AW8=O8 -> TRUE | BA8: 0 | BB8: =AW8-BA8 -> 15 | BC8: 0 | BD8: Regular | BE8: 0 | BF8: 0 | BG8: 0 | BH8: 0 | BI8: 0 | BJ8: 0 | BK8: 0 | BL8: 0 | BM8: 0 | BN8: =AY8*$BM$3 -> 0 | BO8: =AY8+BL8+BM8+BN8+BC8+BG8 -> 26008.5 | BP8: =BO8-AM8 -> 2368.5 | BQ8: =IF(BP8>=0,"Positive Margin","Negative Margin") -> Positive Margin | BR8: No Provision | BS8: =AY8-Y8-Q8-AA8-T8+BC8 -> 2368.5 | BT8: =IF(BS8<0, "Negative Margin at Inception", "Positive Margin at Inception") -> Positive Margin at Inception | BU8: =IFERROR(BP8/BO8,"0") -> 0.091066382 | BV8: =IF(BU8<1%,"Less Than 1%",IF(BU8>2%,"More than 2%",IF(BU8>=1%,"1% - 2%"))) -> More than 2% | BW8: =BM8+BN8 -> 0 | BX8: =AL8+AK8 -> 0 | BY8: =BW8-BX8 -> 0 | BZ8: =BM8 -> 0 | CA8: =AK8 -> 0 | CB8: =BZ8-CA8 -> 0 | CC8: Marketplace (IT Assets Disposition) | CD8: 0 | CE8: =AM8-AL8-AA8 -> 23640 | CF8: =BO8-BN8 -> 26008.5 | CG8: =INT((D8- IF(MONTH(D8) >= 4, DATE(YEAR(D8), 4, 1), DATE(YEAR(D8)-1, 4, 1))) / 7) + 1 -> 1 | CH8: 0 | CI8: 0 | CJ8: =_xlfn.XLOOKUP(AP8,POC!B:B,POC!D:D) -> #N/A | CK8: =AY8-Q8 -> 2368.5 | CL8: =CK8-Y8+Z8 -> 2368.5 | CM8: =BO8-AM8 -> 2368.5 | CN8: =AY8*118% -> 30690.03 | CO8: =-Q8*118% -> -27895.2 | CP8: =-BZ8*118% -> 0 | CQ8: =-CA8*118% -> 0 | CR8: =SUM(CN8:CQ8) -> 2794.83 | CS8: Telangana - HO | CT8: Telangana - HO | CU8: =MID(G8,3,10) -> AADCC6184H | CV8: =MID(AR8,3,10) -> AARFT3586D | CW8: =H8&F8 -> 2026290000000087CHAITANYA INDIA FIN CREDIT PRIVATE LIMITED
B9: ="Q" & IF(ROUNDUP(MONTH(D9)/3,0)-1=0,4,ROUNDUP(MONTH(D9)/3,0)-1) -> Q1 | C9: =TEXT(AN9,"mmm-yy") -> Apr-26 | D9: 46115 | E9: SH04260203 | F9: CHAITANYA INDIA FIN CREDIT PRIVATE LIMITED | G9: 08AADCC6184H1ZI | H9: 2026290000000087 | I9: 46094 | J9: 25-26/PUR/027028 | K9: 46115 | L9: RJ | N9: ITAD Mixed E Waste | O9: 1 | P9: 85 | Q9: =O9*P9 -> 85 | R9: 0 | S9: =O9-R9 -> 1 | T9: 0 | U9: 0 | V9: 0 | W9: 0 | X9: 0 | Y9: 0 | Z9: 0 | AA9: 0 | AB9: =Y9+AA9+Z9 -> 0 | AC9: 0 | AD9: 0 | AE9: 0 | AF9: 0 | AG9: 0 | AH9: 0 | AI9: 0 | AJ9: 0 | AK9: 0 | AL9: =(BN9*P9/AX9)+AB9/O9*(BN9/AX9) -> 0 | AM9: =Q9+AB9+AL9+AK9+AJ9+T9+AE9 -> 85 | AN9: 46115 | AO9: 29/IAD/27IN00001 | AP9: 832139000046796207 | AQ9: TRADEWIND BUSINESS SOLUTIONS LLP | AR9: 07AARFT3586D1ZR | AS9: Jaipur Rajasthan 302020 | AT9: New Delhi | AU9: Delhi | AW9: 1 | AX9: 93.22 | AY9: =AW9*AX9 -> 93.22 | AZ9: =AW9=O9 -> TRUE | BA9: 0 | BB9: =AW9-BA9 -> 1 | BC9: 0 | BD9: Regular | BE9: 0 | BF9: 0 | BG9: 0 | BH9: 0 | BI9: 0 | BJ9: 0 | BK9: 0 | BL9: 0 | BM9: 0 | BN9: =AY9*$BM$3 -> 0 | BO9: =AY9+BL9+BM9+BN9+BC9+BG9 -> 93.22 | BP9: =BO9-AM9 -> 8.22 | BQ9: =IF(BP9>=0,"Positive Margin","Negative Margin") -> Positive Margin | BR9: No Provision | BS9: =AY9-Y9-Q9-AA9-T9+BC9 -> 8.22 | BT9: =IF(BS9<0, "Negative Margin at Inception", "Positive Margin at Inception") -> Positive Margin at Inception | BU9: =IFERROR(BP9/BO9,"0") -> 0.088178502 | BV9: =IF(BU9<1%,"Less Than 1%",IF(BU9>2%,"More than 2%",IF(BU9>=1%,"1% - 2%"))) -> More than 2% | BW9: =BM9+BN9 -> 0 | BX9: =AL9+AK9 -> 0 | BY9: =BW9-BX9 -> 0 | BZ9: =BM9 -> 0 | CA9: =AK9 -> 0 | CB9: =BZ9-CA9 -> 0 | CC9: Marketplace (IT Assets Disposition) | CD9: 0 | CE9: =AM9-AL9-AA9 -> 85 | CF9: =BO9-BN9 -> 93.22 | CG9: =INT((D9- IF(MONTH(D9) >= 4, DATE(YEAR(D9), 4, 1), DATE(YEAR(D9)-1, 4, 1))) / 7) + 1 -> 1 | CH9: 0 | CI9: 0 | CJ9: =_xlfn.XLOOKUP(AP9,POC!B:B,POC!D:D) -> #N/A | CK9: =AY9-Q9 -> 8.22 | CL9: =CK9-Y9+Z9 -> 8.22 | CM9: =BO9-AM9 -> 8.22 | CN9: =AY9*118% -> 109.9996 | CO9: =-Q9*118% -> -100.3 | CP9: =-BZ9*118% -> 0 | CQ9: =-CA9*118% -> 0 | CR9: =SUM(CN9:CQ9) -> 9.6996 | CS9: Telangana - HO | CT9: Telangana - HO | CU9: =MID(G9,3,10) -> AADCC6184H | CV9: =MID(AR9,3,10) -> AARFT3586D | CW9: =H9&F9 -> 2026290000000087CHAITANYA INDIA FIN CREDIT PRIVATE LIMITED
B10: ="Q" & IF(ROUNDUP(MONTH(D10)/3,0)-1=0,4,ROUNDUP(MONTH(D10)/3,0)-1) -> Q1 | C10: =TEXT(AN10,"mmm-yy") -> Apr-26 | D10: 46115 | E10: SH04260203 | F10: CHAITANYA INDIA FIN CREDIT PRIVATE LIMITED | G10: 08AADCC6184H1ZI | H10: 2026290000000087 | I10: 46094 | J10: 25-26/PUR/027028 | K10: 46115 | L10: RJ | N10: ITAD Mixed E Waste | O10: 1 | P10: 1576 | Q10: =O10*P10 -> 1576 | R10: 0 | S10: =O10-R10 -> 1 | T10: 0 | U10: 0 | V10: 0 | W10: 0 | X10: 0 | Y10: 0 | Z10: 0 | AA10: 0 | AB10: =Y10+AA10+Z10 -> 0 | AC10: 0 | AD10: 0 | AE10: 0 | AF10: 0 | AG10: 0 | AH10: 0 | AI10: 0 | AJ10: 0 | AK10: 0 | AL10: =(BN10*P10/AX10)+AB10/O10*(BN10/AX10) -> 0 | AM10: =Q10+AB10+AL10+AK10+AJ10+T10+AE10 -> 1576 | AN10: 46115 | AO10: 29/IAD/27IN00001 | AP10: 832139000046796207 | AQ10: TRADEWIND BUSINESS SOLUTIONS LLP | AR10: 07AARFT3586D1ZR | AS10: Jaipur Rajasthan 302020 | AT10: New Delhi | AU10: Delhi | AW10: 1 | AX10: 1733.9 | AY10: =AW10*AX10 -> 1733.9 | AZ10: =AW10=O10 -> TRUE | BA10: 0 | BB10: =AW10-BA10 -> 1 | BC10: 0 | BD10: Regular | BE10: 0 | BF10: 0 | BG10: 0 | BH10: 0 | BI10: 0 | BJ10: 0 | BK10: 0 | BL10: 0 | BM10: 0 | BN10: =AY10*$BM$3 -> 0 | BO10: =AY10+BL10+BM10+BN10+BC10+BG10 -> 1733.9 | BP10: =BO10-AM10 -> 157.9 | BQ10: =IF(BP10>=0,"Positive Margin","Negative Margin") -> Positive Margin | BR10: No Provision | BS10: =AY10-Y10-Q10-AA10-T10+BC10 -> 157.9 | BT10: =IF(BS10<0, "Negative Margin at Inception", "Positive Margin at Inception") -> Positive Margin at Inception | BU10: =IFERROR(BP10/BO10,"0") -> 0.091066382 | BV10: =IF(BU10<1%,"Less Than 1%",IF(BU10>2%,"More than 2%",IF(BU10>=1%,"1% - 2%"))) -> More than 2% | BW10: =BM10+BN10 -> 0 | BX10: =AL10+AK10 -> 0 | BY10: =BW10-BX10 -> 0 | BZ10: =BM10 -> 0 | CA10: =AK10 -> 0 | CB10: =BZ10-CA10 -> 0 | CC10: Marketplace (IT Assets Disposition) | CD10: 0 | CE10: =AM10-AL10-AA10 -> 1576 | CF10: =BO10-BN10 -> 1733.9 | CG10: =INT((D10- IF(MONTH(D10) >= 4, DATE(YEAR(D10), 4, 1), DATE(YEAR(D10)-1, 4, 1))) / 7) + 1 -> 1 | CH10: 0 | CI10: 0 | CJ10: =_xlfn.XLOOKUP(AP10,POC!B:B,POC!D:D) -> #N/A | CK10: =AY10-Q10 -> 157.9 | CL10: =CK10-Y10+Z10 -> 157.9 | CM10: =BO10-AM10 -> 157.9 | CN10: =AY10*118% -> 2046.002 | CO10: =-Q10*118% -> -1859.68 | CP10: =-BZ10*118% -> 0 | CQ10: =-CA10*118% -> 0 | CR10: =SUM(CN10:CQ10) -> 186.322 | CS10: Telangana - HO | CT10: Telangana - HO | CU10: =MID(G10,3,10) -> AADCC6184H | CV10: =MID(AR10,3,10) -> AARFT3586D | CW10: =H10&F10 -> 2026290000000087CHAITANYA INDIA FIN CREDIT PRIVATE LIMITED
B11: ="Q" & IF(ROUNDUP(MONTH(D11)/3,0)-1=0,4,ROUNDUP(MONTH(D11)/3,0)-1) -> Q1 | C11: =TEXT(AN11,"mmm-yy") -> Apr-26 | D11: 46115 | E11: SH04260307 | F11: CYIENT LIMITED | G11: 36AAACI4487J1Z9 | H11: 9102515564 | I11: 46105 | J11: 25-26/PUR/027036 | K11: 46115 | L11: TS | N11: UPS Battery Scrap | O11: 44 | P11: 4340.95 | Q11: =O11*P11 -> 191001.8 | R11: 0 | S11: =O11-R11 -> 44 | T11: 0 | U11: 0 | V11: 0 | W11: 0 | X11: 0 | Y11: 0 | Z11: 0 | AA11: 0 | AB11: =Y11+AA11+Z11 -> 0 | AC11: 0 | AD11: 0 | AE11: 0 | AF11: 0 | AG11: 0 | AH11: 0 | AI11: 0 | AJ11: 0 | AK11: 0 | AL11: =(BN11*P11/AX11)+AB11/O11*(BN11/AX11) -> 0 | AM11: =Q11+AB11+AL11+AK11+AJ11+T11+AE11 -> 191001.8 | AN11: 46116 | AO11: 36/IAD/27IN00002 | AP11: 832139000055796981 | AQ11: RETECK ENVIROTECH PRIVATE LIMITED | AR11: 27AAHCR2638B1ZK | AS11: Hyderabad Telangana 500081 | AT11: Vadgaon | AU11: Maharashtra | AW11: 44 | AX11: 4672.905 | AY11: =AW11*AX11 -> 205607.82 | AZ11: =AW11=O11 -> TRUE | BA11: 0 | BB11: =AW11-BA11 -> 44 | BC11: 0 | BD11: Regular | BE11: 0 | BF11: 0 | BG11: 0 | BH11: 0 | BI11: 0 | BJ11: 0 | BK11: 0 | BL11: 0 | BM11: 0 | BN11: =AY11*$BM$3 -> 0 | BO11: =AY11+BL11+BM11+BN11+BC11+BG11 -> 205607.82 | BP11: =BO11-AM11 -> 14606.02 | BQ11: =IF(BP11>=0,"Positive Margin","Negative Margin") -> Positive Margin | BR11: No Provision | BS11: =AY11-Y11-Q11-AA11-T11+BC11 -> 14606.02 | BT11: =IF(BS11<0, "Negative Margin at Inception", "Positive Margin at Inception") -> Positive Margin at Inception | BU11: =IFERROR(BP11/BO11,"0") -> 0.071038251 | BV11: =IF(BU11<1%,"Less Than 1%",IF(BU11>2%,"More than 2%",IF(BU11>=1%,"1% - 2%"))) -> More than 2% | BW11: =BM11+BN11 -> 0 | BX11: =AL11+AK11 -> 0 | BY11: =BW11-BX11 -> 0 | BZ11: =BM11 -> 0 | CA11: =AK11 -> 0 | CB11: =BZ11-CA11 -> 0 | CC11: Marketplace (IT Assets Disposition) | CD11: 0 | CE11: =AM11-AL11-AA11 -> 191001.8 | CF11: =BO11-BN11 -> 205607.82 | CG11: =INT((D11- IF(MONTH(D11) >= 4, DATE(YEAR(D11), 4, 1), DATE(YEAR(D11)-1, 4, 1))) / 7) + 1 -> 1 | CH11: 0 | CI11: 0 | CJ11: =_xlfn.XLOOKUP(AP11,POC!B:B,POC!D:D) -> #N/A | CK11: =AY11-Q11 -> 14606.02 | CL11: =CK11-Y11+Z11 -> 14606.02 | CM11: =BO11-AM11 -> 14606.02 | CN11: =AY11*118% -> 242617.23 | CO11: =-Q11*118% -> -225382.12 | CP11: =-BZ11*118% -> 0 | CQ11: =-CA11*118% -> 0 | CR11: =SUM(CN11:CQ11) -> 17235.104 | CS11: Telangana - HO | CT11: Telangana - HO | CU11: =MID(G11,3,10) -> AAACI4487J | CV11: =MID(AR11,3,10) -> AAHCR2638B | CW11: =H11&F11 -> 9102515564CYIENT LIMITED
B12: ="Q" & IF(ROUNDUP(MONTH(D12)/3,0)-1=0,4,ROUNDUP(MONTH(D12)/3,0)-1) -> Q1 | C12: =TEXT(AN12,"mmm-yy") -> Apr-26 | D12: 46115 | E12: SH04260307 | F12: CYIENT LIMITED | G12: 36AAACI4487J1Z9 | H12: 9102515564 | I12: 46105 | J12: 25-26/PUR/027036 | K12: 46115 | L12: TS | N12: UPS Battery Scrap | O12: 40 | P12: 464.95 | Q12: =O12*P12 -> 18598 | R12: 0 | S12: =O12-R12 -> 40 | T12: 0 | U12: 0 | V12: 0 | W12: 0 | X12: 0 | Y12: 0 | Z12: 0 | AA12: 0 | AB12: =Y12+AA12+Z12 -> 0 | AC12: 0 | AD12: 0 | AE12: 0 | AF12: 0 | AG12: 0 | AH12: 0 | AI12: 0 | AJ12: 0 | AK12: 0 | AL12: =(BN12*P12/AX12)+AB12/O12*(BN12/AX12) -> 0 | AM12: =Q12+AB12+AL12+AK12+AJ12+T12+AE12 -> 18598 | AN12: 46116 | AO12: 36/IAD/27IN00002 | AP12: 832139000055796981 | AQ12: RETECK ENVIROTECH PRIVATE LIMITED | AR12: 27AAHCR2638B1ZK | AS12: Hyderabad Telangana 500081 | AT12: Vadgaon | AU12: Maharashtra | AW12: 40 | AX12: 500.505 | AY12: =AW12*AX12 -> 20020.2 | AZ12: =AW12=O12 -> TRUE | BA12: 0 | BB12: =AW12-BA12 -> 40 | BC12: 0 | BD12: Regular | BE12: 0 | BF12: 0 | BG12: 0 | BH12: 0 | BI12: 0 | BJ12: 0 | BK12: 0 | BL12: 0 | BM12: 0 | BN12: =AY12*$BM$3 -> 0 | BO12: =AY12+BL12+BM12+BN12+BC12+BG12 -> 20020.2 | BP12: =BO12-AM12 -> 1422.2 | BQ12: =IF(BP12>=0,"Positive Margin","Negative Margin") -> Positive Margin | BR12: No Provision | BS12: =AY12-Y12-Q12-AA12-T12+BC12 -> 1422.2 | BT12: =IF(BS12<0, "Negative Margin at Inception", "Positive Margin at Inception") -> Positive Margin at Inception | BU12: =IFERROR(BP12/BO12,"0") -> 0.071038251 | BV12: =IF(BU12<1%,"Less Than 1%",IF(BU12>2%,"More than 2%",IF(BU12>=1%,"1% - 2%"))) -> More than 2% | BW12: =BM12+BN12 -> 0 | BX12: =AL12+AK12 -> 0 | BY12: =BW12-BX12 -> 0 | BZ12: =BM12 -> 0 | CA12: =AK12 -> 0 | CB12: =BZ12-CA12 -> 0 | CC12: Marketplace (IT Assets Disposition) | CD12: 0 | CE12: =AM12-AL12-AA12 -> 18598 | CF12: =BO12-BN12 -> 20020.2 | CG12: =INT((D12- IF(MONTH(D12) >= 4, DATE(YEAR(D12), 4, 1), DATE(YEAR(D12)-1, 4, 1))) / 7) + 1 -> 1 | CH12: 0 | CI12: 0 | CJ12: =_xlfn.XLOOKUP(AP12,POC!B:B,POC!D:D) -> #N/A | CK12: =AY12-Q12 -> 1422.2 | CL12: =CK12-Y12+Z12 -> 1422.2 | CM12: =BO12-AM12 -> 1422.2 | CN12: =AY12*118% -> 23623.836 | CO12: =-Q12*118% -> -21945.64 | CP12: =-BZ12*118% -> 0 | CQ12: =-CA12*118% -> 0 | CR12: =SUM(CN12:CQ12) -> 1678.196 | CS12: Telangana - HO | CT12: Telangana - HO | CU12: =MID(G12,3,10) -> AAACI4487J | CV12: =MID(AR12,3,10) -> AAHCR2638B | CW12: =H12&F12 -> 9102515564CYIENT LIMITED
B13: ="Q" & IF(ROUNDUP(MONTH(D13)/3,0)-1=0,4,ROUNDUP(MONTH(D13)/3,0)-1) -> Q1 | C13: =TEXT(AN13,"mmm-yy") -> Apr-26 | D13: 46115 | E13: SH04260307 | F13: CYIENT LIMITED | G13: 36AAACI4487J1Z9 | H13: 9102515564 | I13: 46105 | J13: 25-26/PUR/027036 | K13: 46115 | L13: TS | N13: UPS Battery Scrap | O13: 15 | P13: 763.73 | Q13: =O13*P13 -> 11455.95 | R13: 0 | S13: =O13-R13 -> 15 | T13: 0 | U13: 0 | V13: 0 | W13: 0 | X13: 0 | Y13: 0 | Z13: 0 | AA13: 0 | AB13: =Y13+AA13+Z13 -> 0 | AC13: 0 | AD13: 0 | AE13: 0 | AF13: 0 | AG13: 0 | AH13: 0 | AI13: 0 | AJ13: 0 | AK13: 0 | AL13: =(BN13*P13/AX13)+AB13/O13*(BN13/AX13) -> 0 | AM13: =Q13+AB13+AL13+AK13+AJ13+T13+AE13 -> 11455.95 | AN13: 46116 | AO13: 36/IAD/27IN00002 | AP13: 832139000055796981 | AQ13: RETECK ENVIROTECH PRIVATE LIMITED | AR13: 27AAHCR2638B1ZK | AS13: Hyderabad Telangana 500081 | AT13: Vadgaon | AU13: Maharashtra | AW13: 15 | AX13: 822.128 | AY13: =AW13*AX13 -> 12331.92 | AZ13: =AW13=O13 -> TRUE | BA13: 0 | BB13: =AW13-BA13 -> 15 | BC13: 0 | BD13: Regular | BE13: 0 | BF13: 0 | BG13: 0 | BH13: 0 | BI13: 0 | BJ13: 0 | BK13: 0 | BL13: 0 | BM13: 0 | BN13: =AY13*$BM$3 -> 0 | BO13: =AY13+BL13+BM13+BN13+BC13+BG13 -> 12331.92 | BP13: =BO13-AM13 -> 875.97 | BQ13: =IF(BP13>=0,"Positive Margin","Negative Margin") -> Positive Margin | BR13: No Provision | BS13: =AY13-Y13-Q13-AA13-T13+BC13 -> 875.97 | BT13: =IF(BS13<0, "Negative Margin at Inception", "Positive Margin at Inception") -> Positive Margin at Inception | BU13: =IFERROR(BP13/BO13,"0") -> 0.071032735 | BV13: =IF(BU13<1%,"Less Than 1%",IF(BU13>2%,"More than 2%",IF(BU13>=1%,"1% - 2%"))) -> More than 2% | BW13: =BM13+BN13 -> 0 | BX13: =AL13+AK13 -> 0 | BY13: =BW13-BX13 -> 0 | BZ13: =BM13 -> 0 | CA13: =AK13 -> 0 | CB13: =BZ13-CA13 -> 0 | CC13: Marketplace (IT Assets Disposition) | CD13: 0 | CE13: =AM13-AL13-AA13 -> 11455.95 | CF13: =BO13-BN13 -> 12331.92 | CG13: =INT((D13- IF(MONTH(D13) >= 4, DATE(YEAR(D13), 4, 1), DATE(YEAR(D13)-1, 4, 1))) / 7) + 1 -> 1 | CH13: 0 | CI13: 0 | CJ13: =_xlfn.XLOOKUP(AP13,POC!B:B,POC!D:D) -> #N/A | CK13: =AY13-Q13 -> 875.97 | CL13: =CK13-Y13+Z13 -> 875.97 | CM13: =BO13-AM13 -> 875.97 | CN13: =AY13*118% -> 14551.666 | CO13: =-Q13*118% -> -13518.021 | CP13: =-BZ13*118% -> 0 | CQ13: =-CA13*118% -> 0 | CR13: =SUM(CN13:CQ13) -> 1033.6446 | CS13: Telangana - HO | CT13: Telangana - HO | CU13: =MID(G13,3,10) -> AAACI4487J | CV13: =MID(AR13,3,10) -> AAHCR2638B | CW13: =H13&F13 -> 9102515564CYIENT LIMITED
B14: ="Q" & IF(ROUNDUP(MONTH(D14)/3,0)-1=0,4,ROUNDUP(MONTH(D14)/3,0)-1) -> Q1 | C14: =TEXT(AN14,"mmm-yy") -> Apr-26 | D14: 46115 | E14: SH04260307 | F14: CYIENT LIMITED | G14: 36AAACI4487J1Z9 | H14: 9102515564 | I14: 46105 | J14: 25-26/PUR/027036 | K14: 46115 | L14: TS | N14: UPS Battery Scrap | O14: 6 | P14: 461.55 | Q14: =O14*P14 -> 2769.3 | R14: 0 | S14: =O14-R14 -> 6 | T14: 0 | U14: 0 | V14: 0 | W14: 0 | X14: 0 | Y14: 0 | Z14: 0 | AA14: 0 | AB14: =Y14+AA14+Z14 -> 0 | AC14: 0 | AD14: 0 | AE14: 0 | AF14: 0 | AG14: 0 | AH14: 0 | AI14: 0 | AJ14: 0 | AK14: 0 | AL14: =(BN14*P14/AX14)+AB14/O14*(BN14/AX14) -> 0 | AM14: =Q14+AB14+AL14+AK14+AJ14+T14+AE14 -> 2769.3 | AN14: 46116 | AO14: 36/IAD/27IN00002 | AP14: 832139000055796981 | AQ14: RETECK ENVIROTECH PRIVATE LIMITED | AR14: 27AAHCR2638B1ZK | AS14: Hyderabad Telangana 500081 | AT14: Vadgaon | AU14: Maharashtra | AW14: 6 | AX14: 486.78 | AY14: =AW14*AX14 -> 2920.68 | AZ14: =AW14=O14 -> TRUE | BA14: 0 | BB14: =AW14-BA14 -> 6 | BC14: 0 | BD14: Regular | BE14: 0 | BF14: 0 | BG14: 0 | BH14: 0 | BI14: 0 | BJ14: 0 | BK14: 0 | BL14: 0 | BM14: 0 | BN14: =AY14*$BM$3 -> 0 | BO14: =AY14+BL14+BM14+BN14+BC14+BG14 -> 2920.68 | BP14: =BO14-AM14 -> 151.38 | BQ14: =IF(BP14>=0,"Positive Margin","Negative Margin") -> Positive Margin | BR14: No Provision | BS14: =AY14-Y14-Q14-AA14-T14+BC14 -> 151.38 | BT14: =IF(BS14<0, "Negative Margin at Inception", "Positive Margin at Inception") -> Positive Margin at Inception | BU14: =IFERROR(BP14/BO14,"0") -> 0.051830396 | BV14: =IF(BU14<1%,"Less Than 1%",IF(BU14>2%,"More than 2%",IF(BU14>=1%,"1% - 2%"))) -> More than 2% | BW14: =BM14+BN14 -> 0 | BX14: =AL14+AK14 -> 0 | BY14: =BW14-BX14 -> 0 | BZ14: =BM14 -> 0 | CA14: =AK14 -> 0 | CB14: =BZ14-CA14 -> 0 | CC14: Marketplace (IT Assets Disposition) | CD14: 0 | CE14: =AM14-AL14-AA14 -> 2769.3 | CF14: =BO14-BN14 -> 2920.68 | CG14: =INT((D14- IF(MONTH(D14) >= 4, DATE(YEAR(D14), 4, 1), DATE(YEAR(D14)-1, 4, 1))) / 7) + 1 -> 1 | CH14: 0 | CI14: 0 | CJ14: =_xlfn.XLOOKUP(AP14,POC!B:B,POC!D:D) -> #N/A | CK14: =AY14-Q14 -> 151.38 | CL14: =CK14-Y14+Z14 -> 151.38 | CM14: =BO14-AM14 -> 151.38 | CN14: =AY14*118% -> 3446.4024 | CO14: =-Q14*118% -> -3267.774 | CP14: =-BZ14*118% -> 0 | CQ14: =-CA14*118% -> 0 | CR14: =SUM(CN14:CQ14) -> 178.6284 | CS14: Telangana - HO | CT14: Telangana - HO | CU14: =MID(G14,3,10) -> AAACI4487J | CV14: =MID(AR14,3,10) -> AAHCR2638B | CW14: =H14&F14 -> 9102515564CYIENT LIMITED
B15: ="Q" & IF(ROUNDUP(MONTH(D15)/3,0)-1=0,4,ROUNDUP(MONTH(D15)/3,0)-1) -> Q1 | C15: =TEXT(AN15,"mmm-yy") -> Apr-26 | D15: 46115 | E15: SH04260307 | F15: CYIENT LIMITED | G15: 36AAACI4487J1Z9 | H15: 9102515564 | I15: 46105 | J15: 25-26/PUR/027036 | K15: 46115 | L15: TS | N15: UPS Battery Scrap | O15: 8 | P15: 314.93 | Q15: =O15*P15 -> 2519.44 | R15: 0 | S15: =O15-R15 -> 8 | T15: 0 | U15: 0 | V15: 0 | W15: 0 | X15: 0 | Y15: 0 | Z15: 0 | AA15: 0 | AB15: =Y15+AA15+Z15 -> 0 | AC15: 0 | AD15: 0 | AE15: 0 | AF15: 0 | AG15: 0 | AH15: 0 | AI15: 0 | AJ15: 0 | AK15: 0 | AL15: =(BN15*P15/AX15)+AB15/O15*(BN15/AX15) -> 0 | AM15: =Q15+AB15+AL15+AK15+AJ15+T15+AE15 -> 2519.44 | AN15: 46116 | AO15: 36/IAD/27IN00002 | AP15: 832139000055796981 | AQ15: RETECK ENVIROTECH PRIVATE LIMITED | AR15: 27AAHCR2638B1ZK | AS15: Hyderabad Telangana 500081 | AT15: Vadgaon | AU15: Maharashtra | AW15: 8 | AX15: 339.008 | AY15: =AW15*AX15 -> 2712.064 | AZ15: =AW15=O15 -> TRUE | BA15: 0 | BB15: =AW15-BA15 -> 8 | BC15: 0 | BD15: Regular | BE15: 0 | BF15: 0 | BG15: 0 | BH15: 0 | BI15: 0 | BJ15: 0 | BK15: 0 | BL15: 0 | BM15: 0 | BN15: =AY15*$BM$3 -> 0 | BO15: =AY15+BL15+BM15+BN15+BC15+BG15 -> 2712.064 | BP15: =BO15-AM15 -> 192.624 | BQ15: =IF(BP15>=0,"Positive Margin","Negative Margin") -> Positive Margin | BR15: No Provision | BS15: =AY15-Y15-Q15-AA15-T15+BC15 -> 192.624 | BT15: =IF(BS15<0, "Negative Margin at Inception", "Positive Margin at Inception") -> Positive Margin at Inception | BU15: =IFERROR(BP15/BO15,"0") -> 0.071024873 | BV15: =IF(BU15<1%,"Less Than 1%",IF(BU15>2%,"More than 2%",IF(BU15>=1%,"1% - 2%"))) -> More than 2% | BW15: =BM15+BN15 -> 0 | BX15: =AL15+AK15 -> 0 | BY15: =BW15-BX15 -> 0 | BZ15: =BM15 -> 0 | CA15: =AK15 -> 0 | CB15: =BZ15-CA15 -> 0 | CC15: Marketplace (IT Assets Disposition) | CD15: 0 | CE15: =AM15-AL15-AA15 -> 2519.44 | CF15: =BO15-BN15 -> 2712.064 | CG15: =INT((D15- IF(MONTH(D15) >= 4, DATE(YEAR(D15), 4, 1), DATE(YEAR(D15)-1, 4, 1))) / 7) + 1 -> 1 | CH15: 0 | CI15: 0 | CJ15: =_xlfn.XLOOKUP(AP15,POC!B:B,POC!D:D) -> #N/A | CK15: =AY15-Q15 -> 192.624 | CL15: =CK15-Y15+Z15 -> 192.624 | CM15: =BO15-AM15 -> 192.624 | CN15: =AY15*118% -> 3200.2355 | CO15: =-Q15*118% -> -2972.9392 | CP15: =-BZ15*118% -> 0 | CQ15: =-CA15*118% -> 0 | CR15: =SUM(CN15:CQ15) -> 227.29632 | CS15: Telangana - HO | CT15: Telangana - HO | CU15: =MID(G15,3,10) -> AAACI4487J | CV15: =MID(AR15,3,10) -> AAHCR2638B | CW15: =H15&F15 -> 9102515564CYIENT LIMITED
B16: ="Q" & IF(ROUNDUP(MONTH(D16)/3,0)-1=0,4,ROUNDUP(MONTH(D16)/3,0)-1) -> Q1 | C16: =TEXT(AN16,"mmm-yy") -> Apr-26 | D16: 46115 | E16: SH04260602 | F16: M/S YAKSHIT TRADING | G16: 21BGNPG9019D1ZO | H16: 01 | I16: 46115 | J16: 26-27/PUR/000104 | K16: 46120 | L16: OD | M16: OD02BK4485 | N16: ITAD Mixed E Waste | O16: 700 | P16: 141.4 | Q16: =O16*P16 -> 98980 | R16: 0 | S16: =O16-R16 -> 700 | T16: 0 | U16: 0 | V16: 0 | W16: 0 | X16: 0 | Y16: 0 | Z16: 0 | AA16: 0 | AB16: =Y16+AA16+Z16 -> 0 | AC16: 0 | AD16: 0 | AE16: 0 | AF16: 0 | AG16: 0 | AH16: 0 | AI16: 0 | AJ16: 0 | AK16: 0 | AL16: =(BN16*P16/AX16)+AB16/O16*(BN16/AX16) -> 0 | AM16: =Q16+AB16+AL16+AK16+AJ16+T16+AE16 -> 98980 | AN16: 46120 | AO16: 36/IAD/27IN00003 | AP16: 832139000069594197 | AQ16: FALAH ENTERPRISES | AR16: 29DAKPA5526G1ZP | AS16: Khurda,Odisha,752050 | AT16: Bengaluru | AU16: Karnataka | AV16: 182394915927 | AW16: 700 | AX16: 208.232 | AY16: =AW16*AX16 -> 145762.4 | AZ16: =AW16=O16 -> TRUE | BA16: 0 | BB16: =AW16-BA16 -> 700 | BC16: 0 | BD16: Regular | BE16: 0 | BF16: 0 | BG16: 0 | BH16: 0 | BI16: 0 | BJ16: 0 | BK16: 0 | BL16: 0 | BM16: 0 | BN16: =AY16*$BM$3 -> 0 | BO16: =AY16+BL16+BM16+BN16+BC16+BG16 -> 145762.4 | BP16: =BO16-AM16 -> 46782.4 | BQ16: =IF(BP16>=0,"Positive Margin","Negative Margin") -> Positive Margin | BR16: No Provision | BS16: =AY16-Y16-Q16-AA16-T16+BC16 -> 46782.4 | BT16: =IF(BS16<0, "Negative Margin at Inception", "Positive Margin at Inception") -> Positive Margin at Inception | BU16: =IFERROR(BP16/BO16,"0") -> 0.32094971 | BV16: =IF(BU16<1%,"Less Than 1%",IF(BU16>2%,"More than 2%",IF(BU16>=1%,"1% - 2%"))) -> More than 2% | BW16: =BM16+BN16 -> 0 | BX16: =AL16+AK16 -> 0 | BY16: =BW16-BX16 -> 0 | BZ16: =BM16 -> 0 | CA16: =AK16 -> 0 | CB16: =BZ16-CA16 -> 0 | CC16: Marketplace (IT Assets Disposition) | CD16: 0 | CE16: =AM16-AL16-AA16 -> 98980 | CF16: =BO16-BN16 -> 145762.4 | CG16: =INT((D16- IF(MONTH(D16) >= 4, DATE(YEAR(D16), 4, 1), DATE(YEAR(D16)-1, 4, 1))) / 7) + 1 -> 1 | CH16: 0 | CI16: 0 | CJ16: =_xlfn.XLOOKUP(AP16,POC!B:B,POC!D:D) -> #N/A | CK16: =AY16-Q16 -> 46782.4 | CL16: =CK16-Y16+Z16 -> 46782.4 | CM16: =BO16-AM16 -> 46782.4 | CN16: =AY16*118% -> 171999.63 | CO16: =-Q16*118% -> -116796.4 | CP16: =-BZ16*118% -> 0 | CQ16: =-CA16*118% -> 0 | CR16: =SUM(CN16:CQ16) -> 55203.232 | CS16: Telangana - HO | CT16: Telangana - HO | CU16: =MID(G16,3,10) -> BGNPG9019D | CV16: =MID(AR16,3,10) -> DAKPA5526G | CW16: =H16&F16 -> 01M/S YAKSHIT TRADING
B17: ="Q" & IF(ROUNDUP(MONTH(D17)/3,0)-1=0,4,ROUNDUP(MONTH(D17)/3,0)-1) -> Q1 | C17: =TEXT(AN17,"mmm-yy") -> Apr-26 | D17: 46121 | E17: SH04261306 | F17: HYDERABAD EYE INSTITUTE | G17: 21AAATH0878B1Z8 | H17: 203000016 | I17: 46121 | J17: 26-27/PUR/000668 | K17: 46128 | L17: OD | M17: OD02CK1433 | N17: ITAD Mixed E Waste(Kg) | O17: 730 | P17: 33.9 | Q17: =O17*P17 -> 24747 | R17: 0 | S17: =O17-R17 -> 730 | T17: 0 | U17: 0 | V17: 0 | W17: 0 | X17: 0 | Y17: 0 | Z17: 0 | AA17: 0 | AB17: =Y17+AA17+Z17 -> 0 | AC17: 0 | AD17: 0 | AE17: 0 | AF17: 0 | AG17: 0 | AH17: 0 | AI17: 0 | AJ17: 0 | AK17: 0 | AL17: =(BN17*P17/AX17)+AB17/O17*(BN17/AX17) -> 0 | AM17: =Q17+AB17+AL17+AK17+AJ17+T17+AE17 -> 24747 | AN17: 46128 | AO17: 36/IAD/27IN00005 | AP17: 832139000069594197 | AQ17: FALAH ENTERPRISES | AR17: 29DAKPA5526G1ZP | AS17: Khordha Odisha 751024 | AT17: Bengaluru | AU17: Karnataka | AW17: 730 | AX17: 54.005 | AY17: =AW17*AX17 -> 39423.65 | AZ17: =AW17=O17 -> TRUE | BA17: 0 | BB17: =AW17-BA17 -> 730 | BC17: 0 | BD17: Regular | BE17: 0 | BF17: 0 | BG17: 0 | BH17: 0 | BI17: 0 | BJ17: 0 | BK17: 0 | BL17: 0 | BM17: 0 | BN17: =AY17*$BM$3 -> 0 | BO17: =AY17+BL17+BM17+BN17+BC17+BG17 -> 39423.65 | BP17: =BO17-AM17 -> 14676.65 | BQ17: =IF(BP17>=0,"Positive Margin","Negative Margin") -> Positive Margin | BR17: No Provision | BS17: =AY17-Y17-Q17-AA17-T17+BC17 -> 14676.65 | BT17: =IF(BS17<0, "Negative Margin at Inception", "Positive Margin at Inception") -> Positive Margin at Inception | BU17: =IFERROR(BP17/BO17,"0") -> 0.37228034 | BV17: =IF(BU17<1%,"Less Than 1%",IF(BU17>2%,"More than 2%",IF(BU17>=1%,"1% - 2%"))) -> More than 2% | BW17: =BM17+BN17 -> 0 | BX17: =AL17+AK17 -> 0 | BY17: =BW17-BX17 -> 0 | BZ17: =BM17 -> 0 | CA17: =AK17 -> 0 | CB17: =BZ17-CA17 -> 0 | CC17: Marketplace (IT Assets Disposition) | CD17: 0 | CE17: =AM17-AL17-AA17 -> 24747 | CF17: =BO17-BN17 -> 39423.65 | CG17: =INT((D17- IF(MONTH(D17) >= 4, DATE(YEAR(D17), 4, 1), DATE(YEAR(D17)-1, 4, 1))) / 7) + 1 -> 2 | CH17: 0 | CI17: 0 | CJ17: =_xlfn.XLOOKUP(AP17,POC!B:B,POC!D:D) -> #N/A | CK17: =AY17-Q17 -> 14676.65 | CL17: =CK17-Y17+Z17 -> 14676.65 | CM17: =BO17-AM17 -> 14676.65 | CN17: =AY17*118% -> 46519.907 | CO17: =-Q17*118% -> -29201.46 | CP17: =-BZ17*118% -> 0 | CQ17: =-CA17*118% -> 0 | CR17: =SUM(CN17:CQ17) -> 17318.447 | CS17: Telangana - HO | CT17: Telangana - HO | CU17: =MID(G17,3,10) -> AAATH0878B | CV17: =MID(AR17,3,10) -> DAKPA5526G | CW17: =H17&F17 -> 203000016HYDERABAD EYE INSTITUTE
B18: ="Q" & IF(ROUNDUP(MONTH(D18)/3,0)-1=0,4,ROUNDUP(MONTH(D18)/3,0)-1) -> Q1 | C18: =TEXT(AN18,"mmm-yy") -> Apr-26 | D18: 46126 | E18: SH042614012 | F18: CHAITANYA INDIA FIN CREDIT PRIVATE LIMITED | G18: 29AADCC6184H1ZE | H18: 2026290000000086 | I18: 46094 | J18: 26-27/PUR/000516 | K18: 46126 | L18: KA | N18: ITAD Mixed E Waste | O18: 37 | P18: 847 | Q18: =O18*P18 -> 31339 | R18: 0 | S18: =O18-R18 -> 37 | T18: 0 | U18: 0 | V18: 0 | W18: 0 | X18: 0 | Y18: 0 | Z18: 0 | AA18: 0 | AB18: =Y18+AA18+Z18 -> 0 | AC18: 0 | AD18: 0 | AE18: 0 | AF18: 0 | AG18: 0 | AH18: 0 | AI18: 0 | AJ18: 0 | AK18: 0 | AL18: =(BN18*P18/AX18)+AB18/O18*(BN18/AX18) -> 0 | AM18: =Q18+AB18+AL18+AK18+AJ18+T18+AE18 -> 31339 | AN18: 46126 | AO18: 29/IAD/27IN00003 | AP18: 832139000046796207 | AQ18: TRADEWIND BUSINESS SOLUTIONS LLP | AR18: 07AARFT3586D1ZR | AS18: Bengaluru,Karnataka,560070 | AT18: New Delhi | AU18: Delhi | AW18: 37 | AX18: 932.2 | AY18: =AW18*AX18 -> 34491.4 | AZ18: =AW18=O18 -> TRUE | BA18: 0 | BB18: =AW18-BA18 -> 37 | BC18: 0 | BD18: Regular | BE18: 0 | BF18: 0 | BG18: 0 | BH18: 0 | BI18: 0 | BJ18: 0 | BK18: 0 | BL18: 0 | BM18: 0 | BN18: =AY18*$BM$3 -> 0 | BO18: =AY18+BL18+BM18+BN18+BC18+BG18 -> 34491.4 | BP18: =BO18-AM18 -> 3152.4 | BQ18: =IF(BP18>=0,"Positive Margin","Negative Margin") -> Positive Margin | BR18: No Provision | BS18: =AY18-Y18-Q18-AA18-T18+BC18 -> 3152.4 | BT18: =IF(BS18<0, "Negative Margin at Inception", "Positive Margin at Inception") -> Positive Margin at Inception | BU18: =IFERROR(BP18/BO18,"0") -> 0.091396696 | BV18: =IF(BU18<1%,"Less Than 1%",IF(BU18>2%,"More than 2%",IF(BU18>=1%,"1% - 2%"))) -> More than 2% | BW18: =BM18+BN18 -> 0 | BX18: =AL18+AK18 -> 0 | BY18: =BW18-BX18 -> 0 | BZ18: =BM18 -> 0 | CA18: =AK18 -> 0 | CB18: =BZ18-CA18 -> 0 | CC18: Marketplace (IT Assets Disposition) | CD18: 0 | CE18: =AM18-AL18-AA18 -> 31339 | CF18: =BO18-BN18 -> 34491.4 | CG18: =INT((D18- IF(MONTH(D18) >= 4, DATE(YEAR(D18), 4, 1), DATE(YEAR(D18)-1, 4, 1))) / 7) + 1 -> 2 | CH18: 0 | CI18: 0 | CJ18: =_xlfn.XLOOKUP(AP18,POC!B:B,POC!D:D) -> #N/A | CK18: =AY18-Q18 -> 3152.4 | CL18: =CK18-Y18+Z18 -> 3152.4 | CM18: =BO18-AM18 -> 3152.4 | CN18: =AY18*118% -> 40699.852 | CO18: =-Q18*118% -> -36980.02 | CP18: =-BZ18*118% -> 0 | CQ18: =-CA18*118% -> 0 | CR18: =SUM(CN18:CQ18) -> 3719.832 | CS18: Telangana - HO | CT18: Telangana - HO | CU18: =MID(G18,3,10) -> AADCC6184H | CV18: =MID(AR18,3,10) -> AARFT3586D | CW18: =H18&F18 -> 2026290000000086CHAITANYA INDIA FIN CREDIT PRIVATE LIMITED
B19: ="Q" & IF(ROUNDUP(MONTH(D19)/3,0)-1=0,4,ROUNDUP(MONTH(D19)/3,0)-1) -> Q1 | C19: =TEXT(AN19,"mmm-yy") -> Apr-26 | D19: 46126 | E19: SH042614012 | F19: CHAITANYA INDIA FIN CREDIT PRIVATE LIMITED | G19: 29AADCC6184H1ZE | H19: 2026290000000086 | I19: 46094 | J19: 26-27/PUR/000516 | K19: 46126 | L19: KA | N19: ITAD Mixed E Waste | O19: 101 | P19: 1576 | Q19: =O19*P19 -> 159176 | R19: 0 | S19: =O19-R19 -> 101 | T19: 0 | U19: 0 | V19: 0 | W19: 0 | X19: 0 | Y19: 0 | Z19: 0 | AA19: 0 | AB19: =Y19+AA19+Z19 -> 0 | AC19: 0 | AD19: 0 | AE19: 0 | AF19: 0 | AG19: 0 | AH19: 0 | AI19: 0 | AJ19: 0 | AK19: 0 | AL19: =(BN19*P19/AX19)+AB19/O19*(BN19/AX19) -> 0 | AM19: =Q19+AB19+AL19+AK19+AJ19+T19+AE19 -> 159176 | AN19: 46126 | AO19: 29/IAD/27IN00003 | AP19: 832139000046796207 | AQ19: TRADEWIND BUSINESS SOLUTIONS LLP | AR19: 07AARFT3586D1ZR | AS19: Bengaluru,Karnataka,560070 | AT19: New Delhi | AU19: Delhi | AW19: 101 | AX19: 1733.9 | AY19: =AW19*AX19 -> 175123.9 | AZ19: =AW19=O19 -> TRUE | BA19: 0 | BB19: =AW19-BA19 -> 101 | BC19: 0 | BD19: Regular | BE19: 0 | BF19: 0 | BG19: 0 | BH19: 0 | BI19: 0 | BJ19: 0 | BK19: 0 | BL19: 0 | BM19: 0 | BN19: =AY19*$BM$3 -> 0 | BO19: =AY19+BL19+BM19+BN19+BC19+BG19 -> 175123.9 | BP19: =BO19-AM19 -> 15947.9 | BQ19: =IF(BP19>=0,"Positive Margin","Negative Margin") -> Positive Margin | BR19: No Provision | BS19: =AY19-Y19-Q19-AA19-T19+BC19 -> 15947.9 | BT19: =IF(BS19<0, "Negative Margin at Inception", "Positive Margin at Inception") -> Positive Margin at Inception | BU19: =IFERROR(BP19/BO19,"0") -> 0.091066382 | BV19: =IF(BU19<1%,"Less Than 1%",IF(BU19>2%,"More than 2%",IF(BU19>=1%,"1% - 2%"))) -> More than 2% | BW19: =BM19+BN19 -> 0 | BX19: =AL19+AK19 -> 0 | BY19: =BW19-BX19 -> 0 | BZ19: =BM19 -> 0 | CA19: =AK19 -> 0 | CB19: =BZ19-CA19 -> 0 | CC19: Marketplace (IT Assets Disposition) | CD19: 0 | CE19: =AM19-AL19-AA19 -> 159176 | CF19: =BO19-BN19 -> 175123.9 | CG19: =INT((D19- IF(MONTH(D19) >= 4, DATE(YEAR(D19), 4, 1), DATE(YEAR(D19)-1, 4, 1))) / 7) + 1 -> 2 | CH19: 0 | CI19: 0 | CJ19: =_xlfn.XLOOKUP(AP19,POC!B:B,POC!D:D) -> #N/A | CK19: =AY19-Q19 -> 15947.9 | CL19: =CK19-Y19+Z19 -> 15947.9 | CM19: =BO19-AM19 -> 15947.9 | CN19: =AY19*118% -> 206646.2 | CO19: =-Q19*118% -> -187827.68 | CP19: =-BZ19*118% -> 0 | CQ19: =-CA19*118% -> 0 | CR19: =SUM(CN19:CQ19) -> 18818.522 | CS19: Telangana - HO | CT19: Telangana - HO | CU19: =MID(G19,3,10) -> AADCC6184H | CV19: =MID(AR19,3,10) -> AARFT3586D | CW19: =H19&F19 -> 2026290000000086CHAITANYA INDIA FIN CREDIT PRIVATE LIMITED
B20: ="Q" & IF(ROUNDUP(MONTH(D20)/3,0)-1=0,4,ROUNDUP(MONTH(D20)/3,0)-1) -> Q1 | C20: =TEXT(AN20,"mmm-yy") -> Apr-26 | D20: 46126 | E20: SH042614012 | F20: CHAITANYA INDIA FIN CREDIT PRIVATE LIMITED | G20: 29AADCC6184H1ZE | H20: 2026290000000086 | I20: 46094 | J20: 26-27/PUR/000516 | K20: 46126 | L20: KA | N20: ITAD Mixed E Waste | O20: 41 | P20: 85 | Q20: =O20*P20 -> 3485 | R20: 0 | S20: =O20-R20 -> 41 | T20: 0 | U20: 0 | V20: 0 | W20: 0 | X20: 0 | Y20: 0 | Z20: 0 | AA20: 0 | AB20: =Y20+AA20+Z20 -> 0 | AC20: 0 | AD20: 0 | AE20: 0 | AF20: 0 | AG20: 0 | AH20: 0 | AI20: 0 | AJ20: 0 | AK20: 0 | AL20: =(BN20*P20/AX20)+AB20/O20*(BN20/AX20) -> 0 | AM20: =Q20+AB20+AL20+AK20+AJ20+T20+AE20 -> 3485 | AN20: 46126 | AO20: 29/IAD/27IN00003 | AP20: 832139000046796207 | AQ20: TRADEWIND BUSINESS SOLUTIONS LLP | AR20: 07AARFT3586D1ZR | AS20: Bengaluru,Karnataka,560070 | AT20: New Delhi | AU20: Delhi | AW20: 41 | AX20: 93.22 | AY20: =AW20*AX20 -> 3822.02 | AZ20: =AW20=O20 -> TRUE | BA20: 0 | BB20: =AW20-BA20 -> 41 | BC20: 0 | BD20: Regular | BE20: 0 | BF20: 0 | BG20: 0 | BH20: 0 | BI20: 0 | BJ20: 0 | BK20: 0 | BL20: 0 | BM20: 0 | BN20: =AY20*$BM$3 -> 0 | BO20: =AY20+BL20+BM20+BN20+BC20+BG20 -> 3822.02 | BP20: =BO20-AM20 -> 337.02 | BQ20: =IF(BP20>=0,"Positive Margin","Negative Margin") -> Positive Margin | BR20: No Provision | BS20: =AY20-Y20-Q20-AA20-T20+BC20 -> 337.02 | BT20: =IF(BS20<0, "Negative Margin at Inception", "Positive Margin at Inception") -> Positive Margin at Inception | BU20: =IFERROR(BP20/BO20,"0") -> 0.088178502 | BV20: =IF(BU20<1%,"Less Than 1%",IF(BU20>2%,"More than 2%",IF(BU20>=1%,"1% - 2%"))) -> More than 2% | BW20: =BM20+BN20 -> 0 | BX20: =AL20+AK20 -> 0 | BY20: =BW20-BX20 -> 0 | BZ20: =BM20 -> 0 | CA20: =AK20 -> 0 | CB20: =BZ20-CA20 -> 0 | CC20: Marketplace (IT Assets Disposition) | CD20: 0 | CE20: =AM20-AL20-AA20 -> 3485 | CF20: =BO20-BN20 -> 3822.02 | CG20: =INT((D20- IF(MONTH(D20) >= 4, DATE(YEAR(D20), 4, 1), DATE(YEAR(D20)-1, 4, 1))) / 7) + 1 -> 2 | CH20: 0 | CI20: 0 | CJ20: =_xlfn.XLOOKUP(AP20,POC!B:B,POC!D:D) -> #N/A | CK20: =AY20-Q20 -> 337.02 | CL20: =CK20-Y20+Z20 -> 337.02 | CM20: =BO20-AM20 -> 337.02 | CN20: =AY20*118% -> 4509.9836 | CO20: =-Q20*118% -> -4112.3 | CP20: =-BZ20*118% -> 0 | CQ20: =-CA20*118% -> 0 | CR20: =SUM(CN20:CQ20) -> 397.6836 | CS20: Telangana - HO | CT20: Telangana - HO | CU20: =MID(G20,3,10) -> AADCC6184H | CV20: =MID(AR20,3,10) -> AARFT3586D | CW20: =H20&F20 -> 2026290000000086CHAITANYA INDIA FIN CREDIT PRIVATE LIMITED
B21: ="Q" & IF(ROUNDUP(MONTH(D21)/3,0)-1=0,4,ROUNDUP(MONTH(D21)/3,0)-1) -> Q1 | C21: =TEXT(AN21,"mmm-yy") -> Apr-26 | D21: 46126 | E21: SH042614012 | F21: CHAITANYA INDIA FIN CREDIT PRIVATE LIMITED | G21: 29AADCC6184H1ZE | H21: 2026290000000086 | I21: 46094 | J21: 26-27/PUR/000516 | K21: 46126 | L21: KA | N21: ITAD Mixed E Waste | O21: 1 | P21: 85 | Q21: =O21*P21 -> 85 | R21: 0 | S21: =O21-R21 -> 1 | T21: 0 | U21: 0 | V21: 0 | W21: 0 | X21: 0 | Y21: 0 | Z21: 0 | AA21: 0 | AB21: =Y21+AA21+Z21 -> 0 | AC21: 0 | AD21: 0 | AE21: 0 | AF21: 0 | AG21: 0 | AH21: 0 | AI21: 0 | AJ21: 0 | AK21: 0 | AL21: =(BN21*P21/AX21)+AB21/O21*(BN21/AX21) -> 0 | AM21: =Q21+AB21+AL21+AK21+AJ21+T21+AE21 -> 85 | AN21: 46126 | AO21: 29/IAD/27IN00003 | AP21: 832139000046796207 | AQ21: TRADEWIND BUSINESS SOLUTIONS LLP | AR21: 07AARFT3586D1ZR | AS21: Bengaluru,Karnataka,560070 | AT21: New Delhi | AU21: Delhi | AW21: 1 | AX21: 93.22 | AY21: =AW21*AX21 -> 93.22 | AZ21: =AW21=O21 -> TRUE | BA21: 0 | BB21: =AW21-BA21 -> 1 | BC21: 0 | BD21: Regular | BE21: 0 | BF21: 0 | BG21: 0 | BH21: 0 | BI21: 0 | BJ21: 0 | BK21: 0 | BL21: 0 | BM21: 0 | BN21: =AY21*$BM$3 -> 0 | BO21: =AY21+BL21+BM21+BN21+BC21+BG21 -> 93.22 | BP21: =BO21-AM21 -> 8.22 | BQ21: =IF(BP21>=0,"Positive Margin","Negative Margin") -> Positive Margin | BR21: No Provision | BS21: =AY21-Y21-Q21-AA21-T21+BC21 -> 8.22 | BT21: =IF(BS21<0, "Negative Margin at Inception", "Positive Margin at Inception") -> Positive Margin at Inception | BU21: =IFERROR(BP21/BO21,"0") -> 0.088178502 | BV21: =IF(BU21<1%,"Less Than 1%",IF(BU21>2%,"More than 2%",IF(BU21>=1%,"1% - 2%"))) -> More than 2% | BW21: =BM21+BN21 -> 0 | BX21: =AL21+AK21 -> 0 | BY21: =BW21-BX21 -> 0 | BZ21: =BM21 -> 0 | CA21: =AK21 -> 0 | CB21: =BZ21-CA21 -> 0 | CC21: Marketplace (IT Assets Disposition) | CD21: 0 | CE21: =AM21-AL21-AA21 -> 85 | CF21: =BO21-BN21 -> 93.22 | CG21: =INT((D21- IF(MONTH(D21) >= 4, DATE(YEAR(D21), 4, 1), DATE(YEAR(D21)-1, 4, 1))) / 7) + 1 -> 2 | CH21: 0 | CI21: 0 | CJ21: =_xlfn.XLOOKUP(AP21,POC!B:B,POC!D:D) -> #N/A | CK21: =AY21-Q21 -> 8.22 | CL21: =CK21-Y21+Z21 -> 8.22 | CM21: =BO21-AM21 -> 8.22 | CN21: =AY21*118% -> 109.9996 | CO21: =-Q21*118% -> -100.3 | CP21: =-BZ21*118% -> 0 | CQ21: =-CA21*118% -> 0 | CR21: =SUM(CN21:CQ21) -> 9.6996 | CS21: Telangana - HO | CT21: Telangana - HO | CU21: =MID(G21,3,10) -> AADCC6184H | CV21: =MID(AR21,3,10) -> AARFT3586D | CW21: =H21&F21 -> 2026290000000086CHAITANYA INDIA FIN CREDIT PRIVATE LIMITED
B22: ="Q" & IF(ROUNDUP(MONTH(D22)/3,0)-1=0,4,ROUNDUP(MONTH(D22)/3,0)-1) -> Q1 | C22: =TEXT(AN22,"mmm-yy") -> Apr-26 | D22: 46126 | E22: SH042614012 | F22: CHAITANYA INDIA FIN CREDIT PRIVATE LIMITED | G22: 29AADCC6184H1ZE | H22: 2026290000000086 | I22: 46094 | J22: 26-27/PUR/000516 | K22: 46126 | L22: KA | N22: ITAD Mixed E Waste | O22: 1 | P22: 1780 | Q22: =O22*P22 -> 1780 | R22: 0 | S22: =O22-R22 -> 1 | T22: 0 | U22: 0 | V22: 0 | W22: 0 | X22: 0 | Y22: 0 | Z22: 0 | AA22: 0 | AB22: =Y22+AA22+Z22 -> 0 | AC22: 0 | AD22: 0 | AE22: 0 | AF22: 0 | AG22: 0 | AH22: 0 | AI22: 0 | AJ22: 0 | AK22: 0 | AL22: =(BN22*P22/AX22)+AB22/O22*(BN22/AX22) -> 0 | AM22: =Q22+AB22+AL22+AK22+AJ22+T22+AE22 -> 1780 | AN22: 46126 | AO22: 29/IAD/27IN00003 | AP22: 832139000046796207 | AQ22: TRADEWIND BUSINESS SOLUTIONS LLP | AR22: 07AARFT3586D1ZR | AS22: Bengaluru,Karnataka,560070 | AT22: New Delhi | AU22: Delhi | AW22: 1 | AX22: 2669.49 | AY22: =AW22*AX22 -> 2669.49 | AZ22: =AW22=O22 -> TRUE | BA22: 0 | BB22: =AW22-BA22 -> 1 | BC22: 0 | BD22: Regular | BE22: 0 | BF22: 0 | BG22: 0 | BH22: 0 | BI22: 0 | BJ22: 0 | BK22: 0 | BL22: 0 | BM22: 0 | BN22: =AY22*$BM$3 -> 0 | BO22: =AY22+BL22+BM22+BN22+BC22+BG22 -> 2669.49 | BP22: =BO22-AM22 -> 889.49 | BQ22: =IF(BP22>=0,"Positive Margin","Negative Margin") -> Positive Margin | BR22: No Provision | BS22: =AY22-Y22-Q22-AA22-T22+BC22 -> 889.49 | BT22: =IF(BS22<0, "Negative Margin at Inception", "Positive Margin at Inception") -> Positive Margin at Inception | BU22: =IFERROR(BP22/BO22,"0") -> 0.33320597 | BV22: =IF(BU22<1%,"Less Than 1%",IF(BU22>2%,"More than 2%",IF(BU22>=1%,"1% - 2%"))) -> More than 2% | BW22: =BM22+BN22 -> 0 | BX22: =AL22+AK22 -> 0 | BY22: =BW22-BX22 -> 0 | BZ22: =BM22 -> 0 | CA22: =AK22 -> 0 | CB22: =BZ22-CA22 -> 0 | CC22: Marketplace (IT Assets Disposition) | CD22: 0 | CE22: =AM22-AL22-AA22 -> 1780 | CF22: =BO22-BN22 -> 2669.49 | CG22: =INT((D22- IF(MONTH(D22) >= 4, DATE(YEAR(D22), 4, 1), DATE(YEAR(D22)-1, 4, 1))) / 7) + 1 -> 2 | CH22: 0 | CI22: 0 | CJ22: =_xlfn.XLOOKUP(AP22,POC!B:B,POC!D:D) -> #N/A | CK22: =AY22-Q22 -> 889.49 | CL22: =CK22-Y22+Z22 -> 889.49 | CM22: =BO22-AM22 -> 889.49 | CN22: =AY22*118% -> 3149.9982 | CO22: =-Q22*118% -> -2100.4 | CP22: =-BZ22*118% -> 0 | CQ22: =-CA22*118% -> 0 | CR22: =SUM(CN22:CQ22) -> 1049.5982 | CS22: Telangana - HO | CT22: Telangana - HO | CU22: =MID(G22,3,10) -> AADCC6184H | CV22: =MID(AR22,3,10) -> AARFT3586D | CW22: =H22&F22 -> 2026290000000086CHAITANYA INDIA FIN CREDIT PRIVATE LIMITED
B23: ="Q" & IF(ROUNDUP(MONTH(D23)/3,0)-1=0,4,ROUNDUP(MONTH(D23)/3,0)-1) -> Q1 | C23: =TEXT(AN23,"mmm-yy") -> Apr-26 | D23: 46126 | E23: SH042614012 | F23: CHAITANYA INDIA FIN CREDIT PRIVATE LIMITED | G23: 29AADCC6184H1ZE | H23: 2026290000000086 | I23: 46094 | J23: 26-27/PUR/000516 | K23: 46126 | L23: KA | N23: ITAD Mixed E Waste | O23: 1 | P23: 1356 | Q23: =O23*P23 -> 1356 | R23: 0 | S23: =O23-R23 -> 1 | T23: 0 | U23: 0 | V23: 0 | W23: 0 | X23: 0 | Y23: 0 | Z23: 0 | AA23: 0 | AB23: =Y23+AA23+Z23 -> 0 | AC23: 0 | AD23: 0 | AE23: 0 | AF23: 0 | AG23: 0 | AH23: 0 | AI23: 0 | AJ23: 0 | AK23: 0 | AL23: =(BN23*P23/AX23)+AB23/O23*(BN23/AX23) -> 0 | AM23: =Q23+AB23+AL23+AK23+AJ23+T23+AE23 -> 1356 | AN23: 46126 | AO23: 29/IAD/27IN00003 | AP23: 832139000046796207 | AQ23: TRADEWIND BUSINESS SOLUTIONS LLP | AR23: 07AARFT3586D1ZR | AS23: Bengaluru,Karnataka,560070 | AT23: New Delhi | AU23: Delhi | AW23: 1 | AX23: 2033.9 | AY23: =AW23*AX23 -> 2033.9 | AZ23: =AW23=O23 -> TRUE | BA23: 0 | BB23: =AW23-BA23 -> 1 | BC23: 0 | BD23: Regular | BE23: 0 | BF23: 0 | BG23: 0 | BH23: 0 | BI23: 0 | BJ23: 0 | BK23: 0 | BL23: 0 | BM23: 0 | BN23: =AY23*$BM$3 -> 0 | BO23: =AY23+BL23+BM23+BN23+BC23+BG23 -> 2033.9 | BP23: =BO23-AM23 -> 677.9 | BQ23: =IF(BP23>=0,"Positive Margin","Negative Margin") -> Positive Margin | BR23: No Provision | BS23: =AY23-Y23-Q23-AA23-T23+BC23 -> 677.9 | BT23: =IF(BS23<0, "Negative Margin at Inception", "Positive Margin at Inception") -> Positive Margin at Inception | BU23: =IFERROR(BP23/BO23,"0") -> 0.33330056 | BV23: =IF(BU23<1%,"Less Than 1%",IF(BU23>2%,"More than 2%",IF(BU23>=1%,"1% - 2%"))) -> More than 2% | BW23: =BM23+BN23 -> 0 | BX23: =AL23+AK23 -> 0 | BY23: =BW23-BX23 -> 0 | BZ23: =BM23 -> 0 | CA23: =AK23 -> 0 | CB23: =BZ23-CA23 -> 0 | CC23: Marketplace (IT Assets Disposition) | CD23: 0 | CE23: =AM23-AL23-AA23 -> 1356 | CF23: =BO23-BN23 -> 2033.9 | CG23: =INT((D23- IF(MONTH(D23) >= 4, DATE(YEAR(D23), 4, 1), DATE(YEAR(D23)-1, 4, 1))) / 7) + 1 -> 2 | CH23: 0 | CI23: 0 | CJ23: =_xlfn.XLOOKUP(AP23,POC!B:B,POC!D:D) -> #N/A | CK23: =AY23-Q23 -> 677.9 | CL23: =CK23-Y23+Z23 -> 677.9 | CM23: =BO23-AM23 -> 677.9 | CN23: =AY23*118% -> 2400.002 | CO23: =-Q23*118% -> -1600.08 | CP23: =-BZ23*118% -> 0 | CQ23: =-CA23*118% -> 0 | CR23: =SUM(CN23:CQ23) -> 799.922 | CS23: Telangana - HO | CT23: Telangana - HO | CU23: =MID(G23,3,10) -> AADCC6184H | CV23: =MID(AR23,3,10) -> AARFT3586D | CW23: =H23&F23 -> 2026290000000086CHAITANYA INDIA FIN CREDIT PRIVATE LIMITED
B24: ="Q" & IF(ROUNDUP(MONTH(D24)/3,0)-1=0,4,ROUNDUP(MONTH(D24)/3,0)-1) -> Q1 | C24: =TEXT(AN24,"mmm-yy") -> Apr-26 | D24: 46128 | E24: SH04261602 | F24: CHAITANYA INDIA FIN CREDIT PRIVATE LIMITED | G24: 29AADCC6184H1ZE | H24: 2026290000000099 | I24: 46094 | J24: 26-27/PUR/000696 | K24: 46128 | L24: KA | N24: ITAD Mixed E Waste | O24: 15 | P24: 847 | Q24: =O24*P24 -> 12705 | R24: 0 | S24: =O24-R24 -> 15 | T24: 0 | U24: 0 | V24: 0 | W24: 0 | X24: 0 | Y24: 0 | Z24: 0 | AA24: 0 | AB24: =Y24+AA24+Z24 -> 0 | AC24: 0 | AD24: 0 | AE24: 0 | AF24: 0 | AG24: 0 | AH24: 0 | AI24: 0 | AJ24: 0 | AK24: 0 | AL24: =(BN24*P24/AX24)+AB24/O24*(BN24/AX24) -> 0 | AM24: =Q24+AB24+AL24+AK24+AJ24+T24+AE24 -> 12705 | AN24: 46128 | AO24: 29/IAD/27IN00004 | AP24: 832139000046796207 | AQ24: TRADEWIND BUSINESS SOLUTIONS LLP | AR24: 07AARFT3586D1ZR | AS24: Bengaluru,Karnataka,560070 | AT24: New Delhi | AU24: Delhi | AW24: 15 | AX24: 932.2 | AY24: =AW24*AX24 -> 13983 | AZ24: =AW24=O24 -> TRUE | BA24: 0 | BB24: =AW24-BA24 -> 15 | BC24: 0 | BD24: Regular | BE24: 0 | BF24: 0 | BG24: 0 | BH24: 0 | BI24: 0 | BJ24: 0 | BK24: 0 | BL24: 0 | BM24: 0 | BN24: =AY24*$BM$3 -> 0 | BO24: =AY24+BL24+BM24+BN24+BC24+BG24 -> 13983 | BP24: =BO24-AM24 -> 1278 | BQ24: =IF(BP24>=0,"Positive Margin","Negative Margin") -> Positive Margin | BR24: No Provision | BS24: =AY24-Y24-Q24-AA24-T24+BC24 -> 1278 | BT24: =IF(BS24<0, "Negative Margin at Inception", "Positive Margin at Inception") -> Positive Margin at Inception | BU24: =IFERROR(BP24/BO24,"0") -> 0.091396696 | BV24: =IF(BU24<1%,"Less Than 1%",IF(BU24>2%,"More than 2%",IF(BU24>=1%,"1% - 2%"))) -> More than 2% | BW24: =BM24+BN24 -> 0 | BX24: =AL24+AK24 -> 0 | BY24: =BW24-BX24 -> 0 | BZ24: =BM24 -> 0 | CA24: =AK24 -> 0 | CB24: =BZ24-CA24 -> 0 | CC24: Marketplace (IT Assets Disposition) | CD24: 0 | CE24: =AM24-AL24-AA24 -> 12705 | CF24: =BO24-BN24 -> 13983 | CG24: =INT((D24- IF(MONTH(D24) >= 4, DATE(YEAR(D24), 4, 1), DATE(YEAR(D24)-1, 4, 1))) / 7) + 1 -> 3 | CH24: 0 | CI24: 0 | CJ24: =_xlfn.XLOOKUP(AP24,POC!B:B,POC!D:D) -> #N/A | CK24: =AY24-Q24 -> 1278 | CL24: =CK24-Y24+Z24 -> 1278 | CM24: =BO24-AM24 -> 1278 | CN24: =AY24*118% -> 16499.94 | CO24: =-Q24*118% -> -14991.9 | CP24: =-BZ24*118% -> 0 | CQ24: =-CA24*118% -> 0 | CR24: =SUM(CN24:CQ24) -> 1508.04 | CS24: Telangana - HO | CT24: Telangana - HO | CU24: =MID(G24,3,10) -> AADCC6184H | CV24: =MID(AR24,3,10) -> AARFT3586D | CW24: =H24&F24 -> 2026290000000099CHAITANYA INDIA FIN CREDIT PRIVATE LIMITED
B25: ="Q" & IF(ROUNDUP(MONTH(D25)/3,0)-1=0,4,ROUNDUP(MONTH(D25)/3,0)-1) -> Q1 | C25: =TEXT(AN25,"mmm-yy") -> Apr-26 | D25: 46128 | E25: SH04261602 | F25: CHAITANYA INDIA FIN CREDIT PRIVATE LIMITED | G25: 29AADCC6184H1ZE | H25: 2026290000000099 | I25: 46094 | J25: 26-27/PUR/000696 | K25: 46128 | L25: KA | N25: ITAD Mixed E Waste | O25: 66 | P25: 1576 | Q25: =O25*P25 -> 104016 | R25: 0 | S25: =O25-R25 -> 66 | T25: 0 | U25: 0 | V25: 0 | W25: 0 | X25: 0 | Y25: 0 | Z25: 0 | AA25: 0 | AB25: =Y25+AA25+Z25 -> 0 | AC25: 0 | AD25: 0 | AE25: 0 | AF25: 0 | AG25: 0 | AH25: 0 | AI25: 0 | AJ25: 0 | AK25: 0 | AL25: =(BN25*P25/AX25)+AB25/O25*(BN25/AX25) -> 0 | AM25: =Q25+AB25+AL25+AK25+AJ25+T25+AE25 -> 104016 | AN25: 46128 | AO25: 29/IAD/27IN00004 | AP25: 832139000046796207 | AQ25: TRADEWIND BUSINESS SOLUTIONS LLP | AR25: 07AARFT3586D1ZR | AS25: Bengaluru,Karnataka,560070 | AT25: New Delhi | AU25: Delhi | AW25: 66 | AX25: 1733.9 | AY25: =AW25*AX25 -> 114437.4 | AZ25: =AW25=O25 -> TRUE | BA25: 0 | BB25: =AW25-BA25 -> 66 | BC25: 0 | BD25: Regular | BE25: 0 | BF25: 0 | BG25: 0 | BH25: 0 | BI25: 0 | BJ25: 0 | BK25: 0 | BL25: 0 | BM25: 0 | BN25: =AY25*$BM$3 -> 0 | BO25: =AY25+BL25+BM25+BN25+BC25+BG25 -> 114437.4 | BP25: =BO25-AM25 -> 10421.4 | BQ25: =IF(BP25>=0,"Positive Margin","Negative Margin") -> Positive Margin | BR25: No Provision | BS25: =AY25-Y25-Q25-AA25-T25+BC25 -> 10421.4 | BT25: =IF(BS25<0, "Negative Margin at Inception", "Positive Margin at Inception") -> Positive Margin at Inception | BU25: =IFERROR(BP25/BO25,"0") -> 0.091066382 | BV25: =IF(BU25<1%,"Less Than 1%",IF(BU25>2%,"More than 2%",IF(BU25>=1%,"1% - 2%"))) -> More than 2% | BW25: =BM25+BN25 -> 0 | BX25: =AL25+AK25 -> 0 | BY25: =BW25-BX25 -> 0 | BZ25: =BM25 -> 0 | CA25: =AK25 -> 0 | CB25: =BZ25-CA25 -> 0 | CC25: Marketplace (IT Assets Disposition) | CD25: 0 | CE25: =AM25-AL25-AA25 -> 104016 | CF25: =BO25-BN25 -> 114437.4 | CG25: =INT((D25- IF(MONTH(D25) >= 4, DATE(YEAR(D25), 4, 1), DATE(YEAR(D25)-1, 4, 1))) / 7) + 1 -> 3 | CH25: 0 | CI25: 0 | CJ25: =_xlfn.XLOOKUP(AP25,POC!B:B,POC!D:D) -> #N/A | CK25: =AY25-Q25 -> 10421.4 | CL25: =CK25-Y25+Z25 -> 10421.4 | CM25: =BO25-AM25 -> 10421.4 | CN25: =AY25*118% -> 135036.13 | CO25: =-Q25*118% -> -122738.88 | CP25: =-BZ25*118% -> 0 | CQ25: =-CA25*118% -> 0 | CR25: =SUM(CN25:CQ25) -> 12297.252 | CS25: Telangana - HO | CT25: Telangana - HO | CU25: =MID(G25,3,10) -> AADCC6184H | CV25: =MID(AR25,3,10) -> AARFT3586D | CW25: =H25&F25 -> 2026290000000099CHAITANYA INDIA FIN CREDIT PRIVATE LIMITED
B26: ="Q" & IF(ROUNDUP(MONTH(D26)/3,0)-1=0,4,ROUNDUP(MONTH(D26)/3,0)-1) -> Q1 | C26: =TEXT(AN26,"mmm-yy") -> Apr-26 | D26: 46128 | E26: SH04261602 | F26: CHAITANYA INDIA FIN CREDIT PRIVATE LIMITED | G26: 29AADCC6184H1ZE | H26: 2026290000000099 | I26: 46094 | J26: 26-27/PUR/000696 | K26: 46128 | L26: KA | N26: ITAD Mixed E Waste | O26: 17 | P26: 85 | Q26: =O26*P26 -> 1445 | R26: 0 | S26: =O26-R26 -> 17 | T26: 0 | U26: 0 | V26: 0 | W26: 0 | X26: 0 | Y26: 0 | Z26: 0 | AA26: 0 | AB26: =Y26+AA26+Z26 -> 0 | AC26: 0 | AD26: 0 | AE26: 0 | AF26: 0 | AG26: 0 | AH26: 0 | AI26: 0 | AJ26: 0 | AK26: 0 | AL26: =(BN26*P26/AX26)+AB26/O26*(BN26/AX26) -> 0 | AM26: =Q26+AB26+AL26+AK26+AJ26+T26+AE26 -> 1445 | AN26: 46128 | AO26: 29/IAD/27IN00004 | AP26: 832139000046796207 | AQ26: TRADEWIND BUSINESS SOLUTIONS LLP | AR26: 07AARFT3586D1ZR | AS26: Bengaluru,Karnataka,560070 | AT26: New Delhi | AU26: Delhi | AW26: 17 | AX26: 93.22 | AY26: =AW26*AX26 -> 1584.74 | AZ26: =AW26=O26 -> TRUE | BA26: 0 | BB26: =AW26-BA26 -> 17 | BC26: 0 | BD26: Regular | BE26: 0 | BF26: 0 | BG26: 0 | BH26: 0 | BI26: 0 | BJ26: 0 | BK26: 0 | BL26: 0 | BM26: 0 | BN26: =AY26*$BM$3 -> 0 | BO26: =AY26+BL26+BM26+BN26+BC26+BG26 -> 1584.74 | BP26: =BO26-AM26 -> 139.74 | BQ26: =IF(BP26>=0,"Positive Margin","Negative Margin") -> Positive Margin | BR26: No Provision | BS26: =AY26-Y26-Q26-AA26-T26+BC26 -> 139.74 | BT26: =IF(BS26<0, "Negative Margin at Inception", "Positive Margin at Inception") -> Positive Margin at Inception | BU26: =IFERROR(BP26/BO26,"0") -> 0.088178502 | BV26: =IF(BU26<1%,"Less Than 1%",IF(BU26>2%,"More than 2%",IF(BU26>=1%,"1% - 2%"))) -> More than 2% | BW26: =BM26+BN26 -> 0 | BX26: =AL26+AK26 -> 0 | BY26: =BW26-BX26 -> 0 | BZ26: =BM26 -> 0 | CA26: =AK26 -> 0 | CB26: =BZ26-CA26 -> 0 | CC26: Marketplace (IT Assets Disposition) | CD26: 0 | CE26: =AM26-AL26-AA26 -> 1445 | CF26: =BO26-BN26 -> 1584.74 | CG26: =INT((D26- IF(MONTH(D26) >= 4, DATE(YEAR(D26), 4, 1), DATE(YEAR(D26)-1, 4, 1))) / 7) + 1 -> 3 | CH26: 0 | CI26: 0 | CJ26: =_xlfn.XLOOKUP(AP26,POC!B:B,POC!D:D) -> #N/A | CK26: =AY26-Q26 -> 139.74 | CL26: =CK26-Y26+Z26 -> 139.74 | CM26: =BO26-AM26 -> 139.74 | CN26: =AY26*118% -> 1869.9932 | CO26: =-Q26*118% -> -1705.1 | CP26: =-BZ26*118% -> 0 | CQ26: =-CA26*118% -> 0 | CR26: =SUM(CN26:CQ26) -> 164.8932 | CS26: Telangana - HO | CT26: Telangana - HO | CU26: =MID(G26,3,10) -> AADCC6184H | CV26: =MID(AR26,3,10) -> AARFT3586D | CW26: =H26&F26 -> 2026290000000099CHAITANYA INDIA FIN CREDIT PRIVATE LIMITED
B27: ="Q" & IF(ROUNDUP(MONTH(D27)/3,0)-1=0,4,ROUNDUP(MONTH(D27)/3,0)-1) -> Q1 | C27: =TEXT(AN27,"mmm-yy") -> Apr-26 | D27: 46128 | E27: SH04261602 | F27: CHAITANYA INDIA FIN CREDIT PRIVATE LIMITED | G27: 29AADCC6184H1ZE | H27: 2026290000000099 | I27: 46094 | J27: 26-27/PUR/000696 | K27: 46128 | L27: KA | N27: ITAD Mixed E Waste | O27: 1 | P27: 85 | Q27: =O27*P27 -> 85 | R27: 0 | S27: =O27-R27 -> 1 | T27: 0 | U27: 0 | V27: 0 | W27: 0 | X27: 0 | Y27: 0 | Z27: 0 | AA27: 0 | AB27: =Y27+AA27+Z27 -> 0 | AC27: 0 | AD27: 0 | AE27: 0 | AF27: 0 | AG27: 0 | AH27: 0 | AI27: 0 | AJ27: 0 | AK27: 0 | AL27: =(BN27*P27/AX27)+AB27/O27*(BN27/AX27) -> 0 | AM27: =Q27+AB27+AL27+AK27+AJ27+T27+AE27 -> 85 | AN27: 46128 | AO27: 29/IAD/27IN00004 | AP27: 832139000046796207 | AQ27: TRADEWIND BUSINESS SOLUTIONS LLP | AR27: 07AARFT3586D1ZR | AS27: Bengaluru,Karnataka,560070 | AT27: New Delhi | AU27: Delhi | AW27: 1 | AX27: 93.22 | AY27: =AW27*AX27 -> 93.22 | AZ27: =AW27=O27 -> TRUE | BA27: 0 | BB27: =AW27-BA27 -> 1 | BC27: 0 | BD27: Regular | BE27: 0 | BF27: 0 | BG27: 0 | BH27: 0 | BI27: 0 | BJ27: 0 | BK27: 0 | BL27: 0 | BM27: 0 | BN27: =AY27*$BM$3 -> 0 | BO27: =AY27+BL27+BM27+BN27+BC27+BG27 -> 93.22 | BP27: =BO27-AM27 -> 8.22 | BQ27: =IF(BP27>=0,"Positive Margin","Negative Margin") -> Positive Margin | BR27: No Provision | BS27: =AY27-Y27-Q27-AA27-T27+BC27 -> 8.22 | BT27: =IF(BS27<0, "Negative Margin at Inception", "Positive Margin at Inception") -> Positive Margin at Inception | BU27: =IFERROR(BP27/BO27,"0") -> 0.088178502 | BV27: =IF(BU27<1%,"Less Than 1%",IF(BU27>2%,"More than 2%",IF(BU27>=1%,"1% - 2%"))) -> More than 2% | BW27: =BM27+BN27 -> 0 | BX27: =AL27+AK27 -> 0 | BY27: =BW27-BX27 -> 0 | BZ27: =BM27 -> 0 | CA27: =AK27 -> 0 | CB27: =BZ27-CA27 -> 0 | CC27: Marketplace (IT Assets Disposition) | CD27: 0 | CE27: =AM27-AL27-AA27 -> 85 | CF27: =BO27-BN27 -> 93.22 | CG27: =INT((D27- IF(MONTH(D27) >= 4, DATE(YEAR(D27), 4, 1), DATE(YEAR(D27)-1, 4, 1))) / 7) + 1 -> 3 | CH27: 0 | CI27: 0 | CJ27: =_xlfn.XLOOKUP(AP27,POC!B:B,POC!D:D) -> #N/A | CK27: =AY27-Q27 -> 8.22 | CL27: =CK27-Y27+Z27 -> 8.22 | CM27: =BO27-AM27 -> 8.22 | CN27: =AY27*118% -> 109.9996 | CO27: =-Q27*118% -> -100.3 | CP27: =-BZ27*118% -> 0 | CQ27: =-CA27*118% -> 0 | CR27: =SUM(CN27:CQ27) -> 9.6996 | CS27: Telangana - HO | CT27: Telangana - HO | CU27: =MID(G27,3,10) -> AADCC6184H | CV27: =MID(AR27,3,10) -> AARFT3586D | CW27: =H27&F27 -> 2026290000000099CHAITANYA INDIA FIN CREDIT PRIVATE LIMITED
B28: ="Q" & IF(ROUNDUP(MONTH(D28)/3,0)-1=0,4,ROUNDUP(MONTH(D28)/3,0)-1) -> Q1 | C28: =TEXT(AN28,"mmm-yy") -> Apr-26 | D28: 46128 | E28: SH04261602 | F28: CHAITANYA INDIA FIN CREDIT PRIVATE LIMITED | G28: 29AADCC6184H1ZE | H28: 2026290000000099 | I28: 46094 | J28: 26-27/PUR/000696 | K28: 46128 | L28: KA | N28: ITAD Mixed E Waste | O28: 4 | P28: 85 | Q28: =O28*P28 -> 340 | R28: 0 | S28: =O28-R28 -> 4 | T28: 0 | U28: 0 | V28: 0 | W28: 0 | X28: 0 | Y28: 0 | Z28: 0 | AA28: 0 | AB28: =Y28+AA28+Z28 -> 0 | AC28: 0 | AD28: 0 | AE28: 0 | AF28: 0 | AG28: 0 | AH28: 0 | AI28: 0 | AJ28: 0 | AK28: 0 | AL28: =(BN28*P28/AX28)+AB28/O28*(BN28/AX28) -> 0 | AM28: =Q28+AB28+AL28+AK28+AJ28+T28+AE28 -> 340 | AN28: 46128 | AO28: 29/IAD/27IN00004 | AP28: 832139000046796207 | AQ28: TRADEWIND BUSINESS SOLUTIONS LLP | AR28: 07AARFT3586D1ZR | AS28: Bengaluru,Karnataka,560070 | AT28: New Delhi | AU28: Delhi | AW28: 4 | AX28: 93.22 | AY28: =AW28*AX28 -> 372.88 | AZ28: =AW28=O28 -> TRUE | BA28: 0 | BB28: =AW28-BA28 -> 4 | BC28: 0 | BD28: Regular | BE28: 0 | BF28: 0 | BG28: 0 | BH28: 0 | BI28: 0 | BJ28: 0 | BK28: 0 | BL28: 0 | BM28: 0 | BN28: =AY28*$BM$3 -> 0 | BO28: =AY28+BL28+BM28+BN28+BC28+BG28 -> 372.88 | BP28: =BO28-AM28 -> 32.88 | BQ28: =IF(BP28>=0,"Positive Margin","Negative Margin") -> Positive Margin | BR28: No Provision | BS28: =AY28-Y28-Q28-AA28-T28+BC28 -> 32.88 | BT28: =IF(BS28<0, "Negative Margin at Inception", "Positive Margin at Inception") -> Positive Margin at Inception | BU28: =IFERROR(BP28/BO28,"0") -> 0.088178502 | BV28: =IF(BU28<1%,"Less Than 1%",IF(BU28>2%,"More than 2%",IF(BU28>=1%,"1% - 2%"))) -> More than 2% | BW28: =BM28+BN28 -> 0 | BX28: =AL28+AK28 -> 0 | BY28: =BW28-BX28 -> 0 | BZ28: =BM28 -> 0 | CA28: =AK28 -> 0 | CB28: =BZ28-CA28 -> 0 | CC28: Marketplace (IT Assets Disposition) | CD28: 0 | CE28: =AM28-AL28-AA28 -> 340 | CF28: =BO28-BN28 -> 372.88 | CG28: =INT((D28- IF(MONTH(D28) >= 4, DATE(YEAR(D28), 4, 1), DATE(YEAR(D28)-1, 4, 1))) / 7) + 1 -> 3 | CH28: 0 | CI28: 0 | CJ28: =_xlfn.XLOOKUP(AP28,POC!B:B,POC!D:D) -> #N/A | CK28: =AY28-Q28 -> 32.88 | CL28: =CK28-Y28+Z28 -> 32.88 | CM28: =BO28-AM28 -> 32.88 | CN28: =AY28*118% -> 439.9984 | CO28: =-Q28*118% -> -401.2 | CP28: =-BZ28*118% -> 0 | CQ28: =-CA28*118% -> 0 | CR28: =SUM(CN28:CQ28) -> 38.7984 | CS28: Telangana - HO | CT28: Telangana - HO | CU28: =MID(G28,3,10) -> AADCC6184H | CV28: =MID(AR28,3,10) -> AARFT3586D | CW28: =H28&F28 -> 2026290000000099CHAITANYA INDIA FIN CREDIT PRIVATE LIMITED
B29: ="Q" & IF(ROUNDUP(MONTH(D29)/3,0)-1=0,4,ROUNDUP(MONTH(D29)/3,0)-1) -> Q1 | C29: =TEXT(AN29,"mmm-yy") -> Apr-26 | D29: 46128 | E29: SH04261603 | F29: CHAITANYA INDIA FIN CREDIT PRIVATE LIMITED | G29: 24AADCC6184H1ZO | H29: 2026290000000092 | I29: 46094 | J29: 26-27/PUR/000733 | K29: 46128 | L29: GJ | N29: ITAD Mixed E Waste | O29: 3 | P29: 1576 | Q29: =O29*P29 -> 4728 | R29: 0 | S29: =O29-R29 -> 3 | T29: 0 | U29: 0 | V29: 0 | W29: 0 | X29: 0 | Y29: 0 | Z29: 0 | AA29: 0 | AB29: =Y29+AA29+Z29 -> 0 | AC29: 0 | AD29: 0 | AE29: 0 | AF29: 0 | AG29: 0 | AH29: 0 | AI29: 0 | AJ29: 0 | AK29: 0 | AL29: =(BN29*P29/AX29)+AB29/O29*(BN29/AX29) -> 0 | AM29: =Q29+AB29+AL29+AK29+AJ29+T29+AE29 -> 4728 | AN29: 46128 | AO29: 29/IAD/27IN00005 | AP29: 832139000046796207 | AQ29: TRADEWIND BUSINESS SOLUTIONS LLP | AR29: 07AARFT3586D1ZR | AS29: Himmatnagar,Gujarat,380005 | AT29: New Delhi | AU29: Delhi | AW29: 3 | AX29: 1733.9 | AY29: =AW29*AX29 -> 5201.7 | AZ29: =AW29=O29 -> TRUE | BA29: 0 | BB29: =AW29-BA29 -> 3 | BC29: 0 | BD29: Regular | BE29: 0 | BF29: 0 | BG29: 0 | BH29: 0 | BI29: 0 | BJ29: 0 | BK29: 0 | BL29: 0 | BM29: 0 | BN29: =AY29*$BM$3 -> 0 | BO29: =AY29+BL29+BM29+BN29+BC29+BG29 -> 5201.7 | BP29: =BO29-AM29 -> 473.7 | BQ29: =IF(BP29>=0,"Positive Margin","Negative Margin") -> Positive Margin | BR29: No Provision | BS29: =AY29-Y29-Q29-AA29-T29+BC29 -> 473.7 | BT29: =IF(BS29<0, "Negative Margin at Inception", "Positive Margin at Inception") -> Positive Margin at Inception | BU29: =IFERROR(BP29/BO29,"0") -> 0.091066382 | BV29: =IF(BU29<1%,"Less Than 1%",IF(BU29>2%,"More than 2%",IF(BU29>=1%,"1% - 2%"))) -> More than 2% | BW29: =BM29+BN29 -> 0 | BX29: =AL29+AK29 -> 0 | BY29: =BW29-BX29 -> 0 | BZ29: =BM29 -> 0 | CA29: =AK29 -> 0 | CB29: =BZ29-CA29 -> 0 | CC29: Marketplace (IT Assets Disposition) | CD29: 0 | CE29: =AM29-AL29-AA29 -> 4728 | CF29: =BO29-BN29 -> 5201.7 | CG29: =INT((D29- IF(MONTH(D29) >= 4, DATE(YEAR(D29), 4, 1), DATE(YEAR(D29)-1, 4, 1))) / 7) + 1 -> 3 | CH29: 0 | CI29: 0 | CJ29: =_xlfn.XLOOKUP(AP29,POC!B:B,POC!D:D) -> #N/A | CK29: =AY29-Q29 -> 473.7 | CL29: =CK29-Y29+Z29 -> 473.7 | CM29: =BO29-AM29 -> 473.7 | CN29: =AY29*118% -> 6138.006 | CO29: =-Q29*118% -> -5579.04 | CP29: =-BZ29*118% -> 0 | CQ29: =-CA29*118% -> 0 | CR29: =SUM(CN29:CQ29) -> 558.966 | CS29: Telangana - HO | CT29: Telangana - HO | CU29: =MID(G29,3,10) -> AADCC6184H | CV29: =MID(AR29,3,10) -> AARFT3586D | CW29: =H29&F29 -> 2026290000000092CHAITANYA INDIA FIN CREDIT PRIVATE LIMITED
B30: ="Q" & IF(ROUNDUP(MONTH(D30)/3,0)-1=0,4,ROUNDUP(MONTH(D30)/3,0)-1) -> Q1 | C30: =TEXT(AN30,"mmm-yy") -> Apr-26 | D30: 46128 | E30: SH04261603 | F30: CHAITANYA INDIA FIN CREDIT PRIVATE LIMITED | G30: 24AADCC6184H1ZO | H30: 2026290000000092 | I30: 46094 | J30: 26-27/PUR/000733 | K30: 46128 | L30: GJ | N30: ITAD Mixed E Waste | O30: 6 | P30: 84.666 | Q30: =O30*P30 -> 507.996 | R30: 0 | S30: =O30-R30 -> 6 | T30: 0 | U30: 0 | V30: 0 | W30: 0 | X30: 0 | Y30: 0 | Z30: 0 | AA30: 0 | AB30: =Y30+AA30+Z30 -> 0 | AC30: 0 | AD30: 0 | AE30: 0 | AF30: 0 | AG30: 0 | AH30: 0 | AI30: 0 | AJ30: 0 | AK30: 0 | AL30: =(BN30*P30/AX30)+AB30/O30*(BN30/AX30) -> 0 | AM30: =Q30+AB30+AL30+AK30+AJ30+T30+AE30 -> 507.996 | AN30: 46128 | AO30: 29/IAD/27IN00005 | AP30: 832139000046796207 | AQ30: TRADEWIND BUSINESS SOLUTIONS LLP | AR30: 07AARFT3586D1ZR | AS30: Himmatnagar,Gujarat,380005 | AT30: New Delhi | AU30: Delhi | AW30: 6 | AX30: 93.22 | AY30: =AW30*AX30 -> 559.32 | AZ30: =AW30=O30 -> TRUE | BA30: 0 | BB30: =AW30-BA30 -> 6 | BC30: 0 | BD30: Regular | BE30: 0 | BF30: 0 | BG30: 0 | BH30: 0 | BI30: 0 | BJ30: 0 | BK30: 0 | BL30: 0 | BM30: 0 | BN30: =AY30*$BM$3 -> 0 | BO30: =AY30+BL30+BM30+BN30+BC30+BG30 -> 559.32 | BP30: =BO30-AM30 -> 51.324 | BQ30: =IF(BP30>=0,"Positive Margin","Negative Margin") -> Positive Margin | BR30: No Provision | BS30: =AY30-Y30-Q30-AA30-T30+BC30 -> 51.324 | BT30: =IF(BS30<0, "Negative Margin at Inception", "Positive Margin at Inception") -> Positive Margin at Inception | BU30: =IFERROR(BP30/BO30,"0") -> 0.091761425 | BV30: =IF(BU30<1%,"Less Than 1%",IF(BU30>2%,"More than 2%",IF(BU30>=1%,"1% - 2%"))) -> More than 2% | BW30: =BM30+BN30 -> 0 | BX30: =AL30+AK30 -> 0 | BY30: =BW30-BX30 -> 0 | BZ30: =BM30 -> 0 | CA30: =AK30 -> 0 | CB30: =BZ30-CA30 -> 0 | CC30: Marketplace (IT Assets Disposition) | CD30: 0 | CE30: =AM30-AL30-AA30 -> 507.996 | CF30: =BO30-BN30 -> 559.32 | CG30: =INT((D30- IF(MONTH(D30) >= 4, DATE(YEAR(D30), 4, 1), DATE(YEAR(D30)-1, 4, 1))) / 7) + 1 -> 3 | CH30: 0 | CI30: 0 | CJ30: =_xlfn.XLOOKUP(AP30,POC!B:B,POC!D:D) -> #N/A | CK30: =AY30-Q30 -> 51.324 | CL30: =CK30-Y30+Z30 -> 51.324 | CM30: =BO30-AM30 -> 51.324 | CN30: =AY30*118% -> 659.9976 | CO30: =-Q30*118% -> -599.43528 | CP30: =-BZ30*118% -> 0 | CQ30: =-CA30*118% -> 0 | CR30: =SUM(CN30:CQ30) -> 60.56232 | CS30: Telangana - HO | CT30: Telangana - HO | CU30: =MID(G30,3,10) -> AADCC6184H | CV30: =MID(AR30,3,10) -> AARFT3586D | CW30: =H30&F30 -> 2026290000000092CHAITANYA INDIA FIN CREDIT PRIVATE LIMITED
B31: ="Q" & IF(ROUNDUP(MONTH(D31)/3,0)-1=0,4,ROUNDUP(MONTH(D31)/3,0)-1) -> Q1 | C31: =TEXT(AN31,"mmm-yy") -> Apr-26 | D31: 46132 | E31: SH04262203 | F31: ITW INDIA PRIVATE LIMITED | G31: 27AAACI4550Q1Z6 | H31: 261008721 | I31: 46132 | J31: 26-27/PUR/001235 | K31: 46134 | L31: MH | M31: MH02FG8607 | N31: ITAD Mixed E Waste | O31: 1 | P31: 161170 | Q31: =O31*P31 -> 161170 | R31: 0 | S31: =O31-R31 -> 1 | T31: 0 | U31: 0 | V31: 0 | W31: 0 | X31: 0 | Y31: 0 | Z31: 0 | AA31: 0 | AB31: =Y31+AA31+Z31 -> 0 | AC31: 0 | AD31: 0 | AE31: 0 | AF31: 0 | AG31: 0 | AH31: 0 | AI31: 0 | AJ31: 0 | AK31: 0 | AL31: =(BN31*P31/AX31)+AB31/O31*(BN31/AX31) -> 0 | AM31: =Q31+AB31+AL31+AK31+AJ31+T31+AE31 -> 161170 | AN31: 46134 | AO31: 36/IAD/27IN00007 | AP31: 832139000031064980 | AQ31: GREENLIFE EWASTE RECYCLING PRIVATE LIMITED | AR31: 27AAJCG6268L1ZY | AS31: Pune,Maharashtra,412208 | AT31: Suburban | AU31: Maharashtra | AV31: 152408160469 | AW31: 1 | AX31: 242524.09 | AY31: =AW31*AX31 -> 242524.09 | AZ31: =AW31=O31 -> TRUE | BA31: 0 | BB31: =AW31-BA31 -> 1 | BC31: 0 | BD31: Regular | BE31: 0 | BF31: 0 | BG31: 0 | BH31: 0 | BI31: 0 | BJ31: 0 | BK31: 0 | BL31: 0 | BM31: 0 | BN31: =AY31*$BM$3 -> 0 | BO31: =AY31+BL31+BM31+BN31+BC31+BG31 -> 242524.09 | BP31: =BO31-AM31 -> 81354.09 | BQ31: =IF(BP31>=0,"Positive Margin","Negative Margin") -> Positive Margin | BR31: No Provision | BS31: =AY31-Y31-Q31-AA31-T31+BC31 -> 81354.09 | BT31: =IF(BS31<0, "Negative Margin at Inception", "Positive Margin at Inception") -> Positive Margin at Inception | BU31: =IFERROR(BP31/BO31,"0") -> 0.33544746 | BV31: =IF(BU31<1%,"Less Than 1%",IF(BU31>2%,"More than 2%",IF(BU31>=1%,"1% - 2%"))) -> More than 2% | BW31: =BM31+BN31 -> 0 | BX31: =AL31+AK31 -> 0 | BY31: =BW31-BX31 -> 0 | BZ31: =BM31 -> 0 | CA31: =AK31 -> 0 | CB31: =BZ31-CA31 -> 0 | CC31: Marketplace (IT Assets Disposition) | CD31: 0 | CE31: =AM31-AL31-AA31 -> 161170 | CF31: =BO31-BN31 -> 242524.09 | CG31: =INT((D31- IF(MONTH(D31) >= 4, DATE(YEAR(D31), 4, 1), DATE(YEAR(D31)-1, 4, 1))) / 7) + 1 -> 3 | CH31: 0 | CI31: 0 | CJ31: =_xlfn.XLOOKUP(AP31,POC!B:B,POC!D:D) -> #N/A | CK31: =AY31-Q31 -> 81354.09 | CL31: =CK31-Y31+Z31 -> 81354.09 | CM31: =BO31-AM31 -> 81354.09 | CN31: =AY31*118% -> 286178.43 | CO31: =-Q31*118% -> -190180.6 | CP31: =-BZ31*118% -> 0 | CQ31: =-CA31*118% -> 0 | CR31: =SUM(CN31:CQ31) -> 95997.826 | CS31: Telangana - HO | CT31: Telangana - HO | CU31: =MID(G31,3,10) -> AAACI4550Q | CV31: =MID(AR31,3,10) -> AAJCG6268L | CW31: =H31&F31 -> 261008721ITW INDIA PRIVATE LIMITED
B32: ="Q" & IF(ROUNDUP(MONTH(D32)/3,0)-1=0,4,ROUNDUP(MONTH(D32)/3,0)-1) -> Q1 | C32: =TEXT(AN32,"mmm-yy") -> Apr-26 | D32: 46132 | E32: SH04261605 | F32: CHAITANYA INDIA FIN CREDIT PRIVATE LIMITED | G32: 08AADCC6184H1ZI | H32: 2026290000000096 | I32: 46094 | J32: 26-27/PUR/001021 | K32: 46132 | L32: RJ | N32: ITAD Mixed E Waste | O32: 23 | P32: 1576 | Q32: =O32*P32 -> 36248 | R32: 0 | S32: =O32-R32 -> 23 | T32: 0 | U32: 0 | V32: 0 | W32: 0 | X32: 0 | Y32: 0 | Z32: 0 | AA32: 0 | AB32: =Y32+AA32+Z32 -> 0 | AC32: 0 | AD32: 0 | AE32: 0 | AF32: 0 | AG32: 0 | AH32: 0 | AI32: 0 | AJ32: 0 | AK32: 0 | AL32: =(BN32*P32/AX32)+AB32/O32*(BN32/AX32) -> 0 | AM32: =Q32+AB32+AL32+AK32+AJ32+T32+AE32 -> 36248 | AN32: 46132 | AO32: 29/IAD/27IN00006 | AP32: 832139000046796207 | AQ32: TRADEWIND BUSINESS SOLUTIONS LLP | AR32: 07AARFT3586D1ZR | AS32: Jaipur Rajasthan 302020 | AT32: New Delhi | AU32: Delhi | AW32: 23 | AX32: 1733.9 | AY32: =AW32*AX32 -> 39879.7 | AZ32: =AW32=O32 -> TRUE | BA32: 0 | BB32: =AW32-BA32 -> 23 | BC32: 0 | BD32: Regular | BE32: 0 | BF32: 0 | BG32: 0 | BH32: 0 | BI32: 0 | BJ32: 0 | BK32: 0 | BL32: 0 | BM32: 0 | BN32: =AY32*$BM$3 -> 0 | BO32: =AY32+BL32+BM32+BN32+BC32+BG32 -> 39879.7 | BP32: =BO32-AM32 -> 3631.7 | BQ32: =IF(BP32>=0,"Positive Margin","Negative Margin") -> Positive Margin | BR32: No Provision | BS32: =AY32-Y32-Q32-AA32-T32+BC32 -> 3631.7 | BT32: =IF(BS32<0, "Negative Margin at Inception", "Positive Margin at Inception") -> Positive Margin at Inception | BU32: =IFERROR(BP32/BO32,"0") -> 0.091066382 | BV32: =IF(BU32<1%,"Less Than 1%",IF(BU32>2%,"More than 2%",IF(BU32>=1%,"1% - 2%"))) -> More than 2% | BW32: =BM32+BN32 -> 0 | BX32: =AL32+AK32 -> 0 | BY32: =BW32-BX32 -> 0 | BZ32: =BM32 -> 0 | CA32: =AK32 -> 0 | CB32: =BZ32-CA32 -> 0 | CC32: Marketplace (IT Assets Disposition) | CD32: 0 | CE32: =AM32-AL32-AA32 -> 36248 | CF32: =BO32-BN32 -> 39879.7 | CG32: =INT((D32- IF(MONTH(D32) >= 4, DATE(YEAR(D32), 4, 1), DATE(YEAR(D32)-1, 4, 1))) / 7) + 1 -> 3 | CH32: 0 | CI32: 0 | CJ32: =_xlfn.XLOOKUP(AP32,POC!B:B,POC!D:D) -> #N/A | CK32: =AY32-Q32 -> 3631.7 | CL32: =CK32-Y32+Z32 -> 3631.7 | CM32: =BO32-AM32 -> 3631.7 | CN32: =AY32*118% -> 47058.046 | CO32: =-Q32*118% -> -42772.64 | CP32: =-BZ32*118% -> 0 | CQ32: =-CA32*118% -> 0 | CR32: =SUM(CN32:CQ32) -> 4285.406 | CS32: Telangana - HO | CT32: Telangana - HO | CU32: =MID(G32,3,10) -> AADCC6184H | CV32: =MID(AR32,3,10) -> AARFT3586D | CW32: =H32&F32 -> 2026290000000096CHAITANYA INDIA FIN CREDIT PRIVATE LIMITED
B33: ="Q" & IF(ROUNDUP(MONTH(D33)/3,0)-1=0,4,ROUNDUP(MONTH(D33)/3,0)-1) -> Q1 | C33: =TEXT(AN33,"mmm-yy") -> Apr-26 | D33: 46133 | E33: SH04262101 | F33: CHAITANYA INDIA FIN CREDIT PRIVATE LIMITED | G33: 33AADCC6184H1ZP | H33: 2026290000000097 | I33: 46094 | J33: 26-27/PUR/001074 | K33: 46133 | L33: TN | N33: ITAD Mixed E Waste | O33: 2 | P33: 847 | Q33: =O33*P33 -> 1694 | R33: 0 | S33: =O33-R33 -> 2 | T33: 0 | U33: 0 | V33: 0 | W33: 0 | X33: 0 | Y33: 0 | Z33: 0 | AA33: 0 | AB33: =Y33+AA33+Z33 -> 0 | AC33: 0 | AD33: 0 | AE33: 0 | AF33: 0 | AG33: 0 | AH33: 0 | AI33: 0 | AJ33: 0 | AK33: 0 | AL33: =(BN33*P33/AX33)+AB33/O33*(BN33/AX33) -> 0 | AM33: =Q33+AB33+AL33+AK33+AJ33+T33+AE33 -> 1694 | AN33: 46133 | AO33: 29/IAD/27IN00007 | AP33: 832139000046796207 | AQ33: TRADEWIND BUSINESS SOLUTIONS LLP | AR33: 07AARFT3586D1ZR | AS33: Alamelupuram Tamil Nadu 636905 | AT33: New Delhi | AU33: Delhi | AW33: 2 | AX33: 932.2 | AY33: =AW33*AX33 -> 1864.4 | AZ33: =AW33=O33 -> TRUE | BA33: 0 | BB33: =AW33-BA33 -> 2 | BC33: 0 | BD33: Regular | BE33: 0 | BF33: 0 | BG33: 0 | BH33: 0 | BI33: 0 | BJ33: 0 | BK33: 0 | BL33: 0 | BM33: 0 | BN33: =AY33*$BM$3 -> 0 | BO33: =AY33+BL33+BM33+BN33+BC33+BG33 -> 1864.4 | BP33: =BO33-AM33 -> 170.4 | BQ33: =IF(BP33>=0,"Positive Margin","Negative Margin") -> Positive Margin | BR33: No Provision | BS33: =AY33-Y33-Q33-AA33-T33+BC33 -> 170.4 | BT33: =IF(BS33<0, "Negative Margin at Inception", "Positive Margin at Inception") -> Positive Margin at Inception | BU33: =IFERROR(BP33/BO33,"0") -> 0.091396696 | BV33: =IF(BU33<1%,"Less Than 1%",IF(BU33>2%,"More than 2%",IF(BU33>=1%,"1% - 2%"))) -> More than 2% | BW33: =BM33+BN33 -> 0 | BX33: =AL33+AK33 -> 0 | BY33: =BW33-BX33 -> 0 | BZ33: =BM33 -> 0 | CA33: =AK33 -> 0 | CB33: =BZ33-CA33 -> 0 | CC33: Marketplace (IT Assets Disposition) | CD33: 0 | CE33: =AM33-AL33-AA33 -> 1694 | CF33: =BO33-BN33 -> 1864.4 | CG33: =INT((D33- IF(MONTH(D33) >= 4, DATE(YEAR(D33), 4, 1), DATE(YEAR(D33)-1, 4, 1))) / 7) + 1 -> 3 | CH33: 0 | CI33: 0 | CJ33: =_xlfn.XLOOKUP(AP33,POC!B:B,POC!D:D) -> #N/A | CK33: =AY33-Q33 -> 170.4 | CL33: =CK33-Y33+Z33 -> 170.4 | CM33: =BO33-AM33 -> 170.4 | CN33: =AY33*118% -> 2199.992 | CO33: =-Q33*118% -> -1998.92 | CP33: =-BZ33*118% -> 0 | CQ33: =-CA33*118% -> 0 | CR33: =SUM(CN33:CQ33) -> 201.072 | CS33: Telangana - HO | CT33: Telangana - HO | CU33: =MID(G33,3,10) -> AADCC6184H | CV33: =MID(AR33,3,10) -> AARFT3586D | CW33: =H33&F33 -> 2026290000000097CHAITANYA INDIA FIN CREDIT PRIVATE LIMITED
B34: ="Q" & IF(ROUNDUP(MONTH(D34)/3,0)-1=0,4,ROUNDUP(MONTH(D34)/3,0)-1) -> Q1 | C34: =TEXT(AN34,"mmm-yy") -> Apr-26 | D34: 46133 | E34: SH04262101 | F34: CHAITANYA INDIA FIN CREDIT PRIVATE LIMITED | G34: 33AADCC6184H1ZP | H34: 2026290000000097 | I34: 46094 | J34: 26-27/PUR/001074 | K34: 46133 | L34: TN | N34: ITAD Mixed E Waste | O34: 32 | P34: 1576 | Q34: =O34*P34 -> 50432 | R34: 0 | S34: =O34-R34 -> 32 | T34: 0 | U34: 0 | V34: 0 | W34: 0 | X34: 0 | Y34: 0 | Z34: 0 | AA34: 0 | AB34: =Y34+AA34+Z34 -> 0 | AC34: 0 | AD34: 0 | AE34: 0 | AF34: 0 | AG34: 0 | AH34: 0 | AI34: 0 | AJ34: 0 | AK34: 0 | AL34: =(BN34*P34/AX34)+AB34/O34*(BN34/AX34) -> 0 | AM34: =Q34+AB34+AL34+AK34+AJ34+T34+AE34 -> 50432 | AN34: 46133 | AO34: 29/IAD/27IN00007 | AP34: 832139000046796207 | AQ34: TRADEWIND BUSINESS SOLUTIONS LLP | AR34: 07AARFT3586D1ZR | AS34: Alamelupuram Tamil Nadu 636905 | AT34: New Delhi | AU34: Delhi | AW34: 32 | AX34: 1733.9 | AY34: =AW34*AX34 -> 55484.8 | AZ34: =AW34=O34 -> TRUE | BA34: 0 | BB34: =AW34-BA34 -> 32 | BC34: 0 | BD34: Regular | BE34: 0 | BF34: 0 | BG34: 0 | BH34: 0 | BI34: 0 | BJ34: 0 | BK34: 0 | BL34: 0 | BM34: 0 | BN34: =AY34*$BM$3 -> 0 | BO34: =AY34+BL34+BM34+BN34+BC34+BG34 -> 55484.8 | BP34: =BO34-AM34 -> 5052.8 | BQ34: =IF(BP34>=0,"Positive Margin","Negative Margin") -> Positive Margin | BR34: No Provision | BS34: =AY34-Y34-Q34-AA34-T34+BC34 -> 5052.8 | BT34: =IF(BS34<0, "Negative Margin at Inception", "Positive Margin at Inception") -> Positive Margin at Inception | BU34: =IFERROR(BP34/BO34,"0") -> 0.091066382 | BV34: =IF(BU34<1%,"Less Than 1%",IF(BU34>2%,"More than 2%",IF(BU34>=1%,"1% - 2%"))) -> More than 2% | BW34: =BM34+BN34 -> 0 | BX34: =AL34+AK34 -> 0 | BY34: =BW34-BX34 -> 0 | BZ34: =BM34 -> 0 | CA34: =AK34 -> 0 | CB34: =BZ34-CA34 -> 0 | CC34: Marketplace (IT Assets Disposition) | CD34: 0 | CE34: =AM34-AL34-AA34 -> 50432 | CF34: =BO34-BN34 -> 55484.8 | CG34: =INT((D34- IF(MONTH(D34) >= 4, DATE(YEAR(D34), 4, 1), DATE(YEAR(D34)-1, 4, 1))) / 7) + 1 -> 3 | CH34: 0 | CI34: 0 | CJ34: =_xlfn.XLOOKUP(AP34,POC!B:B,POC!D:D) -> #N/A | CK34: =AY34-Q34 -> 5052.8 | CL34: =CK34-Y34+Z34 -> 5052.8 | CM34: =BO34-AM34 -> 5052.8 | CN34: =AY34*118% -> 65472.064 | CO34: =-Q34*118% -> -59509.76 | CP34: =-BZ34*118% -> 0 | CQ34: =-CA34*118% -> 0 | CR34: =SUM(CN34:CQ34) -> 5962.304 | CS34: Telangana - HO | CT34: Telangana - HO | CU34: =MID(G34,3,10) -> AADCC6184H | CV34: =MID(AR34,3,10) -> AARFT3586D | CW34: =H34&F34 -> 2026290000000097CHAITANYA INDIA FIN CREDIT PRIVATE LIMITED
B35: ="Q" & IF(ROUNDUP(MONTH(D35)/3,0)-1=0,4,ROUNDUP(MONTH(D35)/3,0)-1) -> Q1 | C35: =TEXT(AN35,"mmm-yy") -> Apr-26 | D35: 46133 | E35: SH04262101 | F35: CHAITANYA INDIA FIN CREDIT PRIVATE LIMITED | G35: 33AADCC6184H1ZP | H35: 2026290000000097 | I35: 46094 | J35: 26-27/PUR/001074 | K35: 46133 | L35: TN | N35: ITAD Mixed E Waste | O35: 36 | P35: 85 | Q35: =O35*P35 -> 3060 | R35: 0 | S35: =O35-R35 -> 36 | T35: 0 | U35: 0 | V35: 0 | W35: 0 | X35: 0 | Y35: 0 | Z35: 0 | AA35: 0 | AB35: =Y35+AA35+Z35 -> 0 | AC35: 0 | AD35: 0 | AE35: 0 | AF35: 0 | AG35: 0 | AH35: 0 | AI35: 0 | AJ35: 0 | AK35: 0 | AL35: =(BN35*P35/AX35)+AB35/O35*(BN35/AX35) -> 0 | AM35: =Q35+AB35+AL35+AK35+AJ35+T35+AE35 -> 3060 | AN35: 46133 | AO35: 29/IAD/27IN00007 | AP35: 832139000046796207 | AQ35: TRADEWIND BUSINESS SOLUTIONS LLP | AR35: 07AARFT3586D1ZR | AS35: Alamelupuram Tamil Nadu 636905 | AT35: New Delhi | AU35: Delhi | AW35: 36 | AX35: 93.22 | AY35: =AW35*AX35 -> 3355.92 | AZ35: =AW35=O35 -> TRUE | BA35: 0 | BB35: =AW35-BA35 -> 36 | BC35: 0 | BD35: Regular | BE35: 0 | BF35: 0 | BG35: 0 | BH35: 0 | BI35: 0 | BJ35: 0 | BK35: 0 | BL35: 0 | BM35: 0 | BN35: =AY35*$BM$3 -> 0 | BO35: =AY35+BL35+BM35+BN35+BC35+BG35 -> 3355.92 | BP35: =BO35-AM35 -> 295.92 | BQ35: =IF(BP35>=0,"Positive Margin","Negative Margin") -> Positive Margin | BR35: No Provision | BS35: =AY35-Y35-Q35-AA35-T35+BC35 -> 295.92 | BT35: =IF(BS35<0, "Negative Margin at Inception", "Positive Margin at Inception") -> Positive Margin at Inception | BU35: =IFERROR(BP35/BO35,"0") -> 0.088178502 | BV35: =IF(BU35<1%,"Less Than 1%",IF(BU35>2%,"More than 2%",IF(BU35>=1%,"1% - 2%"))) -> More than 2% | BW35: =BM35+BN35 -> 0 | BX35: =AL35+AK35 -> 0 | BY35: =BW35-BX35 -> 0 | BZ35: =BM35 -> 0 | CA35: =AK35 -> 0 | CB35: =BZ35-CA35 -> 0 | CC35: Marketplace (IT Assets Disposition) | CD35: 0 | CE35: =AM35-AL35-AA35 -> 3060 | CF35: =BO35-BN35 -> 3355.92 | CG35: =INT((D35- IF(MONTH(D35) >= 4, DATE(YEAR(D35), 4, 1), DATE(YEAR(D35)-1, 4, 1))) / 7) + 1 -> 3 | CH35: 0 | CI35: 0 | CJ35: =_xlfn.XLOOKUP(AP35,POC!B:B,POC!D:D) -> #N/A | CK35: =AY35-Q35 -> 295.92 | CL35: =CK35-Y35+Z35 -> 295.92 | CM35: =BO35-AM35 -> 295.92 | CN35: =AY35*118% -> 3959.9856 | CO35: =-Q35*118% -> -3610.8 | CP35: =-BZ35*118% -> 0 | CQ35: =-CA35*118% -> 0 | CR35: =SUM(CN35:CQ35) -> 349.1856 | CS35: Telangana - HO | CT35: Telangana - HO | CU35: =MID(G35,3,10) -> AADCC6184H | CV35: =MID(AR35,3,10) -> AARFT3586D | CW35: =H35&F35 -> 2026290000000097CHAITANYA INDIA FIN CREDIT PRIVATE LIMITED
B36: ="Q" & IF(ROUNDUP(MONTH(D36)/3,0)-1=0,4,ROUNDUP(MONTH(D36)/3,0)-1) -> Q1 | C36: =TEXT(AN36,"mmm-yy") -> Apr-26 | D36: 46133 | E36: SH04262101 | F36: CHAITANYA INDIA FIN CREDIT PRIVATE LIMITED | G36: 33AADCC6184H1ZP | H36: 2026290000000097 | I36: 46094 | J36: 26-27/PUR/001074 | K36: 46133 | L36: TN | N36: ITAD Mixed E Waste | O36: 1 | P36: 85 | Q36: =O36*P36 -> 85 | R36: 0 | S36: =O36-R36 -> 1 | T36: 0 | U36: 0 | V36: 0 | W36: 0 | X36: 0 | Y36: 0 | Z36: 0 | AA36: 0 | AB36: =Y36+AA36+Z36 -> 0 | AC36: 0 | AD36: 0 | AE36: 0 | AF36: 0 | AG36: 0 | AH36: 0 | AI36: 0 | AJ36: 0 | AK36: 0 | AL36: =(BN36*P36/AX36)+AB36/O36*(BN36/AX36) -> 0 | AM36: =Q36+AB36+AL36+AK36+AJ36+T36+AE36 -> 85 | AN36: 46133 | AO36: 29/IAD/27IN00007 | AP36: 832139000046796207 | AQ36: TRADEWIND BUSINESS SOLUTIONS LLP | AR36: 07AARFT3586D1ZR | AS36: Alamelupuram Tamil Nadu 636905 | AT36: New Delhi | AU36: Delhi | AW36: 1 | AX36: 93.22 | AY36: =AW36*AX36 -> 93.22 | AZ36: =AW36=O36 -> TRUE | BA36: 0 | BB36: =AW36-BA36 -> 1 | BC36: 0 | BD36: Regular | BE36: 0 | BF36: 0 | BG36: 0 | BH36: 0 | BI36: 0 | BJ36: 0 | BK36: 0 | BL36: 0 | BM36: 0 | BN36: =AY36*$BM$3 -> 0 | BO36: =AY36+BL36+BM36+BN36+BC36+BG36 -> 93.22 | BP36: =BO36-AM36 -> 8.22 | BQ36: =IF(BP36>=0,"Positive Margin","Negative Margin") -> Positive Margin | BR36: No Provision | BS36: =AY36-Y36-Q36-AA36-T36+BC36 -> 8.22 | BT36: =IF(BS36<0, "Negative Margin at Inception", "Positive Margin at Inception") -> Positive Margin at Inception | BU36: =IFERROR(BP36/BO36,"0") -> 0.088178502 | BV36: =IF(BU36<1%,"Less Than 1%",IF(BU36>2%,"More than 2%",IF(BU36>=1%,"1% - 2%"))) -> More than 2% | BW36: =BM36+BN36 -> 0 | BX36: =AL36+AK36 -> 0 | BY36: =BW36-BX36 -> 0 | BZ36: =BM36 -> 0 | CA36: =AK36 -> 0 | CB36: =BZ36-CA36 -> 0 | CC36: Marketplace (IT Assets Disposition) | CD36: 0 | CE36: =AM36-AL36-AA36 -> 85 | CF36: =BO36-BN36 -> 93.22 | CG36: =INT((D36- IF(MONTH(D36) >= 4, DATE(YEAR(D36), 4, 1), DATE(YEAR(D36)-1, 4, 1))) / 7) + 1 -> 3 | CH36: 0 | CI36: 0 | CJ36: =_xlfn.XLOOKUP(AP36,POC!B:B,POC!D:D) -> #N/A | CK36: =AY36-Q36 -> 8.22 | CL36: =CK36-Y36+Z36 -> 8.22 | CM36: =BO36-AM36 -> 8.22 | CN36: =AY36*118% -> 109.9996 | CO36: =-Q36*118% -> -100.3 | CP36: =-BZ36*118% -> 0 | CQ36: =-CA36*118% -> 0 | CR36: =SUM(CN36:CQ36) -> 9.6996 | CS36: Telangana - HO | CT36: Telangana - HO | CU36: =MID(G36,3,10) -> AADCC6184H | CV36: =MID(AR36,3,10) -> AARFT3586D | CW36: =H36&F36 -> 2026290000000097CHAITANYA INDIA FIN CREDIT PRIVATE LIMITED
B37: ="Q" & IF(ROUNDUP(MONTH(D37)/3,0)-1=0,4,ROUNDUP(MONTH(D37)/3,0)-1) -> Q1 | C37: =TEXT(AN37,"mmm-yy") -> Apr-26 | D37: 46135 | E37: SH04262207 | F37: CHAITANYA INDIA FIN CREDIT PRIVATE LIMITED | G37: 09AADCC6184H1ZG | H37: 2026290000000098 | I37: 46094 | J37: 26-27/PUR/001292 | K37: 46135 | L37: UP | N37: ITAD Mixed E Waste | O37: 6 | P37: 847 | Q37: =O37*P37 -> 5082 | R37: 0 | S37: =O37-R37 -> 6 | T37: 0 | U37: 0 | V37: 0 | W37: 0 | X37: 0 | Y37: 0 | Z37: 0 | AA37: 0 | AB37: =Y37+AA37+Z37 -> 0 | AC37: 0 | AD37: 0 | AE37: 0 | AF37: 0 | AG37: 0 | AH37: 0 | AI37: 0 | AJ37: 0 | AK37: 0 | AL37: =(BN37*P37/AX37)+AB37/O37*(BN37/AX37) -> 0 | AM37: =Q37+AB37+AL37+AK37+AJ37+T37+AE37 -> 5082 | AN37: 46135 | AO37: 29/IAD/27IN00008 | AP37: 832139000046796207 | AQ37: TRADEWIND BUSINESS SOLUTIONS LLP | AR37: 07AARFT3586D1ZR | AS37: Raebareli,Uttar Pradesh,229001 | AT37: New Delhi | AU37: Delhi | AW37: 6 | AX37: 932.2 | AY37: =AW37*AX37 -> 5593.2 | AZ37: =AW37=O37 -> TRUE | BA37: 0 | BB37: =AW37-BA37 -> 6 | BC37: 0 | BD37: Regular | BE37: 0 | BF37: 0 | BG37: 0 | BH37: 0 | BI37: 0 | BJ37: 0 | BK37: 0 | BL37: 0 | BM37: 0 | BN37: =AY37*$BM$3 -> 0 | BO37: =AY37+BL37+BM37+BN37+BC37+BG37 -> 5593.2 | BP37: =BO37-AM37 -> 511.2 | BQ37: =IF(BP37>=0,"Positive Margin","Negative Margin") -> Positive Margin | BR37: No Provision | BS37: =AY37-Y37-Q37-AA37-T37+BC37 -> 511.2 | BT37: =IF(BS37<0, "Negative Margin at Inception", "Positive Margin at Inception") -> Positive Margin at Inception | BU37: =IFERROR(BP37/BO37,"0") -> 0.091396696 | BV37: =IF(BU37<1%,"Less Than 1%",IF(BU37>2%,"More than 2%",IF(BU37>=1%,"1% - 2%"))) -> More than 2% | BW37: =BM37+BN37 -> 0 | BX37: =AL37+AK37 -> 0 | BY37: =BW37-BX37 -> 0 | BZ37: =BM37 -> 0 | CA37: =AK37 -> 0 | CB37: =BZ37-CA37 -> 0 | CC37: Marketplace (IT Assets Disposition) | CD37: 0 | CE37: =AM37-AL37-AA37 -> 5082 | CF37: =BO37-BN37 -> 5593.2 | CG37: =INT((D37- IF(MONTH(D37) >= 4, DATE(YEAR(D37), 4, 1), DATE(YEAR(D37)-1, 4, 1))) / 7) + 1 -> 4 | CH37: 0 | CI37: 0 | CJ37: =_xlfn.XLOOKUP(AP37,POC!B:B,POC!D:D) -> #N/A | CK37: =AY37-Q37 -> 511.2 | CL37: =CK37-Y37+Z37 -> 511.2 | CM37: =BO37-AM37 -> 511.2 | CN37: =AY37*118% -> 6599.976 | CO37: =-Q37*118% -> -5996.76 | CP37: =-BZ37*118% -> 0 | CQ37: =-CA37*118% -> 0 | CR37: =SUM(CN37:CQ37) -> 603.216 | CS37: Telangana - HO | CT37: Telangana - HO | CU37: =MID(G37,3,10) -> AADCC6184H | CV37: =MID(AR37,3,10) -> AARFT3586D | CW37: =H37&F37 -> 2026290000000098CHAITANYA INDIA FIN CREDIT PRIVATE LIMITED
B38: ="Q" & IF(ROUNDUP(MONTH(D38)/3,0)-1=0,4,ROUNDUP(MONTH(D38)/3,0)-1) -> Q1 | C38: =TEXT(AN38,"mmm-yy") -> Apr-26 | D38: 46135 | E38: SH04262207 | F38: CHAITANYA INDIA FIN CREDIT PRIVATE LIMITED | G38: 09AADCC6184H1ZG | H38: 2026290000000098 | I38: 46094 | J38: 26-27/PUR/001292 | K38: 46135 | L38: UP | N38: ITAD Mixed E Waste | O38: 1 | P38: 1576 | Q38: =O38*P38 -> 1576 | R38: 0 | S38: =O38-R38 -> 1 | T38: 0 | U38: 0 | V38: 0 | W38: 0 | X38: 0 | Y38: 0 | Z38: 0 | AA38: 0 | AB38: =Y38+AA38+Z38 -> 0 | AC38: 0 | AD38: 0 | AE38: 0 | AF38: 0 | AG38: 0 | AH38: 0 | AI38: 0 | AJ38: 0 | AK38: 0 | AL38: =(BN38*P38/AX38)+AB38/O38*(BN38/AX38) -> 0 | AM38: =Q38+AB38+AL38+AK38+AJ38+T38+AE38 -> 1576 | AN38: 46135 | AO38: 29/IAD/27IN00008 | AP38: 832139000046796207 | AQ38: TRADEWIND BUSINESS SOLUTIONS LLP | AR38: 07AARFT3586D1ZR | AS38: Raebareli,Uttar Pradesh,229001 | AT38: New Delhi | AU38: Delhi | AW38: 1 | AX38: 1733.9 | AY38: =AW38*AX38 -> 1733.9 | AZ38: =AW38=O38 -> TRUE | BA38: 0 | BB38: =AW38-BA38 -> 1 | BC38: 0 | BD38: Regular | BE38: 0 | BF38: 0 | BG38: 0 | BH38: 0 | BI38: 0 | BJ38: 0 | BK38: 0 | BL38: 0 | BM38: 0 | BN38: =AY38*$BM$3 -> 0 | BO38: =AY38+BL38+BM38+BN38+BC38+BG38 -> 1733.9 | BP38: =BO38-AM38 -> 157.9 | BQ38: =IF(BP38>=0,"Positive Margin","Negative Margin") -> Positive Margin | BR38: No Provision | BS38: =AY38-Y38-Q38-AA38-T38+BC38 -> 157.9 | BT38: =IF(BS38<0, "Negative Margin at Inception", "Positive Margin at Inception") -> Positive Margin at Inception | BU38: =IFERROR(BP38/BO38,"0") -> 0.091066382 | BV38: =IF(BU38<1%,"Less Than 1%",IF(BU38>2%,"More than 2%",IF(BU38>=1%,"1% - 2%"))) -> More than 2% | BW38: =BM38+BN38 -> 0 | BX38: =AL38+AK38 -> 0 | BY38: =BW38-BX38 -> 0 | BZ38: =BM38 -> 0 | CA38: =AK38 -> 0 | CB38: =BZ38-CA38 -> 0 | CC38: Marketplace (IT Assets Disposition) | CD38: 0 | CE38: =AM38-AL38-AA38 -> 1576 | CF38: =BO38-BN38 -> 1733.9 | CG38: =INT((D38- IF(MONTH(D38) >= 4, DATE(YEAR(D38), 4, 1), DATE(YEAR(D38)-1, 4, 1))) / 7) + 1 -> 4 | CH38: 0 | CI38: 0 | CJ38: =_xlfn.XLOOKUP(AP38,POC!B:B,POC!D:D) -> #N/A | CK38: =AY38-Q38 -> 157.9 | CL38: =CK38-Y38+Z38 -> 157.9 | CM38: =BO38-AM38 -> 157.9 | CN38: =AY38*118% -> 2046.002 | CO38: =-Q38*118% -> -1859.68 | CP38: =-BZ38*118% -> 0 | CQ38: =-CA38*118% -> 0 | CR38: =SUM(CN38:CQ38) -> 186.322 | CS38: Telangana - HO | CT38: Telangana - HO | CU38: =MID(G38,3,10) -> AADCC6184H | CV38: =MID(AR38,3,10) -> AARFT3586D | CW38: =H38&F38 -> 2026290000000098CHAITANYA INDIA FIN CREDIT PRIVATE LIMITED
B39: ="Q" & IF(ROUNDUP(MONTH(D39)/3,0)-1=0,4,ROUNDUP(MONTH(D39)/3,0)-1) -> Q1 | C39: =TEXT(AN39,"mmm-yy") -> Apr-26 | D39: 46135 | E39: SH04262207 | F39: CHAITANYA INDIA FIN CREDIT PRIVATE LIMITED | G39: 09AADCC6184H1ZG | H39: 2026290000000098 | I39: 46094 | J39: 26-27/PUR/001292 | K39: 46135 | L39: UP | N39: ITAD Mixed E Waste | O39: 26 | P39: 85 | Q39: =O39*P39 -> 2210 | R39: 0 | S39: =O39-R39 -> 26 | T39: 0 | U39: 0 | V39: 0 | W39: 0 | X39: 0 | Y39: 0 | Z39: 0 | AA39: 0 | AB39: =Y39+AA39+Z39 -> 0 | AC39: 0 | AD39: 0 | AE39: 0 | AF39: 0 | AG39: 0 | AH39: 0 | AI39: 0 | AJ39: 0 | AK39: 0 | AL39: =(BN39*P39/AX39)+AB39/O39*(BN39/AX39) -> 0 | AM39: =Q39+AB39+AL39+AK39+AJ39+T39+AE39 -> 2210 | AN39: 46135 | AO39: 29/IAD/27IN00008 | AP39: 832139000046796207 | AQ39: TRADEWIND BUSINESS SOLUTIONS LLP | AR39: 07AARFT3586D1ZR | AS39: Raebareli,Uttar Pradesh,229001 | AT39: New Delhi | AU39: Delhi | AW39: 26 | AX39: 93.22 | AY39: =AW39*AX39 -> 2423.72 | AZ39: =AW39=O39 -> TRUE | BA39: 0 | BB39: =AW39-BA39 -> 26 | BC39: 0 | BD39: Regular | BE39: 0 | BF39: 0 | BG39: 0 | BH39: 0 | BI39: 0 | BJ39: 0 | BK39: 0 | BL39: 0 | BM39: 0 | BN39: =AY39*$BM$3 -> 0 | BO39: =AY39+BL39+BM39+BN39+BC39+BG39 -> 2423.72 | BP39: =BO39-AM39 -> 213.72 | BQ39: =IF(BP39>=0,"Positive Margin","Negative Margin") -> Positive Margin | BR39: No Provision | BS39: =AY39-Y39-Q39-AA39-T39+BC39 -> 213.72 | BT39: =IF(BS39<0, "Negative Margin at Inception", "Positive Margin at Inception") -> Positive Margin at Inception | BU39: =IFERROR(BP39/BO39,"0") -> 0.088178502 | BV39: =IF(BU39<1%,"Less Than 1%",IF(BU39>2%,"More than 2%",IF(BU39>=1%,"1% - 2%"))) -> More than 2% | BW39: =BM39+BN39 -> 0 | BX39: =AL39+AK39 -> 0 | BY39: =BW39-BX39 -> 0 | BZ39: =BM39 -> 0 | CA39: =AK39 -> 0 | CB39: =BZ39-CA39 -> 0 | CC39: Marketplace (IT Assets Disposition) | CD39: 0 | CE39: =AM39-AL39-AA39 -> 2210 | CF39: =BO39-BN39 -> 2423.72 | CG39: =INT((D39- IF(MONTH(D39) >= 4, DATE(YEAR(D39), 4, 1), DATE(YEAR(D39)-1, 4, 1))) / 7) + 1 -> 4 | CH39: 0 | CI39: 0 | CJ39: =_xlfn.XLOOKUP(AP39,POC!B:B,POC!D:D) -> #N/A | CK39: =AY39-Q39 -> 213.72 | CL39: =CK39-Y39+Z39 -> 213.72 | CM39: =BO39-AM39 -> 213.72 | CN39: =AY39*118% -> 2859.9896 | CO39: =-Q39*118% -> -2607.8 | CP39: =-BZ39*118% -> 0 | CQ39: =-CA39*118% -> 0 | CR39: =SUM(CN39:CQ39) -> 252.1896 | CS39: Telangana - HO | CT39: Telangana - HO | CU39: =MID(G39,3,10) -> AADCC6184H | CV39: =MID(AR39,3,10) -> AARFT3586D | CW39: =H39&F39 -> 2026290000000098CHAITANYA INDIA FIN CREDIT PRIVATE LIMITED
B40: ="Q" & IF(ROUNDUP(MONTH(D40)/3,0)-1=0,4,ROUNDUP(MONTH(D40)/3,0)-1) -> Q1 | C40: =TEXT(AN40,"mmm-yy") -> Apr-26 | D40: 46135 | E40: SH04262207 | F40: CHAITANYA INDIA FIN CREDIT PRIVATE LIMITED | G40: 09AADCC6184H1ZG | H40: 2026290000000098 | I40: 46094 | J40: 26-27/PUR/001292 | K40: 46135 | L40: UP | N40: ITAD Mixed E Waste | O40: 1 | P40: 1576 | Q40: =O40*P40 -> 1576 | R40: 0 | S40: =O40-R40 -> 1 | T40: 0 | U40: 0 | V40: 0 | W40: 0 | X40: 0 | Y40: 0 | Z40: 0 | AA40: 0 | AB40: =Y40+AA40+Z40 -> 0 | AC40: 0 | AD40: 0 | AE40: 0 | AF40: 0 | AG40: 0 | AH40: 0 | AI40: 0 | AJ40: 0 | AK40: 0 | AL40: =(BN40*P40/AX40)+AB40/O40*(BN40/AX40) -> 0 | AM40: =Q40+AB40+AL40+AK40+AJ40+T40+AE40 -> 1576 | AN40: 46135 | AO40: 29/IAD/27IN00008 | AP40: 832139000046796207 | AQ40: TRADEWIND BUSINESS SOLUTIONS LLP | AR40: 07AARFT3586D1ZR | AS40: Raebareli,Uttar Pradesh,229001 | AT40: New Delhi | AU40: Delhi | AW40: 1 | AX40: 1733.9 | AY40: =AW40*AX40 -> 1733.9 | AZ40: =AW40=O40 -> TRUE | BA40: 0 | BB40: =AW40-BA40 -> 1 | BC40: 0 | BD40: Regular | BE40: 0 | BF40: 0 | BG40: 0 | BH40: 0 | BI40: 0 | BJ40: 0 | BK40: 0 | BL40: 0 | BM40: 0 | BN40: =AY40*$BM$3 -> 0 | BO40: =AY40+BL40+BM40+BN40+BC40+BG40 -> 1733.9 | BP40: =BO40-AM40 -> 157.9 | BQ40: =IF(BP40>=0,"Positive Margin","Negative Margin") -> Positive Margin | BR40: No Provision | BS40: =AY40-Y40-Q40-AA40-T40+BC40 -> 157.9 | BT40: =IF(BS40<0, "Negative Margin at Inception", "Positive Margin at Inception") -> Positive Margin at Inception | BU40: =IFERROR(BP40/BO40,"0") -> 0.091066382 | BV40: =IF(BU40<1%,"Less Than 1%",IF(BU40>2%,"More than 2%",IF(BU40>=1%,"1% - 2%"))) -> More than 2% | BW40: =BM40+BN40 -> 0 | BX40: =AL40+AK40 -> 0 | BY40: =BW40-BX40 -> 0 | BZ40: =BM40 -> 0 | CA40: =AK40 -> 0 | CB40: =BZ40-CA40 -> 0 | CC40: Marketplace (IT Assets Disposition) | CD40: 0 | CE40: =AM40-AL40-AA40 -> 1576 | CF40: =BO40-BN40 -> 1733.9 | CG40: =INT((D40- IF(MONTH(D40) >= 4, DATE(YEAR(D40), 4, 1), DATE(YEAR(D40)-1, 4, 1))) / 7) + 1 -> 4 | CH40: 0 | CI40: 0 | CJ40: =_xlfn.XLOOKUP(AP40,POC!B:B,POC!D:D) -> #N/A | CK40: =AY40-Q40 -> 157.9 | CL40: =CK40-Y40+Z40 -> 157.9 | CM40: =BO40-AM40 -> 157.9 | CN40: =AY40*118% -> 2046.002 | CO40: =-Q40*118% -> -1859.68 | CP40: =-BZ40*118% -> 0 | CQ40: =-CA40*118% -> 0 | CR40: =SUM(CN40:CQ40) -> 186.322 | CS40: Telangana - HO | CT40: Telangana - HO | CU40: =MID(G40,3,10) -> AADCC6184H | CV40: =MID(AR40,3,10) -> AARFT3586D | CW40: =H40&F40 -> 2026290000000098CHAITANYA INDIA FIN CREDIT PRIVATE LIMITED
B41: ="Q" & IF(ROUNDUP(MONTH(D41)/3,0)-1=0,4,ROUNDUP(MONTH(D41)/3,0)-1) -> Q1 | C41: =TEXT(AN41,"mmm-yy") -> Apr-26 | D41: 46122 | E41: SH04262103 | F41: NAVATAR CONSULTING PRIVATE LIMITED | G41: 09AACCN4479R1ZJ | H41: Inv/2026-27/01 | I41: 46122 | J41: 26-27/PUR/001072 | K41: 46133 | L41: UP | M41: DL01LV0044 | N41: ITAD Mixed E Waste | O41: 10 | P41: 6567.8 | Q41: =O41*P41 -> 65678 | R41: 0 | S41: =O41-R41 -> 10 | T41: 0 | U41: 0 | V41: 0 | W41: 0 | X41: 0 | Y41: 0 | Z41: 0 | AA41: 0 | AB41: =Y41+AA41+Z41 -> 0 | AC41: 0 | AD41: 0 | AE41: 0 | AF41: 0 | AG41: 0 | AH41: 0 | AI41: 0 | AJ41: 0 | AK41: 0 | AL41: =(BN41*P41/AX41)+AB41/O41*(BN41/AX41) -> 0 | AM41: =Q41+AB41+AL41+AK41+AJ41+T41+AE41 -> 65678 | AN41: 46133 | AO41: 36/IAD/27IN00006 | AP41: 832139000046796207 | AQ41: TRADEWIND BUSINESS SOLUTIONS LLP | AR41: 07AARFT3586D1ZR | AS41: NOIDA,Uttar Pradesh,201301 | AT41: New Delhi | AU41: Delhi | AV41: 162408149669 | AW41: 10 | AX41: 7000 | AY41: =AW41*AX41 -> 70000 | AZ41: =AW41=O41 -> TRUE | BA41: 0 | BB41: =AW41-BA41 -> 10 | BC41: 0 | BD41: Regular | BE41: 0 | BF41: 0 | BG41: 0 | BH41: 0 | BI41: 0 | BJ41: 0 | BK41: 0 | BL41: 0 | BM41: 0 | BN41: =AY41*$BM$3 -> 0 | BO41: =AY41+BL41+BM41+BN41+BC41+BG41 -> 70000 | BP41: =BO41-AM41 -> 4322 | BQ41: =IF(BP41>=0,"Positive Margin","Negative Margin") -> Positive Margin | BR41: No Provision | BS41: =AY41-Y41-Q41-AA41-T41+BC41 -> 4322 | BT41: =IF(BS41<0, "Negative Margin at Inception", "Positive Margin at Inception") -> Positive Margin at Inception | BU41: =IFERROR(BP41/BO41,"0") -> 0.061742857 | BV41: =IF(BU41<1%,"Less Than 1%",IF(BU41>2%,"More than 2%",IF(BU41>=1%,"1% - 2%"))) -> More than 2% | BW41: =BM41+BN41 -> 0 | BX41: =AL41+AK41 -> 0 | BY41: =BW41-BX41 -> 0 | BZ41: =BM41 -> 0 | CA41: =AK41 -> 0 | CB41: =BZ41-CA41 -> 0 | CC41: Marketplace (IT Assets Disposition) | CD41: 0 | CE41: =AM41-AL41-AA41 -> 65678 | CF41: =BO41-BN41 -> 70000 | CG41: =INT((D41- IF(MONTH(D41) >= 4, DATE(YEAR(D41), 4, 1), DATE(YEAR(D41)-1, 4, 1))) / 7) + 1 -> 2 | CH41: 0 | CI41: 0 | CJ41: =_xlfn.XLOOKUP(AP41,POC!B:B,POC!D:D) -> #N/A | CK41: =AY41-Q41 -> 4322 | CL41: =CK41-Y41+Z41 -> 4322 | CM41: =BO41-AM41 -> 4322 | CN41: =AY41*118% -> 82600 | CO41: =-Q41*118% -> -77500.04 | CP41: =-BZ41*118% -> 0 | CQ41: =-CA41*118% -> 0 | CR41: =SUM(CN41:CQ41) -> 5099.96 | CS41: Telangana - HO | CT41: Telangana - HO | CU41: =MID(G41,3,10) -> AACCN4479R | CV41: =MID(AR41,3,10) -> AARFT3586D | CW41: =H41&F41 -> Inv/2026-27/01NAVATAR CONSULTING PRIVATE LIMITED
B42: ="Q" & IF(ROUNDUP(MONTH(D42)/3,0)-1=0,4,ROUNDUP(MONTH(D42)/3,0)-1) -> Q1 | C42: =TEXT(AN42,"mmm-yy") -> Apr-26 | D42: 46122 | E42: SH04262103 | F42: NAVATAR CONSULTING PRIVATE LIMITED | G42: 09AACCN4479R1ZJ | H42: Inv/2026-27/01 | I42: 46122 | J42: 26-27/PUR/001072 | K42: 46133 | L42: UP | M42: DL01LV0044 | N42: ITAD Mixed E Waste | O42: 4 | P42: 1694.93 | Q42: =O42*P42 -> 6779.72 | R42: 0 | S42: =O42-R42 -> 4 | T42: 0 | U42: 0 | V42: 0 | W42: 0 | X42: 0 | Y42: 0 | Z42: 0 | AA42: 0 | AB42: =Y42+AA42+Z42 -> 0 | AC42: 0 | AD42: 0 | AE42: 0 | AF42: 0 | AG42: 0 | AH42: 0 | AI42: 0 | AJ42: 0 | AK42: 0 | AL42: =(BN42*P42/AX42)+AB42/O42*(BN42/AX42) -> 0 | AM42: =Q42+AB42+AL42+AK42+AJ42+T42+AE42 -> 6779.72 | AN42: 46133 | AO42: 36/IAD/27IN00006 | AP42: 832139000046796207 | AQ42: TRADEWIND BUSINESS SOLUTIONS LLP | AR42: 07AARFT3586D1ZR | AS42: NOIDA,Uttar Pradesh,201301 | AT42: New Delhi | AU42: Delhi | AV42: 162408149669 | AW42: 4 | AX42: 1700 | AY42: =AW42*AX42 -> 6800 | AZ42: =AW42=O42 -> TRUE | BA42: 0 | BB42: =AW42-BA42 -> 4 | BC42: 0 | BD42: Regular | BE42: 0 | BF42: 0 | BG42: 0 | BH42: 0 | BI42: 0 | BJ42: 0 | BK42: 0 | BL42: 0 | BM42: 0 | BN42: =AY42*$BM$3 -> 0 | BO42: =AY42+BL42+BM42+BN42+BC42+BG42 -> 6800 | BP42: =BO42-AM42 -> 20.28 | BQ42: =IF(BP42>=0,"Positive Margin","Negative Margin") -> Positive Margin | BR42: No Provision | BS42: =AY42-Y42-Q42-AA42-T42+BC42 -> 20.28 | BT42: =IF(BS42<0, "Negative Margin at Inception", "Positive Margin at Inception") -> Positive Margin at Inception | BU42: =IFERROR(BP42/BO42,"0") -> 0.0029823529 | BV42: =IF(BU42<1%,"Less Than 1%",IF(BU42>2%,"More than 2%",IF(BU42>=1%,"1% - 2%"))) -> Less Than 1% | BW42: =BM42+BN42 -> 0 | BX42: =AL42+AK42 -> 0 | BY42: =BW42-BX42 -> 0 | BZ42: =BM42 -> 0 | CA42: =AK42 -> 0 | CB42: =BZ42-CA42 -> 0 | CC42: Marketplace (IT Assets Disposition) | CD42: 0 | CE42: =AM42-AL42-AA42 -> 6779.72 | CF42: =BO42-BN42 -> 6800 | CG42: =INT((D42- IF(MONTH(D42) >= 4, DATE(YEAR(D42), 4, 1), DATE(YEAR(D42)-1, 4, 1))) / 7) + 1 -> 2 | CH42: 0 | CI42: 0 | CJ42: =_xlfn.XLOOKUP(AP42,POC!B:B,POC!D:D) -> #N/A | CK42: =AY42-Q42 -> 20.28 | CL42: =CK42-Y42+Z42 -> 20.28 | CM42: =BO42-AM42 -> 20.28 | CN42: =AY42*118% -> 8024 | CO42: =-Q42*118% -> -8000.0696 | CP42: =-BZ42*118% -> 0 | CQ42: =-CA42*118% -> 0 | CR42: =SUM(CN42:CQ42) -> 23.9304 | CS42: Telangana - HO | CT42: Telangana - HO | CU42: =MID(G42,3,10) -> AACCN4479R | CV42: =MID(AR42,3,10) -> AARFT3586D | CW42: =H42&F42 -> Inv/2026-27/01NAVATAR CONSULTING PRIVATE LIMITED
B43: ="Q" & IF(ROUNDUP(MONTH(D43)/3,0)-1=0,4,ROUNDUP(MONTH(D43)/3,0)-1) -> Q1 | C43: =TEXT(AN43,"mmm-yy") -> Apr-26 | D43: 46122 | E43: SH04262103 | F43: NAVATAR CONSULTING PRIVATE LIMITED | G43: 09AACCN4479R1ZJ | H43: Inv/2026-27/01 | I43: 46122 | J43: 26-27/PUR/001072 | K43: 46133 | L43: UP | M43: DL01LV0044 | N43: ITAD Mixed E Waste | O43: 10 | P43: 788.14 | Q43: =O43*P43 -> 7881.4 | R43: 0 | S43: =O43-R43 -> 10 | T43: 0 | U43: 0 | V43: 0 | W43: 0 | X43: 0 | Y43: 0 | Z43: 0 | AA43: 0 | AB43: =Y43+AA43+Z43 -> 0 | AC43: 0 | AD43: 0 | AE43: 0 | AF43: 0 | AG43: 0 | AH43: 0 | AI43: 0 | AJ43: 0 | AK43: 0 | AL43: =(BN43*P43/AX43)+AB43/O43*(BN43/AX43) -> 0 | AM43: =Q43+AB43+AL43+AK43+AJ43+T43+AE43 -> 7881.4 | AN43: 46133 | AO43: 36/IAD/27IN00006 | AP43: 832139000046796207 | AQ43: TRADEWIND BUSINESS SOLUTIONS LLP | AR43: 07AARFT3586D1ZR | AS43: NOIDA,Uttar Pradesh,201301 | AT43: New Delhi | AU43: Delhi | AV43: 162408149669 | AW43: 10 | AX43: 1000 | AY43: =AW43*AX43 -> 10000 | AZ43: =AW43=O43 -> TRUE | BA43: 0 | BB43: =AW43-BA43 -> 10 | BC43: 0 | BD43: Regular | BE43: 0 | BF43: 0 | BG43: 0 | BH43: 0 | BI43: 0 | BJ43: 0 | BK43: 0 | BL43: 0 | BM43: 0 | BN43: =AY43*$BM$3 -> 0 | BO43: =AY43+BL43+BM43+BN43+BC43+BG43 -> 10000 | BP43: =BO43-AM43 -> 2118.6 | BQ43: =IF(BP43>=0,"Positive Margin","Negative Margin") -> Positive Margin | BR43: No Provision | BS43: =AY43-Y43-Q43-AA43-T43+BC43 -> 2118.6 | BT43: =IF(BS43<0, "Negative Margin at Inception", "Positive Margin at Inception") -> Positive Margin at Inception | BU43: =IFERROR(BP43/BO43,"0") -> 0.21186 | BV43: =IF(BU43<1%,"Less Than 1%",IF(BU43>2%,"More than 2%",IF(BU43>=1%,"1% - 2%"))) -> More than 2% | BW43: =BM43+BN43 -> 0 | BX43: =AL43+AK43 -> 0 | BY43: =BW43-BX43 -> 0 | BZ43: =BM43 -> 0 | CA43: =AK43 -> 0 | CB43: =BZ43-CA43 -> 0 | CC43: Marketplace (IT Assets Disposition) | CD43: 0 | CE43: =AM43-AL43-AA43 -> 7881.4 | CF43: =BO43-BN43 -> 10000 | CG43: =INT((D43- IF(MONTH(D43) >= 4, DATE(YEAR(D43), 4, 1), DATE(YEAR(D43)-1, 4, 1))) / 7) + 1 -> 2 | CH43: 0 | CI43: 0 | CJ43: =_xlfn.XLOOKUP(AP43,POC!B:B,POC!D:D) -> #N/A | CK43: =AY43-Q43 -> 2118.6 | CL43: =CK43-Y43+Z43 -> 2118.6 | CM43: =BO43-AM43 -> 2118.6 | CN43: =AY43*118% -> 11800 | CO43: =-Q43*118% -> -9300.052 | CP43: =-BZ43*118% -> 0 | CQ43: =-CA43*118% -> 0 | CR43: =SUM(CN43:CQ43) -> 2499.948 | CS43: Telangana - HO | CT43: Telangana - HO | CU43: =MID(G43,3,10) -> AACCN4479R | CV43: =MID(AR43,3,10) -> AARFT3586D | CW43: =H43&F43 -> Inv/2026-27/01NAVATAR CONSULTING PRIVATE LIMITED
B44: ="Q" & IF(ROUNDUP(MONTH(D44)/3,0)-1=0,4,ROUNDUP(MONTH(D44)/3,0)-1) -> Q1 | C44: =TEXT(AN44,"mmm-yy") -> Apr-26 | D44: 46122 | E44: SH04262103 | F44: NAVATAR CONSULTING PRIVATE LIMITED | G44: 09AACCN4479R1ZJ | H44: Inv/2026-27/01 | I44: 46122 | J44: 26-27/PUR/001072 | K44: 46133 | L44: UP | M44: DL01LV0044 | N44: ITAD Mixed E Waste | O44: 15 | P44: 67.8 | Q44: =O44*P44 -> 1017 | R44: 0 | S44: =O44-R44 -> 15 | T44: 0 | U44: 0 | V44: 0 | W44: 0 | X44: 0 | Y44: 0 | Z44: 0 | AA44: 0 | AB44: =Y44+AA44+Z44 -> 0 | AC44: 0 | AD44: 0 | AE44: 0 | AF44: 0 | AG44: 0 | AH44: 0 | AI44: 0 | AJ44: 0 | AK44: 0 | AL44: =(BN44*P44/AX44)+AB44/O44*(BN44/AX44) -> 0 | AM44: =Q44+AB44+AL44+AK44+AJ44+T44+AE44 -> 1017 | AN44: 46133 | AO44: 36/IAD/27IN00006 | AP44: 832139000046796207 | AQ44: TRADEWIND BUSINESS SOLUTIONS LLP | AR44: 07AARFT3586D1ZR | AS44: NOIDA,Uttar Pradesh,201301 | AT44: New Delhi | AU44: Delhi | AV44: 162408149669 | AW44: 15 | AX44: 450 | AY44: =AW44*AX44 -> 6750 | AZ44: =AW44=O44 -> TRUE | BA44: 0 | BB44: =AW44-BA44 -> 15 | BC44: 0 | BD44: Regular | BE44: 0 | BF44: 0 | BG44: 0 | BH44: 0 | BI44: 0 | BJ44: 0 | BK44: 0 | BL44: 0 | BM44: 0 | BN44: =AY44*$BM$3 -> 0 | BO44: =AY44+BL44+BM44+BN44+BC44+BG44 -> 6750 | BP44: =BO44-AM44 -> 5733 | BQ44: =IF(BP44>=0,"Positive Margin","Negative Margin") -> Positive Margin | BR44: No Provision | BS44: =AY44-Y44-Q44-AA44-T44+BC44 -> 5733 | BT44: =IF(BS44<0, "Negative Margin at Inception", "Positive Margin at Inception") -> Positive Margin at Inception | BU44: =IFERROR(BP44/BO44,"0") -> 0.84933333 | BV44: =IF(BU44<1%,"Less Than 1%",IF(BU44>2%,"More than 2%",IF(BU44>=1%,"1% - 2%"))) -> More than 2% | BW44: =BM44+BN44 -> 0 | BX44: =AL44+AK44 -> 0 | BY44: =BW44-BX44 -> 0 | BZ44: =BM44 -> 0 | CA44: =AK44 -> 0 | CB44: =BZ44-CA44 -> 0 | CC44: Marketplace (IT Assets Disposition) | CD44: 0 | CE44: =AM44-AL44-AA44 -> 1017 | CF44: =BO44-BN44 -> 6750 | CG44: =INT((D44- IF(MONTH(D44) >= 4, DATE(YEAR(D44), 4, 1), DATE(YEAR(D44)-1, 4, 1))) / 7) + 1 -> 2 | CH44: 0 | CI44: 0 | CJ44: =_xlfn.XLOOKUP(AP44,POC!B:B,POC!D:D) -> #N/A | CK44: =AY44-Q44 -> 5733 | CL44: =CK44-Y44+Z44 -> 5733 | CM44: =BO44-AM44 -> 5733 | CN44: =AY44*118% -> 7965 | CO44: =-Q44*118% -> -1200.06 | CP44: =-BZ44*118% -> 0 | CQ44: =-CA44*118% -> 0 | CR44: =SUM(CN44:CQ44) -> 6764.94 | CS44: Telangana - HO | CT44: Telangana - HO | CU44: =MID(G44,3,10) -> AACCN4479R | CV44: =MID(AR44,3,10) -> AARFT3586D | CW44: =H44&F44 -> Inv/2026-27/01NAVATAR CONSULTING PRIVATE LIMITED
B45: ="Q" & IF(ROUNDUP(MONTH(D45)/3,0)-1=0,4,ROUNDUP(MONTH(D45)/3,0)-1) -> Q1 | C45: =TEXT(AN45,"mmm-yy") -> Apr-26 | D45: 46122 | E45: SH04262103 | F45: NAVATAR CONSULTING PRIVATE LIMITED | G45: 09AACCN4479R1ZJ | H45: Inv/2026-27/01 | I45: 46122 | J45: 26-27/PUR/001072 | K45: 46133 | L45: UP | M45: DL01LV0044 | N45: ITAD Mixed E Waste | O45: 2 | P45: 211.87 | Q45: =O45*P45 -> 423.74 | R45: 0 | S45: =O45-R45 -> 2 | T45: 0 | U45: 0 | V45: 0 | W45: 0 | X45: 0 | Y45: 0 | Z45: 0 | AA45: 0 | AB45: =Y45+AA45+Z45 -> 0 | AC45: 0 | AD45: 0 | AE45: 0 | AF45: 0 | AG45: 0 | AH45: 0 | AI45: 0 | AJ45: 0 | AK45: 0 | AL45: =(BN45*P45/AX45)+AB45/O45*(BN45/AX45) -> 0 | AM45: =Q45+AB45+AL45+AK45+AJ45+T45+AE45 -> 423.74 | AN45: 46133 | AO45: 36/IAD/27IN00006 | AP45: 832139000046796207 | AQ45: TRADEWIND BUSINESS SOLUTIONS LLP | AR45: 07AARFT3586D1ZR | AS45: NOIDA,Uttar Pradesh,201301 | AT45: New Delhi | AU45: Delhi | AV45: 162408149669 | AW45: 2 | AX45: 400 | AY45: =AW45*AX45 -> 800 | AZ45: =AW45=O45 -> TRUE | BA45: 0 | BB45: =AW45-BA45 -> 2 | BC45: 0 | BD45: Regular | BE45: 0 | BF45: 0 | BG45: 0 | BH45: 0 | BI45: 0 | BJ45: 0 | BK45: 0 | BL45: 0 | BM45: 0 | BN45: =AY45*$BM$3 -> 0 | BO45: =AY45+BL45+BM45+BN45+BC45+BG45 -> 800 | BP45: =BO45-AM45 -> 376.26 | BQ45: =IF(BP45>=0,"Positive Margin","Negative Margin") -> Positive Margin | BR45: No Provision | BS45: =AY45-Y45-Q45-AA45-T45+BC45 -> 376.26 | BT45: =IF(BS45<0, "Negative Margin at Inception", "Positive Margin at Inception") -> Positive Margin at Inception | BU45: =IFERROR(BP45/BO45,"0") -> 0.470325 | BV45: =IF(BU45<1%,"Less Than 1%",IF(BU45>2%,"More than 2%",IF(BU45>=1%,"1% - 2%"))) -> More than 2% | BW45: =BM45+BN45 -> 0 | BX45: =AL45+AK45 -> 0 | BY45: =BW45-BX45 -> 0 | BZ45: =BM45 -> 0 | CA45: =AK45 -> 0 | CB45: =BZ45-CA45 -> 0 | CC45: Marketplace (IT Assets Disposition) | CD45: 0 | CE45: =AM45-AL45-AA45 -> 423.74 | CF45: =BO45-BN45 -> 800 | CG45: =INT((D45- IF(MONTH(D45) >= 4, DATE(YEAR(D45), 4, 1), DATE(YEAR(D45)-1, 4, 1))) / 7) + 1 -> 2 | CH45: 0 | CI45: 0 | CJ45: =_xlfn.XLOOKUP(AP45,POC!B:B,POC!D:D) -> #N/A | CK45: =AY45-Q45 -> 376.26 | CL45: =CK45-Y45+Z45 -> 376.26 | CM45: =BO45-AM45 -> 376.26 | CN45: =AY45*118% -> 944 | CO45: =-Q45*118% -> -500.0132 | CP45: =-BZ45*118% -> 0 | CQ45: =-CA45*118% -> 0 | CR45: =SUM(CN45:CQ45) -> 443.9868 | CS45: Telangana - HO | CT45: Telangana - HO | CU45: =MID(G45,3,10) -> AACCN4479R | CV45: =MID(AR45,3,10) -> AARFT3586D | CW45: =H45&F45 -> Inv/2026-27/01NAVATAR CONSULTING PRIVATE LIMITED
B46: ="Q" & IF(ROUNDUP(MONTH(D46)/3,0)-1=0,4,ROUNDUP(MONTH(D46)/3,0)-1) -> Q1 | C46: =TEXT(AN46,"mmm-yy") -> Apr-26 | D46: 46122 | E46: SH04262103 | F46: NAVATAR CONSULTING PRIVATE LIMITED | G46: 09AACCN4479R1ZJ | H46: Inv/2026-27/01 | I46: 46122 | J46: 26-27/PUR/001072 | K46: 46133 | L46: UP | M46: DL01LV0044 | N46: ITAD Mixed E Waste | O46: 190 | P46: 4.235 | Q46: =O46*P46 -> 804.65 | R46: 0 | S46: =O46-R46 -> 190 | T46: 0 | U46: 0 | V46: 0 | W46: 0 | X46: 0 | Y46: 0 | Z46: 0 | AA46: 0 | AB46: =Y46+AA46+Z46 -> 0 | AC46: 0 | AD46: 0 | AE46: 0 | AF46: 0 | AG46: 0 | AH46: 0 | AI46: 0 | AJ46: 0 | AK46: 0 | AL46: =(BN46*P46/AX46)+AB46/O46*(BN46/AX46) -> 0 | AM46: =Q46+AB46+AL46+AK46+AJ46+T46+AE46 -> 804.65 | AN46: 46133 | AO46: 36/IAD/27IN00006 | AP46: 832139000046796207 | AQ46: TRADEWIND BUSINESS SOLUTIONS LLP | AR46: 07AARFT3586D1ZR | AS46: NOIDA,Uttar Pradesh,201301 | AT46: New Delhi | AU46: Delhi | AV46: 162408149669 | AW46: 190 | AX46: 6 | AY46: =AW46*AX46 -> 1140 | AZ46: =AW46=O46 -> TRUE | BA46: 0 | BB46: =AW46-BA46 -> 190 | BC46: 0 | BD46: Regular | BE46: 0 | BF46: 0 | BG46: 0 | BH46: 0 | BI46: 0 | BJ46: 0 | BK46: 0 | BL46: 0 | BM46: 0 | BN46: =AY46*$BM$3 -> 0 | BO46: =AY46+BL46+BM46+BN46+BC46+BG46 -> 1140 | BP46: =BO46-AM46 -> 335.35 | BQ46: =IF(BP46>=0,"Positive Margin","Negative Margin") -> Positive Margin | BR46: No Provision | BS46: =AY46-Y46-Q46-AA46-T46+BC46 -> 335.35 | BT46: =IF(BS46<0, "Negative Margin at Inception", "Positive Margin at Inception") -> Positive Margin at Inception | BU46: =IFERROR(BP46/BO46,"0") -> 0.29416667 | BV46: =IF(BU46<1%,"Less Than 1%",IF(BU46>2%,"More than 2%",IF(BU46>=1%,"1% - 2%"))) -> More than 2% | BW46: =BM46+BN46 -> 0 | BX46: =AL46+AK46 -> 0 | BY46: =BW46-BX46 -> 0 | BZ46: =BM46 -> 0 | CA46: =AK46 -> 0 | CB46: =BZ46-CA46 -> 0 | CC46: Marketplace (IT Assets Disposition) | CD46: 0 | CE46: =AM46-AL46-AA46 -> 804.65 | CF46: =BO46-BN46 -> 1140 | CG46: =INT((D46- IF(MONTH(D46) >= 4, DATE(YEAR(D46), 4, 1), DATE(YEAR(D46)-1, 4, 1))) / 7) + 1 -> 2 | CH46: 0 | CI46: 0 | CJ46: =_xlfn.XLOOKUP(AP46,POC!B:B,POC!D:D) -> #N/A | CK46: =AY46-Q46 -> 335.35 | CL46: =CK46-Y46+Z46 -> 335.35 | CM46: =BO46-AM46 -> 335.35 | CN46: =AY46*118% -> 1345.2 | CO46: =-Q46*118% -> -949.487 | CP46: =-BZ46*118% -> 0 | CQ46: =-CA46*118% -> 0 | CR46: =SUM(CN46:CQ46) -> 395.713 | CS46: Telangana - HO | CT46: Telangana - HO | CU46: =MID(G46,3,10) -> AACCN4479R | CV46: =MID(AR46,3,10) -> AARFT3586D | CW46: =H46&F46 -> Inv/2026-27/01NAVATAR CONSULTING PRIVATE LIMITED
B47: ="Q" & IF(ROUNDUP(MONTH(D47)/3,0)-1=0,4,ROUNDUP(MONTH(D47)/3,0)-1) -> Q1 | C47: =TEXT(AN47,"mmm-yy") -> Apr-26 | D47: 46122 | E47: SH04262103 | F47: NAVATAR CONSULTING PRIVATE LIMITED | G47: 09AACCN4479R1ZJ | H47: Inv/2026-27/01 | I47: 46122 | J47: 26-27/PUR/001072 | K47: 46133 | L47: UP | M47: DL01LV0044 | N47: ITAD Mixed E Waste | O47: 1 | P47: 105.98 | Q47: =O47*P47 -> 105.98 | R47: 0 | S47: =O47-R47 -> 1 | T47: 0 | U47: 0 | V47: 0 | W47: 0 | X47: 0 | Y47: 0 | Z47: 0 | AA47: 0 | AB47: =Y47+AA47+Z47 -> 0 | AC47: 0 | AD47: 0 | AE47: 0 | AF47: 0 | AG47: 0 | AH47: 0 | AI47: 0 | AJ47: 0 | AK47: 0 | AL47: =(BN47*P47/AX47)+AB47/O47*(BN47/AX47) -> 0 | AM47: =Q47+AB47+AL47+AK47+AJ47+T47+AE47 -> 105.98 | AN47: 46133 | AO47: 36/IAD/27IN00006 | AP47: 832139000046796207 | AQ47: TRADEWIND BUSINESS SOLUTIONS LLP | AR47: 07AARFT3586D1ZR | AS47: NOIDA,Uttar Pradesh,201301 | AT47: New Delhi | AU47: Delhi | AV47: 162408149669 | AW47: 1 | AX47: 207 | AY47: =AW47*AX47 -> 207 | AZ47: =AW47=O47 -> TRUE | BA47: 0 | BB47: =AW47-BA47 -> 1 | BC47: 0 | BD47: Regular | BE47: 0 | BF47: 0 | BG47: 0 | BH47: 0 | BI47: 0 | BJ47: 0 | BK47: 0 | BL47: 0 | BM47: 0 | BN47: =AY47*$BM$3 -> 0 | BO47: =AY47+BL47+BM47+BN47+BC47+BG47 -> 207 | BP47: =BO47-AM47 -> 101.02 | BQ47: =IF(BP47>=0,"Positive Margin","Negative Margin") -> Positive Margin | BR47: No Provision | BS47: =AY47-Y47-Q47-AA47-T47+BC47 -> 101.02 | BT47: =IF(BS47<0, "Negative Margin at Inception", "Positive Margin at Inception") -> Positive Margin at Inception | BU47: =IFERROR(BP47/BO47,"0") -> 0.48801932 | BV47: =IF(BU47<1%,"Less Than 1%",IF(BU47>2%,"More than 2%",IF(BU47>=1%,"1% - 2%"))) -> More than 2% | BW47: =BM47+BN47 -> 0 | BX47: =AL47+AK47 -> 0 | BY47: =BW47-BX47 -> 0 | BZ47: =BM47 -> 0 | CA47: =AK47 -> 0 | CB47: =BZ47-CA47 -> 0 | CC47: Marketplace (IT Assets Disposition) | CD47: 0 | CE47: =AM47-AL47-AA47 -> 105.98 | CF47: =BO47-BN47 -> 207 | CG47: =INT((D47- IF(MONTH(D47) >= 4, DATE(YEAR(D47), 4, 1), DATE(YEAR(D47)-1, 4, 1))) / 7) + 1 -> 2 | CH47: 0 | CI47: 0 | CJ47: =_xlfn.XLOOKUP(AP47,POC!B:B,POC!D:D) -> #N/A | CK47: =AY47-Q47 -> 101.02 | CL47: =CK47-Y47+Z47 -> 101.02 | CM47: =BO47-AM47 -> 101.02 | CN47: =AY47*118% -> 244.26 | CO47: =-Q47*118% -> -125.0564 | CP47: =-BZ47*118% -> 0 | CQ47: =-CA47*118% -> 0 | CR47: =SUM(CN47:CQ47) -> 119.2036 | CS47: Telangana - HO | CT47: Telangana - HO | CU47: =MID(G47,3,10) -> AACCN4479R | CV47: =MID(AR47,3,10) -> AARFT3586D | CW47: =H47&F47 -> Inv/2026-27/01NAVATAR CONSULTING PRIVATE LIMITED
B48: ="Q" & IF(ROUNDUP(MONTH(D48)/3,0)-1=0,4,ROUNDUP(MONTH(D48)/3,0)-1) -> Q1 | C48: =TEXT(AN48,"mmm-yy") -> Apr-26 | D48: 46122 | E48: SH04262103 | F48: NAVATAR CONSULTING PRIVATE LIMITED | G48: 09AACCN4479R1ZJ | H48: Inv/2026-27/01 | I48: 46122 | J48: 26-27/PUR/001072 | K48: 46133 | L48: UP | M48: DL01LV0044 | N48: ITAD Mixed E Waste | O48: 11 | P48: 4.25 | Q48: =O48*P48 -> 46.75 | R48: 0 | S48: =O48-R48 -> 11 | T48: 0 | U48: 0 | V48: 0 | W48: 0 | X48: 0 | Y48: 0 | Z48: 0 | AA48: 0 | AB48: =Y48+AA48+Z48 -> 0 | AC48: 0 | AD48: 0 | AE48: 0 | AF48: 0 | AG48: 0 | AH48: 0 | AI48: 0 | AJ48: 0 | AK48: 0 | AL48: =(BN48*P48/AX48)+AB48/O48*(BN48/AX48) -> 0 | AM48: =Q48+AB48+AL48+AK48+AJ48+T48+AE48 -> 46.75 | AN48: 46133 | AO48: 36/IAD/27IN00006 | AP48: 832139000046796207 | AQ48: TRADEWIND BUSINESS SOLUTIONS LLP | AR48: 07AARFT3586D1ZR | AS48: NOIDA,Uttar Pradesh,201301 | AT48: New Delhi | AU48: Delhi | AV48: 162408149669 | AW48: 11 | AX48: 10 | AY48: =AW48*AX48 -> 110 | AZ48: =AW48=O48 -> TRUE | BA48: 0 | BB48: =AW48-BA48 -> 11 | BC48: 0 | BD48: Regular | BE48: 0 | BF48: 0 | BG48: 0 | BH48: 0 | BI48: 0 | BJ48: 0 | BK48: 0 | BL48: 0 | BM48: 0 | BN48: =AY48*$BM$3 -> 0 | BO48: =AY48+BL48+BM48+BN48+BC48+BG48 -> 110 | BP48: =BO48-AM48 -> 63.25 | BQ48: =IF(BP48>=0,"Positive Margin","Negative Margin") -> Positive Margin | BR48: No Provision | BS48: =AY48-Y48-Q48-AA48-T48+BC48 -> 63.25 | BT48: =IF(BS48<0, "Negative Margin at Inception", "Positive Margin at Inception") -> Positive Margin at Inception | BU48: =IFERROR(BP48/BO48,"0") -> 0.575 | BV48: =IF(BU48<1%,"Less Than 1%",IF(BU48>2%,"More than 2%",IF(BU48>=1%,"1% - 2%"))) -> More than 2% | BW48: =BM48+BN48 -> 0 | BX48: =AL48+AK48 -> 0 | BY48: =BW48-BX48 -> 0 | BZ48: =BM48 -> 0 | CA48: =AK48 -> 0 | CB48: =BZ48-CA48 -> 0 | CC48: Marketplace (IT Assets Disposition) | CD48: 0 | CE48: =AM48-AL48-AA48 -> 46.75 | CF48: =BO48-BN48 -> 110 | CG48: =INT((D48- IF(MONTH(D48) >= 4, DATE(YEAR(D48), 4, 1), DATE(YEAR(D48)-1, 4, 1))) / 7) + 1 -> 2 | CH48: 0 | CI48: 0 | CJ48: =_xlfn.XLOOKUP(AP48,POC!B:B,POC!D:D) -> #N/A | CK48: =AY48-Q48 -> 63.25 | CL48: =CK48-Y48+Z48 -> 63.25 | CM48: =BO48-AM48 -> 63.25 | CN48: =AY48*118% -> 129.8 | CO48: =-Q48*118% -> -55.165 | CP48: =-BZ48*118% -> 0 | CQ48: =-CA48*118% -> 0 | CR48: =SUM(CN48:CQ48) -> 74.635 | CS48: Telangana - HO | CT48: Telangana - HO | CU48: =MID(G48,3,10) -> AACCN4479R | CV48: =MID(AR48,3,10) -> AARFT3586D | CW48: =H48&F48 -> Inv/2026-27/01NAVATAR CONSULTING PRIVATE LIMITED
B49: ="Q" & IF(ROUNDUP(MONTH(D49)/3,0)-1=0,4,ROUNDUP(MONTH(D49)/3,0)-1) -> Q1 | C49: =TEXT(AN49,"mmm-yy") -> Apr-26 | D49: 46122 | E49: SH04262103 | F49: NAVATAR CONSULTING PRIVATE LIMITED | G49: 09AACCN4479R1ZJ | H49: Inv/2026-27/01 | I49: 46122 | J49: 26-27/PUR/001072 | K49: 46133 | L49: UP | M49: DL01LV0044 | N49: ITAD Mixed E Waste | O49: 10 | P49: 127.13 | Q49: =O49*P49 -> 1271.3 | R49: 0 | S49: =O49-R49 -> 10 | T49: 0 | U49: 0 | V49: 0 | W49: 0 | X49: 0 | Y49: 0 | Z49: 0 | AA49: 0 | AB49: =Y49+AA49+Z49 -> 0 | AC49: 0 | AD49: 0 | AE49: 0 | AF49: 0 | AG49: 0 | AH49: 0 | AI49: 0 | AJ49: 0 | AK49: 0 | AL49: =(BN49*P49/AX49)+AB49/O49*(BN49/AX49) -> 0 | AM49: =Q49+AB49+AL49+AK49+AJ49+T49+AE49 -> 1271.3 | AN49: 46133 | AO49: 36/IAD/27IN00006 | AP49: 832139000046796207 | AQ49: TRADEWIND BUSINESS SOLUTIONS LLP | AR49: 07AARFT3586D1ZR | AS49: NOIDA,Uttar Pradesh,201301 | AT49: New Delhi | AU49: Delhi | AV49: 162408149669 | AW49: 10 | AX49: 250 | AY49: =AW49*AX49 -> 2500 | AZ49: =AW49=O49 -> TRUE | BA49: 0 | BB49: =AW49-BA49 -> 10 | BC49: 0 | BD49: Regular | BE49: 0 | BF49: 0 | BG49: 0 | BH49: 0 | BI49: 0 | BJ49: 0 | BK49: 0 | BL49: 0 | BM49: 0 | BN49: =AY49*$BM$3 -> 0 | BO49: =AY49+BL49+BM49+BN49+BC49+BG49 -> 2500 | BP49: =BO49-AM49 -> 1228.7 | BQ49: =IF(BP49>=0,"Positive Margin","Negative Margin") -> Positive Margin | BR49: No Provision | BS49: =AY49-Y49-Q49-AA49-T49+BC49 -> 1228.7 | BT49: =IF(BS49<0, "Negative Margin at Inception", "Positive Margin at Inception") -> Positive Margin at Inception | BU49: =IFERROR(BP49/BO49,"0") -> 0.49148 | BV49: =IF(BU49<1%,"Less Than 1%",IF(BU49>2%,"More than 2%",IF(BU49>=1%,"1% - 2%"))) -> More than 2% | BW49: =BM49+BN49 -> 0 | BX49: =AL49+AK49 -> 0 | BY49: =BW49-BX49 -> 0 | BZ49: =BM49 -> 0 | CA49: =AK49 -> 0 | CB49: =BZ49-CA49 -> 0 | CC49: Marketplace (IT Assets Disposition) | CD49: 0 | CE49: =AM49-AL49-AA49 -> 1271.3 | CF49: =BO49-BN49 -> 2500 | CG49: =INT((D49- IF(MONTH(D49) >= 4, DATE(YEAR(D49), 4, 1), DATE(YEAR(D49)-1, 4, 1))) / 7) + 1 -> 2 | CH49: 0 | CI49: 0 | CJ49: =_xlfn.XLOOKUP(AP49,POC!B:B,POC!D:D) -> #N/A | CK49: =AY49-Q49 -> 1228.7 | CL49: =CK49-Y49+Z49 -> 1228.7 | CM49: =BO49-AM49 -> 1228.7 | CN49: =AY49*118% -> 2950 | CO49: =-Q49*118% -> -1500.134 | CP49: =-BZ49*118% -> 0 | CQ49: =-CA49*118% -> 0 | CR49: =SUM(CN49:CQ49) -> 1449.866 | CS49: Telangana - HO | CT49: Telangana - HO | CU49: =MID(G49,3,10) -> AACCN4479R | CV49: =MID(AR49,3,10) -> AARFT3586D | CW49: =H49&F49 -> Inv/2026-27/01NAVATAR CONSULTING PRIVATE LIMITED
B50: ="Q" & IF(ROUNDUP(MONTH(D50)/3,0)-1=0,4,ROUNDUP(MONTH(D50)/3,0)-1) -> Q1 | C50: =TEXT(AN50,"mmm-yy") -> Apr-26 | D50: 46122 | E50: SH04262103 | F50: NAVATAR CONSULTING PRIVATE LIMITED | G50: 09AACCN4479R1ZJ | H50: Inv/2026-27/01 | I50: 46122 | J50: 26-27/PUR/001072 | K50: 46133 | L50: UP | M50: DL01LV0044 | N50: ITAD Mixed E Waste | O50: 6 | P50: 42.38 | Q50: =O50*P50 -> 254.28 | R50: 0 | S50: =O50-R50 -> 6 | T50: 0 | U50: 0 | V50: 0 | W50: 0 | X50: 0 | Y50: 0 | Z50: 0 | AA50: 0 | AB50: =Y50+AA50+Z50 -> 0 | AC50: 0 | AD50: 0 | AE50: 0 | AF50: 0 | AG50: 0 | AH50: 0 | AI50: 0 | AJ50: 0 | AK50: 0 | AL50: =(BN50*P50/AX50)+AB50/O50*(BN50/AX50) -> 0 | AM50: =Q50+AB50+AL50+AK50+AJ50+T50+AE50 -> 254.28 | AN50: 46133 | AO50: 36/IAD/27IN00006 | AP50: 832139000046796207 | AQ50: TRADEWIND BUSINESS SOLUTIONS LLP | AR50: 07AARFT3586D1ZR | AS50: NOIDA,Uttar Pradesh,201301 | AT50: New Delhi | AU50: Delhi | AV50: 162408149669 | AW50: 6 | AX50: 100 | AY50: =AW50*AX50 -> 600 | AZ50: =AW50=O50 -> TRUE | BA50: 0 | BB50: =AW50-BA50 -> 6 | BC50: 0 | BD50: Regular | BE50: 0 | BF50: 0 | BG50: 0 | BH50: 0 | BI50: 0 | BJ50: 0 | BK50: 0 | BL50: 0 | BM50: 0 | BN50: =AY50*$BM$3 -> 0 | BO50: =AY50+BL50+BM50+BN50+BC50+BG50 -> 600 | BP50: =BO50-AM50 -> 345.72 | BQ50: =IF(BP50>=0,"Positive Margin","Negative Margin") -> Positive Margin | BR50: No Provision | BS50: =AY50-Y50-Q50-AA50-T50+BC50 -> 345.72 | BT50: =IF(BS50<0, "Negative Margin at Inception", "Positive Margin at Inception") -> Positive Margin at Inception | BU50: =IFERROR(BP50/BO50,"0") -> 0.5762 | BV50: =IF(BU50<1%,"Less Than 1%",IF(BU50>2%,"More than 2%",IF(BU50>=1%,"1% - 2%"))) -> More than 2% | BW50: =BM50+BN50 -> 0 | BX50: =AL50+AK50 -> 0 | BY50: =BW50-BX50 -> 0 | BZ50: =BM50 -> 0 | CA50: =AK50 -> 0 | CB50: =BZ50-CA50 -> 0 | CC50: Marketplace (IT Assets Disposition) | CD50: 0 | CE50: =AM50-AL50-AA50 -> 254.28 | CF50: =BO50-BN50 -> 600 | CG50: =INT((D50- IF(MONTH(D50) >= 4, DATE(YEAR(D50), 4, 1), DATE(YEAR(D50)-1, 4, 1))) / 7) + 1 -> 2 | CH50: 0 | CI50: 0 | CJ50: =_xlfn.XLOOKUP(AP50,POC!B:B,POC!D:D) -> #N/A | CK50: =AY50-Q50 -> 345.72 | CL50: =CK50-Y50+Z50 -> 345.72 | CM50: =BO50-AM50 -> 345.72 | CN50: =AY50*118% -> 708 | CO50: =-Q50*118% -> -300.0504 | CP50: =-BZ50*118% -> 0 | CQ50: =-CA50*118% -> 0 | CR50: =SUM(CN50:CQ50) -> 407.9496 | CS50: Telangana - HO | CT50: Telangana - HO | CU50: =MID(G50,3,10) -> AACCN4479R | CV50: =MID(AR50,3,10) -> AARFT3586D | CW50: =H50&F50 -> Inv/2026-27/01NAVATAR CONSULTING PRIVATE LIMITED
B51: ="Q" & IF(ROUNDUP(MONTH(D51)/3,0)-1=0,4,ROUNDUP(MONTH(D51)/3,0)-1) -> Q1 | C51: =TEXT(AN51,"mmm-yy") -> Apr-26 | D51: 46122 | E51: SH04262103 | F51: NAVATAR CONSULTING PRIVATE LIMITED | G51: 09AACCN4479R1ZJ | H51: Inv/2026-27/01 | I51: 46122 | J51: 26-27/PUR/001072 | K51: 46133 | L51: UP | M51: DL01LV0044 | N51: ITAD Mixed E Waste | O51: 11 | P51: 12.71 | Q51: =O51*P51 -> 139.81 | R51: 0 | S51: =O51-R51 -> 11 | T51: 0 | U51: 0 | V51: 0 | W51: 0 | X51: 0 | Y51: 0 | Z51: 0 | AA51: 0 | AB51: =Y51+AA51+Z51 -> 0 | AC51: 0 | AD51: 0 | AE51: 0 | AF51: 0 | AG51: 0 | AH51: 0 | AI51: 0 | AJ51: 0 | AK51: 0 | AL51: =(BN51*P51/AX51)+AB51/O51*(BN51/AX51) -> 0 | AM51: =Q51+AB51+AL51+AK51+AJ51+T51+AE51 -> 139.81 | AN51: 46133 | AO51: 36/IAD/27IN00006 | AP51: 832139000046796207 | AQ51: TRADEWIND BUSINESS SOLUTIONS LLP | AR51: 07AARFT3586D1ZR | AS51: NOIDA,Uttar Pradesh,201301 | AT51: New Delhi | AU51: Delhi | AV51: 162408149669 | AW51: 11 | AX51: 23 | AY51: =AW51*AX51 -> 253 | AZ51: =AW51=O51 -> TRUE | BA51: 0 | BB51: =AW51-BA51 -> 11 | BC51: 0 | BD51: Regular | BE51: 0 | BF51: 0 | BG51: 0 | BH51: 0 | BI51: 0 | BJ51: 0 | BK51: 0 | BL51: 0 | BM51: 0 | BN51: =AY51*$BM$3 -> 0 | BO51: =AY51+BL51+BM51+BN51+BC51+BG51 -> 253 | BP51: =BO51-AM51 -> 113.19 | BQ51: =IF(BP51>=0,"Positive Margin","Negative Margin") -> Positive Margin | BR51: No Provision | BS51: =AY51-Y51-Q51-AA51-T51+BC51 -> 113.19 | BT51: =IF(BS51<0, "Negative Margin at Inception", "Positive Margin at Inception") -> Positive Margin at Inception | BU51: =IFERROR(BP51/BO51,"0") -> 0.4473913 | BV51: =IF(BU51<1%,"Less Than 1%",IF(BU51>2%,"More than 2%",IF(BU51>=1%,"1% - 2%"))) -> More than 2% | BW51: =BM51+BN51 -> 0 | BX51: =AL51+AK51 -> 0 | BY51: =BW51-BX51 -> 0 | BZ51: =BM51 -> 0 | CA51: =AK51 -> 0 | CB51: =BZ51-CA51 -> 0 | CC51: Marketplace (IT Assets Disposition) | CD51: 0 | CE51: =AM51-AL51-AA51 -> 139.81 | CF51: =BO51-BN51 -> 253 | CG51: =INT((D51- IF(MONTH(D51) >= 4, DATE(YEAR(D51), 4, 1), DATE(YEAR(D51)-1, 4, 1))) / 7) + 1 -> 2 | CH51: 0 | CI51: 0 | CJ51: =_xlfn.XLOOKUP(AP51,POC!B:B,POC!D:D) -> #N/A | CK51: =AY51-Q51 -> 113.19 | CL51: =CK51-Y51+Z51 -> 113.19 | CM51: =BO51-AM51 -> 113.19 | CN51: =AY51*118% -> 298.54 | CO51: =-Q51*118% -> -164.9758 | CP51: =-BZ51*118% -> 0 | CQ51: =-CA51*118% -> 0 | CR51: =SUM(CN51:CQ51) -> 133.5642 | CS51: Telangana - HO | CT51: Telangana - HO | CU51: =MID(G51,3,10) -> AACCN4479R | CV51: =MID(AR51,3,10) -> AARFT3586D | CW51: =H51&F51 -> Inv/2026-27/01NAVATAR CONSULTING PRIVATE LIMITED
B52: ="Q" & IF(ROUNDUP(MONTH(D52)/3,0)-1=0,4,ROUNDUP(MONTH(D52)/3,0)-1) -> Q1 | C52: =TEXT(AN52,"mmm-yy") -> Apr-26 | D52: 46122 | E52: SH04262103 | F52: NAVATAR CONSULTING PRIVATE LIMITED | G52: 09AACCN4479R1ZJ | H52: Inv/2026-27/01 | I52: 46122 | J52: 26-27/PUR/001072 | K52: 46133 | L52: UP | M52: DL01LV0044 | N52: ITAD Mixed E Waste | O52: 27 | P52: 12.71 | Q52: =O52*P52 -> 343.17 | R52: 0 | S52: =O52-R52 -> 27 | T52: 0 | U52: 0 | V52: 0 | W52: 0 | X52: 0 | Y52: 0 | Z52: 0 | AA52: 0 | AB52: =Y52+AA52+Z52 -> 0 | AC52: 0 | AD52: 0 | AE52: 0 | AF52: 0 | AG52: 0 | AH52: 0 | AI52: 0 | AJ52: 0 | AK52: 0 | AL52: =(BN52*P52/AX52)+AB52/O52*(BN52/AX52) -> 0 | AM52: =Q52+AB52+AL52+AK52+AJ52+T52+AE52 -> 343.17 | AN52: 46133 | AO52: 36/IAD/27IN00006 | AP52: 832139000046796207 | AQ52: TRADEWIND BUSINESS SOLUTIONS LLP | AR52: 07AARFT3586D1ZR | AS52: NOIDA,Uttar Pradesh,201301 | AT52: New Delhi | AU52: Delhi | AV52: 162408149669 | AW52: 27 | AX52: 20 | AY52: =AW52*AX52 -> 540 | AZ52: =AW52=O52 -> TRUE | BA52: 0 | BB52: =AW52-BA52 -> 27 | BC52: 0 | BD52: Regular | BE52: 0 | BF52: 0 | BG52: 0 | BH52: 0 | BI52: 0 | BJ52: 0 | BK52: 0 | BL52: 0 | BM52: 0 | BN52: =AY52*$BM$3 -> 0 | BO52: =AY52+BL52+BM52+BN52+BC52+BG52 -> 540 | BP52: =BO52-AM52 -> 196.83 | BQ52: =IF(BP52>=0,"Positive Margin","Negative Margin") -> Positive Margin | BR52: No Provision | BS52: =AY52-Y52-Q52-AA52-T52+BC52 -> 196.83 | BT52: =IF(BS52<0, "Negative Margin at Inception", "Positive Margin at Inception") -> Positive Margin at Inception | BU52: =IFERROR(BP52/BO52,"0") -> 0.3645 | BV52: =IF(BU52<1%,"Less Than 1%",IF(BU52>2%,"More than 2%",IF(BU52>=1%,"1% - 2%"))) -> More than 2% | BW52: =BM52+BN52 -> 0 | BX52: =AL52+AK52 -> 0 | BY52: =BW52-BX52 -> 0 | BZ52: =BM52 -> 0 | CA52: =AK52 -> 0 | CB52: =BZ52-CA52 -> 0 | CC52: Marketplace (IT Assets Disposition) | CD52: 0 | CE52: =AM52-AL52-AA52 -> 343.17 | CF52: =BO52-BN52 -> 540 | CG52: =INT((D52- IF(MONTH(D52) >= 4, DATE(YEAR(D52), 4, 1), DATE(YEAR(D52)-1, 4, 1))) / 7) + 1 -> 2 | CH52: 0 | CI52: 0 | CJ52: =_xlfn.XLOOKUP(AP52,POC!B:B,POC!D:D) -> #N/A | CK52: =AY52-Q52 -> 196.83 | CL52: =CK52-Y52+Z52 -> 196.83 | CM52: =BO52-AM52 -> 196.83 | CN52: =AY52*118% -> 637.2 | CO52: =-Q52*118% -> -404.9406 | CP52: =-BZ52*118% -> 0 | CQ52: =-CA52*118% -> 0 | CR52: =SUM(CN52:CQ52) -> 232.2594 | CS52: Telangana - HO | CT52: Telangana - HO | CU52: =MID(G52,3,10) -> AACCN4479R | CV52: =MID(AR52,3,10) -> AARFT3586D | CW52: =H52&F52 -> Inv/2026-27/01NAVATAR CONSULTING PRIVATE LIMITED
... B54: ="Q" & IF(ROUNDUP(MONTH(D54)/3,0)-1=0,4,ROUNDUP(MONTH(D54)/3,0)-1) -> Q1 | C54: =TEXT(AN54,"mmm-yy") -> Apr-26 | D54: 46141 | E54: SH04262909 | F54: RETECK ENVIROTECH PRIVATE LIMITED | G54: 27AAHCR2638B1ZK | H54: 2026-2027-133 | I54: 46141 | J54: 26-27/PUR/001631 | K54: 46141 | L54: MH | M54: MH04LE7099 | N54: ITAD Table | O54: 33 | P54: 4450.85 | Q54: =O54*P54 -> 146878.05 | R54: 0 | S54: =O54-R54 -> 33 | T54: 0 | U54: 0 | V54: 0 | W54: 0 | X54: 0 | Y54: 0 | Z54: 0 | AA54: 0 | AB54: =Y54+AA54+Z54 -> 0 | AC54: 0 | AD54: 0 | AE54: 0 | AF54: 0 | AG54: 0 | AH54: 0 | AI54: 0 | AJ54: 0 | AK54: 0 | AL54: =(BN54*P54/AX54)+AB54/O54*(BN54/AX54) -> 0 | AM54: =Q54+AB54+AL54+AK54+AJ54+T54+AE54 -> 146878.05 | AN54: 46141 | AO54: 36/IAD/27IN00010 | AP54: 832139000031064980 | AQ54: GREENLIFE EWASTE RECYCLING PRIVATE LIMITED | AR54: 27AAJCG6268L1ZY | AS54: Vadgaon,Maharashtra,410220 | AT54: Mumbai Suburban, | AU54: Maharashtra | AV54: 122415318586 | AW54: 33 | AX54: 5303.03 | AY54: =AW54*AX54 -> 174999.99 | AZ54: =AW54=O54 -> TRUE | BA54: 0 | BB54: =AW54-BA54 -> 33 | BC54: 0 | BD54: Regular | BE54: 0 | BF54: 0 | BG54: 0 | BH54: 0 | BI54: 0 | BJ54: 0 | BK54: 0 | BL54: 0 | BM54: 0 | BN54: =AY54*$BM$3 -> 0 | BO54: =AY54+BL54+BM54+BN54+BC54+BG54 -> 174999.99 | BP54: =BO54-AM54 -> 28121.94 | BQ54: =IF(BP54>=0,"Positive Margin","Negative Margin") -> Positive Margin | BR54: No Provision | BS54: =AY54-Y54-Q54-AA54-T54+BC54 -> 28121.94 | BT54: =IF(BS54<0, "Negative Margin at Inception", "Positive Margin at Inception") -> Positive Margin at Inception | BU54: =IFERROR(BP54/BO54,"0") -> 0.16069681 | BV54: =IF(BU54<1%,"Less Than 1%",IF(BU54>2%,"More than 2%",IF(BU54>=1%,"1% - 2%"))) -> More than 2% | BW54: =BM54+BN54 -> 0 | BX54: =AL54+AK54 -> 0 | BY54: =BW54-BX54 -> 0 | BZ54: =BM54 -> 0 | CA54: =AK54 -> 0 | CB54: =BZ54-CA54 -> 0 | CC54: Marketplace (IT Assets Disposition) | CD54: 0 | CE54: =AM54-AL54-AA54 -> 146878.05 | CF54: =BO54-BN54 -> 174999.99 | CG54: =INT((D54- IF(MONTH(D54) >= 4, DATE(YEAR(D54), 4, 1), DATE(YEAR(D54)-1, 4, 1))) / 7) + 1 -> 5 | CH54: 0 | CI54: 0 | CJ54: =_xlfn.XLOOKUP(AP54,POC!B:B,POC!D:D) -> #N/A | CK54: =AY54-Q54 -> 28121.94 | CL54: =CK54-Y54+Z54 -> 28121.94 | CM54: =BO54-AM54 -> 28121.94 | CN54: =AY54*118% -> 206499.99 | CO54: =-Q54*118% -> -173316.1 | CP54: =-BZ54*118% -> 0 | CQ54: =-CA54*118% -> 0 | CR54: =SUM(CN54:CQ54) -> 33183.889 | CS54: Telangana - HO | CT54: Telangana - HO | CU54: =MID(G54,3,10) -> AAHCR2638B | CV54: =MID(AR54,3,10) -> AAJCG6268L | CW54: =H54&F54 -> 2026-2027-133RETECK ENVIROTECH PRIVATE LIMITED
B55: ="Q" & IF(ROUNDUP(MONTH(D55)/3,0)-1=0,4,ROUNDUP(MONTH(D55)/3,0)-1) -> Q1 | C55: =TEXT(AN55,"mmm-yy") -> Apr-26 | D55: 46115 | E55: 36/ITAD/27/OFF/0001 | F55: STELLAR INFORMATION TECHNOLOGY PRIVATE LIMITED | G55: 06AALCS7470E1Z5 | H55: IN/GGN/2526/0782 | I55: 46107 | J55: 25-26/PUR/026969 | K55: 46115 | L55: HR | N55: Stellar Bit Raser (Electronic Licence Key) | O55: 900 | P55: 120 | Q55: =O55*P55 -> 108000 | R55: 0 | S55: =O55-R55 -> 900 | T55: 0 | U55: 0 | V55: 0 | W55: 0 | X55: 0 | Y55: 0 | Z55: 0 | AA55: 0 | AB55: =Y55+AA55+Z55 -> 0 | AC55: 0 | AD55: 0 | AE55: 0 | AF55: 0 | AG55: 0 | AH55: 0 | AI55: 0 | AJ55: 0 | AK55: 0 | AL55: 0 | AM55: =Q55+AB55+AL55+AK55+AJ55+T55+AE55 -> 108000 | AN55: 46115 | AO55: 0 | AP55: 0 | AQ55: 0 | AR55: 0 | AS55: 0 | AT55: 0 | AU55: 0 | AV55: 0 | AW55: 0 | AX55: 0 | AY55: =AW55*AX55 -> 0 | AZ55: =AW55=O55 -> FALSE | BA55: 0 | BB55: =AW55-BA55 -> 0 | BC55: 0 | BD55: Regular | BE55: 0 | BF55: 0 | BG55: 0 | BH55: 0 | BI55: 0 | BJ55: 0 | BK55: 0 | BL55: 0 | BM55: 0 | BN55: =AY55*$BM$3 -> 0 | BO55: =AY55+BL55+BM55+BN55+BC55+BG55 -> 0 | BP55: =BO55-AM55 -> -108000 | BQ55: =IF(BP55>=0,"Positive Margin","Negative Margin") -> Negative Margin | BR55: No Provision | BS55: =AY55-Y55-Q55-AA55-T55+BC55 -> -108000 | BT55: =IF(BS55<0, "Negative Margin at Inception", "Positive Margin at Inception") -> Negative Margin at Inception | BU55: =IFERROR(BP55/BO55,"0") -> 0 | BV55: =IF(BU55<1%,"Less Than 1%",IF(BU55>2%,"More than 2%",IF(BU55>=1%,"1% - 2%"))) -> More than 2% | BW55: =BM55+BN55 -> 0 | BX55: =AL55+AK55 -> 0 | BY55: =BW55-BX55 -> 0 | BZ55: =BM55 -> 0 | CA55: =AK55 -> 0 | CB55: =BZ55-CA55 -> 0 | CC55: Marketplace (IT Assets Disposition) | CD55: 0 | CE55: =AM55-AL55-AA55 -> 108000 | CF55: =BO55-BN55 -> 0 | CG55: =INT((D55- IF(MONTH(D55) >= 4, DATE(YEAR(D55), 4, 1), DATE(YEAR(D55)-1, 4, 1))) / 7) + 1 -> 1 | CH55: 0 | CI55: 0 | CJ55: =_xlfn.XLOOKUP(AP55,POC!B:B,POC!D:D) -> 0 | CK55: =AY55-Q55 -> -108000 | CL55: =CK55-Y55+Z55 -> -108000 | CM55: =BO55-AM55 -> -108000 | CN55: =AY55*118% -> 0 | CO55: =-Q55*118% -> -127440 | CP55: =-BZ55*118% -> 0 | CQ55: =-CA55*118% -> 0 | CR55: =SUM(CN55:CQ55) -> -127440 | CS55: Telangana - HO | CT55: Telangana - HO | CU55: =MID(G55,3,10) -> AALCS7470E | CV55: =MID(AR55,3,10) | CW55: =H55&F55 -> IN/GGN/2526/0782STELLAR INFORMATION TECHNOLOGY PRIVATE LIMITED
B56: ="Q" & IF(ROUNDUP(MONTH(D56)/3,0)-1=0,4,ROUNDUP(MONTH(D56)/3,0)-1) -> Q1 | C56: =TEXT(AN56,"mmm-yy") -> Apr-26 | D56: 46140 | E56: 36/IAD/27/OFF/0001 | F56: 0 | G56: 0 | H56: 0 | I56: 0 | J56: 0 | K56: 0 | L56: 0 | M56: 0 | N56: 0 | O56: 0 | P56: 0 | Q56: =O56*P56 -> 0 | R56: 0 | S56: =O56-R56 -> 0 | T56: 0 | U56: 0 | V56: 0 | W56: 0 | X56: 0 | Y56: 0 | Z56: 0 | AA56: 0 | AB56: =Y56+AA56+Z56 -> 0 | AC56: 0 | AD56: 0 | AE56: 0 | AF56: 0 | AG56: 0 | AH56: 0 | AI56: 0 | AJ56: 0 | AK56: 0 | AL56: 0 | AM56: =Q56+AB56+AL56+AK56+AJ56+T56+AE56 -> 0 | AN56: 46140 | AO56: 36/IAD/27IN00009 | AP56: 832139000077522037 | AQ56: Genpact India Private Limited | AR56: 09AABCE4461B2ZZ | AT56: Noida | AU56: Uttar Pradesh | AV56: 0 | AW56: 999 | AX56: 211.86 | AY56: =AW56*AX56 -> 211648.14 | AZ56: =AW56=O56 -> FALSE | BA56: 0 | BB56: =AW56-BA56 -> 999 | BC56: 0 | BD56: Regular | BE56: 0 | BF56: 0 | BG56: 0 | BH56: 0 | BI56: 0 | BJ56: 0 | BK56: 0 | BL56: 0 | BM56: 0 | BN56: =AY56*$BM$3 -> 0 | BO56: =AY56+BL56+BM56+BN56+BC56+BG56 -> 211648.14 | BP56: =BO56-AM56 -> 211648.14 | BQ56: =IF(BP56>=0,"Positive Margin","Negative Margin") -> Positive Margin | BR56: No Provision | BS56: =AY56-Y56-Q56-AA56-T56+BC56 -> 211648.14 | BT56: =IF(BS56<0, "Negative Margin at Inception", "Positive Margin at Inception") -> Positive Margin at Inception | BU56: =IFERROR(BP56/BO56,"0") -> 1 | BV56: =IF(BU56<1%,"Less Than 1%",IF(BU56>2%,"More than 2%",IF(BU56>=1%,"1% - 2%"))) -> More than 2% | BW56: =BM56+BN56 -> 0 | BX56: =AL56+AK56 -> 0 | BY56: =BW56-BX56 -> 0 | BZ56: =BM56 -> 0 | CA56: =AK56 -> 0 | CB56: =BZ56-CA56 -> 0 | CC56: Marketplace (IT Assets Disposition) | CD56: 0 | CE56: =AM56-AL56-AA56 -> 0 | CF56: =BO56-BN56 -> 211648.14 | CG56: =INT((D56- IF(MONTH(D56) >= 4, DATE(YEAR(D56), 4, 1), DATE(YEAR(D56)-1, 4, 1))) / 7) + 1 -> 4 | CH56: 0 | CI56: 0 | CJ56: =_xlfn.XLOOKUP(AP56,POC!B:B,POC!D:D) -> #N/A | CK56: =AY56-Q56 -> 211648.14 | CL56: =CK56-Y56+Z56 -> 211648.14 | CM56: =BO56-AM56 -> 211648.14 | CN56: =AY56*118% -> 249744.81 | CO56: =-Q56*118% -> 0 | CP56: =-BZ56*118% -> 0 | CQ56: =-CA56*118% -> 0 | CR56: =SUM(CN56:CQ56) -> 249744.81 | CS56: Telangana - HO | CT56: Telangana - HO | CU56: =MID(G56,3,10) | CV56: =MID(AR56,3,10) -> AABCE4461B | CW56: =H56&F56 -> 00
B57: ="Q" & IF(ROUNDUP(MONTH(D57)/3,0)-1=0,4,ROUNDUP(MONTH(D57)/3,0)-1) -> Q1 | C57: =TEXT(AN57,"mmm-yy") -> Apr-26 | D57: 46140 | E57: 36/IAD/27/OFF/0001 | F57: 0 | G57: 0 | H57: 0 | I57: 0 | J57: 0 | K57: 0 | L57: 0 | M57: 0 | N57: 0 | O57: 0 | P57: 0 | Q57: =O57*P57 -> 0 | R57: 0 | S57: =O57-R57 -> 0 | T57: 0 | U57: 0 | V57: 0 | W57: 0 | X57: 0 | Y57: 0 | Z57: 0 | AA57: 0 | AB57: =Y57+AA57+Z57 -> 0 | AC57: 0 | AD57: 0 | AE57: 0 | AF57: 0 | AG57: 0 | AH57: 0 | AI57: 0 | AJ57: 0 | AK57: 0 | AL57: 0 | AM57: =Q57+AB57+AL57+AK57+AJ57+T57+AE57 -> 0 | AN57: 46140 | AO57: 36/IAD/27IN00009 | AP57: 832139000077522037 | AQ57: Genpact India Private Limited | AR57: 09AABCE4461B2ZZ | AT57: Noida | AU57: Uttar Pradesh | AV57: 0 | AW57: 398 | AX57: 158.099 | AY57: =AW57*AX57 -> 62923.402 | AZ57: =AW57=O57 -> FALSE | BA57: 0 | BB57: =AW57-BA57 -> 398 | BC57: 0 | BD57: Regular | BE57: 0 | BF57: 0 | BG57: 0 | BH57: 0 | BI57: 0 | BJ57: 0 | BK57: 0 | BL57: 0 | BM57: 0 | BN57: =AY57*$BM$3 -> 0 | BO57: =AY57+BL57+BM57+BN57+BC57+BG57 -> 62923.402 | BP57: =BO57-AM57 -> 62923.402 | BQ57: =IF(BP57>=0,"Positive Margin","Negative Margin") -> Positive Margin | BR57: No Provision | BS57: =AY57-Y57-Q57-AA57-T57+BC57 -> 62923.402 | BT57: =IF(BS57<0, "Negative Margin at Inception", "Positive Margin at Inception") -> Positive Margin at Inception | BU57: =IFERROR(BP57/BO57,"0") -> 1 | BV57: =IF(BU57<1%,"Less Than 1%",IF(BU57>2%,"More than 2%",IF(BU57>=1%,"1% - 2%"))) -> More than 2% | BW57: =BM57+BN57 -> 0 | BX57: =AL57+AK57 -> 0 | BY57: =BW57-BX57 -> 0 | BZ57: =BM57 -> 0 | CA57: =AK57 -> 0 | CB57: =BZ57-CA57 -> 0 | CC57: Marketplace (IT Assets Disposition) | CD57: 0 | CE57: =AM57-AL57-AA57 -> 0 | CF57: =BO57-BN57 -> 62923.402 | CG57: =INT((D57- IF(MONTH(D57) >= 4, DATE(YEAR(D57), 4, 1), DATE(YEAR(D57)-1, 4, 1))) / 7) + 1 -> 4 | CH57: 0 | CI57: 0 | CJ57: =_xlfn.XLOOKUP(AP57,POC!B:B,POC!D:D) -> #N/A | CK57: =AY57-Q57 -> 62923.402 | CL57: =CK57-Y57+Z57 -> 62923.402 | CM57: =BO57-AM57 -> 62923.402 | CN57: =AY57*118% -> 74249.614 | CO57: =-Q57*118% -> 0 | CP57: =-BZ57*118% -> 0 | CQ57: =-CA57*118% -> 0 | CR57: =SUM(CN57:CQ57) -> 74249.614 | CS57: Telangana - HO | CT57: Telangana - HO | CU57: =MID(G57,3,10) | CV57: =MID(AR57,3,10) -> AABCE4461B | CW57: =H57&F57 -> 00
B58: ="Q" & IF(ROUNDUP(MONTH(D58)/3,0)-1=0,4,ROUNDUP(MONTH(D58)/3,0)-1) -> Q1 | C58: =TEXT(AN58,"mmm-yy") -> Apr-26 | D58: 46140 | E58: 36/IAD/27/OFF/0001 | F58: 0 | G58: 0 | H58: 0 | I58: 0 | J58: 0 | K58: 0 | L58: 0 | M58: 0 | N58: 0 | O58: 0 | P58: 0 | Q58: =O58*P58 -> 0 | R58: 0 | S58: =O58-R58 -> 0 | T58: 0 | U58: 0 | V58: 0 | W58: 0 | X58: 0 | Y58: 0 | Z58: 0 | AA58: 0 | AB58: =Y58+AA58+Z58 -> 0 | AC58: 0 | AD58: 0 | AE58: 0 | AF58: 0 | AG58: 0 | AH58: 0 | AI58: 0 | AJ58: 0 | AK58: 0 | AL58: 0 | AM58: =Q58+AB58+AL58+AK58+AJ58+T58+AE58 -> 0 | AN58: 46140 | AO58: 36/IAD/27IN00009 | AP58: 832139000077522037 | AQ58: Genpact India Private Limited | AR58: 09AABCE4461B2ZZ | AT58: Noida | AU58: Uttar Pradesh | AV58: 0 | AW58: 4 | AX58: 4237.29 | AY58: =AW58*AX58 -> 16949.16 | AZ58: =AW58=O58 -> FALSE | BA58: 0 | BB58: =AW58-BA58 -> 4 | BC58: 0 | BD58: Regular | BE58: 0 | BF58: 0 | BG58: 0 | BH58: 0 | BI58: 0 | BJ58: 0 | BK58: 0 | BL58: 0 | BM58: 0 | BN58: =AY58*$BM$3 -> 0 | BO58: =AY58+BL58+BM58+BN58+BC58+BG58 -> 16949.16 | BP58: =BO58-AM58 -> 16949.16 | BQ58: =IF(BP58>=0,"Positive Margin","Negative Margin") -> Positive Margin | BR58: No Provision | BS58: =AY58-Y58-Q58-AA58-T58+BC58 -> 16949.16 | BT58: =IF(BS58<0, "Negative Margin at Inception", "Positive Margin at Inception") -> Positive Margin at Inception | BU58: =IFERROR(BP58/BO58,"0") -> 1 | BV58: =IF(BU58<1%,"Less Than 1%",IF(BU58>2%,"More than 2%",IF(BU58>=1%,"1% - 2%"))) -> More than 2% | BW58: =BM58+BN58 -> 0 | BX58: =AL58+AK58 -> 0 | BY58: =BW58-BX58 -> 0 | BZ58: =BM58 -> 0 | CA58: =AK58 -> 0 | CB58: =BZ58-CA58 -> 0 | CC58: Marketplace (IT Assets Disposition) | CD58: 0 | CE58: =AM58-AL58-AA58 -> 0 | CF58: =BO58-BN58 -> 16949.16 | CG58: =INT((D58- IF(MONTH(D58) >= 4, DATE(YEAR(D58), 4, 1), DATE(YEAR(D58)-1, 4, 1))) / 7) + 1 -> 4 | CH58: 0 | CI58: 0 | CJ58: =_xlfn.XLOOKUP(AP58,POC!B:B,POC!D:D) -> #N/A | CK58: =AY58-Q58 -> 16949.16 | CL58: =CK58-Y58+Z58 -> 16949.16 | CM58: =BO58-AM58 -> 16949.16 | CN58: =AY58*118% -> 20000.009 | CO58: =-Q58*118% -> 0 | CP58: =-BZ58*118% -> 0 | CQ58: =-CA58*118% -> 0 | CR58: =SUM(CN58:CQ58) -> 20000.009 | CS58: Telangana - HO | CT58: Telangana - HO | CU58: =MID(G58,3,10) | CV58: =MID(AR58,3,10) -> AABCE4461B | CW58: =H58&F58 -> 00
B59: ="Q" & IF(ROUNDUP(MONTH(D59)/3,0)-1=0,4,ROUNDUP(MONTH(D59)/3,0)-1) -> Q1 | C59: =TEXT(AN59,"mmm-yy") -> May-26 | D59: 46147 | E59: SH05260401 | F59: XTGLOBAL INFOTECH LIMITED | G59: 37AAACF5186B4ZQ | H59: XTGL000320202526 | I59: 46147 | J59: 26-27/PUR/001848 | K59: 46148 | L59: AD | M59: AP39UY1853 | N59: Mix E-Waste (ITAD) | O59: 1210 | P59: 35.124 | Q59: =O59*P59 -> 42500.04 | R59: 0 | S59: =O59-R59 -> 1210 | T59: 0 | U59: 0 | V59: 0 | W59: 0 | X59: 0 | Y59: 0 | Z59: 0 | AA59: 0 | AB59: =Y59+AA59+Z59 -> 0 | AC59: 0 | AD59: 0 | AE59: 0 | AF59: 0 | AG59: 0 | AH59: 0 | AI59: 0 | AJ59: 0 | AK59: 0 | AL59: 0 | AM59: =Q59+AB59+AL59+AK59+AJ59+T59+AE59 -> 42500.04 | AN59: 46148 | AO59: 36/IAD/27IN00011 | AP59: 832139000055796981 | AQ59: RETECK ENVIROTECH PRIVATE LIMITED | AR59: 27AAHCR2638B1ZK | AS59: Visakhapatnam,Andhra Pradesh,530045 | AT59: Vadgaon | AU59: Maharashtra | AV59: 152420478663 | AW59: 1210 | AX59: 58.365 | AY59: =AW59*AX59 -> 70621.65 | AZ59: =AW59=O59 -> TRUE | BA59: 0 | BB59: =AW59-BA59 -> 1210 | BC59: 0 | BD59: Regular | BE59: 0 | BF59: 0 | BG59: 0 | BH59: 0 | BI59: 0 | BJ59: 0 | BK59: 0 | BL59: 0 | BM59: 0 | BN59: =AY59*$BM$3 -> 0 | BO59: =AY59+BL59+BM59+BN59+BC59+BG59 -> 70621.65 | BP59: =BO59-AM59 -> 28121.61 | BQ59: =IF(BP59>=0,"Positive Margin","Negative Margin") -> Positive Margin | BR59: No Provision | BS59: =AY59-Y59-Q59-AA59-T59+BC59 -> 28121.61 | BT59: =IF(BS59<0, "Negative Margin at Inception", "Positive Margin at Inception") -> Positive Margin at Inception | BU59: =IFERROR(BP59/BO59,"0") -> 0.39820098 | BV59: =IF(BU59<1%,"Less Than 1%",IF(BU59>2%,"More than 2%",IF(BU59>=1%,"1% - 2%"))) -> More than 2% | BW59: =BM59+BN59 -> 0 | BX59: =AL59+AK59 -> 0 | BY59: =BW59-BX59 -> 0 | BZ59: =BM59 -> 0 | CA59: =AK59 -> 0 | CB59: =BZ59-CA59 -> 0 | CC59: Marketplace (IT Assets Disposition) | CD59: 0 | CE59: =AM59-AL59-AA59 -> 42500.04 | CF59: =BO59-BN59 -> 70621.65 | CG59: =INT((D59- IF(MONTH(D59) >= 4, DATE(YEAR(D59), 4, 1), DATE(YEAR(D59)-1, 4, 1))) / 7) + 1 -> 5 | CH59: 0 | CI59: 0 | CJ59: =_xlfn.XLOOKUP(AP59,POC!B:B,POC!D:D) -> #N/A | CK59: =AY59-Q59 -> 28121.61 | CL59: =CK59-Y59+Z59 -> 28121.61 | CM59: =BO59-AM59 -> 28121.61 | CN59: =AY59*118% -> 83333.547 | CO59: =-Q59*118% -> -50150.047 | CP59: =-BZ59*118% -> 0 | CQ59: =-CA59*118% -> 0 | CR59: =SUM(CN59:CQ59) -> 33183.5 | CS59: Telangana - HO | CT59: Telangana - HO | CU59: =MID(G59,3,10) -> AAACF5186B | CV59: =MID(AR59,3,10) -> AAHCR2638B | CW59: =H59&F59 -> XTGL000320202526XTGLOBAL INFOTECH LIMITED
B60: ="Q" & IF(ROUNDUP(MONTH(D60)/3,0)-1=0,4,ROUNDUP(MONTH(D60)/3,0)-1) -> Q1 | C60: =TEXT(AN60,"mmm-yy") -> May-26 | D60: 46150 | E60: SH05260805 | F60: SUGUNA FOODS PRIVATE LIMITED | G60: 36AADCS0655F2ZI | H60: TGTGIN27/2285 | I60: 46150 | J60: 26-27/PUR/001920 | K60: 46150 | L60: TS | M60: TS12UE4210 | N60: E-Waste ( ITAD 2) | O60: 1 | P60: 84.93 | Q60: =O60*P60 -> 84.93 | R60: 0 | S60: =O60-R60 -> 1 | T60: 0 | U60: 0 | V60: 0 | W60: 0 | X60: 0 | Y60: 0 | Z60: 0 | AA60: 0 | AB60: =Y60+AA60+Z60 -> 0 | AC60: 0 | AD60: 0 | AE60: 0 | AF60: 0 | AG60: 0 | AH60: 0 | AI60: 0 | AJ60: 0 | AK60: 0 | AL60: 0 | AM60: =Q60+AB60+AL60+AK60+AJ60+T60+AE60 -> 84.93 | AN60: 46150 | AO60: 36/IAD/27IN00013 | AP60: 832139000078144049 | AQ60: LIGHTNING COMPUTECH | AR60: 29GOWPS6814G2ZX | AS60: Medak Telangana 502334 | AT60: Bengaluru | AU60: Karnataka | AV60: 152423009910 | AW60: 1 | AX60: 123 | AY60: =AW60*AX60 -> 123 | AZ60: =AW60=O60 -> TRUE | BA60: 0 | BB60: =AW60-BA60 -> 1 | BC60: 0 | BD60: Regular | BE60: 0 | BF60: 0 | BG60: 0 | BH60: 0 | BI60: 0 | BJ60: 0 | BK60: 0 | BL60: 0 | BM60: 0 | BN60: =AY60*$BM$3 -> 0 | BO60: =AY60+BL60+BM60+BN60+BC60+BG60 -> 123 | BP60: =BO60-AM60 -> 38.07 | BQ60: =IF(BP60>=0,"Positive Margin","Negative Margin") -> Positive Margin | BR60: No Provision | BS60: =AY60-Y60-Q60-AA60-T60+BC60 -> 38.07 | BT60: =IF(BS60<0, "Negative Margin at Inception", "Positive Margin at Inception") -> Positive Margin at Inception | BU60: =IFERROR(BP60/BO60,"0") -> 0.3095122 | BV60: =IF(BU60<1%,"Less Than 1%",IF(BU60>2%,"More than 2%",IF(BU60>=1%,"1% - 2%"))) -> More than 2% | BW60: =BM60+BN60 -> 0 | BX60: =AL60+AK60 -> 0 | BY60: =BW60-BX60 -> 0 | BZ60: =BM60 -> 0 | CA60: =AK60 -> 0 | CB60: =BZ60-CA60 -> 0 | CC60: Marketplace (IT Assets Disposition) | CD60: 0 | CE60: =AM60-AL60-AA60 -> 84.93 | CF60: =BO60-BN60 -> 123 | CG60: =INT((D60- IF(MONTH(D60) >= 4, DATE(YEAR(D60), 4, 1), DATE(YEAR(D60)-1, 4, 1))) / 7) + 1 -> 6 | CH60: 0 | CI60: 0 | CJ60: =_xlfn.XLOOKUP(AP60,POC!B:B,POC!D:D) -> #N/A | CK60: =AY60-Q60 -> 38.07 | CL60: =CK60-Y60+Z60 -> 38.07 | CM60: =BO60-AM60 -> 38.07 | CN60: =AY60*118% -> 145.14 | CO60: =-Q60*118% -> -100.2174 | CP60: =-BZ60*118% -> 0 | CQ60: =-CA60*118% -> 0 | CR60: =SUM(CN60:CQ60) -> 44.9226 | CS60: Telangana - HO | CT60: Telangana - HO | CU60: =MID(G60,3,10) -> AADCS0655F | CV60: =MID(AR60,3,10) -> GOWPS6814G
B61: ="Q" & IF(ROUNDUP(MONTH(D61)/3,0)-1=0,4,ROUNDUP(MONTH(D61)/3,0)-1) -> Q1 | C61: =TEXT(AN61,"mmm-yy") -> May-26 | D61: 46150 | E61: SH05260804 | F61: RETECK ENVIROTECH PRIVATE LIMITED | G61: 27AAHCR2638B1ZK | H61: 2026-2027-150 | I61: 46150 | J61: 26-27/PUR/001919 | K61: 46150 | L61: MH | M61: TS12UE4210 | N61: E W Desktop | O61: 32 | P61: 2272.5 | Q61: =O61*P61 -> 72720 | R61: 0 | S61: =O61-R61 -> 32 | T61: 0 | U61: 0 | V61: 0 | W61: 0 | X61: 0 | Y61: 0 | Z61: 0 | AA61: 0 | AB61: =Y61+AA61+Z61 -> 0 | AC61: 0 | AD61: 0 | AE61: 0 | AF61: 0 | AG61: 0 | AH61: 0 | AI61: 0 | AJ61: 0 | AK61: 0 | AL61: 0 | AM61: =Q61+AB61+AL61+AK61+AJ61+T61+AE61 -> 72720 | AN61: 46150 | AO61: 36/IAD/27IN00012 | AP61: 832139000078144049 | AQ61: LIGHTNING COMPUTECH | AR61: 29GOWPS6814G2ZX | AS61: Rangareddy Telangana 500032 | AT61: Bengaluru | AU61: Karnataka | AV61: 192422996727 | AW61: 32 | AX61: 2677 | AY61: =AW61*AX61 -> 85664 | AZ61: =AW61=O61 -> TRUE | BA61: 0 | BB61: =AW61-BA61 -> 32 | BC61: 0 | BD61: Regular | BE61: 0 | BF61: 0 | BG61: 0 | BH61: 0 | BI61: 0 | BJ61: 0 | BK61: 0 | BL61: 0 | BM61: 0 | BN61: =AY61*$BM$3 -> 0 | BO61: =AY61+BL61+BM61+BN61+BC61+BG61 -> 85664 | BP61: =BO61-AM61 -> 12944 | BQ61: =IF(BP61>=0,"Positive Margin","Negative Margin") -> Positive Margin | BR61: No Provision | BS61: =AY61-Y61-Q61-AA61-T61+BC61 -> 12944 | BT61: =IF(BS61<0, "Negative Margin at Inception", "Positive Margin at Inception") -> Positive Margin at Inception | BU61: =IFERROR(BP61/BO61,"0") -> 0.15110198 | BV61: =IF(BU61<1%,"Less Than 1%",IF(BU61>2%,"More than 2%",IF(BU61>=1%,"1% - 2%"))) -> More than 2% | BW61: =BM61+BN61 -> 0 | BX61: =AL61+AK61 -> 0 | BY61: =BW61-BX61 -> 0 | BZ61: =BM61 -> 0 | CA61: =AK61 -> 0 | CB61: =BZ61-CA61 -> 0 | CC61: Marketplace (IT Assets Disposition) | CD61: 0 | CE61: =AM61-AL61-AA61 -> 72720 | CF61: =BO61-BN61 -> 85664 | CG61: =INT((D61- IF(MONTH(D61) >= 4, DATE(YEAR(D61), 4, 1), DATE(YEAR(D61)-1, 4, 1))) / 7) + 1 -> 6 | CH61: 0 | CI61: 0 | CJ61: =_xlfn.XLOOKUP(AP61,POC!B:B,POC!D:D) -> #N/A | CK61: =AY61-Q61 -> 12944 | CL61: =CK61-Y61+Z61 -> 12944 | CM61: =BO61-AM61 -> 12944 | CN61: =AY61*118% -> 101083.52 | CO61: =-Q61*118% -> -85809.6 | CP61: =-BZ61*118% -> 0 | CQ61: =-CA61*118% -> 0 | CR61: =SUM(CN61:CQ61) -> 15273.92 | CS61: Telangana - HO | CT61: Telangana - HO | CU61: =MID(G61,3,10) -> AAHCR2638B | CV61: =MID(AR61,3,10) -> GOWPS6814G
B62: ="Q" & IF(ROUNDUP(MONTH(D62)/3,0)-1=0,4,ROUNDUP(MONTH(D62)/3,0)-1) -> Q1 | C62: =TEXT(AN62,"mmm-yy") -> May-26 | D62: 46150 | E62: SH05260804 | F62: RETECK ENVIROTECH PRIVATE LIMITED | G62: 27AAHCR2638B1ZK | H62: 2026-2027-150 | I62: 46150 | J62: 26-27/PUR/001919 | K62: 46150 | L62: MH | M62: TS12UE4210 | N62: E W Monitor | O62: 32 | P62: 2272.5 | Q62: =O62*P62 -> 72720 | R62: 0 | S62: =O62-R62 -> 32 | T62: 0 | U62: 0 | V62: 0 | W62: 0 | X62: 0 | Y62: 0 | Z62: 0 | AA62: 0 | AB62: =Y62+AA62+Z62 -> 0 | AC62: 0 | AD62: 0 | AE62: 0 | AF62: 0 | AG62: 0 | AH62: 0 | AI62: 0 | AJ62: 0 | AK62: 0 | AL62: 0 | AM62: =Q62+AB62+AL62+AK62+AJ62+T62+AE62 -> 72720 | AN62: 46150 | AO62: 36/IAD/27IN00012 | AP62: 832139000078144049 | AQ62: LIGHTNING COMPUTECH | AR62: 29GOWPS6814G2ZX | AS62: Rangareddy Telangana 500032 | AT62: Bengaluru | AU62: Karnataka | AV62: 192422996727 | AW62: 32 | AX62: 2275 | AY62: =AW62*AX62 -> 72800 | AZ62: =AW62=O62 -> TRUE | BA62: 0 | BB62: =AW62-BA62 -> 32 | BC62: 0 | BD62: Regular | BE62: 0 | BF62: 0 | BG62: 0 | BH62: 0 | BI62: 0 | BJ62: 0 | BK62: 0 | BL62: 0 | BM62: 0 | BN62: =AY62*$BM$3 -> 0 | BO62: =AY62+BL62+BM62+BN62+BC62+BG62 -> 72800 | BP62: =BO62-AM62 -> 80 | BQ62: =IF(BP62>=0,"Positive Margin","Negative Margin") -> Positive Margin | BR62: No Provision | BS62: =AY62-Y62-Q62-AA62-T62+BC62 -> 80 | BT62: =IF(BS62<0, "Negative Margin at Inception", "Positive Margin at Inception") -> Positive Margin at Inception | BU62: =IFERROR(BP62/BO62,"0") -> 0.0010989011 | BV62: =IF(BU62<1%,"Less Than 1%",IF(BU62>2%,"More than 2%",IF(BU62>=1%,"1% - 2%"))) -> Less Than 1% | BW62: =BM62+BN62 -> 0 | BX62: =AL62+AK62 -> 0 | BY62: =BW62-BX62 -> 0 | BZ62: =BM62 -> 0 | CA62: =AK62 -> 0 | CB62: =BZ62-CA62 -> 0 | CC62: Marketplace (IT Assets Disposition) | CD62: 0 | CE62: =AM62-AL62-AA62 -> 72720 | CF62: =BO62-BN62 -> 72800 | CG62: =INT((D62- IF(MONTH(D62) >= 4, DATE(YEAR(D62), 4, 1), DATE(YEAR(D62)-1, 4, 1))) / 7) + 1 -> 6 | CH62: 0 | CI62: 0 | CJ62: =_xlfn.XLOOKUP(AP62,POC!B:B,POC!D:D) -> #N/A | CK62: =AY62-Q62 -> 80 | CL62: =CK62-Y62+Z62 -> 80 | CM62: =BO62-AM62 -> 80 | CN62: =AY62*118% -> 85904 | CO62: =-Q62*118% -> -85809.6 | CP62: =-BZ62*118% -> 0 | CQ62: =-CA62*118% -> 0 | CR62: =SUM(CN62:CQ62) -> 94.4 | CS62: Telangana - HO | CT62: Telangana - HO | CU62: =MID(G62,3,10) -> AAHCR2638B | CV62: =MID(AR62,3,10) -> GOWPS6814G
B63: ="Q" & IF(ROUNDUP(MONTH(D63)/3,0)-1=0,4,ROUNDUP(MONTH(D63)/3,0)-1) -> Q1 | C63: =TEXT(AN63,"mmm-yy") -> May-26 | D63: 46150 | E63: SH05260808 | F63: SUGUNA FOODS PRIVATE LIMITED | G63: 36AADCS0655F2ZI | H63: TGTGIN27/2287 | I63: 46150 | J63: 26-27/PUR/001928 | K63: 46151 | L63: TS | M63: KA03AJ3519 | N63: ITAD LED Monitor | O63: 1 | P63: 85.27 | Q63: =O63*P63 -> 85.27 | R63: 0 | S63: =O63-R63 -> 1 | T63: 0 | U63: 0 | V63: 0 | W63: 0 | X63: 0 | Y63: 0 | Z63: 0 | AA63: 0 | AB63: =Y63+AA63+Z63 -> 0 | AC63: 0 | AD63: 0 | AE63: 0 | AF63: 0 | AG63: 0 | AH63: 0 | AI63: 0 | AJ63: 0 | AK63: 0 | AL63: 0 | AM63: =Q63+AB63+AL63+AK63+AJ63+T63+AE63 -> 85.27 | AN63: 46151 | AO63: 36/IAD/27IN00015 | AP63: 832139000078144049 | AQ63: LIGHTNING COMPUTECH | AR63: 29GOWPS6814G2ZX | AS63: Medak,Telangana,502334 | AT63: Bengaluru | AU63: Karnataka | AV63: 132423878934 | AW63: 1 | AX63: 125 | AY63: =AW63*AX63 -> 125 | AZ63: =AW63=O63 -> TRUE | BA63: 0 | BB63: =AW63-BA63 -> 1 | BC63: 0 | BD63: Regular | BE63: 0 | BF63: 0 | BG63: 0 | BH63: 0 | BI63: 0 | BJ63: 0 | BK63: 0 | BL63: 0 | BM63: 0 | BN63: =AY63*$BM$3 -> 0 | BO63: =AY63+BL63+BM63+BN63+BC63+BG63 -> 125 | BP63: =BO63-AM63 -> 39.73 | BQ63: =IF(BP63>=0,"Positive Margin","Negative Margin") -> Positive Margin | BR63: No Provision | BS63: =AY63-Y63-Q63-AA63-T63+BC63 -> 39.73 | BT63: =IF(BS63<0, "Negative Margin at Inception", "Positive Margin at Inception") -> Positive Margin at Inception | BU63: =IFERROR(BP63/BO63,"0") -> 0.31784 | BV63: =IF(BU63<1%,"Less Than 1%",IF(BU63>2%,"More than 2%",IF(BU63>=1%,"1% - 2%"))) -> More than 2% | BW63: =BM63+BN63 -> 0 | BX63: =AL63+AK63 -> 0 | BY63: =BW63-BX63 -> 0 | BZ63: =BM63 -> 0 | CA63: =AK63 -> 0 | CB63: =BZ63-CA63 -> 0 | CC63: Marketplace (IT Assets Disposition) | CD63: 0 | CE63: =AM63-AL63-AA63 -> 85.27 | CF63: =BO63-BN63 -> 125 | CG63: =INT((D63- IF(MONTH(D63) >= 4, DATE(YEAR(D63), 4, 1), DATE(YEAR(D63)-1, 4, 1))) / 7) + 1 -> 6 | CH63: 0 | CI63: 0 | CJ63: =_xlfn.XLOOKUP(AP63,POC!B:B,POC!D:D) -> #N/A | CK63: =AY63-Q63 -> 39.73 | CL63: =CK63-Y63+Z63 -> 39.73 | CM63: =BO63-AM63 -> 39.73 | CN63: =AY63*118% -> 147.5 | CO63: =-Q63*118% -> -100.6186 | CP63: =-BZ63*118% -> 0 | CQ63: =-CA63*118% -> 0 | CR63: =SUM(CN63:CQ63) -> 46.8814 | CS63: Telangana - HO | CT63: Telangana - HO | CU63: =MID(G63,3,10) -> AADCS0655F | CV63: =MID(AR63,3,10) -> GOWPS6814G
B64: ="Q" & IF(ROUNDUP(MONTH(D64)/3,0)-1=0,4,ROUNDUP(MONTH(D64)/3,0)-1) -> Q1 | C64: =TEXT(AN64,"mmm-yy") -> May-26 | D64: 46150 | E64: SH05260808 | F64: SUGUNA FOODS PRIVATE LIMITED | G64: 36AADCS0655F2ZI | H64: TGTGIN27/2287 | I64: 46150 | J64: 26-27/PUR/001928 | K64: 46151 | L64: TS | M64: KA03AJ3519 | N64: E-Waste ( ITAD 2) | O64: 1 | P64: 61.02 | Q64: =O64*P64 -> 61.02 | R64: 0 | S64: =O64-R64 -> 1 | T64: 0 | U64: 0 | V64: 0 | W64: 0 | X64: 0 | Y64: 0 | Z64: 0 | AA64: 0 | AB64: =Y64+AA64+Z64 -> 0 | AC64: 0 | AD64: 0 | AE64: 0 | AF64: 0 | AG64: 0 | AH64: 0 | AI64: 0 | AJ64: 0 | AK64: 0 | AL64: 0 | AM64: =Q64+AB64+AL64+AK64+AJ64+T64+AE64 -> 61.02 | AN64: 46151 | AO64: 36/IAD/27IN00015 | AP64: 832139000078144049 | AQ64: LIGHTNING COMPUTECH | AR64: 29GOWPS6814G2ZX | AS64: Medak,Telangana,502334 | AT64: Bengaluru | AU64: Karnataka | AV64: 132423878934 | AW64: 1 | AX64: 90 | AY64: =AW64*AX64 -> 90 | AZ64: =AW64=O64 -> TRUE | BA64: 0 | BB64: =AW64-BA64 -> 1 | BC64: 0 | BD64: Regular | BE64: 0 | BF64: 0 | BG64: 0 | BH64: 0 | BI64: 0 | BJ64: 0 | BK64: 0 | BL64: 0 | BM64: 0 | BN64: =AY64*$BM$3 -> 0 | BO64: =AY64+BL64+BM64+BN64+BC64+BG64 -> 90 | BP64: =BO64-AM64 -> 28.98 | BQ64: =IF(BP64>=0,"Positive Margin","Negative Margin") -> Positive Margin | BR64: No Provision | BS64: =AY64-Y64-Q64-AA64-T64+BC64 -> 28.98 | BT64: =IF(BS64<0, "Negative Margin at Inception", "Positive Margin at Inception") -> Positive Margin at Inception | BU64: =IFERROR(BP64/BO64,"0") -> 0.322 | BV64: =IF(BU64<1%,"Less Than 1%",IF(BU64>2%,"More than 2%",IF(BU64>=1%,"1% - 2%"))) -> More than 2% | BW64: =BM64+BN64 -> 0 | BX64: =AL64+AK64 -> 0 | BY64: =BW64-BX64 -> 0 | BZ64: =BM64 -> 0 | CA64: =AK64 -> 0 | CB64: =BZ64-CA64 -> 0 | CC64: Marketplace (IT Assets Disposition) | CD64: 0 | CE64: =AM64-AL64-AA64 -> 61.02 | CF64: =BO64-BN64 -> 90 | CG64: =INT((D64- IF(MONTH(D64) >= 4, DATE(YEAR(D64), 4, 1), DATE(YEAR(D64)-1, 4, 1))) / 7) + 1 -> 6 | CH64: 0 | CI64: 0 | CJ64: =_xlfn.XLOOKUP(AP64,POC!B:B,POC!D:D) -> #N/A | CK64: =AY64-Q64 -> 28.98 | CL64: =CK64-Y64+Z64 -> 28.98 | CM64: =BO64-AM64 -> 28.98 | CN64: =AY64*118% -> 106.2 | CO64: =-Q64*118% -> -72.0036 | CP64: =-BZ64*118% -> 0 | CQ64: =-CA64*118% -> 0 | CR64: =SUM(CN64:CQ64) -> 34.1964 | CS64: Telangana - HO | CT64: Telangana - HO | CU64: =MID(G64,3,10) -> AADCS0655F | CV64: =MID(AR64,3,10) -> GOWPS6814G
B65: ="Q" & IF(ROUNDUP(MONTH(D65)/3,0)-1=0,4,ROUNDUP(MONTH(D65)/3,0)-1) -> Q1 | C65: =TEXT(AN65,"mmm-yy") -> May-26 | D65: 46150 | E65: SH05260808 | F65: SUGUNA FOODS PRIVATE LIMITED | G65: 36AADCS0655F2ZI | H65: TGTGIN27/2287 | I65: 46150 | J65: 26-27/PUR/001928 | K65: 46151 | L65: TS | M65: KA03AJ3519 | N65: ITAD LED Monitor | O65: 1 | P65: 78.23 | Q65: =O65*P65 -> 78.23 | R65: 0 | S65: =O65-R65 -> 1 | T65: 0 | U65: 0 | V65: 0 | W65: 0 | X65: 0 | Y65: 0 | Z65: 0 | AA65: 0 | AB65: =Y65+AA65+Z65 -> 0 | AC65: 0 | AD65: 0 | AE65: 0 | AF65: 0 | AG65: 0 | AH65: 0 | AI65: 0 | AJ65: 0 | AK65: 0 | AL65: 0 | AM65: =Q65+AB65+AL65+AK65+AJ65+T65+AE65 -> 78.23 | AN65: 46151 | AO65: 36/IAD/27IN00015 | AP65: 832139000078144049 | AQ65: LIGHTNING COMPUTECH | AR65: 29GOWPS6814G2ZX | AS65: Medak,Telangana,502334 | AT65: Bengaluru | AU65: Karnataka | AV65: 132423878934 | AW65: 1 | AX65: 115 | AY65: =AW65*AX65 -> 115 | AZ65: =AW65=O65 -> TRUE | BA65: 0 | BB65: =AW65-BA65 -> 1 | BC65: 0 | BD65: Regular | BE65: 0 | BF65: 0 | BG65: 0 | BH65: 0 | BI65: 0 | BJ65: 0 | BK65: 0 | BL65: 0 | BM65: 0 | BN65: =AY65*$BM$3 -> 0 | BO65: =AY65+BL65+BM65+BN65+BC65+BG65 -> 115 | BP65: =BO65-AM65 -> 36.77 | BQ65: =IF(BP65>=0,"Positive Margin","Negative Margin") -> Positive Margin | BR65: No Provision | BS65: =AY65-Y65-Q65-AA65-T65+BC65 -> 36.77 | BT65: =IF(BS65<0, "Negative Margin at Inception", "Positive Margin at Inception") -> Positive Margin at Inception | BU65: =IFERROR(BP65/BO65,"0") -> 0.31973913 | BV65: =IF(BU65<1%,"Less Than 1%",IF(BU65>2%,"More than 2%",IF(BU65>=1%,"1% - 2%"))) -> More than 2% | BW65: =BM65+BN65 -> 0 | BX65: =AL65+AK65 -> 0 | BY65: =BW65-BX65 -> 0 | BZ65: =BM65 -> 0 | CA65: =AK65 -> 0 | CB65: =BZ65-CA65 -> 0 | CC65: Marketplace (IT Assets Disposition) | CD65: 0 | CE65: =AM65-AL65-AA65 -> 78.23 | CF65: =BO65-BN65 -> 115 | CG65: =INT((D65- IF(MONTH(D65) >= 4, DATE(YEAR(D65), 4, 1), DATE(YEAR(D65)-1, 4, 1))) / 7) + 1 -> 6 | CH65: 0 | CI65: 0 | CJ65: =_xlfn.XLOOKUP(AP65,POC!B:B,POC!D:D) -> #N/A | CK65: =AY65-Q65 -> 36.77 | CL65: =CK65-Y65+Z65 -> 36.77 | CM65: =BO65-AM65 -> 36.77 | CN65: =AY65*118% -> 135.7 | CO65: =-Q65*118% -> -92.3114 | CP65: =-BZ65*118% -> 0 | CQ65: =-CA65*118% -> 0 | CR65: =SUM(CN65:CQ65) -> 43.3886 | CS65: Telangana - HO | CT65: Telangana - HO | CU65: =MID(G65,3,10) -> AADCS0655F | CV65: =MID(AR65,3,10) -> GOWPS6814G
B66: ="Q" & IF(ROUNDUP(MONTH(D66)/3,0)-1=0,4,ROUNDUP(MONTH(D66)/3,0)-1) -> Q1 | C66: =TEXT(AN66,"mmm-yy") -> May-26 | D66: 46150 | E66: SH05260808 | F66: SUGUNA FOODS PRIVATE LIMITED | G66: 36AADCS0655F2ZI | H66: TGTGIN27/2287 | I66: 46150 | J66: 26-27/PUR/001928 | K66: 46151 | L66: TS | M66: KA03AJ3519 | N66: E-Waste ( ITAD 2) | O66: 1 | P66: 683.03 | Q66: =O66*P66 -> 683.03 | R66: 0 | S66: =O66-R66 -> 1 | T66: 0 | U66: 0 | V66: 0 | W66: 0 | X66: 0 | Y66: 0 | Z66: 0 | AA66: 0 | AB66: =Y66+AA66+Z66 -> 0 | AC66: 0 | AD66: 0 | AE66: 0 | AF66: 0 | AG66: 0 | AH66: 0 | AI66: 0 | AJ66: 0 | AK66: 0 | AL66: 0 | AM66: =Q66+AB66+AL66+AK66+AJ66+T66+AE66 -> 683.03 | AN66: 46151 | AO66: 36/IAD/27IN00015 | AP66: 832139000078144049 | AQ66: LIGHTNING COMPUTECH | AR66: 29GOWPS6814G2ZX | AS66: Medak,Telangana,502334 | AT66: Bengaluru | AU66: Karnataka | AV66: 132423878934 | AW66: 1 | AX66: 1000 | AY66: =AW66*AX66 -> 1000 | AZ66: =AW66=O66 -> TRUE | BA66: 0 | BB66: =AW66-BA66 -> 1 | BC66: 0 | BD66: Regular | BE66: 0 | BF66: 0 | BG66: 0 | BH66: 0 | BI66: 0 | BJ66: 0 | BK66: 0 | BL66: 0 | BM66: 0 | BN66: =AY66*$BM$3 -> 0 | BO66: =AY66+BL66+BM66+BN66+BC66+BG66 -> 1000 | BP66: =BO66-AM66 -> 316.97 | BQ66: =IF(BP66>=0,"Positive Margin","Negative Margin") -> Positive Margin | BR66: No Provision | BS66: =AY66-Y66-Q66-AA66-T66+BC66 -> 316.97 | BT66: =IF(BS66<0, "Negative Margin at Inception", "Positive Margin at Inception") -> Positive Margin at Inception | BU66: =IFERROR(BP66/BO66,"0") -> 0.31697 | BV66: =IF(BU66<1%,"Less Than 1%",IF(BU66>2%,"More than 2%",IF(BU66>=1%,"1% - 2%"))) -> More than 2% | BW66: =BM66+BN66 -> 0 | BX66: =AL66+AK66 -> 0 | BY66: =BW66-BX66 -> 0 | BZ66: =BM66 -> 0 | CA66: =AK66 -> 0 | CB66: =BZ66-CA66 -> 0 | CC66: Marketplace (IT Assets Disposition) | CD66: 0 | CE66: =AM66-AL66-AA66 -> 683.03 | CF66: =BO66-BN66 -> 1000 | CG66: =INT((D66- IF(MONTH(D66) >= 4, DATE(YEAR(D66), 4, 1), DATE(YEAR(D66)-1, 4, 1))) / 7) + 1 -> 6 | CH66: 0 | CI66: 0 | CJ66: =_xlfn.XLOOKUP(AP66,POC!B:B,POC!D:D) -> #N/A | CK66: =AY66-Q66 -> 316.97 | CL66: =CK66-Y66+Z66 -> 316.97 | CM66: =BO66-AM66 -> 316.97 | CN66: =AY66*118% -> 1180 | CO66: =-Q66*118% -> -805.9754 | CP66: =-BZ66*118% -> 0 | CQ66: =-CA66*118% -> 0 | CR66: =SUM(CN66:CQ66) -> 374.0246 | CS66: Telangana - HO | CT66: Telangana - HO | CU66: =MID(G66,3,10) -> AADCS0655F | CV66: =MID(AR66,3,10) -> GOWPS6814G
B67: ="Q" & IF(ROUNDUP(MONTH(D67)/3,0)-1=0,4,ROUNDUP(MONTH(D67)/3,0)-1) -> Q1 | C67: =TEXT(AN67,"mmm-yy") -> May-26 | D67: 46150 | E67: SH05260808 | F67: SUGUNA FOODS PRIVATE LIMITED | G67: 36AADCS0655F2ZI | H67: TGTGIN27/2287 | I67: 46150 | J67: 26-27/PUR/001928 | K67: 46151 | L67: TS | M67: KA03AJ3519 | N67: Server | O67: 1 | P67: 456.68 | Q67: =O67*P67 -> 456.68 | R67: 0 | S67: =O67-R67 -> 1 | T67: 0 | U67: 0 | V67: 0 | W67: 0 | X67: 0 | Y67: 0 | Z67: 0 | AA67: 0 | AB67: =Y67+AA67+Z67 -> 0 | AC67: 0 | AD67: 0 | AE67: 0 | AF67: 0 | AG67: 0 | AH67: 0 | AI67: 0 | AJ67: 0 | AK67: 0 | AL67: 0 | AM67: =Q67+AB67+AL67+AK67+AJ67+T67+AE67 -> 456.68 | AN67: 46151 | AO67: 36/IAD/27IN00015 | AP67: 832139000078144049 | AQ67: LIGHTNING COMPUTECH | AR67: 29GOWPS6814G2ZX | AS67: Medak,Telangana,502334 | AT67: Bengaluru | AU67: Karnataka | AV67: 132423878934 | AW67: 1 | AX67: 675 | AY67: =AW67*AX67 -> 675 | AZ67: =AW67=O67 -> TRUE | BA67: 0 | BB67: =AW67-BA67 -> 1 | BC67: 0 | BD67: Regular | BE67: 0 | BF67: 0 | BG67: 0 | BH67: 0 | BI67: 0 | BJ67: 0 | BK67: 0 | BL67: 0 | BM67: 0 | BN67: =AY67*$BM$3 -> 0 | BO67: =AY67+BL67+BM67+BN67+BC67+BG67 -> 675 | BP67: =BO67-AM67 -> 218.32 | BQ67: =IF(BP67>=0,"Positive Margin","Negative Margin") -> Positive Margin | BR67: No Provision | BS67: =AY67-Y67-Q67-AA67-T67+BC67 -> 218.32 | BT67: =IF(BS67<0, "Negative Margin at Inception", "Positive Margin at Inception") -> Positive Margin at Inception | BU67: =IFERROR(BP67/BO67,"0") -> 0.32343704 | BV67: =IF(BU67<1%,"Less Than 1%",IF(BU67>2%,"More than 2%",IF(BU67>=1%,"1% - 2%"))) -> More than 2% | BW67: =BM67+BN67 -> 0 | BX67: =AL67+AK67 -> 0 | BY67: =BW67-BX67 -> 0 | BZ67: =BM67 -> 0 | CA67: =AK67 -> 0 | CB67: =BZ67-CA67 -> 0 | CC67: Marketplace (IT Assets Disposition) | CD67: 0 | CE67: =AM67-AL67-AA67 -> 456.68 | CF67: =BO67-BN67 -> 675 | CG67: =INT((D67- IF(MONTH(D67) >= 4, DATE(YEAR(D67), 4, 1), DATE(YEAR(D67)-1, 4, 1))) / 7) + 1 -> 6 | CH67: 0 | CI67: 0 | CJ67: =_xlfn.XLOOKUP(AP67,POC!B:B,POC!D:D) -> #N/A | CK67: =AY67-Q67 -> 218.32 | CL67: =CK67-Y67+Z67 -> 218.32 | CM67: =BO67-AM67 -> 218.32 | CN67: =AY67*118% -> 796.5 | CO67: =-Q67*118% -> -538.8824 | CP67: =-BZ67*118% -> 0 | CQ67: =-CA67*118% -> 0 | CR67: =SUM(CN67:CQ67) -> 257.6176 | CS67: Telangana - HO | CT67: Telangana - HO | CU67: =MID(G67,3,10) -> AADCS0655F | CV67: =MID(AR67,3,10) -> GOWPS6814G
B68: ="Q" & IF(ROUNDUP(MONTH(D68)/3,0)-1=0,4,ROUNDUP(MONTH(D68)/3,0)-1) -> Q1 | C68: =TEXT(AN68,"mmm-yy") -> May-26 | D68: 46150 | E68: SH05260808 | F68: SUGUNA FOODS PRIVATE LIMITED | G68: 36AADCS0655F2ZI | H68: TGTGIN27/2287 | I68: 46150 | J68: 26-27/PUR/001928 | K68: 46151 | L68: TS | M68: KA03AJ3519 | N68: ITAD LED Monitor | O68: 1 | P68: 85.27 | Q68: =O68*P68 -> 85.27 | R68: 0 | S68: =O68-R68 -> 1 | T68: 0 | U68: 0 | V68: 0 | W68: 0 | X68: 0 | Y68: 0 | Z68: 0 | AA68: 0 | AB68: =Y68+AA68+Z68 -> 0 | AC68: 0 | AD68: 0 | AE68: 0 | AF68: 0 | AG68: 0 | AH68: 0 | AI68: 0 | AJ68: 0 | AK68: 0 | AL68: 0 | AM68: =Q68+AB68+AL68+AK68+AJ68+T68+AE68 -> 85.27 | AN68: 46151 | AO68: 36/IAD/27IN00015 | AP68: 832139000078144049 | AQ68: LIGHTNING COMPUTECH | AR68: 29GOWPS6814G2ZX | AS68: Medak,Telangana,502334 | AT68: Bengaluru | AU68: Karnataka | AV68: 132423878934 | AW68: 1 | AX68: 125 | AY68: =AW68*AX68 -> 125 | AZ68: =AW68=O68 -> TRUE | BA68: 0 | BB68: =AW68-BA68 -> 1 | BC68: 0 | BD68: Regular | BE68: 0 | BF68: 0 | BG68: 0 | BH68: 0 | BI68: 0 | BJ68: 0 | BK68: 0 | BL68: 0 | BM68: 0 | BN68: =AY68*$BM$3 -> 0 | BO68: =AY68+BL68+BM68+BN68+BC68+BG68 -> 125 | BP68: =BO68-AM68 -> 39.73 | BQ68: =IF(BP68>=0,"Positive Margin","Negative Margin") -> Positive Margin | BR68: No Provision | BS68: =AY68-Y68-Q68-AA68-T68+BC68 -> 39.73 | BT68: =IF(BS68<0, "Negative Margin at Inception", "Positive Margin at Inception") -> Positive Margin at Inception | BU68: =IFERROR(BP68/BO68,"0") -> 0.31784 | BV68: =IF(BU68<1%,"Less Than 1%",IF(BU68>2%,"More than 2%",IF(BU68>=1%,"1% - 2%"))) -> More than 2% | BW68: =BM68+BN68 -> 0 | BX68: =AL68+AK68 -> 0 | BY68: =BW68-BX68 -> 0 | BZ68: =BM68 -> 0 | CA68: =AK68 -> 0 | CB68: =BZ68-CA68 -> 0 | CC68: Marketplace (IT Assets Disposition) | CD68: 0 | CE68: =AM68-AL68-AA68 -> 85.27 | CF68: =BO68-BN68 -> 125 | CG68: =INT((D68- IF(MONTH(D68) >= 4, DATE(YEAR(D68), 4, 1), DATE(YEAR(D68)-1, 4, 1))) / 7) + 1 -> 6 | CH68: 0 | CI68: 0 | CJ68: =_xlfn.XLOOKUP(AP68,POC!B:B,POC!D:D) -> #N/A | CK68: =AY68-Q68 -> 39.73 | CL68: =CK68-Y68+Z68 -> 39.73 | CM68: =BO68-AM68 -> 39.73 | CN68: =AY68*118% -> 147.5 | CO68: =-Q68*118% -> -100.6186 | CP68: =-BZ68*118% -> 0 | CQ68: =-CA68*118% -> 0 | CR68: =SUM(CN68:CQ68) -> 46.8814 | CS68: Telangana - HO | CT68: Telangana - HO | CU68: =MID(G68,3,10) -> AADCS0655F | CV68: =MID(AR68,3,10) -> GOWPS6814G
B69: ="Q" & IF(ROUNDUP(MONTH(D69)/3,0)-1=0,4,ROUNDUP(MONTH(D69)/3,0)-1) -> Q1 | C69: =TEXT(AN69,"mmm-yy") -> May-26 | D69: 46150 | E69: SH05260808 | F69: SUGUNA FOODS PRIVATE LIMITED | G69: 36AADCS0655F2ZI | H69: TGTGIN27/2287 | I69: 46150 | J69: 26-27/PUR/001928 | K69: 46151 | L69: TS | M69: KA03AJ3519 | N69: E-Waste ( ITAD 2) | O69: 1 | P69: 58.9 | Q69: =O69*P69 -> 58.9 | R69: 0 | S69: =O69-R69 -> 1 | T69: 0 | U69: 0 | V69: 0 | W69: 0 | X69: 0 | Y69: 0 | Z69: 0 | AA69: 0 | AB69: =Y69+AA69+Z69 -> 0 | AC69: 0 | AD69: 0 | AE69: 0 | AF69: 0 | AG69: 0 | AH69: 0 | AI69: 0 | AJ69: 0 | AK69: 0 | AL69: 0 | AM69: =Q69+AB69+AL69+AK69+AJ69+T69+AE69 -> 58.9 | AN69: 46151 | AO69: 36/IAD/27IN00015 | AP69: 832139000078144049 | AQ69: LIGHTNING COMPUTECH | AR69: 29GOWPS6814G2ZX | AS69: Medak,Telangana,502334 | AT69: Bengaluru | AU69: Karnataka | AV69: 132423878934 | AW69: 1 | AX69: 86 | AY69: =AW69*AX69 -> 86 | AZ69: =AW69=O69 -> TRUE | BA69: 0 | BB69: =AW69-BA69 -> 1 | BC69: 0 | BD69: Regular | BE69: 0 | BF69: 0 | BG69: 0 | BH69: 0 | BI69: 0 | BJ69: 0 | BK69: 0 | BL69: 0 | BM69: 0 | BN69: =AY69*$BM$3 -> 0 | BO69: =AY69+BL69+BM69+BN69+BC69+BG69 -> 86 | BP69: =BO69-AM69 -> 27.1 | BQ69: =IF(BP69>=0,"Positive Margin","Negative Margin") -> Positive Margin | BR69: No Provision | BS69: =AY69-Y69-Q69-AA69-T69+BC69 -> 27.1 | BT69: =IF(BS69<0, "Negative Margin at Inception", "Positive Margin at Inception") -> Positive Margin at Inception | BU69: =IFERROR(BP69/BO69,"0") -> 0.31511628 | BV69: =IF(BU69<1%,"Less Than 1%",IF(BU69>2%,"More than 2%",IF(BU69>=1%,"1% - 2%"))) -> More than 2% | BW69: =BM69+BN69 -> 0 | BX69: =AL69+AK69 -> 0 | BY69: =BW69-BX69 -> 0 | BZ69: =BM69 -> 0 | CA69: =AK69 -> 0 | CB69: =BZ69-CA69 -> 0 | CC69: Marketplace (IT Assets Disposition) | CD69: 0 | CE69: =AM69-AL69-AA69 -> 58.9 | CF69: =BO69-BN69 -> 86 | CG69: =INT((D69- IF(MONTH(D69) >= 4, DATE(YEAR(D69), 4, 1), DATE(YEAR(D69)-1, 4, 1))) / 7) + 1 -> 6 | CH69: 0 | CI69: 0 | CJ69: =_xlfn.XLOOKUP(AP69,POC!B:B,POC!D:D) -> #N/A | CK69: =AY69-Q69 -> 27.1 | CL69: =CK69-Y69+Z69 -> 27.1 | CM69: =BO69-AM69 -> 27.1 | CN69: =AY69*118% -> 101.48 | CO69: =-Q69*118% -> -69.502 | CP69: =-BZ69*118% -> 0 | CQ69: =-CA69*118% -> 0 | CR69: =SUM(CN69:CQ69) -> 31.978 | CS69: Telangana - HO | CT69: Telangana - HO | CU69: =MID(G69,3,10) -> AADCS0655F | CV69: =MID(AR69,3,10) -> GOWPS6814G
B70: ="Q" & IF(ROUNDUP(MONTH(D70)/3,0)-1=0,4,ROUNDUP(MONTH(D70)/3,0)-1) -> Q1 | C70: =TEXT(AN70,"mmm-yy") -> May-26 | D70: 46150 | E70: SH05260808 | F70: SUGUNA FOODS PRIVATE LIMITED | G70: 36AADCS0655F2ZI | H70: TGTGIN27/2287 | I70: 46150 | J70: 26-27/PUR/001928 | K70: 46151 | L70: TS | M70: KA03AJ3519 | N70: Server | O70: 1 | P70: 224.17 | Q70: =O70*P70 -> 224.17 | R70: 0 | S70: =O70-R70 -> 1 | T70: 0 | U70: 0 | V70: 0 | W70: 0 | X70: 0 | Y70: 0 | Z70: 0 | AA70: 0 | AB70: =Y70+AA70+Z70 -> 0 | AC70: 0 | AD70: 0 | AE70: 0 | AF70: 0 | AG70: 0 | AH70: 0 | AI70: 0 | AJ70: 0 | AK70: 0 | AL70: 0 | AM70: =Q70+AB70+AL70+AK70+AJ70+T70+AE70 -> 224.17 | AN70: 46151 | AO70: 36/IAD/27IN00015 | AP70: 832139000078144049 | AQ70: LIGHTNING COMPUTECH | AR70: 29GOWPS6814G2ZX | AS70: Medak,Telangana,502334 | AT70: Bengaluru | AU70: Karnataka | AV70: 132423878934 | AW70: 1 | AX70: 330 | AY70: =AW70*AX70 -> 330 | AZ70: =AW70=O70 -> TRUE | BA70: 0 | BB70: =AW70-BA70 -> 1 | BC70: 0 | BD70: Regular | BE70: 0 | BF70: 0 | BG70: 0 | BH70: 0 | BI70: 0 | BJ70: 0 | BK70: 0 | BL70: 0 | BM70: 0 | BN70: =AY70*$BM$3 -> 0 | BO70: =AY70+BL70+BM70+BN70+BC70+BG70 -> 330 | BP70: =BO70-AM70 -> 105.83 | BQ70: =IF(BP70>=0,"Positive Margin","Negative Margin") -> Positive Margin | BR70: No Provision | BS70: =AY70-Y70-Q70-AA70-T70+BC70 -> 105.83 | BT70: =IF(BS70<0, "Negative Margin at Inception", "Positive Margin at Inception") -> Positive Margin at Inception | BU70: =IFERROR(BP70/BO70,"0") -> 0.32069697 | BV70: =IF(BU70<1%,"Less Than 1%",IF(BU70>2%,"More than 2%",IF(BU70>=1%,"1% - 2%"))) -> More than 2% | BW70: =BM70+BN70 -> 0 | BX70: =AL70+AK70 -> 0 | BY70: =BW70-BX70 -> 0 | BZ70: =BM70 -> 0 | CA70: =AK70 -> 0 | CB70: =BZ70-CA70 -> 0 | CC70: Marketplace (IT Assets Disposition) | CD70: 0 | CE70: =AM70-AL70-AA70 -> 224.17 | CF70: =BO70-BN70 -> 330 | CG70: =INT((D70- IF(MONTH(D70) >= 4, DATE(YEAR(D70), 4, 1), DATE(YEAR(D70)-1, 4, 1))) / 7) + 1 -> 6 | CH70: 0 | CI70: 0 | CJ70: =_xlfn.XLOOKUP(AP70,POC!B:B,POC!D:D) -> #N/A | CK70: =AY70-Q70 -> 105.83 | CL70: =CK70-Y70+Z70 -> 105.83 | CM70: =BO70-AM70 -> 105.83 | CN70: =AY70*118% -> 389.4 | CO70: =-Q70*118% -> -264.5206 | CP70: =-BZ70*118% -> 0 | CQ70: =-CA70*118% -> 0 | CR70: =SUM(CN70:CQ70) -> 124.8794 | CS70: Telangana - HO | CT70: Telangana - HO | CU70: =MID(G70,3,10) -> AADCS0655F | CV70: =MID(AR70,3,10) -> GOWPS6814G
B71: ="Q" & IF(ROUNDUP(MONTH(D71)/3,0)-1=0,4,ROUNDUP(MONTH(D71)/3,0)-1) -> Q1 | C71: =TEXT(AN71,"mmm-yy") -> May-26 | D71: 46150 | E71: SH05260808 | F71: SUGUNA FOODS PRIVATE LIMITED | G71: 36AADCS0655F2ZI | H71: TGTGIN27/2287 | I71: 46150 | J71: 26-27/PUR/001928 | K71: 46151 | L71: TS | M71: KA03AJ3519 | N71: E-Waste ( ITAD 2) | O71: 1 | P71: 55.88 | Q71: =O71*P71 -> 55.88 | R71: 0 | S71: =O71-R71 -> 1 | T71: 0 | U71: 0 | V71: 0 | W71: 0 | X71: 0 | Y71: 0 | Z71: 0 | AA71: 0 | AB71: =Y71+AA71+Z71 -> 0 | AC71: 0 | AD71: 0 | AE71: 0 | AF71: 0 | AG71: 0 | AH71: 0 | AI71: 0 | AJ71: 0 | AK71: 0 | AL71: 0 | AM71: =Q71+AB71+AL71+AK71+AJ71+T71+AE71 -> 55.88 | AN71: 46151 | AO71: 36/IAD/27IN00015 | AP71: 832139000078144049 | AQ71: LIGHTNING COMPUTECH | AR71: 29GOWPS6814G2ZX | AS71: Medak,Telangana,502334 | AT71: Bengaluru | AU71: Karnataka | AV71: 132423878934 | AW71: 1 | AX71: 82 | AY71: =AW71*AX71 -> 82 | AZ71: =AW71=O71 -> TRUE | BA71: 0 | BB71: =AW71-BA71 -> 1 | BC71: 0 | BD71: Regular | BE71: 0 | BF71: 0 | BG71: 0 | BH71: 0 | BI71: 0 | BJ71: 0 | BK71: 0 | BL71: 0 | BM71: 0 | BN71: =AY71*$BM$3 -> 0 | BO71: =AY71+BL71+BM71+BN71+BC71+BG71 -> 82 | BP71: =BO71-AM71 -> 26.12 | BQ71: =IF(BP71>=0,"Positive Margin","Negative Margin") -> Positive Margin | BR71: No Provision | BS71: =AY71-Y71-Q71-AA71-T71+BC71 -> 26.12 | BT71: =IF(BS71<0, "Negative Margin at Inception", "Positive Margin at Inception") -> Positive Margin at Inception | BU71: =IFERROR(BP71/BO71,"0") -> 0.31853659 | BV71: =IF(BU71<1%,"Less Than 1%",IF(BU71>2%,"More than 2%",IF(BU71>=1%,"1% - 2%"))) -> More than 2% | BW71: =BM71+BN71 -> 0 | BX71: =AL71+AK71 -> 0 | BY71: =BW71-BX71 -> 0 | BZ71: =BM71 -> 0 | CA71: =AK71 -> 0 | CB71: =BZ71-CA71 -> 0 | CC71: Marketplace (IT Assets Disposition) | CD71: 0 | CE71: =AM71-AL71-AA71 -> 55.88 | CF71: =BO71-BN71 -> 82 | CG71: =INT((D71- IF(MONTH(D71) >= 4, DATE(YEAR(D71), 4, 1), DATE(YEAR(D71)-1, 4, 1))) / 7) + 1 -> 6 | CH71: 0 | CI71: 0 | CJ71: =_xlfn.XLOOKUP(AP71,POC!B:B,POC!D:D) -> #N/A | CK71: =AY71-Q71 -> 26.12 | CL71: =CK71-Y71+Z71 -> 26.12 | CM71: =BO71-AM71 -> 26.12 | CN71: =AY71*118% -> 96.76 | CO71: =-Q71*118% -> -65.9384 | CP71: =-BZ71*118% -> 0 | CQ71: =-CA71*118% -> 0 | CR71: =SUM(CN71:CQ71) -> 30.8216 | CS71: Telangana - HO | CT71: Telangana - HO | CU71: =MID(G71,3,10) -> AADCS0655F | CV71: =MID(AR71,3,10) -> GOWPS6814G
... B110: ="Q" & IF(ROUNDUP(MONTH(D110)/3,0)-1=0,4,ROUNDUP(MONTH(D110)/3,0)-1) -> Q1 | C110: =TEXT(AN110,"mmm-yy") -> May-26 | D110: 46155 | E110: SH05261305 | F110: VWR LAB PRODUCTS PRIVATE LIMITED | G110: 33AACCV3080E1ZO | H110: VWR/02/2627 | I110: 46155 | J110: 26-27/PUR/002159 | K110: 46156 | L110: TN | M110: TN50AA0528 | N110: Monitor Scrap | O110: 1 | P110: 72034 | Q110: =O110*P110 -> 72034 | R110: 0 | S110: =O110-R110 -> 1 | T110: 0 | U110: 0 | V110: 0 | W110: 0 | X110: 0 | Y110: 0 | Z110: 0 | AA110: 0 | AB110: =Y110+AA110+Z110 -> 0 | AC110: 0 | AD110: 0 | AE110: 0 | AF110: 0 | AG110: 0 | AH110: 0 | AI110: 0 | AJ110: 0 | AK110: 0 | AL110: 0 | AM110: =Q110+AB110+AL110+AK110+AJ110+T110+AE110 -> 72034 | AN110: 46156 | AO110: 36/IAD/27IN00016 | AP110: 832139000078144049 | AQ110: LIGHTNING COMPUTECH | AR110: 29GOWPS6814G2ZX | AS110: Coimbatore Tamil Nadu 641021 | AT110: Bengaluru | AU110: Karnataka | AV110: 122427991586 | AW110: 1 | AX110: 83084.081 | AY110: =AW110*AX110 -> 83084.081 | AZ110: =AW110=O110 -> TRUE | BA110: 0 | BB110: =AW110-BA110 -> 1 | BC110: 0 | BD110: Regular | BE110: 0 | BF110: 0 | BG110: 0 | BH110: 0 | BI110: 0 | BJ110: 0 | BK110: 0 | BL110: 0 | BM110: 0 | BN110: =AY110*$BM$3 -> 0 | BO110: =AY110+BL110+BM110+BN110+BC110+BG110 -> 83084.081 | BP110: =BO110-AM110 -> 11050.081 | BQ110: =IF(BP110>=0,"Positive Margin","Negative Margin") -> Positive Margin | BR110: No Provision | BS110: =AY110-Y110-Q110-AA110-T110+BC110 -> 11050.081 | BT110: =IF(BS110<0, "Negative Margin at Inception", "Positive Margin at Inception") -> Positive Margin at Inception | BU110: =IFERROR(BP110/BO110,"0") -> 0.13299878 | BV110: =IF(BU110<1%,"Less Than 1%",IF(BU110>2%,"More than 2%",IF(BU110>=1%,"1% - 2%"))) -> More than 2% | BW110: =BM110+BN110 -> 0 | BX110: =AL110+AK110 -> 0 | BY110: =BW110-BX110 -> 0 | BZ110: =BM110 -> 0 | CA110: =AK110 -> 0 | CB110: =BZ110-CA110 -> 0 | CC110: Marketplace (IT Assets Disposition) | CD110: 0 | CE110: =AM110-AL110-AA110 -> 72034 | CF110: =BO110-BN110 -> 83084.081 | CG110: =INT((D110- IF(MONTH(D110) >= 4, DATE(YEAR(D110), 4, 1), DATE(YEAR(D110)-1, 4, 1))) / 7) + 1 -> 7 | CH110: 0 | CI110: 0 | CJ110: =_xlfn.XLOOKUP(AP110,POC!B:B,POC!D:D) -> #N/A | CK110: =AY110-Q110 -> 11050.081 | CL110: =CK110-Y110+Z110 -> 11050.081 | CM110: =BO110-AM110 -> 11050.081 | CN110: =AY110*118% -> 98039.216 | CO110: =-Q110*118% -> -85000.12 | CP110: =-BZ110*118% -> 0 | CQ110: =-CA110*118% -> 0 | CR110: =SUM(CN110:CQ110) -> 13039.096 | CS110: Telangana - HO | CT110: Telangana - HO | CU110: =MID(G110,3,10) -> AACCV3080E | CV110: =MID(AR110,3,10) -> GOWPS6814G
B111: ="Q" & IF(ROUNDUP(MONTH(D111)/3,0)-1=0,4,ROUNDUP(MONTH(D111)/3,0)-1) -> Q1 | C111: =TEXT(AN111,"mmm-yy") -> May-26 | D111: 46162 | E111: SH05262102 | F111: SMARTSTREAM TECHNOLOGIES INDIA PRIVATE LIMITED | G111: 29AAACG2086M1Z9 | H111: STLIN/02/26-27 | I111: 46162 | J111: 26-27/PUR/002413 | K111: 46163 | L111: KA | N111: ITAD Mixed E Waste | O111: 1 | P111: 589050 | Q111: =O111*P111 -> 589050 | R111: 0 | S111: =O111-R111 -> 1 | T111: 0 | U111: 0 | V111: 0 | W111: 0 | X111: 0 | Y111: 0 | Z111: 0 | AA111: 0 | AB111: =Y111+AA111+Z111 -> 0 | AC111: 0 | AD111: 0 | AE111: 0 | AF111: 0 | AG111: 0 | AH111: 0 | AI111: 0 | AJ111: 0 | AK111: 0 | AL111: 0 | AM111: =Q111+AB111+AL111+AK111+AJ111+T111+AE111 -> 589050 | AN111: 46163 | AO111: 36/IAD/27IN00018 | AP111: 832139000077287080 | AQ111: CONNECT INFO SOLUTIONS INDIA PRIVATE LIMITED | AR111: 27AAFCC0260J1ZU | AS111: Bengaluru,Karnataka,560029 | AT111: Mumbai | AU111: Maharashtra | AW111: 1 | AX111: 628406.45 | AY111: =AW111*AX111 -> 628406.45 | AZ111: =AW111=O111 -> TRUE | BA111: 0 | BB111: =AW111-BA111 -> 1 | BC111: 0 | BD111: Regular | BE111: 0 | BF111: 0 | BG111: 0 | BH111: 0 | BI111: 0 | BJ111: 0 | BK111: 0 | BL111: 0 | BM111: 0 | BN111: =AY111*$BM$3 -> 0 | BO111: =AY111+BL111+BM111+BN111+BC111+BG111 -> 628406.45 | BP111: =BO111-AM111 -> 39356.45 | BQ111: =IF(BP111>=0,"Positive Margin","Negative Margin") -> Positive Margin | BR111: No Provision | BS111: =AY111-Y111-Q111-AA111-T111+BC111 -> 39356.45 | BT111: =IF(BS111<0, "Negative Margin at Inception", "Positive Margin at Inception") -> Positive Margin at Inception | BU111: =IFERROR(BP111/BO111,"0") -> 0.062628972 | BV111: =IF(BU111<1%,"Less Than 1%",IF(BU111>2%,"More than 2%",IF(BU111>=1%,"1% - 2%"))) -> More than 2% | BW111: =BM111+BN111 -> 0 | BX111: =AL111+AK111 -> 0 | BY111: =BW111-BX111 -> 0 | BZ111: =BM111 -> 0 | CA111: =AK111 -> 0 | CB111: =BZ111-CA111 -> 0 | CC111: Marketplace (IT Assets Disposition) | CD111: 0 | CE111: =AM111-AL111-AA111 -> 589050 | CF111: =BO111-BN111 -> 628406.45 | CG111: =INT((D111- IF(MONTH(D111) >= 4, DATE(YEAR(D111), 4, 1), DATE(YEAR(D111)-1, 4, 1))) / 7) + 1 -> 8 | CH111: 0 | CI111: 0 | CJ111: =_xlfn.XLOOKUP(AP111,POC!B:B,POC!D:D) -> #N/A | CK111: =AY111-Q111 -> 39356.45 | CL111: =CK111-Y111+Z111 -> 39356.45 | CM111: =BO111-AM111 -> 39356.45 | CN111: =AY111*118% -> 741519.61 | CO111: =-Q111*118% -> -695079 | CP111: =-BZ111*118% -> 0 | CQ111: =-CA111*118% -> 0 | CR111: =SUM(CN111:CQ111) -> 46440.611 | CS111: Telangana - HO | CT111: Telangana - HO | CU111: =MID(G111,3,10) -> AAACG2086M | CV111: =MID(AR111,3,10) -> AAFCC0260J
B112: ="Q" & IF(ROUNDUP(MONTH(D112)/3,0)-1=0,4,ROUNDUP(MONTH(D112)/3,0)-1) -> Q1 | C112: =TEXT(AN112,"mmm-yy") -> May-26 | D112: 46162 | E112: SH05262101 | F112: SMARTSTREAM TECHNOLOGIES INDIA PRIVATE LIMITED | G112: 27AAACG2086M2ZC | H112: STLIN/01/26-27 | I112: 46162 | J112: 26-27/PUR/002412 | K112: 46163 | L112: MH | N112: ITAD Mixed E Waste | O112: 1 | P112: 322245 | Q112: =O112*P112 -> 322245 | R112: 0 | S112: =O112-R112 -> 1 | T112: 0 | U112: 0 | V112: 0 | W112: 0 | X112: 0 | Y112: 0 | Z112: 0 | AA112: 0 | AB112: =Y112+AA112+Z112 -> 0 | AC112: 0 | AD112: 0 | AE112: 0 | AF112: 0 | AG112: 0 | AH112: 0 | AI112: 0 | AJ112: 0 | AK112: 0 | AL112: 0 | AM112: =Q112+AB112+AL112+AK112+AJ112+T112+AE112 -> 322245 | AN112: 46163 | AO112: 36/IAD/27IN00019 | AP112: 832139000077287080 | AQ112: CONNECT INFO SOLUTIONS INDIA PRIVATE LIMITED | AR112: 27AAFCC0260J1ZU | AS112: Kandivali West, Maharashtra 400053 | AT112: Mumbai | AU112: Maharashtra | AW112: 1 | AX112: 343677.3 | AY112: =AW112*AX112 -> 343677.3 | AZ112: =AW112=O112 -> TRUE | BA112: 0 | BB112: =AW112-BA112 -> 1 | BC112: 0 | BD112: Regular | BE112: 0 | BF112: 0 | BG112: 0 | BH112: 0 | BI112: 0 | BJ112: 0 | BK112: 0 | BL112: 0 | BM112: 0 | BN112: =AY112*$BM$3 -> 0 | BO112: =AY112+BL112+BM112+BN112+BC112+BG112 -> 343677.3 | BP112: =BO112-AM112 -> 21432.3 | BQ112: =IF(BP112>=0,"Positive Margin","Negative Margin") -> Positive Margin | BR112: No Provision | BS112: =AY112-Y112-Q112-AA112-T112+BC112 -> 21432.3 | BT112: =IF(BS112<0, "Negative Margin at Inception", "Positive Margin at Inception") -> Positive Margin at Inception | BU112: =IFERROR(BP112/BO112,"0") -> 0.062361698 | BV112: =IF(BU112<1%,"Less Than 1%",IF(BU112>2%,"More than 2%",IF(BU112>=1%,"1% - 2%"))) -> More than 2% | BW112: =BM112+BN112 -> 0 | BX112: =AL112+AK112 -> 0 | BY112: =BW112-BX112 -> 0 | BZ112: =BM112 -> 0 | CA112: =AK112 -> 0 | CB112: =BZ112-CA112 -> 0 | CC112: Marketplace (IT Assets Disposition) | CD112: 0 | CE112: =AM112-AL112-AA112 -> 322245 | CF112: =BO112-BN112 -> 343677.3 | CG112: =INT((D112- IF(MONTH(D112) >= 4, DATE(YEAR(D112), 4, 1), DATE(YEAR(D112)-1, 4, 1))) / 7) + 1 -> 8 | CH112: 0 | CI112: 0 | CJ112: =_xlfn.XLOOKUP(AP112,POC!B:B,POC!D:D) -> #N/A | CK112: =AY112-Q112 -> 21432.3 | CL112: =CK112-Y112+Z112 -> 21432.3 | CM112: =BO112-AM112 -> 21432.3 | CN112: =AY112*118% -> 405539.21 | CO112: =-Q112*118% -> -380249.1 | CP112: =-BZ112*118% -> 0 | CQ112: =-CA112*118% -> 0 | CR112: =SUM(CN112:CQ112) -> 25290.114 | CS112: Telangana - HO | CT112: Telangana - HO | CU112: =MID(G112,3,10) -> AAACG2086M | CV112: =MID(AR112,3,10) -> AAFCC0260J
