Workbook

Sheet Summary
T2: ="As on"& " "&TEXT(Details!P22,"dd-mmm-yyyy") -> As on 14-Jun-2026 | U2: Non-Ferrous | AJ2: Ferrous | AY2: M3
D3: =TEXT(D5,"mmm-yy") -> Apr-26 | E3: =TEXT(E5,"mmm-yy") -> May-26 | F3: =TEXT(F5,"mmm-yy") -> Jun-26 | G3: =TEXT(G5,"mmm-yy") -> Jul-26 | H3: =TEXT(H5,"mmm-yy") -> Aug-26 | I3: =TEXT(I5,"mmm-yy") -> Sep-26 | J3: =TEXT(J5,"mmm-yy") -> Oct-26 | K3: =TEXT(K5,"mmm-yy") -> Nov-26 | ... O3: =TEXT(O5,"mmm-yy") -> Mar-27 | U3: Apr-25 | V3: =E3 -> May-26 | W3: =F3 -> Jun-26 | X3: =G3 -> Jul-26 | Y3: =H3 -> Aug-26 | Z3: =I3 -> Sep-26 | AA3: =J3 -> Oct-26 | AB3: =K3 -> Nov-26 | AC3: =L3 -> Dec-26 | ... AF3: =O3 -> Mar-27 | AJ3: =D3 -> Apr-26 | AK3: =E3 -> May-26 | AL3: =F3 -> Jun-26 | AM3: =G3 -> Jul-26 | AN3: =H3 -> Aug-26 | AO3: =I3 -> Sep-26 | AP3: =J3 -> Oct-26 | AQ3: =K3 -> Nov-26 | ... AU3: =O3 -> Mar-27 | AY3: =TEXT(AY5,"mmm-yy") -> Apr-26 | AZ3: =TEXT(AZ5,"mmm-yy") -> May-26 | BA3: =TEXT(BA5,"mmm-yy") -> Jun-26 | BB3: =TEXT(BB5,"mmm-yy") -> Jul-26 | BC3: =TEXT(BC5,"mmm-yy") -> Aug-26 | BD3: =TEXT(BD5,"mmm-yy") -> Sep-26 | BE3: =TEXT(BE5,"mmm-yy") -> Oct-26 | BF3: =TEXT(BF5,"mmm-yy") -> Nov-26 | ... BJ3: =TEXT(BJ5,"mmm-yy") -> Mar-27
D4: 30 | E4: 31 | F4: 14 | G4: 0 | H4: 0 | I4: 0 | J4: 0 | K4: 0 | L4: 0 | M4: 0 | N4: 0 | O4: 0 | P4: =SUM(D4:O4) -> 75 | U4: =D4 -> 30 | V4: =E4 -> 31 | W4: =F4 -> 14 | X4: =G4 -> 0 | Y4: =H4 -> 0 | Z4: =I4 -> 0 | AA4: =J4 -> 0 | AB4: =K4 -> 0 | ... AG4: =P4 -> 75 | AJ4: =D4 -> 30 | AK4: =E4 -> 31 | AL4: =F4 -> 14 | AM4: =G4 -> 0 | AN4: =H4 -> 0 | AO4: =I4 -> 0 | AP4: =J4 -> 0 | AQ4: =K4 -> 0 | ... AV4: =P4 -> 75 | AY4: =D4 -> 30 | AZ4: =E4 -> 31 | BA4: =F4 -> 14 | BB4: =G4 -> 0 | BC4: =H4 -> 0 | BD4: =I4 -> 0 | BE4: =J4 -> 0 | BF4: =K4 -> 0 | ... BK4: =P4 -> 75
C5: Marketplace (M4) | D5: 46113 | E5: 46143 | F5: 46174 | G5: 46204 | H5: 46235 | I5: 46266 | J5: 46296 | K5: 46327 | L5: 46357 | M5: 46388 | N5: 46419 | O5: 46447 | P5: FY 2026-27 | T5: Non-Ferrous | U5: =D5 -> 46113 | V5: =E5 -> 46143 | W5: =F5 -> 46174 | X5: =G5 -> 46204 | Y5: =H5 -> 46235 | Z5: =I5 -> 46266 | AA5: =J5 -> 46296 | AB5: =K5 -> 46327 | ... AG5: =P5 -> FY 2026-27 | AI5: Ferrous | AJ5: =U5 -> 46113 | AK5: =V5 -> 46143 | AL5: =W5 -> 46174 | AM5: =X5 -> 46204 | AN5: =Y5 -> 46235 | AO5: =Z5 -> 46266 | AP5: =AA5 -> 46296 | AQ5: =AB5 -> 46327 | ... AV5: =AG5 -> FY 2026-27 | AX5: M3 | AY5: =AJ5 -> 46113 | AZ5: =AK5 -> 46143 | BA5: =AL5 -> 46174 | BB5: =AM5 -> 46204 | BC5: =AN5 -> 46235 | BD5: =AO5 -> 46266 | BE5: =AP5 -> 46296 | BF5: =AQ5 -> 46327 | ... BK5: =AV5 -> FY 2026-27 | BM5: Check
C6: Quantity (MT) | D6: =SUMIFS(Details!$BB$5:$BB$11,Details!$C$5:$C$11,Summary!D$5) -> 62 | E6: =SUMIFS(Details!$BB$5:$BB$11,Details!$C$5:$C$11,Summary!E$5) -> 66 | F6: =SUMIFS(Details!$BB$5:$BB$11,Details!$C$5:$C$11,Summary!F$5) -> 70 | G6: =SUMIFS(Details!$BB$5:$BB$11,Details!$C$5:$C$11,Summary!G$5) -> 0 | H6: =SUMIFS(Details!$BB$5:$BB$11,Details!$C$5:$C$11,Summary!H$5) -> 0 | I6: =SUMIFS(Details!$BB$5:$BB$11,Details!$C$5:$C$11,Summary!I$5) -> 0 | J6: =SUMIFS(Details!$BB$5:$BB$11,Details!$C$5:$C$11,Summary!J$5) -> 0 | K6: =SUMIFS(Details!$BB$5:$BB$11,Details!$C$5:$C$11,Summary!K$5) -> 0 | ... O6: =SUMIFS(Details!$BB$5:$BB$11,Details!$C$5:$C$11,Summary!O$5) -> 0 | P6: =SUM(D6:O6) -> 198 | Q6: =Details!BB12 -> 198 | R6: =P6-Q6 -> 0 | T6: Quantity (MT) | U6: =SUMIFS(Details!$S$5:$S$11,Details!$C$5:$C$11,Summary!U$5,Details!$CK$5:$CK$11,Summary!$T$5)/1000 -> 0 | V6: =SUMIFS(Details!$S$5:$S$11,Details!$C$5:$C$11,Summary!V$5,Details!$CK$5:$CK$11,Summary!$T$5)/1000 -> 0 | W6: =SUMIFS(Details!$S$5:$S$11,Details!$C$5:$C$11,Summary!W$5,Details!$CK$5:$CK$11,Summary!$T$5)/1000 -> 0 | X6: =SUMIFS(Details!$S$5:$S$11,Details!$C$5:$C$11,Summary!X$5,Details!$CK$5:$CK$11,Summary!$T$5)/1000 -> 0 | Y6: =SUMIFS(Details!$S$5:$S$11,Details!$C$5:$C$11,Summary!Y$5,Details!$CK$5:$CK$11,Summary!$T$5)/1000 -> 0 | Z6: =SUMIFS(Details!$S$5:$S$11,Details!$C$5:$C$11,Summary!Z$5,Details!$CK$5:$CK$11,Summary!$T$5)/1000 -> 0 | AA6: =SUMIFS(Details!$S$5:$S$11,Details!$C$5:$C$11,Summary!AA$5,Details!$CK$5:$CK$11,Summary!$T$5)/1000 -> 0 | AB6: =SUMIFS(Details!$S$5:$S$11,Details!$C$5:$C$11,Summary!AB$5,Details!$CK$5:$CK$11,Summary!$T$5)/1000 -> 0 | ... AF6: =SUMIFS(Details!$S$5:$S$11,Details!$C$5:$C$11,Summary!AF$5,Details!$CK$5:$CK$11,Summary!$T$5)/1000 -> 0 | AG6: =SUM(U6:AF6) -> 0 | AI6: Quantity (MT) | AJ6: =SUMIFS(Details!$S$5:$S$11,Details!$C$5:$C$11,Summary!AJ$5,Details!$CK$5:$CK$11,Summary!$AI$5)/1000 -> 0 | AK6: =SUMIFS(Details!$S$5:$S$11,Details!$C$5:$C$11,Summary!AK$5,Details!$CK$5:$CK$11,Summary!$AI$5)/1000 -> 0 | AL6: =SUMIFS(Details!$S$5:$S$11,Details!$C$5:$C$11,Summary!AL$5,Details!$CK$5:$CK$11,Summary!$AI$5)/1000 -> 0 | AM6: =SUMIFS(Details!$S$5:$S$11,Details!$C$5:$C$11,Summary!AM$5,Details!$CK$5:$CK$11,Summary!$AI$5)/1000 -> 0 | AN6: =SUMIFS(Details!$S$5:$S$11,Details!$C$5:$C$11,Summary!AN$5,Details!$CK$5:$CK$11,Summary!$AI$5)/1000 -> 0 | AO6: =SUMIFS(Details!$S$5:$S$11,Details!$C$5:$C$11,Summary!AO$5,Details!$CK$5:$CK$11,Summary!$AI$5)/1000 -> 0 | AP6: =SUMIFS(Details!$S$5:$S$11,Details!$C$5:$C$11,Summary!AP$5,Details!$CK$5:$CK$11,Summary!$AI$5)/1000 -> 0 | AQ6: =SUMIFS(Details!$S$5:$S$11,Details!$C$5:$C$11,Summary!AQ$5,Details!$CK$5:$CK$11,Summary!$AI$5)/1000 -> 0 | ... AU6: =SUMIFS(Details!$S$5:$S$11,Details!$C$5:$C$11,Summary!AU$5,Details!$CK$5:$CK$11,Summary!$AI$5)/1000 -> 0 | AV6: =SUM(AJ6:AU6) -> 0 | AX6: Quantity (MT) | AY6: =SUMIFS(Details!$S$5:$S$11,Details!$C$5:$C$11,Summary!AY$5,Details!$CK$5:$CK$11,Summary!$AX$5)/1000 -> 0 | AZ6: =SUMIFS(Details!$S$5:$S$11,Details!$C$5:$C$11,Summary!AZ$5,Details!$CK$5:$CK$11,Summary!$AX$5)/1000 -> 0 | BA6: =SUMIFS(Details!$S$5:$S$11,Details!$C$5:$C$11,Summary!BA$5,Details!$CK$5:$CK$11,Summary!$AX$5)/1000 -> 0 | BB6: =SUMIFS(Details!$S$5:$S$11,Details!$C$5:$C$11,Summary!BB$5,Details!$CK$5:$CK$11,Summary!$AX$5)/1000 -> 0 | BC6: =SUMIFS(Details!$S$5:$S$11,Details!$C$5:$C$11,Summary!BC$5,Details!$CK$5:$CK$11,Summary!$AX$5)/1000 -> 0 | BD6: =SUMIFS(Details!$S$5:$S$11,Details!$C$5:$C$11,Summary!BD$5,Details!$CK$5:$CK$11,Summary!$AX$5)/1000 -> 0 | BE6: =SUMIFS(Details!$S$5:$S$11,Details!$C$5:$C$11,Summary!BE$5,Details!$CK$5:$CK$11,Summary!$AX$5)/1000 -> 0 | BF6: =SUMIFS(Details!$S$5:$S$11,Details!$C$5:$C$11,Summary!BF$5,Details!$CK$5:$CK$11,Summary!$AX$5)/1000 -> 0 | ... BJ6: =SUMIFS(Details!$S$5:$S$11,Details!$C$5:$C$11,Summary!BJ$5,Details!$CK$5:$CK$11,Summary!$AX$5)/1000 -> 0 | BK6: =SUM(AY6:BJ6) -> 0 | BM6: =(AG6+AV6+BK6)-P6 -> -198
C7: Sales | D7: =SUMIFS(Details!$BQ$5:$BQ$11,Details!$C$5:$C$11,Summary!D$5) -> 32860 | E7: =SUMIFS(Details!$BQ$5:$BQ$11,Details!$C$5:$C$11,Summary!E$5) -> 34980 | F7: =SUMIFS(Details!$BQ$5:$BQ$11,Details!$C$5:$C$11,Summary!F$5) -> 19950 | G7: =SUMIFS(Details!$BQ$5:$BQ$11,Details!$C$5:$C$11,Summary!G$5) -> 0 | H7: =SUMIFS(Details!$BQ$5:$BQ$11,Details!$C$5:$C$11,Summary!H$5) -> 0 | I7: =SUMIFS(Details!$BQ$5:$BQ$11,Details!$C$5:$C$11,Summary!I$5) -> 0 | J7: =SUMIFS(Details!$BQ$5:$BQ$11,Details!$C$5:$C$11,Summary!J$5) -> 0 | K7: =SUMIFS(Details!$BQ$5:$BQ$11,Details!$C$5:$C$11,Summary!K$5) -> 0 | ... O7: =SUMIFS(Details!$BQ$5:$BQ$11,Details!$C$5:$C$11,Summary!O$5) -> 0 | P7: =SUM(D7:O7) -> 87790 | Q7: =Details!BQ12 -> 87790 | R7: =P7-Q7 -> 0 | T7: Sales | U7: =SUMIFS(Details!$BQ$5:$BQ$11,Details!$C$5:$C$11,Summary!U$5,Details!$CK$5:$CK$11,Summary!$T$5) -> 0 | V7: =SUMIFS(Details!$BQ$5:$BQ$11,Details!$C$5:$C$11,Summary!V$5,Details!$CK$5:$CK$11,Summary!$T$5) -> 0 | W7: =SUMIFS(Details!$BQ$5:$BQ$11,Details!$C$5:$C$11,Summary!W$5,Details!$CK$5:$CK$11,Summary!$T$5) -> 0 | X7: =SUMIFS(Details!$BQ$5:$BQ$11,Details!$C$5:$C$11,Summary!X$5,Details!$CK$5:$CK$11,Summary!$T$5) -> 0 | Y7: =SUMIFS(Details!$BQ$5:$BQ$11,Details!$C$5:$C$11,Summary!Y$5,Details!$CK$5:$CK$11,Summary!$T$5) -> 0 | Z7: =SUMIFS(Details!$BQ$5:$BQ$11,Details!$C$5:$C$11,Summary!Z$5,Details!$CK$5:$CK$11,Summary!$T$5) -> 0 | AA7: =SUMIFS(Details!$BQ$5:$BQ$11,Details!$C$5:$C$11,Summary!AA$5,Details!$CK$5:$CK$11,Summary!$T$5) -> 0 | AB7: =SUMIFS(Details!$BQ$5:$BQ$11,Details!$C$5:$C$11,Summary!AB$5,Details!$CK$5:$CK$11,Summary!$T$5) -> 0 | ... AF7: =SUMIFS(Details!$BQ$5:$BQ$11,Details!$C$5:$C$11,Summary!AF$5,Details!$CK$5:$CK$11,Summary!$T$5) -> 0 | AG7: =SUM(U7:AF7) -> 0 | AI7: Sales | AJ7: =SUMIFS(Details!$BQ$5:$BQ$11,Details!$C$5:$C$11,Summary!AJ$5,Details!$CK$5:$CK$11,Summary!$AI$5) -> 0 | AK7: =SUMIFS(Details!$BQ$5:$BQ$11,Details!$C$5:$C$11,Summary!AK$5,Details!$CK$5:$CK$11,Summary!$AI$5) -> 0 | AL7: =SUMIFS(Details!$BQ$5:$BQ$11,Details!$C$5:$C$11,Summary!AL$5,Details!$CK$5:$CK$11,Summary!$AI$5) -> 0 | AM7: =SUMIFS(Details!$BQ$5:$BQ$11,Details!$C$5:$C$11,Summary!AM$5,Details!$CK$5:$CK$11,Summary!$AI$5) -> 0 | AN7: =SUMIFS(Details!$BQ$5:$BQ$11,Details!$C$5:$C$11,Summary!AN$5,Details!$CK$5:$CK$11,Summary!$AI$5) -> 0 | AO7: =SUMIFS(Details!$BQ$5:$BQ$11,Details!$C$5:$C$11,Summary!AO$5,Details!$CK$5:$CK$11,Summary!$AI$5) -> 0 | AP7: =SUMIFS(Details!$BQ$5:$BQ$11,Details!$C$5:$C$11,Summary!AP$5,Details!$CK$5:$CK$11,Summary!$AI$5) -> 0 | AQ7: =SUMIFS(Details!$BQ$5:$BQ$11,Details!$C$5:$C$11,Summary!AQ$5,Details!$CK$5:$CK$11,Summary!$AI$5) -> 0 | ... AU7: =SUMIFS(Details!$BQ$5:$BQ$11,Details!$C$5:$C$11,Summary!AU$5,Details!$CK$5:$CK$11,Summary!$AI$5) -> 0 | AV7: =SUM(AJ7:AU7) -> 0 | AX7: Sales | AY7: =SUMIFS(Details!$BQ$5:$BQ$11,Details!$C$5:$C$11,Summary!AY$5,Details!$CK$5:$CK$11,Summary!$AX$5) -> 0 | AZ7: =SUMIFS(Details!$BQ$5:$BQ$11,Details!$C$5:$C$11,Summary!AZ$5,Details!$CK$5:$CK$11,Summary!$AX$5) -> 0 | BA7: =SUMIFS(Details!$BQ$5:$BQ$11,Details!$C$5:$C$11,Summary!BA$5,Details!$CK$5:$CK$11,Summary!$AX$5) -> 0 | BB7: =SUMIFS(Details!$BQ$5:$BQ$11,Details!$C$5:$C$11,Summary!BB$5,Details!$CK$5:$CK$11,Summary!$AX$5) -> 0 | BC7: =SUMIFS(Details!$BQ$5:$BQ$11,Details!$C$5:$C$11,Summary!BC$5,Details!$CK$5:$CK$11,Summary!$AX$5) -> 0 | BD7: =SUMIFS(Details!$BQ$5:$BQ$11,Details!$C$5:$C$11,Summary!BD$5,Details!$CK$5:$CK$11,Summary!$AX$5) -> 0 | BE7: =SUMIFS(Details!$BQ$5:$BQ$11,Details!$C$5:$C$11,Summary!BE$5,Details!$CK$5:$CK$11,Summary!$AX$5) -> 0 | BF7: =SUMIFS(Details!$BQ$5:$BQ$11,Details!$C$5:$C$11,Summary!BF$5,Details!$CK$5:$CK$11,Summary!$AX$5) -> 0 | ... BJ7: =SUMIFS(Details!$BQ$5:$BQ$11,Details!$C$5:$C$11,Summary!BJ$5,Details!$CK$5:$CK$11,Summary!$AX$5) -> 0 | BK7: =SUM(AY7:BJ7) -> 0 | BM7: =(AG7+AV7+BK7)-P7 -> -87790
C8: Purchases | D8: =SUMIFS(Details!$AM$5:$AM$11,Details!$C$5:$C$11,Summary!D$5)-SUMIFS(Details!$AB$5:$AB$11,Details!$C$5:$C$11,Summary!D$5) -> 29400 | E8: =SUMIFS(Details!$AM$5:$AM$11,Details!$C$5:$C$11,Summary!E$5)-SUMIFS(Details!$AB$5:$AB$11,Details!$C$5:$C$11,Summary!E$5) -> 30900 | F8: =SUMIFS(Details!$AM$5:$AM$11,Details!$C$5:$C$11,Summary!F$5)-SUMIFS(Details!$AB$5:$AB$11,Details!$C$5:$C$11,Summary!F$5) -> 8900 | G8: =SUMIFS(Details!$AM$5:$AM$11,Details!$C$5:$C$11,Summary!G$5)-SUMIFS(Details!$AB$5:$AB$11,Details!$C$5:$C$11,Summary!G$5) -> 0 | H8: =SUMIFS(Details!$AM$5:$AM$11,Details!$C$5:$C$11,Summary!H$5)-SUMIFS(Details!$AB$5:$AB$11,Details!$C$5:$C$11,Summary!H$5) -> 0 | I8: =SUMIFS(Details!$AM$5:$AM$11,Details!$C$5:$C$11,Summary!I$5)-SUMIFS(Details!$AB$5:$AB$11,Details!$C$5:$C$11,Summary!I$5) -> 0 | J8: =SUMIFS(Details!$AM$5:$AM$11,Details!$C$5:$C$11,Summary!J$5)-SUMIFS(Details!$AB$5:$AB$11,Details!$C$5:$C$11,Summary!J$5) -> 0 | K8: =SUMIFS(Details!$AM$5:$AM$11,Details!$C$5:$C$11,Summary!K$5)-SUMIFS(Details!$AB$5:$AB$11,Details!$C$5:$C$11,Summary!K$5) -> 0 | ... O8: =SUMIFS(Details!$AM$5:$AM$11,Details!$C$5:$C$11,Summary!O$5)-SUMIFS(Details!$AB$5:$AB$11,Details!$C$5:$C$11,Summary!O$5) -> 0 | P8: =SUM(D8:O8) -> 69200 | Q8: =Details!P13 -> 69200 | R8: =P8-Q8 -> 0 | T8: Purchases | U8: =SUMIFS(Details!$AM$5:$AM$11,Details!$C$5:$C$11,Summary!U$5,Details!$CK$5:$CK$11,Summary!$T$5)-SUMIFS(Details!$AB$5:$AB$11,Details!$C$5:$C$11,Summary!U$5,Details!$CK$5:$CK$11,Summary!$T$5) -> 0 | V8: =SUMIFS(Details!$AM$5:$AM$11,Details!$C$5:$C$11,Summary!V$5,Details!$CK$5:$CK$11,Summary!$T$5)-SUMIFS(Details!$AB$5:$AB$11,Details!$C$5:$C$11,Summary!V$5,Details!$CK$5:$CK$11,Summary!$T$5) -> 0 | W8: =SUMIFS(Details!$AM$5:$AM$11,Details!$C$5:$C$11,Summary!W$5,Details!$CK$5:$CK$11,Summary!$T$5)-SUMIFS(Details!$AB$5:$AB$11,Details!$C$5:$C$11,Summary!W$5,Details!$CK$5:$CK$11,Summary!$T$5) -> 0 | X8: =SUMIFS(Details!$AM$5:$AM$11,Details!$C$5:$C$11,Summary!X$5,Details!$CK$5:$CK$11,Summary!$T$5)-SUMIFS(Details!$AB$5:$AB$11,Details!$C$5:$C$11,Summary!X$5,Details!$CK$5:$CK$11,Summary!$T$5) -> 0 | Y8: =SUMIFS(Details!$AM$5:$AM$11,Details!$C$5:$C$11,Summary!Y$5,Details!$CK$5:$CK$11,Summary!$T$5)-SUMIFS(Details!$AB$5:$AB$11,Details!$C$5:$C$11,Summary!Y$5,Details!$CK$5:$CK$11,Summary!$T$5) -> 0 | Z8: =SUMIFS(Details!$AM$5:$AM$11,Details!$C$5:$C$11,Summary!Z$5,Details!$CK$5:$CK$11,Summary!$T$5)-SUMIFS(Details!$AB$5:$AB$11,Details!$C$5:$C$11,Summary!Z$5,Details!$CK$5:$CK$11,Summary!$T$5) -> 0 | AA8: =SUMIFS(Details!$AM$5:$AM$11,Details!$C$5:$C$11,Summary!AA$5,Details!$CK$5:$CK$11,Summary!$T$5)-SUMIFS(Details!$AB$5:$AB$11,Details!$C$5:$C$11,Summary!AA$5,Details!$CK$5:$CK$11,Summary!$T$5) -> 0 | AB8: =SUMIFS(Details!$AM$5:$AM$11,Details!$C$5:$C$11,Summary!AB$5,Details!$CK$5:$CK$11,Summary!$T$5)-SUMIFS(Details!$AB$5:$AB$11,Details!$C$5:$C$11,Summary!AB$5,Details!$CK$5:$CK$11,Summary!$T$5) -> 0 | ... AF8: =SUMIFS(Details!$AM$5:$AM$11,Details!$C$5:$C$11,Summary!AF$5,Details!$CK$5:$CK$11,Summary!$T$5)-SUMIFS(Details!$AB$5:$AB$11,Details!$C$5:$C$11,Summary!AF$5,Details!$CK$5:$CK$11,Summary!$T$5) -> 0 | AG8: =SUM(U8:AF8) -> 0 | AI8: Purchases | AJ8: =SUMIFS(Details!$AM$5:$AM$11,Details!$C$5:$C$11,Summary!AJ$5,Details!$CK$5:$CK$11,Summary!$AI$5)-SUMIFS(Details!$AB$5:$AB$11,Details!$C$5:$C$11,Summary!AJ$5,Details!$CK$5:$CK$11,Summary!$AI$5) -> 0 | AK8: =SUMIFS(Details!$AM$5:$AM$11,Details!$C$5:$C$11,Summary!AK$5,Details!$CK$5:$CK$11,Summary!$AI$5)-SUMIFS(Details!$AB$5:$AB$11,Details!$C$5:$C$11,Summary!AK$5,Details!$CK$5:$CK$11,Summary!$AI$5) -> 0 | AL8: =SUMIFS(Details!$AM$5:$AM$11,Details!$C$5:$C$11,Summary!AL$5,Details!$CK$5:$CK$11,Summary!$AI$5)-SUMIFS(Details!$AB$5:$AB$11,Details!$C$5:$C$11,Summary!AL$5,Details!$CK$5:$CK$11,Summary!$AI$5) -> 0 | AM8: =SUMIFS(Details!$AM$5:$AM$11,Details!$C$5:$C$11,Summary!AM$5,Details!$CK$5:$CK$11,Summary!$AI$5)-SUMIFS(Details!$AB$5:$AB$11,Details!$C$5:$C$11,Summary!AM$5,Details!$CK$5:$CK$11,Summary!$AI$5) -> 0 | AN8: =SUMIFS(Details!$AM$5:$AM$11,Details!$C$5:$C$11,Summary!AN$5,Details!$CK$5:$CK$11,Summary!$AI$5)-SUMIFS(Details!$AB$5:$AB$11,Details!$C$5:$C$11,Summary!AN$5,Details!$CK$5:$CK$11,Summary!$AI$5) -> 0 | AO8: =SUMIFS(Details!$AM$5:$AM$11,Details!$C$5:$C$11,Summary!AO$5,Details!$CK$5:$CK$11,Summary!$AI$5)-SUMIFS(Details!$AB$5:$AB$11,Details!$C$5:$C$11,Summary!AO$5,Details!$CK$5:$CK$11,Summary!$AI$5) -> 0 | AP8: =SUMIFS(Details!$AM$5:$AM$11,Details!$C$5:$C$11,Summary!AP$5,Details!$CK$5:$CK$11,Summary!$AI$5)-SUMIFS(Details!$AB$5:$AB$11,Details!$C$5:$C$11,Summary!AP$5,Details!$CK$5:$CK$11,Summary!$AI$5) -> 0 | AQ8: =SUMIFS(Details!$AM$5:$AM$11,Details!$C$5:$C$11,Summary!AQ$5,Details!$CK$5:$CK$11,Summary!$AI$5)-SUMIFS(Details!$AB$5:$AB$11,Details!$C$5:$C$11,Summary!AQ$5,Details!$CK$5:$CK$11,Summary!$AI$5) -> 0 | ... AU8: =SUMIFS(Details!$AM$5:$AM$11,Details!$C$5:$C$11,Summary!AU$5,Details!$CK$5:$CK$11,Summary!$AI$5)-SUMIFS(Details!$AB$5:$AB$11,Details!$C$5:$C$11,Summary!AU$5,Details!$CK$5:$CK$11,Summary!$AI$5) -> 0 | AV8: =SUM(AJ8:AU8) -> 0 | AX8: Purchases | AY8: =SUMIFS(Details!$AM$5:$AM$11,Details!$C$5:$C$11,Summary!AY$5,Details!$CK$5:$CK$11,Summary!$AX$5)-SUMIFS(Details!$AB$5:$AB$11,Details!$C$5:$C$11,Summary!AY$5,Details!$CK$5:$CK$11,Summary!$AX$5) -> 0 | AZ8: =SUMIFS(Details!$AM$5:$AM$11,Details!$C$5:$C$11,Summary!AZ$5,Details!$CK$5:$CK$11,Summary!$AX$5)-SUMIFS(Details!$AB$5:$AB$11,Details!$C$5:$C$11,Summary!AZ$5,Details!$CK$5:$CK$11,Summary!$AX$5) -> 0 | BA8: =SUMIFS(Details!$AM$5:$AM$11,Details!$C$5:$C$11,Summary!BA$5,Details!$CK$5:$CK$11,Summary!$AX$5)-SUMIFS(Details!$AB$5:$AB$11,Details!$C$5:$C$11,Summary!BA$5,Details!$CK$5:$CK$11,Summary!$AX$5) -> 0 | BB8: =SUMIFS(Details!$AM$5:$AM$11,Details!$C$5:$C$11,Summary!BB$5,Details!$CK$5:$CK$11,Summary!$AX$5)-SUMIFS(Details!$AB$5:$AB$11,Details!$C$5:$C$11,Summary!BB$5,Details!$CK$5:$CK$11,Summary!$AX$5) -> 0 | BC8: =SUMIFS(Details!$AM$5:$AM$11,Details!$C$5:$C$11,Summary!BC$5,Details!$CK$5:$CK$11,Summary!$AX$5)-SUMIFS(Details!$AB$5:$AB$11,Details!$C$5:$C$11,Summary!BC$5,Details!$CK$5:$CK$11,Summary!$AX$5) -> 0 | BD8: =SUMIFS(Details!$AM$5:$AM$11,Details!$C$5:$C$11,Summary!BD$5,Details!$CK$5:$CK$11,Summary!$AX$5)-SUMIFS(Details!$AB$5:$AB$11,Details!$C$5:$C$11,Summary!BD$5,Details!$CK$5:$CK$11,Summary!$AX$5) -> 0 | BE8: =SUMIFS(Details!$AM$5:$AM$11,Details!$C$5:$C$11,Summary!BE$5,Details!$CK$5:$CK$11,Summary!$AX$5)-SUMIFS(Details!$AB$5:$AB$11,Details!$C$5:$C$11,Summary!BE$5,Details!$CK$5:$CK$11,Summary!$AX$5) -> 0 | BF8: =SUMIFS(Details!$AM$5:$AM$11,Details!$C$5:$C$11,Summary!BF$5,Details!$CK$5:$CK$11,Summary!$AX$5)-SUMIFS(Details!$AB$5:$AB$11,Details!$C$5:$C$11,Summary!BF$5,Details!$CK$5:$CK$11,Summary!$AX$5) -> 0 | ... BJ8: =SUMIFS(Details!$AM$5:$AM$11,Details!$C$5:$C$11,Summary!BJ$5,Details!$CK$5:$CK$11,Summary!$AX$5)-SUMIFS(Details!$AB$5:$AB$11,Details!$C$5:$C$11,Summary!BJ$5,Details!$CK$5:$CK$11,Summary!$AX$5) -> 0 | BK8: =SUM(AY8:BJ8) -> 0 | BM8: =(AG8+AV8+BK8)-P8 -> -69200
C9: Gross Margin | D9: =D7-D8 -> 3460 | E9: =E7-E8 -> 4080 | F9: =F7-F8 -> 11050 | G9: =G7-G8 -> 0 | H9: =H7-H8 -> 0 | I9: =I7-I8 -> 0 | J9: =J7-J8 -> 0 | K9: =K7-K8 -> 0 | ... P9: =P7-P8 -> 18590 | T9: Gross Margin | U9: =U7-U8 -> 0 | V9: =V7-V8 -> 0 | W9: =W7-W8 -> 0 | X9: =X7-X8 -> 0 | Y9: =Y7-Y8 -> 0 | Z9: =Z7-Z8 -> 0 | AA9: =AA7-AA8 -> 0 | AB9: =AB7-AB8 -> 0 | ... AG9: =AG7-AG8 -> 0 | AI9: Gross Margin | AJ9: =AJ7-AJ8 -> 0 | AK9: =AK7-AK8 -> 0 | AL9: =AL7-AL8 -> 0 | AM9: =AM7-AM8 -> 0 | AN9: =AN7-AN8 -> 0 | AO9: =AO7-AO8 -> 0 | AP9: =AP7-AP8 -> 0 | AQ9: =AQ7-AQ8 -> 0 | ... AV9: =AV7-AV8 -> 0 | AX9: Gross Margin | AY9: =AY7-AY8 -> 0 | AZ9: =AZ7-AZ8 -> 0 | BA9: =BA7-BA8 -> 0 | BB9: =BB7-BB8 -> 0 | BC9: =BC7-BC8 -> 0 | BD9: =BD7-BD8 -> 0 | BE9: =BE7-BE8 -> 0 | BF9: =BF7-BF8 -> 0 | ... BK9: =BK7-BK8 -> 0 | BM9: =(AG9+AV9+BK9)-P9 -> -18590
C10: Gross Margin (%) | D10: =IFERROR((D9/D7),0) -> 0.10529519 | E10: =IFERROR((E9/E7),0) -> 0.11663808 | F10: =IFERROR((F9/F7),0) -> 0.55388471 | G10: =IFERROR((G9/G7),0) -> 0 | H10: =IFERROR((H9/H7),0) -> 0 | I10: =IFERROR((I9/I7),0) -> 0 | J10: =IFERROR((J9/J7),0) -> 0 | K10: =IFERROR((K9/K7),0) -> 0 | ... P10: =IFERROR((P9/P7),0) -> 0.21175533 | T10: Gross Margin (%) | U10: =IFERROR((U9/U7),0) -> 0 | V10: =IFERROR((V9/V7),0) -> 0 | W10: =IFERROR((W9/W7),0) -> 0 | X10: =IFERROR((X9/X7),0) -> 0 | Y10: =IFERROR((Y9/Y7),0) -> 0 | Z10: =IFERROR((Z9/Z7),0) -> 0 | AA10: =IFERROR((AA9/AA7),0) -> 0 | AB10: =IFERROR((AB9/AB7),0) -> 0 | ... AG10: =IFERROR((AG9/AG7),0) -> 0 | AI10: Gross Margin (%) | AJ10: =IFERROR((AJ9/AJ7),0) -> 0 | AK10: =IFERROR((AK9/AK7),0) -> 0 | AL10: =IFERROR((AL9/AL7),0) -> 0 | AM10: =IFERROR((AM9/AM7),0) -> 0 | AN10: =IFERROR((AN9/AN7),0) -> 0 | AO10: =IFERROR((AO9/AO7),0) -> 0 | AP10: =IFERROR((AP9/AP7),0) -> 0 | AQ10: =IFERROR((AQ9/AQ7),0) -> 0 | ... AV10: =IFERROR((AV9/AV7),0) -> 0 | AX10: Gross Margin (%) | AY10: =IFERROR((AY9/AY7),0) -> 0 | AZ10: =IFERROR((AZ9/AZ7),0) -> 0 | BA10: =IFERROR((BA9/BA7),0) -> 0 | BB10: =IFERROR((BB9/BB7),0) -> 0 | BC10: =IFERROR((BC9/BC7),0) -> 0 | BD10: =IFERROR((BD9/BD7),0) -> 0 | BE10: =IFERROR((BE9/BE7),0) -> 0 | BF10: =IFERROR((BF9/BF7),0) -> 0 | ... BK10: =IFERROR((BK9/BK7),0) -> 0 | BM10: =(AG10+AV10+BK10)-P10 -> -0.21175533
C11: Transportation Charges | D11: =SUMIFS(Details!$AB$5:$AB$11,Details!$C$5:$C$11,Summary!D$5) -> 0 | E11: =SUMIFS(Details!$AB$5:$AB$11,Details!$C$5:$C$11,Summary!E$5) -> 0 | F11: =SUMIFS(Details!$AB$5:$AB$11,Details!$C$5:$C$11,Summary!F$5) -> 0 | G11: =SUMIFS(Details!$AB$5:$AB$11,Details!$C$5:$C$11,Summary!G$5) -> 0 | H11: =SUMIFS(Details!$AB$5:$AB$11,Details!$C$5:$C$11,Summary!H$5) -> 0 | I11: =SUMIFS(Details!$AB$5:$AB$11,Details!$C$5:$C$11,Summary!I$5) -> 0 | J11: =SUMIFS(Details!$AB$5:$AB$11,Details!$C$5:$C$11,Summary!J$5) -> 0 | K11: =SUMIFS(Details!$AB$5:$AB$11,Details!$C$5:$C$11,Summary!K$5) -> 0 | ... O11: =SUMIFS(Details!$AB$5:$AB$11,Details!$C$5:$C$11,Summary!O$5) -> 0 | P11: =SUM(D11:O11) -> 0 | Q11: =Details!AB12 -> 0 | R11: =P11-Q11 -> 0 | T11: Transportation Charges | U11: =SUMIFS(Details!$AB$5:$AB$11,Details!$C$5:$C$11,Summary!U$5,Details!$CK$5:$CK$11,Summary!$T$5) -> 0 | V11: =SUMIFS(Details!$AB$5:$AB$11,Details!$C$5:$C$11,Summary!V$5,Details!$CK$5:$CK$11,Summary!$T$5) -> 0 | W11: =SUMIFS(Details!$AB$5:$AB$11,Details!$C$5:$C$11,Summary!W$5,Details!$CK$5:$CK$11,Summary!$T$5) -> 0 | X11: =SUMIFS(Details!$AB$5:$AB$11,Details!$C$5:$C$11,Summary!X$5,Details!$CK$5:$CK$11,Summary!$T$5) -> 0 | Y11: =SUMIFS(Details!$AB$5:$AB$11,Details!$C$5:$C$11,Summary!Y$5,Details!$CK$5:$CK$11,Summary!$T$5) -> 0 | Z11: =SUMIFS(Details!$AB$5:$AB$11,Details!$C$5:$C$11,Summary!Z$5,Details!$CK$5:$CK$11,Summary!$T$5) -> 0 | AA11: =SUMIFS(Details!$AB$5:$AB$11,Details!$C$5:$C$11,Summary!AA$5,Details!$CK$5:$CK$11,Summary!$T$5) -> 0 | AB11: =SUMIFS(Details!$AB$5:$AB$11,Details!$C$5:$C$11,Summary!AB$5,Details!$CK$5:$CK$11,Summary!$T$5) -> 0 | ... AF11: =SUMIFS(Details!$AB$5:$AB$11,Details!$C$5:$C$11,Summary!AF$5,Details!$CK$5:$CK$11,Summary!$T$5) -> 0 | AG11: =SUM(U11:AF11) -> 0 | AI11: Transportation Charges | AJ11: =SUMIFS(Details!$AB$5:$AB$11,Details!$C$5:$C$11,Summary!AJ$5,Details!$CK$5:$CK$11,Summary!$AI$5) -> 0 | AK11: =SUMIFS(Details!$AB$5:$AB$11,Details!$C$5:$C$11,Summary!AK$5,Details!$CK$5:$CK$11,Summary!$AI$5) -> 0 | AL11: =SUMIFS(Details!$AB$5:$AB$11,Details!$C$5:$C$11,Summary!AL$5,Details!$CK$5:$CK$11,Summary!$AI$5) -> 0 | AM11: =SUMIFS(Details!$AB$5:$AB$11,Details!$C$5:$C$11,Summary!AM$5,Details!$CK$5:$CK$11,Summary!$AI$5) -> 0 | AN11: =SUMIFS(Details!$AB$5:$AB$11,Details!$C$5:$C$11,Summary!AN$5,Details!$CK$5:$CK$11,Summary!$AI$5) -> 0 | AO11: =SUMIFS(Details!$AB$5:$AB$11,Details!$C$5:$C$11,Summary!AO$5,Details!$CK$5:$CK$11,Summary!$AI$5) -> 0 | AP11: =SUMIFS(Details!$AB$5:$AB$11,Details!$C$5:$C$11,Summary!AP$5,Details!$CK$5:$CK$11,Summary!$AI$5) -> 0 | AQ11: =SUMIFS(Details!$AB$5:$AB$11,Details!$C$5:$C$11,Summary!AQ$5,Details!$CK$5:$CK$11,Summary!$AI$5) -> 0 | ... AU11: =SUMIFS(Details!$AB$5:$AB$11,Details!$C$5:$C$11,Summary!AU$5,Details!$CK$5:$CK$11,Summary!$AI$5) -> 0 | AV11: =SUM(AJ11:AU11) -> 0 | AX11: Transportation Charges | AY11: =SUMIFS(Details!$AB$5:$AB$11,Details!$C$5:$C$11,Summary!AY$5,Details!$CK$5:$CK$11,Summary!$AX$5) -> 0 | AZ11: =SUMIFS(Details!$AB$5:$AB$11,Details!$C$5:$C$11,Summary!AZ$5,Details!$CK$5:$CK$11,Summary!$AX$5) -> 0 | BA11: =SUMIFS(Details!$AB$5:$AB$11,Details!$C$5:$C$11,Summary!BA$5,Details!$CK$5:$CK$11,Summary!$AX$5) -> 0 | BB11: =SUMIFS(Details!$AB$5:$AB$11,Details!$C$5:$C$11,Summary!BB$5,Details!$CK$5:$CK$11,Summary!$AX$5) -> 0 | BC11: =SUMIFS(Details!$AB$5:$AB$11,Details!$C$5:$C$11,Summary!BC$5,Details!$CK$5:$CK$11,Summary!$AX$5) -> 0 | BD11: =SUMIFS(Details!$AB$5:$AB$11,Details!$C$5:$C$11,Summary!BD$5,Details!$CK$5:$CK$11,Summary!$AX$5) -> 0 | BE11: =SUMIFS(Details!$AB$5:$AB$11,Details!$C$5:$C$11,Summary!BE$5,Details!$CK$5:$CK$11,Summary!$AX$5) -> 0 | BF11: =SUMIFS(Details!$AB$5:$AB$11,Details!$C$5:$C$11,Summary!BF$5,Details!$CK$5:$CK$11,Summary!$AX$5) -> 0 | ... BJ11: =SUMIFS(Details!$AB$5:$AB$11,Details!$C$5:$C$11,Summary!BJ$5,Details!$CK$5:$CK$11,Summary!$AX$5) -> 0 | BK11: =SUM(AY11:BJ11) -> 0 | BM11: =(AG11+AV11+BK11)-P11 -> 0
C12: Operational Cost | D12: =SUMIFS(Details!$AC$5:$AC$11,Details!$C$5:$C$11,Summary!D$5) -> 0 | E12: =SUMIFS(Details!$AC$5:$AC$11,Details!$C$5:$C$11,Summary!E$5) -> 0 | F12: =SUMIFS(Details!$AC$5:$AC$11,Details!$C$5:$C$11,Summary!F$5) -> 0 | G12: =SUMIFS(Details!$AC$5:$AC$11,Details!$C$5:$C$11,Summary!G$5) -> 0 | H12: =SUMIFS(Details!$AC$5:$AC$11,Details!$C$5:$C$11,Summary!H$5) -> 0 | I12: =SUMIFS(Details!$AC$5:$AC$11,Details!$C$5:$C$11,Summary!I$5) -> 0 | J12: =SUMIFS(Details!$AC$5:$AC$11,Details!$C$5:$C$11,Summary!J$5) -> 0 | K12: =SUMIFS(Details!$AC$5:$AC$11,Details!$C$5:$C$11,Summary!K$5) -> 0 | ... O12: =SUMIFS(Details!$AC$5:$AC$11,Details!$C$5:$C$11,Summary!O$5) -> 0 | P12: =SUM(D12:O12) -> 0 | T12: Operational Cost | U12: =SUMIFS(Details!$AC$5:$AC$11,Details!$C$5:$C$11,Summary!U$5,Details!$CK$5:$CK$11,Summary!$T$5) -> 0 | V12: =SUMIFS(Details!$AC$5:$AC$11,Details!$C$5:$C$11,Summary!V$5,Details!$CK$5:$CK$11,Summary!$T$5) -> 0 | W12: =SUMIFS(Details!$AC$5:$AC$11,Details!$C$5:$C$11,Summary!W$5,Details!$CK$5:$CK$11,Summary!$T$5) -> 0 | X12: =SUMIFS(Details!$AC$5:$AC$11,Details!$C$5:$C$11,Summary!X$5,Details!$CK$5:$CK$11,Summary!$T$5) -> 0 | Y12: =SUMIFS(Details!$AC$5:$AC$11,Details!$C$5:$C$11,Summary!Y$5,Details!$CK$5:$CK$11,Summary!$T$5) -> 0 | Z12: =SUMIFS(Details!$AC$5:$AC$11,Details!$C$5:$C$11,Summary!Z$5,Details!$CK$5:$CK$11,Summary!$T$5) -> 0 | AA12: =SUMIFS(Details!$AC$5:$AC$11,Details!$C$5:$C$11,Summary!AA$5,Details!$CK$5:$CK$11,Summary!$T$5) -> 0 | AB12: =SUMIFS(Details!$AC$5:$AC$11,Details!$C$5:$C$11,Summary!AB$5,Details!$CK$5:$CK$11,Summary!$T$5) -> 0 | ... AF12: =SUMIFS(Details!$AC$5:$AC$11,Details!$C$5:$C$11,Summary!AF$5,Details!$CK$5:$CK$11,Summary!$T$5) -> 0 | AG12: =SUM(U12:AF12) -> 0 | AI12: Operational Cost | AJ12: =SUMIFS(Details!$AC$5:$AC$11,Details!$C$5:$C$11,Summary!AJ$5,Details!$CK$5:$CK$11,Summary!$AI$5) -> 0 | AK12: =SUMIFS(Details!$AC$5:$AC$11,Details!$C$5:$C$11,Summary!AK$5,Details!$CK$5:$CK$11,Summary!$AI$5) -> 0 | AL12: =SUMIFS(Details!$AC$5:$AC$11,Details!$C$5:$C$11,Summary!AL$5,Details!$CK$5:$CK$11,Summary!$AI$5) -> 0 | AM12: =SUMIFS(Details!$AC$5:$AC$11,Details!$C$5:$C$11,Summary!AM$5,Details!$CK$5:$CK$11,Summary!$AI$5) -> 0 | AN12: =SUMIFS(Details!$AC$5:$AC$11,Details!$C$5:$C$11,Summary!AN$5,Details!$CK$5:$CK$11,Summary!$AI$5) -> 0 | AO12: =SUMIFS(Details!$AC$5:$AC$11,Details!$C$5:$C$11,Summary!AO$5,Details!$CK$5:$CK$11,Summary!$AI$5) -> 0 | AP12: =SUMIFS(Details!$AC$5:$AC$11,Details!$C$5:$C$11,Summary!AP$5,Details!$CK$5:$CK$11,Summary!$AI$5) -> 0 | AQ12: =SUMIFS(Details!$AC$5:$AC$11,Details!$C$5:$C$11,Summary!AQ$5,Details!$CK$5:$CK$11,Summary!$AI$5) -> 0 | ... AU12: =SUMIFS(Details!$AC$5:$AC$11,Details!$C$5:$C$11,Summary!AU$5,Details!$CK$5:$CK$11,Summary!$AI$5) -> 0 | AV12: =SUM(AJ12:AU12) -> 0 | AX12: Operational Cost | AY12: =SUMIFS(Details!$AC$5:$AC$11,Details!$C$5:$C$11,Summary!AY$5,Details!$CK$5:$CK$11,Summary!$AX$5) -> 0 | AZ12: =SUMIFS(Details!$AC$5:$AC$11,Details!$C$5:$C$11,Summary!AZ$5,Details!$CK$5:$CK$11,Summary!$AX$5) -> 0 | BA12: =SUMIFS(Details!$AC$5:$AC$11,Details!$C$5:$C$11,Summary!BA$5,Details!$CK$5:$CK$11,Summary!$AX$5) -> 0 | BB12: =SUMIFS(Details!$AC$5:$AC$11,Details!$C$5:$C$11,Summary!BB$5,Details!$CK$5:$CK$11,Summary!$AX$5) -> 0 | BC12: =SUMIFS(Details!$AC$5:$AC$11,Details!$C$5:$C$11,Summary!BC$5,Details!$CK$5:$CK$11,Summary!$AX$5) -> 0 | BD12: =SUMIFS(Details!$AC$5:$AC$11,Details!$C$5:$C$11,Summary!BD$5,Details!$CK$5:$CK$11,Summary!$AX$5) -> 0 | BE12: =SUMIFS(Details!$AC$5:$AC$11,Details!$C$5:$C$11,Summary!BE$5,Details!$CK$5:$CK$11,Summary!$AX$5) -> 0 | BF12: =SUMIFS(Details!$AC$5:$AC$11,Details!$C$5:$C$11,Summary!BF$5,Details!$CK$5:$CK$11,Summary!$AX$5) -> 0 | ... BJ12: =SUMIFS(Details!$AC$5:$AC$11,Details!$C$5:$C$11,Summary!BJ$5,Details!$CK$5:$CK$11,Summary!$AX$5) -> 0 | BK12: =SUM(AY12:BJ12) -> 0
C13: Net Margin | D13: =D9-D11-D12 -> 3460 | E13: =E9-E11-E12 -> 4080 | F13: =F9-F11-F12 -> 11050 | G13: =G9-G11-G12 -> 0 | H13: =H9-H11-H12 -> 0 | I13: =I9-I11-I12 -> 0 | J13: =J9-J11-J12 -> 0 | K13: =K9-K11-K12 -> 0 | ... P13: =P9-P11-P12 -> 18590 | T13: Net Margin | U13: =U9-U11-U12 -> 0 | V13: =V9-V11-V12 -> 0 | W13: =W9-W11-W12 -> 0 | X13: =X9-X11-X12 -> 0 | Y13: =Y9-Y11-Y12 -> 0 | Z13: =Z9-Z11-Z12 -> 0 | AA13: =AA9-AA11-AA12 -> 0 | AB13: =AB9-AB11-AB12 -> 0 | ... AG13: =AG9-AG11-AG12 -> 0 | AI13: Net Margin | AJ13: =AJ9-AJ11-AJ12 -> 0 | AK13: =AK9-AK11-AK12 -> 0 | AL13: =AL9-AL11-AL12 -> 0 | AM13: =AM9-AM11-AM12 -> 0 | AN13: =AN9-AN11-AN12 -> 0 | AO13: =AO9-AO11-AO12 -> 0 | AP13: =AP9-AP11-AP12 -> 0 | AQ13: =AQ9-AQ11-AQ12 -> 0 | ... AV13: =AV9-AV11-AV12 -> 0 | AX13: Net Margin | AY13: =AY9-AY11-AY12 -> 0 | AZ13: =AZ9-AZ11-AZ12 -> 0 | BA13: =BA9-BA11-BA12 -> 0 | BB13: =BB9-BB11-BB12 -> 0 | BC13: =BC9-BC11-BC12 -> 0 | BD13: =BD9-BD11-BD12 -> 0 | BE13: =BE9-BE11-BE12 -> 0 | BF13: =BF9-BF11-BF12 -> 0 | ... BK13: =BK9-BK11-BK12 -> 0 | BM13: =(AG13+AV13+BK13)-P13 -> -18590
C14: Net Margin (%) | D14: =IFERROR((D13/D7),0) -> 0.10529519 | E14: =IFERROR((E13/E7),0) -> 0.11663808 | F14: =IFERROR((F13/F7),0) -> 0.55388471 | G14: =IFERROR((G13/G7),0) -> 0 | H14: =IFERROR((H13/H7),0) -> 0 | I14: =IFERROR((I13/I7),0) -> 0 | J14: =IFERROR((J13/J7),0) -> 0 | K14: =IFERROR((K13/K7),0) -> 0 | ... P14: =IFERROR((P13/P7),0) -> 0.21175533 | T14: Net Margin (%) | U14: =IFERROR((U13/U7),0) -> 0 | V14: =IFERROR((V13/V7),0) -> 0 | W14: =IFERROR((W13/W7),0) -> 0 | X14: =IFERROR((X13/X7),0) -> 0 | Y14: =IFERROR((Y13/Y7),0) -> 0 | Z14: =IFERROR((Z13/Z7),0) -> 0 | AA14: =IFERROR((AA13/AA7),0) -> 0 | AB14: =IFERROR((AB13/AB7),0) -> 0 | ... AG14: =IFERROR((AG13/AG7),0) -> 0 | AI14: Net Margin (%) | AJ14: =IFERROR((AJ13/AJ7),0) -> 0 | AK14: =IFERROR((AK13/AK7),0) -> 0 | AL14: =IFERROR((AL13/AL7),0) -> 0 | AM14: =IFERROR((AM13/AM7),0) -> 0 | AN14: =IFERROR((AN13/AN7),0) -> 0 | AO14: =IFERROR((AO13/AO7),0) -> 0 | AP14: =IFERROR((AP13/AP7),0) -> 0 | AQ14: =IFERROR((AQ13/AQ7),0) -> 0 | ... AV14: =IFERROR((AV13/AV7),0) -> 0 | AX14: Net Margin (%) | AY14: =IFERROR((AY13/AY7),0) -> 0 | AZ14: =IFERROR((AZ13/AZ7),0) -> 0 | BA14: =IFERROR((BA13/BA7),0) -> 0 | BB14: =IFERROR((BB13/BB7),0) -> 0 | BC14: =IFERROR((BC13/BC7),0) -> 0 | BD14: =IFERROR((BD13/BD7),0) -> 0 | BE14: =IFERROR((BE13/BE7),0) -> 0 | BF14: =IFERROR((BF13/BF7),0) -> 0 | ... BK14: =IFERROR((BK13/BK7),0) -> 0 | BM14: =(AG14+AV14+BK14)-P14 -> -0.21175533
C15: Other Income | D15: =SUMIFS(Details!$BQ$16:$BQ$17,Details!$C$16:$C$17,Summary!D$5) -> 0 | E15: =SUMIFS(Details!$BQ$16:$BQ$17,Details!$C$16:$C$17,Summary!E$5) -> 0 | F15: =SUMIFS(Details!$BQ$16:$BQ$17,Details!$C$16:$C$17,Summary!F$5) -> 0 | G15: =SUMIFS(Details!$BQ$16:$BQ$17,Details!$C$16:$C$17,Summary!G$5) -> 0 | H15: =SUMIFS(Details!$BQ$16:$BQ$17,Details!$C$16:$C$17,Summary!H$5) -> 0 | I15: =SUMIFS(Details!$BQ$16:$BQ$17,Details!$C$16:$C$17,Summary!I$5) -> 0 | J15: =SUMIFS(Details!$BQ$16:$BQ$17,Details!$C$16:$C$17,Summary!J$5) -> 0 | K15: =SUMIFS(Details!$BQ$16:$BQ$17,Details!$C$16:$C$17,Summary!K$5) -> 0 | ... O15: =SUMIFS(Details!$BQ$16:$BQ$17,Details!$C$16:$C$17,Summary!O$5) -> 0 | P15: =SUM(D15:O15) -> 0 | T15: Other Income | U15: =SUMIFS(Details!$BQ$16:$BQ$17,Details!$C$16:$C$17,Summary!U$5,Details!$CK$16:$CK$17,Summary!$T$5) -> 0 | V15: =SUMIFS(Details!$BQ$16:$BQ$17,Details!$C$16:$C$17,Summary!V$5,Details!$CK$16:$CK$17,Summary!$T$5) -> 0 | W15: =SUMIFS(Details!$BQ$16:$BQ$17,Details!$C$16:$C$17,Summary!W$5,Details!$CK$16:$CK$17,Summary!$T$5) -> 0 | X15: =SUMIFS(Details!$BQ$16:$BQ$17,Details!$C$16:$C$17,Summary!X$5,Details!$CK$16:$CK$17,Summary!$T$5) -> 0 | Y15: =SUMIFS(Details!$BQ$16:$BQ$17,Details!$C$16:$C$17,Summary!Y$5,Details!$CK$16:$CK$17,Summary!$T$5) -> 0 | Z15: =SUMIFS(Details!$BQ$16:$BQ$17,Details!$C$16:$C$17,Summary!Z$5,Details!$CK$16:$CK$17,Summary!$T$5) -> 0 | AA15: =SUMIFS(Details!$BQ$16:$BQ$17,Details!$C$16:$C$17,Summary!AA$5,Details!$CK$16:$CK$17,Summary!$T$5) -> 0 | AB15: =SUMIFS(Details!$BQ$16:$BQ$17,Details!$C$16:$C$17,Summary!AB$5,Details!$CK$16:$CK$17,Summary!$T$5) -> 0 | ... AF15: =SUMIFS(Details!$BQ$16:$BQ$17,Details!$C$16:$C$17,Summary!AF$5,Details!$CK$16:$CK$17,Summary!$T$5) -> 0 | AG15: =SUM(U15:AF15) -> 0 | AI15: Other Income | AJ15: =SUMIFS(Details!$BQ$16:$BQ$17,Details!$C$16:$C$17,Summary!AJ$5,Details!$CK$16:$CK$17,Summary!$AI$5) -> 0 | AK15: =SUMIFS(Details!$BQ$16:$BQ$17,Details!$C$16:$C$17,Summary!AK$5,Details!$CK$16:$CK$17,Summary!$AI$5) -> 0 | AL15: =SUMIFS(Details!$BQ$16:$BQ$17,Details!$C$16:$C$17,Summary!AL$5,Details!$CK$16:$CK$17,Summary!$AI$5) -> 0 | AM15: =SUMIFS(Details!$BQ$16:$BQ$17,Details!$C$16:$C$17,Summary!AM$5,Details!$CK$16:$CK$17,Summary!$AI$5) -> 0 | AN15: =SUMIFS(Details!$BQ$16:$BQ$17,Details!$C$16:$C$17,Summary!AN$5,Details!$CK$16:$CK$17,Summary!$AI$5) -> 0 | AO15: =SUMIFS(Details!$BQ$16:$BQ$17,Details!$C$16:$C$17,Summary!AO$5,Details!$CK$16:$CK$17,Summary!$AI$5) -> 0 | AP15: =SUMIFS(Details!$BQ$16:$BQ$17,Details!$C$16:$C$17,Summary!AP$5,Details!$CK$16:$CK$17,Summary!$AI$5) -> 0 | AQ15: =SUMIFS(Details!$BQ$16:$BQ$17,Details!$C$16:$C$17,Summary!AQ$5,Details!$CK$16:$CK$17,Summary!$AI$5) -> 0 | ... AU15: =SUMIFS(Details!$BQ$16:$BQ$17,Details!$C$16:$C$17,Summary!AU$5,Details!$CK$16:$CK$17,Summary!$AI$5) -> 0 | AV15: =SUM(AJ15:AU15) -> 0 | AX15: Other Income | AY15: =SUMIFS(Details!$BQ$16:$BQ$17,Details!$C$16:$C$17,Summary!AY$5,Details!$CK$16:$CK$17,Summary!$AX$5) -> 0 | AZ15: =SUMIFS(Details!$BQ$16:$BQ$17,Details!$C$16:$C$17,Summary!AZ$5,Details!$CK$16:$CK$17,Summary!$AX$5) -> 0 | BA15: =SUMIFS(Details!$BQ$16:$BQ$17,Details!$C$16:$C$17,Summary!BA$5,Details!$CK$16:$CK$17,Summary!$AX$5) -> 0 | BB15: =SUMIFS(Details!$BQ$16:$BQ$17,Details!$C$16:$C$17,Summary!BB$5,Details!$CK$16:$CK$17,Summary!$AX$5) -> 0 | BC15: =SUMIFS(Details!$BQ$16:$BQ$17,Details!$C$16:$C$17,Summary!BC$5,Details!$CK$16:$CK$17,Summary!$AX$5) -> 0 | BD15: =SUMIFS(Details!$BQ$16:$BQ$17,Details!$C$16:$C$17,Summary!BD$5,Details!$CK$16:$CK$17,Summary!$AX$5) -> 0 | BE15: =SUMIFS(Details!$BQ$16:$BQ$17,Details!$C$16:$C$17,Summary!BE$5,Details!$CK$16:$CK$17,Summary!$AX$5) -> 0 | BF15: =SUMIFS(Details!$BQ$16:$BQ$17,Details!$C$16:$C$17,Summary!BF$5,Details!$CK$16:$CK$17,Summary!$AX$5) -> 0 | ... BJ15: =SUMIFS(Details!$BQ$16:$BQ$17,Details!$C$16:$C$17,Summary!BJ$5,Details!$CK$16:$CK$17,Summary!$AX$5) -> 0 | BK15: =SUM(AY15:BJ15) -> 0 | BM15: =(AG15+AV15+BK15)-P15 -> 0
C16: Transport Charges (%) | D16: =IFERROR((D11/D7),0) -> 0 | E16: =IFERROR((E11/E7),0) -> 0 | F16: =IFERROR((F11/F7),0) -> 0 | G16: =IFERROR((G11/G7),0) -> 0 | H16: =IFERROR((H11/H7),0) -> 0 | I16: =IFERROR((I11/I7),0) -> 0 | J16: =IFERROR((J11/J7),0) -> 0 | K16: =IFERROR((K11/K7),0) -> 0 | ... P16: =IFERROR((P11/P7),0) -> 0 | T16: Transport Charges (%) | U16: =IFERROR((U11/U7),0) -> 0 | V16: =IFERROR((V11/V7),0) -> 0 | W16: =IFERROR((W11/W7),0) -> 0 | X16: =IFERROR((X11/X7),0) -> 0 | Y16: =IFERROR((Y11/Y7),0) -> 0 | Z16: =IFERROR((Z11/Z7),0) -> 0 | AA16: =IFERROR((AA11/AA7),0) -> 0 | AB16: =IFERROR((AB11/AB7),0) -> 0 | ... AG16: =IFERROR((AG11/AG7),0) -> 0 | AI16: Transport Charges (%) | AJ16: =IFERROR((AJ11/AJ7),0) -> 0 | AK16: =IFERROR((AK11/AK7),0) -> 0 | AL16: =IFERROR((AL11/AL7),0) -> 0 | AM16: =IFERROR((AM11/AM7),0) -> 0 | AN16: =IFERROR((AN11/AN7),0) -> 0 | AO16: =IFERROR((AO11/AO7),0) -> 0 | AP16: =IFERROR((AP11/AP7),0) -> 0 | AQ16: =IFERROR((AQ11/AQ7),0) -> 0 | ... AV16: =IFERROR((AV11/AV7),0) -> 0 | AX16: Transport Charges (%) | AY16: =IFERROR((AY11/AY7),0) -> 0 | AZ16: =IFERROR((AZ11/AZ7),0) -> 0 | BA16: =IFERROR((BA11/BA7),0) -> 0 | BB16: =IFERROR((BB11/BB7),0) -> 0 | BC16: =IFERROR((BC11/BC7),0) -> 0 | BD16: =IFERROR((BD11/BD7),0) -> 0 | BE16: =IFERROR((BE11/BE7),0) -> 0 | BF16: =IFERROR((BF11/BF7),0) -> 0 | ... BK16: =IFERROR((BK11/BK7),0) -> 0 | BM16: =(AG16+AV16+BK16)-P16 -> 0
C17: Revenue Per Kg | D17: =IFERROR(D7/(D6*1000),0) -> 0.53 | E17: =IFERROR(E7/(E6*1000),0) -> 0.53 | F17: =IFERROR(F7/(F6*1000),0) -> 0.285 | G17: =IFERROR(G7/(G6*1000),0) -> 0 | H17: =IFERROR(H7/(H6*1000),0) -> 0 | I17: =IFERROR(I7/(I6*1000),0) -> 0 | J17: =IFERROR(J7/(J6*1000),0) -> 0 | K17: =IFERROR(K7/(K6*1000),0) -> 0 | ... O17: =IFERROR(O7/(O6*1000),0) -> 0 | P17: =P7/(P6*1000) -> 0.44338384 | T17: Revenue Per Kg | U17: =IFERROR(U7/(U6*1000),0) -> 0 | V17: =IFERROR(V7/(V6*1000),0) -> 0 | W17: =IFERROR(W7/(W6*1000),0) -> 0 | X17: =IFERROR(X7/(X6*1000),0) -> 0 | Y17: =IFERROR(Y7/(Y6*1000),0) -> 0 | Z17: =IFERROR(Z7/(Z6*1000),0) -> 0 | AA17: =IFERROR(AA7/(AA6*1000),0) -> 0 | AB17: =IFERROR(AB7/(AB6*1000),0) -> 0 | ... AF17: =IFERROR(AF7/(AF6*1000),0) -> 0 | AG17: =AG7/(AG6*1000) -> #DIV/0! | AI17: Revenue Per Kg | AJ17: =IFERROR(AJ7/(AJ6*1000),0) -> 0 | AK17: =IFERROR(AK7/(AK6*1000),0) -> 0 | AL17: =IFERROR(AL7/(AL6*1000),0) -> 0 | AM17: =IFERROR(AM7/(AM6*1000),0) -> 0 | AN17: =IFERROR(AN7/(AN6*1000),0) -> 0 | AO17: =IFERROR(AO7/(AO6*1000),0) -> 0 | AP17: =IFERROR(AP7/(AP6*1000),0) -> 0 | AQ17: =IFERROR(AQ7/(AQ6*1000),0) -> 0 | ... AU17: =IFERROR(AU7/(AU6*1000),0) -> 0 | AV17: =AV7/(AV6*1000) -> #DIV/0! | AX17: Revenue Per Kg | AY17: =IFERROR(AY7/(AY6*1000),0) -> 0 | AZ17: =IFERROR(AZ7/(AZ6*1000),0) -> 0 | BA17: =IFERROR(BA7/(BA6*1000),0) -> 0 | BB17: =IFERROR(BB7/(BB6*1000),0) -> 0 | BC17: =IFERROR(BC7/(BC6*1000),0) -> 0 | BD17: =IFERROR(BD7/(BD6*1000),0) -> 0 | BE17: =IFERROR(BE7/(BE6*1000),0) -> 0 | BF17: =IFERROR(BF7/(BF6*1000),0) -> 0 | ... BJ17: =IFERROR(BJ7/(BJ6*1000),0) -> 0 | BK17: =BK7/(BK6*1000) -> #DIV/0!
C18: Purchase Cost Per Kg | D18: =IFERROR(D8/(D6*1000),0) -> 0.47419355 | E18: =IFERROR(E8/(E6*1000),0) -> 0.46818182 | F18: =IFERROR(F8/(F6*1000),0) -> 0.12714286 | G18: =IFERROR(G8/(G6*1000),0) -> 0 | H18: =IFERROR(H8/(H6*1000),0) -> 0 | I18: =IFERROR(I8/(I6*1000),0) -> 0 | J18: =IFERROR(J8/(J6*1000),0) -> 0 | K18: =IFERROR(K8/(K6*1000),0) -> 0 | ... O18: =IFERROR(O8/(O6*1000),0) -> 0 | P18: =P8/(P6*1000) -> 0.34949495 | T18: Purchase Cost Per Kg | U18: =IFERROR(U8/(U6*1000),0) -> 0 | V18: =IFERROR(V8/(V6*1000),0) -> 0 | W18: =IFERROR(W8/(W6*1000),0) -> 0 | X18: =IFERROR(X8/(X6*1000),0) -> 0 | Y18: =IFERROR(Y8/(Y6*1000),0) -> 0 | Z18: =IFERROR(Z8/(Z6*1000),0) -> 0 | AA18: =IFERROR(AA8/(AA6*1000),0) -> 0 | AB18: =IFERROR(AB8/(AB6*1000),0) -> 0 | ... AF18: =IFERROR(AF8/(AF6*1000),0) -> 0 | AG18: =AG8/(AG6*1000) -> #DIV/0! | AI18: Purchase Cost Per Kg | AJ18: =IFERROR(AJ8/(AJ6*1000),0) -> 0 | AK18: =IFERROR(AK8/(AK6*1000),0) -> 0 | AL18: =IFERROR(AL8/(AL6*1000),0) -> 0 | AM18: =IFERROR(AM8/(AM6*1000),0) -> 0 | AN18: =IFERROR(AN8/(AN6*1000),0) -> 0 | AO18: =IFERROR(AO8/(AO6*1000),0) -> 0 | AP18: =IFERROR(AP8/(AP6*1000),0) -> 0 | AQ18: =IFERROR(AQ8/(AQ6*1000),0) -> 0 | ... AU18: =IFERROR(AU8/(AU6*1000),0) -> 0 | AV18: =AV8/(AV6*1000) -> #DIV/0! | AX18: Purchase Cost Per Kg | AY18: =IFERROR(AY8/(AY6*1000),0) -> 0 | AZ18: =IFERROR(AZ8/(AZ6*1000),0) -> 0 | BA18: =IFERROR(BA8/(BA6*1000),0) -> 0 | BB18: =IFERROR(BB8/(BB6*1000),0) -> 0 | BC18: =IFERROR(BC8/(BC6*1000),0) -> 0 | BD18: =IFERROR(BD8/(BD6*1000),0) -> 0 | BE18: =IFERROR(BE8/(BE6*1000),0) -> 0 | BF18: =IFERROR(BF8/(BF6*1000),0) -> 0 | ... BJ18: =IFERROR(BJ8/(BJ6*1000),0) -> 0 | BK18: =BK8/(BK6*1000) -> #DIV/0!
C19: Transportation Charges Per Kg | D19: =IFERROR(D11/(D6*1000),0) -> 0 | E19: =IFERROR(E11/(E6*1000),0) -> 0 | F19: =IFERROR(F11/(F6*1000),0) -> 0 | G19: =IFERROR(G11/(G6*1000),0) -> 0 | H19: =IFERROR(H11/(H6*1000),0) -> 0 | I19: =IFERROR(I11/(I6*1000),0) -> 0 | J19: =IFERROR(J11/(J6*1000),0) -> 0 | K19: =IFERROR(K11/(K6*1000),0) -> 0 | ... O19: =IFERROR(O11/(O6*1000),0) -> 0 | P19: =P11/(P6*1000) -> 0 | T19: Transportation Charges Per Kg | U19: =IFERROR(U11/(U6*1000),0) -> 0 | V19: =IFERROR(V11/(V6*1000),0) -> 0 | W19: =IFERROR(W11/(W6*1000),0) -> 0 | X19: =IFERROR(X11/(X6*1000),0) -> 0 | Y19: =IFERROR(Y11/(Y6*1000),0) -> 0 | Z19: =IFERROR(Z11/(Z6*1000),0) -> 0 | AA19: =IFERROR(AA11/(AA6*1000),0) -> 0 | AB19: =IFERROR(AB11/(AB6*1000),0) -> 0 | ... AF19: =IFERROR(AF11/(AF6*1000),0) -> 0 | AG19: =AG11/(AG6*1000) -> #DIV/0! | AI19: Transportation Charges Per Kg | AJ19: =IFERROR(AJ11/(AJ6*1000),0) -> 0 | AK19: =IFERROR(AK11/(AK6*1000),0) -> 0 | AL19: =IFERROR(AL11/(AL6*1000),0) -> 0 | AM19: =IFERROR(AM11/(AM6*1000),0) -> 0 | AN19: =IFERROR(AN11/(AN6*1000),0) -> 0 | AO19: =IFERROR(AO11/(AO6*1000),0) -> 0 | AP19: =IFERROR(AP11/(AP6*1000),0) -> 0 | AQ19: =IFERROR(AQ11/(AQ6*1000),0) -> 0 | ... AU19: =IFERROR(AU11/(AU6*1000),0) -> 0 | AV19: =AV11/(AV6*1000) -> #DIV/0! | AX19: Transportation Charges Per Kg | AY19: =IFERROR(AY11/(AY6*1000),0) -> 0 | AZ19: =IFERROR(AZ11/(AZ6*1000),0) -> 0 | BA19: =IFERROR(BA11/(BA6*1000),0) -> 0 | BB19: =IFERROR(BB11/(BB6*1000),0) -> 0 | BC19: =IFERROR(BC11/(BC6*1000),0) -> 0 | BD19: =IFERROR(BD11/(BD6*1000),0) -> 0 | BE19: =IFERROR(BE11/(BE6*1000),0) -> 0 | BF19: =IFERROR(BF11/(BF6*1000),0) -> 0 | ... BJ19: =IFERROR(BJ11/(BJ6*1000),0) -> 0 | BK19: =BK11/(BK6*1000) -> #DIV/0!
C20: No. of Transactions | D20: {=IFERROR(ROWS(_xlfn.UNIQUE(_xlfn._xlws.FILTER(Details!$E$5:$E$11,(Details!$C$5:$C$11)=Summary!D$3))),0)} -> 1 | E20: {=IFERROR(ROWS(_xlfn.UNIQUE(_xlfn._xlws.FILTER(Details!$E$5:$E$11,(Details!$C$5:$C$11)=Summary!E$3))),0)} -> 1 | F20: {=IFERROR(ROWS(_xlfn.UNIQUE(_xlfn._xlws.FILTER(Details!$E$5:$E$11,(Details!$C$5:$C$11)=Summary!F$3))),0)} -> 1 | G20: {=IFERROR(ROWS(_xlfn.UNIQUE(_xlfn._xlws.FILTER(Details!$E$5:$E$11,(Details!$C$5:$C$11)=Summary!G$3))),0)} -> 0 | H20: {=IFERROR(ROWS(_xlfn.UNIQUE(_xlfn._xlws.FILTER(Details!$E$5:$E$11,(Details!$C$5:$C$11)=Summary!H$3))),0)} -> 0 | I20: {=IFERROR(ROWS(_xlfn.UNIQUE(_xlfn._xlws.FILTER(Details!$E$5:$E$11,(Details!$C$5:$C$11)=Summary!I$3))),0)} -> 0 | J20: {=IFERROR(ROWS(_xlfn.UNIQUE(_xlfn._xlws.FILTER(Details!$E$5:$E$11,(Details!$C$5:$C$11)=Summary!J$3))),0)} -> 0 | K20: {=IFERROR(ROWS(_xlfn.UNIQUE(_xlfn._xlws.FILTER(Details!$E$5:$E$11,(Details!$C$5:$C$11)=Summary!K$3))),0)} -> 0 | ... O20: {=IFERROR(ROWS(_xlfn.UNIQUE(_xlfn._xlws.FILTER(Details!$E$5:$E$11,(Details!$C$5:$C$11)=Summary!O$3))),0)} -> 0 | P20: =SUM(D20:O20) -> 3 | T20: No. of Transactions | U20: {=IFERROR(ROWS(_xlfn.UNIQUE(_xlfn._xlws.FILTER(Details!$E$5:$E$11,(Details!$C$5:$C$11=Summary!U$3)*(Details!$CK$5:$CK$11=$T$5)))),0)} -> 0 | V20: {=IFERROR(ROWS(_xlfn.UNIQUE(_xlfn._xlws.FILTER(Details!$E$5:$E$11,(Details!$C$5:$C$11=Summary!V$3)*(Details!$CK$5:$CK$11=$T$5)))),0)} -> 0 | W20: {=IFERROR(ROWS(_xlfn.UNIQUE(_xlfn._xlws.FILTER(Details!$E$5:$E$11,(Details!$C$5:$C$11=Summary!W$3)*(Details!$CK$5:$CK$11=$T$5)))),0)} -> 0 | X20: {=IFERROR(ROWS(_xlfn.UNIQUE(_xlfn._xlws.FILTER(Details!$E$5:$E$11,(Details!$C$5:$C$11=Summary!X$3)*(Details!$CK$5:$CK$11=$T$5)))),0)} -> 0 | Y20: {=IFERROR(ROWS(_xlfn.UNIQUE(_xlfn._xlws.FILTER(Details!$E$5:$E$11,(Details!$C$5:$C$11=Summary!Y$3)*(Details!$CK$5:$CK$11=$T$5)))),0)} -> 0 | Z20: {=IFERROR(ROWS(_xlfn.UNIQUE(_xlfn._xlws.FILTER(Details!$E$5:$E$11,(Details!$C$5:$C$11=Summary!Z$3)*(Details!$CK$5:$CK$11=$T$5)))),0)} -> 0 | AA20: {=IFERROR(ROWS(_xlfn.UNIQUE(_xlfn._xlws.FILTER(Details!$E$5:$E$11,(Details!$C$5:$C$11=Summary!AA$3)*(Details!$CK$5:$CK$11=$T$5)))),0)} -> 0 | AB20: {=IFERROR(ROWS(_xlfn.UNIQUE(_xlfn._xlws.FILTER(Details!$E$5:$E$11,(Details!$C$5:$C$11=Summary!AB$3)*(Details!$CK$5:$CK$11=$T$5)))),0)} -> 0 | ... AF20: {=IFERROR(ROWS(_xlfn.UNIQUE(_xlfn._xlws.FILTER(Details!$E$5:$E$11,(Details!$C$5:$C$11=Summary!AF$3)*(Details!$CK$5:$CK$11=$T$5)))),0)} -> 0 | AG20: =SUM(U20:AF20) -> 0 | AI20: No. of Transactions | AJ20: {=IFERROR(ROWS(_xlfn.UNIQUE(_xlfn._xlws.FILTER(Details!$E$5:$E$11,(Details!$C$5:$C$11=Summary!AJ$3)*(Details!$CK$5:$CK$11=$AI$5)))),0)} -> 0 | AK20: {=IFERROR(ROWS(_xlfn.UNIQUE(_xlfn._xlws.FILTER(Details!$E$5:$E$11,(Details!$C$5:$C$11=Summary!AK$3)*(Details!$CK$5:$CK$11=$AI$5)))),0)} -> 0 | AL20: {=IFERROR(ROWS(_xlfn.UNIQUE(_xlfn._xlws.FILTER(Details!$E$5:$E$11,(Details!$C$5:$C$11=Summary!AL$3)*(Details!$CK$5:$CK$11=$AI$5)))),0)} -> 0 | AM20: {=IFERROR(ROWS(_xlfn.UNIQUE(_xlfn._xlws.FILTER(Details!$E$5:$E$11,(Details!$C$5:$C$11=Summary!AM$3)*(Details!$CK$5:$CK$11=$AI$5)))),0)} -> 0 | AN20: {=IFERROR(ROWS(_xlfn.UNIQUE(_xlfn._xlws.FILTER(Details!$E$5:$E$11,(Details!$C$5:$C$11=Summary!AN$3)*(Details!$CK$5:$CK$11=$AI$5)))),0)} -> 0 | AO20: {=IFERROR(ROWS(_xlfn.UNIQUE(_xlfn._xlws.FILTER(Details!$E$5:$E$11,(Details!$C$5:$C$11=Summary!AO$3)*(Details!$CK$5:$CK$11=$AI$5)))),0)} -> 0 | AP20: {=IFERROR(ROWS(_xlfn.UNIQUE(_xlfn._xlws.FILTER(Details!$E$5:$E$11,(Details!$C$5:$C$11=Summary!AP$3)*(Details!$CK$5:$CK$11=$AI$5)))),0)} -> 0 | AQ20: {=IFERROR(ROWS(_xlfn.UNIQUE(_xlfn._xlws.FILTER(Details!$E$5:$E$11,(Details!$C$5:$C$11=Summary!AQ$3)*(Details!$CK$5:$CK$11=$AI$5)))),0)} -> 0 | ... AU20: {=IFERROR(ROWS(_xlfn.UNIQUE(_xlfn._xlws.FILTER(Details!$E$5:$E$11,(Details!$C$5:$C$11=Summary!AU$3)*(Details!$CK$5:$CK$11=$AI$5)))),0)} -> 0 | AV20: =SUM(AJ20:AU20) -> 0 | AX20: No. of Transactions | AY20: {=IFERROR(ROWS(_xlfn.UNIQUE(_xlfn._xlws.FILTER(Details!$E$5:$E$11,(Details!$C$5:$C$11=Summary!AY$3)*(Details!$CK$5:$CK$11=$AX$5)))),0)} -> 0 | AZ20: {=IFERROR(ROWS(_xlfn.UNIQUE(_xlfn._xlws.FILTER(Details!$E$5:$E$11,(Details!$C$5:$C$11=Summary!AZ$3)*(Details!$CK$5:$CK$11=$AX$5)))),0)} -> 0 | BA20: {=IFERROR(ROWS(_xlfn.UNIQUE(_xlfn._xlws.FILTER(Details!$E$5:$E$11,(Details!$C$5:$C$11=Summary!BA$3)*(Details!$CK$5:$CK$11=$AX$5)))),0)} -> 0 | BB20: {=IFERROR(ROWS(_xlfn.UNIQUE(_xlfn._xlws.FILTER(Details!$E$5:$E$11,(Details!$C$5:$C$11=Summary!BB$3)*(Details!$CK$5:$CK$11=$AX$5)))),0)} -> 0 | BC20: {=IFERROR(ROWS(_xlfn.UNIQUE(_xlfn._xlws.FILTER(Details!$E$5:$E$11,(Details!$C$5:$C$11=Summary!BC$3)*(Details!$CK$5:$CK$11=$AX$5)))),0)} -> 0 | BD20: {=IFERROR(ROWS(_xlfn.UNIQUE(_xlfn._xlws.FILTER(Details!$E$5:$E$11,(Details!$C$5:$C$11=Summary!BD$3)*(Details!$CK$5:$CK$11=$AX$5)))),0)} -> 0 | BE20: {=IFERROR(ROWS(_xlfn.UNIQUE(_xlfn._xlws.FILTER(Details!$E$5:$E$11,(Details!$C$5:$C$11=Summary!BE$3)*(Details!$CK$5:$CK$11=$AX$5)))),0)} -> 0 | BF20: {=IFERROR(ROWS(_xlfn.UNIQUE(_xlfn._xlws.FILTER(Details!$E$5:$E$11,(Details!$C$5:$C$11=Summary!BF$3)*(Details!$CK$5:$CK$11=$AX$5)))),0)} -> 0 | ... BJ20: {=IFERROR(ROWS(_xlfn.UNIQUE(_xlfn._xlws.FILTER(Details!$E$5:$E$11,(Details!$C$5:$C$11=Summary!BJ$3)*(Details!$CK$5:$CK$11=$AX$5)))),0)} -> 0 | BK20: =SUM(AY20:BJ20) -> 0 | BM20: =(AG20+AV20+BK20)-P20 -> -3
C21: No. of Sellers (Aggregators) | D21: {=IFERROR(ROWS(_xlfn.UNIQUE(_xlfn._xlws.FILTER(Details!$F$5:$F$11,(Details!$C$5:$C$11)=Summary!D$3))),0)} -> 1 | E21: {=IFERROR(ROWS(_xlfn.UNIQUE(_xlfn._xlws.FILTER(Details!$F$5:$F$11,(Details!$C$5:$C$11)=Summary!E$3))),0)} -> 1 | F21: {=IFERROR(ROWS(_xlfn.UNIQUE(_xlfn._xlws.FILTER(Details!$F$5:$F$11,(Details!$C$5:$C$11)=Summary!F$3))),0)} -> 1 | G21: {=IFERROR(ROWS(_xlfn.UNIQUE(_xlfn._xlws.FILTER(Details!$F$5:$F$11,(Details!$C$5:$C$11)=Summary!G$3))),0)} -> 0 | H21: {=IFERROR(ROWS(_xlfn.UNIQUE(_xlfn._xlws.FILTER(Details!$F$5:$F$11,(Details!$C$5:$C$11)=Summary!H$3))),0)} -> 0 | I21: {=IFERROR(ROWS(_xlfn.UNIQUE(_xlfn._xlws.FILTER(Details!$F$5:$F$11,(Details!$C$5:$C$11)=Summary!I$3))),0)} -> 0 | J21: {=IFERROR(ROWS(_xlfn.UNIQUE(_xlfn._xlws.FILTER(Details!$F$5:$F$11,(Details!$C$5:$C$11)=Summary!J$3))),0)} -> 0 | K21: {=IFERROR(ROWS(_xlfn.UNIQUE(_xlfn._xlws.FILTER(Details!$F$5:$F$11,(Details!$C$5:$C$11)=Summary!K$3))),0)} -> 0 | ... O21: {=IFERROR(ROWS(_xlfn.UNIQUE(_xlfn._xlws.FILTER(Details!$F$5:$F$11,(Details!$C$5:$C$11)=Summary!O$3))),0)} -> 0 | P21: ='Supplier Metrics'!J2 -> 1 | T21: No. of Sellers (Aggregators) | U21: {=IFERROR(ROWS(_xlfn.UNIQUE(_xlfn._xlws.FILTER(Details!$F$5:$F$11,(Details!$C$5:$C$11=Summary!U$3)*(Details!$CK$5:$CK$11=$T$5)))),0)} -> 0 | V21: {=IFERROR(ROWS(_xlfn.UNIQUE(_xlfn._xlws.FILTER(Details!$F$5:$F$11,(Details!$C$5:$C$11=Summary!V$3)*(Details!$CK$5:$CK$11=$T$5)))),0)} -> 0 | W21: {=IFERROR(ROWS(_xlfn.UNIQUE(_xlfn._xlws.FILTER(Details!$F$5:$F$11,(Details!$C$5:$C$11=Summary!W$3)*(Details!$CK$5:$CK$11=$T$5)))),0)} -> 0 | X21: {=IFERROR(ROWS(_xlfn.UNIQUE(_xlfn._xlws.FILTER(Details!$F$5:$F$11,(Details!$C$5:$C$11=Summary!X$3)*(Details!$CK$5:$CK$11=$T$5)))),0)} -> 0 | Y21: {=IFERROR(ROWS(_xlfn.UNIQUE(_xlfn._xlws.FILTER(Details!$F$5:$F$11,(Details!$C$5:$C$11=Summary!Y$3)*(Details!$CK$5:$CK$11=$T$5)))),0)} -> 0 | Z21: {=IFERROR(ROWS(_xlfn.UNIQUE(_xlfn._xlws.FILTER(Details!$F$5:$F$11,(Details!$C$5:$C$11=Summary!Z$3)*(Details!$CK$5:$CK$11=$T$5)))),0)} -> 0 | AA21: {=IFERROR(ROWS(_xlfn.UNIQUE(_xlfn._xlws.FILTER(Details!$F$5:$F$11,(Details!$C$5:$C$11=Summary!AA$3)*(Details!$CK$5:$CK$11=$T$5)))),0)} -> 0 | AB21: {=IFERROR(ROWS(_xlfn.UNIQUE(_xlfn._xlws.FILTER(Details!$F$5:$F$11,(Details!$C$5:$C$11=Summary!AB$3)*(Details!$CK$5:$CK$11=$T$5)))),0)} -> 0 | ... AF21: {=IFERROR(ROWS(_xlfn.UNIQUE(_xlfn._xlws.FILTER(Details!$F$5:$F$11,(Details!$C$5:$C$11=Summary!AF$3)*(Details!$CK$5:$CK$11=$T$5)))),0)} -> 0 | AG21: =COUNTIF('Supplier Metrics'!I:I,Summary!T5) -> 0 | AI21: No. of Sellers (Aggregators) | AJ21: {=IFERROR(ROWS(_xlfn.UNIQUE(_xlfn._xlws.FILTER(Details!$F$5:$F$11,(Details!$C$5:$C$11=Summary!AJ$3)*(Details!$CK$5:$CK$11=$AI$5)))),0)} -> 0 | AK21: {=IFERROR(ROWS(_xlfn.UNIQUE(_xlfn._xlws.FILTER(Details!$F$5:$F$11,(Details!$C$5:$C$11=Summary!AK$3)*(Details!$CK$5:$CK$11=$AI$5)))),0)} -> 0 | AL21: {=IFERROR(ROWS(_xlfn.UNIQUE(_xlfn._xlws.FILTER(Details!$F$5:$F$11,(Details!$C$5:$C$11=Summary!AL$3)*(Details!$CK$5:$CK$11=$AI$5)))),0)} -> 0 | AM21: {=IFERROR(ROWS(_xlfn.UNIQUE(_xlfn._xlws.FILTER(Details!$F$5:$F$11,(Details!$C$5:$C$11=Summary!AM$3)*(Details!$CK$5:$CK$11=$AI$5)))),0)} -> 0 | AN21: {=IFERROR(ROWS(_xlfn.UNIQUE(_xlfn._xlws.FILTER(Details!$F$5:$F$11,(Details!$C$5:$C$11=Summary!AN$3)*(Details!$CK$5:$CK$11=$AI$5)))),0)} -> 0 | AO21: {=IFERROR(ROWS(_xlfn.UNIQUE(_xlfn._xlws.FILTER(Details!$F$5:$F$11,(Details!$C$5:$C$11=Summary!AO$3)*(Details!$CK$5:$CK$11=$AI$5)))),0)} -> 0 | AP21: {=IFERROR(ROWS(_xlfn.UNIQUE(_xlfn._xlws.FILTER(Details!$F$5:$F$11,(Details!$C$5:$C$11=Summary!AP$3)*(Details!$CK$5:$CK$11=$AI$5)))),0)} -> 0 | AQ21: {=IFERROR(ROWS(_xlfn.UNIQUE(_xlfn._xlws.FILTER(Details!$F$5:$F$11,(Details!$C$5:$C$11=Summary!AQ$3)*(Details!$CK$5:$CK$11=$AI$5)))),0)} -> 0 | ... AU21: {=IFERROR(ROWS(_xlfn.UNIQUE(_xlfn._xlws.FILTER(Details!$F$5:$F$11,(Details!$C$5:$C$11=Summary!AU$3)*(Details!$CK$5:$CK$11=$AI$5)))),0)} -> 0 | AV21: =COUNTIF('Supplier Metrics'!I:I,Summary!AI5) -> 0 | AX21: No. of Sellers (Aggregators) | AY21: {=IFERROR(ROWS(_xlfn.UNIQUE(_xlfn._xlws.FILTER(Details!$F$5:$F$11,(Details!$C$5:$C$11=Summary!AY$3)*(Details!$CK$5:$CK$11=$AX$5)))),0)} -> 0 | AZ21: {=IFERROR(ROWS(_xlfn.UNIQUE(_xlfn._xlws.FILTER(Details!$F$5:$F$11,(Details!$C$5:$C$11=Summary!AZ$3)*(Details!$CK$5:$CK$11=$AX$5)))),0)} -> 0 | BA21: {=IFERROR(ROWS(_xlfn.UNIQUE(_xlfn._xlws.FILTER(Details!$F$5:$F$11,(Details!$C$5:$C$11=Summary!BA$3)*(Details!$CK$5:$CK$11=$AX$5)))),0)} -> 0 | BB21: {=IFERROR(ROWS(_xlfn.UNIQUE(_xlfn._xlws.FILTER(Details!$F$5:$F$11,(Details!$C$5:$C$11=Summary!BB$3)*(Details!$CK$5:$CK$11=$AX$5)))),0)} -> 0 | BC21: {=IFERROR(ROWS(_xlfn.UNIQUE(_xlfn._xlws.FILTER(Details!$F$5:$F$11,(Details!$C$5:$C$11=Summary!BC$3)*(Details!$CK$5:$CK$11=$AX$5)))),0)} -> 0 | BD21: {=IFERROR(ROWS(_xlfn.UNIQUE(_xlfn._xlws.FILTER(Details!$F$5:$F$11,(Details!$C$5:$C$11=Summary!BD$3)*(Details!$CK$5:$CK$11=$AX$5)))),0)} -> 0 | BE21: {=IFERROR(ROWS(_xlfn.UNIQUE(_xlfn._xlws.FILTER(Details!$F$5:$F$11,(Details!$C$5:$C$11=Summary!BE$3)*(Details!$CK$5:$CK$11=$AX$5)))),0)} -> 0 | BF21: {=IFERROR(ROWS(_xlfn.UNIQUE(_xlfn._xlws.FILTER(Details!$F$5:$F$11,(Details!$C$5:$C$11=Summary!BF$3)*(Details!$CK$5:$CK$11=$AX$5)))),0)} -> 0 | ... BJ21: {=IFERROR(ROWS(_xlfn.UNIQUE(_xlfn._xlws.FILTER(Details!$F$5:$F$11,(Details!$C$5:$C$11=Summary!BJ$3)*(Details!$CK$5:$CK$11=$AX$5)))),0)} -> 0 | BK21: =COUNTIF('Supplier Metrics'!I:I,Summary!AX5) -> 0 | BM21: =(AG21+AV21+BK21)-P21 -> -1
C22: No. of Buyers (Recyclers) | D22: {=IFERROR(ROWS(_xlfn.UNIQUE(_xlfn._xlws.FILTER(Details!$AQ$5:$AQ$11,(Details!$C$5:$C$11)=Summary!D$3))),0)} -> 1 | E22: {=IFERROR(ROWS(_xlfn.UNIQUE(_xlfn._xlws.FILTER(Details!$AQ$5:$AQ$11,(Details!$C$5:$C$11)=Summary!E$3))),0)} -> 1 | F22: {=IFERROR(ROWS(_xlfn.UNIQUE(_xlfn._xlws.FILTER(Details!$AQ$5:$AQ$11,(Details!$C$5:$C$11)=Summary!F$3))),0)} -> 1 | G22: {=IFERROR(ROWS(_xlfn.UNIQUE(_xlfn._xlws.FILTER(Details!$AQ$5:$AQ$11,(Details!$C$5:$C$11)=Summary!G$3))),0)} -> 0 | H22: {=IFERROR(ROWS(_xlfn.UNIQUE(_xlfn._xlws.FILTER(Details!$AQ$5:$AQ$11,(Details!$C$5:$C$11)=Summary!H$3))),0)} -> 0 | I22: {=IFERROR(ROWS(_xlfn.UNIQUE(_xlfn._xlws.FILTER(Details!$AQ$5:$AQ$11,(Details!$C$5:$C$11)=Summary!I$3))),0)} -> 0 | J22: {=IFERROR(ROWS(_xlfn.UNIQUE(_xlfn._xlws.FILTER(Details!$AQ$5:$AQ$11,(Details!$C$5:$C$11)=Summary!J$3))),0)} -> 0 | K22: {=IFERROR(ROWS(_xlfn.UNIQUE(_xlfn._xlws.FILTER(Details!$AQ$5:$AQ$11,(Details!$C$5:$C$11)=Summary!K$3))),0)} -> 0 | ... O22: {=IFERROR(ROWS(_xlfn.UNIQUE(_xlfn._xlws.FILTER(Details!$AQ$5:$AQ$11,(Details!$C$5:$C$11)=Summary!O$3))),0)} -> 0 | P22: ='Buyer Metrics'!C3 -> 1 | T22: No. of Buyers (Recyclers) | U22: {=IFERROR(ROWS(_xlfn.UNIQUE(_xlfn._xlws.FILTER(Details!$AQ$5:$AQ$11,(Details!$C$5:$C$11=Summary!U$3)*(Details!$CK$5:$CK$11=$T$5)))),0)} -> 0 | V22: {=IFERROR(ROWS(_xlfn.UNIQUE(_xlfn._xlws.FILTER(Details!$AQ$5:$AQ$11,(Details!$C$5:$C$11=Summary!V$3)*(Details!$CK$5:$CK$11=$T$5)))),0)} -> 0 | W22: {=IFERROR(ROWS(_xlfn.UNIQUE(_xlfn._xlws.FILTER(Details!$AQ$5:$AQ$11,(Details!$C$5:$C$11=Summary!W$3)*(Details!$CK$5:$CK$11=$T$5)))),0)} -> 0 | X22: {=IFERROR(ROWS(_xlfn.UNIQUE(_xlfn._xlws.FILTER(Details!$AQ$5:$AQ$11,(Details!$C$5:$C$11=Summary!X$3)*(Details!$CK$5:$CK$11=$T$5)))),0)} -> 0 | Y22: {=IFERROR(ROWS(_xlfn.UNIQUE(_xlfn._xlws.FILTER(Details!$AQ$5:$AQ$11,(Details!$C$5:$C$11=Summary!Y$3)*(Details!$CK$5:$CK$11=$T$5)))),0)} -> 0 | Z22: {=IFERROR(ROWS(_xlfn.UNIQUE(_xlfn._xlws.FILTER(Details!$AQ$5:$AQ$11,(Details!$C$5:$C$11=Summary!Z$3)*(Details!$CK$5:$CK$11=$T$5)))),0)} -> 0 | AA22: {=IFERROR(ROWS(_xlfn.UNIQUE(_xlfn._xlws.FILTER(Details!$AQ$5:$AQ$11,(Details!$C$5:$C$11=Summary!AA$3)*(Details!$CK$5:$CK$11=$T$5)))),0)} -> 0 | AB22: {=IFERROR(ROWS(_xlfn.UNIQUE(_xlfn._xlws.FILTER(Details!$AQ$5:$AQ$11,(Details!$C$5:$C$11=Summary!AB$3)*(Details!$CK$5:$CK$11=$T$5)))),0)} -> 0 | ... AF22: {=IFERROR(ROWS(_xlfn.UNIQUE(_xlfn._xlws.FILTER(Details!$AQ$5:$AQ$11,(Details!$C$5:$C$11=Summary!AF$3)*(Details!$CK$5:$CK$11=$T$5)))),0)} -> 0 | AG22: =COUNTIFS('Buyer Metrics'!F:F,Summary!T5) -> 0 | AI22: No. of Buyers (Recyclers) | AJ22: {=IFERROR(ROWS(_xlfn.UNIQUE(_xlfn._xlws.FILTER(Details!$AQ$5:$AQ$11,(Details!$C$5:$C$11=Summary!AJ$3)*(Details!$CK$5:$CK$11=$AI$5)))),0)} -> 0 | AK22: {=IFERROR(ROWS(_xlfn.UNIQUE(_xlfn._xlws.FILTER(Details!$AQ$5:$AQ$11,(Details!$C$5:$C$11=Summary!AK$3)*(Details!$CK$5:$CK$11=$AI$5)))),0)} -> 0 | AL22: {=IFERROR(ROWS(_xlfn.UNIQUE(_xlfn._xlws.FILTER(Details!$AQ$5:$AQ$11,(Details!$C$5:$C$11=Summary!AL$3)*(Details!$CK$5:$CK$11=$AI$5)))),0)} -> 0 | AM22: {=IFERROR(ROWS(_xlfn.UNIQUE(_xlfn._xlws.FILTER(Details!$AQ$5:$AQ$11,(Details!$C$5:$C$11=Summary!AM$3)*(Details!$CK$5:$CK$11=$AI$5)))),0)} -> 0 | AN22: {=IFERROR(ROWS(_xlfn.UNIQUE(_xlfn._xlws.FILTER(Details!$AQ$5:$AQ$11,(Details!$C$5:$C$11=Summary!AN$3)*(Details!$CK$5:$CK$11=$AI$5)))),0)} -> 0 | AO22: {=IFERROR(ROWS(_xlfn.UNIQUE(_xlfn._xlws.FILTER(Details!$AQ$5:$AQ$11,(Details!$C$5:$C$11=Summary!AO$3)*(Details!$CK$5:$CK$11=$AI$5)))),0)} -> 0 | AP22: {=IFERROR(ROWS(_xlfn.UNIQUE(_xlfn._xlws.FILTER(Details!$AQ$5:$AQ$11,(Details!$C$5:$C$11=Summary!AP$3)*(Details!$CK$5:$CK$11=$AI$5)))),0)} -> 0 | AQ22: {=IFERROR(ROWS(_xlfn.UNIQUE(_xlfn._xlws.FILTER(Details!$AQ$5:$AQ$11,(Details!$C$5:$C$11=Summary!AQ$3)*(Details!$CK$5:$CK$11=$AI$5)))),0)} -> 0 | ... AU22: {=IFERROR(ROWS(_xlfn.UNIQUE(_xlfn._xlws.FILTER(Details!$AQ$5:$AQ$11,(Details!$C$5:$C$11=Summary!AU$3)*(Details!$CK$5:$CK$11=$AI$5)))),0)} -> 0 | AV22: =COUNTIFS('Buyer Metrics'!F:F,Summary!AI5) -> 0 | AX22: No. of Buyers (Recyclers) | AY22: {=IFERROR(ROWS(_xlfn.UNIQUE(_xlfn._xlws.FILTER(Details!$AQ$5:$AQ$11,(Details!$C$5:$C$11=Summary!AY$3)*(Details!$CK$5:$CK$11=$AX$5)))),0)} -> 0 | AZ22: {=IFERROR(ROWS(_xlfn.UNIQUE(_xlfn._xlws.FILTER(Details!$AQ$5:$AQ$11,(Details!$C$5:$C$11=Summary!AZ$3)*(Details!$CK$5:$CK$11=$AX$5)))),0)} -> 0 | BA22: {=IFERROR(ROWS(_xlfn.UNIQUE(_xlfn._xlws.FILTER(Details!$AQ$5:$AQ$11,(Details!$C$5:$C$11=Summary!BA$3)*(Details!$CK$5:$CK$11=$AX$5)))),0)} -> 0 | BB22: {=IFERROR(ROWS(_xlfn.UNIQUE(_xlfn._xlws.FILTER(Details!$AQ$5:$AQ$11,(Details!$C$5:$C$11=Summary!BB$3)*(Details!$CK$5:$CK$11=$AX$5)))),0)} -> 0 | BC22: {=IFERROR(ROWS(_xlfn.UNIQUE(_xlfn._xlws.FILTER(Details!$AQ$5:$AQ$11,(Details!$C$5:$C$11=Summary!BC$3)*(Details!$CK$5:$CK$11=$AX$5)))),0)} -> 0 | BD22: {=IFERROR(ROWS(_xlfn.UNIQUE(_xlfn._xlws.FILTER(Details!$AQ$5:$AQ$11,(Details!$C$5:$C$11=Summary!BD$3)*(Details!$CK$5:$CK$11=$AX$5)))),0)} -> 0 | BE22: {=IFERROR(ROWS(_xlfn.UNIQUE(_xlfn._xlws.FILTER(Details!$AQ$5:$AQ$11,(Details!$C$5:$C$11=Summary!BE$3)*(Details!$CK$5:$CK$11=$AX$5)))),0)} -> 0 | BF22: {=IFERROR(ROWS(_xlfn.UNIQUE(_xlfn._xlws.FILTER(Details!$AQ$5:$AQ$11,(Details!$C$5:$C$11=Summary!BF$3)*(Details!$CK$5:$CK$11=$AX$5)))),0)} -> 0 | ... BJ22: {=IFERROR(ROWS(_xlfn.UNIQUE(_xlfn._xlws.FILTER(Details!$AQ$5:$AQ$11,(Details!$C$5:$C$11=Summary!BJ$3)*(Details!$CK$5:$CK$11=$AX$5)))),0)} -> 0 | BK22: =COUNTIFS('Buyer Metrics'!F:F,Summary!AX5) -> 0 | BM22: =(AG22+AV22+BK22)-P22 -> -1
C23: Full Rejection | D23: {=IFERROR(ROWS(_xlfn.UNIQUE(_xlfn._xlws.FILTER(Details!$E$5:$E$11,(Details!$C$5:$C$11=Summary!D$3)*(Details!$BT$5:$BT$11=$C$23)))),0)} -> 0 | E23: {=IFERROR(ROWS(_xlfn.UNIQUE(_xlfn._xlws.FILTER(Details!$E$5:$E$11,(Details!$C$5:$C$11=Summary!E$3)*(Details!$BT$5:$BT$11=$C$23)))),0)} -> 0 | F23: {=IFERROR(ROWS(_xlfn.UNIQUE(_xlfn._xlws.FILTER(Details!$E$5:$E$11,(Details!$C$5:$C$11=Summary!F$3)*(Details!$BT$5:$BT$11=$C$23)))),0)} -> 0 | G23: {=IFERROR(ROWS(_xlfn.UNIQUE(_xlfn._xlws.FILTER(Details!$E$5:$E$11,(Details!$C$5:$C$11=Summary!G$3)*(Details!$BT$5:$BT$11=$C$23)))),0)} -> 0 | H23: {=IFERROR(ROWS(_xlfn.UNIQUE(_xlfn._xlws.FILTER(Details!$E$5:$E$11,(Details!$C$5:$C$11=Summary!H$3)*(Details!$BT$5:$BT$11=$C$23)))),0)} -> 0 | I23: {=IFERROR(ROWS(_xlfn.UNIQUE(_xlfn._xlws.FILTER(Details!$E$5:$E$11,(Details!$C$5:$C$11=Summary!I$3)*(Details!$BT$5:$BT$11=$C$23)))),0)} -> 0 | J23: {=IFERROR(ROWS(_xlfn.UNIQUE(_xlfn._xlws.FILTER(Details!$E$5:$E$11,(Details!$C$5:$C$11=Summary!J$3)*(Details!$BT$5:$BT$11=$C$23)))),0)} -> 0 | K23: {=IFERROR(ROWS(_xlfn.UNIQUE(_xlfn._xlws.FILTER(Details!$E$5:$E$11,(Details!$C$5:$C$11=Summary!K$3)*(Details!$BT$5:$BT$11=$C$23)))),0)} -> 0 | ... O23: {=IFERROR(ROWS(_xlfn.UNIQUE(_xlfn._xlws.FILTER(Details!$E$5:$E$11,(Details!$C$5:$C$11=Summary!O$3)*(Details!$BT$5:$BT$11=$C$23)))),0)} -> 0 | P23: =SUM(D23:O23) -> 0 | T23: Full Rejection | U23: {=IFERROR(ROWS(_xlfn.UNIQUE(_xlfn._xlws.FILTER(Details!$E$5:$E$11,(Details!$C$5:$C$11=Summary!U$3)*(Details!$BT$5:$BT$11=$C$23)*(Details!$CK$5:$CK$11=$T$5)))),0)} -> 0 | V23: {=IFERROR(ROWS(_xlfn.UNIQUE(_xlfn._xlws.FILTER(Details!$E$5:$E$11,(Details!$C$5:$C$11=Summary!V$3)*(Details!$BT$5:$BT$11=$C$23)*(Details!$CK$5:$CK$11=$T$5)))),0)} -> 0 | W23: {=IFERROR(ROWS(_xlfn.UNIQUE(_xlfn._xlws.FILTER(Details!$E$5:$E$11,(Details!$C$5:$C$11=Summary!W$3)*(Details!$BT$5:$BT$11=$C$23)*(Details!$CK$5:$CK$11=$T$5)))),0)} -> 0 | X23: {=IFERROR(ROWS(_xlfn.UNIQUE(_xlfn._xlws.FILTER(Details!$E$5:$E$11,(Details!$C$5:$C$11=Summary!X$3)*(Details!$BT$5:$BT$11=$C$23)*(Details!$CK$5:$CK$11=$T$5)))),0)} -> 0 | Y23: {=IFERROR(ROWS(_xlfn.UNIQUE(_xlfn._xlws.FILTER(Details!$E$5:$E$11,(Details!$C$5:$C$11=Summary!Y$3)*(Details!$BT$5:$BT$11=$C$23)*(Details!$CK$5:$CK$11=$T$5)))),0)} -> 0 | Z23: {=IFERROR(ROWS(_xlfn.UNIQUE(_xlfn._xlws.FILTER(Details!$E$5:$E$11,(Details!$C$5:$C$11=Summary!Z$3)*(Details!$BT$5:$BT$11=$C$23)*(Details!$CK$5:$CK$11=$T$5)))),0)} -> 0 | AA23: {=IFERROR(ROWS(_xlfn.UNIQUE(_xlfn._xlws.FILTER(Details!$E$5:$E$11,(Details!$C$5:$C$11=Summary!AA$3)*(Details!$BT$5:$BT$11=$C$23)*(Details!$CK$5:$CK$11=$T$5)))),0)} -> 0 | AB23: {=IFERROR(ROWS(_xlfn.UNIQUE(_xlfn._xlws.FILTER(Details!$E$5:$E$11,(Details!$C$5:$C$11=Summary!AB$3)*(Details!$BT$5:$BT$11=$C$23)*(Details!$CK$5:$CK$11=$T$5)))),0)} -> 0 | ... AF23: {=IFERROR(ROWS(_xlfn.UNIQUE(_xlfn._xlws.FILTER(Details!$E$5:$E$11,(Details!$C$5:$C$11=Summary!AF$3)*(Details!$BT$5:$BT$11=$C$23)*(Details!$CK$5:$CK$11=$T$5)))),0)} -> 0 | AG23: =SUM(U23:AF23) -> 0 | AI23: Full Rejection | AJ23: {=IFERROR(ROWS(_xlfn.UNIQUE(_xlfn._xlws.FILTER(Details!$E$5:$E$11,(Details!$C$5:$C$11=Summary!AJ$3)*(Details!$BT$5:$BT$11=$C$23)*(Details!$CK$5:$CK$11=$AI$5)))),0)} -> 0 | AK23: {=IFERROR(ROWS(_xlfn.UNIQUE(_xlfn._xlws.FILTER(Details!$E$5:$E$11,(Details!$C$5:$C$11=Summary!AK$3)*(Details!$BT$5:$BT$11=$C$23)*(Details!$CK$5:$CK$11=$AI$5)))),0)} -> 0 | AL23: {=IFERROR(ROWS(_xlfn.UNIQUE(_xlfn._xlws.FILTER(Details!$E$5:$E$11,(Details!$C$5:$C$11=Summary!AL$3)*(Details!$BT$5:$BT$11=$C$23)*(Details!$CK$5:$CK$11=$AI$5)))),0)} -> 0 | AM23: {=IFERROR(ROWS(_xlfn.UNIQUE(_xlfn._xlws.FILTER(Details!$E$5:$E$11,(Details!$C$5:$C$11=Summary!AM$3)*(Details!$BT$5:$BT$11=$C$23)*(Details!$CK$5:$CK$11=$AI$5)))),0)} -> 0 | AN23: {=IFERROR(ROWS(_xlfn.UNIQUE(_xlfn._xlws.FILTER(Details!$E$5:$E$11,(Details!$C$5:$C$11=Summary!AN$3)*(Details!$BT$5:$BT$11=$C$23)*(Details!$CK$5:$CK$11=$AI$5)))),0)} -> 0 | AO23: {=IFERROR(ROWS(_xlfn.UNIQUE(_xlfn._xlws.FILTER(Details!$E$5:$E$11,(Details!$C$5:$C$11=Summary!AO$3)*(Details!$BT$5:$BT$11=$C$23)*(Details!$CK$5:$CK$11=$AI$5)))),0)} -> 0 | AP23: {=IFERROR(ROWS(_xlfn.UNIQUE(_xlfn._xlws.FILTER(Details!$E$5:$E$11,(Details!$C$5:$C$11=Summary!AP$3)*(Details!$BT$5:$BT$11=$C$23)*(Details!$CK$5:$CK$11=$AI$5)))),0)} -> 0 | AQ23: {=IFERROR(ROWS(_xlfn.UNIQUE(_xlfn._xlws.FILTER(Details!$E$5:$E$11,(Details!$C$5:$C$11=Summary!AQ$3)*(Details!$BT$5:$BT$11=$C$23)*(Details!$CK$5:$CK$11=$AI$5)))),0)} -> 0 | ... AU23: {=IFERROR(ROWS(_xlfn.UNIQUE(_xlfn._xlws.FILTER(Details!$E$5:$E$11,(Details!$C$5:$C$11=Summary!AU$3)*(Details!$BT$5:$BT$11=$C$23)*(Details!$CK$5:$CK$11=$AI$5)))),0)} -> 0 | AV23: =SUM(AJ23:AU23) -> 0 | AX23: Full Rejection | AY23: {=IFERROR(ROWS(_xlfn.UNIQUE(_xlfn._xlws.FILTER(Details!$E$5:$E$11,(Details!$C$5:$C$11=Summary!AY$3)*(Details!$BT$5:$BT$11=$C$23)*(Details!$CK$5:$CK$11=$AX$5)))),0)} -> 0 | AZ23: {=IFERROR(ROWS(_xlfn.UNIQUE(_xlfn._xlws.FILTER(Details!$E$5:$E$11,(Details!$C$5:$C$11=Summary!AZ$3)*(Details!$BT$5:$BT$11=$C$23)*(Details!$CK$5:$CK$11=$AX$5)))),0)} -> 0 | BA23: {=IFERROR(ROWS(_xlfn.UNIQUE(_xlfn._xlws.FILTER(Details!$E$5:$E$11,(Details!$C$5:$C$11=Summary!BA$3)*(Details!$BT$5:$BT$11=$C$23)*(Details!$CK$5:$CK$11=$AX$5)))),0)} -> 0 | BB23: {=IFERROR(ROWS(_xlfn.UNIQUE(_xlfn._xlws.FILTER(Details!$E$5:$E$11,(Details!$C$5:$C$11=Summary!BB$3)*(Details!$BT$5:$BT$11=$C$23)*(Details!$CK$5:$CK$11=$AX$5)))),0)} -> 0 | BC23: {=IFERROR(ROWS(_xlfn.UNIQUE(_xlfn._xlws.FILTER(Details!$E$5:$E$11,(Details!$C$5:$C$11=Summary!BC$3)*(Details!$BT$5:$BT$11=$C$23)*(Details!$CK$5:$CK$11=$AX$5)))),0)} -> 0 | BD23: {=IFERROR(ROWS(_xlfn.UNIQUE(_xlfn._xlws.FILTER(Details!$E$5:$E$11,(Details!$C$5:$C$11=Summary!BD$3)*(Details!$BT$5:$BT$11=$C$23)*(Details!$CK$5:$CK$11=$AX$5)))),0)} -> 0 | BE23: {=IFERROR(ROWS(_xlfn.UNIQUE(_xlfn._xlws.FILTER(Details!$E$5:$E$11,(Details!$C$5:$C$11=Summary!BE$3)*(Details!$BT$5:$BT$11=$C$23)*(Details!$CK$5:$CK$11=$AX$5)))),0)} -> 0 | BF23: {=IFERROR(ROWS(_xlfn.UNIQUE(_xlfn._xlws.FILTER(Details!$E$5:$E$11,(Details!$C$5:$C$11=Summary!BF$3)*(Details!$BT$5:$BT$11=$C$23)*(Details!$CK$5:$CK$11=$AX$5)))),0)} -> 0 | ... BJ23: {=IFERROR(ROWS(_xlfn.UNIQUE(_xlfn._xlws.FILTER(Details!$E$5:$E$11,(Details!$C$5:$C$11=Summary!BJ$3)*(Details!$BT$5:$BT$11=$C$23)*(Details!$CK$5:$CK$11=$AX$5)))),0)} -> 0 | BK23: =SUM(AY23:BJ23) -> 0 | BM23: =(AG23+AV23+BK23)-P23 -> 0
C24: Receivable (Exl Legacy) | D24: 173686.02 | E24: 177992.52 | F24: 198939.52 | G24: 0 | H24: 0 | I24: 0 | J24: 0 | K24: 0 | L24: 0 | M24: 0 | N24: 0 | O24: 0 | P24: =F24 -> 198939.52 | T24: Receivable (Exl Legacy) | AF24: 0 | AG24: =AVERAGE(U24:AE24) -> #DIV/0! | AI24: Receivable (Exl Legacy) | AU24: 0 | AV24: =AVERAGE(AJ24:AT24) -> #DIV/0! | AX24: Receivable (Exl Legacy) | BJ24: 0 | BK24: =AVERAGE(AY24:BI24) -> #DIV/0!
C25: DSO (Days) | D25: =IFERROR(((D24/(D7*1.18))*D4),0) -> 134.38059 | E25: =IFERROR(((E24/(E7*1.18))*E4),0) -> 133.67852 | F25: =IFERROR(((F24/(F7*1.18))*F4),0) -> 118.31075 | G25: =IFERROR(((G24/(G7*1.18))*G4),0) -> 0 | H25: =IFERROR(((H24/(H7*1.18))*H4),0) -> 0 | I25: =IFERROR(((I24/(I7*1.18))*I4),0) -> 0 | J25: =IFERROR(((J24/(J7*1.18))*J4),0) -> 0 | K25: =IFERROR(((K24/(K7*1.18))*K4),0) -> 0 | ... P25: =IFERROR(((P24/(P7*1.18))*P4),0) -> 144.03077 | T25: DSO (Days) | U25: =IFERROR(((U24/(U7*1.18))*U4),0) -> 0 | V25: =IFERROR(((V24/(V7*1.18))*V4),0) -> 0 | W25: =IFERROR(((W24/(W7*1.18))*W4),0) -> 0 | X25: =IFERROR(((X24/(X7*1.18))*X4),0) -> 0 | Y25: =IFERROR(((Y24/(Y7*1.18))*Y4),0) -> 0 | Z25: =IFERROR(((Z24/(Z7*1.18))*Z4),0) -> 0 | AA25: =IFERROR(((AA24/(AA7*1.18))*AA4),0) -> 0 | AB25: =IFERROR(((AB24/(AB7*1.18))*AB4),0) -> 0 | ... AG25: =IFERROR(((AG24/(AG7*1.18))*AG4),0) -> 0 | AI25: DSO (Days) | AJ25: =IFERROR(((AJ24/(AJ7*1.18))*AJ4),0) -> 0 | AK25: =IFERROR(((AK24/(AK7*1.18))*AK4),0) -> 0 | AL25: =IFERROR(((AL24/(AL7*1.18))*AL4),0) -> 0 | AM25: =IFERROR(((AM24/(AM7*1.18))*AM4),0) -> 0 | AN25: =IFERROR(((AN24/(AN7*1.18))*AN4),0) -> 0 | AO25: =IFERROR(((AO24/(AO7*1.18))*AO4),0) -> 0 | AP25: =IFERROR(((AP24/(AP7*1.18))*AP4),0) -> 0 | AQ25: =IFERROR(((AQ24/(AQ7*1.18))*AQ4),0) -> 0 | ... AV25: =IFERROR(((AV24/(AV7*1.18))*AV4),0) -> 0 | AX25: DSO (Days) | AY25: =IFERROR(((AY24/(AY7*1.18))*AY4),0) -> 0 | AZ25: =IFERROR(((AZ24/(AZ7*1.18))*AZ4),0) -> 0 | BA25: =IFERROR(((BA24/(BA7*1.18))*BA4),0) -> 0 | BB25: =IFERROR(((BB24/(BB7*1.18))*BB4),0) -> 0 | BC25: =IFERROR(((BC24/(BC7*1.18))*BC4),0) -> 0 | BD25: =IFERROR(((BD24/(BD7*1.18))*BD4),0) -> 0 | BE25: =IFERROR(((BE24/(BE7*1.18))*BE4),0) -> 0 | BF25: =IFERROR(((BF24/(BF7*1.18))*BF4),0) -> 0 | ... BK25: =IFERROR(((BK24/(BK7*1.18))*BK4),0) -> 0
C26: Payable | D26: 77779 | E26: 73167.89 | F26: 82512.89 | G26: 0 | H26: 0 | I26: 0 | J26: 0 | K26: 0 | L26: 0 | M26: 0 | N26: 0 | O26: 0 | P26: =F26 -> 82512.89 | T26: Payable | AG26: =AVERAGE(U26:AE26) -> #DIV/0! | AI26: Payable | AX26: Payable
C27: DPO (Days) | D27: =IFERROR(((D26/(D8*1.18))*D4),0) -> 67.259599 | E27: =IFERROR(((E26/(E8*1.18))*E4),0) -> 62.207355 | F27: =IFERROR(((F26/(F8*1.18))*F4),0) -> 109.99624 | G27: =IFERROR(((G26/(G8*1.18))*G4),0) -> 0 | H27: =IFERROR(((H26/(H8*1.18))*H4),0) -> 0 | I27: =IFERROR(((I26/(I8*1.18))*I4),0) -> 0 | J27: =IFERROR(((J26/(J8*1.18))*J4),0) -> 0 | K27: =IFERROR(((K26/(K8*1.18))*K4),0) -> 0 | ... P27: =IFERROR(((P26/(P8*1.18))*P4),0) -> 75.787043 | T27: DPO (Days) | AI27: DPO (Days) | AX27: DPO (Days)
C28: Working Capital Days | D28: =D25-D27 -> 67.120994 | E28: =E25-E27 -> 71.471166 | F28: =F25-F27 -> 8.3145114 | G28: =G25-G27 -> 0 | H28: =H25-H27 -> 0 | I28: =I25-I27 -> 0 | J28: =J25-J27 -> 0 | K28: =K25-K27 -> 0 | ... P28: =P25-P27 -> 68.243724
C29: Credit Notes (Value - Incl. Prov) | D29: =-SUMIFS(Details!$BY$5:$BY$11,Details!$C$5:$C$11,Summary!D$5) -> 0 | E29: =-SUMIFS(Details!$BY$5:$BY$11,Details!$C$5:$C$11,Summary!E$5) -> 0 | F29: =-SUMIFS(Details!$BY$5:$BY$11,Details!$C$5:$C$11,Summary!F$5) -> 0 | G29: =-SUMIFS(Details!$BY$5:$BY$11,Details!$C$5:$C$11,Summary!G$5) -> 0 | H29: =-SUMIFS(Details!$BY$5:$BY$11,Details!$C$5:$C$11,Summary!H$5) -> 0 | I29: =-SUMIFS(Details!$BY$5:$BY$11,Details!$C$5:$C$11,Summary!I$5) -> 0 | J29: =-SUMIFS(Details!$BY$5:$BY$11,Details!$C$5:$C$11,Summary!J$5) -> 0 | K29: =-SUMIFS(Details!$BY$5:$BY$11,Details!$C$5:$C$11,Summary!K$5) -> 0 | ... O29: =-SUMIFS(Details!$BY$5:$BY$11,Details!$C$5:$C$11,Summary!O$5) -> 0 | P29: =SUM(D29:O29) -> 0 | Q29: =(-Details!BO12-Details!BP12) -> 0 | R29: =P29-Q29 -> 0 | T29: Credit Notes (Value - Incl. Prov) | U29: =-SUMIFS(Details!$BY$5:$BY$11,Details!$C$5:$C$11,Summary!U$5,Details!$CK$5:$CK$11,Summary!$T$5) -> 0 | V29: =-SUMIFS(Details!$BY$5:$BY$11,Details!$C$5:$C$11,Summary!V$5,Details!$CK$5:$CK$11,Summary!$T$5) -> 0 | W29: =-SUMIFS(Details!$BY$5:$BY$11,Details!$C$5:$C$11,Summary!W$5,Details!$CK$5:$CK$11,Summary!$T$5) -> 0 | X29: =-SUMIFS(Details!$BY$5:$BY$11,Details!$C$5:$C$11,Summary!X$5,Details!$CK$5:$CK$11,Summary!$T$5) -> 0 | Y29: =-SUMIFS(Details!$BY$5:$BY$11,Details!$C$5:$C$11,Summary!Y$5,Details!$CK$5:$CK$11,Summary!$T$5) -> 0 | Z29: =-SUMIFS(Details!$BY$5:$BY$11,Details!$C$5:$C$11,Summary!Z$5,Details!$CK$5:$CK$11,Summary!$T$5) -> 0 | AA29: =-SUMIFS(Details!$BY$5:$BY$11,Details!$C$5:$C$11,Summary!AA$5,Details!$CK$5:$CK$11,Summary!$T$5) -> 0 | AB29: =-SUMIFS(Details!$BY$5:$BY$11,Details!$C$5:$C$11,Summary!AB$5,Details!$CK$5:$CK$11,Summary!$T$5) -> 0 | ... AF29: =-SUMIFS(Details!$BY$5:$BY$11,Details!$C$5:$C$11,Summary!AF$5,Details!$CK$5:$CK$11,Summary!$T$5) -> 0 | AG29: =SUM(U29:AF29) -> 0 | AI29: Credit Notes (Value - Incl. Prov) | AJ29: =-SUMIFS(Details!$BY$5:$BY$11,Details!$C$5:$C$11,Summary!AJ$5,Details!$CK$5:$CK$11,Summary!$AI$5) -> 0 | AK29: =-SUMIFS(Details!$BY$5:$BY$11,Details!$C$5:$C$11,Summary!AK$5,Details!$CK$5:$CK$11,Summary!$AI$5) -> 0 | AL29: =-SUMIFS(Details!$BY$5:$BY$11,Details!$C$5:$C$11,Summary!AL$5,Details!$CK$5:$CK$11,Summary!$AI$5) -> 0 | AM29: =-SUMIFS(Details!$BY$5:$BY$11,Details!$C$5:$C$11,Summary!AM$5,Details!$CK$5:$CK$11,Summary!$AI$5) -> 0 | AN29: =-SUMIFS(Details!$BY$5:$BY$11,Details!$C$5:$C$11,Summary!AN$5,Details!$CK$5:$CK$11,Summary!$AI$5) -> 0 | AO29: =-SUMIFS(Details!$BY$5:$BY$11,Details!$C$5:$C$11,Summary!AO$5,Details!$CK$5:$CK$11,Summary!$AI$5) -> 0 | AP29: =-SUMIFS(Details!$BY$5:$BY$11,Details!$C$5:$C$11,Summary!AP$5,Details!$CK$5:$CK$11,Summary!$AI$5) -> 0 | AQ29: =-SUMIFS(Details!$BY$5:$BY$11,Details!$C$5:$C$11,Summary!AQ$5,Details!$CK$5:$CK$11,Summary!$AI$5) -> 0 | ... AU29: =-SUMIFS(Details!$BY$5:$BY$11,Details!$C$5:$C$11,Summary!AU$5,Details!$CK$5:$CK$11,Summary!$AI$5) -> 0 | AV29: =SUM(AJ29:AU29) -> 0 | AX29: Credit Notes (Value - Incl. Prov) | AY29: =-SUMIFS(Details!$BY$5:$BY$11,Details!$C$5:$C$11,Summary!AY$5,Details!$CK$5:$CK$11,Summary!$AX$5) -> 0 | AZ29: =-SUMIFS(Details!$BY$5:$BY$11,Details!$C$5:$C$11,Summary!AZ$5,Details!$CK$5:$CK$11,Summary!$AX$5) -> 0 | BA29: =-SUMIFS(Details!$BY$5:$BY$11,Details!$C$5:$C$11,Summary!BA$5,Details!$CK$5:$CK$11,Summary!$AX$5) -> 0 | BB29: =-SUMIFS(Details!$BY$5:$BY$11,Details!$C$5:$C$11,Summary!BB$5,Details!$CK$5:$CK$11,Summary!$AX$5) -> 0 | BC29: =-SUMIFS(Details!$BY$5:$BY$11,Details!$C$5:$C$11,Summary!BC$5,Details!$CK$5:$CK$11,Summary!$AX$5) -> 0 | BD29: =-SUMIFS(Details!$BY$5:$BY$11,Details!$C$5:$C$11,Summary!BD$5,Details!$CK$5:$CK$11,Summary!$AX$5) -> 0 | BE29: =-SUMIFS(Details!$BY$5:$BY$11,Details!$C$5:$C$11,Summary!BE$5,Details!$CK$5:$CK$11,Summary!$AX$5) -> 0 | BF29: =-SUMIFS(Details!$BY$5:$BY$11,Details!$C$5:$C$11,Summary!BF$5,Details!$CK$5:$CK$11,Summary!$AX$5) -> 0 | ... BJ29: =-SUMIFS(Details!$BY$5:$BY$11,Details!$C$5:$C$11,Summary!BJ$5,Details!$CK$5:$CK$11,Summary!$AX$5) -> 0 | BK29: =SUM(AY29:BJ29) -> 0 | BM29: =(AG29+AV29+BK29)-P29 -> 0
C30: Credit Notes (% to Revenue) | D30: =IFERROR((D29/D7),0) -> 0 | E30: =IFERROR((E29/E7),0) -> 0 | F30: =IFERROR((F29/F7),0) -> 0 | G30: =IFERROR((G29/G7),0) -> 0 | H30: =IFERROR((H29/H7),0) -> 0 | I30: =IFERROR((I29/I7),0) -> 0 | J30: =IFERROR((J29/J7),0) -> 0 | K30: =IFERROR((K29/K7),0) -> 0 | ... O30: =IFERROR((O29/O7),0) -> 0 | P30: =P29/P7 -> 0 | R30: =P30-Q30 -> 0 | T30: Credit Notes (% to Revenue) | U30: =U29/U7 -> #DIV/0! | V30: =V29/V7 -> #DIV/0! | W30: =W29/W7 -> #DIV/0! | X30: =X29/X7 -> #DIV/0! | Y30: =Y29/Y7 -> #DIV/0! | Z30: =Z29/Z7 -> #DIV/0! | AA30: =AA29/AA7 -> #DIV/0! | AB30: =AB29/AB7 -> #DIV/0! | ... AG30: =AG29/AG7 -> #DIV/0! | AI30: Credit Notes (% to Revenue) | AJ30: =AJ29/AJ7 -> #DIV/0! | AK30: =AK29/AK7 -> #DIV/0! | AL30: =AL29/AL7 -> #DIV/0! | AM30: =AM29/AM7 -> #DIV/0! | AN30: =AN29/AN7 -> #DIV/0! | AO30: =AO29/AO7 -> #DIV/0! | AP30: =AP29/AP7 -> #DIV/0! | AQ30: =AQ29/AQ7 -> #DIV/0! | ... AV30: =AV29/AV7 -> #DIV/0! | AX30: Credit Notes (% to Revenue) | AY30: =AY29/AY7 -> #DIV/0! | AZ30: =AZ29/AZ7 -> #DIV/0! | BA30: =BA29/BA7 -> #DIV/0! | BB30: =BB29/BB7 -> #DIV/0! | BC30: =BC29/BC7 -> #DIV/0! | BD30: =BD29/BD7 -> #DIV/0! | BE30: =BE29/BE7 -> #DIV/0! | BF30: =BF29/BF7 -> #DIV/0! | ... BK30: =BK29/BK7 -> #DIV/0!
C31: Debit Notes (Value - Incl. Prov) | D31: =-SUMIFS(Details!$BZ$5:$BZ$11,Details!$C$5:$C$11,Summary!D$5) -> 0 | E31: =-SUMIFS(Details!$BZ$5:$BZ$11,Details!$C$5:$C$11,Summary!E$5) -> 0 | F31: =-SUMIFS(Details!$BZ$5:$BZ$11,Details!$C$5:$C$11,Summary!F$5) -> 0 | G31: =-SUMIFS(Details!$BZ$5:$BZ$11,Details!$C$5:$C$11,Summary!G$5) -> 0 | H31: =-SUMIFS(Details!$BZ$5:$BZ$11,Details!$C$5:$C$11,Summary!H$5) -> 0 | I31: =-SUMIFS(Details!$BZ$5:$BZ$11,Details!$C$5:$C$11,Summary!I$5) -> 0 | J31: =-SUMIFS(Details!$BZ$5:$BZ$11,Details!$C$5:$C$11,Summary!J$5) -> 0 | K31: =-SUMIFS(Details!$BZ$5:$BZ$11,Details!$C$5:$C$11,Summary!K$5) -> 0 | ... O31: =-SUMIFS(Details!$BZ$5:$BZ$11,Details!$C$5:$C$11,Summary!O$5) -> 0 | P31: =SUM(D31:O31) -> 0 | Q31: =(-Details!AK12-Details!AL12) -> 0 | R31: =P31-Q31 -> 0 | T31: Debit Notes (Value - Incl. Prov) | U31: =-SUMIFS(Details!$BZ$5:$BZ$11,Details!$C$5:$C$11,Summary!U$5,Details!$CK$5:$CK$11,Summary!$T$5) -> 0 | V31: =-SUMIFS(Details!$BZ$5:$BZ$11,Details!$C$5:$C$11,Summary!V$5,Details!$CK$5:$CK$11,Summary!$T$5) -> 0 | W31: =-SUMIFS(Details!$BZ$5:$BZ$11,Details!$C$5:$C$11,Summary!W$5,Details!$CK$5:$CK$11,Summary!$T$5) -> 0 | X31: =-SUMIFS(Details!$BZ$5:$BZ$11,Details!$C$5:$C$11,Summary!X$5,Details!$CK$5:$CK$11,Summary!$T$5) -> 0 | Y31: =-SUMIFS(Details!$BZ$5:$BZ$11,Details!$C$5:$C$11,Summary!Y$5,Details!$CK$5:$CK$11,Summary!$T$5) -> 0 | Z31: =-SUMIFS(Details!$BZ$5:$BZ$11,Details!$C$5:$C$11,Summary!Z$5,Details!$CK$5:$CK$11,Summary!$T$5) -> 0 | AA31: =-SUMIFS(Details!$BZ$5:$BZ$11,Details!$C$5:$C$11,Summary!AA$5,Details!$CK$5:$CK$11,Summary!$T$5) -> 0 | AB31: =-SUMIFS(Details!$BZ$5:$BZ$11,Details!$C$5:$C$11,Summary!AB$5,Details!$CK$5:$CK$11,Summary!$T$5) -> 0 | ... AF31: =-SUMIFS(Details!$BZ$5:$BZ$11,Details!$C$5:$C$11,Summary!AF$5,Details!$CK$5:$CK$11,Summary!$T$5) -> 0 | AG31: =SUM(U31:AF31) -> 0 | AI31: Debit Notes (Value - Incl. Prov) | AJ31: =-SUMIFS(Details!$BZ$5:$BZ$11,Details!$C$5:$C$11,Summary!AJ$5,Details!$CK$5:$CK$11,Summary!$AI$5) -> 0 | AK31: =-SUMIFS(Details!$BZ$5:$BZ$11,Details!$C$5:$C$11,Summary!AK$5,Details!$CK$5:$CK$11,Summary!$AI$5) -> 0 | AL31: =-SUMIFS(Details!$BZ$5:$BZ$11,Details!$C$5:$C$11,Summary!AL$5,Details!$CK$5:$CK$11,Summary!$AI$5) -> 0 | AM31: =-SUMIFS(Details!$BZ$5:$BZ$11,Details!$C$5:$C$11,Summary!AM$5,Details!$CK$5:$CK$11,Summary!$AI$5) -> 0 | AN31: =-SUMIFS(Details!$BZ$5:$BZ$11,Details!$C$5:$C$11,Summary!AN$5,Details!$CK$5:$CK$11,Summary!$AI$5) -> 0 | AO31: =-SUMIFS(Details!$BZ$5:$BZ$11,Details!$C$5:$C$11,Summary!AO$5,Details!$CK$5:$CK$11,Summary!$AI$5) -> 0 | AP31: =-SUMIFS(Details!$BZ$5:$BZ$11,Details!$C$5:$C$11,Summary!AP$5,Details!$CK$5:$CK$11,Summary!$AI$5) -> 0 | AQ31: =-SUMIFS(Details!$BZ$5:$BZ$11,Details!$C$5:$C$11,Summary!AQ$5,Details!$CK$5:$CK$11,Summary!$AI$5) -> 0 | ... AU31: =-SUMIFS(Details!$BZ$5:$BZ$11,Details!$C$5:$C$11,Summary!AU$5,Details!$CK$5:$CK$11,Summary!$AI$5) -> 0 | AV31: =SUM(AJ31:AU31) -> 0 | AX31: Debit Notes (Value - Incl. Prov) | AY31: =-SUMIFS(Details!$BZ$5:$BZ$11,Details!$C$5:$C$11,Summary!AY$5,Details!$CK$5:$CK$11,Summary!$AX$5) -> 0 | AZ31: =-SUMIFS(Details!$BZ$5:$BZ$11,Details!$C$5:$C$11,Summary!AZ$5,Details!$CK$5:$CK$11,Summary!$AX$5) -> 0 | BA31: =-SUMIFS(Details!$BZ$5:$BZ$11,Details!$C$5:$C$11,Summary!BA$5,Details!$CK$5:$CK$11,Summary!$AX$5) -> 0 | BB31: =-SUMIFS(Details!$BZ$5:$BZ$11,Details!$C$5:$C$11,Summary!BB$5,Details!$CK$5:$CK$11,Summary!$AX$5) -> 0 | BC31: =-SUMIFS(Details!$BZ$5:$BZ$11,Details!$C$5:$C$11,Summary!BC$5,Details!$CK$5:$CK$11,Summary!$AX$5) -> 0 | BD31: =-SUMIFS(Details!$BZ$5:$BZ$11,Details!$C$5:$C$11,Summary!BD$5,Details!$CK$5:$CK$11,Summary!$AX$5) -> 0 | BE31: =-SUMIFS(Details!$BZ$5:$BZ$11,Details!$C$5:$C$11,Summary!BE$5,Details!$CK$5:$CK$11,Summary!$AX$5) -> 0 | BF31: =-SUMIFS(Details!$BZ$5:$BZ$11,Details!$C$5:$C$11,Summary!BF$5,Details!$CK$5:$CK$11,Summary!$AX$5) -> 0 | ... BJ31: =-SUMIFS(Details!$BZ$5:$BZ$11,Details!$C$5:$C$11,Summary!BJ$5,Details!$CK$5:$CK$11,Summary!$AX$5) -> 0 | BK31: =SUM(AY31:BJ31) -> 0 | BM31: =(AG31+AV31+BK31)-P31 -> 0
C32: Debit Notes (% to Purchase) | D32: =IFERROR((D31/D8),0) -> 0 | E32: =IFERROR((E31/E8),0) -> 0 | F32: =IFERROR((F31/F8),0) -> 0 | G32: =IFERROR((G31/G8),0) -> 0 | H32: =IFERROR((H31/H8),0) -> 0 | I32: =IFERROR((I31/I8),0) -> 0 | J32: =IFERROR((J31/J8),0) -> 0 | K32: =IFERROR((K31/K8),0) -> 0 | ... O32: =IFERROR((O31/O8),0) -> 0 | P32: =P31/P8 -> 0 | T32: Debit Notes (% to Purchase) | U32: =U31/U8 -> #DIV/0! | V32: =V31/V8 -> #DIV/0! | W32: =W31/W8 -> #DIV/0! | X32: =X31/X8 -> #DIV/0! | Y32: =Y31/Y8 -> #DIV/0! | Z32: =Z31/Z8 -> #DIV/0! | AA32: =AA31/AA8 -> #DIV/0! | AB32: =AB31/AB8 -> #DIV/0! | ... AG32: =AG31/AG8 -> #DIV/0! | AI32: Debit Notes (% to Purchase) | AJ32: =AJ31/AJ8 -> #DIV/0! | AK32: =AK31/AK8 -> #DIV/0! | AL32: =AL31/AL8 -> #DIV/0! | AM32: =AM31/AM8 -> #DIV/0! | AN32: =AN31/AN8 -> #DIV/0! | AO32: =AO31/AO8 -> #DIV/0! | AP32: =AP31/AP8 -> #DIV/0! | AQ32: =AQ31/AQ8 -> #DIV/0! | ... AV32: =AV31/AV8 -> #DIV/0! | AX32: Debit Notes (% to Purchase) | AY32: =AY31/AY8 -> #DIV/0! | AZ32: =AZ31/AZ8 -> #DIV/0! | BA32: =BA31/BA8 -> #DIV/0! | BB32: =BB31/BB8 -> #DIV/0! | BC32: =BC31/BC8 -> #DIV/0! | BD32: =BD31/BD8 -> #DIV/0! | BE32: =BE31/BE8 -> #DIV/0! | BF32: =BF31/BF8 -> #DIV/0! | ... BK32: =BK31/BK8 -> #DIV/0!
C34: KPI's without Provisions | D34: =D5 -> 46113 | E34: =E5 -> 46143 | F34: =F5 -> 46174 | G34: =G5 -> 46204 | H34: =H5 -> 46235 | I34: =I5 -> 46266 | J34: =J5 -> 46296 | K34: =K5 -> 46327 | ... P34: =P5 -> FY 2026-27 | T34: KPI's without Provisions | U34: =U5 -> 46113 | V34: =V5 -> 46143 | W34: =W5 -> 46174 | X34: =X5 -> 46204 | Y34: =Y5 -> 46235 | Z34: =Z5 -> 46266 | AA34: =AA5 -> 46296 | AB34: =AB5 -> 46327 | ... AG34: =AG5 -> FY 2026-27 | AI34: KPI's without Provisions | AJ34: =AJ5 -> 46113 | AK34: =AK5 -> 46143 | AL34: =AL5 -> 46174 | AM34: =AM5 -> 46204 | AN34: =AN5 -> 46235 | AO34: =AO5 -> 46266 | AP34: =AP5 -> 46296 | AQ34: =AQ5 -> 46327 | ... AV34: =AV5 -> FY 2026-27 | AX34: KPI's without Provisions | AY34: =AY5 -> 46113 | AZ34: =AZ5 -> 46143 | BA34: =BA5 -> 46174 | BB34: =BB5 -> 46204 | BC34: =BC5 -> 46235 | BD34: =BD5 -> 46266 | BE34: =BE5 -> 46296 | BF34: =BF5 -> 46327 | ... BK34: =BK5 -> FY 2026-27
C35: Sales without Provision | D35: =D7+D54 -> 32860 | E35: =E7+E54 -> 34980 | F35: =F7+F54 -> 19950 | G35: =G7+G54 -> 0 | H35: =H7+H54 -> 0 | I35: =I7+I54 -> 0 | J35: =J7+J54 -> 0 | K35: =K7+K54 -> 0 | ... O35: =O7+O54 -> 0 | P35: =SUM(D35:O35) -> 87790 | T35: Sales without Provision | U35: =U7+U48 -> 0 | V35: =V7+V48 -> 0 | W35: =W7+W48 -> 0 | X35: =X7+X48 -> 0 | Y35: =Y7+Y48 -> 0 | Z35: =Z7+Z48 -> 0 | AA35: =AA7+AA48 -> 0 | AB35: =AB7+AB48 -> 0 | ... AF35: =AF7+AF48 -> 0 | AG35: =SUM(U35:AF35) -> 0 | AI35: Sales without Provision | AJ35: =AJ7+AJ48 -> 0 | AK35: =AK7+AK48 -> 0 | AL35: =AL7+AL48 -> 0 | AM35: =AM7+AM48 -> 0 | AN35: =AN7+AN48 -> 0 | AO35: =AO7+AO48 -> 0 | AP35: =AP7+AP48 -> 0 | AQ35: =AQ7+AQ48 -> 0 | ... AU35: =AU7+AU48 -> 0 | AV35: =SUM(AJ35:AU35) -> 0 | AX35: Sales without Provision | AY35: =AY7+AY48 -> 0 | AZ35: =AZ7+AZ48 -> 0 | BA35: =BA7+BA48 -> 0 | BB35: =BB7+BB48 -> 0 | BC35: =BC7+BC48 -> 0 | BD35: =BD7+BD48 -> 0 | BE35: =BE7+BE48 -> 0 | BF35: =BF7+BF48 -> 0 | ... BJ35: =BJ7+BJ48 -> 0 | BK35: =SUM(AY35:BJ35) -> 0 | BM35: =(AG35+AV35+BK35)-P35 -> -87790
C36: Purchases without Provision | D36: =D8+D53+D11 -> 29400 | E36: =E8+E53+E11 -> 30900 | F36: =F8+F53+F11 -> 8900 | G36: =G8+G53+G11 -> 0 | H36: =H8+H53+H11 -> 0 | I36: =I8+I53+I11 -> 0 | J36: =J8+J53+J11 -> 0 | K36: =K8+K53+K11 -> 0 | ... O36: =O8+O53+O11 -> 0 | P36: =SUM(D36:O36) -> 69200 | T36: Purchases without Provision | U36: =U8+U47+U11 -> 0 | V36: =V8+V47+V11 -> 0 | W36: =W8+W47+W11 -> 0 | X36: =X8+X47+X11 -> 0 | Y36: =Y8+Y47+Y11 -> 0 | Z36: =Z8+Z47+Z11 -> 0 | AA36: =AA8+AA47+AA11 -> 0 | AB36: =AB8+AB47+AB11 -> 0 | ... AF36: =AF8+AF47+AF11 -> 0 | AG36: =SUM(U36:AF36) -> 0 | AI36: Purchases without Provision | AJ36: =AJ8+AJ47+AJ11 -> 0 | AK36: =AK8+AK47+AK11 -> 0 | AL36: =AL8+AL47+AL11 -> 0 | AM36: =AM8+AM47+AM11 -> 0 | AN36: =AN8+AN47+AN11 -> 0 | AO36: =AO8+AO47+AO11 -> 0 | AP36: =AP8+AP47+AP11 -> 0 | AQ36: =AQ8+AQ47+AQ11 -> 0 | ... AU36: =AU8+AU47+AU11 -> 0 | AV36: =SUM(AJ36:AU36) -> 0 | AX36: Purchases without Provision | AY36: =AY8+AY47+AY11 -> 0 | AZ36: =AZ8+AZ47+AZ11 -> 0 | BA36: =BA8+BA47+BA11 -> 0 | BB36: =BB8+BB47+BB11 -> 0 | BC36: =BC8+BC47+BC11 -> 0 | BD36: =BD8+BD47+BD11 -> 0 | BE36: =BE8+BE47+BE11 -> 0 | BF36: =BF8+BF47+BF11 -> 0 | ... BJ36: =BJ8+BJ47+BJ11 -> 0 | BK36: =SUM(AY36:BJ36) -> 0 | BM36: =(AG36+AV36+BK36)-P36 -> -69200
C37: Contribution without Provision | D37: =D35-D36 -> 3460 | E37: =E35-E36 -> 4080 | F37: =F35-F36 -> 11050 | G37: =G35-G36 -> 0 | H37: =H35-H36 -> 0 | I37: =I35-I36 -> 0 | J37: =J35-J36 -> 0 | K37: =K35-K36 -> 0 | ... P37: =P35-P36 -> 18590 | T37: Contribution without Provision | U37: =U35-U36 -> 0 | V37: =V35-V36 -> 0 | W37: =W35-W36 -> 0 | X37: =X35-X36 -> 0 | Y37: =Y35-Y36 -> 0 | Z37: =Z35-Z36 -> 0 | AA37: =AA35-AA36 -> 0 | AB37: =AB35-AB36 -> 0 | ... AG37: =AG35-AG36 -> 0 | AI37: Contribution without Provision | AJ37: =AJ35-AJ36 -> 0 | AK37: =AK35-AK36 -> 0 | AL37: =AL35-AL36 -> 0 | AM37: =AM35-AM36 -> 0 | AN37: =AN35-AN36 -> 0 | AO37: =AO35-AO36 -> 0 | AP37: =AP35-AP36 -> 0 | AQ37: =AQ35-AQ36 -> 0 | ... AV37: =AV35-AV36 -> 0 | AX37: Contribution without Provision | AY37: =AY35-AY36 -> 0 | AZ37: =AZ35-AZ36 -> 0 | BA37: =BA35-BA36 -> 0 | BB37: =BB35-BB36 -> 0 | BC37: =BC35-BC36 -> 0 | BD37: =BD35-BD36 -> 0 | BE37: =BE35-BE36 -> 0 | BF37: =BF35-BF36 -> 0 | ... BK37: =BK35-BK36 -> 0
C38: Contribution (%) | D38: =D37/D35 -> 0.10529519 | E38: =E37/E35 -> 0.11663808 | F38: =F37/F35 -> 0.55388471 | G38: =G37/G35 -> #DIV/0! | H38: =H37/H35 -> #DIV/0! | I38: =I37/I35 -> #DIV/0! | J38: =J37/J35 -> #DIV/0! | K38: =K37/K35 -> #DIV/0! | ... P38: =P37/P35 -> 0.21175533 | T38: Contribution (%) | U38: =U37/U35 -> #DIV/0! | V38: =V37/V35 -> #DIV/0! | W38: =W37/W35 -> #DIV/0! | X38: =X37/X35 -> #DIV/0! | Y38: =Y37/Y35 -> #DIV/0! | Z38: =Z37/Z35 -> #DIV/0! | AA38: =AA37/AA35 -> #DIV/0! | AB38: =AB37/AB35 -> #DIV/0! | ... AG38: =AG37/AG35 -> #DIV/0! | AI38: Contribution (%) | AJ38: =AJ37/AJ35 -> #DIV/0! | AK38: =AK37/AK35 -> #DIV/0! | AL38: =AL37/AL35 -> #DIV/0! | AM38: =AM37/AM35 -> #DIV/0! | AN38: =AN37/AN35 -> #DIV/0! | AO38: =AO37/AO35 -> #DIV/0! | AP38: =AP37/AP35 -> #DIV/0! | AQ38: =AQ37/AQ35 -> #DIV/0! | ... AV38: =AV37/AV35 -> #DIV/0! | AX38: Contribution (%) | AY38: =AY37/AY35 -> #DIV/0! | AZ38: =AZ37/AZ35 -> #DIV/0! | BA38: =BA37/BA35 -> #DIV/0! | BB38: =BB37/BB35 -> #DIV/0! | BC38: =BC37/BC35 -> #DIV/0! | BD38: =BD37/BD35 -> #DIV/0! | BE38: =BE37/BE35 -> #DIV/0! | BF38: =BF37/BF35 -> #DIV/0! | ... BK38: =BK37/BK35 -> #DIV/0!
C40: Business Trends | D40: =D5 -> 46113 | E40: =E5 -> 46143 | F40: =F5 -> 46174 | G40: =G5 -> 46204 | H40: =H5 -> 46235 | I40: =I5 -> 46266 | J40: =J5 -> 46296 | K40: =K5 -> 46327 | ... P40: =P5 -> FY 2026-27 | T40: Business Trends | U40: =U5 -> 46113 | V40: =V5 -> 46143 | W40: =W5 -> 46174 | X40: =X5 -> 46204 | Y40: =Y5 -> 46235 | Z40: =Z5 -> 46266 | AA40: =AA5 -> 46296 | AB40: =AB5 -> 46327 | ... AG40: =AG5 -> FY 2026-27 | AI40: Business Trends | AJ40: =AJ5 -> 46113 | AK40: =AK5 -> 46143 | AL40: =AL5 -> 46174 | AM40: =AM5 -> 46204 | AN40: =AN5 -> 46235 | AO40: =AO5 -> 46266 | AP40: =AP5 -> 46296 | AQ40: =AQ5 -> 46327 | ... AV40: =AV5 -> FY 2026-27 | AX40: Business Trends | AY40: =AY5 -> 46113 | AZ40: =AZ5 -> 46143 | BA40: =BA5 -> 46174 | BB40: =BB5 -> 46204 | BC40: =BC5 -> 46235 | BD40: =BD5 -> 46266 | BE40: =BE5 -> 46296 | BF40: =BF5 -> 46327 | ... BK40: =BK5 -> FY 2026-27
C41: Sales-Revenue (MoM) | D41: =IFERROR(((D7/C7)-1),0) -> 0 | E41: =IFERROR(((E7/D7)-1),0) -> 0.064516129 | F41: =IFERROR(((F7/E7)-1),0) -> -0.4296741 | G41: =IFERROR(((G7/F7)-1),0) -> -1 | H41: =IFERROR(((H7/G7)-1),0) -> 0 | I41: =IFERROR(((I7/H7)-1),0) -> 0 | J41: =IFERROR(((J7/I7)-1),0) -> 0 | K41: =IFERROR(((K7/J7)-1),0) -> 0 | ... O41: =IFERROR(((O7/N7)-1),0) -> 0 | P41: 0 | T41: Sales-Revenue (MoM) | U41: =IFERROR(((U7/T7)-1),0) -> 0 | V41: =IFERROR(((V7/U7)-1),0) -> 0 | W41: =IFERROR(((W7/V7)-1),0) -> 0 | X41: =IFERROR(((X7/W7)-1),0) -> 0 | Y41: =IFERROR(((Y7/X7)-1),0) -> 0 | Z41: =IFERROR(((Z7/Y7)-1),0) -> 0 | AA41: =IFERROR(((AA7/Z7)-1),0) -> 0 | AB41: =IFERROR(((AB7/AA7)-1),0) -> 0 | ... AF41: =IFERROR(((AF7/AE7)-1),0) -> 0 | AG41: 0 | AI41: Sales-Revenue (MoM) | AJ41: =IFERROR(((AJ7/AI7)-1),0) -> 0 | AK41: =IFERROR(((AK7/AJ7)-1),0) -> 0 | AL41: =IFERROR(((AL7/AK7)-1),0) -> 0 | AM41: =IFERROR(((AM7/AL7)-1),0) -> 0 | AN41: =IFERROR(((AN7/AM7)-1),0) -> 0 | AO41: =IFERROR(((AO7/AN7)-1),0) -> 0 | AP41: =IFERROR(((AP7/AO7)-1),0) -> 0 | AQ41: =IFERROR(((AQ7/AP7)-1),0) -> 0 | ... AU41: =IFERROR(((AU7/AT7)-1),0) -> 0 | AV41: 0 | AX41: Sales-Revenue (MoM) | AY41: =IFERROR(((AY7/AX7)-1),0) -> 0 | AZ41: =IFERROR(((AZ7/AY7)-1),0) -> 0 | BA41: =IFERROR(((BA7/AZ7)-1),0) -> 0 | BB41: =IFERROR(((BB7/BA7)-1),0) -> 0 | BC41: =IFERROR(((BC7/BB7)-1),0) -> 0 | BD41: =IFERROR(((BD7/BC7)-1),0) -> 0 | BE41: =IFERROR(((BE7/BD7)-1),0) -> 0 | BF41: =IFERROR(((BF7/BE7)-1),0) -> 0 | ... BJ41: =IFERROR(((BJ7/BI7)-1),0) -> 0 | BK41: 0
C42: Sales-Volume (MoM) | D42: =IFERROR(((D6/C6)-1),0) -> 0 | E42: =IFERROR(((E6/D6)-1),0) -> 0.064516129 | F42: =IFERROR(((F6/E6)-1),0) -> 0.060606061 | G42: =IFERROR(((G6/F6)-1),0) -> -1 | H42: =IFERROR(((H6/G6)-1),0) -> 0 | I42: =IFERROR(((I6/H6)-1),0) -> 0 | J42: =IFERROR(((J6/I6)-1),0) -> 0 | K42: =IFERROR(((K6/J6)-1),0) -> 0 | ... O42: =IFERROR(((O6/N6)-1),0) -> 0 | P42: 0 | T42: Sales-Volume (MoM) | U42: =IFERROR(((U6/T6)-1),0) -> 0 | V42: =IFERROR(((V6/U6)-1),0) -> 0 | W42: =IFERROR(((W6/V6)-1),0) -> 0 | X42: =IFERROR(((X6/W6)-1),0) -> 0 | Y42: =IFERROR(((Y6/X6)-1),0) -> 0 | Z42: =IFERROR(((Z6/Y6)-1),0) -> 0 | AA42: =IFERROR(((AA6/Z6)-1),0) -> 0 | AB42: =IFERROR(((AB6/AA6)-1),0) -> 0 | ... AF42: =IFERROR(((AF6/AE6)-1),0) -> 0 | AG42: 0 | AI42: Sales-Volume (MoM) | AJ42: =IFERROR(((AJ6/AI6)-1),0) -> 0 | AK42: =IFERROR(((AK6/AJ6)-1),0) -> 0 | AL42: =IFERROR(((AL6/AK6)-1),0) -> 0 | AM42: =IFERROR(((AM6/AL6)-1),0) -> 0 | AN42: =IFERROR(((AN6/AM6)-1),0) -> 0 | AO42: =IFERROR(((AO6/AN6)-1),0) -> 0 | AP42: =IFERROR(((AP6/AO6)-1),0) -> 0 | AQ42: =IFERROR(((AQ6/AP6)-1),0) -> 0 | ... AU42: =IFERROR(((AU6/AT6)-1),0) -> 0 | AV42: 0 | AX42: Sales-Volume (MoM) | AY42: =IFERROR(((AY6/AX6)-1),0) -> 0 | AZ42: =IFERROR(((AZ6/AY6)-1),0) -> 0 | BA42: =IFERROR(((BA6/AZ6)-1),0) -> 0 | BB42: =IFERROR(((BB6/BA6)-1),0) -> 0 | BC42: =IFERROR(((BC6/BB6)-1),0) -> 0 | BD42: =IFERROR(((BD6/BC6)-1),0) -> 0 | BE42: =IFERROR(((BE6/BD6)-1),0) -> 0 | BF42: =IFERROR(((BF6/BE6)-1),0) -> 0 | ... BJ42: =IFERROR(((BJ6/BI6)-1),0) -> 0 | BK42: 0
C43: Sales-Transactions (MoM) | D43: =IFERROR(((D20/C20)-1),0) -> 0 | E43: =IFERROR(((E20/D20)-1),0) -> 0 | F43: =IFERROR(((F20/E20)-1),0) -> 0 | G43: =IFERROR(((G20/F20)-1),0) -> -1 | H43: =IFERROR(((H20/G20)-1),0) -> 0 | I43: =IFERROR(((I20/H20)-1),0) -> 0 | J43: =IFERROR(((J20/I20)-1),0) -> 0 | K43: =IFERROR(((K20/J20)-1),0) -> 0 | ... O43: =IFERROR(((O20/N20)-1),0) -> 0 | P43: 0 | T43: Sales-Transactions (MoM) | U43: =IFERROR(((U20/T20)-1),0) -> 0 | V43: =IFERROR(((V20/U20)-1),0) -> 0 | W43: =IFERROR(((W20/V20)-1),0) -> 0 | X43: =IFERROR(((X20/W20)-1),0) -> 0 | Y43: =IFERROR(((Y20/X20)-1),0) -> 0 | Z43: =IFERROR(((Z20/Y20)-1),0) -> 0 | AA43: =IFERROR(((AA20/Z20)-1),0) -> 0 | AB43: =IFERROR(((AB20/AA20)-1),0) -> 0 | ... AF43: =IFERROR(((AF20/AE20)-1),0) -> 0 | AG43: 0 | AI43: Sales-Transactions (MoM) | AJ43: =IFERROR(((AJ20/AI20)-1),0) -> 0 | AK43: =IFERROR(((AK20/AJ20)-1),0) -> 0 | AL43: =IFERROR(((AL20/AK20)-1),0) -> 0 | AM43: =IFERROR(((AM20/AL20)-1),0) -> 0 | AN43: =IFERROR(((AN20/AM20)-1),0) -> 0 | AO43: =IFERROR(((AO20/AN20)-1),0) -> 0 | AP43: =IFERROR(((AP20/AO20)-1),0) -> 0 | AQ43: =IFERROR(((AQ20/AP20)-1),0) -> 0 | ... AU43: =IFERROR(((AU20/AT20)-1),0) -> 0 | AV43: 0 | AX43: Sales-Transactions (MoM) | AY43: =IFERROR(((AY20/AX20)-1),0) -> 0 | AZ43: =IFERROR(((AZ20/AY20)-1),0) -> 0 | BA43: =IFERROR(((BA20/AZ20)-1),0) -> 0 | BB43: =IFERROR(((BB20/BA20)-1),0) -> 0 | BC43: =IFERROR(((BC20/BB20)-1),0) -> 0 | BD43: =IFERROR(((BD20/BC20)-1),0) -> 0 | BE43: =IFERROR(((BE20/BD20)-1),0) -> 0 | BF43: =IFERROR(((BF20/BE20)-1),0) -> 0 | ... BJ43: =IFERROR(((BJ20/BI20)-1),0) -> 0 | BK43: 0
C45: Loss Making Transactions | D45: =D5 -> 46113 | E45: =E5 -> 46143 | F45: =F5 -> 46174 | G45: =G5 -> 46204 | H45: =H5 -> 46235 | I45: =I5 -> 46266 | J45: =J5 -> 46296 | K45: =K5 -> 46327 | ... P45: =P5 -> FY 2026-27
C46: No of LMT @ Inception | D46: 3 | E46: 1 | F46: 0 | G46: 0 | H46: 4 | I46: 0 | J46: 0 | K46: 8 | L46: 0 | M46: 0 | N46: 0 | O46: 0 | P46: =SUM(D46:O46) -> 16 | T46: CN & DN Provisions | U46: =U5 -> 46113 | V46: =V5 -> 46143 | W46: =W5 -> 46174 | X46: =X5 -> 46204 | Y46: =Y5 -> 46235 | Z46: =Z5 -> 46266 | AA46: =AA5 -> 46296 | AB46: =AB5 -> 46327 | ... AG46: =AG5 -> FY 2026-27 | AI46: CN & DN Provisions | AJ46: =AJ5 -> 46113 | AK46: =AK5 -> 46143 | AL46: =AL5 -> 46174 | AM46: =AM5 -> 46204 | AN46: =AN5 -> 46235 | AO46: =AO5 -> 46266 | AP46: =AP5 -> 46296 | AQ46: =AQ5 -> 46327 | ... AV46: =AV5 -> FY 2026-27 | AX46: CN & DN Provisions | AY46: =AY5 -> 46113 | AZ46: =AZ5 -> 46143 | BA46: =BA5 -> 46174 | BB46: =BB5 -> 46204 | BC46: =BC5 -> 46235 | BD46: =BD5 -> 46266 | BE46: =BE5 -> 46296 | BF46: =BF5 -> 46327 | ... BK46: =BK5 -> FY 2026-27
C47: Value of LMT @ Inception | D47: 67735 | E47: 44712 | F47: 0 | G47: 0 | H47: 18138 | I47: 0 | J47: 0 | K47: 59790 | L47: 0 | M47: 0 | N47: 0 | O47: 0 | P47: =SUM(D47:O47) -> 190375 | T47: DN Provision | U47: =-SUMIFS(Details!$AL$5:$AL$11,Details!$C$5:$C$11,Summary!U$5,Details!$CK$5:$CK$11,Summary!$T$5) -> 0 | V47: =-SUMIFS(Details!$AL$5:$AL$11,Details!$C$5:$C$11,Summary!V$5,Details!$CK$5:$CK$11,Summary!$T$5) -> 0 | W47: =-SUMIFS(Details!$AL$5:$AL$11,Details!$C$5:$C$11,Summary!W$5,Details!$CK$5:$CK$11,Summary!$T$5) -> 0 | X47: =-SUMIFS(Details!$AL$5:$AL$11,Details!$C$5:$C$11,Summary!X$5,Details!$CK$5:$CK$11,Summary!$T$5) -> 0 | Y47: =-SUMIFS(Details!$AL$5:$AL$11,Details!$C$5:$C$11,Summary!Y$5,Details!$CK$5:$CK$11,Summary!$T$5) -> 0 | Z47: =-SUMIFS(Details!$AL$5:$AL$11,Details!$C$5:$C$11,Summary!Z$5,Details!$CK$5:$CK$11,Summary!$T$5) -> 0 | AA47: =-SUMIFS(Details!$AL$5:$AL$11,Details!$C$5:$C$11,Summary!AA$5,Details!$CK$5:$CK$11,Summary!$T$5) -> 0 | AB47: =-SUMIFS(Details!$AL$5:$AL$11,Details!$C$5:$C$11,Summary!AB$5,Details!$CK$5:$CK$11,Summary!$T$5) -> 0 | ... AF47: =-SUMIFS(Details!$AL$5:$AL$11,Details!$C$5:$C$11,Summary!AF$5,Details!$CK$5:$CK$11,Summary!$T$5) -> 0 | AG47: =SUM(U47:AF47) -> 0 | AI47: DN Provision | AJ47: =-SUMIFS(Details!$AL$5:$AL$11,Details!$C$5:$C$11,Summary!AJ$5,Details!$CK$5:$CK$11,Summary!$AI$5) -> 0 | AK47: =-SUMIFS(Details!$AL$5:$AL$11,Details!$C$5:$C$11,Summary!AK$5,Details!$CK$5:$CK$11,Summary!$AI$5) -> 0 | AL47: =-SUMIFS(Details!$AL$5:$AL$11,Details!$C$5:$C$11,Summary!AL$5,Details!$CK$5:$CK$11,Summary!$AI$5) -> 0 | AM47: =-SUMIFS(Details!$AL$5:$AL$11,Details!$C$5:$C$11,Summary!AM$5,Details!$CK$5:$CK$11,Summary!$AI$5) -> 0 | AN47: =-SUMIFS(Details!$AL$5:$AL$11,Details!$C$5:$C$11,Summary!AN$5,Details!$CK$5:$CK$11,Summary!$AI$5) -> 0 | AO47: =-SUMIFS(Details!$AL$5:$AL$11,Details!$C$5:$C$11,Summary!AO$5,Details!$CK$5:$CK$11,Summary!$AI$5) -> 0 | AP47: =-SUMIFS(Details!$AL$5:$AL$11,Details!$C$5:$C$11,Summary!AP$5,Details!$CK$5:$CK$11,Summary!$AI$5) -> 0 | AQ47: =-SUMIFS(Details!$AL$5:$AL$11,Details!$C$5:$C$11,Summary!AQ$5,Details!$CK$5:$CK$11,Summary!$AI$5) -> 0 | ... AU47: =-SUMIFS(Details!$AL$5:$AL$11,Details!$C$5:$C$11,Summary!AU$5,Details!$CK$5:$CK$11,Summary!$AI$5) -> 0 | AV47: =SUM(AJ47:AU47) -> 0 | AX47: DN Provision | AY47: =-SUMIFS(Details!$AL$5:$AL$11,Details!$C$5:$C$11,Summary!AY$5,Details!$CK$5:$CK$11,Summary!$AX$5) -> 0 | AZ47: =-SUMIFS(Details!$AL$5:$AL$11,Details!$C$5:$C$11,Summary!AZ$5,Details!$CK$5:$CK$11,Summary!$AX$5) -> 0 | BA47: =-SUMIFS(Details!$AL$5:$AL$11,Details!$C$5:$C$11,Summary!BA$5,Details!$CK$5:$CK$11,Summary!$AX$5) -> 0 | BB47: =-SUMIFS(Details!$AL$5:$AL$11,Details!$C$5:$C$11,Summary!BB$5,Details!$CK$5:$CK$11,Summary!$AX$5) -> 0 | BC47: =-SUMIFS(Details!$AL$5:$AL$11,Details!$C$5:$C$11,Summary!BC$5,Details!$CK$5:$CK$11,Summary!$AX$5) -> 0 | BD47: =-SUMIFS(Details!$AL$5:$AL$11,Details!$C$5:$C$11,Summary!BD$5,Details!$CK$5:$CK$11,Summary!$AX$5) -> 0 | BE47: =-SUMIFS(Details!$AL$5:$AL$11,Details!$C$5:$C$11,Summary!BE$5,Details!$CK$5:$CK$11,Summary!$AX$5) -> 0 | BF47: =-SUMIFS(Details!$AL$5:$AL$11,Details!$C$5:$C$11,Summary!BF$5,Details!$CK$5:$CK$11,Summary!$AX$5) -> 0 | ... BJ47: =-SUMIFS(Details!$AL$5:$AL$11,Details!$C$5:$C$11,Summary!BJ$5,Details!$CK$5:$CK$11,Summary!$AX$5) -> 0 | BK47: =SUM(AY47:BJ47) -> 0
C48: No of LMT | D48: 2 | E48: 2 | F48: 0 | G48: 1 | H48: 8 | I48: 0 | J48: 0 | K48: 7 | L48: 0 | M48: 0 | N48: 0 | O48: 0 | P48: =SUM(D48:O48) -> 20 | T48: CN Provision | U48: =-SUMIFS(Details!$BP$5:$BP$11,Details!$C$5:$C$11,Summary!U$5,Details!$CK$5:$CK$11,Summary!$T$5) -> 0 | V48: =-SUMIFS(Details!$BP$5:$BP$11,Details!$C$5:$C$11,Summary!V$5,Details!$CK$5:$CK$11,Summary!$T$5) -> 0 | W48: =-SUMIFS(Details!$BP$5:$BP$11,Details!$C$5:$C$11,Summary!W$5,Details!$CK$5:$CK$11,Summary!$T$5) -> 0 | X48: =-SUMIFS(Details!$BP$5:$BP$11,Details!$C$5:$C$11,Summary!X$5,Details!$CK$5:$CK$11,Summary!$T$5) -> 0 | Y48: =-SUMIFS(Details!$BP$5:$BP$11,Details!$C$5:$C$11,Summary!Y$5,Details!$CK$5:$CK$11,Summary!$T$5) -> 0 | Z48: =-SUMIFS(Details!$BP$5:$BP$11,Details!$C$5:$C$11,Summary!Z$5,Details!$CK$5:$CK$11,Summary!$T$5) -> 0 | AA48: =-SUMIFS(Details!$BP$5:$BP$11,Details!$C$5:$C$11,Summary!AA$5,Details!$CK$5:$CK$11,Summary!$T$5) -> 0 | AB48: =-SUMIFS(Details!$BP$5:$BP$11,Details!$C$5:$C$11,Summary!AB$5,Details!$CK$5:$CK$11,Summary!$T$5) -> 0 | ... AF48: =-SUMIFS(Details!$BP$5:$BP$11,Details!$C$5:$C$11,Summary!AF$5,Details!$CK$5:$CK$11,Summary!$T$5) -> 0 | AG48: =SUM(U48:AF48) -> 0 | AI48: CN Provision | AJ48: =-SUMIFS(Details!$BP$5:$BP$11,Details!$C$5:$C$11,Summary!AJ$5,Details!$CK$5:$CK$11,Summary!$AI$5) -> 0 | AK48: =-SUMIFS(Details!$BP$5:$BP$11,Details!$C$5:$C$11,Summary!AK$5,Details!$CK$5:$CK$11,Summary!$AI$5) -> 0 | AL48: =-SUMIFS(Details!$BP$5:$BP$11,Details!$C$5:$C$11,Summary!AL$5,Details!$CK$5:$CK$11,Summary!$AI$5) -> 0 | AM48: =-SUMIFS(Details!$BP$5:$BP$11,Details!$C$5:$C$11,Summary!AM$5,Details!$CK$5:$CK$11,Summary!$AI$5) -> 0 | AN48: =-SUMIFS(Details!$BP$5:$BP$11,Details!$C$5:$C$11,Summary!AN$5,Details!$CK$5:$CK$11,Summary!$AI$5) -> 0 | AO48: =-SUMIFS(Details!$BP$5:$BP$11,Details!$C$5:$C$11,Summary!AO$5,Details!$CK$5:$CK$11,Summary!$AI$5) -> 0 | AP48: =-SUMIFS(Details!$BP$5:$BP$11,Details!$C$5:$C$11,Summary!AP$5,Details!$CK$5:$CK$11,Summary!$AI$5) -> 0 | AQ48: =-SUMIFS(Details!$BP$5:$BP$11,Details!$C$5:$C$11,Summary!AQ$5,Details!$CK$5:$CK$11,Summary!$AI$5) -> 0 | ... AU48: =-SUMIFS(Details!$BP$5:$BP$11,Details!$C$5:$C$11,Summary!AU$5,Details!$CK$5:$CK$11,Summary!$AI$5) -> 0 | AV48: =SUM(AJ48:AU48) -> 0 | AX48: CN Provision | AY48: =-SUMIFS(Details!$BP$5:$BP$11,Details!$C$5:$C$11,Summary!AY$5,Details!$CK$5:$CK$11,Summary!$AX$5) -> 0 | AZ48: =-SUMIFS(Details!$BP$5:$BP$11,Details!$C$5:$C$11,Summary!AZ$5,Details!$CK$5:$CK$11,Summary!$AX$5) -> 0 | BA48: =-SUMIFS(Details!$BP$5:$BP$11,Details!$C$5:$C$11,Summary!BA$5,Details!$CK$5:$CK$11,Summary!$AX$5) -> 0 | BB48: =-SUMIFS(Details!$BP$5:$BP$11,Details!$C$5:$C$11,Summary!BB$5,Details!$CK$5:$CK$11,Summary!$AX$5) -> 0 | BC48: =-SUMIFS(Details!$BP$5:$BP$11,Details!$C$5:$C$11,Summary!BC$5,Details!$CK$5:$CK$11,Summary!$AX$5) -> 0 | BD48: =-SUMIFS(Details!$BP$5:$BP$11,Details!$C$5:$C$11,Summary!BD$5,Details!$CK$5:$CK$11,Summary!$AX$5) -> 0 | BE48: =-SUMIFS(Details!$BP$5:$BP$11,Details!$C$5:$C$11,Summary!BE$5,Details!$CK$5:$CK$11,Summary!$AX$5) -> 0 | BF48: =-SUMIFS(Details!$BP$5:$BP$11,Details!$C$5:$C$11,Summary!BF$5,Details!$CK$5:$CK$11,Summary!$AX$5) -> 0 | ... BJ48: =-SUMIFS(Details!$BP$5:$BP$11,Details!$C$5:$C$11,Summary!BJ$5,Details!$CK$5:$CK$11,Summary!$AX$5) -> 0 | BK48: =SUM(AY48:BJ48) -> 0
C49: % of LMT | D49: =IFERROR((D48/D20),0) -> 2 | E49: =IFERROR((E48/E20),0) -> 2 | F49: =IFERROR((F48/F20),0) -> 0 | G49: =IFERROR((G48/G20),0) -> 0 | H49: =IFERROR((H48/H20),0) -> 0 | I49: =IFERROR((I48/I20),0) -> 0 | J49: =IFERROR((J48/J20),0) -> 0 | K49: =IFERROR((K48/K20),0) -> 0 | ... P49: =IFERROR((P48/P20),0) -> 6.6666667
C50: Value of LMT | D50: 16695 | E50: 44749 | F50: 0 | G50: 21436 | H50: 81846 | I50: 0 | J50: 0 | K50: 37763 | L50: 0 | M50: 0 | N50: 0 | O50: 0 | P50: =SUM(D50:O50) -> 202489 | T50: Qty Returned | U50: =U5 -> 46113 | V50: =V5 -> 46143 | W50: =W5 -> 46174 | X50: =X5 -> 46204 | Y50: =Y5 -> 46235 | Z50: =Z5 -> 46266 | AA50: =AA5 -> 46296 | AB50: =AB5 -> 46327 | ... AG50: =AG5 -> FY 2026-27 | AI50: Qty Returned | AJ50: =AJ5 -> 46113 | AK50: =AK5 -> 46143 | AL50: =AL5 -> 46174 | AM50: =AM5 -> 46204 | AN50: =AN5 -> 46235 | AO50: =AO5 -> 46266 | AP50: =AP5 -> 46296 | AQ50: =AQ5 -> 46327 | ... AV50: =AV5 -> FY 2026-27 | AX50: Qty Returned | AY50: =AY5 -> 46113 | AZ50: =AZ5 -> 46143 | BA50: =BA5 -> 46174 | BB50: =BB5 -> 46204 | BC50: =BC5 -> 46235 | BD50: =BD5 -> 46266 | BE50: =BE5 -> 46296 | BF50: =BF5 -> 46327 | ... BK50: =BK5 -> FY 2026-27
U51: =SUMIFS(Details!$R$5:$R$11,Details!$C$5:$C$11,Summary!U$5,Details!$CK$5:$CK$11,Summary!$T$5)/1000 -> 0 | V51: =SUMIFS(Details!$R$5:$R$11,Details!$C$5:$C$11,Summary!V$5,Details!$CK$5:$CK$11,Summary!$T$5)/1000 -> 0 | W51: =SUMIFS(Details!$R$5:$R$11,Details!$C$5:$C$11,Summary!W$5,Details!$CK$5:$CK$11,Summary!$T$5)/1000 -> 0 | X51: =SUMIFS(Details!$R$5:$R$11,Details!$C$5:$C$11,Summary!X$5,Details!$CK$5:$CK$11,Summary!$T$5)/1000 -> 0 | Y51: =SUMIFS(Details!$R$5:$R$11,Details!$C$5:$C$11,Summary!Y$5,Details!$CK$5:$CK$11,Summary!$T$5)/1000 -> 0 | Z51: =SUMIFS(Details!$R$5:$R$11,Details!$C$5:$C$11,Summary!Z$5,Details!$CK$5:$CK$11,Summary!$T$5)/1000 -> 0 | AA51: =SUMIFS(Details!$R$5:$R$11,Details!$C$5:$C$11,Summary!AA$5,Details!$CK$5:$CK$11,Summary!$T$5)/1000 -> 0 | AB51: =SUMIFS(Details!$R$5:$R$11,Details!$C$5:$C$11,Summary!AB$5,Details!$CK$5:$CK$11,Summary!$T$5)/1000 -> 0 | ... AF51: =SUMIFS(Details!$R$5:$R$11,Details!$C$5:$C$11,Summary!AF$5,Details!$CK$5:$CK$11,Summary!$T$5)/1000 -> 0 | AG51: =SUM(U51:AF51) -> 0 | AJ51: =SUMIFS(Details!$R$5:$R$11,Details!$C$5:$C$11,Summary!AJ$5,Details!$CK$5:$CK$11,Summary!$AI$5)/1000 -> 0 | AK51: =SUMIFS(Details!$R$5:$R$11,Details!$C$5:$C$11,Summary!AK$5,Details!$CK$5:$CK$11,Summary!$AI$5)/1000 -> 0 | AL51: =SUMIFS(Details!$R$5:$R$11,Details!$C$5:$C$11,Summary!AL$5,Details!$CK$5:$CK$11,Summary!$AI$5)/1000 -> 0 | AM51: =SUMIFS(Details!$R$5:$R$11,Details!$C$5:$C$11,Summary!AM$5,Details!$CK$5:$CK$11,Summary!$AI$5)/1000 -> 0 | AN51: =SUMIFS(Details!$R$5:$R$11,Details!$C$5:$C$11,Summary!AN$5,Details!$CK$5:$CK$11,Summary!$AI$5)/1000 -> 0 | AO51: =SUMIFS(Details!$R$5:$R$11,Details!$C$5:$C$11,Summary!AO$5,Details!$CK$5:$CK$11,Summary!$AI$5)/1000 -> 0 | AP51: =SUMIFS(Details!$R$5:$R$11,Details!$C$5:$C$11,Summary!AP$5,Details!$CK$5:$CK$11,Summary!$AI$5)/1000 -> 0 | AQ51: =SUMIFS(Details!$R$5:$R$11,Details!$C$5:$C$11,Summary!AQ$5,Details!$CK$5:$CK$11,Summary!$AI$5)/1000 -> 0 | ... AU51: =SUMIFS(Details!$R$5:$R$11,Details!$C$5:$C$11,Summary!AU$5,Details!$CK$5:$CK$11,Summary!$AI$5)/1000 -> 0 | AV51: =SUM(AJ51:AU51) -> 0 | AY51: =SUMIFS(Details!$R$5:$R$11,Details!$C$5:$C$11,Summary!AY$5,Details!$CK$5:$CK$11,Summary!$AX$5)/1000 -> 0 | AZ51: =SUMIFS(Details!$R$5:$R$11,Details!$C$5:$C$11,Summary!AZ$5,Details!$CK$5:$CK$11,Summary!$AX$5)/1000 -> 0 | BA51: =SUMIFS(Details!$R$5:$R$11,Details!$C$5:$C$11,Summary!BA$5,Details!$CK$5:$CK$11,Summary!$AX$5)/1000 -> 0 | BB51: =SUMIFS(Details!$R$5:$R$11,Details!$C$5:$C$11,Summary!BB$5,Details!$CK$5:$CK$11,Summary!$AX$5)/1000 -> 0 | BC51: =SUMIFS(Details!$R$5:$R$11,Details!$C$5:$C$11,Summary!BC$5,Details!$CK$5:$CK$11,Summary!$AX$5)/1000 -> 0 | BD51: =SUMIFS(Details!$R$5:$R$11,Details!$C$5:$C$11,Summary!BD$5,Details!$CK$5:$CK$11,Summary!$AX$5)/1000 -> 0 | BE51: =SUMIFS(Details!$R$5:$R$11,Details!$C$5:$C$11,Summary!BE$5,Details!$CK$5:$CK$11,Summary!$AX$5)/1000 -> 0 | BF51: =SUMIFS(Details!$R$5:$R$11,Details!$C$5:$C$11,Summary!BF$5,Details!$CK$5:$CK$11,Summary!$AX$5)/1000 -> 0 | ... BJ51: =SUMIFS(Details!$R$5:$R$11,Details!$C$5:$C$11,Summary!BJ$5,Details!$CK$5:$CK$11,Summary!$AX$5)/1000 -> 0 | BK51: =SUM(AY51:BJ51) -> 0
C52: CN & DN Provisions | D52: =D5 -> 46113 | E52: =E5 -> 46143 | F52: =F5 -> 46174 | G52: =G5 -> 46204 | H52: =H5 -> 46235 | I52: =I5 -> 46266 | J52: =J5 -> 46296 | K52: =K5 -> 46327 | ... P52: =P5 -> FY 2026-27 | Q52: =ROUND(Q53-Q54,2)-ROUND(P37-P13,2) -> 0
C53: DN Provision | D53: =-SUMIFS(Details!$AL$5:$AL$11,Details!$C$5:$C$11,Summary!D$5) -> 0 | E53: =-SUMIFS(Details!$AL$5:$AL$11,Details!$C$5:$C$11,Summary!E$5) -> 0 | F53: =-SUMIFS(Details!$AL$5:$AL$11,Details!$C$5:$C$11,Summary!F$5) -> 0 | G53: =-SUMIFS(Details!$AL$5:$AL$11,Details!$C$5:$C$11,Summary!G$5) -> 0 | H53: =-SUMIFS(Details!$AL$5:$AL$11,Details!$C$5:$C$11,Summary!H$5) -> 0 | I53: =-SUMIFS(Details!$AL$5:$AL$11,Details!$C$5:$C$11,Summary!I$5) -> 0 | J53: =-SUMIFS(Details!$AL$5:$AL$11,Details!$C$5:$C$11,Summary!J$5) -> 0 | K53: =-SUMIFS(Details!$AL$5:$AL$11,Details!$C$5:$C$11,Summary!K$5) -> 0 | ... O53: =-SUMIFS(Details!$AL$5:$AL$11,Details!$C$5:$C$11,Summary!O$5) -> 0 | P53: =SUM(D53:O53) -> 0 | Q53: =Details!AL12 -> 0 | T53: Margins | U53: =U5 -> 46113 | V53: =V5 -> 46143 | W53: =W5 -> 46174 | X53: =X5 -> 46204 | Y53: =Y5 -> 46235 | Z53: =Z5 -> 46266 | AA53: =AA5 -> 46296 | AB53: =AB5 -> 46327 | ... AG53: =AG5 -> FY 2026-27 | AI53: Margins | AJ53: =AJ5 -> 46113 | AK53: =AK5 -> 46143 | AL53: =AL5 -> 46174 | AM53: =AM5 -> 46204 | AN53: =AN5 -> 46235 | AO53: =AO5 -> 46266 | AP53: =AP5 -> 46296 | AQ53: =AQ5 -> 46327 | ... AV53: =AV5 -> FY 2026-27 | AX53: Margins | AY53: =AY5 -> 46113 | AZ53: =AZ5 -> 46143 | BA53: =BA5 -> 46174 | BB53: =BB5 -> 46204 | BC53: =BC5 -> 46235 | BD53: =BD5 -> 46266 | BE53: =BE5 -> 46296 | BF53: =BF5 -> 46327 | ... BK53: =BK5 -> FY 2026-27 | BM53: =(AG47+AV47+BK47)-P53 -> 0
C54: CN Provision | D54: =-SUMIFS(Details!$BP$5:$BP$11,Details!$C$5:$C$11,Summary!D$5) -> 0 | E54: =-SUMIFS(Details!$BP$5:$BP$11,Details!$C$5:$C$11,Summary!E$5) -> 0 | F54: =-SUMIFS(Details!$BP$5:$BP$11,Details!$C$5:$C$11,Summary!F$5) -> 0 | G54: =-SUMIFS(Details!$BP$5:$BP$11,Details!$C$5:$C$11,Summary!G$5) -> 0 | H54: =-SUMIFS(Details!$BP$5:$BP$11,Details!$C$5:$C$11,Summary!H$5) -> 0 | I54: =-SUMIFS(Details!$BP$5:$BP$11,Details!$C$5:$C$11,Summary!I$5) -> 0 | J54: =-SUMIFS(Details!$BP$5:$BP$11,Details!$C$5:$C$11,Summary!J$5) -> 0 | K54: =-SUMIFS(Details!$BP$5:$BP$11,Details!$C$5:$C$11,Summary!K$5) -> 0 | ... O54: =-SUMIFS(Details!$BP$5:$BP$11,Details!$C$5:$C$11,Summary!O$5) -> 0 | P54: =SUM(D54:O54) -> 0 | Q54: =Details!BP12 -> 0 | R54: =Q54+P54 -> 0 | T54: Gross Margin | U54: =SUMIFS(Details!$CN$5:$CN$11,Details!$C$5:$C$11,Summary!U$5,Details!$CK$5:$CK$11,Summary!$T$5) -> 0 | V54: =SUMIFS(Details!$CN$5:$CN$11,Details!$C$5:$C$11,Summary!V$5,Details!$CK$5:$CK$11,Summary!$T$5) -> 0 | W54: =SUMIFS(Details!$CN$5:$CN$11,Details!$C$5:$C$11,Summary!W$5,Details!$CK$5:$CK$11,Summary!$T$5) -> 0 | X54: =SUMIFS(Details!$CN$5:$CN$11,Details!$C$5:$C$11,Summary!X$5,Details!$CK$5:$CK$11,Summary!$T$5) -> 0 | Y54: =SUMIFS(Details!$CN$5:$CN$11,Details!$C$5:$C$11,Summary!Y$5,Details!$CK$5:$CK$11,Summary!$T$5) -> 0 | Z54: =SUMIFS(Details!$CN$5:$CN$11,Details!$C$5:$C$11,Summary!Z$5,Details!$CK$5:$CK$11,Summary!$T$5) -> 0 | AA54: =SUMIFS(Details!$CN$5:$CN$11,Details!$C$5:$C$11,Summary!AA$5,Details!$CK$5:$CK$11,Summary!$T$5) -> 0 | AB54: =SUMIFS(Details!$CN$5:$CN$11,Details!$C$5:$C$11,Summary!AB$5,Details!$CK$5:$CK$11,Summary!$T$5) -> 0 | ... AF54: =SUMIFS(Details!$CN$5:$CN$11,Details!$C$5:$C$11,Summary!AF$5,Details!$CK$5:$CK$11,Summary!$T$5) -> 0 | AG54: =SUM(U54:AF54) -> 0 | AI54: Gross Margin | AJ54: =SUMIFS(Details!$CN$5:$CN$11,Details!$C$5:$C$11,Summary!AJ$5,Details!$CK$5:$CK$11,Summary!$AI$5) -> 0 | AK54: =SUMIFS(Details!$CN$5:$CN$11,Details!$C$5:$C$11,Summary!AK$5,Details!$CK$5:$CK$11,Summary!$AI$5) -> 0 | AL54: =SUMIFS(Details!$CN$5:$CN$11,Details!$C$5:$C$11,Summary!AL$5,Details!$CK$5:$CK$11,Summary!$AI$5) -> 0 | AM54: =SUMIFS(Details!$CN$5:$CN$11,Details!$C$5:$C$11,Summary!AM$5,Details!$CK$5:$CK$11,Summary!$AI$5) -> 0 | AN54: =SUMIFS(Details!$CN$5:$CN$11,Details!$C$5:$C$11,Summary!AN$5,Details!$CK$5:$CK$11,Summary!$AI$5) -> 0 | AO54: =SUMIFS(Details!$CN$5:$CN$11,Details!$C$5:$C$11,Summary!AO$5,Details!$CK$5:$CK$11,Summary!$AI$5) -> 0 | AP54: =SUMIFS(Details!$CN$5:$CN$11,Details!$C$5:$C$11,Summary!AP$5,Details!$CK$5:$CK$11,Summary!$AI$5) -> 0 | AQ54: =SUMIFS(Details!$CN$5:$CN$11,Details!$C$5:$C$11,Summary!AQ$5,Details!$CK$5:$CK$11,Summary!$AI$5) -> 0 | ... AU54: =SUMIFS(Details!$CN$5:$CN$11,Details!$C$5:$C$11,Summary!AU$5,Details!$CK$5:$CK$11,Summary!$AI$5) -> 0 | AV54: =SUM(AJ54:AU54) -> 0 | AX54: Gross Margin | AY54: =SUMIFS(Details!$CN$5:$CN$11,Details!$C$5:$C$11,Summary!AY$5,Details!$CK$5:$CK$11,Summary!$AX$5) -> 0 | AZ54: =SUMIFS(Details!$CN$5:$CN$11,Details!$C$5:$C$11,Summary!AZ$5,Details!$CK$5:$CK$11,Summary!$AX$5) -> 0 | BA54: =SUMIFS(Details!$CN$5:$CN$11,Details!$C$5:$C$11,Summary!BA$5,Details!$CK$5:$CK$11,Summary!$AX$5) -> 0 | BB54: =SUMIFS(Details!$CN$5:$CN$11,Details!$C$5:$C$11,Summary!BB$5,Details!$CK$5:$CK$11,Summary!$AX$5) -> 0 | BC54: =SUMIFS(Details!$CN$5:$CN$11,Details!$C$5:$C$11,Summary!BC$5,Details!$CK$5:$CK$11,Summary!$AX$5) -> 0 | BD54: =SUMIFS(Details!$CN$5:$CN$11,Details!$C$5:$C$11,Summary!BD$5,Details!$CK$5:$CK$11,Summary!$AX$5) -> 0 | BE54: =SUMIFS(Details!$CN$5:$CN$11,Details!$C$5:$C$11,Summary!BE$5,Details!$CK$5:$CK$11,Summary!$AX$5) -> 0 | BF54: =SUMIFS(Details!$CN$5:$CN$11,Details!$C$5:$C$11,Summary!BF$5,Details!$CK$5:$CK$11,Summary!$AX$5) -> 0 | ... BJ54: =SUMIFS(Details!$CN$5:$CN$11,Details!$C$5:$C$11,Summary!BJ$5,Details!$CK$5:$CK$11,Summary!$AX$5) -> 0 | BK54: =SUM(AY54:BJ54) -> 0 | BM54: =(AG48+AV48+BK48)-P54 -> 0
T55: Recykal Margin | U55: =SUMIFS(Details!$CO$5:$CO$11,Details!$C$5:$C$11,Summary!U$5,Details!$CK$5:$CK$11,Summary!$T$5) -> 0 | V55: =SUMIFS(Details!$CO$5:$CO$11,Details!$C$5:$C$11,Summary!V$5,Details!$CK$5:$CK$11,Summary!$T$5) -> 0 | W55: =SUMIFS(Details!$CO$5:$CO$11,Details!$C$5:$C$11,Summary!W$5,Details!$CK$5:$CK$11,Summary!$T$5) -> 0 | X55: =SUMIFS(Details!$CO$5:$CO$11,Details!$C$5:$C$11,Summary!X$5,Details!$CK$5:$CK$11,Summary!$T$5) -> 0 | Y55: =SUMIFS(Details!$CO$5:$CO$11,Details!$C$5:$C$11,Summary!Y$5,Details!$CK$5:$CK$11,Summary!$T$5) -> 0 | Z55: =SUMIFS(Details!$CO$5:$CO$11,Details!$C$5:$C$11,Summary!Z$5,Details!$CK$5:$CK$11,Summary!$T$5) -> 0 | AA55: =SUMIFS(Details!$CO$5:$CO$11,Details!$C$5:$C$11,Summary!AA$5,Details!$CK$5:$CK$11,Summary!$T$5) -> 0 | AB55: =SUMIFS(Details!$CO$5:$CO$11,Details!$C$5:$C$11,Summary!AB$5,Details!$CK$5:$CK$11,Summary!$T$5) -> 0 | ... AF55: =SUMIFS(Details!$CO$5:$CO$11,Details!$C$5:$C$11,Summary!AF$5,Details!$CK$5:$CK$11,Summary!$T$5) -> 0 | AG55: =SUM(U55:AF55) -> 0 | AI55: Recykal Margin | AJ55: =SUMIFS(Details!$CO$5:$CO$11,Details!$C$5:$C$11,Summary!AJ$5,Details!$CK$5:$CK$11,Summary!$AI$5) -> 0 | AK55: =SUMIFS(Details!$CO$5:$CO$11,Details!$C$5:$C$11,Summary!AK$5,Details!$CK$5:$CK$11,Summary!$AI$5) -> 0 | AL55: =SUMIFS(Details!$CO$5:$CO$11,Details!$C$5:$C$11,Summary!AL$5,Details!$CK$5:$CK$11,Summary!$AI$5) -> 0 | AM55: =SUMIFS(Details!$CO$5:$CO$11,Details!$C$5:$C$11,Summary!AM$5,Details!$CK$5:$CK$11,Summary!$AI$5) -> 0 | AN55: =SUMIFS(Details!$CO$5:$CO$11,Details!$C$5:$C$11,Summary!AN$5,Details!$CK$5:$CK$11,Summary!$AI$5) -> 0 | AO55: =SUMIFS(Details!$CO$5:$CO$11,Details!$C$5:$C$11,Summary!AO$5,Details!$CK$5:$CK$11,Summary!$AI$5) -> 0 | AP55: =SUMIFS(Details!$CO$5:$CO$11,Details!$C$5:$C$11,Summary!AP$5,Details!$CK$5:$CK$11,Summary!$AI$5) -> 0 | AQ55: =SUMIFS(Details!$CO$5:$CO$11,Details!$C$5:$C$11,Summary!AQ$5,Details!$CK$5:$CK$11,Summary!$AI$5) -> 0 | ... AU55: =SUMIFS(Details!$CO$5:$CO$11,Details!$C$5:$C$11,Summary!AU$5,Details!$CK$5:$CK$11,Summary!$AI$5) -> 0 | AV55: =SUM(AJ55:AU55) -> 0 | AX55: Recykal Margin | AY55: =SUMIFS(Details!$CO$5:$CO$11,Details!$C$5:$C$11,Summary!AY$5,Details!$CK$5:$CK$11,Summary!$AX$5) -> 0 | AZ55: =SUMIFS(Details!$CO$5:$CO$11,Details!$C$5:$C$11,Summary!AZ$5,Details!$CK$5:$CK$11,Summary!$AX$5) -> 0 | BA55: =SUMIFS(Details!$CO$5:$CO$11,Details!$C$5:$C$11,Summary!BA$5,Details!$CK$5:$CK$11,Summary!$AX$5) -> 0 | BB55: =SUMIFS(Details!$CO$5:$CO$11,Details!$C$5:$C$11,Summary!BB$5,Details!$CK$5:$CK$11,Summary!$AX$5) -> 0 | BC55: =SUMIFS(Details!$CO$5:$CO$11,Details!$C$5:$C$11,Summary!BC$5,Details!$CK$5:$CK$11,Summary!$AX$5) -> 0 | BD55: =SUMIFS(Details!$CO$5:$CO$11,Details!$C$5:$C$11,Summary!BD$5,Details!$CK$5:$CK$11,Summary!$AX$5) -> 0 | BE55: =SUMIFS(Details!$CO$5:$CO$11,Details!$C$5:$C$11,Summary!BE$5,Details!$CK$5:$CK$11,Summary!$AX$5) -> 0 | BF55: =SUMIFS(Details!$CO$5:$CO$11,Details!$C$5:$C$11,Summary!BF$5,Details!$CK$5:$CK$11,Summary!$AX$5) -> 0 | ... BJ55: =SUMIFS(Details!$CO$5:$CO$11,Details!$C$5:$C$11,Summary!BJ$5,Details!$CK$5:$CK$11,Summary!$AX$5) -> 0 | BK55: =SUM(AY55:BJ55) -> 0
C56: Qty Returned | D56: =D5 -> 46113 | E56: =E5 -> 46143 | F56: =F5 -> 46174 | G56: =G5 -> 46204 | H56: =H5 -> 46235 | I56: =I5 -> 46266 | J56: =J5 -> 46296 | K56: =K5 -> 46327 | ... P56: =P5 -> FY 2026-27 | T56: Net Margin | U56: =SUMIFS(Details!$CP$5:$CP$11,Details!$C$5:$C$11,Summary!U$5,Details!$CK$5:$CK$11,Summary!$T$5) -> 0 | V56: =SUMIFS(Details!$CP$5:$CP$11,Details!$C$5:$C$11,Summary!V$5,Details!$CK$5:$CK$11,Summary!$T$5) -> 0 | W56: =SUMIFS(Details!$CP$5:$CP$11,Details!$C$5:$C$11,Summary!W$5,Details!$CK$5:$CK$11,Summary!$T$5) -> 0 | X56: =SUMIFS(Details!$CP$5:$CP$11,Details!$C$5:$C$11,Summary!X$5,Details!$CK$5:$CK$11,Summary!$T$5) -> 0 | Y56: =SUMIFS(Details!$CP$5:$CP$11,Details!$C$5:$C$11,Summary!Y$5,Details!$CK$5:$CK$11,Summary!$T$5) -> 0 | Z56: =SUMIFS(Details!$CP$5:$CP$11,Details!$C$5:$C$11,Summary!Z$5,Details!$CK$5:$CK$11,Summary!$T$5) -> 0 | AA56: =SUMIFS(Details!$CP$5:$CP$11,Details!$C$5:$C$11,Summary!AA$5,Details!$CK$5:$CK$11,Summary!$T$5) -> 0 | AB56: =SUMIFS(Details!$CP$5:$CP$11,Details!$C$5:$C$11,Summary!AB$5,Details!$CK$5:$CK$11,Summary!$T$5) -> 0 | ... AF56: =SUMIFS(Details!$CP$5:$CP$11,Details!$C$5:$C$11,Summary!AF$5,Details!$CK$5:$CK$11,Summary!$T$5) -> 0 | AG56: =SUM(U56:AF56) -> 0 | AI56: Net Margin | AJ56: =SUMIFS(Details!$CP$5:$CP$11,Details!$C$5:$C$11,Summary!AJ$5,Details!$CK$5:$CK$11,Summary!$AI$5) -> 0 | AK56: =SUMIFS(Details!$CP$5:$CP$11,Details!$C$5:$C$11,Summary!AK$5,Details!$CK$5:$CK$11,Summary!$AI$5) -> 0 | AL56: =SUMIFS(Details!$CP$5:$CP$11,Details!$C$5:$C$11,Summary!AL$5,Details!$CK$5:$CK$11,Summary!$AI$5) -> 0 | AM56: =SUMIFS(Details!$CP$5:$CP$11,Details!$C$5:$C$11,Summary!AM$5,Details!$CK$5:$CK$11,Summary!$AI$5) -> 0 | AN56: =SUMIFS(Details!$CP$5:$CP$11,Details!$C$5:$C$11,Summary!AN$5,Details!$CK$5:$CK$11,Summary!$AI$5) -> 0 | AO56: =SUMIFS(Details!$CP$5:$CP$11,Details!$C$5:$C$11,Summary!AO$5,Details!$CK$5:$CK$11,Summary!$AI$5) -> 0 | AP56: =SUMIFS(Details!$CP$5:$CP$11,Details!$C$5:$C$11,Summary!AP$5,Details!$CK$5:$CK$11,Summary!$AI$5) -> 0 | AQ56: =SUMIFS(Details!$CP$5:$CP$11,Details!$C$5:$C$11,Summary!AQ$5,Details!$CK$5:$CK$11,Summary!$AI$5) -> 0 | ... AU56: =SUMIFS(Details!$CP$5:$CP$11,Details!$C$5:$C$11,Summary!AU$5,Details!$CK$5:$CK$11,Summary!$AI$5) -> 0 | AV56: =SUM(AJ56:AU56) -> 0 | AX56: Net Margin | AY56: =SUMIFS(Details!$CP$5:$CP$11,Details!$C$5:$C$11,Summary!AY$5,Details!$CK$5:$CK$11,Summary!$AX$5) -> 0 | AZ56: =SUMIFS(Details!$CP$5:$CP$11,Details!$C$5:$C$11,Summary!AZ$5,Details!$CK$5:$CK$11,Summary!$AX$5) -> 0 | BA56: =SUMIFS(Details!$CP$5:$CP$11,Details!$C$5:$C$11,Summary!BA$5,Details!$CK$5:$CK$11,Summary!$AX$5) -> 0 | BB56: =SUMIFS(Details!$CP$5:$CP$11,Details!$C$5:$C$11,Summary!BB$5,Details!$CK$5:$CK$11,Summary!$AX$5) -> 0 | BC56: =SUMIFS(Details!$CP$5:$CP$11,Details!$C$5:$C$11,Summary!BC$5,Details!$CK$5:$CK$11,Summary!$AX$5) -> 0 | BD56: =SUMIFS(Details!$CP$5:$CP$11,Details!$C$5:$C$11,Summary!BD$5,Details!$CK$5:$CK$11,Summary!$AX$5) -> 0 | BE56: =SUMIFS(Details!$CP$5:$CP$11,Details!$C$5:$C$11,Summary!BE$5,Details!$CK$5:$CK$11,Summary!$AX$5) -> 0 | BF56: =SUMIFS(Details!$CP$5:$CP$11,Details!$C$5:$C$11,Summary!BF$5,Details!$CK$5:$CK$11,Summary!$AX$5) -> 0 | ... BJ56: =SUMIFS(Details!$CP$5:$CP$11,Details!$C$5:$C$11,Summary!BJ$5,Details!$CK$5:$CK$11,Summary!$AX$5) -> 0 | BK56: =SUM(AY56:BJ56) -> 0
D57: =SUMIFS(Details!$R$5:$R$11,Details!$C$5:$C$11,Summary!D$5)/1000 -> 0 | E57: =SUMIFS(Details!$R$5:$R$11,Details!$C$5:$C$11,Summary!E$5)/1000 -> 0 | F57: =SUMIFS(Details!$R$5:$R$11,Details!$C$5:$C$11,Summary!F$5)/1000 -> 0 | G57: =SUMIFS(Details!$R$5:$R$11,Details!$C$5:$C$11,Summary!G$5)/1000 -> 0 | H57: =SUMIFS(Details!$R$5:$R$11,Details!$C$5:$C$11,Summary!H$5)/1000 -> 0 | I57: =SUMIFS(Details!$R$5:$R$11,Details!$C$5:$C$11,Summary!I$5)/1000 -> 0 | J57: =SUMIFS(Details!$R$5:$R$11,Details!$C$5:$C$11,Summary!J$5)/1000 -> 0 | K57: =SUMIFS(Details!$R$5:$R$11,Details!$C$5:$C$11,Summary!K$5)/1000 -> 0 | ... O57: =SUMIFS(Details!$R$5:$R$11,Details!$C$5:$C$11,Summary!O$5)/1000 -> 0 | P57: =SUM(D57:O57) -> 0 | BM57: =(AG51+AV51+BK51)-P57 -> 0
C59: Margins | D59: =D5 -> 46113 | E59: =E5 -> 46143 | F59: =F5 -> 46174 | G59: =G5 -> 46204 | H59: =H5 -> 46235 | I59: =I5 -> 46266 | J59: =J5 -> 46296 | K59: =K5 -> 46327 | ... P59: =P5 -> FY 2026-27
C60: Gross Margin | D60: =SUMIFS(Details!$CN$5:$CN$11,Details!$C$5:$C$11,Summary!D$5) -> 3460 | E60: =SUMIFS(Details!$CN$5:$CN$11,Details!$C$5:$C$11,Summary!E$5) -> 4080 | F60: =SUMIFS(Details!$CN$5:$CN$11,Details!$C$5:$C$11,Summary!F$5) -> 11050 | G60: =SUMIFS(Details!$CN$5:$CN$11,Details!$C$5:$C$11,Summary!G$5) -> 0 | H60: =SUMIFS(Details!$CN$5:$CN$11,Details!$C$5:$C$11,Summary!H$5) -> 0 | I60: =SUMIFS(Details!$CN$5:$CN$11,Details!$C$5:$C$11,Summary!I$5) -> 0 | J60: =SUMIFS(Details!$CN$5:$CN$11,Details!$C$5:$C$11,Summary!J$5) -> 0 | K60: =SUMIFS(Details!$CN$5:$CN$11,Details!$C$5:$C$11,Summary!K$5) -> 0 | ... O60: =SUMIFS(Details!$CN$5:$CN$11,Details!$C$5:$C$11,Summary!O$5) -> 0 | P60: =SUM(D60:O60) -> 18590
C61: Recykal Margin | D61: =SUMIFS(Details!$CO$5:$CO$11,Details!$C$5:$C$11,Summary!D$5) -> 3460 | E61: =SUMIFS(Details!$CO$5:$CO$11,Details!$C$5:$C$11,Summary!E$5) -> 4080 | F61: =SUMIFS(Details!$CO$5:$CO$11,Details!$C$5:$C$11,Summary!F$5) -> 11050 | G61: =SUMIFS(Details!$CO$5:$CO$11,Details!$C$5:$C$11,Summary!G$5) -> 0 | H61: =SUMIFS(Details!$CO$5:$CO$11,Details!$C$5:$C$11,Summary!H$5) -> 0 | I61: =SUMIFS(Details!$CO$5:$CO$11,Details!$C$5:$C$11,Summary!I$5) -> 0 | J61: =SUMIFS(Details!$CO$5:$CO$11,Details!$C$5:$C$11,Summary!J$5) -> 0 | K61: =SUMIFS(Details!$CO$5:$CO$11,Details!$C$5:$C$11,Summary!K$5) -> 0 | ... O61: =SUMIFS(Details!$CO$5:$CO$11,Details!$C$5:$C$11,Summary!O$5) -> 0 | P61: =SUM(D61:O61) -> 18590
C62: Net Margin | D62: =SUMIFS(Details!$CP$5:$CP$11,Details!$C$5:$C$11,Summary!D$5) -> 3460 | E62: =SUMIFS(Details!$CP$5:$CP$11,Details!$C$5:$C$11,Summary!E$5) -> 4080 | F62: =SUMIFS(Details!$CP$5:$CP$11,Details!$C$5:$C$11,Summary!F$5) -> 11050 | G62: =SUMIFS(Details!$CP$5:$CP$11,Details!$C$5:$C$11,Summary!G$5) -> 0 | H62: =SUMIFS(Details!$CP$5:$CP$11,Details!$C$5:$C$11,Summary!H$5) -> 0 | I62: =SUMIFS(Details!$CP$5:$CP$11,Details!$C$5:$C$11,Summary!I$5) -> 0 | J62: =SUMIFS(Details!$CP$5:$CP$11,Details!$C$5:$C$11,Summary!J$5) -> 0 | K62: =SUMIFS(Details!$CP$5:$CP$11,Details!$C$5:$C$11,Summary!K$5) -> 0 | ... O62: =SUMIFS(Details!$CP$5:$CP$11,Details!$C$5:$C$11,Summary!O$5) -> 0 | P62: =SUM(D62:O62) -> 18590
C64: Financial with GST | D64: Sales | E64: Purchases
C65: =Details!P22 -> 46187 | D65: =SUMIFS(Details!$BQ$5:$BQ$11,Details!$D$5:$D$11,Summary!$C65)*118% -> 0 | E65: =SUMIFS(Details!$AM$5:$AM$11,Details!$D$5:$D$11,Summary!$C65)*118% -> 0
C66: =TEXT(C65,"mmm-yy") -> Jun-26 | D66: =SUMIFS(Details!$BQ$5:$BQ$11,Details!$C$5:$C$11,Summary!$C66)*118% -> 23541 | E66: =SUMIFS(Details!$AM$5:$AM$11,Details!$C$5:$C$11,Summary!$C66)*118% -> 10502
C67: Fy 2025-26 | D67: =Details!BQ12*118% -> 103592.2 | E67: =Details!AM12*118% -> 81656

Sheet Details
AA1: 0
B3: Raw Data -M4 | F3: Purchase Details | U3: Logistic Details of the transaction | AF3: Debit Notes to Suppliers | AM3: Sales Details | BD3: DN to Customer | BH3: Credit Notes from Customers | BO3: 0 | BU3: To be checked | BX3: CN & DN Checks | CH3: Without Provisions | CM3: Margin Buckets | CP3: Financials with GST
B4: Quarter | C4: Month | D4: Date | E4: Shipment ID | F4: Supplier Name | G4: GST Reg No. | H4: Vendor Invoice No. | I4: Vendor Invoice Date | J4: P V No. | K4: P V Date | L4: State (Origin) | M4: Vehicle No. | N4: Material | O4: Qty (Kg) | P4: Price/Kg | Q4: Purchase Price | R4: Return Qty | S4: Net Qty | T4: Basic Customs Duty | U4: Transporter Name | V4: LR NO/BILL NO | W4: J V No. | X4: JV Date | Y4: Logistics cost | Z4: Debit note on logistic cost | AA4: Logistics Provision | AB4: Total Logistics Cost | AC4: Operational Cost | AD4: Cost/Kg. | AE4: Divertion/Internal | AF4: Debit Note No. | AG4: Debit Note Date. | AH4: Debit Note No. 2 | AI4: Debit Note Date. 2 | AJ4: Full Debit Note | AK4: Actual Debit Note | AL4: Provision for DN | AM4: Total Cost | AN4: Inv. Date | AO4: Inv. No. | AP4: Customer ID | AQ4: Buyer Name | AR4: Buyer GST Number | AS4: Location (Origin) | AT4: Location (Destination) | AU4: State (Destination) | AV4: E-WayBill Number | AW4: Qty(Kg) | AX4: Rate/Kg | AY4: Amount | AZ4: Qty Check | BA4: Return Qty | BB4: Net Qty | BC4: Divertion/Internal | BD4: Return Type | BE4: Date : DN to Buyer | BF4: DN to Buyer | BG4: Amount | BH4: Credit Note No:1 | BI4: CN Date. No:1 | BJ4: Credit Note No:2 | BK4: CN Date. No:2 | BL4: Cash Discount(Provision) | BM4: Cash Discount | BN4: Full Credit Notes | BO4: Actual Credit Note | BP4: Provision for CN | BQ4: Net Revenue | BR4: Margin | BS4: Reamrks - Margin | BT4: Remarks | BU4: LMI @ Inception | BV4: Remarks @ Inception | BW4: Margin (%) | BX4: Margin Bucket | BY4: Total CN(Inc.Provisions) | BZ4: Total DN(Inc.Provisions) | CA4: Check | CB4: Actaul CN | CC4: Actual DN | CD4: Check | CE4: Material-Short Form | CF4: Supplier Type | CG4: Month | CH4: Cost | CI4: Revenue | CJ4: Week No: | CK4: Category (Material) | CL4: Broad Category | CM4: Customer POC Name | CN4: Gross Margin | CO4: Recykal Margin | CP4: Net Margin | CQ4: Sales | CR4: Purchases | CS4: Credit Note | CT4: Debit Note | CU4: Margin | CV4: Bill Branch | CW4: Inv Branch | CX4: Vendor PAN No | CY4: Customer PAN No | CZ4: GST TDS Applicability | DA4: Cash Discount. No | DB4: CD Date | DC4: Cash Discount. No.2 | DD4: CD Date.2 | DE4: Total DN | DF4: Total CN
B5: ="Q" & IF(ROUNDUP(MONTH(D5)/3,0)-1=0,4,ROUNDUP(MONTH(D5)/3,0)-1) -> Q1 | C5: =TEXT(AN5,"mmm-yy") -> Apr-26 | D5: 46134 | E5: SH04262802 | F5: SRP ACE GREEN MARKETING | G5: 33AELFS5871E1ZT | H5: ACE/26-27/0046 | I5: 46134 | J5: 26-27/PUR/001499 | K5: 46140 | L5: TN | N5: Polo T Shirt | O5: 62 | P5: 450 | Q5: =O5*P5 -> 27900 | R5: 0 | S5: =O5-R5 -> 62 | T5: 0 | U5: 0 | V5: 0 | W5: 0 | X5: 0 | Y5: 0 | Z5: 0 | AA5: 0 | AB5: =Y5+AA5+Z5 -> 0 | AC5: 0 | AD5: 0 | AE5: 0 | AF5: 0 | AG5: 0 | AH5: 0 | AI5: 0 | AJ5: 0 | AK5: 0 | AL5: 0 | AM5: =Q5+AB5+AL5+AK5+AJ5+T5+AE5 -> 27900 | AN5: 46140 | AO5: 36/M4/27IN00001 | AP5: 832139000059026300 | AQ5: INFINITYBOX PRIVATE LIMITED | AR5: 29AAFCI4561G1ZF | AS5: Hyderabad Telangana 500032 | AT5: Bengaluru | AU5: Karnataka | AV5: 0 | AW5: 62 | AX5: 530 | AY5: =AW5*AX5 -> 32860 | AZ5: =AW5=O5 -> TRUE | BA5: 0 | BB5: =AW5-BA5 -> 62 | BC5: 0 | BD5: Regular | BE5: 0 | BF5: 0 | BG5: 0 | BH5: 0 | BI5: 0 | BJ5: 0 | BK5: 0 | BL5: 0 | BM5: 0 | BN5: 0 | BO5: 0 | BP5: =AY5*$BO$3 -> 0 | BQ5: =AY5+BN5+BO5+BP5+BC5+BG5+BM5+BL5 -> 32860 | BR5: =BQ5-AM5 -> 4960 | BS5: =IF(BR5>=0,"Positive Margin","Negative Margin") -> Positive Margin | BT5: DN & CN Provision | BU5: =AY5-Y5-Q5-AA5-T5+BC5 -> 4960 | BV5: =IF(BU5<0, "Negative Margin at Inception", "Positive Margin at Inception") -> Positive Margin at Inception | BW5: =IFERROR(BR5/BQ5,"0") -> 0.1509434 | BX5: =IF(BW5<1%,"Less Than 1%",IF(BW5>2%,"More than 2%",IF(BW5>=1%,"1% - 2%"))) -> More than 2% | BY5: =BO5+BP5 -> 0 | BZ5: =AL5+AK5 -> 0 | CA5: =BY5-BZ5 -> 0 | CB5: =BO5 -> 0 | CC5: =AK5 -> 0 | CD5: =CB5-CC5 -> 0 | CE5: Marketplace (Metal Waste) | CF5: =_xlfn.XLOOKUP(G5,'Supplier Metrics'!C:C,'Supplier Metrics'!H:H) -> Manufacturer | CG5: =TEXT(AN5,"mmm-yy") -> Apr-26 | CH5: =AM5-AL5 -> 27900 | CI5: =BQ5-BP5 -> 32860 | CJ5: =INT((D5- IF(MONTH(D5) >= 4, DATE(YEAR(D5), 4, 1), DATE(YEAR(D5)-1, 4, 1))) / 7) + 1 -> 4 | CK5: {=_xlfn.XLOOKUP(N5,#REF!,#REF!)} -> #REF! | CM5: =_xlfn.XLOOKUP(AR5,Receivables!B:B,Receivables!D:D) -> #N/A | CN5: =AY5-Q5 -> 4960 | CO5: =CN5-AB5 -> 4960 | CP5: =BQ5-AM5 -> 4960 | CQ5: =AY5*118% -> 38774.8 | CR5: =Q5*118% -> 32922 | CS5: =CB5*118% -> 0 | CT5: =CC5*118% -> 0 | CU5: =(CQ5-CS5)-(CR5-CT5) -> 5852.8 | CV5: Telangana - HO | CW5: Telangana - HO | CX5: =MID(G5,3,10) -> AELFS5871E | CY5: =MID(AR5,3,10) -> AAFCI4561G | CZ5: No | DA5: 0 | DB5: 0 | DC5: 0 | DD5: 0 | DE5: =AE5+AJ5+AK5 -> 0 | DF5: =BN5+BO5+BC5 -> 0
B6: ="Q" & IF(ROUNDUP(MONTH(D6)/3,0)-1=0,4,ROUNDUP(MONTH(D6)/3,0)-1) -> Q1 | C6: =TEXT(AN6,"mmm-yy") -> Apr-26 | D6: 46134 | E6: SH04262802 | F6: SRP ACE GREEN MARKETING | G6: 33AELFS5871E1ZT | H6: ACE/26-27/0046 | I6: 46134 | J6: 26-27/PUR/001499 | K6: 46140 | L6: TN | N6: Transport Charge | O6: 1 | P6: 1500 | Q6: =O6*P6 -> 1500 | R6: 0 | S6: =O6-R6 -> 1 | T6: 0 | U6: 0 | V6: 0 | W6: 0 | X6: 0 | Y6: 0 | Z6: 0 | AA6: 0 | AB6: =Y6+AA6+Z6 -> 0 | AC6: 0 | AD6: 0 | AE6: 0 | AF6: 0 | AG6: 0 | AH6: 0 | AI6: 0 | AJ6: 0 | AK6: 0 | AL6: 0 | AM6: =Q6+AB6+AL6+AK6+AJ6+T6+AE6 -> 1500 | AN6: 46140 | AO6: 36/M4/27IN00001 | AP6: 832139000059026300 | AQ6: INFINITYBOX PRIVATE LIMITED | AR6: 29AAFCI4561G1ZF | AS6: Hyderabad Telangana 500032 | AT6: Bengaluru | AU6: Karnataka | AV6: 0 | AW6: 0 | AX6: 0 | AY6: =AW6*AX6 -> 0 | AZ6: =AW6=O6 -> FALSE | BA6: 0 | BB6: =AW6-BA6 -> 0 | BC6: 0 | BD6: Regular | BE6: 0 | BF6: 0 | BG6: 0 | BH6: 0 | BI6: 0 | BJ6: 0 | BK6: 0 | BL6: 0 | BM6: 0 | BN6: 0 | BO6: 0 | BP6: =AY6*$BO$3 -> 0 | BQ6: =AY6+BN6+BO6+BP6+BC6+BG6+BM6+BL6 -> 0 | BR6: =BQ6-AM6 -> -1500 | BS6: =IF(BR6>=0,"Positive Margin","Negative Margin") -> Negative Margin | BT6: DN & CN Provision | BU6: =AY6-Y6-Q6-AA6-T6+BC6 -> -1500 | BV6: =IF(BU6<0, "Negative Margin at Inception", "Positive Margin at Inception") -> Negative Margin at Inception | BW6: =IFERROR(BR6/BQ6,"0") -> 0 | BX6: =IF(BW6<1%,"Less Than 1%",IF(BW6>2%,"More than 2%",IF(BW6>=1%,"1% - 2%"))) -> More than 2% | BY6: =BO6+BP6 -> 0 | BZ6: =AL6+AK6 -> 0 | CA6: =BY6-BZ6 -> 0 | CB6: =BO6 -> 0 | CC6: =AK6 -> 0 | CD6: =CB6-CC6 -> 0 | CE6: Marketplace (Metal Waste) | CF6: =_xlfn.XLOOKUP(G6,'Supplier Metrics'!C:C,'Supplier Metrics'!H:H) -> Manufacturer | CG6: =TEXT(AN6,"mmm-yy") -> Apr-26 | CH6: =AM6-AL6 -> 1500 | CI6: =BQ6-BP6 -> 0 | CJ6: =INT((D6- IF(MONTH(D6) >= 4, DATE(YEAR(D6), 4, 1), DATE(YEAR(D6)-1, 4, 1))) / 7) + 1 -> 4 | CK6: {=_xlfn.XLOOKUP(N6,#REF!,#REF!)} -> #REF! | CM6: =_xlfn.XLOOKUP(AR6,Receivables!B:B,Receivables!D:D) -> #N/A | CN6: =AY6-Q6 -> -1500 | CO6: =CN6-AB6 -> -1500 | CP6: =BQ6-AM6 -> -1500 | CQ6: =AY6*118% -> 0 | CR6: =Q6*118% -> 1770 | CS6: =CB6*118% -> 0 | CT6: =CC6*118% -> 0 | CU6: =(CQ6-CS6)-(CR6-CT6) -> -1770 | CV6: Telangana - HO | CW6: Telangana - HO | CX6: =MID(G6,3,10) -> AELFS5871E | CY6: =MID(AR6,3,10) -> AAFCI4561G | CZ6: No | DA6: 0 | DB6: 0 | DC6: 0 | DD6: 0 | DE6: =AE6+AJ6+AK6 -> 0 | DF6: =BN6+BO6+BC6 -> 0
B7: ="Q" & IF(ROUNDUP(MONTH(D7)/3,0)-1=0,4,ROUNDUP(MONTH(D7)/3,0)-1) -> Q1 | C7: =TEXT(AN7,"mmm-yy") -> May-26 | D7: 46156 | E7: SH05261901 | F7: SRP ACE GREEN MARKETING | G7: 33AELFS5871E1ZT | H7: ACE/26-27/0068 | I7: 46156 | J7: 26-27/PUR/002300 | K7: 46161 | L7: TN | N7: Polo T Shirt | O7: 66 | P7: 450 | Q7: =O7*P7 -> 29700 | R7: 0 | S7: =O7-R7 -> 66 | T7: 0 | U7: 0 | V7: 0 | W7: 0 | X7: 0 | Y7: 0 | Z7: 0 | AA7: 0 | AB7: =Y7+AA7+Z7 -> 0 | AC7: 0 | AD7: 0 | AE7: 0 | AF7: 0 | AG7: 0 | AH7: 0 | AI7: 0 | AJ7: 0 | AK7: 0 | AL7: 0 | AM7: =Q7+AB7+AL7+AK7+AJ7+T7+AE7 -> 29700 | AN7: 46161 | AO7: 36/M4/27IN00002 | AP7: 832139000059026300 | AQ7: INFINITYBOX PRIVATE LIMITED | AR7: 29AAFCI4561G1ZF | AS7: Hyderabad Telangana 500032 | AT7: Bengaluru | AU7: Karnataka | AV7: 0 | AW7: 66 | AX7: 530 | AY7: =AW7*AX7 -> 34980 | AZ7: =AW7=O7 -> TRUE | BA7: 0 | BB7: =AW7-BA7 -> 66 | BC7: 0 | BD7: Regular | BE7: 0 | BF7: 0 | BG7: 0 | BH7: 0 | BI7: 0 | BJ7: 0 | BK7: 0 | BL7: 0 | BM7: 0 | BN7: 0 | BO7: 0 | BP7: =AY7*$BO$3 -> 0 | BQ7: =AY7+BN7+BO7+BP7+BC7+BG7+BM7+BL7 -> 34980 | BR7: =BQ7-AM7 -> 5280 | BS7: =IF(BR7>=0,"Positive Margin","Negative Margin") -> Positive Margin | BT7: DN & CN Provision | BU7: =AY7-Y7-Q7-AA7-T7+BC7 -> 5280 | BV7: =IF(BU7<0, "Negative Margin at Inception", "Positive Margin at Inception") -> Positive Margin at Inception | BW7: =IFERROR(BR7/BQ7,"0") -> 0.1509434 | BX7: =IF(BW7<1%,"Less Than 1%",IF(BW7>2%,"More than 2%",IF(BW7>=1%,"1% - 2%"))) -> More than 2% | BY7: =BO7+BP7 -> 0 | BZ7: =AL7+AK7 -> 0 | CA7: =BY7-BZ7 -> 0 | CB7: =BO7 -> 0 | CC7: =AK7 -> 0 | CD7: =CB7-CC7 -> 0 | CE7: Marketplace (Metal Waste) | CF7: =_xlfn.XLOOKUP(G7,'Supplier Metrics'!C:C,'Supplier Metrics'!H:H) -> Manufacturer | CG7: =TEXT(AN7,"mmm-yy") -> May-26 | CH7: =AM7-AL7 -> 29700 | CI7: =BQ7-BP7 -> 34980 | CJ7: =INT((D7- IF(MONTH(D7) >= 4, DATE(YEAR(D7), 4, 1), DATE(YEAR(D7)-1, 4, 1))) / 7) + 1 -> 7 | CK7: {=_xlfn.XLOOKUP(N7,#REF!,#REF!)} -> #REF! | CM7: =_xlfn.XLOOKUP(AR7,Receivables!B:B,Receivables!D:D) -> #N/A | CN7: =AY7-Q7 -> 5280 | CO7: =CN7-AB7 -> 5280 | CP7: =BQ7-AM7 -> 5280 | CQ7: =AY7*118% -> 41276.4 | CR7: =Q7*118% -> 35046 | CS7: =CB7*118% -> 0 | CT7: =CC7*118% -> 0 | CU7: =(CQ7-CS7)-(CR7-CT7) -> 6230.4 | CV7: Telangana - HO | CW7: Telangana - HO | CX7: =MID(G7,3,10) -> AELFS5871E | CY7: =MID(AR7,3,10) -> AAFCI4561G | CZ7: No | DA7: 0 | DB7: 0 | DC7: 0 | DD7: 0 | DE7: =AE7+AJ7+AK7 -> 0 | DF7: =BN7+BO7+BC7 -> 0
B8: ="Q" & IF(ROUNDUP(MONTH(D8)/3,0)-1=0,4,ROUNDUP(MONTH(D8)/3,0)-1) -> Q1 | C8: =TEXT(AN8,"mmm-yy") -> May-26 | D8: 46156 | E8: SH05261901 | F8: SRP ACE GREEN MARKETING | G8: 33AELFS5871E1ZT | H8: ACE/26-27/0068 | I8: 46156 | J8: 26-27/PUR/002300 | K8: 46161 | L8: TN | N8: Transport Charge | O8: 1 | P8: 1200 | Q8: =O8*P8 -> 1200 | R8: 0 | S8: =O8-R8 -> 1 | T8: 0 | U8: 0 | V8: 0 | W8: 0 | X8: 0 | Y8: 0 | Z8: 0 | AA8: 0 | AB8: =Y8+AA8+Z8 -> 0 | AC8: 0 | AD8: 0 | AE8: 0 | AF8: 0 | AG8: 0 | AH8: 0 | AI8: 0 | AJ8: 0 | AK8: 0 | AL8: 0 | AM8: =Q8+AB8+AL8+AK8+AJ8+T8+AE8 -> 1200 | AN8: 46161 | AO8: 36/M4/27IN00002 | AP8: 832139000059026300 | AQ8: INFINITYBOX PRIVATE LIMITED | AR8: 29AAFCI4561G1ZF | AS8: Hyderabad Telangana 500032 | AT8: Bengaluru | AU8: Karnataka | AV8: 0 | AW8: 0 | AX8: 0 | AY8: 0 | AZ8: =AW8=O8 -> FALSE | BA8: 0 | BB8: =AW8-BA8 -> 0 | BC8: 0 | BD8: Regular | BE8: 0 | BF8: 0 | BG8: 0 | BH8: 0 | BI8: 0 | BJ8: 0 | BK8: 0 | BL8: 0 | BM8: 0 | BN8: 0 | BO8: 0 | BP8: =AY8*$BO$3 -> 0 | BQ8: =AY8+BN8+BO8+BP8+BC8+BG8+BM8+BL8 -> 0 | BR8: =BQ8-AM8 -> -1200 | BS8: =IF(BR8>=0,"Positive Margin","Negative Margin") -> Negative Margin | BT8: DN & CN Provision | BU8: =AY8-Y8-Q8-AA8-T8+BC8 -> -1200 | BV8: =IF(BU8<0, "Negative Margin at Inception", "Positive Margin at Inception") -> Negative Margin at Inception | BW8: =IFERROR(BR8/BQ8,"0") -> 0 | BX8: =IF(BW8<1%,"Less Than 1%",IF(BW8>2%,"More than 2%",IF(BW8>=1%,"1% - 2%"))) -> More than 2% | BY8: =BO8+BP8 -> 0 | BZ8: =AL8+AK8 -> 0 | CA8: =BY8-BZ8 -> 0 | CB8: =BO8 -> 0 | CC8: =AK8 -> 0 | CD8: =CB8-CC8 -> 0 | CE8: Marketplace (Metal Waste) | CF8: =_xlfn.XLOOKUP(G8,'Supplier Metrics'!C:C,'Supplier Metrics'!H:H) -> Manufacturer | CG8: =TEXT(AN8,"mmm-yy") -> May-26 | CH8: =AM8-AL8 -> 1200 | CI8: =BQ8-BP8 -> 0 | CJ8: =INT((D8- IF(MONTH(D8) >= 4, DATE(YEAR(D8), 4, 1), DATE(YEAR(D8)-1, 4, 1))) / 7) + 1 -> 7 | CK8: {=_xlfn.XLOOKUP(N8,#REF!,#REF!)} -> #REF! | CM8: =_xlfn.XLOOKUP(AR8,Receivables!B:B,Receivables!D:D) -> #N/A | CN8: =AY8-Q8 -> -1200 | CO8: =CN8-AB8 -> -1200 | CP8: =BQ8-AM8 -> -1200 | CQ8: =AY8*118% -> 0 | CR8: =Q8*118% -> 1416 | CS8: =CB8*118% -> 0 | CT8: =CC8*118% -> 0 | CU8: =(CQ8-CS8)-(CR8-CT8) -> -1416 | CV8: Telangana - HO | CW8: Telangana - HO | CX8: =MID(G8,3,10) -> AELFS5871E | CY8: =MID(AR8,3,10) -> AAFCI4561G | CZ8: No | DA8: 0 | DB8: 0 | DC8: 0 | DD8: 0 | DE8: =AE8+AJ8+AK8 -> 0 | DF8: =BN8+BO8+BC8 -> 0
B9: ="Q" & IF(ROUNDUP(MONTH(D9)/3,0)-1=0,4,ROUNDUP(MONTH(D9)/3,0)-1) -> Q1 | C9: =TEXT(AN9,"mmm-yy") -> Jun-26 | D9: 46182 | E9: SH06261002 | F9: SRP ACE GREEN MARKETING | G9: 33AELFS5871E1ZT | H9: ACE/26-27/0107 | I9: 46182 | J9: 26-27/PUR/003546 | K9: 46183 | L9: TN | N9: Recycle Cap | O9: 70 | P9: 110 | Q9: =O9*P9 -> 7700 | R9: 0 | S9: =O9-R9 -> 70 | T9: 0 | U9: 0 | V9: 0 | W9: 0 | X9: 0 | Y9: 0 | Z9: 0 | AA9: 0 | AB9: =Y9+AA9+Z9 -> 0 | AC9: 0 | AD9: 0 | AE9: 0 | AF9: 0 | AG9: 0 | AH9: 0 | AI9: 0 | AJ9: 0 | AK9: 0 | AL9: 0 | AM9: =Q9+AB9+AL9+AK9+AJ9+T9+AE9 -> 7700 | AN9: 46183 | AO9: 36/M4/27IN00003 | AP9: 832139000059026300 | AQ9: INFINITYBOX PRIVATE LIMITED | AR9: 29AAFCI4561G1ZF | AS9: Hyderabad Telangana 500032 | AT9: Bengaluru | AU9: Karnataka | AV9: 0 | AW9: 70 | AX9: 285 | AY9: =AW9*AX9 -> 19950 | AZ9: =AW9=O9 -> TRUE | BA9: 0 | BB9: =AW9-BA9 -> 70 | BC9: 0 | BD9: Regular | BE9: 0 | BF9: 0 | BG9: 0 | BH9: 0 | BI9: 0 | BJ9: 0 | BK9: 0 | BL9: 0 | BM9: 0 | BN9: 0 | BO9: 0 | BP9: =AY9*$BO$3 -> 0 | BQ9: =AY9+BN9+BO9+BP9+BC9+BG9+BM9+BL9 -> 19950 | BR9: =BQ9-AM9 -> 12250 | BS9: =IF(BR9>=0,"Positive Margin","Negative Margin") -> Positive Margin | BT9: DN & CN Provision | BU9: =AY9-Y9-Q9-AA9-T9+BC9 -> 12250 | BV9: =IF(BU9<0, "Negative Margin at Inception", "Positive Margin at Inception") -> Positive Margin at Inception | BW9: =IFERROR(BR9/BQ9,"0") -> 0.61403509 | BX9: =IF(BW9<1%,"Less Than 1%",IF(BW9>2%,"More than 2%",IF(BW9>=1%,"1% - 2%"))) -> More than 2% | BY9: =BO9+BP9 -> 0 | BZ9: =AL9+AK9 -> 0 | CA9: =BY9-BZ9 -> 0 | CB9: =BO9 -> 0 | CC9: =AK9 -> 0 | CD9: =CB9-CC9 -> 0 | CE9: Marketplace (Metal Waste) | CF9: =_xlfn.XLOOKUP(G9,'Supplier Metrics'!C:C,'Supplier Metrics'!H:H) -> Manufacturer | CG9: =TEXT(AN9,"mmm-yy") -> Jun-26 | CH9: =AM9-AL9 -> 7700 | CI9: =BQ9-BP9 -> 19950 | CJ9: =INT((D9- IF(MONTH(D9) >= 4, DATE(YEAR(D9), 4, 1), DATE(YEAR(D9)-1, 4, 1))) / 7) + 1 -> 10 | CK9: {=_xlfn.XLOOKUP(N9,#REF!,#REF!)} -> #REF! | CM9: =_xlfn.XLOOKUP(AR9,Receivables!B:B,Receivables!D:D) -> #N/A | CN9: =AY9-Q9 -> 12250 | CO9: =CN9-AB9 -> 12250 | CP9: =BQ9-AM9 -> 12250 | CQ9: =AY9*118% -> 23541 | CR9: =Q9*118% -> 9086 | CS9: =CB9*118% -> 0 | CT9: =CC9*118% -> 0 | CU9: =(CQ9-CS9)-(CR9-CT9) -> 14455 | CV9: Telangana - HO | CW9: Telangana - HO | CX9: =MID(G9,3,10) -> AELFS5871E | CY9: =MID(AR9,3,10) -> AAFCI4561G | CZ9: No | DA9: 0 | DB9: 0 | DC9: 0 | DD9: 0 | DE9: =AE9+AJ9+AK9 -> 0 | DF9: =BN9+BO9+BC9 -> 0
B10: ="Q" & IF(ROUNDUP(MONTH(D10)/3,0)-1=0,4,ROUNDUP(MONTH(D10)/3,0)-1) -> Q1 | C10: =TEXT(AN10,"mmm-yy") -> Jun-26 | D10: 46182 | E10: SH06261002 | F10: SRP ACE GREEN MARKETING | G10: 33AELFS5871E1ZT | H10: ACE/26-27/0107 | I10: 46182 | J10: 26-27/PUR/003546 | K10: 46183 | L10: TN | N10: Transport Charge | O10: 1 | P10: 1200 | Q10: =O10*P10 -> 1200 | R10: 0 | S10: =O10-R10 -> 1 | T10: 0 | U10: 0 | V10: 0 | W10: 0 | X10: 0 | Y10: 0 | Z10: 0 | AA10: 0 | AB10: =Y10+AA10+Z10 -> 0 | AC10: 0 | AD10: 0 | AE10: 0 | AF10: 0 | AG10: 0 | AH10: 0 | AI10: 0 | AJ10: 0 | AK10: 0 | AL10: 0 | AM10: =Q10+AB10+AL10+AK10+AJ10+T10+AE10 -> 1200 | AN10: 46183 | AO10: 36/M4/27IN00003 | AP10: 832139000059026300 | AQ10: INFINITYBOX PRIVATE LIMITED | AR10: 29AAFCI4561G1ZF | AS10: Hyderabad Telangana 500032 | AT10: Bengaluru | AU10: Karnataka | AV10: 0 | AW10: 0 | AX10: 0 | AY10: 0 | AZ10: =AW10=O10 -> FALSE | BA10: 0 | BB10: =AW10-BA10 -> 0 | BC10: 0 | BD10: Regular | BE10: 0 | BF10: 0 | BG10: 0 | BH10: 0 | BI10: 0 | BJ10: 0 | BK10: 0 | BL10: 0 | BM10: 0 | BN10: 0 | BO10: 0 | BP10: =AY10*$BO$3 -> 0 | BQ10: =AY10+BN10+BO10+BP10+BC10+BG10+BM10+BL10 -> 0 | BR10: =BQ10-AM10 -> -1200 | BS10: =IF(BR10>=0,"Positive Margin","Negative Margin") -> Negative Margin | BT10: DN & CN Provision | BU10: =AY10-Y10-Q10-AA10-T10+BC10 -> -1200 | BV10: =IF(BU10<0, "Negative Margin at Inception", "Positive Margin at Inception") -> Negative Margin at Inception | BW10: =IFERROR(BR10/BQ10,"0") -> 0 | BX10: =IF(BW10<1%,"Less Than 1%",IF(BW10>2%,"More than 2%",IF(BW10>=1%,"1% - 2%"))) -> More than 2% | BY10: =BO10+BP10 -> 0 | BZ10: =AL10+AK10 -> 0 | CA10: =BY10-BZ10 -> 0 | CB10: =BO10 -> 0 | CC10: =AK10 -> 0 | CD10: =CB10-CC10 -> 0 | CE10: Marketplace (Metal Waste) | CF10: =_xlfn.XLOOKUP(G10,'Supplier Metrics'!C:C,'Supplier Metrics'!H:H) -> Manufacturer | CG10: =TEXT(AN10,"mmm-yy") -> Jun-26 | CH10: =AM10-AL10 -> 1200 | CI10: =BQ10-BP10 -> 0 | CJ10: =INT((D10- IF(MONTH(D10) >= 4, DATE(YEAR(D10), 4, 1), DATE(YEAR(D10)-1, 4, 1))) / 7) + 1 -> 10 | CK10: {=_xlfn.XLOOKUP(N10,#REF!,#REF!)} -> #REF! | CM10: =_xlfn.XLOOKUP(AR10,Receivables!B:B,Receivables!D:D) -> #N/A | CN10: =AY10-Q10 -> -1200 | CO10: =CN10-AB10 -> -1200 | CP10: =BQ10-AM10 -> -1200 | CQ10: =AY10*118% -> 0 | CR10: =Q10*118% -> 1416 | CS10: =CB10*118% -> 0 | CT10: =CC10*118% -> 0 | CU10: =(CQ10-CS10)-(CR10-CT10) -> -1416 | CV10: Telangana - HO | CW10: Telangana - HO | CX10: =MID(G10,3,10) -> AELFS5871E | CY10: =MID(AR10,3,10) -> AAFCI4561G | CZ10: No | DA10: 0 | DB10: 0 | DC10: 0 | DD10: 0 | DE10: =AE10+AJ10+AK10 -> 0 | DF10: =BN10+BO10+BC10 -> 0
F12: Total | O12: =SUBTOTAL(9,O5:O11) -> 201 | Q12: =SUBTOTAL(9,Q5:Q11) -> 69200 | R12: =SUBTOTAL(9,R5:R11) -> 0 | S12: =SUBTOTAL(9,S5:S11) -> 201 | T12: =SUBTOTAL(9,T5:T11) -> 0 | Y12: =SUBTOTAL(9,Y5:Y11) -> 0 | Z12: =SUBTOTAL(9,Z5:Z11) -> 0 | AA12: =SUBTOTAL(9,AA5:AA11) -> 0 | AB12: =SUBTOTAL(9,AB5:AB11) -> 0 | AC12: =SUBTOTAL(9,AC5:AC11) -> 0 | AD12: =SUBTOTAL(1,AD5:AD11) -> 0 | AE12: =SUBTOTAL(9,AE5:AE11) -> 0 | AJ12: =SUBTOTAL(9,AJ5:AJ11) -> 0 | AK12: =SUBTOTAL(9,AK5:AK11) -> 0 | AL12: =SUBTOTAL(9,AL5:AL11) -> 0 | AM12: =SUBTOTAL(9,AM5:AM11) -> 69200 | AW12: =SUBTOTAL(9,AW5:AW11) -> 198 | AX12: =SUBTOTAL(101,AX5:AX11) -> 224.16667 | AY12: =SUBTOTAL(9,AY5:AY11) -> 87790 | BA12: =SUBTOTAL(9,BA5:BA11) -> 0 | BB12: =SUBTOTAL(9,BB5:BB11) -> 198 | BC12: =SUBTOTAL(9,BC5:BC11) -> 0 | BG12: =SUBTOTAL(9,BG5:BG11) -> 0 | BL12: =SUBTOTAL(9,BL5:BL11) -> 0 | BM12: =SUBTOTAL(9,BM5:BM11) -> 0 | BN12: =SUBTOTAL(9,BN5:BN11) -> 0 | BO12: =SUBTOTAL(9,BO5:BO11) -> 0 | BP12: =SUBTOTAL(9,BP5:BP11) -> 0 | BQ12: =SUBTOTAL(9,BQ5:BQ11) -> 87790 | BR12: =SUBTOTAL(9,BR5:BR11) -> 18590 | BU12: =SUBTOTAL(9,BU5:BU11) -> 18590 | BY12: =SUBTOTAL(9,BY1:BY11) -> 0 | BZ12: =SUBTOTAL(9,BZ1:BZ11) -> 0 | CA12: =SUBTOTAL(9,CA1:CA11) -> 0 | CB12: =SUBTOTAL(9,CB5:CB11) -> 0 | CC12: =SUBTOTAL(9,CC5:CC11) -> 0 | CD12: =SUBTOTAL(9,CD5:CD11) -> 0 | CH12: =SUBTOTAL(9,CH5:CH11) -> 69200 | CI12: =SUBTOTAL(9,CI5:CI11) -> 87790 | CN12: =SUBTOTAL(9,CN5:CN11) -> 18590 | CO12: =SUBTOTAL(9,CO5:CO11) -> 18590 | CP12: =SUBTOTAL(9,CP5:CP11) -> 18590 | CQ12: =SUBTOTAL(9,CQ5:CQ11) -> 103592.2 | CR12: =SUBTOTAL(9,CR5:CR11) -> 81656 | CS12: =SUBTOTAL(9,CS5:CS11) -> 0 | CT12: =SUBTOTAL(9,CT5:CT11) -> 0 | CU12: =SUBTOTAL(9,CU5:CU11) -> 21936.2
N13: =O12-AW12 -> 3 | P13: =Q12+AK12+AJ12+AL12+T12+AE12 -> 69200 | Q13: =Q12+'Recon Items'!G5+'Recon Items'!G6+'Recon Items'!C33 -> 69200 | AA13: =AB12/AY12 -> 0 | AJ13: =AK12+AJ12 -> 0 | AK13: Total CN in FY 2026-27 | BB13: =BB12-S12 -> -3 | BD13: =BG12+AY12 -> 87790 | BJ13: Total CN in FY 2025-26 | BK13: =BN12+BO12+BC12 -> 0 | BM13: =BK13/AY12 -> 0 | BP13: =BR12/BQ12 -> 0.21175533 | BT13: =BU12/AY12 -> 0.21175533 | BZ13: =BZ12/BY12 -> #DIV/0! | CC13: =IFERROR(CC12/CB12,0) -> 0 | CI13: =(CI12-CH12)/CI12 -> 0.21175533 | CN13: =CN12/AY12 -> 0.21175533 | CO13: =CO12/(Q12+AB12) -> 0.26864162 | CP13: =CP12/BQ12 -> 0.21175533
B14: Other Income | AC14: =+AL12+AK12 -> 0 | AJ14: =-'Last year''s'!F101 -> 0 | AK14: Total CN of FY 2025-26 | BJ14: Total CN of FY 2024-25 | BK14: =-'Last year''s'!L104-89445 -> -89445
B15: Quarter | C15: Month | D15: Date | E15: Shipment ID | F15: Supplier Name | G15: GST Reg No. | H15: Vendor Invoice No. | I15: Vendor Invoice Date | J15: P V No. | K15: P V Date | L15: State (Origin) | M15: Vehicle No. | N15: Material | O15: Qty (Kg) | P15: Price/Kg | Q15: Purchase Price | R15: Return Qty | S15: Net Qty | T15: Basic Customs Duty | U15: Transporter Name | V15: LR NO/BILL NO | W15: J V No. | X15: JV Date | Y15: Logistics cost | Z15: Debit note on logistic cost | AA15: Logistics Provision | AB15: Total Logistics Cost | AC15: Operational Cost | AD15: Cost/Kg. | AE15: Divertion/Internal | AF15: Debit Note No. | AG15: Debit Note Date. | AH15: Debit Note No. 2 | AI15: Debit Note Date. 2 | AJ15: Full Debit Note | AK15: Actual Debit Note | AL15: Provision for DN | AM15: Total Cost | AN15: Inv. Date | AO15: Inv. No. | AP15: Customer ID | AQ15: Buyer Name | AR15: Buyer GST Number | AS15: Location (Origin) | AT15: Location (Destination) | AU15: State (Destination) | AV15: E-WayBill Number | AW15: Qty(Kg) | AX15: Rate/Kg | AY15: Amount | AZ15: Qty Check | BA15: Return Qty | BB15: Net Qty | BC15: Divertion/Internal | BD15: Return Type | BE15: Date : DN to Buyer | BF15: DN to Buyer | BG15: Amount | BH15: Credit Note No:1 | BI15: CN Date. No:1 | BJ15: Credit Note No:2 | BK15: CN Date. No:2 | BL15: Cash Discount(Provision) | BM15: Cash Discount | BN15: Full Credit Notes | BO15: Actual Credit Note | BP15: Provision for CN | BQ15: Net Revenue | BR15: Margin | BS15: Reamrks - Margin | BT15: Remarks | BU15: LMI @ Inception | BV15: Remarks @ Inception | BW15: Margin (%) | BX15: Margin Bucket | BY15: Total CN(Inc.Provisions) | BZ15: Total DN(Inc.Provisions) | CA15: Check | CB15: Actaul CN | CC15: Actual DN | CD15: Check | CE15: Material-Short Form | CF15: Supplier Type | CG15: Month | CH15: Cost | CI15: Revenue | CJ15: Week No: | CK15: Category (Material) | CL15: Broad Category | CM15: Customer POC Name | CN15: Gross Margin | CO15: Recykal Margin | CP15: Net Margin | CQ15: Sales | CR15: Purchases | CS15: Credit Note | CT15: Debit Note | CU15: Margin | CV15: Bill Branch | CW15: Inv Branch | CX15: Vendor PAN No | CY15: Customer PAN No | CZ15: GST TDS Applicability | DA15: Cash Discount. No | DB15: CD Date | DC15: Cash Discount. No.2 | DD15: CD Date.2 | DE15: Total DN | DF15: Total CN
B16: ="Q" & IF(ROUNDUP(MONTH(D16)/3,0)-1=0,4,ROUNDUP(MONTH(D16)/3,0)-1) -> Q4 | C16: =TEXT(AN16,"mmm-yy") -> May-26 | Q16: =O16*P16 -> 0 | R16: 0 | S16: =O16-R16 -> 0 | T16: 0 | U16: 0 | V16: 0 | W16: 0 | X16: 0 | Y16: 0 | Z16: 0 | AA16: 0 | AB16: =Y16+AA16+Z16 -> 0 | AC16: 0 | AD16: 0 | AE16: 0 | AF16: 0 | AG16: 0 | AH16: 0 | AI16: 0 | AJ16: 0 | AK16: 0 | AL16: 0 | AM16: =Q16+AB16+AL16+AK16+AJ16+T16+AE16 -> 0 | AN16: 46156 | AY16: =AW16*AX16 -> 0 | AZ16: =AW16=O16 -> TRUE | BA16: 0 | BB16: =AW16-BA16 -> 0 | BC16: 0 | BD16: Regular | BE16: 0 | BF16: 0 | BG16: 0 | BH16: 0 | BI16: 0 | BJ16: 0 | BK16: 0 | BL16: =-IF(AR16="21AABCJ1969M1ZF",(AY16*2%),0) -> 0 | BM16: 0 | BN16: 0 | BO16: 0 | BP16: 0 | BQ16: =AY16+BN16+BO16+BP16+BC16+BG16+BM16+BL16 -> 0 | BR16: =BQ16-AM16 -> 0 | BS16: =IF(BR16>=0,"Positive Margin","Negative Margin") -> Positive Margin | BT16: Finance Up Charge | BU16: =AY16-Y16-Q16-AA16-T16+BC16 -> 0 | BV16: =IF(BU16<0, "Negative Margin at Inception", "Positive Margin at Inception") -> Positive Margin at Inception | BW16: =IFERROR(BR16/BQ16,"0") -> 0 | BX16: =IF(BW16<1%,"Less Than 1%",IF(BW16>2%,"More than 2%",IF(BW16>=1%,"1% - 2%"))) -> More than 2% | BY16: =BO16+BP16 -> 0 | BZ16: =AL16+AK16 -> 0 | CA16: =BY16-BZ16 -> 0 | CB16: =BO16 -> 0 | CC16: =AK16 -> 0 | CD16: =CB16-CC16 -> 0 | CE16: Marketplace Purchases (Metal) | CF16: 0 | CG16: =TEXT(AN16,"mmm-yy") -> May-26 | CH16: =AM16-AL16 -> 0 | CI16: =BQ16-BP16 -> 0 | CJ16: =INT((D16- IF(MONTH(D16) >= 4, DATE(YEAR(D16), 4, 1), DATE(YEAR(D16)-1, 4, 1))) / 7) + 1 -> -99098 | CK16: 0 | CL16: 0 | CM16: =_xlfn.XLOOKUP(AR16,Receivables!B:B,Receivables!D:D) -> 0 | CN16: =AY16-Q16 -> 0 | CO16: =CN16-AB16 -> 0 | CP16: =BQ16-AM16 -> 0 | CQ16: =AY16*118% -> 0 | CR16: =Q16*118% -> 0 | CS16: =CB16*118% -> 0 | CT16: =CC16*118% -> 0 | CU16: =(CQ16-CS16)-(CR16-CT16) -> 0 | CV16: Telangana - HO | CW16: Telangana - HO | CX16: =MID(G16,3,10) | CY16: =MID(AR16,3,10) | CZ16: 0 | DA16: 0 | DB16: 0 | DC16: 0 | DD16: 0 | DE16: 0 | DF16: 0
F18: Total | O18: =SUBTOTAL(9,O16:O17) -> 0 | Q18: =SUBTOTAL(9,Q16:Q17) -> 0 | R18: =SUBTOTAL(9,R16:R17) -> 0 | S18: =SUBTOTAL(9,S16:S17) -> 0 | T18: =SUBTOTAL(9,T11:T17) -> 0 | Y18: =SUBTOTAL(9,Y16:Y17) -> 0 | Z18: =SUBTOTAL(9,Z16:Z17) -> 0 | AA18: =SUBTOTAL(9,AA16:AA17) -> 0 | AB18: =SUBTOTAL(9,AB16:AB17) -> 0 | AC18: =SUBTOTAL(9,AC16:AC17) -> 0 | AD18: =SUBTOTAL(1,AD11:AD17) -> 0 | AE18: =SUBTOTAL(9,AE16:AE17) -> 0 | AJ18: =SUBTOTAL(9,AJ16:AJ17) -> 0 | AK18: =SUBTOTAL(9,AK16:AK17) -> 0 | AL18: =SUBTOTAL(9,AL16:AL17) -> 0 | AM18: =SUBTOTAL(9,AM16:AM17) -> 0 | AW18: =SUBTOTAL(9,AW16:AW17) -> 0 | AY18: =SUBTOTAL(9,AY16:AY17) -> 0 | BA18: =SUBTOTAL(9,BA16:BA17) -> 0 | BB18: =SUBTOTAL(9,BB16:BB17) -> 0 | BC18: =SUBTOTAL(9,BC16:BC17) -> 0 | BG18: =SUBTOTAL(9,BG16:BG17) -> 0 | BL18: =SUBTOTAL(9,BL16:BL17) -> 0 | BM18: =SUBTOTAL(9,BM16:BM17) -> 0 | BN18: =SUBTOTAL(9,BN16:BN17) -> 0 | BO18: =SUBTOTAL(9,BO16:BO17) -> 0 | BP18: =SUBTOTAL(9,BP16:BP17) -> 0 | BQ18: =SUBTOTAL(9,BQ16:BQ17) -> 0 | BR18: =SUBTOTAL(9,BR16:BR17) -> 0 | BU18: =SUBTOTAL(9,BU16:BU17) -> 0 | BY18: =SUBTOTAL(9,BY16:BY17) -> 0 | BZ18: =SUBTOTAL(9,BZ16:BZ17) -> 0 | CA18: =SUBTOTAL(9,CA16:CA17) -> 0 | CB18: =SUBTOTAL(9,CB16:CB17) -> 0 | CC18: =SUBTOTAL(9,CC16:CC17) -> 0 | CD18: =SUBTOTAL(9,CD16:CD17) -> 0 | CH18: =SUBTOTAL(9,CH16:CH17) -> 0 | CI18: =SUBTOTAL(9,CI16:CI17) -> 0 | CN18: =SUBTOTAL(9,CN16:CN17) -> 0 | CO18: =SUBTOTAL(9,CO16:CO17) -> 0 | CP18: =SUBTOTAL(9,CP16:CP17) -> 0 | CQ18: =SUBTOTAL(9,CQ16:CQ17) -> 0 | CR18: =SUBTOTAL(9,CR16:CR17) -> 0 | CS18: =SUBTOTAL(9,CS16:CS17) -> 0 | CT18: =SUBTOTAL(9,CT16:CT17) -> 0 | CU18: =SUBTOTAL(9,CU16:CU17) -> 0
N20: Particulars | O20: Amount | AA20: Particulars | AC20: Amount | AR20: Particulars | AS20: Amount
N21: Net Purchase as per report | O21: =Q12+AJ12+AK12+AE12 -> 69200 | AA21: Net Logistic Cost as per report | AC21: =Y12+Z12 -> 0 | AR21: Net Sales As per report | AS21: =+AY12+BN12+BO12+BC12+BG12+BQ18 -> 87790
N22: As per ZOHO | O22: 69200 | P22: 46187 | AA22: As per ZOHO | AC22: 0 | AD22: =P22 -> 46187 | AR22: As per ZOHO | AS22: 87790 | AT22: =P22 -> 46187
N23: Variance | O23: =O22-O21 -> 0 | AA23: Variance | AC23: =AC22-AC21 -> 0 | AR23: Variance | AS23: =AS21-AS22 -> 0
N24: DN Provision in Zoho FY 25-26 | O24: 0 | AA24: Fy 2025-26 Logistic Provision Reversal | AC24: 0 | AR24: CN Provision in Zoho FY 25-26 | AS24: ='Last year''s'!L3 -> 0
N25: JV for last year Bills | O25: 0 | AA25: FY 2025-26 Logistics | AC25: ='Last year''s'!R65 -> 0 | AR25: FY 2025-26 Credit notes | AS25: =-'Last year''s'!L4 -> 0
N26: Debit note FY 25-26 | O26: ='Last year''s'!F101 -> 0 | AA26: Reco | AR26: Reconciliation | AS26: =-'Recon Items'!C29+'Recon Items'!G29+'Recon Items'!R8 -> 0
N27: Reconciliation | O27: ='Recon Items'!G19-'Recon Items'!C19-'Recon Items'!N19+'Recon Items'!C33 -> 0 | AA27: Institutional Business | AC27: ='Recon Items'!K33 -> 0 | AR27: Institutional Business | AS27: ='Recon Items'!G33 -> 0
N28: Institutional Business | O28: ='Recon Items'!C51 -> 0 | AA28: Variance | AC28: =-AC23+AC24+AC25+AC27 -> 0 | AR28: Final Variance | AS28: =AS23+AS25+AS26+AS24+AS27 -> 0
N29: Variance | O29: =O23+O26-O27-O24-O28-O25 -> 0
BJ41: =SUM(BJ35:BJ40) -> 0
BJ42: =BJ34-BJ41 -> 0
AK48: =AK49-AK50 -> 0

Sheet Recon Items
J3: Qty Reco | M3: FY 2026-27 bills considered ths year | Q3: FY 2026-27
B4: Bills in report not in P&L | C4: Amount | D4: Qty | F4: Bills in P&L not in report | G4: Amount | H4: Qty | J4: Qty Check | K4: =Details!AD22 -> 46187 | M4: Bills in report not in P&L | N4: Amount | O4: Qty | Q4: DN to Customer | R4: Amount
J6: As Per Report | K6: =-Details!AW12 -> -198
J7: As per Zoho(till last month)
J8: As per Zoho (current month) | K8: 71 | R8: =SUM(R5:R7) -> 0
Q9: FY 2026-27
J10: Variance | K10: =SUM(K6:K9)-H19-R27 -> -127 | Q10: CN to suuplier (excess Qty) | R10: Qty
J15: BCD not in Report | K15: Amount
B19: G.Total | C19: =SUM(C5:C18) -> 0 | F19: G.Total | G19: =SUBTOTAL(9,G5:G18) -> 0 | H19: =SUBTOTAL(9,H5:H18) -> 0 | K19: =SUM(K16:K18) -> 0 | M19: G.Total | N19: =SUM(N5:N18) -> 0 | O19: =SUM(O5:O18) -> 0
B22: Sales in report not in P&L | C22: Amount | D22: Qty | F22: Sales in P&L not in report | G22: Amount | H22: Qty | J22: Bils in Report & P&L , Sale yet to be done
Q27: G.Total | R27: =SUM(R11:R26) -> 0
B29: G.Total | C29: =SUM(C23:C28) -> 0 | F29: G.Total | G29: =SUBTOTAL(9,G23:G28) -> 0 | H29: 0 | J29: G.Total
B32: Institutional Business X Metal
B33: Bills in P&L not in report | C33: =SUBTOTAL(9,C35:C40) -> 0 | D33: =SUM(D35:D44) -> 0 | F33: Sales in P&L not in report | G33: =SUBTOTAL(9,G35:G45) -> 0 | J33: Logistics in P&L not in report
B34: Bills in P&L not in report | C34: Amount | D34: Qty | F34: Sales in P&L not in report | G34: Amount | H34: Qty | J34: Sales in P&L not in report | K34: Amount | L34: Qty
AA682: -568957
AA687: =-AA683+AA684-AA685 -> 0

Sheet Margins
B2: Shipment ID | C2: Margin | E2: Shipment ID | F2: Margin(LMT) | J2: Category-Margins
B3: {=_xlfn._xlws.SORT(_xlfn.PIVOTBY(Details!E5:E11,,Details!BR5:BR11,_xleta.SUM,3),2,1)} -> SH04262802 | C3: -1500 | E3: {=_xlfn._xlws.SORT(_xlfn.PIVOTBY(Details!E5:E11,,Details!BU5:BU11,_xleta.SUM,3),2,1)} -> SH04262802 | F3: -1500 | J3: Business Category | K3: GM(Sal-Pur) | L3: RM(Sal-Pur-Log) | M3: Net Margin
B4: 0 | C4: 0 | E4: 0 | F4: 0 | J4: Non-Ferrous | K4: =SUMIFS(Details!$CN$5:$CN$11,Details!$CK$5:$CK$11,Margins!$J4)/SUMIFS(Details!$BQ$5:$BQ$11,Details!$CK$5:$CK$11,Margins!$J4) -> #DIV/0! | L4: =SUMIFS(Details!$CO$5:$CO$11,Details!$CK$5:$CK$11,Margins!$J4)/SUMIFS(Details!$BQ$5:$BQ$11,Details!$CK$5:$CK$11,Margins!$J4) -> #DIV/0! | M4: =SUMIFS(Details!$CP$5:$CP$11,Details!$CK$5:$CK$11,Margins!$J4)/SUMIFS(Details!$BQ$5:$BQ$11,Details!$CK$5:$CK$11,Margins!$J4) -> #DIV/0!
B5: SH05261901 | C5: 4080 | E5: SH05261901 | F5: 4080 | J5: Ferrous | K5: =SUMIFS(Details!$CN$5:$CN$11,Details!$CK$5:$CK$11,Margins!$J5)/SUMIFS(Details!$BQ$5:$BQ$11,Details!$CK$5:$CK$11,Margins!$J5) -> #DIV/0! | L5: =SUMIFS(Details!$CO$5:$CO$11,Details!$CK$5:$CK$11,Margins!$J5)/SUMIFS(Details!$BQ$5:$BQ$11,Details!$CK$5:$CK$11,Margins!$J5) -> #DIV/0! | M5: =SUMIFS(Details!$CP$5:$CP$11,Details!$CK$5:$CK$11,Margins!$J5)/SUMIFS(Details!$BQ$5:$BQ$11,Details!$CK$5:$CK$11,Margins!$J5) -> #DIV/0!
B6: SH04262802 | C6: 4960 | E6: SH04262802 | F6: 4960 | J6: M3 | K6: =SUMIFS(Details!$CN$5:$CN$11,Details!$CK$5:$CK$11,Margins!$J6)/SUMIFS(Details!$BQ$5:$BQ$11,Details!$CK$5:$CK$11,Margins!$J6) -> #DIV/0! | L6: =SUMIFS(Details!$CO$5:$CO$11,Details!$CK$5:$CK$11,Margins!$J6)/SUMIFS(Details!$BQ$5:$BQ$11,Details!$CK$5:$CK$11,Margins!$J6) -> #DIV/0! | M6: =SUMIFS(Details!$CP$5:$CP$11,Details!$CK$5:$CK$11,Margins!$J6)/SUMIFS(Details!$BQ$5:$BQ$11,Details!$CK$5:$CK$11,Margins!$J6) -> #DIV/0!
B7: SH06261002 | C7: 11050 | E7: SH06261002 | F7: 11050
B8: Total | C8: 13630 | E8: Total | F8: 13630

Sheet Supplier Metrics
D1: =D2-Summary!P8-Summary!P11 -> 0
D2: =SUBTOTAL(9,D4:D27) -> 69200 | J2: =COUNTA(_xlfn.ANCHORARRAY(J4)) -> 1
B3: Supplier Name | C3: GST Reg No. | D3: Purchases | E3: Qty Supplied(MT) | F3: State | G3: POC Name | H3: Supplier Type | I3: Category | J3: Count Supplier Name | L3: Supplier Name | M3: GST Reg No. | N3: Supplier Type | O3: Remarks | P3: POC Name
B4: =_xlfn.XLOOKUP(C4,Details!$G$5:$G$11,Details!$F$5:$F$11) -> SRP ACE GREEN MARKETING | C4: {=_xlfn.UNIQUE(_xlfn._TRO_TRAILING(Details!G5:G11))} -> 33AELFS5871E1ZT | D4: =SUMIFS(Details!$AM$5:$AM$11,Details!$G$5:$G$11,'Supplier Metrics'!C4) -> 69200 | E4: =SUMIFS(Details!$S$5:$S$11,Details!$G$5:$G$11,'Supplier Metrics'!C4)/1000 -> 0.201 | F4: =_xlfn.XLOOKUP(C4,Details!G:G,Details!L:L) -> TN | G4: Amit Jha | H4: =_xlfn.XLOOKUP(C4,M:M,N:N) -> Manufacturer | I4: =_xlfn.XLOOKUP(C4,Details!G:G,Details!CK:CK) -> #REF! | J4: {=_xlfn.UNIQUE(MID(_xlfn._TRO_TRAILING(Details!G5:G11),3,10))} -> AELFS5871E | L4: ASHIRVAD PIPES PRIVATE LIMITED COMPANY | M4: 21AABCA7061K1ZX | N4: Others
B5: =_xlfn.XLOOKUP(C5,Details!$G$5:$G$11,Details!$F$5:$F$11) -> 0 | D5: =SUMIFS(Details!$AM$5:$AM$11,Details!$G$5:$G$11,'Supplier Metrics'!C5) -> 0 | E5: =SUMIFS(Details!$S$5:$S$11,Details!$G$5:$G$11,'Supplier Metrics'!C5)/1000 -> 0 | F5: =_xlfn.XLOOKUP(C5,Details!G:G,Details!L:L) -> 0 | G5: Amit Jha | H5: =_xlfn.XLOOKUP(C5,M:M,N:N) -> 0 | I5: =_xlfn.XLOOKUP(C5,Details!G:G,Details!CK:CK) -> 0 | L5: CORE COMPETENCY TRAINING & SERVICES PRIVATE LIMITED COMPANY | M5: 07AACCC6113H1Z0 | N5: Corporate
B6: =_xlfn.XLOOKUP(C6,Details!$G$5:$G$11,Details!$F$5:$F$11) -> 0 | D6: =SUMIFS(Details!$AM$5:$AM$11,Details!$G$5:$G$11,'Supplier Metrics'!C6) -> 0 | E6: =SUMIFS(Details!$S$5:$S$11,Details!$G$5:$G$11,'Supplier Metrics'!C6)/1000 -> 0 | F6: =_xlfn.XLOOKUP(C6,Details!G:G,Details!L:L) -> 0 | G6: Amit Jha | H6: =_xlfn.XLOOKUP(C6,M:M,N:N) -> 0 | I6: =_xlfn.XLOOKUP(C6,Details!G:G,Details!CK:CK) -> 0 | L6: Apollo Sugar Clinics Limited | M6: 29AAKCA6933D1ZK | N6: Others
B7: =_xlfn.XLOOKUP(C7,Details!$G$5:$G$11,Details!$F$5:$F$11) -> 0 | D7: =SUMIFS(Details!$AM$5:$AM$11,Details!$G$5:$G$11,'Supplier Metrics'!C7) -> 0 | E7: =SUMIFS(Details!$S$5:$S$11,Details!$G$5:$G$11,'Supplier Metrics'!C7)/1000 -> 0 | F7: =_xlfn.XLOOKUP(C7,Details!G:G,Details!L:L) -> 0 | G7: Amit Jha | H7: =_xlfn.XLOOKUP(C7,M:M,N:N) -> 0 | I7: =_xlfn.XLOOKUP(C7,Details!G:G,Details!CK:CK) -> 0 | L7: MON EXPORTS | M7: 19AVJPG9890L1ZN | N7: Manufacturer
B8: =_xlfn.XLOOKUP(C8,Details!$G$5:$G$11,Details!$F$5:$F$11) -> 0 | D8: =SUMIFS(Details!$AM$5:$AM$11,Details!$G$5:$G$11,'Supplier Metrics'!C8) -> 0 | E8: =SUMIFS(Details!$S$5:$S$11,Details!$G$5:$G$11,'Supplier Metrics'!C8)/1000 -> 0 | F8: =_xlfn.XLOOKUP(C8,Details!G:G,Details!L:L) -> 0 | G8: Amit Jha | H8: =_xlfn.XLOOKUP(C8,M:M,N:N) -> 0 | I8: =_xlfn.XLOOKUP(C8,Details!G:G,Details!CK:CK) -> 0 | L8: M/S. HAVELLS INDIA LIMITED - Odisha | M8: 21AAACH0351E1ZH | N8: Others
L9: CORE COMPETENCY MARINE TRAINING PRIVATE LIMITED COMPANY | M9: 07AACCC6114A1ZD | N9: Others
L10: MARINE MANAGEMENT SERVICES PVT. LTD. | M10: 27AACCM2420R1Z9 | N10: Others
L11: DODLA DAIRY LIMITED | M11: 36AABCD5077E1ZS | N11: Others
L12: ALLIANCE DENTAL CARE LIMITED | M12: 29AAECA1118N1ZM | N12: Others
L13: SMITH STONE WALTERS PVT. LTD. | M13: 27AARCS7335N1ZG | N13: Corporate
L14: KANINI SOFTWARE SOLUTIONS INDIA PRIVATE LIMITED COMPANY | M14: 33AACCG4879L1Z7 | N14: Others
L15: VER SE INNOVATION PRIVATE LIMITED COMPANY | M15: 29AACCV5133G1ZB | N15: Others
L16: Shri shyam plastic udyog | M16: 06ANQPT2502B1Z8 | N16: Others
L17: DODLA DAIRY LIMITED | M17: 29AABCD5077E1ZN | N17: Others
L18: M/S HAVELLS INDIA LIMITED - Assam | M18: 18AAACH0351E1Z4 | N18: Others
L19: ALLIANCE DENTAL CARE LIMITED | M19: 36AAECA1118N1ZR | N19: Others
L20: APOLLO SUGAR CLINICS LIMITED | M20: 33AAKCA6933D1ZV | N20: Others
... L1428: BMS ENTERPRISES | M1428: 07AIXPR2550B1Z3 | N1428: Processor

Sheet Buyer Metrics
G2: =G3-Summary!P6 -> -197.802 | H2: =H3-Summary!Q7 -> 0 | I2: =I3-Summary!P13 -> 0 | J2: =J3-Summary!P16 -> 0.21175533 | K2: =K3-Details!CB12 -> 0 | M2: =M3-Summary!P20 -> 3 | AH2: Revenue Metrics for Cohort Analysis | AU2: Quantity Metrics for Cohort Analysis
C3: =COUNTA(_xlfn.ANCHORARRAY(C5)) -> 1 | D3: =COUNTA(_xlfn.ANCHORARRAY(D5)) -> 1 | G3: =SUM(G$5:G51)/1000 -> 0.198 | H3: =SUM(H$5:H51) -> 87790 | I3: =SUM(I$5:I51) -> 18590 | J3: =I3/H3 -> 0.21175533 | K3: =SUM(K$5:K51) -> 0 | L3: =K3/H3 -> 0 | M3: =SUM(M$5:M51) -> 6 | N3: =SUBTOTAL(1,N5:N51) -> 7315.8333 | O3: =SUBTOTAL(1,O5:O5) -> 147.79461 | R3: "Top 10" Revenue Gainers | S3: =SUM(S5:S14) -> 87790 | T3: =SUM(T5:T14) -> 18590 | U3: =SUM(S5:S14)/$H$3 -> 1 | V3: =SUM(T5:T14)/$I$3 -> 1 | AH3: =SUBTOTAL(9,AH5:AH124) -> 0 | AI3: =SUBTOTAL(9,AI5:AI124) -> 0 | AJ3: =SUBTOTAL(9,AJ5:AJ124) -> 0 | AK3: =SUBTOTAL(9,AK5:AK124) -> 0 | AL3: =SUBTOTAL(9,AL5:AL124) -> 0 | AM3: =SUBTOTAL(9,AM5:AM124) -> 0 | AN3: =SUBTOTAL(9,AN5:AN124) -> 0 | AO3: =SUBTOTAL(9,AO5:AO124) -> 0 | AP3: =SUBTOTAL(9,AP5:AP124) -> 0 | AU3: =SUBTOTAL(9,AU5:AU124) -> 0 | AV3: =SUBTOTAL(9,AV5:AV124) -> 0 | AW3: =SUBTOTAL(9,AW5:AW124) -> 0 | AX3: =SUBTOTAL(9,AX5:AX124) -> 0 | AY3: =SUBTOTAL(9,AY5:AY124) -> 0 | AZ3: =SUBTOTAL(9,AZ5:AZ124) -> 0 | BA3: =SUBTOTAL(9,BA5:BA124) -> 0 | BB3: =SUBTOTAL(9,BB5:BB124) -> 0 | BC3: =SUBTOTAL(9,BC5:BC124) -> 0
B4: Customer Name | C4: Count Recyclers | D4: Customer ID | E4: POC Name | F4: Category | G4: Qty | H4: Revenue | I4: Margin | J4: Margin(% | K4: Debit Notes | L4: DN to Sale(%) | M4: No of transactions | N4: Avg Tran Value | O4: Avg.Price/kg | R4: Top 10 Customers in FY 2024-25 | S4: Revenue | T4: Margin | U4: % of Total Revenue | V4: % of Total Margin | Y4: Particulars | Z4: {=TRANSPOSE(_xlfn.UNIQUE(Details!#REF!))} -> #REF! | AF4: {=_xlfn.UNIQUE(_xlfn._TRO_TRAILING(Details!CY4:CY11))} -> Customer PAN No | AG4: Customer Name | AH4: {=TRANSPOSE(_xlfn.UNIQUE(Details!#REF!))} -> #REF! | AU4: {=TRANSPOSE(_xlfn.UNIQUE(Details!#REF!))} -> #REF!
B5: =(_xlfn.XLOOKUP(D5,Details!$AR$5:$AR$11,Details!$AQ$5:$AQ$11)) -> INFINITYBOX PRIVATE LIMITED | C5: {=_xlfn.UNIQUE(MID(_xlfn._TRO_TRAILING(Details!AR5:AR11),3,10))} -> AAFCI4561G | D5: {=_xlfn.UNIQUE(_xlfn._TRO_TRAILING(Details!AR5:AR11))} -> 29AAFCI4561G1ZF | E5: =_xlfn.XLOOKUP(D5,Receivables!B:B,Receivables!D:D) -> #N/A | F5: =_xlfn.XLOOKUP(D5,Receivables!B:B,Receivables!E:E) -> #N/A | G5: =SUMIFS(Details!$BB$5:$BB$11,Details!$AR$5:$AR$11,'Buyer Metrics'!D5) -> 198 | H5: =SUMIFS(Details!$BQ$5:$BQ$11,Details!$AR$5:$AR$11,'Buyer Metrics'!$D5) -> 87790 | I5: =SUMIFS(Details!$BR$5:$BR$11,Details!$AR$5:$AR$11,'Buyer Metrics'!D5) -> 18590 | J5: =I5/H5 -> 0.21175533 | K5: =SUMIFS(Details!$CB$5:$CB$11,Details!$AR$5:$AR$11,'Buyer Metrics'!$D5) -> 0 | L5: =K5/H5 -> 0 | M5: {=COUNTA(_xlfn.UNIQUE(_xlfn._xlws.FILTER(Details!AO:AO,Details!AR:AR='Buyer Metrics'!$D5)))} -> 3 | N5: =H5/M5 -> 29263.333 | O5: =IFERROR((N5/G5),0) -> 147.79461 | R5: =_xlfn.XLOOKUP(S5,$H$5:$H$47,$B$5:$B$47) -> INFINITYBOX PRIVATE LIMITED | S5: =LARGE($H$5:$H$47,1) -> 87790 | T5: =_xlfn.XLOOKUP(R5,B:B,I:I) -> 18590 | U5: =S5/$H$3 -> 1 | V5: =T5/$I$3 -> 1 | Y5: Revenue | Z5: =SUMIFS(Details!#REF!,Details!#REF!,'Buyer Metrics'!$Z$3,Details!#REF!,'Buyer Metrics'!Z$4) -> #REF! | AA5: =SUMIFS(Details!#REF!,Details!#REF!,'Buyer Metrics'!$Z$3,Details!#REF!,'Buyer Metrics'!AA$4) -> #REF! | AB5: =SUMIFS(Details!#REF!,Details!#REF!,'Buyer Metrics'!$Z$3,Details!#REF!,'Buyer Metrics'!AB$4) -> #REF! | AC5: =SUMIFS(Details!#REF!,Details!#REF!,'Buyer Metrics'!$Z$3,Details!#REF!,'Buyer Metrics'!AC$4) -> #REF! | AF5: AAFCI4561G | AG5: =_xlfn.XLOOKUP(AF5,Details!CY:CY,Details!AQ:AQ) -> INFINITYBOX PRIVATE LIMITED | AH5: =SUMIFS(Details!$BQ:$BQ,Details!$CY:$CY,'Buyer Metrics'!$AF5,Details!$C:$C,'Buyer Metrics'!AH$4) -> 0 | AI5: =SUMIFS(Details!$BQ:$BQ,Details!$CY:$CY,'Buyer Metrics'!$AF5,Details!$C:$C,'Buyer Metrics'!AI$4) -> 0 | AJ5: =SUMIFS(Details!$BQ:$BQ,Details!$CY:$CY,'Buyer Metrics'!$AF5,Details!$C:$C,'Buyer Metrics'!AJ$4) -> 0 | AK5: =SUMIFS(Details!$BQ:$BQ,Details!$CY:$CY,'Buyer Metrics'!$AF5,Details!$C:$C,'Buyer Metrics'!AK$4) -> 0 | AL5: =SUMIFS(Details!$BQ:$BQ,Details!$CY:$CY,'Buyer Metrics'!$AF5,Details!$C:$C,'Buyer Metrics'!AL$4) -> 0 | AM5: =SUMIFS(Details!$BQ:$BQ,Details!$CY:$CY,'Buyer Metrics'!$AF5,Details!$C:$C,'Buyer Metrics'!AM$4) -> 0 | AN5: =SUMIFS(Details!$BQ:$BQ,Details!$CY:$CY,'Buyer Metrics'!$AF5,Details!$C:$C,'Buyer Metrics'!AN$4) -> 0 | AO5: =SUMIFS(Details!$BQ:$BQ,Details!$CY:$CY,'Buyer Metrics'!$AF5,Details!$C:$C,'Buyer Metrics'!AO$4) -> 0 | AP5: =SUMIFS(Details!$BQ:$BQ,Details!$CY:$CY,'Buyer Metrics'!$AF5,Details!$C:$C,'Buyer Metrics'!AP$4) -> 0 | AU5: =SUMIFS(Details!$BB:$BB,Details!$CY:$CY,'Buyer Metrics'!$AF5,Details!$C:$C,'Buyer Metrics'!AU$4) -> 0 | AV5: =SUMIFS(Details!$BB:$BB,Details!$CY:$CY,'Buyer Metrics'!$AF5,Details!$C:$C,'Buyer Metrics'!AV$4) -> 0 | AW5: =SUMIFS(Details!$BB:$BB,Details!$CY:$CY,'Buyer Metrics'!$AF5,Details!$C:$C,'Buyer Metrics'!AW$4) -> 0 | AX5: =SUMIFS(Details!$BB:$BB,Details!$CY:$CY,'Buyer Metrics'!$AF5,Details!$C:$C,'Buyer Metrics'!AX$4) -> 0 | AY5: =SUMIFS(Details!$BB:$BB,Details!$CY:$CY,'Buyer Metrics'!$AF5,Details!$C:$C,'Buyer Metrics'!AY$4) -> 0 | AZ5: =SUMIFS(Details!$BB:$BB,Details!$CY:$CY,'Buyer Metrics'!$AF5,Details!$C:$C,'Buyer Metrics'!AZ$4) -> 0 | BA5: =SUMIFS(Details!$BB:$BB,Details!$CY:$CY,'Buyer Metrics'!$AF5,Details!$C:$C,'Buyer Metrics'!BA$4) -> 0 | BB5: =SUMIFS(Details!$BB:$BB,Details!$CY:$CY,'Buyer Metrics'!$AF5,Details!$C:$C,'Buyer Metrics'!BB$4) -> 0 | BC5: =SUMIFS(Details!$BB:$BB,Details!$CY:$CY,'Buyer Metrics'!$AF5,Details!$C:$C,'Buyer Metrics'!BC$4) -> 0
B6: =(_xlfn.XLOOKUP(D6,Details!$AR$5:$AR$11,Details!$AQ$5:$AQ$11)) -> 0 | E6: =_xlfn.XLOOKUP(D6,Receivables!B:B,Receivables!D:D) -> 0 | F6: =_xlfn.XLOOKUP(D6,Receivables!B:B,Receivables!E:E) -> 0 | G6: =SUMIFS(Details!$BB$5:$BB$11,Details!$AR$5:$AR$11,'Buyer Metrics'!D6) -> 0 | H6: =SUMIFS(Details!$BQ$5:$BQ$11,Details!$AR$5:$AR$11,'Buyer Metrics'!$D6) -> 0 | I6: =SUMIFS(Details!$BR$5:$BR$11,Details!$AR$5:$AR$11,'Buyer Metrics'!D6) -> 0 | J6: =I6/H6 -> #DIV/0! | K6: =SUMIFS(Details!$CB$5:$CB$11,Details!$AR$5:$AR$11,'Buyer Metrics'!$D6) -> 0 | L6: =K6/H6 -> #DIV/0! | M6: {=COUNTA(_xlfn.UNIQUE(_xlfn._xlws.FILTER(Details!AO:AO,Details!AR:AR='Buyer Metrics'!$D6)))} -> 1 | N6: =H6/M6 -> 0 | O6: =IFERROR((N6/G6),0) -> 0 | Z6: =SUMIFS(Details!$BQ:$BQ,Details!$C:$C,'Buyer Metrics'!Z$4) -> 0 | AA6: =SUMIFS(Details!$BQ:$BQ,Details!$C:$C,'Buyer Metrics'!AA$4) -> 0 | AB6: =SUMIFS(Details!$BQ:$BQ,Details!$C:$C,'Buyer Metrics'!AB$4) -> 0 | AC6: =SUMIFS(Details!$BQ:$BQ,Details!$C:$C,'Buyer Metrics'!AC$4) -> 0 | AG6: =_xlfn.XLOOKUP(AF6,Details!CY:CY,Details!AQ:AQ) -> 0 | AH6: =SUMIFS(Details!$BQ:$BQ,Details!$CY:$CY,'Buyer Metrics'!$AF6,Details!$C:$C,'Buyer Metrics'!AH$4) -> 0 | AI6: =SUMIFS(Details!$BQ:$BQ,Details!$CY:$CY,'Buyer Metrics'!$AF6,Details!$C:$C,'Buyer Metrics'!AI$4) -> 0 | AJ6: =SUMIFS(Details!$BQ:$BQ,Details!$CY:$CY,'Buyer Metrics'!$AF6,Details!$C:$C,'Buyer Metrics'!AJ$4) -> 0 | AK6: =SUMIFS(Details!$BQ:$BQ,Details!$CY:$CY,'Buyer Metrics'!$AF6,Details!$C:$C,'Buyer Metrics'!AK$4) -> 0 | AL6: =SUMIFS(Details!$BQ:$BQ,Details!$CY:$CY,'Buyer Metrics'!$AF6,Details!$C:$C,'Buyer Metrics'!AL$4) -> 0 | AM6: =SUMIFS(Details!$BQ:$BQ,Details!$CY:$CY,'Buyer Metrics'!$AF6,Details!$C:$C,'Buyer Metrics'!AM$4) -> 0 | AN6: =SUMIFS(Details!$BQ:$BQ,Details!$CY:$CY,'Buyer Metrics'!$AF6,Details!$C:$C,'Buyer Metrics'!AN$4) -> 0 | AO6: =SUMIFS(Details!$BQ:$BQ,Details!$CY:$CY,'Buyer Metrics'!$AF6,Details!$C:$C,'Buyer Metrics'!AO$4) -> 0 | AP6: =SUMIFS(Details!$BQ:$BQ,Details!$CY:$CY,'Buyer Metrics'!$AF6,Details!$C:$C,'Buyer Metrics'!AP$4) -> 0 | AU6: =SUMIFS(Details!$BB:$BB,Details!$CY:$CY,'Buyer Metrics'!$AF6,Details!$C:$C,'Buyer Metrics'!AU$4) -> 0 | AV6: =SUMIFS(Details!$BB:$BB,Details!$CY:$CY,'Buyer Metrics'!$AF6,Details!$C:$C,'Buyer Metrics'!AV$4) -> 0 | AW6: =SUMIFS(Details!$BB:$BB,Details!$CY:$CY,'Buyer Metrics'!$AF6,Details!$C:$C,'Buyer Metrics'!AW$4) -> 0 | AX6: =SUMIFS(Details!$BB:$BB,Details!$CY:$CY,'Buyer Metrics'!$AF6,Details!$C:$C,'Buyer Metrics'!AX$4) -> 0 | AY6: =SUMIFS(Details!$BB:$BB,Details!$CY:$CY,'Buyer Metrics'!$AF6,Details!$C:$C,'Buyer Metrics'!AY$4) -> 0 | AZ6: =SUMIFS(Details!$BB:$BB,Details!$CY:$CY,'Buyer Metrics'!$AF6,Details!$C:$C,'Buyer Metrics'!AZ$4) -> 0 | BA6: =SUMIFS(Details!$BB:$BB,Details!$CY:$CY,'Buyer Metrics'!$AF6,Details!$C:$C,'Buyer Metrics'!BA$4) -> 0 | BB6: =SUMIFS(Details!$BB:$BB,Details!$CY:$CY,'Buyer Metrics'!$AF6,Details!$C:$C,'Buyer Metrics'!BB$4) -> 0 | BC6: =SUMIFS(Details!$BB:$BB,Details!$CY:$CY,'Buyer Metrics'!$AF6,Details!$C:$C,'Buyer Metrics'!BC$4) -> 0
B7: =(_xlfn.XLOOKUP(D7,Details!$AR$5:$AR$11,Details!$AQ$5:$AQ$11)) -> 0 | E7: =_xlfn.XLOOKUP(D7,Receivables!B:B,Receivables!D:D) -> 0 | F7: =_xlfn.XLOOKUP(D7,Receivables!B:B,Receivables!E:E) -> 0 | G7: =SUMIFS(Details!$BB$5:$BB$11,Details!$AR$5:$AR$11,'Buyer Metrics'!D7) -> 0 | H7: =SUMIFS(Details!$BQ$5:$BQ$11,Details!$AR$5:$AR$11,'Buyer Metrics'!$D7) -> 0 | I7: =SUMIFS(Details!$BR$5:$BR$11,Details!$AR$5:$AR$11,'Buyer Metrics'!D7) -> 0 | J7: =I7/H7 -> #DIV/0! | K7: =SUMIFS(Details!$CB$5:$CB$11,Details!$AR$5:$AR$11,'Buyer Metrics'!$D7) -> 0 | L7: =K7/H7 -> #DIV/0! | M7: {=COUNTA(_xlfn.UNIQUE(_xlfn._xlws.FILTER(Details!AO:AO,Details!AR:AR='Buyer Metrics'!$D7)))} -> 1 | N7: =H7/M7 -> 0 | O7: =IFERROR((N7/G7),0) -> 0 | Z7: =Z6-Z5 -> #REF! | AA7: =AA6-AA5 -> #REF! | AB7: =AB6-AB5 -> #REF! | AC7: =AC6-AC5 -> #REF! | AG7: =_xlfn.XLOOKUP(AF7,Details!CY:CY,Details!AQ:AQ) -> 0 | AH7: =SUMIFS(Details!$BQ:$BQ,Details!$CY:$CY,'Buyer Metrics'!$AF7,Details!$C:$C,'Buyer Metrics'!AH$4) -> 0 | AI7: =SUMIFS(Details!$BQ:$BQ,Details!$CY:$CY,'Buyer Metrics'!$AF7,Details!$C:$C,'Buyer Metrics'!AI$4) -> 0 | AJ7: =SUMIFS(Details!$BQ:$BQ,Details!$CY:$CY,'Buyer Metrics'!$AF7,Details!$C:$C,'Buyer Metrics'!AJ$4) -> 0 | AK7: =SUMIFS(Details!$BQ:$BQ,Details!$CY:$CY,'Buyer Metrics'!$AF7,Details!$C:$C,'Buyer Metrics'!AK$4) -> 0 | AL7: =SUMIFS(Details!$BQ:$BQ,Details!$CY:$CY,'Buyer Metrics'!$AF7,Details!$C:$C,'Buyer Metrics'!AL$4) -> 0 | AM7: =SUMIFS(Details!$BQ:$BQ,Details!$CY:$CY,'Buyer Metrics'!$AF7,Details!$C:$C,'Buyer Metrics'!AM$4) -> 0 | AN7: =SUMIFS(Details!$BQ:$BQ,Details!$CY:$CY,'Buyer Metrics'!$AF7,Details!$C:$C,'Buyer Metrics'!AN$4) -> 0 | AO7: =SUMIFS(Details!$BQ:$BQ,Details!$CY:$CY,'Buyer Metrics'!$AF7,Details!$C:$C,'Buyer Metrics'!AO$4) -> 0 | AP7: =SUMIFS(Details!$BQ:$BQ,Details!$CY:$CY,'Buyer Metrics'!$AF7,Details!$C:$C,'Buyer Metrics'!AP$4) -> 0 | AU7: =SUMIFS(Details!$BB:$BB,Details!$CY:$CY,'Buyer Metrics'!$AF7,Details!$C:$C,'Buyer Metrics'!AU$4) -> 0 | AV7: =SUMIFS(Details!$BB:$BB,Details!$CY:$CY,'Buyer Metrics'!$AF7,Details!$C:$C,'Buyer Metrics'!AV$4) -> 0 | AW7: =SUMIFS(Details!$BB:$BB,Details!$CY:$CY,'Buyer Metrics'!$AF7,Details!$C:$C,'Buyer Metrics'!AW$4) -> 0 | AX7: =SUMIFS(Details!$BB:$BB,Details!$CY:$CY,'Buyer Metrics'!$AF7,Details!$C:$C,'Buyer Metrics'!AX$4) -> 0 | AY7: =SUMIFS(Details!$BB:$BB,Details!$CY:$CY,'Buyer Metrics'!$AF7,Details!$C:$C,'Buyer Metrics'!AY$4) -> 0 | AZ7: =SUMIFS(Details!$BB:$BB,Details!$CY:$CY,'Buyer Metrics'!$AF7,Details!$C:$C,'Buyer Metrics'!AZ$4) -> 0 | BA7: =SUMIFS(Details!$BB:$BB,Details!$CY:$CY,'Buyer Metrics'!$AF7,Details!$C:$C,'Buyer Metrics'!BA$4) -> 0 | BB7: =SUMIFS(Details!$BB:$BB,Details!$CY:$CY,'Buyer Metrics'!$AF7,Details!$C:$C,'Buyer Metrics'!BB$4) -> 0 | BC7: =SUMIFS(Details!$BB:$BB,Details!$CY:$CY,'Buyer Metrics'!$AF7,Details!$C:$C,'Buyer Metrics'!BC$4) -> 0
B8: =(_xlfn.XLOOKUP(D8,Details!$AR$5:$AR$11,Details!$AQ$5:$AQ$11)) -> 0 | E8: =_xlfn.XLOOKUP(D8,Receivables!B:B,Receivables!D:D) -> 0 | F8: =_xlfn.XLOOKUP(D8,Receivables!B:B,Receivables!E:E) -> 0 | G8: =SUMIFS(Details!$BB$5:$BB$11,Details!$AR$5:$AR$11,'Buyer Metrics'!D8) -> 0 | H8: =SUMIFS(Details!$BQ$5:$BQ$11,Details!$AR$5:$AR$11,'Buyer Metrics'!$D8) -> 0 | I8: =SUMIFS(Details!$BR$5:$BR$11,Details!$AR$5:$AR$11,'Buyer Metrics'!D8) -> 0 | J8: =I8/H8 -> #DIV/0! | K8: =SUMIFS(Details!$CB$5:$CB$11,Details!$AR$5:$AR$11,'Buyer Metrics'!$D8) -> 0 | L8: =K8/H8 -> #DIV/0! | M8: {=COUNTA(_xlfn.UNIQUE(_xlfn._xlws.FILTER(Details!AO:AO,Details!AR:AR='Buyer Metrics'!$D8)))} -> 1 | N8: =H8/M8 -> 0 | O8: =IFERROR((N8/G8),0) -> 0 | Y8: Qty | Z8: =SUMIFS(Details!#REF!,Details!#REF!,'Buyer Metrics'!$Z$3,Details!#REF!,'Buyer Metrics'!Z$4) -> #REF! | AA8: =SUMIFS(Details!#REF!,Details!#REF!,'Buyer Metrics'!$Z$3,Details!#REF!,'Buyer Metrics'!AA$4) -> #REF! | AB8: =SUMIFS(Details!#REF!,Details!#REF!,'Buyer Metrics'!$Z$3,Details!#REF!,'Buyer Metrics'!AB$4) -> #REF! | AC8: =SUMIFS(Details!#REF!,Details!#REF!,'Buyer Metrics'!$Z$3,Details!#REF!,'Buyer Metrics'!AC$4) -> #REF! | AG8: =_xlfn.XLOOKUP(AF8,Details!CY:CY,Details!AQ:AQ) -> 0 | AH8: =SUMIFS(Details!$BQ:$BQ,Details!$CY:$CY,'Buyer Metrics'!$AF8,Details!$C:$C,'Buyer Metrics'!AH$4) -> 0 | AI8: =SUMIFS(Details!$BQ:$BQ,Details!$CY:$CY,'Buyer Metrics'!$AF8,Details!$C:$C,'Buyer Metrics'!AI$4) -> 0 | AJ8: =SUMIFS(Details!$BQ:$BQ,Details!$CY:$CY,'Buyer Metrics'!$AF8,Details!$C:$C,'Buyer Metrics'!AJ$4) -> 0 | AK8: =SUMIFS(Details!$BQ:$BQ,Details!$CY:$CY,'Buyer Metrics'!$AF8,Details!$C:$C,'Buyer Metrics'!AK$4) -> 0 | AL8: =SUMIFS(Details!$BQ:$BQ,Details!$CY:$CY,'Buyer Metrics'!$AF8,Details!$C:$C,'Buyer Metrics'!AL$4) -> 0 | AM8: =SUMIFS(Details!$BQ:$BQ,Details!$CY:$CY,'Buyer Metrics'!$AF8,Details!$C:$C,'Buyer Metrics'!AM$4) -> 0 | AN8: =SUMIFS(Details!$BQ:$BQ,Details!$CY:$CY,'Buyer Metrics'!$AF8,Details!$C:$C,'Buyer Metrics'!AN$4) -> 0 | AO8: =SUMIFS(Details!$BQ:$BQ,Details!$CY:$CY,'Buyer Metrics'!$AF8,Details!$C:$C,'Buyer Metrics'!AO$4) -> 0 | AP8: =SUMIFS(Details!$BQ:$BQ,Details!$CY:$CY,'Buyer Metrics'!$AF8,Details!$C:$C,'Buyer Metrics'!AP$4) -> 0 | AU8: =SUMIFS(Details!$BB:$BB,Details!$CY:$CY,'Buyer Metrics'!$AF8,Details!$C:$C,'Buyer Metrics'!AU$4) -> 0 | AV8: =SUMIFS(Details!$BB:$BB,Details!$CY:$CY,'Buyer Metrics'!$AF8,Details!$C:$C,'Buyer Metrics'!AV$4) -> 0 | AW8: =SUMIFS(Details!$BB:$BB,Details!$CY:$CY,'Buyer Metrics'!$AF8,Details!$C:$C,'Buyer Metrics'!AW$4) -> 0 | AX8: =SUMIFS(Details!$BB:$BB,Details!$CY:$CY,'Buyer Metrics'!$AF8,Details!$C:$C,'Buyer Metrics'!AX$4) -> 0 | AY8: =SUMIFS(Details!$BB:$BB,Details!$CY:$CY,'Buyer Metrics'!$AF8,Details!$C:$C,'Buyer Metrics'!AY$4) -> 0 | AZ8: =SUMIFS(Details!$BB:$BB,Details!$CY:$CY,'Buyer Metrics'!$AF8,Details!$C:$C,'Buyer Metrics'!AZ$4) -> 0 | BA8: =SUMIFS(Details!$BB:$BB,Details!$CY:$CY,'Buyer Metrics'!$AF8,Details!$C:$C,'Buyer Metrics'!BA$4) -> 0 | BB8: =SUMIFS(Details!$BB:$BB,Details!$CY:$CY,'Buyer Metrics'!$AF8,Details!$C:$C,'Buyer Metrics'!BB$4) -> 0 | BC8: =SUMIFS(Details!$BB:$BB,Details!$CY:$CY,'Buyer Metrics'!$AF8,Details!$C:$C,'Buyer Metrics'!BC$4) -> 0
Z9: =SUMIFS(Details!$BB:$BB,Details!$C:$C,'Buyer Metrics'!Z$4) -> 0 | AA9: =SUMIFS(Details!$BB:$BB,Details!$C:$C,'Buyer Metrics'!AA$4) -> 0 | AB9: =SUMIFS(Details!$BB:$BB,Details!$C:$C,'Buyer Metrics'!AB$4) -> 0 | AC9: =SUMIFS(Details!$BB:$BB,Details!$C:$C,'Buyer Metrics'!AC$4) -> 0 | AU9: =SUMIFS(Details!$BB:$BB,Details!$CY:$CY,'Buyer Metrics'!$AF9,Details!$C:$C,'Buyer Metrics'!AU$4) -> 0 | AV9: =SUMIFS(Details!$BB:$BB,Details!$CY:$CY,'Buyer Metrics'!$AF9,Details!$C:$C,'Buyer Metrics'!AV$4) -> 0 | AW9: =SUMIFS(Details!$BB:$BB,Details!$CY:$CY,'Buyer Metrics'!$AF9,Details!$C:$C,'Buyer Metrics'!AW$4) -> 0 | AX9: =SUMIFS(Details!$BB:$BB,Details!$CY:$CY,'Buyer Metrics'!$AF9,Details!$C:$C,'Buyer Metrics'!AX$4) -> 0 | AY9: =SUMIFS(Details!$BB:$BB,Details!$CY:$CY,'Buyer Metrics'!$AF9,Details!$C:$C,'Buyer Metrics'!AY$4) -> 0 | AZ9: =SUMIFS(Details!$BB:$BB,Details!$CY:$CY,'Buyer Metrics'!$AF9,Details!$C:$C,'Buyer Metrics'!AZ$4) -> 0 | BA9: =SUMIFS(Details!$BB:$BB,Details!$CY:$CY,'Buyer Metrics'!$AF9,Details!$C:$C,'Buyer Metrics'!BA$4) -> 0 | BB9: =SUMIFS(Details!$BB:$BB,Details!$CY:$CY,'Buyer Metrics'!$AF9,Details!$C:$C,'Buyer Metrics'!BB$4) -> 0 | BC9: =SUMIFS(Details!$BB:$BB,Details!$CY:$CY,'Buyer Metrics'!$AF9,Details!$C:$C,'Buyer Metrics'!BC$4) -> 0
Z10: =Z8-Z9 -> #REF! | AA10: =AA8-AA9 -> #REF! | AB10: =AB8-AB9 -> #REF! | AC10: =AC8-AC9 -> #REF! | AU10: =SUMIFS(Details!$BB:$BB,Details!$CY:$CY,'Buyer Metrics'!$AF10,Details!$C:$C,'Buyer Metrics'!AU$4) -> 0 | AV10: =SUMIFS(Details!$BB:$BB,Details!$CY:$CY,'Buyer Metrics'!$AF10,Details!$C:$C,'Buyer Metrics'!AV$4) -> 0 | AW10: =SUMIFS(Details!$BB:$BB,Details!$CY:$CY,'Buyer Metrics'!$AF10,Details!$C:$C,'Buyer Metrics'!AW$4) -> 0 | AX10: =SUMIFS(Details!$BB:$BB,Details!$CY:$CY,'Buyer Metrics'!$AF10,Details!$C:$C,'Buyer Metrics'!AX$4) -> 0 | AY10: =SUMIFS(Details!$BB:$BB,Details!$CY:$CY,'Buyer Metrics'!$AF10,Details!$C:$C,'Buyer Metrics'!AY$4) -> 0 | AZ10: =SUMIFS(Details!$BB:$BB,Details!$CY:$CY,'Buyer Metrics'!$AF10,Details!$C:$C,'Buyer Metrics'!AZ$4) -> 0 | BA10: =SUMIFS(Details!$BB:$BB,Details!$CY:$CY,'Buyer Metrics'!$AF10,Details!$C:$C,'Buyer Metrics'!BA$4) -> 0 | BB10: =SUMIFS(Details!$BB:$BB,Details!$CY:$CY,'Buyer Metrics'!$AF10,Details!$C:$C,'Buyer Metrics'!BB$4) -> 0 | BC10: =SUMIFS(Details!$BB:$BB,Details!$CY:$CY,'Buyer Metrics'!$AF10,Details!$C:$C,'Buyer Metrics'!BC$4) -> 0
AU11: =SUMIFS(Details!$BB:$BB,Details!$CY:$CY,'Buyer Metrics'!$AF11,Details!$C:$C,'Buyer Metrics'!AU$4) -> 0 | AV11: =SUMIFS(Details!$BB:$BB,Details!$CY:$CY,'Buyer Metrics'!$AF11,Details!$C:$C,'Buyer Metrics'!AV$4) -> 0 | AW11: =SUMIFS(Details!$BB:$BB,Details!$CY:$CY,'Buyer Metrics'!$AF11,Details!$C:$C,'Buyer Metrics'!AW$4) -> 0 | AX11: =SUMIFS(Details!$BB:$BB,Details!$CY:$CY,'Buyer Metrics'!$AF11,Details!$C:$C,'Buyer Metrics'!AX$4) -> 0 | AY11: =SUMIFS(Details!$BB:$BB,Details!$CY:$CY,'Buyer Metrics'!$AF11,Details!$C:$C,'Buyer Metrics'!AY$4) -> 0 | AZ11: =SUMIFS(Details!$BB:$BB,Details!$CY:$CY,'Buyer Metrics'!$AF11,Details!$C:$C,'Buyer Metrics'!AZ$4) -> 0 | BA11: =SUMIFS(Details!$BB:$BB,Details!$CY:$CY,'Buyer Metrics'!$AF11,Details!$C:$C,'Buyer Metrics'!BA$4) -> 0 | BB11: =SUMIFS(Details!$BB:$BB,Details!$CY:$CY,'Buyer Metrics'!$AF11,Details!$C:$C,'Buyer Metrics'!BB$4) -> 0 | BC11: =SUMIFS(Details!$BB:$BB,Details!$CY:$CY,'Buyer Metrics'!$AF11,Details!$C:$C,'Buyer Metrics'!BC$4) -> 0
AU12: =SUMIFS(Details!$BB:$BB,Details!$CY:$CY,'Buyer Metrics'!$AF12,Details!$C:$C,'Buyer Metrics'!AU$4) -> 0 | AV12: =SUMIFS(Details!$BB:$BB,Details!$CY:$CY,'Buyer Metrics'!$AF12,Details!$C:$C,'Buyer Metrics'!AV$4) -> 0 | AW12: =SUMIFS(Details!$BB:$BB,Details!$CY:$CY,'Buyer Metrics'!$AF12,Details!$C:$C,'Buyer Metrics'!AW$4) -> 0 | AX12: =SUMIFS(Details!$BB:$BB,Details!$CY:$CY,'Buyer Metrics'!$AF12,Details!$C:$C,'Buyer Metrics'!AX$4) -> 0 | AY12: =SUMIFS(Details!$BB:$BB,Details!$CY:$CY,'Buyer Metrics'!$AF12,Details!$C:$C,'Buyer Metrics'!AY$4) -> 0 | AZ12: =SUMIFS(Details!$BB:$BB,Details!$CY:$CY,'Buyer Metrics'!$AF12,Details!$C:$C,'Buyer Metrics'!AZ$4) -> 0 | BA12: =SUMIFS(Details!$BB:$BB,Details!$CY:$CY,'Buyer Metrics'!$AF12,Details!$C:$C,'Buyer Metrics'!BA$4) -> 0 | BB12: =SUMIFS(Details!$BB:$BB,Details!$CY:$CY,'Buyer Metrics'!$AF12,Details!$C:$C,'Buyer Metrics'!BB$4) -> 0 | BC12: =SUMIFS(Details!$BB:$BB,Details!$CY:$CY,'Buyer Metrics'!$AF12,Details!$C:$C,'Buyer Metrics'!BC$4) -> 0
AU13: =SUMIFS(Details!$BB:$BB,Details!$CY:$CY,'Buyer Metrics'!$AF13,Details!$C:$C,'Buyer Metrics'!AU$4) -> 0 | AV13: =SUMIFS(Details!$BB:$BB,Details!$CY:$CY,'Buyer Metrics'!$AF13,Details!$C:$C,'Buyer Metrics'!AV$4) -> 0 | AW13: =SUMIFS(Details!$BB:$BB,Details!$CY:$CY,'Buyer Metrics'!$AF13,Details!$C:$C,'Buyer Metrics'!AW$4) -> 0 | AX13: =SUMIFS(Details!$BB:$BB,Details!$CY:$CY,'Buyer Metrics'!$AF13,Details!$C:$C,'Buyer Metrics'!AX$4) -> 0 | AY13: =SUMIFS(Details!$BB:$BB,Details!$CY:$CY,'Buyer Metrics'!$AF13,Details!$C:$C,'Buyer Metrics'!AY$4) -> 0 | AZ13: =SUMIFS(Details!$BB:$BB,Details!$CY:$CY,'Buyer Metrics'!$AF13,Details!$C:$C,'Buyer Metrics'!AZ$4) -> 0 | BA13: =SUMIFS(Details!$BB:$BB,Details!$CY:$CY,'Buyer Metrics'!$AF13,Details!$C:$C,'Buyer Metrics'!BA$4) -> 0 | BB13: =SUMIFS(Details!$BB:$BB,Details!$CY:$CY,'Buyer Metrics'!$AF13,Details!$C:$C,'Buyer Metrics'!BB$4) -> 0 | BC13: =SUMIFS(Details!$BB:$BB,Details!$CY:$CY,'Buyer Metrics'!$AF13,Details!$C:$C,'Buyer Metrics'!BC$4) -> 0
AU14: =SUMIFS(Details!$BB:$BB,Details!$CY:$CY,'Buyer Metrics'!$AF14,Details!$C:$C,'Buyer Metrics'!AU$4) -> 0 | AV14: =SUMIFS(Details!$BB:$BB,Details!$CY:$CY,'Buyer Metrics'!$AF14,Details!$C:$C,'Buyer Metrics'!AV$4) -> 0 | AW14: =SUMIFS(Details!$BB:$BB,Details!$CY:$CY,'Buyer Metrics'!$AF14,Details!$C:$C,'Buyer Metrics'!AW$4) -> 0 | AX14: =SUMIFS(Details!$BB:$BB,Details!$CY:$CY,'Buyer Metrics'!$AF14,Details!$C:$C,'Buyer Metrics'!AX$4) -> 0 | AY14: =SUMIFS(Details!$BB:$BB,Details!$CY:$CY,'Buyer Metrics'!$AF14,Details!$C:$C,'Buyer Metrics'!AY$4) -> 0 | AZ14: =SUMIFS(Details!$BB:$BB,Details!$CY:$CY,'Buyer Metrics'!$AF14,Details!$C:$C,'Buyer Metrics'!AZ$4) -> 0 | BA14: =SUMIFS(Details!$BB:$BB,Details!$CY:$CY,'Buyer Metrics'!$AF14,Details!$C:$C,'Buyer Metrics'!BA$4) -> 0 | BB14: =SUMIFS(Details!$BB:$BB,Details!$CY:$CY,'Buyer Metrics'!$AF14,Details!$C:$C,'Buyer Metrics'!BB$4) -> 0 | BC14: =SUMIFS(Details!$BB:$BB,Details!$CY:$CY,'Buyer Metrics'!$AF14,Details!$C:$C,'Buyer Metrics'!BC$4) -> 0
AU15: =SUMIFS(Details!$BB:$BB,Details!$CY:$CY,'Buyer Metrics'!$AF15,Details!$C:$C,'Buyer Metrics'!AU$4) -> 0 | AV15: =SUMIFS(Details!$BB:$BB,Details!$CY:$CY,'Buyer Metrics'!$AF15,Details!$C:$C,'Buyer Metrics'!AV$4) -> 0 | AW15: =SUMIFS(Details!$BB:$BB,Details!$CY:$CY,'Buyer Metrics'!$AF15,Details!$C:$C,'Buyer Metrics'!AW$4) -> 0 | AX15: =SUMIFS(Details!$BB:$BB,Details!$CY:$CY,'Buyer Metrics'!$AF15,Details!$C:$C,'Buyer Metrics'!AX$4) -> 0 | AY15: =SUMIFS(Details!$BB:$BB,Details!$CY:$CY,'Buyer Metrics'!$AF15,Details!$C:$C,'Buyer Metrics'!AY$4) -> 0 | AZ15: =SUMIFS(Details!$BB:$BB,Details!$CY:$CY,'Buyer Metrics'!$AF15,Details!$C:$C,'Buyer Metrics'!AZ$4) -> 0 | BA15: =SUMIFS(Details!$BB:$BB,Details!$CY:$CY,'Buyer Metrics'!$AF15,Details!$C:$C,'Buyer Metrics'!BA$4) -> 0 | BB15: =SUMIFS(Details!$BB:$BB,Details!$CY:$CY,'Buyer Metrics'!$AF15,Details!$C:$C,'Buyer Metrics'!BB$4) -> 0 | BC15: =SUMIFS(Details!$BB:$BB,Details!$CY:$CY,'Buyer Metrics'!$AF15,Details!$C:$C,'Buyer Metrics'!BC$4) -> 0
AU16: =SUMIFS(Details!$BB:$BB,Details!$CY:$CY,'Buyer Metrics'!$AF16,Details!$C:$C,'Buyer Metrics'!AU$4) -> 0 | AV16: =SUMIFS(Details!$BB:$BB,Details!$CY:$CY,'Buyer Metrics'!$AF16,Details!$C:$C,'Buyer Metrics'!AV$4) -> 0 | AW16: =SUMIFS(Details!$BB:$BB,Details!$CY:$CY,'Buyer Metrics'!$AF16,Details!$C:$C,'Buyer Metrics'!AW$4) -> 0 | AX16: =SUMIFS(Details!$BB:$BB,Details!$CY:$CY,'Buyer Metrics'!$AF16,Details!$C:$C,'Buyer Metrics'!AX$4) -> 0 | AY16: =SUMIFS(Details!$BB:$BB,Details!$CY:$CY,'Buyer Metrics'!$AF16,Details!$C:$C,'Buyer Metrics'!AY$4) -> 0 | AZ16: =SUMIFS(Details!$BB:$BB,Details!$CY:$CY,'Buyer Metrics'!$AF16,Details!$C:$C,'Buyer Metrics'!AZ$4) -> 0 | BA16: =SUMIFS(Details!$BB:$BB,Details!$CY:$CY,'Buyer Metrics'!$AF16,Details!$C:$C,'Buyer Metrics'!BA$4) -> 0 | BB16: =SUMIFS(Details!$BB:$BB,Details!$CY:$CY,'Buyer Metrics'!$AF16,Details!$C:$C,'Buyer Metrics'!BB$4) -> 0 | BC16: =SUMIFS(Details!$BB:$BB,Details!$CY:$CY,'Buyer Metrics'!$AF16,Details!$C:$C,'Buyer Metrics'!BC$4) -> 0
AU17: =SUMIFS(Details!$BB:$BB,Details!$CY:$CY,'Buyer Metrics'!$AF17,Details!$C:$C,'Buyer Metrics'!AU$4) -> 0 | AV17: =SUMIFS(Details!$BB:$BB,Details!$CY:$CY,'Buyer Metrics'!$AF17,Details!$C:$C,'Buyer Metrics'!AV$4) -> 0 | AW17: =SUMIFS(Details!$BB:$BB,Details!$CY:$CY,'Buyer Metrics'!$AF17,Details!$C:$C,'Buyer Metrics'!AW$4) -> 0 | AX17: =SUMIFS(Details!$BB:$BB,Details!$CY:$CY,'Buyer Metrics'!$AF17,Details!$C:$C,'Buyer Metrics'!AX$4) -> 0 | AY17: =SUMIFS(Details!$BB:$BB,Details!$CY:$CY,'Buyer Metrics'!$AF17,Details!$C:$C,'Buyer Metrics'!AY$4) -> 0 | AZ17: =SUMIFS(Details!$BB:$BB,Details!$CY:$CY,'Buyer Metrics'!$AF17,Details!$C:$C,'Buyer Metrics'!AZ$4) -> 0 | BA17: =SUMIFS(Details!$BB:$BB,Details!$CY:$CY,'Buyer Metrics'!$AF17,Details!$C:$C,'Buyer Metrics'!BA$4) -> 0 | BB17: =SUMIFS(Details!$BB:$BB,Details!$CY:$CY,'Buyer Metrics'!$AF17,Details!$C:$C,'Buyer Metrics'!BB$4) -> 0 | BC17: =SUMIFS(Details!$BB:$BB,Details!$CY:$CY,'Buyer Metrics'!$AF17,Details!$C:$C,'Buyer Metrics'!BC$4) -> 0
AU18: =SUMIFS(Details!$BB:$BB,Details!$CY:$CY,'Buyer Metrics'!$AF18,Details!$C:$C,'Buyer Metrics'!AU$4) -> 0 | AV18: =SUMIFS(Details!$BB:$BB,Details!$CY:$CY,'Buyer Metrics'!$AF18,Details!$C:$C,'Buyer Metrics'!AV$4) -> 0 | AW18: =SUMIFS(Details!$BB:$BB,Details!$CY:$CY,'Buyer Metrics'!$AF18,Details!$C:$C,'Buyer Metrics'!AW$4) -> 0 | AX18: =SUMIFS(Details!$BB:$BB,Details!$CY:$CY,'Buyer Metrics'!$AF18,Details!$C:$C,'Buyer Metrics'!AX$4) -> 0 | AY18: =SUMIFS(Details!$BB:$BB,Details!$CY:$CY,'Buyer Metrics'!$AF18,Details!$C:$C,'Buyer Metrics'!AY$4) -> 0 | AZ18: =SUMIFS(Details!$BB:$BB,Details!$CY:$CY,'Buyer Metrics'!$AF18,Details!$C:$C,'Buyer Metrics'!AZ$4) -> 0 | BA18: =SUMIFS(Details!$BB:$BB,Details!$CY:$CY,'Buyer Metrics'!$AF18,Details!$C:$C,'Buyer Metrics'!BA$4) -> 0 | BB18: =SUMIFS(Details!$BB:$BB,Details!$CY:$CY,'Buyer Metrics'!$AF18,Details!$C:$C,'Buyer Metrics'!BB$4) -> 0 | BC18: =SUMIFS(Details!$BB:$BB,Details!$CY:$CY,'Buyer Metrics'!$AF18,Details!$C:$C,'Buyer Metrics'!BC$4) -> 0
AU19: =SUMIFS(Details!$BB:$BB,Details!$CY:$CY,'Buyer Metrics'!$AF19,Details!$C:$C,'Buyer Metrics'!AU$4) -> 0 | AV19: =SUMIFS(Details!$BB:$BB,Details!$CY:$CY,'Buyer Metrics'!$AF19,Details!$C:$C,'Buyer Metrics'!AV$4) -> 0 | AW19: =SUMIFS(Details!$BB:$BB,Details!$CY:$CY,'Buyer Metrics'!$AF19,Details!$C:$C,'Buyer Metrics'!AW$4) -> 0 | AX19: =SUMIFS(Details!$BB:$BB,Details!$CY:$CY,'Buyer Metrics'!$AF19,Details!$C:$C,'Buyer Metrics'!AX$4) -> 0 | AY19: =SUMIFS(Details!$BB:$BB,Details!$CY:$CY,'Buyer Metrics'!$AF19,Details!$C:$C,'Buyer Metrics'!AY$4) -> 0 | AZ19: =SUMIFS(Details!$BB:$BB,Details!$CY:$CY,'Buyer Metrics'!$AF19,Details!$C:$C,'Buyer Metrics'!AZ$4) -> 0 | BA19: =SUMIFS(Details!$BB:$BB,Details!$CY:$CY,'Buyer Metrics'!$AF19,Details!$C:$C,'Buyer Metrics'!BA$4) -> 0 | BB19: =SUMIFS(Details!$BB:$BB,Details!$CY:$CY,'Buyer Metrics'!$AF19,Details!$C:$C,'Buyer Metrics'!BB$4) -> 0 | BC19: =SUMIFS(Details!$BB:$BB,Details!$CY:$CY,'Buyer Metrics'!$AF19,Details!$C:$C,'Buyer Metrics'!BC$4) -> 0
AU20: =SUMIFS(Details!$BB:$BB,Details!$CY:$CY,'Buyer Metrics'!$AF20,Details!$C:$C,'Buyer Metrics'!AU$4) -> 0 | AV20: =SUMIFS(Details!$BB:$BB,Details!$CY:$CY,'Buyer Metrics'!$AF20,Details!$C:$C,'Buyer Metrics'!AV$4) -> 0 | AW20: =SUMIFS(Details!$BB:$BB,Details!$CY:$CY,'Buyer Metrics'!$AF20,Details!$C:$C,'Buyer Metrics'!AW$4) -> 0 | AX20: =SUMIFS(Details!$BB:$BB,Details!$CY:$CY,'Buyer Metrics'!$AF20,Details!$C:$C,'Buyer Metrics'!AX$4) -> 0 | AY20: =SUMIFS(Details!$BB:$BB,Details!$CY:$CY,'Buyer Metrics'!$AF20,Details!$C:$C,'Buyer Metrics'!AY$4) -> 0 | AZ20: =SUMIFS(Details!$BB:$BB,Details!$CY:$CY,'Buyer Metrics'!$AF20,Details!$C:$C,'Buyer Metrics'!AZ$4) -> 0 | BA20: =SUMIFS(Details!$BB:$BB,Details!$CY:$CY,'Buyer Metrics'!$AF20,Details!$C:$C,'Buyer Metrics'!BA$4) -> 0 | BB20: =SUMIFS(Details!$BB:$BB,Details!$CY:$CY,'Buyer Metrics'!$AF20,Details!$C:$C,'Buyer Metrics'!BB$4) -> 0 | BC20: =SUMIFS(Details!$BB:$BB,Details!$CY:$CY,'Buyer Metrics'!$AF20,Details!$C:$C,'Buyer Metrics'!BC$4) -> 0
AU21: =SUMIFS(Details!$BB:$BB,Details!$CY:$CY,'Buyer Metrics'!$AF21,Details!$C:$C,'Buyer Metrics'!AU$4) -> 0 | AV21: =SUMIFS(Details!$BB:$BB,Details!$CY:$CY,'Buyer Metrics'!$AF21,Details!$C:$C,'Buyer Metrics'!AV$4) -> 0 | AW21: =SUMIFS(Details!$BB:$BB,Details!$CY:$CY,'Buyer Metrics'!$AF21,Details!$C:$C,'Buyer Metrics'!AW$4) -> 0 | AX21: =SUMIFS(Details!$BB:$BB,Details!$CY:$CY,'Buyer Metrics'!$AF21,Details!$C:$C,'Buyer Metrics'!AX$4) -> 0 | AY21: =SUMIFS(Details!$BB:$BB,Details!$CY:$CY,'Buyer Metrics'!$AF21,Details!$C:$C,'Buyer Metrics'!AY$4) -> 0 | AZ21: =SUMIFS(Details!$BB:$BB,Details!$CY:$CY,'Buyer Metrics'!$AF21,Details!$C:$C,'Buyer Metrics'!AZ$4) -> 0 | BA21: =SUMIFS(Details!$BB:$BB,Details!$CY:$CY,'Buyer Metrics'!$AF21,Details!$C:$C,'Buyer Metrics'!BA$4) -> 0 | BB21: =SUMIFS(Details!$BB:$BB,Details!$CY:$CY,'Buyer Metrics'!$AF21,Details!$C:$C,'Buyer Metrics'!BB$4) -> 0 | BC21: =SUMIFS(Details!$BB:$BB,Details!$CY:$CY,'Buyer Metrics'!$AF21,Details!$C:$C,'Buyer Metrics'!BC$4) -> 0
AU22: =SUMIFS(Details!$BB:$BB,Details!$CY:$CY,'Buyer Metrics'!$AF22,Details!$C:$C,'Buyer Metrics'!AU$4) -> 0 | AV22: =SUMIFS(Details!$BB:$BB,Details!$CY:$CY,'Buyer Metrics'!$AF22,Details!$C:$C,'Buyer Metrics'!AV$4) -> 0 | AW22: =SUMIFS(Details!$BB:$BB,Details!$CY:$CY,'Buyer Metrics'!$AF22,Details!$C:$C,'Buyer Metrics'!AW$4) -> 0 | AX22: =SUMIFS(Details!$BB:$BB,Details!$CY:$CY,'Buyer Metrics'!$AF22,Details!$C:$C,'Buyer Metrics'!AX$4) -> 0 | AY22: =SUMIFS(Details!$BB:$BB,Details!$CY:$CY,'Buyer Metrics'!$AF22,Details!$C:$C,'Buyer Metrics'!AY$4) -> 0 | AZ22: =SUMIFS(Details!$BB:$BB,Details!$CY:$CY,'Buyer Metrics'!$AF22,Details!$C:$C,'Buyer Metrics'!AZ$4) -> 0 | BA22: =SUMIFS(Details!$BB:$BB,Details!$CY:$CY,'Buyer Metrics'!$AF22,Details!$C:$C,'Buyer Metrics'!BA$4) -> 0 | BB22: =SUMIFS(Details!$BB:$BB,Details!$CY:$CY,'Buyer Metrics'!$AF22,Details!$C:$C,'Buyer Metrics'!BB$4) -> 0 | BC22: =SUMIFS(Details!$BB:$BB,Details!$CY:$CY,'Buyer Metrics'!$AF22,Details!$C:$C,'Buyer Metrics'!BC$4) -> 0
... AU124: =SUMIFS(Details!$BB:$BB,Details!$CY:$CY,'Buyer Metrics'!$AF124,Details!$C:$C,'Buyer Metrics'!AU$4) -> 0 | AV124: =SUMIFS(Details!$BB:$BB,Details!$CY:$CY,'Buyer Metrics'!$AF124,Details!$C:$C,'Buyer Metrics'!AV$4) -> 0 | AW124: =SUMIFS(Details!$BB:$BB,Details!$CY:$CY,'Buyer Metrics'!$AF124,Details!$C:$C,'Buyer Metrics'!AW$4) -> 0 | AX124: =SUMIFS(Details!$BB:$BB,Details!$CY:$CY,'Buyer Metrics'!$AF124,Details!$C:$C,'Buyer Metrics'!AX$4) -> 0 | AY124: =SUMIFS(Details!$BB:$BB,Details!$CY:$CY,'Buyer Metrics'!$AF124,Details!$C:$C,'Buyer Metrics'!AY$4) -> 0 | AZ124: =SUMIFS(Details!$BB:$BB,Details!$CY:$CY,'Buyer Metrics'!$AF124,Details!$C:$C,'Buyer Metrics'!AZ$4) -> 0 | BA124: =SUMIFS(Details!$BB:$BB,Details!$CY:$CY,'Buyer Metrics'!$AF124,Details!$C:$C,'Buyer Metrics'!BA$4) -> 0 | BB124: =SUMIFS(Details!$BB:$BB,Details!$CY:$CY,'Buyer Metrics'!$AF124,Details!$C:$C,'Buyer Metrics'!BB$4) -> 0 | BC124: =SUMIFS(Details!$BB:$BB,Details!$CY:$CY,'Buyer Metrics'!$AF124,Details!$C:$C,'Buyer Metrics'!BC$4) -> 0

Sheet Receivables
I1: =SUBTOTAL(9,I3:I20) -> 198939.52 | J1: =SUBTOTAL(9,J3:J20) -> 231362.02
B2: date | C2: status | D2: entity | E2: age | F2: due_date | G2: transaction_number | H2: customer_name | I2: balance | J2: amount | K2: payment_terms | L2: gst_no | M2: credit_limit | N2: unused_credits_receivable_amount | O2: contact.CF.Vertical Name | P2: Check
B3: 45980 | C3: overdue | D3: invoice | E3: 206 | F3: 2025-11-20 | G3: 26/MPM4/INV0018 | H3: Pernod Ricard India Foundation | I3: 27.5 | J3: 32450 | K3: Net 5 (Days) | M3: 100000 | N3: 0 | O3: Marketplace (M4) | P3: Marketplace Sales (M4)
B4: 46070 | C4: overdue | D4: invoice | E4: 111 | F4: 2026-02-23 | G4: 26/MPM4/INV0022 | H4: BLACK GOLD RECYCLING PRIVATE LIMITED (36) | I4: 7500.16 | J4: 7500.16 | K4: Net 5 (Days) | L4: 36AAMCB5608A1ZY | M4: 45000000 | N4: 0 | O4: Marketplace (Re-Commerce) | P4: Marketplace Sales (M4)
B5: 46101 | C5: overdue | D5: invoice | E5: 80 | F5: 2026-03-26 | G5: 26/MPM4/INV0023 | H5: BLACK GOLD RECYCLING PRIVATE LIMITED (36) | I5: 35000.7 | J5: 35000.7 | K5: Net 5 (Days) | L5: 36AAMCB5608A1ZY | M5: 45000000 | N5: 0 | O5: Marketplace (Re-Commerce) | P5: Marketplace Sales (M4)
B6: 46106 | C6: overdue | D6: invoice | E6: 75 | F6: 2026-03-31 | G6: 26/MPM4/INV0024 | H6: INFINITYBOX PRIVATE LIMITED | I6: 56731.5 | J6: 56731.5 | K6: Advance Payment | L6: 29AAFCI4561G1ZF | M6: 500000 | N6: 0 | O6: Marketplace (M4) | P6: Marketplace Sales (M4)
B7: 46112 | C7: overdue | D7: invoice | E7: 69 | F7: 2026-04-06 | G7: 26/MPM4/INV0025 | H7: BLACK GOLD RECYCLING PRIVATE LIMITED (36) | I7: 7500.16 | J7: 7500.16 | K7: Net 5 (Days) | L7: 36AAMCB5608A1ZY | M7: 45000000 | N7: 0 | O7: Marketplace (Re-Commerce) | P7: Marketplace Sales (M4)
B8: 46140 | C8: overdue | D8: invoice | E8: 41 | F8: 2026-05-04 | G8: 36/M4/27IN00001 | H8: INFINITYBOX PRIVATE LIMITED | I8: 34503 | J8: 34503 | K8: Advance Payment | L8: 29AAFCI4561G1ZF | M8: 500000 | N8: 0 | O8: Marketplace (M4) | P8: Marketplace Sales (M4)
B9: 46161 | C9: overdue | D9: invoice | E9: 20 | F9: 2026-05-25 | G9: 36/M4/27IN00002 | H9: INFINITYBOX PRIVATE LIMITED | I9: 36729 | J9: 36729 | K9: Advance Payment | L9: 29AAFCI4561G1ZF | M9: 500000 | N9: 0 | O9: Marketplace (M4) | P9: Marketplace Sales (M4)
B10: 46183 | C10: sent | D10: invoice | F10: 2026-06-16 | G10: 36/M4/27IN00003 | H10: INFINITYBOX PRIVATE LIMITED | I10: 20947.5 | J10: 20947.5 | K10: Advance Payment | L10: 29AAFCI4561G1ZF | M10: 500000 | N10: 0 | O10: Marketplace (M4) | P10: Marketplace Sales (M4)

Sheet POC
D1: Rohan Gupta
E2: 30 | F2: 15 | G2: 0 | H2: 0 | I2: 0 | J2: 0 | K2: 0 | L2: 0 | M2: 0 | N2: 0 | O2: 0 | P2: 0 | Q2: 45
B3: {=_xlfn.UNIQUE(Details!CM4:CM11)} -> Customer POC Name | D3: =D1 -> Rohan Gupta | E3: 45748 | F3: May-25 | G3: Jun-25 | H3: Jul-25 | I3: Aug-25 | J3: Sep-25 | K3: Oct-25 | L3: Nov-25 | M3: Dec-25 | N3: Jan-26 | O3: Feb-26 | P3: Mar-26 | Q3: FY 2025-26
B4: #N/A | D4: Quantity (MT) | E4: =SUMIFS(Details!BA:BA,Details!CL:CL,POC!$D$3,Details!CF:CF,POC!E$3)/1000 -> 0 | F4: 450.1419 | G4: 0 | H4: 0 | I4: 0 | J4: 0 | K4: 0 | L4: 0 | M4: 0 | N4: 0 | O4: 0 | P4: 0 | Q4: 1434.2252
B5: 0 | D5: Sales | E5: =SUMIFS(Details!BA:BA,Details!CL:CL,POC!$D$3,Details!CF:CF,POC!E$3)/1000 -> 0 | F5: 2.1917196e+08 | G5: 0 | H5: 0 | I5: 0 | J5: 0 | K5: 0 | L5: 0 | M5: 0 | N5: 0 | O5: 0 | P5: 0 | Q5: 5.6169703e+08
D6: Purchases | E6: 3.3894035e+08 | F6: 2.1700534e+08 | G6: 0 | H6: 0 | I6: 0 | J6: 0 | K6: 0 | L6: 0 | M6: 0 | N6: 0 | O6: 0 | P6: 0 | Q6: 5.5594569e+08
D7: Transportation Charges | E7: 0 | F7: 147155 | G7: 0 | H7: 0 | I7: 0 | J7: 0 | K7: 0 | L7: 0 | M7: 0 | N7: 0 | O7: 0 | P7: 0 | Q7: 147155
D8: Net Sales | E8: 3584718.7 | F8: 2166623 | G8: 0 | H8: 0 | I8: 0 | J8: 0 | K8: 0 | L8: 0 | M8: 0 | N8: 0 | O8: 0 | P8: 0 | Q8: 5751341.7
D9: Contribution | E9: 3584718.7 | F9: 2019468 | G9: 0 | H9: 0 | I9: 0 | J9: 0 | K9: 0 | L9: 0 | M9: 0 | N9: 0 | O9: 0 | P9: 0 | Q9: 5604186.7
D10: Net Sales (%) | E10: 0.010465566 | F10: 0.0098854932 | G10: 0 | H10: 0 | I10: 0 | J10: 0 | K10: 0 | L10: 0 | M10: 0 | N10: 0 | O10: 0 | P10: 0 | Q10: 0.010239224
D11: Transport Charges (%) | E11: 0 | F11: 0.00067141343 | G11: 0 | H11: 0 | I11: 0 | J11: 0 | K11: 0 | L11: 0 | M11: 0 | N11: 0 | O11: 0 | P11: 0 | Q11: 0.00026198287
D12: Contribution (%) | E12: 0.010465566 | F12: 0.0092140798 | G12: 0 | H12: 0 | I12: 0 | J12: 0 | K12: 0 | L12: 0 | M12: 0 | N12: 0 | O12: 0 | P12: 0 | Q12: 0.0099772411
D13: Revenue Per Kg | E13: 348.0651 | F13: 486.89527 | G13: #DIV/0! | H13: #DIV/0! | I13: #DIV/0! | J13: #DIV/0! | K13: #DIV/0! | L13: #DIV/0! | M13: #DIV/0! | N13: #DIV/0! | O13: #DIV/0! | P13: #DIV/0! | Q13: 391.63794
D14: Purchase Cost Per Kg | E14: 344.4224 | F14: 482.08207 | G14: #DIV/0! | H14: #DIV/0! | I14: #DIV/0! | J14: #DIV/0! | K14: #DIV/0! | L14: #DIV/0! | M14: #DIV/0! | N14: #DIV/0! | O14: #DIV/0! | P14: #DIV/0! | Q14: 387.62788
D15: Transportation Charges Per Kg | E15: 0 | F15: 0.32690803 | G15: #DIV/0! | H15: #DIV/0! | I15: #DIV/0! | J15: #DIV/0! | K15: #DIV/0! | L15: #DIV/0! | M15: #DIV/0! | N15: #DIV/0! | O15: #DIV/0! | P15: #DIV/0! | Q15: 0.10260243
D16: No. of Transactions | E16: 61 | F16: 37 | G16: 0 | H16: 0 | I16: 0 | J16: 0 | K16: 0 | L16: 0 | M16: 0 | N16: 0 | O16: 0 | P16: 0 | Q16: 98
D17: No. of Sellers (Aggregators) | E17: 10 | F17: 7 | G17: 0 | H17: 0 | I17: 0 | J17: 0 | K17: 0 | L17: 0 | M17: 0 | N17: 0 | O17: 0 | P17: 0 | Q17: 12
D18: No. of Buyers (Recyclers) | E18: 7 | F18: 11 | G18: 0 | H18: 0 | I18: 0 | J18: 0 | K18: 0 | L18: 0 | M18: 0 | N18: 0 | O18: 0 | P18: 0 | Q18: 13
D19: Full Rejection | E19: 0 | F19: 0 | G19: 0 | H19: 0 | I19: 0 | J19: 0 | K19: 0 | L19: 0 | M19: 0 | N19: 0 | O19: 0 | P19: 0 | Q19: 0
D20: Receivables (exl Legacy) | E20: 0 | F20: 1.8153706e+08 | G20: 0 | H20: 0 | I20: 0 | J20: 0 | K20: 0 | L20: 0 | M20: 0 | N20: 0 | O20: 0 | P20: 0 | Q20: 1.8153706e+08
D21: DSO (Days) | E21: 0 | F21: 10.529059 | G21: 0 | H21: 0 | I21: 0 | J21: 0 | K21: 0 | L21: 0 | M21: 0 | N21: 0 | O21: 0 | P21: 0 | Q21: 12.325192
D22: Credit Notes (Value - Incl. Prov) | E22: 8128770.9 | F22: 5575918.2 | G22: 0 | H22: 0 | I22: 0 | J22: 0 | K22: 0 | L22: 0 | M22: 0 | N22: 0 | O22: 0 | P22: 0 | Q22: 13704689
D23: Credit Notes (% to Revenue) | E23: 0.023731901 | F23: 0.025440837 | G23: #DIV/0! | H23: #DIV/0! | I23: #DIV/0! | J23: #DIV/0! | K23: #DIV/0! | L23: #DIV/0! | M23: #DIV/0! | N23: #DIV/0! | O23: #DIV/0! | P23: #DIV/0! | Q23: 0.024398721
D24: Debit Notes (Value - Incl. Prov) | E24: 8049284.3 | F24: 5522976 | G24: 0 | H24: 0 | I24: 0 | J24: 0 | K24: 0 | L24: 0 | M24: 0 | N24: 0 | O24: 0 | P24: 0 | Q24: 13572260
D25: Debit Notes (% to Purchase) | E25: 0.02374838 | F25: 0.025450876 | G25: #DIV/0! | H25: #DIV/0! | I25: #DIV/0! | J25: #DIV/0! | K25: #DIV/0! | L25: #DIV/0! | M25: #DIV/0! | N25: #DIV/0! | O25: #DIV/0! | P25: #DIV/0! | Q25: 0.024412925
D27: KPI's without Provisions | E27: Apr-25 | F27: 45778 | G27: 45809 | H27: 45839 | I27: 45870 | J27: 45901 | K27: 45931 | L27: 45962 | M27: 45992 | N27: 46023 | O27: 46054 | P27: 46082 | Q27: FY 2025-26
D28: Sales without Provision | E28: 3.351243e+08 | F28: 2.1406416e+08 | G28: 0 | H28: 0 | I28: 0 | J28: 0 | K28: 0 | L28: 0 | M28: 0 | N28: 0 | O28: 0 | P28: 0 | Q28: 5.4918846e+08
D29: Purchases without Provision | E29: 3.3161174e+08 | F29: 2.1194674e+08 | G29: 0 | H29: 0 | I29: 0 | J29: 0 | K29: 0 | L29: 0 | M29: 0 | N29: 0 | O29: 0 | P29: 0 | Q29: 5.4355848e+08
D30: Contribution without Provision | E30: 3512561.6 | F30: 2117412.9 | G30: 0 | H30: 0 | I30: 0 | J30: 0 | K30: 0 | L30: 0 | M30: 0 | N30: 0 | O30: 0 | P30: 0 | Q30: 5629974.5
D31: Contribution (%) | E31: 0.010481369 | F31: 0.0098914875 | G31: #DIV/0! | H31: #DIV/0! | I31: #DIV/0! | J31: #DIV/0! | K31: #DIV/0! | L31: #DIV/0! | M31: #DIV/0! | N31: #DIV/0! | O31: #DIV/0! | P31: #DIV/0! | Q31: 0.010251444
D33: Business Trends | E33: Apr-25 | F33: 45778 | G33: 45809 | H33: 45839 | I33: 45870 | J33: 45901 | K33: 45931 | L33: 45962 | M33: 45992 | N33: 46023 | O33: 46054 | P33: 46082 | Q33: FY 2025-26
D34: Sales-Revenue (MoM) | E34: 0 | F34: -0.36012869 | G34: -1 | H34: 0 | I34: 0 | J34: 0 | K34: 0 | L34: 0 | M34: 0 | N34: 0 | O34: 0 | P34: 0 | Q34: 0
D35: Sales-Volume (MoM) | E35: 0 | F35: -0.54257747 | G35: -1 | H35: 0 | I35: 0 | J35: 0 | K35: 0 | L35: 0 | M35: 0 | N35: 0 | O35: 0 | P35: 0 | Q35: 0
D36: Sales-Transactions (MoM) | E36: 0 | F36: -0.39344262 | G36: -1 | H36: 0 | I36: 0 | J36: 0 | K36: 0 | L36: 0 | M36: 0 | N36: 0 | O36: 0 | P36: 0 | Q36: 0
D38: Loss Making Transactions | E38: Apr-25 | F38: 45778 | G38: 45809 | H38: 45839 | I38: 45870 | J38: 45901 | K38: 45931 | L38: 45962 | M38: 45992 | N38: 46023 | O38: 46054 | P38: 46082 | Q38: FY 2025-26
D39: No of LMT @ Inception | E39: 2 | F39: 0 | G39: 0 | H39: 0 | I39: 0 | J39: 0 | K39: 0 | L39: 0 | M39: 0 | N39: 0 | O39: 0 | P39: 0 | Q39: 0
D40: Value of LMT @ Inception | E40: 57062 | F40: 0 | G40: 0 | H40: 0 | I40: 0 | J40: 0 | K40: 0 | L40: 0 | M40: 0 | N40: 0 | O40: 0 | P40: 0 | Q40: 0
D41: No of LMT | E41: 1 | F41: 0 | G41: 0 | H41: 0 | I41: 0 | J41: 0 | K41: 0 | L41: 0 | M41: 0 | N41: 0 | O41: 0 | P41: 0 | Q41: 0
D42: % of LMT | E42: 0.016393443 | F42: 0 | G42: 0 | H42: 0 | I42: 0 | J42: 0 | K42: 0 | L42: 0 | M42: 0 | N42: 0 | O42: 0 | P42: 0 | Q42: 0
D43: Value of LMT | E43: 15787 | F43: 0 | G43: 0 | H43: 0 | I43: 0 | J43: 0 | K43: 0 | L43: 0 | M43: 0 | N43: 0 | O43: 0 | P43: 0 | Q43: 0
D45: CN & DN Provisions | E45: Apr-25 | F45: 45778 | G45: 45809 | H45: 45839 | I45: 45870 | J45: 45901 | K45: 45931 | L45: 45962 | M45: 45992 | N45: 46023 | O45: 46054 | P45: 46082 | Q45: FY 2025-26
D46: DN Provision | E46: 7328604.7 | F46: 5058598.3 | G46: 0 | H46: 0 | I46: 0 | J46: 0 | K46: 0 | L46: 0 | M46: 0 | N46: 0 | O46: 0 | P46: 0 | Q46: 12387203
D47: CN Provision | E47: 7400761.8 | F47: 5107808.3 | G47: 0 | H47: 0 | I47: 0 | J47: 0 | K47: 0 | L47: 0 | M47: 0 | N47: 0 | O47: 0 | P47: 0 | Q47: 12508570
D49: Qty Returned | E49: Apr-25 | F49: 45778 | G49: 45809 | H49: 45839 | I49: 45870 | J49: 45901 | K49: 45931 | L49: 45962 | M49: 45992 | N49: 46023 | O49: 46054 | P49: 46082 | Q49: FY 2025-26
E50: 0 | F50: 0 | G50: 0 | H50: 0 | I50: 0 | J50: 0 | K50: 0 | L50: 0 | M50: 0 | N50: 0 | O50: 0 | P50: 0 | Q50: 0
D52: Margins | E52: Apr-25 | F52: 45778 | G52: 45809 | H52: 45839 | I52: 45870 | J52: 45901 | K52: 45931 | L52: 45962 | M52: 45992 | N52: 46023 | O52: 46054 | P52: 46082 | Q52: FY 2025-26
D53: Gross Margin | E53: 3664205.4 | F53: 2219565.2 | G53: 0 | H53: 0 | I53: 0 | J53: 0 | K53: 0 | L53: 0 | M53: 0 | N53: 0 | O53: 0 | P53: 0 | Q53: 5883770.5
D54: Recykal Margin | E54: 3664205.4 | F54: 2072410.2 | G54: 0 | H54: 0 | I54: 0 | J54: 0 | K54: 0 | L54: 0 | M54: 0 | N54: 0 | O54: 0 | P54: 0 | Q54: 5736615.5
D55: Net Margin | E55: 3584718.7 | F55: 2019468 | G55: 0 | H55: 0 | I55: 0 | J55: 0 | K55: 0 | L55: 0 | M55: 0 | N55: 0 | O55: 0 | P55: 0 | Q55: 5604186.7

Sheet GST TDS
A1: IGST TDS Payable-2%
B2: GST TDS to be deducted by Customers for Fy 2025-26 | M2: =SUBTOTAL(9,M4:M100) -> 0 | N2: =SUBTOTAL(9,N4:N100) -> 0 | O2: =SUBTOTAL(9,O4:O100) -> 0 | P2: =SUBTOTAL(9,P4:P100) -> 0 | Q2: =SUBTOTAL(9,Q4:Q100) -> 0 | R2: =SUBTOTAL(9,R4:R100) -> 0
B3: SO Number | C3: Month | D3: Customer Name | E3: GST Numbers | F3: Sale Value | G3: GST TDS | J3: {=_xlfn.UNIQUE(_xlfn._TRO_TRAILING(D3:D999))} -> Customer Name | K3: GST IN | L3: PAN No | M3: {=_xlfn.TOROW(_xlfn.UNIQUE(C4:C2000))} -> #VALUE! | N3: 0 | O3: 0
B4: {=_xlfn.UNIQUE(_xlfn._xlws.FILTER(Details!E:E,Details!CZ:CZ='GST TDS'!A1))} -> #VALUE! | C4: =_xlfn.XLOOKUP(B4,Details!E:E,Details!CG:CG) -> #VALUE! | D4: =_xlfn.XLOOKUP(B4,Details!E:E,Details!AQ:AQ) -> #VALUE! | E4: =_xlfn.XLOOKUP(B4,Details!E:E,Details!AR:AR) -> #VALUE! | F4: =SUMIFS(Details!AY:AY,Details!E:E,'GST TDS'!B4) -> 0 | G4: =F4*2% -> 0 | J4: #VALUE! | K4: =_xlfn.XLOOKUP(J4,Details!AQ:AQ,Details!AR:AR) -> #VALUE! | L4: =MID(K4,3,10) -> #VALUE! | M4: =SUMIFS($G:$G,$D:$D,$J4,$C:$C,M$3) -> 0 | N4: =SUMIFS($G:$G,$D:$D,$J4,$C:$C,N$3) -> 0 | O4: =SUMIFS($G:$G,$D:$D,$J4,$C:$C,O$3) -> 0 | P4: =SUMIFS($G:$G,$D:$D,$J4,$C:$C,P$3) -> 0 | Q4: =SUMIFS($G:$G,$D:$D,$J4,$C:$C,Q$3) -> 0 | R4: =SUMIFS($G:$G,$D:$D,$J4,$C:$C,R$3) -> 0
C5: =_xlfn.XLOOKUP(B5,Details!E:E,Details!CG:CG) -> 0 | D5: =_xlfn.XLOOKUP(B5,Details!E:E,Details!AQ:AQ) -> 0 | E5: =_xlfn.XLOOKUP(B5,Details!E:E,Details!AR:AR) -> 0 | F5: =SUMIFS(Details!AY:AY,Details!E:E,'GST TDS'!B5) -> 0 | G5: =F5*2% -> 0 | J5: 0 | K5: =_xlfn.XLOOKUP(J5,Details!AQ:AQ,Details!AR:AR) -> #N/A | L5: =MID(K5,3,10) -> #N/A | M5: =SUMIFS($G:$G,$D:$D,$J5,$C:$C,M$3) -> 0 | N5: =SUMIFS($G:$G,$D:$D,$J5,$C:$C,N$3) -> 0 | O5: =SUMIFS($G:$G,$D:$D,$J5,$C:$C,O$3) -> 0 | P5: =SUMIFS($G:$G,$D:$D,$J5,$C:$C,P$3) -> 0 | Q5: =SUMIFS($G:$G,$D:$D,$J5,$C:$C,Q$3) -> 0 | R5: =SUMIFS($G:$G,$D:$D,$J5,$C:$C,R$3) -> 0
C6: =_xlfn.XLOOKUP(B6,Details!E:E,Details!CG:CG) -> 0 | D6: =_xlfn.XLOOKUP(B6,Details!E:E,Details!AQ:AQ) -> 0 | E6: =_xlfn.XLOOKUP(B6,Details!E:E,Details!AR:AR) -> 0 | F6: =SUMIFS(Details!AY:AY,Details!E:E,'GST TDS'!B6) -> 0 | G6: =F6*2% -> 0 | K6: =_xlfn.XLOOKUP(J6,Details!AQ:AQ,Details!AR:AR) -> 0 | L6: =MID(K6,3,10) | M6: =SUMIFS($G:$G,$D:$D,$J6,$C:$C,M$3) -> 0 | N6: =SUMIFS($G:$G,$D:$D,$J6,$C:$C,N$3) -> 0 | O6: =SUMIFS($G:$G,$D:$D,$J6,$C:$C,O$3) -> 0 | P6: =SUMIFS($G:$G,$D:$D,$J6,$C:$C,P$3) -> 0 | Q6: =SUMIFS($G:$G,$D:$D,$J6,$C:$C,Q$3) -> 0 | R6: =SUMIFS($G:$G,$D:$D,$J6,$C:$C,R$3) -> 0
C7: =_xlfn.XLOOKUP(B7,Details!E:E,Details!CG:CG) -> 0 | D7: =_xlfn.XLOOKUP(B7,Details!E:E,Details!AQ:AQ) -> 0 | E7: =_xlfn.XLOOKUP(B7,Details!E:E,Details!AR:AR) -> 0 | F7: =SUMIFS(Details!AY:AY,Details!E:E,'GST TDS'!B7) -> 0 | G7: =F7*2% -> 0 | K7: =_xlfn.XLOOKUP(J7,Details!AQ:AQ,Details!AR:AR) -> 0 | L7: =MID(K7,3,10) | M7: =SUMIFS($G:$G,$D:$D,$J7,$C:$C,M$3) -> 0 | N7: =SUMIFS($G:$G,$D:$D,$J7,$C:$C,N$3) -> 0 | O7: =SUMIFS($G:$G,$D:$D,$J7,$C:$C,O$3) -> 0 | P7: =SUMIFS($G:$G,$D:$D,$J7,$C:$C,P$3) -> 0 | Q7: =SUMIFS($G:$G,$D:$D,$J7,$C:$C,Q$3) -> 0 | R7: =SUMIFS($G:$G,$D:$D,$J7,$C:$C,R$3) -> 0
C8: =_xlfn.XLOOKUP(B8,Details!E:E,Details!CG:CG) -> 0 | D8: =_xlfn.XLOOKUP(B8,Details!E:E,Details!AQ:AQ) -> 0 | E8: =_xlfn.XLOOKUP(B8,Details!E:E,Details!AR:AR) -> 0 | F8: =SUMIFS(Details!AY:AY,Details!E:E,'GST TDS'!B8) -> 0 | G8: =F8*2% -> 0 | K8: =_xlfn.XLOOKUP(J8,Details!AQ:AQ,Details!AR:AR) -> 0 | L8: =MID(K8,3,10) | M8: =SUMIFS($G:$G,$D:$D,$J8,$C:$C,M$3) -> 0 | N8: =SUMIFS($G:$G,$D:$D,$J8,$C:$C,N$3) -> 0 | O8: =SUMIFS($G:$G,$D:$D,$J8,$C:$C,O$3) -> 0 | P8: =SUMIFS($G:$G,$D:$D,$J8,$C:$C,P$3) -> 0 | Q8: =SUMIFS($G:$G,$D:$D,$J8,$C:$C,Q$3) -> 0 | R8: =SUMIFS($G:$G,$D:$D,$J8,$C:$C,R$3) -> 0
C9: =_xlfn.XLOOKUP(B9,Details!E:E,Details!CG:CG) -> 0 | D9: =_xlfn.XLOOKUP(B9,Details!E:E,Details!AQ:AQ) -> 0 | E9: =_xlfn.XLOOKUP(B9,Details!E:E,Details!AR:AR) -> 0 | F9: =SUMIFS(Details!AY:AY,Details!E:E,'GST TDS'!B9) -> 0 | G9: =F9*2% -> 0 | K9: =_xlfn.XLOOKUP(J9,Details!AQ:AQ,Details!AR:AR) -> 0 | L9: =MID(K9,3,10) | M9: =SUMIFS($G:$G,$D:$D,$J9,$C:$C,M$3) -> 0 | N9: =SUMIFS($G:$G,$D:$D,$J9,$C:$C,N$3) -> 0 | O9: =SUMIFS($G:$G,$D:$D,$J9,$C:$C,O$3) -> 0 | P9: =SUMIFS($G:$G,$D:$D,$J9,$C:$C,P$3) -> 0 | Q9: =SUMIFS($G:$G,$D:$D,$J9,$C:$C,Q$3) -> 0 | R9: =SUMIFS($G:$G,$D:$D,$J9,$C:$C,R$3) -> 0
C10: =_xlfn.XLOOKUP(B10,Details!E:E,Details!CG:CG) -> 0 | D10: =_xlfn.XLOOKUP(B10,Details!E:E,Details!AQ:AQ) -> 0 | E10: =_xlfn.XLOOKUP(B10,Details!E:E,Details!AR:AR) -> 0 | F10: =SUMIFS(Details!AY:AY,Details!E:E,'GST TDS'!B10) -> 0 | G10: =F10*2% -> 0 | K10: =_xlfn.XLOOKUP(J10,Details!AQ:AQ,Details!AR:AR) -> 0 | L10: =MID(K10,3,10) | M10: =SUMIFS($G:$G,$D:$D,$J10,$C:$C,M$3) -> 0 | N10: =SUMIFS($G:$G,$D:$D,$J10,$C:$C,N$3) -> 0 | O10: =SUMIFS($G:$G,$D:$D,$J10,$C:$C,O$3) -> 0 | P10: =SUMIFS($G:$G,$D:$D,$J10,$C:$C,P$3) -> 0 | Q10: =SUMIFS($G:$G,$D:$D,$J10,$C:$C,Q$3) -> 0 | R10: =SUMIFS($G:$G,$D:$D,$J10,$C:$C,R$3) -> 0
C11: =_xlfn.XLOOKUP(B11,Details!E:E,Details!CG:CG) -> 0 | D11: =_xlfn.XLOOKUP(B11,Details!E:E,Details!AQ:AQ) -> 0 | E11: =_xlfn.XLOOKUP(B11,Details!E:E,Details!AR:AR) -> 0 | F11: =SUMIFS(Details!AY:AY,Details!E:E,'GST TDS'!B11) -> 0 | G11: =F11*2% -> 0 | K11: =_xlfn.XLOOKUP(J11,Details!AQ:AQ,Details!AR:AR) -> 0 | L11: =MID(K11,3,10) | M11: =SUMIFS($G:$G,$D:$D,$J11,$C:$C,M$3) -> 0 | N11: =SUMIFS($G:$G,$D:$D,$J11,$C:$C,N$3) -> 0 | O11: =SUMIFS($G:$G,$D:$D,$J11,$C:$C,O$3) -> 0 | P11: =SUMIFS($G:$G,$D:$D,$J11,$C:$C,P$3) -> 0 | Q11: =SUMIFS($G:$G,$D:$D,$J11,$C:$C,Q$3) -> 0 | R11: =SUMIFS($G:$G,$D:$D,$J11,$C:$C,R$3) -> 0
C12: =_xlfn.XLOOKUP(B12,Details!E:E,Details!CG:CG) -> 0 | D12: =_xlfn.XLOOKUP(B12,Details!E:E,Details!AQ:AQ) -> 0 | E12: =_xlfn.XLOOKUP(B12,Details!E:E,Details!AR:AR) -> 0 | F12: =SUMIFS(Details!AY:AY,Details!E:E,'GST TDS'!B12) -> 0 | G12: =F12*2% -> 0 | K12: =_xlfn.XLOOKUP(J12,Details!AQ:AQ,Details!AR:AR) -> 0 | L12: =MID(K12,3,10) | M12: =SUMIFS($G:$G,$D:$D,$J12,$C:$C,M$3) -> 0 | N12: =SUMIFS($G:$G,$D:$D,$J12,$C:$C,N$3) -> 0 | O12: =SUMIFS($G:$G,$D:$D,$J12,$C:$C,O$3) -> 0 | P12: =SUMIFS($G:$G,$D:$D,$J12,$C:$C,P$3) -> 0 | Q12: =SUMIFS($G:$G,$D:$D,$J12,$C:$C,Q$3) -> 0 | R12: =SUMIFS($G:$G,$D:$D,$J12,$C:$C,R$3) -> 0
C13: =_xlfn.XLOOKUP(B13,Details!E:E,Details!CG:CG) -> 0 | D13: =_xlfn.XLOOKUP(B13,Details!E:E,Details!AQ:AQ) -> 0 | E13: =_xlfn.XLOOKUP(B13,Details!E:E,Details!AR:AR) -> 0 | F13: =SUMIFS(Details!AY:AY,Details!E:E,'GST TDS'!B13) -> 0 | G13: =F13*2% -> 0 | K13: =_xlfn.XLOOKUP(J13,Details!AQ:AQ,Details!AR:AR) -> 0 | L13: =MID(K13,3,10) | M13: =SUMIFS($G:$G,$D:$D,$J13,$C:$C,M$3) -> 0 | N13: =SUMIFS($G:$G,$D:$D,$J13,$C:$C,N$3) -> 0 | O13: =SUMIFS($G:$G,$D:$D,$J13,$C:$C,O$3) -> 0 | P13: =SUMIFS($G:$G,$D:$D,$J13,$C:$C,P$3) -> 0 | Q13: =SUMIFS($G:$G,$D:$D,$J13,$C:$C,Q$3) -> 0 | R13: =SUMIFS($G:$G,$D:$D,$J13,$C:$C,R$3) -> 0
C14: =_xlfn.XLOOKUP(B14,Details!E:E,Details!CG:CG) -> 0 | D14: =_xlfn.XLOOKUP(B14,Details!E:E,Details!AQ:AQ) -> 0 | E14: =_xlfn.XLOOKUP(B14,Details!E:E,Details!AR:AR) -> 0 | F14: =SUMIFS(Details!AY:AY,Details!E:E,'GST TDS'!B14) -> 0 | G14: =F14*2% -> 0 | K14: =_xlfn.XLOOKUP(J14,Details!AQ:AQ,Details!AR:AR) -> 0 | L14: =MID(K14,3,10) | M14: =SUMIFS($G:$G,$D:$D,$J14,$C:$C,M$3) -> 0 | N14: =SUMIFS($G:$G,$D:$D,$J14,$C:$C,N$3) -> 0 | O14: =SUMIFS($G:$G,$D:$D,$J14,$C:$C,O$3) -> 0 | P14: =SUMIFS($G:$G,$D:$D,$J14,$C:$C,P$3) -> 0 | Q14: =SUMIFS($G:$G,$D:$D,$J14,$C:$C,Q$3) -> 0 | R14: =SUMIFS($G:$G,$D:$D,$J14,$C:$C,R$3) -> 0
C15: =_xlfn.XLOOKUP(B15,Details!E:E,Details!CG:CG) -> 0 | D15: =_xlfn.XLOOKUP(B15,Details!E:E,Details!AQ:AQ) -> 0 | E15: =_xlfn.XLOOKUP(B15,Details!E:E,Details!AR:AR) -> 0 | F15: =SUMIFS(Details!AY:AY,Details!E:E,'GST TDS'!B15) -> 0 | G15: =F15*2% -> 0 | K15: =_xlfn.XLOOKUP(J15,Details!AQ:AQ,Details!AR:AR) -> 0 | L15: =MID(K15,3,10) | M15: =SUMIFS($G:$G,$D:$D,$J15,$C:$C,M$3) -> 0 | N15: =SUMIFS($G:$G,$D:$D,$J15,$C:$C,N$3) -> 0 | O15: =SUMIFS($G:$G,$D:$D,$J15,$C:$C,O$3) -> 0 | P15: =SUMIFS($G:$G,$D:$D,$J15,$C:$C,P$3) -> 0 | Q15: =SUMIFS($G:$G,$D:$D,$J15,$C:$C,Q$3) -> 0 | R15: =SUMIFS($G:$G,$D:$D,$J15,$C:$C,R$3) -> 0
