Workbook

Sheet Summary
D2: =TEXT(D4, "mmm-yy") -> Apr-26 | E2: =TEXT(E4, "mmm-yy") -> May-26 | F2: =TEXT(F4, "mmm-yy") -> Jun-26 | G2: =TEXT(G4, "mmm-yy") -> Jul-26 | H2: =TEXT(H4, "mmm-yy") -> Aug-26 | I2: =TEXT(I4, "mmm-yy") -> Sep-26 | J2: =TEXT(J4, "mmm-yy") -> Oct-26 | K2: =TEXT(K4, "mmm-yy") -> Nov-26 | ... O2: =TEXT(O4, "mmm-yy") -> Mar-27
D3: 30 | E3: 31 | F3: 21 | G3: 0 | H3: 0 | I3: 0 | J3: 0 | K3: 0 | L3: 0 | M3: 0 | N3: 0 | O3: 0 | P3: =SUM(D3:O3) -> 82
C4: Marketplace (Plastic) | D4: 46113 | E4: 46143 | F4: 46174 | G4: 46204 | H4: 46235 | I4: 46266 | J4: 46296 | K4: 46327 | L4: 46357 | M4: 46388 | N4: 46419 | O4: 46447 | P4: FY 2026-27
C5: Quantity (MT) | D5: 36.25 | E5: =SUMIFS(Details!$BB$4:$BB$8,Details!$C$4:$C$8,Summary!E$4)/1000 -> 0 | F5: =SUMIFS(Details!$BB$4:$BB$8,Details!$C$4:$C$8,Summary!F$4)/1000 -> 0 | G5: =SUMIFS(Details!$BB$4:$BB$8,Details!$C$4:$C$8,Summary!G$4)/1000 -> 0 | H5: =SUMIFS(Details!$BB$4:$BB$8,Details!$C$4:$C$8,Summary!H$4)/1000 -> 0 | I5: =SUMIFS(Details!$BB$4:$BB$8,Details!$C$4:$C$8,Summary!I$4)/1000 -> 0 | J5: =SUMIFS(Details!$BB$4:$BB$8,Details!$C$4:$C$8,Summary!J$4)/1000 -> 0 | K5: =SUMIFS(Details!$BB$4:$BB$8,Details!$C$4:$C$8,Summary!K$4)/1000 -> 0 | L5: =SUMIFS(Details!$BB$4:$BB$8,Details!$C$4:$C$8,Summary!L$4)/1000 -> 0 | ... O5: =SUMIFS(Details!$BB$4:$BB$8,Details!$C$4:$C$8,Summary!O$4)/1000 -> 0 | P5: =SUM(D5:O5) -> 36.25 | Q5: =Details!BB9/1000 -> 36.25 | R5: =P5-Q5 -> 0
C6: Net Revenue | D6: 2167276.3 | E6: =SUMIFS(Details!$BL$4:$BL$8,Details!$C$4:$C$8,Summary!E$4) -> 0 | F6: =SUMIFS(Details!$BL$4:$BL$8,Details!$C$4:$C$8,Summary!F$4) -> 0 | G6: =SUMIFS(Details!$BL$4:$BL$8,Details!$C$4:$C$8,Summary!G$4) -> 0 | H6: =SUMIFS(Details!$BL$4:$BL$8,Details!$C$4:$C$8,Summary!H$4) -> 0 | I6: =SUMIFS(Details!$BL$4:$BL$8,Details!$C$4:$C$8,Summary!I$4) -> 0 | J6: =SUMIFS(Details!$BL$4:$BL$8,Details!$C$4:$C$8,Summary!J$4) -> 0 | K6: =SUMIFS(Details!$BL$4:$BL$8,Details!$C$4:$C$8,Summary!K$4) -> 0 | L6: =SUMIFS(Details!$BL$4:$BL$8,Details!$C$4:$C$8,Summary!L$4) -> 0 | ... O6: =SUMIFS(Details!$BL$4:$BL$8,Details!$C$4:$C$8,Summary!O$4) -> 0 | P6: =SUM(D6:O6) -> 2167276.3 | Q6: =Details!BL9 -> 2185035 | R6: =P6-Q6+P75 -> -17758.688
C7: Purchases | D7: 2130617.5 | E7: =SUMIFS(Details!$AM$4:$AM$8,Details!$C$4:$C$8,Summary!E$4)-SUMIFS(Details!$AB$4:$AB$8,Details!$C$4:$C$8,Summary!E$4) -> 0 | F7: =SUMIFS(Details!$AM$4:$AM$8,Details!$C$4:$C$8,Summary!F$4)-SUMIFS(Details!$AB$4:$AB$8,Details!$C$4:$C$8,Summary!F$4) -> 0 | G7: =SUMIFS(Details!$AM$4:$AM$8,Details!$C$4:$C$8,Summary!G$4)-SUMIFS(Details!$AB$4:$AB$8,Details!$C$4:$C$8,Summary!G$4) -> 0 | H7: =SUMIFS(Details!$AM$4:$AM$8,Details!$C$4:$C$8,Summary!H$4)-SUMIFS(Details!$AB$4:$AB$8,Details!$C$4:$C$8,Summary!H$4) -> 0 | I7: =SUMIFS(Details!$AM$4:$AM$8,Details!$C$4:$C$8,Summary!I$4)-SUMIFS(Details!$AB$4:$AB$8,Details!$C$4:$C$8,Summary!I$4) -> 0 | J7: =SUMIFS(Details!$AM$4:$AM$8,Details!$C$4:$C$8,Summary!J$4)-SUMIFS(Details!$AB$4:$AB$8,Details!$C$4:$C$8,Summary!J$4) -> 0 | K7: =SUMIFS(Details!$AM$4:$AM$8,Details!$C$4:$C$8,Summary!K$4)-SUMIFS(Details!$AB$4:$AB$8,Details!$C$4:$C$8,Summary!K$4) -> 0 | L7: =SUMIFS(Details!$AM$4:$AM$8,Details!$C$4:$C$8,Summary!L$4)-SUMIFS(Details!$AB$4:$AB$8,Details!$C$4:$C$8,Summary!L$4) -> 0 | ... O7: =SUMIFS(Details!$AM$4:$AM$8,Details!$C$4:$C$8,Summary!O$4)-SUMIFS(Details!$AB$4:$AB$8,Details!$C$4:$C$8,Summary!O$4) -> 0 | P7: =SUM(D7:O7) -> 2130617.5 | Q7: =Details!P10 -> 2147861 | R7: =P7-Q7 -> -17243.55
C8: Gross Margin | D8: =D6-D7 -> 36658.837 | E8: =E6-E7 -> 0 | F8: =F6-F7 -> 0 | G8: =G6-G7 -> 0 | H8: =H6-H7 -> 0 | I8: =I6-I7 -> 0 | J8: =J6-J7 -> 0 | K8: =K6-K7 -> 0 | ... O8: =O6-O7 -> 0 | P8: =SUM(D8:O8) -> 36658.837
C9: Gross Margin (%) | D9: =IFERROR((D8/D6),0) -> 0.016914704 | E9: =IFERROR((E8/E6),0) -> 0 | F9: =IFERROR((F8/F6),0) -> 0 | G9: =IFERROR((G8/G6),0) -> 0 | H9: =IFERROR((H8/H6),0) -> 0 | I9: =IFERROR((I8/I6),0) -> 0 | J9: =IFERROR((J8/J6),0) -> 0 | K9: =IFERROR((K8/K6),0) -> 0 | ... P9: =IFERROR((P8/P6),0) -> 0.016914704
C10: Transportation Charges | D10: 0 | E10: =SUMIFS(Details!$AB$4:$AB$8,Details!$C$4:$C$8,Summary!E$4) -> 0 | F10: =SUMIFS(Details!$AB$4:$AB$8,Details!$C$4:$C$8,Summary!F$4) -> 0 | G10: =SUMIFS(Details!$AB$4:$AB$8,Details!$C$4:$C$8,Summary!G$4) -> 0 | H10: =SUMIFS(Details!$AB$4:$AB$8,Details!$C$4:$C$8,Summary!H$4) -> 0 | I10: =SUMIFS(Details!$AB$4:$AB$8,Details!$C$4:$C$8,Summary!I$4) -> 0 | J10: =SUMIFS(Details!$AB$4:$AB$8,Details!$C$4:$C$8,Summary!J$4) -> 0 | K10: =SUMIFS(Details!$AB$4:$AB$8,Details!$C$4:$C$8,Summary!K$4) -> 0 | L10: =SUMIFS(Details!$AB$4:$AB$8,Details!$C$4:$C$8,Summary!L$4) -> 0 | ... O10: =SUMIFS(Details!$AB$4:$AB$8,Details!$C$4:$C$8,Summary!O$4) -> 0 | P10: =SUM(D10:O10) -> 0 | Q10: =Details!AB9 -> 0 | R10: =P10-Q10 -> 0
C11: Operational Cost | D11: =SUMIFS(Details!$AC$4:$AC$8,Details!$C$4:$C$8,Summary!D$4) -> 0 | E11: =SUMIFS(Details!$AC$4:$AC$8,Details!$C$4:$C$8,Summary!E$4) -> 0 | F11: =SUMIFS(Details!$AC$4:$AC$8,Details!$C$4:$C$8,Summary!F$4) -> 0 | G11: =SUMIFS(Details!$AC$4:$AC$8,Details!$C$4:$C$8,Summary!G$4) -> 0 | H11: =SUMIFS(Details!$AC$4:$AC$8,Details!$C$4:$C$8,Summary!H$4) -> 0 | I11: =SUMIFS(Details!$AC$4:$AC$8,Details!$C$4:$C$8,Summary!I$4) -> 0 | J11: =SUMIFS(Details!$AC$4:$AC$8,Details!$C$4:$C$8,Summary!J$4) -> 0 | K11: =SUMIFS(Details!$AC$4:$AC$8,Details!$C$4:$C$8,Summary!K$4) -> 0 | ... O11: =SUMIFS(Details!$AC$4:$AC$8,Details!$C$4:$C$8,Summary!O$4) -> 0 | P11: =SUM(D11:O11) -> 0
C12: Net Margin | D12: =D6-D7-D10-D11 -> 36658.837 | E12: =E6-E7-E10-E11 -> 0 | F12: =F6-F7-F10-F11 -> 0 | G12: =G6-G7-G10-G11 -> 0 | H12: =H6-H7-H10-H11 -> 0 | I12: =I6-I7-I10-I11 -> 0 | J12: =J6-J7-J10-J11 -> 0 | K12: =K6-K7-K10-K11 -> 0 | ... O12: =O6-O7-O10-O11 -> 0 | P12: =SUM(D12:O12) -> 36658.837
C13: Net Margin (%) | D13: =IFERROR((D12/D6),0) -> 0.016914704 | E13: =IFERROR((E12/E6),0) -> 0 | F13: =IFERROR((F12/F6),0) -> 0 | G13: =IFERROR((G12/G6),0) -> 0 | H13: =IFERROR((H12/H6),0) -> 0 | I13: =IFERROR((I12/I6),0) -> 0 | J13: =IFERROR((J12/J6),0) -> 0 | K13: =IFERROR((K12/K6),0) -> 0 | ... P13: =IFERROR((P12/P6),0) -> 0.016914704
C14: Other Income | D14: =SUMIFS(Details!$BL$13:$BL$17,Details!$C$13:$C$17,Summary!D$4) -> 1363676 | E14: =SUMIFS(Details!$BL$13:$BL$17,Details!$C$13:$C$17,Summary!E$4) -> 0 | F14: =SUMIFS(Details!$BL$13:$BL$17,Details!$C$13:$C$17,Summary!F$4) -> 0 | G14: =SUMIFS(Details!$BL$13:$BL$17,Details!$C$13:$C$17,Summary!G$4) -> 0 | H14: =SUMIFS(Details!$BL$13:$BL$17,Details!$C$13:$C$17,Summary!H$4) -> 0 | I14: =SUMIFS(Details!$BL$13:$BL$17,Details!$C$13:$C$17,Summary!I$4) -> 0 | J14: =SUMIFS(Details!$BL$13:$BL$17,Details!$C$13:$C$17,Summary!J$4) -> 0 | K14: =SUMIFS(Details!$BL$13:$BL$17,Details!$C$13:$C$17,Summary!K$4) -> 0 | ... O14: =SUMIFS(Details!$BL$13:$BL$17,Details!$C$13:$C$17,Summary!O$4) -> 0 | P14: =SUM(D14:O14) -> 1363676
C15: Transport Charges (%) | D15: =IFERROR((D10/D6),0) -> 0 | E15: =IFERROR((E10/E6),0) -> 0 | F15: =IFERROR((F10/F6),0) -> 0 | G15: =IFERROR((G10/G6),0) -> 0 | H15: =IFERROR((H10/H6),0) -> 0 | I15: =IFERROR((I10/I6),0) -> 0 | J15: =IFERROR((J10/J6),0) -> 0 | K15: =IFERROR((K10/K6),0) -> 0 | ... P15: =IFERROR((P10/P6),0) -> 0
C16: Revenue Per Kg | D16: =IFERROR(D6/(D5*1000),0) -> 59.786933 | E16: =IFERROR(E6/(E5*1000),0) -> 0 | F16: =IFERROR(F6/(F5*1000),0) -> 0 | G16: =IFERROR(G6/(G5*1000),0) -> 0 | H16: =IFERROR(H6/(H5*1000),0) -> 0 | I16: =IFERROR(I6/(I5*1000),0) -> 0 | J16: =IFERROR(J6/(J5*1000),0) -> 0 | K16: =IFERROR(K6/(K5*1000),0) -> 0 | ... O16: =IFERROR(O6/(O5*1000),0) -> 0 | P16: =+P6/(P5*1000) -> 59.786933
C17: Purchase Cost Per Kg | D17: =IFERROR(D7/(D5*1000),0) -> 58.775654 | E17: =IFERROR(E7/(E5*1000),0) -> 0 | F17: =IFERROR(F7/(F5*1000),0) -> 0 | G17: =IFERROR(G7/(G5*1000),0) -> 0 | H17: =IFERROR(H7/(H5*1000),0) -> 0 | I17: =IFERROR(I7/(I5*1000),0) -> 0 | J17: =IFERROR(J7/(J5*1000),0) -> 0 | K17: =IFERROR(K7/(K5*1000),0) -> 0 | ... O17: =IFERROR(O7/(O5*1000),0) -> 0 | P17: =+P7/(P5*1000) -> 58.775654
C18: Transportation Charges Per Kg | D18: =D10/(D5*1000) -> 0 | E18: =E10/(E5*1000) -> #DIV/0! | F18: =F10/(F5*1000) -> #DIV/0! | G18: =G10/(G5*1000) -> #DIV/0! | H18: =H10/(H5*1000) -> #DIV/0! | I18: =I10/(I5*1000) -> #DIV/0! | J18: =J10/(J5*1000) -> #DIV/0! | K18: =K10/(K5*1000) -> #DIV/0! | ... P18: =P10/(P5*1000) -> 0
C19: No. of Transactions | D19: {=IFERROR(ROWS(_xlfn.UNIQUE(_xlfn._xlws.FILTER(Details!$AO$5:$AO$8, (Details!$C$5:$C$8)=Summary!D$2))),0)} -> 3 | E19: {=IFERROR(ROWS(_xlfn.UNIQUE(_xlfn._xlws.FILTER(Details!$AO$5:$AO$8, (Details!$C$5:$C$8)=Summary!E$2))),0)} -> 0 | F19: {=IFERROR(ROWS(_xlfn.UNIQUE(_xlfn._xlws.FILTER(Details!$AO$5:$AO$8, (Details!$C$5:$C$8)=Summary!F$2))),0)} -> 0 | G19: {=IFERROR(ROWS(_xlfn.UNIQUE(_xlfn._xlws.FILTER(Details!$AO$5:$AO$8, (Details!$C$5:$C$8)=Summary!G$2))),0)} -> 0 | H19: {=IFERROR(ROWS(_xlfn.UNIQUE(_xlfn._xlws.FILTER(Details!$AO$5:$AO$8, (Details!$C$5:$C$8)=Summary!H$2))),0)} -> 0 | I19: {=IFERROR(ROWS(_xlfn.UNIQUE(_xlfn._xlws.FILTER(Details!$AO$5:$AO$8, (Details!$C$5:$C$8)=Summary!I$2))),0)} -> 0 | J19: {=IFERROR(ROWS(_xlfn.UNIQUE(_xlfn._xlws.FILTER(Details!$AO$5:$AO$8, (Details!$C$5:$C$8)=Summary!J$2))),0)} -> 0 | K19: {=IFERROR(ROWS(_xlfn.UNIQUE(_xlfn._xlws.FILTER(Details!$AO$5:$AO$8, (Details!$C$5:$C$8)=Summary!K$2))),0)} -> 0 | ... O19: {=IFERROR(ROWS(_xlfn.UNIQUE(_xlfn._xlws.FILTER(Details!$AO$5:$AO$8, (Details!$C$5:$C$8)=Summary!O$2))),0)} -> 0 | P19: =SUM(D19:O19) -> 3
C20: No. of Sellers (Aggregators) | D20: {=IFERROR(ROWS(_xlfn.UNIQUE(_xlfn._xlws.FILTER(MID(Details!$G$5:$G$8,3,10), (Details!$C$5:$C$8)=Summary!D$2))),0)-1} -> 2 | E20: {=IFERROR(ROWS(_xlfn.UNIQUE(_xlfn._xlws.FILTER(MID(Details!$G$5:$G$8,3,10), (Details!$C$5:$C$8)=Summary!E$2))),0)} -> 0 | F20: {=IFERROR(ROWS(_xlfn.UNIQUE(_xlfn._xlws.FILTER(MID(Details!$G$5:$G$8,3,10), (Details!$C$5:$C$8)=Summary!F$2))),0)} -> 0 | G20: {=IFERROR(ROWS(_xlfn.UNIQUE(_xlfn._xlws.FILTER(MID(Details!$G$5:$G$8,3,10), (Details!$C$5:$C$8)=Summary!G$2))),0)} -> 0 | H20: {=IFERROR(ROWS(_xlfn.UNIQUE(_xlfn._xlws.FILTER(MID(Details!$G$5:$G$8,3,10), (Details!$C$5:$C$8)=Summary!H$2))),0)} -> 0 | I20: {=IFERROR(ROWS(_xlfn.UNIQUE(_xlfn._xlws.FILTER(MID(Details!$G$5:$G$8,3,10), (Details!$C$5:$C$8)=Summary!I$2))),0)} -> 0 | J20: {=IFERROR(ROWS(_xlfn.UNIQUE(_xlfn._xlws.FILTER(MID(Details!$G$5:$G$8,3,10), (Details!$C$5:$C$8)=Summary!J$2))),0)} -> 0 | K20: {=IFERROR(ROWS(_xlfn.UNIQUE(_xlfn._xlws.FILTER(MID(Details!$G$5:$G$8,3,10), (Details!$C$5:$C$8)=Summary!K$2))),0)} -> 0 | L20: {=IFERROR(ROWS(_xlfn.UNIQUE(_xlfn._xlws.FILTER(MID(Details!$G$5:$G$8,3,10), (Details!$C$5:$C$8)=Summary!L$2))),0)} -> 0 | ... O20: {=IFERROR(ROWS(_xlfn.UNIQUE(_xlfn._xlws.FILTER(MID(Details!$G$5:$G$8,3,10), (Details!$C$5:$C$8)=Summary!O$2))),0)} -> 0 | P20: ='Supplier Metrics'!E2-1 -> 2
C21: No. of Buyers (Recyclers) | D21: {=IFERROR(ROWS(_xlfn.UNIQUE(_xlfn._xlws.FILTER(MID(Details!$AR$5:$AR$8,3,10), (Details!$C$5:$C$8)=Summary!D$2))),0)-1} -> 2 | E21: {=IFERROR(ROWS(_xlfn.UNIQUE(_xlfn._xlws.FILTER(MID(Details!$AR$5:$AR$8,3,10), (Details!$C$5:$C$8)=Summary!E$2))),0)} -> 0 | F21: {=IFERROR(ROWS(_xlfn.UNIQUE(_xlfn._xlws.FILTER(MID(Details!$AR$5:$AR$8,3,10), (Details!$C$5:$C$8)=Summary!F$2))),0)} -> 0 | G21: {=IFERROR(ROWS(_xlfn.UNIQUE(_xlfn._xlws.FILTER(MID(Details!$AR$5:$AR$8,3,10), (Details!$C$5:$C$8)=Summary!G$2))),0)} -> 0 | H21: {=IFERROR(ROWS(_xlfn.UNIQUE(_xlfn._xlws.FILTER(MID(Details!$AR$5:$AR$8,3,10), (Details!$C$5:$C$8)=Summary!H$2))),0)} -> 0 | I21: {=IFERROR(ROWS(_xlfn.UNIQUE(_xlfn._xlws.FILTER(MID(Details!$AR$5:$AR$8,3,10), (Details!$C$5:$C$8)=Summary!I$2))),0)} -> 0 | J21: {=IFERROR(ROWS(_xlfn.UNIQUE(_xlfn._xlws.FILTER(MID(Details!$AR$5:$AR$8,3,10), (Details!$C$5:$C$8)=Summary!J$2))),0)} -> 0 | K21: {=IFERROR(ROWS(_xlfn.UNIQUE(_xlfn._xlws.FILTER(MID(Details!$AR$5:$AR$8,3,10), (Details!$C$5:$C$8)=Summary!K$2))),0)} -> 0 | L21: {=IFERROR(ROWS(_xlfn.UNIQUE(_xlfn._xlws.FILTER(MID(Details!$AR$5:$AR$8,3,10), (Details!$C$5:$C$8)=Summary!L$2))),0)} -> 0 | ... O21: {=IFERROR(ROWS(_xlfn.UNIQUE(_xlfn._xlws.FILTER(MID(Details!$AR$5:$AR$8,3,10), (Details!$C$5:$C$8)=Summary!O$2))),0)} -> 0 | P21: ='Buyer Metrics'!B3-1 -> 2
C22: Full Rejection | D22: {=IFERROR(ROWS(_xlfn.UNIQUE(_xlfn._xlws.FILTER(Details!$E$5:$E$8,(Details!$C$5:$C$8=Summary!D$2)*(Details!$BO$5:$BO$8=Summary!$C$22)))),0)} -> 0 | E22: {=IFERROR(ROWS(_xlfn.UNIQUE(_xlfn._xlws.FILTER(Details!$E$5:$E$8,(Details!$C$5:$C$8=Summary!E$2)*(Details!$BO$5:$BO$8=Summary!$C$22)))),0)} -> 0 | F22: {=IFERROR(ROWS(_xlfn.UNIQUE(_xlfn._xlws.FILTER(Details!$E$5:$E$8,(Details!$C$5:$C$8=Summary!F$2)*(Details!$BO$5:$BO$8=Summary!$C$22)))),0)} -> 0 | G22: {=IFERROR(ROWS(_xlfn.UNIQUE(_xlfn._xlws.FILTER(Details!$E$5:$E$8,(Details!$C$5:$C$8=Summary!G$2)*(Details!$BO$5:$BO$8=Summary!$C$22)))),0)} -> 0 | H22: {=IFERROR(ROWS(_xlfn.UNIQUE(_xlfn._xlws.FILTER(Details!$E$5:$E$8,(Details!$C$5:$C$8=Summary!H$2)*(Details!$BO$5:$BO$8=Summary!$C$22)))),0)} -> 0 | I22: {=IFERROR(ROWS(_xlfn.UNIQUE(_xlfn._xlws.FILTER(Details!$E$5:$E$8,(Details!$C$5:$C$8=Summary!I$2)*(Details!$BO$5:$BO$8=Summary!$C$22)))),0)} -> 0 | J22: {=IFERROR(ROWS(_xlfn.UNIQUE(_xlfn._xlws.FILTER(Details!$E$5:$E$8,(Details!$C$5:$C$8=Summary!J$2)*(Details!$BO$5:$BO$8=Summary!$C$22)))),0)} -> 0 | K22: {=IFERROR(ROWS(_xlfn.UNIQUE(_xlfn._xlws.FILTER(Details!$E$5:$E$8,(Details!$C$5:$C$8=Summary!K$2)*(Details!$BO$5:$BO$8=Summary!$C$22)))),0)} -> 0 | ... O22: {=IFERROR(ROWS(_xlfn.UNIQUE(_xlfn._xlws.FILTER(Details!$E$5:$E$8,(Details!$C$5:$C$8=Summary!O$2)*(Details!$BO$5:$BO$8=Summary!$C$22)))),0)} -> 0 | P22: =SUM(D22:O22) -> 0
C23: Receivable | D23: 72181241 | E23: 60130029 | F23: 54302522 | G23: 0 | H23: 0 | I23: 0 | J23: 0 | K23: 0 | L23: 0 | M23: 0 | N23: 0 | O23: 0 | P23: =F23 -> 54302522
C24: DSO (Days) | D24: =IFERROR(((D23/(D6*1.18))*D3),0) -> 846.7385 | E24: =IFERROR(((E23/(E6*1.18))*E3),0) -> 0 | F24: =IFERROR(((F23/(F6*1.18))*F3),0) -> 0 | G24: =IFERROR(((G23/(G6*1.18))*G3),0) -> 0 | H24: =IFERROR(((H23/(H6*1.18))*H3),0) -> 0 | I24: =IFERROR(((I23/(I6*1.18))*I3),0) -> 0 | J24: =IFERROR(((J23/(J6*1.18))*J3),0) -> 0 | K24: =IFERROR(((K23/(K6*1.18))*K3),0) -> 0 | ... O24: =IFERROR(((O23/(O6*1.18))*O3),0) -> 0 | P24: =IFERROR(((P23)/(P6*1.18)*P3),0) -> 1741.1555
C25: Payable | D25: 23789534 | E25: 21485726 | F25: 19968208 | G25: 0 | H25: 0 | I25: 0 | J25: 0 | K25: 0 | L25: 0 | M25: 0 | N25: 0 | O25: 0 | P25: =F25 -> 19968208
C26: DPO (Days) | D26: =IFERROR(((D25/(D7*1.18))*D3),0) -> 283.87013 | E26: =IFERROR(((E25/(E7*1.18))*E3),0) -> 0 | F26: =IFERROR(((F25/(F7*1.18))*F3),0) -> 0 | G26: =IFERROR(((G25/(G7*1.18))*G3),0) -> 0 | H26: =IFERROR(((H25/(H7*1.18))*H3),0) -> 0 | I26: =IFERROR(((I25/(I7*1.18))*I3),0) -> 0 | J26: =IFERROR(((J25/(J7*1.18))*J3),0) -> 0 | K26: =IFERROR(((K25/(K7*1.18))*K3),0) -> 0 | ... P26: =IFERROR(((P25/(P7*1.18))*P3),0) -> 651.27658
C27: Working Capital Days | D27: =D24-D26 -> 562.86837 | E27: =E24-E26 -> 0 | F27: =F24-F26 -> 0 | G27: =G24-G26 -> 0 | H27: =H24-H26 -> 0 | I27: =I24-I26 -> 0 | J27: =J24-J26 -> 0 | K27: =K24-K26 -> 0 | ... P27: =P24-P26 -> 1089.8789
C28: Credit Notes (Value - Incl. Prov) | D28: 55571.188 | E28: =-SUMIFS(Details!$BT$4:$BT$8,Details!$C$4:$C$8,Summary!E4) -> 0 | F28: =-SUMIFS(Details!$BT$4:$BT$8,Details!$C$4:$C$8,Summary!F4) -> 0 | G28: =-SUMIFS(Details!$BT$4:$BT$8,Details!$C$4:$C$8,Summary!G4) -> 0 | H28: =-SUMIFS(Details!$BT$4:$BT$8,Details!$C$4:$C$8,Summary!H4) -> 0 | I28: =-SUMIFS(Details!$BT$4:$BT$8,Details!$C$4:$C$8,Summary!I4) -> 0 | J28: =-SUMIFS(Details!$BT$4:$BT$8,Details!$C$4:$C$8,Summary!J4) -> 0 | K28: =-SUMIFS(Details!$BT$4:$BT$8,Details!$C$4:$C$8,Summary!K4) -> 0 | L28: =-SUMIFS(Details!$BT$4:$BT$8,Details!$C$4:$C$8,Summary!L4) -> 0 | ... O28: =-SUMIFS(Details!$BT$4:$BT$8,Details!$C$4:$C$8,Summary!O4) -> 0 | P28: =SUM(D28:O28) -> 55571.188 | Q28: =(-Details!BJ9-Details!BK9) -> 37812.5 | R28: =P28-Q28 -> 17758.688
C29: Credit Notes (% to Revenue) | D29: =IFERROR((D28/D6),0) -> 0.025641026 | E29: =IFERROR((E28/E6),0) -> 0 | F29: =IFERROR((F28/F6),0) -> 0 | G29: =IFERROR((G28/G6),0) -> 0 | H29: =IFERROR((H28/H6),0) -> 0 | I29: =IFERROR((I28/I6),0) -> 0 | J29: =IFERROR((J28/J6),0) -> 0 | K29: =IFERROR((K28/K6),0) -> 0 | ... O29: =IFERROR((O28/O6),0) -> 0 | P29: =+P28/P6 -> 0.025641026
C30: Debit Notes (Value - Incl. Prov) | D30: 50677.025 | E30: =-SUMIFS(Details!$BU$4:$BU$8,Details!$C$4:$C$8,Summary!E4) -> 0 | F30: =-SUMIFS(Details!$BU$4:$BU$8,Details!$C$4:$C$8,Summary!F4) -> 0 | G30: =-SUMIFS(Details!$BU$4:$BU$8,Details!$C$4:$C$8,Summary!G4) -> 0 | H30: =-SUMIFS(Details!$BU$4:$BU$8,Details!$C$4:$C$8,Summary!H4) -> 0 | I30: =-SUMIFS(Details!$BU$4:$BU$8,Details!$C$4:$C$8,Summary!I4) -> 0 | J30: =-SUMIFS(Details!$BU$4:$BU$8,Details!$C$4:$C$8,Summary!J4) -> 0 | K30: =-SUMIFS(Details!$BU$4:$BU$8,Details!$C$4:$C$8,Summary!K4) -> 0 | L30: =-SUMIFS(Details!$BU$4:$BU$8,Details!$C$4:$C$8,Summary!L4) -> 0 | ... O30: =-SUMIFS(Details!$BU$4:$BU$8,Details!$C$4:$C$8,Summary!O4) -> 0 | P30: =SUM(D30:O30) -> 50677.025 | Q30: =(-Details!AK9-Details!AL9) -> 33433.475 | R30: =P30-Q30 -> 17243.55
C31: Debit Notes (% to Purchase) | D31: =IFERROR((D30/D7),0) -> 0.023785135 | E31: =IFERROR((E30/E7),0) -> 0 | F31: =IFERROR((F30/F7),0) -> 0 | G31: =IFERROR((G30/G7),0) -> 0 | H31: =IFERROR((H30/H7),0) -> 0 | I31: =IFERROR((I30/I7),0) -> 0 | J31: =IFERROR((J30/J7),0) -> 0 | K31: =IFERROR((K30/K7),0) -> 0 | ... O31: =IFERROR((O30/O7),0) -> 0 | P31: =(P30/(P7+P10)) -> 0.023785135
C33: KPI's without Provisions | D33: =D4 -> 46113 | E33: =E4 -> 46143 | F33: =F4 -> 46174 | G33: =G4 -> 46204 | H33: =H4 -> 46235 | I33: =I4 -> 46266 | J33: =J4 -> 46296 | K33: =K4 -> 46327 | ... P33: =P4 -> FY 2026-27
C34: Sales without Provision | D34: =D6+D53 -> 2205088.8 | E34: =E6+E53 -> 0 | F34: =F6+F53 -> 0 | G34: =G6+G53 -> 0 | H34: =H6+H53 -> 0 | I34: =I6+I53 -> 0 | J34: =J6+J53 -> 0 | K34: =K6+K53 -> 0 | ... O34: =O6+O53 -> 0 | P34: =SUM(D34:O34) -> 2205088.8
C35: Purchases without Provision | D35: =D7+D10+D52 -> 2153085.1 | E35: =E7+E10+E52 -> 0 | F35: =F7+F10+F52 -> 0 | G35: =G7+G10+G52 -> 0 | H35: =H7+H10+H52 -> 0 | I35: =I7+I10+I52 -> 0 | J35: =J7+J10+J52 -> 0 | K35: =K7+K10+K52 -> 0 | ... O35: =O7+O10+O52 -> 0 | P35: =SUM(D35:O35) -> 2153085.1
C36: Contribution without Provision | D36: =D34-D35 -> 52003.712 | E36: =E34-E35 -> 0 | F36: =F34-F35 -> 0 | G36: =G34-G35 -> 0 | H36: =H34-H35 -> 0 | I36: =I34-I35 -> 0 | J36: =J34-J35 -> 0 | K36: =K34-K35 -> 0 | ... P36: =P34-P35 -> 52003.712
C37: Contribution (%) | D37: =D36/D34 -> 0.0235835 | E37: =E36/E34 -> #DIV/0! | F37: =F36/F34 -> #DIV/0! | G37: =G36/G34 -> #DIV/0! | H37: =H36/H34 -> #DIV/0! | I37: =I36/I34 -> #DIV/0! | J37: =J36/J34 -> #DIV/0! | K37: =K36/K34 -> #DIV/0! | ... P37: =P36/P34 -> 0.0235835
C39: Business Trends | D39: =D4 -> 46113 | E39: =E4 -> 46143 | F39: =F4 -> 46174 | G39: =G4 -> 46204 | H39: =H4 -> 46235 | I39: =I4 -> 46266 | J39: =J4 -> 46296 | K39: =K4 -> 46327 | ... P39: =P4 -> FY 2026-27
C40: Sales-Revenue (MoM) | D40: =IFERROR(((D6/C6)-1),0) -> 0 | E40: =IFERROR(((E6/D6)-1),0) -> -1 | F40: =IFERROR(((F6/E6)-1),0) -> 0 | G40: =IFERROR(((G6/F6)-1),0) -> 0 | H40: =IFERROR(((H6/G6)-1),0) -> 0 | I40: =IFERROR(((I6/H6)-1),0) -> 0 | J40: =IFERROR(((J6/I6)-1),0) -> 0 | K40: =IFERROR(((K6/J6)-1),0) -> 0 | ... O40: =IFERROR(((O6/N6)-1),0) -> 0 | P40: 0
C41: Sales-Volume (MoM) | D41: =IFERROR(((D5/C5)-1),0) -> 0 | E41: =IFERROR(((E5/D5)-1),0) -> -1 | F41: =IFERROR(((F5/E5)-1),0) -> 0 | G41: =IFERROR(((G5/F5)-1),0) -> 0 | H41: =IFERROR(((H5/G5)-1),0) -> 0 | I41: =IFERROR(((I5/H5)-1),0) -> 0 | J41: =IFERROR(((J5/I5)-1),0) -> 0 | K41: =IFERROR(((K5/J5)-1),0) -> 0 | ... O41: =IFERROR(((O5/N5)-1),0) -> 0 | P41: 0
C42: Sales-Transactions (MoM) | D42: =IFERROR(((D19/C19)-1),0) -> 0 | E42: =IFERROR(((E19/D19)-1),0) -> -1 | F42: =IFERROR(((F19/E19)-1),0) -> 0 | G42: =IFERROR(((G19/F19)-1),0) -> 0 | H42: =IFERROR(((#REF!/G19)-1),0) -> 0 | I42: =IFERROR(((I19/#REF!)-1),0) -> 0 | J42: =IFERROR(((J19/I19)-1),0) -> 0 | K42: =IFERROR(((K19/J19)-1),0) -> 0 | L42: =IFERROR(((L19/K19)-1),0) -> 0 | M42: =IFERROR(((M19/L19)-1),0) -> 0 | N42: =IFERROR(((N19/M19)-1),0) -> 0 | O42: =IFERROR(((O19/N19)-1),0) -> 0 | P42: 0
C44: Loss Making Transactions | D44: =D39 -> 46113 | E44: =E39 -> 46143 | F44: =F39 -> 46174 | G44: =G39 -> 46204 | H44: =H39 -> 46235 | I44: =I39 -> 46266 | J44: =J39 -> 46296 | K44: =K39 -> 46327 | ... P44: =P39 -> FY 2026-27
C45: No of LMI | D45: 0 | E45: 0 | F45: 0 | G45: 0 | H45: 0 | I45: 0 | J45: 0 | K45: 0 | L45: 0 | M45: 0 | N45: 0 | O45: 0 | P45: =SUM(D45:O45) -> 0
C46: Value of LMI | D46: 0 | E46: 0 | F46: 0 | G46: 0 | H46: 0 | I46: 0 | J46: 0 | K46: 0 | L46: 0 | M46: 0 | N46: 0 | O46: 0 | P46: =SUM(D46:O46) -> 0
C47: No of loss Making Transactions | D47: 0 | E47: 0 | F47: 0 | G47: 0 | H47: 0 | I47: 0 | J47: 0 | K47: 0 | L47: 0 | M47: 0 | N47: 0 | O47: 0 | P47: =SUM(D47:O47) -> 0
C48: % of Loss Making Transactions | D48: =IFERROR(D47/D19,0) -> 0 | E48: =IFERROR(E47/E19,0) -> 0 | F48: =IFERROR(F47/F19,0) -> 0 | G48: =IFERROR(G47/G19,0) -> 0 | H48: =IFERROR(H47/#REF!,0) -> 0 | I48: =IFERROR(I47/I19,0) -> 0 | J48: =IFERROR(J47/J19,0) -> 0 | K48: =IFERROR(K47/K19,0) -> 0 | L48: =IFERROR(L47/L19,0) -> 0 | M48: =IFERROR(M47/M19,0) -> 0 | N48: =IFERROR(N47/N19,0) -> 0 | O48: =IFERROR(O47/O19,0) -> 0 | P48: =IFERROR(P47/P19,0) -> 0
C49: Value Of Making Transactions | D49: 0 | E49: 0 | F49: 0 | G49: 0 | H49: 0 | I49: 0 | J49: 0 | K49: 0 | L49: 0 | M49: 0 | N49: 0 | O49: 0 | P49: =SUM(D49:O49) -> 0
C51: CN & DN Provisions | D51: =D44 -> 46113 | E51: =E44 -> 46143 | F51: =F44 -> 46174 | G51: =G44 -> 46204 | H51: =H44 -> 46235 | I51: =I44 -> 46266 | J51: =J44 -> 46296 | K51: =K44 -> 46327 | ... P51: =P44 -> FY 2026-27 | Q51: =ROUND(Q52-Q53,2)-ROUND(P36-P12,2) -> 0
C52: DN Provision | D52: =-SUMIFS(Details!$AL$4:$AL$8,Details!$C$4:$C$8,Summary!D51) -> 22467.625 | E52: =-SUMIFS(Details!$AL$4:$AL$8,Details!$C$4:$C$8,Summary!E51) -> 0 | F52: =-SUMIFS(Details!$AL$4:$AL$8,Details!$C$4:$C$8,Summary!F51) -> 0 | G52: =-SUMIFS(Details!$AL$4:$AL$8,Details!$C$4:$C$8,Summary!G51) -> 0 | H52: =-SUMIFS(Details!$AL$4:$AL$8,Details!$C$4:$C$8,Summary!H51) -> 0 | I52: =-SUMIFS(Details!$AL$4:$AL$8,Details!$C$4:$C$8,Summary!I51) -> 0 | J52: =-SUMIFS(Details!$AL$4:$AL$8,Details!$C$4:$C$8,Summary!J51) -> 0 | K52: =-SUMIFS(Details!$AL$4:$AL$8,Details!$C$4:$C$8,Summary!K51) -> 0 | ... O52: =-SUMIFS(Details!$AL$4:$AL$8,Details!$C$4:$C$8,Summary!O51) -> 0 | P52: =SUM(D52:O52) -> 22467.625 | Q52: =Details!AL9 -> -22467.625 | R52: =Q52+P52 -> 0
C53: CN Provision | D53: =-SUMIFS(Details!$BK$4:$BK$8,Details!$C$4:$C$8,Summary!D51) -> 37812.5 | E53: =-SUMIFS(Details!$BK$4:$BK$8,Details!$C$4:$C$8,Summary!E51) -> 0 | F53: =-SUMIFS(Details!$BK$4:$BK$8,Details!$C$4:$C$8,Summary!F51) -> 0 | G53: =-SUMIFS(Details!$BK$4:$BK$8,Details!$C$4:$C$8,Summary!G51) -> 0 | H53: =-SUMIFS(Details!$BK$4:$BK$8,Details!$C$4:$C$8,Summary!H51) -> 0 | I53: =-SUMIFS(Details!$BK$4:$BK$8,Details!$C$4:$C$8,Summary!I51) -> 0 | J53: =-SUMIFS(Details!$BK$4:$BK$8,Details!$C$4:$C$8,Summary!J51) -> 0 | K53: =-SUMIFS(Details!$BK$4:$BK$8,Details!$C$4:$C$8,Summary!K51) -> 0 | ... O53: =-SUMIFS(Details!$BK$4:$BK$8,Details!$C$4:$C$8,Summary!O51) -> 0 | P53: =SUM(D53:O53) -> 37812.5 | Q53: =Details!BK9 -> -37812.5 | R53: =Q53+P53 -> 0
C55: Qty Returned | D55: =D51 -> 46113 | E55: =E51 -> 46143 | F55: =F51 -> 46174 | G55: =G51 -> 46204 | H55: =H51 -> 46235 | I55: =I51 -> 46266 | J55: =J51 -> 46296 | K55: =K51 -> 46327 | ... P55: =P51 -> FY 2026-27
D56: =SUMIFS(Details!$R$5:$R$8,Details!$C$5:$C$8,Summary!D55)/1000 -> 0 | E56: =SUMIFS(Details!$R$5:$R$8,Details!$C$5:$C$8,Summary!E55)/1000 -> 0 | F56: =SUMIFS(Details!$R$5:$R$8,Details!$C$5:$C$8,Summary!F55)/1000 -> 0 | G56: =SUMIFS(Details!$R$5:$R$8,Details!$C$5:$C$8,Summary!G55)/1000 -> 0 | H56: =SUMIFS(Details!$R$5:$R$8,Details!$C$5:$C$8,Summary!H55)/1000 -> 0 | I56: =SUMIFS(Details!$R$5:$R$8,Details!$C$5:$C$8,Summary!I55)/1000 -> 0 | J56: =SUMIFS(Details!$R$5:$R$8,Details!$C$5:$C$8,Summary!J55)/1000 -> 0 | K56: =SUMIFS(Details!$R$5:$R$8,Details!$C$5:$C$8,Summary!K55)/1000 -> 0 | ... O56: =SUMIFS(Details!$R$5:$R$8,Details!$C$5:$C$8,Summary!O55)/1000 -> 0 | P56: =SUM(D56:O56) -> 0
C58: Margins | D58: 45748 | E58: 45778 | F58: 45809 | G58: 45839 | H58: 45870 | I58: 45901 | J58: 45931 | K58: 45962 | L58: 45992 | M58: 46023 | N58: 46054 | O58: 46082 | P58: FY 2025-26
C59: Gross Margin | D59: =SUMIFS(Details!$CI$5:$CI$8,Details!$C$5:$C$8,Summary!D$58) -> 0 | E59: =SUMIFS(Details!$CI$5:$CI$8,Details!$C$5:$C$8,Summary!E$58) -> 0 | F59: =SUMIFS(Details!$CI$5:$CI$8,Details!$C$5:$C$8,Summary!F$58) -> 0 | G59: =SUMIFS(Details!$CI$5:$CI$8,Details!$C$5:$C$8,Summary!G$58) -> 0 | H59: =SUMIFS(Details!$CI$5:$CI$8,Details!$C$5:$C$8,Summary!H$58) -> 0 | I59: =SUMIFS(Details!$CI$5:$CI$8,Details!$C$5:$C$8,Summary!I$58) -> 0 | J59: =SUMIFS(Details!$CI$5:$CI$8,Details!$C$5:$C$8,Summary!J$58) -> 0 | K59: =SUMIFS(Details!$CI$5:$CI$8,Details!$C$5:$C$8,Summary!K$58) -> 0 | ... O59: =SUMIFS(Details!$CI$5:$CI$8,Details!$C$5:$C$8,Summary!O$58) -> 0 | P59: =SUM(D59:O59) -> 0
C60: Recykal Margin | D60: =SUMIFS(Details!$CJ$5:$CJ$8,Details!$C$5:$C$8,Summary!D$58) -> 0 | E60: =SUMIFS(Details!$CJ$5:$CJ$8,Details!$C$5:$C$8,Summary!E$58) -> 0 | F60: =SUMIFS(Details!$CJ$5:$CJ$8,Details!$C$5:$C$8,Summary!F$58) -> 0 | G60: =SUMIFS(Details!$CJ$5:$CJ$8,Details!$C$5:$C$8,Summary!G$58) -> 0 | H60: =SUMIFS(Details!$CJ$5:$CJ$8,Details!$C$5:$C$8,Summary!H$58) -> 0 | I60: =SUMIFS(Details!$CJ$5:$CJ$8,Details!$C$5:$C$8,Summary!I$58) -> 0 | J60: =SUMIFS(Details!$CJ$5:$CJ$8,Details!$C$5:$C$8,Summary!J$58) -> 0 | K60: =SUMIFS(Details!$CJ$5:$CJ$8,Details!$C$5:$C$8,Summary!K$58) -> 0 | ... O60: =SUMIFS(Details!$CJ$5:$CJ$8,Details!$C$5:$C$8,Summary!O$58) -> 0 | P60: =SUM(D60:O60) -> 0
C61: Net Margin | D61: =SUMIFS(Details!$CK$5:$CK$8,Details!$C$5:$C$8,Summary!D$58) -> 0 | E61: =SUMIFS(Details!$CK$5:$CK$8,Details!$C$5:$C$8,Summary!E$58) -> 0 | F61: =SUMIFS(Details!$CK$5:$CK$8,Details!$C$5:$C$8,Summary!F$58) -> 0 | G61: =SUMIFS(Details!$CK$5:$CK$8,Details!$C$5:$C$8,Summary!G$58) -> 0 | H61: =SUMIFS(Details!$CK$5:$CK$8,Details!$C$5:$C$8,Summary!H$58) -> 0 | I61: =SUMIFS(Details!$CK$5:$CK$8,Details!$C$5:$C$8,Summary!I$58) -> 0 | J61: =SUMIFS(Details!$CK$5:$CK$8,Details!$C$5:$C$8,Summary!J$58) -> 0 | K61: =SUMIFS(Details!$CK$5:$CK$8,Details!$C$5:$C$8,Summary!K$58) -> 0 | ... O61: =SUMIFS(Details!$CK$5:$CK$8,Details!$C$5:$C$8,Summary!O$58) -> 0 | P61: =SUM(D61:O61) -> 0
C63: Financial with GST | D63: Sales | E63: Purchases
C64: =Details!P22 -> 46194 | D64: =SUMIFS(Details!$BL$5:$BL$8,Details!$D$5:$D$8,Summary!C64)*118% -> 0 | E64: =SUMIFS(Details!$AM$5:$AM$8,Details!$D$5:$D$8,Summary!C64)*118% -> 0
C65: =TEXT(C64,"mmm-yy") -> Jun-26 | D65: =SUMIFS(Details!$BL$5:$BL$8,Details!$C$5:$C$8,Summary!C65)*118% -> 0 | E65: =SUMIFS(Details!$AM$5:$AM$8,Details!$C$5:$C$8,Summary!C65)*118% -> 0
C66: Fy 2025-26 | D66: =Details!BL9*118% -> 2578341.3 | E66: =Details!AM9*118% -> 2534476

Sheet Details
B3: Raw Data -Plastic | F3: Purchase Details | U3: Logistic Details of the transaction | AF3: Debit Notes to Suppliers | AM3: Sales Details | BD3: DN to Customer | BE3: Credit Notes from Customers | BJ3: -0.025 | BS3: CN & DN Checks | CB3: Without Provisions | CH3: Margin Buckets | CK3: Financials with GST
B4: Quarter | C4: Month | D4: Date | E4: Shipment ID | F4: Supplier Name | G4: GST Reg No. | H4: Vendor Invoice No. | I4: Vendor Invoice Date | J4: P V No. | K4: P V Date | L4: State (Origin) | M4: Vehicle No. | N4: Material | O4: Qty (Kg) | P4: Price/Kg | Q4: Purchase Price | R4: Return Qty | S4: Net Qty | T4: Basic Customs Duty | U4: Transporter Name | V4: LR NO/BILL NO | W4: J V No. | X4: JV Date | Y4: Logistics cost | Z4: Debit note on logistic cost | AA4: Logistics Provision | AB4: Total Logistics Cost | AC4: Operational Cost | AD4: Cost/Kg. | AE4: Divertion/Internal | AF4: Debit Note No. | AG4: Debit Note Date. | AH4: Debit Note No. 2 | AI4: Debit Note Date. 2 | AJ4: Full Debit Note | AK4: Actual Debit Note | AL4: Provision for DN | AM4: Total Cost | AN4: Inv. Date | AO4: Inv. No. | AP4: Customer ID | AQ4: Buyer Name | AR4: Buyer GST Number | AS4: Location (Origin) | AT4: Location (Destination) | AU4: State (Destination) | AV4: E-WayBill Number | AW4: Qty(Kg) | AX4: Rate/Kg | AY4: Amount | AZ4: Qty Check | BA4: Return Qty | BB4: Net Qty | BC4: Divertion/Internal | BD4: Return Type | BE4: Credit Note No:1 | BF4: CN Date. No:1 | BG4: Credit Note No:2 | BH4: CN Date. No:2 | BI4: Full Credit Notes | BJ4: Actual Credit Note | BK4: Provision for CN | BL4: Net Revenue | BM4: Margin | BN4: Reamrks - Margin | BO4: Remarks | BP4: LMI @ Inception | BQ4: Remarks @ Inception | BR4: Margin (%) | BS4: Margin Bucket | BT4: Total CN(Inc.Provisions) | BU4: Total DN(Inc.Provisions) | BV4: Check | BW4: Actaul CN | BX4: Actual DN | BY4: Check | BZ4: Material-Short Form | CA4: Supplier Type | CB4: Month | CC4: Cost | CD4: Revenue | CE4: Week No: | CF4: Category (Material) | CG4: Broad Category | CH4: POC Name | CI4: Gross Margin | CJ4: Recykal Margin | CK4: Net Margin | CL4: Sales | CM4: Purchases | CN4: Credit Note | CO4: Debit Note | CP4: Margin | CQ4: Bill Branch | CR4: Inv Branch | CS4: Vendor PAN No | CT4: Customer PAN No | CU4: GST TDS Applicability | CV4: Cash Discount(Provision) | CW4: Cash Discount | CX4: Cash Discount. No | CY4: CD Date
B5: ="Q" & IF(ROUNDUP(MONTH(D5)/3,0)-1=0,4,ROUNDUP(MONTH(D5)/3,0)-1) -> Q1 | C5: =TEXT(AN5,"mmm-yy") -> Apr-26 | D5: 46114 | E5: SH04260306 | F5: BHAGIRATHI POLYMER PRIVATE LIMITED | G5: 09AALCB0491L1ZA | H5: BPPL/26-27/1 | I5: 46114 | J5: 26-27/PUR/000001 | K5: 46115 | L5: UP | M5: UP15JT8380 | N5: PET - Hot Washed White Flakes, Grade 2 | O5: 10845 | P5: 63.6 | Q5: =O5*P5 -> 689742 | R5: 0 | S5: =O5-R5 -> 10845 | T5: 0 | U5: 0 | V5: 0 | W5: 0 | X5: 0 | Y5: 0 | Z5: 0 | AA5: 0 | AB5: =Y5+AA5+Z5 -> 0 | AC5: 0 | AD5: =IFERROR((Q5+AB5)/S5,0) -> 63.6 | AE5: 0 | AF5: 0 | AG5: 0 | AH5: 0 | AI5: 0 | AJ5: 0 | AK5: 0 | AL5: 0 | AM5: =Q5+AB5+AL5+AK5+AJ5+T5+AE5 -> 689742 | AN5: 46115 | AO5: 36/PET/27IN00002 | AP5: 832139000005565947 | AQ5: Silver Ecotex LLP | AR5: 09AEJFS8446P1ZY | AS5: Meerut,Uttar Pradesh,250002 | AT5: Shamali | AU5: Uttar Pradesh | AW5: 10845 | AX5: 65.5 | AY5: =AW5*AX5 -> 710347.5 | AZ5: =AW5=O5 -> TRUE | BA5: 0 | BB5: =AW5-BA5 -> 10845 | BC5: 0 | BD5: Regular | BE5: 0 | BF5: 0 | BG5: 0 | BH5: 0 | BI5: 0 | BJ5: 0 | BK5: 0 | BL5: =AY5+BI5+BJ5+BK5+BC5 -> 710347.5 | BM5: =BL5-AM5 -> 20605.5 | BN5: =IF(BM5>=0,"Positive Margin","Negative Margin") -> Positive Margin | BO5: NO DN | BP5: =AY5-Y5-Q5-AA5-T5+BC5 -> 20605.5 | BQ5: =IF(BP5<0, "Negative Margin at Inception", "Positive Margin at Inception") -> Positive Margin at Inception | BR5: =IFERROR(BM5/BL5,"0") -> 0.029007634 | BS5: =IF(BR5<1%,"Less Than 1%",IF(BR5>2%,"More than 2%",IF(BR5>=1%,"1% - 2%"))) -> More than 2% | BT5: =BJ5+BK5 -> 0 | BU5: =AL5+AK5 -> 0 | BV5: =BT5-BU5 -> 0 | BW5: =BJ5 -> 0 | BX5: =AK5 -> 0 | BY5: =BW5-BX5 -> 0 | BZ5: Marketplace (Plastic Waste) | CA5: 0 | CB5: =TEXT(AN5,"mmm-yy") -> Apr-26 | CC5: =AM5-AL5-AA5 -> 689742 | CD5: =BL5-BK5 -> 710347.5 | CE5: =INT((D5- IF(MONTH(D5) >= 4, DATE(YEAR(D5), 4, 1), DATE(YEAR(D5)-1, 4, 1))) / 7) + 1 -> 1 | CF5: Plastic | CG5: Plastic | CH5: =_xlfn.XLOOKUP(AR5,receivables!B:B,receivables!D:D) -> Neelesh Dixit | CI5: =AY5-Q5 -> 20605.5 | CJ5: =CI5-Y5+Z5 -> 20605.5 | CK5: =BL5-AM5 -> 20605.5 | CL5: =AY5*118% -> 838210.05 | CM5: =-Q5*118% -> -813895.56 | CN5: =-BW5*118% -> 0 | CO5: =-BX5*118% -> 0 | CP5: =SUM(CL5:CO5) -> 24314.49 | CQ5: Telangana - HO | CR5: Telangana - HO | CS5: =MID(G5,3,10) -> AALCB0491L | CT5: =MID(AR5,3,10) -> AEJFS8446P | CU5: 0 | CV5: 0 | CW5: 0 | CX5: 0 | CY5: 0
B6: ="Q" & IF(ROUNDUP(MONTH(D6)/3,0)-1=0,4,ROUNDUP(MONTH(D6)/3,0)-1) -> Q1 | C6: =TEXT(AN6,"mmm-yy") -> Apr-26 | D6: 46116 | E6: SH04261004 | F6: MK POLYPET INDIA PRIVATE LIMITED | G6: 29AAQCM8215Q1ZG | H6: MPI/26-27/6 | I6: 46116 | J6: 26-27/PUR/000396 | K6: 46122 | L6: KA | M6: KA569215 | N6: WASTE PLASTIC-PP | O6: 16490 | P6: 54.5 | Q6: =O6*P6 -> 898705 | R6: 0 | S6: =O6-R6 -> 16490 | T6: 0 | U6: 0 | V6: 0 | W6: 0 | X6: 0 | Y6: 0 | Z6: 0 | AA6: 0 | AB6: =Y6+AA6+Z6 -> 0 | AC6: 0 | AD6: =IFERROR((Q6+AB6)/S6,0) -> 54.5 | AE6: 0 | AF6: 36/PET/27VC00009 | AG6: 46129 | AH6: 0 | AI6: 0 | AJ6: 0 | AK6: -10965.85 | AL6: =(BK6*P6/AX6)+AB6/O6*(BK6/AX6) -> -22467.625 | AM6: =Q6+AB6+AL6+AK6+AJ6+T6+AE6 -> 865271.53 | AN6: 46122 | AO6: 36/PET/27IN00003 | AP6: 832139000000121856 | AQ6: J B ECOTEX LIMITED | AR6: 24AAFCJ3332A1Z9 | AS6: Kallur Karnataka 585330 | AT6: Surat | AU6: Gujarat | AV6: 182397339124 | AW6: 16490 | AX6: 55.5 | AY6: =AW6*AX6 -> 915195 | AZ6: =AW6=O6 -> TRUE | BA6: 0 | BB6: =AW6-BA6 -> 16490 | BC6: 0 | BD6: Regular | BE6: 0 | BF6: 0 | BG6: 0 | BH6: 0 | BI6: 0 | BJ6: 0 | BK6: =AY6*$BJ$3 -> -22879.875 | BL6: =AY6+BI6+BJ6+BK6+BC6 -> 892315.12 | BM6: =BL6-AM6 -> 27043.6 | BN6: =IF(BM6>=0,"Positive Margin","Negative Margin") -> Positive Margin | BO6: DN & CN Provision | BP6: =AY6-Y6-Q6-AA6-T6+BC6 -> 16490 | BQ6: =IF(BP6<0, "Negative Margin at Inception", "Positive Margin at Inception") -> Positive Margin at Inception | BR6: =IFERROR(BM6/BL6,"0") -> 0.03030723 | BS6: =IF(BR6<1%,"Less Than 1%",IF(BR6>2%,"More than 2%",IF(BR6>=1%,"1% - 2%"))) -> More than 2% | BT6: =BJ6+BK6 -> -22879.875 | BU6: =AL6+AK6 -> -33433.475 | BV6: =BT6-BU6 -> 10553.6 | BW6: =BJ6 -> 0 | BX6: =AK6 -> -10965.85 | BY6: =BW6-BX6 -> 10965.85 | BZ6: Marketplace (Plastic Waste) | CA6: 0 | CB6: =TEXT(AN6,"mmm-yy") -> Apr-26 | CC6: =AM6-AL6-AA6 -> 887739.15 | CD6: =BL6-BK6 -> 915195 | CE6: =INT((D6- IF(MONTH(D6) >= 4, DATE(YEAR(D6), 4, 1), DATE(YEAR(D6)-1, 4, 1))) / 7) + 1 -> 1 | CF6: Plastic | CG6: Plastic | CH6: =_xlfn.XLOOKUP(AR6,receivables!B:B,receivables!D:D) -> Neelesh Dixit | CI6: =AY6-Q6 -> 16490 | CJ6: =CI6-Y6+Z6 -> 16490 | CK6: =BL6-AM6 -> 27043.6 | CL6: =AY6*118% -> 1079930.1 | CM6: =-Q6*118% -> -1060471.9 | CN6: =-BW6*118% -> 0 | CO6: =-BX6*118% -> 12939.703 | CP6: =SUM(CL6:CO6) -> 32397.903 | CQ6: Telangana - HO | CR6: Telangana - HO | CS6: =MID(G6,3,10) -> AAQCM8215Q | CT6: =MID(AR6,3,10) -> AAFCJ3332A | CU6: 0 | CV6: 0 | CW6: 0 | CX6: 0 | CY6: 0
B7: ="Q" & IF(ROUNDUP(MONTH(D7)/3,0)-1=0,4,ROUNDUP(MONTH(D7)/3,0)-1) -> Q1 | C7: =TEXT(AN7,"mmm-yy") -> Apr-26 | D7: 46135 | E7: SH04262304 | F7: HITARTH ENTERPRISES | G7: 23AAPFH5775E1Z6 | H7: HE/26-27/10 | I7: 46135 | J7: 26-27/PUR/001402 | K7: 46136 | L7: MP | M7: UP24T8069 | N7: Hot washed PET flakes | O7: 8915 | P7: 66.5 | Q7: =O7*P7 -> 592847.5 | R7: 0 | S7: =O7-R7 -> 8915 | T7: 0 | U7: 0 | V7: 0 | W7: 0 | X7: 0 | Y7: 0 | Z7: 0 | AA7: 0 | AB7: =Y7+AA7+Z7 -> 0 | AC7: 0 | AD7: =IFERROR((Q7+AB7)/S7,0) -> 66.5 | AE7: 0 | AF7: 0 | AG7: 0 | AH7: 0 | AI7: 0 | AJ7: 0 | AK7: 0 | AL7: 0 | AM7: =Q7+AB7+AL7+AK7+AJ7+T7+AE7 -> 592847.5 | AN7: 46136 | AO7: 36/PET/27IN00004 | AP7: 832139000000024349 | AQ7: BLUEOCEAN ECOTECH LIMITED | AR7: 23AAICB1747Q1ZC | AS7: Pratap Pura, Madhya Pradesh 472246 | AT7: Bhopal | AU7: Madhya Pradesh | AV7: 0 | AW7: 8915 | AX7: 67 | AY7: =AW7*AX7 -> 597305 | AZ7: =AW7=O7 -> TRUE | BA7: 0 | BB7: =AW7-BA7 -> 8915 | BC7: 0 | BD7: Regular | BE7: 0 | BF7: 0 | BG7: 0 | BH7: 0 | BI7: 0 | BJ7: 0 | BK7: =AY7*$BJ$3 -> -14932.625 | BL7: =AY7+BI7+BJ7+BK7+BC7 -> 582372.38 | BM7: =BL7-AM7 -> -10475.125 | BN7: =IF(BM7>=0,"Positive Margin","Negative Margin") -> Negative Margin | BO7: Excess Qty DN | BP7: =AY7-Y7-Q7-AA7-T7+BC7 -> 4457.5 | BQ7: =IF(BP7<0, "Negative Margin at Inception", "Positive Margin at Inception") -> Positive Margin at Inception | BR7: =IFERROR(BM7/BL7,"0") -> -0.017986988 | BS7: =IF(BR7<1%,"Less Than 1%",IF(BR7>2%,"More than 2%",IF(BR7>=1%,"1% - 2%"))) -> Less Than 1% | BT7: =BJ7+BK7 -> -14932.625 | BU7: =AL7+AK7 -> 0 | BV7: =BT7-BU7 -> -14932.625 | BW7: =BJ7 -> 0 | BX7: =AK7 -> 0 | BY7: =BW7-BX7 -> 0 | BZ7: Marketplace (Plastic Waste) | CA7: 0 | CB7: =TEXT(AN7,"mmm-yy") -> Apr-26 | CC7: =AM7-AL7-AA7 -> 592847.5 | CD7: =BL7-BK7 -> 597305 | CE7: =INT((D7- IF(MONTH(D7) >= 4, DATE(YEAR(D7), 4, 1), DATE(YEAR(D7)-1, 4, 1))) / 7) + 1 -> 4 | CF7: Plastic | CG7: Plastic | CH7: =_xlfn.XLOOKUP(AR7,receivables!B:B,receivables!D:D) -> Neelesh Dixit | CI7: =AY7-Q7 -> 4457.5 | CJ7: =CI7-Y7+Z7 -> 4457.5 | CK7: =BL7-AM7 -> -10475.125 | CL7: =AY7*118% -> 704819.9 | CM7: =-Q7*118% -> -699560.05 | CN7: =-BW7*118% -> 0 | CO7: =-BX7*118% -> 0 | CP7: =SUM(CL7:CO7) -> 5259.85 | CQ7: Telangana - HO | CR7: Telangana - HO | CS7: =MID(G7,3,10) -> AAPFH5775E | CT7: =MID(AR7,3,10) -> AAICB1747Q | CU7: 0 | CV7: 0 | CW7: 0 | CX7: 0 | CY7: 0
F9: Total | O9: =SUBTOTAL(9,O5:O8) -> 36250 | Q9: =SUBTOTAL(9,Q5:Q8) -> 2181294.5 | S9: =SUBTOTAL(9,S5:S8) -> 36250 | T9: =SUBTOTAL(9,T5:T8) -> 0 | Y9: =SUBTOTAL(9,Y5:Y8) -> 0 | Z9: =SUBTOTAL(9,Z5:Z8) -> 0 | AA9: =SUBTOTAL(9,AA5:AA8) -> 0 | AB9: =SUBTOTAL(9,AB5:AB8) -> 0 | AC9: =SUBTOTAL(9,AC5:AC8) -> 0 | AD9: =SUBTOTAL(1,AD5:AD8) -> 61.533333 | AE9: =SUBTOTAL(9,AE5:AE8) -> 0 | AJ9: =SUBTOTAL(9,AJ5:AJ8) -> 0 | AK9: =SUBTOTAL(9,AK5:AK8) -> -10965.85 | AL9: =SUBTOTAL(9,AL5:AL8) -> -22467.625 | AM9: =SUBTOTAL(9,AM5:AM8) -> 2147861 | AW9: =SUBTOTAL(9,AW5:AW8) -> 36250 | AX9: =SUBTOTAL(101,AX5:AX8) -> 62.666667 | AY9: =SUBTOTAL(9,AY5:AY8) -> 2222847.5 | BA9: =SUBTOTAL(9,BA5:BA8) -> 0 | BB9: =SUBTOTAL(9,BB5:BB8) -> 36250 | BC9: =SUBTOTAL(9,BC5:BC8) -> 0 | BI9: =SUBTOTAL(9,BI5:BI8) -> 0 | BJ9: =SUBTOTAL(9,BJ5:BJ8) -> 0 | BK9: =SUBTOTAL(9,BK5:BK8) -> -37812.5 | BL9: =SUBTOTAL(9,BL5:BL8) -> 2185035 | BM9: =SUBTOTAL(9,BM5:BM8) -> 37173.975 | BP9: =SUBTOTAL(9,BP5:BP8) -> 41553 | BT9: =SUBTOTAL(9,BT5:BT8) -> -37812.5 | BU9: =SUBTOTAL(9,BU5:BU8) -> -33433.475 | BV9: =SUBTOTAL(9,BV5:BV8) -> -4379.025 | BW9: =SUBTOTAL(9,BW5:BW8) -> 0 | BX9: =SUBTOTAL(9,BX5:BX8) -> -10965.85 | BY9: =SUBTOTAL(9,BY5:BY8) -> 10965.85 | CC9: =SUBTOTAL(9,CC5:CC8) -> 2170328.6 | CD9: =SUBTOTAL(9,CD5:CD8) -> 2222847.5 | CI9: =SUBTOTAL(9,CI5:CI8) -> 41553 | CJ9: =SUBTOTAL(9,CJ5:CJ8) -> 41553 | CK9: =SUBTOTAL(9,CK5:CK8) -> 37173.975 | CL9: =SUBTOTAL(9,CL5:CL8) -> 2622960 | CM9: =SUBTOTAL(9,CM5:CM8) -> -2573927.5 | CN9: =SUBTOTAL(9,CN5:CN8) -> 0 | CO9: =SUBTOTAL(9,CO5:CO8) -> 12939.703 | CP9: =SUBTOTAL(9,CP5:CP8) -> 61972.243
N10: =O9-AW9+'Recon Items'!R31 -> 0 | P10: =Q9+AK9+AJ9+AL9+T9+AE9 -> 2147861 | Q10: =Q9*18% -> 392633.01 | R10: =Q10*25% -> 98158.253 | AA10: =AB9/AY9 -> 0 | AC10: =+AL9+AK9 -> -33433.475 | AI10: Total DN in FY 2025-26 | AJ10: =AK9+AJ9+AE9 -> -10965.85 | AM10: =AM9*18% -> 386614.98 | BE10: Total CN in FY 2025-26 | BF10: =BI9+BJ9+BC9+BJ18 -> 0 | BH10: =BF10/AY9 -> 0 | BK10: =BM9/BL9 -> 0.017012988 | BO10: =BP9/AY9 -> 0.01869359 | BU10: =BU9/BT9 -> 0.88419107 | BX10: =IFERROR(BX9/BW9,0) -> 0 | CA10: With GST | CB10: =CC9*118% -> 2560987.8 | CC10: =CD9*118% -> 2622960
AI11: Total DN of FY 2024-25 | AJ11: =-'Last year''s'!F30 -> -718187.35 | BE11: Total CN of FY 2024-25 | BF11: =-'Last year''s'!L30 -> -729139.49
B12: Quarter | C12: Month | D12: Date | E12: Shipment ID | F12: Supplier Name | G12: GST Reg No. | H12: Vendor Invoice No. | I12: Vendor Invoice Date | J12: P V No. | K12: P V Date | L12: State (Origin) | M12: Vehicle No. | N12: Material | O12: Qty (Kg) | P12: Price/Kg | Q12: Purchase Price | R12: Return Qty | S12: Net Qty | T12: Basic Customs Duty | U12: Transporter Name | V12: LR NO/BILL NO | W12: J V No. | X12: JV Date | Y12: Logistics cost | Z12: Debit note on logistic cost | AA12: Logistics Provision | AB12: Total Logistics Cost | AC12: Operational Cost | AD12: Cost/Kg. | AE12: Divertion/Internal | AF12: Debit Note No. | AG12: Debit Note Date. | AH12: Debit Note No. 2 | AI12: Debit Note Date. 2 | AJ12: Full Debit Note | AK12: Actual Debit Note | AL12: Provision for DN | AM12: Total Cost | AN12: Inv. Date | AO12: Inv. No. | AP12: Customer ID | AQ12: Buyer Name | AR12: Buyer GST Number | AS12: Location (Origin) | AT12: Location (Destination) | AU12: State (Destination) | AV12: E-WayBill Number | AW12: Qty(Kg) | AX12: Rate/Kg | AY12: Amount | AZ12: Qty Check | BA12: Return Qty | BB12: Net Qty | BC12: Divertion/Internal | BD12: Return Type | BE12: Credit Note No:1 | BF12: CN Date. No:1 | BG12: Credit Note No:2 | BH12: CN Date. No:2 | BI12: Full Credit Notes | BJ12: Actual Credit Note | BK12: Provision for CN | BL12: Net Revenue | BM12: Margin | BN12: Reamrks - Margin | BO12: Remarks | BP12: LMI @ Inception | BQ12: Remarks @ Inception | BR12: Margin (%) | BS12: Margin Bucket | BT12: Total CN(Inc.Provisions) | BU12: Total DN(Inc.Provisions) | BV12: Check | BW12: Actaul CN | BX12: Actual DN | BY12: Check | BZ12: Material-Short Form | CA12: Supplier Type | CB12: Month | CC12: Cost | CD12: Revenue | CE12: Week No: | CF12: Category (Material) | CG12: Broad Category | CH12: POC Name | CI12: Gross Margin | CJ12: Recykal Margin | CK12: Net Margin | CL12: Sales | CM12: Purchases | CN12: Credit Note | CO12: Debit Note | CP12: Margin | CQ12: Bill Branch | CR12: Inv Branch | CS12: Vendor PAN No | CT12: Customer PAN No | CU12: GST TDS Applicability | CV12: Cash Discount(Provision) | CW12: Cash Discount | CX12: Cash Discount. No | CY12: CD Date
B13: Q2 | C13: =TEXT(AN13,"mmm-yy") -> Apr-26 | D13: =AN13 -> 46122 | E13: 0 | F13: 0 | G13: 0 | H13: 0 | I13: 0 | J13: 0 | K13: 0 | L13: 0 | M13: 0 | N13: 0 | O13: 0 | P13: 0 | Q13: =O13*P13 -> 0 | R13: 0 | S13: =O13-R13 -> 0 | T13: 0 | U13: 0 | V13: 0 | W13: 0 | X13: 0 | Y13: 0 | Z13: 0 | AA13: 0 | AB13: =Y13+AA13+Z13 -> 0 | AC13: 0 | AD13: =IFERROR((Q13+AB13)/S13,0) -> 0 | AE13: 0 | AF13: 0 | AG13: 0 | AH13: 0 | AI13: 0 | AJ13: 0 | AK13: 0 | AL13: 0 | AM13: =Q13+AB13+AL13+AK13+AJ13+T13+AE13 -> 0 | AN13: 46122 | AO13: 36/PET/27DN00001 | AP13: 832139000000027397 | AQ13: Sri Chakra Poly Plast India Private Limited | AR13: 36AAOCS6150Q1ZJ | AT13: Kandi | AU13: Telangana | AV13: 0 | AW13: 1 | AX13: 303019 | AY13: =AW13*AX13 -> 303019 | AZ13: =AW13=O13 -> FALSE | BA13: 0 | BB13: =AW13-BA13 -> 1 | BC13: 0 | BD13: Regular | BE13: 36/PET/27CN00010 | BF13: 46167 | BG13: 0 | BH13: 0 | BI13: -303019 | BJ13: 0 | BK13: 0 | BL13: =AY13+BI13+BJ13+BK13+BC13 -> 0 | BM13: =BL13-AM13 -> 0 | BN13: =IF(BM13>=0,"Positive Margin","Negative Margin") -> Positive Margin | BO13: Finance Up Charges | BP13: =AY13-Y13-Q13-AA13-T13+BC13 -> 303019 | BQ13: =IF(BP13<0, "Negative Margin at Inception", "Positive Margin at Inception") -> Positive Margin at Inception | BR13: =IFERROR(BM13/BL13,"0") -> 0 | BS13: =IF(BR13<1%,"Less Than 1%",IF(BR13>2%,"More than 2%",IF(BR13>=1%,"1% - 2%"))) -> More than 2% | BT13: =BJ13+BK13 -> 0 | BU13: =AL13+AK13 -> 0 | BV13: =BT13-BU13 -> 0 | BW13: =BJ13 -> 0 | BX13: =AK13 -> 0 | BY13: =BW13-BX13 -> 0 | BZ13: Marketplace (Plastic Waste) | CA13: 0 | CB13: =TEXT(AN13,"mmm-yy") -> Apr-26 | CC13: =AM13-AL13-AA13 -> 0 | CD13: =BL13-BK13 -> 0 | CE13: =INT((D13- IF(MONTH(D13) >= 4, DATE(YEAR(D13), 4, 1), DATE(YEAR(D13)-1, 4, 1))) / 7) + 1 -> 2 | CF13: Plastic | CG13: Plastic | CH13: =_xlfn.XLOOKUP(AR13,receivables!B:B,receivables!D:D) -> #N/A | CI13: =AY13-Q13 -> 303019 | CJ13: =CI13-Y13+Z13 -> 303019 | CK13: =BL13-AM13 -> 0 | CL13: =AY13*118% -> 357562.42 | CM13: =-Q13*118% -> 0 | CN13: =-BW13*118% -> 0 | CO13: =-BX13*118% -> 0 | CP13: =SUM(CL13:CO13) -> 357562.42 | CQ13: Telangana - HO | CR13: Telangana - HO | CS13: =MID(G13,3,10) | CT13: =MID(AR13,3,10) -> AAOCS6150Q | CU13: 0 | CV13: 0 | CW13: 0 | CX13: 0 | CY13: 0
B14: Q2 | C14: =TEXT(AN14,"mmm-yy") -> Apr-26 | D14: =AN14 -> 46125 | E14: 0 | F14: 0 | G14: 0 | H14: 0 | I14: 0 | J14: 0 | K14: 0 | L14: 0 | M14: 0 | N14: 0 | O14: 0 | P14: 0 | Q14: =O14*P14 -> 0 | R14: 0 | S14: =O14-R14 -> 0 | T14: 0 | U14: 0 | V14: 0 | W14: 0 | X14: 0 | Y14: 0 | Z14: 0 | AA14: 0 | AB14: =Y14+AA14+Z14 -> 0 | AC14: 0 | AD14: =IFERROR((Q14+AB14)/S14,0) -> 0 | AE14: 0 | AF14: 0 | AG14: 0 | AH14: 0 | AI14: 0 | AJ14: 0 | AK14: 0 | AL14: 0 | AM14: =Q14+AB14+AL14+AK14+AJ14+T14+AE14 -> 0 | AN14: 46125 | AO14: 36/PET/27DN00002 | AP14: 832139000000022933 | AQ14: Apex International | AR14: 05AAQFA3937J1Z7 | AT14: KASHIPUR | AU14: Uttarakhand | AV14: 0 | AW14: 1 | AX14: 608652.03 | AY14: =AW14*AX14 -> 608652.03 | AZ14: =AW14=O14 -> FALSE | BA14: 0 | BB14: =AW14-BA14 -> 1 | BC14: 0 | BD14: Regular | BE14: 0 | BF14: 0 | BG14: 0 | BH14: 0 | BI14: 0 | BJ14: 0 | BK14: 0 | BL14: =AY14+BI14+BJ14+BK14+BC14 -> 608652.03 | BM14: =BL14-AM14 -> 608652.03 | BN14: =IF(BM14>=0,"Positive Margin","Negative Margin") -> Positive Margin | BO14: Finance Up Charges | BP14: =AY14-Y14-Q14-AA14-T14+BC14 -> 608652.03 | BQ14: =IF(BP14<0, "Negative Margin at Inception", "Positive Margin at Inception") -> Positive Margin at Inception | BR14: =IFERROR(BM14/BL14,"0") -> 1 | BS14: =IF(BR14<1%,"Less Than 1%",IF(BR14>2%,"More than 2%",IF(BR14>=1%,"1% - 2%"))) -> More than 2% | BT14: =BJ14+BK14 -> 0 | BU14: =AL14+AK14 -> 0 | BV14: =BT14-BU14 -> 0 | BW14: =BJ14 -> 0 | BX14: =AK14 -> 0 | BY14: =BW14-BX14 -> 0 | BZ14: Marketplace (Plastic Waste) | CA14: 0 | CB14: =TEXT(AN14,"mmm-yy") -> Apr-26 | CC14: =AM14-AL14-AA14 -> 0 | CD14: =BL14-BK14 -> 608652.03 | CE14: =INT((D14- IF(MONTH(D14) >= 4, DATE(YEAR(D14), 4, 1), DATE(YEAR(D14)-1, 4, 1))) / 7) + 1 -> 2 | CF14: Plastic | CG14: Plastic | CH14: =_xlfn.XLOOKUP(AR14,receivables!B:B,receivables!D:D) -> #N/A | CI14: =AY14-Q14 -> 608652.03 | CJ14: =CI14-Y14+Z14 -> 608652.03 | CK14: =BL14-AM14 -> 608652.03 | CL14: =AY14*118% -> 718209.4 | CM14: =-Q14*118% -> 0 | CN14: =-BW14*118% -> 0 | CO14: =-BX14*118% -> 0 | CP14: =SUM(CL14:CO14) -> 718209.4 | CQ14: Telangana - HO | CR14: Telangana - HO | CS14: =MID(G14,3,10) | CT14: =MID(AR14,3,10) -> AAQFA3937J | CU14: 0 | CV14: 0 | CW14: 0 | CX14: 0 | CY14: 0
B15: Q2 | C15: =TEXT(AN15,"mmm-yy") -> Apr-26 | D15: =AN15 -> 46125 | E15: 0 | F15: 0 | G15: 0 | H15: 0 | I15: 0 | J15: 0 | K15: 0 | L15: 0 | M15: 0 | N15: 0 | O15: 0 | P15: 0 | Q15: =O15*P15 -> 0 | R15: 0 | S15: =O15-R15 -> 0 | T15: 0 | U15: 0 | V15: 0 | W15: 0 | X15: 0 | Y15: 0 | Z15: 0 | AA15: 0 | AB15: =Y15+AA15+Z15 -> 0 | AC15: 0 | AD15: =IFERROR((Q15+AB15)/S15,0) -> 0 | AE15: 0 | AF15: 0 | AG15: 0 | AH15: 0 | AI15: 0 | AJ15: 0 | AK15: 0 | AL15: 0 | AM15: =Q15+AB15+AL15+AK15+AJ15+T15+AE15 -> 0 | AN15: 46125 | AO15: 36/PET/27DN00003 | AP15: 832139000007459042 | AQ15: JAINARAIN FABTECH LIMITED | AR15: 09AADCJ2313B1Z6 | AT15: Meerut | AU15: Uttar Pradesh | AV15: 0 | AW15: 1 | AX15: 755024 | AY15: =AW15*AX15 -> 755024 | AZ15: =AW15=O15 -> FALSE | BA15: 0 | BB15: =AW15-BA15 -> 1 | BC15: 0 | BD15: Regular | BE15: 0 | BF15: 0 | BG15: 0 | BH15: 0 | BI15: 0 | BJ15: 0 | BK15: 0 | BL15: =AY15+BI15+BJ15+BK15+BC15 -> 755024 | BM15: =BL15-AM15 -> 755024 | BN15: =IF(BM15>=0,"Positive Margin","Negative Margin") -> Positive Margin | BO15: Finance Up Charges | BP15: =AY15-Y15-Q15-AA15-T15+BC15 -> 755024 | BQ15: =IF(BP15<0, "Negative Margin at Inception", "Positive Margin at Inception") -> Positive Margin at Inception | BR15: =IFERROR(BM15/BL15,"0") -> 1 | BS15: =IF(BR15<1%,"Less Than 1%",IF(BR15>2%,"More than 2%",IF(BR15>=1%,"1% - 2%"))) -> More than 2% | BT15: =BJ15+BK15 -> 0 | BU15: =AL15+AK15 -> 0 | BV15: =BT15-BU15 -> 0 | BW15: =BJ15 -> 0 | BX15: =AK15 -> 0 | BY15: =BW15-BX15 -> 0 | BZ15: Marketplace (Plastic Waste) | CA15: 0 | CB15: =TEXT(AN15,"mmm-yy") -> Apr-26 | CC15: =AM15-AL15-AA15 -> 0 | CD15: =BL15-BK15 -> 755024 | CE15: =INT((D15- IF(MONTH(D15) >= 4, DATE(YEAR(D15), 4, 1), DATE(YEAR(D15)-1, 4, 1))) / 7) + 1 -> 2 | CF15: Plastic | CG15: Plastic | CH15: =_xlfn.XLOOKUP(AR15,receivables!B:B,receivables!D:D) -> #N/A | CI15: =AY15-Q15 -> 755024 | CJ15: =CI15-Y15+Z15 -> 755024 | CK15: =BL15-AM15 -> 755024 | CL15: =AY15*118% -> 890928.32 | CM15: =-Q15*118% -> 0 | CN15: =-BW15*118% -> 0 | CO15: =-BX15*118% -> 0 | CP15: =SUM(CL15:CO15) -> 890928.32 | CQ15: Telangana - HO | CR15: Telangana - HO | CS15: =MID(G15,3,10) | CT15: =MID(AR15,3,10) -> AADCJ2313B | CU15: 0 | CV15: 0 | CW15: 0 | CX15: 0 | CY15: 0
B16: Q2 | C16: =TEXT(AN16,"mmm-yy") -> Apr-26 | D16: =AN16 -> 46132 | E16: 0 | F16: 0 | G16: 0 | H16: 0 | I16: 0 | J16: 0 | K16: 0 | L16: 0 | M16: 0 | N16: 0 | O16: 0 | P16: 0 | Q16: =O16*P16 -> 0 | R16: 0 | S16: =O16-R16 -> 0 | T16: 0 | U16: 0 | V16: 0 | W16: 0 | X16: 0 | Y16: 0 | Z16: 0 | AA16: 0 | AB16: =Y16+AA16+Z16 -> 0 | AC16: 0 | AD16: =IFERROR((Q16+AB16)/S16,0) -> 0 | AE16: 0 | AF16: 0 | AG16: 0 | AH16: 0 | AI16: 0 | AJ16: 0 | AK16: 0 | AL16: 0 | AM16: =Q16+AB16+AL16+AK16+AJ16+T16+AE16 -> 0 | AN16: 46132 | AO16: 36/PET/27DN00004 | AP16: 832139000058476217 | AQ16: NATIONAL FIBRES PRIVATE LIMITED | AR16: 26AAICN2675D1ZG | AT16: Silvassa | AU16: Dadra and Nagar Haveli and Daman and Diu | AV16: 0 | AW16: 1 | AX16: 395165.28 | AY16: =AW16*AX16 -> 395165.28 | AZ16: =AW16=O16 -> FALSE | BA16: 0 | BB16: =AW16-BA16 -> 1 | BC16: 0 | BD16: Regular | BE16: 36/PET/27CN00011 | BF16: 46168 | BG16: 0 | BH16: 0 | BI16: -395165.28 | BJ16: 0 | BK16: 0 | BL16: =AY16+BI16+BJ16+BK16+BC16 -> 0 | BM16: =BL16-AM16 -> 0 | BN16: =IF(BM16>=0,"Positive Margin","Negative Margin") -> Positive Margin | BO16: Finance Up Charges | BP16: =AY16-Y16-Q16-AA16-T16+BC16 -> 395165.28 | BQ16: =IF(BP16<0, "Negative Margin at Inception", "Positive Margin at Inception") -> Positive Margin at Inception | BR16: =IFERROR(BM16/BL16,"0") -> 0 | BS16: =IF(BR16<1%,"Less Than 1%",IF(BR16>2%,"More than 2%",IF(BR16>=1%,"1% - 2%"))) -> More than 2% | BT16: =BJ16+BK16 -> 0 | BU16: =AL16+AK16 -> 0 | BV16: =BT16-BU16 -> 0 | BW16: =BJ16 -> 0 | BX16: =AK16 -> 0 | BY16: =BW16-BX16 -> 0 | BZ16: Marketplace (Plastic Waste) | CA16: 0 | CB16: =TEXT(AN16,"mmm-yy") -> Apr-26 | CC16: =AM16-AL16-AA16 -> 0 | CD16: =BL16-BK16 -> 0 | CE16: =INT((D16- IF(MONTH(D16) >= 4, DATE(YEAR(D16), 4, 1), DATE(YEAR(D16)-1, 4, 1))) / 7) + 1 -> 3 | CF16: Plastic | CG16: Plastic | CH16: =_xlfn.XLOOKUP(AR16,receivables!B:B,receivables!D:D) -> #N/A | CI16: =AY16-Q16 -> 395165.28 | CJ16: =CI16-Y16+Z16 -> 395165.28 | CK16: =BL16-AM16 -> 0 | CL16: =AY16*118% -> 466295.03 | CM16: =-Q16*118% -> 0 | CN16: =-BW16*118% -> 0 | CO16: =-BX16*118% -> 0 | CP16: =SUM(CL16:CO16) -> 466295.03 | CQ16: Telangana - HO | CR16: Telangana - HO | CS16: =MID(G16,3,10) | CT16: =MID(AR16,3,10) -> AAICN2675D | CU16: 0 | CV16: 0 | CW16: 0 | CX16: 0 | CY16: 0
F18: Total | O18: =SUBTOTAL(9,O13:O17) -> 0 | Q18: =SUBTOTAL(9,Q13:Q17) -> 0 | R18: =SUBTOTAL(9,R13:R17) -> 0 | S18: =SUBTOTAL(9,S13:S17) -> 0 | T18: =SUBTOTAL(9,T13:T17) -> 0 | Y18: =SUBTOTAL(9,Y13:Y17) -> 0 | Z18: =SUBTOTAL(9,Z13:Z17) -> 0 | AA18: =SUBTOTAL(9,AA13:AA17) -> 0 | AB18: =SUBTOTAL(9,AB13:AB17) -> 0 | AC18: =SUBTOTAL(9,AC13:AC17) -> 0 | AD18: =SUBTOTAL(9,AD13:AD17) -> 0 | AE18: =SUBTOTAL(9,AE13:AE17) -> 0 | AF18: =SUBTOTAL(9,AF13:AF17) -> 0 | AG18: =SUBTOTAL(9,AG13:AG17) -> 0 | AJ18: =SUBTOTAL(9,AJ13:AJ17) -> 0 | AK18: =SUBTOTAL(9,AK13:AK17) -> 0 | AL18: =SUBTOTAL(9,AL13:AL17) -> 0 | AM18: =SUBTOTAL(9,AM13:AM17) -> 0 | AW18: =SUBTOTAL(9,AW13:AW17) -> 4 | AY18: =SUBTOTAL(9,AY13:AY17) -> 2061860.3 | BA18: =SUBTOTAL(9,BA13:BA17) -> 0 | BB18: =SUBTOTAL(9,BB13:BB17) -> 4 | BC18: =SUBTOTAL(9,BC13:BC17) -> 0 | BI18: =SUBTOTAL(9,BI13:BI17) -> -698184.28 | BJ18: =SUBTOTAL(9,BJ13:BJ17) -> 0 | BK18: =SUBTOTAL(9,BK13:BK17) -> 0 | BL18: =SUBTOTAL(9,BL13:BL17) -> 1363676 | BM18: =SUBTOTAL(9,BM13:BM17) -> 1363676 | BP18: =SUBTOTAL(9,BP13:BP17) -> 2061860.3 | BT18: =SUBTOTAL(9,BT13:BT17) -> 0 | BU18: =SUBTOTAL(9,BU13:BU17) -> 0 | BV18: =SUBTOTAL(9,BV13:BV17) -> 0 | BW18: =SUBTOTAL(9,BW13:BW17) -> 0 | BX18: =SUBTOTAL(9,BX13:BX17) -> 0 | BY18: =SUBTOTAL(9,BY13:BY17) -> 0 | CC18: =SUBTOTAL(9,CC13:CC17) -> 0 | CD18: =SUBTOTAL(9,CD13:CD17) -> 1363676 | CI18: =SUBTOTAL(9,CI13:CI17) -> 2061860.3 | CJ18: =SUBTOTAL(9,CJ13:CJ17) -> 2061860.3 | CK18: =SUBTOTAL(9,CK13:CK17) -> 1363676 | CL18: =SUBTOTAL(9,CL13:CL17) -> 2432995.2 | CM18: =SUBTOTAL(9,CM13:CM17) -> 0 | CN18: =SUBTOTAL(9,CN13:CN17) -> 0 | CO18: =SUBTOTAL(9,CO13:CO17) -> 0 | CP18: =SUBTOTAL(9,CP13:CP17) -> 2432995.2
N20: Particulars | O20: Amount | AA20: Particulars | AC20: Amount | AX20: Particulars | AY20: Amount
N21: Net Purchase as per report | O21: =Q9+AJ9+AK9+AE9+Q18+AK18 -> 2170328.6 | AA21: Net Logistic Cost as per report | AC21: =Y9+Z9 -> 0 | AX21: Net Sales As per report | AY21: =+AY9+BI9+BJ9+BC9+AY18+BJ18+BI18+BC18 -> 3586523.5
N22: As per ZOHO | O22: 1778946.3 | P22: 46194 | AA22: As per ZOHO | AC22: 0 | AD22: =P22 -> 46194 | AX22: As per ZOHO | AY22: 3173162 | AZ22: =P22 -> 46194
N23: Variance | O23: =O22-O21 -> -391382.33 | AA23: Variance | AC23: =-(AC22-AC21) -> 0 | AX23: Variance | AY23: =AY21-AY22 -> 413361.58
N24: Provision for DN to Vendors(Fy 2024-25) | O24: ='Last year''s'!F3 -> 309308 | AA24: Fy 2024-25 Logistic Provision Reversal | AC24: 0 | AX24: CN Provision in Zoho FY 25-26 | AY24: ='Last year''s'!L3 -> 315777.91
N25: JV for last year Bills | O25: 0 | AA25: FY 2025-26 Logistics | AC25: 0 | AX25: FY 2025-26 Credit notes | AY25: =-'Last year''s'!L30 -> -729139.49
N26: Debit note FY 25-26 | O26: ='Last year''s'!F30 -> 718187.35 | AA26: Provision for Logistics (Fy 2025-26) | AC26: 0 | AX26: Provision for CN from Customers(Fy 2025-26) | AY26: 0
N27: Paper | O27: =-'Recon Items'!C46 -> 0 | AA27: Paper | AC27: =-'Recon Items'!K56 -> 0 | AX27: Paper | AY27: ='Recon Items'!G46 -> 0
N28: Reconciliation | O28: ='Recon Items'!G18-'Recon Items'!C18-'Recon Items'!N18+'Recon Items'!C43 -> 17497.02 | AA28: Reconciliation | AC28: ='Recon Items'!K42 -> 0 | AX28: Reconciliation | AY28: =-'Recon Items'!C29+'Recon Items'!G29+'Recon Items'!R24+'Recon Items'!H43 -> 0
N29: Variance | O29: =O23+O26-O28-O25-O24-O27 -> 1.1641532e-10 | AA29: Variance | AC29: =SUM(AC23:AC28) -> 0 | AX29: Final Variance | AY29: =AY23+AY25+AY28+AY24-AY26-AY27 -> 5.8207661e-11
BG42: =SUM(BG36:BG41) -> 0
BG43: =BG35-BG42 -> 0
AK49: =AK50-AK51 -> 0

Sheet Recon Items
J3: Qty Reco | M3: FY 2025-26 bills considered ths year | Q3: FY 2025-26
B4: Bills in report not in P&L | C4: Amount | F4: Bills in P&L not in report | G4: Amount | H4: Qty | J4: Qty Check | K4: =Details!AD22 -> 46194 | M4: Bills in report not in P&L | N4: Amount | O4: Qty | Q4: DN to Customer | R4: Amount
M5: SH022606031 | N5: 11011.02 | O5: 1
J6: As Per Report | K6: =-Details!AW9 -> -36250 | M6: SH012627021 | N6: 4536 | O6: 70
J7: As per Zoho(till last month) | K7: 36351 | M7: SH012621039 | N7: 1950 | O7: 30
J8: As per Zoho (current month) | K8: 0
J9: Reco | K9: =R31+I42 -> 0
J10: Variance | K10: =SUM(K6:K9)-H18-O18 -> 0
J14: BCD not in Report | K14: Amount
B18: G.Total | C18: =SUM(C5:C17) -> 0 | F18: G.Total | G18: =SUBTOTAL(9,G5:G17) -> 0 | H18: =SUBTOTAL(9,H5:H17) -> 0 | K18: =SUM(K15:K17) -> 0 | M18: G.Total | N18: =-SUM(N5:N17) -> -17497.02 | O18: =SUM(O5:O17) -> 101
B21: Sales in report not in P&L | C21: Amount | F21: Sales in P&L not in report | G21: Amount | H21: Qty | J21: Bils in Report & P&L , Sale yet to be done
Q24: G.Total | R24: =SUM(R5:R23) -> 0
Q25: Offline orders & Divertions
Q26: SO Number | R26: Qty
B29: G.Total | C29: =SUM(C22:C28) -> 0 | F29: G.Total | G29: =SUBTOTAL(9,G22:G28) -> 0 | H29: 0 | J29: G.Total
B31: DRS | Q31: G.Total | R31: =SUM(R27:R30) -> 0
B32: Bills | C32: Amount | D32: DN | F32: Invoices | G32: Amount | H32: CN | I32: Qty | J32: Logistic Bill | K32: Amount
B42: G.Total | C42: =SUM(C33:C41) -> 0 | D42: =SUM(D33:D41) -> 0 | F42: G.Total | G42: =SUBTOTAL(9,G33:G41) -> 0 | H42: =SUBTOTAL(9,H33:H41) -> 0 | I42: =SUBTOTAL(9,I33:I41) -> 0 | J42: G.Total | K42: =SUBTOTAL(9,K33:K41) -> 0
C43: =C42-D42 -> 0 | H43: =G42+H42 -> 0
B46: Paper | C46: =C56-D56 -> 0 | G46: =G56-H56 -> 0
B47: Bills | C47: Amount | D47: DN | F47: Invoices | G47: Amount | H47: CN | I47: Qty | J47: Logistic Bill | K47: Amount
B56: G.Total | C56: =SUM(C48:C55) -> 0 | D56: =SUM(D48:D55) -> 0 | F56: G.Total | G56: =SUBTOTAL(9,G48:G55) -> 0 | H56: =SUBTOTAL(9,H48:H55) -> 0 | I56: =SUBTOTAL(9,I48:I55) -> 0 | J56: G.Total | K56: =SUBTOTAL(9,K48:K55) -> 0
AB696: -568957
AB701: =-AB697+AB698-AB699 -> 0

Sheet Supplier Metrics
D1: =D2-Summary!Q7 -> 0
D2: =SUBTOTAL(9,D4:D25) -> 2147861 | E2: =COUNTA(_xlfn.ANCHORARRAY(E4)) -> 3
B3: Supplier Name | C3: GST Reg No. | D3: Purchases | E3: Count Supplier Name
B4: =_xlfn.XLOOKUP(C4,Details!$G$5:$G$8,Details!$F$5:$F$8) -> BHAGIRATHI POLYMER PRIVATE LIMITED | C4: {=_xlfn.UNIQUE(_xlfn._TRO_TRAILING(Details!G5:G8))} -> 09AALCB0491L1ZA | D4: =SUMIFS(Details!$AM$5:$AM$8,Details!$G$5:$G$8,'Supplier Metrics'!C4)-SUMIFS(Details!$AB$5:$AB$8,Details!$G$5:$G$8,'Supplier Metrics'!C4) -> 689742 | E4: {=_xlfn.UNIQUE(MID(_xlfn._TRO_TRAILING(Details!G5:G8),3,10))} -> AALCB0491L
B5: =_xlfn.XLOOKUP(C5,Details!$G$5:$G$8,Details!$F$5:$F$8) -> MK POLYPET INDIA PRIVATE LIMITED | C5: 29AAQCM8215Q1ZG | D5: =SUMIFS(Details!$AM$5:$AM$8,Details!$G$5:$G$8,'Supplier Metrics'!C5)-SUMIFS(Details!$AB$5:$AB$8,Details!$G$5:$G$8,'Supplier Metrics'!C5) -> 865271.53 | E5: AAQCM8215Q
B6: =_xlfn.XLOOKUP(C6,Details!$G$5:$G$8,Details!$F$5:$F$8) -> HITARTH ENTERPRISES | C6: 23AAPFH5775E1Z6 | D6: =SUMIFS(Details!$AM$5:$AM$8,Details!$G$5:$G$8,'Supplier Metrics'!C6)-SUMIFS(Details!$AB$5:$AB$8,Details!$G$5:$G$8,'Supplier Metrics'!C6) -> 592847.5 | E6: AAPFH5775E
B7: =_xlfn.XLOOKUP(C7,Details!$G$5:$G$8,Details!$F$5:$F$8) -> 0 | D7: =SUMIFS(Details!$AM$5:$AM$8,Details!$G$5:$G$8,'Supplier Metrics'!C7)-SUMIFS(Details!$AB$5:$AB$8,Details!$G$5:$G$8,'Supplier Metrics'!C7) -> 0

Sheet Buyer Metrics
F2: =F3-Summary!P6-Details!BL18 -> -1345917.3 | G2: =G3-Summary!P12-Summary!P75-Details!BM18 -> -1363160.9 | H2: =H3-Summary!P13 -> 9.8284264e-05 | I2: =I3-Details!BW9 -> 0 | K2: =K3-Summary!P19 -> 0 | S2: Revenue | AD2: Qty
B3: =COUNTA(_xlfn.ANCHORARRAY(B5)) -> 3 | C3: =COUNTA(_xlfn.ANCHORARRAY(C5)) -> 3 | E3: =SUM(E$5:E5) -> 10845 | F3: =SUM(F$5:F83) -> 2185035 | G3: =SUM(G$5:G83) -> 37173.975 | H3: =G3/F3 -> 0.017012988 | I3: =SUM(I$5:I83) -> 0 | J3: =I3/F3 -> 0 | K3: =SUM(K$5:K83) -> 3 | L3: =SUBTOTAL(1,L5:L83) -> 728345 | M3: =F3/E3 -> 201.47856 | N3: =SUM(N$5:N83) -> 0 | S3: =SUBTOTAL(9,S5:S5) -> 0 | T3: =SUBTOTAL(9,T5:T5) -> 0 | U3: =SUBTOTAL(9,U5:U5) -> 0 | V3: =SUBTOTAL(9,V5:V5) -> 0 | W3: =SUBTOTAL(9,W5:W5) -> 0 | X3: =SUBTOTAL(9,X5:X5) -> 0 | Y3: =SUBTOTAL(9,Y5:Y5) -> 0 | Z3: =SUBTOTAL(9,Z5:Z5) -> 0 | ... AB3: =SUBTOTAL(9,AB5:AB5) -> 0 | AD3: =SUBTOTAL(9,AD5:AD5) -> 0 | AE3: =SUBTOTAL(9,AE5:AE5) -> 0 | AF3: =SUBTOTAL(9,AF5:AF5) -> 0 | AG3: =SUBTOTAL(9,AG5:AG5) -> 0 | AH3: =SUBTOTAL(9,AH5:AH5) -> 0 | AI3: =SUBTOTAL(9,AI5:AI5) -> 0 | AJ3: =SUBTOTAL(9,AJ5:AJ5) -> 0 | AK3: =SUBTOTAL(9,AK5:AK5) -> 0 | ... AM3: =SUBTOTAL(9,AM5:AM5) -> 0
B4: Count Recyclers | C4: Customer ID | D4: Customer Name | E4: Qty | F4: Revenue | G4: Margin | H4: Margin(% | I4: Debit Notes | J4: DN to Sale(%) | K4: No of transactions | L4: Avg Tran Value | M4: Avg.Price/kg | N4: Receivables | Q4: Count Recyclers | R4: Name | S4: Apr-25 | T4: May-25 | U4: Jun-25 | V4: Jul-25 | W4: Aug-25 | X4: Sep-25 | Y4: Oct-25 | Z4: Nov-25 | AA4: Dec-25 | AB4: Jan-26 | AD4: Apr-25 | AE4: May-25 | AF4: Jun-25 | AG4: Jul-25 | AH4: Aug-25 | AI4: Sep-25 | AJ4: Oct-25 | AK4: Nov-25 | AL4: Dec-25 | AM4: Jan-26
B5: {=_xlfn.UNIQUE(MID(_xlfn._TRO_TRAILING(Details!AR5:AR8),3,10))} -> AEJFS8446P | C5: {=_xlfn.UNIQUE(_xlfn._TRO_TRAILING(Details!AR5:AR8))} -> 09AEJFS8446P1ZY | D5: =(_xlfn.XLOOKUP(C5,Details!$AR$5:$AR$8,Details!$AQ$5:$AQ$8)) -> Silver Ecotex LLP | E5: =SUMIFS(Details!BB:BB,Details!AR:AR,'Buyer Metrics'!$C5) -> 10845 | F5: =SUMIFS(Details!BL:BL,Details!AR:AR,'Buyer Metrics'!$C5) -> 710347.5 | G5: =SUMIFS(Details!BM:BM,Details!AR:AR,'Buyer Metrics'!$C5) -> 20605.5 | H5: =G5/F5 -> 0.029007634 | I5: =SUMIFS(Details!BW:BW,Details!AR:AR,'Buyer Metrics'!C5) -> 0 | J5: =-(I5/F5) -> 0 | K5: {=COUNTA(_xlfn.UNIQUE(_xlfn._xlws.FILTER(Details!AO5:AO8,Details!AR5:AR8='Buyer Metrics'!$C5)))} -> 1 | L5: =F5/K5 -> 710347.5 | M5: =F5/E5 -> 65.5 | N5: =IFERROR(_xlfn.XLOOKUP(C5,receivables!#REF!,receivables!#REF!),0) -> 0 | Q5: {=_xlfn.UNIQUE(Details!CT5:CT8)} -> AEJFS8446P | R5: =_xlfn.XLOOKUP(Q5,Details!CT:CT,Details!AQ:AQ) -> Silver Ecotex LLP | S5: =SUMIFS(Details!$BL:$BL,Details!$CT:$CT,'Buyer Metrics'!$Q5,Details!$C:$C,'Buyer Metrics'!S$4) -> 0 | T5: =SUMIFS(Details!$BL:$BL,Details!$CT:$CT,'Buyer Metrics'!$Q5,Details!$C:$C,'Buyer Metrics'!T$4) -> 0 | U5: =SUMIFS(Details!$BL:$BL,Details!$CT:$CT,'Buyer Metrics'!$Q5,Details!$C:$C,'Buyer Metrics'!U$4) -> 0 | V5: =SUMIFS(Details!$BL:$BL,Details!$CT:$CT,'Buyer Metrics'!$Q5,Details!$C:$C,'Buyer Metrics'!V$4) -> 0 | W5: =SUMIFS(Details!$BL:$BL,Details!$CT:$CT,'Buyer Metrics'!$Q5,Details!$C:$C,'Buyer Metrics'!W$4) -> 0 | X5: =SUMIFS(Details!$BL:$BL,Details!$CT:$CT,'Buyer Metrics'!$Q5,Details!$C:$C,'Buyer Metrics'!X$4) -> 0 | Y5: =SUMIFS(Details!$BL:$BL,Details!$CT:$CT,'Buyer Metrics'!$Q5,Details!$C:$C,'Buyer Metrics'!Y$4) -> 0 | Z5: =SUMIFS(Details!$BL:$BL,Details!$CT:$CT,'Buyer Metrics'!$Q5,Details!$C:$C,'Buyer Metrics'!Z$4) -> 0 | ... AB5: =SUMIFS(Details!$BL:$BL,Details!$CT:$CT,'Buyer Metrics'!$Q5,Details!$C:$C,'Buyer Metrics'!AB$4) -> 0 | AD5: =SUMIFS(Details!$BB:$BB,Details!$CT:$CT,'Buyer Metrics'!$Q5,Details!$C:$C,'Buyer Metrics'!AD$4) -> 0 | AE5: =SUMIFS(Details!$BB:$BB,Details!$CT:$CT,'Buyer Metrics'!$Q5,Details!$C:$C,'Buyer Metrics'!AE$4) -> 0 | AF5: =SUMIFS(Details!$BB:$BB,Details!$CT:$CT,'Buyer Metrics'!$Q5,Details!$C:$C,'Buyer Metrics'!AF$4) -> 0 | AG5: =SUMIFS(Details!$BB:$BB,Details!$CT:$CT,'Buyer Metrics'!$Q5,Details!$C:$C,'Buyer Metrics'!AG$4) -> 0 | AH5: =SUMIFS(Details!$BB:$BB,Details!$CT:$CT,'Buyer Metrics'!$Q5,Details!$C:$C,'Buyer Metrics'!AH$4) -> 0 | AI5: =SUMIFS(Details!$BB:$BB,Details!$CT:$CT,'Buyer Metrics'!$Q5,Details!$C:$C,'Buyer Metrics'!AI$4) -> 0 | AJ5: =SUMIFS(Details!$BB:$BB,Details!$CT:$CT,'Buyer Metrics'!$Q5,Details!$C:$C,'Buyer Metrics'!AJ$4) -> 0 | AK5: =SUMIFS(Details!$BB:$BB,Details!$CT:$CT,'Buyer Metrics'!$Q5,Details!$C:$C,'Buyer Metrics'!AK$4) -> 0 | ... AM5: =SUMIFS(Details!$BB:$BB,Details!$CT:$CT,'Buyer Metrics'!$Q5,Details!$C:$C,'Buyer Metrics'!AM$4) -> 0
B6: AAFCJ3332A | C6: 24AAFCJ3332A1Z9 | D6: =(_xlfn.XLOOKUP(C6,Details!$AR$5:$AR$8,Details!$AQ$5:$AQ$8)) -> J B ECOTEX LIMITED | E6: =SUMIFS(Details!BB:BB,Details!AR:AR,'Buyer Metrics'!$C6) -> 16490 | F6: =SUMIFS(Details!BL:BL,Details!AR:AR,'Buyer Metrics'!$C6) -> 892315.12 | G6: =SUMIFS(Details!BM:BM,Details!AR:AR,'Buyer Metrics'!$C6) -> 27043.6 | H6: =G6/F6 -> 0.03030723 | I6: =SUMIFS(Details!BW:BW,Details!AR:AR,'Buyer Metrics'!C6) -> 0 | J6: =-(I6/F6) -> 0 | K6: {=COUNTA(_xlfn.UNIQUE(_xlfn._xlws.FILTER(Details!AO6:AO9,Details!AR6:AR9='Buyer Metrics'!$C6)))} -> 1 | L6: =F6/K6 -> 892315.12 | M6: =F6/E6 -> 54.1125 | N6: =IFERROR(_xlfn.XLOOKUP(C6,receivables!#REF!,receivables!#REF!),0) -> 0 | Q6: AAFCJ3332A
B7: AAICB1747Q | C7: 23AAICB1747Q1ZC | D7: =(_xlfn.XLOOKUP(C7,Details!$AR$5:$AR$8,Details!$AQ$5:$AQ$8)) -> BLUEOCEAN ECOTECH LIMITED | E7: =SUMIFS(Details!BB:BB,Details!AR:AR,'Buyer Metrics'!$C7) -> 8915 | F7: =SUMIFS(Details!BL:BL,Details!AR:AR,'Buyer Metrics'!$C7) -> 582372.38 | G7: =SUMIFS(Details!BM:BM,Details!AR:AR,'Buyer Metrics'!$C7) -> -10475.125 | H7: =G7/F7 -> -0.017986988 | I7: =SUMIFS(Details!BW:BW,Details!AR:AR,'Buyer Metrics'!C7) -> 0 | J7: =-(I7/F7) -> 0 | K7: {=COUNTA(_xlfn.UNIQUE(_xlfn._xlws.FILTER(Details!AO7:AO10,Details!AR7:AR10='Buyer Metrics'!$C7)))} -> 1 | L7: =F7/K7 -> 582372.38 | M7: =F7/E7 -> 65.325 | N7: =IFERROR(_xlfn.XLOOKUP(C7,receivables!#REF!,receivables!#REF!),0) -> 0 | Q7: AAICB1747Q
Q8: 0

Sheet Material Metrics
B2: Material | C2: Category A | D2: Category B
B3: {=_xlfn.UNIQUE(_xlfn._TRO_TRAILING(Details!N5:N8))} -> PET - Hot Washed White Flakes, Grade 2 | C3: PET
B4: WASTE PLASTIC-PP
B5: Hot washed PET flakes
C41: HDPE
C42: HDPE

Sheet receivables
D1: =Details!P22 -> 46194 | E1: =SUBTOTAL(9,E3:E136) -> #N/A | R1: =SUBTOTAL(9,R3:R1000) -> 1.1283315e+08 | S1: =SUBTOTAL(9,S3:S1000) -> 1.5939088e+08 | AA1: =SUBTOTAL(9,AA3:AA150) -> 776632.63 | AB1: =R1-AA1 -> 1.1205652e+08 | AE1: Legacy | AF1: =R1-AA1-SUM(AF3:AF16)-AF18 -> 54302522 | AO1: =SUM(AO3:AO480) -> 19968208
B2: Customer ID | C2: Buyer Name | D2: POC Name | E2: Recivables | H2: POC Name | I2: Buyer Name | K2: date | L2: status | M2: entity | N2: age | O2: due_date | P2: transaction_number | Q2: customer_name | R2: balance | S2: amount | T2: payment_terms | U2: gst_no | V2: credit_limit | W2: unused_credits_receivable_amount | X2: contact.CF.Vertical Name | Y2: Check | Z2: Customer Name | AA2: Unused | AE2: Customer Name | AF2: Current O/s | AH2: date | AI2: status | AJ2: entity | AK2: age | AL2: due_date | AM2: transaction_number | AN2: vendor_name | AO2: balance | AP2: amount | AQ2: gst_no | AR2: vendor.CF.Vertical Name | AS2: vendor.CF.MSME Category
B3: {=_xlfn.UNIQUE(_xlfn._TRO_TRAILING(Details!AR5:AR8))} -> 09AEJFS8446P1ZY | C3: =_xlfn.XLOOKUP(B3,Details!AR:AR,Details!AQ:AQ) -> Silver Ecotex LLP | D3: Neelesh Dixit | E3: =_xlfn.XLOOKUP(C3,I:I,H:H) -> Neelesh Dixit | H3: Neelesh Dixit | I3: M/S KASHI VISHWANATH TEXTILE MILL PRIVATE LIMITED | K3: 44801 | L3: overdue | M3: invoice | N3: 1375 | O3: 2022-09-15 | P3: 23/MPPET/INV2883 | Q3: VANSH POLYPACK LLP | R3: 866675.04 | S3: 1073444.2 | T3: Net 15 (Days) | U3: 09AARFV5599C1ZE | V3: 0.01 | W3: 0 | X3: Marketplace (Plastic Waste) | Y3: Marketplace (Plastic Waste) | Z3: {=_xlfn.UNIQUE(Q3:Q766)} -> VANSH POLYPACK LLP | AA3: =_xlfn.XLOOKUP(Z3,Q:Q,W:W) -> 0 | AE3: VANSH POLYPACK LLP | AF3: =SUMIFS(R:R,Q:Q,AE3) -> 27995932 | AH3: 2022-03-31 | AI3: overdue | AJ3: bill | AK3: 1540 | AL3: 2022-04-03 | AM3: 15294 | AN3: NEW SHALIMAR ROADWAYS | AO3: 7140 | AP3: 51000 | AQ3: 23AAIFN0748A2ZR | AR3: Marketplace (Plastic Waste) | AS3: Small
B4: 24AAFCJ3332A1Z9 | C4: =_xlfn.XLOOKUP(B4,Details!AR:AR,Details!AQ:AQ) -> J B ECOTEX LIMITED | D4: Neelesh Dixit | E4: =_xlfn.XLOOKUP(C4,I:I,H:H) -> Ramesh G | H4: Neelesh Dixit | I4: NIRMAL FIBRES PRIVATE LIMITED | K4: 44803 | L4: overdue | M4: invoice | N4: 1372 | O4: 2022-09-18 | P4: 23/MPPET/INV2909 | Q4: VANSH POLYPACK LLP | R4: 451970.68 | S4: 472619.5 | T4: Net 15 (Days) | U4: 09AARFV5599C1ZE | V4: 0.01 | W4: 0 | X4: Marketplace (Plastic Waste) | Y4: Marketplace (Plastic Waste) | Z4: INDIA POLYMERS | AA4: =_xlfn.XLOOKUP(Z4,Q:Q,W:W) -> 0 | AE4: INDIA POLYMERS | AF4: =SUMIFS(R:R,Q:Q,AE4) -> 26666038 | AH4: 2022-03-31 | AI4: overdue | AJ4: bill | AK4: 1542 | AL4: 2022-04-01 | AM4: 692302 | AN4: VRL Logistics Ltd | AO4: 1800 | AP4: 97000 | AQ4: 29AABCV3609C1ZJ | AR4: Marketplace (Plastic Waste) | AS4: Not Registered
B5: 23AAICB1747Q1ZC | C5: =_xlfn.XLOOKUP(B5,Details!AR:AR,Details!AQ:AQ) -> BLUEOCEAN ECOTECH LIMITED | D5: Neelesh Dixit | E5: =_xlfn.XLOOKUP(C5,I:I,H:H) -> #N/A | H5: Neelesh Dixit | I5: SHRIMAN NARAYAN FIBER UDHOG PRIVATE LIMITED | K5: 44803 | L5: overdue | M5: invoice | N5: 1373 | O5: 2022-09-17 | P5: 23/MPPET/INV2926 | Q5: VANSH POLYPACK LLP | R5: 432229.03 | S5: 439509.63 | T5: Net 15 (Days) | U5: 09AARFV5599C1ZE | V5: 0.01 | W5: 0 | X5: Marketplace (Plastic Waste) | Y5: Marketplace (Plastic Waste) | Z5: HALIFAX GREENTECH LLP | AA5: =_xlfn.XLOOKUP(Z5,Q:Q,W:W) -> 0 | AE5: VERDE POLYSFY PRIVATE LIMITED | AF5: =SUMIFS(R:R,Q:Q,AE5) -> 0 | AH5: 2022-03-31 | AI5: overdue | AJ5: bill | AK5: 1542 | AL5: 2022-04-01 | AM5: 693004 | AN5: VRL Logistics Ltd | AO5: 1900 | AP5: 95000 | AQ5: 29AABCV3609C1ZJ | AR5: Marketplace (Plastic Waste) | AS5: Not Registered
H6: Ramesh G | I6: Sri Chakra Poly Plast India Private Limited | K6: 44803 | L6: overdue | M6: invoice | N6: 1373 | O6: 2022-09-17 | P6: 23/MPPET/INV2915 | Q6: VANSH POLYPACK LLP | R6: 422383.48 | S6: 431934.4 | T6: Net 15 (Days) | U6: 09AARFV5599C1ZE | V6: 0.01 | W6: 0 | X6: Marketplace (Plastic Waste) | Y6: Marketplace (Plastic Waste) | Z6: Shiva Texfabs Limited | AA6: =_xlfn.XLOOKUP(Z6,Q:Q,W:W) -> 0 | AE6: HALIFAX GREENTECH LLP | AF6: =SUMIFS(R:R,Q:Q,AE6) -> 3092029 | AH6: 2022-04-03 | AI6: overdue | AJ6: bill | AK6: 1539 | AL6: 2022-04-04 | AM6: 352 | AN6: SRIJA POLYMERS | AO6: 5224.59 | AP6: 818731.2 | AQ6: 36AMLPB6731C1ZD | AR6: Marketplace (Plastic Waste) | AS6: Not Registered
H7: Neelesh Dixit | I7: RPG Industrial Product Private Limited | K7: 44803 | L7: overdue | M7: invoice | N7: 1373 | O7: 2022-09-17 | P7: 23/MPPET/INV2928 | Q7: VANSH POLYPACK LLP | R7: 887115.6 | S7: 912981.2 | T7: Net 15 (Days) | U7: 09AARFV5599C1ZE | V7: 0.01 | W7: 0 | X7: Marketplace (Plastic Waste) | Y7: Marketplace (Plastic Waste) | Z7: Modestpet Pack Private Limited | AA7: =_xlfn.XLOOKUP(Z7,Q:Q,W:W) -> 0 | AE7: MLS INDUSTRIES | AF7: =SUMIFS(R:R,Q:Q,AE7) -> 0 | AH7: 2022-04-08 | AI7: overdue | AJ7: bill | AK7: 1533 | AL7: 2022-04-10 | AM7: 35 | AN7: Sri Balaji Plastic | AO7: 143337.33 | AP7: 955130.36 | AQ7: 36BDOPR6297L2ZF | AR7: Marketplace (Plastic Waste) | AS7: Not Registered
H8: Gitika | I8: SANDBERRY FIBRETECH PRIVATE LIMITED | K8: 44803 | L8: overdue | M8: invoice | N8: 1373 | O8: 2022-09-17 | P8: 23/MPPET/INV2925 | Q8: VANSH POLYPACK LLP | R8: 911233.24 | S8: 960984.4 | T8: Net 15 (Days) | U8: 09AARFV5599C1ZE | V8: 0.01 | W8: 0 | X8: Marketplace (Plastic Waste) | Y8: Marketplace (Plastic Waste) | Z8: Nextgen Fibres Private Limited | AA8: =_xlfn.XLOOKUP(Z8,Q:Q,W:W) -> 0 | AE8: EMINENT DEALERS PVT LTD | AF8: =SUMIFS(R:R,Q:Q,AE8) -> 0 | AH8: 2022-04-11 | AI8: overdue | AJ8: bill | AK8: 1531 | AL8: 2022-04-12 | AM8: 792 | AN8: S.K.ENTERPRISE | AO8: 3460.34 | AP8: 1039574.1 | AQ8: 19AJLPR9792C1ZG | AR8: Marketplace (Plastic Waste) | AS8: Not Registered
H9: Pushpraj | I9: RSWM LIMITED | K9: 44803 | L9: overdue | M9: invoice | N9: 1373 | O9: 2022-09-17 | P9: 23/MPPET/INV2933 | Q9: VANSH POLYPACK LLP | R9: 415681.7 | S9: 422478.5 | T9: Net 15 (Days) | U9: 09AARFV5599C1ZE | V9: 0.01 | W9: 0 | X9: Marketplace (Plastic Waste) | Y9: Marketplace (Plastic Waste) | Z9: KANCHAN INDIA LIMITED | AA9: =_xlfn.XLOOKUP(Z9,Q:Q,W:W) -> 0 | AE9: Nitika Polymer | AF9: =SUMIFS(R:R,Q:Q,AE9) -> 0 | AH9: 2022-04-12 | AI9: overdue | AJ9: bill | AK9: 1528 | AL9: 2022-04-15 | AM9: 36 | AN9: Sri Balaji Plastic | AO9: 137343.77 | AP9: 925120 | AQ9: 36BDOPR6297L2ZF | AR9: Marketplace (Plastic Waste) | AS9: Not Registered
H10: Neelesh Dixit | I10: Ganesha Ecosphere Limited (Unit-2) | K10: 44803 | L10: overdue | M10: invoice | N10: 1373 | O10: 2022-09-17 | P10: 23/MPPET/INV2929 | Q10: VANSH POLYPACK LLP | R10: 841243.12 | S10: 866596.6 | T10: Net 15 (Days) | U10: 09AARFV5599C1ZE | V10: 0.01 | W10: 0 | X10: Marketplace (Plastic Waste) | Y10: Marketplace (Plastic Waste) | Z10: Ganesha Ecotech Private Limited (Warangal) | AA10: =_xlfn.XLOOKUP(Z10,Q:Q,W:W) -> 0 | AE10: PUSHPANJALI ENTERPRISES | AF10: =SUMIFS(R:R,Q:Q,AE10) -> 0 | AH10: 2022-04-13 | AI10: overdue | AJ10: bill | AK10: 1527 | AL10: 2022-04-16 | AM10: 37 | AN10: Sri Balaji Plastic | AO10: 58178.26 | AP10: 381390.76 | AQ10: 36BDOPR6297L2ZF | AR10: Marketplace (Plastic Waste) | AS10: Not Registered
H11: Ramesh G | I11: Ganesha Ecotech Private Limited (Warangal) | K11: 44804 | L11: overdue | M11: invoice | N11: 1372 | O11: 2022-09-18 | P11: 23/MPPET/INV2940 | Q11: VANSH POLYPACK LLP | R11: 551705.62 | S11: 576646.1 | T11: Net 15 (Days) | U11: 09AARFV5599C1ZE | V11: 0.01 | W11: 0 | X11: Marketplace (Plastic Waste) | Y11: Marketplace (Plastic Waste) | Z11: DODHIA INDUSTRIES LIMITED | AA11: =_xlfn.XLOOKUP(Z11,Q:Q,W:W) -> 0 | AE11: M/S SHLOK AND SANS | AF11: =SUMIFS(R:R,Q:Q,AE11) -> 0 | AH11: 2022-04-14 | AI11: overdue | AJ11: bill | AK11: 1528 | AL11: 2022-04-15 | AM11: 3 | AN11: K.G.N ENTERPRISES | AO11: 60378.8 | AP11: 410746.2 | AQ11: 09BOUPS9047E1Z4 | AR11: Marketplace (Plastic Waste) | AS11: Not Registered
H12: Pushpraj | I12: KANCHAN INDIA LIMITED | K12: 44804 | L12: overdue | M12: invoice | N12: 1372 | O12: 2022-09-18 | P12: 23/MPPET/INV2932 | Q12: VANSH POLYPACK LLP | R12: 767912.08 | S12: 788665.74 | T12: Net 15 (Days) | U12: 09AARFV5599C1ZE | V12: 0.01 | W12: 0 | X12: Marketplace (Plastic Waste) | Y12: Marketplace (Plastic Waste) | Z12: NIRMAL FIBRES PRIVATE LIMITED | AA12: =_xlfn.XLOOKUP(Z12,Q:Q,W:W) -> 0 | AE12: A N Service Enterprises | AF12: =SUMIFS(R:R,Q:Q,AE12) -> 0 | AH12: 2022-04-17 | AI12: overdue | AJ12: bill | AK12: 1524 | AL12: 2022-04-19 | AM12: 38 | AN12: Sri Balaji Plastic | AO12: 113896.62 | AP12: 746655.62 | AQ12: 36BDOPR6297L2ZF | AR12: Marketplace (Plastic Waste) | AS12: Not Registered
H13: Gitika | I13: AEC PLAST PRIVATE LIMITED | K13: 44804 | L13: overdue | M13: invoice | N13: 1372 | O13: 2022-09-18 | P13: 23/MPPET/INV2938 | Q13: VANSH POLYPACK LLP | R13: 566640.42 | S13: 572459 | T13: Net 15 (Days) | U13: 09AARFV5599C1ZE | V13: 0.01 | W13: 0 | X13: Marketplace (Plastic Waste) | Y13: Marketplace (Plastic Waste) | Z13: J B ECOTEX LIMITED | AA13: =_xlfn.XLOOKUP(Z13,Q:Q,W:W) -> 50812.5 | AE13: SHREE SALASAR POLYFLEX (P) LTD. | AF13: =SUMIFS(R:R,Q:Q,AE13) -> 0 | AH13: 2022-04-18 | AI13: overdue | AJ13: bill | AK13: 1524 | AL13: 2022-04-19 | AM13: 802 | AN13: S.K.ENTERPRISE | AO13: 3115.14 | AP13: 944041.3 | AQ13: 19AJLPR9792C1ZG | AR13: Marketplace (Plastic Waste) | AS13: Not Registered
H14: Ramesh G | I14: SULOCHANA COTTON SPINNING MILLS (P)LTD | K14: 44804 | L14: overdue | M14: invoice | N14: 1371 | O14: 2022-09-19 | P14: 23/MPPET/INV2942 | Q14: VANSH POLYPACK LLP | R14: 793323.6 | S14: 813194.8 | T14: Net 15 (Days) | U14: 09AARFV5599C1ZE | V14: 0.01 | W14: 0 | X14: Marketplace (Plastic Waste) | Y14: Marketplace (Plastic Waste) | Z14: NATIONAL FIBRES PRIVATE LIMITED | AA14: =_xlfn.XLOOKUP(Z14,Q:Q,W:W) -> 0 | AE14: M/S PAL INDUSTRIES | AF14: =SUMIFS(R:R,Q:Q,AE14) -> 0 | AH14: 2022-04-19 | AI14: overdue | AJ14: bill | AK14: 1524 | AL14: 2022-04-19 | AM14: 1846 | AN14: KRS Road Transport Co | AO14: 1000 | AP14: 99000 | AQ14: 33AVAPR5377E1ZK | AR14: Marketplace (Plastic Waste) | AS14: Not Registered
H15: Pushpraj | I15: Prism Infratech Management Private Limited | K15: 44804 | L15: overdue | M15: invoice | N15: 1372 | O15: 2022-09-18 | P15: 23/MPPET/INV2950 | Q15: VANSH POLYPACK LLP | R15: 896761.4 | S15: 929825 | T15: Net 15 (Days) | U15: 09AARFV5599C1ZE | V15: 0.01 | W15: 0 | X15: Marketplace (Plastic Waste) | Y15: Marketplace (Plastic Waste) | Z15: RSWM LIMITED | AA15: =_xlfn.XLOOKUP(Z15,Q:Q,W:W) -> 0 | AE15: Jai Jeen Mata Trading Company | AF15: =SUMIFS(R:R,Q:Q,AE15) -> 0 | AH15: 2022-04-20 | AI15: overdue | AJ15: bill | AK15: 1523 | AL15: 2022-04-20 | AM15: 1854 | AN15: KRS Road Transport Co | AO15: 300 | AP15: 107800 | AQ15: 33AVAPR5377E1ZK | AR15: Marketplace (Plastic Waste) | AS15: Not Registered
H16: Ramesh G | I16: KUNDANA TECHNO TEX PRIVATE LIMITED | K16: 44804 | L16: overdue | M16: invoice | N16: 1371 | O16: 2022-09-19 | P16: 23/MPPET/INV2961 | Q16: VANSH POLYPACK LLP | R16: 948247.24 | S16: 982363.4 | T16: Net 15 (Days) | U16: 09AARFV5599C1ZE | V16: 0.01 | W16: 0 | X16: Marketplace (Plastic Waste) | Y16: Marketplace (Plastic Waste) | Z16: M/S ARIHANT INDUSTRIES | AA16: =_xlfn.XLOOKUP(Z16,Q:Q,W:W) -> 0 | AE16: Maa Durga Industries | AF16: =SUMIFS(R:R,Q:Q,AE16) -> 0 | AH16: 2022-04-20 | AI16: overdue | AJ16: bill | AK16: 1518 | AL16: 2022-04-25 | AM16: 804 | AN16: S.K.ENTERPRISE | AO16: 853.95 | AP16: 931503.8 | AQ16: 19AJLPR9792C1ZG | AR16: Marketplace (Plastic Waste) | AS16: Not Registered
H17: Gitika | I17: DODHIA SYNTHETICS LIMITED | K17: 44804 | L17: overdue | M17: invoice | N17: 1371 | O17: 2022-09-19 | P17: 23/MPPET/INV2963 | Q17: VANSH POLYPACK LLP | R17: 740490.62 | S17: 797415 | T17: Net 15 (Days) | U17: 09AARFV5599C1ZE | V17: 0.01 | W17: 0 | X17: Marketplace (Plastic Waste) | Y17: Marketplace (Plastic Waste) | Z17: M/S KASHI VISHWANATH TEXTILE MILL PRIVATE LIMITED | AA17: =_xlfn.XLOOKUP(Z17,Q:Q,W:W) -> 0 | AH17: 2022-04-22 | AI17: overdue | AJ17: bill | AK17: 1518 | AL17: 2022-04-25 | AM17: 2 | AN17: Sri Balaji Plastic | AO17: 133085.22 | AP17: 880185.6 | AQ17: 36BDOPR6297L2ZF | AR17: Marketplace (Plastic Waste) | AS17: Not Registered
H18: Shashank | I18: Nextgen Fibres Private Limited | K18: 44806 | L18: overdue | M18: invoice | N18: 1370 | O18: 2022-09-20 | P18: 23/MPPET/INV2995 | Q18: VANSH POLYPACK LLP | R18: 448748.36 | S18: 464829.4 | T18: Net 15 (Days) | U18: 09AARFV5599C1ZE | V18: 0.01 | W18: 0 | X18: Marketplace (Plastic Waste) | Y18: Marketplace (Plastic Waste) | Z18: IDVB RECYCLING OPERATIONS PRIVATE LIMITED | AA18: =_xlfn.XLOOKUP(Z18,Q:Q,W:W) -> 0 | AE18: DRS | AH18: 2022-04-23 | AI18: overdue | AJ18: bill | AK18: 1519 | AL18: 2022-04-24 | AM18: 4 | AN18: K.G.N ENTERPRISES | AO18: 52417.16 | AP18: 361419.25 | AQ18: 09BOUPS9047E1Z4 | AR18: Marketplace (Plastic Waste) | AS18: Not Registered
H19: Neelesh Dixit | I19: Silver Ecotex LLP | K19: 44806 | L19: overdue | M19: invoice | N19: 1370 | O19: 2022-09-20 | P19: 23/MPPET/INV3005 | Q19: VANSH POLYPACK LLP | R19: 717098.96 | S19: 755198.8 | T19: Net 15 (Days) | U19: 09AARFV5599C1ZE | V19: 0.01 | W19: 0 | X19: Marketplace (Plastic Waste) | Y19: Marketplace (Plastic Waste) | Z19: DIVYADHAN RECYCLING INDUSTRIES LIMITED | AA19: =_xlfn.XLOOKUP(Z19,Q:Q,W:W) -> 0 | AH19: 2022-04-23 | AI19: overdue | AJ19: bill | AK19: 1520 | AL19: 2022-04-23 | AM19: VTBILL-001 | AN19: Vinayaka Traders | AO19: 60411.6 | AP19: 396031.6 | AQ19: 36BEWPR9948M1Z0 | AR19: Marketplace (Plastic Waste) | AS19: Not Registered
H20: Neelesh Dixit | I20: RELIANCE INDUSTRIES LIMITED | K20: 44806 | L20: overdue | M20: invoice | N20: 1370 | O20: 2022-09-20 | P20: 23/MPPET/INV3003 | Q20: VANSH POLYPACK LLP | R20: 469104.4 | S20: 491754.5 | T20: Net 15 (Days) | U20: 09AARFV5599C1ZE | V20: 0.01 | W20: 0 | X20: Marketplace (Plastic Waste) | Y20: Marketplace (Plastic Waste) | Z20: CHIRIPAL POLY FILMS LIMITED | AA20: =_xlfn.XLOOKUP(Z20,Q:Q,W:W) -> 0 | AH20: 2022-04-24 | AI20: overdue | AJ20: bill | AK20: 1516 | AL20: 2022-04-27 | AM20: 3 | AN20: Sri Balaji Plastic | AO20: 134744.35 | AP20: 891062.26 | AQ20: 36BDOPR6297L2ZF | AR20: Marketplace (Plastic Waste) | AS20: Not Registered
H21: Gitika | I21: Alliance Fibres Limited | K21: 44807 | L21: overdue | M21: invoice | N21: 1369 | O21: 2022-09-21 | P21: 23/MPPET/INV3011 | Q21: VANSH POLYPACK LLP | R21: 682043.9 | S21: 707101.2 | T21: Net 15 (Days) | U21: 09AARFV5599C1ZE | V21: 0.01 | W21: 0 | X21: Marketplace (Plastic Waste) | Y21: Marketplace (Plastic Waste) | Z21: MAGPET POLYMERS PRIVATE LIMITED | AA21: =_xlfn.XLOOKUP(Z21,Q:Q,W:W) -> 0 | AH21: 2022-04-27 | AI21: overdue | AJ21: bill | AK21: 1515 | AL21: 2022-04-28 | AM21: 025/2022-23 | AN21: Bhawani Enterprises | AO21: 147090.88 | AP21: 970287.45 | AQ21: 07AYKPT7284P1Z8 | AR21: Marketplace (Plastic Waste) | AS21: Not Registered
H22: Shashank | I22: GUNJAN INDUSTRIES | K22: 44807 | L22: overdue | M22: invoice | N22: 1369 | O22: 2022-09-21 | P22: 23/MPPET/INV3025 | Q22: VANSH POLYPACK LLP | R22: 895443.14 | S22: 917977.6 | T22: Net 15 (Days) | U22: 09AARFV5599C1ZE | V22: 0.01 | W22: 0 | X22: Marketplace (Plastic Waste) | Y22: Marketplace (Plastic Waste) | Z22: HITARTH ENTERPRISES | AA22: =_xlfn.XLOOKUP(Z22,Q:Q,W:W) -> 0 | AH22: 2022-04-28 | AI22: overdue | AJ22: bill | AK22: 1515 | AL22: 2022-04-28 | AM22: VTBILL-002 | AN22: Vinayaka Traders | AO22: 62622 | AP22: 410522 | AQ22: 36BEWPR9948M1Z0 | AR22: Marketplace (Plastic Waste) | AS22: Not Registered
H23: Gitika | I23: BADRI COTSYN LIMITED | K23: 44807 | L23: overdue | M23: invoice | N23: 1369 | O23: 2022-09-21 | P23: 23/MPPET/INV3015 | Q23: VANSH POLYPACK LLP | R23: 847298.16 | S23: 871025.6 | T23: Net 15 (Days) | U23: 09AARFV5599C1ZE | V23: 0.01 | W23: 0 | X23: Marketplace (Plastic Waste) | Y23: Marketplace (Plastic Waste) | Z23: RPG INDUSTRIAL PRODUCT PRIVATE LIMITED | AA23: =_xlfn.XLOOKUP(Z23,Q:Q,W:W) -> 0 | AH23: 2022-04-29 | AI23: overdue | AJ23: bill | AK23: 1514 | AL23: 2022-04-29 | AM23: JBRL-108 | AN23: Jai Bhawani Roadlines | AO23: 520 | AP23: 58240 | AQ23: 29CYPPS8892B1ZH | AR23: Marketplace (Plastic Waste) | AS23: Micro
H24: Neelesh Dixit | I24: SHRI MAN NARAYAN POLYTAX PVT LTD | K24: 44807 | L24: overdue | M24: invoice | N24: 1369 | O24: 2022-09-21 | P24: 23/MPPET/INV3026 | Q24: VANSH POLYPACK LLP | R24: 774181.6 | S24: 787185.2 | T24: Net 15 (Days) | U24: 09AARFV5599C1ZE | V24: 0.01 | W24: 0 | X24: Marketplace (Plastic Waste) | Y24: Marketplace (Plastic Waste) | Z24: BLUEOCEAN ECOTECH LIMITED | AA24: =_xlfn.XLOOKUP(Z24,Q:Q,W:W) -> 0 | AH24: 2022-04-29 | AI24: overdue | AJ24: bill | AK24: 1514 | AL24: 2022-04-29 | AM24: JBRL -109 | AN24: Jai Bhawani Roadlines | AO24: 520 | AP24: 58240 | AQ24: 29CYPPS8892B1ZH | AR24: Marketplace (Plastic Waste) | AS24: Micro
H25: Pushpraj | I25: MAHALAKSHMI SPINTEX PRIVATE LIMITED | K25: 44808 | L25: overdue | M25: invoice | N25: 1368 | O25: 2022-09-22 | P25: 23/MPPET/INV3047 | Q25: VANSH POLYPACK LLP | R25: 501193.39 | S25: 507243.25 | T25: Net 15 (Days) | U25: 09AARFV5599C1ZE | V25: 0.01 | W25: 0 | X25: Marketplace (Plastic Waste) | Y25: Marketplace (Plastic Waste) | Z25: AVI GLOBAL PLAST PRIVATE LIMITED | AA25: =_xlfn.XLOOKUP(Z25,Q:Q,W:W) -> 0 | AH25: 2022-04-29 | AI25: overdue | AJ25: bill | AK25: 1511 | AL25: 2022-05-02 | AM25: 39 | AN25: Sri Balaji Plastic | AO25: 124328.49 | AP25: 822778.6 | AQ25: 36BDOPR6297L2ZF | AR25: Marketplace (Plastic Waste) | AS25: Not Registered
H26: Neelesh Dixit | I26: PASHUPATI EXCRUSION PRIVATE LIMITED | K26: 44808 | L26: overdue | M26: invoice | N26: 1368 | O26: 2022-09-22 | P26: 23/MPPET/INV3050 | Q26: VANSH POLYPACK LLP | R26: 841957.92 | S26: 861741.8 | T26: Net 15 (Days) | U26: 09AARFV5599C1ZE | V26: 0.01 | W26: 0 | X26: Marketplace (Plastic Waste) | Y26: Marketplace (Plastic Waste) | Z26: JAINARAIN FABTECH LIMITED | AA26: =_xlfn.XLOOKUP(Z26,Q:Q,W:W) -> 0 | AH26: 2022-05-03 | AI26: overdue | AJ26: bill | AK26: 1507 | AL26: 2022-05-06 | AM26: 40 | AN26: Sri Balaji Plastic | AO26: 126916.57 | AP26: 837353.8 | AQ26: 36BDOPR6297L2ZF | AR26: Marketplace (Plastic Waste) | AS26: Not Registered
H27: Shashank | I27: BHAGYAVARDHAN POLYFLAKES PRIVATE LIMITED | K27: 44808 | L27: overdue | M27: invoice | N27: 1368 | O27: 2022-09-22 | P27: 23/MPPET/INV3049 | Q27: VANSH POLYPACK LLP | R27: 430261.8 | S27: 435383 | T27: Net 15 (Days) | U27: 09AARFV5599C1ZE | V27: 0.01 | W27: 0 | X27: Marketplace (Plastic Waste) | Y27: Marketplace (Plastic Waste) | Z27: AMAANI POLYFLAKES | AA27: =_xlfn.XLOOKUP(Z27,Q:Q,W:W) -> 0 | AH27: 2022-05-04 | AI27: overdue | AJ27: bill | AK27: 1508 | AL27: 2022-05-05 | AM27: MLE/22-23/017 | AN27: MAHALAKSHMI ENTERPRISES | AO27: 45.8 | AP27: 237014.8 | AQ27: 36AARFM8215E1Z3 | AR27: Marketplace (Plastic Waste) | AS27: Not Registered
H28: Neelesh Dixit | I28: M/S ARIHANT INDUSTRIES | K28: 44808 | L28: overdue | M28: invoice | N28: 1368 | O28: 2022-09-22 | P28: 23/MPPET/INV3056 | Q28: VANSH POLYPACK LLP | R28: 739013.3 | S28: 764920.2 | T28: Net 15 (Days) | U28: 09AARFV5599C1ZE | V28: 0.01 | W28: 0 | X28: Marketplace (Plastic Waste) | Y28: Marketplace (Plastic Waste) | Z28: SHRI MAN NARAYAN POLYTAX PVT LTD | AA28: =_xlfn.XLOOKUP(Z28,Q:Q,W:W) -> 0 | AH28: 2022-05-06 | AI28: overdue | AJ28: bill | AK28: 1504 | AL28: 2022-05-09 | AM28: 41 | AN28: Sri Balaji Plastic | AO28: 137856.6 | AP28: 902960.6 | AQ28: 36BDOPR6297L2ZF | AR28: Marketplace (Plastic Waste) | AS28: Not Registered
H29: Neelesh Dixit | I29: RUNGTA GREENTECH LIMITED | K29: 44809 | L29: overdue | M29: invoice | N29: 1367 | O29: 2022-09-23 | P29: 23/MPPET/INV3068 | Q29: VANSH POLYPACK LLP | R29: 795067.76 | S29: 832238.35 | T29: Net 15 (Days) | U29: 09AARFV5599C1ZE | V29: 0.01 | W29: 0 | X29: Marketplace (Plastic Waste) | Y29: Marketplace (Plastic Waste) | Z29: KUNDANA TECHNO TEX PRIVATE LIMITED | AA29: =_xlfn.XLOOKUP(Z29,Q:Q,W:W) -> 697117.64 | AH29: 2022-05-10 | AI29: overdue | AJ29: bill | AK29: 1503 | AL29: 2022-05-10 | AM29: QT2021TP27757 | AN29: Quick Digital Technologies Private Limited | AO29: 231 | AP29: 107000 | AQ29: 06AAACQ3830D1ZW | AR29: Marketplace (Plastic Waste) | AS29: Not Registered
H30: Gitika | I30: TAPADIA POLYESTERS PRIVATE LIMITED | K30: 44810 | L30: overdue | M30: invoice | N30: 1366 | O30: 2022-09-24 | P30: 23/MPPET/INV3087 | Q30: VANSH POLYPACK LLP | R30: 505840.48 | S30: 511887.98 | T30: Net 15 (Days) | U30: 09AARFV5599C1ZE | V30: 0.01 | W30: 0 | X30: Marketplace (Plastic Waste) | Y30: Marketplace (Plastic Waste) | Z30: Apex International | AA30: =_xlfn.XLOOKUP(Z30,Q:Q,W:W) -> 0 | AH30: 2022-05-10 | AI30: overdue | AJ30: bill | AK30: 1500 | AL30: 2022-05-13 | AM30: 42 | AN30: Sri Balaji Plastic | AO30: 135751.5 | AP30: 889172.5 | AQ30: 36BDOPR6297L2ZF | AR30: Marketplace (Plastic Waste) | AS30: Not Registered
... H36: Ramesh G | I36: MANJUSHREE TECHNOPACK LIMITED | K36: 44814 | L36: overdue | M36: invoice | N36: 1362 | O36: 2022-09-28 | P36: 23/MPPET/INV3196 | Q36: VANSH POLYPACK LLP | R36: 493203.4 | S36: 518449.5 | T36: Net 15 (Days) | U36: 09AARFV5599C1ZE | V36: 0.01 | W36: 0 | X36: Marketplace (Plastic Waste) | Y36: Marketplace (Plastic Waste) | Z36: ALLIANCE FIBRES PRIVATE LIMITED | AA36: =_xlfn.XLOOKUP(Z36,Q:Q,W:W) -> 28702.49 | AH36: 2022-05-14 | AI36: overdue | AJ36: bill | AK36: 1497 | AL36: 2022-05-16 | AM36: 44 | AN36: Sri Balaji Plastic | AO36: 131911.52 | AP36: 869818.8 | AQ36: 36BDOPR6297L2ZF | AR36: Marketplace (Plastic Waste) | AS36: Not Registered
H37: Gitika | I37: Amaani Polyflakes | K37: 44814 | L37: overdue | M37: invoice | N37: 1362 | O37: 2022-09-28 | P37: 23/MPPET/INV3189 | Q37: VANSH POLYPACK LLP | R37: 332821.83 | S37: 334950.55 | T37: Net 15 (Days) | U37: 09AARFV5599C1ZE | V37: 0.01 | W37: 0 | X37: Marketplace (Plastic Waste) | Y37: Marketplace (Plastic Waste) | Z37: 0 | AH37: 2022-05-14 | AI37: overdue | AJ37: bill | AK37: 1499 | AL37: 2022-05-14 | AM37: QT2021TP27020 | AN37: Quick Digital Technologies Private Limited | AO37: 1020 | AP37: 51000 | AQ37: 06AAACQ3830D1ZW | AR37: Marketplace (Plastic Waste) | AS37: Not Registered
H38: Ramesh G | I38: J B ECOTEX LIMITED | K38: 44815 | L38: overdue | M38: invoice | N38: 1361 | O38: 2022-09-29 | P38: 23/MPPET/INV3235 | Q38: VANSH POLYPACK LLP | R38: 425607.8 | S38: 442806.3 | T38: Net 15 (Days) | U38: 09AARFV5599C1ZE | V38: 0.01 | W38: 0 | X38: Marketplace (Plastic Waste) | Y38: Marketplace (Plastic Waste) | AH38: 2022-05-14 | AI38: overdue | AJ38: bill | AK38: 1499 | AL38: 2022-05-14 | AM38: 1926 | AN38: KRS Road Transport Co | AO38: 1400 | AP38: 140000 | AQ38: 33AVAPR5377E1ZK | AR38: Marketplace (Plastic Waste) | AS38: Not Registered
H39: Shashank | I39: GOPAL PLASTIC | K39: 44815 | L39: overdue | M39: invoice | N39: 1360 | O39: 2022-09-30 | P39: 23/MPPET/INV3239 | Q39: VANSH POLYPACK LLP | R39: 390669.22 | S39: 409461.9 | T39: Net 15 (Days) | U39: 09AARFV5599C1ZE | V39: 0.01 | W39: 0 | X39: Marketplace (Plastic Waste) | Y39: Marketplace (Plastic Waste) | AH39: 2022-05-15 | AI39: overdue | AJ39: bill | AK39: 1498 | AL39: 2022-05-15 | AM39: 15 | AN39: SURYA TRADINGS | AO39: 138358.8 | AP39: 907018.8 | AQ39: 32CXBPP5021J1ZP | AR39: Marketplace (Plastic Waste) | AS39: Not Registered
H40: Gitika | I40: SAHEB FIBRE PRIVATE LIMITED | K40: 44815 | L40: overdue | M40: invoice | N40: 1361 | O40: 2022-09-29 | P40: 23/MPPET/INV3240 | Q40: VANSH POLYPACK LLP | R40: 317917.91 | S40: 324360.85 | T40: Net 15 (Days) | U40: 09AARFV5599C1ZE | V40: 0.01 | W40: 0 | X40: Marketplace (Plastic Waste) | Y40: Marketplace (Plastic Waste) | AH40: 2022-05-18 | AI40: overdue | AJ40: bill | AK40: 1495 | AL40: 2022-05-18 | AM40: JBRL-112 | AN40: Jai Bhawani Roadlines | AO40: 1064 | AP40: 106400 | AQ40: 29CYPPS8892B1ZH | AR40: Marketplace (Plastic Waste) | AS40: Micro
H41: Shashank | I41: GOKUL PLASTIC | K41: 44830 | L41: overdue | M41: invoice | N41: 1345 | O41: 2022-10-15 | P41: 23/MPPET/INV3618 | Q41: VANSH POLYPACK LLP | R41: 1134943 | S41: 1141433 | T41: Net 15 (Days) | U41: 09AARFV5599C1ZE | V41: 0.01 | W41: 0 | X41: Marketplace (Plastic Waste) | Y41: Marketplace (Plastic Waste) | AH41: 2022-05-18 | AI41: overdue | AJ41: bill | AK41: 1495 | AL41: 2022-05-18 | AM41: 016 | AN41: SURYA TRADINGS | AO41: 70315.56 | AP41: 460957.56 | AQ41: 32CXBPP5021J1ZP | AR41: Marketplace (Plastic Waste) | AS41: Not Registered
H42: Ramesh G | I42: SHREE RENGA POLYESTER PRIVATE LIMITED | K42: 44862 | L42: overdue | M42: invoice | N42: 1313 | O42: 2022-11-16 | P42: 23/MPPET/INV4163 | Q42: INDIA POLYMERS | R42: 227636.96 | S42: 502863.4 | T42: Immediate | U42: 02AAGFI0380M1ZI | V42: 0.01 | W42: 0 | X42: Marketplace (Plastic Waste) | Y42: Marketplace (Plastic Waste) | AH42: 2022-05-19 | AI42: overdue | AJ42: bill | AK42: 1494 | AL42: 2022-05-19 | AM42: 1930 | AN42: KRS Road Transport Co | AO42: 1200 | AP42: 120000 | AQ42: 33AVAPR5377E1ZK | AR42: Marketplace (Plastic Waste) | AS42: Not Registered
H43: Ramesh G | I43: RECRAFT PROCESSING PRIVATE LIMITED | K43: 44862 | L43: overdue | M43: invoice | N43: 1313 | O43: 2022-11-16 | P43: 23/MPPET/INV4166 | Q43: INDIA POLYMERS | R43: 571628.1 | S43: 573846.5 | T43: Immediate | U43: 02AAGFI0380M1ZI | V43: 0.01 | W43: 0 | X43: Marketplace (Plastic Waste) | Y43: Marketplace (Plastic Waste) | AH43: 2022-05-20 | AI43: overdue | AJ43: bill | AK43: 1493 | AL43: 2022-05-20 | AM43: 017 | AN43: SURYA TRADINGS | AO43: 78494.4 | AP43: 514574.4 | AQ43: 32CXBPP5021J1ZP | AR43: Marketplace (Plastic Waste) | AS43: Not Registered
H44: Neelesh Dixit | I44: Apex International | K44: 44863 | L44: overdue | M44: invoice | N44: 1312 | O44: 2022-11-17 | P44: 23/MPPET/INV4176 | Q44: INDIA POLYMERS | R44: 445923.6 | S44: 450702.6 | T44: Immediate | U44: 02AAGFI0380M1ZI | V44: 0.01 | W44: 0 | X44: Marketplace (Plastic Waste) | Y44: Marketplace (Plastic Waste) | AH44: 2022-05-23 | AI44: overdue | AJ44: bill | AK44: 1490 | AL44: 2022-05-23 | AM44: 1937 | AN44: KRS Road Transport Co | AO44: 1700 | AP44: 170000 | AQ44: 33AVAPR5377E1ZK | AR44: Marketplace (Plastic Waste) | AS44: Not Registered
H45: Pankaj | I45: ELITE INDUSTRIES | K45: 44864 | L45: overdue | M45: invoice | N45: 1311 | O45: 2022-11-18 | P45: 23/MPPET/INV4197 | Q45: INDIA POLYMERS | R45: 526157.1 | S45: 532063 | T45: Immediate | U45: 02AAGFI0380M1ZI | V45: 0.01 | W45: 0 | X45: Marketplace (Plastic Waste) | Y45: Marketplace (Plastic Waste) | AH45: 2022-05-23 | AI45: overdue | AJ45: bill | AK45: 1490 | AL45: 2022-05-23 | AM45: 1938 | AN45: KRS Road Transport Co | AO45: 1310 | AP45: 131000 | AQ45: 33AVAPR5377E1ZK | AR45: Marketplace (Plastic Waste) | AS45: Not Registered
H46: Shashank | I46: SAMRUDDHI INDUSTRIES | K46: 44864 | L46: overdue | M46: invoice | N46: 1311 | O46: 2022-11-18 | P46: 23/MPPET/INV4202 | Q46: INDIA POLYMERS | R46: 604244.8 | S46: 604244.8 | T46: Immediate | U46: 02AAGFI0380M1ZI | V46: 0.01 | W46: 0 | X46: Marketplace (Plastic Waste) | Y46: Marketplace (Plastic Waste) | AH46: 2022-05-24 | AI46: overdue | AJ46: bill | AK46: 1489 | AL46: 2022-05-24 | AM46: 1940 | AN46: KRS Road Transport Co | AO46: 57 | AP46: 5663 | AQ46: 33AVAPR5377E1ZK | AR46: Marketplace (Plastic Waste) | AS46: Not Registered
H47: Shashank | I47: SAARK INDUSTRIES | K47: 44865 | L47: overdue | M47: invoice | N47: 1310 | O47: 2022-11-19 | P47: 23/MPPET/INV4212 | Q47: INDIA POLYMERS | R47: 562430.8 | S47: 562430.8 | T47: Immediate | U47: 02AAGFI0380M1ZI | V47: 0.01 | W47: 0 | X47: Marketplace (Plastic Waste) | Y47: Marketplace (Plastic Waste) | AH47: 2022-05-24 | AI47: overdue | AJ47: bill | AK47: 1489 | AL47: 2022-05-24 | AM47: 1939 | AN47: KRS Road Transport Co | AO47: 68 | AP47: 6783 | AQ47: 33AVAPR5377E1ZK | AR47: Marketplace (Plastic Waste) | AS47: Not Registered
H48: Ramesh G | I48: JB RPET INDUSTRIES PRIVATE LIMITED | K48: 44866 | L48: overdue | M48: invoice | N48: 1309 | O48: 2022-11-20 | P48: 23/MPPET/INV4221 | Q48: INDIA POLYMERS | R48: 427087.5 | S48: 429353.1 | T48: Immediate | U48: 02AAGFI0380M1ZI | V48: 0.01 | W48: 0 | X48: Marketplace (Plastic Waste) | Y48: Marketplace (Plastic Waste) | AH48: 2022-05-25 | AI48: overdue | AJ48: bill | AK48: 1488 | AL48: 2022-05-25 | AM48: 299 | AN48: Mahaveer Roadlines | AO48: 1060 | AP48: 106000 | AQ48: 08AMSPC8506F1ZX | AR48: Marketplace (Plastic Waste) | AS48: Micro
H49: Shashank | I49: SWACHH POLYMERS | K49: 44866 | L49: overdue | M49: invoice | N49: 1309 | O49: 2022-11-20 | P49: 23/MPPET/INV4230 | Q49: INDIA POLYMERS | R49: 477472.5 | S49: 487514.3 | T49: Immediate | U49: 02AAGFI0380M1ZI | V49: 0.01 | W49: 0 | X49: Marketplace (Plastic Waste) | Y49: Marketplace (Plastic Waste) | AH49: 2022-05-28 | AI49: overdue | AJ49: bill | AK49: 1485 | AL49: 2022-05-28 | AM49: A13 | AN49: AS Scraps | AO49: 102982.24 | AP49: 890428 | AQ49: 32BJYPA9497H2ZI | AR49: Marketplace (Plastic Waste) | AS49: Not Registered
... H59: Neelesh Dixit | I59: JAINARAIN FABTECH LIMITED | K59: 44869 | L59: overdue | M59: invoice | N59: 1306 | O59: 2022-11-23 | P59: 23/MPPET/INV4320 | Q59: INDIA POLYMERS | R59: 480766.6 | S59: 483539.6 | T59: Immediate | U59: 02AAGFI0380M1ZI | V59: 0.01 | W59: 0 | X59: Marketplace (Plastic Waste) | Y59: Marketplace (Plastic Waste) | AH59: 2022-06-07 | AI59: overdue | AJ59: bill | AK59: 1475 | AL59: 2022-06-07 | AM59: 17 | AN59: AS Scraps | AO59: 77463 | AP59: 507813 | AQ59: 32BJYPA9497H2ZI | AR59: Marketplace (Plastic Waste) | AS59: Not Registered
K60: 44869 | L60: overdue | M60: invoice | N60: 1307 | O60: 2022-11-22 | P60: 23/MPPET/INV4329 | Q60: INDIA POLYMERS | R60: 485328.4 | S60: 490378.8 | T60: Immediate | U60: 02AAGFI0380M1ZI | V60: 0.01 | W60: 0 | X60: Marketplace (Plastic Waste) | Y60: Marketplace (Plastic Waste) | AH60: 2022-06-10 | AI60: overdue | AJ60: bill | AK60: 1472 | AL60: 2022-06-10 | AM60: 5766 | AN60: Vikajit Logistics | AO60: 850 | AP60: 85000 | AR60: Marketplace (Plastic Waste) | AS60: Not Registered
K61: 44869 | L61: overdue | M61: invoice | N61: 1307 | O61: 2022-11-22 | P61: 23/MPPET/INV4334 | Q61: INDIA POLYMERS | R61: 572588.85 | S61: 575450.35 | T61: Immediate | U61: 02AAGFI0380M1ZI | V61: 0.01 | W61: 0 | X61: Marketplace (Plastic Waste) | Y61: Marketplace (Plastic Waste) | AH61: 2022-06-11 | AI61: overdue | AJ61: bill | AK61: 1471 | AL61: 2022-06-11 | AM61: 19 | AN61: AS Scraps | AO61: 79578.4 | AP61: 554707.85 | AQ61: 32BJYPA9497H2ZI | AR61: Marketplace (Plastic Waste) | AS61: Not Registered
K62: 44870 | L62: overdue | M62: invoice | N62: 1306 | O62: 2022-11-23 | P62: 23/MPPET/INV4344 | Q62: INDIA POLYMERS | R62: 583414.6 | S62: 589485.7 | T62: Immediate | U62: 02AAGFI0380M1ZI | V62: 0.01 | W62: 0 | X62: Marketplace (Plastic Waste) | Y62: Marketplace (Plastic Waste) | AH62: 2022-06-12 | AI62: overdue | AJ62: bill | AK62: 1470 | AL62: 2022-06-12 | AM62: 20 | AN62: AS Scraps | AO62: 84059.78 | AP62: 550591.53 | AQ62: 32BJYPA9497H2ZI | AR62: Marketplace (Plastic Waste) | AS62: Not Registered
K63: 44870 | L63: overdue | M63: invoice | N63: 1306 | O63: 2022-11-23 | P63: 23/MPPET/INV4338 | Q63: INDIA POLYMERS | R63: 472713.9 | S63: 472713.9 | T63: Immediate | U63: 02AAGFI0380M1ZI | V63: 0.01 | W63: 0 | X63: Marketplace (Plastic Waste) | Y63: Marketplace (Plastic Waste) | AH63: 2022-06-17 | AI63: overdue | AJ63: bill | AK63: 1465 | AL63: 2022-06-17 | AM63: 23 | AN63: Royal Traders | AO63: 501 | AP63: 591293.87 | AQ63: 09AUYPK3390H1ZX | AR63: Marketplace (Plastic Waste) | AS63: Not Registered
K64: 44870 | L64: overdue | M64: invoice | N64: 1306 | O64: 2022-11-23 | P64: 23/MPPET/INV4347 | Q64: INDIA POLYMERS | R64: 748628.1 | S64: 751123.8 | T64: Immediate | U64: 02AAGFI0380M1ZI | V64: 0.01 | W64: 0 | X64: Marketplace (Plastic Waste) | Y64: Marketplace (Plastic Waste) | AH64: 2022-06-17 | AI64: overdue | AJ64: bill | AK64: 1465 | AL64: 2022-06-17 | AM64: 20 | AN64: SURYA TRADINGS | AO64: 118848.36 | AP64: 780416.6 | AQ64: 32CXBPP5021J1ZP | AR64: Marketplace (Plastic Waste) | AS64: Not Registered
K65: 44870 | L65: overdue | M65: invoice | N65: 1306 | O65: 2022-11-23 | P65: 23/MPPET/INV4356 | Q65: INDIA POLYMERS | R65: 501464.1 | S65: 501464.1 | T65: Immediate | U65: 02AAGFI0380M1ZI | V65: 0.01 | W65: 0 | X65: Marketplace (Plastic Waste) | Y65: Marketplace (Plastic Waste) | AH65: 2022-06-20 | AI65: overdue | AJ65: bill | AK65: 1462 | AL65: 2022-06-20 | AM65: 2125 | AN65: Jay Shree Salsar Road Lines | AO65: 595 | AP65: 58905 | AQ65: 21CPCPP6789Q1Z0 | AR65: Marketplace (Plastic Waste) | AS65: Not Registered
K66: 44870 | L66: overdue | M66: invoice | N66: 1306 | O66: 2022-11-23 | P66: 23/MPPET/INV4360 | Q66: INDIA POLYMERS | R66: 633187.8 | S66: 637483 | T66: Immediate | U66: 02AAGFI0380M1ZI | V66: 0.01 | W66: 0 | X66: Marketplace (Plastic Waste) | Y66: Marketplace (Plastic Waste) | AH66: 2022-06-22 | AI66: overdue | AJ66: bill | AK66: 1460 | AL66: 2022-06-22 | AM66: 21 | AN66: SURYA TRADINGS | AO66: 128251.4 | AP66: 894676 | AQ66: 32CXBPP5021J1ZP | AR66: Marketplace (Plastic Waste) | AS66: Not Registered
K67: 44870 | L67: overdue | M67: invoice | N67: 1306 | O67: 2022-11-23 | P67: 23/MPPET/INV4367 | Q67: INDIA POLYMERS | R67: 508453.8 | S67: 511840.4 | T67: Immediate | U67: 02AAGFI0380M1ZI | V67: 0.01 | W67: 0 | X67: Marketplace (Plastic Waste) | Y67: Marketplace (Plastic Waste) | AH67: 2022-06-25 | AI67: overdue | AJ67: bill | AK67: 1456 | AL67: 2022-06-26 | AM67: 017 | AN67: K-NO-W WASTE | AO67: 49999.11 | AP67: 419554.9 | AQ67: 15ABUPE6315K1ZF | AR67: Marketplace (Plastic Waste) | AS67: Not Registered
K68: 44871 | L68: overdue | M68: invoice | N68: 1305 | O68: 2022-11-24 | P68: 23/MPPET/INV4386 | Q68: INDIA POLYMERS | R68: 408880.8 | S68: 412184.8 | T68: Immediate | U68: 02AAGFI0380M1ZI | V68: 0.01 | W68: 0 | X68: Marketplace (Plastic Waste) | Y68: Marketplace (Plastic Waste) | AH68: 2022-06-26 | AI68: overdue | AJ68: bill | AK68: 1456 | AL68: 2022-06-26 | AM68: 22 | AN68: SURYA TRADINGS | AO68: 129838.5 | AP68: 851163.5 | AQ68: 32CXBPP5021J1ZP | AR68: Marketplace (Plastic Waste) | AS68: Not Registered
K69: 44871 | L69: overdue | M69: invoice | N69: 1305 | O69: 2022-11-24 | P69: 23/MPPET/INV4385 | Q69: INDIA POLYMERS | R69: 495050.75 | S69: 498396.05 | T69: Immediate | U69: 02AAGFI0380M1ZI | V69: 0.01 | W69: 0 | X69: Marketplace (Plastic Waste) | Y69: Marketplace (Plastic Waste) | AH69: 2022-06-28 | AI69: overdue | AJ69: bill | AK69: 1454 | AL69: 2022-06-28 | AM69: 23 | AN69: SURYA TRADINGS | AO69: 77821.56 | AP69: 510163.56 | AQ69: 32CXBPP5021J1ZP | AR69: Marketplace (Plastic Waste) | AS69: Not Registered
K70: 44872 | L70: overdue | M70: invoice | N70: 1304 | O70: 2022-11-25 | P70: 23/MPPET/INV4398 | Q70: INDIA POLYMERS | R70: 710487.2 | S70: 729921.8 | T70: Immediate | U70: 02AAGFI0380M1ZI | V70: 0.01 | W70: 0 | X70: Marketplace (Plastic Waste) | Y70: Marketplace (Plastic Waste) | AH70: 2022-06-29 | AI70: overdue | AJ70: bill | AK70: 1453 | AL70: 2022-06-29 | AM70: SSR-PET-06-22-03 | AN70: S S RECLAIMERS | AO70: 862 | AP70: 1301091.6 | AQ70: 37ADKFS3802K1ZS | AR70: Marketplace (Plastic Waste) | AS70: Micro
K71: 44874 | L71: overdue | M71: invoice | N71: 1302 | O71: 2022-11-27 | P71: 23/MPPET/INV4426 | Q71: INDIA POLYMERS | R71: 587472.9 | S71: 594493.9 | T71: Immediate | U71: 02AAGFI0380M1ZI | V71: 0.01 | W71: 0 | X71: Marketplace (Plastic Waste) | Y71: Marketplace (Plastic Waste) | AH71: 2022-07-01 | AI71: overdue | AJ71: bill | AK71: 1451 | AL71: 2022-07-01 | AM71: SRI -PET-06-22-02 | AN71: Sreshta Recycling Industries | AO71: 7339.12 | AP71: 1328178.5 | AQ71: 37EHYPP5556D1ZK | AR71: Marketplace (Plastic Waste) | AS71: Micro
K72: 44874 | L72: overdue | M72: invoice | N72: 1302 | O72: 2022-11-27 | P72: 23/MPPET/INV4428 | Q72: INDIA POLYMERS | R72: 506578.5 | S72: 506578.5 | T72: Immediate | U72: 02AAGFI0380M1ZI | V72: 0.01 | W72: 0 | X72: Marketplace (Plastic Waste) | Y72: Marketplace (Plastic Waste) | AH72: 2022-07-01 | AI72: overdue | AJ72: bill | AK72: 1451 | AL72: 2022-07-01 | AM72: 1866 | AN72: KRS Road Transport Co | AO72: 1200 | AP72: 120000 | AQ72: 33AVAPR5377E1ZK | AR72: Marketplace (Plastic Waste) | AS72: Not Registered
... K89: 44898 | L89: overdue | M89: invoice | N89: 1278 | O89: 2022-12-21 | P89: 23/MPPET/INV4790 | Q89: INDIA POLYMERS | R89: 534489.9 | S89: 534489.9 | T89: Immediate | U89: 02AAGFI0380M1ZI | V89: 0.01 | W89: 0 | X89: Marketplace (Plastic Waste) | Y89: Marketplace (Plastic Waste) | AH89: 2022-07-13 | AI89: overdue | AJ89: bill | AK89: 1439 | AL89: 2022-07-13 | AM89: RT001/22 | AN89: Sri Sakthi Transport | AO89: 255 | AP89: 25500 | AQ89: 29AKYPC3424G2ZX | AR89: Marketplace (Plastic Waste) | AS89: Not Registered
K90: 44903 | L90: overdue | M90: invoice | N90: 1273 | O90: 2022-12-26 | P90: 23/MPPET/INV4832 | Q90: INDIA POLYMERS | R90: 422071.4 | S90: 422071.4 | T90: Immediate | U90: 02AAGFI0380M1ZI | V90: 0.01 | W90: 0 | X90: Marketplace (Plastic Waste) | Y90: Marketplace (Plastic Waste) | AH90: 2022-07-14 | AI90: overdue | AJ90: bill | AK90: 1438 | AL90: 2022-07-14 | AM90: 103 | AN90: Fast Logistics | AO90: 1000 | AP90: 18000 | AR90: Marketplace (Plastic Waste) | AS90: Not Registered
K91: 44903 | L91: overdue | M91: invoice | N91: 1273 | O91: 2022-12-26 | P91: 23/MPPET/INV4831 | Q91: INDIA POLYMERS | R91: 354271.5 | S91: 360614 | T91: Immediate | U91: 02AAGFI0380M1ZI | V91: 0.01 | W91: 0 | X91: Marketplace (Plastic Waste) | Y91: Marketplace (Plastic Waste) | AH91: 2022-07-17 | AI91: overdue | AJ91: bill | AK91: 1434 | AL91: 2022-07-18 | AM91: 31 | AN91: SURYA TRADINGS | AO91: 95268.77 | AP91: 674612.2 | AQ91: 32CXBPP5021J1ZP | AR91: Marketplace (Plastic Waste) | AS91: Not Registered
K92: 44906 | L92: overdue | M92: invoice | N92: 1270 | O92: 2022-12-29 | P92: 23/MPPET/INV4855 | Q92: INDIA POLYMERS | R92: 523510.8 | S92: 523510.8 | T92: Immediate | U92: 02AAGFI0380M1ZI | V92: 0.01 | W92: 0 | X92: Marketplace (Plastic Waste) | Y92: Marketplace (Plastic Waste) | AH92: 2022-07-20 | AI92: overdue | AJ92: bill | AK92: 1429 | AL92: 2022-07-23 | AM92: 136 | AN92: A G TRADERS | AO92: 515 | AP92: 607618.87 | AQ92: 36KVPPS7164K1ZE | AR92: Marketplace (Plastic Waste) | AS92: Not Registered
K93: 45010 | L93: overdue | M93: invoice | N93: 1171 | O93: 2023-04-07 | P93: 23/MPPET/INV6265 | Q93: HALIFAX GREENTECH LLP | R93: 128249.43 | S93: 803697.13 | T93: Net 15 (Days) | U93: 24AAKFH9080R1ZK | V93: 0.01 | W93: 0 | X93: Marketplace (Plastic Waste) | Y93: Marketplace (Plastic Waste) | AH93: 2022-07-21 | AI93: overdue | AJ93: bill | AK93: 1431 | AL93: 2022-07-21 | AM93: 407 | AN93: Gandhi Roadways | AO93: 630 | AP93: 63000 | AR93: Marketplace (Plastic Waste) | AS93: Not Registered
K94: 45011 | L94: overdue | M94: invoice | N94: 1170 | O94: 2023-04-08 | P94: 23/MPPET/INV6271 | Q94: HALIFAX GREENTECH LLP | R94: 794693.25 | S94: 804915 | T94: Net 15 (Days) | U94: 24AAKFH9080R1ZK | V94: 0.01 | W94: 0 | X94: Marketplace (Plastic Waste) | Y94: Marketplace (Plastic Waste) | AH94: 2022-07-21 | AI94: overdue | AJ94: bill | AK94: 1430 | AL94: 2022-07-22 | AM94: 446 | AN94: Gandhi Roadways | AO94: 700 | AP94: 70000 | AR94: Marketplace (Plastic Waste) | AS94: Not Registered
K95: 45011 | L95: overdue | M95: invoice | N95: 1170 | O95: 2023-04-08 | P95: 23/MPPET/INV6276 | Q95: HALIFAX GREENTECH LLP | R95: 777285 | S95: 787202.9 | T95: Net 15 (Days) | U95: 24AAKFH9080R1ZK | V95: 0.01 | W95: 0 | X95: Marketplace (Plastic Waste) | Y95: Marketplace (Plastic Waste) | AH95: 2022-07-22 | AI95: overdue | AJ95: bill | AK95: 1430 | AL95: 2022-07-22 | AM95: JBRL-102 | AN95: Jai Bhawani Roadlines | AO95: 1540 | AP95: 56000 | AQ95: 29CYPPS8892B1ZH | AR95: Marketplace (Plastic Waste) | AS95: Micro
K96: 45012 | L96: overdue | M96: invoice | N96: 1169 | O96: 2023-04-09 | P96: 23/MPPET/INV6283 | Q96: HALIFAX GREENTECH LLP | R96: 685057.5 | S96: 687491.25 | T96: Net 15 (Days) | U96: 24AAKFH9080R1ZK | V96: 0.01 | W96: 0 | X96: Marketplace (Plastic Waste) | Y96: Marketplace (Plastic Waste) | AH96: 2022-07-22 | AI96: overdue | AJ96: bill | AK96: 1429 | AL96: 2022-07-23 | AM96: 113 | AN96: D.D.ENTERPRISES | AO96: 305 | AP96: 360336.6 | AQ96: 09CIBPS2261N1ZT | AR96: Marketplace (Plastic Waste) | AS96: Micro
K97: 45012 | L97: overdue | M97: invoice | N97: 1169 | O97: 2023-04-09 | P97: 23/MPPET/INV6282 | Q97: HALIFAX GREENTECH LLP | R97: 706743.87 | S97: 713315 | T97: Net 15 (Days) | U97: 24AAKFH9080R1ZK | V97: 0.01 | W97: 0 | X97: Marketplace (Plastic Waste) | Y97: Marketplace (Plastic Waste) | AH97: 2022-07-22 | AI97: overdue | AJ97: bill | AK97: 1429 | AL97: 2022-07-23 | AM97: 32 | AN97: SURYA TRADINGS | AO97: 55392.92 | AP97: 399919.95 | AQ97: 32CXBPP5021J1ZP | AR97: Marketplace (Plastic Waste) | AS97: Not Registered
K98: 45064 | L98: overdue | M98: debit_note | N98: 1130 | O98: 2023-05-18 | P98: 24/MPPET/DN0004 | Q98: INDIA POLYMERS | R98: 2120 | S98: 2120 | T98: Immediate | U98: 02AAGFI0380M1ZI | V98: 0.01 | W98: 0 | X98: Marketplace (Plastic Waste) | Y98: Marketplace (Plastic Waste) | AH98: 2022-07-26 | AI98: overdue | AJ98: bill | AK98: 1425 | AL98: 2022-07-27 | AM98: 15 | AN98: Capital Polymers | AO98: 299 | AP98: 363822.35 | AQ98: 23AUFPK8549M1Z4 | AR98: Marketplace (Plastic Waste) | AS98: Not Registered
K99: 45106 | L99: overdue | M99: invoice | N99: 1082 | O99: 2023-07-05 | P99: 24/MPPET/INV0937 | Q99: Shiva Texfabs Limited | R99: 151902.59 | S99: 422074.2 | T99: Net 6 (Days) | U99: 03AACCS0279A1ZZ | V99: 3000000 | W99: 0 | X99: Marketplace (Plastic Waste) | Y99: Marketplace (Plastic Waste) | AH99: 2022-07-26 | AI99: overdue | AJ99: bill | AK99: 1426 | AL99: 2022-07-26 | AM99: 16005 | AN99: NEW SHALIMAR ROADWAYS | AO99: 10920 | AP99: 100100 | AQ99: 23AAIFN0748A2ZR | AR99: Marketplace (Plastic Waste) | AS99: Small
K100: 45112 | L100: overdue | M100: invoice | N100: 1076 | O100: 2023-07-11 | P100: 24/MPPET/INV1008 | Q100: Shiva Texfabs Limited | R100: 750763.2 | S100: 770917.6 | T100: Net 6 (Days) | U100: 03AACCS0279A1ZZ | V100: 3000000 | W100: 0 | X100: Marketplace (Plastic Waste) | Y100: Marketplace (Plastic Waste) | AH100: 2022-07-27 | AI100: overdue | AJ100: bill | AK100: 1425 | AL100: 2022-07-27 | AM100: XPCC2182/03/2022 | AN100: Instant Supply Chain Solutions Private Limited | AO100: 4186 | AP100: 99330 | AQ100: 06AAFCI4823D1ZW | AR100: Marketplace (Plastic Waste) | AS100: Medium
K101: 45112 | L101: overdue | M101: invoice | N101: 1076 | O101: 2023-07-11 | P101: 24/MPPET/INV1015 | Q101: Shiva Texfabs Limited | R101: 468212.2 | S101: 472536.9 | T101: Net 6 (Days) | U101: 03AACCS0279A1ZZ | V101: 3000000 | W101: 0 | X101: Marketplace (Plastic Waste) | Y101: Marketplace (Plastic Waste) | AH101: 2022-07-27 | AI101: overdue | AJ101: bill | AK101: 1422 | AL101: 2022-07-30 | AM101: 29 | AN101: Sri Kanakadurga Industries | AO101: 105230 | AP101: 743990 | AQ101: 37ATSPN4497P1ZC | AR101: Marketplace (Plastic Waste) | AS101: Not Registered
K102: 45119 | L102: overdue | M102: invoice | N102: 1069 | O102: 2023-07-18 | P102: 24/MPPET/INV1084 | Q102: Shiva Texfabs Limited | R102: 22420 | S102: 476472.2 | T102: Net 6 (Days) | U102: 03AACCS0279A1ZZ | V102: 3000000 | W102: 0 | X102: Marketplace (Plastic Waste) | Y102: Marketplace (Plastic Waste) | AH102: 2022-07-29 | AI102: overdue | AJ102: bill | AK102: 1423 | AL102: 2022-07-29 | AM102: MTC/2022-23/047 | AN102: Manisha Trading Company | AO102: 820 | AP102: 967222.4 | AQ102: 08AGWPS8576K1Z1 | AR102: Marketplace (Plastic Waste) | AS102: Not Registered
K103: 45121 | L103: overdue | M103: invoice | N103: 1067 | O103: 2023-07-20 | P103: 24/MPPET/INV1095 | Q103: Shiva Texfabs Limited | R103: 647985.2 | S103: 649814.2 | T103: Net 6 (Days) | U103: 03AACCS0279A1ZZ | V103: 3000000 | W103: 0 | X103: Marketplace (Plastic Waste) | Y103: Marketplace (Plastic Waste) | AH103: 2022-07-29 | AI103: overdue | AJ103: bill | AK103: 1421 | AL103: 2022-07-31 | AM103: 6/22-23 | AN103: Shree Krishna Metal | AO103: 57866.4 | AP103: 379346.4 | AQ103: 21AAPPU2800B1Z6 | AR103: Marketplace (Plastic Waste) | AS103: Not Registered
K104: 45124 | L104: overdue | M104: invoice | N104: 1064 | O104: 2023-07-23 | P104: 24/MPPET/INV1121 | Q104: Shiva Texfabs Limited | R104: 857352.6 | S104: 866969.6 | T104: Net 6 (Days) | U104: 03AACCS0279A1ZZ | V104: 3000000 | W104: 0 | X104: Marketplace (Plastic Waste) | Y104: Marketplace (Plastic Waste) | AH104: 2022-07-30 | AI104: overdue | AJ104: bill | AK104: 1420 | AL104: 2022-08-01 | AM104: 1962 | AN104: New India Roadways | AO104: 8843 | AP104: 8843 | AQ104: 07JGAPK6274B1ZG | AR104: Marketplace (Plastic Waste) | AS104: Not Registered
K105: 45153 | L105: overdue | M105: invoice | N105: 1027 | O105: 2023-08-29 | P105: 24/MPPET/INV1250 | Q105: Modestpet Pack Private Limited | R105: 302399.36 | S105: 1330257.5 | T105: Net 45 (Days) | U105: 27AAPCM1780R1ZJ | V105: 2000000 | W105: 0 | X105: Marketplace (Plastic Waste) | Y105: Marketplace (Plastic Waste) | AH105: 2022-07-30 | AI105: overdue | AJ105: bill | AK105: 1420 | AL105: 2022-08-01 | AM105: 1987 | AN105: New India Roadways | AO105: 5678 | AP105: 5678 | AQ105: 07JGAPK6274B1ZG | AR105: Marketplace (Plastic Waste) | AS105: Not Registered
K106: 45155 | L106: overdue | M106: invoice | N106: 1021 | O106: 2023-09-04 | P106: 24/MPPET/INV1255 | Q106: INDIA POLYMERS | R106: 899301.6 | S106: 971659.2 | T106: Immediate | U106: 02AAGFI0380M1ZI | V106: 0.01 | W106: 0 | X106: Marketplace (Plastic Waste) | Y106: Marketplace (Plastic Waste) | AH106: 2022-07-30 | AI106: overdue | AJ106: bill | AK106: 1420 | AL106: 2022-08-01 | AM106: 1967 | AN106: New India Roadways | AO106: 7564 | AP106: 7564 | AQ106: 07JGAPK6274B1ZG | AR106: Marketplace (Plastic Waste) | AS106: Not Registered
... K135: 45994 | L135: overdue | M135: invoice | N135: 181 | O135: 2025-12-22 | P135: 26/MPPET/INV1545 | Q135: RSWM LIMITED | R135: 9440.08 | S135: 953491.74 | T135: Net 10 (Days) | U135: 08AAACR9700M1Z3 | V135: 15000000 | W135: 0 | X135: Marketplace (Plastic Waste) | Y135: Marketplace Sales (Plastic) | AH135: 2022-10-31 | AI135: overdue | AJ135: bill | AK135: 1329 | AL135: 2022-10-31 | AM135: KMEC/1155 | AN135: M/S K.M.ENGINEERING & CONSTRUCTION | AO135: 64531.8 | AP135: 423041.8 | AQ135: 21BBLPM2205G2Z5 | AR135: Marketplace (Plastic Waste) | AS135: Not Registered
K136: 45999 | L136: overdue | M136: invoice | N136: 176 | O136: 2025-12-27 | P136: 26/MPPET/INV1575 | Q136: RSWM LIMITED | R136: 6706.06 | S136: 675807.05 | T136: Net 10 (Days) | U136: 08AAACR9700M1Z3 | V136: 15000000 | W136: 0 | X136: Marketplace (Plastic Waste) | Y136: Marketplace Sales (Plastic) | AH136: 2022-10-31 | AI136: overdue | AJ136: bill | AK136: 1329 | AL136: 2022-10-31 | AM136: 5746 | AN136: Vikajit Logistics | AO136: 610 | AP136: 61000 | AR136: Marketplace (Plastic Waste) | AS136: Not Registered
K137: 46001 | L137: overdue | M137: invoice | N137: 170 | O137: 2026-01-02 | P137: 26/MPPET/INV1593 | Q137: M/S KASHI VISHWANATH TEXTILE MILL PRIVATE LIMITED | R137: 68973.16 | S137: 733743.8 | T137: Net 30 (Days) | U137: 05AABCS5269H1ZA | V137: 10000000 | W137: 0 | X137: Marketplace (Plastic Waste) | Y137: Marketplace Sales (Plastic) | AH137: 2022-10-31 | AI137: overdue | AJ137: bill | AK137: 1329 | AL137: 2022-10-31 | AM137: 5733 | AN137: Vikajit Logistics | AO137: 660 | AP137: 66000 | AR137: Marketplace (Plastic Waste) | AS137: Not Registered
K138: 46012 | L138: overdue | M138: invoice | N138: 168 | O138: 2026-01-04 | P138: 26/MPPET/INV1702 | Q138: IDVB RECYCLING OPERATIONS PRIVATE LIMITED | R138: 2412.42 | S138: 249062.4 | T138: Net 30 (Days) | U138: 21AAGCI6765F1ZM | V138: 20000000 | W138: 0 | X138: Marketplace (Plastic Waste) | Y138: Marketplace Sales (Plastic) | AH138: 2022-10-31 | AI138: overdue | AJ138: bill | AK138: 1329 | AL138: 2022-10-31 | AM138: 5742 | AN138: Vikajit Logistics | AO138: 610 | AP138: 61000 | AR138: Marketplace (Plastic Waste) | AS138: Not Registered
K139: 46013 | L139: overdue | M139: invoice | N139: 162 | O139: 2026-01-10 | P139: 26/MPPET/INV1711 | Q139: RSWM LIMITED | R139: 4442.22 | S139: 448456.3 | T139: Net 10 (Days) | U139: 08AAACR9700M1Z3 | V139: 15000000 | W139: 0 | X139: Marketplace (Plastic Waste) | Y139: Marketplace Sales (Plastic) | AH139: 2022-11-03 | AI139: overdue | AJ139: bill | AK139: 1322 | AL139: 2022-11-07 | AM139: 180 | AN139: Mahalakshmi Enterprises (PET) | AO139: 89733.73 | AP139: 734436.72 | AQ139: 36AYJPD7638L1ZY | AR139: Marketplace (Plastic Waste) | AS139: Micro
K140: 46015 | L140: overdue | M140: invoice | N140: 159 | O140: 2026-01-13 | P140: 26/MPPET/INV1724 | Q140: DIVYADHAN RECYCLING INDUSTRIES LIMITED | R140: 24159.43 | S140: 1457807.4 | T140: Net 30 (Days) | U140: 02AADCD4621Q1ZO | V140: 10000000 | W140: 0 | X140: Marketplace (Plastic Waste) | Y140: Marketplace Sales (Plastic) | AH140: 2022-11-08 | AI140: overdue | AJ140: bill | AK140: 1319 | AL140: 2022-11-10 | AM140: 4876 | AN140: New India Roadways | AO140: 9063 | AP140: 9063 | AQ140: 07JGAPK6274B1ZG | AR140: Marketplace (Plastic Waste) | AS140: Not Registered
K141: 46015 | L141: overdue | M141: invoice | N141: 165 | O141: 2026-01-07 | P141: 26/MPPET/INV1727 | Q141: IDVB RECYCLING OPERATIONS PRIVATE LIMITED | R141: 270.25 | S141: 121706.6 | T141: Net 30 (Days) | U141: 21AAGCI6765F1ZM | V141: 20000000 | W141: 0 | X141: Marketplace (Plastic Waste) | Y141: Marketplace Sales (Plastic) | AH141: 2022-11-08 | AI141: overdue | AJ141: bill | AK141: 1319 | AL141: 2022-11-10 | AM141: 4881 | AN141: New India Roadways | AO141: 6103 | AP141: 6103 | AQ141: 07JGAPK6274B1ZG | AR141: Marketplace (Plastic Waste) | AS141: Not Registered
K142: 46016 | L142: overdue | M142: invoice | N142: 159 | O142: 2026-01-13 | P142: 26/MPPET/INV1739 | Q142: CHIRIPAL POLY FILMS LIMITED | R142: 8205.6 | S142: 835356.6 | T142: Net 15 (Days) | U142: 01AADCC7403M1ZX | V142: 30000000 | W142: 0 | X142: Marketplace (Plastic Waste) | Y142: Marketplace Sales (Plastic) | AH142: 2022-11-24 | AI142: overdue | AJ142: bill | AK142: 1304 | AL142: 2022-11-25 | AM142: 5288 | AN142: New India Roadways | AO142: 6670 | AP142: 6670 | AQ142: 07JGAPK6274B1ZG | AR142: Marketplace (Plastic Waste) | AS142: Not Registered
K143: 46016 | L143: overdue | M143: invoice | N143: 159 | O143: 2026-01-13 | P143: 26/MPPET/INV1735 | Q143: CHIRIPAL POLY FILMS LIMITED | R143: 8152.2 | S143: 823343.2 | T143: Net 15 (Days) | U143: 01AADCC7403M1ZX | V143: 30000000 | W143: 0 | X143: Marketplace (Plastic Waste) | Y143: Marketplace Sales (Plastic) | AH143: 2022-11-24 | AI143: overdue | AJ143: bill | AK143: 1304 | AL143: 2022-11-25 | AM143: 5274 | AN143: New India Roadways | AO143: 3841 | AP143: 3841 | AQ143: 07JGAPK6274B1ZG | AR143: Marketplace (Plastic Waste) | AS143: Not Registered
K144: 46017 | L144: overdue | M144: invoice | N144: 163 | O144: 2026-01-09 | P144: 26/MPPET/INV1748 | Q144: IDVB RECYCLING OPERATIONS PRIVATE LIMITED | R144: 1820.63 | S144: 182011.6 | T144: Net 30 (Days) | U144: 21AAGCI6765F1ZM | V144: 20000000 | W144: 0 | X144: Marketplace (Plastic Waste) | Y144: Marketplace Sales (Plastic) | AH144: 2022-11-24 | AI144: overdue | AJ144: bill | AK144: 1304 | AL144: 2022-11-25 | AM144: 5271 | AN144: New India Roadways | AO144: 10182 | AP144: 10182 | AQ144: 07JGAPK6274B1ZG | AR144: Marketplace (Plastic Waste) | AS144: Not Registered
K145: 46021 | L145: overdue | M145: invoice | N145: 154 | O145: 2026-01-18 | P145: 26/MPPET/INV1773 | Q145: CHIRIPAL POLY FILMS LIMITED | R145: 8351.8 | S145: 843508.8 | T145: Net 15 (Days) | U145: 01AADCC7403M1ZX | V145: 30000000 | W145: 0 | X145: Marketplace (Plastic Waste) | Y145: Marketplace Sales (Plastic) | AH145: 2022-12-08 | AI145: overdue | AJ145: bill | AK145: 1291 | AL145: 2022-12-08 | AM145: MN.22.035 | AN145: MOTHER NATURE WASTE MANAGEMENT AND RECYCLING INDUSTRY | AO145: 37220.44 | AP145: 453804.4 | AQ145: 29ABTFM3326P1ZD | AR145: Marketplace (Plastic Waste) | AS145: Micro
K146: 46022 | L146: overdue | M146: invoice | N146: 158 | O146: 2026-01-14 | P146: 26/MPPET/INV1775 | Q146: IDVB RECYCLING OPERATIONS PRIVATE LIMITED | R146: 1365.8 | S146: 127188.6 | T146: Net 30 (Days) | U146: 21AAGCI6765F1ZM | V146: 20000000 | W146: 0 | X146: Marketplace (Plastic Waste) | Y146: Marketplace Sales (Plastic) | AH146: 2022-12-10 | AI146: overdue | AJ146: bill | AK146: 1287 | AL146: 2022-12-12 | AM146: 321 | AN146: S S Speed Logistics | AO146: 5400 | AP146: 49950 | AQ146: 08BSXPK0990F1Z7 | AR146: Marketplace (Plastic Waste) | AS146: Not Registered
K147: 46019 | L147: overdue | M147: invoice | N147: 146 | O147: 2026-01-26 | P147: 26/MPPET/INV1762 | Q147: NIRMAL FIBRES PRIVATE LIMITED | R147: 100670.6 | S147: 752084.8 | T147: Net 30 (Days) | U147: 09AABCN0376N1Z4 | V147: 30000000 | W147: 0 | X147: Marketplace (Plastic Waste) | Y147: Marketplace Sales (Plastic) | AH147: 2022-12-10 | AI147: overdue | AJ147: bill | AK147: 1287 | AL147: 2022-12-12 | AM147: DEC01 | AN147: Bilaspur Plastic | AO147: 69365.44 | AP147: 544719.27 | AQ147: 22AQAPA1867H1ZD | AR147: Marketplace (Plastic Waste) | AS147: Not Registered
K148: 46026 | L148: overdue | M148: invoice | N148: 149 | O148: 2026-01-23 | P148: 26/MPPET/INV1812 | Q148: CHIRIPAL POLY FILMS LIMITED | R148: 7951.6 | S148: 803177.6 | T148: Net 15 (Days) | U148: 01AADCC7403M1ZX | V148: 30000000 | W148: 0 | X148: Marketplace (Plastic Waste) | Y148: Marketplace Sales (Plastic) | AH148: 2022-12-22 | AI148: overdue | AJ148: bill | AK148: 1273 | AL148: 2022-12-26 | AM148: 3A | AN148: K-NO-W WASTE | AO148: 4741.43 | AP148: 99569.93 | AQ148: 15ABUPE6315K1ZF | AR148: Marketplace (Plastic Waste) | AS148: Not Registered
K149: 46027 | L149: overdue | M149: invoice | N149: 148 | O149: 2026-01-24 | P149: 26/MPPET/INV1815 | Q149: CHIRIPAL POLY FILMS LIMITED | R149: 7692.8 | S149: 777005.8 | T149: Net 15 (Days) | U149: 01AADCC7403M1ZX | V149: 30000000 | W149: 0 | X149: Marketplace (Plastic Waste) | Y149: Marketplace Sales (Plastic) | AH149: 2022-12-23 | AI149: overdue | AJ149: bill | AK149: 1276 | AL149: 2022-12-23 | AM149: 344 | AN149: YAKUB ENTERPRISES | AO149: 119427.22 | AP149: 805420.8 | AQ149: 29CHSPK9882K1Z2 | AR149: Marketplace (Plastic Waste) | AS149: Not Registered
K150: 46028 | L150: overdue | M150: invoice | N150: 147 | O150: 2026-01-25 | P150: 26/MPPET/INV1825 | Q150: CHIRIPAL POLY FILMS LIMITED | R150: 16676 | S150: 845225 | T150: Net 15 (Days) | U150: 01AADCC7403M1ZX | V150: 30000000 | W150: 0 | X150: Marketplace (Plastic Waste) | Y150: Marketplace Sales (Plastic) | AH150: 2022-12-27 | AI150: overdue | AJ150: bill | AK150: 1268 | AL150: 2022-12-31 | AM150: 68 | AN150: NATURE FRIENDLY PLASTIC | AO150: 58921.14 | AP150: 456111.3 | AQ150: 21ALDPL6775F1Z6 | AR150: Marketplace (Plastic Waste) | AS150: Micro
... K158: 46043 | L158: overdue | M158: invoice | N158: 132 | O158: 2026-02-09 | P158: 26/MPPET/INV1979 | Q158: CHIRIPAL POLY FILMS LIMITED | R158: 16945.2 | S158: 885555.2 | T158: Net 15 (Days) | U158: 01AADCC7403M1ZX | V158: 30000000 | W158: 0 | X158: Marketplace (Plastic Waste) | Y158: Marketplace Sales (Plastic) | AH158: 2023-01-20 | AI158: overdue | AJ158: bill | AK158: 1248 | AL158: 2023-01-20 | AM158: 7423 | AN158: New India Roadways | AO158: 5316 | AP158: 5316 | AQ158: 07JGAPK6274B1ZG | AR158: Marketplace (Plastic Waste) | AS158: Not Registered
K159: 46050 | L159: overdue | M159: invoice | N159: 130 | O159: 2026-02-11 | P159: 26/MPPET/INV2026 | Q159: MAGPET POLYMERS PRIVATE LIMITED | R159: 31279.54 | S159: 666652.8 | U159: 19AAICS7344C1Z8 | V159: 5000000 | W159: 0 | X159: Marketplace (Plastic Waste) | Y159: Marketplace Sales (Plastic) | AH159: 2023-01-21 | AI159: overdue | AJ159: bill | AK159: 1247 | AL159: 2023-01-21 | AM159: 7533 | AN159: New India Roadways | AO159: 7930 | AP159: 7930 | AQ159: 07JGAPK6274B1ZG | AR159: Marketplace (Plastic Waste) | AS159: Not Registered
K160: 46051 | L160: overdue | M160: invoice | N160: 124 | O160: 2026-02-17 | P160: 26/MPPET/INV2036 | Q160: HITARTH ENTERPRISES | R160: 415998.21 | S160: 429924.3 | T160: Net 30 (Days) | U160: 23AAPFH5775E1Z6 | V160: 8000000 | W160: 0 | X160: Marketplace (Plastic Waste) | Y160: Marketplace Sales (Plastic) | AH160: 2023-02-01 | AI160: overdue | AJ160: bill | AK160: 1236 | AL160: 2023-02-01 | AM160: 258 | AN160: Road King Transport And Contractor | AO160: 5916 | AP160: 54230 | AQ160: 07ABBFR9279E1ZV | AR160: Marketplace (Plastic Waste) | AS160: Not Registered
K161: 46052 | L161: overdue | M161: invoice | N161: 123 | O161: 2026-02-18 | P161: 26/MPPET/INV2043 | Q161: HITARTH ENTERPRISES | R161: 540645.69 | S161: 569239.4 | T161: Net 30 (Days) | U161: 23AAPFH5775E1Z6 | V161: 8000000 | W161: 0 | X161: Marketplace (Plastic Waste) | Y161: Marketplace Sales (Plastic) | AH161: 2023-02-07 | AI161: overdue | AJ161: bill | AK161: 1229 | AL161: 2023-02-08 | AM161: 350 | AN161: S S Speed Logistics | AO161: 9600 | AP161: 88800 | AQ161: 08BSXPK0990F1Z7 | AR161: Marketplace (Plastic Waste) | AS161: Not Registered
K162: 46052 | L162: overdue | M162: invoice | N162: 123 | O162: 2026-02-18 | P162: 26/MPPET/INV2048 | Q162: HITARTH ENTERPRISES | R162: 360507.2 | S162: 360507.2 | T162: Net 30 (Days) | U162: 23AAPFH5775E1Z6 | V162: 8000000 | W162: 0 | X162: Marketplace (Plastic Waste) | Y162: Marketplace Sales (Plastic) | AH162: 2023-02-07 | AI162: overdue | AJ162: bill | AK162: 1226 | AL162: 2023-02-11 | AM162: INV-199 | AN162: Eartth Resource Management | AO162: 43233.28 | AP162: 664425.56 | AQ162: 36AAIFE7936R1ZJ | AR162: Marketplace (Plastic Waste) | AS162: Micro
K163: 46052 | L163: overdue | M163: invoice | N163: 118 | O163: 2026-02-23 | P163: 26/MPPET/INV2045 | Q163: RPG INDUSTRIAL PRODUCT PRIVATE LIMITED | R163: 350000 | S163: 550986.7 | T163: Net 30 (Days) | U163: 09AABCR6248K2ZY | V163: 30000000 | W163: 0 | X163: Marketplace (Plastic Waste) | Y163: Marketplace Sales (Plastic) | AH163: 2023-02-08 | AI163: overdue | AJ163: bill | AK163: 1225 | AL163: 2023-02-12 | AM163: 413 | AN163: SRIJA POLYMERS | AO163: 94641.57 | AP163: 663965.8 | AQ163: 36AMLPB6731C1ZD | AR163: Marketplace (Plastic Waste) | AS163: Not Registered
K164: 46055 | L164: overdue | M164: invoice | N164: 109 | O164: 2026-03-04 | P164: 26/MPPET/INV2078 | Q164: BLUEOCEAN ECOTECH LIMITED | R164: 689488.85 | S164: 775560.9 | T164: Net 30 (Days) | U164: 23AAICB1747Q1ZC | V164: 40000000 | W164: 0 | X164: Marketplace (Plastic Waste) | Y164: Marketplace Sales (Plastic) | AH164: 2023-02-09 | AI164: overdue | AJ164: bill | AK164: 1228 | AL164: 2023-02-09 | AM164: 370 | AN164: S S Speed Logistics | AO164: 9600 | AP164: 88800 | AQ164: 08BSXPK0990F1Z7 | AR164: Marketplace (Plastic Waste) | AS164: Not Registered
K165: 46055 | L165: overdue | M165: invoice | N165: 120 | O165: 2026-02-21 | P165: 26/MPPET/INV2074 | Q165: HITARTH ENTERPRISES | R165: 680175.78 | S165: 697167.6 | T165: Net 30 (Days) | U165: 23AAPFH5775E1Z6 | V165: 8000000 | W165: 0 | X165: Marketplace (Plastic Waste) | Y165: Marketplace Sales (Plastic) | AH165: 2023-02-09 | AI165: overdue | AJ165: bill | AK165: 1228 | AL165: 2023-02-09 | AM165: SR/22-23/292 | AN165: Spark Riser | AO165: 5632.8 | AP165: 58476.2 | AQ165: 33CHNPR6823G1Z1 | AR165: Marketplace (Plastic Waste) | AS165: Not Registered
...

Sheet Last year's
D2: JV Number | E2: Particulars | F2: Amount | J2: JV Number | K2: Particulars | L2: Amount
E3: Marketplace DN, CN and Expense Provisions | 31-03-2026 | F3: 309308 | K3: Marketplace DN, CN and Expense Provisions | 31-03-2026 | L3: 315777.91
E4: Accounted in FY 2026-27 | F4: =F30 -> 718187.35 | K4: Accounted in FY 26-27 | L4: ='Last year''s'!L30 -> 729139.49
E5: NO DN value | K5: NO DN value | L5: 0
F6: =F3-F4-F5 -> -408879.35 | K6: Closing Provision | L6: =L3-L4-L5 -> -413361.58
B8: Debit note Pertaining to FY 2025-26 | H8: Credit note Pertaining to FY 25-26 | N8: FY 24-25 Logistic Bills accounted Fy 26-27
B9: SO Number | C9: Debit Note Date | D9: Debit Note Number | E9: Vendor Name | F9: SubTotal | H9: SO Number | I9: Credit Note Date | J9: Credit Note Number | K9: Customer Name | L9: CN Amount | N9: Bill Date | O9: Bill Number | P9: PurchaseOrder | Q9: Vendor Name | R9: Amount
B10: SH032607013 | C10: 46119 | D10: 36/PET/27VC00001 | E10: GURU KURPA PLAST | F10: 19722.02 | H10: SH032607013 | I10: 46119 | J10: 36/PET/27CN00001 | K10: J B ECOTEX LIMITED | L10: 20336.85
B11: SH02262807 | C11: 46119 | D11: 36/PET/27VC00002 | E11: GURU KURPA PLAST | F11: 27379.81 | H11: SH02262807 | I11: 46119 | J11: 36/PET/27CN00002 | K11: J B ECOTEX LIMITED | L11: 28163.76
B12: SH022617046 | C12: 46129 | D12: 36/PET/27VC00003 | E12: AH ENTERPRISES | F12: 55181.5 | H12: SH022617046 | I12: 46129 | J12: 36/PET/27CN00003 | K12: RPG INDUSTRIAL PRODUCT PRIVATE LIMITED | L12: 55700
B13: SH02260309 | C13: 46129 | D13: 36/PET/27VC00005 | E13: SUPER DISPOSABLE TRADING | F13: 145008.55 | H13: SH02260309 | I13: 46129 | J13: 36/PET/27CN00005 | K13: AIRSON POLY INDUSTRIES | L13: 145183.64
B14: SH022605019 | C14: 46129 | D14: 36/PET/27VC00006 | E14: SUPER DISPOSABLE TRADING | F14: 134999.9 | H14: SH022605019 | I14: 46129 | J14: 36/PET/27CN00006 | K14: AIRSON POLY INDUSTRIES | L14: 134999.9
B15: SH022602029 | C15: 46129 | D15: 36/PET/27VC00004 | E15: SUPER DISPOSABLE TRADING | F15: 60093.33 | H15: SH022602029 | I15: 46129 | J15: 36/PET/27CN00004 | K15: AIRSON POLY INDUSTRIES | L15: 60268.04
B16: SH022609011 | C16: 46129 | D16: 36/PET/27VC00007 | E16: Ceekay Green Care Agencies | F16: 241988.16 | H16: SH022609011 | I16: 46129 | J16: 36/PET/27CN00007 | K16: RAKSHITAM ECOFIBRE PRIVATE LIMITED | L16: 249550.3
B17: SH012631015 | C17: 46129 | D17: 36/PET/27VC00008 | E17: SALIM PLASTIC | F17: 53904 | H17: SH012631015 | I17: 46129 | J17: 36/PET/27CN00008 | K17: ALLIANCE FIBRES PRIVATE LIMITED | L17: 55027
B18: SH012631015 | C18: 46189 | D18: P00049/25-26 | E18: SALIM PLASTIC | F18: -20089.92 | H18: SH012631015 | I18: 46189 | J18: 36/PET/27DN00005 | K18: ALLIANCE FIBRES PRIVATE LIMITED | L18: -20090
B30: G.Total | F30: =SUBTOTAL(9,F10:F29) -> 718187.35 | H30: G.Total | L30: =SUM(L10:L29) -> 729139.49
N31: G.Total | R31: =SUM(R10:R30) -> 0
L35: =L30-F30-R31 -> 10952.14

Sheet Revenue - Reco
C4: Sales - Reconciliation | F4: Purchases - Reconciliation | I4: Logistic Cost- Reconciliation
C5: Particulars | D5: Amount | F5: Particulars | G5: Amount | I5: Particulars | J5: Amount
C6: Net Revenue as per MIS Report | D6: =Details!AY21 -> 3586523.5 | F6: Net Purchases as per MIS Report | G6: =Details!O21 -> 2170328.6 | I6: Net Logistic as per MIS Report | J6: =Details!AC21 -> 0
C7: Credit Notes issued in FY-25 pertaining to FY-24 | D7: =Details!AY25 -> -729139.49 | F7: Debit Notes issued in FY-25 pertaining to FY-24 | G7: =-Details!O26 -> -718187.35 | I7: Logistic Bills issued in FY-25 pertaining to FY-24 | J7: =Details!AC25 -> 0
F8: DN Provision in Zoho FY 24-25 | G8: =Details!O24 -> 309308 | I8: Logistic Provision in Zoho FY 24-25 | J8: =Details!AC26 -> 0
C9: Reconciliation | D9: =Details!AY28 -> 0 | F9: JV for Last year Bills | G9: 0 | J9: =SUM(J6:J8) -> 0
C10: CN Provision in Zoho FY 24-25 | D10: =-Details!AY26 -> 0 | F10: Last year bills considered this year | G10: =-'Recon Items'!N18 -> 17497.02 | I10: Logistic Cost as per P&L Report (Zoho Books) | J10: =Details!AC22 -> 0
D11: =SUM(D6:D10) -> 2857384 | F11: Final - Variance | G11: ='Recon Items'!G18 -> 0 | I11: Final - Variance | J11: =J9-J10 -> 0
C12: Revenue as per P&L Report (Zoho Books) | D12: =Details!AY22 -> 3173162 | G12: =SUM(G6:G11) -> 1778946.3
C13: Final - Variance | D13: =D11-D12 -> -315777.91 | F13: Cost as per P&L Report (Zoho Books) | G13: =Details!O22 -> 1778946.3
F14: Final - Variance | G14: =G12-G13-'Recon Items'!C18 -> -2.3283064e-10
