Workbook

Sheet Summary
D2: =TEXT(D4, "mmm-yy") -> Apr-26 | E2: =TEXT(E4, "mmm-yy") -> May-26 | F2: =TEXT(F4, "mmm-yy") -> Jun-26 | G2: =TEXT(G4, "mmm-yy") -> Jul-26 | H2: =TEXT(H4, "mmm-yy") -> Aug-26 | I2: =TEXT(I4, "mmm-yy") -> Sep-26 | J2: =TEXT(J4, "mmm-yy") -> Oct-25 | K2: =TEXT(K4, "mmm-yy") -> Nov-25 | ... Q2: =TEXT(Q4, "mmm-yy") -> Mar-26
D3: 30 | E3: 31 | F3: 21 | G3: 0 | H3: 0 | I3: 0 | J3: 0 | K3: 0 | L3: 0 | M3: 0 | N3: 0 | O3: 0 | P3: 0 | Q3: 0 | R3: =SUM(D3:Q3) -> 82
C4: Marketplace (AFR) | D4: 46113 | E4: 46143 | F4: 46174 | G4: 46204 | H4: 46235 | I4: 46266 | J4: 45931 | K4: 45962 | L4: 46296 | M4: 46327 | N4: 45992 | O4: 46023 | P4: 46054 | Q4: 46082 | R4: FY 2026-27
C5: Quantity (MT) | D5: 19.16 | E5: =SUMIFS(Details!$BB$4:$BB$18,Details!$C$4:$C$18,Summary!E$4)/1000 -> 55.8 | F5: =SUMIFS(Details!$BB$4:$BB$18,Details!$C$4:$C$18,Summary!F$4)/1000 -> 112.91 | G5: =SUMIFS(Details!$BB$4:$BB$18,Details!$C$4:$C$18,Summary!G$4)/1000 -> 0 | H5: =SUMIFS(Details!$BB$4:$BB$18,Details!$C$4:$C$18,Summary!H$4)/1000 -> 0 | I5: =SUMIFS(Details!$BB$4:$BB$18,Details!$C$4:$C$18,Summary!I$4)/1000 -> 0 | J5: =SUMIFS(Details!$BB$4:$BB$18,Details!$C$4:$C$18,Summary!J$4)/1000 -> 0 | K5: =SUMIFS(Details!$BB$4:$BB$18,Details!$C$4:$C$18,Summary!K$4)/1000 -> 0 | L5: =SUMIFS(Details!$BB$4:$BB$18,Details!$C$4:$C$18,Summary!L$4)/1000 -> 0 | ... Q5: =SUMIFS(Details!$BB$4:$BB$18,Details!$C$4:$C$18,Summary!Q$4)/1000 -> 0 | R5: =SUM(D5:Q5) -> 187.87 | S5: =Details!BB19/1000 -> 187.87 | T5: =R5-S5 -> 0 | U5: =-T5 -> 0
C6: Sales | D6: 268100 | E6: =SUMIFS(Details!$BO$4:$BO$18,Details!$C$4:$C$18,Summary!E$4) -> 729921 | F6: =SUMIFS(Details!$BO$4:$BO$18,Details!$C$4:$C$18,Summary!F$4) -> 1028032.6 | G6: =SUMIFS(Details!$BO$4:$BO$18,Details!$C$4:$C$18,Summary!G$4) -> 0 | H6: =SUMIFS(Details!$BO$4:$BO$18,Details!$C$4:$C$18,Summary!H$4) -> 0 | I6: =SUMIFS(Details!$BO$4:$BO$18,Details!$C$4:$C$18,Summary!I$4) -> 0 | J6: =SUMIFS(Details!$BO$4:$BO$18,Details!$C$4:$C$18,Summary!J$4) -> 0 | K6: =SUMIFS(Details!$BO$4:$BO$18,Details!$C$4:$C$18,Summary!K$4) -> 0 | L6: =SUMIFS(Details!$BO$4:$BO$18,Details!$C$4:$C$18,Summary!L$4) -> 0 | ... Q6: =SUMIFS(Details!$BO$4:$BO$18,Details!$C$4:$C$18,Summary!Q$4) -> 0 | R6: =SUM(D6:Q6) -> 2026053.6 | S6: =Details!BO19 -> 2026053.6 | T6: =R6-S6+R71 -> 0 | U6: =-T6 -> 0
C7: Purchases | D7: 220225 | E7: =SUMIFS(Details!$AM$4:$AM$18,Details!$C$4:$C$18,Summary!E$4)-SUMIFS(Details!$AB$4:$AB$18,Details!$C$4:$C$18,Summary!E$4) -> 660165 | F7: =SUMIFS(Details!$AM$4:$AM$18,Details!$C$4:$C$18,Summary!F$4)-SUMIFS(Details!$AB$4:$AB$18,Details!$C$4:$C$18,Summary!F$4) -> 969640 | G7: =SUMIFS(Details!$AM$4:$AM$18,Details!$C$4:$C$18,Summary!G$4)-SUMIFS(Details!$AB$4:$AB$18,Details!$C$4:$C$18,Summary!G$4) -> 0 | H7: =SUMIFS(Details!$AM$4:$AM$18,Details!$C$4:$C$18,Summary!H$4)-SUMIFS(Details!$AB$4:$AB$18,Details!$C$4:$C$18,Summary!H$4) -> 0 | I7: =SUMIFS(Details!$AM$4:$AM$18,Details!$C$4:$C$18,Summary!I$4)-SUMIFS(Details!$AB$4:$AB$18,Details!$C$4:$C$18,Summary!I$4) -> 0 | J7: =SUMIFS(Details!$AM$4:$AM$18,Details!$C$4:$C$18,Summary!J$4)-SUMIFS(Details!$AB$4:$AB$18,Details!$C$4:$C$18,Summary!J$4) -> 0 | K7: =SUMIFS(Details!$AM$4:$AM$18,Details!$C$4:$C$18,Summary!K$4)-SUMIFS(Details!$AB$4:$AB$18,Details!$C$4:$C$18,Summary!K$4) -> 0 | L7: =SUMIFS(Details!$AM$4:$AM$18,Details!$C$4:$C$18,Summary!L$4)-SUMIFS(Details!$AB$4:$AB$18,Details!$C$4:$C$18,Summary!L$4) -> 0 | ... Q7: =SUMIFS(Details!$AM$4:$AM$18,Details!$C$4:$C$18,Summary!Q$4)-SUMIFS(Details!$AB$4:$AB$18,Details!$C$4:$C$18,Summary!Q$4) -> 0 | R7: =SUM(D7:Q7) -> 1850030 | S7: =Details!P20 -> 1850030 | T7: =R7-S7 -> 0 | U7: =-T7 -> 0
C8: Gross Margin | D8: =D6-D7 -> 47875 | E8: =E6-E7 -> 69756 | F8: =F6-F7 -> 58392.6 | G8: =G6-G7 -> 0 | H8: =H6-H7 -> 0 | I8: =I6-I7 -> 0 | J8: =J6-J7 -> 0 | K8: =K6-K7 -> 0 | ... Q8: =Q6-Q7 -> 0 | R8: =SUM(D8:Q8) -> 176023.6
C9: Gross Margin (%) | D9: =IFERROR((D8/D6),0) -> 0.17857143 | E9: =IFERROR((E8/E6),0) -> 0.095566507 | F9: =IFERROR((F8/F6),0) -> 0.056800339 | G9: =IFERROR((G8/G6),0) -> 0 | H9: =IFERROR((H8/H6),0) -> 0 | I9: =IFERROR((I8/I6),0) -> 0 | J9: =IFERROR((J8/J6),0) -> 0 | K9: =IFERROR((K8/K6),0) -> 0 | ... R9: =IFERROR((R8/R6),0) -> 0.086880031
C10: Transportation Charges | D10: 54711 | E10: =SUMIFS(Details!$AB$4:$AB$18,Details!$C$4:$C$18,Summary!E$4) -> 0 | F10: =SUMIFS(Details!$AB$4:$AB$18,Details!$C$4:$C$18,Summary!F$4) -> 0 | G10: =SUMIFS(Details!$AB$4:$AB$18,Details!$C$4:$C$18,Summary!G$4) -> 0 | H10: =SUMIFS(Details!$AB$4:$AB$18,Details!$C$4:$C$18,Summary!H$4) -> 0 | I10: =SUMIFS(Details!$AB$4:$AB$18,Details!$C$4:$C$18,Summary!I$4) -> 0 | J10: =SUMIFS(Details!$AB$4:$AB$18,Details!$C$4:$C$18,Summary!J$4) -> 0 | K10: =SUMIFS(Details!$AB$4:$AB$18,Details!$C$4:$C$18,Summary!K$4) -> 0 | L10: =SUMIFS(Details!$AB$4:$AB$18,Details!$C$4:$C$18,Summary!L$4) -> 0 | ... Q10: =SUMIFS(Details!$AB$4:$AB$18,Details!$C$4:$C$18,Summary!Q$4) -> 0 | R10: =SUM(D10:Q10) -> 54711 | S10: =Details!AB19+Details!AB35 -> 54711 | T10: =R10-S10 -> 0 | U10: =-T10 -> 0
C11: Operational Expenses | D11: =SUMIFS(Details!$AC$4:$AC$18,Details!$C$4:$C$18,Summary!D$4)+SUMIFS(Details!AM24:AM34,Details!C24:C34,Summary!D4)-SUMIFS(Details!AB24:AB34,Details!C24:C34,Summary!D4) -> 332906 | E11: =SUMIFS(Details!$AC$5:$AC$18,Details!$C$5:$C$18,Summary!E$4)+SUMIFS(Details!AM24:AM34,Details!C24:C34,Summary!E4)-SUMIFS(Details!AB24:AB34,Details!C24:C34,Summary!E4) -> 222000 | F11: =SUMIFS(Details!$AC$4:$AC$18,Details!$C$4:$C$18,Summary!F$4) -> 0 | G11: =SUMIFS(Details!$AC$4:$AC$18,Details!$C$4:$C$18,Summary!G$4) -> 0 | H11: =SUMIFS(Details!$AC$4:$AC$18,Details!$C$4:$C$18,Summary!H$4) -> 0 | I11: =SUMIFS(Details!$AC$4:$AC$18,Details!$C$4:$C$18,Summary!I$4) -> 0 | J11: =SUMIFS(Details!$AC$4:$AC$18,Details!$C$4:$C$18,Summary!J$4) -> 0 | K11: =SUMIFS(Details!$AC$4:$AC$18,Details!$C$4:$C$18,Summary!K$4) -> 0 | L11: =SUMIFS(Details!$AC$4:$AC$18,Details!$C$4:$C$18,Summary!L$4) -> 0 | M11: =SUMIFS(Details!$AC$4:$AC$18,Details!$C$4:$C$18,Summary!M$4) -> 0 | ... Q11: =SUMIFS(Details!$AC$4:$AC$18,Details!$C$4:$C$18,Summary!Q$4) -> 0 | R11: =SUM(D11:Q11) -> 554906
C12: Net Margin | D12: =D6-D7-D10-D11 -> -339742 | E12: =E6-E7-E10-E11 -> -152244 | F12: =F6-F7-F10 -> 58392.6 | G12: =G6-G7-G10 -> 0 | H12: =H6-H7-H10 -> 0 | I12: =I6-I7-I10 -> 0 | J12: =J6-J7-J10 -> 0 | K12: =K6-K7-K10 -> 0 | L12: =L6-L7-L10 -> 0 | M12: =M6-M7-M10 -> 0 | ... Q12: =Q6-Q7-Q10 -> 0 | R12: =SUM(D12:Q12) -> -433593.4
C13: Net Margin (%) | D13: =IFERROR((D12/D6),0) -> -1.2672212 | E13: =IFERROR((E12/E6),0) -> -0.208576 | F13: =IFERROR((F12/F6),0) -> 0.056800339 | G13: =IFERROR((G12/G6),0) -> 0 | H13: =IFERROR((H12/H6),0) -> 0 | I13: =IFERROR((I12/I6),0) -> 0 | J13: =IFERROR((J12/J6),0) -> 0 | K13: =IFERROR((K12/K6),0) -> 0 | ... R13: =IFERROR((R12/R6),0) -> -0.21400885
C14: Other Income | D14: 0 | E14: 0 | F14: 0 | G14: 0 | H14: 0 | I14: 0 | J14: 0 | K14: 0 | L14: 0 | M14: 0 | N14: 0 | O14: 0 | P14: 0 | Q14: 0 | R14: =SUM(D14:Q14) -> 0
C15: Transport Charges (%) | D15: =IFERROR((D10/D6),0) -> 0.20406938 | E15: =IFERROR((E10/E6),0) -> 0 | F15: =IFERROR((F10/F6),0) -> 0 | G15: =IFERROR((G10/G6),0) -> 0 | H15: =IFERROR((H10/H6),0) -> 0 | I15: =IFERROR((I10/I6),0) -> 0 | J15: =IFERROR((J10/J6),0) -> 0 | K15: =IFERROR((K10/K6),0) -> 0 | ... R15: =IFERROR((R10/R6),0) -> 0.027003728
C16: Revenue Per Kg | D16: =IFERROR(+D6/(D5*1000),0) -> 13.992693 | E16: =IFERROR(+E6/(E5*1000),0) -> 13.081022 | F16: =IFERROR(+F6/(F5*1000),0) -> 9.1048853 | G16: =IFERROR(+G6/(G5*1000),0) -> 0 | H16: =IFERROR(+H6/(H5*1000),0) -> 0 | I16: =IFERROR(+I6/(I5*1000),0) -> 0 | J16: =IFERROR(+J6/(J5*1000),0) -> 0 | K16: =IFERROR(+K6/(K5*1000),0) -> 0 | ... Q16: =IFERROR(+Q6/(Q5*1000),0) -> 0 | R16: =+R6/(R5*1000) -> 10.784338
C17: Purchase Cost Per Kg | D17: =IFERROR(+D7/(D5*1000),0) -> 11.493998 | E17: =IFERROR(+E7/(E5*1000),0) -> 11.830914 | F17: =IFERROR(+F7/(F5*1000),0) -> 8.5877247 | G17: =IFERROR(+G7/(G5*1000),0) -> 0 | H17: =IFERROR(+H7/(H5*1000),0) -> 0 | I17: =IFERROR(+I7/(I5*1000),0) -> 0 | J17: =IFERROR(+J7/(J5*1000),0) -> 0 | K17: =IFERROR(+K7/(K5*1000),0) -> 0 | ... Q17: =IFERROR(+Q7/(Q5*1000),0) -> 0 | R17: =+R7/(R5*1000) -> 9.8473945
C18: Transportation Charges Per Kg | D18: =IFERROR(D10/(D5*1000),0) -> 2.8554802 | E18: =IFERROR(E10/(E5*1000),0) -> 0 | F18: =IFERROR(F10/(F5*1000),0) -> 0 | G18: =IFERROR(G10/(G5*1000),0) -> 0 | H18: =IFERROR(H10/(H5*1000),0) -> 0 | I18: =IFERROR(I10/(I5*1000),0) -> 0 | J18: =IFERROR(J10/(J5*1000),0) -> 0 | K18: =IFERROR(K10/(K5*1000),0) -> 0 | ... Q18: =IFERROR(Q10/(Q5*1000),0) -> 0 | R18: =R10/(R5*1000) -> 0.29121733
C19: No. of Transactions | D19: {=IFERROR(ROWS(_xlfn.UNIQUE(_xlfn._xlws.FILTER(Details!$AO$5:$AO$18, (Details!$C$5:$C$18)=Summary!D$2))),0)} -> 1 | E19: {=IFERROR(ROWS(_xlfn.UNIQUE(_xlfn._xlws.FILTER(Details!$AO$5:$AO$18, (Details!$C$5:$C$18)=Summary!E$2))),0)} -> 3 | F19: {=IFERROR(ROWS(_xlfn.UNIQUE(_xlfn._xlws.FILTER(Details!$AO$5:$AO$18, (Details!$C$5:$C$18)=Summary!F$2))),0)} -> 9 | G19: {=IFERROR(ROWS(_xlfn.UNIQUE(_xlfn._xlws.FILTER(Details!$AO$5:$AO$18, (Details!$C$5:$C$18)=Summary!G$2))),0)} -> 0 | H19: {=IFERROR(ROWS(_xlfn.UNIQUE(_xlfn._xlws.FILTER(Details!$AO$5:$AO$18, (Details!$C$5:$C$18)=Summary!H$2))),0)} -> 0 | I19: {=IFERROR(ROWS(_xlfn.UNIQUE(_xlfn._xlws.FILTER(Details!$AO$5:$AO$18, (Details!$C$5:$C$18)=Summary!I$2))),0)} -> 0 | J19: {=IFERROR(ROWS(_xlfn.UNIQUE(_xlfn._xlws.FILTER(Details!$AO$5:$AO$18, (Details!$C$5:$C$18)=Summary!J$2))),0)} -> 0 | K19: {=IFERROR(ROWS(_xlfn.UNIQUE(_xlfn._xlws.FILTER(Details!$AO$5:$AO$18, (Details!$C$5:$C$18)=Summary!K$2))),0)} -> 0 | ... Q19: {=IFERROR(ROWS(_xlfn.UNIQUE(_xlfn._xlws.FILTER(Details!$AO$5:$AO$18, (Details!$C$5:$C$18)=Summary!Q$2))),0)} -> 0 | R19: =SUM(D19:Q19) -> 13
C20: No. of Sellers (Aggregators) | D20: {=IFERROR(ROWS(_xlfn.UNIQUE(_xlfn._xlws.FILTER(MID(Details!$G$5:$G$18,3,10), (Details!$C$5:$C$18)=Summary!D$2))),0)} -> 1 | E20: {=IFERROR(ROWS(_xlfn.UNIQUE(_xlfn._xlws.FILTER(MID(Details!$G$5:$G$18,3,10), (Details!$C$5:$C$18)=Summary!E$2))),0)} -> 1 | F20: {=IFERROR(ROWS(_xlfn.UNIQUE(_xlfn._xlws.FILTER(MID(Details!$G$5:$G$18,3,10), (Details!$C$5:$C$18)=Summary!F$2))),0)} -> 2 | G20: {=IFERROR(ROWS(_xlfn.UNIQUE(_xlfn._xlws.FILTER(MID(Details!$G$5:$G$18,3,10), (Details!$C$5:$C$18)=Summary!G$2))),0)} -> 0 | H20: {=IFERROR(ROWS(_xlfn.UNIQUE(_xlfn._xlws.FILTER(MID(Details!$G$5:$G$18,3,10), (Details!$C$5:$C$18)=Summary!H$2))),0)} -> 0 | I20: {=IFERROR(ROWS(_xlfn.UNIQUE(_xlfn._xlws.FILTER(MID(Details!$G$5:$G$18,3,10), (Details!$C$5:$C$18)=Summary!I$2))),0)} -> 0 | J20: {=IFERROR(ROWS(_xlfn.UNIQUE(_xlfn._xlws.FILTER(MID(Details!$G$5:$G$18,3,10), (Details!$C$5:$C$18)=Summary!J$2))),0)} -> 0 | K20: {=IFERROR(ROWS(_xlfn.UNIQUE(_xlfn._xlws.FILTER(MID(Details!$G$5:$G$18,3,10), (Details!$C$5:$C$18)=Summary!K$2))),0)} -> 0 | ... Q20: {=IFERROR(ROWS(_xlfn.UNIQUE(_xlfn._xlws.FILTER(MID(Details!$G$5:$G$18,3,10), (Details!$C$5:$C$18)=Summary!Q$2))),0)} -> 0 | R20: ='Supplier Metrics'!B2 -> 1
C21: No. of Buyers (Recyclers) | D21: {=IFERROR(ROWS(_xlfn.UNIQUE(_xlfn._xlws.FILTER(MID(Details!$AR$5:$AR$18,3,10), (Details!$C$5:$C$18)=Summary!D$2))),0)} -> 1 | E21: {=IFERROR(ROWS(_xlfn.UNIQUE(_xlfn._xlws.FILTER(MID(Details!$AR$5:$AR$18,3,10), (Details!$C$5:$C$18)=Summary!E$2))),0)} -> 1 | F21: {=IFERROR(ROWS(_xlfn.UNIQUE(_xlfn._xlws.FILTER(MID(Details!$AR$5:$AR$18,3,10), (Details!$C$5:$C$18)=Summary!F$2))),0)} -> 2 | G21: {=IFERROR(ROWS(_xlfn.UNIQUE(_xlfn._xlws.FILTER(MID(Details!$AR$5:$AR$18,3,10), (Details!$C$5:$C$18)=Summary!G$2))),0)} -> 0 | H21: {=IFERROR(ROWS(_xlfn.UNIQUE(_xlfn._xlws.FILTER(MID(Details!$AR$5:$AR$18,3,10), (Details!$C$5:$C$18)=Summary!H$2))),0)} -> 0 | I21: {=IFERROR(ROWS(_xlfn.UNIQUE(_xlfn._xlws.FILTER(MID(Details!$AR$5:$AR$18,3,10), (Details!$C$5:$C$18)=Summary!I$2))),0)} -> 0 | J21: {=IFERROR(ROWS(_xlfn.UNIQUE(_xlfn._xlws.FILTER(MID(Details!$AR$5:$AR$18,3,10), (Details!$C$5:$C$18)=Summary!J$2))),0)} -> 0 | K21: {=IFERROR(ROWS(_xlfn.UNIQUE(_xlfn._xlws.FILTER(MID(Details!$AR$5:$AR$18,3,10), (Details!$C$5:$C$18)=Summary!K$2))),0)} -> 0 | ... Q21: {=IFERROR(ROWS(_xlfn.UNIQUE(_xlfn._xlws.FILTER(MID(Details!$AR$5:$AR$18,3,10), (Details!$C$5:$C$18)=Summary!Q$2))),0)} -> 0 | R21: ='Buyer Metrics'!B3 -> 2
C22: Full Rejection | D22: {=IFERROR(ROWS(_xlfn.UNIQUE(_xlfn._xlws.FILTER(Details!$E$5:$E$18,(Details!$C$5:$C$18=Summary!D$2)*(Details!$BR$5:$BR$18=Summary!$C$22)))),0)} -> 0 | E22: {=IFERROR(ROWS(_xlfn.UNIQUE(_xlfn._xlws.FILTER(Details!$E$5:$E$18,(Details!$C$5:$C$18=Summary!E$4)*(Details!$BR$5:$BR$18=Summary!$C$22)))),0)} -> 0 | F22: {=IFERROR(ROWS(_xlfn.UNIQUE(_xlfn._xlws.FILTER(Details!$E$5:$E$18,(Details!$C$5:$C$18=Summary!F$4)*(Details!$BR$5:$BR$18=Summary!$C$22)))),0)} -> 0 | G22: {=IFERROR(ROWS(_xlfn.UNIQUE(_xlfn._xlws.FILTER(Details!$E$5:$E$18,(Details!$C$5:$C$18=Summary!G$4)*(Details!$BR$5:$BR$18=Summary!$C$22)))),0)} -> 0 | H22: {=IFERROR(ROWS(_xlfn.UNIQUE(_xlfn._xlws.FILTER(Details!$E$5:$E$18,(Details!$C$5:$C$18=Summary!H$4)*(Details!$BR$5:$BR$18=Summary!$C$22)))),0)} -> 0 | I22: {=IFERROR(ROWS(_xlfn.UNIQUE(_xlfn._xlws.FILTER(Details!$E$5:$E$18,(Details!$C$5:$C$18=Summary!I$4)*(Details!$BR$5:$BR$18=Summary!$C$22)))),0)} -> 0 | J22: {=IFERROR(ROWS(_xlfn.UNIQUE(_xlfn._xlws.FILTER(Details!$E$5:$E$18,(Details!$C$5:$C$18=Summary!J$4)*(Details!$BR$5:$BR$18=Summary!$C$22)))),0)} -> 0 | K22: {=IFERROR(ROWS(_xlfn.UNIQUE(_xlfn._xlws.FILTER(Details!$E$5:$E$18,(Details!$C$5:$C$18=Summary!K$4)*(Details!$BR$5:$BR$18=Summary!$C$22)))),0)} -> 0 | L22: {=IFERROR(ROWS(_xlfn.UNIQUE(_xlfn._xlws.FILTER(Details!$E$5:$E$18,(Details!$C$5:$C$18=Summary!L$4)*(Details!$BR$5:$BR$18=Summary!$C$22)))),0)} -> 0 | ... Q22: {=IFERROR(ROWS(_xlfn.UNIQUE(_xlfn._xlws.FILTER(Details!$E$5:$E$18,(Details!$C$5:$C$18=Summary!Q$4)*(Details!$BR$5:$BR$18=Summary!$C$22)))),0)} -> 0 | R22: =SUM(D22:Q22) -> 0
C23: Receivable | D23: 796441.6 | E23: 600884.96 | F23: 1671613.1 | G23: 0 | H23: 0 | I23: 0 | J23: 0 | K23: 0 | L23: 0 | M23: 0 | N23: 0 | O23: 0 | P23: 0 | Q23: 0 | R23: =F23 -> 1671613.1
C24: DSO (Days) | D24: =IFERROR(((D23/(D6*1.18))*D3),0) -> 75.52598 | E24: =IFERROR(((E23/(E6*1.18))*E3),0) -> 21.626944 | F24: =IFERROR(((F23/(F6*1.18))*F3),0) -> 28.937843 | G24: =IFERROR(((G23/(G6*1.18))*G3),0) -> 0 | H24: =IFERROR(((H23/(H6*1.18))*H3),0) -> 0 | I24: =IFERROR(((I23/(I6*1.18))*I3),0) -> 0 | J24: =IFERROR(((J23/(J6*1.18))*J3),0) -> 0 | K24: =IFERROR(((K23/(K6*1.18))*K3),0) -> 0 | ... Q24: =IFERROR(((Q23/(Q6*1.18))*Q3),0) -> 0 | R24: =IFERROR(((R23)/(R6*1.18)*R3),0) -> 57.334585
C25: Payable | D25: 287674.16 | E25: 561938.06 | F25: 948429.3 | G25: 0 | H25: 0 | I25: 0 | J25: 0 | K25: 0 | L25: 0 | M25: 0 | N25: 0 | O25: 0 | P25: 0 | Q25: 0 | R25: =F25 -> 948429.3
C26: DPO (Days) | D26: =IFERROR(((D25/(D7*1.18))*D3),0) -> 33.210352 | E26: =IFERROR(((E25/(E7*1.18))*E3),0) -> 22.362257 | F26: =IFERROR(((F25/(F7*1.18))*F3),0) -> 17.407313 | G26: =IFERROR(((G25/(G7*1.18))*G3),0) -> 0 | H26: =IFERROR(((H25/(H7*1.18))*H3),0) -> 0 | I26: =IFERROR(((I25/(I7*1.18))*I3),0) -> 0 | J26: =IFERROR(((J25/(J7*1.18))*J3),0) -> 0 | K26: =IFERROR(((K25/(K7*1.18))*K3),0) -> 0 | ... R26: =IFERROR(((R25/(R7*1.18))*R3),0) -> 35.625259
C27: Working Capital Days | D27: =D24-D26 -> 42.315628 | E27: =E24-E26 -> -0.73531292 | F27: =F24-F26 -> 11.530531 | G27: =G24-G26 -> 0 | H27: =H24-H26 -> 0 | I27: =I24-I26 -> 0 | J27: =J24-J26 -> 0 | K27: =K24-K26 -> 0 | ... R27: =R24-R26 -> 21.709325
C28: Credit Notes (Value - Incl. Prov) | D28: 140 | E28: =-SUMIFS(Details!$BW$4:$BW$18,Details!$C$4:$C$18,Summary!E4) -> 560 | F28: =-SUMIFS(Details!$BW$4:$BW$18,Details!$C$4:$C$18,Summary!F4) -> 0 | G28: =-SUMIFS(Details!$BW$4:$BW$18,Details!$C$4:$C$18,Summary!G4) -> 0 | H28: =-SUMIFS(Details!$BW$4:$BW$18,Details!$C$4:$C$18,Summary!H4) -> 0 | I28: =-SUMIFS(Details!$BW$4:$BW$18,Details!$C$4:$C$18,Summary!I4) -> 0 | J28: =-SUMIFS(Details!$BW$4:$BW$18,Details!$C$4:$C$18,Summary!J4) -> 0 | K28: =-SUMIFS(Details!$BW$4:$BW$18,Details!$C$4:$C$18,Summary!K4) -> 0 | L28: =-SUMIFS(Details!$BW$4:$BW$18,Details!$C$4:$C$18,Summary!L4) -> 0 | ... Q28: =-SUMIFS(Details!$BW$4:$BW$18,Details!$C$4:$C$18,Summary!Q4) -> 0 | R28: =SUM(D28:Q28) -> 700 | S28: =(Details!BM19-Details!BN19) -> -700 | T28: =R28+S28 -> 0
C29: Credit Notes (% to Revenue) | D29: =IFERROR((+D28/D6),0) -> 0.00052219321 | E29: =IFERROR((+E28/E6),0) -> 0.00076720631 | F29: =IFERROR((+F28/F6),0) -> 0 | G29: =IFERROR((+G28/G6),0) -> 0 | H29: =IFERROR((+H28/H6),0) -> 0 | I29: =IFERROR((+I28/I6),0) -> 0 | J29: =IFERROR((+J28/J6),0) -> 0 | K29: =IFERROR((+K28/K6),0) -> 0 | ... Q29: =IFERROR((+Q28/Q6),0) -> 0 | R29: =+R28/R6 -> 0.00034549925
C30: Debit Notes (Value - Incl. Prov) | D30: 115 | E30: =SUMIFS(Details!$BX$4:$BX$18,Details!$C$4:$C$18,Summary!E4) -> -460 | F30: =-SUMIFS(Details!$BX$4:$BX$18,Details!$C$4:$C$18,Summary!F4) -> 0 | G30: =-SUMIFS(Details!$BX$4:$BX$18,Details!$C$4:$C$18,Summary!G4) -> 0 | H30: =-SUMIFS(Details!$BX$4:$BX$18,Details!$C$4:$C$18,Summary!H4) -> 0 | I30: =-SUMIFS(Details!$BX$4:$BX$18,Details!$C$4:$C$18,Summary!I4) -> 0 | J30: =-SUMIFS(Details!$BX$4:$BX$18,Details!$C$4:$C$18,Summary!J4) -> 0 | K30: =-SUMIFS(Details!$BX$4:$BX$18,Details!$C$4:$C$18,Summary!K4) -> 0 | L30: =-SUMIFS(Details!$BX$4:$BX$18,Details!$C$4:$C$18,Summary!L4) -> 0 | M30: =-SUMIFS(Details!$BX$4:$BX$18,Details!$C$4:$C$18,Summary!M4) -> 0 | ... Q30: =-SUMIFS(Details!$BX$4:$BX$18,Details!$C$4:$C$18,Summary!Q4) -> 0 | R30: =SUM(D30:Q30) -> -345 | S30: =(Details!AK19-Details!AL19) -> -575 | T30: =R30+S30 -> -920
C31: Debit Notes (% to Purchase) | D31: =IFERROR((D30/D7),0) -> 0.00052219321 | E31: =IFERROR((E30/E7),0) -> -0.0006967955 | F31: =IFERROR((F30/F7),0) -> 0 | G31: =IFERROR((G30/G7),0) -> 0 | H31: =IFERROR((H30/H7),0) -> 0 | I31: =IFERROR((I30/I7),0) -> 0 | J31: =IFERROR((J30/J7),0) -> 0 | K31: =IFERROR((K30/K7),0) -> 0 | ... Q31: =IFERROR((Q30/Q7),0) -> 0 | R31: =(R30/(R7+R10)) -> -0.00018112699
C33: KPI's without Provisions | D33: =D4 -> 46113 | E33: =E4 -> 46143 | F33: =F4 -> 46174 | G33: =G4 -> 46204 | H33: =H4 -> 46235 | I33: =I4 -> 46266 | J33: =J4 -> 45931 | K33: =K4 -> 45962 | L33: 46296 | M33: 46327 | N33: =N4 -> 45992 | O33: =O4 -> 46023 | P33: =P4 -> 46054 | Q33: =Q4 -> 46082 | R33: =R4 -> FY 2026-27
C34: Sales without Provision | D34: =D6+D53 -> 268100 | E34: =E6+E53 -> 729921 | F34: =F6+F53 -> 1028032.6 | G34: =G6+G53 -> 0 | H34: =H6+H53 -> 0 | I34: =I6+I53 -> 0 | J34: =J6+J53 -> 0 | K34: =K6+K53 -> 0 | ... Q34: =Q6+Q53 -> 0 | R34: =SUM(D34:Q34) -> 2026053.6
C35: Purchases without Provision | D35: =D7+D10+D52 -> 274936 | E35: =E7+E10+E52 -> 660165 | F35: =F7+F10+F52 -> 969640 | G35: =G7+G10+G52 -> 0 | H35: =H7+H10+H52 -> 0 | I35: =I7+I10+I52 -> 0 | J35: =J7+J10+J52 -> 0 | K35: =K7+K10+K52 -> 0 | ... Q35: =Q7+Q10+Q52 -> 0 | R35: =SUM(D35:Q35) -> 1904741
C36: Contribution without Provision | D36: =D34-D35 -> -6836 | E36: =E34-E35 -> 69756 | F36: =F34-F35 -> 58392.6 | G36: =G34-G35 -> 0 | H36: =H34-H35 -> 0 | I36: =I34-I35 -> 0 | J36: =J34-J35 -> 0 | K36: =K34-K35 -> 0 | ... R36: =R34-R35 -> 121312.6
C37: Contribution (%) | D37: =D36/D34 -> -0.025497949 | E37: =E36/E34 -> 0.095566507 | F37: =F36/F34 -> 0.056800339 | G37: =G36/G34 -> #DIV/0! | H37: =H36/H34 -> #DIV/0! | I37: =I36/I34 -> #DIV/0! | J37: =J36/J34 -> #DIV/0! | K37: =K36/K34 -> #DIV/0! | ... R37: =R36/R34 -> 0.059876303
C39: Business Trends | D39: =D4 -> 46113 | E39: =E4 -> 46143 | F39: =F4 -> 46174 | G39: =G4 -> 46204 | H39: =H4 -> 46235 | I39: =I4 -> 46266 | J39: =J4 -> 45931 | K39: =K4 -> 45962 | L39: 46296 | M39: 46327 | N39: =N4 -> 45992 | O39: =O4 -> 46023 | P39: =P4 -> 46054 | Q39: =Q4 -> 46082 | R39: =R4 -> FY 2026-27
C40: Sales-Revenue (MoM) | D40: =IFERROR(((D6/C6)-1),0) -> 0 | E40: =IFERROR(((E6/D6)-1),0) -> 1.7225699 | F40: =IFERROR(((F6/E6)-1),0) -> 0.40841625 | G40: =IFERROR(((G6/F6)-1),0) -> -1 | H40: =IFERROR(((H6/G6)-1),0) -> 0 | I40: =IFERROR(((I6/H6)-1),0) -> 0 | J40: =IFERROR(((J6/I6)-1),0) -> 0 | K40: =IFERROR(((K6/J6)-1),0) -> 0 | ... M40: =IFERROR(((M6/L6)-1),0) -> 0 | N40: =IFERROR(((N6/K6)-1),0) -> 0 | O40: =IFERROR(((O6/N6)-1),0) -> 0 | P40: =IFERROR(((P6/O6)-1),0) -> 0 | Q40: =IFERROR(((Q6/P6)-1),0) -> 0 | R40: 0
C41: Sales-Volume (MoM) | D41: =IFERROR(((D5/C5)-1),0) -> 0 | E41: =IFERROR(((E5/D5)-1),0) -> 1.9123173 | F41: =IFERROR(((F5/E5)-1),0) -> 1.0234767 | G41: =IFERROR(((G5/F5)-1),0) -> -1 | H41: =IFERROR(((H5/G5)-1),0) -> 0 | I41: =IFERROR(((I5/H5)-1),0) -> 0 | J41: =IFERROR(((J5/I5)-1),0) -> 0 | K41: =IFERROR(((K5/J5)-1),0) -> 0 | ... M41: =IFERROR(((M5/L5)-1),0) -> 0 | N41: =IFERROR(((N5/K5)-1),0) -> 0 | O41: =IFERROR(((O5/N5)-1),0) -> 0 | P41: =IFERROR(((P5/O5)-1),0) -> 0 | Q41: =IFERROR(((Q5/P5)-1),0) -> 0 | R41: 0
C42: Sales-Transactions (MoM) | D42: =IFERROR(((D19/C19)-1),0) -> 0 | E42: =IFERROR(((E19/D19)-1),0) -> 2 | F42: =IFERROR(((F19/E19)-1),0) -> 2 | G42: =IFERROR(((G19/F19)-1),0) -> -1 | H42: =IFERROR(((#REF!/G19)-1),0) -> 0 | I42: =IFERROR(((I19/#REF!)-1),0) -> 0 | J42: =IFERROR(((J19/#REF!)-1),0) -> 0 | K42: =IFERROR(((K19/#REF!)-1),0) -> 0 | L42: =IFERROR(((L19/#REF!)-1),0) -> 0 | M42: =IFERROR(((M19/#REF!)-1),0) -> 0 | N42: =IFERROR(((N19/K19)-1),0) -> 0 | O42: =IFERROR(((O19/N19)-1),0) -> 0 | P42: =IFERROR(((P19/O19)-1),0) -> 0 | Q42: =IFERROR(((Q19/P19)-1),0) -> 0 | R42: 0
C44: Loss Making Transactions | D44: =D39 -> 46113 | E44: =E39 -> 46143 | F44: =F39 -> 46174 | G44: =G39 -> 46204 | H44: =H39 -> 46235 | I44: =I39 -> 46266 | J44: =J39 -> 45931 | K44: =K39 -> 45962 | L44: 46296 | M44: 46327 | N44: =N39 -> 45992 | O44: =O39 -> 46023 | P44: =P39 -> 46054 | Q44: =Q39 -> 46082 | R44: =R39 -> FY 2026-27
C45: No of LMT @ Inception | D45: 0 | E45: 0 | F45: 0 | G45: 0 | H45: 0 | I45: 0 | J45: 0 | K45: 0 | L45: 0 | M45: 0 | N45: 0 | O45: 0 | P45: 0 | Q45: 0 | R45: =SUM(D45:Q45) -> 0
C46: Value of LMT @ Inception | D46: 0 | E46: 0 | F46: 0 | G46: 0 | H46: 0 | I46: 0 | J46: 0 | K46: 0 | L46: 0 | M46: 0 | N46: 0 | O46: 0 | P46: 0 | Q46: 0 | R46: =SUM(D46:Q46) -> 0
C47: No of LMT | D47: 0 | E47: 0 | F47: 0 | G47: 0 | H47: 0 | I47: 0 | J47: 0 | K47: 0 | L47: 0 | M47: 0 | N47: 0 | O47: 0 | P47: 0 | Q47: 0 | R47: =SUM(D47:Q47) -> 0
C48: % of LMT | D48: =IFERROR(D47/D19,0) -> 0 | E48: =IFERROR(E47/E19,0) -> 0 | F48: =IFERROR(F47/F19,0) -> 0 | G48: =IFERROR(G47/G19,0) -> 0 | H48: =IFERROR(H47/#REF!,0) -> 0 | I48: =IFERROR(I47/I19,0) -> 0 | J48: =IFERROR(J47/J19,0) -> 0 | K48: =IFERROR(K47/K19,0) -> 0 | L48: =IFERROR(L47/L19,0) -> 0 | M48: =IFERROR(M47/M19,0) -> 0 | N48: =IFERROR(N47/N19,0) -> 0 | O48: =IFERROR(O47/O19,0) -> 0 | P48: =IFERROR(P47/P19,0) -> 0 | ... R48: =IFERROR(R47/R19,0) -> 0
C49: Value of LMT | D49: 0 | E49: 0 | F49: 0 | G49: 0 | H49: 0 | I49: 0 | J49: 1 | K49: 2 | L49: 3 | M49: 4 | N49: 0 | O49: 0 | P49: 0 | Q49: 0 | R49: =SUM(D49:Q49) -> 10
C51: CN & DN Provisions | D51: =D44 -> 46113 | E51: =E44 -> 46143 | F51: =F44 -> 46174 | G51: =G44 -> 46204 | H51: =H44 -> 46235 | I51: =I44 -> 46266 | J51: =J44 -> 45931 | K51: =K44 -> 45962 | L51: 46296 | M51: 46327 | N51: =N44 -> 45992 | O51: =O44 -> 46023 | P51: =P44 -> 46054 | Q51: =Q44 -> 46082 | R51: =R44 -> FY 2026-27 | S51: =ROUND(S52-S53,2)-ROUND(R36-R12,2) -> -554906
C52: DN Provision | D52: =-SUMIFS(Details!$AL$4:$AL$18,Details!$C$4:$C$18,Summary!D51) -> 0 | E52: =-SUMIFS(Details!$AL$4:$AL$18,Details!$C$4:$C$18,Summary!E51) -> 0 | F52: =-SUMIFS(Details!$AL$4:$AL$18,Details!$C$4:$C$18,Summary!F51) -> 0 | G52: =-SUMIFS(Details!$AL$4:$AL$18,Details!$C$4:$C$18,Summary!G51) -> 0 | H52: =-SUMIFS(Details!$AL$4:$AL$18,Details!$C$4:$C$18,Summary!H51) -> 0 | I52: =-SUMIFS(Details!$AL$4:$AL$18,Details!$C$4:$C$18,Summary!I51) -> 0 | J52: =-SUMIFS(Details!$AL$4:$AL$18,Details!$C$4:$C$18,Summary!J51) -> 0 | K52: =-SUMIFS(Details!$AL$4:$AL$18,Details!$C$4:$C$18,Summary!K51) -> 0 | ... Q52: =-SUMIFS(Details!$AL$4:$AL$18,Details!$C$4:$C$18,Summary!Q51) -> 0 | R52: =SUM(D52:Q52) -> 0 | S52: =Details!AL19 -> 0 | T52: =S52+R52 -> 0
C53: CN Provision | D53: =-SUMIFS(Details!$BN$4:$BN$18,Details!$C$4:$C$18,Summary!D51) -> 0 | E53: =-SUMIFS(Details!$BN$4:$BN$18,Details!$C$4:$C$18,Summary!E51) -> 0 | F53: =-SUMIFS(Details!$BN$4:$BN$18,Details!$C$4:$C$18,Summary!F51) -> 0 | G53: =-SUMIFS(Details!$BN$4:$BN$18,Details!$C$4:$C$18,Summary!G51) -> 0 | H53: =-SUMIFS(Details!$BN$4:$BN$18,Details!$C$4:$C$18,Summary!H51) -> 0 | I53: =-SUMIFS(Details!$BN$4:$BN$18,Details!$C$4:$C$18,Summary!I51) -> 0 | J53: =-SUMIFS(Details!$BN$4:$BN$18,Details!$C$4:$C$18,Summary!J51) -> 0 | K53: =-SUMIFS(Details!$BN$4:$BN$18,Details!$C$4:$C$18,Summary!K51) -> 0 | ... Q53: =-SUMIFS(Details!$BN$4:$BN$18,Details!$C$4:$C$18,Summary!Q51) -> 0 | R53: =SUM(D53:Q53) -> 0 | S53: =Details!BN19 -> 0 | T53: =S53+R53 -> 0
C55: Qty Returned | D55: 45748 | E55: 45778 | F55: 45809 | G55: 45839 | H55: 45870 | I55: 45901 | J55: 45931 | K55: 45962 | L55: 46296 | M55: 46327 | N55: 45992 | O55: 46023 | P55: 46054 | Q55: 46082 | R55: FY 2025-26
D56: =SUMIFS(Details!$BA$4:$BA$18,Details!$C$4:$C$18,Summary!D$4)/1000 -> 0 | E56: =SUMIFS(Details!$BA$4:$BA$18,Details!$C$4:$C$18,Summary!E$4)/1000 -> 0 | F56: =SUMIFS(Details!$BA$4:$BA$18,Details!$C$4:$C$18,Summary!F$4)/1000 -> 0 | G56: =SUMIFS(Details!$BA$4:$BA$18,Details!$C$4:$C$18,Summary!G$4)/1000 -> 0 | H56: =SUMIFS(Details!$BA$4:$BA$18,Details!$C$4:$C$18,Summary!H$4)/1000 -> 0 | I56: =SUMIFS(Details!$BA$4:$BA$18,Details!$C$4:$C$18,Summary!I$4)/1000 -> 0 | J56: =SUMIFS(Details!$BA$4:$BA$18,Details!$C$4:$C$18,Summary!J$4)/1000 -> 0 | K56: =SUMIFS(Details!$BA$4:$BA$18,Details!$C$4:$C$18,Summary!K$4)/1000 -> 0 | ... Q56: =SUMIFS(Details!$BA$4:$BA$18,Details!$C$4:$C$18,Summary!Q$4)/1000 -> 0 | R56: =SUM(D56:Q56) -> 0
C58: Margins | D58: 45748 | E58: 45778 | F58: 45809 | G58: 45839 | H58: 45870 | I58: 45901 | J58: 45931 | K58: 45962 | L58: 46296 | M58: 46327 | N58: 45992 | O58: 46023 | P58: 46054 | Q58: 46082 | R58: FY 2025-26
C59: Gross Margin | D59: =SUMIFS(Details!$CL$5:$CL$18,Details!$C$5:$C$18,Summary!D$58) -> 0 | E59: =SUMIFS(Details!$CL$5:$CL$18,Details!$C$5:$C$18,Summary!E$58) -> 0 | F59: =SUMIFS(Details!$CL$5:$CL$18,Details!$C$5:$C$18,Summary!F$58) -> 0 | G59: =SUMIFS(Details!$CL$5:$CL$18,Details!$C$5:$C$18,Summary!G$58) -> 0 | H59: =SUMIFS(Details!$CL$5:$CL$18,Details!$C$5:$C$18,Summary!H$58) -> 0 | I59: =SUMIFS(Details!$CL$5:$CL$18,Details!$C$5:$C$18,Summary!I$58) -> 0 | J59: =SUMIFS(Details!$CL$5:$CL$18,Details!$C$5:$C$18,Summary!J$58) -> 0 | K59: =SUMIFS(Details!$CL$5:$CL$18,Details!$C$5:$C$18,Summary!K$58) -> 0 | ... Q59: =SUMIFS(Details!$CL$5:$CL$18,Details!$C$5:$C$18,Summary!Q$58) -> 0 | R59: =SUM(D59:Q59) -> 0
C60: Recykal Margin | D60: =SUMIFS(Details!$CM$5:$CM$18,Details!$C$5:$C$18,Summary!D$58) -> 0 | E60: =SUMIFS(Details!$CM$5:$CM$18,Details!$C$5:$C$18,Summary!E$58) -> 0 | F60: =SUMIFS(Details!$CM$5:$CM$18,Details!$C$5:$C$18,Summary!F$58) -> 0 | G60: =SUMIFS(Details!$CM$5:$CM$18,Details!$C$5:$C$18,Summary!G$58) -> 0 | H60: =SUMIFS(Details!$CM$5:$CM$18,Details!$C$5:$C$18,Summary!H$58) -> 0 | I60: =SUMIFS(Details!$CM$5:$CM$18,Details!$C$5:$C$18,Summary!I$58) -> 0 | J60: =SUMIFS(Details!$CM$5:$CM$18,Details!$C$5:$C$18,Summary!J$58) -> 0 | K60: =SUMIFS(Details!$CM$5:$CM$18,Details!$C$5:$C$18,Summary!K$58) -> 0 | ... Q60: =SUMIFS(Details!$CM$5:$CM$18,Details!$C$5:$C$18,Summary!Q$58) -> 0 | R60: =SUM(D60:Q60) -> 0
C61: Net Margin | D61: =SUMIFS(Details!$CN$5:$CN$18,Details!$C$5:$C$18,Summary!D$58) -> 0 | E61: =SUMIFS(Details!$CN$5:$CN$18,Details!$C$5:$C$18,Summary!E$58) -> 0 | F61: =SUMIFS(Details!$CN$5:$CN$18,Details!$C$5:$C$18,Summary!F$58) -> 0 | G61: =SUMIFS(Details!$CN$5:$CN$18,Details!$C$5:$C$18,Summary!G$58) -> 0 | H61: =SUMIFS(Details!$CN$5:$CN$18,Details!$C$5:$C$18,Summary!H$58) -> 0 | I61: =SUMIFS(Details!$CN$5:$CN$18,Details!$C$5:$C$18,Summary!I$58) -> 0 | J61: =SUMIFS(Details!$CN$5:$CN$18,Details!$C$5:$C$18,Summary!J$58) -> 0 | K61: =SUMIFS(Details!$CN$5:$CN$18,Details!$C$5:$C$18,Summary!K$58) -> 0 | ... Q61: =SUMIFS(Details!$CN$5:$CN$18,Details!$C$5:$C$18,Summary!Q$58) -> 0 | R61: =SUM(D61:Q61) -> 0
C63: Financial with GST | D63: Sales | E63: Purchases
C64: =Details!P39 -> 46194 | D64: =SUMIFS(Details!$BO$5:$BO$18,Details!$D$5:$D$18,Summary!$C$64)*118% -> 0 | E64: =SUMIFS(Details!$AM$5:$AM$18,Details!$D$5:$D$18,Summary!$C$64)*118% -> 0
C65: =TEXT(C64,"mmm-yy") -> Jun-26 | D65: =SUMIFS(Details!$BO$5:$BO$18,Details!$C$5:$C$18,Summary!$C$65)*118% -> 1213078.5 | E65: =SUMIFS(Details!$AM$5:$AM$18,Details!$C$5:$C$18,Summary!$C$65)*118% -> 1144175.2
C66: Fy 2025-26 | D66: =Details!BO19*118% -> 2390743.2 | E66: =Details!AM19*118% -> 2183035.4

Sheet Details
B3: Raw Data -AFR | F3: Purchase Details | U3: Logistic Details of the transaction | AF3: Debit Notes to Suppliers | AM3: Sales Details | BD3: DN to Customer | BH3: Credit Notes from Customers | BM3: -0.025 | BV3: CN & DN Checks | CE3: Without Provisions | CK3: Margin Buckets | CN3: Financials with GST
B4: Quarter | C4: Month | D4: Date | E4: Shipment ID | F4: Supplier Name | G4: GST Reg No. | H4: Vendor Invoice No. | I4: Vendor Invoice Date | J4: P V No. | K4: P V Date | L4: State (Origin) | M4: Vehicle No. | N4: Material | O4: Qty (Kg) | P4: Price/Kg | Q4: Purchase Price | R4: Return Qty | S4: Net Qty | T4: Basic Customs Duty | U4: Transporter Name | V4: LR NO/BILL NO | W4: J V No. | X4: JV Date | Y4: Logistics cost | Z4: Debit note on logistic cost | AA4: Logistics Provision | AB4: Total Logistics Cost | AC4: Opeartional Cost | AD4: Cost/Kg. | AE4: Divertion/Internal | AF4: Debit Note No. | AG4: Debit Note Date. | AH4: Debit Note No. 2 | AI4: Debit Note Date. 2 | AJ4: Full Debit Note | AK4: Actual Debit Note | AL4: Provision for DN | AM4: Total Cost | AN4: Inv. Date | AO4: Inv. No. | AP4: Customer ID | AQ4: Buyer Name | AR4: Buyer GST Number | AS4: Location (Origin) | AT4: Location (Destination) | AU4: State (Destination) | AV4: E-way Bill No | AW4: Qty(Kg) | AX4: Rate/Kg | AY4: Amount | AZ4: Qty Check | BA4: Return Qty | BB4: Net Qty | BC4: Divertion/Internal | BD4: Return Type | BE4: Date : DN to Buyer | BF4: DN to Buyer | BG4: Amount | BH4: Credit Note No:1 | BI4: CN Date. No:1 | BJ4: Credit Note No:2 | BK4: CN Date. No:2 | BL4: Full Credit Notes | BM4: Actual Credit Note | BN4: Provision for CN | BO4: Net Revenue | BP4: Margin | BQ4: Reamrks - Margin | BR4: Remarks | BS4: LMI @ Inception | BT4: Remarks @ Inception | BU4: Margin (%) | BV4: Margin Bucket | BW4: Total CN(Inc.Provisions) | BX4: Total DN(Inc.Provisions) | BY4: Check | BZ4: Actaul CN | CA4: Actual DN | CB4: Check | CC4: Material-Short Form | CD4: Supplier Type | CE4: Month | CF4: Cost | CG4: Revenue | CH4: Week No: | CI4: Category (Material) | CJ4: Broad Category | CK4: POC Name | CL4: Gross Margin | CM4: Recykal Margin | CN4: Net Margin | CO4: Sales | CP4: Purchases | CQ4: Credit Note | CR4: Debit Note | CS4: Margin | CT4: Bill Branch | CU4: Inv Branch | CV4: Vendor PAN No | CW4: Customer PAN No
B5: ="Q" & IF(ROUNDUP(MONTH(D5)/3,0)-1=0,4,ROUNDUP(MONTH(D5)/3,0)-1) -> Q1 | C5: =TEXT(AN5,"mmm-yy") -> Apr-26 | D5: 46120 | E5: SH04260801 | F5: SRI PRASANNA TRADERS | G5: 37ANHPG0363J1Z1 | H5: 2 | I5: 46120 | J5: 26-27/PUR/000242 | K5: 46120 | L5: AD | M5: AP39WE3236 | N5: Pyrolysis Char - Briquettes | O5: 19160 | P5: 11.5 | Q5: =O5*P5 -> 220340 | R5: 0 | S5: =O5-R5 -> 19160 | T5: 0 | U5: 0 | V5: 0 | W5: 0 | X5: 0 | Y5: 0 | Z5: 0 | AA5: 0 | AB5: =Y5+AA5+Z5 -> 0 | AC5: 0 | AD5: 0 | AE5: 0 | AF5: 36/AFR/27VC00012 | AG5: 46128 | AH5: 0 | AI5: 0 | AJ5: 0 | AK5: -115 | AL5: 0 | AM5: =Q5+AB5+AL5+AK5+AJ5+T5+AE5 -> 220225 | AN5: 46120 | AO5: 36/AFR/27IN00001 | AP5: 832139000056764186 | AQ5: MRF LIMITED (36) | AR5: 36AAACM4154G1ZO | AS5: Tadpatri,Andhra Pradesh,515455 | AT5: Sadashivpet | AU5: Telangana | AW5: 19160 | AX5: 14 | AY5: =AW5*AX5 -> 268240 | AZ5: =AW5=O5 -> TRUE | BA5: 0 | BB5: =AW5-BA5 -> 19160 | BC5: 0 | BD5: Regular | BE5: 0 | BF5: 0 | BG5: 0 | BH5: 36/AFR/27CN00012 | BI5: 46128 | BJ5: 0 | BK5: 0 | BL5: 0 | BM5: -140 | BN5: 0 | BO5: =AY5+BL5+BM5+BN5+BC5+BG5 -> 268100 | BP5: =BO5-AM5 -> 47875 | BQ5: =IF(BP5>=0,"Positive Margin","Negative Margin") -> Positive Margin | BR5: DN & CN Issued | BS5: =AY5-Y5-Q5-AA5-T5+BC5 -> 47900 | BT5: =IF(BS5<0, "Negative Margin at Inception", "Positive Margin at Inception") -> Positive Margin at Inception | BU5: =IFERROR(BP5/BO5,"0") -> 0.17857143 | BV5: =IF(BU5<1%,"Less Than 1%",IF(BU5>2%,"More than 2%",IF(BU5>=1%,"1% - 2%"))) -> More than 2% | BW5: =BM5+BN5 -> -140 | BX5: =AL5+AK5 -> -115 | BY5: =BW5-BX5 -> -25 | BZ5: =BM5 -> -140 | CA5: =AK5 -> -115 | CB5: =BZ5-CA5 -> -25 | CC5: Marketplace Purchases (AFR) | CD5: 0 | CE5: =TEXT(AN5,"mmm-yy") -> Apr-26 | CF5: =AM5-AL5-AA5 -> 220225 | CG5: =BO5-BN5 -> 268100 | CH5: =INT((D5- IF(MONTH(D5) >= 4, DATE(YEAR(D5), 4, 1), DATE(YEAR(D5)-1, 4, 1))) / 7) + 1 -> 2 | CI5: AFR | CJ5: AFR | CK5: 0 | CL5: =AY5-Q5 -> 47900 | CM5: =CL5-Y5+Z5 -> 47900 | CN5: =BO5-AM5 -> 47875 | CO5: =AY5*118% -> 316523.2 | CP5: =-Q5*118% -> -260001.2 | CQ5: =-BZ5*118% -> 165.2 | CR5: =-CA5*118% -> 135.7 | CS5: =SUM(CO5:CR5) -> 56822.9 | CT5: Telangana - HO | CU5: Telangana - HO | CV5: =MID(G5,3,10) -> ANHPG0363J | CW5: =MID(AR5,3,10) -> AAACM4154G
B6: ="Q" & IF(ROUNDUP(MONTH(D6)/3,0)-1=0,4,ROUNDUP(MONTH(D6)/3,0)-1) -> Q1 | C6: =TEXT(AN6,"mmm-yy") -> May-26 | D6: 46151 | E6: SH05260901 | F6: SRI PRASANNA TRADERS | G6: 37ANHPG0363J1Z1 | H6: 11 | I6: 46151 | J6: 26-27/PUR/001929 | K6: 46151 | L6: AD | M6: TG29T7657 | N6: Pyrolysis Char - Briquettes | O6: 17950 | P6: 11.5 | Q6: =O6*P6 -> 206425 | R6: 0 | S6: =O6-R6 -> 17950 | T6: 0 | U6: 0 | V6: 0 | W6: 0 | X6: 0 | Y6: 0 | Z6: 0 | AA6: 0 | AB6: =Y6+AA6+Z6 -> 0 | AC6: 0 | AD6: 0 | AE6: 0 | AF6: 36/AFR/27VC00013 | AG6: 46168 | AH6: 0 | AI6: 0 | AJ6: 0 | AK6: -460 | AL6: 0 | AM6: =Q6+AB6+AL6+AK6+AJ6+T6+AE6 -> 205965 | AN6: 46151 | AO6: 36/AFR/27IN00002 | AP6: 832139000056764186 | AQ6: MRF LIMITED (36) | AR6: 36AAACM4154G1ZO | AS6: Proddatur Andhra Pradesh 516360 | AT6: Sadashivpet | AU6: Telangana | AW6: 17950 | AX6: 14 | AY6: =AW6*AX6 -> 251300 | AZ6: =AW6=O6 -> TRUE | BA6: 0 | BB6: =AW6-BA6 -> 17950 | BC6: 0 | BD6: Regular | BE6: 0 | BF6: 0 | BG6: 0 | BH6: 36/AFR/27CN00013 | BI6: 46168 | BJ6: 0 | BK6: 0 | BL6: 0 | BM6: -560 | BN6: 0 | BO6: =AY6+BL6+BM6+BN6+BC6+BG6 -> 250740 | BP6: =BO6-AM6 -> 44775 | BQ6: =IF(BP6>=0,"Positive Margin","Negative Margin") -> Positive Margin | BR6: DN & CN Issued | BS6: =AY6-Y6-Q6-AA6-T6+BC6 -> 44875 | BT6: =IF(BS6<0, "Negative Margin at Inception", "Positive Margin at Inception") -> Positive Margin at Inception | BU6: =IFERROR(BP6/BO6,"0") -> 0.17857143 | BV6: =IF(BU6<1%,"Less Than 1%",IF(BU6>2%,"More than 2%",IF(BU6>=1%,"1% - 2%"))) -> More than 2% | BW6: =BM6+BN6 -> -560 | BX6: =AL6+AK6 -> -460 | BY6: =BW6-BX6 -> -100 | BZ6: =BM6 -> -560 | CA6: =AK6 -> -460 | CB6: =BZ6-CA6 -> -100 | CC6: Marketplace Purchases (AFR) | CD6: 0 | CE6: =TEXT(AN6,"mmm-yy") -> May-26 | CF6: =AM6-AL6-AA6 -> 205965 | CG6: =BO6-BN6 -> 250740 | CH6: =INT((D6- IF(MONTH(D6) >= 4, DATE(YEAR(D6), 4, 1), DATE(YEAR(D6)-1, 4, 1))) / 7) + 1 -> 6 | CI6: AFR | CJ6: AFR | CK6: 0 | CL6: =AY6-Q6 -> 44875 | CM6: =CL6-Y6+Z6 -> 44875 | CN6: =BO6-AM6 -> 44775 | CO6: =AY6*118% -> 296534 | CP6: =-Q6*118% -> -243581.5 | CQ6: =-BZ6*118% -> 660.8 | CR6: =-CA6*118% -> 542.8 | CS6: =SUM(CO6:CR6) -> 54156.1 | CT6: Telangana - HO | CU6: Telangana - HO | CV6: =MID(G6,3,10) -> ANHPG0363J | CW6: =MID(AR6,3,10) -> AAACM4154G
B7: ="Q" & IF(ROUNDUP(MONTH(D7)/3,0)-1=0,4,ROUNDUP(MONTH(D7)/3,0)-1) -> Q1 | C7: =TEXT(AN7,"mmm-yy") -> May-26 | D7: 46155 | E7: SH05261303 | F7: SRI PRASANNA TRADERS | G7: 37ANHPG0363J1Z1 | H7: 13 | I7: 46155 | J7: 26-27/PUR/002090 | K7: 46155 | L7: AD | M7: AP39WL0468 | N7: Pyrolysis Char - Briquettes | O7: 23980 | P7: 12 | Q7: =O7*P7 -> 287760 | R7: 0 | S7: =O7-R7 -> 23980 | T7: 0 | U7: 0 | V7: 0 | W7: 0 | X7: 0 | Y7: 0 | Z7: 0 | AA7: 0 | AB7: =Y7+AA7+Z7 -> 0 | AC7: 0 | AD7: 0 | AE7: 0 | AF7: 0 | AG7: 0 | AH7: 0 | AI7: 0 | AJ7: 0 | AK7: 0 | AL7: 0 | AM7: =Q7+AB7+AL7+AK7+AJ7+T7+AE7 -> 287760 | AN7: 46155 | AO7: 36/AFR/27IN00003 | AP7: 832139000056764186 | AQ7: MRF LIMITED (36) | AR7: 36AAACM4154G1ZO | AS7: Tadipatri,Andhra Pradesh,515413 | AT7: Sadashivpet | AU7: Telangana | AW7: 23980 | AX7: 12.66 | AY7: =AW7*AX7 -> 303586.8 | AZ7: =AW7=O7 -> TRUE | BA7: 0 | BB7: =AW7-BA7 -> 23980 | BC7: 0 | BD7: Regular | BE7: 0 | BF7: 0 | BG7: 0 | BH7: 0 | BI7: 0 | BJ7: 0 | BK7: 0 | BL7: 0 | BM7: 0 | BN7: 0 | BO7: =AY7+BL7+BM7+BN7+BC7+BG7 -> 303586.8 | BP7: =BO7-AM7 -> 15826.8 | BQ7: =IF(BP7>=0,"Positive Margin","Negative Margin") -> Positive Margin | BR7: No DN | BS7: =AY7-Y7-Q7-AA7-T7+BC7 -> 15826.8 | BT7: =IF(BS7<0, "Negative Margin at Inception", "Positive Margin at Inception") -> Positive Margin at Inception | BU7: =IFERROR(BP7/BO7,"0") -> 0.052132701 | BV7: =IF(BU7<1%,"Less Than 1%",IF(BU7>2%,"More than 2%",IF(BU7>=1%,"1% - 2%"))) -> More than 2% | BW7: =BM7+BN7 -> 0 | BX7: =AL7+AK7 -> 0 | BY7: =BW7-BX7 -> 0 | BZ7: =BM7 -> 0 | CA7: =AK7 -> 0 | CB7: =BZ7-CA7 -> 0 | CC7: Marketplace Purchases (AFR) | CD7: 0 | CE7: =TEXT(AN7,"mmm-yy") -> May-26 | CF7: =AM7-AL7-AA7 -> 287760 | CG7: =BO7-BN7 -> 303586.8 | CH7: =INT((D7- IF(MONTH(D7) >= 4, DATE(YEAR(D7), 4, 1), DATE(YEAR(D7)-1, 4, 1))) / 7) + 1 -> 7 | CI7: AFR | CJ7: AFR | CK7: 0 | CL7: =AY7-Q7 -> 15826.8 | CM7: =CL7-Y7+Z7 -> 15826.8 | CN7: =BO7-AM7 -> 15826.8 | CO7: =AY7*118% -> 358232.42 | CP7: =-Q7*118% -> -339556.8 | CQ7: =-BZ7*118% -> 0 | CR7: =-CA7*118% -> 0 | CS7: =SUM(CO7:CR7) -> 18675.624 | CT7: Telangana - HO | CU7: Telangana - HO | CV7: =MID(G7,3,10) -> ANHPG0363J | CW7: =MID(AR7,3,10) -> AAACM4154G
B8: ="Q" & IF(ROUNDUP(MONTH(D8)/3,0)-1=0,4,ROUNDUP(MONTH(D8)/3,0)-1) -> Q1 | C8: =TEXT(AN8,"mmm-yy") -> May-26 | D8: 46168 | E8: SH05262501 | F8: SRI PRASANNA TRADERS | G8: 37ANHPG0363J1Z1 | H8: 19 | I8: 46168 | J8: 26-27/PUR/002617 | K8: 46168 | L8: AD | M8: AP39WR1641 | N8: Pyrolysis Char - Briquettes | O8: 13870 | P8: 12 | Q8: =O8*P8 -> 166440 | R8: 0 | S8: =O8-R8 -> 13870 | T8: 0 | U8: 0 | V8: 0 | W8: 0 | X8: 0 | Y8: 0 | Z8: 0 | AA8: 0 | AB8: =Y8+AA8+Z8 -> 0 | AC8: 0 | AD8: 0 | AE8: 0 | AF8: 0 | AG8: 0 | AH8: 0 | AI8: 0 | AJ8: 0 | AK8: 0 | AL8: 0 | AM8: =Q8+AB8+AL8+AK8+AJ8+T8+AE8 -> 166440 | AN8: 46168 | AO8: 36/AFR/27IN00004 | AP8: 832139000056764186 | AQ8: MRF LIMITED (36) | AR8: 36AAACM4154G1ZO | AS8: Proddatur Andhra Pradesh 516360 | AT8: Sadashivpet | AU8: Telangana | AW8: 13870 | AX8: 12.66 | AY8: =AW8*AX8 -> 175594.2 | AZ8: =AW8=O8 -> TRUE | BA8: 0 | BB8: =AW8-BA8 -> 13870 | BC8: 0 | BD8: Regular | BE8: 0 | BF8: 0 | BG8: 0 | BH8: 0 | BI8: 0 | BJ8: 0 | BK8: 0 | BL8: 0 | BM8: 0 | BN8: 0 | BO8: =AY8+BL8+BM8+BN8+BC8+BG8 -> 175594.2 | BP8: =BO8-AM8 -> 9154.2 | BQ8: =IF(BP8>=0,"Positive Margin","Negative Margin") -> Positive Margin | BR8: No DN | BS8: =AY8-Y8-Q8-AA8-T8+BC8 -> 9154.2 | BT8: =IF(BS8<0, "Negative Margin at Inception", "Positive Margin at Inception") -> Positive Margin at Inception | BU8: =IFERROR(BP8/BO8,"0") -> 0.052132701 | BV8: =IF(BU8<1%,"Less Than 1%",IF(BU8>2%,"More than 2%",IF(BU8>=1%,"1% - 2%"))) -> More than 2% | BW8: =BM8+BN8 -> 0 | BX8: =AL8+AK8 -> 0 | BY8: =BW8-BX8 -> 0 | BZ8: =BM8 -> 0 | CA8: =AK8 -> 0 | CB8: =BZ8-CA8 -> 0 | CC8: Marketplace Purchases (AFR) | CD8: 0 | CE8: =TEXT(AN8,"mmm-yy") -> May-26 | CF8: =AM8-AL8-AA8 -> 166440 | CG8: =BO8-BN8 -> 175594.2 | CH8: =INT((D8- IF(MONTH(D8) >= 4, DATE(YEAR(D8), 4, 1), DATE(YEAR(D8)-1, 4, 1))) / 7) + 1 -> 8 | CI8: AFR | CJ8: AFR | CK8: 0 | CL8: =AY8-Q8 -> 9154.2 | CM8: =CL8-Y8+Z8 -> 9154.2 | CN8: =BO8-AM8 -> 9154.2 | CO8: =AY8*118% -> 207201.16 | CP8: =-Q8*118% -> -196399.2 | CQ8: =-BZ8*118% -> 0 | CR8: =-CA8*118% -> 0 | CS8: =SUM(CO8:CR8) -> 10801.956 | CT8: Telangana - HO | CU8: Telangana - HO | CV8: =MID(G8,3,10) -> ANHPG0363J | CW8: =MID(AR8,3,10) -> AAACM4154G
B9: ="Q" & IF(ROUNDUP(MONTH(D9)/3,0)-1=0,4,ROUNDUP(MONTH(D9)/3,0)-1) -> Q1 | C9: =TEXT(AN9,"mmm-yy") -> Jun-26 | D9: 46174 | E9: SH05262704 | F9: SRI RAGHAVENDRA CORPORATION | G9: 37AGCPV7437N2ZK | H9: INV-26-800 | I9: 46174 | J9: 26-27/PUR/003034 | K9: 46174 | L9: AD | M9: AP27Y5049 | N9: Chilli Husk | O9: 11960 | P9: 3.4 | Q9: =O9*P9 -> 40664 | R9: 0 | S9: =O9-R9 -> 11960 | T9: 0 | U9: 0 | V9: 0 | W9: 0 | X9: 0 | Y9: 0 | Z9: 0 | AA9: 0 | AB9: =Y9+AA9+Z9 -> 0 | AC9: 0 | AD9: 0 | AE9: 0 | AF9: 0 | AG9: 0 | AH9: 0 | AI9: 0 | AJ9: 0 | AK9: 0 | AL9: 0 | AM9: =Q9+AB9+AL9+AK9+AJ9+T9+AE9 -> 40664 | AN9: 46174 | AO9: 36/AFR/27IN00005 | AP9: 832139000078794413 | AQ9: ULTRATECH CEMENT LIMITED | AR9: 37AAACL6442L1Z9 | AS9: Guntur,Andhra Pradesh,522005 | AT9: Vijayawada | AU9: Andhra Pradesh | AW9: 11960 | AX9: 3.7 | AY9: =AW9*AX9 -> 44252 | AZ9: =AW9=O9 -> TRUE | BA9: 0 | BB9: =AW9-BA9 -> 11960 | BC9: 0 | BD9: Regular | BE9: 0 | BF9: 0 | BG9: 0 | BH9: 0 | BI9: 0 | BJ9: 0 | BK9: 0 | BL9: 0 | BM9: 0 | BN9: 0 | BO9: =AY9+BL9+BM9+BN9+BC9+BG9 -> 44252 | BP9: =BO9-AM9 -> 3588 | BQ9: =IF(BP9>=0,"Positive Margin","Negative Margin") -> Positive Margin | BR9: No Provision | BS9: =AY9-Y9-Q9-AA9-T9+BC9 -> 3588 | BT9: =IF(BS9<0, "Negative Margin at Inception", "Positive Margin at Inception") -> Positive Margin at Inception | BU9: =IFERROR(BP9/BO9,"0") -> 0.081081081 | BV9: =IF(BU9<1%,"Less Than 1%",IF(BU9>2%,"More than 2%",IF(BU9>=1%,"1% - 2%"))) -> More than 2% | BW9: =BM9+BN9 -> 0 | BX9: =AL9+AK9 -> 0 | BY9: =BW9-BX9 -> 0 | BZ9: =BM9 -> 0 | CA9: =AK9 -> 0 | CB9: =BZ9-CA9 -> 0 | CC9: Marketplace Purchases (AFR) | CD9: 0 | CE9: =TEXT(AN9,"mmm-yy") -> Jun-26 | CF9: =AM9-AL9-AA9 -> 40664 | CG9: =BO9-BN9 -> 44252 | CH9: =INT((D9- IF(MONTH(D9) >= 4, DATE(YEAR(D9), 4, 1), DATE(YEAR(D9)-1, 4, 1))) / 7) + 1 -> 9 | CI9: AFR | CJ9: AFR | CK9: 0 | CL9: =AY9-Q9 -> 3588 | CM9: =CL9-Y9+Z9 -> 3588 | CN9: =BO9-AM9 -> 3588 | CO9: =AY9*118% -> 52217.36 | CP9: =-Q9*118% -> -47983.52 | CQ9: =-BZ9*118% -> 0 | CR9: =-CA9*118% -> 0 | CS9: =SUM(CO9:CR9) -> 4233.84 | CT9: Telangana - HO | CU9: Telangana - HO | CV9: =MID(G9,3,10) -> AGCPV7437N | CW9: =MID(AR9,3,10) -> AAACL6442L
B10: ="Q" & IF(ROUNDUP(MONTH(D10)/3,0)-1=0,4,ROUNDUP(MONTH(D10)/3,0)-1) -> Q1 | C10: =TEXT(AN10,"mmm-yy") -> Jun-26 | D10: 46176 | E10: SH06260301 | F10: SRI RAGHAVENDRA CORPORATION | G10: 37AGCPV7437N2ZK | H10: INV-26-802 | I10: 46176 | J10: 26-27/PUR/003224 | K10: 46176 | L10: AD | M10: TS12UD3174 | N10: Chilli Husk | O10: 12010 | P10: 3.4 | Q10: =O10*P10 -> 40834 | R10: 0 | S10: =O10-R10 -> 12010 | T10: 0 | U10: 0 | V10: 0 | W10: 0 | X10: 0 | Y10: 0 | Z10: 0 | AA10: 0 | AB10: =Y10+AA10+Z10 -> 0 | AC10: 0 | AD10: 0 | AE10: 0 | AF10: 0 | AG10: 0 | AH10: 0 | AI10: 0 | AJ10: 0 | AK10: 0 | AL10: 0 | AM10: =Q10+AB10+AL10+AK10+AJ10+T10+AE10 -> 40834 | AN10: 46176 | AO10: 36/AFR/27IN00006 | AP10: 832139000078794413 | AQ10: ULTRATECH CEMENT LIMITED | AR10: 37AAACL6442L1Z9 | AS10: Guntur Andhra Pradesh 522005 | AT10: Vijayawada | AU10: Andhra Pradesh | AW10: 12010 | AX10: 3.7 | AY10: =AW10*AX10 -> 44437 | AZ10: =AW10=O10 -> TRUE | BA10: 0 | BB10: =AW10-BA10 -> 12010 | BC10: 0 | BD10: Regular | BE10: 0 | BF10: 0 | BG10: 0 | BH10: 0 | BI10: 0 | BJ10: 0 | BK10: 0 | BL10: 0 | BM10: 0 | BN10: 0 | BO10: =AY10+BL10+BM10+BN10+BC10+BG10 -> 44437 | BP10: =BO10-AM10 -> 3603 | BQ10: =IF(BP10>=0,"Positive Margin","Negative Margin") -> Positive Margin | BR10: No Provision | BS10: =AY10-Y10-Q10-AA10-T10+BC10 -> 3603 | BT10: =IF(BS10<0, "Negative Margin at Inception", "Positive Margin at Inception") -> Positive Margin at Inception | BU10: =IFERROR(BP10/BO10,"0") -> 0.081081081 | BV10: =IF(BU10<1%,"Less Than 1%",IF(BU10>2%,"More than 2%",IF(BU10>=1%,"1% - 2%"))) -> More than 2% | BW10: =BM10+BN10 -> 0 | BX10: =AL10+AK10 -> 0 | BY10: =BW10-BX10 -> 0 | BZ10: =BM10 -> 0 | CA10: =AK10 -> 0 | CB10: =BZ10-CA10 -> 0 | CC10: Marketplace Purchases (AFR) | CD10: 0 | CE10: =TEXT(AN10,"mmm-yy") -> Jun-26 | CF10: =AM10-AL10-AA10 -> 40834 | CG10: =BO10-BN10 -> 44437 | CH10: =INT((D10- IF(MONTH(D10) >= 4, DATE(YEAR(D10), 4, 1), DATE(YEAR(D10)-1, 4, 1))) / 7) + 1 -> 10 | CI10: AFR | CJ10: AFR | CK10: 0 | CL10: =AY10-Q10 -> 3603 | CM10: =CL10-Y10+Z10 -> 3603 | CN10: =BO10-AM10 -> 3603 | CO10: =AY10*118% -> 52435.66 | CP10: =-Q10*118% -> -48184.12 | CQ10: =-BZ10*118% -> 0 | CR10: =-CA10*118% -> 0 | CS10: =SUM(CO10:CR10) -> 4251.54 | CT10: Telangana - HO | CU10: Telangana - HO | CV10: =MID(G10,3,10) -> AGCPV7437N | CW10: =MID(AR10,3,10) -> AAACL6442L
B11: ="Q" & IF(ROUNDUP(MONTH(D11)/3,0)-1=0,4,ROUNDUP(MONTH(D11)/3,0)-1) -> Q1 | C11: =TEXT(AN11,"mmm-yy") -> Jun-26 | D11: 46176 | E11: SH06260302 | F11: SRI RAGHAVENDRA CORPORATION | G11: 37AGCPV7437N2ZK | H11: INV-26-801 | I11: 46176 | J11: 26-27/PUR/003226 | K11: 46176 | L11: AD | M11: TG05U6911 | N11: Chilli Husk | O11: 12015 | P11: 3.4 | Q11: =O11*P11 -> 40851 | R11: 0 | S11: =O11-R11 -> 12015 | T11: 0 | U11: 0 | V11: 0 | W11: 0 | X11: 0 | Y11: 0 | Z11: 0 | AA11: 0 | AB11: =Y11+AA11+Z11 -> 0 | AC11: 0 | AD11: 0 | AE11: 0 | AF11: 0 | AG11: 0 | AH11: 0 | AI11: 0 | AJ11: 0 | AK11: 0 | AL11: 0 | AM11: =Q11+AB11+AL11+AK11+AJ11+T11+AE11 -> 40851 | AN11: 46176 | AO11: 36/AFR/27IN00007 | AP11: 832139000078794413 | AQ11: ULTRATECH CEMENT LIMITED | AR11: 37AAACL6442L1Z9 | AS11: Guntur,Andhra Pradesh,522005 | AT11: Vijayawada | AU11: Andhra Pradesh | AW11: 12015 | AX11: 3.7 | AY11: =AW11*AX11 -> 44455.5 | AZ11: =AW11=O11 -> TRUE | BA11: 0 | BB11: =AW11-BA11 -> 12015 | BC11: 0 | BD11: Regular | BE11: 0 | BF11: 0 | BG11: 0 | BH11: 0 | BI11: 0 | BJ11: 0 | BK11: 0 | BL11: 0 | BM11: 0 | BN11: 0 | BO11: =AY11+BL11+BM11+BN11+BC11+BG11 -> 44455.5 | BP11: =BO11-AM11 -> 3604.5 | BQ11: =IF(BP11>=0,"Positive Margin","Negative Margin") -> Positive Margin | BR11: No Provision | BS11: =AY11-Y11-Q11-AA11-T11+BC11 -> 3604.5 | BT11: =IF(BS11<0, "Negative Margin at Inception", "Positive Margin at Inception") -> Positive Margin at Inception | BU11: =IFERROR(BP11/BO11,"0") -> 0.081081081 | BV11: =IF(BU11<1%,"Less Than 1%",IF(BU11>2%,"More than 2%",IF(BU11>=1%,"1% - 2%"))) -> More than 2% | BW11: =BM11+BN11 -> 0 | BX11: =AL11+AK11 -> 0 | BY11: =BW11-BX11 -> 0 | BZ11: =BM11 -> 0 | CA11: =AK11 -> 0 | CB11: =BZ11-CA11 -> 0 | CC11: Marketplace Purchases (AFR) | CD11: 0 | CE11: =TEXT(AN11,"mmm-yy") -> Jun-26 | CF11: =AM11-AL11-AA11 -> 40851 | CG11: =BO11-BN11 -> 44455.5 | CH11: =INT((D11- IF(MONTH(D11) >= 4, DATE(YEAR(D11), 4, 1), DATE(YEAR(D11)-1, 4, 1))) / 7) + 1 -> 10 | CI11: AFR | CJ11: AFR | CK11: 0 | CL11: =AY11-Q11 -> 3604.5 | CM11: =CL11-Y11+Z11 -> 3604.5 | CN11: =BO11-AM11 -> 3604.5 | CO11: =AY11*118% -> 52457.49 | CP11: =-Q11*118% -> -48204.18 | CQ11: =-BZ11*118% -> 0 | CR11: =-CA11*118% -> 0 | CS11: =SUM(CO11:CR11) -> 4253.31 | CT11: Telangana - HO | CU11: Telangana - HO | CV11: =MID(G11,3,10) -> AGCPV7437N | CW11: =MID(AR11,3,10) -> AAACL6442L
B12: ="Q" & IF(ROUNDUP(MONTH(D12)/3,0)-1=0,4,ROUNDUP(MONTH(D12)/3,0)-1) -> Q1 | C12: =TEXT(AN12,"mmm-yy") -> Jun-26 | D12: 46177 | E12: SH06260402 | F12: SRI PRASANNA TRADERS | G12: 37ANHPG0363J1Z1 | H12: 25 | I12: 46177 | J12: 26-27/PUR/003277 | K12: 46177 | L12: AD | M12: AP02TH1557 | N12: Pyrolysis Char - Briquettes | O12: 10380 | P12: 12 | Q12: =O12*P12 -> 124560 | R12: 0 | S12: =O12-R12 -> 10380 | T12: 0 | U12: 0 | V12: 0 | W12: 0 | X12: 0 | Y12: 0 | Z12: 0 | AA12: 0 | AB12: =Y12+AA12+Z12 -> 0 | AC12: 0 | AD12: 0 | AE12: 0 | AF12: 0 | AG12: 0 | AH12: 0 | AI12: 0 | AJ12: 0 | AK12: 0 | AL12: 0 | AM12: =Q12+AB12+AL12+AK12+AJ12+T12+AE12 -> 124560 | AN12: 46177 | AO12: 36/AFR/27IN00008 | AP12: 832139000056764186 | AQ12: MRF LIMITED (36) | AR12: 36AAACM4154G1ZO | AS12: Proddatur Andhra Pradesh 516360 | AT12: Sadashivpet | AU12: Telangana | AW12: 10380 | AX12: 12.66 | AY12: =AW12*AX12 -> 131410.8 | AZ12: =AW12=O12 -> TRUE | BA12: 0 | BB12: =AW12-BA12 -> 10380 | BC12: 0 | BD12: Regular | BE12: 0 | BF12: 0 | BG12: 0 | BH12: 0 | BI12: 0 | BJ12: 0 | BK12: 0 | BL12: 0 | BM12: 0 | BN12: 0 | BO12: =AY12+BL12+BM12+BN12+BC12+BG12 -> 131410.8 | BP12: =BO12-AM12 -> 6850.8 | BQ12: =IF(BP12>=0,"Positive Margin","Negative Margin") -> Positive Margin | BR12: No Provision | BS12: =AY12-Y12-Q12-AA12-T12+BC12 -> 6850.8 | BT12: =IF(BS12<0, "Negative Margin at Inception", "Positive Margin at Inception") -> Positive Margin at Inception | BU12: =IFERROR(BP12/BO12,"0") -> 0.052132701 | BV12: =IF(BU12<1%,"Less Than 1%",IF(BU12>2%,"More than 2%",IF(BU12>=1%,"1% - 2%"))) -> More than 2% | BW12: =BM12+BN12 -> 0 | BX12: =AL12+AK12 -> 0 | BY12: =BW12-BX12 -> 0 | BZ12: =BM12 -> 0 | CA12: =AK12 -> 0 | CB12: =BZ12-CA12 -> 0 | CC12: Marketplace Purchases (AFR) | CD12: 0 | CE12: =TEXT(AN12,"mmm-yy") -> Jun-26 | CF12: =AM12-AL12-AA12 -> 124560 | CG12: =BO12-BN12 -> 131410.8 | CH12: =INT((D12- IF(MONTH(D12) >= 4, DATE(YEAR(D12), 4, 1), DATE(YEAR(D12)-1, 4, 1))) / 7) + 1 -> 10 | CI12: AFR | CJ12: AFR | CK12: 0 | CL12: =AY12-Q12 -> 6850.8 | CM12: =CL12-Y12+Z12 -> 6850.8 | CN12: =BO12-AM12 -> 6850.8 | CO12: =AY12*118% -> 155064.74 | CP12: =-Q12*118% -> -146980.8 | CQ12: =-BZ12*118% -> 0 | CR12: =-CA12*118% -> 0 | CS12: =SUM(CO12:CR12) -> 8083.944 | CT12: Telangana - HO | CU12: Telangana - HO | CV12: =MID(G12,3,10) -> ANHPG0363J | CW12: =MID(AR12,3,10) -> AAACM4154G
B13: ="Q" & IF(ROUNDUP(MONTH(D13)/3,0)-1=0,4,ROUNDUP(MONTH(D13)/3,0)-1) -> Q1 | C13: =TEXT(AN13,"mmm-yy") -> Jun-26 | D13: 46180 | E13: SH06260602 | F13: SRI PRASANNA TRADERS | G13: 37ANHPG0363J1Z1 | H13: 26 | I13: 46180 | J13: 26-27/PUR/003302 | K13: 46180 | L13: AD | M13: AP39UL9769 | N13: Pyrolysis Char - Briquettes | O13: 14380 | P13: 12 | Q13: =O13*P13 -> 172560 | R13: 0 | S13: =O13-R13 -> 14380 | T13: 0 | U13: 0 | V13: 0 | W13: 0 | X13: 0 | Y13: 0 | Z13: 0 | AA13: 0 | AB13: =Y13+AA13+Z13 -> 0 | AC13: 0 | AD13: 0 | AE13: 0 | AF13: 0 | AG13: 0 | AH13: 0 | AI13: 0 | AJ13: 0 | AK13: 0 | AL13: 0 | AM13: =Q13+AB13+AL13+AK13+AJ13+T13+AE13 -> 172560 | AN13: 46180 | AO13: 36/AFR/27IN00009 | AP13: 832139000056764186 | AQ13: MRF LIMITED (36) | AR13: 36AAACM4154G1ZO | AS13: Proddatur Andhra Pradesh 516360 | AT13: Sadashivpet | AU13: Telangana | AW13: 14380 | AX13: 12.66 | AY13: =AW13*AX13 -> 182050.8 | AZ13: =AW13=O13 -> TRUE | BA13: 0 | BB13: =AW13-BA13 -> 14380 | BC13: 0 | BD13: Regular | BE13: 0 | BF13: 0 | BG13: 0 | BH13: 0 | BI13: 0 | BJ13: 0 | BK13: 0 | BL13: 0 | BM13: 0 | BN13: 0 | BO13: =AY13+BL13+BM13+BN13+BC13+BG13 -> 182050.8 | BP13: =BO13-AM13 -> 9490.8 | BQ13: =IF(BP13>=0,"Positive Margin","Negative Margin") -> Positive Margin | BR13: No Provision | BS13: =AY13-Y13-Q13-AA13-T13+BC13 -> 9490.8 | BT13: =IF(BS13<0, "Negative Margin at Inception", "Positive Margin at Inception") -> Positive Margin at Inception | BU13: =IFERROR(BP13/BO13,"0") -> 0.052132701 | BV13: =IF(BU13<1%,"Less Than 1%",IF(BU13>2%,"More than 2%",IF(BU13>=1%,"1% - 2%"))) -> More than 2% | BW13: =BM13+BN13 -> 0 | BX13: =AL13+AK13 -> 0 | BY13: =BW13-BX13 -> 0 | BZ13: =BM13 -> 0 | CA13: =AK13 -> 0 | CB13: =BZ13-CA13 -> 0 | CC13: Marketplace Purchases (AFR) | CD13: 0 | CE13: =TEXT(AN13,"mmm-yy") -> Jun-26 | CF13: =AM13-AL13-AA13 -> 172560 | CG13: =BO13-BN13 -> 182050.8 | CH13: =INT((D13- IF(MONTH(D13) >= 4, DATE(YEAR(D13), 4, 1), DATE(YEAR(D13)-1, 4, 1))) / 7) + 1 -> 10 | CI13: AFR | CJ13: AFR | CK13: 0 | CL13: =AY13-Q13 -> 9490.8 | CM13: =CL13-Y13+Z13 -> 9490.8 | CN13: =BO13-AM13 -> 9490.8 | CO13: =AY13*118% -> 214819.94 | CP13: =-Q13*118% -> -203620.8 | CQ13: =-BZ13*118% -> 0 | CR13: =-CA13*118% -> 0 | CS13: =SUM(CO13:CR13) -> 11199.144 | CT13: Telangana - HO | CU13: Telangana - HO | CV13: =MID(G13,3,10) -> ANHPG0363J | CW13: =MID(AR13,3,10) -> AAACM4154G
B14: ="Q" & IF(ROUNDUP(MONTH(D14)/3,0)-1=0,4,ROUNDUP(MONTH(D14)/3,0)-1) -> Q1 | C14: =TEXT(AN14,"mmm-yy") -> Jun-26 | D14: 46181 | E14: SH06260701 | F14: SRI RAGHAVENDRA CORPORATION | G14: 37AGCPV7437N2ZK | H14: INV-26-803 | I14: 46181 | J14: 26-27/PUR/003308 | K14: 46181 | L14: AD | M14: TG04T7342 | N14: Chilli Husk | O14: 8815 | P14: 3.4 | Q14: =O14*P14 -> 29971 | R14: 0 | S14: =O14-R14 -> 8815 | T14: 0 | U14: 0 | V14: 0 | W14: 0 | X14: 0 | Y14: 0 | Z14: 0 | AA14: 0 | AB14: =Y14+AA14+Z14 -> 0 | AC14: 0 | AD14: 0 | AE14: 0 | AF14: 0 | AG14: 0 | AH14: 0 | AI14: 0 | AJ14: 0 | AK14: 0 | AL14: 0 | AM14: =Q14+AB14+AL14+AK14+AJ14+T14+AE14 -> 29971 | AN14: 46181 | AO14: 36/AFR/27IN00010 | AP14: 832139000078794413 | AQ14: ULTRATECH CEMENT LIMITED | AR14: 37AAACL6442L1Z9 | AS14: Guntur,Andhra Pradesh,522005 | AT14: Vijayawada | AU14: Andhra Pradesh | AW14: 8815 | AX14: 3.7 | AY14: =AW14*AX14 -> 32615.5 | AZ14: =AW14=O14 -> TRUE | BA14: 0 | BB14: =AW14-BA14 -> 8815 | BC14: 0 | BD14: Regular | BE14: 0 | BF14: 0 | BG14: 0 | BH14: 0 | BI14: 0 | BJ14: 0 | BK14: 0 | BL14: 0 | BM14: 0 | BN14: 0 | BO14: =AY14+BL14+BM14+BN14+BC14+BG14 -> 32615.5 | BP14: =BO14-AM14 -> 2644.5 | BQ14: =IF(BP14>=0,"Positive Margin","Negative Margin") -> Positive Margin | BR14: No Provision | BS14: =AY14-Y14-Q14-AA14-T14+BC14 -> 2644.5 | BT14: =IF(BS14<0, "Negative Margin at Inception", "Positive Margin at Inception") -> Positive Margin at Inception | BU14: =IFERROR(BP14/BO14,"0") -> 0.081081081 | BV14: =IF(BU14<1%,"Less Than 1%",IF(BU14>2%,"More than 2%",IF(BU14>=1%,"1% - 2%"))) -> More than 2% | BW14: =BM14+BN14 -> 0 | BX14: =AL14+AK14 -> 0 | BY14: =BW14-BX14 -> 0 | BZ14: =BM14 -> 0 | CA14: =AK14 -> 0 | CB14: =BZ14-CA14 -> 0 | CC14: Marketplace Purchases (AFR) | CD14: 0 | CE14: =TEXT(AN14,"mmm-yy") -> Jun-26 | CF14: =AM14-AL14-AA14 -> 29971 | CG14: =BO14-BN14 -> 32615.5 | CH14: =INT((D14- IF(MONTH(D14) >= 4, DATE(YEAR(D14), 4, 1), DATE(YEAR(D14)-1, 4, 1))) / 7) + 1 -> 10 | CI14: AFR | CJ14: AFR | CK14: 0 | CL14: =AY14-Q14 -> 2644.5 | CM14: =CL14-Y14+Z14 -> 2644.5 | CN14: =BO14-AM14 -> 2644.5 | CO14: =AY14*118% -> 38486.29 | CP14: =-Q14*118% -> -35365.78 | CQ14: =-BZ14*118% -> 0 | CR14: =-CA14*118% -> 0 | CS14: =SUM(CO14:CR14) -> 3120.51 | CT14: Telangana - HO | CU14: Telangana - HO | CV14: =MID(G14,3,10) -> AGCPV7437N | CW14: =MID(AR14,3,10) -> AAACL6442L
B15: ="Q" & IF(ROUNDUP(MONTH(D15)/3,0)-1=0,4,ROUNDUP(MONTH(D15)/3,0)-1) -> Q1 | C15: =TEXT(AN15,"mmm-yy") -> Jun-26 | D15: 46181 | E15: SH06260802 | F15: SRI PRASANNA TRADERS | G15: 37ANHPG0363J1Z1 | H15: 27 | I15: 46181 | J15: 26-27/PUR/003337 | K15: 46181 | L15: AD | M15: AP39UV4495 | N15: Pyrolysis Char - Briquettes | O15: 13000 | P15: 12 | Q15: =O15*P15 -> 156000 | R15: 0 | S15: =O15-R15 -> 13000 | T15: 0 | U15: 0 | V15: 0 | W15: 0 | X15: 0 | Y15: 0 | Z15: 0 | AA15: 0 | AB15: =Y15+AA15+Z15 -> 0 | AC15: 0 | AD15: 0 | AE15: 0 | AF15: 0 | AG15: 0 | AH15: 0 | AI15: 0 | AJ15: 0 | AK15: 0 | AL15: 0 | AM15: =Q15+AB15+AL15+AK15+AJ15+T15+AE15 -> 156000 | AN15: 46181 | AO15: 36/AFR/27IN00011 | AP15: 832139000056764186 | AQ15: MRF LIMITED (36) | AR15: 36AAACM4154G1ZO | AS15: Proddatur Andhra Pradesh 516360 | AT15: Sadashivpet | AU15: Telangana | AW15: 13000 | AX15: 12.66 | AY15: =AW15*AX15 -> 164580 | AZ15: =AW15=O15 -> TRUE | BA15: 0 | BB15: =AW15-BA15 -> 13000 | BC15: 0 | BD15: Regular | BE15: 0 | BF15: 0 | BG15: 0 | BH15: 0 | BI15: 0 | BJ15: 0 | BK15: 0 | BL15: 0 | BM15: 0 | BN15: 0 | BO15: =AY15+BL15+BM15+BN15+BC15+BG15 -> 164580 | BP15: =BO15-AM15 -> 8580 | BQ15: =IF(BP15>=0,"Positive Margin","Negative Margin") -> Positive Margin | BR15: No Provision | BS15: =AY15-Y15-Q15-AA15-T15+BC15 -> 8580 | BT15: =IF(BS15<0, "Negative Margin at Inception", "Positive Margin at Inception") -> Positive Margin at Inception | BU15: =IFERROR(BP15/BO15,"0") -> 0.052132701 | BV15: =IF(BU15<1%,"Less Than 1%",IF(BU15>2%,"More than 2%",IF(BU15>=1%,"1% - 2%"))) -> More than 2% | BW15: =BM15+BN15 -> 0 | BX15: =AL15+AK15 -> 0 | BY15: =BW15-BX15 -> 0 | BZ15: =BM15 -> 0 | CA15: =AK15 -> 0 | CB15: =BZ15-CA15 -> 0 | CC15: Marketplace Purchases (AFR) | CD15: 0 | CE15: =TEXT(AN15,"mmm-yy") -> Jun-26 | CF15: =AM15-AL15-AA15 -> 156000 | CG15: =BO15-BN15 -> 164580 | CH15: =INT((D15- IF(MONTH(D15) >= 4, DATE(YEAR(D15), 4, 1), DATE(YEAR(D15)-1, 4, 1))) / 7) + 1 -> 10 | CI15: AFR | CJ15: AFR | CK15: 0 | CL15: =AY15-Q15 -> 8580 | CM15: =CL15-Y15+Z15 -> 8580 | CN15: =BO15-AM15 -> 8580 | CO15: =AY15*118% -> 194204.4 | CP15: =-Q15*118% -> -184080 | CQ15: =-BZ15*118% -> 0 | CR15: =-CA15*118% -> 0 | CS15: =SUM(CO15:CR15) -> 10124.4 | CT15: Telangana - HO | CU15: Telangana - HO | CV15: =MID(G15,3,10) -> ANHPG0363J | CW15: =MID(AR15,3,10) -> AAACM4154G
B16: ="Q" & IF(ROUNDUP(MONTH(D16)/3,0)-1=0,4,ROUNDUP(MONTH(D16)/3,0)-1) -> Q1 | C16: =TEXT(AN16,"mmm-yy") -> Jun-26 | D16: 46186 | E16: SH06261301 | F16: SRI PRASANNA TRADERS | G16: 37ANHPG0363J1Z1 | H16: 32 | I16: 46186 | J16: 26-27/PUR/003646 | K16: 46186 | L16: AD | M16: AP39UN1375 | N16: Pyrolysis Char - Briquettes | O16: 15220 | P16: 12 | Q16: =O16*P16 -> 182640 | R16: 0 | S16: =O16-R16 -> 15220 | T16: 0 | U16: 0 | V16: 0 | W16: 0 | X16: 0 | Y16: 0 | Z16: 0 | AA16: 0 | AB16: =Y16+AA16+Z16 -> 0 | AC16: 0 | AD16: 0 | AE16: 0 | AF16: 0 | AG16: 0 | AH16: 0 | AI16: 0 | AJ16: 0 | AK16: 0 | AL16: 0 | AM16: =Q16+AB16+AL16+AK16+AJ16+T16+AE16 -> 182640 | AN16: 46186 | AO16: 36/AFR/27IN00012 | AP16: 832139000056764186 | AQ16: MRF LIMITED (36) | AR16: 36AAACM4154G1ZO | AS16: Proddatur,Andhra Pradesh,516360 | AT16: Sadashivpet | AU16: Telangana | AW16: 15220 | AX16: 12.66 | AY16: =AW16*AX16 -> 192685.2 | AZ16: =AW16=O16 -> TRUE | BA16: 0 | BB16: =AW16-BA16 -> 15220 | BC16: 0 | BD16: Regular | BE16: 0 | BF16: 0 | BG16: 0 | BH16: 0 | BI16: 0 | BJ16: 0 | BK16: 0 | BL16: 0 | BM16: 0 | BN16: 0 | BO16: =AY16+BL16+BM16+BN16+BC16+BG16 -> 192685.2 | BP16: =BO16-AM16 -> 10045.2 | BQ16: =IF(BP16>=0,"Positive Margin","Negative Margin") -> Positive Margin | BR16: No Provision | BS16: =AY16-Y16-Q16-AA16-T16+BC16 -> 10045.2 | BT16: =IF(BS16<0, "Negative Margin at Inception", "Positive Margin at Inception") -> Positive Margin at Inception | BU16: =IFERROR(BP16/BO16,"0") -> 0.052132701 | BV16: =IF(BU16<1%,"Less Than 1%",IF(BU16>2%,"More than 2%",IF(BU16>=1%,"1% - 2%"))) -> More than 2% | BW16: =BM16+BN16 -> 0 | BX16: =AL16+AK16 -> 0 | BY16: =BW16-BX16 -> 0 | BZ16: =BM16 -> 0 | CA16: =AK16 -> 0 | CB16: =BZ16-CA16 -> 0 | CC16: Marketplace Purchases (AFR) | CD16: 0 | CE16: =TEXT(AN16,"mmm-yy") -> Jun-26 | CF16: =AM16-AL16-AA16 -> 182640 | CG16: =BO16-BN16 -> 192685.2 | CH16: =INT((D16- IF(MONTH(D16) >= 4, DATE(YEAR(D16), 4, 1), DATE(YEAR(D16)-1, 4, 1))) / 7) + 1 -> 11 | CI16: AFR | CJ16: AFR | CK16: 0 | CL16: =AY16-Q16 -> 10045.2 | CM16: =CL16-Y16+Z16 -> 10045.2 | CN16: =BO16-AM16 -> 10045.2 | CO16: =AY16*118% -> 227368.54 | CP16: =-Q16*118% -> -215515.2 | CQ16: =-BZ16*118% -> 0 | CR16: =-CA16*118% -> 0 | CS16: =SUM(CO16:CR16) -> 11853.336 | CT16: Telangana - HO | CU16: Telangana - HO | CV16: =MID(G16,3,10) -> ANHPG0363J | CW16: =MID(AR16,3,10) -> AAACM4154G
B17: ="Q" & IF(ROUNDUP(MONTH(D17)/3,0)-1=0,4,ROUNDUP(MONTH(D17)/3,0)-1) -> Q1 | C17: =TEXT(AN17,"mmm-yy") -> Jun-26 | D17: 46191 | E17: SH06261606 | F17: SRI PRASANNA TRADERS | G17: 37ANHPG0363J1Z1 | H17: 36 | I17: 46191 | J17: 26-27/PUR/003921 | K17: 46191 | L17: AD | M17: AP39WH8039 | N17: Pyrolysis Char - Briquettes | O17: 15130 | P17: 12 | Q17: =O17*P17 -> 181560 | R17: 0 | S17: =O17-R17 -> 15130 | T17: 0 | U17: 0 | V17: 0 | W17: 0 | X17: 0 | Y17: 0 | Z17: 0 | AA17: 0 | AB17: =Y17+AA17+Z17 -> 0 | AC17: 0 | AD17: 0 | AE17: 0 | AF17: 0 | AG17: 0 | AH17: 0 | AI17: 0 | AJ17: 0 | AK17: 0 | AL17: 0 | AM17: =Q17+AB17+AL17+AK17+AJ17+T17+AE17 -> 181560 | AN17: 46191 | AO17: 36/AFR/27IN00013 | AP17: 832139000056764186 | AQ17: MRF LIMITED (36) | AR17: 36AAACM4154G1ZO | AS17: Proddatur Andhra Pradesh 516360 | AT17: Sadashivpet | AU17: Telangana | AW17: 15130 | AX17: 12.66 | AY17: =AW17*AX17 -> 191545.8 | AZ17: =AW17=O17 -> TRUE | BA17: 0 | BB17: =AW17-BA17 -> 15130 | BC17: 0 | BD17: Regular | BE17: 0 | BF17: 0 | BG17: 0 | BH17: 0 | BI17: 0 | BJ17: 0 | BK17: 0 | BL17: 0 | BM17: 0 | BN17: 0 | BO17: =AY17+BL17+BM17+BN17+BC17+BG17 -> 191545.8 | BP17: =BO17-AM17 -> 9985.8 | BQ17: =IF(BP17>=0,"Positive Margin","Negative Margin") -> Positive Margin | BR17: No Provision | BS17: =AY17-Y17-Q17-AA17-T17+BC17 -> 9985.8 | BT17: =IF(BS17<0, "Negative Margin at Inception", "Positive Margin at Inception") -> Positive Margin at Inception | BU17: =IFERROR(BP17/BO17,"0") -> 0.052132701 | BV17: =IF(BU17<1%,"Less Than 1%",IF(BU17>2%,"More than 2%",IF(BU17>=1%,"1% - 2%"))) -> More than 2% | BW17: =BM17+BN17 -> 0 | BX17: =AL17+AK17 -> 0 | BY17: =BW17-BX17 -> 0 | BZ17: =BM17 -> 0 | CA17: =AK17 -> 0 | CB17: =BZ17-CA17 -> 0 | CC17: Marketplace Purchases (AFR) | CD17: 0 | CE17: =TEXT(AN17,"mmm-yy") -> Jun-26 | CF17: =AM17-AL17-AA17 -> 181560 | CG17: =BO17-BN17 -> 191545.8 | CH17: =INT((D17- IF(MONTH(D17) >= 4, DATE(YEAR(D17), 4, 1), DATE(YEAR(D17)-1, 4, 1))) / 7) + 1 -> 12 | CI17: AFR | CJ17: AFR | CK17: 0 | CL17: =AY17-Q17 -> 9985.8 | CM17: =CL17-Y17+Z17 -> 9985.8 | CN17: =BO17-AM17 -> 9985.8 | CO17: =AY17*118% -> 226024.04 | CP17: =-Q17*118% -> -214240.8 | CQ17: =-BZ17*118% -> 0 | CR17: =-CA17*118% -> 0 | CS17: =SUM(CO17:CR17) -> 11783.244 | CT17: Telangana - HO | CU17: Telangana - HO | CV17: =MID(G17,3,10) -> ANHPG0363J | CW17: =MID(AR17,3,10) -> AAACM4154G
F19: Total | O19: =SUBTOTAL(9,O5:O18) -> 187870 | Q19: =SUBTOTAL(9,Q5:Q18) -> 1850605 | S19: =SUBTOTAL(9,S5:S18) -> 187870 | T19: =SUBTOTAL(9,T5:T18) -> 0 | Y19: =SUBTOTAL(9,Y5:Y18) -> 0 | Z19: =SUBTOTAL(9,Z5:Z18) -> 0 | AA19: =SUBTOTAL(9,AA5:AA18) -> 0 | AB19: =SUBTOTAL(9,AB5:AB18) -> 0 | AC19: =SUBTOTAL(9,AC5:AC18) -> 0 | AD19: =SUBTOTAL(1,AD5:AD18) -> 0 | AE19: =SUBTOTAL(9,AE5:AE18) -> 0 | AJ19: =SUBTOTAL(9,AJ5:AJ18) -> 0 | AK19: =SUBTOTAL(9,AK5:AK18) -> -575 | AL19: =SUBTOTAL(9,AL5:AL18) -> 0 | AM19: =SUBTOTAL(9,AM5:AM18) -> 1850030 | AW19: =SUBTOTAL(9,AW5:AW18) -> 187870 | AX19: =SUBTOTAL(101,AX5:AX18) -> 10.109231 | AY19: =SUBTOTAL(9,AY5:AY18) -> 2026753.6 | BA19: =SUBTOTAL(9,BA5:BA18) -> 0 | BB19: =SUBTOTAL(9,BB5:BB18) -> 187870 | BC19: =SUBTOTAL(9,BC5:BC18) -> 0 | BG19: =SUBTOTAL(9,BG5:BG18) -> 0 | BL19: =SUBTOTAL(9,BL5:BL18) -> 0 | BM19: =SUBTOTAL(9,BM5:BM18) -> -700 | BN19: =SUBTOTAL(9,BN5:BN18) -> 0 | BO19: =SUBTOTAL(9,BO5:BO18) -> 2026053.6 | BP19: =SUBTOTAL(9,BP5:BP18) -> 176023.6 | BS19: =SUBTOTAL(9,BS5:BS18) -> 176148.6 | BW19: =SUBTOTAL(9,BV1:BV18) -> 0 | BX19: =SUBTOTAL(9,BW1:BW18) -> -700 | BY19: =SUBTOTAL(9,BX1:BX18) -> -575 | BZ19: =SUBTOTAL(9,BY1:BY18) -> -125 | CA19: =SUBTOTAL(9,BZ1:BZ18) -> -700 | CB19: =SUBTOTAL(9,CA1:CA18) -> -575 | CF19: =SUBTOTAL(9,CE1:CE18) -> 0 | CG19: =SUBTOTAL(9,CF1:CF18) -> 1850030 | CL19: =SUBTOTAL(9,CK1:CK18) -> 0 | CM19: =SUBTOTAL(9,CL1:CL18) -> 176148.6 | CN19: =SUBTOTAL(9,CM1:CM18) -> 176148.6 | CO19: =SUBTOTAL(9,CN1:CN18) -> 176023.6 | CP19: =SUBTOTAL(9,CO1:CO18) -> 2391569.2 | CQ19: =SUBTOTAL(9,CP1:CP18) -> -2183713.9 | CR19: =SUBTOTAL(9,CQ1:CQ18) -> 826 | CS19: =SUBTOTAL(9,CR1:CR18) -> 678.5
N20: =O19-AW19 -> 0 | P20: =Q19+AK19+AJ19+AL19+T19+AE19 -> 1850030 | AA20: =AB19/AY19 -> 0 | BK20: =BK21/AY19 -> 0 | BN20: =BP19/BO19 -> 0.086880031 | BR20: =BS19/AY19 -> 0.0869117 | BX20: =BX19/BW19 -> #DIV/0! | CA20: =IFERROR(CA19/BZ19,0) -> 5.6 | CD20: With GST | CE20: =CF19*118% -> 0 | CF20: =CG19*118% -> 2183035.4
AC21: =+AL19+AK19 -> -575
B23: Quarter | C23: Month | D23: Date | E23: Shipment ID | F23: Supplier Name | G23: GST Reg No. | H23: Vendor Invoice No. | I23: Vendor Invoice Date | J23: P V No. | K23: P V Date | L23: State (Origin) | M23: Vehicle No. | N23: Material | O23: Qty (Kg) | P23: Price/Kg | Q23: Purchase Price | R23: Return Qty | S23: Net Qty | T23: Basic Customs Duty | U23: Transporter Name | V23: LR NO/BILL NO | W23: J V No. | X23: JV Date | Y23: Logistics cost | Z23: Debit note on logistic cost | AA23: Logistics Provision | AB23: Total Logistics Cost | AC23: Opeartional Cost | AD23: Cost/Kg. | AE23: Divertion/Internal | AF23: Debit Note No. | AG23: Debit Note Date. | AH23: Debit Note No. 2 | AI23: Debit Note Date. 2 | AJ23: Full Debit Note | AK23: Actual Debit Note | AL23: Provision for DN | AM23: Total Cost | AN23: Inv. Date | AO23: Inv. No. | AP23: Customer ID | AQ23: Buyer Name | AR23: Buyer GST Number | AS23: Location (Origin) | AT23: Location (Destination) | AU23: State (Destination) | AV23: E-way Bill No | AW23: Qty(Kg) | AX23: Rate/Kg | AY23: Amount | AZ23: Qty Check | BA23: Return Qty | BB23: Net Qty | BC23: Divertion/Internal | BD23: Return Type | BE23: Date : DN to Buyer | BF23: DN to Buyer | BG23: Amount | BH23: Credit Note No:1 | BI23: CN Date. No:1 | BJ23: Credit Note No:2 | BK23: CN Date. No:2 | BL23: Full Credit Notes | BM23: Actual Credit Note | BN23: Provision for CN | BO23: Net Revenue | BP23: Margin | BQ23: Reamrks - Margin | BR23: Remarks | BS23: LMI @ Inception | BT23: Remarks @ Inception | BU23: Margin (%) | BV23: Margin Bucket | BW23: Total CN(Inc.Provisions) | BX23: Total DN(Inc.Provisions) | BY23: Check | BZ23: Actaul CN | CA23: Actual DN | CB23: Check | CC23: Material-Short Form | CD23: Supplier Type | CE23: Month | CF23: Cost | CG23: Revenue | CH23: Week No: | CI23: Category (Material) | CJ23: Broad Category | CK23: POC Name | CL23: Gross Margin | CM23: Recykal Margin | CN23: Net Margin | CO23: Sales | CP23: Purchases | CQ23: Credit Note | CR23: Debit Note | CS23: Margin | CT23: Bill Branch | CU23: Inv Branch | CV23: Vendor PAN No | CW23: Customer PAN No
B24: ="Q" & IF(ROUNDUP(MONTH(D24)/3,0)-1=0,4,ROUNDUP(MONTH(D24)/3,0)-1) -> Q1 | C24: =TEXT(AN24,"mmm-yy") -> Apr-26 | D24: 46133 | F24: TIMES MARINE SERVICES PRIVATE LIMITED | G24: 33AAICT1418L1ZB | H24: TMSPL/047 | I24: 46133 | J24: 26-27/PUR/001067 | K24: 46133 | L24: TN | N24: Technical Testing and Analysis Services | O24: 4 | P24: 20000 | Q24: =O24*P24 -> 80000 | R24: 0 | S24: =O24-R24 -> 4 | T24: 0 | U24: 0 | V24: 0 | W24: 0 | X24: 0 | Y24: 0 | Z24: 0 | AA24: 0 | AB24: =Y24+AA24+Z24 -> 0 | AC24: 0 | AD24: 0 | AE24: 0 | AF24: 0 | AG24: 0 | AH24: 0 | AI24: 0 | AJ24: 0 | AK24: 0 | AL24: 0 | AM24: =Q24+AB24+AL24+AK24+AJ24+T24+AE24 -> 80000 | AN24: =D24 -> 46133 | AO24: 0 | AP24: 0 | AQ24: 0 | AR24: 0 | AS24: 0 | AT24: 0 | AU24: 0 | AV24: 0 | AW24: 0 | AX24: 0 | AY24: =AW24*AX24 -> 0 | AZ24: =AW24=O24 -> FALSE | BA24: 0 | BB24: =AW24-BA24 -> 0 | BC24: 0 | BD24: Regular | BE24: 0 | BF24: 0 | BG24: 0 | BH24: 0 | BI24: 0 | BJ24: 0 | BK24: 0 | BL24: 0 | BM24: 0 | BN24: 0 | BO24: =AY24+BL24+BM24+BN24+BC24+BG24 -> 0 | BP24: =BO24-AM24 -> -80000 | BQ24: =IF(BP24>=0,"Positive Margin","Negative Margin") -> Negative Margin | BR24: No Provision | BS24: =AY24-Y24-Q24-AA24-T24+BC24 -> -80000 | BT24: =IF(BS24<0, "Negative Margin at Inception", "Positive Margin at Inception") -> Negative Margin at Inception | BU24: =IFERROR(BP24/BO24,"0") -> 0 | BV24: =IF(BU24<1%,"Less Than 1%",IF(BU24>2%,"More than 2%",IF(BU24>=1%,"1% - 2%"))) -> More than 2% | BW24: =BM24+BN24 -> 0 | BX24: =AL24+AK24 -> 0 | BY24: =BW24-BX24 -> 0 | BZ24: =BM24 -> 0 | CA24: =AK24 -> 0 | CB24: =BZ24-CA24 -> 0 | CC24: Marketplace Purchases (AFR) | CD24: 0 | CE24: =TEXT(AN24,"mmm-yy") -> Apr-26 | CF24: =AM24-AL24-AA24 -> 80000 | CG24: =BO24-BN24 -> 0 | CH24: =INT((D24- IF(MONTH(D24) >= 4, DATE(YEAR(D24), 4, 1), DATE(YEAR(D24)-1, 4, 1))) / 7) + 1 -> 3 | CI24: AFR | CJ24: AFR | CK24: 0 | CL24: =AY24-Q24 -> -80000 | CM24: =CL24-Y24+Z24 -> -80000 | CN24: =BO24-AM24 -> -80000 | CO24: =AY24*118% -> 0 | CP24: =-Q24*118% -> -94400 | CQ24: =-BZ24*118% -> 0 | CR24: =-CA24*118% -> 0 | CS24: =SUM(CO24:CR24) -> -94400 | CT24: Telangana - HO | CU24: Telangana - HO | CV24: =MID(G24,3,10) -> AAICT1418L | CW24: =MID(AR24,3,10)
B25: ="Q" & IF(ROUNDUP(MONTH(D25)/3,0)-1=0,4,ROUNDUP(MONTH(D25)/3,0)-1) -> Q1 | C25: =TEXT(AN25,"mmm-yy") -> Apr-26 | D25: 46133 | F25: SRI PRASANNA TRADERS | G25: 37ANHPG0363J1Z1 | H25: 143 | I25: 46098 | J25: 26-27/PUR/001059 | K25: 46133 | L25: AD | N25: Electrical Installation Service | O25: 1 | P25: 49905 | Q25: =O25*P25 -> 49905 | R25: 0 | S25: =O25-R25 -> 1 | T25: 0 | U25: 0 | V25: 0 | W25: 0 | X25: 0 | Y25: 0 | Z25: 0 | AA25: 0 | AB25: =Y25+AA25+Z25 -> 0 | AC25: 0 | AD25: 0 | AE25: 0 | AF25: 0 | AG25: 0 | AH25: 0 | AI25: 0 | AJ25: 0 | AK25: 0 | AL25: 0 | AM25: =Q25+AB25+AL25+AK25+AJ25+T25+AE25 -> 49905 | AN25: =D25 -> 46133 | AO25: 0 | AP25: 0 | AQ25: 0 | AR25: 0 | AS25: 0 | AT25: 0 | AU25: 0 | AV25: 0 | AW25: 0 | AX25: 0 | AY25: =AW25*AX25 -> 0 | AZ25: =AW25=O25 -> FALSE | BA25: 0 | BB25: =AW25-BA25 -> 0 | BC25: 0 | BD25: Regular | BE25: 0 | BF25: 0 | BG25: 0 | BH25: 0 | BI25: 0 | BJ25: 0 | BK25: 0 | BL25: 0 | BM25: 0 | BN25: 0 | BO25: =AY25+BL25+BM25+BN25+BC25+BG25 -> 0 | BP25: =BO25-AM25 -> -49905 | BQ25: =IF(BP25>=0,"Positive Margin","Negative Margin") -> Negative Margin | BR25: No Provision | BS25: =AY25-Y25-Q25-AA25-T25+BC25 -> -49905 | BT25: =IF(BS25<0, "Negative Margin at Inception", "Positive Margin at Inception") -> Negative Margin at Inception | BU25: =IFERROR(BP25/BO25,"0") -> 0 | BV25: =IF(BU25<1%,"Less Than 1%",IF(BU25>2%,"More than 2%",IF(BU25>=1%,"1% - 2%"))) -> More than 2% | BW25: =BM25+BN25 -> 0 | BX25: =AL25+AK25 -> 0 | BY25: =BW25-BX25 -> 0 | BZ25: =BM25 -> 0 | CA25: =AK25 -> 0 | CB25: =BZ25-CA25 -> 0 | CC25: Marketplace Purchases (AFR) | CD25: 0 | CE25: =TEXT(AN25,"mmm-yy") -> Apr-26 | CF25: =AM25-AL25-AA25 -> 49905 | CG25: =BO25-BN25 -> 0 | CH25: =INT((D25- IF(MONTH(D25) >= 4, DATE(YEAR(D25), 4, 1), DATE(YEAR(D25)-1, 4, 1))) / 7) + 1 -> 3 | CI25: AFR | CJ25: AFR | CK25: 0 | CL25: =AY25-Q25 -> -49905 | CM25: =CL25-Y25+Z25 -> -49905 | CN25: =BO25-AM25 -> -49905 | CO25: =AY25*118% -> 0 | CP25: =-Q25*118% -> -58887.9 | CQ25: =-BZ25*118% -> 0 | CR25: =-CA25*118% -> 0 | CS25: =SUM(CO25:CR25) -> -58887.9 | CT25: Telangana - HO | CU25: Telangana - HO | CV25: =MID(G25,3,10) -> ANHPG0363J | CW25: =MID(AR25,3,10)
B26: ="Q" & IF(ROUNDUP(MONTH(D26)/3,0)-1=0,4,ROUNDUP(MONTH(D26)/3,0)-1) -> Q1 | C26: =TEXT(AN26,"mmm-yy") -> Apr-26 | D26: 46133 | F26: SRI PRASANNA TRADERS | G26: 37ANHPG0363J1Z1 | H26: 144 | I26: 46098 | J26: 26-27/PUR/001060 | K26: 46133 | L26: AD | N26: Manpower Services | O26: 1 | P26: 133200 | Q26: =O26*P26 -> 133200 | R26: 0 | S26: =O26-R26 -> 1 | T26: 0 | U26: 0 | V26: 0 | W26: 0 | X26: 0 | Y26: 0 | Z26: 0 | AA26: 0 | AB26: =Y26+AA26+Z26 -> 0 | AC26: 0 | AD26: 0 | AE26: 0 | AF26: 0 | AG26: 0 | AH26: 0 | AI26: 0 | AJ26: 0 | AK26: 0 | AL26: 0 | AM26: =Q26+AB26+AL26+AK26+AJ26+T26+AE26 -> 133200 | AN26: =D26 -> 46133 | AO26: 0 | AP26: 0 | AQ26: 0 | AR26: 0 | AS26: 0 | AT26: 0 | AU26: 0 | AV26: 0 | AW26: 0 | AX26: 0 | AY26: =AW26*AX26 -> 0 | AZ26: =AW26=O26 -> FALSE | BA26: 0 | BB26: =AW26-BA26 -> 0 | BC26: 0 | BD26: Regular | BE26: 0 | BF26: 0 | BG26: 0 | BH26: 0 | BI26: 0 | BJ26: 0 | BK26: 0 | BL26: 0 | BM26: 0 | BN26: 0 | BO26: =AY26+BL26+BM26+BN26+BC26+BG26 -> 0 | BP26: =BO26-AM26 -> -133200 | BQ26: =IF(BP26>=0,"Positive Margin","Negative Margin") -> Negative Margin | BR26: No Provision | BS26: =AY26-Y26-Q26-AA26-T26+BC26 -> -133200 | BT26: =IF(BS26<0, "Negative Margin at Inception", "Positive Margin at Inception") -> Negative Margin at Inception | BU26: =IFERROR(BP26/BO26,"0") -> 0 | BV26: =IF(BU26<1%,"Less Than 1%",IF(BU26>2%,"More than 2%",IF(BU26>=1%,"1% - 2%"))) -> More than 2% | BW26: =BM26+BN26 -> 0 | BX26: =AL26+AK26 -> 0 | BY26: =BW26-BX26 -> 0 | BZ26: =BM26 -> 0 | CA26: =AK26 -> 0 | CB26: =BZ26-CA26 -> 0 | CC26: Marketplace Purchases (AFR) | CD26: 0 | CE26: =TEXT(AN26,"mmm-yy") -> Apr-26 | CF26: =AM26-AL26-AA26 -> 133200 | CG26: =BO26-BN26 -> 0 | CH26: =INT((D26- IF(MONTH(D26) >= 4, DATE(YEAR(D26), 4, 1), DATE(YEAR(D26)-1, 4, 1))) / 7) + 1 -> 3 | CI26: AFR | CJ26: AFR | CK26: 0 | CL26: =AY26-Q26 -> -133200 | CM26: =CL26-Y26+Z26 -> -133200 | CN26: =BO26-AM26 -> -133200 | CO26: =AY26*118% -> 0 | CP26: =-Q26*118% -> -157176 | CQ26: =-BZ26*118% -> 0 | CR26: =-CA26*118% -> 0 | CS26: =SUM(CO26:CR26) -> -157176 | CT26: Telangana - HO | CU26: Telangana - HO | CV26: =MID(G26,3,10) -> ANHPG0363J | CW26: =MID(AR26,3,10)
B27: ="Q" & IF(ROUNDUP(MONTH(D27)/3,0)-1=0,4,ROUNDUP(MONTH(D27)/3,0)-1) -> Q1 | C27: =TEXT(AN27,"mmm-yy") -> Apr-26 | D27: 46136 | F27: SRI PRASANNA TRADERS | G27: 37ANHPG0363J1Z1 | H27: 6 | I27: 46136 | J27: 26-27/PUR/001354 | K27: 46136 | L27: AD | N27: Bentonite Powder | O27: 3810 | P27: 7.1 | Q27: =O27*P27 -> 27051 | R27: 0 | S27: =O27-R27 -> 3810 | T27: 0 | U27: 0 | V27: 0 | W27: 0 | X27: 0 | Y27: 0 | Z27: 0 | AA27: 0 | AB27: =Y27+AA27+Z27 -> 0 | AC27: 0 | AD27: 0 | AE27: 0 | AF27: 0 | AG27: 0 | AH27: 0 | AI27: 0 | AJ27: 0 | AK27: 0 | AL27: 0 | AM27: =Q27+AB27+AL27+AK27+AJ27+T27+AE27 -> 27051 | AN27: =D27 -> 46136 | AO27: 0 | AP27: 0 | AQ27: 0 | AR27: 0 | AS27: 0 | AT27: 0 | AU27: 0 | AV27: 0 | AW27: 0 | AX27: 0 | AY27: =AW27*AX27 -> 0 | AZ27: =AW27=O27 -> FALSE | BA27: 0 | BB27: =AW27-BA27 -> 0 | BC27: 0 | BD27: Regular | BE27: 0 | BF27: 0 | BG27: 0 | BH27: 0 | BI27: 0 | BJ27: 0 | BK27: 0 | BL27: 0 | BM27: 0 | BN27: 0 | BO27: =AY27+BL27+BM27+BN27+BC27+BG27 -> 0 | BP27: =BO27-AM27 -> -27051 | BQ27: =IF(BP27>=0,"Positive Margin","Negative Margin") -> Negative Margin | BR27: No Provision | BS27: =AY27-Y27-Q27-AA27-T27+BC27 -> -27051 | BT27: =IF(BS27<0, "Negative Margin at Inception", "Positive Margin at Inception") -> Negative Margin at Inception | BU27: =IFERROR(BP27/BO27,"0") -> 0 | BV27: =IF(BU27<1%,"Less Than 1%",IF(BU27>2%,"More than 2%",IF(BU27>=1%,"1% - 2%"))) -> More than 2% | BW27: =BM27+BN27 -> 0 | BX27: =AL27+AK27 -> 0 | BY27: =BW27-BX27 -> 0 | BZ27: =BM27 -> 0 | CA27: =AK27 -> 0 | CB27: =BZ27-CA27 -> 0 | CC27: Marketplace Purchases (AFR) | CD27: 0 | CE27: =TEXT(AN27,"mmm-yy") -> Apr-26 | CF27: =AM27-AL27-AA27 -> 27051 | CG27: =BO27-BN27 -> 0 | CH27: =INT((D27- IF(MONTH(D27) >= 4, DATE(YEAR(D27), 4, 1), DATE(YEAR(D27)-1, 4, 1))) / 7) + 1 -> 4 | CI27: AFR | CJ27: AFR | CK27: 0 | CL27: =AY27-Q27 -> -27051 | CM27: =CL27-Y27+Z27 -> -27051 | CN27: =BO27-AM27 -> -27051 | CO27: =AY27*118% -> 0 | CP27: =-Q27*118% -> -31920.18 | CQ27: =-BZ27*118% -> 0 | CR27: =-CA27*118% -> 0 | CS27: =SUM(CO27:CR27) -> -31920.18 | CT27: Telangana - HO | CU27: Telangana - HO | CV27: =MID(G27,3,10) -> ANHPG0363J | CW27: =MID(AR27,3,10)
B28: ="Q" & IF(ROUNDUP(MONTH(D28)/3,0)-1=0,4,ROUNDUP(MONTH(D28)/3,0)-1) -> Q1 | C28: =TEXT(AN28,"mmm-yy") -> Apr-26 | D28: 46136 | F28: SRI PRASANNA TRADERS | G28: 37ANHPG0363J1Z1 | H28: 7 | I28: 46136 | J28: 26-27/PUR/001360 | K28: 46136 | L28: AD | N28: Starch | O28: 950 | P28: 45 | Q28: =O28*P28 -> 42750 | R28: 0 | S28: =O28-R28 -> 950 | T28: 0 | U28: 0 | V28: 0 | W28: 0 | X28: 0 | Y28: 0 | Z28: 0 | AA28: 0 | AB28: =Y28+AA28+Z28 -> 0 | AC28: 0 | AD28: 0 | AE28: 0 | AF28: 0 | AG28: 0 | AH28: 0 | AI28: 0 | AJ28: 0 | AK28: 0 | AL28: 0 | AM28: =Q28+AB28+AL28+AK28+AJ28+T28+AE28 -> 42750 | AN28: =D28 -> 46136 | AO28: 0 | AP28: 0 | AQ28: 0 | AR28: 0 | AS28: 0 | AT28: 0 | AU28: 0 | AV28: 0 | AW28: 0 | AX28: 0 | AY28: =AW28*AX28 -> 0 | AZ28: =AW28=O28 -> FALSE | BA28: 0 | BB28: =AW28-BA28 -> 0 | BC28: 0 | BD28: Regular | BE28: 0 | BF28: 0 | BG28: 0 | BH28: 0 | BI28: 0 | BJ28: 0 | BK28: 0 | BL28: 0 | BM28: 0 | BN28: 0 | BO28: =AY28+BL28+BM28+BN28+BC28+BG28 -> 0 | BP28: =BO28-AM28 -> -42750 | BQ28: =IF(BP28>=0,"Positive Margin","Negative Margin") -> Negative Margin | BR28: No Provision | BS28: =AY28-Y28-Q28-AA28-T28+BC28 -> -42750 | BT28: =IF(BS28<0, "Negative Margin at Inception", "Positive Margin at Inception") -> Negative Margin at Inception | BU28: =IFERROR(BP28/BO28,"0") -> 0 | BV28: =IF(BU28<1%,"Less Than 1%",IF(BU28>2%,"More than 2%",IF(BU28>=1%,"1% - 2%"))) -> More than 2% | BW28: =BM28+BN28 -> 0 | BX28: =AL28+AK28 -> 0 | BY28: =BW28-BX28 -> 0 | BZ28: =BM28 -> 0 | CA28: =AK28 -> 0 | CB28: =BZ28-CA28 -> 0 | CC28: Marketplace Purchases (AFR) | CD28: 0 | CE28: =TEXT(AN28,"mmm-yy") -> Apr-26 | CF28: =AM28-AL28-AA28 -> 42750 | CG28: =BO28-BN28 -> 0 | CH28: =INT((D28- IF(MONTH(D28) >= 4, DATE(YEAR(D28), 4, 1), DATE(YEAR(D28)-1, 4, 1))) / 7) + 1 -> 4 | CI28: AFR | CJ28: AFR | CK28: 0 | CL28: =AY28-Q28 -> -42750 | CM28: =CL28-Y28+Z28 -> -42750 | CN28: =BO28-AM28 -> -42750 | CO28: =AY28*118% -> 0 | CP28: =-Q28*118% -> -50445 | CQ28: =-BZ28*118% -> 0 | CR28: =-CA28*118% -> 0 | CS28: =SUM(CO28:CR28) -> -50445 | CT28: Telangana - HO | CU28: Telangana - HO | CV28: =MID(G28,3,10) -> ANHPG0363J | CW28: =MID(AR28,3,10)
B29: ="Q" & IF(ROUNDUP(MONTH(D29)/3,0)-1=0,4,ROUNDUP(MONTH(D29)/3,0)-1) -> Q1 | C29: =TEXT(AN29,"mmm-yy") -> Apr-26 | D29: 46133 | F29: SRI PRASANNA TRADERS | G29: 37ANHPG0363J1Z1 | H29: 145 | I29: 46098 | J29: 26-27/PUR/001061 | K29: 46133 | L29: AD | N29: Transport Charges | O29: 1 | P29: 0 | Q29: =O29*P29 -> 0 | R29: 0 | S29: =O29-R29 -> 1 | T29: 0 | U29: 0 | V29: 0 | W29: 0 | X29: 0 | Y29: 42000 | Z29: 0 | AA29: 0 | AB29: =Y29+AA29+Z29 -> 42000 | AC29: 0 | AD29: 0 | AE29: 0 | AF29: 0 | AG29: 0 | AH29: 0 | AI29: 0 | AJ29: 0 | AK29: 0 | AL29: 0 | AM29: =Q29+AB29+AL29+AK29+AJ29+T29+AE29 -> 42000 | AN29: =D29 -> 46133 | AO29: 0 | AP29: 0 | AQ29: 0 | AR29: 0 | AS29: 0 | AT29: 0 | AU29: 0 | AV29: 0 | AW29: 0 | AX29: 0 | AY29: =AW29*AX29 -> 0 | AZ29: =AW29=O29 -> FALSE | BA29: 0 | BB29: =AW29-BA29 -> 0 | BC29: 0 | BD29: Regular | BE29: 0 | BF29: 0 | BG29: 0 | BH29: 0 | BI29: 0 | BJ29: 0 | BK29: 0 | BL29: 0 | BM29: 0 | BN29: 0 | BO29: =AY29+BL29+BM29+BN29+BC29+BG29 -> 0 | BP29: =BO29-AM29 -> -42000 | BQ29: =IF(BP29>=0,"Positive Margin","Negative Margin") -> Negative Margin | BR29: No Provision | BS29: =AY29-Y29-Q29-AA29-T29+BC29 -> -42000 | BT29: =IF(BS29<0, "Negative Margin at Inception", "Positive Margin at Inception") -> Negative Margin at Inception | BU29: =IFERROR(BP29/BO29,"0") -> 0 | BV29: =IF(BU29<1%,"Less Than 1%",IF(BU29>2%,"More than 2%",IF(BU29>=1%,"1% - 2%"))) -> More than 2% | BW29: =BM29+BN29 -> 0 | BX29: =AL29+AK29 -> 0 | BY29: =BW29-BX29 -> 0 | BZ29: =BM29 -> 0 | CA29: =AK29 -> 0 | CB29: =BZ29-CA29 -> 0 | CC29: Marketplace Purchases (AFR) | CD29: 0 | CE29: =TEXT(AN29,"mmm-yy") -> Apr-26 | CF29: =AM29-AL29-AA29 -> 42000 | CG29: =BO29-BN29 -> 0 | CH29: =INT((D29- IF(MONTH(D29) >= 4, DATE(YEAR(D29), 4, 1), DATE(YEAR(D29)-1, 4, 1))) / 7) + 1 -> 3 | CI29: AFR | CJ29: AFR | CK29: 0 | CL29: =AY29-Q29 -> 0 | CM29: =CL29-Y29+Z29 -> -42000 | CN29: =BO29-AM29 -> -42000 | CO29: =AY29*118% -> 0 | CP29: =-Q29*118% -> 0 | CQ29: =-BZ29*118% -> 0 | CR29: =-CA29*118% -> 0 | CS29: =SUM(CO29:CR29) -> 0 | CT29: Telangana - HO | CU29: Telangana - HO | CV29: =MID(G29,3,10) -> ANHPG0363J | CW29: =MID(AR29,3,10)
B30: ="Q" & IF(ROUNDUP(MONTH(D30)/3,0)-1=0,4,ROUNDUP(MONTH(D30)/3,0)-1) -> Q1 | C30: =TEXT(AN30,"mmm-yy") -> Apr-26 | D30: 46136 | F30: SRI PRASANNA TRADERS | G30: 37ANHPG0363J1Z1 | H30: 8 | I30: 46136 | J30: 26-27/PUR/001364 | K30: 46136 | L30: AD | N30: Transport Charges | O30: 1 | P30: 0 | Q30: =O30*P30 -> 0 | R30: 0 | S30: =O30-R30 -> 1 | T30: 0 | U30: 0 | V30: 0 | W30: 0 | X30: 0 | Y30: 12711 | Z30: 0 | AA30: 0 | AB30: =Y30+AA30+Z30 -> 12711 | AC30: 0 | AD30: 0 | AE30: 0 | AF30: 0 | AG30: 0 | AH30: 0 | AI30: 0 | AJ30: 0 | AK30: 0 | AL30: 0 | AM30: =Q30+AB30+AL30+AK30+AJ30+T30+AE30 -> 12711 | AN30: =D30 -> 46136 | AO30: 0 | AP30: 0 | AQ30: 0 | AR30: 0 | AS30: 0 | AT30: 0 | AU30: 0 | AV30: 0 | AW30: 0 | AX30: 0 | AY30: =AW30*AX30 -> 0 | AZ30: =AW30=O30 -> FALSE | BA30: 0 | BB30: =AW30-BA30 -> 0 | BC30: 0 | BD30: Regular | BE30: 0 | BF30: 0 | BG30: 0 | BH30: 0 | BI30: 0 | BJ30: 0 | BK30: 0 | BL30: 0 | BM30: 0 | BN30: 0 | BO30: =AY30+BL30+BM30+BN30+BC30+BG30 -> 0 | BP30: =BO30-AM30 -> -12711 | BQ30: =IF(BP30>=0,"Positive Margin","Negative Margin") -> Negative Margin | BR30: No Provision | BS30: =AY30-Y30-Q30-AA30-T30+BC30 -> -12711 | BT30: =IF(BS30<0, "Negative Margin at Inception", "Positive Margin at Inception") -> Negative Margin at Inception | BU30: =IFERROR(BP30/BO30,"0") -> 0 | BV30: =IF(BU30<1%,"Less Than 1%",IF(BU30>2%,"More than 2%",IF(BU30>=1%,"1% - 2%"))) -> More than 2% | BW30: =BM30+BN30 -> 0 | BX30: =AL30+AK30 -> 0 | BY30: =BW30-BX30 -> 0 | BZ30: =BM30 -> 0 | CA30: =AK30 -> 0 | CB30: =BZ30-CA30 -> 0 | CC30: Marketplace Purchases (AFR) | CD30: 0 | CE30: =TEXT(AN30,"mmm-yy") -> Apr-26 | CF30: =AM30-AL30-AA30 -> 12711 | CG30: =BO30-BN30 -> 0 | CH30: =INT((D30- IF(MONTH(D30) >= 4, DATE(YEAR(D30), 4, 1), DATE(YEAR(D30)-1, 4, 1))) / 7) + 1 -> 4 | CI30: AFR | CJ30: AFR | CK30: 0 | CL30: =AY30-Q30 -> 0 | CM30: =CL30-Y30+Z30 -> -12711 | CN30: =BO30-AM30 -> -12711 | CO30: =AY30*118% -> 0 | CP30: =-Q30*118% -> 0 | CQ30: =-BZ30*118% -> 0 | CR30: =-CA30*118% -> 0 | CS30: =SUM(CO30:CR30) -> 0 | CT30: Telangana - HO | CU30: Telangana - HO | CV30: =MID(G30,3,10) -> ANHPG0363J | CW30: =MID(AR30,3,10)
B31: ="Q" & IF(ROUNDUP(MONTH(D31)/3,0)-1=0,4,ROUNDUP(MONTH(D31)/3,0)-1) -> Q1 | C31: =TEXT(AN31,"mmm-yy") -> May-26 | D31: 2026-05-06 | F31: TIMES MARINE SERVICES PRIVATE LIMITED | G31: 33AAICT1418L1ZB | H31: TMSPL/097 | I31: 46148 | J31: 26-27/PUR/002132 | K31: 46157 | L31: TN | N31: Technical Testing and Analysis Services | O31: 3 | P31: 3000 | Q31: =O31*P31 -> 9000 | R31: 0 | S31: =O31-R31 -> 3 | T31: 0 | U31: 0 | V31: 0 | W31: 0 | X31: 0 | Y31: 0 | Z31: 0 | AA31: 0 | AB31: =Y31+AA31+Z31 -> 0 | AC31: 0 | AD31: 0 | AE31: 0 | AF31: 0 | AG31: 0 | AH31: 0 | AI31: 0 | AJ31: 0 | AK31: 0 | AL31: 0 | AM31: =Q31+AB31+AL31+AK31+AJ31+T31+AE31 -> 9000 | AN31: 2026-05-06 | AO31: 0 | AP31: 0 | AQ31: 0 | AR31: 0 | AS31: 0 | AT31: 0 | AU31: 0 | AV31: 0 | AW31: 0 | AX31: 0 | AY31: =AW31*AX31 -> 0 | AZ31: =AW31=O31 -> FALSE | BA31: 0 | BB31: =AW31-BA31 -> 0 | BC31: 0 | BD31: Regular | BE31: 0 | BF31: 0 | BG31: 0 | BH31: 0 | BI31: 0 | BJ31: 0 | BK31: 0 | BL31: 0 | BM31: 0 | BN31: 0 | BO31: =AY31+BL31+BM31+BN31+BC31+BG31 -> 0 | BP31: =BO31-AM31 -> -9000 | BQ31: =IF(BP31>=0,"Positive Margin","Negative Margin") -> Negative Margin | BR31: No Provision | BS31: =AY31-Y31-Q31-AA31-T31+BC31 -> -9000 | BT31: =IF(BS31<0, "Negative Margin at Inception", "Positive Margin at Inception") -> Negative Margin at Inception | BU31: =IFERROR(BP31/BO31,"0") -> 0 | BV31: =IF(BU31<1%,"Less Than 1%",IF(BU31>2%,"More than 2%",IF(BU31>=1%,"1% - 2%"))) -> More than 2% | BW31: =BM31+BN31 -> 0 | BX31: =AL31+AK31 -> 0 | BY31: =BW31-BX31 -> 0 | BZ31: =BM31 -> 0 | CA31: =AK31 -> 0 | CB31: =BZ31-CA31 -> 0 | CC31: Marketplace Purchases (AFR) | CD31: 0 | CE31: =TEXT(AN31,"mmm-yy") -> May-26 | CF31: =AM31-AL31-AA31 -> 9000 | CG31: =BO31-BN31 -> 0 | CH31: =INT((D31- IF(MONTH(D31) >= 4, DATE(YEAR(D31), 4, 1), DATE(YEAR(D31)-1, 4, 1))) / 7) + 1 -> 6 | CI31: AFR | CJ31: AFR | CK31: 0 | CL31: =AY31-Q31 -> -9000 | CM31: =CL31-Y31+Z31 -> -9000 | CN31: =BO31-AM31 -> -9000 | CO31: =AY31*118% -> 0 | CP31: =-Q31*118% -> -10620 | CQ31: =-BZ31*118% -> 0 | CR31: =-CA31*118% -> 0 | CS31: =SUM(CO31:CR31) -> -10620 | CT31: Telangana - HO | CU31: Telangana - HO | CV31: =MID(G31,3,10) -> AAICT1418L | CW31: =MID(AR31,3,10)
B32: ="Q" & IF(ROUNDUP(MONTH(D32)/3,0)-1=0,4,ROUNDUP(MONTH(D32)/3,0)-1) -> Q1 | C32: =TEXT(AN32,"mmm-yy") -> May-26 | D32: 2026-05-06 | F32: TIMES MARINE SERVICES PRIVATE LIMITED | G32: 33AAICT1418L1ZB | H32: TMSPL/097 | I32: 46148 | J32: 26-27/PUR/002132 | K32: 46157 | L32: TN | N32: Technical Testing and Analysis Services | O32: 6 | P32: 5500 | Q32: =O32*P32 -> 33000 | R32: 0 | S32: =O32-R32 -> 6 | T32: 0 | U32: 0 | V32: 0 | W32: 0 | X32: 0 | Y32: 0 | Z32: 0 | AA32: 0 | AB32: =Y32+AA32+Z32 -> 0 | AC32: 0 | AD32: 0 | AE32: 0 | AF32: 0 | AG32: 0 | AH32: 0 | AI32: 0 | AJ32: 0 | AK32: 0 | AL32: 0 | AM32: =Q32+AB32+AL32+AK32+AJ32+T32+AE32 -> 33000 | AN32: 2026-05-06 | AO32: 0 | AP32: 0 | AQ32: 0 | AR32: 0 | AS32: 0 | AT32: 0 | AU32: 0 | AV32: 0 | AW32: 0 | AX32: 0 | AY32: =AW32*AX32 -> 0 | AZ32: =AW32=O32 -> FALSE | BA32: 0 | BB32: =AW32-BA32 -> 0 | BC32: 0 | BD32: Regular | BE32: 0 | BF32: 0 | BG32: 0 | BH32: 0 | BI32: 0 | BJ32: 0 | BK32: 0 | BL32: 0 | BM32: 0 | BN32: 0 | BO32: =AY32+BL32+BM32+BN32+BC32+BG32 -> 0 | BP32: =BO32-AM32 -> -33000 | BQ32: =IF(BP32>=0,"Positive Margin","Negative Margin") -> Negative Margin | BR32: No Provision | BS32: =AY32-Y32-Q32-AA32-T32+BC32 -> -33000 | BT32: =IF(BS32<0, "Negative Margin at Inception", "Positive Margin at Inception") -> Negative Margin at Inception | BU32: =IFERROR(BP32/BO32,"0") -> 0 | BV32: =IF(BU32<1%,"Less Than 1%",IF(BU32>2%,"More than 2%",IF(BU32>=1%,"1% - 2%"))) -> More than 2% | BW32: =BM32+BN32 -> 0 | BX32: =AL32+AK32 -> 0 | BY32: =BW32-BX32 -> 0 | BZ32: =BM32 -> 0 | CA32: =AK32 -> 0 | CB32: =BZ32-CA32 -> 0 | CC32: Marketplace Purchases (AFR) | CD32: 0 | CE32: =TEXT(AN32,"mmm-yy") -> May-26 | CF32: =AM32-AL32-AA32 -> 33000 | CG32: =BO32-BN32 -> 0 | CH32: =INT((D32- IF(MONTH(D32) >= 4, DATE(YEAR(D32), 4, 1), DATE(YEAR(D32)-1, 4, 1))) / 7) + 1 -> 6 | CI32: AFR | CJ32: AFR | CK32: 0 | CL32: =AY32-Q32 -> -33000 | CM32: =CL32-Y32+Z32 -> -33000 | CN32: =BO32-AM32 -> -33000 | CO32: =AY32*118% -> 0 | CP32: =-Q32*118% -> -38940 | CQ32: =-BZ32*118% -> 0 | CR32: =-CA32*118% -> 0 | CS32: =SUM(CO32:CR32) -> -38940 | CT32: Telangana - HO | CU32: Telangana - HO | CV32: =MID(G32,3,10) -> AAICT1418L | CW32: =MID(AR32,3,10)
B33: ="Q" & IF(ROUNDUP(MONTH(D33)/3,0)-1=0,4,ROUNDUP(MONTH(D33)/3,0)-1) -> Q1 | C33: =TEXT(AN33,"mmm-yy") -> May-26 | D33: 46158 | F33: SRI PRASANNA TRADERS | G33: 37ANHPG0363J1Z1 | H33: 15 | I33: 46158 | J33: 26-27/PUR/001193 | K33: 46160 | L33: AD | N33: Manpower Services | O33: 1 | P33: 180000 | Q33: =O33*P33 -> 180000 | R33: 0 | S33: =O33-R33 -> 1 | T33: 0 | U33: 0 | V33: 0 | W33: 0 | X33: 0 | Y33: 0 | Z33: 0 | AA33: 0 | AB33: =Y33+AA33+Z33 -> 0 | AC33: 0 | AD33: 0 | AE33: 0 | AF33: 0 | AG33: 0 | AH33: 0 | AI33: 0 | AJ33: 0 | AK33: 0 | AL33: 0 | AM33: =Q33+AB33+AL33+AK33+AJ33+T33+AE33 -> 180000 | AN33: 46158 | AO33: 0 | AP33: 0 | AQ33: 0 | AR33: 0 | AS33: 0 | AT33: 0 | AU33: 0 | AV33: 0 | AW33: 0 | AX33: 0 | AY33: =AW33*AX33 -> 0 | AZ33: =AW33=O33 -> FALSE | BA33: 0 | BB33: =AW33-BA33 -> 0 | BC33: 0 | BD33: Regular | BE33: 0 | BF33: 0 | BG33: 0 | BH33: 0 | BI33: 0 | BJ33: 0 | BK33: 0 | BL33: 0 | BM33: 0 | BN33: 0 | BO33: =AY33+BL33+BM33+BN33+BC33+BG33 -> 0 | BP33: =BO33-AM33 -> -180000 | BQ33: =IF(BP33>=0,"Positive Margin","Negative Margin") -> Negative Margin | BR33: No Provision | BS33: =AY33-Y33-Q33-AA33-T33+BC33 -> -180000 | BT33: =IF(BS33<0, "Negative Margin at Inception", "Positive Margin at Inception") -> Negative Margin at Inception | BU33: =IFERROR(BP33/BO33,"0") -> 0 | BV33: =IF(BU33<1%,"Less Than 1%",IF(BU33>2%,"More than 2%",IF(BU33>=1%,"1% - 2%"))) -> More than 2% | BW33: =BM33+BN33 -> 0 | BX33: =AL33+AK33 -> 0 | BY33: =BW33-BX33 -> 0 | BZ33: =BM33 -> 0 | CA33: =AK33 -> 0 | CB33: =BZ33-CA33 -> 0 | CC33: Marketplace Purchases (AFR) | CD33: 0 | CE33: =TEXT(AN33,"mmm-yy") -> May-26 | CF33: =AM33-AL33-AA33 -> 180000 | CG33: =BO33-BN33 -> 0 | CH33: =INT((D33- IF(MONTH(D33) >= 4, DATE(YEAR(D33), 4, 1), DATE(YEAR(D33)-1, 4, 1))) / 7) + 1 -> 7 | CI33: AFR | CJ33: AFR | CK33: 0 | CL33: =AY33-Q33 -> -180000 | CM33: =CL33-Y33+Z33 -> -180000 | CN33: =BO33-AM33 -> -180000 | CO33: =AY33*118% -> 0 | CP33: =-Q33*118% -> -212400 | CQ33: =-BZ33*118% -> 0 | CR33: =-CA33*118% -> 0 | CS33: =SUM(CO33:CR33) -> -212400 | CT33: Telangana - HO | CU33: Telangana - HO | CV33: =MID(G33,3,10) -> ANHPG0363J | CW33: =MID(AR33,3,10)
F35: Total | O35: =SUBTOTAL(9,O24:O34) -> 4778 | Q35: =SUBTOTAL(9,Q24:Q34) -> 554906 | S35: =SUBTOTAL(9,S24:S34) -> 4778 | T35: =SUBTOTAL(9,T24:T34) -> 0 | Y35: =SUBTOTAL(9,Y24:Y34) -> 54711 | Z35: =SUBTOTAL(9,Z24:Z34) -> 0 | AA35: =SUBTOTAL(9,AA24:AA34) -> 0 | AB35: =SUBTOTAL(9,AB24:AB34) -> 54711 | AC35: =SUBTOTAL(9,AC24:AC34) -> 0 | AD35: =SUBTOTAL(1,AD24:AD34) -> 0 | AE35: =SUBTOTAL(9,AE24:AE34) -> 0 | AJ35: =SUBTOTAL(9,AJ24:AJ34) -> 0 | AK35: =SUBTOTAL(9,AK24:AK34) -> 0 | AL35: =SUBTOTAL(9,AL24:AL34) -> 0 | AM35: =SUBTOTAL(9,AM24:AM34) -> 609617 | AW35: =SUBTOTAL(9,AW24:AW34) -> 0 | AX35: =SUBTOTAL(101,AX24:AX34) -> 0 | AY35: =SUBTOTAL(9,AY24:AY34) -> 0 | BA35: =SUBTOTAL(9,BA24:BA34) -> 0 | BB35: =SUBTOTAL(9,BB24:BB34) -> 0 | BC35: =SUBTOTAL(9,BC24:BC34) -> 0 | BG35: =SUBTOTAL(9,BG24:BG34) -> 0 | BL35: =SUBTOTAL(9,BL24:BL34) -> 0 | BM35: =SUBTOTAL(9,BM24:BM34) -> 0 | BN35: =SUBTOTAL(9,BN24:BN34) -> 0 | BO35: =SUBTOTAL(9,BO24:BO34) -> 0 | BP35: =SUBTOTAL(9,BP24:BP34) -> -609617 | BS35: =SUBTOTAL(9,BS24:BS34) -> -609617 | BW35: =SUBTOTAL(9,BV20:BV34) -> 0 | BX35: =SUBTOTAL(9,BW20:BW34) -> 0 | BY35: =SUBTOTAL(9,BX20:BX34) -> #DIV/0! | BZ35: =SUBTOTAL(9,BY20:BY34) -> 0 | CA35: =SUBTOTAL(9,BZ20:BZ34) -> 0 | CB35: =SUBTOTAL(9,CA20:CA34) -> 5.6 | CF35: =SUBTOTAL(9,CE20:CE34) -> 0 | CG35: =SUBTOTAL(9,CF20:CF34) -> 2792652.4 | CL35: =SUBTOTAL(9,CK20:CK34) -> 0 | CM35: =SUBTOTAL(9,CL20:CL34) -> -554906 | CN35: =SUBTOTAL(9,CM20:CM34) -> -609617 | CO35: =SUBTOTAL(9,CN20:CN34) -> -609617 | CP35: =SUBTOTAL(9,CO20:CO34) -> 0 | CQ35: =SUBTOTAL(9,CP20:CP34) -> -654789.08 | CR35: =SUBTOTAL(9,CQ20:CQ34) -> 0 | CS35: =SUBTOTAL(9,CR20:CR34) -> 0
N37: Particulars | O37: Amount | AA37: Particulars | AC37: Amount | AR37: Particulars | AT37: Amount
N38: Net Purchase as per report | O38: =Q19+AJ19+AK19+Q35 -> 2404936 | AA38: Net Logistic Cost as per report | AC38: =Y19+Z19+AB35 -> 54711 | AR38: Net Sales As per report | AT38: =+AY19+BL19+BM19+BC19+BG19 -> 2026053.6
N39: As per ZOHO | O39: 2354172 | P39: 46194 | AA39: As per ZOHO | AC39: 54711 | AD39: =P39 -> 46194 | AR39: As per ZOHO | AT39: 1967519.6 | AU39: =P39 -> 46194
N40: Variance | O40: =O39-O38 -> -50764 | AA40: Variance | AC40: =AC39-AC38 -> 0 | AR40: Variance | AT40: =AT38-AT39 -> 58534
N41: DN Provision in Zoho FY 25-26 | O41: ='Last year''s'!G3 -> 244602 | AA41: Fy 2024-25 Logistic Provision Reversal | AC41: 0 | AR41: CN Provision in Zoho FY 24-25 | AT41: ='Last year''s'!N3 -> 227297.5
N42: JV for last year Bills | O42: 0 | AA42: FY 2023-24 Logistics | AC42: ='Last year''s'!T32 -> 0 | AR42: FY 2024-25 Credit notes | AT42: ='Last year''s'!N5 -> 168763.5
N43: Debit note FY 25-26 | O43: ='Last year''s'!G4 -> 295366 | AR43: Reconciliation | AT43: =-'Recon Items'!C29+'Recon Items'!F29+'Recon Items'!Q8 -> 0
N44: Reconciliation | O44: ='Recon Items'!F18-'Recon Items'!C18-'Recon Items'!M18 -> 0 | AA44: Institutional Business | AR44: Institutional Business | AT44: ='Recon Items'!F64 -> 0
N45: Institutional Business | O45: ='Recon Items'!C64 -> 0 | AA45: Variance | AC45: =-AC40+AC41+AC42 -> 0 | AR45: Final Variance | AT45: =AT40+AT42+AT43-AT41+AT44 -> 0
N46: Variance | O46: =O40+O43-O44-O41-O45-O42 -> 0
BJ58: =SUM(BJ52:BJ57) -> 0
BJ59: =BJ51-BJ58 -> 0
AK65: =AK66-AK67 -> 0

Sheet AP & AR
N1: =I2-N2 -> 1671613.1
I2: =SUBTOTAL(9,I4:I49) -> 1792414.2 | J2: =SUBTOTAL(9,J4:J49) -> 4152274.9 | N2: =SUBTOTAL(9,N4:N1048576) -> 120801.16 | Y2: =SUM(Y4:Y24) -> 948429.3 | Z2: =SUM(Z4:Z24) -> 2428102.2
B3: date | C3: status | D3: entity | E3: age | F3: due_date | G3: transaction_number | H3: customer_name | I3: balance | J3: amount | K3: payment_terms | L3: gst_no | M3: credit_limit | N3: unused_credits_receivable_amount | O3: contact.CF.Vertical Name | P3: Check | R3: date | S3: status | T3: entity | U3: age | V3: due_date | W3: transaction_number | X3: vendor_name | Y3: balance | Z3: amount | AA3: gst_no | AB3: vendor.CF.Vertical Name | AC3: vendor.CF.MSME Category
B4: 46104 | C4: overdue | D4: invoice | E4: 88 | F4: 2026-03-25 | G4: 26/MPAFR/INV0085 | H4: ATTAQUANT CATKEM TRADE LLP | I4: 20780.2 | J4: 2098777.7 | K4: Net 3 (days) | L4: 27ACAFA4787C1ZI | M4: 3000000 | N4: 0 | O4: Marketplace (AFR) | P4: Marketplace Sales (AFR) | R4: 2026-03-09 | S4: overdue | T4: bill | U4: 104 | V4: 2026-03-09 | W4: 125 | X4: SRI PRASANNA TRADERS | Y4: 42170.85 | Z4: 276453.35 | AA4: 37ANHPG0363J1Z1 | AB4: Marketplace (AFR) | AC4: SMALL
B5: 46151 | C5: overdue | D5: invoice | E5: 29 | F5: 2026-05-23 | G5: 36/AFR/27IN00002 | H5: MRF LIMITED (36) | I5: 14670.78 | J5: 296534 | K5: Advance Payment | L5: 36AAACM4154G1ZO | M5: 4800000 | N5: 120801.16 | O5: Marketplace (AFR) | P5: Marketplace Sales (AFR) | R5: 2026-03-09 | S5: overdue | T5: bill | U5: 104 | V5: 2026-03-09 | W5: 123 | X5: SRI PRASANNA TRADERS | Y5: 4572 | Z5: 29972 | AA5: 37ANHPG0363J1Z1 | AB5: Marketplace (AFR) | AC5: SMALL
B6: 46155 | C6: overdue | D6: invoice | E6: 25 | F6: 2026-05-27 | G6: 36/AFR/27IN00003 | H6: MRF LIMITED (36) | I6: 358232.42 | J6: 358232.42 | K6: Advance Payment | L6: 36AAACM4154G1ZO | M6: 4800000 | N6: 0 | O6: Marketplace (AFR) | P6: Marketplace Sales (AFR) | R6: 2026-03-09 | S6: overdue | T6: bill | U6: 104 | V6: 2026-03-09 | W6: 126 | X6: SRI PRASANNA TRADERS | Y6: 4185 | Z6: 27435 | AA6: 37ANHPG0363J1Z1 | AB6: Marketplace (AFR) | AC6: SMALL
B7: 46168 | C7: overdue | D7: invoice | E7: 12 | F7: 2026-06-09 | G7: 36/AFR/27IN00004 | H7: MRF LIMITED (36) | I7: 207201.16 | J7: 207201.16 | K7: Advance Payment | L7: 36AAACM4154G1ZO | M7: 4800000 | N7: 0 | O7: Marketplace (AFR) | P7: Marketplace Sales (AFR) | R7: 2026-03-13 | S7: overdue | T7: bill | U7: 100 | V7: 2026-03-13 | W7: 124 | X7: SRI PRASANNA TRADERS | Y7: 22428 | Z7: 22428 | AA7: 37ANHPG0363J1Z1 | AB7: Marketplace (AFR) | AC7: SMALL
B8: 46174 | C8: overdue | D8: invoice | E8: 13 | F8: 2026-06-08 | G8: 36/AFR/27IN00005 | H8: ULTRATECH CEMENT LIMITED | I8: 46464.6 | J8: 46464.6 | K8: Net 15 (Days) | L8: 37AAACL6442L1Z9 | M8: 12000000 | N8: 0 | O8: Marketplace (AFR) | P8: Marketplace Sales (AFR) | R8: 2026-05-09 | S8: overdue | T8: bill | U8: 39 | V8: 2026-05-13 | W8: 11 | X8: SRI PRASANNA TRADERS | Y8: 36613.7 | Z8: 243581.5 | AA8: 37ANHPG0363J1Z1 | AB8: Marketplace (AFR) | AC8: SMALL
B9: 46176 | C9: overdue | D9: invoice | E9: 11 | F9: 2026-06-10 | G9: 36/AFR/27IN00007 | H9: ULTRATECH CEMENT LIMITED | I9: 46678.28 | J9: 46678.28 | K9: Net 15 (Days) | L9: 37AAACL6442L1Z9 | M9: 12000000 | N9: 0 | O9: Marketplace (AFR) | P9: Marketplace Sales (AFR) | R9: 2026-05-13 | S9: overdue | T9: bill | U9: 35 | V9: 2026-05-17 | W9: 13 | X9: SRI PRASANNA TRADERS | Y9: 339556.8 | Z9: 339556.8 | AA9: 37ANHPG0363J1Z1 | AB9: Marketplace (AFR) | AC9: SMALL
B10: 46176 | C10: overdue | D10: invoice | E10: 11 | F10: 2026-06-10 | G10: 36/AFR/27IN00006 | H10: ULTRATECH CEMENT LIMITED | I10: 46658.85 | J10: 46658.85 | K10: Net 15 (Days) | L10: 37AAACL6442L1Z9 | M10: 12000000 | N10: 0 | O10: Marketplace (AFR) | P10: Marketplace Sales (AFR) | R10: 2026-05-16 | S10: overdue | T10: bill | U10: 34 | V10: 2026-05-18 | W10: 15 | X10: SRI PRASANNA TRADERS | Y10: 32400 | Z10: 210600 | AA10: 37ANHPG0363J1Z1 | AB10: Marketplace (AFR) | AC10: SMALL
B11: 46177 | C11: overdue | D11: invoice | E11: 3 | F11: 2026-06-18 | G11: 36/AFR/27IN00008 | H11: MRF LIMITED (36) | I11: 155064.74 | J11: 155064.74 | K11: Advance Payment | L11: 36AAACM4154G1ZO | M11: 4800000 | N11: 0 | O11: Marketplace (AFR) | P11: Marketplace Sales (AFR) | R11: 2026-05-26 | S11: overdue | T11: bill | U11: 22 | V11: 2026-05-30 | W11: 19 | X11: SRI PRASANNA TRADERS | Y11: 29959.2 | Z11: 196399.2 | AA11: 37ANHPG0363J1Z1 | AB11: Marketplace (AFR) | AC11: SMALL
B12: 46181 | C12: overdue | D12: invoice | E12: 6 | F12: 2026-06-15 | G12: 36/AFR/27IN00010 | H12: ULTRATECH CEMENT LIMITED | I12: 34246.28 | J12: 34246.28 | K12: Net 15 (Days) | L12: 37AAACL6442L1Z9 | M12: 12000000 | N12: 0 | O12: Marketplace (AFR) | P12: Marketplace Sales (AFR) | R12: 2026-06-03 | S12: overdue | T12: bill | U12: 14 | V12: 2026-06-07 | W12: INV-26-802 | X12: SRI RAGHAVENDRA CORPORATION | Y12: 33503.05 | Z12: 42875.7 | AA12: 37AGCPV7437N2ZK | AB12: Marketplace (AFR) | AC12: MICRO
B13: 46180 | C13: sent | D13: invoice | F13: 2026-06-21 | G13: 36/AFR/27IN00009 | H13: MRF LIMITED (36) | I13: 214819.94 | J13: 214819.94 | K13: Advance Payment | L13: 36AAACM4154G1ZO | M13: 4800000 | N13: 0 | O13: Marketplace (AFR) | P13: Marketplace Sales (AFR) | R13: 2026-06-03 | S13: overdue | T13: bill | U13: 14 | V13: 2026-06-07 | W13: INV-26-801 | X13: SRI RAGHAVENDRA CORPORATION | Y13: 42893.55 | Z13: 42893.55 | AA13: 37AGCPV7437N2ZK | AB13: Marketplace (AFR) | AC13: MICRO
B14: 46181 | C14: sent | D14: invoice | F14: 2026-06-22 | G14: 36/AFR/27IN00011 | H14: MRF LIMITED (36) | I14: 194204.4 | J14: 194204.4 | K14: Advance Payment | L14: 36AAACM4154G1ZO | M14: 4800000 | N14: 0 | O14: Marketplace (AFR) | P14: Marketplace Sales (AFR) | R14: 2026-06-04 | S14: overdue | T14: bill | U14: 13 | V14: 2026-06-08 | W14: 25 | X14: SRI PRASANNA TRADERS | Y14: 22420.8 | Z14: 146980.8 | AA14: 37ANHPG0363J1Z1 | AB14: Marketplace (AFR) | AC14: SMALL
B15: 46186 | C15: sent | D15: invoice | F15: 2026-06-27 | G15: 36/AFR/27IN00012 | H15: MRF LIMITED (36) | I15: 227368.54 | J15: 227368.54 | K15: Advance Payment | L15: 36AAACM4154G1ZO | M15: 4800000 | N15: 0 | O15: Marketplace (AFR) | P15: Marketplace Sales (AFR) | R15: 2026-06-07 | S15: overdue | T15: bill | U15: 10 | V15: 2026-06-11 | W15: 26 | X15: SRI PRASANNA TRADERS | Y15: 31060.8 | Z15: 203620.8 | AA15: 37ANHPG0363J1Z1 | AB15: Marketplace (AFR) | AC15: SMALL
B16: 46191 | C16: sent | D16: invoice | F16: 2026-07-02 | G16: 36/AFR/27IN00013 | H16: MRF LIMITED (36) | I16: 226024.04 | J16: 226024.04 | K16: Advance Payment | L16: 36AAACM4154G1ZO | M16: 4800000 | N16: 0 | O16: Marketplace (AFR) | P16: Marketplace Sales (AFR) | R16: 2026-06-08 | S16: overdue | T16: bill | U16: 9 | V16: 2026-06-12 | W16: INV-26-803 | X16: SRI RAGHAVENDRA CORPORATION | Y16: 31469.55 | Z16: 31469.55 | AA16: 37AGCPV7437N2ZK | AB16: Marketplace (AFR) | AC16: MICRO
R17: 2026-06-08 | S17: overdue | T17: bill | U17: 9 | V17: 2026-06-12 | W17: 27 | X17: SRI PRASANNA TRADERS | Y17: 28080 | Z17: 184080 | AA17: 37ANHPG0363J1Z1 | AB17: Marketplace (AFR) | AC17: SMALL
R18: 2026-06-13 | S18: overdue | T18: bill | U18: 4 | V18: 2026-06-17 | W18: 32 | X18: SRI PRASANNA TRADERS | Y18: 32875.2 | Z18: 215515.2 | AA18: 37ANHPG0363J1Z1 | AB18: Marketplace (AFR) | AC18: SMALL
R19: 2026-06-18 | S19: open | T19: bill | V19: 2026-06-22 | W19: 36 | X19: SRI PRASANNA TRADERS | Y19: 214240.8 | Z19: 214240.8 | AA19: 37ANHPG0363J1Z1 | AB19: Marketplace (AFR) | AC19: SMALL

Sheet Recon Items
I3: Qty Reco | L3: FY 2025-26 bills considered ths year | P3: FY 2025-26
B4: Bills in report not in P&L | C4: Amount | E4: Bills in P&L not in report | F4: Amount | G4: Qty | I4: Qty Check | J4: =Details!AD39 -> 46194 | L4: Bills in report not in P&L | M4: Amount | N4: Qty | P4: DN to Customer | Q4: Amount
I6: As Per Report | J6: =-Details!AW19 -> -187870
I7: As per Zoho(till May) | J7: 74960
I8: As per Zoho Current Month | J8: 112910 | Q8: =SUM(Q5:Q7) -> 0
P9: FY 2025-26
I10: Variance | J10: =SUM(J6:J9)-G18 -> 0 | P10: DN to Customer | Q10: Qty
I14: BCD not in Report | J14: Amount
B18: G.Total | C18: =SUM(C5:C17) -> 0 | E18: G.Total | F18: =SUBTOTAL(9,F5:F17) -> 0 | G18: =SUBTOTAL(9,G5:G17) -> 0 | J18: =SUM(J15:J17) -> 0 | L18: G.Total | M18: =SUM(M5:M17) -> 0 | N18: =SUM(N5:N17) -> 0
B21: Sales in report not in P&L | C21: Amount | E21: Sales in P&L not in report | F21: Amount | G21: Qty | I21: Bils in Report & P&L , Sale yet to be done
P26: G.Total | Q26: =SUM(Q11:Q25) -> 0
B29: G.Total | C29: =SUM(C22:C28) -> 0 | E29: G.Total | F29: =SUBTOTAL(9,F22:F28) -> 0 | G29: 0 | I29: G.Total
AA695: -568957
AA700: =-AA696+AA697-AA698 -> 0

Sheet Supplier Metrics
B2: =COUNTA(B4:B150) -> 1 | D2: =SUBTOTAL(9,D4:D9) -> 1698285 | E2: =COUNTA(_xlfn.ANCHORARRAY(E4))-1 -> 1
B3: Supplier Name | C3: GST Reg No. | D3: Purchases | E3: Count Supplier Name
B4: =_xlfn.XLOOKUP(C4,Details!$G$5:$G$18,Details!$F$5:$F$18) -> SRI PRASANNA TRADERS | C4: {=_xlfn.UNIQUE(_xlfn._TRO_TRAILING(Details!G5:G18))} -> 37ANHPG0363J1Z1 | D4: =SUMIFS(Details!$Q$5:$Q$18,Details!$G$5:$G$18,'Supplier Metrics'!C4) -> 1698285 | E4: {=_xlfn.UNIQUE(MID(_xlfn._TRO_TRAILING(Details!G5:G18),3,10))} -> ANHPG0363J
C5: 37AGCPV7437N2ZK | E5: AGCPV7437N

Sheet Buyer Metrics
F2: =F3-Summary!R6 -> 0 | G2: =G3-Summary!R8 -> -13440 | H2: =H3-Summary!R9 -> -0.0066335856 | I2: =I3-Details!AY19 -> 0 | J2: =J3+Details!BZ19 -> 575 | L2: =L3-Summary!R19 -> -3
B3: =COUNTA(_xlfn.ANCHORARRAY(B5)) -> 2 | C3: =COUNTA(_xlfn.ANCHORARRAY(C5)) -> 3 | E3: =SUM(E$5:E10) -> 187870 | F3: =SUM(F$5:F150) -> 2026053.6 | G3: =SUM(G$5:G150) -> 162583.6 | H3: =G3/F3 -> 0.080246446 | I3: =SUM(I$5:I10) -> 2026753.6 | J3: =SUM(J$5:J10) -> 700 | K3: =J3/F3 -> 0.00034549925 | L3: =SUM(L$5:L10) -> 10 | M3: =SUBTOTAL(1,M5:M150) -> 186268.53
B4: Count Recyclers | C4: Customer ID | D4: Customer Name | E4: Qty | F4: Revenue | G4: Margin | H4: Margin(% | I4: Sale Value | J4: Debit Notes | K4: DN to Sale(%) | L4: No of transactions | M4: Avg Tran Value
B5: {=_xlfn.UNIQUE(MID(_xlfn._TRO_TRAILING(Details!AR5:AR18),3,10))} -> AAACM4154G | C5: {=_xlfn.UNIQUE(Details!AR5:AR18)} -> 36AAACM4154G1ZO | D5: =(_xlfn.XLOOKUP(C5,Details!$AR$5:$AR$18,Details!$AQ$5:$AQ$18)) -> MRF LIMITED (36) | E5: =SUMIFS(Details!BB:BB,Details!AR:AR,'Buyer Metrics'!$C5) -> 143070 | F5: =SUMIFS(Details!BO:BO,Details!AR:AR,'Buyer Metrics'!$C5) -> 1860293.6 | G5: =SUMIFS(Details!BP:BP,Details!AR:AR,'Buyer Metrics'!$C5) -> 162583.6 | H5: =IFERROR((G5/F5),0) -> 0.087396742 | I5: =SUMIFS(Details!$AY$5:$AY18,Details!$AR$5:$AR18,'Buyer Metrics'!$C5) -> 1860993.6 | J5: =-SUMIFS(Details!$BZ$5:$BZ18,Details!$AR$5:$AR18,'Buyer Metrics'!$C5) -> 700 | K5: =IFERROR((J5/I5),0) -> 0.00037614315 | L5: {=COUNTA(_xlfn.UNIQUE(_xlfn._xlws.FILTER(Details!AO5:AO18,Details!AR5:AR18='Buyer Metrics'!$C5)))} -> 9 | M5: =I5/L5 -> 206777.07
B6: AAACL6442L | C6: 37AAACL6442L1Z9 | D6: =(_xlfn.XLOOKUP(C6,Details!$AR$5:$AR$18,Details!$AQ$5:$AQ$18)) -> ULTRATECH CEMENT LIMITED | E6: =SUMIFS(Details!BB:BB,Details!AR:AR,'Buyer Metrics'!$C6) -> 44800 | F6: =SUMIFS(Details!BO:BO,Details!AR:AR,'Buyer Metrics'!$C6) -> 165760 | G6: 0 | H6: =IFERROR((G6/F6),0) -> 0 | I6: =SUMIFS(Details!$AY$5:$AY19,Details!$AR$5:$AR19,'Buyer Metrics'!$C6) -> 165760 | J6: =-SUMIFS(Details!$BZ$5:$BZ19,Details!$AR$5:$AR19,'Buyer Metrics'!$C6) -> 0 | K6: =IFERROR((J6/I6),0) -> 0 | L6: {=COUNTA(_xlfn.UNIQUE(_xlfn._xlws.FILTER(Details!AO18:AO19,Details!AR18:AR19='Buyer Metrics'!$C6)))} -> 1 | M6: =I6/L6 -> 165760
C7: 0
G9: 0

Sheet Last year's
E2: JV Number | F2: Particulars | G2: Amount | L2: JV Number | M2: Particulars | N2: Amount
F3: Provision for DN as on 31st Mar-2026 | G3: 244602 | M3: Provision for Debit Notes from Customers as on 31st Mar-2026 | N3: 227297.5
F4: Accounted in FY 2026-27 | G4: =G8 -> 295366 | M4: Opening Provision | N4: 0
F5: NO DN value | M5: Accounted in FY 26-27 | N5: =N8 -> 168763.5
G6: =G3-G4-G5 -> -50764 | M6: Closing Provision | N6: =N3-N4-N5 -> 58534
B8: Debit note Pertaining to FY 2025-26 | G8: =SUBTOTAL(9,G10:G82) -> 295366 | I8: Credit note Pertaining to FY 2025-26 | N8: =SUBTOTAL(9,N10:N82) -> 168763.5 | P8: FY 2025-26 Logistic Bills accounted
B9: SO Number | C9: Month | D9: Debit Note Date | E9: Debit Note Number | F9: Vendor Name | G9: SubTotal | I9: SO Number | J9: Month | K9: Credit Note Date | L9: Credit Note Number | M9: Customer Name | N9: CN Amount | P9: Bill Date | Q9: Bill Number | R9: PurchaseOrder | S9: Vendor Name | T9: Amount
B10: SH03260604 | C10: =TEXT(D10,"mmm-yy") -> Apr-26 | D10: 46113 | E10: 36/AFR/27VC00001 | F10: SRI PRASANNA TRADERS | G10: 1380 | I10: SH03260604 | J10: =TEXT(K10,"mmm-yy") -> Apr-26 | K10: 46113 | L10: 36/AFR/27CN00001 | M10: MRF LIMITED (36) | N10: 1680
B11: SH03260909 | C11: =TEXT(D11,"mmm-yy") -> Apr-26 | D11: 46114 | E11: 36/AFR/27VC00002 | F11: SRI PRASANNA TRADERS | G11: 115 | I11: SH03261601 | J11: =TEXT(K11,"mmm-yy") -> Apr-26 | K11: 46114 | L11: 36/AFR/27CN00003 | M11: MRF LIMITED (36) | N11: 420
B12: SH03261601 | C12: =TEXT(D12,"mmm-yy") -> Apr-26 | D12: 46114 | E12: 36/AFR/27VC00003 | F12: SRI PRASANNA TRADERS | G12: 345 | I12: SH03260909 | J12: =TEXT(K12,"mmm-yy") -> Apr-26 | K12: 46114 | L12: 36/AFR/27CN00002 | M12: MRF LIMITED (36) | N12: 140
B13: SH022627033 | C13: =TEXT(D13,"mmm-yy") -> Apr-26 | D13: 46118 | E13: 36/AFR/27VC00004 | F13: SRI RAGHAVENDRA CORPORATION | G13: 637 | I13: SH022627033 | J13: =TEXT(K13,"mmm-yy") -> Apr-26 | K13: 46118 | L13: 36/AFR/27CN00004 | M13: MRF LIMITED (36) | N13: 734.5
B14: SH022627034 | C14: =TEXT(D14,"mmm-yy") -> Apr-26 | D14: 46118 | E14: 36/AFR/27VC00007 | F14: SRI RAGHAVENDRA CORPORATION | G14: 1176 | I14: SH032601012 | J14: =TEXT(K14,"mmm-yy") -> Apr-26 | K14: 46118 | L14: 36/AFR/27CN00005 | M14: MRF LIMITED (36) | N14: 1356
B15: SH032601012 | C15: =TEXT(D15,"mmm-yy") -> Apr-26 | D15: 46118 | E15: 36/AFR/27VC00005 | F15: SRI RAGHAVENDRA CORPORATION | G15: 1372 | I15: SH022627034 | J15: =TEXT(K15,"mmm-yy") -> Apr-26 | K15: 46118 | L15: 36/AFR/27CN00007 | M15: MRF LIMITED (36) | N15: 1582
B16: SH03262203 | C16: =TEXT(D16,"mmm-yy") -> Apr-26 | D16: 46126 | E16: 36/AFR/27VC00008 | F16: SRI RAGHAVENDRA CORPORATION | G16: 2750 | I16: SH03262203 | J16: =TEXT(K16,"mmm-yy") -> Apr-26 | K16: 46126 | L16: 36/AFR/27CN00008 | M16: ATTAQUANT CATKEM TRADE LLP | N16: 2775
B17: SH012616025 | C17: =TEXT(D17,"mmm-yy") -> Apr-26 | D17: 46127 | E17: 36/AFR/27VC00010 | F17: HARI HARA TRADERS | G17: 80808 | I17: SH012616025 | J17: =TEXT(K17,"mmm-yy") -> Apr-26 | K17: 46127 | L17: 36/AFR/27CN00010 | M17: MRF LIMITED (36) | N17: 74592
B18: SH012620031 | C18: =TEXT(D18,"mmm-yy") -> Apr-26 | D18: 46127 | E18: 36/AFR/27VC00009 | F18: HARI HARA TRADERS | G18: 78851 | I18: SH122523036 | J18: =TEXT(K18,"mmm-yy") -> Apr-26 | K18: 46127 | L18: 36/AFR/27CN00011 | M18: MRF LIMITED (36) | N18: 71232
B19: SH122523036 | C19: =TEXT(D19,"mmm-yy") -> Apr-26 | D19: 46127 | E19: 36/AFR/27VC00011 | F19: HARI HARA TRADERS | G19: 77168 | I19: SH012620031 | J19: =TEXT(K19,"mmm-yy") -> Apr-26 | K19: 46127 | L19: 36/AFR/27CN00009 | M19: MRF LIMITED (36) | N19: 72786
B20: SH022627034 | C20: =TEXT(D20,"mmm-yy") -> Jun-26 | D20: 46188 | E20: 36/AFR/27VC00015 | F20: SRI RAGHAVENDRA CORPORATION | G20: 50764 | I20: SH022627034 | J20: =TEXT(K20,"mmm-yy") -> Jun-26 | K20: 46188 | L20: 36/AFR/27CN00014 | M20: MRF LIMITED (36) | N20: -58534
P32: G.Total | T32: =SUM(T10:T31) -> 0

Sheet Revenue - Reco
C4: Sales - Reconciliation | F4: Purchases - Reconciliation | I4: Logistic Cost- Reconciliation
C5: Particulars | D5: Amount | F5: Particulars | G5: Amount | I5: Particulars | J5: Amount
C6: Net Revenue as per MIS Report | D6: =Details!AT38 -> 2026053.6 | F6: Net Purchases as per MIS Report | G6: =Details!O38 -> 2404936 | I6: Net Logistic as per MIS Report | J6: =Details!AC38 -> 54711
C7: Credit Notes issued in FY-25 pertaining to FY-24 | D7: =Details!AT42 -> 168763.5 | F7: Debit Notes issued in FY-25 pertaining to FY-24 | G7: =-Details!O43 -> -295366 | I7: Logistic Bills issued in FY-25 pertaining to FY-24 | J7: =Details!AC42 -> 0
C8: Fy 2023-24 DN to Customers | D8: ='Recon Items'!Q8 -> 0 | F8: DN Provision in Zoho FY 23-24 | G8: =Details!O41 -> 244602 | I8: Logistic Provision in Zoho FY 23-24 | J8: =Details!AC41 -> 0
C9: Reconciliation | D9: =Details!AT43 -> 0 | F9: JV for Last year Bills | G9: 0 | J9: =SUM(J6:J8) -> 54711
C10: CN Provision in Zoho FY 23-24 | D10: =Details!AT41 -> 227297.5 | F10: Last year bills considered this year | G10: =-'Recon Items'!M18 -> 0 | I10: Logistic Cost as per P&L Report (Zoho Books) | J10: =Details!AC39 -> 54711
D11: =SUM(D6:D10) -> 2422114.6 | F11: Final - Variance | G11: ='Recon Items'!F18 -> 0 | I11: Final - Variance | J11: =J9-J10 -> 0
C12: Revenue as per P&L Report (Zoho Books) | D12: =Details!AT39 -> 1967519.6 | G12: =SUM(G6:G11) -> 2354172
C13: Final - Variance | D13: =D11-D12 -> 454595 | F13: Cost as per P&L Report (Zoho Books) | G13: =Details!O39 -> 2354172
F14: Final - Variance | G14: =G12-G13-'Recon Items'!C18 -> 0
