Workbook

Sheet Summary
U2: ="As on"& " "&TEXT(Details!P64,"dd-mmm-yyyy") -> As on 21-Jun-2026 | V2: Non-Ferrous | AK2: Ferrous | AZ2: M3
D3: =TEXT(D5,"mmm-yy") -> Apr-26 | E3: =TEXT(E5,"mmm-yy") -> May-26 | F3: =TEXT(F5,"mmm-yy") -> Jun-26 | G3: =TEXT(G5,"mmm-yy") -> Jul-26 | H3: =TEXT(H5,"mmm-yy") -> Aug-26 | I3: =TEXT(I5,"mmm-yy") -> Sep-26 | J3: =TEXT(J5,"mmm-yy") -> Oct-26 | K3: =TEXT(K5,"mmm-yy") -> Nov-26 | ... O3: =TEXT(O5,"mmm-yy") -> Mar-27 | V3: Apr-25 | W3: =E3 -> May-26 | X3: =F3 -> Jun-26 | Y3: =G3 -> Jul-26 | Z3: =H3 -> Aug-26 | AA3: =I3 -> Sep-26 | AB3: =J3 -> Oct-26 | AC3: =K3 -> Nov-26 | AD3: =L3 -> Dec-26 | ... AG3: =O3 -> Mar-27 | AK3: =D3 -> Apr-26 | AL3: =E3 -> May-26 | AM3: =F3 -> Jun-26 | AN3: =G3 -> Jul-26 | AO3: =H3 -> Aug-26 | AP3: =I3 -> Sep-26 | AQ3: =J3 -> Oct-26 | AR3: =K3 -> Nov-26 | ... AV3: =O3 -> Mar-27 | AZ3: =TEXT(AZ5,"mmm-yy") -> Apr-26 | BA3: =TEXT(BA5,"mmm-yy") -> May-26 | BB3: =TEXT(BB5,"mmm-yy") -> Jun-26 | BC3: =TEXT(BC5,"mmm-yy") -> Jul-26 | BD3: =TEXT(BD5,"mmm-yy") -> Aug-26 | BE3: =TEXT(BE5,"mmm-yy") -> Sep-26 | BF3: =TEXT(BF5,"mmm-yy") -> Oct-26 | BG3: =TEXT(BG5,"mmm-yy") -> Nov-26 | ... BK3: =TEXT(BK5,"mmm-yy") -> Mar-27
D4: 30 | E4: 31 | F4: 21 | G4: 0 | H4: 0 | I4: 0 | J4: 0 | K4: 0 | L4: 0 | M4: 0 | N4: 0 | O4: 0 | P4: =SUM(D4:O4) -> 82 | V4: =D4 -> 30 | W4: =E4 -> 31 | X4: =F4 -> 21 | Y4: =G4 -> 0 | Z4: =H4 -> 0 | AA4: =I4 -> 0 | AB4: =J4 -> 0 | AC4: =K4 -> 0 | ... AH4: =P4 -> 82 | AK4: =D4 -> 30 | AL4: =E4 -> 31 | AM4: =F4 -> 21 | AN4: =G4 -> 0 | AO4: =H4 -> 0 | AP4: =I4 -> 0 | AQ4: =J4 -> 0 | AR4: =K4 -> 0 | ... AW4: =P4 -> 82 | AZ4: =D4 -> 30 | BA4: =E4 -> 31 | BB4: =F4 -> 21 | BC4: =G4 -> 0 | BD4: =H4 -> 0 | BE4: =I4 -> 0 | BF4: =J4 -> 0 | BG4: =K4 -> 0 | ... BL4: =P4 -> 82
C5: Marketplace (End Generator) | D5: 46113 | E5: 46143 | F5: 46174 | G5: 46204 | H5: 46235 | I5: 46266 | J5: 46296 | K5: 46327 | L5: 46357 | M5: 46388 | N5: 46419 | O5: 46447 | P5: FY 2026-27 | U5: Non-Ferrous | V5: =D5 -> 46113 | W5: =E5 -> 46143 | X5: =F5 -> 46174 | Y5: =G5 -> 46204 | Z5: =H5 -> 46235 | AA5: =I5 -> 46266 | AB5: =J5 -> 46296 | AC5: =K5 -> 46327 | ... AH5: =P5 -> FY 2026-27 | AJ5: Ferrous | AK5: =V5 -> 46113 | AL5: =W5 -> 46143 | AM5: =X5 -> 46174 | AN5: =Y5 -> 46204 | AO5: =Z5 -> 46235 | AP5: =AA5 -> 46266 | AQ5: =AB5 -> 46296 | AR5: =AC5 -> 46327 | ... AW5: =AH5 -> FY 2026-27 | AY5: M3 | AZ5: =AK5 -> 46113 | BA5: =AL5 -> 46143 | BB5: =AM5 -> 46174 | BC5: =AN5 -> 46204 | BD5: =AO5 -> 46235 | BE5: =AP5 -> 46266 | BF5: =AQ5 -> 46296 | BG5: =AR5 -> 46327 | ... BL5: =AW5 -> FY 2026-27 | BN5: Check
C6: Quantity (MT) | D6: 276.706 | E6: 129.15 | F6: =SUMIFS(Details!$BB$5:$BB$53,Details!$C$5:$C$53,Summary!F$5)/1000 -> 114.015 | G6: =SUMIFS(Details!$BB$5:$BB$53,Details!$C$5:$C$53,Summary!G$5)/1000 -> 0 | H6: =SUMIFS(Details!$BB$5:$BB$53,Details!$C$5:$C$53,Summary!H$5)/1000 -> 0 | I6: =SUMIFS(Details!$BB$5:$BB$53,Details!$C$5:$C$53,Summary!I$5)/1000 -> 0 | J6: =SUMIFS(Details!$BB$5:$BB$53,Details!$C$5:$C$53,Summary!J$5)/1000 -> 0 | K6: =SUMIFS(Details!$BB$5:$BB$53,Details!$C$5:$C$53,Summary!K$5)/1000 -> 0 | L6: =SUMIFS(Details!$BB$5:$BB$53,Details!$C$5:$C$53,Summary!L$5)/1000 -> 0 | M6: =SUMIFS(Details!$BB$5:$BB$53,Details!$C$5:$C$53,Summary!M$5)/1000 -> 0 | ... O6: =SUMIFS(Details!$BB$5:$BB$53,Details!$C$5:$C$53,Summary!O$5)/1000 -> 0 | P6: =SUM(D6:O6) -> 519.871 | Q6: =Details!BB54/1000 -> 519.761 | R6: =P6-Q6 -> 0.11 | T6: =-R6 -> -0.11 | U6: Quantity (MT) | V6: =SUMIFS(Details!$S$5:$S$53,Details!$C$5:$C$53,Summary!V$5,Details!$CK$5:$CK$53,Summary!$U$5)/1000 -> 26.99 | W6: =SUMIFS(Details!$S$5:$S$53,Details!$C$5:$C$53,Summary!W$5,Details!$CK$5:$CK$53,Summary!$U$5)/1000 -> 25.43 | X6: =SUMIFS(Details!$S$5:$S$53,Details!$C$5:$C$53,Summary!X$5,Details!$CK$5:$CK$53,Summary!$U$5)/1000 -> 14.385 | Y6: =SUMIFS(Details!$S$5:$S$53,Details!$C$5:$C$53,Summary!Y$5,Details!$CK$5:$CK$53,Summary!$U$5)/1000 -> 0 | Z6: =SUMIFS(Details!$S$5:$S$53,Details!$C$5:$C$53,Summary!Z$5,Details!$CK$5:$CK$53,Summary!$U$5)/1000 -> 0 | AA6: =SUMIFS(Details!$S$5:$S$53,Details!$C$5:$C$53,Summary!AA$5,Details!$CK$5:$CK$53,Summary!$U$5)/1000 -> 0 | AB6: =SUMIFS(Details!$S$5:$S$53,Details!$C$5:$C$53,Summary!AB$5,Details!$CK$5:$CK$53,Summary!$U$5)/1000 -> 0 | AC6: =SUMIFS(Details!$S$5:$S$53,Details!$C$5:$C$53,Summary!AC$5,Details!$CK$5:$CK$53,Summary!$U$5)/1000 -> 0 | ... AG6: =SUMIFS(Details!$S$5:$S$53,Details!$C$5:$C$53,Summary!AG$5,Details!$CK$5:$CK$53,Summary!$U$5)/1000 -> 0 | AH6: =SUM(V6:AG6) -> 66.805 | AJ6: Quantity (MT) | AK6: =SUMIFS(Details!$S$5:$S$53,Details!$C$5:$C$53,Summary!AK$5,Details!$CK$5:$CK$53,Summary!$AJ$5)/1000 -> 249.605 | AL6: =SUMIFS(Details!$S$5:$S$53,Details!$C$5:$C$53,Summary!AL$5,Details!$CK$5:$CK$53,Summary!$AJ$5)/1000 -> 104.47 | AM6: =SUMIFS(Details!$S$5:$S$53,Details!$C$5:$C$53,Summary!AM$5,Details!$CK$5:$CK$53,Summary!$AJ$5)/1000 -> 99.631 | AN6: =SUMIFS(Details!$S$5:$S$53,Details!$C$5:$C$53,Summary!AN$5,Details!$CK$5:$CK$53,Summary!$AJ$5)/1000 -> 0 | AO6: =SUMIFS(Details!$S$5:$S$53,Details!$C$5:$C$53,Summary!AO$5,Details!$CK$5:$CK$53,Summary!$AJ$5)/1000 -> 0 | AP6: =SUMIFS(Details!$S$5:$S$53,Details!$C$5:$C$53,Summary!AP$5,Details!$CK$5:$CK$53,Summary!$AJ$5)/1000 -> 0 | AQ6: =SUMIFS(Details!$S$5:$S$53,Details!$C$5:$C$53,Summary!AQ$5,Details!$CK$5:$CK$53,Summary!$AJ$5)/1000 -> 0 | AR6: =SUMIFS(Details!$S$5:$S$53,Details!$C$5:$C$53,Summary!AR$5,Details!$CK$5:$CK$53,Summary!$AJ$5)/1000 -> 0 | ... AV6: =SUMIFS(Details!$S$5:$S$53,Details!$C$5:$C$53,Summary!AV$5,Details!$CK$5:$CK$53,Summary!$AJ$5)/1000 -> 0 | AW6: =SUM(AK6:AV6) -> 453.706 | AY6: Quantity (MT) | AZ6: =SUMIFS(Details!$S$5:$S$53,Details!$C$5:$C$53,Summary!AZ$5,Details!$CK$5:$CK$53,Summary!$AY$5)/1000 -> 0 | BA6: =SUMIFS(Details!$S$5:$S$53,Details!$C$5:$C$53,Summary!BA$5,Details!$CK$5:$CK$53,Summary!$AY$5)/1000 -> 0 | BB6: =SUMIFS(Details!$S$5:$S$53,Details!$C$5:$C$53,Summary!BB$5,Details!$CK$5:$CK$53,Summary!$AY$5)/1000 -> 0 | BC6: =SUMIFS(Details!$S$5:$S$53,Details!$C$5:$C$53,Summary!BC$5,Details!$CK$5:$CK$53,Summary!$AY$5)/1000 -> 0 | BD6: =SUMIFS(Details!$S$5:$S$53,Details!$C$5:$C$53,Summary!BD$5,Details!$CK$5:$CK$53,Summary!$AY$5)/1000 -> 0 | BE6: =SUMIFS(Details!$S$5:$S$53,Details!$C$5:$C$53,Summary!BE$5,Details!$CK$5:$CK$53,Summary!$AY$5)/1000 -> 0 | BF6: =SUMIFS(Details!$S$5:$S$53,Details!$C$5:$C$53,Summary!BF$5,Details!$CK$5:$CK$53,Summary!$AY$5)/1000 -> 0 | BG6: =SUMIFS(Details!$S$5:$S$53,Details!$C$5:$C$53,Summary!BG$5,Details!$CK$5:$CK$53,Summary!$AY$5)/1000 -> 0 | ... BK6: =SUMIFS(Details!$S$5:$S$53,Details!$C$5:$C$53,Summary!BK$5,Details!$CK$5:$CK$53,Summary!$AY$5)/1000 -> 0 | BL6: =SUM(AZ6:BK6) -> 0 | BN6: =(AH6+AW6+BL6)-P6 -> 0.64 | CI6: =E6 -> 129.15 | CJ6: =T6+CI6 -> 129.04
C7: Sales | D7: 16902407 | E7: 11693868 | F7: =SUMIFS(Details!$BQ$5:$BQ$53,Details!$C$5:$C$53,Summary!F$5) -> 8359215.8 | G7: =SUMIFS(Details!$BQ$5:$BQ$53,Details!$C$5:$C$53,Summary!G$5) -> 0 | H7: =SUMIFS(Details!$BQ$5:$BQ$53,Details!$C$5:$C$53,Summary!H$5) -> 0 | I7: =SUMIFS(Details!$BQ$5:$BQ$53,Details!$C$5:$C$53,Summary!I$5) -> 0 | J7: =SUMIFS(Details!$BQ$5:$BQ$53,Details!$C$5:$C$53,Summary!J$5) -> 0 | K7: =SUMIFS(Details!$BQ$5:$BQ$53,Details!$C$5:$C$53,Summary!K$5) -> 0 | L7: =SUMIFS(Details!$BQ$5:$BQ$53,Details!$C$5:$C$53,Summary!L$5) -> 0 | M7: =SUMIFS(Details!$BQ$5:$BQ$53,Details!$C$5:$C$53,Summary!M$5) -> 0 | ... O7: =SUMIFS(Details!$BQ$5:$BQ$53,Details!$C$5:$C$53,Summary!O$5) -> 0 | P7: =SUM(D7:O7) -> 36955490 | Q7: =Details!BQ54 -> 37120499 | R7: =P7-Q7 -> -165008.1 | T7: =-R7 -> 165008.1 | U7: Sales | V7: =SUMIFS(Details!$BQ$5:$BQ$53,Details!$C$5:$C$53,Summary!V$5,Details!$CK$5:$CK$53,Summary!$U$5) -> 8931160 | W7: =SUMIFS(Details!$BQ$5:$BQ$53,Details!$C$5:$C$53,Summary!W$5,Details!$CK$5:$CK$53,Summary!$U$5) -> 8709308 | X7: =SUMIFS(Details!$BQ$5:$BQ$53,Details!$C$5:$C$53,Summary!X$5,Details!$CK$5:$CK$53,Summary!$U$5) -> 4932219.5 | Y7: =SUMIFS(Details!$BQ$5:$BQ$53,Details!$C$5:$C$53,Summary!Y$5,Details!$CK$5:$CK$53,Summary!$U$5) -> 0 | Z7: =SUMIFS(Details!$BQ$5:$BQ$53,Details!$C$5:$C$53,Summary!Z$5,Details!$CK$5:$CK$53,Summary!$U$5) -> 0 | AA7: =SUMIFS(Details!$BQ$5:$BQ$53,Details!$C$5:$C$53,Summary!AA$5,Details!$CK$5:$CK$53,Summary!$U$5) -> 0 | AB7: =SUMIFS(Details!$BQ$5:$BQ$53,Details!$C$5:$C$53,Summary!AB$5,Details!$CK$5:$CK$53,Summary!$U$5) -> 0 | AC7: =SUMIFS(Details!$BQ$5:$BQ$53,Details!$C$5:$C$53,Summary!AC$5,Details!$CK$5:$CK$53,Summary!$U$5) -> 0 | ... AG7: =SUMIFS(Details!$BQ$5:$BQ$53,Details!$C$5:$C$53,Summary!AG$5,Details!$CK$5:$CK$53,Summary!$U$5) -> 0 | AH7: =SUM(V7:AG7) -> 22572688 | AJ7: Sales | AK7: =SUMIFS(Details!$BQ$5:$BQ$53,Details!$C$5:$C$53,Summary!AK$5,Details!$CK$5:$CK$53,Summary!$AJ$5) -> 7989785.8 | AL7: =SUMIFS(Details!$BQ$5:$BQ$53,Details!$C$5:$C$53,Summary!AL$5,Details!$CK$5:$CK$53,Summary!$AJ$5) -> 3124279 | AM7: =SUMIFS(Details!$BQ$5:$BQ$53,Details!$C$5:$C$53,Summary!AM$5,Details!$CK$5:$CK$53,Summary!$AJ$5) -> 3426996.2 | AN7: =SUMIFS(Details!$BQ$5:$BQ$53,Details!$C$5:$C$53,Summary!AN$5,Details!$CK$5:$CK$53,Summary!$AJ$5) -> 0 | AO7: =SUMIFS(Details!$BQ$5:$BQ$53,Details!$C$5:$C$53,Summary!AO$5,Details!$CK$5:$CK$53,Summary!$AJ$5) -> 0 | AP7: =SUMIFS(Details!$BQ$5:$BQ$53,Details!$C$5:$C$53,Summary!AP$5,Details!$CK$5:$CK$53,Summary!$AJ$5) -> 0 | AQ7: =SUMIFS(Details!$BQ$5:$BQ$53,Details!$C$5:$C$53,Summary!AQ$5,Details!$CK$5:$CK$53,Summary!$AJ$5) -> 0 | AR7: =SUMIFS(Details!$BQ$5:$BQ$53,Details!$C$5:$C$53,Summary!AR$5,Details!$CK$5:$CK$53,Summary!$AJ$5) -> 0 | ... AV7: =SUMIFS(Details!$BQ$5:$BQ$53,Details!$C$5:$C$53,Summary!AV$5,Details!$CK$5:$CK$53,Summary!$AJ$5) -> 0 | AW7: =SUM(AK7:AV7) -> 14541061 | AY7: Sales | AZ7: =SUMIFS(Details!$BQ$5:$BQ$53,Details!$C$5:$C$53,Summary!AZ$5,Details!$CK$5:$CK$53,Summary!$AY$5) -> 0 | BA7: =SUMIFS(Details!$BQ$5:$BQ$53,Details!$C$5:$C$53,Summary!BA$5,Details!$CK$5:$CK$53,Summary!$AY$5) -> 0 | BB7: =SUMIFS(Details!$BQ$5:$BQ$53,Details!$C$5:$C$53,Summary!BB$5,Details!$CK$5:$CK$53,Summary!$AY$5) -> 0 | BC7: =SUMIFS(Details!$BQ$5:$BQ$53,Details!$C$5:$C$53,Summary!BC$5,Details!$CK$5:$CK$53,Summary!$AY$5) -> 0 | BD7: =SUMIFS(Details!$BQ$5:$BQ$53,Details!$C$5:$C$53,Summary!BD$5,Details!$CK$5:$CK$53,Summary!$AY$5) -> 0 | BE7: =SUMIFS(Details!$BQ$5:$BQ$53,Details!$C$5:$C$53,Summary!BE$5,Details!$CK$5:$CK$53,Summary!$AY$5) -> 0 | BF7: =SUMIFS(Details!$BQ$5:$BQ$53,Details!$C$5:$C$53,Summary!BF$5,Details!$CK$5:$CK$53,Summary!$AY$5) -> 0 | BG7: =SUMIFS(Details!$BQ$5:$BQ$53,Details!$C$5:$C$53,Summary!BG$5,Details!$CK$5:$CK$53,Summary!$AY$5) -> 0 | ... BK7: =SUMIFS(Details!$BQ$5:$BQ$53,Details!$C$5:$C$53,Summary!BK$5,Details!$CK$5:$CK$53,Summary!$AY$5) -> 0 | BL7: =SUM(AZ7:BK7) -> 0 | BN7: =(AH7+AW7+BL7)-P7 -> 158258.1 | CI7: =E7 -> 11693868 | CJ7: =T7+CI7 -> 11858876
C8: Purchases | D8: 16663815 | E8: 11364387 | F8: =SUMIFS(Details!$AM$5:$AM$53,Details!$C$5:$C$53,Summary!F$5)-SUMIFS(Details!$AB$5:$AB$53,Details!$C$5:$C$53,Summary!F$5) -> 8135007 | G8: =SUMIFS(Details!$AM$5:$AM$53,Details!$C$5:$C$53,Summary!G$5)-SUMIFS(Details!$AB$5:$AB$53,Details!$C$5:$C$53,Summary!G$5) -> 0 | H8: =SUMIFS(Details!$AM$5:$AM$53,Details!$C$5:$C$53,Summary!H$5)-SUMIFS(Details!$AB$5:$AB$53,Details!$C$5:$C$53,Summary!H$5) -> 0 | I8: =SUMIFS(Details!$AM$5:$AM$53,Details!$C$5:$C$53,Summary!I$5)-SUMIFS(Details!$AB$5:$AB$53,Details!$C$5:$C$53,Summary!I$5) -> 0 | J8: =SUMIFS(Details!$AM$5:$AM$53,Details!$C$5:$C$53,Summary!J$5)-SUMIFS(Details!$AB$5:$AB$53,Details!$C$5:$C$53,Summary!J$5) -> 0 | K8: =SUMIFS(Details!$AM$5:$AM$53,Details!$C$5:$C$53,Summary!K$5)-SUMIFS(Details!$AB$5:$AB$53,Details!$C$5:$C$53,Summary!K$5) -> 0 | L8: =SUMIFS(Details!$AM$5:$AM$53,Details!$C$5:$C$53,Summary!L$5)-SUMIFS(Details!$AB$5:$AB$53,Details!$C$5:$C$53,Summary!L$5) -> 0 | M8: =SUMIFS(Details!$AM$5:$AM$53,Details!$C$5:$C$53,Summary!M$5)-SUMIFS(Details!$AB$5:$AB$53,Details!$C$5:$C$53,Summary!M$5) -> 0 | ... O8: =SUMIFS(Details!$AM$5:$AM$53,Details!$C$5:$C$53,Summary!O$5)-SUMIFS(Details!$AB$5:$AB$53,Details!$C$5:$C$53,Summary!O$5) -> 0 | P8: =SUM(D8:O8) -> 36163209 | Q8: =Details!P55 -> 36323313 | R8: =P8-Q8 -> -160104.08 | T8: =-R8 -> 160104.08 | U8: Purchases | V8: =SUMIFS(Details!$AM$5:$AM$53,Details!$C$5:$C$53,Summary!V$5,Details!$CK$5:$CK$53,Summary!$U$5)-SUMIFS(Details!$AB$5:$AB$53,Details!$C$5:$C$53,Summary!V$5,Details!$CK$5:$CK$53,Summary!$U$5) -> 8673578.9 | W8: =SUMIFS(Details!$AM$5:$AM$53,Details!$C$5:$C$53,Summary!W$5,Details!$CK$5:$CK$53,Summary!$U$5)-SUMIFS(Details!$AB$5:$AB$53,Details!$C$5:$C$53,Summary!W$5,Details!$CK$5:$CK$53,Summary!$U$5) -> 8465886.5 | X8: =SUMIFS(Details!$AM$5:$AM$53,Details!$C$5:$C$53,Summary!X$5,Details!$CK$5:$CK$53,Summary!$U$5)-SUMIFS(Details!$AB$5:$AB$53,Details!$C$5:$C$53,Summary!X$5,Details!$CK$5:$CK$53,Summary!$U$5) -> 4784088.3 | Y8: =SUMIFS(Details!$AM$5:$AM$53,Details!$C$5:$C$53,Summary!Y$5,Details!$CK$5:$CK$53,Summary!$U$5)-SUMIFS(Details!$AB$5:$AB$53,Details!$C$5:$C$53,Summary!Y$5,Details!$CK$5:$CK$53,Summary!$U$5) -> 0 | Z8: =SUMIFS(Details!$AM$5:$AM$53,Details!$C$5:$C$53,Summary!Z$5,Details!$CK$5:$CK$53,Summary!$U$5)-SUMIFS(Details!$AB$5:$AB$53,Details!$C$5:$C$53,Summary!Z$5,Details!$CK$5:$CK$53,Summary!$U$5) -> 0 | AA8: =SUMIFS(Details!$AM$5:$AM$53,Details!$C$5:$C$53,Summary!AA$5,Details!$CK$5:$CK$53,Summary!$U$5)-SUMIFS(Details!$AB$5:$AB$53,Details!$C$5:$C$53,Summary!AA$5,Details!$CK$5:$CK$53,Summary!$U$5) -> 0 | AB8: =SUMIFS(Details!$AM$5:$AM$53,Details!$C$5:$C$53,Summary!AB$5,Details!$CK$5:$CK$53,Summary!$U$5)-SUMIFS(Details!$AB$5:$AB$53,Details!$C$5:$C$53,Summary!AB$5,Details!$CK$5:$CK$53,Summary!$U$5) -> 0 | AC8: =SUMIFS(Details!$AM$5:$AM$53,Details!$C$5:$C$53,Summary!AC$5,Details!$CK$5:$CK$53,Summary!$U$5)-SUMIFS(Details!$AB$5:$AB$53,Details!$C$5:$C$53,Summary!AC$5,Details!$CK$5:$CK$53,Summary!$U$5) -> 0 | ... AG8: =SUMIFS(Details!$AM$5:$AM$53,Details!$C$5:$C$53,Summary!AG$5,Details!$CK$5:$CK$53,Summary!$U$5)-SUMIFS(Details!$AB$5:$AB$53,Details!$C$5:$C$53,Summary!AG$5,Details!$CK$5:$CK$53,Summary!$U$5) -> 0 | AH8: =SUM(V8:AG8) -> 21923554 | AJ8: Purchases | AK8: =SUMIFS(Details!$AM$5:$AM$53,Details!$C$5:$C$53,Summary!AK$5,Details!$CK$5:$CK$53,Summary!$AJ$5)-SUMIFS(Details!$AB$5:$AB$53,Details!$C$5:$C$53,Summary!AK$5,Details!$CK$5:$CK$53,Summary!$AJ$5) -> 7980660.2 | AL8: =SUMIFS(Details!$AM$5:$AM$53,Details!$C$5:$C$53,Summary!AL$5,Details!$CK$5:$CK$53,Summary!$AJ$5)-SUMIFS(Details!$AB$5:$AB$53,Details!$C$5:$C$53,Summary!AL$5,Details!$CK$5:$CK$53,Summary!$AJ$5) -> 3061430.7 | AM8: =SUMIFS(Details!$AM$5:$AM$53,Details!$C$5:$C$53,Summary!AM$5,Details!$CK$5:$CK$53,Summary!$AJ$5)-SUMIFS(Details!$AB$5:$AB$53,Details!$C$5:$C$53,Summary!AM$5,Details!$CK$5:$CK$53,Summary!$AJ$5) -> 3350918.8 | AN8: =SUMIFS(Details!$AM$5:$AM$53,Details!$C$5:$C$53,Summary!AN$5,Details!$CK$5:$CK$53,Summary!$AJ$5)-SUMIFS(Details!$AB$5:$AB$53,Details!$C$5:$C$53,Summary!AN$5,Details!$CK$5:$CK$53,Summary!$AJ$5) -> 0 | AO8: =SUMIFS(Details!$AM$5:$AM$53,Details!$C$5:$C$53,Summary!AO$5,Details!$CK$5:$CK$53,Summary!$AJ$5)-SUMIFS(Details!$AB$5:$AB$53,Details!$C$5:$C$53,Summary!AO$5,Details!$CK$5:$CK$53,Summary!$AJ$5) -> 0 | AP8: =SUMIFS(Details!$AM$5:$AM$53,Details!$C$5:$C$53,Summary!AP$5,Details!$CK$5:$CK$53,Summary!$AJ$5)-SUMIFS(Details!$AB$5:$AB$53,Details!$C$5:$C$53,Summary!AP$5,Details!$CK$5:$CK$53,Summary!$AJ$5) -> 0 | AQ8: =SUMIFS(Details!$AM$5:$AM$53,Details!$C$5:$C$53,Summary!AQ$5,Details!$CK$5:$CK$53,Summary!$AJ$5)-SUMIFS(Details!$AB$5:$AB$53,Details!$C$5:$C$53,Summary!AQ$5,Details!$CK$5:$CK$53,Summary!$AJ$5) -> 0 | AR8: =SUMIFS(Details!$AM$5:$AM$53,Details!$C$5:$C$53,Summary!AR$5,Details!$CK$5:$CK$53,Summary!$AJ$5)-SUMIFS(Details!$AB$5:$AB$53,Details!$C$5:$C$53,Summary!AR$5,Details!$CK$5:$CK$53,Summary!$AJ$5) -> 0 | ... AV8: =SUMIFS(Details!$AM$5:$AM$53,Details!$C$5:$C$53,Summary!AV$5,Details!$CK$5:$CK$53,Summary!$AJ$5)-SUMIFS(Details!$AB$5:$AB$53,Details!$C$5:$C$53,Summary!AV$5,Details!$CK$5:$CK$53,Summary!$AJ$5) -> 0 | AW8: =SUM(AK8:AV8) -> 14393010 | AY8: Purchases | AZ8: =SUMIFS(Details!$AM$5:$AM$53,Details!$C$5:$C$53,Summary!AZ$5,Details!$CK$5:$CK$53,Summary!$AY$5)-SUMIFS(Details!$AB$5:$AB$53,Details!$C$5:$C$53,Summary!AZ$5,Details!$CK$5:$CK$53,Summary!$AY$5) -> 0 | BA8: =SUMIFS(Details!$AM$5:$AM$53,Details!$C$5:$C$53,Summary!BA$5,Details!$CK$5:$CK$53,Summary!$AY$5)-SUMIFS(Details!$AB$5:$AB$53,Details!$C$5:$C$53,Summary!BA$5,Details!$CK$5:$CK$53,Summary!$AY$5) -> 0 | BB8: =SUMIFS(Details!$AM$5:$AM$53,Details!$C$5:$C$53,Summary!BB$5,Details!$CK$5:$CK$53,Summary!$AY$5)-SUMIFS(Details!$AB$5:$AB$53,Details!$C$5:$C$53,Summary!BB$5,Details!$CK$5:$CK$53,Summary!$AY$5) -> 0 | BC8: =SUMIFS(Details!$AM$5:$AM$53,Details!$C$5:$C$53,Summary!BC$5,Details!$CK$5:$CK$53,Summary!$AY$5)-SUMIFS(Details!$AB$5:$AB$53,Details!$C$5:$C$53,Summary!BC$5,Details!$CK$5:$CK$53,Summary!$AY$5) -> 0 | BD8: =SUMIFS(Details!$AM$5:$AM$53,Details!$C$5:$C$53,Summary!BD$5,Details!$CK$5:$CK$53,Summary!$AY$5)-SUMIFS(Details!$AB$5:$AB$53,Details!$C$5:$C$53,Summary!BD$5,Details!$CK$5:$CK$53,Summary!$AY$5) -> 0 | BE8: =SUMIFS(Details!$AM$5:$AM$53,Details!$C$5:$C$53,Summary!BE$5,Details!$CK$5:$CK$53,Summary!$AY$5)-SUMIFS(Details!$AB$5:$AB$53,Details!$C$5:$C$53,Summary!BE$5,Details!$CK$5:$CK$53,Summary!$AY$5) -> 0 | BF8: =SUMIFS(Details!$AM$5:$AM$53,Details!$C$5:$C$53,Summary!BF$5,Details!$CK$5:$CK$53,Summary!$AY$5)-SUMIFS(Details!$AB$5:$AB$53,Details!$C$5:$C$53,Summary!BF$5,Details!$CK$5:$CK$53,Summary!$AY$5) -> 0 | BG8: =SUMIFS(Details!$AM$5:$AM$53,Details!$C$5:$C$53,Summary!BG$5,Details!$CK$5:$CK$53,Summary!$AY$5)-SUMIFS(Details!$AB$5:$AB$53,Details!$C$5:$C$53,Summary!BG$5,Details!$CK$5:$CK$53,Summary!$AY$5) -> 0 | ... BK8: =SUMIFS(Details!$AM$5:$AM$53,Details!$C$5:$C$53,Summary!BK$5,Details!$CK$5:$CK$53,Summary!$AY$5)-SUMIFS(Details!$AB$5:$AB$53,Details!$C$5:$C$53,Summary!BK$5,Details!$CK$5:$CK$53,Summary!$AY$5) -> 0 | BL8: =SUM(AZ8:BK8) -> 0 | BN8: =(AH8+AW8+BL8)-P8 -> 153354.08 | CI8: =E8 -> 11364387 | CJ8: =T8+CI8 -> 11524491
C9: Gross Margin | D9: =D7-D8 -> 238591.53 | E9: =E7-E8 -> 329480.87 | F9: =F7-F8 -> 224208.75 | G9: =G7-G8 -> 0 | H9: =H7-H8 -> 0 | I9: =I7-I8 -> 0 | J9: =J7-J8 -> 0 | K9: =K7-K8 -> 0 | ... P9: =P7-P8 -> 792281.15 | U9: Gross Margin | V9: =V7-V8 -> 257581.1 | W9: =W7-W8 -> 243421.5 | X9: =X7-X8 -> 148131.29 | Y9: =Y7-Y8 -> 0 | Z9: =Z7-Z8 -> 0 | AA9: =AA7-AA8 -> 0 | AB9: =AB7-AB8 -> 0 | AC9: =AC7-AC8 -> 0 | ... AH9: =AH7-AH8 -> 649133.89 | AJ9: Gross Margin | AK9: =AK7-AK8 -> 9125.5903 | AL9: =AL7-AL8 -> 62848.221 | AM9: =AM7-AM8 -> 76077.468 | AN9: =AN7-AN8 -> 0 | AO9: =AO7-AO8 -> 0 | AP9: =AP7-AP8 -> 0 | AQ9: =AQ7-AQ8 -> 0 | AR9: =AR7-AR8 -> 0 | ... AW9: =AW7-AW8 -> 148051.28 | AY9: Gross Margin | AZ9: =AZ7-AZ8 -> 0 | BA9: =BA7-BA8 -> 0 | BB9: =BB7-BB8 -> 0 | BC9: =BC7-BC8 -> 0 | BD9: =BD7-BD8 -> 0 | BE9: =BE7-BE8 -> 0 | BF9: =BF7-BF8 -> 0 | BG9: =BG7-BG8 -> 0 | ... BL9: =BL7-BL8 -> 0 | BN9: =(AH9+AW9+BL9)-P9 -> 4904.0175
C10: Gross Margin (%) | D10: =IFERROR((D9/D7),0) -> 0.014115832 | E10: =IFERROR((E9/E7),0) -> 0.028175525 | F10: =IFERROR((F9/F7),0) -> 0.026821745 | G10: =IFERROR((G9/G7),0) -> 0 | H10: =IFERROR((H9/H7),0) -> 0 | I10: =IFERROR((I9/I7),0) -> 0 | J10: =IFERROR((J9/J7),0) -> 0 | K10: =IFERROR((K9/K7),0) -> 0 | ... P10: =IFERROR((P9/P7),0) -> 0.021438794 | U10: Gross Margin (%) | V10: =IFERROR((V9/V7),0) -> 0.028840722 | W10: =IFERROR((W9/W7),0) -> 0.02794958 | X10: =IFERROR((X9/X7),0) -> 0.030033393 | Y10: =IFERROR((Y9/Y7),0) -> 0 | Z10: =IFERROR((Z9/Z7),0) -> 0 | AA10: =IFERROR((AA9/AA7),0) -> 0 | AB10: =IFERROR((AB9/AB7),0) -> 0 | AC10: =IFERROR((AC9/AC7),0) -> 0 | ... AH10: =IFERROR((AH9/AH7),0) -> 0.028757492 | AJ10: Gross Margin (%) | AK10: =IFERROR((AK9/AK7),0) -> 0.0011421571 | AL10: =IFERROR((AL9/AL7),0) -> 0.020116072 | AM10: =IFERROR((AM9/AM7),0) -> 0.022199461 | AN10: =IFERROR((AN9/AN7),0) -> 0 | AO10: =IFERROR((AO9/AO7),0) -> 0 | AP10: =IFERROR((AP9/AP7),0) -> 0 | AQ10: =IFERROR((AQ9/AQ7),0) -> 0 | AR10: =IFERROR((AR9/AR7),0) -> 0 | ... AW10: =IFERROR((AW9/AW7),0) -> 0.010181601 | AY10: Gross Margin (%) | AZ10: =IFERROR((AZ9/AZ7),0) -> 0 | BA10: =IFERROR((BA9/BA7),0) -> 0 | BB10: =IFERROR((BB9/BB7),0) -> 0 | BC10: =IFERROR((BC9/BC7),0) -> 0 | BD10: =IFERROR((BD9/BD7),0) -> 0 | BE10: =IFERROR((BE9/BE7),0) -> 0 | BF10: =IFERROR((BF9/BF7),0) -> 0 | BG10: =IFERROR((BG9/BG7),0) -> 0 | ... BL10: =IFERROR((BL9/BL7),0) -> 0 | BN10: =(AH10+AW10+BL10)-P10 -> 0.017500299
C11: Transportation Charges | D11: =SUMIFS(Details!$AB$5:$AB$53,Details!$C$5:$C$53,Summary!D$5) -> 0 | E11: =SUMIFS(Details!$AB$5:$AB$53,Details!$C$5:$C$53,Summary!E$5) -> 0 | F11: =SUMIFS(Details!$AB$5:$AB$53,Details!$C$5:$C$53,Summary!F$5) -> 0 | G11: =SUMIFS(Details!$AB$5:$AB$53,Details!$C$5:$C$53,Summary!G$5) -> 0 | H11: =SUMIFS(Details!$AB$5:$AB$53,Details!$C$5:$C$53,Summary!H$5) -> 0 | I11: =SUMIFS(Details!$AB$5:$AB$53,Details!$C$5:$C$53,Summary!I$5) -> 0 | J11: =SUMIFS(Details!$AB$5:$AB$53,Details!$C$5:$C$53,Summary!J$5) -> 0 | K11: =SUMIFS(Details!$AB$5:$AB$53,Details!$C$5:$C$53,Summary!K$5) -> 0 | ... O11: =SUMIFS(Details!$AB$5:$AB$53,Details!$C$5:$C$53,Summary!O$5) -> 0 | P11: =SUM(D11:O11) -> 0 | Q11: =Details!AB54 -> 0 | R11: =P11-Q11 -> 0 | T11: =-R11 -> 0 | U11: Quantity (MT) | V11: =SUMIFS(Details!$S$5:$S$53,Details!$C$5:$C$53,Summary!V$5,Details!$CK$5:$CK$53,Summary!$U$5)/1000 -> 26.99 | W11: =SUMIFS(Details!$S$5:$S$53,Details!$C$5:$C$53,Summary!W$5,Details!$CK$5:$CK$53,Summary!$U$5)/1000 -> 25.43 | X11: =SUMIFS(Details!$S$5:$S$53,Details!$C$5:$C$53,Summary!X$5,Details!$CK$5:$CK$53,Summary!$U$5)/1000 -> 14.385 | Y11: =SUMIFS(Details!$S$5:$S$53,Details!$C$5:$C$53,Summary!Y$5,Details!$CK$5:$CK$53,Summary!$U$5)/1000 -> 0 | Z11: =SUMIFS(Details!$S$5:$S$53,Details!$C$5:$C$53,Summary!Z$5,Details!$CK$5:$CK$53,Summary!$U$5)/1000 -> 0 | AA11: =SUMIFS(Details!$S$5:$S$53,Details!$C$5:$C$53,Summary!AA$5,Details!$CK$5:$CK$53,Summary!$U$5)/1000 -> 0 | AB11: =SUMIFS(Details!$S$5:$S$53,Details!$C$5:$C$53,Summary!AB$5,Details!$CK$5:$CK$53,Summary!$U$5)/1000 -> 0 | AC11: =SUMIFS(Details!$S$5:$S$53,Details!$C$5:$C$53,Summary!AC$5,Details!$CK$5:$CK$53,Summary!$U$5)/1000 -> 0 | ... AG11: =SUMIFS(Details!$S$5:$S$53,Details!$C$5:$C$53,Summary!AG$5,Details!$CK$5:$CK$53,Summary!$U$5)/1000 -> 0 | AH11: =SUM(V11:AG11) -> 66.805 | AJ11: Quantity (MT) | AK11: =SUMIFS(Details!$S$5:$S$53,Details!$C$5:$C$53,Summary!AK$5,Details!$CK$5:$CK$53,Summary!$AJ$5)/1000 -> 249.605 | AL11: =SUMIFS(Details!$S$5:$S$53,Details!$C$5:$C$53,Summary!AL$5,Details!$CK$5:$CK$53,Summary!$AJ$5)/1000 -> 104.47 | AM11: =SUMIFS(Details!$S$5:$S$53,Details!$C$5:$C$53,Summary!AM$5,Details!$CK$5:$CK$53,Summary!$AJ$5)/1000 -> 99.631 | AN11: =SUMIFS(Details!$S$5:$S$53,Details!$C$5:$C$53,Summary!AN$5,Details!$CK$5:$CK$53,Summary!$AJ$5)/1000 -> 0 | AO11: =SUMIFS(Details!$S$5:$S$53,Details!$C$5:$C$53,Summary!AO$5,Details!$CK$5:$CK$53,Summary!$AJ$5)/1000 -> 0 | AP11: =SUMIFS(Details!$S$5:$S$53,Details!$C$5:$C$53,Summary!AP$5,Details!$CK$5:$CK$53,Summary!$AJ$5)/1000 -> 0 | AQ11: =SUMIFS(Details!$S$5:$S$53,Details!$C$5:$C$53,Summary!AQ$5,Details!$CK$5:$CK$53,Summary!$AJ$5)/1000 -> 0 | AR11: =SUMIFS(Details!$S$5:$S$53,Details!$C$5:$C$53,Summary!AR$5,Details!$CK$5:$CK$53,Summary!$AJ$5)/1000 -> 0 | ... AV11: =SUMIFS(Details!$S$5:$S$53,Details!$C$5:$C$53,Summary!AV$5,Details!$CK$5:$CK$53,Summary!$AJ$5)/1000 -> 0 | AW11: =SUM(AK11:AV11) -> 453.706 | AY11: Quantity (MT) | AZ11: =SUMIFS(Details!$S$5:$S$53,Details!$C$5:$C$53,Summary!AZ$5,Details!$CK$5:$CK$53,Summary!$AY$5)/1000 -> 0 | BA11: =SUMIFS(Details!$S$5:$S$53,Details!$C$5:$C$53,Summary!BA$5,Details!$CK$5:$CK$53,Summary!$AY$5)/1000 -> 0 | BB11: =SUMIFS(Details!$S$5:$S$53,Details!$C$5:$C$53,Summary!BB$5,Details!$CK$5:$CK$53,Summary!$AY$5)/1000 -> 0 | BC11: =SUMIFS(Details!$S$5:$S$53,Details!$C$5:$C$53,Summary!BC$5,Details!$CK$5:$CK$53,Summary!$AY$5)/1000 -> 0 | BD11: =SUMIFS(Details!$S$5:$S$53,Details!$C$5:$C$53,Summary!BD$5,Details!$CK$5:$CK$53,Summary!$AY$5)/1000 -> 0 | BE11: =SUMIFS(Details!$S$5:$S$53,Details!$C$5:$C$53,Summary!BE$5,Details!$CK$5:$CK$53,Summary!$AY$5)/1000 -> 0 | BF11: =SUMIFS(Details!$S$5:$S$53,Details!$C$5:$C$53,Summary!BF$5,Details!$CK$5:$CK$53,Summary!$AY$5)/1000 -> 0 | BG11: =SUMIFS(Details!$S$5:$S$53,Details!$C$5:$C$53,Summary!BG$5,Details!$CK$5:$CK$53,Summary!$AY$5)/1000 -> 0 | ... BK11: =SUMIFS(Details!$S$5:$S$53,Details!$C$5:$C$53,Summary!BK$5,Details!$CK$5:$CK$53,Summary!$AY$5)/1000 -> 0 | BL11: =SUM(AZ11:BK11) -> 0 | BN11: =(AH11+AW11+BL11)-P11 -> 520.511 | CI11: =E11 -> 0 | CJ11: =T11+CI11 -> 0
C12: Operational Cost | D12: =SUMIFS(Details!$AC$5:$AC$53,Details!$C$5:$C$53,Summary!D$5) -> 0 | E12: =SUMIFS(Details!$AC$5:$AC$53,Details!$C$5:$C$53,Summary!E$5) -> 0 | F12: =SUMIFS(Details!$AC$5:$AC$53,Details!$C$5:$C$53,Summary!F$5) -> 0 | G12: =SUMIFS(Details!$AC$5:$AC$53,Details!$C$5:$C$53,Summary!G$5) -> 0 | H12: =SUMIFS(Details!$AC$5:$AC$53,Details!$C$5:$C$53,Summary!H$5) -> 0 | I12: =SUMIFS(Details!$AC$5:$AC$53,Details!$C$5:$C$53,Summary!I$5) -> 0 | J12: =SUMIFS(Details!$AC$5:$AC$53,Details!$C$5:$C$53,Summary!J$5) -> 0 | K12: =SUMIFS(Details!$AC$5:$AC$53,Details!$C$5:$C$53,Summary!K$5) -> 0 | ... O12: =SUMIFS(Details!$AC$5:$AC$53,Details!$C$5:$C$53,Summary!O$5) -> 0 | P12: =SUM(D12:O12) -> 0 | R12: =P12-Q12 -> 0 | T12: =-R12 -> 0 | U12: Quantity (MT) | V12: =SUMIFS(Details!$S$5:$S$53,Details!$C$5:$C$53,Summary!V$5,Details!$CK$5:$CK$53,Summary!$U$5)/1000 -> 26.99 | W12: =SUMIFS(Details!$S$5:$S$53,Details!$C$5:$C$53,Summary!W$5,Details!$CK$5:$CK$53,Summary!$U$5)/1000 -> 25.43 | X12: =SUMIFS(Details!$S$5:$S$53,Details!$C$5:$C$53,Summary!X$5,Details!$CK$5:$CK$53,Summary!$U$5)/1000 -> 14.385 | Y12: =SUMIFS(Details!$S$5:$S$53,Details!$C$5:$C$53,Summary!Y$5,Details!$CK$5:$CK$53,Summary!$U$5)/1000 -> 0 | Z12: =SUMIFS(Details!$S$5:$S$53,Details!$C$5:$C$53,Summary!Z$5,Details!$CK$5:$CK$53,Summary!$U$5)/1000 -> 0 | AA12: =SUMIFS(Details!$S$5:$S$53,Details!$C$5:$C$53,Summary!AA$5,Details!$CK$5:$CK$53,Summary!$U$5)/1000 -> 0 | AB12: =SUMIFS(Details!$S$5:$S$53,Details!$C$5:$C$53,Summary!AB$5,Details!$CK$5:$CK$53,Summary!$U$5)/1000 -> 0 | AC12: =SUMIFS(Details!$S$5:$S$53,Details!$C$5:$C$53,Summary!AC$5,Details!$CK$5:$CK$53,Summary!$U$5)/1000 -> 0 | ... AG12: =SUMIFS(Details!$S$5:$S$53,Details!$C$5:$C$53,Summary!AG$5,Details!$CK$5:$CK$53,Summary!$U$5)/1000 -> 0 | AH12: =SUM(V12:AG12) -> 66.805 | AJ12: Quantity (MT) | AK12: =SUMIFS(Details!$S$5:$S$53,Details!$C$5:$C$53,Summary!AK$5,Details!$CK$5:$CK$53,Summary!$AJ$5)/1000 -> 249.605 | AL12: =SUMIFS(Details!$S$5:$S$53,Details!$C$5:$C$53,Summary!AL$5,Details!$CK$5:$CK$53,Summary!$AJ$5)/1000 -> 104.47 | AM12: =SUMIFS(Details!$S$5:$S$53,Details!$C$5:$C$53,Summary!AM$5,Details!$CK$5:$CK$53,Summary!$AJ$5)/1000 -> 99.631 | AN12: =SUMIFS(Details!$S$5:$S$53,Details!$C$5:$C$53,Summary!AN$5,Details!$CK$5:$CK$53,Summary!$AJ$5)/1000 -> 0 | AO12: =SUMIFS(Details!$S$5:$S$53,Details!$C$5:$C$53,Summary!AO$5,Details!$CK$5:$CK$53,Summary!$AJ$5)/1000 -> 0 | AP12: =SUMIFS(Details!$S$5:$S$53,Details!$C$5:$C$53,Summary!AP$5,Details!$CK$5:$CK$53,Summary!$AJ$5)/1000 -> 0 | AQ12: =SUMIFS(Details!$S$5:$S$53,Details!$C$5:$C$53,Summary!AQ$5,Details!$CK$5:$CK$53,Summary!$AJ$5)/1000 -> 0 | AR12: =SUMIFS(Details!$S$5:$S$53,Details!$C$5:$C$53,Summary!AR$5,Details!$CK$5:$CK$53,Summary!$AJ$5)/1000 -> 0 | ... AV12: =SUMIFS(Details!$S$5:$S$53,Details!$C$5:$C$53,Summary!AV$5,Details!$CK$5:$CK$53,Summary!$AJ$5)/1000 -> 0 | AW12: =SUM(AK12:AV12) -> 453.706 | AY12: Quantity (MT) | AZ12: =SUMIFS(Details!$S$5:$S$53,Details!$C$5:$C$53,Summary!AZ$5,Details!$CK$5:$CK$53,Summary!$AY$5)/1000 -> 0 | BA12: =SUMIFS(Details!$S$5:$S$53,Details!$C$5:$C$53,Summary!BA$5,Details!$CK$5:$CK$53,Summary!$AY$5)/1000 -> 0 | BB12: =SUMIFS(Details!$S$5:$S$53,Details!$C$5:$C$53,Summary!BB$5,Details!$CK$5:$CK$53,Summary!$AY$5)/1000 -> 0 | BC12: =SUMIFS(Details!$S$5:$S$53,Details!$C$5:$C$53,Summary!BC$5,Details!$CK$5:$CK$53,Summary!$AY$5)/1000 -> 0 | BD12: =SUMIFS(Details!$S$5:$S$53,Details!$C$5:$C$53,Summary!BD$5,Details!$CK$5:$CK$53,Summary!$AY$5)/1000 -> 0 | BE12: =SUMIFS(Details!$S$5:$S$53,Details!$C$5:$C$53,Summary!BE$5,Details!$CK$5:$CK$53,Summary!$AY$5)/1000 -> 0 | BF12: =SUMIFS(Details!$S$5:$S$53,Details!$C$5:$C$53,Summary!BF$5,Details!$CK$5:$CK$53,Summary!$AY$5)/1000 -> 0 | BG12: =SUMIFS(Details!$S$5:$S$53,Details!$C$5:$C$53,Summary!BG$5,Details!$CK$5:$CK$53,Summary!$AY$5)/1000 -> 0 | ... BK12: =SUMIFS(Details!$S$5:$S$53,Details!$C$5:$C$53,Summary!BK$5,Details!$CK$5:$CK$53,Summary!$AY$5)/1000 -> 0 | BL12: =SUM(AZ12:BK12) -> 0 | BN12: =(AH12+AW12+BL12)-P12 -> 520.511 | CI12: =E12 -> 0 | CJ12: =T12+CI12 -> 0
C13: Net Margin | D13: =D9-D11-D12 -> 238591.53 | E13: =E9-E11-E12 -> 329480.87 | F13: =F9-F11-F12 -> 224208.75 | G13: =G9-G11-G12 -> 0 | H13: =H9-H11-H12 -> 0 | I13: =I9-I11-I12 -> 0 | J13: =J9-J11-J12 -> 0 | K13: =K9-K11-K12 -> 0 | ... P13: =P9-P11-P12 -> 792281.15 | U13: Net Margin | V13: =V9-V11-V12 -> 257527.12 | W13: =W9-W11-W12 -> 243370.64 | X13: =X9-X11-X12 -> 148102.52 | Y13: =Y9-Y11-Y12 -> 0 | Z13: =Z9-Z11-Z12 -> 0 | AA13: =AA9-AA11-AA12 -> 0 | AB13: =AB9-AB11-AB12 -> 0 | AC13: =AC9-AC11-AC12 -> 0 | ... AH13: =AH9-AH11-AH12 -> 649000.28 | AJ13: Net Margin | AK13: =AK9-AK11-AK12 -> 8626.3803 | AL13: =AL9-AL11-AL12 -> 62639.281 | AM13: =AM9-AM11-AM12 -> 75878.206 | AN13: =AN9-AN11-AN12 -> 0 | AO13: =AO9-AO11-AO12 -> 0 | AP13: =AP9-AP11-AP12 -> 0 | AQ13: =AQ9-AQ11-AQ12 -> 0 | AR13: =AR9-AR11-AR12 -> 0 | ... AW13: =AW9-AW11-AW12 -> 147143.87 | AY13: Net Margin | AZ13: =AZ9-AZ11-AZ12 -> 0 | BA13: =BA9-BA11-BA12 -> 0 | BB13: =BB9-BB11-BB12 -> 0 | BC13: =BC9-BC11-BC12 -> 0 | BD13: =BD9-BD11-BD12 -> 0 | BE13: =BE9-BE11-BE12 -> 0 | BF13: =BF9-BF11-BF12 -> 0 | BG13: =BG9-BG11-BG12 -> 0 | ... BL13: =BL9-BL11-BL12 -> 0 | BN13: =(AH13+AW13+BL13)-P13 -> 3862.9955
C14: Net Margin (%) | D14: =IFERROR((D13/D7),0) -> 0.014115832 | E14: =IFERROR((E13/E7),0) -> 0.028175525 | F14: =IFERROR((F13/F7),0) -> 0.026821745 | G14: =IFERROR((G13/G7),0) -> 0 | H14: =IFERROR((H13/H7),0) -> 0 | I14: =IFERROR((I13/I7),0) -> 0 | J14: =IFERROR((J13/J7),0) -> 0 | K14: =IFERROR((K13/K7),0) -> 0 | ... P14: =IFERROR((P13/P7),0) -> 0.021438794 | U14: Net Margin (%) | V14: =IFERROR((V13/V7),0) -> 0.028834678 | W14: =IFERROR((W13/W7),0) -> 0.027943741 | X14: =IFERROR((X13/X7),0) -> 0.03002756 | Y14: =IFERROR((Y13/Y7),0) -> 0 | Z14: =IFERROR((Z13/Z7),0) -> 0 | AA14: =IFERROR((AA13/AA7),0) -> 0 | AB14: =IFERROR((AB13/AB7),0) -> 0 | AC14: =IFERROR((AC13/AC7),0) -> 0 | ... AH14: =IFERROR((AH13/AH7),0) -> 0.028751573 | AJ14: Net Margin (%) | AK14: =IFERROR((AK13/AK7),0) -> 0.001079676 | AL14: =IFERROR((AL13/AL7),0) -> 0.020049196 | AM14: =IFERROR((AM13/AM7),0) -> 0.022141316 | AN14: =IFERROR((AN13/AN7),0) -> 0 | AO14: =IFERROR((AO13/AO7),0) -> 0 | AP14: =IFERROR((AP13/AP7),0) -> 0 | AQ14: =IFERROR((AQ13/AQ7),0) -> 0 | AR14: =IFERROR((AR13/AR7),0) -> 0 | ... AW14: =IFERROR((AW13/AW7),0) -> 0.010119197 | AY14: Net Margin (%) | AZ14: =IFERROR((AZ13/AZ7),0) -> 0 | BA14: =IFERROR((BA13/BA7),0) -> 0 | BB14: =IFERROR((BB13/BB7),0) -> 0 | BC14: =IFERROR((BC13/BC7),0) -> 0 | BD14: =IFERROR((BD13/BD7),0) -> 0 | BE14: =IFERROR((BE13/BE7),0) -> 0 | BF14: =IFERROR((BF13/BF7),0) -> 0 | BG14: =IFERROR((BG13/BG7),0) -> 0 | ... BL14: =IFERROR((BL13/BL7),0) -> 0 | BN14: =(AH14+AW14+BL14)-P14 -> 0.017431977
C15: Other Income | D15: =SUMIFS(Details!$BQ$58:$BQ$59,Details!$C$58:$C$59,Summary!D$5) -> 0 | E15: =SUMIFS(Details!$BQ$58:$BQ$59,Details!$C$58:$C$59,Summary!E$5) -> 108894 | F15: =SUMIFS(Details!$BQ$58:$BQ$59,Details!$C$58:$C$59,Summary!F$5) -> 0 | G15: =SUMIFS(Details!$BQ$58:$BQ$59,Details!$C$58:$C$59,Summary!G$5) -> 0 | H15: =SUMIFS(Details!$BQ$58:$BQ$59,Details!$C$58:$C$59,Summary!H$5) -> 0 | I15: =SUMIFS(Details!$BQ$58:$BQ$59,Details!$C$58:$C$59,Summary!I$5) -> 0 | J15: =SUMIFS(Details!$BQ$58:$BQ$59,Details!$C$58:$C$59,Summary!J$5) -> 0 | K15: =SUMIFS(Details!$BQ$58:$BQ$59,Details!$C$58:$C$59,Summary!K$5) -> 0 | ... O15: =SUMIFS(Details!$BQ$58:$BQ$59,Details!$C$58:$C$59,Summary!O$5) -> 0 | P15: =SUM(D15:O15) -> 108894 | U15: Other Income | V15: =SUMIFS(Details!$BQ$58:$BQ$59,Details!$C$58:$C$59,Summary!V$5,Details!$CK$58:$CK$59,Summary!$U$5) -> 0 | W15: =SUMIFS(Details!$BQ$58:$BQ$59,Details!$C$58:$C$59,Summary!W$5,Details!$CK$58:$CK$59,Summary!$U$5) -> 0 | X15: =SUMIFS(Details!$BQ$58:$BQ$59,Details!$C$58:$C$59,Summary!X$5,Details!$CK$58:$CK$59,Summary!$U$5) -> 0 | Y15: =SUMIFS(Details!$BQ$58:$BQ$59,Details!$C$58:$C$59,Summary!Y$5,Details!$CK$58:$CK$59,Summary!$U$5) -> 0 | Z15: =SUMIFS(Details!$BQ$58:$BQ$59,Details!$C$58:$C$59,Summary!Z$5,Details!$CK$58:$CK$59,Summary!$U$5) -> 0 | AA15: =SUMIFS(Details!$BQ$58:$BQ$59,Details!$C$58:$C$59,Summary!AA$5,Details!$CK$58:$CK$59,Summary!$U$5) -> 0 | AB15: =SUMIFS(Details!$BQ$58:$BQ$59,Details!$C$58:$C$59,Summary!AB$5,Details!$CK$58:$CK$59,Summary!$U$5) -> 0 | AC15: =SUMIFS(Details!$BQ$58:$BQ$59,Details!$C$58:$C$59,Summary!AC$5,Details!$CK$58:$CK$59,Summary!$U$5) -> 0 | ... AG15: =SUMIFS(Details!$BQ$58:$BQ$59,Details!$C$58:$C$59,Summary!AG$5,Details!$CK$58:$CK$59,Summary!$U$5) -> 0 | AH15: =SUM(V15:AG15) -> 0 | AJ15: Other Income | AK15: =SUMIFS(Details!$BQ$58:$BQ$59,Details!$C$58:$C$59,Summary!AK$5,Details!$CK$58:$CK$59,Summary!$AJ$5) -> 0 | AL15: =SUMIFS(Details!$BQ$58:$BQ$59,Details!$C$58:$C$59,Summary!AL$5,Details!$CK$58:$CK$59,Summary!$AJ$5) -> 0 | AM15: =SUMIFS(Details!$BQ$58:$BQ$59,Details!$C$58:$C$59,Summary!AM$5,Details!$CK$58:$CK$59,Summary!$AJ$5) -> 0 | AN15: =SUMIFS(Details!$BQ$58:$BQ$59,Details!$C$58:$C$59,Summary!AN$5,Details!$CK$58:$CK$59,Summary!$AJ$5) -> 0 | AO15: =SUMIFS(Details!$BQ$58:$BQ$59,Details!$C$58:$C$59,Summary!AO$5,Details!$CK$58:$CK$59,Summary!$AJ$5) -> 0 | AP15: =SUMIFS(Details!$BQ$58:$BQ$59,Details!$C$58:$C$59,Summary!AP$5,Details!$CK$58:$CK$59,Summary!$AJ$5) -> 0 | AQ15: =SUMIFS(Details!$BQ$58:$BQ$59,Details!$C$58:$C$59,Summary!AQ$5,Details!$CK$58:$CK$59,Summary!$AJ$5) -> 0 | AR15: =SUMIFS(Details!$BQ$58:$BQ$59,Details!$C$58:$C$59,Summary!AR$5,Details!$CK$58:$CK$59,Summary!$AJ$5) -> 0 | ... AV15: =SUMIFS(Details!$BQ$58:$BQ$59,Details!$C$58:$C$59,Summary!AV$5,Details!$CK$58:$CK$59,Summary!$AJ$5) -> 0 | AW15: =SUM(AK15:AV15) -> 0 | AY15: Other Income | AZ15: =SUMIFS(Details!$BQ$58:$BQ$59,Details!$C$58:$C$59,Summary!AZ$5,Details!$CK$58:$CK$59,Summary!$AY$5) -> 0 | BA15: =SUMIFS(Details!$BQ$58:$BQ$59,Details!$C$58:$C$59,Summary!BA$5,Details!$CK$58:$CK$59,Summary!$AY$5) -> 0 | BB15: =SUMIFS(Details!$BQ$58:$BQ$59,Details!$C$58:$C$59,Summary!BB$5,Details!$CK$58:$CK$59,Summary!$AY$5) -> 0 | BC15: =SUMIFS(Details!$BQ$58:$BQ$59,Details!$C$58:$C$59,Summary!BC$5,Details!$CK$58:$CK$59,Summary!$AY$5) -> 0 | BD15: =SUMIFS(Details!$BQ$58:$BQ$59,Details!$C$58:$C$59,Summary!BD$5,Details!$CK$58:$CK$59,Summary!$AY$5) -> 0 | BE15: =SUMIFS(Details!$BQ$58:$BQ$59,Details!$C$58:$C$59,Summary!BE$5,Details!$CK$58:$CK$59,Summary!$AY$5) -> 0 | BF15: =SUMIFS(Details!$BQ$58:$BQ$59,Details!$C$58:$C$59,Summary!BF$5,Details!$CK$58:$CK$59,Summary!$AY$5) -> 0 | BG15: =SUMIFS(Details!$BQ$58:$BQ$59,Details!$C$58:$C$59,Summary!BG$5,Details!$CK$58:$CK$59,Summary!$AY$5) -> 0 | ... BK15: =SUMIFS(Details!$BQ$58:$BQ$59,Details!$C$58:$C$59,Summary!BK$5,Details!$CK$58:$CK$59,Summary!$AY$5) -> 0 | BL15: =SUM(AZ15:BK15) -> 0 | BN15: =(AH15+AW15+BL15)-P15 -> -108894
C16: Transport Charges (%) | D16: =IFERROR((D11/D7),0) -> 0 | E16: =IFERROR((E11/E7),0) -> 0 | F16: =IFERROR((F11/F7),0) -> 0 | G16: =IFERROR((G11/G7),0) -> 0 | H16: =IFERROR((H11/H7),0) -> 0 | I16: =IFERROR((I11/I7),0) -> 0 | J16: =IFERROR((J11/J7),0) -> 0 | K16: =IFERROR((K11/K7),0) -> 0 | ... P16: =IFERROR((P11/P7),0) -> 0 | U16: Transport Charges (%) | V16: =IFERROR((V11/V7),0) -> 3.0220039e-06 | W16: =IFERROR((W11/W7),0) -> 2.9198646e-06 | X16: =IFERROR((X11/X7),0) -> 2.9165368e-06 | Y16: =IFERROR((Y11/Y7),0) -> 0 | Z16: =IFERROR((Z11/Z7),0) -> 0 | AA16: =IFERROR((AA11/AA7),0) -> 0 | AB16: =IFERROR((AB11/AB7),0) -> 0 | AC16: =IFERROR((AC11/AC7),0) -> 0 | ... AH16: =IFERROR((AH11/AH7),0) -> 2.9595501e-06 | AJ16: Transport Charges (%) | AK16: =IFERROR((AK11/AK7),0) -> 3.1240512e-05 | AL16: =IFERROR((AL11/AL7),0) -> 3.3438115e-05 | AM16: =IFERROR((AM11/AM7),0) -> 2.9072398e-05 | AN16: =IFERROR((AN11/AN7),0) -> 0 | AO16: =IFERROR((AO11/AO7),0) -> 0 | AP16: =IFERROR((AP11/AP7),0) -> 0 | AQ16: =IFERROR((AQ11/AQ7),0) -> 0 | AR16: =IFERROR((AR11/AR7),0) -> 0 | ... AW16: =IFERROR((AW11/AW7),0) -> 3.1201712e-05 | AY16: Transport Charges (%) | AZ16: =IFERROR((AZ11/AZ7),0) -> 0 | BA16: =IFERROR((BA11/BA7),0) -> 0 | BB16: =IFERROR((BB11/BB7),0) -> 0 | BC16: =IFERROR((BC11/BC7),0) -> 0 | BD16: =IFERROR((BD11/BD7),0) -> 0 | BE16: =IFERROR((BE11/BE7),0) -> 0 | BF16: =IFERROR((BF11/BF7),0) -> 0 | BG16: =IFERROR((BG11/BG7),0) -> 0 | ... BL16: =IFERROR((BL11/BL7),0) -> 0 | BN16: =(AH16+AW16+BL16)-P16 -> 3.4161262e-05
C17: Revenue Per Kg | D17: =IFERROR(D7/(D6*1000),0) -> 61.084351 | E17: =IFERROR(E7/(E6*1000),0) -> 90.544856 | F17: =IFERROR(F7/(F6*1000),0) -> 73.316807 | G17: =IFERROR(G7/(G6*1000),0) -> 0 | H17: =IFERROR(H7/(H6*1000),0) -> 0 | I17: =IFERROR(I7/(I6*1000),0) -> 0 | J17: =IFERROR(J7/(J6*1000),0) -> 0 | K17: =IFERROR(K7/(K6*1000),0) -> 0 | ... O17: =IFERROR(O7/(O6*1000),0) -> 0 | P17: =P7/(P6*1000) -> 71.085886 | U17: Revenue Per Kg | V17: =IFERROR(V7/(V6*1000),0) -> 330.90626 | W17: =IFERROR(W7/(W6*1000),0) -> 342.48164 | X17: =IFERROR(X7/(X6*1000),0) -> 342.87241 | Y17: =IFERROR(Y7/(Y6*1000),0) -> 0 | Z17: =IFERROR(Z7/(Z6*1000),0) -> 0 | AA17: =IFERROR(AA7/(AA6*1000),0) -> 0 | AB17: =IFERROR(AB7/(AB6*1000),0) -> 0 | AC17: =IFERROR(AC7/(AC6*1000),0) -> 0 | ... AG17: =IFERROR(AG7/(AG6*1000),0) -> 0 | AH17: =AH7/(AH6*1000) -> 337.88919 | AJ17: Revenue Per Kg | AK17: =IFERROR(AK7/(AK6*1000),0) -> 32.009719 | AL17: =IFERROR(AL7/(AL6*1000),0) -> 29.905992 | AM17: =IFERROR(AM7/(AM6*1000),0) -> 34.396887 | AN17: =IFERROR(AN7/(AN6*1000),0) -> 0 | AO17: =IFERROR(AO7/(AO6*1000),0) -> 0 | AP17: =IFERROR(AP7/(AP6*1000),0) -> 0 | AQ17: =IFERROR(AQ7/(AQ6*1000),0) -> 0 | AR17: =IFERROR(AR7/(AR6*1000),0) -> 0 | ... AV17: =IFERROR(AV7/(AV6*1000),0) -> 0 | AW17: =AW7/(AW6*1000) -> 32.049523 | AY17: Revenue Per Kg | AZ17: =IFERROR(AZ7/(AZ6*1000),0) -> 0 | BA17: =IFERROR(BA7/(BA6*1000),0) -> 0 | BB17: =IFERROR(BB7/(BB6*1000),0) -> 0 | BC17: =IFERROR(BC7/(BC6*1000),0) -> 0 | BD17: =IFERROR(BD7/(BD6*1000),0) -> 0 | BE17: =IFERROR(BE7/(BE6*1000),0) -> 0 | BF17: =IFERROR(BF7/(BF6*1000),0) -> 0 | BG17: =IFERROR(BG7/(BG6*1000),0) -> 0 | ... BK17: =IFERROR(BK7/(BK6*1000),0) -> 0 | BL17: =BL7/(BL6*1000) -> #DIV/0!
C18: Purchase Cost Per Kg | D18: =IFERROR(D8/(D6*1000),0) -> 60.222095 | E18: =IFERROR(E8/(E6*1000),0) -> 87.993707 | F18: =IFERROR(F8/(F6*1000),0) -> 71.350323 | G18: =IFERROR(G8/(G6*1000),0) -> 0 | H18: =IFERROR(H8/(H6*1000),0) -> 0 | I18: =IFERROR(I8/(I6*1000),0) -> 0 | J18: =IFERROR(J8/(J6*1000),0) -> 0 | K18: =IFERROR(K8/(K6*1000),0) -> 0 | ... O18: =IFERROR(O8/(O6*1000),0) -> 0 | P18: =P8/(P6*1000) -> 69.56189 | U18: Purchase Cost Per Kg | V18: =IFERROR(V8/(V6*1000),0) -> 321.36269 | W18: =IFERROR(W8/(W6*1000),0) -> 332.90942 | X18: =IFERROR(X8/(X6*1000),0) -> 332.57478 | Y18: =IFERROR(Y8/(Y6*1000),0) -> 0 | Z18: =IFERROR(Z8/(Z6*1000),0) -> 0 | AA18: =IFERROR(AA8/(AA6*1000),0) -> 0 | AB18: =IFERROR(AB8/(AB6*1000),0) -> 0 | AC18: =IFERROR(AC8/(AC6*1000),0) -> 0 | ... AG18: =IFERROR(AG8/(AG6*1000),0) -> 0 | AH18: =AH8/(AH6*1000) -> 328.17235 | AJ18: Purchase Cost Per Kg | AK18: =IFERROR(AK8/(AK6*1000),0) -> 31.973159 | AL18: =IFERROR(AL8/(AL6*1000),0) -> 29.304401 | AM18: =IFERROR(AM8/(AM6*1000),0) -> 33.633295 | AN18: =IFERROR(AN8/(AN6*1000),0) -> 0 | AO18: =IFERROR(AO8/(AO6*1000),0) -> 0 | AP18: =IFERROR(AP8/(AP6*1000),0) -> 0 | AQ18: =IFERROR(AQ8/(AQ6*1000),0) -> 0 | AR18: =IFERROR(AR8/(AR6*1000),0) -> 0 | ... AV18: =IFERROR(AV8/(AV6*1000),0) -> 0 | AW18: =AW8/(AW6*1000) -> 31.723208 | AY18: Purchase Cost Per Kg | AZ18: =IFERROR(AZ8/(AZ6*1000),0) -> 0 | BA18: =IFERROR(BA8/(BA6*1000),0) -> 0 | BB18: =IFERROR(BB8/(BB6*1000),0) -> 0 | BC18: =IFERROR(BC8/(BC6*1000),0) -> 0 | BD18: =IFERROR(BD8/(BD6*1000),0) -> 0 | BE18: =IFERROR(BE8/(BE6*1000),0) -> 0 | BF18: =IFERROR(BF8/(BF6*1000),0) -> 0 | BG18: =IFERROR(BG8/(BG6*1000),0) -> 0 | ... BK18: =IFERROR(BK8/(BK6*1000),0) -> 0 | BL18: =BL8/(BL6*1000) -> #DIV/0!
C19: Transportation Charges Per Kg | D19: =IFERROR(D11/(D6*1000),0) -> 0 | E19: =IFERROR(E11/(E6*1000),0) -> 0 | F19: =IFERROR(F11/(F6*1000),0) -> 0 | G19: =IFERROR(G11/(G6*1000),0) -> 0 | H19: =IFERROR(H11/(H6*1000),0) -> 0 | I19: =IFERROR(I11/(I6*1000),0) -> 0 | J19: =IFERROR(J11/(J6*1000),0) -> 0 | K19: =IFERROR(K11/(K6*1000),0) -> 0 | ... O19: =IFERROR(O11/(O6*1000),0) -> 0 | P19: =P11/(P6*1000) -> 0 | U19: Transportation Charges Per Kg | V19: =IFERROR(V11/(V6*1000),0) -> 0.001 | W19: =IFERROR(W11/(W6*1000),0) -> 0.001 | X19: =IFERROR(X11/(X6*1000),0) -> 0.001 | Y19: =IFERROR(Y11/(Y6*1000),0) -> 0 | Z19: =IFERROR(Z11/(Z6*1000),0) -> 0 | AA19: =IFERROR(AA11/(AA6*1000),0) -> 0 | AB19: =IFERROR(AB11/(AB6*1000),0) -> 0 | AC19: =IFERROR(AC11/(AC6*1000),0) -> 0 | ... AG19: =IFERROR(AG11/(AG6*1000),0) -> 0 | AH19: =AH11/(AH6*1000) -> 0.001 | AJ19: Transportation Charges Per Kg | AK19: =IFERROR(AK11/(AK6*1000),0) -> 0.001 | AL19: =IFERROR(AL11/(AL6*1000),0) -> 0.001 | AM19: =IFERROR(AM11/(AM6*1000),0) -> 0.001 | AN19: =IFERROR(AN11/(AN6*1000),0) -> 0 | AO19: =IFERROR(AO11/(AO6*1000),0) -> 0 | AP19: =IFERROR(AP11/(AP6*1000),0) -> 0 | AQ19: =IFERROR(AQ11/(AQ6*1000),0) -> 0 | AR19: =IFERROR(AR11/(AR6*1000),0) -> 0 | ... AV19: =IFERROR(AV11/(AV6*1000),0) -> 0 | AW19: =AW11/(AW6*1000) -> 0.001 | AY19: Transportation Charges Per Kg | AZ19: =IFERROR(AZ11/(AZ6*1000),0) -> 0 | BA19: =IFERROR(BA11/(BA6*1000),0) -> 0 | BB19: =IFERROR(BB11/(BB6*1000),0) -> 0 | BC19: =IFERROR(BC11/(BC6*1000),0) -> 0 | BD19: =IFERROR(BD11/(BD6*1000),0) -> 0 | BE19: =IFERROR(BE11/(BE6*1000),0) -> 0 | BF19: =IFERROR(BF11/(BF6*1000),0) -> 0 | BG19: =IFERROR(BG11/(BG6*1000),0) -> 0 | ... BK19: =IFERROR(BK11/(BK6*1000),0) -> 0 | BL19: =BL11/(BL6*1000) -> #DIV/0!
C20: No. of Transactions | D20: {=IFERROR(ROWS(_xlfn.UNIQUE(_xlfn._xlws.FILTER(Details!$E$5:$E$53,(Details!$C$5:$C$53)=Summary!D$3))),0)} -> 22 | E20: {=IFERROR(ROWS(_xlfn.UNIQUE(_xlfn._xlws.FILTER(Details!$E$5:$E$53,(Details!$C$5:$C$53)=Summary!E$3))),0)} -> 16 | F20: {=IFERROR(ROWS(_xlfn.UNIQUE(_xlfn._xlws.FILTER(Details!$E$5:$E$53,(Details!$C$5:$C$53)=Summary!F$3))),0)} -> 9 | G20: {=IFERROR(ROWS(_xlfn.UNIQUE(_xlfn._xlws.FILTER(Details!$E$5:$E$53,(Details!$C$5:$C$53)=Summary!G$3))),0)} -> 0 | H20: {=IFERROR(ROWS(_xlfn.UNIQUE(_xlfn._xlws.FILTER(Details!$E$5:$E$53,(Details!$C$5:$C$53)=Summary!H$3))),0)} -> 0 | I20: {=IFERROR(ROWS(_xlfn.UNIQUE(_xlfn._xlws.FILTER(Details!$E$5:$E$53,(Details!$C$5:$C$53)=Summary!I$3))),0)} -> 0 | J20: {=IFERROR(ROWS(_xlfn.UNIQUE(_xlfn._xlws.FILTER(Details!$E$5:$E$53,(Details!$C$5:$C$53)=Summary!J$3))),0)} -> 0 | K20: {=IFERROR(ROWS(_xlfn.UNIQUE(_xlfn._xlws.FILTER(Details!$E$5:$E$53,(Details!$C$5:$C$53)=Summary!K$3))),0)} -> 0 | ... O20: {=IFERROR(ROWS(_xlfn.UNIQUE(_xlfn._xlws.FILTER(Details!$E$5:$E$53,(Details!$C$5:$C$53)=Summary!O$3))),0)} -> 0 | P20: =SUM(D20:O20) -> 47 | U20: No. of Transactions | V20: {=IFERROR(ROWS(_xlfn.UNIQUE(_xlfn._xlws.FILTER(Details!$E$5:$E$53,(Details!$C$5:$C$53=Summary!V$3)*(Details!$CK$5:$CK$53=$U$5)))),0)} -> 0 | W20: {=IFERROR(ROWS(_xlfn.UNIQUE(_xlfn._xlws.FILTER(Details!$E$5:$E$53,(Details!$C$5:$C$53=Summary!W$3)*(Details!$CK$5:$CK$53=$U$5)))),0)} -> 0 | X20: {=IFERROR(ROWS(_xlfn.UNIQUE(_xlfn._xlws.FILTER(Details!$E$5:$E$53,(Details!$C$5:$C$53=Summary!X$3)*(Details!$CK$5:$CK$53=$U$5)))),0)} -> 0 | Y20: {=IFERROR(ROWS(_xlfn.UNIQUE(_xlfn._xlws.FILTER(Details!$E$5:$E$53,(Details!$C$5:$C$53=Summary!Y$3)*(Details!$CK$5:$CK$53=$U$5)))),0)} -> 0 | Z20: {=IFERROR(ROWS(_xlfn.UNIQUE(_xlfn._xlws.FILTER(Details!$E$5:$E$53,(Details!$C$5:$C$53=Summary!Z$3)*(Details!$CK$5:$CK$53=$U$5)))),0)} -> 0 | AA20: {=IFERROR(ROWS(_xlfn.UNIQUE(_xlfn._xlws.FILTER(Details!$E$5:$E$53,(Details!$C$5:$C$53=Summary!AA$3)*(Details!$CK$5:$CK$53=$U$5)))),0)} -> 0 | AB20: {=IFERROR(ROWS(_xlfn.UNIQUE(_xlfn._xlws.FILTER(Details!$E$5:$E$53,(Details!$C$5:$C$53=Summary!AB$3)*(Details!$CK$5:$CK$53=$U$5)))),0)} -> 0 | AC20: {=IFERROR(ROWS(_xlfn.UNIQUE(_xlfn._xlws.FILTER(Details!$E$5:$E$53,(Details!$C$5:$C$53=Summary!AC$3)*(Details!$CK$5:$CK$53=$U$5)))),0)} -> 0 | ... AG20: {=IFERROR(ROWS(_xlfn.UNIQUE(_xlfn._xlws.FILTER(Details!$E$5:$E$53,(Details!$C$5:$C$53=Summary!AG$3)*(Details!$CK$5:$CK$53=$U$5)))),0)} -> 0 | AH20: =SUM(V20:AG20) -> 0 | AJ20: No. of Transactions | AK20: {=IFERROR(ROWS(_xlfn.UNIQUE(_xlfn._xlws.FILTER(Details!$E$5:$E$53,(Details!$C$5:$C$53=Summary!AK$3)*(Details!$CK$5:$CK$53=$AJ$5)))),0)} -> 0 | AL20: {=IFERROR(ROWS(_xlfn.UNIQUE(_xlfn._xlws.FILTER(Details!$E$5:$E$53,(Details!$C$5:$C$53=Summary!AL$3)*(Details!$CK$5:$CK$53=$AJ$5)))),0)} -> 0 | AM20: {=IFERROR(ROWS(_xlfn.UNIQUE(_xlfn._xlws.FILTER(Details!$E$5:$E$53,(Details!$C$5:$C$53=Summary!AM$3)*(Details!$CK$5:$CK$53=$AJ$5)))),0)} -> 0 | AN20: {=IFERROR(ROWS(_xlfn.UNIQUE(_xlfn._xlws.FILTER(Details!$E$5:$E$53,(Details!$C$5:$C$53=Summary!AN$3)*(Details!$CK$5:$CK$53=$AJ$5)))),0)} -> 0 | AO20: {=IFERROR(ROWS(_xlfn.UNIQUE(_xlfn._xlws.FILTER(Details!$E$5:$E$53,(Details!$C$5:$C$53=Summary!AO$3)*(Details!$CK$5:$CK$53=$AJ$5)))),0)} -> 0 | AP20: {=IFERROR(ROWS(_xlfn.UNIQUE(_xlfn._xlws.FILTER(Details!$E$5:$E$53,(Details!$C$5:$C$53=Summary!AP$3)*(Details!$CK$5:$CK$53=$AJ$5)))),0)} -> 0 | AQ20: {=IFERROR(ROWS(_xlfn.UNIQUE(_xlfn._xlws.FILTER(Details!$E$5:$E$53,(Details!$C$5:$C$53=Summary!AQ$3)*(Details!$CK$5:$CK$53=$AJ$5)))),0)} -> 0 | AR20: {=IFERROR(ROWS(_xlfn.UNIQUE(_xlfn._xlws.FILTER(Details!$E$5:$E$53,(Details!$C$5:$C$53=Summary!AR$3)*(Details!$CK$5:$CK$53=$AJ$5)))),0)} -> 0 | ... AV20: {=IFERROR(ROWS(_xlfn.UNIQUE(_xlfn._xlws.FILTER(Details!$E$5:$E$53,(Details!$C$5:$C$53=Summary!AV$3)*(Details!$CK$5:$CK$53=$AJ$5)))),0)} -> 0 | AW20: =SUM(AK20:AV20) -> 0 | AY20: No. of Transactions | AZ20: {=IFERROR(ROWS(_xlfn.UNIQUE(_xlfn._xlws.FILTER(Details!$E$5:$E$53,(Details!$C$5:$C$53=Summary!AZ$3)*(Details!$CK$5:$CK$53=$AY$5)))),0)} -> 0 | BA20: {=IFERROR(ROWS(_xlfn.UNIQUE(_xlfn._xlws.FILTER(Details!$E$5:$E$53,(Details!$C$5:$C$53=Summary!BA$3)*(Details!$CK$5:$CK$53=$AY$5)))),0)} -> 0 | BB20: {=IFERROR(ROWS(_xlfn.UNIQUE(_xlfn._xlws.FILTER(Details!$E$5:$E$53,(Details!$C$5:$C$53=Summary!BB$3)*(Details!$CK$5:$CK$53=$AY$5)))),0)} -> 0 | BC20: {=IFERROR(ROWS(_xlfn.UNIQUE(_xlfn._xlws.FILTER(Details!$E$5:$E$53,(Details!$C$5:$C$53=Summary!BC$3)*(Details!$CK$5:$CK$53=$AY$5)))),0)} -> 0 | BD20: {=IFERROR(ROWS(_xlfn.UNIQUE(_xlfn._xlws.FILTER(Details!$E$5:$E$53,(Details!$C$5:$C$53=Summary!BD$3)*(Details!$CK$5:$CK$53=$AY$5)))),0)} -> 0 | BE20: {=IFERROR(ROWS(_xlfn.UNIQUE(_xlfn._xlws.FILTER(Details!$E$5:$E$53,(Details!$C$5:$C$53=Summary!BE$3)*(Details!$CK$5:$CK$53=$AY$5)))),0)} -> 0 | BF20: {=IFERROR(ROWS(_xlfn.UNIQUE(_xlfn._xlws.FILTER(Details!$E$5:$E$53,(Details!$C$5:$C$53=Summary!BF$3)*(Details!$CK$5:$CK$53=$AY$5)))),0)} -> 0 | BG20: {=IFERROR(ROWS(_xlfn.UNIQUE(_xlfn._xlws.FILTER(Details!$E$5:$E$53,(Details!$C$5:$C$53=Summary!BG$3)*(Details!$CK$5:$CK$53=$AY$5)))),0)} -> 0 | ... BK20: {=IFERROR(ROWS(_xlfn.UNIQUE(_xlfn._xlws.FILTER(Details!$E$5:$E$53,(Details!$C$5:$C$53=Summary!BK$3)*(Details!$CK$5:$CK$53=$AY$5)))),0)} -> 0 | BL20: =SUM(AZ20:BK20) -> 0 | BN20: =(AH20+AW20+BL20)-P20 -> -47
C21: No. of Sellers (Aggregators) | D21: {=IFERROR(ROWS(_xlfn.UNIQUE(_xlfn._xlws.FILTER(Details!$F$5:$F$53,(Details!$C$5:$C$53)=Summary!D$3))),0)} -> 5 | E21: {=IFERROR(ROWS(_xlfn.UNIQUE(_xlfn._xlws.FILTER(Details!$F$5:$F$53,(Details!$C$5:$C$53)=Summary!E$3))),0)} -> 3 | F21: {=IFERROR(ROWS(_xlfn.UNIQUE(_xlfn._xlws.FILTER(Details!$F$5:$F$53,(Details!$C$5:$C$53)=Summary!F$3))),0)} -> 4 | G21: {=IFERROR(ROWS(_xlfn.UNIQUE(_xlfn._xlws.FILTER(Details!$F$5:$F$53,(Details!$C$5:$C$53)=Summary!G$3))),0)} -> 0 | H21: {=IFERROR(ROWS(_xlfn.UNIQUE(_xlfn._xlws.FILTER(Details!$F$5:$F$53,(Details!$C$5:$C$53)=Summary!H$3))),0)} -> 0 | I21: {=IFERROR(ROWS(_xlfn.UNIQUE(_xlfn._xlws.FILTER(Details!$F$5:$F$53,(Details!$C$5:$C$53)=Summary!I$3))),0)} -> 0 | J21: {=IFERROR(ROWS(_xlfn.UNIQUE(_xlfn._xlws.FILTER(Details!$F$5:$F$53,(Details!$C$5:$C$53)=Summary!J$3))),0)} -> 0 | K21: {=IFERROR(ROWS(_xlfn.UNIQUE(_xlfn._xlws.FILTER(Details!$F$5:$F$53,(Details!$C$5:$C$53)=Summary!K$3))),0)} -> 0 | ... O21: {=IFERROR(ROWS(_xlfn.UNIQUE(_xlfn._xlws.FILTER(Details!$F$5:$F$53,(Details!$C$5:$C$53)=Summary!O$3))),0)} -> 0 | P21: ='Supplier Metrics'!J2 -> 8 | U21: No. of Sellers (Aggregators) | V21: {=IFERROR(ROWS(_xlfn.UNIQUE(_xlfn._xlws.FILTER(Details!$F$5:$F$53,(Details!$C$5:$C$53=Summary!V$3)*(Details!$CK$5:$CK$53=$U$5)))),0)} -> 0 | W21: {=IFERROR(ROWS(_xlfn.UNIQUE(_xlfn._xlws.FILTER(Details!$F$5:$F$53,(Details!$C$5:$C$53=Summary!W$3)*(Details!$CK$5:$CK$53=$U$5)))),0)} -> 0 | X21: {=IFERROR(ROWS(_xlfn.UNIQUE(_xlfn._xlws.FILTER(Details!$F$5:$F$53,(Details!$C$5:$C$53=Summary!X$3)*(Details!$CK$5:$CK$53=$U$5)))),0)} -> 0 | Y21: {=IFERROR(ROWS(_xlfn.UNIQUE(_xlfn._xlws.FILTER(Details!$F$5:$F$53,(Details!$C$5:$C$53=Summary!Y$3)*(Details!$CK$5:$CK$53=$U$5)))),0)} -> 0 | Z21: {=IFERROR(ROWS(_xlfn.UNIQUE(_xlfn._xlws.FILTER(Details!$F$5:$F$53,(Details!$C$5:$C$53=Summary!Z$3)*(Details!$CK$5:$CK$53=$U$5)))),0)} -> 0 | AA21: {=IFERROR(ROWS(_xlfn.UNIQUE(_xlfn._xlws.FILTER(Details!$F$5:$F$53,(Details!$C$5:$C$53=Summary!AA$3)*(Details!$CK$5:$CK$53=$U$5)))),0)} -> 0 | AB21: {=IFERROR(ROWS(_xlfn.UNIQUE(_xlfn._xlws.FILTER(Details!$F$5:$F$53,(Details!$C$5:$C$53=Summary!AB$3)*(Details!$CK$5:$CK$53=$U$5)))),0)} -> 0 | AC21: {=IFERROR(ROWS(_xlfn.UNIQUE(_xlfn._xlws.FILTER(Details!$F$5:$F$53,(Details!$C$5:$C$53=Summary!AC$3)*(Details!$CK$5:$CK$53=$U$5)))),0)} -> 0 | ... AG21: {=IFERROR(ROWS(_xlfn.UNIQUE(_xlfn._xlws.FILTER(Details!$F$5:$F$53,(Details!$C$5:$C$53=Summary!AG$3)*(Details!$CK$5:$CK$53=$U$5)))),0)} -> 0 | AH21: =COUNTIF('Supplier Metrics'!I:I,Summary!U5) -> 1 | AJ21: No. of Sellers (Aggregators) | AK21: {=IFERROR(ROWS(_xlfn.UNIQUE(_xlfn._xlws.FILTER(Details!$F$5:$F$53,(Details!$C$5:$C$53=Summary!AK$3)*(Details!$CK$5:$CK$53=$AJ$5)))),0)} -> 0 | AL21: {=IFERROR(ROWS(_xlfn.UNIQUE(_xlfn._xlws.FILTER(Details!$F$5:$F$53,(Details!$C$5:$C$53=Summary!AL$3)*(Details!$CK$5:$CK$53=$AJ$5)))),0)} -> 0 | AM21: {=IFERROR(ROWS(_xlfn.UNIQUE(_xlfn._xlws.FILTER(Details!$F$5:$F$53,(Details!$C$5:$C$53=Summary!AM$3)*(Details!$CK$5:$CK$53=$AJ$5)))),0)} -> 0 | AN21: {=IFERROR(ROWS(_xlfn.UNIQUE(_xlfn._xlws.FILTER(Details!$F$5:$F$53,(Details!$C$5:$C$53=Summary!AN$3)*(Details!$CK$5:$CK$53=$AJ$5)))),0)} -> 0 | AO21: {=IFERROR(ROWS(_xlfn.UNIQUE(_xlfn._xlws.FILTER(Details!$F$5:$F$53,(Details!$C$5:$C$53=Summary!AO$3)*(Details!$CK$5:$CK$53=$AJ$5)))),0)} -> 0 | AP21: {=IFERROR(ROWS(_xlfn.UNIQUE(_xlfn._xlws.FILTER(Details!$F$5:$F$53,(Details!$C$5:$C$53=Summary!AP$3)*(Details!$CK$5:$CK$53=$AJ$5)))),0)} -> 0 | AQ21: {=IFERROR(ROWS(_xlfn.UNIQUE(_xlfn._xlws.FILTER(Details!$F$5:$F$53,(Details!$C$5:$C$53=Summary!AQ$3)*(Details!$CK$5:$CK$53=$AJ$5)))),0)} -> 0 | AR21: {=IFERROR(ROWS(_xlfn.UNIQUE(_xlfn._xlws.FILTER(Details!$F$5:$F$53,(Details!$C$5:$C$53=Summary!AR$3)*(Details!$CK$5:$CK$53=$AJ$5)))),0)} -> 0 | ... AV21: {=IFERROR(ROWS(_xlfn.UNIQUE(_xlfn._xlws.FILTER(Details!$F$5:$F$53,(Details!$C$5:$C$53=Summary!AV$3)*(Details!$CK$5:$CK$53=$AJ$5)))),0)} -> 0 | AW21: =COUNTIF('Supplier Metrics'!I:I,Summary!AJ5) -> 7 | AY21: No. of Sellers (Aggregators) | AZ21: {=IFERROR(ROWS(_xlfn.UNIQUE(_xlfn._xlws.FILTER(Details!$F$5:$F$53,(Details!$C$5:$C$53=Summary!AZ$3)*(Details!$CK$5:$CK$53=$AY$5)))),0)} -> 0 | BA21: {=IFERROR(ROWS(_xlfn.UNIQUE(_xlfn._xlws.FILTER(Details!$F$5:$F$53,(Details!$C$5:$C$53=Summary!BA$3)*(Details!$CK$5:$CK$53=$AY$5)))),0)} -> 0 | BB21: {=IFERROR(ROWS(_xlfn.UNIQUE(_xlfn._xlws.FILTER(Details!$F$5:$F$53,(Details!$C$5:$C$53=Summary!BB$3)*(Details!$CK$5:$CK$53=$AY$5)))),0)} -> 0 | BC21: {=IFERROR(ROWS(_xlfn.UNIQUE(_xlfn._xlws.FILTER(Details!$F$5:$F$53,(Details!$C$5:$C$53=Summary!BC$3)*(Details!$CK$5:$CK$53=$AY$5)))),0)} -> 0 | BD21: {=IFERROR(ROWS(_xlfn.UNIQUE(_xlfn._xlws.FILTER(Details!$F$5:$F$53,(Details!$C$5:$C$53=Summary!BD$3)*(Details!$CK$5:$CK$53=$AY$5)))),0)} -> 0 | BE21: {=IFERROR(ROWS(_xlfn.UNIQUE(_xlfn._xlws.FILTER(Details!$F$5:$F$53,(Details!$C$5:$C$53=Summary!BE$3)*(Details!$CK$5:$CK$53=$AY$5)))),0)} -> 0 | BF21: {=IFERROR(ROWS(_xlfn.UNIQUE(_xlfn._xlws.FILTER(Details!$F$5:$F$53,(Details!$C$5:$C$53=Summary!BF$3)*(Details!$CK$5:$CK$53=$AY$5)))),0)} -> 0 | BG21: {=IFERROR(ROWS(_xlfn.UNIQUE(_xlfn._xlws.FILTER(Details!$F$5:$F$53,(Details!$C$5:$C$53=Summary!BG$3)*(Details!$CK$5:$CK$53=$AY$5)))),0)} -> 0 | ... BK21: {=IFERROR(ROWS(_xlfn.UNIQUE(_xlfn._xlws.FILTER(Details!$F$5:$F$53,(Details!$C$5:$C$53=Summary!BK$3)*(Details!$CK$5:$CK$53=$AY$5)))),0)} -> 0 | BL21: =COUNTIF('Supplier Metrics'!I:I,Summary!AY5) -> 0 | BN21: =(AH21+AW21+BL21)-P21 -> 0
C22: No. of Buyers (Recyclers) | D22: {=IFERROR(ROWS(_xlfn.UNIQUE(_xlfn._xlws.FILTER(Details!$AQ$5:$AQ$53,(Details!$C$5:$C$53)=Summary!D$3))),0)} -> 4 | E22: {=IFERROR(ROWS(_xlfn.UNIQUE(_xlfn._xlws.FILTER(Details!$AQ$5:$AQ$53,(Details!$C$5:$C$53)=Summary!E$3))),0)} -> 4 | F22: {=IFERROR(ROWS(_xlfn.UNIQUE(_xlfn._xlws.FILTER(Details!$AQ$5:$AQ$53,(Details!$C$5:$C$53)=Summary!F$3))),0)} -> 6 | G22: {=IFERROR(ROWS(_xlfn.UNIQUE(_xlfn._xlws.FILTER(Details!$AQ$5:$AQ$53,(Details!$C$5:$C$53)=Summary!G$3))),0)} -> 0 | H22: {=IFERROR(ROWS(_xlfn.UNIQUE(_xlfn._xlws.FILTER(Details!$AQ$5:$AQ$53,(Details!$C$5:$C$53)=Summary!H$3))),0)} -> 0 | I22: {=IFERROR(ROWS(_xlfn.UNIQUE(_xlfn._xlws.FILTER(Details!$AQ$5:$AQ$53,(Details!$C$5:$C$53)=Summary!I$3))),0)} -> 0 | J22: {=IFERROR(ROWS(_xlfn.UNIQUE(_xlfn._xlws.FILTER(Details!$AQ$5:$AQ$53,(Details!$C$5:$C$53)=Summary!J$3))),0)} -> 0 | K22: {=IFERROR(ROWS(_xlfn.UNIQUE(_xlfn._xlws.FILTER(Details!$AQ$5:$AQ$53,(Details!$C$5:$C$53)=Summary!K$3))),0)} -> 0 | ... O22: {=IFERROR(ROWS(_xlfn.UNIQUE(_xlfn._xlws.FILTER(Details!$AQ$5:$AQ$53,(Details!$C$5:$C$53)=Summary!O$3))),0)} -> 0 | P22: ='Buyer Metrics'!C3 -> 8 | U22: No. of Buyers (Recyclers) | V22: {=IFERROR(ROWS(_xlfn.UNIQUE(_xlfn._xlws.FILTER(Details!$AQ$5:$AQ$53,(Details!$C$5:$C$53=Summary!V$3)*(Details!$CK$5:$CK$53=$U$5)))),0)} -> 0 | W22: {=IFERROR(ROWS(_xlfn.UNIQUE(_xlfn._xlws.FILTER(Details!$AQ$5:$AQ$53,(Details!$C$5:$C$53=Summary!W$3)*(Details!$CK$5:$CK$53=$U$5)))),0)} -> 0 | X22: {=IFERROR(ROWS(_xlfn.UNIQUE(_xlfn._xlws.FILTER(Details!$AQ$5:$AQ$53,(Details!$C$5:$C$53=Summary!X$3)*(Details!$CK$5:$CK$53=$U$5)))),0)} -> 0 | Y22: {=IFERROR(ROWS(_xlfn.UNIQUE(_xlfn._xlws.FILTER(Details!$AQ$5:$AQ$53,(Details!$C$5:$C$53=Summary!Y$3)*(Details!$CK$5:$CK$53=$U$5)))),0)} -> 0 | Z22: {=IFERROR(ROWS(_xlfn.UNIQUE(_xlfn._xlws.FILTER(Details!$AQ$5:$AQ$53,(Details!$C$5:$C$53=Summary!Z$3)*(Details!$CK$5:$CK$53=$U$5)))),0)} -> 0 | AA22: {=IFERROR(ROWS(_xlfn.UNIQUE(_xlfn._xlws.FILTER(Details!$AQ$5:$AQ$53,(Details!$C$5:$C$53=Summary!AA$3)*(Details!$CK$5:$CK$53=$U$5)))),0)} -> 0 | AB22: {=IFERROR(ROWS(_xlfn.UNIQUE(_xlfn._xlws.FILTER(Details!$AQ$5:$AQ$53,(Details!$C$5:$C$53=Summary!AB$3)*(Details!$CK$5:$CK$53=$U$5)))),0)} -> 0 | AC22: {=IFERROR(ROWS(_xlfn.UNIQUE(_xlfn._xlws.FILTER(Details!$AQ$5:$AQ$53,(Details!$C$5:$C$53=Summary!AC$3)*(Details!$CK$5:$CK$53=$U$5)))),0)} -> 0 | ... AG22: {=IFERROR(ROWS(_xlfn.UNIQUE(_xlfn._xlws.FILTER(Details!$AQ$5:$AQ$53,(Details!$C$5:$C$53=Summary!AG$3)*(Details!$CK$5:$CK$53=$U$5)))),0)} -> 0 | AH22: =COUNTIFS('Buyer Metrics'!F:F,Summary!U5) -> 2 | AJ22: No. of Buyers (Recyclers) | AK22: {=IFERROR(ROWS(_xlfn.UNIQUE(_xlfn._xlws.FILTER(Details!$AQ$5:$AQ$53,(Details!$C$5:$C$53=Summary!AK$3)*(Details!$CK$5:$CK$53=$AJ$5)))),0)} -> 0 | AL22: {=IFERROR(ROWS(_xlfn.UNIQUE(_xlfn._xlws.FILTER(Details!$AQ$5:$AQ$53,(Details!$C$5:$C$53=Summary!AL$3)*(Details!$CK$5:$CK$53=$AJ$5)))),0)} -> 0 | AM22: {=IFERROR(ROWS(_xlfn.UNIQUE(_xlfn._xlws.FILTER(Details!$AQ$5:$AQ$53,(Details!$C$5:$C$53=Summary!AM$3)*(Details!$CK$5:$CK$53=$AJ$5)))),0)} -> 0 | AN22: {=IFERROR(ROWS(_xlfn.UNIQUE(_xlfn._xlws.FILTER(Details!$AQ$5:$AQ$53,(Details!$C$5:$C$53=Summary!AN$3)*(Details!$CK$5:$CK$53=$AJ$5)))),0)} -> 0 | AO22: {=IFERROR(ROWS(_xlfn.UNIQUE(_xlfn._xlws.FILTER(Details!$AQ$5:$AQ$53,(Details!$C$5:$C$53=Summary!AO$3)*(Details!$CK$5:$CK$53=$AJ$5)))),0)} -> 0 | AP22: {=IFERROR(ROWS(_xlfn.UNIQUE(_xlfn._xlws.FILTER(Details!$AQ$5:$AQ$53,(Details!$C$5:$C$53=Summary!AP$3)*(Details!$CK$5:$CK$53=$AJ$5)))),0)} -> 0 | AQ22: {=IFERROR(ROWS(_xlfn.UNIQUE(_xlfn._xlws.FILTER(Details!$AQ$5:$AQ$53,(Details!$C$5:$C$53=Summary!AQ$3)*(Details!$CK$5:$CK$53=$AJ$5)))),0)} -> 0 | AR22: {=IFERROR(ROWS(_xlfn.UNIQUE(_xlfn._xlws.FILTER(Details!$AQ$5:$AQ$53,(Details!$C$5:$C$53=Summary!AR$3)*(Details!$CK$5:$CK$53=$AJ$5)))),0)} -> 0 | ... AV22: {=IFERROR(ROWS(_xlfn.UNIQUE(_xlfn._xlws.FILTER(Details!$AQ$5:$AQ$53,(Details!$C$5:$C$53=Summary!AV$3)*(Details!$CK$5:$CK$53=$AJ$5)))),0)} -> 0 | AW22: =COUNTIFS('Buyer Metrics'!F:F,Summary!AJ5) -> 6 | AY22: No. of Buyers (Recyclers) | AZ22: {=IFERROR(ROWS(_xlfn.UNIQUE(_xlfn._xlws.FILTER(Details!$AQ$5:$AQ$53,(Details!$C$5:$C$53=Summary!AZ$3)*(Details!$CK$5:$CK$53=$AY$5)))),0)} -> 0 | BA22: {=IFERROR(ROWS(_xlfn.UNIQUE(_xlfn._xlws.FILTER(Details!$AQ$5:$AQ$53,(Details!$C$5:$C$53=Summary!BA$3)*(Details!$CK$5:$CK$53=$AY$5)))),0)} -> 0 | BB22: {=IFERROR(ROWS(_xlfn.UNIQUE(_xlfn._xlws.FILTER(Details!$AQ$5:$AQ$53,(Details!$C$5:$C$53=Summary!BB$3)*(Details!$CK$5:$CK$53=$AY$5)))),0)} -> 0 | BC22: {=IFERROR(ROWS(_xlfn.UNIQUE(_xlfn._xlws.FILTER(Details!$AQ$5:$AQ$53,(Details!$C$5:$C$53=Summary!BC$3)*(Details!$CK$5:$CK$53=$AY$5)))),0)} -> 0 | BD22: {=IFERROR(ROWS(_xlfn.UNIQUE(_xlfn._xlws.FILTER(Details!$AQ$5:$AQ$53,(Details!$C$5:$C$53=Summary!BD$3)*(Details!$CK$5:$CK$53=$AY$5)))),0)} -> 0 | BE22: {=IFERROR(ROWS(_xlfn.UNIQUE(_xlfn._xlws.FILTER(Details!$AQ$5:$AQ$53,(Details!$C$5:$C$53=Summary!BE$3)*(Details!$CK$5:$CK$53=$AY$5)))),0)} -> 0 | BF22: {=IFERROR(ROWS(_xlfn.UNIQUE(_xlfn._xlws.FILTER(Details!$AQ$5:$AQ$53,(Details!$C$5:$C$53=Summary!BF$3)*(Details!$CK$5:$CK$53=$AY$5)))),0)} -> 0 | BG22: {=IFERROR(ROWS(_xlfn.UNIQUE(_xlfn._xlws.FILTER(Details!$AQ$5:$AQ$53,(Details!$C$5:$C$53=Summary!BG$3)*(Details!$CK$5:$CK$53=$AY$5)))),0)} -> 0 | ... BK22: {=IFERROR(ROWS(_xlfn.UNIQUE(_xlfn._xlws.FILTER(Details!$AQ$5:$AQ$53,(Details!$C$5:$C$53=Summary!BK$3)*(Details!$CK$5:$CK$53=$AY$5)))),0)} -> 0 | BL22: =COUNTIFS('Buyer Metrics'!F:F,Summary!AY5) -> 0 | BN22: =(AH22+AW22+BL22)-P22 -> 0
C23: Full Rejection | D23: {=IFERROR(ROWS(_xlfn.UNIQUE(_xlfn._xlws.FILTER(Details!$E$5:$E$53,(Details!$C$5:$C$53=Summary!D$3)*(Details!$BT$5:$BT$53=$C$23)))),0)} -> 1 | E23: {=IFERROR(ROWS(_xlfn.UNIQUE(_xlfn._xlws.FILTER(Details!$E$5:$E$53,(Details!$C$5:$C$53=Summary!E$3)*(Details!$BT$5:$BT$53=$C$23)))),0)} -> 0 | F23: {=IFERROR(ROWS(_xlfn.UNIQUE(_xlfn._xlws.FILTER(Details!$E$5:$E$53,(Details!$C$5:$C$53=Summary!F$3)*(Details!$BT$5:$BT$53=$C$23)))),0)} -> 0 | G23: {=IFERROR(ROWS(_xlfn.UNIQUE(_xlfn._xlws.FILTER(Details!$E$5:$E$53,(Details!$C$5:$C$53=Summary!G$3)*(Details!$BT$5:$BT$53=$C$23)))),0)} -> 0 | H23: {=IFERROR(ROWS(_xlfn.UNIQUE(_xlfn._xlws.FILTER(Details!$E$5:$E$53,(Details!$C$5:$C$53=Summary!H$3)*(Details!$BT$5:$BT$53=$C$23)))),0)} -> 0 | I23: {=IFERROR(ROWS(_xlfn.UNIQUE(_xlfn._xlws.FILTER(Details!$E$5:$E$53,(Details!$C$5:$C$53=Summary!I$3)*(Details!$BT$5:$BT$53=$C$23)))),0)} -> 0 | J23: {=IFERROR(ROWS(_xlfn.UNIQUE(_xlfn._xlws.FILTER(Details!$E$5:$E$53,(Details!$C$5:$C$53=Summary!J$3)*(Details!$BT$5:$BT$53=$C$23)))),0)} -> 0 | K23: {=IFERROR(ROWS(_xlfn.UNIQUE(_xlfn._xlws.FILTER(Details!$E$5:$E$53,(Details!$C$5:$C$53=Summary!K$3)*(Details!$BT$5:$BT$53=$C$23)))),0)} -> 0 | ... O23: {=IFERROR(ROWS(_xlfn.UNIQUE(_xlfn._xlws.FILTER(Details!$E$5:$E$53,(Details!$C$5:$C$53=Summary!O$3)*(Details!$BT$5:$BT$53=$C$23)))),0)} -> 0 | P23: =SUM(D23:O23) -> 1 | U23: Full Rejection | V23: {=IFERROR(ROWS(_xlfn.UNIQUE(_xlfn._xlws.FILTER(Details!$E$5:$E$53,(Details!$C$5:$C$53=Summary!V$3)*(Details!$BT$5:$BT$53=$C$23)*(Details!$CK$5:$CK$53=$U$5)))),0)} -> 0 | W23: {=IFERROR(ROWS(_xlfn.UNIQUE(_xlfn._xlws.FILTER(Details!$E$5:$E$53,(Details!$C$5:$C$53=Summary!W$3)*(Details!$BT$5:$BT$53=$C$23)*(Details!$CK$5:$CK$53=$U$5)))),0)} -> 0 | X23: {=IFERROR(ROWS(_xlfn.UNIQUE(_xlfn._xlws.FILTER(Details!$E$5:$E$53,(Details!$C$5:$C$53=Summary!X$3)*(Details!$BT$5:$BT$53=$C$23)*(Details!$CK$5:$CK$53=$U$5)))),0)} -> 0 | Y23: {=IFERROR(ROWS(_xlfn.UNIQUE(_xlfn._xlws.FILTER(Details!$E$5:$E$53,(Details!$C$5:$C$53=Summary!Y$3)*(Details!$BT$5:$BT$53=$C$23)*(Details!$CK$5:$CK$53=$U$5)))),0)} -> 0 | Z23: {=IFERROR(ROWS(_xlfn.UNIQUE(_xlfn._xlws.FILTER(Details!$E$5:$E$53,(Details!$C$5:$C$53=Summary!Z$3)*(Details!$BT$5:$BT$53=$C$23)*(Details!$CK$5:$CK$53=$U$5)))),0)} -> 0 | AA23: {=IFERROR(ROWS(_xlfn.UNIQUE(_xlfn._xlws.FILTER(Details!$E$5:$E$53,(Details!$C$5:$C$53=Summary!AA$3)*(Details!$BT$5:$BT$53=$C$23)*(Details!$CK$5:$CK$53=$U$5)))),0)} -> 0 | AB23: {=IFERROR(ROWS(_xlfn.UNIQUE(_xlfn._xlws.FILTER(Details!$E$5:$E$53,(Details!$C$5:$C$53=Summary!AB$3)*(Details!$BT$5:$BT$53=$C$23)*(Details!$CK$5:$CK$53=$U$5)))),0)} -> 0 | AC23: {=IFERROR(ROWS(_xlfn.UNIQUE(_xlfn._xlws.FILTER(Details!$E$5:$E$53,(Details!$C$5:$C$53=Summary!AC$3)*(Details!$BT$5:$BT$53=$C$23)*(Details!$CK$5:$CK$53=$U$5)))),0)} -> 0 | ... AG23: {=IFERROR(ROWS(_xlfn.UNIQUE(_xlfn._xlws.FILTER(Details!$E$5:$E$53,(Details!$C$5:$C$53=Summary!AG$3)*(Details!$BT$5:$BT$53=$C$23)*(Details!$CK$5:$CK$53=$U$5)))),0)} -> 0 | AH23: =SUM(V23:AG23) -> 0 | AJ23: Full Rejection | AK23: {=IFERROR(ROWS(_xlfn.UNIQUE(_xlfn._xlws.FILTER(Details!$E$5:$E$53,(Details!$C$5:$C$53=Summary!AK$3)*(Details!$BT$5:$BT$53=$C$23)*(Details!$CK$5:$CK$53=$AJ$5)))),0)} -> 0 | AL23: {=IFERROR(ROWS(_xlfn.UNIQUE(_xlfn._xlws.FILTER(Details!$E$5:$E$53,(Details!$C$5:$C$53=Summary!AL$3)*(Details!$BT$5:$BT$53=$C$23)*(Details!$CK$5:$CK$53=$AJ$5)))),0)} -> 0 | AM23: {=IFERROR(ROWS(_xlfn.UNIQUE(_xlfn._xlws.FILTER(Details!$E$5:$E$53,(Details!$C$5:$C$53=Summary!AM$3)*(Details!$BT$5:$BT$53=$C$23)*(Details!$CK$5:$CK$53=$AJ$5)))),0)} -> 0 | AN23: {=IFERROR(ROWS(_xlfn.UNIQUE(_xlfn._xlws.FILTER(Details!$E$5:$E$53,(Details!$C$5:$C$53=Summary!AN$3)*(Details!$BT$5:$BT$53=$C$23)*(Details!$CK$5:$CK$53=$AJ$5)))),0)} -> 0 | AO23: {=IFERROR(ROWS(_xlfn.UNIQUE(_xlfn._xlws.FILTER(Details!$E$5:$E$53,(Details!$C$5:$C$53=Summary!AO$3)*(Details!$BT$5:$BT$53=$C$23)*(Details!$CK$5:$CK$53=$AJ$5)))),0)} -> 0 | AP23: {=IFERROR(ROWS(_xlfn.UNIQUE(_xlfn._xlws.FILTER(Details!$E$5:$E$53,(Details!$C$5:$C$53=Summary!AP$3)*(Details!$BT$5:$BT$53=$C$23)*(Details!$CK$5:$CK$53=$AJ$5)))),0)} -> 0 | AQ23: {=IFERROR(ROWS(_xlfn.UNIQUE(_xlfn._xlws.FILTER(Details!$E$5:$E$53,(Details!$C$5:$C$53=Summary!AQ$3)*(Details!$BT$5:$BT$53=$C$23)*(Details!$CK$5:$CK$53=$AJ$5)))),0)} -> 0 | AR23: {=IFERROR(ROWS(_xlfn.UNIQUE(_xlfn._xlws.FILTER(Details!$E$5:$E$53,(Details!$C$5:$C$53=Summary!AR$3)*(Details!$BT$5:$BT$53=$C$23)*(Details!$CK$5:$CK$53=$AJ$5)))),0)} -> 0 | ... AV23: {=IFERROR(ROWS(_xlfn.UNIQUE(_xlfn._xlws.FILTER(Details!$E$5:$E$53,(Details!$C$5:$C$53=Summary!AV$3)*(Details!$BT$5:$BT$53=$C$23)*(Details!$CK$5:$CK$53=$AJ$5)))),0)} -> 0 | AW23: =SUM(AK23:AV23) -> 0 | AY23: Full Rejection | AZ23: {=IFERROR(ROWS(_xlfn.UNIQUE(_xlfn._xlws.FILTER(Details!$E$5:$E$53,(Details!$C$5:$C$53=Summary!AZ$3)*(Details!$BT$5:$BT$53=$C$23)*(Details!$CK$5:$CK$53=$AY$5)))),0)} -> 0 | BA23: {=IFERROR(ROWS(_xlfn.UNIQUE(_xlfn._xlws.FILTER(Details!$E$5:$E$53,(Details!$C$5:$C$53=Summary!BA$3)*(Details!$BT$5:$BT$53=$C$23)*(Details!$CK$5:$CK$53=$AY$5)))),0)} -> 0 | BB23: {=IFERROR(ROWS(_xlfn.UNIQUE(_xlfn._xlws.FILTER(Details!$E$5:$E$53,(Details!$C$5:$C$53=Summary!BB$3)*(Details!$BT$5:$BT$53=$C$23)*(Details!$CK$5:$CK$53=$AY$5)))),0)} -> 0 | BC23: {=IFERROR(ROWS(_xlfn.UNIQUE(_xlfn._xlws.FILTER(Details!$E$5:$E$53,(Details!$C$5:$C$53=Summary!BC$3)*(Details!$BT$5:$BT$53=$C$23)*(Details!$CK$5:$CK$53=$AY$5)))),0)} -> 0 | BD23: {=IFERROR(ROWS(_xlfn.UNIQUE(_xlfn._xlws.FILTER(Details!$E$5:$E$53,(Details!$C$5:$C$53=Summary!BD$3)*(Details!$BT$5:$BT$53=$C$23)*(Details!$CK$5:$CK$53=$AY$5)))),0)} -> 0 | BE23: {=IFERROR(ROWS(_xlfn.UNIQUE(_xlfn._xlws.FILTER(Details!$E$5:$E$53,(Details!$C$5:$C$53=Summary!BE$3)*(Details!$BT$5:$BT$53=$C$23)*(Details!$CK$5:$CK$53=$AY$5)))),0)} -> 0 | BF23: {=IFERROR(ROWS(_xlfn.UNIQUE(_xlfn._xlws.FILTER(Details!$E$5:$E$53,(Details!$C$5:$C$53=Summary!BF$3)*(Details!$BT$5:$BT$53=$C$23)*(Details!$CK$5:$CK$53=$AY$5)))),0)} -> 0 | BG23: {=IFERROR(ROWS(_xlfn.UNIQUE(_xlfn._xlws.FILTER(Details!$E$5:$E$53,(Details!$C$5:$C$53=Summary!BG$3)*(Details!$BT$5:$BT$53=$C$23)*(Details!$CK$5:$CK$53=$AY$5)))),0)} -> 0 | ... BK23: {=IFERROR(ROWS(_xlfn.UNIQUE(_xlfn._xlws.FILTER(Details!$E$5:$E$53,(Details!$C$5:$C$53=Summary!BK$3)*(Details!$BT$5:$BT$53=$C$23)*(Details!$CK$5:$CK$53=$AY$5)))),0)} -> 0 | BL23: =SUM(AZ23:BK23) -> 0 | BN23: =(AH23+AW23+BL23)-P23 -> -1
C24: Receivable (Exl Legacy) | D24: 1.1453541e+08 | E24: 96373901 | F24: 94601540 | G24: 0 | H24: 0 | I24: 0 | J24: 0 | K24: 0 | L24: 0 | M24: 0 | N24: 0 | O24: 0 | P24: =F24 -> 94601540 | U24: Receivable (Exl Legacy) | AG24: 0 | AH24: =AVERAGE(V24:AF24) -> #DIV/0! | AJ24: Receivable (Exl Legacy) | AV24: 0 | AW24: =AVERAGE(AK24:AU24) -> #DIV/0! | AY24: Receivable (Exl Legacy) | BK24: 0 | BL24: =AVERAGE(AZ24:BJ24) -> #DIV/0!
C25: DSO (Days) | D25: =IFERROR(((D24/(D7*1.18))*D4),0) -> 172.27826 | E25: =IFERROR(((E24/(E7*1.18))*E4),0) -> 216.51148 | F25: =IFERROR(((F24/(F7*1.18))*F4),0) -> 201.40486 | G25: =IFERROR(((G24/(G7*1.18))*G4),0) -> 0 | H25: =IFERROR(((H24/(H7*1.18))*H4),0) -> 0 | I25: =IFERROR(((I24/(I7*1.18))*I4),0) -> 0 | J25: =IFERROR(((J24/(J7*1.18))*J4),0) -> 0 | K25: =IFERROR(((K24/(K7*1.18))*K4),0) -> 0 | ... P25: =IFERROR(((P24/(P7*1.18))*P4),0) -> 177.88981 | U25: DSO (Days) | V25: =IFERROR(((V24/(V7*1.18))*V4),0) -> 0 | W25: =IFERROR(((W24/(W7*1.18))*W4),0) -> 0 | X25: =IFERROR(((X24/(X7*1.18))*X4),0) -> 0 | Y25: =IFERROR(((Y24/(Y7*1.18))*Y4),0) -> 0 | Z25: =IFERROR(((Z24/(Z7*1.18))*Z4),0) -> 0 | AA25: =IFERROR(((AA24/(AA7*1.18))*AA4),0) -> 0 | AB25: =IFERROR(((AB24/(AB7*1.18))*AB4),0) -> 0 | AC25: =IFERROR(((AC24/(AC7*1.18))*AC4),0) -> 0 | ... AH25: =IFERROR(((AH24/(AH7*1.18))*AH4),0) -> 0 | AJ25: DSO (Days) | AK25: =IFERROR(((AK24/(AK7*1.18))*AK4),0) -> 0 | AL25: =IFERROR(((AL24/(AL7*1.18))*AL4),0) -> 0 | AM25: =IFERROR(((AM24/(AM7*1.18))*AM4),0) -> 0 | AN25: =IFERROR(((AN24/(AN7*1.18))*AN4),0) -> 0 | AO25: =IFERROR(((AO24/(AO7*1.18))*AO4),0) -> 0 | AP25: =IFERROR(((AP24/(AP7*1.18))*AP4),0) -> 0 | AQ25: =IFERROR(((AQ24/(AQ7*1.18))*AQ4),0) -> 0 | AR25: =IFERROR(((AR24/(AR7*1.18))*AR4),0) -> 0 | ... AW25: =IFERROR(((AW24/(AW7*1.18))*AW4),0) -> 0 | AY25: DSO (Days) | AZ25: =IFERROR(((AZ24/(AZ7*1.18))*AZ4),0) -> 0 | BA25: =IFERROR(((BA24/(BA7*1.18))*BA4),0) -> 0 | BB25: =IFERROR(((BB24/(BB7*1.18))*BB4),0) -> 0 | BC25: =IFERROR(((BC24/(BC7*1.18))*BC4),0) -> 0 | BD25: =IFERROR(((BD24/(BD7*1.18))*BD4),0) -> 0 | BE25: =IFERROR(((BE24/(BE7*1.18))*BE4),0) -> 0 | BF25: =IFERROR(((BF24/(BF7*1.18))*BF4),0) -> 0 | BG25: =IFERROR(((BG24/(BG7*1.18))*BG4),0) -> 0 | ... BL25: =IFERROR(((BL24/(BL7*1.18))*BL4),0) -> 0
C26: Payable | D26: 25291578 | E26: 12692977 | F26: 14596912 | G26: 0 | H26: 0 | I26: 0 | J26: 0 | K26: 0 | L26: 0 | M26: 0 | N26: 0 | O26: 0 | P26: =F26 -> 14596912 | U26: Payable | AH26: =AVERAGE(V26:AF26) -> #DIV/0! | AJ26: Payable | AY26: Payable
C27: DPO (Days) | D27: =IFERROR(((D26/(D8*1.18))*D4),0) -> 38.586975 | E27: =IFERROR(((E26/(E8*1.18))*E4),0) -> 29.342502 | F27: =IFERROR(((F26/(F8*1.18))*F4),0) -> 31.933047 | G27: =IFERROR(((G26/(G8*1.18))*G4),0) -> 0 | H27: =IFERROR(((H26/(H8*1.18))*H4),0) -> 0 | I27: =IFERROR(((I26/(I8*1.18))*I4),0) -> 0 | J27: =IFERROR(((J26/(J8*1.18))*J4),0) -> 0 | K27: =IFERROR(((K26/(K8*1.18))*K4),0) -> 0 | ... P27: =IFERROR(((P26/(P8*1.18))*P4),0) -> 28.049549 | U27: DPO (Days) | AJ27: DPO (Days) | AY27: DPO (Days)
C28: Working Capital Days | D28: =D25-D27 -> 133.69128 | E28: =E25-E27 -> 187.16898 | F28: =F25-F27 -> 169.47182 | G28: =G25-G27 -> 0 | H28: =H25-H27 -> 0 | I28: =I25-I27 -> 0 | J28: =J25-J27 -> 0 | K28: =K25-K27 -> 0 | ... P28: =P25-P27 -> 149.84026
C29: Credit Notes (Value - Incl. Prov) | D29: 236391.2 | E29: 276677.88 | F29: =-SUMIFS(Details!$BY$5:$BY$53,Details!$C$5:$C$53,Summary!F$5) -> 272586.72 | G29: =-SUMIFS(Details!$BY$5:$BY$53,Details!$C$5:$C$53,Summary!G$5) -> 0 | H29: =-SUMIFS(Details!$BY$5:$BY$53,Details!$C$5:$C$53,Summary!H$5) -> 0 | I29: =-SUMIFS(Details!$BY$5:$BY$53,Details!$C$5:$C$53,Summary!I$5) -> 0 | J29: =-SUMIFS(Details!$BY$5:$BY$53,Details!$C$5:$C$53,Summary!J$5) -> 0 | K29: =-SUMIFS(Details!$BY$5:$BY$53,Details!$C$5:$C$53,Summary!K$5) -> 0 | L29: =-SUMIFS(Details!$BY$5:$BY$53,Details!$C$5:$C$53,Summary!L$5) -> 0 | M29: =-SUMIFS(Details!$BY$5:$BY$53,Details!$C$5:$C$53,Summary!M$5) -> 0 | ... O29: =-SUMIFS(Details!$BY$5:$BY$53,Details!$C$5:$C$53,Summary!O$5) -> 0 | P29: =SUM(D29:O29) -> 785655.8 | Q29: =(-Details!BO54-Details!BP54) -> 614927.7 | R29: =P29-Q29 -> 170728.1 | T29: =-R29 -> -170728.1 | U29: Quantity (MT) | V29: =SUMIFS(Details!$S$5:$S$53,Details!$C$5:$C$53,Summary!V$5,Details!$CK$5:$CK$53,Summary!$U$5)/1000 -> 26.99 | W29: =SUMIFS(Details!$S$5:$S$53,Details!$C$5:$C$53,Summary!W$5,Details!$CK$5:$CK$53,Summary!$U$5)/1000 -> 25.43 | X29: =SUMIFS(Details!$S$5:$S$53,Details!$C$5:$C$53,Summary!X$5,Details!$CK$5:$CK$53,Summary!$U$5)/1000 -> 14.385 | Y29: =SUMIFS(Details!$S$5:$S$53,Details!$C$5:$C$53,Summary!Y$5,Details!$CK$5:$CK$53,Summary!$U$5)/1000 -> 0 | Z29: =SUMIFS(Details!$S$5:$S$53,Details!$C$5:$C$53,Summary!Z$5,Details!$CK$5:$CK$53,Summary!$U$5)/1000 -> 0 | AA29: =SUMIFS(Details!$S$5:$S$53,Details!$C$5:$C$53,Summary!AA$5,Details!$CK$5:$CK$53,Summary!$U$5)/1000 -> 0 | AB29: =SUMIFS(Details!$S$5:$S$53,Details!$C$5:$C$53,Summary!AB$5,Details!$CK$5:$CK$53,Summary!$U$5)/1000 -> 0 | AC29: =SUMIFS(Details!$S$5:$S$53,Details!$C$5:$C$53,Summary!AC$5,Details!$CK$5:$CK$53,Summary!$U$5)/1000 -> 0 | ... AG29: =SUMIFS(Details!$S$5:$S$53,Details!$C$5:$C$53,Summary!AG$5,Details!$CK$5:$CK$53,Summary!$U$5)/1000 -> 0 | AH29: =SUM(V29:AG29) -> 66.805 | AJ29: Quantity (MT) | AK29: =SUMIFS(Details!$S$5:$S$53,Details!$C$5:$C$53,Summary!AK$5,Details!$CK$5:$CK$53,Summary!$AJ$5)/1000 -> 249.605 | AL29: =SUMIFS(Details!$S$5:$S$53,Details!$C$5:$C$53,Summary!AL$5,Details!$CK$5:$CK$53,Summary!$AJ$5)/1000 -> 104.47 | AM29: =SUMIFS(Details!$S$5:$S$53,Details!$C$5:$C$53,Summary!AM$5,Details!$CK$5:$CK$53,Summary!$AJ$5)/1000 -> 99.631 | AN29: =SUMIFS(Details!$S$5:$S$53,Details!$C$5:$C$53,Summary!AN$5,Details!$CK$5:$CK$53,Summary!$AJ$5)/1000 -> 0 | AO29: =SUMIFS(Details!$S$5:$S$53,Details!$C$5:$C$53,Summary!AO$5,Details!$CK$5:$CK$53,Summary!$AJ$5)/1000 -> 0 | AP29: =SUMIFS(Details!$S$5:$S$53,Details!$C$5:$C$53,Summary!AP$5,Details!$CK$5:$CK$53,Summary!$AJ$5)/1000 -> 0 | AQ29: =SUMIFS(Details!$S$5:$S$53,Details!$C$5:$C$53,Summary!AQ$5,Details!$CK$5:$CK$53,Summary!$AJ$5)/1000 -> 0 | AR29: =SUMIFS(Details!$S$5:$S$53,Details!$C$5:$C$53,Summary!AR$5,Details!$CK$5:$CK$53,Summary!$AJ$5)/1000 -> 0 | ... AV29: =SUMIFS(Details!$S$5:$S$53,Details!$C$5:$C$53,Summary!AV$5,Details!$CK$5:$CK$53,Summary!$AJ$5)/1000 -> 0 | AW29: =SUM(AK29:AV29) -> 453.706 | AY29: Quantity (MT) | AZ29: =SUMIFS(Details!$S$5:$S$53,Details!$C$5:$C$53,Summary!AZ$5,Details!$CK$5:$CK$53,Summary!$AY$5)/1000 -> 0 | BA29: =SUMIFS(Details!$S$5:$S$53,Details!$C$5:$C$53,Summary!BA$5,Details!$CK$5:$CK$53,Summary!$AY$5)/1000 -> 0 | BB29: =SUMIFS(Details!$S$5:$S$53,Details!$C$5:$C$53,Summary!BB$5,Details!$CK$5:$CK$53,Summary!$AY$5)/1000 -> 0 | BC29: =SUMIFS(Details!$S$5:$S$53,Details!$C$5:$C$53,Summary!BC$5,Details!$CK$5:$CK$53,Summary!$AY$5)/1000 -> 0 | BD29: =SUMIFS(Details!$S$5:$S$53,Details!$C$5:$C$53,Summary!BD$5,Details!$CK$5:$CK$53,Summary!$AY$5)/1000 -> 0 | BE29: =SUMIFS(Details!$S$5:$S$53,Details!$C$5:$C$53,Summary!BE$5,Details!$CK$5:$CK$53,Summary!$AY$5)/1000 -> 0 | BF29: =SUMIFS(Details!$S$5:$S$53,Details!$C$5:$C$53,Summary!BF$5,Details!$CK$5:$CK$53,Summary!$AY$5)/1000 -> 0 | BG29: =SUMIFS(Details!$S$5:$S$53,Details!$C$5:$C$53,Summary!BG$5,Details!$CK$5:$CK$53,Summary!$AY$5)/1000 -> 0 | ... BK29: =SUMIFS(Details!$S$5:$S$53,Details!$C$5:$C$53,Summary!BK$5,Details!$CK$5:$CK$53,Summary!$AY$5)/1000 -> 0 | BL29: =SUM(AZ29:BK29) -> 0 | BN29: =(AH29+AW29+BL29)-P29 -> -785135.29 | CI29: =E29 -> 276677.88 | CJ29: =T29+CI29 -> 105949.78
C30: Credit Notes (% to Revenue) | D30: =IFERROR((D29/D7),0) -> 0.013985654 | E30: =IFERROR((E29/E7),0) -> 0.023660082 | F30: =IFERROR((F29/F7),0) -> 0.032609125 | G30: =IFERROR((G29/G7),0) -> 0 | H30: =IFERROR((H29/H7),0) -> 0 | I30: =IFERROR((I29/I7),0) -> 0 | J30: =IFERROR((J29/J7),0) -> 0 | K30: =IFERROR((K29/K7),0) -> 0 | ... O30: =IFERROR((O29/O7),0) -> 0 | P30: =P29/P7 -> 0.021259515 | R30: =P30-Q30 -> 0.021259515 | U30: Credit Notes (% to Revenue) | V30: =V29/V7 -> 3.0220039e-06 | W30: =W29/W7 -> 2.9198646e-06 | X30: =X29/X7 -> 2.9165368e-06 | Y30: =Y29/Y7 -> #DIV/0! | Z30: =Z29/Z7 -> #DIV/0! | AA30: =AA29/AA7 -> #DIV/0! | AB30: =AB29/AB7 -> #DIV/0! | AC30: =AC29/AC7 -> #DIV/0! | ... AH30: =AH29/AH7 -> 2.9595501e-06 | AJ30: Credit Notes (% to Revenue) | AK30: =AK29/AK7 -> 3.1240512e-05 | AL30: =AL29/AL7 -> 3.3438115e-05 | AM30: =AM29/AM7 -> 2.9072398e-05 | AN30: =AN29/AN7 -> #DIV/0! | AO30: =AO29/AO7 -> #DIV/0! | AP30: =AP29/AP7 -> #DIV/0! | AQ30: =AQ29/AQ7 -> #DIV/0! | AR30: =AR29/AR7 -> #DIV/0! | ... AW30: =AW29/AW7 -> 3.1201712e-05 | AY30: Credit Notes (% to Revenue) | AZ30: =AZ29/AZ7 -> #DIV/0! | BA30: =BA29/BA7 -> #DIV/0! | BB30: =BB29/BB7 -> #DIV/0! | BC30: =BC29/BC7 -> #DIV/0! | BD30: =BD29/BD7 -> #DIV/0! | BE30: =BE29/BE7 -> #DIV/0! | BF30: =BF29/BF7 -> #DIV/0! | BG30: =BG29/BG7 -> #DIV/0! | ... BL30: =BL29/BL7 -> #DIV/0!
C31: Debit Notes (Value - Incl. Prov) | D31: 417679.38 | E31: 385503.5 | F31: =-SUMIFS(Details!$BZ$5:$BZ$53,Details!$C$5:$C$53,Summary!F$5) -> 315848.12 | G31: =-SUMIFS(Details!$BZ$5:$BZ$53,Details!$C$5:$C$53,Summary!G$5) -> 0 | H31: =-SUMIFS(Details!$BZ$5:$BZ$53,Details!$C$5:$C$53,Summary!H$5) -> 0 | I31: =-SUMIFS(Details!$BZ$5:$BZ$53,Details!$C$5:$C$53,Summary!I$5) -> 0 | J31: =-SUMIFS(Details!$BZ$5:$BZ$53,Details!$C$5:$C$53,Summary!J$5) -> 0 | K31: =-SUMIFS(Details!$BZ$5:$BZ$53,Details!$C$5:$C$53,Summary!K$5) -> 0 | L31: =-SUMIFS(Details!$BZ$5:$BZ$53,Details!$C$5:$C$53,Summary!L$5) -> 0 | M31: =-SUMIFS(Details!$BZ$5:$BZ$53,Details!$C$5:$C$53,Summary!M$5) -> 0 | ... O31: =-SUMIFS(Details!$BZ$5:$BZ$53,Details!$C$5:$C$53,Summary!O$5) -> 0 | P31: =SUM(D31:O31) -> 1119031 | Q31: =(-Details!AK54-Details!AL54) -> 953327.92 | R31: =P31-Q31 -> 165703.08 | T31: =-R31 -> -165703.08 | U31: Quantity (MT) | V31: =SUMIFS(Details!$S$5:$S$53,Details!$C$5:$C$53,Summary!V$5,Details!$CK$5:$CK$53,Summary!$U$5)/1000 -> 26.99 | W31: =SUMIFS(Details!$S$5:$S$53,Details!$C$5:$C$53,Summary!W$5,Details!$CK$5:$CK$53,Summary!$U$5)/1000 -> 25.43 | X31: =SUMIFS(Details!$S$5:$S$53,Details!$C$5:$C$53,Summary!X$5,Details!$CK$5:$CK$53,Summary!$U$5)/1000 -> 14.385 | Y31: =SUMIFS(Details!$S$5:$S$53,Details!$C$5:$C$53,Summary!Y$5,Details!$CK$5:$CK$53,Summary!$U$5)/1000 -> 0 | Z31: =SUMIFS(Details!$S$5:$S$53,Details!$C$5:$C$53,Summary!Z$5,Details!$CK$5:$CK$53,Summary!$U$5)/1000 -> 0 | AA31: =SUMIFS(Details!$S$5:$S$53,Details!$C$5:$C$53,Summary!AA$5,Details!$CK$5:$CK$53,Summary!$U$5)/1000 -> 0 | AB31: =SUMIFS(Details!$S$5:$S$53,Details!$C$5:$C$53,Summary!AB$5,Details!$CK$5:$CK$53,Summary!$U$5)/1000 -> 0 | AC31: =SUMIFS(Details!$S$5:$S$53,Details!$C$5:$C$53,Summary!AC$5,Details!$CK$5:$CK$53,Summary!$U$5)/1000 -> 0 | ... AG31: =SUMIFS(Details!$S$5:$S$53,Details!$C$5:$C$53,Summary!AG$5,Details!$CK$5:$CK$53,Summary!$U$5)/1000 -> 0 | AH31: =SUM(V31:AG31) -> 66.805 | AJ31: Quantity (MT) | AK31: =SUMIFS(Details!$S$5:$S$53,Details!$C$5:$C$53,Summary!AK$5,Details!$CK$5:$CK$53,Summary!$AJ$5)/1000 -> 249.605 | AL31: =SUMIFS(Details!$S$5:$S$53,Details!$C$5:$C$53,Summary!AL$5,Details!$CK$5:$CK$53,Summary!$AJ$5)/1000 -> 104.47 | AM31: =SUMIFS(Details!$S$5:$S$53,Details!$C$5:$C$53,Summary!AM$5,Details!$CK$5:$CK$53,Summary!$AJ$5)/1000 -> 99.631 | AN31: =SUMIFS(Details!$S$5:$S$53,Details!$C$5:$C$53,Summary!AN$5,Details!$CK$5:$CK$53,Summary!$AJ$5)/1000 -> 0 | AO31: =SUMIFS(Details!$S$5:$S$53,Details!$C$5:$C$53,Summary!AO$5,Details!$CK$5:$CK$53,Summary!$AJ$5)/1000 -> 0 | AP31: =SUMIFS(Details!$S$5:$S$53,Details!$C$5:$C$53,Summary!AP$5,Details!$CK$5:$CK$53,Summary!$AJ$5)/1000 -> 0 | AQ31: =SUMIFS(Details!$S$5:$S$53,Details!$C$5:$C$53,Summary!AQ$5,Details!$CK$5:$CK$53,Summary!$AJ$5)/1000 -> 0 | AR31: =SUMIFS(Details!$S$5:$S$53,Details!$C$5:$C$53,Summary!AR$5,Details!$CK$5:$CK$53,Summary!$AJ$5)/1000 -> 0 | ... AV31: =SUMIFS(Details!$S$5:$S$53,Details!$C$5:$C$53,Summary!AV$5,Details!$CK$5:$CK$53,Summary!$AJ$5)/1000 -> 0 | AW31: =SUM(AK31:AV31) -> 453.706 | AY31: Quantity (MT) | AZ31: =SUMIFS(Details!$S$5:$S$53,Details!$C$5:$C$53,Summary!AZ$5,Details!$CK$5:$CK$53,Summary!$AY$5)/1000 -> 0 | BA31: =SUMIFS(Details!$S$5:$S$53,Details!$C$5:$C$53,Summary!BA$5,Details!$CK$5:$CK$53,Summary!$AY$5)/1000 -> 0 | BB31: =SUMIFS(Details!$S$5:$S$53,Details!$C$5:$C$53,Summary!BB$5,Details!$CK$5:$CK$53,Summary!$AY$5)/1000 -> 0 | BC31: =SUMIFS(Details!$S$5:$S$53,Details!$C$5:$C$53,Summary!BC$5,Details!$CK$5:$CK$53,Summary!$AY$5)/1000 -> 0 | BD31: =SUMIFS(Details!$S$5:$S$53,Details!$C$5:$C$53,Summary!BD$5,Details!$CK$5:$CK$53,Summary!$AY$5)/1000 -> 0 | BE31: =SUMIFS(Details!$S$5:$S$53,Details!$C$5:$C$53,Summary!BE$5,Details!$CK$5:$CK$53,Summary!$AY$5)/1000 -> 0 | BF31: =SUMIFS(Details!$S$5:$S$53,Details!$C$5:$C$53,Summary!BF$5,Details!$CK$5:$CK$53,Summary!$AY$5)/1000 -> 0 | BG31: =SUMIFS(Details!$S$5:$S$53,Details!$C$5:$C$53,Summary!BG$5,Details!$CK$5:$CK$53,Summary!$AY$5)/1000 -> 0 | ... BK31: =SUMIFS(Details!$S$5:$S$53,Details!$C$5:$C$53,Summary!BK$5,Details!$CK$5:$CK$53,Summary!$AY$5)/1000 -> 0 | BL31: =SUM(AZ31:BK31) -> 0 | BN31: =(AH31+AW31+BL31)-P31 -> -1118510.5 | CI31: =E31 -> 385503.5 | CJ31: =T31+CI31 -> 219800.42
C32: Debit Notes (% to Purchase) | D32: =IFERROR((D31/D8),0) -> 0.025065051 | E32: =IFERROR((E31/E8),0) -> 0.033922066 | F32: =IFERROR((F31/F8),0) -> 0.038825796 | G32: =IFERROR((G31/G8),0) -> 0 | H32: =IFERROR((H31/H8),0) -> 0 | I32: =IFERROR((I31/I8),0) -> 0 | J32: =IFERROR((J31/J8),0) -> 0 | K32: =IFERROR((K31/K8),0) -> 0 | ... O32: =IFERROR((O31/O8),0) -> 0 | P32: =P31/P8 -> 0.030943907 | U32: Debit Notes (% to Purchase) | V32: =V31/V8 -> 3.1117489e-06 | W32: =W31/W8 -> 3.0038201e-06 | X32: =X31/X8 -> 3.0068425e-06 | Y32: =Y31/Y8 -> #DIV/0! | Z32: =Z31/Z8 -> #DIV/0! | AA32: =AA31/AA8 -> #DIV/0! | AB32: =AB31/AB8 -> #DIV/0! | AC32: =AC31/AC8 -> #DIV/0! | ... AH32: =AH31/AH8 -> 3.0471794e-06 | AJ32: Debit Notes (% to Purchase) | AK32: =AK31/AK8 -> 3.1276234e-05 | AL32: =AL31/AL8 -> 3.4124568e-05 | AM32: =AM31/AM8 -> 2.9732443e-05 | AN32: =AN31/AN8 -> #DIV/0! | AO32: =AO31/AO8 -> #DIV/0! | AP32: =AP31/AP8 -> #DIV/0! | AQ32: =AQ31/AQ8 -> #DIV/0! | AR32: =AR31/AR8 -> #DIV/0! | ... AW32: =AW31/AW8 -> 3.1522663e-05 | AY32: Debit Notes (% to Purchase) | AZ32: =AZ31/AZ8 -> #DIV/0! | BA32: =BA31/BA8 -> #DIV/0! | BB32: =BB31/BB8 -> #DIV/0! | BC32: =BC31/BC8 -> #DIV/0! | BD32: =BD31/BD8 -> #DIV/0! | BE32: =BE31/BE8 -> #DIV/0! | BF32: =BF31/BF8 -> #DIV/0! | BG32: =BG31/BG8 -> #DIV/0! | ... BL32: =BL31/BL8 -> #DIV/0!
C34: KPI's without Provisions | D34: =D5 -> 46113 | E34: =E5 -> 46143 | F34: =F5 -> 46174 | G34: =G5 -> 46204 | H34: =H5 -> 46235 | I34: =I5 -> 46266 | J34: =J5 -> 46296 | K34: =K5 -> 46327 | ... P34: =P5 -> FY 2026-27 | U34: KPI's without Provisions | V34: =V5 -> 46113 | W34: =W5 -> 46143 | X34: =X5 -> 46174 | Y34: =Y5 -> 46204 | Z34: =Z5 -> 46235 | AA34: =AA5 -> 46266 | AB34: =AB5 -> 46296 | AC34: =AC5 -> 46327 | ... AH34: =AH5 -> FY 2026-27 | AJ34: KPI's without Provisions | AK34: =AK5 -> 46113 | AL34: =AL5 -> 46143 | AM34: =AM5 -> 46174 | AN34: =AN5 -> 46204 | AO34: =AO5 -> 46235 | AP34: =AP5 -> 46266 | AQ34: =AQ5 -> 46296 | AR34: =AR5 -> 46327 | ... AW34: =AW5 -> FY 2026-27 | AY34: KPI's without Provisions | AZ34: =AZ5 -> 46113 | BA34: =BA5 -> 46143 | BB34: =BB5 -> 46174 | BC34: =BC5 -> 46204 | BD34: =BD5 -> 46235 | BE34: =BE5 -> 46266 | BF34: =BF5 -> 46296 | BG34: =BG5 -> 46327 | ... BL34: =BL5 -> FY 2026-27
C35: Sales without Provision | D35: =D7+D54 -> 16902407 | E35: =E7+E54 -> 11693868 | F35: =F7+F54 -> 8626312.5 | G35: =G7+G54 -> 0 | H35: =H7+H54 -> 0 | I35: =I7+I54 -> 0 | J35: =J7+J54 -> 0 | K35: =K7+K54 -> 0 | ... O35: =O7+O54 -> 0 | P35: =SUM(D35:O35) -> 37222587 | U35: Sales without Provision | V35: =V7+V48 -> 8931160 | W35: =W7+W48 -> 8709308 | X35: =X7+X48 -> 5035955 | Y35: =Y7+Y48 -> 0 | Z35: =Z7+Z48 -> 0 | AA35: =AA7+AA48 -> 0 | AB35: =AB7+AB48 -> 0 | AC35: =AC7+AC48 -> 0 | ... AG35: =AG7+AG48 -> 0 | AH35: =SUM(V35:AG35) -> 22676423 | AJ35: Sales without Provision | AK35: =AK7+AK48 -> 7989785.8 | AL35: =AL7+AL48 -> 3124279 | AM35: =AM7+AM48 -> 3590357.5 | AN35: =AN7+AN48 -> 0 | AO35: =AO7+AO48 -> 0 | AP35: =AP7+AP48 -> 0 | AQ35: =AQ7+AQ48 -> 0 | AR35: =AR7+AR48 -> 0 | ... AV35: =AV7+AV48 -> 0 | AW35: =SUM(AK35:AV35) -> 14704422 | AY35: Sales without Provision | AZ35: =AZ7+AZ48 -> 0 | BA35: =BA7+BA48 -> 0 | BB35: =BB7+BB48 -> 0 | BC35: =BC7+BC48 -> 0 | BD35: =BD7+BD48 -> 0 | BE35: =BE7+BE48 -> 0 | BF35: =BF7+BF48 -> 0 | BG35: =BG7+BG48 -> 0 | ... BK35: =BK7+BK48 -> 0 | BL35: =SUM(AZ35:BK35) -> 0 | BN35: =(AH35+AW35+BL35)-P35 -> 158258.1
C36: Purchases without Provision | D36: =D8+D53+D11 -> 16663815 | E36: =E8+E53+E11 -> 11364387 | F36: =F8+F53+F11 -> 8395365.2 | G36: =G8+G53+G11 -> 0 | H36: =H8+H53+H11 -> 0 | I36: =I8+I53+I11 -> 0 | J36: =J8+J53+J11 -> 0 | K36: =K8+K53+K11 -> 0 | ... O36: =O8+O53+O11 -> 0 | P36: =SUM(D36:O36) -> 36423567 | U36: Purchases without Provision | V36: =V8+V47+V11 -> 8673605.9 | W36: =W8+W47+W11 -> 8465911.9 | X36: =X8+X47+X11 -> 4884726 | Y36: =Y8+Y47+Y11 -> 0 | Z36: =Z8+Z47+Z11 -> 0 | AA36: =AA8+AA47+AA11 -> 0 | AB36: =AB8+AB47+AB11 -> 0 | AC36: =AC8+AC47+AC11 -> 0 | ... AG36: =AG8+AG47+AG11 -> 0 | AH36: =SUM(V36:AG36) -> 22024244 | AJ36: Purchases without Provision | AK36: =AK8+AK47+AK11 -> 7980909.8 | AL36: =AL8+AL47+AL11 -> 3061535.2 | AM36: =AM8+AM47+AM11 -> 3510753.1 | AN36: =AN8+AN47+AN11 -> 0 | AO36: =AO8+AO47+AO11 -> 0 | AP36: =AP8+AP47+AP11 -> 0 | AQ36: =AQ8+AQ47+AQ11 -> 0 | AR36: =AR8+AR47+AR11 -> 0 | ... AV36: =AV8+AV47+AV11 -> 0 | AW36: =SUM(AK36:AV36) -> 14553198 | AY36: Purchases without Provision | AZ36: =AZ8+AZ47+AZ11 -> 0 | BA36: =BA8+BA47+BA11 -> 0 | BB36: =BB8+BB47+BB11 -> 0 | BC36: =BC8+BC47+BC11 -> 0 | BD36: =BD8+BD47+BD11 -> 0 | BE36: =BE8+BE47+BE11 -> 0 | BF36: =BF8+BF47+BF11 -> 0 | BG36: =BG8+BG47+BG11 -> 0 | ... BK36: =BK8+BK47+BK11 -> 0 | BL36: =SUM(AZ36:BK36) -> 0 | BN36: =(AH36+AW36+BL36)-P36 -> 153874.59
C37: Contribution without Provision | D37: =D35-D36 -> 238591.53 | E37: =E35-E36 -> 329480.87 | F37: =F35-F36 -> 230947.35 | G37: =G35-G36 -> 0 | H37: =H35-H36 -> 0 | I37: =I35-I36 -> 0 | J37: =J35-J36 -> 0 | K37: =K35-K36 -> 0 | ... P37: =P35-P36 -> 799019.75 | U37: Contribution without Provision | V37: =V35-V36 -> 257554.11 | W37: =W35-W36 -> 243396.07 | X37: =X35-X36 -> 151228.97 | Y37: =Y35-Y36 -> 0 | Z37: =Z35-Z36 -> 0 | AA37: =AA35-AA36 -> 0 | AB37: =AB35-AB36 -> 0 | AC37: =AC35-AC36 -> 0 | ... AH37: =AH35-AH36 -> 652179.15 | AJ37: Contribution without Provision | AK37: =AK35-AK36 -> 8875.9853 | AL37: =AL35-AL36 -> 62743.751 | AM37: =AM35-AM36 -> 79604.369 | AN37: =AN35-AN36 -> 0 | AO37: =AO35-AO36 -> 0 | AP37: =AP35-AP36 -> 0 | AQ37: =AQ35-AQ36 -> 0 | AR37: =AR35-AR36 -> 0 | ... AW37: =AW35-AW36 -> 151224.11 | AY37: Contribution without Provision | AZ37: =AZ35-AZ36 -> 0 | BA37: =BA35-BA36 -> 0 | BB37: =BB35-BB36 -> 0 | BC37: =BC35-BC36 -> 0 | BD37: =BD35-BD36 -> 0 | BE37: =BE35-BE36 -> 0 | BF37: =BF35-BF36 -> 0 | BG37: =BG35-BG36 -> 0 | ... BL37: =BL35-BL36 -> 0
C38: Contribution (%) | D38: =D37/D35 -> 0.014115832 | E38: =E37/E35 -> 0.028175525 | F38: =F37/F35 -> 0.02677243 | G38: =G37/G35 -> #DIV/0! | H38: =H37/H35 -> #DIV/0! | I38: =I37/I35 -> #DIV/0! | J38: =J37/J35 -> #DIV/0! | K38: =K37/K35 -> #DIV/0! | ... P38: =P37/P35 -> 0.021465992 | U38: Contribution (%) | V38: =V37/V35 -> 0.0288377 | W38: =W37/W35 -> 0.027946661 | X38: =X37/X35 -> 0.030029848 | Y38: =Y37/Y35 -> #DIV/0! | Z38: =Z37/Z35 -> #DIV/0! | AA38: =AA37/AA35 -> #DIV/0! | AB38: =AB37/AB35 -> #DIV/0! | AC38: =AC37/AC35 -> #DIV/0! | ... AH38: =AH37/AH35 -> 0.02876023 | AJ38: Contribution (%) | AK38: =AK37/AK35 -> 0.0011109166 | AL38: =AL37/AL35 -> 0.020082634 | AM38: =AM37/AM35 -> 0.022171711 | AN38: =AN37/AN35 -> #DIV/0! | AO38: =AO37/AO35 -> #DIV/0! | AP38: =AP37/AP35 -> #DIV/0! | AQ38: =AQ37/AQ35 -> #DIV/0! | AR38: =AR37/AR35 -> #DIV/0! | ... AW38: =AW37/AW35 -> 0.01028426 | AY38: Contribution (%) | AZ38: =AZ37/AZ35 -> #DIV/0! | BA38: =BA37/BA35 -> #DIV/0! | BB38: =BB37/BB35 -> #DIV/0! | BC38: =BC37/BC35 -> #DIV/0! | BD38: =BD37/BD35 -> #DIV/0! | BE38: =BE37/BE35 -> #DIV/0! | BF38: =BF37/BF35 -> #DIV/0! | BG38: =BG37/BG35 -> #DIV/0! | ... BL38: =BL37/BL35 -> #DIV/0!
C40: Business Trends | D40: =D5 -> 46113 | E40: =E5 -> 46143 | F40: =F5 -> 46174 | G40: =G5 -> 46204 | H40: =H5 -> 46235 | I40: =I5 -> 46266 | J40: =J5 -> 46296 | K40: =K5 -> 46327 | ... P40: =P5 -> FY 2026-27 | U40: Business Trends | V40: =V5 -> 46113 | W40: =W5 -> 46143 | X40: =X5 -> 46174 | Y40: =Y5 -> 46204 | Z40: =Z5 -> 46235 | AA40: =AA5 -> 46266 | AB40: =AB5 -> 46296 | AC40: =AC5 -> 46327 | ... AH40: =AH5 -> FY 2026-27 | AJ40: Business Trends | AK40: =AK5 -> 46113 | AL40: =AL5 -> 46143 | AM40: =AM5 -> 46174 | AN40: =AN5 -> 46204 | AO40: =AO5 -> 46235 | AP40: =AP5 -> 46266 | AQ40: =AQ5 -> 46296 | AR40: =AR5 -> 46327 | ... AW40: =AW5 -> FY 2026-27 | AY40: Business Trends | AZ40: =AZ5 -> 46113 | BA40: =BA5 -> 46143 | BB40: =BB5 -> 46174 | BC40: =BC5 -> 46204 | BD40: =BD5 -> 46235 | BE40: =BE5 -> 46266 | BF40: =BF5 -> 46296 | BG40: =BG5 -> 46327 | ... BL40: =BL5 -> FY 2026-27
C41: Sales-Revenue (MoM) | D41: =IFERROR(((D7/C7)-1),0) -> 0 | E41: =IFERROR(((E7/D7)-1),0) -> -0.30815366 | F41: =IFERROR(((F7/E7)-1),0) -> -0.28516247 | G41: =IFERROR(((G7/F7)-1),0) -> -1 | H41: =IFERROR(((H7/G7)-1),0) -> 0 | I41: =IFERROR(((I7/H7)-1),0) -> 0 | J41: =IFERROR(((J7/I7)-1),0) -> 0 | K41: =IFERROR(((K7/J7)-1),0) -> 0 | ... O41: =IFERROR(((O7/N7)-1),0) -> 0 | P41: 0 | U41: Sales-Revenue (MoM) | V41: =IFERROR(((V7/U7)-1),0) -> 0 | W41: =IFERROR(((W7/V7)-1),0) -> -0.024840222 | X41: =IFERROR(((X7/W7)-1),0) -> -0.43368411 | Y41: =IFERROR(((Y7/X7)-1),0) -> -1 | Z41: =IFERROR(((Z7/Y7)-1),0) -> 0 | AA41: =IFERROR(((AA7/Z7)-1),0) -> 0 | AB41: =IFERROR(((AB7/AA7)-1),0) -> 0 | AC41: =IFERROR(((AC7/AB7)-1),0) -> 0 | ... AG41: =IFERROR(((AG7/AF7)-1),0) -> 0 | AH41: 0 | AJ41: Sales-Revenue (MoM) | AK41: =IFERROR(((AK7/AJ7)-1),0) -> 0 | AL41: =IFERROR(((AL7/AK7)-1),0) -> -0.60896587 | AM41: =IFERROR(((AM7/AL7)-1),0) -> 0.096891887 | AN41: =IFERROR(((AN7/AM7)-1),0) -> -1 | AO41: =IFERROR(((AO7/AN7)-1),0) -> 0 | AP41: =IFERROR(((AP7/AO7)-1),0) -> 0 | AQ41: =IFERROR(((AQ7/AP7)-1),0) -> 0 | AR41: =IFERROR(((AR7/AQ7)-1),0) -> 0 | ... AV41: =IFERROR(((AV7/AU7)-1),0) -> 0 | AW41: 0 | AY41: Sales-Revenue (MoM) | AZ41: =IFERROR(((AZ7/AY7)-1),0) -> 0 | BA41: =IFERROR(((BA7/AZ7)-1),0) -> 0 | BB41: =IFERROR(((BB7/BA7)-1),0) -> 0 | BC41: =IFERROR(((BC7/BB7)-1),0) -> 0 | BD41: =IFERROR(((BD7/BC7)-1),0) -> 0 | BE41: =IFERROR(((BE7/BD7)-1),0) -> 0 | BF41: =IFERROR(((BF7/BE7)-1),0) -> 0 | BG41: =IFERROR(((BG7/BF7)-1),0) -> 0 | ... BK41: =IFERROR(((BK7/BJ7)-1),0) -> 0 | BL41: 0
C42: Sales-Volume (MoM) | D42: =IFERROR(((D6/C6)-1),0) -> 0 | E42: =IFERROR(((E6/D6)-1),0) -> -0.53325913 | F42: =IFERROR(((F6/E6)-1),0) -> -0.11718931 | G42: =IFERROR(((G6/F6)-1),0) -> -1 | H42: =IFERROR(((H6/G6)-1),0) -> 0 | I42: =IFERROR(((I6/H6)-1),0) -> 0 | J42: =IFERROR(((J6/I6)-1),0) -> 0 | K42: =IFERROR(((K6/J6)-1),0) -> 0 | ... O42: =IFERROR(((O6/N6)-1),0) -> 0 | P42: 0 | U42: Sales-Volume (MoM) | V42: =IFERROR(((V6/U6)-1),0) -> 0 | W42: =IFERROR(((W6/V6)-1),0) -> -0.057799185 | X42: =IFERROR(((X6/W6)-1),0) -> -0.43432953 | Y42: =IFERROR(((Y6/X6)-1),0) -> -1 | Z42: =IFERROR(((Z6/Y6)-1),0) -> 0 | AA42: =IFERROR(((AA6/Z6)-1),0) -> 0 | AB42: =IFERROR(((AB6/AA6)-1),0) -> 0 | AC42: =IFERROR(((AC6/AB6)-1),0) -> 0 | ... AG42: =IFERROR(((AG6/AF6)-1),0) -> 0 | AH42: 0 | AJ42: Sales-Volume (MoM) | AK42: =IFERROR(((AK6/AJ6)-1),0) -> 0 | AL42: =IFERROR(((AL6/AK6)-1),0) -> -0.5814587 | AM42: =IFERROR(((AM6/AL6)-1),0) -> -0.046319518 | AN42: =IFERROR(((AN6/AM6)-1),0) -> -1 | AO42: =IFERROR(((AO6/AN6)-1),0) -> 0 | AP42: =IFERROR(((AP6/AO6)-1),0) -> 0 | AQ42: =IFERROR(((AQ6/AP6)-1),0) -> 0 | AR42: =IFERROR(((AR6/AQ6)-1),0) -> 0 | ... AV42: =IFERROR(((AV6/AU6)-1),0) -> 0 | AW42: 0 | AY42: Sales-Volume (MoM) | AZ42: =IFERROR(((AZ6/AY6)-1),0) -> 0 | BA42: =IFERROR(((BA6/AZ6)-1),0) -> 0 | BB42: =IFERROR(((BB6/BA6)-1),0) -> 0 | BC42: =IFERROR(((BC6/BB6)-1),0) -> 0 | BD42: =IFERROR(((BD6/BC6)-1),0) -> 0 | BE42: =IFERROR(((BE6/BD6)-1),0) -> 0 | BF42: =IFERROR(((BF6/BE6)-1),0) -> 0 | BG42: =IFERROR(((BG6/BF6)-1),0) -> 0 | ... BK42: =IFERROR(((BK6/BJ6)-1),0) -> 0 | BL42: 0
C43: Sales-Transactions (MoM) | D43: =IFERROR(((D20/C20)-1),0) -> 0 | E43: =IFERROR(((E20/D20)-1),0) -> -0.27272727 | F43: =IFERROR(((F20/E20)-1),0) -> -0.4375 | G43: =IFERROR(((G20/F20)-1),0) -> -1 | H43: =IFERROR(((H20/G20)-1),0) -> 0 | I43: =IFERROR(((I20/H20)-1),0) -> 0 | J43: =IFERROR(((J20/I20)-1),0) -> 0 | K43: =IFERROR(((K20/J20)-1),0) -> 0 | ... O43: =IFERROR(((O20/N20)-1),0) -> 0 | P43: 0 | U43: Sales-Transactions (MoM) | V43: =IFERROR(((V20/U20)-1),0) -> 0 | W43: =IFERROR(((W20/V20)-1),0) -> 0 | X43: =IFERROR(((X20/W20)-1),0) -> 0 | Y43: =IFERROR(((Y20/X20)-1),0) -> 0 | Z43: =IFERROR(((Z20/Y20)-1),0) -> 0 | AA43: =IFERROR(((AA20/Z20)-1),0) -> 0 | AB43: =IFERROR(((AB20/AA20)-1),0) -> 0 | AC43: =IFERROR(((AC20/AB20)-1),0) -> 0 | ... AG43: =IFERROR(((AG20/AF20)-1),0) -> 0 | AH43: 0 | AJ43: Sales-Transactions (MoM) | AK43: =IFERROR(((AK20/AJ20)-1),0) -> 0 | AL43: =IFERROR(((AL20/AK20)-1),0) -> 0 | AM43: =IFERROR(((AM20/AL20)-1),0) -> 0 | AN43: =IFERROR(((AN20/AM20)-1),0) -> 0 | AO43: =IFERROR(((AO20/AN20)-1),0) -> 0 | AP43: =IFERROR(((AP20/AO20)-1),0) -> 0 | AQ43: =IFERROR(((AQ20/AP20)-1),0) -> 0 | AR43: =IFERROR(((AR20/AQ20)-1),0) -> 0 | ... AV43: =IFERROR(((AV20/AU20)-1),0) -> 0 | AW43: 0 | AY43: Sales-Transactions (MoM) | AZ43: =IFERROR(((AZ20/AY20)-1),0) -> 0 | BA43: =IFERROR(((BA20/AZ20)-1),0) -> 0 | BB43: =IFERROR(((BB20/BA20)-1),0) -> 0 | BC43: =IFERROR(((BC20/BB20)-1),0) -> 0 | BD43: =IFERROR(((BD20/BC20)-1),0) -> 0 | BE43: =IFERROR(((BE20/BD20)-1),0) -> 0 | BF43: =IFERROR(((BF20/BE20)-1),0) -> 0 | BG43: =IFERROR(((BG20/BF20)-1),0) -> 0 | ... BK43: =IFERROR(((BK20/BJ20)-1),0) -> 0 | BL43: 0
C45: Loss Making Transactions | D45: =D5 -> 46113 | E45: =E5 -> 46143 | F45: =F5 -> 46174 | G45: =G5 -> 46204 | H45: =H5 -> 46235 | I45: =I5 -> 46266 | J45: =J5 -> 46296 | K45: =K5 -> 46327 | ... P45: =P5 -> FY 2026-27
C46: No of LMT @ Inception | D46: 3 | E46: 1 | F46: 0 | G46: 0 | H46: 4 | I46: 0 | J46: 0 | K46: 8 | L46: 0 | M46: 0 | N46: 0 | O46: 0 | P46: =SUM(D46:O46) -> 16 | U46: CN & DN Provisions | V46: =V5 -> 46113 | W46: =W5 -> 46143 | X46: =X5 -> 46174 | Y46: =Y5 -> 46204 | Z46: =Z5 -> 46235 | AA46: =AA5 -> 46266 | AB46: =AB5 -> 46296 | AC46: =AC5 -> 46327 | ... AH46: =AH5 -> FY 2026-27 | AJ46: CN & DN Provisions | AK46: =AK5 -> 46113 | AL46: =AL5 -> 46143 | AM46: =AM5 -> 46174 | AN46: =AN5 -> 46204 | AO46: =AO5 -> 46235 | AP46: =AP5 -> 46266 | AQ46: =AQ5 -> 46296 | AR46: =AR5 -> 46327 | ... AW46: =AW5 -> FY 2026-27 | AY46: CN & DN Provisions | AZ46: =AZ5 -> 46113 | BA46: =BA5 -> 46143 | BB46: =BB5 -> 46174 | BC46: =BC5 -> 46204 | BD46: =BD5 -> 46235 | BE46: =BE5 -> 46266 | BF46: =BF5 -> 46296 | BG46: =BG5 -> 46327 | ... BL46: =BL5 -> FY 2026-27
C47: Value of LMT @ Inception | D47: 67735 | E47: 44712 | F47: 0 | G47: 0 | H47: 18138 | I47: 0 | J47: 0 | K47: 59790 | L47: 0 | M47: 0 | N47: 0 | O47: 0 | P47: =SUM(D47:O47) -> 190375 | U47: DN Provision | V47: =-SUMIFS(Details!$AL$5:$AL$53,Details!$C$5:$C$53,Summary!V$5,Details!$CK$5:$CK$53,Summary!$U$5) -> 0 | W47: =-SUMIFS(Details!$AL$5:$AL$53,Details!$C$5:$C$53,Summary!W$5,Details!$CK$5:$CK$53,Summary!$U$5) -> 0 | X47: =-SUMIFS(Details!$AL$5:$AL$53,Details!$C$5:$C$53,Summary!X$5,Details!$CK$5:$CK$53,Summary!$U$5) -> 100623.39 | Y47: =-SUMIFS(Details!$AL$5:$AL$53,Details!$C$5:$C$53,Summary!Y$5,Details!$CK$5:$CK$53,Summary!$U$5) -> 0 | Z47: =-SUMIFS(Details!$AL$5:$AL$53,Details!$C$5:$C$53,Summary!Z$5,Details!$CK$5:$CK$53,Summary!$U$5) -> 0 | AA47: =-SUMIFS(Details!$AL$5:$AL$53,Details!$C$5:$C$53,Summary!AA$5,Details!$CK$5:$CK$53,Summary!$U$5) -> 0 | AB47: =-SUMIFS(Details!$AL$5:$AL$53,Details!$C$5:$C$53,Summary!AB$5,Details!$CK$5:$CK$53,Summary!$U$5) -> 0 | AC47: =-SUMIFS(Details!$AL$5:$AL$53,Details!$C$5:$C$53,Summary!AC$5,Details!$CK$5:$CK$53,Summary!$U$5) -> 0 | ... AG47: =-SUMIFS(Details!$AL$5:$AL$53,Details!$C$5:$C$53,Summary!AG$5,Details!$CK$5:$CK$53,Summary!$U$5) -> 0 | AH47: =SUM(V47:AG47) -> 100623.39 | AJ47: DN Provision | AK47: =-SUMIFS(Details!$AL$5:$AL$53,Details!$C$5:$C$53,Summary!AK$5,Details!$CK$5:$CK$53,Summary!$AJ$5) -> 0 | AL47: =-SUMIFS(Details!$AL$5:$AL$53,Details!$C$5:$C$53,Summary!AL$5,Details!$CK$5:$CK$53,Summary!$AJ$5) -> 0 | AM47: =-SUMIFS(Details!$AL$5:$AL$53,Details!$C$5:$C$53,Summary!AM$5,Details!$CK$5:$CK$53,Summary!$AJ$5) -> 159734.73 | AN47: =-SUMIFS(Details!$AL$5:$AL$53,Details!$C$5:$C$53,Summary!AN$5,Details!$CK$5:$CK$53,Summary!$AJ$5) -> 0 | AO47: =-SUMIFS(Details!$AL$5:$AL$53,Details!$C$5:$C$53,Summary!AO$5,Details!$CK$5:$CK$53,Summary!$AJ$5) -> 0 | AP47: =-SUMIFS(Details!$AL$5:$AL$53,Details!$C$5:$C$53,Summary!AP$5,Details!$CK$5:$CK$53,Summary!$AJ$5) -> 0 | AQ47: =-SUMIFS(Details!$AL$5:$AL$53,Details!$C$5:$C$53,Summary!AQ$5,Details!$CK$5:$CK$53,Summary!$AJ$5) -> 0 | AR47: =-SUMIFS(Details!$AL$5:$AL$53,Details!$C$5:$C$53,Summary!AR$5,Details!$CK$5:$CK$53,Summary!$AJ$5) -> 0 | ... AV47: =-SUMIFS(Details!$AL$5:$AL$53,Details!$C$5:$C$53,Summary!AV$5,Details!$CK$5:$CK$53,Summary!$AJ$5) -> 0 | AW47: =SUM(AK47:AV47) -> 159734.73 | AY47: DN Provision | AZ47: =-SUMIFS(Details!$AL$5:$AL$53,Details!$C$5:$C$53,Summary!AZ$5,Details!$CK$5:$CK$53,Summary!$AY$5) -> 0 | BA47: =-SUMIFS(Details!$AL$5:$AL$53,Details!$C$5:$C$53,Summary!BA$5,Details!$CK$5:$CK$53,Summary!$AY$5) -> 0 | BB47: =-SUMIFS(Details!$AL$5:$AL$53,Details!$C$5:$C$53,Summary!BB$5,Details!$CK$5:$CK$53,Summary!$AY$5) -> 0 | BC47: =-SUMIFS(Details!$AL$5:$AL$53,Details!$C$5:$C$53,Summary!BC$5,Details!$CK$5:$CK$53,Summary!$AY$5) -> 0 | BD47: =-SUMIFS(Details!$AL$5:$AL$53,Details!$C$5:$C$53,Summary!BD$5,Details!$CK$5:$CK$53,Summary!$AY$5) -> 0 | BE47: =-SUMIFS(Details!$AL$5:$AL$53,Details!$C$5:$C$53,Summary!BE$5,Details!$CK$5:$CK$53,Summary!$AY$5) -> 0 | BF47: =-SUMIFS(Details!$AL$5:$AL$53,Details!$C$5:$C$53,Summary!BF$5,Details!$CK$5:$CK$53,Summary!$AY$5) -> 0 | BG47: =-SUMIFS(Details!$AL$5:$AL$53,Details!$C$5:$C$53,Summary!BG$5,Details!$CK$5:$CK$53,Summary!$AY$5) -> 0 | ... BK47: =-SUMIFS(Details!$AL$5:$AL$53,Details!$C$5:$C$53,Summary!BK$5,Details!$CK$5:$CK$53,Summary!$AY$5) -> 0 | BL47: =SUM(AZ47:BK47) -> 0
C48: No of LMT | D48: 2 | E48: 2 | F48: 0 | G48: 1 | H48: 8 | I48: 0 | J48: 0 | K48: 7 | L48: 0 | M48: 0 | N48: 0 | O48: 0 | P48: =SUM(D48:O48) -> 20 | U48: CN Provision | V48: =-SUMIFS(Details!$BP$5:$BP$53,Details!$C$5:$C$53,Summary!V$5,Details!$CK$5:$CK$53,Summary!$U$5) -> 0 | W48: =-SUMIFS(Details!$BP$5:$BP$53,Details!$C$5:$C$53,Summary!W$5,Details!$CK$5:$CK$53,Summary!$U$5) -> 0 | X48: =-SUMIFS(Details!$BP$5:$BP$53,Details!$C$5:$C$53,Summary!X$5,Details!$CK$5:$CK$53,Summary!$U$5) -> 103735.45 | Y48: =-SUMIFS(Details!$BP$5:$BP$53,Details!$C$5:$C$53,Summary!Y$5,Details!$CK$5:$CK$53,Summary!$U$5) -> 0 | Z48: =-SUMIFS(Details!$BP$5:$BP$53,Details!$C$5:$C$53,Summary!Z$5,Details!$CK$5:$CK$53,Summary!$U$5) -> 0 | AA48: =-SUMIFS(Details!$BP$5:$BP$53,Details!$C$5:$C$53,Summary!AA$5,Details!$CK$5:$CK$53,Summary!$U$5) -> 0 | AB48: =-SUMIFS(Details!$BP$5:$BP$53,Details!$C$5:$C$53,Summary!AB$5,Details!$CK$5:$CK$53,Summary!$U$5) -> 0 | AC48: =-SUMIFS(Details!$BP$5:$BP$53,Details!$C$5:$C$53,Summary!AC$5,Details!$CK$5:$CK$53,Summary!$U$5) -> 0 | ... AG48: =-SUMIFS(Details!$BP$5:$BP$53,Details!$C$5:$C$53,Summary!AG$5,Details!$CK$5:$CK$53,Summary!$U$5) -> 0 | AH48: =SUM(V48:AG48) -> 103735.45 | AJ48: CN Provision | AK48: =-SUMIFS(Details!$BP$5:$BP$53,Details!$C$5:$C$53,Summary!AK$5,Details!$CK$5:$CK$53,Summary!$AJ$5) -> 0 | AL48: =-SUMIFS(Details!$BP$5:$BP$53,Details!$C$5:$C$53,Summary!AL$5,Details!$CK$5:$CK$53,Summary!$AJ$5) -> 0 | AM48: =-SUMIFS(Details!$BP$5:$BP$53,Details!$C$5:$C$53,Summary!AM$5,Details!$CK$5:$CK$53,Summary!$AJ$5) -> 163361.27 | AN48: =-SUMIFS(Details!$BP$5:$BP$53,Details!$C$5:$C$53,Summary!AN$5,Details!$CK$5:$CK$53,Summary!$AJ$5) -> 0 | AO48: =-SUMIFS(Details!$BP$5:$BP$53,Details!$C$5:$C$53,Summary!AO$5,Details!$CK$5:$CK$53,Summary!$AJ$5) -> 0 | AP48: =-SUMIFS(Details!$BP$5:$BP$53,Details!$C$5:$C$53,Summary!AP$5,Details!$CK$5:$CK$53,Summary!$AJ$5) -> 0 | AQ48: =-SUMIFS(Details!$BP$5:$BP$53,Details!$C$5:$C$53,Summary!AQ$5,Details!$CK$5:$CK$53,Summary!$AJ$5) -> 0 | AR48: =-SUMIFS(Details!$BP$5:$BP$53,Details!$C$5:$C$53,Summary!AR$5,Details!$CK$5:$CK$53,Summary!$AJ$5) -> 0 | ... AV48: =-SUMIFS(Details!$BP$5:$BP$53,Details!$C$5:$C$53,Summary!AV$5,Details!$CK$5:$CK$53,Summary!$AJ$5) -> 0 | AW48: =SUM(AK48:AV48) -> 163361.27 | AY48: CN Provision | AZ48: =-SUMIFS(Details!$BP$5:$BP$53,Details!$C$5:$C$53,Summary!AZ$5,Details!$CK$5:$CK$53,Summary!$AY$5) -> 0 | BA48: =-SUMIFS(Details!$BP$5:$BP$53,Details!$C$5:$C$53,Summary!BA$5,Details!$CK$5:$CK$53,Summary!$AY$5) -> 0 | BB48: =-SUMIFS(Details!$BP$5:$BP$53,Details!$C$5:$C$53,Summary!BB$5,Details!$CK$5:$CK$53,Summary!$AY$5) -> 0 | BC48: =-SUMIFS(Details!$BP$5:$BP$53,Details!$C$5:$C$53,Summary!BC$5,Details!$CK$5:$CK$53,Summary!$AY$5) -> 0 | BD48: =-SUMIFS(Details!$BP$5:$BP$53,Details!$C$5:$C$53,Summary!BD$5,Details!$CK$5:$CK$53,Summary!$AY$5) -> 0 | BE48: =-SUMIFS(Details!$BP$5:$BP$53,Details!$C$5:$C$53,Summary!BE$5,Details!$CK$5:$CK$53,Summary!$AY$5) -> 0 | BF48: =-SUMIFS(Details!$BP$5:$BP$53,Details!$C$5:$C$53,Summary!BF$5,Details!$CK$5:$CK$53,Summary!$AY$5) -> 0 | BG48: =-SUMIFS(Details!$BP$5:$BP$53,Details!$C$5:$C$53,Summary!BG$5,Details!$CK$5:$CK$53,Summary!$AY$5) -> 0 | ... BK48: =-SUMIFS(Details!$BP$5:$BP$53,Details!$C$5:$C$53,Summary!BK$5,Details!$CK$5:$CK$53,Summary!$AY$5) -> 0 | BL48: =SUM(AZ48:BK48) -> 0
C49: % of LMT | D49: =IFERROR((D48/D20),0) -> 0.090909091 | E49: =IFERROR((E48/E20),0) -> 0.125 | F49: =IFERROR((F48/F20),0) -> 0 | G49: =IFERROR((G48/G20),0) -> 0 | H49: =IFERROR((H48/H20),0) -> 0 | I49: =IFERROR((I48/I20),0) -> 0 | J49: =IFERROR((J48/J20),0) -> 0 | K49: =IFERROR((K48/K20),0) -> 0 | ... P49: =IFERROR((P48/P20),0) -> 0.42553191
C50: Value of LMT | D50: 16695 | E50: 44749 | F50: 0 | G50: 21436 | H50: 81846 | I50: 0 | J50: 0 | K50: 37763 | L50: 0 | M50: 0 | N50: 0 | O50: 0 | P50: =SUM(D50:O50) -> 202489 | U50: Qty Returned | V50: =V5 -> 46113 | W50: =W5 -> 46143 | X50: =X5 -> 46174 | Y50: =Y5 -> 46204 | Z50: =Z5 -> 46235 | AA50: =AA5 -> 46266 | AB50: =AB5 -> 46296 | AC50: =AC5 -> 46327 | ... AH50: =AH5 -> FY 2026-27 | AJ50: Qty Returned | AK50: =AK5 -> 46113 | AL50: =AL5 -> 46143 | AM50: =AM5 -> 46174 | AN50: =AN5 -> 46204 | AO50: =AO5 -> 46235 | AP50: =AP5 -> 46266 | AQ50: =AQ5 -> 46296 | AR50: =AR5 -> 46327 | ... AW50: =AW5 -> FY 2026-27 | AY50: Qty Returned | AZ50: =AZ5 -> 46113 | BA50: =BA5 -> 46143 | BB50: =BB5 -> 46174 | BC50: =BC5 -> 46204 | BD50: =BD5 -> 46235 | BE50: =BE5 -> 46266 | BF50: =BF5 -> 46296 | BG50: =BG5 -> 46327 | ... BL50: =BL5 -> FY 2026-27
V51: =SUMIFS(Details!$R$5:$R$53,Details!$C$5:$C$53,Summary!V$5,Details!$CK$5:$CK$53,Summary!$U$5)/1000 -> 0 | W51: =SUMIFS(Details!$R$5:$R$53,Details!$C$5:$C$53,Summary!W$5,Details!$CK$5:$CK$53,Summary!$U$5)/1000 -> 0 | X51: =SUMIFS(Details!$R$5:$R$53,Details!$C$5:$C$53,Summary!X$5,Details!$CK$5:$CK$53,Summary!$U$5)/1000 -> 0 | Y51: =SUMIFS(Details!$R$5:$R$53,Details!$C$5:$C$53,Summary!Y$5,Details!$CK$5:$CK$53,Summary!$U$5)/1000 -> 0 | Z51: =SUMIFS(Details!$R$5:$R$53,Details!$C$5:$C$53,Summary!Z$5,Details!$CK$5:$CK$53,Summary!$U$5)/1000 -> 0 | AA51: =SUMIFS(Details!$R$5:$R$53,Details!$C$5:$C$53,Summary!AA$5,Details!$CK$5:$CK$53,Summary!$U$5)/1000 -> 0 | AB51: =SUMIFS(Details!$R$5:$R$53,Details!$C$5:$C$53,Summary!AB$5,Details!$CK$5:$CK$53,Summary!$U$5)/1000 -> 0 | AC51: =SUMIFS(Details!$R$5:$R$53,Details!$C$5:$C$53,Summary!AC$5,Details!$CK$5:$CK$53,Summary!$U$5)/1000 -> 0 | ... AG51: =SUMIFS(Details!$R$5:$R$53,Details!$C$5:$C$53,Summary!AG$5,Details!$CK$5:$CK$53,Summary!$U$5)/1000 -> 0 | AH51: =SUM(V51:AG51) -> 0 | AK51: =SUMIFS(Details!$R$5:$R$53,Details!$C$5:$C$53,Summary!AK$5,Details!$CK$5:$CK$53,Summary!$AJ$5)/1000 -> 17.69 | AL51: =SUMIFS(Details!$R$5:$R$53,Details!$C$5:$C$53,Summary!AL$5,Details!$CK$5:$CK$53,Summary!$AJ$5)/1000 -> 0 | AM51: =SUMIFS(Details!$R$5:$R$53,Details!$C$5:$C$53,Summary!AM$5,Details!$CK$5:$CK$53,Summary!$AJ$5)/1000 -> 27.79 | AN51: =SUMIFS(Details!$R$5:$R$53,Details!$C$5:$C$53,Summary!AN$5,Details!$CK$5:$CK$53,Summary!$AJ$5)/1000 -> 0 | AO51: =SUMIFS(Details!$R$5:$R$53,Details!$C$5:$C$53,Summary!AO$5,Details!$CK$5:$CK$53,Summary!$AJ$5)/1000 -> 0 | AP51: =SUMIFS(Details!$R$5:$R$53,Details!$C$5:$C$53,Summary!AP$5,Details!$CK$5:$CK$53,Summary!$AJ$5)/1000 -> 0 | AQ51: =SUMIFS(Details!$R$5:$R$53,Details!$C$5:$C$53,Summary!AQ$5,Details!$CK$5:$CK$53,Summary!$AJ$5)/1000 -> 0 | AR51: =SUMIFS(Details!$R$5:$R$53,Details!$C$5:$C$53,Summary!AR$5,Details!$CK$5:$CK$53,Summary!$AJ$5)/1000 -> 0 | ... AV51: =SUMIFS(Details!$R$5:$R$53,Details!$C$5:$C$53,Summary!AV$5,Details!$CK$5:$CK$53,Summary!$AJ$5)/1000 -> 0 | AW51: =SUM(AK51:AV51) -> 45.48 | AZ51: =SUMIFS(Details!$R$5:$R$53,Details!$C$5:$C$53,Summary!AZ$5,Details!$CK$5:$CK$53,Summary!$AY$5)/1000 -> 0 | BA51: =SUMIFS(Details!$R$5:$R$53,Details!$C$5:$C$53,Summary!BA$5,Details!$CK$5:$CK$53,Summary!$AY$5)/1000 -> 0 | BB51: =SUMIFS(Details!$R$5:$R$53,Details!$C$5:$C$53,Summary!BB$5,Details!$CK$5:$CK$53,Summary!$AY$5)/1000 -> 0 | BC51: =SUMIFS(Details!$R$5:$R$53,Details!$C$5:$C$53,Summary!BC$5,Details!$CK$5:$CK$53,Summary!$AY$5)/1000 -> 0 | BD51: =SUMIFS(Details!$R$5:$R$53,Details!$C$5:$C$53,Summary!BD$5,Details!$CK$5:$CK$53,Summary!$AY$5)/1000 -> 0 | BE51: =SUMIFS(Details!$R$5:$R$53,Details!$C$5:$C$53,Summary!BE$5,Details!$CK$5:$CK$53,Summary!$AY$5)/1000 -> 0 | BF51: =SUMIFS(Details!$R$5:$R$53,Details!$C$5:$C$53,Summary!BF$5,Details!$CK$5:$CK$53,Summary!$AY$5)/1000 -> 0 | BG51: =SUMIFS(Details!$R$5:$R$53,Details!$C$5:$C$53,Summary!BG$5,Details!$CK$5:$CK$53,Summary!$AY$5)/1000 -> 0 | ... BK51: =SUMIFS(Details!$R$5:$R$53,Details!$C$5:$C$53,Summary!BK$5,Details!$CK$5:$CK$53,Summary!$AY$5)/1000 -> 0 | BL51: =SUM(AZ51:BK51) -> 0
C52: CN & DN Provisions | D52: =D5 -> 46113 | E52: =E5 -> 46143 | F52: =F5 -> 46174 | G52: =G5 -> 46204 | H52: =H5 -> 46235 | I52: =I5 -> 46266 | J52: =J5 -> 46296 | K52: =K5 -> 46327 | ... P52: =P5 -> FY 2026-27 | Q52: =ROUND(Q53-Q54,2)-ROUND(P37-P13,2) -> 0
C53: DN Provision | D53: =-SUMIFS(Details!$AL$5:$AL$53,Details!$C$5:$C$53,Summary!D$5) -> 0 | E53: =-SUMIFS(Details!$AL$5:$AL$53,Details!$C$5:$C$53,Summary!E$5) -> 0 | F53: =-SUMIFS(Details!$AL$5:$AL$53,Details!$C$5:$C$53,Summary!F$5) -> 260358.12 | G53: =-SUMIFS(Details!$AL$5:$AL$53,Details!$C$5:$C$53,Summary!G$5) -> 0 | H53: =-SUMIFS(Details!$AL$5:$AL$53,Details!$C$5:$C$53,Summary!H$5) -> 0 | I53: =-SUMIFS(Details!$AL$5:$AL$53,Details!$C$5:$C$53,Summary!I$5) -> 0 | J53: =-SUMIFS(Details!$AL$5:$AL$53,Details!$C$5:$C$53,Summary!J$5) -> 0 | K53: =-SUMIFS(Details!$AL$5:$AL$53,Details!$C$5:$C$53,Summary!K$5) -> 0 | ... O53: =-SUMIFS(Details!$AL$5:$AL$53,Details!$C$5:$C$53,Summary!O$5) -> 0 | P53: =SUM(D53:O53) -> 260358.12 | Q53: =Details!AL54 -> -260358.12 | U53: Margins | V53: =V5 -> 46113 | W53: =W5 -> 46143 | X53: =X5 -> 46174 | Y53: =Y5 -> 46204 | Z53: =Z5 -> 46235 | AA53: =AA5 -> 46266 | AB53: =AB5 -> 46296 | AC53: =AC5 -> 46327 | ... AH53: =AH5 -> FY 2026-27 | AJ53: Margins | AK53: =AK5 -> 46113 | AL53: =AL5 -> 46143 | AM53: =AM5 -> 46174 | AN53: =AN5 -> 46204 | AO53: =AO5 -> 46235 | AP53: =AP5 -> 46266 | AQ53: =AQ5 -> 46296 | AR53: =AR5 -> 46327 | ... AW53: =AW5 -> FY 2026-27 | AY53: Margins | AZ53: =AZ5 -> 46113 | BA53: =BA5 -> 46143 | BB53: =BB5 -> 46174 | BC53: =BC5 -> 46204 | BD53: =BD5 -> 46235 | BE53: =BE5 -> 46266 | BF53: =BF5 -> 46296 | BG53: =BG5 -> 46327 | ... BL53: =BL5 -> FY 2026-27 | BN53: =(AH47+AW47+BL47)-P53 -> 0
C54: CN Provision | D54: =-SUMIFS(Details!$BP$5:$BP$53,Details!$C$5:$C$53,Summary!D$5) -> 0 | E54: =-SUMIFS(Details!$BP$5:$BP$53,Details!$C$5:$C$53,Summary!E$5) -> 0 | F54: =-SUMIFS(Details!$BP$5:$BP$53,Details!$C$5:$C$53,Summary!F$5) -> 267096.72 | G54: =-SUMIFS(Details!$BP$5:$BP$53,Details!$C$5:$C$53,Summary!G$5) -> 0 | H54: =-SUMIFS(Details!$BP$5:$BP$53,Details!$C$5:$C$53,Summary!H$5) -> 0 | I54: =-SUMIFS(Details!$BP$5:$BP$53,Details!$C$5:$C$53,Summary!I$5) -> 0 | J54: =-SUMIFS(Details!$BP$5:$BP$53,Details!$C$5:$C$53,Summary!J$5) -> 0 | K54: =-SUMIFS(Details!$BP$5:$BP$53,Details!$C$5:$C$53,Summary!K$5) -> 0 | ... O54: =-SUMIFS(Details!$BP$5:$BP$53,Details!$C$5:$C$53,Summary!O$5) -> 0 | P54: =SUM(D54:O54) -> 267096.72 | Q54: =Details!BP54 -> -267096.72 | R54: =Q54+P54 -> 0 | U54: Gross Margin | V54: =SUMIFS(Details!$CN$5:$CN$53,Details!$C$5:$C$53,Summary!V$5,Details!$CK$5:$CK$53,Summary!$U$5) -> 257581.1 | W54: =SUMIFS(Details!$CN$5:$CN$53,Details!$C$5:$C$53,Summary!W$5,Details!$CK$5:$CK$53,Summary!$U$5) -> 243680.25 | X54: =SUMIFS(Details!$CN$5:$CN$53,Details!$C$5:$C$53,Summary!X$5,Details!$CK$5:$CK$53,Summary!$U$5) -> 151243.35 | Y54: =SUMIFS(Details!$CN$5:$CN$53,Details!$C$5:$C$53,Summary!Y$5,Details!$CK$5:$CK$53,Summary!$U$5) -> 0 | Z54: =SUMIFS(Details!$CN$5:$CN$53,Details!$C$5:$C$53,Summary!Z$5,Details!$CK$5:$CK$53,Summary!$U$5) -> 0 | AA54: =SUMIFS(Details!$CN$5:$CN$53,Details!$C$5:$C$53,Summary!AA$5,Details!$CK$5:$CK$53,Summary!$U$5) -> 0 | AB54: =SUMIFS(Details!$CN$5:$CN$53,Details!$C$5:$C$53,Summary!AB$5,Details!$CK$5:$CK$53,Summary!$U$5) -> 0 | AC54: =SUMIFS(Details!$CN$5:$CN$53,Details!$C$5:$C$53,Summary!AC$5,Details!$CK$5:$CK$53,Summary!$U$5) -> 0 | ... AG54: =SUMIFS(Details!$CN$5:$CN$53,Details!$C$5:$C$53,Summary!AG$5,Details!$CK$5:$CK$53,Summary!$U$5) -> 0 | AH54: =SUM(V54:AG54) -> 652504.7 | AJ54: Gross Margin | AK54: =SUMIFS(Details!$CN$5:$CN$53,Details!$C$5:$C$53,Summary!AK$5,Details!$CK$5:$CK$53,Summary!$AJ$5) -> -220742.25 | AL54: =SUMIFS(Details!$CN$5:$CN$53,Details!$C$5:$C$53,Summary!AL$5,Details!$CK$5:$CK$53,Summary!$AJ$5) -> -23025 | AM54: =SUMIFS(Details!$CN$5:$CN$53,Details!$C$5:$C$53,Summary!AM$5,Details!$CK$5:$CK$53,Summary!$AJ$5) -> 51936 | AN54: =SUMIFS(Details!$CN$5:$CN$53,Details!$C$5:$C$53,Summary!AN$5,Details!$CK$5:$CK$53,Summary!$AJ$5) -> 0 | AO54: =SUMIFS(Details!$CN$5:$CN$53,Details!$C$5:$C$53,Summary!AO$5,Details!$CK$5:$CK$53,Summary!$AJ$5) -> 0 | AP54: =SUMIFS(Details!$CN$5:$CN$53,Details!$C$5:$C$53,Summary!AP$5,Details!$CK$5:$CK$53,Summary!$AJ$5) -> 0 | AQ54: =SUMIFS(Details!$CN$5:$CN$53,Details!$C$5:$C$53,Summary!AQ$5,Details!$CK$5:$CK$53,Summary!$AJ$5) -> 0 | AR54: =SUMIFS(Details!$CN$5:$CN$53,Details!$C$5:$C$53,Summary!AR$5,Details!$CK$5:$CK$53,Summary!$AJ$5) -> 0 | ... AV54: =SUMIFS(Details!$CN$5:$CN$53,Details!$C$5:$C$53,Summary!AV$5,Details!$CK$5:$CK$53,Summary!$AJ$5) -> 0 | AW54: =SUM(AK54:AV54) -> -191831.25 | AY54: Gross Margin | AZ54: =SUMIFS(Details!$CN$5:$CN$53,Details!$C$5:$C$53,Summary!AZ$5,Details!$CK$5:$CK$53,Summary!$AY$5) -> 0 | BA54: =SUMIFS(Details!$CN$5:$CN$53,Details!$C$5:$C$53,Summary!BA$5,Details!$CK$5:$CK$53,Summary!$AY$5) -> 0 | BB54: =SUMIFS(Details!$CN$5:$CN$53,Details!$C$5:$C$53,Summary!BB$5,Details!$CK$5:$CK$53,Summary!$AY$5) -> 0 | BC54: =SUMIFS(Details!$CN$5:$CN$53,Details!$C$5:$C$53,Summary!BC$5,Details!$CK$5:$CK$53,Summary!$AY$5) -> 0 | BD54: =SUMIFS(Details!$CN$5:$CN$53,Details!$C$5:$C$53,Summary!BD$5,Details!$CK$5:$CK$53,Summary!$AY$5) -> 0 | BE54: =SUMIFS(Details!$CN$5:$CN$53,Details!$C$5:$C$53,Summary!BE$5,Details!$CK$5:$CK$53,Summary!$AY$5) -> 0 | BF54: =SUMIFS(Details!$CN$5:$CN$53,Details!$C$5:$C$53,Summary!BF$5,Details!$CK$5:$CK$53,Summary!$AY$5) -> 0 | BG54: =SUMIFS(Details!$CN$5:$CN$53,Details!$C$5:$C$53,Summary!BG$5,Details!$CK$5:$CK$53,Summary!$AY$5) -> 0 | ... BK54: =SUMIFS(Details!$CN$5:$CN$53,Details!$C$5:$C$53,Summary!BK$5,Details!$CK$5:$CK$53,Summary!$AY$5) -> 0 | BL54: =SUM(AZ54:BK54) -> 0 | BN54: =(AH48+AW48+BL48)-P54 -> 0
U55: Recykal Margin | V55: =SUMIFS(Details!$CO$5:$CO$53,Details!$C$5:$C$53,Summary!V$5,Details!$CK$5:$CK$53,Summary!$U$5) -> 257581.1 | W55: =SUMIFS(Details!$CO$5:$CO$53,Details!$C$5:$C$53,Summary!W$5,Details!$CK$5:$CK$53,Summary!$U$5) -> 243680.25 | X55: =SUMIFS(Details!$CO$5:$CO$53,Details!$C$5:$C$53,Summary!X$5,Details!$CK$5:$CK$53,Summary!$U$5) -> 151243.35 | Y55: =SUMIFS(Details!$CO$5:$CO$53,Details!$C$5:$C$53,Summary!Y$5,Details!$CK$5:$CK$53,Summary!$U$5) -> 0 | Z55: =SUMIFS(Details!$CO$5:$CO$53,Details!$C$5:$C$53,Summary!Z$5,Details!$CK$5:$CK$53,Summary!$U$5) -> 0 | AA55: =SUMIFS(Details!$CO$5:$CO$53,Details!$C$5:$C$53,Summary!AA$5,Details!$CK$5:$CK$53,Summary!$U$5) -> 0 | AB55: =SUMIFS(Details!$CO$5:$CO$53,Details!$C$5:$C$53,Summary!AB$5,Details!$CK$5:$CK$53,Summary!$U$5) -> 0 | AC55: =SUMIFS(Details!$CO$5:$CO$53,Details!$C$5:$C$53,Summary!AC$5,Details!$CK$5:$CK$53,Summary!$U$5) -> 0 | ... AG55: =SUMIFS(Details!$CO$5:$CO$53,Details!$C$5:$C$53,Summary!AG$5,Details!$CK$5:$CK$53,Summary!$U$5) -> 0 | AH55: =SUM(V55:AG55) -> 652504.7 | AJ55: Recykal Margin | AK55: =SUMIFS(Details!$CO$5:$CO$53,Details!$C$5:$C$53,Summary!AK$5,Details!$CK$5:$CK$53,Summary!$AJ$5) -> -220742.25 | AL55: =SUMIFS(Details!$CO$5:$CO$53,Details!$C$5:$C$53,Summary!AL$5,Details!$CK$5:$CK$53,Summary!$AJ$5) -> -23025 | AM55: =SUMIFS(Details!$CO$5:$CO$53,Details!$C$5:$C$53,Summary!AM$5,Details!$CK$5:$CK$53,Summary!$AJ$5) -> 51936 | AN55: =SUMIFS(Details!$CO$5:$CO$53,Details!$C$5:$C$53,Summary!AN$5,Details!$CK$5:$CK$53,Summary!$AJ$5) -> 0 | AO55: =SUMIFS(Details!$CO$5:$CO$53,Details!$C$5:$C$53,Summary!AO$5,Details!$CK$5:$CK$53,Summary!$AJ$5) -> 0 | AP55: =SUMIFS(Details!$CO$5:$CO$53,Details!$C$5:$C$53,Summary!AP$5,Details!$CK$5:$CK$53,Summary!$AJ$5) -> 0 | AQ55: =SUMIFS(Details!$CO$5:$CO$53,Details!$C$5:$C$53,Summary!AQ$5,Details!$CK$5:$CK$53,Summary!$AJ$5) -> 0 | AR55: =SUMIFS(Details!$CO$5:$CO$53,Details!$C$5:$C$53,Summary!AR$5,Details!$CK$5:$CK$53,Summary!$AJ$5) -> 0 | ... AV55: =SUMIFS(Details!$CO$5:$CO$53,Details!$C$5:$C$53,Summary!AV$5,Details!$CK$5:$CK$53,Summary!$AJ$5) -> 0 | AW55: =SUM(AK55:AV55) -> -191831.25 | AY55: Recykal Margin | AZ55: =SUMIFS(Details!$CO$5:$CO$53,Details!$C$5:$C$53,Summary!AZ$5,Details!$CK$5:$CK$53,Summary!$AY$5) -> 0 | BA55: =SUMIFS(Details!$CO$5:$CO$53,Details!$C$5:$C$53,Summary!BA$5,Details!$CK$5:$CK$53,Summary!$AY$5) -> 0 | BB55: =SUMIFS(Details!$CO$5:$CO$53,Details!$C$5:$C$53,Summary!BB$5,Details!$CK$5:$CK$53,Summary!$AY$5) -> 0 | BC55: =SUMIFS(Details!$CO$5:$CO$53,Details!$C$5:$C$53,Summary!BC$5,Details!$CK$5:$CK$53,Summary!$AY$5) -> 0 | BD55: =SUMIFS(Details!$CO$5:$CO$53,Details!$C$5:$C$53,Summary!BD$5,Details!$CK$5:$CK$53,Summary!$AY$5) -> 0 | BE55: =SUMIFS(Details!$CO$5:$CO$53,Details!$C$5:$C$53,Summary!BE$5,Details!$CK$5:$CK$53,Summary!$AY$5) -> 0 | BF55: =SUMIFS(Details!$CO$5:$CO$53,Details!$C$5:$C$53,Summary!BF$5,Details!$CK$5:$CK$53,Summary!$AY$5) -> 0 | BG55: =SUMIFS(Details!$CO$5:$CO$53,Details!$C$5:$C$53,Summary!BG$5,Details!$CK$5:$CK$53,Summary!$AY$5) -> 0 | ... BK55: =SUMIFS(Details!$CO$5:$CO$53,Details!$C$5:$C$53,Summary!BK$5,Details!$CK$5:$CK$53,Summary!$AY$5) -> 0 | BL55: =SUM(AZ55:BK55) -> 0
C56: Qty Returned | D56: =D5 -> 46113 | E56: =E5 -> 46143 | F56: =F5 -> 46174 | G56: =G5 -> 46204 | H56: =H5 -> 46235 | I56: =I5 -> 46266 | J56: =J5 -> 46296 | K56: =K5 -> 46327 | ... P56: =P5 -> FY 2026-27 | U56: Net Margin | V56: =SUMIFS(Details!$CP$5:$CP$53,Details!$C$5:$C$53,Summary!V$5,Details!$CK$5:$CK$53,Summary!$U$5) -> 257581.1 | W56: =SUMIFS(Details!$CP$5:$CP$53,Details!$C$5:$C$53,Summary!W$5,Details!$CK$5:$CK$53,Summary!$U$5) -> 243421.5 | X56: =SUMIFS(Details!$CP$5:$CP$53,Details!$C$5:$C$53,Summary!X$5,Details!$CK$5:$CK$53,Summary!$U$5) -> 148131.29 | Y56: =SUMIFS(Details!$CP$5:$CP$53,Details!$C$5:$C$53,Summary!Y$5,Details!$CK$5:$CK$53,Summary!$U$5) -> 0 | Z56: =SUMIFS(Details!$CP$5:$CP$53,Details!$C$5:$C$53,Summary!Z$5,Details!$CK$5:$CK$53,Summary!$U$5) -> 0 | AA56: =SUMIFS(Details!$CP$5:$CP$53,Details!$C$5:$C$53,Summary!AA$5,Details!$CK$5:$CK$53,Summary!$U$5) -> 0 | AB56: =SUMIFS(Details!$CP$5:$CP$53,Details!$C$5:$C$53,Summary!AB$5,Details!$CK$5:$CK$53,Summary!$U$5) -> 0 | AC56: =SUMIFS(Details!$CP$5:$CP$53,Details!$C$5:$C$53,Summary!AC$5,Details!$CK$5:$CK$53,Summary!$U$5) -> 0 | ... AG56: =SUMIFS(Details!$CP$5:$CP$53,Details!$C$5:$C$53,Summary!AG$5,Details!$CK$5:$CK$53,Summary!$U$5) -> 0 | AH56: =SUM(V56:AG56) -> 649133.89 | AJ56: Net Margin | AK56: =SUMIFS(Details!$CP$5:$CP$53,Details!$C$5:$C$53,Summary!AK$5,Details!$CK$5:$CK$53,Summary!$AJ$5) -> 9125.5903 | AL56: =SUMIFS(Details!$CP$5:$CP$53,Details!$C$5:$C$53,Summary!AL$5,Details!$CK$5:$CK$53,Summary!$AJ$5) -> 62848.221 | AM56: =SUMIFS(Details!$CP$5:$CP$53,Details!$C$5:$C$53,Summary!AM$5,Details!$CK$5:$CK$53,Summary!$AJ$5) -> 76077.468 | AN56: =SUMIFS(Details!$CP$5:$CP$53,Details!$C$5:$C$53,Summary!AN$5,Details!$CK$5:$CK$53,Summary!$AJ$5) -> 0 | AO56: =SUMIFS(Details!$CP$5:$CP$53,Details!$C$5:$C$53,Summary!AO$5,Details!$CK$5:$CK$53,Summary!$AJ$5) -> 0 | AP56: =SUMIFS(Details!$CP$5:$CP$53,Details!$C$5:$C$53,Summary!AP$5,Details!$CK$5:$CK$53,Summary!$AJ$5) -> 0 | AQ56: =SUMIFS(Details!$CP$5:$CP$53,Details!$C$5:$C$53,Summary!AQ$5,Details!$CK$5:$CK$53,Summary!$AJ$5) -> 0 | AR56: =SUMIFS(Details!$CP$5:$CP$53,Details!$C$5:$C$53,Summary!AR$5,Details!$CK$5:$CK$53,Summary!$AJ$5) -> 0 | ... AV56: =SUMIFS(Details!$CP$5:$CP$53,Details!$C$5:$C$53,Summary!AV$5,Details!$CK$5:$CK$53,Summary!$AJ$5) -> 0 | AW56: =SUM(AK56:AV56) -> 148051.28 | AY56: Net Margin | AZ56: =SUMIFS(Details!$CP$5:$CP$53,Details!$C$5:$C$53,Summary!AZ$5,Details!$CK$5:$CK$53,Summary!$AY$5) -> 0 | BA56: =SUMIFS(Details!$CP$5:$CP$53,Details!$C$5:$C$53,Summary!BA$5,Details!$CK$5:$CK$53,Summary!$AY$5) -> 0 | BB56: =SUMIFS(Details!$CP$5:$CP$53,Details!$C$5:$C$53,Summary!BB$5,Details!$CK$5:$CK$53,Summary!$AY$5) -> 0 | BC56: =SUMIFS(Details!$CP$5:$CP$53,Details!$C$5:$C$53,Summary!BC$5,Details!$CK$5:$CK$53,Summary!$AY$5) -> 0 | BD56: =SUMIFS(Details!$CP$5:$CP$53,Details!$C$5:$C$53,Summary!BD$5,Details!$CK$5:$CK$53,Summary!$AY$5) -> 0 | BE56: =SUMIFS(Details!$CP$5:$CP$53,Details!$C$5:$C$53,Summary!BE$5,Details!$CK$5:$CK$53,Summary!$AY$5) -> 0 | BF56: =SUMIFS(Details!$CP$5:$CP$53,Details!$C$5:$C$53,Summary!BF$5,Details!$CK$5:$CK$53,Summary!$AY$5) -> 0 | BG56: =SUMIFS(Details!$CP$5:$CP$53,Details!$C$5:$C$53,Summary!BG$5,Details!$CK$5:$CK$53,Summary!$AY$5) -> 0 | ... BK56: =SUMIFS(Details!$CP$5:$CP$53,Details!$C$5:$C$53,Summary!BK$5,Details!$CK$5:$CK$53,Summary!$AY$5) -> 0 | BL56: =SUM(AZ56:BK56) -> 0
D57: =SUMIFS(Details!$R$5:$R$53,Details!$C$5:$C$53,Summary!D$5)/1000 -> 17.69 | E57: =SUMIFS(Details!$R$5:$R$53,Details!$C$5:$C$53,Summary!E$5)/1000 -> 0 | F57: =SUMIFS(Details!$R$5:$R$53,Details!$C$5:$C$53,Summary!F$5)/1000 -> 27.79 | G57: =SUMIFS(Details!$R$5:$R$53,Details!$C$5:$C$53,Summary!G$5)/1000 -> 0 | H57: =SUMIFS(Details!$R$5:$R$53,Details!$C$5:$C$53,Summary!H$5)/1000 -> 0 | I57: =SUMIFS(Details!$R$5:$R$53,Details!$C$5:$C$53,Summary!I$5)/1000 -> 0 | J57: =SUMIFS(Details!$R$5:$R$53,Details!$C$5:$C$53,Summary!J$5)/1000 -> 0 | K57: =SUMIFS(Details!$R$5:$R$53,Details!$C$5:$C$53,Summary!K$5)/1000 -> 0 | ... O57: =SUMIFS(Details!$R$5:$R$53,Details!$C$5:$C$53,Summary!O$5)/1000 -> 0 | P57: =SUM(D57:O57) -> 45.48 | BN57: =(AH51+AW51+BL51)-P57 -> 0
C59: Margins | D59: =D5 -> 46113 | E59: =E5 -> 46143 | F59: =F5 -> 46174 | G59: =G5 -> 46204 | H59: =H5 -> 46235 | I59: =I5 -> 46266 | J59: =J5 -> 46296 | K59: =K5 -> 46327 | ... P59: =P5 -> FY 2026-27
C60: Gross Margin | D60: =SUMIFS(Details!$CN$5:$CN$53,Details!$C$5:$C$53,Summary!D$5) -> 36838.85 | E60: =SUMIFS(Details!$CN$5:$CN$53,Details!$C$5:$C$53,Summary!E$5) -> 220655.25 | F60: =SUMIFS(Details!$CN$5:$CN$53,Details!$C$5:$C$53,Summary!F$5) -> 203179.35 | G60: =SUMIFS(Details!$CN$5:$CN$53,Details!$C$5:$C$53,Summary!G$5) -> 0 | H60: =SUMIFS(Details!$CN$5:$CN$53,Details!$C$5:$C$53,Summary!H$5) -> 0 | I60: =SUMIFS(Details!$CN$5:$CN$53,Details!$C$5:$C$53,Summary!I$5) -> 0 | J60: =SUMIFS(Details!$CN$5:$CN$53,Details!$C$5:$C$53,Summary!J$5) -> 0 | K60: =SUMIFS(Details!$CN$5:$CN$53,Details!$C$5:$C$53,Summary!K$5) -> 0 | ... O60: =SUMIFS(Details!$CN$5:$CN$53,Details!$C$5:$C$53,Summary!O$5) -> 0 | P60: =SUM(D60:O60) -> 460673.45
C61: Recykal Margin | D61: =SUMIFS(Details!$CO$5:$CO$53,Details!$C$5:$C$53,Summary!D$5) -> 36838.85 | E61: =SUMIFS(Details!$CO$5:$CO$53,Details!$C$5:$C$53,Summary!E$5) -> 220655.25 | F61: =SUMIFS(Details!$CO$5:$CO$53,Details!$C$5:$C$53,Summary!F$5) -> 203179.35 | G61: =SUMIFS(Details!$CO$5:$CO$53,Details!$C$5:$C$53,Summary!G$5) -> 0 | H61: =SUMIFS(Details!$CO$5:$CO$53,Details!$C$5:$C$53,Summary!H$5) -> 0 | I61: =SUMIFS(Details!$CO$5:$CO$53,Details!$C$5:$C$53,Summary!I$5) -> 0 | J61: =SUMIFS(Details!$CO$5:$CO$53,Details!$C$5:$C$53,Summary!J$5) -> 0 | K61: =SUMIFS(Details!$CO$5:$CO$53,Details!$C$5:$C$53,Summary!K$5) -> 0 | ... O61: =SUMIFS(Details!$CO$5:$CO$53,Details!$C$5:$C$53,Summary!O$5) -> 0 | P61: =SUM(D61:O61) -> 460673.45
C62: Net Margin | D62: =SUMIFS(Details!$CP$5:$CP$53,Details!$C$5:$C$53,Summary!D$5) -> 266706.69 | E62: =SUMIFS(Details!$CP$5:$CP$53,Details!$C$5:$C$53,Summary!E$5) -> 306269.73 | F62: =SUMIFS(Details!$CP$5:$CP$53,Details!$C$5:$C$53,Summary!F$5) -> 224208.75 | G62: =SUMIFS(Details!$CP$5:$CP$53,Details!$C$5:$C$53,Summary!G$5) -> 0 | H62: =SUMIFS(Details!$CP$5:$CP$53,Details!$C$5:$C$53,Summary!H$5) -> 0 | I62: =SUMIFS(Details!$CP$5:$CP$53,Details!$C$5:$C$53,Summary!I$5) -> 0 | J62: =SUMIFS(Details!$CP$5:$CP$53,Details!$C$5:$C$53,Summary!J$5) -> 0 | K62: =SUMIFS(Details!$CP$5:$CP$53,Details!$C$5:$C$53,Summary!K$5) -> 0 | ... O62: =SUMIFS(Details!$CP$5:$CP$53,Details!$C$5:$C$53,Summary!O$5) -> 0 | P62: =SUM(D62:O62) -> 797185.17
C64: Financial with GST | D64: Sales | E64: Purchases
C65: =Details!P64 -> 46194 | D65: =SUMIFS(Details!$BQ$5:$BQ$53,Details!$D$5:$D$53,Summary!$C65)*118% -> 0 | E65: =SUMIFS(Details!$AM$5:$AM$53,Details!$D$5:$D$53,Summary!$C65)*118% -> 0
C66: =TEXT(C65,"mmm-yy") -> Jun-26 | D66: =SUMIFS(Details!$BQ$5:$BQ$53,Details!$C$5:$C$53,Summary!$C66)*118% -> 9863874.6 | E66: =SUMIFS(Details!$AM$5:$AM$53,Details!$C$5:$C$53,Summary!$C66)*118% -> 9599308.3
C67: Fy 2025-26 | D67: =Details!BQ54*118% -> 43802188 | E67: =Details!AM54*118% -> 42861510

Sheet Details
AA1: 0
B3: Raw Data -METAL | F3: Purchase Details | U3: Logistic Details of the transaction | AF3: Debit Notes to Suppliers | AM3: Sales Details | BD3: DN to Customer | BH3: Credit Notes from Customers | BO3: -0.0455 | BU3: To be checked | BX3: CN & DN Checks | CH3: Without Provisions | CM3: Margin Buckets | CP3: Financials with GST
B4: Quarter | C4: Month | D4: Date | E4: Shipment ID | F4: Supplier Name | G4: GST Reg No. | H4: Vendor Invoice No. | I4: Vendor Invoice Date | J4: P V No. | K4: P V Date | L4: State (Origin) | M4: Vehicle No. | N4: Material | O4: Qty (Kg) | P4: Price/Kg | Q4: Purchase Price | R4: Return Qty | S4: Net Qty | T4: Basic Customs Duty | U4: Transporter Name | V4: LR NO/BILL NO | W4: J V No. | X4: JV Date | Y4: Logistics cost | Z4: Debit note on logistic cost | AA4: Logistics Provision | AB4: Total Logistics Cost | AC4: Operational Cost | AD4: Cost/Kg. | AE4: Divertion/Internal | AF4: Debit Note No. | AG4: Debit Note Date. | AH4: Debit Note No. 2 | AI4: Debit Note Date. 2 | AJ4: Full Debit Note | AK4: Actual Debit Note | AL4: Provision for DN | AM4: Total Cost | AN4: Inv. Date | AO4: Inv. No. | AP4: Customer ID | AQ4: Buyer Name | AR4: Buyer GST Number | AS4: Location (Origin) | AT4: Location (Destination) | AU4: State (Destination) | AV4: E-WayBill Number | AW4: Qty(Kg) | AX4: Rate/Kg | AY4: Amount | AZ4: Qty Check | BA4: Return Qty | BB4: Net Qty | BC4: Divertion/Internal | BD4: Return Type | BE4: Date : DN to Buyer | BF4: DN to Buyer | BG4: Amount | BH4: Credit Note No:1 | BI4: CN Date. No:1 | BJ4: Credit Note No:2 | BK4: CN Date. No:2 | BL4: Cash Discount(Provision) | BM4: Cash Discount | BN4: Full Credit Notes | BO4: Actual Credit Note | BP4: Provision for CN | BQ4: Net Revenue | BR4: Margin | BS4: Reamrks - Margin | BT4: Remarks | BU4: LMI @ Inception | BV4: Remarks @ Inception | BW4: Margin (%) | BX4: Margin Bucket | BY4: Total CN(Inc.Provisions) | BZ4: Total DN(Inc.Provisions) | CA4: Check | CB4: Actaul CN | CC4: Actual DN | CD4: Check | CE4: Material-Short Form | CF4: Supplier Type | CG4: Month | CH4: Cost | CI4: Revenue | CJ4: Week No: | CK4: Category (Material) | CL4: Broad Category | CM4: Customer POC Name | CN4: Gross Margin | CO4: Recykal Margin | CP4: Net Margin | CQ4: Sales | CR4: Purchases | CS4: Credit Note | CT4: Debit Note | CU4: Margin | CV4: Bill Branch | CW4: Inv Branch | CX4: Vendor PAN No | CY4: Customer PAN No | CZ4: GST TDS Applicability | DA4: Cash Discount. No | DB4: CD Date | DC4: Cash Discount. No.2 | DD4: CD Date.2 | DE4: Total DN | DF4: Total CN
B5: ="Q" & IF(ROUNDUP(MONTH(D5)/3,0)-1=0,4,ROUNDUP(MONTH(D5)/3,0)-1) -> Q1 | C5: =TEXT(AN5,"mmm-yy") -> Apr-26 | D5: 46113 | E5: SH04260101 | F5: NISHA TRADING COMPANY | G5: 27CFUPK7292B1ZZ | H5: 1372 | I5: 46113 | J5: 25-26/PUR/026853 | K5: 46113 | L5: MH | M5: MH48DQ1304 | N5: Boring & Turning | O5: 10870 | P5: 30.9 | Q5: =O5*P5 -> 335883 | R5: 0 | S5: =O5-R5 -> 10870 | T5: 0 | U5: 0 | V5: 0 | W5: 0 | X5: 0 | Y5: 0 | Z5: 0 | AA5: 0 | AB5: =Y5+AA5+Z5 -> 0 | AC5: 0 | AD5: 0 | AE5: 0 | AF5: 36/MET/27VC00006 | AG5: 46114 | AH5: 36/MET/27VC00080 | AI5: 46146 | AJ5: 0 | AK5: =-3074.55-2174 -> -5248.55 | AL5: 0 | AM5: =Q5+AB5+AL5+AK5+AJ5+T5+AE5 -> 330634.45 | AN5: 46113 | AO5: 36/MET/27IN00001 | AP5: 832139000044272012 | AQ5: ARCELORMITTAL NIPPON STEEL INDIA PRIVATE LIMITED | AR5: 27AAACE1741P1ZH | AS5: Vasai Maharashtra 401208 | AT5: Raighadh | AU5: Maharashtra | AV5: 152388999660 | AW5: 10870 | AX5: 31.5 | AY5: =AW5*AX5 -> 342405 | AZ5: =AW5=O5 -> TRUE | BA5: 0 | BB5: =AW5-BA5 -> 10870 | BC5: 0 | BD5: Regular | BE5: 0 | BF5: 0 | BG5: 0 | BH5: 36/MET/27CN00006 | BI5: 46114 | BJ5: 36/MET/27CN00092 | BK5: 46146 | BL5: =-IF(AR5="21AABCJ1969M1ZF",(AY5*2%),0) -> 0 | BM5: 0 | BN5: 0 | BO5: =-3134-2174 -> -5308 | BP5: 0 | BQ5: =AY5+BN5+BO5+BP5+BC5+BG5+BM5+BL5 -> 337097 | BR5: =BQ5-AM5 -> 6462.55 | BS5: =IF(BR5>=0,"Positive Margin","Negative Margin") -> Positive Margin | BT5: DN & CN Issued | BU5: =AY5-Y5-Q5-AA5-T5+BC5 -> 6522 | BV5: =IF(BU5<0, "Negative Margin at Inception", "Positive Margin at Inception") -> Positive Margin at Inception | BW5: =IFERROR(BR5/BQ5,"0") -> 0.019171188 | BX5: =IF(BW5<1%,"Less Than 1%",IF(BW5>2%,"More than 2%",IF(BW5>=1%,"1% - 2%"))) -> 1% - 2% | BY5: =BO5+BP5 -> -5308 | BZ5: =AL5+AK5 -> -5248.55 | CA5: =BY5-BZ5 -> -59.45 | CB5: =BO5 -> -5308 | CC5: =AK5 -> -5248.55 | CD5: =CB5-CC5 -> -59.45 | CE5: Marketplace (Metal Waste) | CF5: =_xlfn.XLOOKUP(G5,'Supplier Metrics'!C:C,'Supplier Metrics'!H:H) -> Trader With Warehouse | CG5: =TEXT(AN5,"mmm-yy") -> Apr-26 | CH5: =AM5-AL5 -> 330634.45 | CI5: =BQ5-BP5 -> 337097 | CJ5: =INT((D5- IF(MONTH(D5) >= 4, DATE(YEAR(D5), 4, 1), DATE(YEAR(D5)-1, 4, 1))) / 7) + 1 -> 1 | CK5: {=_xlfn.XLOOKUP(N5,'Material Metrics'!B:B,'Material Metrics'!C:D)} -> Ferrous | CL5: Ferrous | CM5: =_xlfn.XLOOKUP(AR5,Receivables!B:B,Receivables!D:D) -> Gaurav Uttam Kothimeere | CN5: =AY5-Q5 -> 6522 | CO5: =CN5-AB5 -> 6522 | CP5: =BQ5-AM5 -> 6462.55 | CQ5: =AY5*118% -> 404037.9 | CR5: =Q5*118% -> 396341.94 | CS5: =CB5*118% -> -6263.44 | CT5: =CC5*118% -> -6193.289 | CU5: =(CQ5-CS5)-(CR5-CT5) -> 7766.111 | CV5: Telangana - HO | CW5: Telangana - HO | CX5: =MID(G5,3,10) -> CFUPK7292B | CY5: =MID(AR5,3,10) -> AAACE1741P | CZ5: No | DA5: 0 | DB5: 0 | DC5: 0 | DD5: 0 | DE5: =AE5+AJ5+AK5 -> -5248.55 | DF5: =BN5+BO5+BC5 -> -5308
B6: ="Q" & IF(ROUNDUP(MONTH(D6)/3,0)-1=0,4,ROUNDUP(MONTH(D6)/3,0)-1) -> Q1 | C6: =TEXT(AN6,"mmm-yy") -> Apr-26 | D6: 46113 | E6: SH04260102 | F6: NISHA TRADING COMPANY | G6: 27CFUPK7292B1ZZ | H6: 1373 | I6: 46113 | J6: 25-26/PUR/026854 | K6: 46113 | L6: MH | M6: MH48AG5755 | N6: Boring & Turning | O6: 11020 | P6: 30.9 | Q6: =O6*P6 -> 340518 | R6: 0 | S6: =O6-R6 -> 11020 | T6: 0 | U6: 0 | V6: 0 | W6: 0 | X6: 0 | Y6: 0 | Z6: 0 | AA6: 0 | AB6: =Y6+AA6+Z6 -> 0 | AC6: 0 | AD6: 0 | AE6: 0 | AF6: 36/MET/27VC00007 | AG6: 46114 | AH6: 36/MET/27VC00003 | AI6: 46114 | AJ6: 0 | AK6: =-2472-3332 -> -5804 | AL6: 0 | AM6: =Q6+AB6+AL6+AK6+AJ6+T6+AE6 -> 334714 | AN6: 46113 | AO6: 36/MET/27IN00002 | AP6: 832139000044272012 | AQ6: ARCELORMITTAL NIPPON STEEL INDIA PRIVATE LIMITED | AR6: 27AAACE1741P1ZH | AS6: Vasai Maharashtra 401208 | AT6: Raighadh | AU6: Maharashtra | AV6: 162389000852 | AW6: 11020 | AX6: 31.5 | AY6: =AW6*AX6 -> 347130 | AZ6: =AW6=O6 -> TRUE | BA6: 0 | BB6: =AW6-BA6 -> 11020 | BC6: 0 | BD6: Regular | BE6: 0 | BF6: 0 | BG6: 0 | BH6: 36/MET/27CN00003 | BI6: 46114 | BJ6: 36/MET/27CN00007 | BK6: 46114 | BL6: =-IF(AR6="21AABCJ1969M1ZF",(AY6*2%),0) -> 0 | BM6: 0 | BN6: 0 | BO6: =-3396-2520 -> -5916 | BP6: 0 | BQ6: =AY6+BN6+BO6+BP6+BC6+BG6+BM6+BL6 -> 341214 | BR6: =BQ6-AM6 -> 6500 | BS6: =IF(BR6>=0,"Positive Margin","Negative Margin") -> Positive Margin | BT6: DN & CN Issued | BU6: =AY6-Y6-Q6-AA6-T6+BC6 -> 6612 | BV6: =IF(BU6<0, "Negative Margin at Inception", "Positive Margin at Inception") -> Positive Margin at Inception | BW6: =IFERROR(BR6/BQ6,"0") -> 0.019049629 | BX6: =IF(BW6<1%,"Less Than 1%",IF(BW6>2%,"More than 2%",IF(BW6>=1%,"1% - 2%"))) -> 1% - 2% | BY6: =BO6+BP6 -> -5916 | BZ6: =AL6+AK6 -> -5804 | CA6: =BY6-BZ6 -> -112 | CB6: =BO6 -> -5916 | CC6: =AK6 -> -5804 | CD6: =CB6-CC6 -> -112 | CE6: Marketplace (Metal Waste) | CF6: =_xlfn.XLOOKUP(G6,'Supplier Metrics'!C:C,'Supplier Metrics'!H:H) -> Trader With Warehouse | CG6: =TEXT(AN6,"mmm-yy") -> Apr-26 | CH6: =AM6-AL6 -> 334714 | CI6: =BQ6-BP6 -> 341214 | CJ6: =INT((D6- IF(MONTH(D6) >= 4, DATE(YEAR(D6), 4, 1), DATE(YEAR(D6)-1, 4, 1))) / 7) + 1 -> 1 | CK6: {=_xlfn.XLOOKUP(N6,'Material Metrics'!B:B,'Material Metrics'!C:D)} -> Ferrous | CL6: Ferrous | CM6: =_xlfn.XLOOKUP(AR6,Receivables!B:B,Receivables!D:D) -> Gaurav Uttam Kothimeere | CN6: =AY6-Q6 -> 6612 | CO6: =CN6-AB6 -> 6612 | CP6: =BQ6-AM6 -> 6500 | CQ6: =AY6*118% -> 409613.4 | CR6: =Q6*118% -> 401811.24 | CS6: =CB6*118% -> -6980.88 | CT6: =CC6*118% -> -6848.72 | CU6: =(CQ6-CS6)-(CR6-CT6) -> 7934.32 | CV6: Telangana - HO | CW6: Telangana - HO | CX6: =MID(G6,3,10) -> CFUPK7292B | CY6: =MID(AR6,3,10) -> AAACE1741P | CZ6: No | DA6: 0 | DB6: 0 | DC6: 0 | DD6: 0 | DE6: =AE6+AJ6+AK6 -> -5804 | DF6: =BN6+BO6+BC6 -> -5916
B7: ="Q" & IF(ROUNDUP(MONTH(D7)/3,0)-1=0,4,ROUNDUP(MONTH(D7)/3,0)-1) -> Q1 | C7: =TEXT(AN7,"mmm-yy") -> Apr-26 | D7: 46121 | E7: SH04260903 | F7: BMS ENTERPRISES | G7: 07AIXPR2550B1Z3 | H7: 45 | I7: 46121 | J7: 26-27/PUR/000303 | K7: 46121 | L7: DL | M7: DL01MA6901 | N7: Aluminium Wire Scrap | O7: 6505 | P7: 313.14 | Q7: =O7*P7 -> 2036975.7 | R7: 0 | S7: =O7-R7 -> 6505 | T7: 0 | U7: 0 | V7: 0 | W7: 0 | X7: 0 | Y7: 0 | Z7: 0 | AA7: 0 | AB7: =Y7+AA7+Z7 -> 0 | AC7: 0 | AD7: 0 | AE7: 0 | AF7: 0 | AG7: 0 | AH7: 0 | AI7: 0 | AJ7: 0 | AK7: 0 | AL7: 0 | AM7: =Q7+AB7+AL7+AK7+AJ7+T7+AE7 -> 2036975.7 | AN7: 46121 | AO7: 36/MET/27IN00003 | AP7: 832139000042107085 | AQ7: NOIDA ALUMINIUM COMPANY PRIVATE LIMITED | AR7: 09AAACN0064G1ZR | AS7: NORTH EAST DELHI,Delhi,110094 | AT7: Noida | AU7: Uttar Pradesh | AW7: 6505 | AX7: 322 | AY7: =AW7*AX7 -> 2094610 | AZ7: =AW7=O7 -> TRUE | BA7: 0 | BB7: =AW7-BA7 -> 6505 | BC7: 0 | BD7: Regular | BE7: 0 | BF7: 0 | BG7: 0 | BH7: 0 | BI7: 0 | BJ7: 0 | BK7: 0 | BL7: 0 | BM7: 0 | BN7: 0 | BO7: 0 | BP7: 0 | BQ7: =AY7+BN7+BO7+BP7+BC7+BG7+BM7+BL7 -> 2094610 | BR7: =BQ7-AM7 -> 57634.3 | BS7: =IF(BR7>=0,"Positive Margin","Negative Margin") -> Positive Margin | BT7: No Debit Note | BU7: =AY7-Y7-Q7-AA7-T7+BC7 -> 57634.3 | BV7: =IF(BU7<0, "Negative Margin at Inception", "Positive Margin at Inception") -> Positive Margin at Inception | BW7: =IFERROR(BR7/BQ7,"0") -> 0.027515528 | BX7: =IF(BW7<1%,"Less Than 1%",IF(BW7>2%,"More than 2%",IF(BW7>=1%,"1% - 2%"))) -> More than 2% | BY7: =BO7+BP7 -> 0 | BZ7: =AL7+AK7 -> 0 | CA7: =BY7-BZ7 -> 0 | CB7: =BO7 -> 0 | CC7: =AK7 -> 0 | CD7: =CB7-CC7 -> 0 | CE7: Marketplace (Metal Waste) | CF7: =_xlfn.XLOOKUP(G7,'Supplier Metrics'!C:C,'Supplier Metrics'!H:H) -> Processor | CG7: =TEXT(AN7,"mmm-yy") -> Apr-26 | CH7: =AM7-AL7 -> 2036975.7 | CI7: =BQ7-BP7 -> 2094610 | CJ7: =INT((D7- IF(MONTH(D7) >= 4, DATE(YEAR(D7), 4, 1), DATE(YEAR(D7)-1, 4, 1))) / 7) + 1 -> 2 | CK7: {=_xlfn.XLOOKUP(N7,'Material Metrics'!B:B,'Material Metrics'!C:D)} -> Non-Ferrous | CL7: Aluminium | CM7: =_xlfn.XLOOKUP(AR7,Receivables!B:B,Receivables!D:D) -> Daulat Biyani | CN7: =AY7-Q7 -> 57634.3 | CO7: =CN7-AB7 -> 57634.3 | CP7: =BQ7-AM7 -> 57634.3 | CQ7: =AY7*118% -> 2471639.8 | CR7: =Q7*118% -> 2403631.3 | CS7: =CB7*118% -> 0 | CT7: =CC7*118% -> 0 | CU7: =(CQ7-CS7)-(CR7-CT7) -> 68008.474 | CV7: Telangana - HO | CW7: Telangana - HO | CX7: =MID(G7,3,10) -> AIXPR2550B | CY7: =MID(AR7,3,10) -> AAACN0064G | CZ7: No | DA7: 0 | DB7: 0 | DC7: 0 | DD7: 0 | DE7: =AE7+AJ7+AK7 -> 0 | DF7: =BN7+BO7+BC7 -> 0
B8: ="Q" & IF(ROUNDUP(MONTH(D8)/3,0)-1=0,4,ROUNDUP(MONTH(D8)/3,0)-1) -> Q1 | C8: =TEXT(AN8,"mmm-yy") -> Apr-26 | D8: 46126 | E8: SH04261401 | F8: NAWABI METALS | G8: 27AOBPK6586N1Z9 | H8: NM/26-27/019 | I8: 46126 | J8: 26-27/PUR/000514 | K8: 46126 | L8: MH | M8: MH04EL6835 | N8: HR_END_CUT | O8: 18650 | P8: 35.4 | Q8: =O8*P8 -> 660210 | R8: 0 | S8: =O8-R8 -> 18650 | T8: 0 | U8: 0 | V8: 0 | W8: 0 | X8: 0 | Y8: 0 | Z8: 0 | AA8: 0 | AB8: =Y8+AA8+Z8 -> 0 | AC8: 0 | AD8: 0 | AE8: 0 | AF8: 36/MET/27VC00050 | AG8: 46132 | AH8: 36/MET/27VC00059 | AI8: 46139 | AJ8: 0 | AK8: =-32318-26012 -> -58330 | AL8: 0 | AM8: =Q8+AB8+AL8+AK8+AJ8+T8+AE8 -> 601880 | AN8: 46126 | AO8: 36/MET/27IN00007 | AP8: 832139000032849620 | AQ8: JSW STEEL LIMITED (27) | AR8: 27AAACJ4323N1ZG | AS8: Thane Maharashtra 400612 | AT8: Raigad | AU8: Maharashtra | AV8: 132400728368 | AW8: 18650 | AX8: 34 | AY8: =AW8*AX8 -> 634100 | AZ8: =AW8=O8 -> TRUE | BA8: 0 | BB8: =AW8-BA8 -> 18650 | BC8: 0 | BD8: Regular | BE8: 0 | BF8: 0 | BG8: 0 | BH8: 36/MET/27CN00069 | BI8: 46132 | BJ8: 0 | BK8: 0 | BL8: 0 | BM8: 0 | BN8: 0 | BO8: -32220 | BP8: 0 | BQ8: =AY8+BN8+BO8+BP8+BC8+BG8+BM8+BL8 -> 601880 | BR8: =BQ8-AM8 -> 0 | BS8: =IF(BR8>=0,"Positive Margin","Negative Margin") -> Positive Margin | BT8: DN & CN Issued | BU8: =AY8-Y8-Q8-AA8-T8+BC8 -> -26110 | BV8: =IF(BU8<0, "Negative Margin at Inception", "Positive Margin at Inception") -> Negative Margin at Inception | BW8: =IFERROR(BR8/BQ8,"0") -> 0 | BX8: =IF(BW8<1%,"Less Than 1%",IF(BW8>2%,"More than 2%",IF(BW8>=1%,"1% - 2%"))) -> Less Than 1% | BY8: =BO8+BP8 -> -32220 | BZ8: =AL8+AK8 -> -58330 | CA8: =BY8-BZ8 -> 26110 | CB8: =BO8 -> -32220 | CC8: =AK8 -> -58330 | CD8: =CB8-CC8 -> 26110 | CE8: Marketplace (Metal Waste) | CF8: =_xlfn.XLOOKUP(G8,'Supplier Metrics'!C:C,'Supplier Metrics'!H:H) -> Trader With Warehouse | CG8: =TEXT(AN8,"mmm-yy") -> Apr-26 | CH8: =AM8-AL8 -> 601880 | CI8: =BQ8-BP8 -> 601880 | CJ8: =INT((D8- IF(MONTH(D8) >= 4, DATE(YEAR(D8), 4, 1), DATE(YEAR(D8)-1, 4, 1))) / 7) + 1 -> 2 | CK8: {=_xlfn.XLOOKUP(N8,'Material Metrics'!B:B,'Material Metrics'!C:D)} -> Ferrous | CL8: Ferrous | CM8: =_xlfn.XLOOKUP(AR8,Receivables!B:B,Receivables!D:D) -> Shadab | CN8: =AY8-Q8 -> -26110 | CO8: =CN8-AB8 -> -26110 | CP8: =BQ8-AM8 -> 0 | CQ8: =AY8*118% -> 748238 | CR8: =Q8*118% -> 779047.8 | CS8: =CB8*118% -> -38019.6 | CT8: =CC8*118% -> -68829.4 | CU8: =(CQ8-CS8)-(CR8-CT8) -> -61619.6 | CV8: Telangana - HO | CW8: Telangana - HO | CX8: =MID(G8,3,10) -> AOBPK6586N | CY8: =MID(AR8,3,10) -> AAACJ4323N | CZ8: No | DA8: 0 | DB8: 0 | DC8: 0 | DD8: 0 | DE8: =AE8+AJ8+AK8 -> -58330 | DF8: =BN8+BO8+BC8 -> -32220
B9: ="Q" & IF(ROUNDUP(MONTH(D9)/3,0)-1=0,4,ROUNDUP(MONTH(D9)/3,0)-1) -> Q1 | C9: =TEXT(AN9,"mmm-yy") -> Apr-26 | D9: 46126 | E9: SH04261402 | F9: NAWABI METALS | G9: 27AOBPK6586N1Z9 | H9: NM/26-27/021 | I9: 46126 | J9: 26-27/PUR/000513 | K9: 46126 | L9: MH | M9: MH04FP2663 | N9: HR_END_CUT | O9: 18110 | P9: 35.4 | Q9: =O9*P9 -> 641094 | R9: 0 | S9: =O9-R9 -> 18110 | T9: 0 | U9: 0 | V9: 0 | W9: 0 | X9: 0 | Y9: 0 | Z9: 0 | AA9: 0 | AB9: =Y9+AA9+Z9 -> 0 | AC9: 0 | AD9: 0 | AE9: 0 | AF9: 36/MET/27VC00037 | AG9: 46128 | AH9: 36/MET/27VC00048 & 00060 | AI9: 46132 | AJ9: 0 | AK9: =-3894-3622-20700 -> -28216 | AL9: 0 | AM9: =Q9+AB9+AL9+AK9+AJ9+T9+AE9 -> 612878 | AN9: 46126 | AO9: 36/MET/27IN00005 | AP9: 832139000032849620 | AQ9: JSW STEEL LIMITED (27) | AR9: 27AAACJ4323N1ZG | AS9: Thane Maharashtra 400612 | AT9: raigad | AU9: Maharashtra | AV9: 182400743027 | AW9: 18110 | AX9: 34.25 | AY9: =AW9*AX9 -> 620267.5 | AZ9: =AW9=O9 -> TRUE | BA9: 0 | BB9: =AW9-BA9 -> 18110 | BC9: 0 | BD9: Regular | BE9: 0 | BF9: 0 | BG9: 0 | BH9: 36/MET/27CN00063 | BI9: 46128 | BJ9: 36/MET/27CN00067 | BK9: 46132 | BL9: 0 | BM9: 0 | BN9: 0 | BO9: =-3767.5-3622 -> -7389.5 | BP9: 0 | BQ9: =AY9+BN9+BO9+BP9+BC9+BG9+BM9+BL9 -> 612878 | BR9: =BQ9-AM9 -> 0 | BS9: =IF(BR9>=0,"Positive Margin","Negative Margin") -> Positive Margin | BT9: DN & CN Issued | BU9: =AY9-Y9-Q9-AA9-T9+BC9 -> -20826.5 | BV9: =IF(BU9<0, "Negative Margin at Inception", "Positive Margin at Inception") -> Negative Margin at Inception | BW9: =IFERROR(BR9/BQ9,"0") -> 0 | BX9: =IF(BW9<1%,"Less Than 1%",IF(BW9>2%,"More than 2%",IF(BW9>=1%,"1% - 2%"))) -> Less Than 1% | BY9: =BO9+BP9 -> -7389.5 | BZ9: =AL9+AK9 -> -28216 | CA9: =BY9-BZ9 -> 20826.5 | CB9: =BO9 -> -7389.5 | CC9: =AK9 -> -28216 | CD9: =CB9-CC9 -> 20826.5 | CE9: Marketplace (Metal Waste) | CF9: =_xlfn.XLOOKUP(G9,'Supplier Metrics'!C:C,'Supplier Metrics'!H:H) -> Trader With Warehouse | CG9: =TEXT(AN9,"mmm-yy") -> Apr-26 | CH9: =AM9-AL9 -> 612878 | CI9: =BQ9-BP9 -> 612878 | CJ9: =INT((D9- IF(MONTH(D9) >= 4, DATE(YEAR(D9), 4, 1), DATE(YEAR(D9)-1, 4, 1))) / 7) + 1 -> 2 | CK9: {=_xlfn.XLOOKUP(N9,'Material Metrics'!B:B,'Material Metrics'!C:D)} -> Ferrous | CL9: Ferrous | CM9: =_xlfn.XLOOKUP(AR9,Receivables!B:B,Receivables!D:D) -> Shadab | CN9: =AY9-Q9 -> -20826.5 | CO9: =CN9-AB9 -> -20826.5 | CP9: =BQ9-AM9 -> 0 | CQ9: =AY9*118% -> 731915.65 | CR9: =Q9*118% -> 756490.92 | CS9: =CB9*118% -> -8719.61 | CT9: =CC9*118% -> -33294.88 | CU9: =(CQ9-CS9)-(CR9-CT9) -> -49150.54 | CV9: Telangana - HO | CW9: Telangana - HO | CX9: =MID(G9,3,10) -> AOBPK6586N | CY9: =MID(AR9,3,10) -> AAACJ4323N | CZ9: No | DA9: 0 | DB9: 0 | DC9: 0 | DD9: 0 | DE9: =AE9+AJ9+AK9 -> -28216 | DF9: =BN9+BO9+BC9 -> -7389.5
B10: ="Q" & IF(ROUNDUP(MONTH(D10)/3,0)-1=0,4,ROUNDUP(MONTH(D10)/3,0)-1) -> Q1 | C10: =TEXT(AN10,"mmm-yy") -> Apr-26 | D10: 46126 | E10: SH04261403 | F10: NAWABI METALS | G10: 27AOBPK6586N1Z9 | H10: NM/26-27/020 | I10: 46126 | J10: 26-27/PUR/000511 | K10: 46126 | L10: MH | M10: MH46F4348 | N10: HR_END_CUT | O10: 20110 | P10: 35.4 | Q10: =O10*P10 -> 711894 | R10: 0 | S10: =O10-R10 -> 20110 | T10: 0 | U10: 0 | V10: 0 | W10: 0 | X10: 0 | Y10: 0 | Z10: 0 | AA10: 0 | AB10: =Y10+AA10+Z10 -> 0 | AC10: 0 | AD10: 0 | AE10: 0 | AF10: 36/MET/27VC00049 | AG10: 46132 | AH10: 36/MET/27VC00061 | AI10: 46139 | AJ10: 0 | AK10: =-43406-23023 -> -66429 | AL10: 0 | AM10: =Q10+AB10+AL10+AK10+AJ10+T10+AE10 -> 645465 | AN10: 46126 | AO10: 36/MET/27IN00004 | AP10: 832139000032849620 | AQ10: JSW STEEL LIMITED (27) | AR10: 27AAACJ4323N1ZG | AS10: Thane Maharashtra 400612 | AT10: Raigad | AU10: Maharashtra | AV10: 182400716876 | AW10: 20110 | AX10: 34.25 | AY10: =AW10*AX10 -> 688767.5 | AZ10: =AW10=O10 -> TRUE | BA10: 0 | BB10: =AW10-BA10 -> 20110 | BC10: 0 | BD10: Regular | BE10: 0 | BF10: 0 | BG10: 0 | BH10: 36/MET/27CN00068 | BI10: 46132 | BJ10: 0 | BK10: 0 | BL10: 0 | BM10: 0 | BN10: 0 | BO10: -43302.5 | BP10: 0 | BQ10: =AY10+BN10+BO10+BP10+BC10+BG10+BM10+BL10 -> 645465 | BR10: =BQ10-AM10 -> 0 | BS10: =IF(BR10>=0,"Positive Margin","Negative Margin") -> Positive Margin | BT10: DN & CN Issued | BU10: =AY10-Y10-Q10-AA10-T10+BC10 -> -23126.5 | BV10: =IF(BU10<0, "Negative Margin at Inception", "Positive Margin at Inception") -> Negative Margin at Inception | BW10: =IFERROR(BR10/BQ10,"0") -> 0 | BX10: =IF(BW10<1%,"Less Than 1%",IF(BW10>2%,"More than 2%",IF(BW10>=1%,"1% - 2%"))) -> Less Than 1% | BY10: =BO10+BP10 -> -43302.5 | BZ10: =AL10+AK10 -> -66429 | CA10: =BY10-BZ10 -> 23126.5 | CB10: =BO10 -> -43302.5 | CC10: =AK10 -> -66429 | CD10: =CB10-CC10 -> 23126.5 | CE10: Marketplace (Metal Waste) | CF10: =_xlfn.XLOOKUP(G10,'Supplier Metrics'!C:C,'Supplier Metrics'!H:H) -> Trader With Warehouse | CG10: =TEXT(AN10,"mmm-yy") -> Apr-26 | CH10: =AM10-AL10 -> 645465 | CI10: =BQ10-BP10 -> 645465 | CJ10: =INT((D10- IF(MONTH(D10) >= 4, DATE(YEAR(D10), 4, 1), DATE(YEAR(D10)-1, 4, 1))) / 7) + 1 -> 2 | CK10: {=_xlfn.XLOOKUP(N10,'Material Metrics'!B:B,'Material Metrics'!C:D)} -> Ferrous | CL10: Ferrous | CM10: =_xlfn.XLOOKUP(AR10,Receivables!B:B,Receivables!D:D) -> Shadab | CN10: =AY10-Q10 -> -23126.5 | CO10: =CN10-AB10 -> -23126.5 | CP10: =BQ10-AM10 -> 0 | CQ10: =AY10*118% -> 812745.65 | CR10: =Q10*118% -> 840034.92 | CS10: =CB10*118% -> -51096.95 | CT10: =CC10*118% -> -78386.22 | CU10: =(CQ10-CS10)-(CR10-CT10) -> -54578.54 | CV10: Telangana - HO | CW10: Telangana - HO | CX10: =MID(G10,3,10) -> AOBPK6586N | CY10: =MID(AR10,3,10) -> AAACJ4323N | CZ10: No | DA10: 0 | DB10: 0 | DC10: 0 | DD10: 0 | DE10: =AE10+AJ10+AK10 -> -66429 | DF10: =BN10+BO10+BC10 -> -43302.5
B11: ="Q" & IF(ROUNDUP(MONTH(D11)/3,0)-1=0,4,ROUNDUP(MONTH(D11)/3,0)-1) -> Q1 | C11: =TEXT(AN11,"mmm-yy") -> Apr-26 | D11: 46126 | E11: SH04261404 | F11: NAWABI METALS | G11: 27AOBPK6586N1Z9 | H11: NM/26-27/022 | I11: 46126 | J11: 26-27/PUR/000512 | K11: 46126 | L11: MH | M11: MH04FU3620 | N11: HR_END_CUT | O11: 17280 | P11: 35.4 | Q11: =O11*P11 -> 611712 | R11: 0 | S11: =O11-R11 -> 17280 | T11: 0 | U11: 0 | V11: 0 | W11: 0 | X11: 0 | Y11: 0 | Z11: 0 | AA11: 0 | AB11: =Y11+AA11+Z11 -> 0 | AC11: 0 | AD11: 0 | AE11: 0 | AF11: 36/MET/27VC00051 | AG11: 46132 | AH11: 36/MET/27VC00062 | AI11: 46139 | AJ11: 0 | AK11: =-15126-19746 -> -34872 | AL11: 0 | AM11: =Q11+AB11+AL11+AK11+AJ11+T11+AE11 -> 576840 | AN11: 46126 | AO11: 36/MET/27IN00006 | AP11: 832139000032849620 | AQ11: JSW STEEL LIMITED (27) | AR11: 27AAACJ4323N1ZG | AS11: Thane Maharashtra 400612 | AT11: Raigad | AU11: Maharashtra | AV11: 192400710574 | AW11: 17280 | AX11: 34 | AY11: =AW11*AX11 -> 587520 | AZ11: =AW11=O11 -> TRUE | BA11: 0 | BB11: =AW11-BA11 -> 17280 | BC11: 0 | BD11: Regular | BE11: 0 | BF11: 0 | BG11: 0 | BH11: 36/MET/27CN00070 | BI11: 46132 | BJ11: 0 | BK11: 0 | BL11: 0 | BM11: 0 | BN11: 0 | BO11: -14972 | BP11: 0 | BQ11: =AY11+BN11+BO11+BP11+BC11+BG11+BM11+BL11 -> 572548 | BR11: =BQ11-AM11 -> -4292 | BS11: =IF(BR11>=0,"Positive Margin","Negative Margin") -> Negative Margin | BT11: DN & CN Issued | BU11: =AY11-Y11-Q11-AA11-T11+BC11 -> -24192 | BV11: =IF(BU11<0, "Negative Margin at Inception", "Positive Margin at Inception") -> Negative Margin at Inception | BW11: =IFERROR(BR11/BQ11,"0") -> -0.0074963147 | BX11: =IF(BW11<1%,"Less Than 1%",IF(BW11>2%,"More than 2%",IF(BW11>=1%,"1% - 2%"))) -> Less Than 1% | BY11: =BO11+BP11 -> -14972 | BZ11: =AL11+AK11 -> -34872 | CA11: =BY11-BZ11 -> 19900 | CB11: =BO11 -> -14972 | CC11: =AK11 -> -34872 | CD11: =CB11-CC11 -> 19900 | CE11: Marketplace (Metal Waste) | CF11: =_xlfn.XLOOKUP(G11,'Supplier Metrics'!C:C,'Supplier Metrics'!H:H) -> Trader With Warehouse | CG11: =TEXT(AN11,"mmm-yy") -> Apr-26 | CH11: =AM11-AL11 -> 576840 | CI11: =BQ11-BP11 -> 572548 | CJ11: =INT((D11- IF(MONTH(D11) >= 4, DATE(YEAR(D11), 4, 1), DATE(YEAR(D11)-1, 4, 1))) / 7) + 1 -> 2 | CK11: {=_xlfn.XLOOKUP(N11,'Material Metrics'!B:B,'Material Metrics'!C:D)} -> Ferrous | CL11: Ferrous | CM11: =_xlfn.XLOOKUP(AR11,Receivables!B:B,Receivables!D:D) -> Shadab | CN11: =AY11-Q11 -> -24192 | CO11: =CN11-AB11 -> -24192 | CP11: =BQ11-AM11 -> -4292 | CQ11: =AY11*118% -> 693273.6 | CR11: =Q11*118% -> 721820.16 | CS11: =CB11*118% -> -17666.96 | CT11: =CC11*118% -> -41148.96 | CU11: =(CQ11-CS11)-(CR11-CT11) -> -52028.56 | CV11: Telangana - HO | CW11: Telangana - HO | CX11: =MID(G11,3,10) -> AOBPK6586N | CY11: =MID(AR11,3,10) -> AAACJ4323N | CZ11: No | DA11: 0 | DB11: 0 | DC11: 0 | DD11: 0 | DE11: =AE11+AJ11+AK11 -> -34872 | DF11: =BN11+BO11+BC11 -> -14972
B12: ="Q" & IF(ROUNDUP(MONTH(D12)/3,0)-1=0,4,ROUNDUP(MONTH(D12)/3,0)-1) -> Q1 | C12: =TEXT(AN12,"mmm-yy") -> Apr-26 | D12: 46128 | E12: SH04261506 | F12: BMS ENTERPRISES | G12: 07AIXPR2550B1Z3 | H12: 47 | I12: 46128 | J12: 26-27/PUR/000794 | K12: 46129 | L12: DL | M12: DL01MA8616 | N12: Aluminium Wire Scrap | O12: 5850 | P12: 317.98 | Q12: =O12*P12 -> 1860183 | R12: 0 | S12: =O12-R12 -> 5850 | T12: 0 | U12: 0 | V12: 0 | W12: 0 | X12: 0 | Y12: 0 | Z12: 0 | AA12: 0 | AB12: =Y12+AA12+Z12 -> 0 | AC12: 0 | AD12: 0 | AE12: 0 | AF12: 0 | AG12: 0 | AH12: 0 | AI12: 0 | AJ12: 0 | AK12: 0 | AL12: 0 | AM12: =Q12+AB12+AL12+AK12+AJ12+T12+AE12 -> 1860183 | AN12: 46129 | AO12: 36/MET/27IN00010 | AP12: 832139000042107085 | AQ12: NOIDA ALUMINIUM COMPANY PRIVATE LIMITED | AR12: 09AAACN0064G1ZR | AS12: NORTH EAST DELHI, Delhi 110094 | AT12: Noida | AU12: Uttar Pradesh | AW12: 5850 | AX12: 328 | AY12: =AW12*AX12 -> 1918800 | AZ12: =AW12=O12 -> TRUE | BA12: 0 | BB12: =AW12-BA12 -> 5850 | BC12: 0 | BD12: Regular | BE12: 0 | BF12: 0 | BG12: 0 | BH12: 0 | BI12: 0 | BJ12: 0 | BK12: 0 | BL12: 0 | BM12: 0 | BN12: 0 | BO12: 0 | BP12: 0 | BQ12: =AY12+BN12+BO12+BP12+BC12+BG12+BM12+BL12 -> 1918800 | BR12: =BQ12-AM12 -> 58617 | BS12: =IF(BR12>=0,"Positive Margin","Negative Margin") -> Positive Margin | BT12: No Debit Note | BU12: =AY12-Y12-Q12-AA12-T12+BC12 -> 58617 | BV12: =IF(BU12<0, "Negative Margin at Inception", "Positive Margin at Inception") -> Positive Margin at Inception | BW12: =IFERROR(BR12/BQ12,"0") -> 0.03054878 | BX12: =IF(BW12<1%,"Less Than 1%",IF(BW12>2%,"More than 2%",IF(BW12>=1%,"1% - 2%"))) -> More than 2% | BY12: =BO12+BP12 -> 0 | BZ12: =AL12+AK12 -> 0 | CA12: =BY12-BZ12 -> 0 | CB12: =BO12 -> 0 | CC12: =AK12 -> 0 | CD12: =CB12-CC12 -> 0 | CE12: Marketplace (Metal Waste) | CF12: =_xlfn.XLOOKUP(G12,'Supplier Metrics'!C:C,'Supplier Metrics'!H:H) -> Processor | CG12: =TEXT(AN12,"mmm-yy") -> Apr-26 | CH12: =AM12-AL12 -> 1860183 | CI12: =BQ12-BP12 -> 1918800 | CJ12: =INT((D12- IF(MONTH(D12) >= 4, DATE(YEAR(D12), 4, 1), DATE(YEAR(D12)-1, 4, 1))) / 7) + 1 -> 3 | CK12: {=_xlfn.XLOOKUP(N12,'Material Metrics'!B:B,'Material Metrics'!C:D)} -> Non-Ferrous | CL12: Aluminium | CM12: =_xlfn.XLOOKUP(AR12,Receivables!B:B,Receivables!D:D) -> Daulat Biyani | CN12: =AY12-Q12 -> 58617 | CO12: =CN12-AB12 -> 58617 | CP12: =BQ12-AM12 -> 58617 | CQ12: =AY12*118% -> 2264184 | CR12: =Q12*118% -> 2195015.9 | CS12: =CB12*118% -> 0 | CT12: =CC12*118% -> 0 | CU12: =(CQ12-CS12)-(CR12-CT12) -> 69168.06 | CV12: Telangana - HO | CW12: Telangana - HO | CX12: =MID(G12,3,10) -> AIXPR2550B | CY12: =MID(AR12,3,10) -> AAACN0064G | CZ12: No | DA12: 0 | DB12: 0 | DC12: 0 | DD12: 0 | DE12: =AE12+AJ12+AK12 -> 0 | DF12: =BN12+BO12+BC12 -> 0
B13: ="Q" & IF(ROUNDUP(MONTH(D13)/3,0)-1=0,4,ROUNDUP(MONTH(D13)/3,0)-1) -> Q1 | C13: =TEXT(AN13,"mmm-yy") -> Apr-26 | D13: 46129 | E13: SH04261606 | F13: NAWABI METALS | G13: 27AOBPK6586N1Z9 | H13: NM/26-27/029 | I13: 46129 | J13: 26-27/PUR/000782 | K13: 46129 | L13: MH | M13: MH12RN9572 | N13: DISMANTLED PnS | O13: 24980 | P13: 34.4 | Q13: =O13*P13 -> 859312 | R13: 0 | S13: =O13-R13 -> 24980 | T13: 0 | U13: 0 | V13: 0 | W13: 0 | X13: 0 | Y13: 0 | Z13: 0 | AA13: 0 | AB13: =Y13+AA13+Z13 -> 0 | AC13: 0 | AD13: 0 | AE13: 0 | AF13: 36/MET/27VC00057 | AG13: 46139 | AH13: 36/MET/27VC00063 | AI13: 46139 | AJ13: 0 | AK13: =-1720-28670 -> -30390 | AL13: 0 | AM13: =Q13+AB13+AL13+AK13+AJ13+T13+AE13 -> 828922 | AN13: 46129 | AO13: 36/MET/27IN00009 | AP13: 832139000032849620 | AQ13: JSW STEEL LIMITED (27) | AR13: 27AAACJ4323N1ZG | AS13: Raighadh,Maharashtra,410203 | AT13: Raigad | AU13: Maharashtra | AV13: 152403223006 | AW13: 24980 | AX13: 33.25 | AY13: =AW13*AX13 -> 830585 | AZ13: =AW13=O13 -> TRUE | BA13: 0 | BB13: =AW13-BA13 -> 24980 | BC13: 0 | BD13: Regular | BE13: 0 | BF13: 0 | BG13: 0 | BH13: 36/MET/27CN00076 | BI13: 46139 | BJ13: 0 | BK13: 0 | BL13: 0 | BM13: 0 | BN13: 0 | BO13: -1662.5 | BP13: 0 | BQ13: =AY13+BN13+BO13+BP13+BC13+BG13+BM13+BL13 -> 828922.5 | BR13: =BQ13-AM13 -> 0.5 | BS13: =IF(BR13>=0,"Positive Margin","Negative Margin") -> Positive Margin | BT13: DN & CN Issued | BU13: =AY13-Y13-Q13-AA13-T13+BC13 -> -28727 | BV13: =IF(BU13<0, "Negative Margin at Inception", "Positive Margin at Inception") -> Negative Margin at Inception | BW13: =IFERROR(BR13/BQ13,"0") -> 6.031927e-07 | BX13: =IF(BW13<1%,"Less Than 1%",IF(BW13>2%,"More than 2%",IF(BW13>=1%,"1% - 2%"))) -> Less Than 1% | BY13: =BO13+BP13 -> -1662.5 | BZ13: =AL13+AK13 -> -30390 | CA13: =BY13-BZ13 -> 28727.5 | CB13: =BO13 -> -1662.5 | CC13: =AK13 -> -30390 | CD13: =CB13-CC13 -> 28727.5 | CE13: Marketplace (Metal Waste) | CF13: =_xlfn.XLOOKUP(G13,'Supplier Metrics'!C:C,'Supplier Metrics'!H:H) -> Trader With Warehouse | CG13: =TEXT(AN13,"mmm-yy") -> Apr-26 | CH13: =AM13-AL13 -> 828922 | CI13: =BQ13-BP13 -> 828922.5 | CJ13: =INT((D13- IF(MONTH(D13) >= 4, DATE(YEAR(D13), 4, 1), DATE(YEAR(D13)-1, 4, 1))) / 7) + 1 -> 3 | CK13: {=_xlfn.XLOOKUP(N13,'Material Metrics'!B:B,'Material Metrics'!C:D)} -> Ferrous | CL13: Ferrous | CM13: =_xlfn.XLOOKUP(AR13,Receivables!B:B,Receivables!D:D) -> Shadab | CN13: =AY13-Q13 -> -28727 | CO13: =CN13-AB13 -> -28727 | CP13: =BQ13-AM13 -> 0.5 | CQ13: =AY13*118% -> 980090.3 | CR13: =Q13*118% -> 1013988.2 | CS13: =CB13*118% -> -1961.75 | CT13: =CC13*118% -> -35860.2 | CU13: =(CQ13-CS13)-(CR13-CT13) -> -67796.31 | CV13: Telangana - HO | CW13: Telangana - HO | CX13: =MID(G13,3,10) -> AOBPK6586N | CY13: =MID(AR13,3,10) -> AAACJ4323N | CZ13: No | DA13: 0 | DB13: 0 | DC13: 0 | DD13: 0 | DE13: =AE13+AJ13+AK13 -> -30390 | DF13: =BN13+BO13+BC13 -> -1662.5
B14: ="Q" & IF(ROUNDUP(MONTH(D14)/3,0)-1=0,4,ROUNDUP(MONTH(D14)/3,0)-1) -> Q1 | C14: =TEXT(AN14,"mmm-yy") -> Apr-26 | D14: 46130 | E14: SH04261801 | F14: NAWABI METALS | G14: 27AOBPK6586N1Z9 | H14: NM/26-27/031 | I14: 46130 | J14: 26-27/PUR/000924 | K14: 46130 | L14: MH | M14: MH04EL1887 | N14: HR_END_CUT | O14: 17690 | P14: 35.4 | Q14: =O14*P14 -> 626226 | R14: 17690 | S14: =O14-R14 -> 0 | T14: 0 | U14: 0 | V14: 0 | W14: 0 | X14: 0 | Y14: 0 | Z14: 0 | AA14: 0 | AB14: =Y14+AA14+Z14 -> 0 | AC14: 0 | AD14: 0 | AE14: 0 | AF14: 36/MET/27VC00052 | AG14: 46133 | AH14: 0 | AI14: 0 | AJ14: -626226 | AK14: 0 | AL14: 0 | AM14: =Q14+AB14+AL14+AK14+AJ14+T14+AE14 -> 0 | AN14: 46130 | AO14: 36/MET/27IN00011 | AP14: 832139000032849620 | AQ14: JSW STEEL LIMITED (27) | AR14: 27AAACJ4323N1ZG | AS14: Thane,Maharashtra,400612 | AT14: Raigad | AU14: Maharashtra | AV14: 112404499026 | AW14: 17690 | AX14: 34.25 | AY14: =AW14*AX14 -> 605882.5 | AZ14: =AW14=O14 -> TRUE | BA14: 17690 | BB14: =AW14-BA14 -> 0 | BC14: 0 | BD14: Regular | BE14: 0 | BF14: 0 | BG14: 0 | BH14: 36/MET/27CN00071 | BI14: 46133 | BJ14: 0 | BK14: 0 | BL14: 0 | BM14: 0 | BN14: -605882.5 | BO14: 0 | BP14: 0 | BQ14: =AY14+BN14+BO14+BP14+BC14+BG14+BM14+BL14 -> 0 | BR14: =BQ14-AM14 -> 0 | BS14: =IF(BR14>=0,"Positive Margin","Negative Margin") -> Positive Margin | BT14: Full Rejection | BU14: =AY14-Y14-Q14-AA14-T14+BC14 -> -20343.5 | BV14: =IF(BU14<0, "Negative Margin at Inception", "Positive Margin at Inception") -> Negative Margin at Inception | BW14: =IFERROR(BR14/BQ14,"0") -> 0 | BX14: =IF(BW14<1%,"Less Than 1%",IF(BW14>2%,"More than 2%",IF(BW14>=1%,"1% - 2%"))) -> More than 2% | BY14: =BO14+BP14 -> 0 | BZ14: =AL14+AK14 -> 0 | CA14: =BY14-BZ14 -> 0 | CB14: =BO14 -> 0 | CC14: =AK14 -> 0 | CD14: =CB14-CC14 -> 0 | CE14: Marketplace (Metal Waste) | CF14: =_xlfn.XLOOKUP(G14,'Supplier Metrics'!C:C,'Supplier Metrics'!H:H) -> Trader With Warehouse | CG14: =TEXT(AN14,"mmm-yy") -> Apr-26 | CH14: =AM14-AL14 -> 0 | CI14: =BQ14-BP14 -> 0 | CJ14: =INT((D14- IF(MONTH(D14) >= 4, DATE(YEAR(D14), 4, 1), DATE(YEAR(D14)-1, 4, 1))) / 7) + 1 -> 3 | CK14: {=_xlfn.XLOOKUP(N14,'Material Metrics'!B:B,'Material Metrics'!C:D)} -> Ferrous | CL14: Ferrous | CM14: =_xlfn.XLOOKUP(AR14,Receivables!B:B,Receivables!D:D) -> Shadab | CN14: =AY14-Q14 -> -20343.5 | CO14: =CN14-AB14 -> -20343.5 | CP14: =BQ14-AM14 -> 0 | CQ14: =AY14*118% -> 714941.35 | CR14: =Q14*118% -> 738946.68 | CS14: =CB14*118% -> 0 | CT14: =CC14*118% -> 0 | CU14: =(CQ14-CS14)-(CR14-CT14) -> -24005.33 | CV14: Telangana - HO | CW14: Telangana - HO | CX14: =MID(G14,3,10) -> AOBPK6586N | CY14: =MID(AR14,3,10) -> AAACJ4323N | CZ14: No | DA14: 0 | DB14: 0 | DC14: 0 | DD14: 0 | DE14: =AE14+AJ14+AK14 -> -626226 | DF14: =BN14+BO14+BC14 -> -605882.5
B15: ="Q" & IF(ROUNDUP(MONTH(D15)/3,0)-1=0,4,ROUNDUP(MONTH(D15)/3,0)-1) -> Q1 | C15: =TEXT(AN15,"mmm-yy") -> Apr-26 | D15: 46130 | E15: SH04261807 | F15: NAWABI METALS | G15: 27AOBPK6586N1Z9 | H15: NM/26-27/032 | I15: 46130 | J15: 26-27/PUR/000940 | K15: 46131 | L15: MH | M15: MH14DM6131 | N15: DISMANTLED PnS | O15: 24530 | P15: 34.4 | Q15: =O15*P15 -> 843832 | R15: 0 | S15: =O15-R15 -> 24530 | T15: 0 | U15: 0 | V15: 0 | W15: 0 | X15: 0 | Y15: 0 | Z15: 0 | AA15: 0 | AB15: =Y15+AA15+Z15 -> 0 | AC15: 0 | AD15: 0 | AE15: 0 | AF15: 36/MET/27VC00064 | AG15: 46139 | AH15: 0 | AI15: 0 | AJ15: 0 | AK15: -28210 | AL15: 0 | AM15: =Q15+AB15+AL15+AK15+AJ15+T15+AE15 -> 815622 | AN15: 46131 | AO15: 36/MET/27IN00012 | AP15: 832139000032849620 | AQ15: JSW STEEL LIMITED (27) | AR15: 27AAACJ4323N1ZG | AS15: Pune Maharashtra 411048 | AT15: Raigad | AU15: Maharashtra | AV15: 172405156285 | AW15: 24530 | AX15: 33.25 | AY15: =AW15*AX15 -> 815622.5 | AZ15: =AW15=O15 -> TRUE | BA15: 0 | BB15: =AW15-BA15 -> 24530 | BC15: 0 | BD15: Regular | BE15: 0 | BF15: 0 | BG15: 0 | BH15: 0 | BI15: 0 | BJ15: 0 | BK15: 0 | BL15: 0 | BM15: 0 | BN15: 0 | BO15: 0 | BP15: 0 | BQ15: =AY15+BN15+BO15+BP15+BC15+BG15+BM15+BL15 -> 815622.5 | BR15: =BQ15-AM15 -> 0.5 | BS15: =IF(BR15>=0,"Positive Margin","Negative Margin") -> Positive Margin | BT15: No Debit Note | BU15: =AY15-Y15-Q15-AA15-T15+BC15 -> -28209.5 | BV15: =IF(BU15<0, "Negative Margin at Inception", "Positive Margin at Inception") -> Negative Margin at Inception | BW15: =IFERROR(BR15/BQ15,"0") -> 6.130287e-07 | BX15: =IF(BW15<1%,"Less Than 1%",IF(BW15>2%,"More than 2%",IF(BW15>=1%,"1% - 2%"))) -> Less Than 1% | BY15: =BO15+BP15 -> 0 | BZ15: =AL15+AK15 -> -28210 | CA15: =BY15-BZ15 -> 28210 | CB15: =BO15 -> 0 | CC15: =AK15 -> -28210 | CD15: =CB15-CC15 -> 28210 | CE15: Marketplace (Metal Waste) | CF15: =_xlfn.XLOOKUP(G15,'Supplier Metrics'!C:C,'Supplier Metrics'!H:H) -> Trader With Warehouse | CG15: =TEXT(AN15,"mmm-yy") -> Apr-26 | CH15: =AM15-AL15 -> 815622 | CI15: =BQ15-BP15 -> 815622.5 | CJ15: =INT((D15- IF(MONTH(D15) >= 4, DATE(YEAR(D15), 4, 1), DATE(YEAR(D15)-1, 4, 1))) / 7) + 1 -> 3 | CK15: {=_xlfn.XLOOKUP(N15,'Material Metrics'!B:B,'Material Metrics'!C:D)} -> Ferrous | CL15: Ferrous | CM15: =_xlfn.XLOOKUP(AR15,Receivables!B:B,Receivables!D:D) -> Shadab | CN15: =AY15-Q15 -> -28209.5 | CO15: =CN15-AB15 -> -28209.5 | CP15: =BQ15-AM15 -> 0.5 | CQ15: =AY15*118% -> 962434.55 | CR15: =Q15*118% -> 995721.76 | CS15: =CB15*118% -> 0 | CT15: =CC15*118% -> -33287.8 | CU15: =(CQ15-CS15)-(CR15-CT15) -> -66575.01 | CV15: Telangana - HO | CW15: Telangana - HO | CX15: =MID(G15,3,10) -> AOBPK6586N | CY15: =MID(AR15,3,10) -> AAACJ4323N | CZ15: No | DA15: 0 | DB15: 0 | DC15: 0 | DD15: 0 | DE15: =AE15+AJ15+AK15 -> -28210 | DF15: =BN15+BO15+BC15 -> 0
B16: ="Q" & IF(ROUNDUP(MONTH(D16)/3,0)-1=0,4,ROUNDUP(MONTH(D16)/3,0)-1) -> Q1 | C16: =TEXT(AN16,"mmm-yy") -> Apr-26 | D16: 46133 | E16: SH04262106 | F16: NAWABI METALS | G16: 27AOBPK6586N1Z9 | H16: NM/26-27/033 | I16: 46133 | J16: 26-27/PUR/001075 | K16: 46133 | L16: MH | M16: MH12FC8048 | N16: Boring & Turning | O16: 16960 | P16: 33.05 | Q16: =O16*P16 -> 560528 | R16: 0 | S16: =O16-R16 -> 16960 | T16: 0 | U16: 0 | V16: 0 | W16: 0 | X16: 0 | Y16: 0 | Z16: 0 | AA16: 0 | AB16: =Y16+AA16+Z16 -> 0 | AC16: 0 | AD16: 0 | AE16: 0 | AF16: 36/MET/27VC00054 | AG16: 46136 | AH16: 36/MET/27VC00058 & 36/MET/27VC00088 | AI16: 46139 | AJ16: 0 | AK16: =-8563-992-29628 -> -39183 | AL16: 0 | AM16: =Q16+AB16+AL16+AK16+AJ16+T16+AE16 -> 521345 | AN16: 46133 | AO16: 36/MET/27IN00013 | AP16: 832139000044272012 | AQ16: ARCELORMITTAL NIPPON STEEL INDIA PRIVATE LIMITED | AR16: 27AAACE1741P1ZH | AS16: Pune,Maharashtra,412203 | AT16: Raighadh | AU16: Maharashtra | AV16: 112407496561 | AW16: 16960 | AX16: 31.3 | AY16: =AW16*AX16 -> 530848 | AZ16: =AW16=O16 -> TRUE | BA16: 0 | BB16: =AW16-BA16 -> 16960 | BC16: 0 | BD16: Regular | BE16: 0 | BF16: 0 | BG16: 0 | BH16: 36/MET/27CN00073 | BI16: 46136 | BJ16: 36/MET/27CN00077 | BK16: 46139 | BL16: 0 | BM16: 0 | BN16: 0 | BO16: =-8110-939 -> -9049 | BP16: 0 | BQ16: =AY16+BN16+BO16+BP16+BC16+BG16+BM16+BL16 -> 521799 | BR16: =BQ16-AM16 -> 454 | BS16: =IF(BR16>=0,"Positive Margin","Negative Margin") -> Positive Margin | BT16: DN & CN Issued | BU16: =AY16-Y16-Q16-AA16-T16+BC16 -> -29680 | BV16: =IF(BU16<0, "Negative Margin at Inception", "Positive Margin at Inception") -> Negative Margin at Inception | BW16: =IFERROR(BR16/BQ16,"0") -> 0.00087006683 | BX16: =IF(BW16<1%,"Less Than 1%",IF(BW16>2%,"More than 2%",IF(BW16>=1%,"1% - 2%"))) -> Less Than 1% | BY16: =BO16+BP16 -> -9049 | BZ16: =AL16+AK16 -> -39183 | CA16: =BY16-BZ16 -> 30134 | CB16: =BO16 -> -9049 | CC16: =AK16 -> -39183 | CD16: =CB16-CC16 -> 30134 | CE16: Marketplace (Metal Waste) | CF16: =_xlfn.XLOOKUP(G16,'Supplier Metrics'!C:C,'Supplier Metrics'!H:H) -> Trader With Warehouse | CG16: =TEXT(AN16,"mmm-yy") -> Apr-26 | CH16: =AM16-AL16 -> 521345 | CI16: =BQ16-BP16 -> 521799 | CJ16: =INT((D16- IF(MONTH(D16) >= 4, DATE(YEAR(D16), 4, 1), DATE(YEAR(D16)-1, 4, 1))) / 7) + 1 -> 3 | CK16: {=_xlfn.XLOOKUP(N16,'Material Metrics'!B:B,'Material Metrics'!C:D)} -> Ferrous | CL16: Ferrous | CM16: =_xlfn.XLOOKUP(AR16,Receivables!B:B,Receivables!D:D) -> Gaurav Uttam Kothimeere | CN16: =AY16-Q16 -> -29680 | CO16: =CN16-AB16 -> -29680 | CP16: =BQ16-AM16 -> 454 | CQ16: =AY16*118% -> 626400.64 | CR16: =Q16*118% -> 661423.04 | CS16: =CB16*118% -> -10677.82 | CT16: =CC16*118% -> -46235.94 | CU16: =(CQ16-CS16)-(CR16-CT16) -> -70580.52 | CV16: Telangana - HO | CW16: Telangana - HO | CX16: =MID(G16,3,10) -> AOBPK6586N | CY16: =MID(AR16,3,10) -> AAACE1741P | CZ16: No | DA16: 0 | DB16: 0 | DC16: 0 | DD16: 0 | DE16: =AE16+AJ16+AK16 -> -39183 | DF16: =BN16+BO16+BC16 -> -9049
B17: ="Q" & IF(ROUNDUP(MONTH(D17)/3,0)-1=0,4,ROUNDUP(MONTH(D17)/3,0)-1) -> Q1 | C17: =TEXT(AN17,"mmm-yy") -> Apr-26 | D17: 46134 | E17: SH04262209 | F17: NISHA TRADING COMPANY | G17: 27CFUPK7292B1ZZ | H17: 1413 | I17: 46134 | J17: 26-27/PUR/001267 | K17: 46134 | L17: MH | M17: MH04KF2197 | N17: Boring & Turning | O17: 11560 | P17: 31.3 | Q17: =O17*P17 -> 361828 | R17: 0 | S17: =O17-R17 -> 11560 | T17: 0 | U17: 0 | V17: 0 | W17: 0 | X17: 0 | Y17: 0 | Z17: 0 | AA17: 0 | AB17: =Y17+AA17+Z17 -> 0 | AC17: 0 | AD17: 0 | AE17: 0 | AF17: 36/MET/27VC00055 | AG17: 46137 | AH17: 36/MET/27VC00055 | AI17: 46137 | AJ17: 0 | AK17: =-3831.1186440678-626 -> -4457.1186 | AL17: 0 | AM17: =Q17+AB17+AL17+AK17+AJ17+T17+AE17 -> 357370.88 | AN17: 46134 | AO17: 36/MET/27IN00014 | AP17: 832139000044272012 | AQ17: ARCELORMITTAL NIPPON STEEL INDIA PRIVATE LIMITED | AR17: 27AAACE1741P1ZH | AS17: Vasai Maharashtra 401208 | AT17: Raighadh | AU17: Maharashtra | AV17: 102408509935 | AW17: 11560 | AX17: 31.3 | AY17: =AW17*AX17 -> 361828 | AZ17: =AW17=O17 -> TRUE | BA17: 0 | BB17: =AW17-BA17 -> 11560 | BC17: 0 | BD17: Regular | BE17: 0 | BF17: 0 | BG17: 0 | BH17: 36/MET/27CN00074 | BI17: 46137 | BJ17: 36/MET/27CN00075 | BK17: 46137 | BL17: 0 | BM17: 0 | BN17: 0 | BO17: =-3831.12-626 -> -4457.12 | BP17: 0 | BQ17: =AY17+BN17+BO17+BP17+BC17+BG17+BM17+BL17 -> 357370.88 | BR17: =BQ17-AM17 -> -0.0013559322 | BS17: =IF(BR17>=0,"Positive Margin","Negative Margin") -> Negative Margin | BT17: DN & CN Issued | BU17: =AY17-Y17-Q17-AA17-T17+BC17 -> 0 | BV17: =IF(BU17<0, "Negative Margin at Inception", "Positive Margin at Inception") -> Positive Margin at Inception | BW17: =IFERROR(BR17/BQ17,"0") -> -3.7941877e-09 | BX17: =IF(BW17<1%,"Less Than 1%",IF(BW17>2%,"More than 2%",IF(BW17>=1%,"1% - 2%"))) -> Less Than 1% | BY17: =BO17+BP17 -> -4457.12 | BZ17: =AL17+AK17 -> -4457.1186 | CA17: =BY17-BZ17 -> -0.0013559322 | CB17: =BO17 -> -4457.12 | CC17: =AK17 -> -4457.1186 | CD17: =CB17-CC17 -> -0.0013559322 | CE17: Marketplace (Metal Waste) | CF17: =_xlfn.XLOOKUP(G17,'Supplier Metrics'!C:C,'Supplier Metrics'!H:H) -> Trader With Warehouse | CG17: =TEXT(AN17,"mmm-yy") -> Apr-26 | CH17: =AM17-AL17 -> 357370.88 | CI17: =BQ17-BP17 -> 357370.88 | CJ17: =INT((D17- IF(MONTH(D17) >= 4, DATE(YEAR(D17), 4, 1), DATE(YEAR(D17)-1, 4, 1))) / 7) + 1 -> 4 | CK17: {=_xlfn.XLOOKUP(N17,'Material Metrics'!B:B,'Material Metrics'!C:D)} -> Ferrous | CL17: Ferrous | CM17: =_xlfn.XLOOKUP(AR17,Receivables!B:B,Receivables!D:D) -> Gaurav Uttam Kothimeere | CN17: =AY17-Q17 -> 0 | CO17: =CN17-AB17 -> 0 | CP17: =BQ17-AM17 -> -0.0013559322 | CQ17: =AY17*118% -> 426957.04 | CR17: =Q17*118% -> 426957.04 | CS17: =CB17*118% -> -5259.4016 | CT17: =CC17*118% -> -5259.4 | CU17: =(CQ17-CS17)-(CR17-CT17) -> 0.0016 | CV17: Telangana - HO | CW17: Telangana - HO | CX17: =MID(G17,3,10) -> CFUPK7292B | CY17: =MID(AR17,3,10) -> AAACE1741P | CZ17: No | DA17: 0 | DB17: 0 | DC17: 0 | DD17: 0 | DE17: =AE17+AJ17+AK17 -> -4457.1186 | DF17: =BN17+BO17+BC17 -> -4457.12
B18: ="Q" & IF(ROUNDUP(MONTH(D18)/3,0)-1=0,4,ROUNDUP(MONTH(D18)/3,0)-1) -> Q1 | C18: =TEXT(AN18,"mmm-yy") -> Apr-26 | D18: 46135 | E18: SH04262302 | F18: BMS ENTERPRISES | G18: 07AIXPR2550B1Z3 | H18: 49 | I18: 46135 | J18: 26-27/PUR/001331 | K18: 46135 | L18: DL | M18: HR38AC9067 | N18: Aluminium Wire Scrap | O18: 5870 | P18: 323.81 | Q18: =O18*P18 -> 1900764.7 | R18: 0 | S18: =O18-R18 -> 5870 | T18: 0 | U18: 0 | V18: 0 | W18: 0 | X18: 0 | Y18: 0 | Z18: 0 | AA18: 0 | AB18: =Y18+AA18+Z18 -> 0 | AC18: 0 | AD18: 0 | AE18: 0 | AF18: 0 | AG18: 0 | AH18: 0 | AI18: 0 | AJ18: 0 | AK18: 0 | AL18: 0 | AM18: =Q18+AB18+AL18+AK18+AJ18+T18+AE18 -> 1900764.7 | AN18: 46135 | AO18: 36/MET/27IN00015 | AP18: 832139000042107085 | AQ18: NOIDA ALUMINIUM COMPANY PRIVATE LIMITED | AR18: 09AAACN0064G1ZR | AS18: NORTH EAST DELHI, Delhi 110094 | AT18: Noida | AU18: Uttar Pradesh | AW18: 5870 | AX18: 334 | AY18: =AW18*AX18 -> 1960580 | AZ18: =AW18=O18 -> TRUE | BA18: 0 | BB18: =AW18-BA18 -> 5870 | BC18: 0 | BD18: Regular | BE18: 0 | BF18: 0 | BG18: 0 | BH18: 0 | BI18: 0 | BJ18: 0 | BK18: 0 | BL18: 0 | BM18: 0 | BN18: 0 | BO18: 0 | BP18: 0 | BQ18: =AY18+BN18+BO18+BP18+BC18+BG18+BM18+BL18 -> 1960580 | BR18: =BQ18-AM18 -> 59815.3 | BS18: =IF(BR18>=0,"Positive Margin","Negative Margin") -> Positive Margin | BT18: No Debit Note | BU18: =AY18-Y18-Q18-AA18-T18+BC18 -> 59815.3 | BV18: =IF(BU18<0, "Negative Margin at Inception", "Positive Margin at Inception") -> Positive Margin at Inception | BW18: =IFERROR(BR18/BQ18,"0") -> 0.030508982 | BX18: =IF(BW18<1%,"Less Than 1%",IF(BW18>2%,"More than 2%",IF(BW18>=1%,"1% - 2%"))) -> More than 2% | BY18: =BO18+BP18 -> 0 | BZ18: =AL18+AK18 -> 0 | CA18: =BY18-BZ18 -> 0 | CB18: =BO18 -> 0 | CC18: =AK18 -> 0 | CD18: =CB18-CC18 -> 0 | CE18: Marketplace (Metal Waste) | CF18: =_xlfn.XLOOKUP(G18,'Supplier Metrics'!C:C,'Supplier Metrics'!H:H) -> Processor | CG18: =TEXT(AN18,"mmm-yy") -> Apr-26 | CH18: =AM18-AL18 -> 1900764.7 | CI18: =BQ18-BP18 -> 1960580 | CJ18: =INT((D18- IF(MONTH(D18) >= 4, DATE(YEAR(D18), 4, 1), DATE(YEAR(D18)-1, 4, 1))) / 7) + 1 -> 4 | CK18: {=_xlfn.XLOOKUP(N18,'Material Metrics'!B:B,'Material Metrics'!C:D)} -> Non-Ferrous | CL18: Aluminium | CM18: =_xlfn.XLOOKUP(AR18,Receivables!B:B,Receivables!D:D) -> Daulat Biyani | CN18: =AY18-Q18 -> 59815.3 | CO18: =CN18-AB18 -> 59815.3 | CP18: =BQ18-AM18 -> 59815.3 | CQ18: =AY18*118% -> 2313484.4 | CR18: =Q18*118% -> 2242902.3 | CS18: =CB18*118% -> 0 | CT18: =CC18*118% -> 0 | CU18: =(CQ18-CS18)-(CR18-CT18) -> 70582.054 | CV18: Telangana - HO | CW18: Telangana - HO | CX18: =MID(G18,3,10) -> AIXPR2550B | CY18: =MID(AR18,3,10) -> AAACN0064G | CZ18: No | DA18: 0 | DB18: 0 | DC18: 0 | DD18: 0 | DE18: =AE18+AJ18+AK18 -> 0 | DF18: =BN18+BO18+BC18 -> 0
B19: ="Q" & IF(ROUNDUP(MONTH(D19)/3,0)-1=0,4,ROUNDUP(MONTH(D19)/3,0)-1) -> Q1 | C19: =TEXT(AN19,"mmm-yy") -> Apr-26 | D19: 46135 | E19: SH04262305 | F19: AUM METALS AND TECHNO-CERAMICS PRIVATE LIMITED | G19: 27AADCA1895P1Z3 | H19: 9/2026-27 | I19: 46135 | J19: 26-27/PUR/001333 | K19: 46136 | L19: MH | M19: MH18BG4766 | N19: HR_END_CUT | O19: 22525 | P19: 35.7 | Q19: =O19*P19 -> 804142.5 | R19: 0 | S19: =O19-R19 -> 22525 | T19: 0 | U19: 0 | V19: 0 | W19: 0 | X19: 0 | Y19: 0 | Z19: 0 | AA19: 0 | AB19: =Y19+AA19+Z19 -> 0 | AC19: 0 | AD19: 0 | AE19: 0 | AF19: 36/MET/27VC00065 | AG19: 46139 | AH19: 36/MET/27VC00095 | AI19: 46149 | AJ19: 0 | AK19: =-32567-2320.5 -> -34887.5 | AL19: 0 | AM19: =Q19+AB19+AL19+AK19+AJ19+T19+AE19 -> 769255 | AN19: 46136 | AO19: 36/MET/27IN00016 | AP19: 832139000032849620 | AQ19: JSW STEEL LIMITED (27) | AR19: 27AAACJ4323N1ZG | AS19: Mumbai Maharashtra 400010 | AT19: raigad | AU19: Maharashtra | AV19: 172409669099 | AW19: 22525 | AX19: 34.25 | AY19: =AW19*AX19 -> 771481.25 | AZ19: =AW19=O19 -> TRUE | BA19: 0 | BB19: =AW19-BA19 -> 22525 | BC19: 0 | BD19: Regular | BE19: 0 | BF19: 0 | BG19: 0 | BH19: 36/MET/27CN00102 | BI19: 46149 | BJ19: 0 | BK19: 0 | BL19: 0 | BM19: 0 | BN19: 0 | BO19: -2226.25 | BP19: 0 | BQ19: =AY19+BN19+BO19+BP19+BC19+BG19+BM19+BL19 -> 769255 | BR19: =BQ19-AM19 -> 0 | BS19: =IF(BR19>=0,"Positive Margin","Negative Margin") -> Positive Margin | BT19: DN & CN Issued | BU19: =AY19-Y19-Q19-AA19-T19+BC19 -> -32661.25 | BV19: =IF(BU19<0, "Negative Margin at Inception", "Positive Margin at Inception") -> Negative Margin at Inception | BW19: =IFERROR(BR19/BQ19,"0") -> 0 | BX19: =IF(BW19<1%,"Less Than 1%",IF(BW19>2%,"More than 2%",IF(BW19>=1%,"1% - 2%"))) -> Less Than 1% | BY19: =BO19+BP19 -> -2226.25 | BZ19: =AL19+AK19 -> -34887.5 | CA19: =BY19-BZ19 -> 32661.25 | CB19: =BO19 -> -2226.25 | CC19: =AK19 -> -34887.5 | CD19: =CB19-CC19 -> 32661.25 | CE19: Marketplace (Metal Waste) | CF19: =_xlfn.XLOOKUP(G19,'Supplier Metrics'!C:C,'Supplier Metrics'!H:H) -> Trader With Warehouse | CG19: =TEXT(AN19,"mmm-yy") -> Apr-26 | CH19: =AM19-AL19 -> 769255 | CI19: =BQ19-BP19 -> 769255 | CJ19: =INT((D19- IF(MONTH(D19) >= 4, DATE(YEAR(D19), 4, 1), DATE(YEAR(D19)-1, 4, 1))) / 7) + 1 -> 4 | CK19: {=_xlfn.XLOOKUP(N19,'Material Metrics'!B:B,'Material Metrics'!C:D)} -> Ferrous | CL19: Ferrous | CM19: =_xlfn.XLOOKUP(AR19,Receivables!B:B,Receivables!D:D) -> Shadab | CN19: =AY19-Q19 -> -32661.25 | CO19: =CN19-AB19 -> -32661.25 | CP19: =BQ19-AM19 -> 0 | CQ19: =AY19*118% -> 910347.88 | CR19: =Q19*118% -> 948888.15 | CS19: =CB19*118% -> -2626.975 | CT19: =CC19*118% -> -41167.25 | CU19: =(CQ19-CS19)-(CR19-CT19) -> -77080.55 | CV19: Telangana - HO | CW19: Telangana - HO | CX19: =MID(G19,3,10) -> AADCA1895P | CY19: =MID(AR19,3,10) -> AAACJ4323N | CZ19: No | DA19: 0 | DB19: 0 | DC19: 0 | DD19: 0 | DE19: =AE19+AJ19+AK19 -> -34887.5 | DF19: =BN19+BO19+BC19 -> -2226.25
B20: ="Q" & IF(ROUNDUP(MONTH(D20)/3,0)-1=0,4,ROUNDUP(MONTH(D20)/3,0)-1) -> Q1 | C20: =TEXT(AN20,"mmm-yy") -> Apr-26 | D20: 46138 | E20: SH04262503 | F20: NISHA TRADING COMPANY | G20: 27CFUPK7292B1ZZ | H20: 1418 | I20: 46138 | J20: 26-27/PUR/001436 | K20: 46138 | L20: MH | M20: MH48AY1949 | N20: Boring & Turning | O20: 10150 | P20: 31.3 | Q20: =O20*P20 -> 317695 | R20: 0 | S20: =O20-R20 -> 10150 | T20: 0 | U20: 0 | V20: 0 | W20: 0 | X20: 0 | Y20: 0 | Z20: 0 | AA20: 0 | AB20: =Y20+AA20+Z20 -> 0 | AC20: 0 | AD20: 0 | AE20: 0 | AF20: 36/MET/27VC00071 | AG20: 46140 | AH20: 36/MET/27VC00072 | AI20: 46140 | AJ20: 0 | AK20: =-5947-5352 -> -11299 | AL20: =(BP20*P20/AX20)+AB20/O20*(BP20/AX20) -> 0 | AM20: =Q20+AB20+AL20+AK20+AJ20+T20+AE20 -> 306396 | AN20: 46138 | AO20: 36/MET/27IN00017 | AP20: 832139000044272012 | AQ20: ARCELORMITTAL NIPPON STEEL INDIA PRIVATE LIMITED | AR20: 27AAACE1741P1ZH | AS20: Taluka Bhiwandi,Maharashtra,421302 | AT20: Raighadh | AU20: Maharashtra | AV20: 132411667430 | AW20: 10150 | AX20: 31.3 | AY20: =AW20*AX20 -> 317695 | AZ20: =AW20=O20 -> TRUE | BA20: 0 | BB20: =AW20-BA20 -> 10150 | BC20: 0 | BD20: Regular | BE20: 0 | BF20: 0 | BG20: 0 | BH20: 36/MET/27CN00084 | BI20: 46140 | BJ20: 36/MET/27CN00083 | BK20: 46140 | BL20: 0 | BM20: 0 | BN20: 0 | BO20: =-5352.3-5947 -> -11299.3 | BP20: 0 | BQ20: =AY20+BN20+BO20+BP20+BC20+BG20+BM20+BL20 -> 306395.7 | BR20: =BQ20-AM20 -> -0.3 | BS20: =IF(BR20>=0,"Positive Margin","Negative Margin") -> Negative Margin | BT20: DN & CN Issued | BU20: =AY20-Y20-Q20-AA20-T20+BC20 -> 0 | BV20: =IF(BU20<0, "Negative Margin at Inception", "Positive Margin at Inception") -> Positive Margin at Inception | BW20: =IFERROR(BR20/BQ20,"0") -> -9.7912601e-07 | BX20: =IF(BW20<1%,"Less Than 1%",IF(BW20>2%,"More than 2%",IF(BW20>=1%,"1% - 2%"))) -> Less Than 1% | BY20: =BO20+BP20 -> -11299.3 | BZ20: =AL20+AK20 -> -11299 | CA20: =BY20-BZ20 -> -0.3 | CB20: =BO20 -> -11299.3 | CC20: =AK20 -> -11299 | CD20: =CB20-CC20 -> -0.3 | CE20: Marketplace (Metal Waste) | CF20: =_xlfn.XLOOKUP(G20,'Supplier Metrics'!C:C,'Supplier Metrics'!H:H) -> Trader With Warehouse | CG20: =TEXT(AN20,"mmm-yy") -> Apr-26 | CH20: =AM20-AL20 -> 306396 | CI20: =BQ20-BP20 -> 306395.7 | CJ20: =INT((D20- IF(MONTH(D20) >= 4, DATE(YEAR(D20), 4, 1), DATE(YEAR(D20)-1, 4, 1))) / 7) + 1 -> 4 | CK20: {=_xlfn.XLOOKUP(N20,'Material Metrics'!B:B,'Material Metrics'!C:D)} -> Ferrous | CL20: Ferrous | CM20: =_xlfn.XLOOKUP(AR20,Receivables!B:B,Receivables!D:D) -> Gaurav Uttam Kothimeere | CN20: =AY20-Q20 -> 0 | CO20: =CN20-AB20 -> 0 | CP20: =BQ20-AM20 -> -0.3 | CQ20: =AY20*118% -> 374880.1 | CR20: =Q20*118% -> 374880.1 | CS20: =CB20*118% -> -13333.174 | CT20: =CC20*118% -> -13332.82 | CU20: =(CQ20-CS20)-(CR20-CT20) -> 0.354 | CV20: Telangana - HO | CW20: Telangana - HO | CX20: =MID(G20,3,10) -> CFUPK7292B | CY20: =MID(AR20,3,10) -> AAACE1741P | CZ20: No | DA20: 0 | DB20: 0 | DC20: 0 | DD20: 0 | DE20: =AE20+AJ20+AK20 -> -11299 | DF20: =BN20+BO20+BC20 -> -11299.3
B21: ="Q" & IF(ROUNDUP(MONTH(D21)/3,0)-1=0,4,ROUNDUP(MONTH(D21)/3,0)-1) -> Q1 | C21: =TEXT(AN21,"mmm-yy") -> Apr-26 | D21: 46139 | F21: Emami Paper Mills Ltd. | G21: 21AABCG1428Q1ZO | H21: 5901000008 | I21: 46112 | J21: 26-27/PUR/001470 | K21: 46139 | L21: OD | N21: Hydra charges | O21: 1 | P21: 6750 | Q21: =O21*P21 -> 6750 | R21: 0 | S21: =O21-R21 -> 1 | T21: 0 | U21: 0 | V21: 0 | W21: 0 | X21: 0 | Y21: 0 | Z21: 0 | AA21: 0 | AB21: =Y21+AA21+Z21 -> 0 | AC21: 0 | AD21: 0 | AE21: 0 | AF21: 0 | AG21: 0 | AH21: 0 | AI21: 0 | AJ21: 0 | AK21: 0 | AL21: =(BP21*P21/AX21)+AB21/O21*(BP21/AX21) -> 0 | AM21: =Q21+AB21+AL21+AK21+AJ21+T21+AE21 -> 6750 | AN21: 46139 | AO21: 36/MET/27IN00020 | AP21: 832139000061736683 | AQ21: M/S KGN SS ENTERPRISES | AR21: 21BNPPA0347H1ZG | AT21: Remuna | AU21: Odisha | AW21: 1 | AX21: 6750 | AY21: =AW21*AX21 -> 6750 | AZ21: =AW21=O21 -> TRUE | BA21: 0 | BB21: =AW21-BA21 -> 1 | BC21: 0 | BD21: Regular | BE21: 0 | BF21: 0 | BG21: 0 | BH21: 0 | BI21: 0 | BJ21: 0 | BK21: 0 | BL21: 0 | BM21: 0 | BN21: 0 | BO21: 0 | BP21: 0 | BQ21: =AY21+BN21+BO21+BP21+BC21+BG21+BM21+BL21 -> 6750 | BR21: =BQ21-AM21 -> 0 | BS21: =IF(BR21>=0,"Positive Margin","Negative Margin") -> Positive Margin | BT21: DN & CN Issued | BU21: =AY21-Y21-Q21-AA21-T21+BC21 -> 0 | BV21: =IF(BU21<0, "Negative Margin at Inception", "Positive Margin at Inception") -> Positive Margin at Inception | BW21: =IFERROR(BR21/BQ21,"0") -> 0 | BX21: =IF(BW21<1%,"Less Than 1%",IF(BW21>2%,"More than 2%",IF(BW21>=1%,"1% - 2%"))) -> Less Than 1% | BY21: =BO21+BP21 -> 0 | BZ21: =AL21+AK21 -> 0 | CA21: =BY21-BZ21 -> 0 | CB21: =BO21 -> 0 | CC21: =AK21 -> 0 | CD21: =CB21-CC21 -> 0 | CE21: Marketplace (Metal Waste) | CF21: =_xlfn.XLOOKUP(G21,'Supplier Metrics'!C:C,'Supplier Metrics'!H:H) -> Auction/RVSF | CG21: =TEXT(AN21,"mmm-yy") -> Apr-26 | CH21: =AM21-AL21 -> 6750 | CI21: =BQ21-BP21 -> 6750 | CJ21: =INT((D21- IF(MONTH(D21) >= 4, DATE(YEAR(D21), 4, 1), DATE(YEAR(D21)-1, 4, 1))) / 7) + 1 -> 4 | CK21: {=_xlfn.XLOOKUP(N21,'Material Metrics'!B:B,'Material Metrics'!C:D)} -> #N/A | CM21: =_xlfn.XLOOKUP(AR21,Receivables!B:B,Receivables!D:D) -> Sunil Sharma | CN21: =AY21-Q21 -> 0 | CO21: =CN21-AB21 -> 0 | CP21: =BQ21-AM21 -> 0 | CQ21: =AY21*118% -> 7965 | CR21: =Q21*118% -> 7965 | CS21: =CB21*118% -> 0 | CT21: =CC21*118% -> 0 | CU21: =(CQ21-CS21)-(CR21-CT21) -> 0 | CV21: Telangana - HO | CW21: Telangana - HO | CX21: =MID(G21,3,10) -> AABCG1428Q | CY21: =MID(AR21,3,10) -> BNPPA0347H | CZ21: No | DA21: 0 | DB21: 0 | DC21: 0 | DD21: 0 | DE21: =AE21+AJ21+AK21 -> 0 | DF21: =BN21+BO21+BC21 -> 0
B22: ="Q" & IF(ROUNDUP(MONTH(D22)/3,0)-1=0,4,ROUNDUP(MONTH(D22)/3,0)-1) -> Q1 | C22: =TEXT(AN22,"mmm-yy") -> Apr-26 | D22: 46138 | E22: SH04262601 | F22: NISHA TRADING COMPANY | G22: 27CFUPK7292B1ZZ | H22: 1419 | I22: 46138 | J22: 26-27/PUR/001450 | K22: 46139 | L22: MH | M22: MH48CQ1482 | N22: Boring & Turning | O22: 10240 | P22: 31.3 | Q22: =O22*P22 -> 320512 | R22: 0 | S22: =O22-R22 -> 10240 | T22: 0 | U22: 0 | V22: 0 | W22: 0 | X22: 0 | Y22: 0 | Z22: 0 | AA22: 0 | AB22: =Y22+AA22+Z22 -> 0 | AC22: 0 | AD22: 0 | AE22: 0 | AF22: 36/MET/27VC00067 | AG22: 46140 | AH22: 36/MET/27VC00068 | AI22: 46140 | AJ22: 0 | AK22: =-5634-7673 -> -13307 | AL22: =(BP22*P22/AX22)+AB22/O22*(BP22/AX22) -> 0 | AM22: =Q22+AB22+AL22+AK22+AJ22+T22+AE22 -> 307205 | AN22: 46139 | AO22: 36/MET/27IN00019 | AP22: 832139000044272012 | AQ22: ARCELORMITTAL NIPPON STEEL INDIA PRIVATE LIMITED | AR22: 27AAACE1741P1ZH | AS22: Bhiwandi Maharashtra 421302 | AT22: Raighadh | AU22: Maharashtra | AV22: 132412248883 | AW22: 10240 | AX22: 31.3 | AY22: =AW22*AX22 -> 320512 | AZ22: =AW22=O22 -> TRUE | BA22: 0 | BB22: =AW22-BA22 -> 10240 | BC22: 0 | BD22: Regular | BE22: 0 | BF22: 0 | BG22: 0 | BH22: 36/MET/27CN00079 | BI22: 46140 | BJ22: 36/MET/27CN00080 | BK22: 46140 | BL22: 0 | BM22: 0 | BN22: 0 | BO22: =-5634-7673 -> -13307 | BP22: 0 | BQ22: =AY22+BN22+BO22+BP22+BC22+BG22+BM22+BL22 -> 307205 | BR22: =BQ22-AM22 -> 0 | BS22: =IF(BR22>=0,"Positive Margin","Negative Margin") -> Positive Margin | BT22: DN & CN Issued | BU22: =AY22-Y22-Q22-AA22-T22+BC22 -> 0 | BV22: =IF(BU22<0, "Negative Margin at Inception", "Positive Margin at Inception") -> Positive Margin at Inception | BW22: =IFERROR(BR22/BQ22,"0") -> 0 | BX22: =IF(BW22<1%,"Less Than 1%",IF(BW22>2%,"More than 2%",IF(BW22>=1%,"1% - 2%"))) -> Less Than 1% | BY22: =BO22+BP22 -> -13307 | BZ22: =AL22+AK22 -> -13307 | CA22: =BY22-BZ22 -> 0 | CB22: =BO22 -> -13307 | CC22: =AK22 -> -13307 | CD22: =CB22-CC22 -> 0 | CE22: Marketplace (Metal Waste) | CF22: =_xlfn.XLOOKUP(G22,'Supplier Metrics'!C:C,'Supplier Metrics'!H:H) -> Trader With Warehouse | CG22: =TEXT(AN22,"mmm-yy") -> Apr-26 | CH22: =AM22-AL22 -> 307205 | CI22: =BQ22-BP22 -> 307205 | CJ22: =INT((D22- IF(MONTH(D22) >= 4, DATE(YEAR(D22), 4, 1), DATE(YEAR(D22)-1, 4, 1))) / 7) + 1 -> 4 | CK22: {=_xlfn.XLOOKUP(N22,'Material Metrics'!B:B,'Material Metrics'!C:D)} -> Ferrous | CL22: Ferrous | CM22: =_xlfn.XLOOKUP(AR22,Receivables!B:B,Receivables!D:D) -> Gaurav Uttam Kothimeere | CN22: =AY22-Q22 -> 0 | CO22: =CN22-AB22 -> 0 | CP22: =BQ22-AM22 -> 0 | CQ22: =AY22*118% -> 378204.16 | CR22: =Q22*118% -> 378204.16 | CS22: =CB22*118% -> -15702.26 | CT22: =CC22*118% -> -15702.26 | CU22: =(CQ22-CS22)-(CR22-CT22) -> 0 | CV22: Telangana - HO | CW22: Telangana - HO | CX22: =MID(G22,3,10) -> CFUPK7292B | CY22: =MID(AR22,3,10) -> AAACE1741P | CZ22: No | DA22: 0 | DB22: 0 | DC22: 0 | DD22: 0 | DE22: =AE22+AJ22+AK22 -> -13307 | DF22: =BN22+BO22+BC22 -> -13307
B23: ="Q" & IF(ROUNDUP(MONTH(D23)/3,0)-1=0,4,ROUNDUP(MONTH(D23)/3,0)-1) -> Q1 | C23: =TEXT(AN23,"mmm-yy") -> Apr-26 | D23: 46138 | E23: SH04262602 | F23: NISHA TRADING COMPANY | G23: 27CFUPK7292B1ZZ | H23: 1420 | I23: 46138 | J23: 26-27/PUR/001448 | K23: 46139 | L23: MH | M23: MH48AG5755 | N23: Boring & Turning | O23: 11570 | P23: 31.3 | Q23: =O23*P23 -> 362141 | R23: 0 | S23: =O23-R23 -> 11570 | T23: 0 | U23: 0 | V23: 0 | W23: 0 | X23: 0 | Y23: 0 | Z23: 0 | AA23: 0 | AB23: =Y23+AA23+Z23 -> 0 | AC23: 0 | AD23: 0 | AE23: 0 | AF23: 36/MET/27VC00069 | AG23: 46140 | AH23: 36/MET/27VC00070 | AI23: 46140 | AJ23: 0 | AK23: =-5321-10586 -> -15907 | AL23: =(BP23*P23/AX23)+AB23/O23*(BP23/AX23) -> 0 | AM23: =Q23+AB23+AL23+AK23+AJ23+T23+AE23 -> 346234 | AN23: 46139 | AO23: 36/MET/27IN00018 | AP23: 832139000044272012 | AQ23: ARCELORMITTAL NIPPON STEEL INDIA PRIVATE LIMITED | AR23: 27AAACE1741P1ZH | AS23: Bhiwandi,Maharashtra,421302 | AT23: Raigad | AU23: Maharashtra | AV23: 102412246721 | AW23: 11570 | AX23: 31.3 | AY23: =AW23*AX23 -> 362141 | AZ23: =AW23=O23 -> TRUE | BA23: 0 | BB23: =AW23-BA23 -> 11570 | BC23: 0 | BD23: Regular | BE23: 0 | BF23: 0 | BG23: 0 | BH23: 36/MET/27CN00082 | BI23: 46140 | BJ23: 36/MET/27CN00081 | BK23: 46140 | BL23: 0 | BM23: 0 | BN23: 0 | BO23: =-10585.66-5321 -> -15906.66 | BP23: 0 | BQ23: =AY23+BN23+BO23+BP23+BC23+BG23+BM23+BL23 -> 346234.34 | BR23: =BQ23-AM23 -> 0.34 | BS23: =IF(BR23>=0,"Positive Margin","Negative Margin") -> Positive Margin | BT23: DN & CN Issued | BU23: =AY23-Y23-Q23-AA23-T23+BC23 -> 0 | BV23: =IF(BU23<0, "Negative Margin at Inception", "Positive Margin at Inception") -> Positive Margin at Inception | BW23: =IFERROR(BR23/BQ23,"0") -> 9.8199387e-07 | BX23: =IF(BW23<1%,"Less Than 1%",IF(BW23>2%,"More than 2%",IF(BW23>=1%,"1% - 2%"))) -> Less Than 1% | BY23: =BO23+BP23 -> -15906.66 | BZ23: =AL23+AK23 -> -15907 | CA23: =BY23-BZ23 -> 0.34 | CB23: =BO23 -> -15906.66 | CC23: =AK23 -> -15907 | CD23: =CB23-CC23 -> 0.34 | CE23: Marketplace (Metal Waste) | CF23: =_xlfn.XLOOKUP(G23,'Supplier Metrics'!C:C,'Supplier Metrics'!H:H) -> Trader With Warehouse | CG23: =TEXT(AN23,"mmm-yy") -> Apr-26 | CH23: =AM23-AL23 -> 346234 | CI23: =BQ23-BP23 -> 346234.34 | CJ23: =INT((D23- IF(MONTH(D23) >= 4, DATE(YEAR(D23), 4, 1), DATE(YEAR(D23)-1, 4, 1))) / 7) + 1 -> 4 | CK23: {=_xlfn.XLOOKUP(N23,'Material Metrics'!B:B,'Material Metrics'!C:D)} -> Ferrous | CL23: Ferrous | CM23: =_xlfn.XLOOKUP(AR23,Receivables!B:B,Receivables!D:D) -> Gaurav Uttam Kothimeere | CN23: =AY23-Q23 -> 0 | CO23: =CN23-AB23 -> 0 | CP23: =BQ23-AM23 -> 0.34 | CQ23: =AY23*118% -> 427326.38 | CR23: =Q23*118% -> 427326.38 | CS23: =CB23*118% -> -18769.859 | CT23: =CC23*118% -> -18770.26 | CU23: =(CQ23-CS23)-(CR23-CT23) -> -0.4012 | CV23: Telangana - HO | CW23: Telangana - HO | CX23: =MID(G23,3,10) -> CFUPK7292B | CY23: =MID(AR23,3,10) -> AAACE1741P | CZ23: No | DA23: 0 | DB23: 0 | DC23: 0 | DD23: 0 | DE23: =AE23+AJ23+AK23 -> -15907 | DF23: =BN23+BO23+BC23 -> -15906.66
B24: ="Q" & IF(ROUNDUP(MONTH(D24)/3,0)-1=0,4,ROUNDUP(MONTH(D24)/3,0)-1) -> Q1 | C24: =TEXT(AN24,"mmm-yy") -> Apr-26 | D24: 46139 | E24: SH04262707 | F24: NISHA TRADING COMPANY | G24: 27CFUPK7292B1ZZ | H24: 1422 | I24: 46139 | J24: 26-27/PUR/001479 | K24: 46139 | L24: MH | M24: MH04KF2197 | N24: Boring & Turning | O24: 10230 | P24: 31.3 | Q24: =O24*P24 -> 320199 | R24: 0 | S24: =O24-R24 -> 10230 | T24: 0 | U24: 0 | V24: 0 | W24: 0 | X24: 0 | Y24: 0 | Z24: 0 | AA24: 0 | AB24: =Y24+AA24+Z24 -> 0 | AC24: 0 | AD24: 0 | AE24: 0 | AF24: 36/MET/27VC00073 | AG24: 46142 | AH24: 0 | AI24: 0 | AJ24: 0 | AK24: -18806.61 | AL24: =(BP24*P24/AX24)+AB24/O24*(BP24/AX24) -> 0 | AM24: =Q24+AB24+AL24+AK24+AJ24+T24+AE24 -> 301392.39 | AN24: 46139 | AO24: 36/MET/27IN00021 | AP24: 832139000044272012 | AQ24: ARCELORMITTAL NIPPON STEEL INDIA PRIVATE LIMITED | AR24: 27AAACE1741P1ZH | AS24: Palghar Maharashtra 401208 | AT24: Raighadh | AU24: Maharashtra | AV24: 172412928693 | AW24: 10230 | AX24: 31.3 | AY24: =AW24*AX24 -> 320199 | AZ24: =AW24=O24 -> TRUE | BA24: 0 | BB24: =AW24-BA24 -> 10230 | BC24: 0 | BD24: Regular | BE24: 0 | BF24: 0 | BG24: 0 | BH24: 36/MET/27CN00085 | BI24: 46142 | BJ24: 0 | BK24: 0 | BL24: 0 | BM24: 0 | BN24: 0 | BO24: -18806.61 | BP24: 0 | BQ24: =AY24+BN24+BO24+BP24+BC24+BG24+BM24+BL24 -> 301392.39 | BR24: =BQ24-AM24 -> 0.00016949151 | BS24: =IF(BR24>=0,"Positive Margin","Negative Margin") -> Positive Margin | BT24: DN & CN Issued | BU24: =AY24-Y24-Q24-AA24-T24+BC24 -> 0 | BV24: =IF(BU24<0, "Negative Margin at Inception", "Positive Margin at Inception") -> Positive Margin at Inception | BW24: =IFERROR(BR24/BQ24,"0") -> 5.6236162e-10 | BX24: =IF(BW24<1%,"Less Than 1%",IF(BW24>2%,"More than 2%",IF(BW24>=1%,"1% - 2%"))) -> Less Than 1% | BY24: =BO24+BP24 -> -18806.61 | BZ24: =AL24+AK24 -> -18806.61 | CA24: =BY24-BZ24 -> 0.0001694915 | CB24: =BO24 -> -18806.61 | CC24: =AK24 -> -18806.61 | CD24: =CB24-CC24 -> 0.0001694915 | CE24: Marketplace (Metal Waste) | CF24: =_xlfn.XLOOKUP(G24,'Supplier Metrics'!C:C,'Supplier Metrics'!H:H) -> Trader With Warehouse | CG24: =TEXT(AN24,"mmm-yy") -> Apr-26 | CH24: =AM24-AL24 -> 301392.39 | CI24: =BQ24-BP24 -> 301392.39 | CJ24: =INT((D24- IF(MONTH(D24) >= 4, DATE(YEAR(D24), 4, 1), DATE(YEAR(D24)-1, 4, 1))) / 7) + 1 -> 4 | CK24: {=_xlfn.XLOOKUP(N24,'Material Metrics'!B:B,'Material Metrics'!C:D)} -> Ferrous | CL24: Ferrous | CM24: =_xlfn.XLOOKUP(AR24,Receivables!B:B,Receivables!D:D) -> Gaurav Uttam Kothimeere | CN24: =AY24-Q24 -> 0 | CO24: =CN24-AB24 -> 0 | CP24: =BQ24-AM24 -> 0.00016949151 | CQ24: =AY24*118% -> 377834.82 | CR24: =Q24*118% -> 377834.82 | CS24: =CB24*118% -> -22191.8 | CT24: =CC24*118% -> -22191.8 | CU24: =(CQ24-CS24)-(CR24-CT24) -> -0.00020000001 | CV24: Telangana - HO | CW24: Telangana - HO | CX24: =MID(G24,3,10) -> CFUPK7292B | CY24: =MID(AR24,3,10) -> AAACE1741P | CZ24: No | DA24: 0 | DB24: 0 | DC24: 0 | DD24: 0 | DE24: =AE24+AJ24+AK24 -> -18806.61 | DF24: =BN24+BO24+BC24 -> -18806.61
B25: ="Q" & IF(ROUNDUP(MONTH(D25)/3,0)-1=0,4,ROUNDUP(MONTH(D25)/3,0)-1) -> Q1 | C25: =TEXT(AN25,"mmm-yy") -> Apr-26 | D25: 46139 | E25: SH04262706 | F25: BMS ENTERPRISES | G25: 07AIXPR2550B1Z3 | H25: 51 | I25: 46139 | J25: 26-27/PUR/001480 | K25: 46140 | L25: DL | M25: DL01MA9300 | N25: Aluminium Wire Scrap | O25: 8765 | P25: 328.7 | Q25: =O25*P25 -> 2881055.5 | R25: 0 | S25: =O25-R25 -> 8765 | T25: 0 | U25: 0 | V25: 0 | W25: 0 | X25: 0 | Y25: 0 | Z25: 0 | AA25: 0 | AB25: =Y25+AA25+Z25 -> 0 | AC25: 0 | AD25: 0 | AE25: 0 | AF25: 36/MET/27VC00066 | AG25: 46140 | AH25: 0 | AI25: 0 | AJ25: 0 | AK25: -5400 | AL25: =(BP25*P25/AX25)+AB25/O25*(BP25/AX25) -> 0 | AM25: =Q25+AB25+AL25+AK25+AJ25+T25+AE25 -> 2875655.5 | AN25: 46140 | AO25: 36/MET/27IN00022 | AP25: 832139000042107085 | AQ25: NOIDA ALUMINIUM COMPANY PRIVATE LIMITED | AR25: 09AAACN0064G1ZR | AS25: NORTH EAST DELHI,Delhi,110094 | AT25: Noida | AU25: Uttar Pradesh | AW25: 8765 | AX25: 338 | AY25: =AW25*AX25 -> 2962570 | AZ25: =AW25=O25 -> TRUE | BA25: 0 | BB25: =AW25-BA25 -> 8765 | BC25: 0 | BD25: Regular | BE25: 0 | BF25: 0 | BG25: 0 | BH25: 36/MET/27CN00078 | BI25: 46140 | BJ25: 0 | BK25: 0 | BL25: 0 | BM25: 0 | BN25: 0 | BO25: -5400 | BP25: 0 | BQ25: =AY25+BN25+BO25+BP25+BC25+BG25+BM25+BL25 -> 2957170 | BR25: =BQ25-AM25 -> 81514.5 | BS25: =IF(BR25>=0,"Positive Margin","Negative Margin") -> Positive Margin | BT25: DN & CN Issued | BU25: =AY25-Y25-Q25-AA25-T25+BC25 -> 81514.5 | BV25: =IF(BU25<0, "Negative Margin at Inception", "Positive Margin at Inception") -> Positive Margin at Inception | BW25: =IFERROR(BR25/BQ25,"0") -> 0.027565037 | BX25: =IF(BW25<1%,"Less Than 1%",IF(BW25>2%,"More than 2%",IF(BW25>=1%,"1% - 2%"))) -> More than 2% | BY25: =BO25+BP25 -> -5400 | BZ25: =AL25+AK25 -> -5400 | CA25: =BY25-BZ25 -> 0 | CB25: =BO25 -> -5400 | CC25: =AK25 -> -5400 | CD25: =CB25-CC25 -> 0 | CE25: Marketplace (Metal Waste) | CF25: =_xlfn.XLOOKUP(G25,'Supplier Metrics'!C:C,'Supplier Metrics'!H:H) -> Processor | CG25: =TEXT(AN25,"mmm-yy") -> Apr-26 | CH25: =AM25-AL25 -> 2875655.5 | CI25: =BQ25-BP25 -> 2957170 | CJ25: =INT((D25- IF(MONTH(D25) >= 4, DATE(YEAR(D25), 4, 1), DATE(YEAR(D25)-1, 4, 1))) / 7) + 1 -> 4 | CK25: {=_xlfn.XLOOKUP(N25,'Material Metrics'!B:B,'Material Metrics'!C:D)} -> Non-Ferrous | CL25: Aluminium | CM25: =_xlfn.XLOOKUP(AR25,Receivables!B:B,Receivables!D:D) -> Daulat Biyani | CN25: =AY25-Q25 -> 81514.5 | CO25: =CN25-AB25 -> 81514.5 | CP25: =BQ25-AM25 -> 81514.5 | CQ25: =AY25*118% -> 3495832.6 | CR25: =Q25*118% -> 3399645.5 | CS25: =CB25*118% -> -6372 | CT25: =CC25*118% -> -6372 | CU25: =(CQ25-CS25)-(CR25-CT25) -> 96187.11 | CV25: Telangana - HO | CW25: Telangana - HO | CX25: =MID(G25,3,10) -> AIXPR2550B | CY25: =MID(AR25,3,10) -> AAACN0064G | CZ25: No | DA25: 0 | DB25: 0 | DC25: 0 | DD25: 0 | DE25: =AE25+AJ25+AK25 -> -5400 | DF25: =BN25+BO25+BC25 -> -5400
B26: ="Q" & IF(ROUNDUP(MONTH(D26)/3,0)-1=0,4,ROUNDUP(MONTH(D26)/3,0)-1) -> Q1 | C26: =TEXT(AN26,"mmm-yy") -> Apr-26 | D26: 46140 | E26: SH04262806 | F26: NISHA TRADING COMPANY | G26: 27CFUPK7292B1ZZ | H26: 1427 | I26: 46140 | J26: 26-27/PUR/001536 | K26: 46141 | L26: MH | M26: MH48AY1949 | N26: Boring & Turning | O26: 10820 | P26: 31.3 | Q26: =O26*P26 -> 338666 | R26: 0 | S26: =O26-R26 -> 10820 | T26: 0 | U26: 0 | V26: 0 | W26: 0 | X26: 0 | Y26: 0 | Z26: 0 | AA26: 0 | AB26: =Y26+AA26+Z26 -> 0 | AC26: 0 | AD26: 0 | AE26: 0 | AF26: 36/MET/27VC00074 | AG26: 46142 | AH26: 0 | AI26: 0 | AJ26: 0 | AK26: -14159.492 | AL26: 0 | AM26: =Q26+AB26+AL26+AK26+AJ26+T26+AE26 -> 324506.51 | AN26: 46141 | AO26: 36/MET/27IN00023 | AP26: 832139000044272012 | AQ26: ARCELORMITTAL NIPPON STEEL INDIA PRIVATE LIMITED | AR26: 27AAACE1741P1ZH | AS26: Taluka Bhiwandi Maharashtra 421302 | AT26: Raighadh | AU26: Maharashtra | AV26: 182414167495 | AW26: 10820 | AX26: 31.3 | AY26: =AW26*AX26 -> 338666 | AZ26: =AW26=O26 -> TRUE | BA26: 0 | BB26: =AW26-BA26 -> 10820 | BC26: 0 | BD26: Regular | BE26: 0 | BF26: 0 | BG26: 0 | BH26: 36/MET/27CN00086 | BI26: 46142 | BJ26: 0 | BK26: 0 | BL26: 0 | BM26: 0 | BN26: 0 | BO26: -14159.49 | BP26: 0 | BQ26: =AY26+BN26+BO26+BP26+BC26+BG26+BM26+BL26 -> 324506.51 | BR26: =BQ26-AM26 -> 0.0015254237 | BS26: =IF(BR26>=0,"Positive Margin","Negative Margin") -> Positive Margin | BT26: DN & CN Issued | BU26: =AY26-Y26-Q26-AA26-T26+BC26 -> 0 | BV26: =IF(BU26<0, "Negative Margin at Inception", "Positive Margin at Inception") -> Positive Margin at Inception | BW26: =IFERROR(BR26/BQ26,"0") -> 4.7007492e-09 | BX26: =IF(BW26<1%,"Less Than 1%",IF(BW26>2%,"More than 2%",IF(BW26>=1%,"1% - 2%"))) -> Less Than 1% | BY26: =BO26+BP26 -> -14159.49 | BZ26: =AL26+AK26 -> -14159.492 | CA26: =BY26-BZ26 -> 0.0015254237 | CB26: =BO26 -> -14159.49 | CC26: =AK26 -> -14159.492 | CD26: =CB26-CC26 -> 0.0015254237 | CE26: Marketplace (Metal Waste) | CF26: =_xlfn.XLOOKUP(G26,'Supplier Metrics'!C:C,'Supplier Metrics'!H:H) -> Trader With Warehouse | CG26: =TEXT(AN26,"mmm-yy") -> Apr-26 | CH26: =AM26-AL26 -> 324506.51 | CI26: =BQ26-BP26 -> 324506.51 | CJ26: =INT((D26- IF(MONTH(D26) >= 4, DATE(YEAR(D26), 4, 1), DATE(YEAR(D26)-1, 4, 1))) / 7) + 1 -> 4 | CK26: {=_xlfn.XLOOKUP(N26,'Material Metrics'!B:B,'Material Metrics'!C:D)} -> Ferrous | CL26: Ferrous | CM26: =_xlfn.XLOOKUP(AR26,Receivables!B:B,Receivables!D:D) -> Gaurav Uttam Kothimeere | CN26: =AY26-Q26 -> 0 | CO26: =CN26-AB26 -> 0 | CP26: =BQ26-AM26 -> 0.0015254237 | CQ26: =AY26*118% -> 399625.88 | CR26: =Q26*118% -> 399625.88 | CS26: =CB26*118% -> -16708.198 | CT26: =CC26*118% -> -16708.2 | CU26: =(CQ26-CS26)-(CR26-CT26) -> -0.0018 | CV26: Telangana - HO | CW26: Telangana - HO | CX26: =MID(G26,3,10) -> CFUPK7292B | CY26: =MID(AR26,3,10) -> AAACE1741P | CZ26: No | DA26: 0 | DB26: 0 | DC26: 0 | DD26: 0 | DE26: =AE26+AJ26+AK26 -> -14159.492 | DF26: =BN26+BO26+BC26 -> -14159.49
B27: ="Q" & IF(ROUNDUP(MONTH(D27)/3,0)-1=0,4,ROUNDUP(MONTH(D27)/3,0)-1) -> Q1 | C27: =TEXT(AN27,"mmm-yy") -> May-26 | D27: 46143 | E27: SH04263006 | F27: NISHA TRADING COMPANY | G27: 27CFUPK7292B1ZZ | H27: 1431 | I27: 46143 | J27: 26-27/PUR/001662 | K27: 46143 | L27: MH | M27: MH48J2111 | N27: Boring & Turning | O27: 10505 | P27: 31.3 | Q27: =O27*P27 -> 328806.5 | R27: 0 | S27: =O27-R27 -> 10505 | T27: 0 | U27: 0 | V27: 0 | W27: 0 | X27: 0 | Y27: 0 | Z27: 0 | AA27: 0 | AB27: =Y27+AA27+Z27 -> 0 | AC27: 0 | AD27: 0 | AE27: 0 | AF27: 36/MET/27VC00075 | AG27: 46146 | AH27: 36/MET/27VC00076 | AI27: 46146 | AJ27: 0 | AK27: =-3599.5-6936 -> -10535.5 | AL27: 0 | AM27: =Q27+AB27+AL27+AK27+AJ27+T27+AE27 -> 318271 | AN27: 46143 | AO27: 36/MET/27IN00024 | AP27: 832139000044272012 | AQ27: ARCELORMITTAL NIPPON STEEL INDIA PRIVATE LIMITED | AR27: 27AAACE1741P1ZH | AS27: PALGHAR,Maharashtra,401208 | AT27: Raighadh | AU27: Maharashtra | AV27: 162416373768 | AW27: 10505 | AX27: 31.3 | AY27: =AW27*AX27 -> 328806.5 | AZ27: =AW27=O27 -> TRUE | BA27: 0 | BB27: =AW27-BA27 -> 10505 | BC27: 0 | BD27: Regular | BE27: 0 | BF27: 0 | BG27: 0 | BH27: 36/MET/27CN00088 | BI27: 46146 | BJ27: 36/MET/27CN00087 | BK27: 46146 | BL27: 0 | BM27: 0 | BN27: 0 | BO27: =-6935.77-3600 -> -10535.77 | BP27: 0 | BQ27: =AY27+BN27+BO27+BP27+BC27+BG27+BM27+BL27 -> 318270.73 | BR27: =BQ27-AM27 -> -0.27 | BS27: =IF(BR27>=0,"Positive Margin","Negative Margin") -> Negative Margin | BT27: DN & CN Issued | BU27: =AY27-Y27-Q27-AA27-T27+BC27 -> 0 | BV27: =IF(BU27<0, "Negative Margin at Inception", "Positive Margin at Inception") -> Positive Margin at Inception | BW27: =IFERROR(BR27/BQ27,"0") -> -8.4833437e-07 | BX27: =IF(BW27<1%,"Less Than 1%",IF(BW27>2%,"More than 2%",IF(BW27>=1%,"1% - 2%"))) -> Less Than 1% | BY27: =BO27+BP27 -> -10535.77 | BZ27: =AL27+AK27 -> -10535.5 | CA27: =BY27-BZ27 -> -0.27 | CB27: =BO27 -> -10535.77 | CC27: =AK27 -> -10535.5 | CD27: =CB27-CC27 -> -0.27 | CE27: Marketplace (Metal Waste) | CF27: =_xlfn.XLOOKUP(G27,'Supplier Metrics'!C:C,'Supplier Metrics'!H:H) -> Trader With Warehouse | CG27: =TEXT(AN27,"mmm-yy") -> May-26 | CH27: =AM27-AL27 -> 318271 | CI27: =BQ27-BP27 -> 318270.73 | CJ27: =INT((D27- IF(MONTH(D27) >= 4, DATE(YEAR(D27), 4, 1), DATE(YEAR(D27)-1, 4, 1))) / 7) + 1 -> 5 | CK27: {=_xlfn.XLOOKUP(N27,'Material Metrics'!B:B,'Material Metrics'!C:D)} -> Ferrous | CL27: Ferrous | CM27: =_xlfn.XLOOKUP(AR27,Receivables!B:B,Receivables!D:D) -> Gaurav Uttam Kothimeere | CN27: =AY27-Q27 -> 0 | CO27: =CN27-AB27 -> 0 | CP27: =BQ27-AM27 -> -0.27 | CQ27: =AY27*118% -> 387991.67 | CR27: =Q27*118% -> 387991.67 | CS27: =CB27*118% -> -12432.209 | CT27: =CC27*118% -> -12431.89 | CU27: =(CQ27-CS27)-(CR27-CT27) -> 0.3186 | CV27: Telangana - HO | CW27: Telangana - HO | CX27: =MID(G27,3,10) -> CFUPK7292B | CY27: =MID(AR27,3,10) -> AAACE1741P | CZ27: No | DA27: 0 | DB27: 0 | DC27: 0 | DD27: 0 | DE27: =AE27+AJ27+AK27 -> -10535.5 | DF27: =BN27+BO27+BC27 -> -10535.77
B28: ="Q" & IF(ROUNDUP(MONTH(D28)/3,0)-1=0,4,ROUNDUP(MONTH(D28)/3,0)-1) -> Q1 | C28: =TEXT(AN28,"mmm-yy") -> May-26 | D28: 46143 | E28: SH04263007 | F28: NISHA TRADING COMPANY | G28: 27CFUPK7292B1ZZ | H28: 1433 | I28: 46143 | J28: 26-27/PUR/001663 | K28: 46143 | L28: MH | M28: MH48CQ4111 | N28: Boring & Turning | O28: 12340 | P28: 31.3 | Q28: =O28*P28 -> 386242 | R28: 0 | S28: =O28-R28 -> 12340 | T28: 0 | U28: 0 | V28: 0 | W28: 0 | X28: 0 | Y28: 0 | Z28: 0 | AA28: 0 | AB28: =Y28+AA28+Z28 -> 0 | AC28: 0 | AD28: 0 | AE28: 0 | AF28: 36/MET/27VC00077 | AG28: 46146 | AH28: 36/MET/27VC00083 | AI28: 46147 | AJ28: 0 | AK28: =-18967.7966101695-8638 -> -27605.797 | AL28: 0 | AM28: =Q28+AB28+AL28+AK28+AJ28+T28+AE28 -> 358636.2 | AN28: 46143 | AO28: 36/MET/27IN00025 | AP28: 832139000044272012 | AQ28: ARCELORMITTAL NIPPON STEEL INDIA PRIVATE LIMITED | AR28: 27AAACE1741P1ZH | AS28: Palghar,Maharashtra,401208 | AT28: Raighadh | AU28: Maharashtra | AV28: 102416383321 | AW28: 12340 | AX28: 31.3 | AY28: =AW28*AX28 -> 386242 | AZ28: =AW28=O28 -> TRUE | BA28: 0 | BB28: =AW28-BA28 -> 12340 | BC28: 0 | BD28: Regular | BE28: 0 | BF28: 0 | BG28: 0 | BH28: 36/MET/27CN00089 | BI28: 46146 | BJ28: 0 | BK28: 0 | BL28: 0 | BM28: 0 | BN28: 0 | BO28: -18967.8 | BP28: 0 | BQ28: =AY28+BN28+BO28+BP28+BC28+BG28+BM28+BL28 -> 367274.2 | BR28: =BQ28-AM28 -> 8637.9966 | BS28: =IF(BR28>=0,"Positive Margin","Negative Margin") -> Positive Margin | BT28: DN & CN Issued | BU28: =AY28-Y28-Q28-AA28-T28+BC28 -> 0 | BV28: =IF(BU28<0, "Negative Margin at Inception", "Positive Margin at Inception") -> Positive Margin at Inception | BW28: =IFERROR(BR28/BQ28,"0") -> 0.023519203 | BX28: =IF(BW28<1%,"Less Than 1%",IF(BW28>2%,"More than 2%",IF(BW28>=1%,"1% - 2%"))) -> More than 2% | BY28: =BO28+BP28 -> -18967.8 | BZ28: =AL28+AK28 -> -27605.797 | CA28: =BY28-BZ28 -> 8637.9966 | CB28: =BO28 -> -18967.8 | CC28: =AK28 -> -27605.797 | CD28: =CB28-CC28 -> 8637.9966 | CE28: Marketplace (Metal Waste) | CF28: =_xlfn.XLOOKUP(G28,'Supplier Metrics'!C:C,'Supplier Metrics'!H:H) -> Trader With Warehouse | CG28: =TEXT(AN28,"mmm-yy") -> May-26 | CH28: =AM28-AL28 -> 358636.2 | CI28: =BQ28-BP28 -> 367274.2 | CJ28: =INT((D28- IF(MONTH(D28) >= 4, DATE(YEAR(D28), 4, 1), DATE(YEAR(D28)-1, 4, 1))) / 7) + 1 -> 5 | CK28: {=_xlfn.XLOOKUP(N28,'Material Metrics'!B:B,'Material Metrics'!C:D)} -> Ferrous | CL28: Ferrous | CM28: =_xlfn.XLOOKUP(AR28,Receivables!B:B,Receivables!D:D) -> Gaurav Uttam Kothimeere | CN28: =AY28-Q28 -> 0 | CO28: =CN28-AB28 -> 0 | CP28: =BQ28-AM28 -> 8637.9966 | CQ28: =AY28*118% -> 455765.56 | CR28: =Q28*118% -> 455765.56 | CS28: =CB28*118% -> -22382.004 | CT28: =CC28*118% -> -32574.84 | CU28: =(CQ28-CS28)-(CR28-CT28) -> -10192.836 | CV28: Telangana - HO | CW28: Telangana - HO | CX28: =MID(G28,3,10) -> CFUPK7292B | CY28: =MID(AR28,3,10) -> AAACE1741P | CZ28: No | DA28: 0 | DB28: 0 | DC28: 0 | DD28: 0 | DE28: =AE28+AJ28+AK28 -> -27605.797 | DF28: =BN28+BO28+BC28 -> -18967.8
B29: ="Q" & IF(ROUNDUP(MONTH(D29)/3,0)-1=0,4,ROUNDUP(MONTH(D29)/3,0)-1) -> Q1 | C29: =TEXT(AN29,"mmm-yy") -> May-26 | D29: 46143 | E29: SH04263008 | F29: NISHA TRADING COMPANY | G29: 27CFUPK7292B1ZZ | H29: 1432 | I29: 46143 | J29: 26-27/PUR/001664 | K29: 46143 | L29: MH | M29: MH04GC6627 | N29: Boring & Turning | O29: 11100 | P29: 31.3 | Q29: =O29*P29 -> 347430 | R29: 0 | S29: =O29-R29 -> 11100 | T29: 0 | U29: 0 | V29: 0 | W29: 0 | X29: 0 | Y29: 0 | Z29: 0 | AA29: 0 | AB29: =Y29+AA29+Z29 -> 0 | AC29: 0 | AD29: 0 | AE29: 0 | AF29: 36/MET/27VC00078 | AG29: 46146 | AH29: 36/MET/27VC00084 | AI29: 46147 | AJ29: 0 | AK29: =-3361.6186440678-7770 -> -11131.619 | AL29: 0 | AM29: =Q29+AB29+AL29+AK29+AJ29+T29+AE29 -> 336298.38 | AN29: 46143 | AO29: 36/MET/27IN00026 | AP29: 832139000044272012 | AQ29: ARCELORMITTAL NIPPON STEEL INDIA PRIVATE LIMITED | AR29: 27AAACE1741P1ZH | AS29: Palghar,Maharashtra,401208 | AT29: Raighadh | AU29: Maharashtra | AV29: 162416392804 | AW29: 11100 | AX29: 31.3 | AY29: =AW29*AX29 -> 347430 | AZ29: =AW29=O29 -> TRUE | BA29: 0 | BB29: =AW29-BA29 -> 11100 | BC29: 0 | BD29: Regular | BE29: 0 | BF29: 0 | BG29: 0 | BH29: 36/MET/27CN00090 | BI29: 46146 | BJ29: 0 | BK29: 0 | BL29: 0 | BM29: 0 | BN29: 0 | BO29: -3361.62 | BP29: 0 | BQ29: =AY29+BN29+BO29+BP29+BC29+BG29+BM29+BL29 -> 344068.38 | BR29: =BQ29-AM29 -> 7769.9986 | BS29: =IF(BR29>=0,"Positive Margin","Negative Margin") -> Positive Margin | BT29: DN & CN Issued | BU29: =AY29-Y29-Q29-AA29-T29+BC29 -> 0 | BV29: =IF(BU29<0, "Negative Margin at Inception", "Positive Margin at Inception") -> Positive Margin at Inception | BW29: =IFERROR(BR29/BQ29,"0") -> 0.022582716 | BX29: =IF(BW29<1%,"Less Than 1%",IF(BW29>2%,"More than 2%",IF(BW29>=1%,"1% - 2%"))) -> More than 2% | BY29: =BO29+BP29 -> -3361.62 | BZ29: =AL29+AK29 -> -11131.619 | CA29: =BY29-BZ29 -> 7769.9986 | CB29: =BO29 -> -3361.62 | CC29: =AK29 -> -11131.619 | CD29: =CB29-CC29 -> 7769.9986 | CE29: Marketplace (Metal Waste) | CF29: =_xlfn.XLOOKUP(G29,'Supplier Metrics'!C:C,'Supplier Metrics'!H:H) -> Trader With Warehouse | CG29: =TEXT(AN29,"mmm-yy") -> May-26 | CH29: =AM29-AL29 -> 336298.38 | CI29: =BQ29-BP29 -> 344068.38 | CJ29: =INT((D29- IF(MONTH(D29) >= 4, DATE(YEAR(D29), 4, 1), DATE(YEAR(D29)-1, 4, 1))) / 7) + 1 -> 5 | CK29: {=_xlfn.XLOOKUP(N29,'Material Metrics'!B:B,'Material Metrics'!C:D)} -> Ferrous | CL29: Ferrous | CM29: =_xlfn.XLOOKUP(AR29,Receivables!B:B,Receivables!D:D) -> Gaurav Uttam Kothimeere | CN29: =AY29-Q29 -> 0 | CO29: =CN29-AB29 -> 0 | CP29: =BQ29-AM29 -> 7769.9986 | CQ29: =AY29*118% -> 409967.4 | CR29: =Q29*118% -> 409967.4 | CS29: =CB29*118% -> -3966.7116 | CT29: =CC29*118% -> -13135.31 | CU29: =(CQ29-CS29)-(CR29-CT29) -> -9168.5984 | CV29: Telangana - HO | CW29: Telangana - HO | CX29: =MID(G29,3,10) -> CFUPK7292B | CY29: =MID(AR29,3,10) -> AAACE1741P | CZ29: No | DA29: 0 | DB29: 0 | DC29: 0 | DD29: 0 | DE29: =AE29+AJ29+AK29 -> -11131.619 | DF29: =BN29+BO29+BC29 -> -3361.62
B30: ="Q" & IF(ROUNDUP(MONTH(D30)/3,0)-1=0,4,ROUNDUP(MONTH(D30)/3,0)-1) -> Q1 | C30: =TEXT(AN30,"mmm-yy") -> May-26 | D30: 46145 | E30: SH05260302 | F30: NISHA TRADING COMPANY | G30: 27CFUPK7292B1ZZ | H30: 1435 | I30: 46145 | J30: 26-27/PUR/001703 | K30: 46145 | L30: MH | M30: MH46BB0277 | N30: Boring & Turning | O30: 9210 | P30: 31.3 | Q30: =O30*P30 -> 288273 | R30: 0 | S30: =O30-R30 -> 9210 | T30: 0 | U30: 0 | V30: 0 | W30: 0 | X30: 0 | Y30: 0 | Z30: 0 | AA30: 0 | AB30: =Y30+AA30+Z30 -> 0 | AC30: 0 | AD30: 0 | AE30: 0 | AF30: 36/MET/27VC00081 | AG30: 46146 | AH30: 36/MET/27VC00085 &90 | AI30: 46147 | AJ30: 0 | AK30: =-1252-6419-4841 -> -12512 | AL30: 0 | AM30: =Q30+AB30+AL30+AK30+AJ30+T30+AE30 -> 275761 | AN30: 46145 | AO30: 36/MET/27IN00027 | AP30: 832139000044272012 | AQ30: ARCELORMITTAL NIPPON STEEL INDIA PRIVATE LIMITED | AR30: 27AAACE1741P1ZH | AS30: Palghar,Maharashtra,401208 | AT30: Raighadh | AU30: Maharashtra | AV30: 192418152528 | AW30: 9210 | AX30: 31.3 | AY30: =AW30*AX30 -> 288273 | AZ30: =AW30=O30 -> TRUE | BA30: 0 | BB30: =AW30-BA30 -> 9210 | BC30: 0 | BD30: Regular | BE30: 0 | BF30: 0 | BG30: 0 | BH30: 36/MET/27CN00094 | BI30: 46146 | BJ30: 36/MET/27CN00097 | BK30: 46148 | BL30: 0 | BM30: 0 | BN30: 0 | BO30: =-1252-4841 -> -6093 | BP30: 0 | BQ30: =AY30+BN30+BO30+BP30+BC30+BG30+BM30+BL30 -> 282180 | BR30: =BQ30-AM30 -> 6419 | BS30: =IF(BR30>=0,"Positive Margin","Negative Margin") -> Positive Margin | BT30: DN & CN Issued | BU30: =AY30-Y30-Q30-AA30-T30+BC30 -> 0 | BV30: =IF(BU30<0, "Negative Margin at Inception", "Positive Margin at Inception") -> Positive Margin at Inception | BW30: =IFERROR(BR30/BQ30,"0") -> 0.022747891 | BX30: =IF(BW30<1%,"Less Than 1%",IF(BW30>2%,"More than 2%",IF(BW30>=1%,"1% - 2%"))) -> More than 2% | BY30: =BO30+BP30 -> -6093 | BZ30: =AL30+AK30 -> -12512 | CA30: =BY30-BZ30 -> 6419 | CB30: =BO30 -> -6093 | CC30: =AK30 -> -12512 | CD30: =CB30-CC30 -> 6419 | CE30: Marketplace (Metal Waste) | CF30: =_xlfn.XLOOKUP(G30,'Supplier Metrics'!C:C,'Supplier Metrics'!H:H) -> Trader With Warehouse | CG30: =TEXT(AN30,"mmm-yy") -> May-26 | CH30: =AM30-AL30 -> 275761 | CI30: =BQ30-BP30 -> 282180 | CJ30: =INT((D30- IF(MONTH(D30) >= 4, DATE(YEAR(D30), 4, 1), DATE(YEAR(D30)-1, 4, 1))) / 7) + 1 -> 5 | CK30: {=_xlfn.XLOOKUP(N30,'Material Metrics'!B:B,'Material Metrics'!C:D)} -> Ferrous | CL30: Ferrous | CM30: =_xlfn.XLOOKUP(AR30,Receivables!B:B,Receivables!D:D) -> Gaurav Uttam Kothimeere | CN30: =AY30-Q30 -> 0 | CO30: =CN30-AB30 -> 0 | CP30: =BQ30-AM30 -> 6419 | CQ30: =AY30*118% -> 340162.14 | CR30: =Q30*118% -> 340162.14 | CS30: =CB30*118% -> -7189.74 | CT30: =CC30*118% -> -14764.16 | CU30: =(CQ30-CS30)-(CR30-CT30) -> -7574.42 | CV30: Telangana - HO | CW30: Telangana - HO | CX30: =MID(G30,3,10) -> CFUPK7292B | CY30: =MID(AR30,3,10) -> AAACE1741P | CZ30: No | DA30: 0 | DB30: 0 | DC30: 0 | DD30: 0 | DE30: =AE30+AJ30+AK30 -> -12512 | DF30: =BN30+BO30+BC30 -> -6093
B31: ="Q" & IF(ROUNDUP(MONTH(D31)/3,0)-1=0,4,ROUNDUP(MONTH(D31)/3,0)-1) -> Q1 | C31: =TEXT(AN31,"mmm-yy") -> May-26 | D31: 46145 | E31: SH05260304 | F31: NISHA TRADING COMPANY | G31: 27CFUPK7292B1ZZ | H31: 1437 | I31: 46145 | J31: 26-27/PUR/001709 | K31: 46146 | L31: MH | M31: MH47AS9186 | N31: Boring & Turning | O31: 10410 | P31: 31.3 | Q31: =O31*P31 -> 325833 | R31: 0 | S31: =O31-R31 -> 10410 | T31: 0 | U31: 0 | V31: 0 | W31: 0 | X31: 0 | Y31: 0 | Z31: 0 | AA31: 0 | AB31: =Y31+AA31+Z31 -> 0 | AC31: 0 | AD31: 0 | AE31: 0 | AF31: 36/MET/27VC00087 | AG31: 46147 | AH31: 36/MET/27VC00092 & 93 | AI31: 46148 | AJ31: 0 | AK31: =-7280-313-6240 -> -13833 | AL31: 0 | AM31: =Q31+AB31+AL31+AK31+AJ31+T31+AE31 -> 312000 | AN31: 46146 | AO31: 36/MET/27IN00029 | AP31: 832139000044272012 | AQ31: ARCELORMITTAL NIPPON STEEL INDIA PRIVATE LIMITED | AR31: 27AAACE1741P1ZH | AS31: Kandivali West Maharashtra 400104 | AT31: Raighadh | AU31: Maharashtra | AV31: 142418349860 | AW31: 10410 | AX31: 31.3 | AY31: =AW31*AX31 -> 325833 | AZ31: =AW31=O31 -> TRUE | BA31: 0 | BB31: =AW31-BA31 -> 10410 | BC31: 0 | BD31: Regular | BE31: 0 | BF31: 0 | BG31: 0 | BH31: 36/MET/27CN00100 | BI31: 46148 | BJ31: 36/MET/27CN00099 | BK31: 46148 | BL31: 0 | BM31: 0 | BN31: 0 | BO31: =-313-6240 -> -6553 | BP31: 0 | BQ31: =AY31+BN31+BO31+BP31+BC31+BG31+BM31+BL31 -> 319280 | BR31: =BQ31-AM31 -> 7280 | BS31: =IF(BR31>=0,"Positive Margin","Negative Margin") -> Positive Margin | BT31: DN & CN Issued | BU31: =AY31-Y31-Q31-AA31-T31+BC31 -> 0 | BV31: =IF(BU31<0, "Negative Margin at Inception", "Positive Margin at Inception") -> Positive Margin at Inception | BW31: =IFERROR(BR31/BQ31,"0") -> 0.022801303 | BX31: =IF(BW31<1%,"Less Than 1%",IF(BW31>2%,"More than 2%",IF(BW31>=1%,"1% - 2%"))) -> More than 2% | BY31: =BO31+BP31 -> -6553 | BZ31: =AL31+AK31 -> -13833 | CA31: =BY31-BZ31 -> 7280 | CB31: =BO31 -> -6553 | CC31: =AK31 -> -13833 | CD31: =CB31-CC31 -> 7280 | CE31: Marketplace (Metal Waste) | CF31: =_xlfn.XLOOKUP(G31,'Supplier Metrics'!C:C,'Supplier Metrics'!H:H) -> Trader With Warehouse | CG31: =TEXT(AN31,"mmm-yy") -> May-26 | CH31: =AM31-AL31 -> 312000 | CI31: =BQ31-BP31 -> 319280 | CJ31: =INT((D31- IF(MONTH(D31) >= 4, DATE(YEAR(D31), 4, 1), DATE(YEAR(D31)-1, 4, 1))) / 7) + 1 -> 5 | CK31: {=_xlfn.XLOOKUP(N31,'Material Metrics'!B:B,'Material Metrics'!C:D)} -> Ferrous | CL31: Ferrous | CM31: =_xlfn.XLOOKUP(AR31,Receivables!B:B,Receivables!D:D) -> Gaurav Uttam Kothimeere | CN31: =AY31-Q31 -> 0 | CO31: =CN31-AB31 -> 0 | CP31: =BQ31-AM31 -> 7280 | CQ31: =AY31*118% -> 384482.94 | CR31: =Q31*118% -> 384482.94 | CS31: =CB31*118% -> -7732.54 | CT31: =CC31*118% -> -16322.94 | CU31: =(CQ31-CS31)-(CR31-CT31) -> -8590.4 | CV31: Telangana - HO | CW31: Telangana - HO | CX31: =MID(G31,3,10) -> CFUPK7292B | CY31: =MID(AR31,3,10) -> AAACE1741P | CZ31: No | DA31: 0 | DB31: 0 | DC31: 0 | DD31: 0 | DE31: =AE31+AJ31+AK31 -> -13833 | DF31: =BN31+BO31+BC31 -> -6553
