Workbook

Sheet Summary
D2: =TEXT(D4, "mmm-yy") -> Apr-26 | E2: =TEXT(E4, "mmm-yy") -> May-26 | F2: =TEXT(F4, "mmm-yy") -> Jun-26 | G2: =TEXT(G4, "mmm-yy") -> Jul-26 | H2: =TEXT(H4, "mmm-yy") -> Aug-26 | I2: =TEXT(I4, "mmm-yy") -> Sep-26 | J2: =TEXT(J4, "mmm-yy") -> Oct-26 | K2: =TEXT(K4, "mmm-yy") -> Nov-26 | ... O2: =TEXT(O4, "mmm-yy") -> Mar-27
D3: 30 | E3: 31 | F3: 21 | G3: 0 | H3: 0 | I3: 0 | J3: 0 | K3: 0 | L3: 0 | M3: 0 | N3: 0 | O3: 0 | P3: =SUM(D3:O3) -> 82
C4: Marketplace (Rewerse) | D4: 46113 | E4: 46143 | F4: 46174 | G4: 46204 | H4: 46235 | I4: 46266 | J4: 46296 | K4: 46327 | L4: 46357 | M4: 46388 | N4: 46419 | O4: 46447 | P4: FY 2026-27
C5: Quantity (MT) | D5: 66.68 | E5: =SUMIFS(Details!$BB$4:$BB$78,Details!$C$4:$C$78,Summary!E$4)/1000 -> 104.875 | F5: =SUMIFS(Details!$BB$4:$BB$78,Details!$C$4:$C$78,Summary!F$4)/1000 -> 78.795 | G5: =SUMIFS(Details!$BB$4:$BB$78,Details!$C$4:$C$78,Summary!G$4)/1000 -> 0 | H5: =SUMIFS(Details!$BB$4:$BB$78,Details!$C$4:$C$78,Summary!H$4)/1000 -> 0 | I5: =SUMIFS(Details!$BB$4:$BB$78,Details!$C$4:$C$78,Summary!I$4)/1000 -> 0 | J5: =SUMIFS(Details!$BB$4:$BB$78,Details!$C$4:$C$78,Summary!J$4)/1000 -> 0 | K5: =SUMIFS(Details!$BB$4:$BB$78,Details!$C$4:$C$78,Summary!K$4)/1000 -> 0 | L5: =SUMIFS(Details!$BB$4:$BB$78,Details!$C$4:$C$78,Summary!L$4)/1000 -> 0 | ... O5: =SUMIFS(Details!$BB$4:$BB$78,Details!$C$4:$C$78,Summary!O$4)/1000 -> 0 | P5: =SUM(D5:O5) -> 250.35 | Q5: =Details!BB79/1000 -> 250.35 | R5: =P5-Q5 -> 0
C6: Net Revenue | D6: 3196586.2 | E6: =SUMIFS(Details!$BO$4:$BO$78,Details!$C$4:$C$78,Summary!E$4) -> 5917999.6 | F6: =SUMIFS(Details!$BO$4:$BO$78,Details!$C$4:$C$78,Summary!F$4) -> 5820545.2 | G6: =SUMIFS(Details!$BO$4:$BO$78,Details!$C$4:$C$78,Summary!G$4) -> 0 | H6: =SUMIFS(Details!$BO$4:$BO$78,Details!$C$4:$C$78,Summary!H$4) -> 0 | I6: =SUMIFS(Details!$BO$4:$BO$78,Details!$C$4:$C$78,Summary!I$4) -> 0 | J6: =SUMIFS(Details!$BO$4:$BO$78,Details!$C$4:$C$78,Summary!J$4) -> 0 | K6: =SUMIFS(Details!$BO$4:$BO$78,Details!$C$4:$C$78,Summary!K$4) -> 0 | L6: =SUMIFS(Details!$BO$4:$BO$78,Details!$C$4:$C$78,Summary!L$4) -> 0 | ... O6: =SUMIFS(Details!$BO$4:$BO$78,Details!$C$4:$C$78,Summary!O$4) -> 0 | P6: =SUM(D6:O6) -> 14935131 | Q6: =Details!BO79 -> 14964433 | R6: =P6-Q6 -> -29302.12
C7: Purchases | D7: 2734490 | E7: =SUMIFS(Details!$AM$4:$AM$78,Details!$C$4:$C$78,Summary!E$4)-SUMIFS(Details!$AB$4:$AB$78,Details!$C$4:$C$78,Summary!E$4) -> 4656790 | F7: =SUMIFS(Details!$AM$4:$AM$78,Details!$C$4:$C$78,Summary!F$4)-SUMIFS(Details!$AB$4:$AB$78,Details!$C$4:$C$78,Summary!F$4) -> 4432995 | G7: =SUMIFS(Details!$AM$4:$AM$78,Details!$C$4:$C$78,Summary!G$4)-SUMIFS(Details!$AB$4:$AB$78,Details!$C$4:$C$78,Summary!G$4) -> 0 | H7: =SUMIFS(Details!$AM$4:$AM$78,Details!$C$4:$C$78,Summary!H$4)-SUMIFS(Details!$AB$4:$AB$78,Details!$C$4:$C$78,Summary!H$4) -> 0 | I7: =SUMIFS(Details!$AM$4:$AM$78,Details!$C$4:$C$78,Summary!I$4)-SUMIFS(Details!$AB$4:$AB$78,Details!$C$4:$C$78,Summary!I$4) -> 0 | J7: =SUMIFS(Details!$AM$4:$AM$78,Details!$C$4:$C$78,Summary!J$4)-SUMIFS(Details!$AB$4:$AB$78,Details!$C$4:$C$78,Summary!J$4) -> 0 | K7: =SUMIFS(Details!$AM$4:$AM$78,Details!$C$4:$C$78,Summary!K$4)-SUMIFS(Details!$AB$4:$AB$78,Details!$C$4:$C$78,Summary!K$4) -> 0 | L7: =SUMIFS(Details!$AM$4:$AM$78,Details!$C$4:$C$78,Summary!L$4)-SUMIFS(Details!$AB$4:$AB$78,Details!$C$4:$C$78,Summary!L$4) -> 0 | ... O7: =SUMIFS(Details!$AM$4:$AM$78,Details!$C$4:$C$78,Summary!O$4)-SUMIFS(Details!$AB$4:$AB$78,Details!$C$4:$C$78,Summary!O$4) -> 0 | P7: =SUM(D7:O7) -> 11824275 | Q7: =Details!P80 -> 11824275 | R7: =P7-Q7 -> 0
C8: Gross Margin | D8: =D6-D7 -> 462096.25 | E8: =E6-E7 -> 1261209.6 | F8: =F6-F7 -> 1387550.2 | G8: =G6-G7 -> 0 | H8: =H6-H7 -> 0 | I8: =I6-I7 -> 0 | J8: =J6-J7 -> 0 | K8: =K6-K7 -> 0 | ... O8: =O6-O7 -> 0 | P8: =SUM(D8:O8) -> 3110856.1
C9: Gross Margin (%) | D9: =IFERROR((D8/D6),0) -> 0.14455929 | E9: =IFERROR((E8/E6),0) -> 0.21311417 | F9: =IFERROR((F8/F6),0) -> 0.23838836 | G9: =IFERROR((G8/G6),0) -> 0 | H9: =IFERROR((H8/H6),0) -> 0 | I9: =IFERROR((I8/I6),0) -> 0 | J9: =IFERROR((J8/J6),0) -> 0 | K9: =IFERROR((K8/K6),0) -> 0 | ... P9: =IFERROR((P8/P6),0) -> 0.20829118
C10: Transportation Charges | D10: =SUMIFS(Details!$AB$4:$AB$78,Details!$C$4:$C$78,Summary!D$4) -> 0 | E10: =SUMIFS(Details!$AB$4:$AB$78,Details!$C$4:$C$78,Summary!E$4) -> 0 | F10: =SUMIFS(Details!$AB$4:$AB$78,Details!$C$4:$C$78,Summary!F$4) -> 0 | G10: =SUMIFS(Details!$AB$4:$AB$78,Details!$C$4:$C$78,Summary!G$4) -> 0 | H10: =SUMIFS(Details!$AB$4:$AB$78,Details!$C$4:$C$78,Summary!H$4) -> 0 | I10: =SUMIFS(Details!$AB$4:$AB$78,Details!$C$4:$C$78,Summary!I$4) -> 0 | J10: =SUMIFS(Details!$AB$4:$AB$78,Details!$C$4:$C$78,Summary!J$4) -> 0 | K10: =SUMIFS(Details!$AB$4:$AB$78,Details!$C$4:$C$78,Summary!K$4) -> 0 | ... O10: =SUMIFS(Details!$AB$4:$AB$78,Details!$C$4:$C$78,Summary!O$4) -> 0 | P10: =SUM(D10:O10) -> 0 | Q10: =Details!AB79 -> 0 | R10: =P10-Q10 -> 0
C11: Operational Cost | D11: =Details!AC83 -> 857135.62 | E11: =Details!AC84 -> 1348111.9 | F11: =Details!AC85 -> 1112867.4 | G11: =SUMIFS(Details!$AC$4:$AC$86,Details!$C$4:$C$86,Summary!G$4) -> 0 | H11: =SUMIFS(Details!$AC$4:$AC$86,Details!$C$4:$C$86,Summary!H$4) -> 0 | I11: =SUMIFS(Details!$AC$4:$AC$86,Details!$C$4:$C$86,Summary!I$4) -> 0 | J11: =SUMIFS(Details!$AC$4:$AC$86,Details!$C$4:$C$86,Summary!J$4) -> 0 | K11: =SUMIFS(Details!$AC$4:$AC$86,Details!$C$4:$C$86,Summary!K$4) -> 0 | L11: =SUMIFS(Details!$AC$4:$AC$86,Details!$C$4:$C$86,Summary!L$4) -> 0 | M11: =SUMIFS(Details!$AC$4:$AC$86,Details!$C$4:$C$86,Summary!M$4) -> 0 | N11: =SUMIFS(Details!$AC$4:$AC$86,Details!$C$4:$C$86,Summary!N$4) -> 0 | O11: =SUMIFS(Details!$AC$4:$AC$86,Details!$C$4:$C$86,Summary!O$4) -> 0 | P11: =SUM(D11:O11) -> 3318114.9
C12: Net Margin | D12: =D6-D7-D10-D11 -> -395039.37 | E12: =E6-E7-E10-E11 -> -86902.286 | F12: =F6-F7-F10-F11 -> 274682.81 | G12: =G6-G7-G10-G11 -> 0 | H12: =H6-H7-H10-H11 -> 0 | I12: =I6-I7-I10-I11 -> 0 | J12: =J6-J7-J10-J11 -> 0 | K12: =K6-K7-K10-K11 -> 0 | ... O12: =O6-O7-O10-O11 -> 0 | P12: =SUM(D12:O12) -> -207258.85
C13: Net Margin (%) | D13: =IFERROR((D12/D6),0) -> -0.12358164 | E13: =IFERROR((E12/E6),0) -> -0.014684402 | F13: =IFERROR((F12/F6),0) -> 0.047191937 | G13: =IFERROR((G12/G6),0) -> 0 | H13: =IFERROR((H12/H6),0) -> 0 | I13: =IFERROR((I12/I6),0) -> 0 | J13: =IFERROR((J12/J6),0) -> 0 | K13: =IFERROR((K12/K6),0) -> 0 | ... P13: =IFERROR((P12/P6),0) -> -0.01387727
C14: Other Income | D14: =SUMIFS(Details!$BO$83:$BO$86,Details!$C$83:$C$86,Summary!D$4) -> 0 | E14: =SUMIFS(Details!$BO$83:$BO$86,Details!$C$83:$C$86,Summary!E$4) -> 0 | F14: =SUMIFS(Details!$BO$83:$BO$86,Details!$C$83:$C$86,Summary!F$4) -> 0 | G14: =SUMIFS(Details!$BO$83:$BO$86,Details!$C$83:$C$86,Summary!G$4) -> 0 | H14: =SUMIFS(Details!$BO$83:$BO$86,Details!$C$83:$C$86,Summary!H$4) -> 0 | I14: =SUMIFS(Details!$BO$83:$BO$86,Details!$C$83:$C$86,Summary!I$4) -> 0 | J14: =SUMIFS(Details!$BO$83:$BO$86,Details!$C$83:$C$86,Summary!J$4) -> 0 | K14: =SUMIFS(Details!$BO$83:$BO$86,Details!$C$83:$C$86,Summary!K$4) -> 0 | ... O14: =SUMIFS(Details!$BO$83:$BO$86,Details!$C$83:$C$86,Summary!O$4) -> 0 | P14: =SUM(D14:O14) -> 0
C15: Transport Charges (%) | D15: =IFERROR((D10/D6),0) -> 0 | E15: =IFERROR((E10/E6),0) -> 0 | F15: =IFERROR((F10/F6),0) -> 0 | G15: =IFERROR((G10/G6),0) -> 0 | H15: =IFERROR((H10/H6),0) -> 0 | I15: =IFERROR((I10/I6),0) -> 0 | J15: =IFERROR((J10/J6),0) -> 0 | K15: =IFERROR((K10/K6),0) -> 0 | ... P15: =IFERROR((P10/P6),0) -> 0
C16: Revenue Per Kg | D16: =+D6/(D5*1000) -> 47.939206 | E16: =+E6/(E5*1000) -> 56.429078 | F16: =+F6/(F5*1000) -> 73.869475 | G16: =+G6/(G5*1000) -> #DIV/0! | H16: =+H6/(H5*1000) -> #DIV/0! | I16: =+I6/(I5*1000) -> #DIV/0! | J16: =+J6/(J5*1000) -> #DIV/0! | K16: =+K6/(K5*1000) -> #DIV/0! | ... P16: =+P6/(P5*1000) -> 59.657004
C17: Purchase Cost Per Kg | D17: =+D7/(D5*1000) -> 41.009148 | E17: =+E7/(E5*1000) -> 44.403242 | F17: =+F7/(F5*1000) -> 56.259852 | G17: =+G7/(G5*1000) -> #DIV/0! | H17: =+H7/(H5*1000) -> #DIV/0! | I17: =+I7/(I5*1000) -> #DIV/0! | J17: =+J7/(J5*1000) -> #DIV/0! | K17: =+K7/(K5*1000) -> #DIV/0! | ... P17: =+P7/(P5*1000) -> 47.230977
C18: Transportation Charges Per Kg | D18: =D10/(D5*1000) -> 0 | E18: =E10/(E5*1000) -> 0 | F18: =F10/(F5*1000) -> 0 | G18: =G10/(G5*1000) -> #DIV/0! | H18: =H10/(H5*1000) -> #DIV/0! | I18: =I10/(I5*1000) -> #DIV/0! | J18: =J10/(J5*1000) -> #DIV/0! | K18: =K10/(K5*1000) -> #DIV/0! | ... P18: =P10/(P5*1000) -> 0
C19: No. of Transactions | D19: {=IFERROR(ROWS(_xlfn.UNIQUE(_xlfn._xlws.FILTER(Details!$AO$5:$AO$78, (Details!$C$5:$C$78)=Summary!D$2))),0)-1} -> 6 | E19: {=IFERROR(ROWS(_xlfn.UNIQUE(_xlfn._xlws.FILTER(Details!$AO$5:$AO$78, (Details!$C$5:$C$78)=Summary!E$2))),0)} -> 11 | F19: {=IFERROR(ROWS(_xlfn.UNIQUE(_xlfn._xlws.FILTER(Details!$AO$5:$AO$78, (Details!$C$5:$C$78)=Summary!F$2))),0)} -> 8 | G19: {=IFERROR(ROWS(_xlfn.UNIQUE(_xlfn._xlws.FILTER(Details!$AO$5:$AO$78, (Details!$C$5:$C$78)=Summary!G$2))),0)} -> 0 | H19: {=IFERROR(ROWS(_xlfn.UNIQUE(_xlfn._xlws.FILTER(Details!$AO$5:$AO$78, (Details!$C$5:$C$78)=Summary!H$2))),0)} -> 0 | I19: {=IFERROR(ROWS(_xlfn.UNIQUE(_xlfn._xlws.FILTER(Details!$AO$5:$AO$78, (Details!$C$5:$C$78)=Summary!I$2))),0)} -> 0 | J19: {=IFERROR(ROWS(_xlfn.UNIQUE(_xlfn._xlws.FILTER(Details!$AO$5:$AO$78, (Details!$C$5:$C$78)=Summary!J$2))),0)} -> 0 | K19: {=IFERROR(ROWS(_xlfn.UNIQUE(_xlfn._xlws.FILTER(Details!$AO$5:$AO$78, (Details!$C$5:$C$78)=Summary!K$2))),0)} -> 0 | L19: {=IFERROR(ROWS(_xlfn.UNIQUE(_xlfn._xlws.FILTER(Details!$AO$5:$AO$78, (Details!$C$5:$C$78)=Summary!L$2))),0)} -> 0 | ... O19: {=IFERROR(ROWS(_xlfn.UNIQUE(_xlfn._xlws.FILTER(Details!$AO$5:$AO$78, (Details!$C$5:$C$78)=Summary!O$2))),0)} -> 0 | P19: =SUM(D19:O19) -> 25
C20: No. of Sellers (Aggregators) | D20: {=IFERROR(ROWS(_xlfn.UNIQUE(_xlfn._xlws.FILTER(MID(Details!$G$5:$G$78,3,10), (Details!$C$5:$C$78)=Summary!D$2))),0)} -> 1 | E20: {=IFERROR(ROWS(_xlfn.UNIQUE(_xlfn._xlws.FILTER(MID(Details!$G$5:$G$78,3,10), (Details!$C$5:$C$78)=Summary!E$2))),0)} -> 1 | F20: {=IFERROR(ROWS(_xlfn.UNIQUE(_xlfn._xlws.FILTER(MID(Details!$G$5:$G$78,3,10), (Details!$C$5:$C$78)=Summary!F$2))),0)} -> 1 | G20: {=IFERROR(ROWS(_xlfn.UNIQUE(_xlfn._xlws.FILTER(MID(Details!$G$5:$G$78,3,10), (Details!$C$5:$C$78)=Summary!G$2))),0)} -> 0 | H20: {=IFERROR(ROWS(_xlfn.UNIQUE(_xlfn._xlws.FILTER(MID(Details!$G$5:$G$78,3,10), (Details!$C$5:$C$78)=Summary!H$2))),0)} -> 0 | I20: {=IFERROR(ROWS(_xlfn.UNIQUE(_xlfn._xlws.FILTER(MID(Details!$G$5:$G$78,3,10), (Details!$C$5:$C$78)=Summary!I$2))),0)} -> 0 | J20: {=IFERROR(ROWS(_xlfn.UNIQUE(_xlfn._xlws.FILTER(MID(Details!$G$5:$G$78,3,10), (Details!$C$5:$C$78)=Summary!J$2))),0)} -> 0 | K20: {=IFERROR(ROWS(_xlfn.UNIQUE(_xlfn._xlws.FILTER(MID(Details!$G$5:$G$78,3,10), (Details!$C$5:$C$78)=Summary!K$2))),0)} -> 0 | ... O20: {=IFERROR(ROWS(_xlfn.UNIQUE(_xlfn._xlws.FILTER(MID(Details!$G$5:$G$78,3,10), (Details!$C$5:$C$78)=Summary!O$2))),0)} -> 0 | P20: ='Supplier Metrics'!E2 -> 1
C21: No. of Buyers (Recyclers) | D21: {=IFERROR(ROWS(_xlfn.UNIQUE(_xlfn._xlws.FILTER(MID(Details!$AR$5:$AR$78,3,10), (Details!$C$5:$C$78)=Summary!D$2))),0)} -> 1 | E21: {=IFERROR(ROWS(_xlfn.UNIQUE(_xlfn._xlws.FILTER(MID(Details!$AR$5:$AR$78,3,10), (Details!$C$5:$C$78)=Summary!E$2))),0)} -> 1 | F21: {=IFERROR(ROWS(_xlfn.UNIQUE(_xlfn._xlws.FILTER(MID(Details!$AR$5:$AR$78,3,10), (Details!$C$5:$C$78)=Summary!F$2))),0)} -> 3 | G21: {=IFERROR(ROWS(_xlfn.UNIQUE(_xlfn._xlws.FILTER(MID(Details!$AR$5:$AR$78,3,10), (Details!$C$5:$C$78)=Summary!G$2))),0)} -> 0 | H21: {=IFERROR(ROWS(_xlfn.UNIQUE(_xlfn._xlws.FILTER(MID(Details!$AR$5:$AR$78,3,10), (Details!$C$5:$C$78)=Summary!H$2))),0)} -> 0 | I21: {=IFERROR(ROWS(_xlfn.UNIQUE(_xlfn._xlws.FILTER(MID(Details!$AR$5:$AR$78,3,10), (Details!$C$5:$C$78)=Summary!I$2))),0)} -> 0 | J21: {=IFERROR(ROWS(_xlfn.UNIQUE(_xlfn._xlws.FILTER(MID(Details!$AR$5:$AR$78,3,10), (Details!$C$5:$C$78)=Summary!J$2))),0)} -> 0 | K21: {=IFERROR(ROWS(_xlfn.UNIQUE(_xlfn._xlws.FILTER(MID(Details!$AR$5:$AR$78,3,10), (Details!$C$5:$C$78)=Summary!K$2))),0)} -> 0 | ... O21: {=IFERROR(ROWS(_xlfn.UNIQUE(_xlfn._xlws.FILTER(MID(Details!$AR$5:$AR$78,3,10), (Details!$C$5:$C$78)=Summary!O$2))),0)} -> 0 | P21: ='Buyer Metrics'!B3 -> 3
C22: Full Rejections | D22: {=IFERROR(ROWS(_xlfn.UNIQUE(_xlfn._xlws.FILTER(Details!$E$5:$E$78,(Details!$C$5:$C$78=Summary!D$2)*(Details!$BR$5:$BR$78=Summary!$C$22)))),0)} -> 0 | E22: {=IFERROR(ROWS(_xlfn.UNIQUE(_xlfn._xlws.FILTER(Details!$E$5:$E$78,(Details!$C$5:$C$78=Summary!E$2)*(Details!$BR$5:$BR$78=Summary!$C$22)))),0)} -> 0 | F22: {=IFERROR(ROWS(_xlfn.UNIQUE(_xlfn._xlws.FILTER(Details!$E$5:$E$78,(Details!$C$5:$C$78=Summary!F$2)*(Details!$BR$5:$BR$78=Summary!$C$22)))),0)} -> 0 | G22: {=IFERROR(ROWS(_xlfn.UNIQUE(_xlfn._xlws.FILTER(Details!$E$5:$E$78,(Details!$C$5:$C$78=Summary!G$2)*(Details!$BR$5:$BR$78=Summary!$C$22)))),0)} -> 0 | H22: {=IFERROR(ROWS(_xlfn.UNIQUE(_xlfn._xlws.FILTER(Details!$E$5:$E$78,(Details!$C$5:$C$78=Summary!H$2)*(Details!$BR$5:$BR$78=Summary!$C$22)))),0)} -> 0 | I22: {=IFERROR(ROWS(_xlfn.UNIQUE(_xlfn._xlws.FILTER(Details!$E$5:$E$78,(Details!$C$5:$C$78=Summary!I$2)*(Details!$BR$5:$BR$78=Summary!$C$22)))),0)} -> 0 | J22: {=IFERROR(ROWS(_xlfn.UNIQUE(_xlfn._xlws.FILTER(Details!$E$5:$E$78,(Details!$C$5:$C$78=Summary!J$2)*(Details!$BR$5:$BR$78=Summary!$C$22)))),0)} -> 0 | K22: {=IFERROR(ROWS(_xlfn.UNIQUE(_xlfn._xlws.FILTER(Details!$E$5:$E$78,(Details!$C$5:$C$78=Summary!K$2)*(Details!$BR$5:$BR$78=Summary!$C$22)))),0)} -> 0 | ... O22: {=IFERROR(ROWS(_xlfn.UNIQUE(_xlfn._xlws.FILTER(Details!$E$5:$E$78,(Details!$C$5:$C$78=Summary!O$2)*(Details!$BR$5:$BR$78=Summary!$C$22)))),0)} -> 0 | P22: =SUM(D22:O22) -> 0
C23: Receivable | D23: 6409082 | E23: 11960843 | F23: 13783192 | G23: 0 | H23: 0 | I23: 0 | J23: 0 | K23: 0 | L23: 0 | M23: 0 | N23: 0 | O23: 0 | P23: =F23 -> 13783192
C24: DSO (Days) | D24: =IFERROR(((D23/(D6*1.18))*D3),0) -> 50.973992 | E24: =IFERROR(((E23/(E6*1.18))*E3),0) -> 53.096579 | F24: =IFERROR(((F23/(F6*1.18))*F3),0) -> 42.142804 | G24: =IFERROR(((G23/(G6*1.18))*G3),0) -> 0 | H24: =IFERROR(((H23/(H6*1.18))*H3),0) -> 0 | I24: =IFERROR(((I23/(I6*1.18))*I3),0) -> 0 | J24: =IFERROR(((J23/(J6*1.18))*J3),0) -> 0 | K24: =IFERROR(((K23/(K6*1.18))*K3),0) -> 0 | ... O24: =IFERROR(((O23/(O6*1.18))*O3),0) -> 0 | P24: =IFERROR(((P23)/(P6*1.18)*P3),0) -> 64.13168
C25: Payable | D25: -6728200.6 | E25: -5803401.5 | F25: -6406913.3 | G25: 0 | H25: 0 | I25: 0 | J25: 0 | K25: 0 | L25: 0 | M25: 0 | N25: 0 | O25: 0 | P25: =F25 -> -6406913.3
C26: DPO (Days) | D26: =IFERROR(((D25/(D7*1.18))*D3),0) -> -62.554973 | E26: =IFERROR(((E25/(E7*1.18))*E3),0) -> -32.739772 | F26: =IFERROR(((F25/(F7*1.18))*F3),0) -> -25.721062 | G26: =IFERROR(((G25/(G7*1.18))*G3),0) -> 0 | H26: =IFERROR(((H25/(H7*1.18))*H3),0) -> 0 | I26: =IFERROR(((I25/(I7*1.18))*I3),0) -> 0 | J26: =IFERROR(((J25/(J7*1.18))*J3),0) -> 0 | K26: =IFERROR(((K25/(K7*1.18))*K3),0) -> 0 | ... P26: =IFERROR(((P25/(P7*1.18))*P3),0) -> -37.653571
C27: Working Capital Days | D27: =D24-D26 -> 113.52897 | E27: =E24-E26 -> 85.836351 | F27: =F24-F26 -> 67.863865 | G27: =G24-G26 -> 0 | H27: =H24-H26 -> 0 | I27: =I24-I26 -> 0 | J27: =J24-J26 -> 0 | K27: =K24-K26 -> 0 | ... P27: =P24-P26 -> 101.78525
C28: Credit Notes (Value - Incl. Prov) | D28: 81963.75 | E28: =-SUMIFS(Details!$BW$4:$BW$78,Details!$C$4:$C$78,Summary!E4) -> 143785.43 | F28: =-SUMIFS(Details!$BW$4:$BW$78,Details!$C$4:$C$78,Summary!F4) -> 149244.75 | G28: =-SUMIFS(Details!$BW$4:$BW$78,Details!$C$4:$C$78,Summary!G4) -> 0 | H28: =-SUMIFS(Details!$BW$4:$BW$78,Details!$C$4:$C$78,Summary!H4) -> 0 | I28: =-SUMIFS(Details!$BW$4:$BW$78,Details!$C$4:$C$78,Summary!I4) -> 0 | J28: =-SUMIFS(Details!$BW$4:$BW$78,Details!$C$4:$C$78,Summary!J4) -> 0 | K28: =-SUMIFS(Details!$BW$4:$BW$78,Details!$C$4:$C$78,Summary!K4) -> 0 | L28: =-SUMIFS(Details!$BW$4:$BW$78,Details!$C$4:$C$78,Summary!L4) -> 0 | ... O28: =-SUMIFS(Details!$BW$4:$BW$78,Details!$C$4:$C$78,Summary!O4) -> 0 | P28: =SUM(D28:O28) -> 374993.93 | Q28: =(-Details!BM79-Details!BN79) -> 345691.82 | R28: =P28-Q28 -> 29302.12
C29: Credit Notes (% to Revenue) | D29: =+D28/D6 -> 0.025641026 | E29: =+E28/E6 -> 0.02429629 | F29: =+F28/F6 -> 0.025641026 | G29: =+G28/G6 -> #DIV/0! | H29: =+H28/H6 -> #DIV/0! | I29: =+I28/I6 -> #DIV/0! | J29: =+J28/J6 -> #DIV/0! | K29: =+K28/K6 -> #DIV/0! | ... P29: =+P28/P6 -> 0.025108178
C30: Debit Notes (Value - Incl. Prov) | D30: =-SUMIFS(Details!$BX$4:$BX$78,Details!$C$4:$C$78,Summary!D4) -> 0 | E30: =-SUMIFS(Details!$BX$4:$BX$78,Details!$C$4:$C$78,Summary!E4) -> 0 | F30: =-SUMIFS(Details!$BX$4:$BX$78,Details!$C$4:$C$78,Summary!F4) -> 0 | G30: =-SUMIFS(Details!$BX$4:$BX$78,Details!$C$4:$C$78,Summary!G4) -> 0 | H30: =-SUMIFS(Details!$BX$4:$BX$78,Details!$C$4:$C$78,Summary!H4) -> 0 | I30: =-SUMIFS(Details!$BX$4:$BX$78,Details!$C$4:$C$78,Summary!I4) -> 0 | J30: =-SUMIFS(Details!$BX$4:$BX$78,Details!$C$4:$C$78,Summary!J4) -> 0 | K30: =-SUMIFS(Details!$BX$4:$BX$78,Details!$C$4:$C$78,Summary!K4) -> 0 | ... O30: =-SUMIFS(Details!$BX$4:$BX$78,Details!$C$4:$C$78,Summary!O4) -> 0 | P30: =SUM(D30:O30) -> 0 | Q30: =(-Details!AK79-Details!AL79) -> 0 | R30: =P30-Q30 -> 0
C31: Debit Notes (% to Purchase) | D31: =(D30/D7) -> 0 | E31: =(E30/E7) -> 0 | F31: =(F30/F7) -> 0 | G31: =(G30/G7) -> #DIV/0! | H31: =(H30/(H7+H10)) -> #DIV/0! | I31: =(I30/(I7+I10)) -> #DIV/0! | J31: =(J30/(J7+J10)) -> #DIV/0! | K31: =(K30/(K7+K10)) -> #DIV/0! | L31: =(L30/(L7+L10)) -> #DIV/0! | M31: =(M30/(M7+M10)) -> #DIV/0! | N31: =(N30/(N7+N10)) -> #DIV/0! | O31: =(O30/(O7+O10)) -> #DIV/0! | P31: =(P30/(P7+P10)) -> 0
C32: Indirect Expenses | D32: 226775 | E32: 226775 | F32: =E32*F3/30 -> 158742.5 | P32: =SUM(D32:F32) -> 612292.5
C33: Margin after Indirect Expenses | D33: =D12-D32 -> -621814.37 | E33: =E12-E32 -> -313677.29 | F33: =F12-F32 -> 115940.31 | G33: =G12-G32 -> 0 | H33: =H12-H32 -> 0 | I33: =I12-I32 -> 0 | J33: =J12-J32 -> 0 | K33: =K12-K32 -> 0 | ... P33: =P12-P32 -> -819551.35
C34: Margin % | D34: =D33/D6 -> -0.19452451 | E34: =E33/E6 -> -0.053003939 | F34: =F33/F6 -> 0.019919149 | G34: =G33/G6 -> #DIV/0! | H34: =H33/H6 -> #DIV/0! | I34: =I33/I6 -> #DIV/0! | J34: =J33/J6 -> #DIV/0! | K34: =K33/K6 -> #DIV/0! | ... P34: =P33/P6 -> -0.054874065
C37: KPI's without Provisions | D37: =D4 -> 46113 | E37: =E4 -> 46143 | F37: =F4 -> 46174 | G37: =G4 -> 46204 | H37: =H4 -> 46235 | I37: =I4 -> 46266 | J37: =J4 -> 46296 | K37: =K4 -> 46327 | ... P37: =P4 -> FY 2026-27
C38: Sales without Provision | D38: =D6+D57 -> 3207647.5 | E38: =E6+E57 -> 6056973.4 | F38: =F6+F57 -> 5969790 | G38: =G6+G57 -> 0 | H38: =H6+H57 -> 0 | I38: =I6+I57 -> 0 | J38: =J6+J57 -> 0 | K38: =K6+K57 -> 0 | ... O38: =O6+O57 -> 0 | P38: =SUM(D38:O38) -> 15234411
C39: Purchases without Provision | D39: =D7+D10+D56 -> 2734490 | E39: =E7+E10+E56 -> 4656790 | F39: =F7+F10+F56 -> 4432995 | G39: =G7+G10+G56 -> 0 | H39: =H7+H10+H56 -> 0 | I39: =I7+I10+I56 -> 0 | J39: =J7+J10+J56 -> 0 | K39: =K7+K10+K56 -> 0 | ... O39: =O7+O10+O56 -> 0 | P39: =SUM(D39:O39) -> 11824275
C40: Contribution without Provision | D40: =D38-D39 -> 473157.5 | E40: =E38-E39 -> 1400183.4 | F40: =F38-F39 -> 1536795 | G40: =G38-G39 -> 0 | H40: =H38-H39 -> 0 | I40: =I38-I39 -> 0 | J40: =J38-J39 -> 0 | K40: =K38-K39 -> 0 | ... P40: =P38-P39 -> 3410135.9
C41: Contribution (%) | D41: =D40/D38 -> 0.14750919 | E41: =E40/E38 -> 0.23116883 | F41: =F40/F38 -> 0.25742865 | G41: =G40/G38 -> #DIV/0! | H41: =H40/H38 -> #DIV/0! | I41: =I40/I38 -> #DIV/0! | J41: =J40/J38 -> #DIV/0! | K41: =K40/K38 -> #DIV/0! | ... P41: =P40/P38 -> 0.22384429
C43: Business Trends | D43: =D4 -> 46113 | E43: =E4 -> 46143 | F43: =F4 -> 46174 | G43: =G4 -> 46204 | H43: =H4 -> 46235 | I43: =I4 -> 46266 | J43: =J4 -> 46296 | K43: =K4 -> 46327 | ... P43: =P4 -> FY 2026-27
C44: Sales-Revenue (MoM) | D44: =IFERROR(((D6/C6)-1),0) -> 0 | E44: =IFERROR(((E6/D6)-1),0) -> 0.85134988 | F44: =IFERROR(((F6/E6)-1),0) -> -0.016467442 | G44: =IFERROR(((G6/F6)-1),0) -> -1 | H44: =IFERROR(((H6/G6)-1),0) -> 0 | I44: =IFERROR(((I6/H6)-1),0) -> 0 | J44: =IFERROR(((J6/I6)-1),0) -> 0 | K44: =IFERROR(((K6/J6)-1),0) -> 0 | ... O44: =IFERROR(((O6/N6)-1),0) -> 0 | P44: 0
C45: Sales-Volume (MoM) | D45: =IFERROR(((D5/C5)-1),0) -> 0 | E45: =IFERROR(((E5/D5)-1),0) -> 0.57281044 | F45: =IFERROR(((F5/E5)-1),0) -> -0.248677 | G45: =IFERROR(((G5/F5)-1),0) -> -1 | H45: =IFERROR(((H5/G5)-1),0) -> 0 | I45: =IFERROR(((I5/H5)-1),0) -> 0 | J45: =IFERROR(((J5/I5)-1),0) -> 0 | K45: =IFERROR(((K5/J5)-1),0) -> 0 | ... O45: =IFERROR(((O5/N5)-1),0) -> 0 | P45: 0
C46: Sales-Transactions (MoM) | D46: =IFERROR(((D19/C19)-1),0) -> 0 | E46: =IFERROR(((E19/D19)-1),0) -> 0.83333333 | F46: =IFERROR(((F19/E19)-1),0) -> -0.27272727 | G46: =IFERROR(((G19/F19)-1),0) -> -1 | H46: =IFERROR(((#REF!/G19)-1),0) -> 0 | I46: =IFERROR(((I19/#REF!)-1),0) -> 0 | J46: =IFERROR(((J19/I19)-1),0) -> 0 | K46: =IFERROR(((K19/J19)-1),0) -> 0 | L46: =IFERROR(((L19/K19)-1),0) -> 0 | M46: =IFERROR(((M19/L19)-1),0) -> 0 | N46: =IFERROR(((N19/M19)-1),0) -> 0 | O46: =IFERROR(((O19/N19)-1),0) -> 0 | P46: 0
C48: Loss Making Transactions | D48: =D43 -> 46113 | E48: =E43 -> 46143 | F48: =F43 -> 46174 | G48: =G43 -> 46204 | H48: =H43 -> 46235 | I48: =I43 -> 46266 | J48: =J43 -> 46296 | K48: =K43 -> 46327 | ... P48: =P43 -> FY 2026-27
C49: No of LMI | D49: 0 | E49: 0 | F49: 0 | G49: 0 | H49: 0 | I49: 0 | J49: 0 | K49: 0 | L49: 0 | M49: 0 | N49: 0 | O49: 0 | P49: =SUM(D49:O49) -> 0
C50: Value of LMI | D50: 0 | E50: 0 | F50: 0 | G50: 0 | H50: 0 | I50: 0 | J50: 0 | K50: 0 | L50: 0 | M50: 0 | N50: 0 | O50: 0 | P50: =SUM(D50:O50) -> 0
C51: No of loss Making Transactions | D51: 0 | E51: 0 | F51: 0 | G51: 0 | H51: 0 | I51: 0 | J51: 0 | K51: 0 | L51: 0 | M51: 0 | N51: 0 | O51: 0 | P51: =SUM(D51:O51) -> 0
C52: % of Loss Making Transactions | D52: =IFERROR(D51/D19,0) -> 0 | E52: =IFERROR(E51/E19,0) -> 0 | F52: =IFERROR(F51/F19,0) -> 0 | G52: =IFERROR(G51/G19,0) -> 0 | H52: =IFERROR(H51/#REF!,0) -> 0 | I52: =IFERROR(I51/I19,0) -> 0 | J52: =IFERROR(J51/J19,0) -> 0 | K52: =IFERROR(K51/K19,0) -> 0 | L52: =IFERROR(L51/L19,0) -> 0 | M52: =IFERROR(M51/M19,0) -> 0 | N52: =IFERROR(N51/N19,0) -> 0 | O52: =IFERROR(O51/O19,0) -> 0 | P52: =IFERROR(P51/P19,0) -> 0
C53: Value Of Making Transactions | D53: 0 | E53: 0 | F53: 0 | G53: 0 | H53: 0 | I53: 0 | J53: 0 | K53: 0 | L53: 0 | M53: 0 | N53: 0 | O53: 0 | P53: =SUM(D53:O53) -> 0
C55: CN & DN Provisions | D55: =D48 -> 46113 | E55: =E48 -> 46143 | F55: =F48 -> 46174 | G55: =G48 -> 46204 | H55: =H48 -> 46235 | I55: =I48 -> 46266 | J55: =J48 -> 46296 | K55: =K48 -> 46327 | ... P55: =P48 -> FY 2026-27 | Q55: =ROUND(Q56-Q57,2)-ROUND(P40-P12,2) -> -3318114.9
C56: DN Provision | D56: =-SUMIFS(Details!$AL$4:$AL$78,Details!$C$4:$C$78,Summary!D55) -> 0 | E56: =-SUMIFS(Details!$AL$4:$AL$78,Details!$C$4:$C$78,Summary!E55) -> 0 | F56: =-SUMIFS(Details!$AL$4:$AL$78,Details!$C$4:$C$78,Summary!F55) -> 0 | G56: =-SUMIFS(Details!$AL$4:$AL$78,Details!$C$4:$C$78,Summary!G55) -> 0 | H56: =-SUMIFS(Details!$AL$4:$AL$78,Details!$C$4:$C$78,Summary!H55) -> 0 | I56: =-SUMIFS(Details!$AL$4:$AL$78,Details!$C$4:$C$78,Summary!I55) -> 0 | J56: =-SUMIFS(Details!$AL$4:$AL$78,Details!$C$4:$C$78,Summary!J55) -> 0 | K56: =-SUMIFS(Details!$AL$4:$AL$78,Details!$C$4:$C$78,Summary!K55) -> 0 | ... O56: =-SUMIFS(Details!$AL$4:$AL$78,Details!$C$4:$C$78,Summary!O55) -> 0 | P56: =SUM(D56:O56) -> 0 | Q56: =Details!AL79 -> 0 | R56: =Q56+P56 -> 0
C57: CN Provision | D57: =-SUMIFS(Details!$BN$4:$BN$78,Details!$C$4:$C$78,Summary!D55) -> 11061.25 | E57: =-SUMIFS(Details!$BN$4:$BN$78,Details!$C$4:$C$78,Summary!E55) -> 138973.88 | F57: =-SUMIFS(Details!$BN$4:$BN$78,Details!$C$4:$C$78,Summary!F55) -> 149244.75 | G57: =-SUMIFS(Details!$BN$4:$BN$78,Details!$C$4:$C$78,Summary!G55) -> 0 | H57: =-SUMIFS(Details!$BN$4:$BN$78,Details!$C$4:$C$78,Summary!H55) -> 0 | I57: =-SUMIFS(Details!$BN$4:$BN$78,Details!$C$4:$C$78,Summary!I55) -> 0 | J57: =-SUMIFS(Details!$BN$4:$BN$78,Details!$C$4:$C$78,Summary!J55) -> 0 | K57: =-SUMIFS(Details!$BN$4:$BN$78,Details!$C$4:$C$78,Summary!K55) -> 0 | ... O57: =-SUMIFS(Details!$BN$4:$BN$78,Details!$C$4:$C$78,Summary!O55) -> 0 | P57: =SUM(D57:O57) -> 299279.88 | Q57: =Details!BN79 -> -299279.88 | R57: =Q57+P57 -> 0
C59: Qty Returned | D59: =D55 -> 46113 | E59: =E55 -> 46143 | F59: =F55 -> 46174 | G59: =G55 -> 46204 | H59: =H55 -> 46235 | I59: =I55 -> 46266 | J59: =J55 -> 46296 | K59: =K55 -> 46327 | ... P59: =P55 -> FY 2026-27
D60: =SUMIFS(Details!$R$5:$R$78,Details!$C$5:$C$78,Summary!D59)/1000 -> 0 | E60: =SUMIFS(Details!$R$5:$R$78,Details!$C$5:$C$78,Summary!E59)/1000 -> 0 | F60: =SUMIFS(Details!$R$5:$R$78,Details!$C$5:$C$78,Summary!F59)/1000 -> 0 | G60: =SUMIFS(Details!$R$5:$R$78,Details!$C$5:$C$78,Summary!G59)/1000 -> 0 | H60: =SUMIFS(Details!$R$5:$R$78,Details!$C$5:$C$78,Summary!H59)/1000 -> 0 | I60: =SUMIFS(Details!$R$5:$R$78,Details!$C$5:$C$78,Summary!I59)/1000 -> 0 | J60: =SUMIFS(Details!$R$5:$R$78,Details!$C$5:$C$78,Summary!J59)/1000 -> 0 | K60: =SUMIFS(Details!$R$5:$R$78,Details!$C$5:$C$78,Summary!K59)/1000 -> 0 | ... O60: =SUMIFS(Details!$R$5:$R$78,Details!$C$5:$C$78,Summary!O59)/1000 -> 0 | P60: =SUM(D60:O60) -> 0
C62: Margins | D62: 45748 | E62: 45778 | F62: 45809 | G62: 45839 | H62: 45870 | I62: 45901 | J62: 45931 | K62: 45962 | L62: 45992 | M62: 46023 | N62: 46054 | O62: 46082 | P62: FY 2025-26
C63: Gross Margin | D63: =SUMIFS(Details!$CL$5:$CL$78,Details!$C$5:$C$78,Summary!D$62) -> 0 | E63: =SUMIFS(Details!$CL$5:$CL$78,Details!$C$5:$C$78,Summary!E$62) -> 0 | F63: =SUMIFS(Details!$CL$5:$CL$78,Details!$C$5:$C$78,Summary!F$62) -> 0 | G63: =SUMIFS(Details!$CL$5:$CL$78,Details!$C$5:$C$78,Summary!G$62) -> 0 | H63: =SUMIFS(Details!$CL$5:$CL$78,Details!$C$5:$C$78,Summary!H$62) -> 0 | I63: =SUMIFS(Details!$CL$5:$CL$78,Details!$C$5:$C$78,Summary!I$62) -> 0 | J63: =SUMIFS(Details!$CL$5:$CL$78,Details!$C$5:$C$78,Summary!J$62) -> 0 | K63: =SUMIFS(Details!$CL$5:$CL$78,Details!$C$5:$C$78,Summary!K$62) -> 0 | ... O63: =SUMIFS(Details!$CL$5:$CL$78,Details!$C$5:$C$78,Summary!O$62) -> 0 | P63: =SUM(D63:O63) -> 0
C64: Recykal Margin | D64: =SUMIFS(Details!$CM$5:$CM$78,Details!$C$5:$C$78,Summary!D$62) -> 0 | E64: =SUMIFS(Details!$CM$5:$CM$78,Details!$C$5:$C$78,Summary!E$62) -> 0 | F64: =SUMIFS(Details!$CM$5:$CM$78,Details!$C$5:$C$78,Summary!F$62) -> 0 | G64: =SUMIFS(Details!$CM$5:$CM$78,Details!$C$5:$C$78,Summary!G$62) -> 0 | H64: =SUMIFS(Details!$CM$5:$CM$78,Details!$C$5:$C$78,Summary!H$62) -> 0 | I64: =SUMIFS(Details!$CM$5:$CM$78,Details!$C$5:$C$78,Summary!I$62) -> 0 | J64: =SUMIFS(Details!$CM$5:$CM$78,Details!$C$5:$C$78,Summary!J$62) -> 0 | K64: =SUMIFS(Details!$CM$5:$CM$78,Details!$C$5:$C$78,Summary!K$62) -> 0 | ... O64: =SUMIFS(Details!$CM$5:$CM$78,Details!$C$5:$C$78,Summary!O$62) -> 0 | P64: =SUM(D64:O64) -> 0
C65: Net Margin | D65: =SUMIFS(Details!$CN$5:$CN$78,Details!$C$5:$C$78,Summary!D$62) -> 0 | E65: =SUMIFS(Details!$CN$5:$CN$78,Details!$C$5:$C$78,Summary!E$62) -> 0 | F65: =SUMIFS(Details!$CN$5:$CN$78,Details!$C$5:$C$78,Summary!F$62) -> 0 | G65: =SUMIFS(Details!$CN$5:$CN$78,Details!$C$5:$C$78,Summary!G$62) -> 0 | H65: =SUMIFS(Details!$CN$5:$CN$78,Details!$C$5:$C$78,Summary!H$62) -> 0 | I65: =SUMIFS(Details!$CN$5:$CN$78,Details!$C$5:$C$78,Summary!I$62) -> 0 | J65: =SUMIFS(Details!$CN$5:$CN$78,Details!$C$5:$C$78,Summary!J$62) -> 0 | K65: =SUMIFS(Details!$CN$5:$CN$78,Details!$C$5:$C$78,Summary!K$62) -> 0 | ... O65: =SUMIFS(Details!$CN$5:$CN$78,Details!$C$5:$C$78,Summary!O$62) -> 0 | P65: =SUM(D65:O65) -> 0
C67: Financial with GST | D67: Sales | E67: Purchases
C68: =Details!P91 -> 46194 | D68: =SUMIFS(Details!$BO$5:$BO$78,Details!$D$5:$D$78,Summary!C68)*118% -> 652529.08 | E68: =SUMIFS(Details!$AM$5:$AM$78,Details!$D$5:$D$78,Summary!C68)*118% -> 522132.3
C69: =TEXT(C68,"mmm-yy") -> Jun-26 | D69: =SUMIFS(Details!$BO$5:$BO$78,Details!$C$5:$C$78,Summary!C69)*118% -> 6868243.4 | E69: =SUMIFS(Details!$AM$5:$AM$78,Details!$C$5:$C$78,Summary!C69)*118% -> 5230934.1
C70: Fy 2025-26 | D70: =Details!BO79*118% -> 17658031 | E70: =Details!AM79*118% -> 13952644

Sheet Details
B3: Raw Data -Rewerse | F3: Purchase Details | U3: Logistic Details of the transaction | AF3: Debit Notes to Suppliers | AM3: Sales Details | BD3: DN to Customer | BH3: Credit Notes from Customers | BM3: -0.025 | BV3: CN & DN Checks | CE3: Without Provisions | CK3: Margin Buckets | CN3: Financials with GST
B4: Quarter | C4: Month | D4: Date | E4: Shipment ID | F4: Supplier Name | G4: GST Reg No. | H4: Vendor Invoice No. | I4: Vendor Invoice Date | J4: P V No. | K4: P V Date | L4: State (Origin) | M4: Vehicle No. | N4: Material | O4: Qty (Kg) | P4: Price/Kg | Q4: Purchase Price | R4: Return Qty | S4: Net Qty | T4: Basic Customs Duty | U4: Transporter Name | V4: LR NO/BILL NO | W4: J V No. | X4: JV Date | Y4: Logistics cost | Z4: Debit note on logistic cost | AA4: Logistics Provision | AB4: Total Logistics Cost | AC4: Operational Cost | AD4: Cost/Kg. | AE4: Divertion/Internal | AF4: Debit Note No. | AG4: Debit Note Date. | AH4: Debit Note No. 2 | AI4: Debit Note Date. 2 | AJ4: Full Debit Note | AK4: Actual Debit Note | AL4: Provision for DN | AM4: Total Cost | AN4: Inv. Date | AO4: Inv. No. | AP4: Customer ID | AQ4: Buyer Name | AR4: Buyer GST Number | AS4: Location (Origin) | AT4: Location (Destination) | AU4: State (Destination) | AV4: E-WayBill Number | AW4: Qty(Kg) | AX4: Rate/Kg | AY4: Amount | AZ4: Qty Check | BA4: Return Qty | BB4: Net Qty | BC4: Divertion/Internal | BD4: Return Type | BE4: Date : DN to Buyer | BF4: DN to Buyer | BG4: Amount | BH4: Credit Note No:1 | BI4: CN Date. No:1 | BJ4: Credit Note No:2 | BK4: CN Date. No:2 | BL4: Full Credit Notes | BM4: Actual Credit Note | BN4: Provision for CN | BO4: Net Revenue | BP4: Margin | BQ4: Reamrks - Margin | BR4: Remarks | BS4: LMI @ Inception | BT4: Remarks @ Inception | BU4: Margin (%) | BV4: Margin Bucket | BW4: Total CN(Inc.Provisions) | BX4: Total DN(Inc.Provisions) | BY4: Check | BZ4: Actaul CN | CA4: Actual DN | CB4: Check | CC4: Material-Short Form | CD4: Supplier Type | CE4: Month | CF4: Cost | CG4: Revenue | CH4: Week No: | CI4: Category (Material) | CJ4: Broad Category | CK4: POC Name | CL4: Gross Margin | CM4: Recykal Margin | CN4: Net Margin | CO4: Sales | CP4: Purchases | CQ4: Credit Note | CR4: Debit Note | CS4: Margin | CT4: Bill Branch | CU4: Inv Branch | CV4: Vendor PAN No | CW4: Customer PAN No | CX4: GST TDS Applicability | CY4: Cash Discount(Provision) | CZ4: Cash Discount | DA4: Cash Discount. No | DB4: CD Date
B5: ="Q" & IF(ROUNDUP(MONTH(D5)/3,0)-1=0,4,ROUNDUP(MONTH(D5)/3,0)-1) -> Q1 | C5: =TEXT(AN5,"mmm-yy") -> Apr-26 | D5: 46118 | E5: SH042606010 | F5: BLACK GOLD RECYCLING PRIVATE LIMITED | G5: 27AAMCB5608A1ZX | H5: 25/PUN/INV0270 | I5: 46118 | J5: 26-27/PUR/000107 | K5: 46118 | L5: MH | M5: DD01AC9819 | N5: PET Bottle Scrap Baled - Clear | O5: 9217 | P5: 39.5 | Q5: =O5*P5 -> 364071.5 | R5: 0 | S5: =O5-R5 -> 9217 | T5: 0 | U5: 0 | V5: 0 | W5: 0 | X5: 0 | Y5: 0 | Z5: 0 | AA5: 0 | AB5: =Y5+AA5+Z5 -> 0 | AC5: 0 | AD5: =IFERROR((Q5+AB5)/S5,0) -> 39.5 | AE5: 0 | AF5: 0 | AG5: 0 | AH5: 0 | AI5: 0 | AJ5: 0 | AK5: 0 | AL5: 0 | AM5: =Q5+AB5+AL5+AK5+AJ5+T5+AE5 -> 364071.5 | AN5: 46118 | AO5: 36/REW/27IN00001 | AP5: 832139000052985017 | AQ5: DALMIA POLYPRO INDUSTRIES PRIVATE LIMITED (27) | AR5: 27AAACD5406E1Z3 | AS5: Koregaon Bhima Maharashtra 412216 | AT5: Dindori | AU5: Maharashtra | AV5: 0 | AW5: 9217 | AX5: 46 | AY5: =AW5*AX5 -> 423982 | AZ5: =AW5=O5 -> TRUE | BA5: 0 | BB5: =AW5-BA5 -> 9217 | BC5: 0 | BD5: Regular | BE5: 0 | BF5: 0 | BG5: 0 | BH5: 0 | BI5: 0 | BJ5: 0 | BK5: 0 | BL5: 0 | BM5: 0 | BN5: =AY5*$BM$3 -> -10599.55 | BO5: =AY5+BL5+BM5+BN5+BC5+BG5 -> 413382.45 | BP5: =BO5-AM5 -> 49310.95 | BQ5: =IF(BP5>=0,"Positive Margin","Negative Margin") -> Positive Margin | BR5: CN Provision | BS5: =AY5-Y5-Q5-AA5-T5+BC5 -> 59910.5 | BT5: =IF(BS5<0, "Negative Margin at Inception", "Positive Margin at Inception") -> Positive Margin at Inception | BU5: =IFERROR(BP5/BO5,"0") -> 0.11928651 | BV5: =IF(BU5<1%,"Less Than 1%",IF(BU5>2%,"More than 2%",IF(BU5>=1%,"1% - 2%"))) -> More than 2% | BW5: =BM5+BN5 -> -10599.55 | BX5: =AL5+AK5 -> 0 | BY5: =BW5-BX5 -> -10599.55 | BZ5: =BM5 -> 0 | CA5: =AK5 -> 0 | CB5: =BZ5-CA5 -> 0 | CC5: Marketplace (Rewerse) | CD5: 0 | CE5: =TEXT(AN5,"mmm-yy") -> Apr-26 | CF5: =AM5-AL5-AA5 -> 364071.5 | CG5: =BO5-BN5 -> 423982 | CH5: =INT((D5- IF(MONTH(D5) >= 4, DATE(YEAR(D5), 4, 1), DATE(YEAR(D5)-1, 4, 1))) / 7) + 1 -> 1 | CI5: Plastic | CJ5: Plastic | CK5: =_xlfn.XLOOKUP(AR5,receivables!B:B,receivables!D:D) -> Neelesh Dixit | CL5: =AY5-Q5 -> 59910.5 | CM5: =CL5-Y5+Z5 -> 59910.5 | CN5: =BO5-AM5 -> 49310.95 | CO5: =AY5*118% -> 500298.76 | CP5: =-Q5*118% -> -429604.37 | CQ5: =-BZ5*118% -> 0 | CR5: =-CA5*118% -> 0 | CS5: =SUM(CO5:CR5) -> 70694.39 | CT5: Telangana - HO | CU5: Telangana - HO | CV5: =MID(G5,3,10) -> AAMCB5608A | CW5: =MID(AR5,3,10) -> AAACD5406E | CX5: 0 | CY5: 0 | CZ5: 0 | DA5: 0 | DB5: 0
B6: ="Q" & IF(ROUNDUP(MONTH(D6)/3,0)-1=0,4,ROUNDUP(MONTH(D6)/3,0)-1) -> Q1 | C6: =TEXT(AN6,"mmm-yy") -> Apr-26 | D6: 46118 | E6: SH042606010 | F6: BLACK GOLD RECYCLING PRIVATE LIMITED | G6: 27AAMCB5608A1ZX | H6: 25/PUN/INV0270 | I6: 46118 | J6: 26-27/PUR/000107 | K6: 46118 | L6: MH | M6: DD01AC9819 | N6: PET Bottle Scrap Baled - Green | O6: 513 | P6: 34.5 | Q6: =O6*P6 -> 17698.5 | R6: 0 | S6: =O6-R6 -> 513 | T6: 0 | U6: 0 | V6: 0 | W6: 0 | X6: 0 | Y6: 0 | Z6: 0 | AA6: 0 | AB6: =Y6+AA6+Z6 -> 0 | AC6: 0 | AD6: =IFERROR((Q6+AB6)/S6,0) -> 34.5 | AE6: 0 | AF6: 0 | AG6: 0 | AH6: 0 | AI6: 0 | AJ6: 0 | AK6: 0 | AL6: 0 | AM6: =Q6+AB6+AL6+AK6+AJ6+T6+AE6 -> 17698.5 | AN6: 46118 | AO6: 36/REW/27IN00001 | AP6: 832139000052985017 | AQ6: DALMIA POLYPRO INDUSTRIES PRIVATE LIMITED (27) | AR6: 27AAACD5406E1Z3 | AS6: Koregaon Bhima Maharashtra 412216 | AT6: Dindori | AU6: Maharashtra | AV6: 0 | AW6: 513 | AX6: 36 | AY6: =AW6*AX6 -> 18468 | AZ6: =AW6=O6 -> TRUE | BA6: 0 | BB6: =AW6-BA6 -> 513 | BC6: 0 | BD6: Regular | BE6: 0 | BF6: 0 | BG6: 0 | BH6: 0 | BI6: 0 | BJ6: 0 | BK6: 0 | BL6: 0 | BM6: 0 | BN6: =AY6*$BM$3 -> -461.7 | BO6: =AY6+BL6+BM6+BN6+BC6+BG6 -> 18006.3 | BP6: =BO6-AM6 -> 307.8 | BQ6: =IF(BP6>=0,"Positive Margin","Negative Margin") -> Positive Margin | BR6: CN Provision | BS6: =AY6-Y6-Q6-AA6-T6+BC6 -> 769.5 | BT6: =IF(BS6<0, "Negative Margin at Inception", "Positive Margin at Inception") -> Positive Margin at Inception | BU6: =IFERROR(BP6/BO6,"0") -> 0.017094017 | BV6: =IF(BU6<1%,"Less Than 1%",IF(BU6>2%,"More than 2%",IF(BU6>=1%,"1% - 2%"))) -> 1% - 2% | BW6: =BM6+BN6 -> -461.7 | BX6: =AL6+AK6 -> 0 | BY6: =BW6-BX6 -> -461.7 | BZ6: =BM6 -> 0 | CA6: =AK6 -> 0 | CB6: =BZ6-CA6 -> 0 | CC6: Marketplace (Rewerse) | CD6: 0 | CE6: =TEXT(AN6,"mmm-yy") -> Apr-26 | CF6: =AM6-AL6-AA6 -> 17698.5 | CG6: =BO6-BN6 -> 18468 | CH6: =INT((D6- IF(MONTH(D6) >= 4, DATE(YEAR(D6), 4, 1), DATE(YEAR(D6)-1, 4, 1))) / 7) + 1 -> 1 | CI6: Plastic | CJ6: Plastic | CK6: =_xlfn.XLOOKUP(AR6,receivables!B:B,receivables!D:D) -> Neelesh Dixit | CL6: =AY6-Q6 -> 769.5 | CM6: =CL6-Y6+Z6 -> 769.5 | CN6: =BO6-AM6 -> 307.8 | CO6: =AY6*118% -> 21792.24 | CP6: =-Q6*118% -> -20884.23 | CQ6: =-BZ6*118% -> 0 | CR6: =-CA6*118% -> 0 | CS6: =SUM(CO6:CR6) -> 908.01 | CT6: Telangana - HO | CU6: Telangana - HO | CV6: =MID(G6,3,10) -> AAMCB5608A | CW6: =MID(AR6,3,10) -> AAACD5406E | CX6: 0 | CY6: 0 | CZ6: 0 | DA6: 0 | DB6: 0
B7: ="Q" & IF(ROUNDUP(MONTH(D7)/3,0)-1=0,4,ROUNDUP(MONTH(D7)/3,0)-1) -> Q1 | C7: =TEXT(AN7,"mmm-yy") -> Apr-26 | D7: 46120 | E7: SH04260802 | F7: BLACK GOLD RECYCLING PRIVATE LIMITED | G7: 27AAMCB5608A1ZX | H7: 25/PUN/INV0273 | I7: 46120 | J7: 26-27/PUR/000239 | K7: 46120 | L7: MH | M7: DD01J9582 | N7: PET Bottle Scrap Baled - Clear | O7: 7945 | P7: 41 | Q7: =O7*P7 -> 325745 | R7: 0 | S7: =O7-R7 -> 7945 | T7: 0 | U7: 0 | V7: 0 | W7: 0 | X7: 0 | Y7: 0 | Z7: 0 | AA7: 0 | AB7: =Y7+AA7+Z7 -> 0 | AC7: 0 | AD7: =IFERROR((Q7+AB7)/S7,0) -> 41 | AE7: 0 | AF7: 0 | AG7: 0 | AH7: 0 | AI7: 0 | AJ7: 0 | AK7: 0 | AL7: 0 | AM7: =Q7+AB7+AL7+AK7+AJ7+T7+AE7 -> 325745 | AN7: 46120 | AO7: 36/REW/27IN00002 | AP7: 832139000052985017 | AQ7: DALMIA POLYPRO INDUSTRIES PRIVATE LIMITED (27) | AR7: 27AAACD5406E1Z3 | AS7: Koregaon Bhima Maharashtra 412216 | AT7: Dindori | AU7: Maharashtra | AV7: 0 | AW7: 7945 | AX7: 46 | AY7: =AW7*AX7 -> 365470 | AZ7: =AW7=O7 -> TRUE | BA7: 0 | BB7: =AW7-BA7 -> 7945 | BC7: 0 | BD7: Regular | BE7: 0 | BF7: 0 | BG7: 0 | BH7: 36/REW/27CN00024 | BI7: 46181 | BJ7: 0 | BK7: 0 | BL7: 0 | BM7: -4529.62 | BN7: 0 | BO7: =AY7+BL7+BM7+BN7+BC7+BG7 -> 360940.38 | BP7: =BO7-AM7 -> 35195.38 | BQ7: =IF(BP7>=0,"Positive Margin","Negative Margin") -> Positive Margin | BR7: CN Issued | BS7: =AY7-Y7-Q7-AA7-T7+BC7 -> 39725 | BT7: =IF(BS7<0, "Negative Margin at Inception", "Positive Margin at Inception") -> Positive Margin at Inception | BU7: =IFERROR(BP7/BO7,"0") -> 0.097510231 | BV7: =IF(BU7<1%,"Less Than 1%",IF(BU7>2%,"More than 2%",IF(BU7>=1%,"1% - 2%"))) -> More than 2% | BW7: =BM7+BN7 -> -4529.62 | BX7: =AL7+AK7 -> 0 | BY7: =BW7-BX7 -> -4529.62 | BZ7: =BM7 -> -4529.62 | CA7: =AK7 -> 0 | CB7: =BZ7-CA7 -> -4529.62 | CC7: Marketplace (Rewerse) | CD7: 0 | CE7: =TEXT(AN7,"mmm-yy") -> Apr-26 | CF7: =AM7-AL7-AA7 -> 325745 | CG7: =BO7-BN7 -> 360940.38 | CH7: =INT((D7- IF(MONTH(D7) >= 4, DATE(YEAR(D7), 4, 1), DATE(YEAR(D7)-1, 4, 1))) / 7) + 1 -> 2 | CI7: Plastic | CJ7: Plastic | CK7: =_xlfn.XLOOKUP(AR7,receivables!B:B,receivables!D:D) -> Neelesh Dixit | CL7: =AY7-Q7 -> 39725 | CM7: =CL7-Y7+Z7 -> 39725 | CN7: =BO7-AM7 -> 35195.38 | CO7: =AY7*118% -> 431254.6 | CP7: =-Q7*118% -> -384379.1 | CQ7: =-BZ7*118% -> 5344.9516 | CR7: =-CA7*118% -> 0 | CS7: =SUM(CO7:CR7) -> 52220.452 | CT7: Telangana - HO | CU7: Telangana - HO | CV7: =MID(G7,3,10) -> AAMCB5608A | CW7: =MID(AR7,3,10) -> AAACD5406E | CX7: 0 | CY7: 0 | CZ7: 0 | DA7: 0 | DB7: 0
B8: ="Q" & IF(ROUNDUP(MONTH(D8)/3,0)-1=0,4,ROUNDUP(MONTH(D8)/3,0)-1) -> Q1 | C8: =TEXT(AN8,"mmm-yy") -> Apr-26 | D8: 46120 | E8: SH04260802 | F8: BLACK GOLD RECYCLING PRIVATE LIMITED | G8: 27AAMCB5608A1ZX | H8: 25/PUN/INV0273 | I8: 46120 | J8: 26-27/PUR/000239 | K8: 46120 | L8: MH | M8: DD01J9582 | N8: PET Bottle Scrap Baled - Green | O8: 348 | P8: 36 | Q8: =O8*P8 -> 12528 | R8: 0 | S8: =O8-R8 -> 348 | T8: 0 | U8: 0 | V8: 0 | W8: 0 | X8: 0 | Y8: 0 | Z8: 0 | AA8: 0 | AB8: =Y8+AA8+Z8 -> 0 | AC8: 0 | AD8: =IFERROR((Q8+AB8)/S8,0) -> 36 | AE8: 0 | AF8: 0 | AG8: 0 | AH8: 0 | AI8: 0 | AJ8: 0 | AK8: 0 | AL8: 0 | AM8: =Q8+AB8+AL8+AK8+AJ8+T8+AE8 -> 12528 | AN8: 46120 | AO8: 36/REW/27IN00002 | AP8: 832139000052985017 | AQ8: DALMIA POLYPRO INDUSTRIES PRIVATE LIMITED (27) | AR8: 27AAACD5406E1Z3 | AS8: Koregaon Bhima Maharashtra 412216 | AT8: Dindori | AU8: Maharashtra | AV8: 0 | AW8: 348 | AX8: 36 | AY8: =AW8*AX8 -> 12528 | AZ8: =AW8=O8 -> TRUE | BA8: 0 | BB8: =AW8-BA8 -> 348 | BC8: 0 | BD8: Regular | BE8: 0 | BF8: 0 | BG8: 0 | BH8: 36/REW/27CN00024 | BI8: 46181 | BJ8: 0 | BK8: 0 | BL8: 0 | BM8: 0 | BN8: 0 | BO8: =AY8+BL8+BM8+BN8+BC8+BG8 -> 12528 | BP8: =BO8-AM8 -> 0 | BQ8: =IF(BP8>=0,"Positive Margin","Negative Margin") -> Positive Margin | BR8: CN Issued | BS8: =AY8-Y8-Q8-AA8-T8+BC8 -> 0 | BT8: =IF(BS8<0, "Negative Margin at Inception", "Positive Margin at Inception") -> Positive Margin at Inception | BU8: =IFERROR(BP8/BO8,"0") -> 0 | BV8: =IF(BU8<1%,"Less Than 1%",IF(BU8>2%,"More than 2%",IF(BU8>=1%,"1% - 2%"))) -> Less Than 1% | BW8: =BM8+BN8 -> 0 | BX8: =AL8+AK8 -> 0 | BY8: =BW8-BX8 -> 0 | BZ8: =BM8 -> 0 | CA8: =AK8 -> 0 | CB8: =BZ8-CA8 -> 0 | CC8: Marketplace (Rewerse) | CD8: 0 | CE8: =TEXT(AN8,"mmm-yy") -> Apr-26 | CF8: =AM8-AL8-AA8 -> 12528 | CG8: =BO8-BN8 -> 12528 | CH8: =INT((D8- IF(MONTH(D8) >= 4, DATE(YEAR(D8), 4, 1), DATE(YEAR(D8)-1, 4, 1))) / 7) + 1 -> 2 | CI8: Plastic | CJ8: Plastic | CK8: =_xlfn.XLOOKUP(AR8,receivables!B:B,receivables!D:D) -> Neelesh Dixit | CL8: =AY8-Q8 -> 0 | CM8: =CL8-Y8+Z8 -> 0 | CN8: =BO8-AM8 -> 0 | CO8: =AY8*118% -> 14783.04 | CP8: =-Q8*118% -> -14783.04 | CQ8: =-BZ8*118% -> 0 | CR8: =-CA8*118% -> 0 | CS8: =SUM(CO8:CR8) -> 0 | CT8: Telangana - HO | CU8: Telangana - HO | CV8: =MID(G8,3,10) -> AAMCB5608A | CW8: =MID(AR8,3,10) -> AAACD5406E | CX8: 0 | CY8: 0 | CZ8: 0 | DA8: 0 | DB8: 0
B9: ="Q" & IF(ROUNDUP(MONTH(D9)/3,0)-1=0,4,ROUNDUP(MONTH(D9)/3,0)-1) -> Q1 | C9: =TEXT(AN9,"mmm-yy") -> Apr-26 | D9: 46120 | E9: SH04260802 | F9: BLACK GOLD RECYCLING PRIVATE LIMITED | G9: 27AAMCB5608A1ZX | H9: 25/PUN/INV0273 | I9: 46120 | J9: 26-27/PUR/000239 | K9: 46120 | L9: MH | M9: DD01J9582 | N9: PET Liquor Bottle Scrap Baled | O9: 927 | P9: 41 | Q9: =O9*P9 -> 38007 | R9: 0 | S9: =O9-R9 -> 927 | T9: 0 | U9: 0 | V9: 0 | W9: 0 | X9: 0 | Y9: 0 | Z9: 0 | AA9: 0 | AB9: =Y9+AA9+Z9 -> 0 | AC9: 0 | AD9: =IFERROR((Q9+AB9)/S9,0) -> 41 | AE9: 0 | AF9: 0 | AG9: 0 | AH9: 0 | AI9: 0 | AJ9: 0 | AK9: 0 | AL9: 0 | AM9: =Q9+AB9+AL9+AK9+AJ9+T9+AE9 -> 38007 | AN9: 46120 | AO9: 36/REW/27IN00002 | AP9: 832139000052985017 | AQ9: DALMIA POLYPRO INDUSTRIES PRIVATE LIMITED (27) | AR9: 27AAACD5406E1Z3 | AS9: Koregaon Bhima Maharashtra 412216 | AT9: Dindori | AU9: Maharashtra | AV9: 0 | AW9: 927 | AX9: 51 | AY9: =AW9*AX9 -> 47277 | AZ9: =AW9=O9 -> TRUE | BA9: 0 | BB9: =AW9-BA9 -> 927 | BC9: 0 | BD9: Regular | BE9: 0 | BF9: 0 | BG9: 0 | BH9: 36/REW/27CN00024 | BI9: 46181 | BJ9: 0 | BK9: 0 | BL9: 0 | BM9: 0 | BN9: 0 | BO9: =AY9+BL9+BM9+BN9+BC9+BG9 -> 47277 | BP9: =BO9-AM9 -> 9270 | BQ9: =IF(BP9>=0,"Positive Margin","Negative Margin") -> Positive Margin | BR9: CN Issued | BS9: =AY9-Y9-Q9-AA9-T9+BC9 -> 9270 | BT9: =IF(BS9<0, "Negative Margin at Inception", "Positive Margin at Inception") -> Positive Margin at Inception | BU9: =IFERROR(BP9/BO9,"0") -> 0.19607843 | BV9: =IF(BU9<1%,"Less Than 1%",IF(BU9>2%,"More than 2%",IF(BU9>=1%,"1% - 2%"))) -> More than 2% | BW9: =BM9+BN9 -> 0 | BX9: =AL9+AK9 -> 0 | BY9: =BW9-BX9 -> 0 | BZ9: =BM9 -> 0 | CA9: =AK9 -> 0 | CB9: =BZ9-CA9 -> 0 | CC9: Marketplace (Rewerse) | CD9: 0 | CE9: =TEXT(AN9,"mmm-yy") -> Apr-26 | CF9: =AM9-AL9-AA9 -> 38007 | CG9: =BO9-BN9 -> 47277 | CH9: =INT((D9- IF(MONTH(D9) >= 4, DATE(YEAR(D9), 4, 1), DATE(YEAR(D9)-1, 4, 1))) / 7) + 1 -> 2 | CI9: Plastic | CJ9: Plastic | CK9: =_xlfn.XLOOKUP(AR9,receivables!B:B,receivables!D:D) -> Neelesh Dixit | CL9: =AY9-Q9 -> 9270 | CM9: =CL9-Y9+Z9 -> 9270 | CN9: =BO9-AM9 -> 9270 | CO9: =AY9*118% -> 55786.86 | CP9: =-Q9*118% -> -44848.26 | CQ9: =-BZ9*118% -> 0 | CR9: =-CA9*118% -> 0 | CS9: =SUM(CO9:CR9) -> 10938.6 | CT9: Telangana - HO | CU9: Telangana - HO | CV9: =MID(G9,3,10) -> AAMCB5608A | CW9: =MID(AR9,3,10) -> AAACD5406E | CX9: 0 | CY9: 0 | CZ9: 0 | DA9: 0 | DB9: 0
B10: ="Q" & IF(ROUNDUP(MONTH(D10)/3,0)-1=0,4,ROUNDUP(MONTH(D10)/3,0)-1) -> Q1 | C10: =TEXT(AN10,"mmm-yy") -> Apr-26 | D10: 46123 | E10: SH04261101 | F10: BLACK GOLD RECYCLING PRIVATE LIMITED | G10: 27AAMCB5608A1ZX | H10: 25/PUN/INV0280 | I10: 46123 | J10: 26-27/PUR/000399 | K10: 46123 | L10: MH | M10: MH13EP3779 | N10: PET Bottle Scrap Baled - Clear | O10: 7855 | P10: 41 | Q10: =O10*P10 -> 322055 | R10: 0 | S10: =O10-R10 -> 7855 | T10: 0 | U10: 0 | V10: 0 | W10: 0 | X10: 0 | Y10: 0 | Z10: 0 | AA10: 0 | AB10: =Y10+AA10+Z10 -> 0 | AC10: 0 | AD10: =IFERROR((Q10+AB10)/S10,0) -> 41 | AE10: 0 | AF10: 0 | AG10: 0 | AH10: 0 | AI10: 0 | AJ10: 0 | AK10: 0 | AL10: 0 | AM10: =Q10+AB10+AL10+AK10+AJ10+T10+AE10 -> 322055 | AN10: 46123 | AO10: 36/REW/27IN00003 | AP10: 832139000052985017 | AQ10: DALMIA POLYPRO INDUSTRIES PRIVATE LIMITED (27) | AR10: 27AAACD5406E1Z3 | AS10: Koregaon Bhima Maharashtra 412216 | AT10: Dindori | AU10: Maharashtra | AV10: 0 | AW10: 7855 | AX10: 46 | AY10: =AW10*AX10 -> 361330 | AZ10: =AW10=O10 -> TRUE | BA10: 0 | BB10: =AW10-BA10 -> 7855 | BC10: 0 | BD10: Regular | BE10: 0 | BF10: 0 | BG10: 0 | BH10: 36/REW/27CN00026 | BI10: 46181 | BJ10: 0 | BK10: 0 | BL10: 0 | BM10: -8421.68 | BN10: 0 | BO10: =AY10+BL10+BM10+BN10+BC10+BG10 -> 352908.32 | BP10: =BO10-AM10 -> 30853.32 | BQ10: =IF(BP10>=0,"Positive Margin","Negative Margin") -> Positive Margin | BR10: CN Issued | BS10: =AY10-Y10-Q10-AA10-T10+BC10 -> 39275 | BT10: =IF(BS10<0, "Negative Margin at Inception", "Positive Margin at Inception") -> Positive Margin at Inception | BU10: =IFERROR(BP10/BO10,"0") -> 0.087425879 | BV10: =IF(BU10<1%,"Less Than 1%",IF(BU10>2%,"More than 2%",IF(BU10>=1%,"1% - 2%"))) -> More than 2% | BW10: =BM10+BN10 -> -8421.68 | BX10: =AL10+AK10 -> 0 | BY10: =BW10-BX10 -> -8421.68 | BZ10: =BM10 -> -8421.68 | CA10: =AK10 -> 0 | CB10: =BZ10-CA10 -> -8421.68 | CC10: Marketplace (Rewerse) | CD10: 0 | CE10: =TEXT(AN10,"mmm-yy") -> Apr-26 | CF10: =AM10-AL10-AA10 -> 322055 | CG10: =BO10-BN10 -> 352908.32 | CH10: =INT((D10- IF(MONTH(D10) >= 4, DATE(YEAR(D10), 4, 1), DATE(YEAR(D10)-1, 4, 1))) / 7) + 1 -> 2 | CI10: Plastic | CJ10: Plastic | CK10: =_xlfn.XLOOKUP(AR10,receivables!B:B,receivables!D:D) -> Neelesh Dixit | CL10: =AY10-Q10 -> 39275 | CM10: =CL10-Y10+Z10 -> 39275 | CN10: =BO10-AM10 -> 30853.32 | CO10: =AY10*118% -> 426369.4 | CP10: =-Q10*118% -> -380024.9 | CQ10: =-BZ10*118% -> 9937.5824 | CR10: =-CA10*118% -> 0 | CS10: =SUM(CO10:CR10) -> 56282.082 | CT10: Telangana - HO | CU10: Telangana - HO | CV10: =MID(G10,3,10) -> AAMCB5608A | CW10: =MID(AR10,3,10) -> AAACD5406E | CX10: 0 | CY10: 0 | CZ10: 0 | DA10: 0 | DB10: 0
B11: ="Q" & IF(ROUNDUP(MONTH(D11)/3,0)-1=0,4,ROUNDUP(MONTH(D11)/3,0)-1) -> Q1 | C11: =TEXT(AN11,"mmm-yy") -> Apr-26 | D11: 46123 | E11: SH04261101 | F11: BLACK GOLD RECYCLING PRIVATE LIMITED | G11: 27AAMCB5608A1ZX | H11: 25/PUN/INV0280 | I11: 46123 | J11: 26-27/PUR/000399 | K11: 46123 | L11: MH | M11: MH13EP3779 | N11: PET Bottle Scrap Baled - Green | O11: 614 | P11: 36 | Q11: =O11*P11 -> 22104 | R11: 0 | S11: =O11-R11 -> 614 | T11: 0 | U11: 0 | V11: 0 | W11: 0 | X11: 0 | Y11: 0 | Z11: 0 | AA11: 0 | AB11: =Y11+AA11+Z11 -> 0 | AC11: 0 | AD11: =IFERROR((Q11+AB11)/S11,0) -> 36 | AE11: 0 | AF11: 0 | AG11: 0 | AH11: 0 | AI11: 0 | AJ11: 0 | AK11: 0 | AL11: 0 | AM11: =Q11+AB11+AL11+AK11+AJ11+T11+AE11 -> 22104 | AN11: 46123 | AO11: 36/REW/27IN00003 | AP11: 832139000052985017 | AQ11: DALMIA POLYPRO INDUSTRIES PRIVATE LIMITED (27) | AR11: 27AAACD5406E1Z3 | AS11: Koregaon Bhima Maharashtra 412216 | AT11: Dindori | AU11: Maharashtra | AV11: 0 | AW11: 614 | AX11: 36 | AY11: =AW11*AX11 -> 22104 | AZ11: =AW11=O11 -> TRUE | BA11: 0 | BB11: =AW11-BA11 -> 614 | BC11: 0 | BD11: Regular | BE11: 0 | BF11: 0 | BG11: 0 | BH11: 36/REW/27CN00026 | BI11: 46181 | BJ11: 0 | BK11: 0 | BL11: 0 | BM11: 0 | BN11: 0 | BO11: =AY11+BL11+BM11+BN11+BC11+BG11 -> 22104 | BP11: =BO11-AM11 -> 0 | BQ11: =IF(BP11>=0,"Positive Margin","Negative Margin") -> Positive Margin | BR11: CN Issued | BS11: =AY11-Y11-Q11-AA11-T11+BC11 -> 0 | BT11: =IF(BS11<0, "Negative Margin at Inception", "Positive Margin at Inception") -> Positive Margin at Inception | BU11: =IFERROR(BP11/BO11,"0") -> 0 | BV11: =IF(BU11<1%,"Less Than 1%",IF(BU11>2%,"More than 2%",IF(BU11>=1%,"1% - 2%"))) -> Less Than 1% | BW11: =BM11+BN11 -> 0 | BX11: =AL11+AK11 -> 0 | BY11: =BW11-BX11 -> 0 | BZ11: =BM11 -> 0 | CA11: =AK11 -> 0 | CB11: =BZ11-CA11 -> 0 | CC11: Marketplace (Rewerse) | CD11: 0 | CE11: =TEXT(AN11,"mmm-yy") -> Apr-26 | CF11: =AM11-AL11-AA11 -> 22104 | CG11: =BO11-BN11 -> 22104 | CH11: =INT((D11- IF(MONTH(D11) >= 4, DATE(YEAR(D11), 4, 1), DATE(YEAR(D11)-1, 4, 1))) / 7) + 1 -> 2 | CI11: Plastic | CJ11: Plastic | CK11: =_xlfn.XLOOKUP(AR11,receivables!B:B,receivables!D:D) -> Neelesh Dixit | CL11: =AY11-Q11 -> 0 | CM11: =CL11-Y11+Z11 -> 0 | CN11: =BO11-AM11 -> 0 | CO11: =AY11*118% -> 26082.72 | CP11: =-Q11*118% -> -26082.72 | CQ11: =-BZ11*118% -> 0 | CR11: =-CA11*118% -> 0 | CS11: =SUM(CO11:CR11) -> 0 | CT11: Telangana - HO | CU11: Telangana - HO | CV11: =MID(G11,3,10) -> AAMCB5608A | CW11: =MID(AR11,3,10) -> AAACD5406E | CX11: 0 | CY11: 0 | CZ11: 0 | DA11: 0 | DB11: 0
B12: ="Q" & IF(ROUNDUP(MONTH(D12)/3,0)-1=0,4,ROUNDUP(MONTH(D12)/3,0)-1) -> Q1 | C12: =TEXT(AN12,"mmm-yy") -> Apr-26 | D12: 46123 | E12: SH04261101 | F12: BLACK GOLD RECYCLING PRIVATE LIMITED | G12: 27AAMCB5608A1ZX | H12: 25/PUN/INV0280 | I12: 46123 | J12: 26-27/PUR/000399 | K12: 46123 | L12: MH | M12: MH13EP3779 | N12: PET Liquor Bottle Scrap Baled | O12: 596 | P12: 41 | Q12: =O12*P12 -> 24436 | R12: 0 | S12: =O12-R12 -> 596 | T12: 0 | U12: 0 | V12: 0 | W12: 0 | X12: 0 | Y12: 0 | Z12: 0 | AA12: 0 | AB12: =Y12+AA12+Z12 -> 0 | AC12: 0 | AD12: =IFERROR((Q12+AB12)/S12,0) -> 41 | AE12: 0 | AF12: 0 | AG12: 0 | AH12: 0 | AI12: 0 | AJ12: 0 | AK12: 0 | AL12: 0 | AM12: =Q12+AB12+AL12+AK12+AJ12+T12+AE12 -> 24436 | AN12: 46123 | AO12: 36/REW/27IN00003 | AP12: 832139000052985017 | AQ12: DALMIA POLYPRO INDUSTRIES PRIVATE LIMITED (27) | AR12: 27AAACD5406E1Z3 | AS12: Koregaon Bhima Maharashtra 412216 | AT12: Dindori | AU12: Maharashtra | AV12: 0 | AW12: 596 | AX12: 51 | AY12: =AW12*AX12 -> 30396 | AZ12: =AW12=O12 -> TRUE | BA12: 0 | BB12: =AW12-BA12 -> 596 | BC12: 0 | BD12: Regular | BE12: 0 | BF12: 0 | BG12: 0 | BH12: 36/REW/27CN00026 | BI12: 46181 | BJ12: 0 | BK12: 0 | BL12: 0 | BM12: 0 | BN12: 0 | BO12: =AY12+BL12+BM12+BN12+BC12+BG12 -> 30396 | BP12: =BO12-AM12 -> 5960 | BQ12: =IF(BP12>=0,"Positive Margin","Negative Margin") -> Positive Margin | BR12: CN Issued | BS12: =AY12-Y12-Q12-AA12-T12+BC12 -> 5960 | BT12: =IF(BS12<0, "Negative Margin at Inception", "Positive Margin at Inception") -> Positive Margin at Inception | BU12: =IFERROR(BP12/BO12,"0") -> 0.19607843 | BV12: =IF(BU12<1%,"Less Than 1%",IF(BU12>2%,"More than 2%",IF(BU12>=1%,"1% - 2%"))) -> More than 2% | BW12: =BM12+BN12 -> 0 | BX12: =AL12+AK12 -> 0 | BY12: =BW12-BX12 -> 0 | BZ12: =BM12 -> 0 | CA12: =AK12 -> 0 | CB12: =BZ12-CA12 -> 0 | CC12: Marketplace (Rewerse) | CD12: 0 | CE12: =TEXT(AN12,"mmm-yy") -> Apr-26 | CF12: =AM12-AL12-AA12 -> 24436 | CG12: =BO12-BN12 -> 30396 | CH12: =INT((D12- IF(MONTH(D12) >= 4, DATE(YEAR(D12), 4, 1), DATE(YEAR(D12)-1, 4, 1))) / 7) + 1 -> 2 | CI12: Plastic | CJ12: Plastic | CK12: =_xlfn.XLOOKUP(AR12,receivables!B:B,receivables!D:D) -> Neelesh Dixit | CL12: =AY12-Q12 -> 5960 | CM12: =CL12-Y12+Z12 -> 5960 | CN12: =BO12-AM12 -> 5960 | CO12: =AY12*118% -> 35867.28 | CP12: =-Q12*118% -> -28834.48 | CQ12: =-BZ12*118% -> 0 | CR12: =-CA12*118% -> 0 | CS12: =SUM(CO12:CR12) -> 7032.8 | CT12: Telangana - HO | CU12: Telangana - HO | CV12: =MID(G12,3,10) -> AAMCB5608A | CW12: =MID(AR12,3,10) -> AAACD5406E | CX12: 0 | CY12: 0 | CZ12: 0 | DA12: 0 | DB12: 0
B13: ="Q" & IF(ROUNDUP(MONTH(D13)/3,0)-1=0,4,ROUNDUP(MONTH(D13)/3,0)-1) -> Q1 | C13: =TEXT(AN13,"mmm-yy") -> Apr-26 | D13: 46127 | E13: SH04261505 | F13: BLACK GOLD RECYCLING PRIVATE LIMITED | G13: 27AAMCB5608A1ZX | H13: 25/PUN/INV0282 | I13: 46127 | J13: 26-27/PUR/000612 | K13: 46127 | L13: MH | M13: DD01AC9819 | N13: PET Bottle Scrap Baled - Clear | O13: 9044 | P13: 41 | Q13: =O13*P13 -> 370804 | R13: 0 | S13: =O13-R13 -> 9044 | T13: 0 | U13: 0 | V13: 0 | W13: 0 | X13: 0 | Y13: 0 | Z13: 0 | AA13: 0 | AB13: =Y13+AA13+Z13 -> 0 | AC13: 0 | AD13: =IFERROR((Q13+AB13)/S13,0) -> 41 | AE13: 0 | AF13: 0 | AG13: 0 | AH13: 0 | AI13: 0 | AJ13: 0 | AK13: 0 | AL13: 0 | AM13: =Q13+AB13+AL13+AK13+AJ13+T13+AE13 -> 370804 | AN13: 46127 | AO13: 36/REW/27IN00004 | AP13: 832139000052985017 | AQ13: DALMIA POLYPRO INDUSTRIES PRIVATE LIMITED (27) | AR13: 27AAACD5406E1Z3 | AS13: Koregaon Bhima Maharashtra 412216 | AT13: Dindori | AU13: Maharashtra | AV13: 0 | AW13: 9044 | AX13: 52 | AY13: =AW13*AX13 -> 470288 | AZ13: =AW13=O13 -> TRUE | BA13: 0 | BB13: =AW13-BA13 -> 9044 | BC13: 0 | BD13: Regular | BE13: 0 | BF13: 0 | BG13: 0 | BH13: 36/REW/27CN00027 | BI13: 46181 | BJ13: 0 | BK13: 0 | BL13: 0 | BM13: -12971.6 | BN13: 0 | BO13: =AY13+BL13+BM13+BN13+BC13+BG13 -> 457316.4 | BP13: =BO13-AM13 -> 86512.4 | BQ13: =IF(BP13>=0,"Positive Margin","Negative Margin") -> Positive Margin | BR13: CN Issued | BS13: =AY13-Y13-Q13-AA13-T13+BC13 -> 99484 | BT13: =IF(BS13<0, "Negative Margin at Inception", "Positive Margin at Inception") -> Positive Margin at Inception | BU13: =IFERROR(BP13/BO13,"0") -> 0.18917406 | BV13: =IF(BU13<1%,"Less Than 1%",IF(BU13>2%,"More than 2%",IF(BU13>=1%,"1% - 2%"))) -> More than 2% | BW13: =BM13+BN13 -> -12971.6 | BX13: =AL13+AK13 -> 0 | BY13: =BW13-BX13 -> -12971.6 | BZ13: =BM13 -> -12971.6 | CA13: =AK13 -> 0 | CB13: =BZ13-CA13 -> -12971.6 | CC13: Marketplace (Rewerse) | CD13: 0 | CE13: =TEXT(AN13,"mmm-yy") -> Apr-26 | CF13: =AM13-AL13-AA13 -> 370804 | CG13: =BO13-BN13 -> 457316.4 | CH13: =INT((D13- IF(MONTH(D13) >= 4, DATE(YEAR(D13), 4, 1), DATE(YEAR(D13)-1, 4, 1))) / 7) + 1 -> 3 | CI13: Plastic | CJ13: Plastic | CK13: =_xlfn.XLOOKUP(AR13,receivables!B:B,receivables!D:D) -> Neelesh Dixit | CL13: =AY13-Q13 -> 99484 | CM13: =CL13-Y13+Z13 -> 99484 | CN13: =BO13-AM13 -> 86512.4 | CO13: =AY13*118% -> 554939.84 | CP13: =-Q13*118% -> -437548.72 | CQ13: =-BZ13*118% -> 15306.488 | CR13: =-CA13*118% -> 0 | CS13: =SUM(CO13:CR13) -> 132697.61 | CT13: Telangana - HO | CU13: Telangana - HO | CV13: =MID(G13,3,10) -> AAMCB5608A | CW13: =MID(AR13,3,10) -> AAACD5406E | CX13: 0 | CY13: 0 | CZ13: 0 | DA13: 0 | DB13: 0
B14: ="Q" & IF(ROUNDUP(MONTH(D14)/3,0)-1=0,4,ROUNDUP(MONTH(D14)/3,0)-1) -> Q1 | C14: =TEXT(AN14,"mmm-yy") -> Apr-26 | D14: 46127 | E14: SH04261505 | F14: BLACK GOLD RECYCLING PRIVATE LIMITED | G14: 27AAMCB5608A1ZX | H14: 25/PUN/INV0282 | I14: 46127 | J14: 26-27/PUR/000612 | K14: 46127 | L14: MH | M14: DD01AC9819 | N14: PET Bottle Scrap Baled - Green | O14: 466 | P14: 36 | Q14: =O14*P14 -> 16776 | R14: 0 | S14: =O14-R14 -> 466 | T14: 0 | U14: 0 | V14: 0 | W14: 0 | X14: 0 | Y14: 0 | Z14: 0 | AA14: 0 | AB14: =Y14+AA14+Z14 -> 0 | AC14: 0 | AD14: =IFERROR((Q14+AB14)/S14,0) -> 36 | AE14: 0 | AF14: 0 | AG14: 0 | AH14: 0 | AI14: 0 | AJ14: 0 | AK14: 0 | AL14: 0 | AM14: =Q14+AB14+AL14+AK14+AJ14+T14+AE14 -> 16776 | AN14: 46127 | AO14: 36/REW/27IN00004 | AP14: 832139000052985017 | AQ14: DALMIA POLYPRO INDUSTRIES PRIVATE LIMITED (27) | AR14: 27AAACD5406E1Z3 | AS14: Koregaon Bhima Maharashtra 412216 | AT14: Dindori | AU14: Maharashtra | AV14: 0 | AW14: 466 | AX14: 42 | AY14: =AW14*AX14 -> 19572 | AZ14: =AW14=O14 -> TRUE | BA14: 0 | BB14: =AW14-BA14 -> 466 | BC14: 0 | BD14: Regular | BE14: 0 | BF14: 0 | BG14: 0 | BH14: 36/REW/27CN00027 | BI14: 46181 | BJ14: 0 | BK14: 0 | BL14: 0 | BM14: 0 | BN14: 0 | BO14: =AY14+BL14+BM14+BN14+BC14+BG14 -> 19572 | BP14: =BO14-AM14 -> 2796 | BQ14: =IF(BP14>=0,"Positive Margin","Negative Margin") -> Positive Margin | BR14: CN Issued | BS14: =AY14-Y14-Q14-AA14-T14+BC14 -> 2796 | BT14: =IF(BS14<0, "Negative Margin at Inception", "Positive Margin at Inception") -> Positive Margin at Inception | BU14: =IFERROR(BP14/BO14,"0") -> 0.14285714 | BV14: =IF(BU14<1%,"Less Than 1%",IF(BU14>2%,"More than 2%",IF(BU14>=1%,"1% - 2%"))) -> More than 2% | BW14: =BM14+BN14 -> 0 | BX14: =AL14+AK14 -> 0 | BY14: =BW14-BX14 -> 0 | BZ14: =BM14 -> 0 | CA14: =AK14 -> 0 | CB14: =BZ14-CA14 -> 0 | CC14: Marketplace (Rewerse) | CD14: 0 | CE14: =TEXT(AN14,"mmm-yy") -> Apr-26 | CF14: =AM14-AL14-AA14 -> 16776 | CG14: =BO14-BN14 -> 19572 | CH14: =INT((D14- IF(MONTH(D14) >= 4, DATE(YEAR(D14), 4, 1), DATE(YEAR(D14)-1, 4, 1))) / 7) + 1 -> 3 | CI14: Plastic | CJ14: Plastic | CK14: =_xlfn.XLOOKUP(AR14,receivables!B:B,receivables!D:D) -> Neelesh Dixit | CL14: =AY14-Q14 -> 2796 | CM14: =CL14-Y14+Z14 -> 2796 | CN14: =BO14-AM14 -> 2796 | CO14: =AY14*118% -> 23094.96 | CP14: =-Q14*118% -> -19795.68 | CQ14: =-BZ14*118% -> 0 | CR14: =-CA14*118% -> 0 | CS14: =SUM(CO14:CR14) -> 3299.28 | CT14: Telangana - HO | CU14: Telangana - HO | CV14: =MID(G14,3,10) -> AAMCB5608A | CW14: =MID(AR14,3,10) -> AAACD5406E | CX14: 0 | CY14: 0 | CZ14: 0 | DA14: 0 | DB14: 0
B15: ="Q" & IF(ROUNDUP(MONTH(D15)/3,0)-1=0,4,ROUNDUP(MONTH(D15)/3,0)-1) -> Q1 | C15: =TEXT(AN15,"mmm-yy") -> Apr-26 | D15: 46130 | E15: SH04261806 | F15: BLACK GOLD RECYCLING PRIVATE LIMITED | G15: 27AAMCB5608A1ZX | H15: 25/PUN/INV0285 | I15: 46130 | J15: 26-27/PUR/000939 | K15: 46130 | L15: MH | M15: DD01AC9274 | N15: PET Bottle Scrap Baled - Clear | O15: 8199 | P15: 41.5 | Q15: =O15*P15 -> 340258.5 | R15: 0 | S15: =O15-R15 -> 8199 | T15: 0 | U15: 0 | V15: 0 | W15: 0 | X15: 0 | Y15: 0 | Z15: 0 | AA15: 0 | AB15: =Y15+AA15+Z15 -> 0 | AC15: 0 | AD15: =IFERROR((Q15+AB15)/S15,0) -> 41.5 | AE15: 0 | AF15: 0 | AG15: 0 | AH15: 0 | AI15: 0 | AJ15: 0 | AK15: 0 | AL15: 0 | AM15: =Q15+AB15+AL15+AK15+AJ15+T15+AE15 -> 340258.5 | AN15: 46130 | AO15: 36/REW/27IN00005 | AP15: 832139000052985017 | AQ15: DALMIA POLYPRO INDUSTRIES PRIVATE LIMITED (27) | AR15: 27AAACD5406E1Z3 | AS15: Koregaon Bhima Maharashtra 412216 | AT15: Dindori | AU15: Maharashtra | AV15: 0 | AW15: 8199 | AX15: 52 | AY15: =AW15*AX15 -> 426348 | AZ15: =AW15=O15 -> TRUE | BA15: 0 | BB15: =AW15-BA15 -> 8199 | BC15: 0 | BD15: Regular | BE15: 0 | BF15: 0 | BG15: 0 | BH15: 36/REW/27CN00028 | BI15: 46181 | BJ15: 0 | BK15: 0 | BL15: 0 | BM15: -3076.84 | BN15: 0 | BO15: =AY15+BL15+BM15+BN15+BC15+BG15 -> 423271.16 | BP15: =BO15-AM15 -> 83012.66 | BQ15: =IF(BP15>=0,"Positive Margin","Negative Margin") -> Positive Margin | BR15: CN Issued | BS15: =AY15-Y15-Q15-AA15-T15+BC15 -> 86089.5 | BT15: =IF(BS15<0, "Negative Margin at Inception", "Positive Margin at Inception") -> Positive Margin at Inception | BU15: =IFERROR(BP15/BO15,"0") -> 0.1961217 | BV15: =IF(BU15<1%,"Less Than 1%",IF(BU15>2%,"More than 2%",IF(BU15>=1%,"1% - 2%"))) -> More than 2% | BW15: =BM15+BN15 -> -3076.84 | BX15: =AL15+AK15 -> 0 | BY15: =BW15-BX15 -> -3076.84 | BZ15: =BM15 -> -3076.84 | CA15: =AK15 -> 0 | CB15: =BZ15-CA15 -> -3076.84 | CC15: Marketplace (Rewerse) | CD15: 0 | CE15: =TEXT(AN15,"mmm-yy") -> Apr-26 | CF15: =AM15-AL15-AA15 -> 340258.5 | CG15: =BO15-BN15 -> 423271.16 | CH15: =INT((D15- IF(MONTH(D15) >= 4, DATE(YEAR(D15), 4, 1), DATE(YEAR(D15)-1, 4, 1))) / 7) + 1 -> 3 | CI15: Plastic | CJ15: Plastic | CK15: =_xlfn.XLOOKUP(AR15,receivables!B:B,receivables!D:D) -> Neelesh Dixit | CL15: =AY15-Q15 -> 86089.5 | CM15: =CL15-Y15+Z15 -> 86089.5 | CN15: =BO15-AM15 -> 83012.66 | CO15: =AY15*118% -> 503090.64 | CP15: =-Q15*118% -> -401505.03 | CQ15: =-BZ15*118% -> 3630.6712 | CR15: =-CA15*118% -> 0 | CS15: =SUM(CO15:CR15) -> 105216.28 | CT15: Telangana - HO | CU15: Telangana - HO | CV15: =MID(G15,3,10) -> AAMCB5608A | CW15: =MID(AR15,3,10) -> AAACD5406E | CX15: 0 | CY15: 0 | CZ15: 0 | DA15: 0 | DB15: 0
B16: ="Q" & IF(ROUNDUP(MONTH(D16)/3,0)-1=0,4,ROUNDUP(MONTH(D16)/3,0)-1) -> Q1 | C16: =TEXT(AN16,"mmm-yy") -> Apr-26 | D16: 46130 | E16: SH04261806 | F16: BLACK GOLD RECYCLING PRIVATE LIMITED | G16: 27AAMCB5608A1ZX | H16: 25/PUN/INV0285 | I16: 46130 | J16: 26-27/PUR/000939 | K16: 46130 | L16: MH | M16: DD01AC9274 | N16: PET Bottle Scrap Baled - Green | O16: 690 | P16: 36.5 | Q16: =O16*P16 -> 25185 | R16: 0 | S16: =O16-R16 -> 690 | T16: 0 | U16: 0 | V16: 0 | W16: 0 | X16: 0 | Y16: 0 | Z16: 0 | AA16: 0 | AB16: =Y16+AA16+Z16 -> 0 | AC16: 0 | AD16: =IFERROR((Q16+AB16)/S16,0) -> 36.5 | AE16: 0 | AF16: 0 | AG16: 0 | AH16: 0 | AI16: 0 | AJ16: 0 | AK16: 0 | AL16: 0 | AM16: =Q16+AB16+AL16+AK16+AJ16+T16+AE16 -> 25185 | AN16: 46130 | AO16: 36/REW/27IN00005 | AP16: 832139000052985017 | AQ16: DALMIA POLYPRO INDUSTRIES PRIVATE LIMITED (27) | AR16: 27AAACD5406E1Z3 | AS16: Koregaon Bhima Maharashtra 412216 | AT16: Dindori | AU16: Maharashtra | AV16: 0 | AW16: 690 | AX16: 42 | AY16: =AW16*AX16 -> 28980 | AZ16: =AW16=O16 -> TRUE | BA16: 0 | BB16: =AW16-BA16 -> 690 | BC16: 0 | BD16: Regular | BE16: 0 | BF16: 0 | BG16: 0 | BH16: 36/REW/27CN00028 | BI16: 46181 | BJ16: 0 | BK16: 0 | BL16: 0 | BM16: 0 | BN16: 0 | BO16: =AY16+BL16+BM16+BN16+BC16+BG16 -> 28980 | BP16: =BO16-AM16 -> 3795 | BQ16: =IF(BP16>=0,"Positive Margin","Negative Margin") -> Positive Margin | BR16: CN Issued | BS16: =AY16-Y16-Q16-AA16-T16+BC16 -> 3795 | BT16: =IF(BS16<0, "Negative Margin at Inception", "Positive Margin at Inception") -> Positive Margin at Inception | BU16: =IFERROR(BP16/BO16,"0") -> 0.13095238 | BV16: =IF(BU16<1%,"Less Than 1%",IF(BU16>2%,"More than 2%",IF(BU16>=1%,"1% - 2%"))) -> More than 2% | BW16: =BM16+BN16 -> 0 | BX16: =AL16+AK16 -> 0 | BY16: =BW16-BX16 -> 0 | BZ16: =BM16 -> 0 | CA16: =AK16 -> 0 | CB16: =BZ16-CA16 -> 0 | CC16: Marketplace (Rewerse) | CD16: 0 | CE16: =TEXT(AN16,"mmm-yy") -> Apr-26 | CF16: =AM16-AL16-AA16 -> 25185 | CG16: =BO16-BN16 -> 28980 | CH16: =INT((D16- IF(MONTH(D16) >= 4, DATE(YEAR(D16), 4, 1), DATE(YEAR(D16)-1, 4, 1))) / 7) + 1 -> 3 | CI16: Plastic | CJ16: Plastic | CK16: =_xlfn.XLOOKUP(AR16,receivables!B:B,receivables!D:D) -> Neelesh Dixit | CL16: =AY16-Q16 -> 3795 | CM16: =CL16-Y16+Z16 -> 3795 | CN16: =BO16-AM16 -> 3795 | CO16: =AY16*118% -> 34196.4 | CP16: =-Q16*118% -> -29718.3 | CQ16: =-BZ16*118% -> 0 | CR16: =-CA16*118% -> 0 | CS16: =SUM(CO16:CR16) -> 4478.1 | CT16: Telangana - HO | CU16: Telangana - HO | CV16: =MID(G16,3,10) -> AAMCB5608A | CW16: =MID(AR16,3,10) -> AAACD5406E | CX16: 0 | CY16: 0 | CZ16: 0 | DA16: 0 | DB16: 0
B17: ="Q" & IF(ROUNDUP(MONTH(D17)/3,0)-1=0,4,ROUNDUP(MONTH(D17)/3,0)-1) -> Q1 | C17: =TEXT(AN17,"mmm-yy") -> Apr-26 | D17: 46130 | E17: SH04261806 | F17: BLACK GOLD RECYCLING PRIVATE LIMITED | G17: 27AAMCB5608A1ZX | H17: 25/PUN/INV0285 | I17: 46130 | J17: 26-27/PUR/000939 | K17: 46130 | L17: MH | M17: DD01AC9274 | N17: PET Liquor Bottle Scrap Baled | O17: 751 | P17: 41.5 | Q17: =O17*P17 -> 31166.5 | R17: 0 | S17: =O17-R17 -> 751 | T17: 0 | U17: 0 | V17: 0 | W17: 0 | X17: 0 | Y17: 0 | Z17: 0 | AA17: 0 | AB17: =Y17+AA17+Z17 -> 0 | AC17: 0 | AD17: =IFERROR((Q17+AB17)/S17,0) -> 41.5 | AE17: 0 | AF17: 0 | AG17: 0 | AH17: 0 | AI17: 0 | AJ17: 0 | AK17: 0 | AL17: 0 | AM17: =Q17+AB17+AL17+AK17+AJ17+T17+AE17 -> 31166.5 | AN17: 46130 | AO17: 36/REW/27IN00005 | AP17: 832139000052985017 | AQ17: DALMIA POLYPRO INDUSTRIES PRIVATE LIMITED (27) | AR17: 27AAACD5406E1Z3 | AS17: Koregaon Bhima Maharashtra 412216 | AT17: Dindori | AU17: Maharashtra | AV17: 0 | AW17: 751 | AX17: 57 | AY17: =AW17*AX17 -> 42807 | AZ17: =AW17=O17 -> TRUE | BA17: 0 | BB17: =AW17-BA17 -> 751 | BC17: 0 | BD17: Regular | BE17: 0 | BF17: 0 | BG17: 0 | BH17: 36/REW/27CN00028 | BI17: 46181 | BJ17: 0 | BK17: 0 | BL17: 0 | BM17: 0 | BN17: 0 | BO17: =AY17+BL17+BM17+BN17+BC17+BG17 -> 42807 | BP17: =BO17-AM17 -> 11640.5 | BQ17: =IF(BP17>=0,"Positive Margin","Negative Margin") -> Positive Margin | BR17: CN Issued | BS17: =AY17-Y17-Q17-AA17-T17+BC17 -> 11640.5 | BT17: =IF(BS17<0, "Negative Margin at Inception", "Positive Margin at Inception") -> Positive Margin at Inception | BU17: =IFERROR(BP17/BO17,"0") -> 0.27192982 | BV17: =IF(BU17<1%,"Less Than 1%",IF(BU17>2%,"More than 2%",IF(BU17>=1%,"1% - 2%"))) -> More than 2% | BW17: =BM17+BN17 -> 0 | BX17: =AL17+AK17 -> 0 | BY17: =BW17-BX17 -> 0 | BZ17: =BM17 -> 0 | CA17: =AK17 -> 0 | CB17: =BZ17-CA17 -> 0 | CC17: Marketplace (Rewerse) | CD17: 0 | CE17: =TEXT(AN17,"mmm-yy") -> Apr-26 | CF17: =AM17-AL17-AA17 -> 31166.5 | CG17: =BO17-BN17 -> 42807 | CH17: =INT((D17- IF(MONTH(D17) >= 4, DATE(YEAR(D17), 4, 1), DATE(YEAR(D17)-1, 4, 1))) / 7) + 1 -> 3 | CI17: Plastic | CJ17: Plastic | CK17: =_xlfn.XLOOKUP(AR17,receivables!B:B,receivables!D:D) -> Neelesh Dixit | CL17: =AY17-Q17 -> 11640.5 | CM17: =CL17-Y17+Z17 -> 11640.5 | CN17: =BO17-AM17 -> 11640.5 | CO17: =AY17*118% -> 50512.26 | CP17: =-Q17*118% -> -36776.47 | CQ17: =-BZ17*118% -> 0 | CR17: =-CA17*118% -> 0 | CS17: =SUM(CO17:CR17) -> 13735.79 | CT17: Telangana - HO | CU17: Telangana - HO | CV17: =MID(G17,3,10) -> AAMCB5608A | CW17: =MID(AR17,3,10) -> AAACD5406E | CX17: 0 | CY17: 0 | CZ17: 0 | DA17: 0 | DB17: 0
B18: ="Q" & IF(ROUNDUP(MONTH(D18)/3,0)-1=0,4,ROUNDUP(MONTH(D18)/3,0)-1) -> Q1 | C18: =TEXT(AN18,"mmm-yy") -> Apr-26 | D18: 46134 | E18: SH04262206 | F18: BLACK GOLD RECYCLING PRIVATE LIMITED | G18: 27AAMCB5608A1ZX | H18: 25/PUN/INV0286 | I18: 46134 | J18: 26-27/PUR/001265 | K18: 46134 | L18: MH | M18: MH27DT1409 | N18: PET Bottle Scrap Baled - Clear | O18: 8711 | P18: 42 | Q18: =O18*P18 -> 365862 | R18: 0 | S18: =O18-R18 -> 8711 | T18: 0 | U18: 0 | V18: 0 | W18: 0 | X18: 0 | Y18: 0 | Z18: 0 | AA18: 0 | AB18: =Y18+AA18+Z18 -> 0 | AC18: 0 | AD18: =IFERROR((Q18+AB18)/S18,0) -> 42 | AE18: 0 | AF18: 0 | AG18: 0 | AH18: 0 | AI18: 0 | AJ18: 0 | AK18: 0 | AL18: 0 | AM18: =Q18+AB18+AL18+AK18+AJ18+T18+AE18 -> 365862 | AN18: 46134 | AO18: 36/REW/27IN00006 | AP18: 832139000052985017 | AQ18: DALMIA POLYPRO INDUSTRIES PRIVATE LIMITED (27) | AR18: 27AAACD5406E1Z3 | AS18: Bhima Maharashtra 412216 | AT18: Dindori | AU18: Maharashtra | AV18: 0 | AW18: 8711 | AX18: 52 | AY18: =AW18*AX18 -> 452972 | AZ18: =AW18=O18 -> TRUE | BA18: 0 | BB18: =AW18-BA18 -> 8711 | BC18: 0 | BD18: Regular | BE18: 0 | BF18: 0 | BG18: 0 | BH18: 36/REW/27CN00029 | BI18: 46181 | BJ18: 0 | BK18: 0 | BL18: 0 | BM18: -4975.88 | BN18: 0 | BO18: =AY18+BL18+BM18+BN18+BC18+BG18 -> 447996.12 | BP18: =BO18-AM18 -> 82134.12 | BQ18: =IF(BP18>=0,"Positive Margin","Negative Margin") -> Positive Margin | BR18: CN Issued | BS18: =AY18-Y18-Q18-AA18-T18+BC18 -> 87110 | BT18: =IF(BS18<0, "Negative Margin at Inception", "Positive Margin at Inception") -> Positive Margin at Inception | BU18: =IFERROR(BP18/BO18,"0") -> 0.18333668 | BV18: =IF(BU18<1%,"Less Than 1%",IF(BU18>2%,"More than 2%",IF(BU18>=1%,"1% - 2%"))) -> More than 2% | BW18: =BM18+BN18 -> -4975.88 | BX18: =AL18+AK18 -> 0 | BY18: =BW18-BX18 -> -4975.88 | BZ18: =BM18 -> -4975.88 | CA18: =AK18 -> 0 | CB18: =BZ18-CA18 -> -4975.88 | CC18: Marketplace (Rewerse) | CD18: 0 | CE18: =TEXT(AN18,"mmm-yy") -> Apr-26 | CF18: =AM18-AL18-AA18 -> 365862 | CG18: =BO18-BN18 -> 447996.12 | CH18: =INT((D18- IF(MONTH(D18) >= 4, DATE(YEAR(D18), 4, 1), DATE(YEAR(D18)-1, 4, 1))) / 7) + 1 -> 4 | CI18: Plastic | CJ18: Plastic | CK18: =_xlfn.XLOOKUP(AR18,receivables!B:B,receivables!D:D) -> Neelesh Dixit | CL18: =AY18-Q18 -> 87110 | CM18: =CL18-Y18+Z18 -> 87110 | CN18: =BO18-AM18 -> 82134.12 | CO18: =AY18*118% -> 534506.96 | CP18: =-Q18*118% -> -431717.16 | CQ18: =-BZ18*118% -> 5871.5384 | CR18: =-CA18*118% -> 0 | CS18: =SUM(CO18:CR18) -> 108661.34 | CT18: Telangana - HO | CU18: Telangana - HO | CV18: =MID(G18,3,10) -> AAMCB5608A | CW18: =MID(AR18,3,10) -> AAACD5406E | CX18: 0 | CY18: 0 | CZ18: 0 | DA18: 0 | DB18: 0
... B25: ="Q" & IF(ROUNDUP(MONTH(D25)/3,0)-1=0,4,ROUNDUP(MONTH(D25)/3,0)-1) -> Q1 | C25: =TEXT(AN25,"mmm-yy") -> May-26 | D25: 46145 | E25: SH05260301 | F25: BLACK GOLD RECYCLING PRIVATE LIMITED | G25: 27AAMCB5608A1ZX | H25: 25/PUN/INV0293 | I25: 46145 | J25: 26-27/PUR/001702 | K25: 46145 | L25: MH | M25: DD01AC9274 | N25: PET Bottle Scrap Baled - Green | O25: 521 | P25: 38.5 | Q25: =O25*P25 -> 20058.5 | R25: 0 | S25: =O25-R25 -> 521 | T25: 0 | U25: 0 | V25: 0 | W25: 0 | X25: 0 | Y25: 0 | Z25: 0 | AA25: 0 | AB25: =Y25+AA25+Z25 -> 0 | AC25: 0 | AD25: =IFERROR((Q25+AB25)/S25,0) -> 38.5 | AE25: 0 | AF25: 0 | AG25: 0 | AH25: 0 | AI25: 0 | AJ25: 0 | AK25: 0 | AL25: 0 | AM25: =Q25+AB25+AL25+AK25+AJ25+T25+AE25 -> 20058.5 | AN25: 46145 | AO25: 36/REW/27IN00008 | AP25: 832139000052985017 | AQ25: DALMIA POLYPRO INDUSTRIES PRIVATE LIMITED (27) | AR25: 27AAACD5406E1Z3 | AS25: Koregaon Bhima Maharashtra 412216 | AT25: Dindori | AU25: Maharashtra | AV25: 0 | AW25: 521 | AX25: 42 | AY25: =AW25*AX25 -> 21882 | AZ25: =AW25=O25 -> TRUE | BA25: 0 | BB25: =AW25-BA25 -> 521 | BC25: 0 | BD25: Regular | BE25: 0 | BF25: 0 | BG25: 0 | BH25: 36/REW/27CN00031 | BI25: 46181 | BJ25: 0 | BK25: 0 | BL25: 0 | BM25: 0 | BN25: 0 | BO25: =AY25+BL25+BM25+BN25+BC25+BG25 -> 21882 | BP25: =BO25-AM25 -> 1823.5 | BQ25: =IF(BP25>=0,"Positive Margin","Negative Margin") -> Positive Margin | BR25: CN Issued | BS25: =AY25-Y25-Q25-AA25-T25+BC25 -> 1823.5 | BT25: =IF(BS25<0, "Negative Margin at Inception", "Positive Margin at Inception") -> Positive Margin at Inception | BU25: =IFERROR(BP25/BO25,"0") -> 0.083333333 | BV25: =IF(BU25<1%,"Less Than 1%",IF(BU25>2%,"More than 2%",IF(BU25>=1%,"1% - 2%"))) -> More than 2% | BW25: =BM25+BN25 -> 0 | BX25: =AL25+AK25 -> 0 | BY25: =BW25-BX25 -> 0 | BZ25: =BM25 -> 0 | CA25: =AK25 -> 0 | CB25: =BZ25-CA25 -> 0 | CC25: Marketplace (Rewerse) | CD25: 0 | CE25: =TEXT(AN25,"mmm-yy") -> May-26 | CF25: =AM25-AL25-AA25 -> 20058.5 | CG25: =BO25-BN25 -> 21882 | CH25: =INT((D25- IF(MONTH(D25) >= 4, DATE(YEAR(D25), 4, 1), DATE(YEAR(D25)-1, 4, 1))) / 7) + 1 -> 5 | CI25: Plastic | CJ25: Plastic | CK25: =_xlfn.XLOOKUP(AR25,receivables!B:B,receivables!D:D) -> Neelesh Dixit | CL25: =AY25-Q25 -> 1823.5 | CM25: =CL25-Y25+Z25 -> 1823.5 | CN25: =BO25-AM25 -> 1823.5 | CO25: =AY25*118% -> 25820.76 | CP25: =-Q25*118% -> -23669.03 | CQ25: =-BZ25*118% -> 0 | CR25: =-CA25*118% -> 0 | CS25: =SUM(CO25:CR25) -> 2151.73 | CT25: Telangana - HO | CU25: Telangana - HO | CV25: =MID(G25,3,10) -> AAMCB5608A | CW25: =MID(AR25,3,10) -> AAACD5406E | CX25: 0 | CY25: 0 | CZ25: 0 | DA25: 0 | DB25: 0
B26: ="Q" & IF(ROUNDUP(MONTH(D26)/3,0)-1=0,4,ROUNDUP(MONTH(D26)/3,0)-1) -> Q1 | C26: =TEXT(AN26,"mmm-yy") -> May-26 | D26: 46147 | E26: SH05260505 | F26: BLACK GOLD RECYCLING PRIVATE LIMITED | G26: 27AAMCB5608A1ZX | H26: 25/PUN/INV0295 | I26: 46147 | J26: 26-27/PUR/001826 | K26: 46147 | L26: MH | M26: DD01AG9184 | N26: PET Bottle Scrap Baled - Clear | O26: 7918 | P26: 44 | Q26: =O26*P26 -> 348392 | R26: 0 | S26: =O26-R26 -> 7918 | T26: 0 | U26: 0 | V26: 0 | W26: 0 | X26: 0 | Y26: 0 | Z26: 0 | AA26: 0 | AB26: =Y26+AA26+Z26 -> 0 | AC26: 0 | AD26: =IFERROR((Q26+AB26)/S26,0) -> 44 | AE26: 0 | AF26: 0 | AG26: 0 | AH26: 0 | AI26: 0 | AJ26: 0 | AK26: 0 | AL26: 0 | AM26: =Q26+AB26+AL26+AK26+AJ26+T26+AE26 -> 348392 | AN26: 46147 | AO26: 36/REW/27IN00009 | AP26: 832139000052985017 | AQ26: DALMIA POLYPRO INDUSTRIES PRIVATE LIMITED (27) | AR26: 27AAACD5406E1Z3 | AS26: Bhima Maharashtra 412216 | AT26: Dindori | AU26: Maharashtra | AV26: 0 | AW26: 7918 | AX26: 60 | AY26: =AW26*AX26 -> 475080 | AZ26: =AW26=O26 -> TRUE | BA26: 0 | BB26: =AW26-BA26 -> 7918 | BC26: 0 | BD26: Regular | BE26: 0 | BF26: 0 | BG26: 0 | BH26: 0 | BI26: 0 | BJ26: 0 | BK26: 0 | BL26: 0 | BM26: 0 | BN26: =AY26*$BM$3 -> -11877 | BO26: =AY26+BL26+BM26+BN26+BC26+BG26 -> 463203 | BP26: =BO26-AM26 -> 114811 | BQ26: =IF(BP26>=0,"Positive Margin","Negative Margin") -> Positive Margin | BR26: CN Provision | BS26: =AY26-Y26-Q26-AA26-T26+BC26 -> 126688 | BT26: =IF(BS26<0, "Negative Margin at Inception", "Positive Margin at Inception") -> Positive Margin at Inception | BU26: =IFERROR(BP26/BO26,"0") -> 0.24786325 | BV26: =IF(BU26<1%,"Less Than 1%",IF(BU26>2%,"More than 2%",IF(BU26>=1%,"1% - 2%"))) -> More than 2% | BW26: =BM26+BN26 -> -11877 | BX26: =AL26+AK26 -> 0 | BY26: =BW26-BX26 -> -11877 | BZ26: =BM26 -> 0 | CA26: =AK26 -> 0 | CB26: =BZ26-CA26 -> 0 | CC26: Marketplace (Rewerse) | CD26: 0 | CE26: =TEXT(AN26,"mmm-yy") -> May-26 | CF26: =AM26-AL26-AA26 -> 348392 | CG26: =BO26-BN26 -> 475080 | CH26: =INT((D26- IF(MONTH(D26) >= 4, DATE(YEAR(D26), 4, 1), DATE(YEAR(D26)-1, 4, 1))) / 7) + 1 -> 5 | CI26: Plastic | CJ26: Plastic | CK26: =_xlfn.XLOOKUP(AR26,receivables!B:B,receivables!D:D) -> Neelesh Dixit | CL26: =AY26-Q26 -> 126688 | CM26: =CL26-Y26+Z26 -> 126688 | CN26: =BO26-AM26 -> 114811 | CO26: =AY26*118% -> 560594.4 | CP26: =-Q26*118% -> -411102.56 | CQ26: =-BZ26*118% -> 0 | CR26: =-CA26*118% -> 0 | CS26: =SUM(CO26:CR26) -> 149491.84 | CT26: Telangana - HO | CU26: Telangana - HO | CV26: =MID(G26,3,10) -> AAMCB5608A | CW26: =MID(AR26,3,10) -> AAACD5406E | CX26: 0 | CY26: 0 | CZ26: 0 | DA26: 0 | DB26: 0
B27: ="Q" & IF(ROUNDUP(MONTH(D27)/3,0)-1=0,4,ROUNDUP(MONTH(D27)/3,0)-1) -> Q1 | C27: =TEXT(AN27,"mmm-yy") -> May-26 | D27: 46147 | E27: SH05260505 | F27: BLACK GOLD RECYCLING PRIVATE LIMITED | G27: 27AAMCB5608A1ZX | H27: 25/PUN/INV0295 | I27: 46147 | J27: 26-27/PUR/001826 | K27: 46147 | L27: MH | M27: DD01AG9184 | N27: PET Bottle Scrap Baled - Green | O27: 676 | P27: 39 | Q27: =O27*P27 -> 26364 | R27: 0 | S27: =O27-R27 -> 676 | T27: 0 | U27: 0 | V27: 0 | W27: 0 | X27: 0 | Y27: 0 | Z27: 0 | AA27: 0 | AB27: =Y27+AA27+Z27 -> 0 | AC27: 0 | AD27: =IFERROR((Q27+AB27)/S27,0) -> 39 | AE27: 0 | AF27: 0 | AG27: 0 | AH27: 0 | AI27: 0 | AJ27: 0 | AK27: 0 | AL27: 0 | AM27: =Q27+AB27+AL27+AK27+AJ27+T27+AE27 -> 26364 | AN27: 46147 | AO27: 36/REW/27IN00009 | AP27: 832139000052985017 | AQ27: DALMIA POLYPRO INDUSTRIES PRIVATE LIMITED (27) | AR27: 27AAACD5406E1Z3 | AS27: Bhima Maharashtra 412216 | AT27: Dindori | AU27: Maharashtra | AV27: 0 | AW27: 676 | AX27: 50 | AY27: =AW27*AX27 -> 33800 | AZ27: =AW27=O27 -> TRUE | BA27: 0 | BB27: =AW27-BA27 -> 676 | BC27: 0 | BD27: Regular | BE27: 0 | BF27: 0 | BG27: 0 | BH27: 0 | BI27: 0 | BJ27: 0 | BK27: 0 | BL27: 0 | BM27: 0 | BN27: =AY27*$BM$3 -> -845 | BO27: =AY27+BL27+BM27+BN27+BC27+BG27 -> 32955 | BP27: =BO27-AM27 -> 6591 | BQ27: =IF(BP27>=0,"Positive Margin","Negative Margin") -> Positive Margin | BR27: CN Provision | BS27: =AY27-Y27-Q27-AA27-T27+BC27 -> 7436 | BT27: =IF(BS27<0, "Negative Margin at Inception", "Positive Margin at Inception") -> Positive Margin at Inception | BU27: =IFERROR(BP27/BO27,"0") -> 0.2 | BV27: =IF(BU27<1%,"Less Than 1%",IF(BU27>2%,"More than 2%",IF(BU27>=1%,"1% - 2%"))) -> More than 2% | BW27: =BM27+BN27 -> -845 | BX27: =AL27+AK27 -> 0 | BY27: =BW27-BX27 -> -845 | BZ27: =BM27 -> 0 | CA27: =AK27 -> 0 | CB27: =BZ27-CA27 -> 0 | CC27: Marketplace (Rewerse) | CD27: 0 | CE27: =TEXT(AN27,"mmm-yy") -> May-26 | CF27: =AM27-AL27-AA27 -> 26364 | CG27: =BO27-BN27 -> 33800 | CH27: =INT((D27- IF(MONTH(D27) >= 4, DATE(YEAR(D27), 4, 1), DATE(YEAR(D27)-1, 4, 1))) / 7) + 1 -> 5 | CI27: Plastic | CJ27: Plastic | CK27: =_xlfn.XLOOKUP(AR27,receivables!B:B,receivables!D:D) -> Neelesh Dixit | CL27: =AY27-Q27 -> 7436 | CM27: =CL27-Y27+Z27 -> 7436 | CN27: =BO27-AM27 -> 6591 | CO27: =AY27*118% -> 39884 | CP27: =-Q27*118% -> -31109.52 | CQ27: =-BZ27*118% -> 0 | CR27: =-CA27*118% -> 0 | CS27: =SUM(CO27:CR27) -> 8774.48 | CT27: Telangana - HO | CU27: Telangana - HO | CV27: =MID(G27,3,10) -> AAMCB5608A | CW27: =MID(AR27,3,10) -> AAACD5406E | CX27: 0 | CY27: 0 | CZ27: 0 | DA27: 0 | DB27: 0
B28: ="Q" & IF(ROUNDUP(MONTH(D28)/3,0)-1=0,4,ROUNDUP(MONTH(D28)/3,0)-1) -> Q1 | C28: =TEXT(AN28,"mmm-yy") -> May-26 | D28: 46147 | E28: SH05260505 | F28: BLACK GOLD RECYCLING PRIVATE LIMITED | G28: 27AAMCB5608A1ZX | H28: 25/PUN/INV0295 | I28: 46147 | J28: 26-27/PUR/001826 | K28: 46147 | L28: MH | M28: DD01AG9184 | N28: PET Liquor Bottle Scrap Baled | O28: 1321 | P28: 44 | Q28: =O28*P28 -> 58124 | R28: 0 | S28: =O28-R28 -> 1321 | T28: 0 | U28: 0 | V28: 0 | W28: 0 | X28: 0 | Y28: 0 | Z28: 0 | AA28: 0 | AB28: =Y28+AA28+Z28 -> 0 | AC28: 0 | AD28: =IFERROR((Q28+AB28)/S28,0) -> 44 | AE28: 0 | AF28: 0 | AG28: 0 | AH28: 0 | AI28: 0 | AJ28: 0 | AK28: 0 | AL28: 0 | AM28: =Q28+AB28+AL28+AK28+AJ28+T28+AE28 -> 58124 | AN28: 46147 | AO28: 36/REW/27IN00009 | AP28: 832139000052985017 | AQ28: DALMIA POLYPRO INDUSTRIES PRIVATE LIMITED (27) | AR28: 27AAACD5406E1Z3 | AS28: Bhima Maharashtra 412216 | AT28: Dindori | AU28: Maharashtra | AV28: 0 | AW28: 1321 | AX28: 65 | AY28: =AW28*AX28 -> 85865 | AZ28: =AW28=O28 -> TRUE | BA28: 0 | BB28: =AW28-BA28 -> 1321 | BC28: 0 | BD28: Regular | BE28: 0 | BF28: 0 | BG28: 0 | BH28: 0 | BI28: 0 | BJ28: 0 | BK28: 0 | BL28: 0 | BM28: 0 | BN28: =AY28*$BM$3 -> -2146.625 | BO28: =AY28+BL28+BM28+BN28+BC28+BG28 -> 83718.375 | BP28: =BO28-AM28 -> 25594.375 | BQ28: =IF(BP28>=0,"Positive Margin","Negative Margin") -> Positive Margin | BR28: CN Provision | BS28: =AY28-Y28-Q28-AA28-T28+BC28 -> 27741 | BT28: =IF(BS28<0, "Negative Margin at Inception", "Positive Margin at Inception") -> Positive Margin at Inception | BU28: =IFERROR(BP28/BO28,"0") -> 0.30571992 | BV28: =IF(BU28<1%,"Less Than 1%",IF(BU28>2%,"More than 2%",IF(BU28>=1%,"1% - 2%"))) -> More than 2% | BW28: =BM28+BN28 -> -2146.625 | BX28: =AL28+AK28 -> 0 | BY28: =BW28-BX28 -> -2146.625 | BZ28: =BM28 -> 0 | CA28: =AK28 -> 0 | CB28: =BZ28-CA28 -> 0 | CC28: Marketplace (Rewerse) | CD28: 0 | CE28: =TEXT(AN28,"mmm-yy") -> May-26 | CF28: =AM28-AL28-AA28 -> 58124 | CG28: =BO28-BN28 -> 85865 | CH28: =INT((D28- IF(MONTH(D28) >= 4, DATE(YEAR(D28), 4, 1), DATE(YEAR(D28)-1, 4, 1))) / 7) + 1 -> 5 | CI28: Plastic | CJ28: Plastic | CK28: =_xlfn.XLOOKUP(AR28,receivables!B:B,receivables!D:D) -> Neelesh Dixit | CL28: =AY28-Q28 -> 27741 | CM28: =CL28-Y28+Z28 -> 27741 | CN28: =BO28-AM28 -> 25594.375 | CO28: =AY28*118% -> 101320.7 | CP28: =-Q28*118% -> -68586.32 | CQ28: =-BZ28*118% -> 0 | CR28: =-CA28*118% -> 0 | CS28: =SUM(CO28:CR28) -> 32734.38 | CT28: Telangana - HO | CU28: Telangana - HO | CV28: =MID(G28,3,10) -> AAMCB5608A | CW28: =MID(AR28,3,10) -> AAACD5406E | CX28: 0 | CY28: 0 | CZ28: 0 | DA28: 0 | DB28: 0
B29: ="Q" & IF(ROUNDUP(MONTH(D29)/3,0)-1=0,4,ROUNDUP(MONTH(D29)/3,0)-1) -> Q1 | C29: =TEXT(AN29,"mmm-yy") -> May-26 | D29: 46151 | E29: SH05260903 | F29: BLACK GOLD RECYCLING PRIVATE LIMITED | G29: 27AAMCB5608A1ZX | H29: 25/PUN/INV0298 | I29: 46151 | J29: 26-27/PUR/001930 | K29: 46151 | L29: MH | M29: DD01AE9181 | N29: PET Bottle Scrap Baled - Clear | O29: 8599 | P29: 45.5 | Q29: =O29*P29 -> 391254.5 | R29: 0 | S29: =O29-R29 -> 8599 | T29: 0 | U29: 0 | V29: 0 | W29: 0 | X29: 0 | Y29: 0 | Z29: 0 | AA29: 0 | AB29: =Y29+AA29+Z29 -> 0 | AC29: 0 | AD29: =IFERROR((Q29+AB29)/S29,0) -> 45.5 | AE29: 0 | AF29: 0 | AG29: 0 | AH29: 0 | AI29: 0 | AJ29: 0 | AK29: 0 | AL29: 0 | AM29: =Q29+AB29+AL29+AK29+AJ29+T29+AE29 -> 391254.5 | AN29: 46151 | AO29: 36/REW/27IN00010 | AP29: 832139000052985017 | AQ29: DALMIA POLYPRO INDUSTRIES PRIVATE LIMITED (27) | AR29: 27AAACD5406E1Z3 | AS29: Koregaon Bhima,Maharashtra,412216 | AT29: Dindori | AU29: Maharashtra | AV29: 0 | AW29: 8599 | AX29: 60 | AY29: =AW29*AX29 -> 515940 | AZ29: =AW29=O29 -> TRUE | BA29: 0 | BB29: =AW29-BA29 -> 8599 | BC29: 0 | BD29: Regular | BE29: 0 | BF29: 0 | BG29: 0 | BH29: 0 | BI29: 0 | BJ29: 0 | BK29: 0 | BL29: 0 | BM29: 0 | BN29: =AY29*$BM$3 -> -12898.5 | BO29: =AY29+BL29+BM29+BN29+BC29+BG29 -> 503041.5 | BP29: =BO29-AM29 -> 111787 | BQ29: =IF(BP29>=0,"Positive Margin","Negative Margin") -> Positive Margin | BR29: CN Provision | BS29: =AY29-Y29-Q29-AA29-T29+BC29 -> 124685.5 | BT29: =IF(BS29<0, "Negative Margin at Inception", "Positive Margin at Inception") -> Positive Margin at Inception | BU29: =IFERROR(BP29/BO29,"0") -> 0.22222222 | BV29: =IF(BU29<1%,"Less Than 1%",IF(BU29>2%,"More than 2%",IF(BU29>=1%,"1% - 2%"))) -> More than 2% | BW29: =BM29+BN29 -> -12898.5 | BX29: =AL29+AK29 -> 0 | BY29: =BW29-BX29 -> -12898.5 | BZ29: =BM29 -> 0 | CA29: =AK29 -> 0 | CB29: =BZ29-CA29 -> 0 | CC29: Marketplace (Rewerse) | CD29: 0 | CE29: =TEXT(AN29,"mmm-yy") -> May-26 | CF29: =AM29-AL29-AA29 -> 391254.5 | CG29: =BO29-BN29 -> 515940 | CH29: =INT((D29- IF(MONTH(D29) >= 4, DATE(YEAR(D29), 4, 1), DATE(YEAR(D29)-1, 4, 1))) / 7) + 1 -> 6 | CI29: Plastic | CJ29: Plastic | CK29: =_xlfn.XLOOKUP(AR29,receivables!B:B,receivables!D:D) -> Neelesh Dixit | CL29: =AY29-Q29 -> 124685.5 | CM29: =CL29-Y29+Z29 -> 124685.5 | CN29: =BO29-AM29 -> 111787 | CO29: =AY29*118% -> 608809.2 | CP29: =-Q29*118% -> -461680.31 | CQ29: =-BZ29*118% -> 0 | CR29: =-CA29*118% -> 0 | CS29: =SUM(CO29:CR29) -> 147128.89 | CT29: Telangana - HO | CU29: Telangana - HO | CV29: =MID(G29,3,10) -> AAMCB5608A | CW29: =MID(AR29,3,10) -> AAACD5406E | CX29: 0 | CY29: 0 | CZ29: 0 | DA29: 0 | DB29: 0
B30: ="Q" & IF(ROUNDUP(MONTH(D30)/3,0)-1=0,4,ROUNDUP(MONTH(D30)/3,0)-1) -> Q1 | C30: =TEXT(AN30,"mmm-yy") -> May-26 | D30: 46151 | E30: SH05260903 | F30: BLACK GOLD RECYCLING PRIVATE LIMITED | G30: 27AAMCB5608A1ZX | H30: 25/PUN/INV0298 | I30: 46151 | J30: 26-27/PUR/001930 | K30: 46151 | L30: MH | M30: DD01AE9181 | N30: PET Bottle Scrap Baled - Green | O30: 491 | P30: 40.5 | Q30: =O30*P30 -> 19885.5 | R30: 0 | S30: =O30-R30 -> 491 | T30: 0 | U30: 0 | V30: 0 | W30: 0 | X30: 0 | Y30: 0 | Z30: 0 | AA30: 0 | AB30: =Y30+AA30+Z30 -> 0 | AC30: 0 | AD30: =IFERROR((Q30+AB30)/S30,0) -> 40.5 | AE30: 0 | AF30: 0 | AG30: 0 | AH30: 0 | AI30: 0 | AJ30: 0 | AK30: 0 | AL30: 0 | AM30: =Q30+AB30+AL30+AK30+AJ30+T30+AE30 -> 19885.5 | AN30: 46151 | AO30: 36/REW/27IN00010 | AP30: 832139000052985017 | AQ30: DALMIA POLYPRO INDUSTRIES PRIVATE LIMITED (27) | AR30: 27AAACD5406E1Z3 | AS30: Koregaon Bhima,Maharashtra,412216 | AT30: Dindori | AU30: Maharashtra | AV30: 0 | AW30: 491 | AX30: 50 | AY30: =AW30*AX30 -> 24550 | AZ30: =AW30=O30 -> TRUE | BA30: 0 | BB30: =AW30-BA30 -> 491 | BC30: 0 | BD30: Regular | BE30: 0 | BF30: 0 | BG30: 0 | BH30: 0 | BI30: 0 | BJ30: 0 | BK30: 0 | BL30: 0 | BM30: 0 | BN30: =AY30*$BM$3 -> -613.75 | BO30: =AY30+BL30+BM30+BN30+BC30+BG30 -> 23936.25 | BP30: =BO30-AM30 -> 4050.75 | BQ30: =IF(BP30>=0,"Positive Margin","Negative Margin") -> Positive Margin | BR30: CN Provision | BS30: =AY30-Y30-Q30-AA30-T30+BC30 -> 4664.5 | BT30: =IF(BS30<0, "Negative Margin at Inception", "Positive Margin at Inception") -> Positive Margin at Inception | BU30: =IFERROR(BP30/BO30,"0") -> 0.16923077 | BV30: =IF(BU30<1%,"Less Than 1%",IF(BU30>2%,"More than 2%",IF(BU30>=1%,"1% - 2%"))) -> More than 2% | BW30: =BM30+BN30 -> -613.75 | BX30: =AL30+AK30 -> 0 | BY30: =BW30-BX30 -> -613.75 | BZ30: =BM30 -> 0 | CA30: =AK30 -> 0 | CB30: =BZ30-CA30 -> 0 | CC30: Marketplace (Rewerse) | CD30: 0 | CE30: =TEXT(AN30,"mmm-yy") -> May-26 | CF30: =AM30-AL30-AA30 -> 19885.5 | CG30: =BO30-BN30 -> 24550 | CH30: =INT((D30- IF(MONTH(D30) >= 4, DATE(YEAR(D30), 4, 1), DATE(YEAR(D30)-1, 4, 1))) / 7) + 1 -> 6 | CI30: Plastic | CJ30: Plastic | CK30: =_xlfn.XLOOKUP(AR30,receivables!B:B,receivables!D:D) -> Neelesh Dixit | CL30: =AY30-Q30 -> 4664.5 | CM30: =CL30-Y30+Z30 -> 4664.5 | CN30: =BO30-AM30 -> 4050.75 | CO30: =AY30*118% -> 28969 | CP30: =-Q30*118% -> -23464.89 | CQ30: =-BZ30*118% -> 0 | CR30: =-CA30*118% -> 0 | CS30: =SUM(CO30:CR30) -> 5504.11 | CT30: Telangana - HO | CU30: Telangana - HO | CV30: =MID(G30,3,10) -> AAMCB5608A | CW30: =MID(AR30,3,10) -> AAACD5406E | CX30: 0 | CY30: 0 | CZ30: 0 | DA30: 0 | DB30: 0
B31: ="Q" & IF(ROUNDUP(MONTH(D31)/3,0)-1=0,4,ROUNDUP(MONTH(D31)/3,0)-1) -> Q1 | C31: =TEXT(AN31,"mmm-yy") -> May-26 | D31: 46151 | E31: SH05260903 | F31: BLACK GOLD RECYCLING PRIVATE LIMITED | G31: 27AAMCB5608A1ZX | H31: 25/PUN/INV0298 | I31: 46151 | J31: 26-27/PUR/001930 | K31: 46151 | L31: MH | M31: DD01AE9181 | N31: PET Liquor Bottle Scrap Baled | O31: 1150 | P31: 45.5 | Q31: =O31*P31 -> 52325 | R31: 0 | S31: =O31-R31 -> 1150 | T31: 0 | U31: 0 | V31: 0 | W31: 0 | X31: 0 | Y31: 0 | Z31: 0 | AA31: 0 | AB31: =Y31+AA31+Z31 -> 0 | AC31: 0 | AD31: =IFERROR((Q31+AB31)/S31,0) -> 45.5 | AE31: 0 | AF31: 0 | AG31: 0 | AH31: 0 | AI31: 0 | AJ31: 0 | AK31: 0 | AL31: 0 | AM31: =Q31+AB31+AL31+AK31+AJ31+T31+AE31 -> 52325 | AN31: 46151 | AO31: 36/REW/27IN00010 | AP31: 832139000052985017 | AQ31: DALMIA POLYPRO INDUSTRIES PRIVATE LIMITED (27) | AR31: 27AAACD5406E1Z3 | AS31: Koregaon Bhima,Maharashtra,412216 | AT31: Dindori | AU31: Maharashtra | AV31: 0 | AW31: 1150 | AX31: 65 | AY31: =AW31*AX31 -> 74750 | AZ31: =AW31=O31 -> TRUE | BA31: 0 | BB31: =AW31-BA31 -> 1150 | BC31: 0 | BD31: Regular | BE31: 0 | BF31: 0 | BG31: 0 | BH31: 0 | BI31: 0 | BJ31: 0 | BK31: 0 | BL31: 0 | BM31: 0 | BN31: =AY31*$BM$3 -> -1868.75 | BO31: =AY31+BL31+BM31+BN31+BC31+BG31 -> 72881.25 | BP31: =BO31-AM31 -> 20556.25 | BQ31: =IF(BP31>=0,"Positive Margin","Negative Margin") -> Positive Margin | BR31: CN Provision | BS31: =AY31-Y31-Q31-AA31-T31+BC31 -> 22425 | BT31: =IF(BS31<0, "Negative Margin at Inception", "Positive Margin at Inception") -> Positive Margin at Inception | BU31: =IFERROR(BP31/BO31,"0") -> 0.28205128 | BV31: =IF(BU31<1%,"Less Than 1%",IF(BU31>2%,"More than 2%",IF(BU31>=1%,"1% - 2%"))) -> More than 2% | BW31: =BM31+BN31 -> -1868.75 | BX31: =AL31+AK31 -> 0 | BY31: =BW31-BX31 -> -1868.75 | BZ31: =BM31 -> 0 | CA31: =AK31 -> 0 | CB31: =BZ31-CA31 -> 0 | CC31: Marketplace (Rewerse) | CD31: 0 | CE31: =TEXT(AN31,"mmm-yy") -> May-26 | CF31: =AM31-AL31-AA31 -> 52325 | CG31: =BO31-BN31 -> 74750 | CH31: =INT((D31- IF(MONTH(D31) >= 4, DATE(YEAR(D31), 4, 1), DATE(YEAR(D31)-1, 4, 1))) / 7) + 1 -> 6 | CI31: Plastic | CJ31: Plastic | CK31: =_xlfn.XLOOKUP(AR31,receivables!B:B,receivables!D:D) -> Neelesh Dixit | CL31: =AY31-Q31 -> 22425 | CM31: =CL31-Y31+Z31 -> 22425 | CN31: =BO31-AM31 -> 20556.25 | CO31: =AY31*118% -> 88205 | CP31: =-Q31*118% -> -61743.5 | CQ31: =-BZ31*118% -> 0 | CR31: =-CA31*118% -> 0 | CS31: =SUM(CO31:CR31) -> 26461.5 | CT31: Telangana - HO | CU31: Telangana - HO | CV31: =MID(G31,3,10) -> AAMCB5608A | CW31: =MID(AR31,3,10) -> AAACD5406E | CX31: 0 | CY31: 0 | CZ31: 0 | DA31: 0 | DB31: 0
B32: ="Q" & IF(ROUNDUP(MONTH(D32)/3,0)-1=0,4,ROUNDUP(MONTH(D32)/3,0)-1) -> Q1 | C32: =TEXT(AN32,"mmm-yy") -> May-26 | D32: 46158 | E32: SH05261603 | F32: BLACK GOLD RECYCLING PRIVATE LIMITED | G32: 27AAMCB5608A1ZX | H32: 25/PUN/INV0302 | I32: 46158 | J32: 26-27/PUR/002263 | K32: 46158 | L32: MH | M32: MH43BP9096 | N32: PET Bottle Scrap Baled - Clear | O32: 6229 | P32: 46 | Q32: =O32*P32 -> 286534 | R32: 0 | S32: =O32-R32 -> 6229 | T32: 0 | U32: 0 | V32: 0 | W32: 0 | X32: 0 | Y32: 0 | Z32: 0 | AA32: 0 | AB32: =Y32+AA32+Z32 -> 0 | AC32: 0 | AD32: =IFERROR((Q32+AB32)/S32,0) -> 46 | AE32: 0 | AF32: 0 | AG32: 0 | AH32: 0 | AI32: 0 | AJ32: 0 | AK32: 0 | AL32: 0 | AM32: =Q32+AB32+AL32+AK32+AJ32+T32+AE32 -> 286534 | AN32: 46158 | AO32: 36/REW/27IN00011 | AP32: 832139000052985017 | AQ32: DALMIA POLYPRO INDUSTRIES PRIVATE LIMITED (27) | AR32: 27AAACD5406E1Z3 | AS32: Koregaon Bhima, Maharashtra 412216 | AT32: Dindori | AU32: Maharashtra | AW32: 6229 | AX32: 60 | AY32: =AW32*AX32 -> 373740 | AZ32: =AW32=O32 -> TRUE | BA32: 0 | BB32: =AW32-BA32 -> 6229 | BC32: 0 | BD32: Regular | BE32: 0 | BF32: 0 | BG32: 0 | BH32: 0 | BI32: 0 | BJ32: 0 | BK32: 0 | BL32: 0 | BM32: 0 | BN32: =AY32*$BM$3 -> -9343.5 | BO32: =AY32+BL32+BM32+BN32+BC32+BG32 -> 364396.5 | BP32: =BO32-AM32 -> 77862.5 | BQ32: =IF(BP32>=0,"Positive Margin","Negative Margin") -> Positive Margin | BR32: CN Provision | BS32: =AY32-Y32-Q32-AA32-T32+BC32 -> 87206 | BT32: =IF(BS32<0, "Negative Margin at Inception", "Positive Margin at Inception") -> Positive Margin at Inception | BU32: =IFERROR(BP32/BO32,"0") -> 0.21367521 | BV32: =IF(BU32<1%,"Less Than 1%",IF(BU32>2%,"More than 2%",IF(BU32>=1%,"1% - 2%"))) -> More than 2% | BW32: =BM32+BN32 -> -9343.5 | BX32: =AL32+AK32 -> 0 | BY32: =BW32-BX32 -> -9343.5 | BZ32: =BM32 -> 0 | CA32: =AK32 -> 0 | CB32: =BZ32-CA32 -> 0 | CC32: Marketplace (Rewerse) | CD32: 0 | CE32: =TEXT(AN32,"mmm-yy") -> May-26 | CF32: =AM32-AL32-AA32 -> 286534 | CG32: =BO32-BN32 -> 373740 | CH32: =INT((D32- IF(MONTH(D32) >= 4, DATE(YEAR(D32), 4, 1), DATE(YEAR(D32)-1, 4, 1))) / 7) + 1 -> 7 | CI32: Plastic | CJ32: Plastic | CK32: =_xlfn.XLOOKUP(AR32,receivables!B:B,receivables!D:D) -> Neelesh Dixit | CL32: =AY32-Q32 -> 87206 | CM32: =CL32-Y32+Z32 -> 87206 | CN32: =BO32-AM32 -> 77862.5 | CO32: =AY32*118% -> 441013.2 | CP32: =-Q32*118% -> -338110.12 | CQ32: =-BZ32*118% -> 0 | CR32: =-CA32*118% -> 0 | CS32: =SUM(CO32:CR32) -> 102903.08 | CT32: Telangana - HO | CU32: Telangana - HO | CV32: =MID(G32,3,10) -> AAMCB5608A | CW32: =MID(AR32,3,10) -> AAACD5406E | CX32: 0 | CY32: 0 | CZ32: 0 | DA32: 0 | DB32: 0
B33: ="Q" & IF(ROUNDUP(MONTH(D33)/3,0)-1=0,4,ROUNDUP(MONTH(D33)/3,0)-1) -> Q1 | C33: =TEXT(AN33,"mmm-yy") -> May-26 | D33: 46158 | E33: SH05261603 | F33: BLACK GOLD RECYCLING PRIVATE LIMITED | G33: 27AAMCB5608A1ZX | H33: 25/PUN/INV0302 | I33: 46158 | J33: 26-27/PUR/002263 | K33: 46158 | L33: MH | M33: MH43BP9096 | N33: PET Bottle Scrap Baled - Green | O33: 691 | P33: 41 | Q33: =O33*P33 -> 28331 | R33: 0 | S33: =O33-R33 -> 691 | T33: 0 | U33: 0 | V33: 0 | W33: 0 | X33: 0 | Y33: 0 | Z33: 0 | AA33: 0 | AB33: =Y33+AA33+Z33 -> 0 | AC33: 0 | AD33: =IFERROR((Q33+AB33)/S33,0) -> 41 | AE33: 0 | AF33: 0 | AG33: 0 | AH33: 0 | AI33: 0 | AJ33: 0 | AK33: 0 | AL33: 0 | AM33: =Q33+AB33+AL33+AK33+AJ33+T33+AE33 -> 28331 | AN33: 46158 | AO33: 36/REW/27IN00011 | AP33: 832139000052985017 | AQ33: DALMIA POLYPRO INDUSTRIES PRIVATE LIMITED (27) | AR33: 27AAACD5406E1Z3 | AS33: Koregaon Bhima, Maharashtra 412216 | AT33: Dindori | AU33: Maharashtra | AW33: 691 | AX33: 50 | AY33: =AW33*AX33 -> 34550 | AZ33: =AW33=O33 -> TRUE | BA33: 0 | BB33: =AW33-BA33 -> 691 | BC33: 0 | BD33: Regular | BE33: 0 | BF33: 0 | BG33: 0 | BH33: 0 | BI33: 0 | BJ33: 0 | BK33: 0 | BL33: 0 | BM33: 0 | BN33: =AY33*$BM$3 -> -863.75 | BO33: =AY33+BL33+BM33+BN33+BC33+BG33 -> 33686.25 | BP33: =BO33-AM33 -> 5355.25 | BQ33: =IF(BP33>=0,"Positive Margin","Negative Margin") -> Positive Margin | BR33: CN Provision | BS33: =AY33-Y33-Q33-AA33-T33+BC33 -> 6219 | BT33: =IF(BS33<0, "Negative Margin at Inception", "Positive Margin at Inception") -> Positive Margin at Inception | BU33: =IFERROR(BP33/BO33,"0") -> 0.15897436 | BV33: =IF(BU33<1%,"Less Than 1%",IF(BU33>2%,"More than 2%",IF(BU33>=1%,"1% - 2%"))) -> More than 2% | BW33: =BM33+BN33 -> -863.75 | BX33: =AL33+AK33 -> 0 | BY33: =BW33-BX33 -> -863.75 | BZ33: =BM33 -> 0 | CA33: =AK33 -> 0 | CB33: =BZ33-CA33 -> 0 | CC33: Marketplace (Rewerse) | CD33: 0 | CE33: =TEXT(AN33,"mmm-yy") -> May-26 | CF33: =AM33-AL33-AA33 -> 28331 | CG33: =BO33-BN33 -> 34550 | CH33: =INT((D33- IF(MONTH(D33) >= 4, DATE(YEAR(D33), 4, 1), DATE(YEAR(D33)-1, 4, 1))) / 7) + 1 -> 7 | CI33: Plastic | CJ33: Plastic | CK33: =_xlfn.XLOOKUP(AR33,receivables!B:B,receivables!D:D) -> Neelesh Dixit | CL33: =AY33-Q33 -> 6219 | CM33: =CL33-Y33+Z33 -> 6219 | CN33: =BO33-AM33 -> 5355.25 | CO33: =AY33*118% -> 40769 | CP33: =-Q33*118% -> -33430.58 | CQ33: =-BZ33*118% -> 0 | CR33: =-CA33*118% -> 0 | CS33: =SUM(CO33:CR33) -> 7338.42 | CT33: Telangana - HO | CU33: Telangana - HO | CV33: =MID(G33,3,10) -> AAMCB5608A | CW33: =MID(AR33,3,10) -> AAACD5406E | CX33: 0 | CY33: 0 | CZ33: 0 | DA33: 0 | DB33: 0
B34: ="Q" & IF(ROUNDUP(MONTH(D34)/3,0)-1=0,4,ROUNDUP(MONTH(D34)/3,0)-1) -> Q1 | C34: =TEXT(AN34,"mmm-yy") -> May-26 | D34: 46158 | E34: SH05261603 | F34: BLACK GOLD RECYCLING PRIVATE LIMITED | G34: 27AAMCB5608A1ZX | H34: 25/PUN/INV0302 | I34: 46158 | J34: 26-27/PUR/002263 | K34: 46158 | L34: MH | M34: MH43BP9096 | N34: PET Liquor Bottle Scrap Baled | O34: 1165 | P34: 46 | Q34: =O34*P34 -> 53590 | R34: 0 | S34: =O34-R34 -> 1165 | T34: 0 | U34: 0 | V34: 0 | W34: 0 | X34: 0 | Y34: 0 | Z34: 0 | AA34: 0 | AB34: =Y34+AA34+Z34 -> 0 | AC34: 0 | AD34: =IFERROR((Q34+AB34)/S34,0) -> 46 | AE34: 0 | AF34: 0 | AG34: 0 | AH34: 0 | AI34: 0 | AJ34: 0 | AK34: 0 | AL34: 0 | AM34: =Q34+AB34+AL34+AK34+AJ34+T34+AE34 -> 53590 | AN34: 46158 | AO34: 36/REW/27IN00011 | AP34: 832139000052985017 | AQ34: DALMIA POLYPRO INDUSTRIES PRIVATE LIMITED (27) | AR34: 27AAACD5406E1Z3 | AS34: Koregaon Bhima, Maharashtra 412216 | AT34: Dindori | AU34: Maharashtra | AW34: 1165 | AX34: 65 | AY34: =AW34*AX34 -> 75725 | AZ34: =AW34=O34 -> TRUE | BA34: 0 | BB34: =AW34-BA34 -> 1165 | BC34: 0 | BD34: Regular | BE34: 0 | BF34: 0 | BG34: 0 | BH34: 0 | BI34: 0 | BJ34: 0 | BK34: 0 | BL34: 0 | BM34: 0 | BN34: =AY34*$BM$3 -> -1893.125 | BO34: =AY34+BL34+BM34+BN34+BC34+BG34 -> 73831.875 | BP34: =BO34-AM34 -> 20241.875 | BQ34: =IF(BP34>=0,"Positive Margin","Negative Margin") -> Positive Margin | BR34: CN Provision | BS34: =AY34-Y34-Q34-AA34-T34+BC34 -> 22135 | BT34: =IF(BS34<0, "Negative Margin at Inception", "Positive Margin at Inception") -> Positive Margin at Inception | BU34: =IFERROR(BP34/BO34,"0") -> 0.27416174 | BV34: =IF(BU34<1%,"Less Than 1%",IF(BU34>2%,"More than 2%",IF(BU34>=1%,"1% - 2%"))) -> More than 2% | BW34: =BM34+BN34 -> -1893.125 | BX34: =AL34+AK34 -> 0 | BY34: =BW34-BX34 -> -1893.125 | BZ34: =BM34 -> 0 | CA34: =AK34 -> 0 | CB34: =BZ34-CA34 -> 0 | CC34: Marketplace (Rewerse) | CD34: 0 | CE34: =TEXT(AN34,"mmm-yy") -> May-26 | CF34: =AM34-AL34-AA34 -> 53590 | CG34: =BO34-BN34 -> 75725 | CH34: =INT((D34- IF(MONTH(D34) >= 4, DATE(YEAR(D34), 4, 1), DATE(YEAR(D34)-1, 4, 1))) / 7) + 1 -> 7 | CI34: Plastic | CJ34: Plastic | CK34: =_xlfn.XLOOKUP(AR34,receivables!B:B,receivables!D:D) -> Neelesh Dixit | CL34: =AY34-Q34 -> 22135 | CM34: =CL34-Y34+Z34 -> 22135 | CN34: =BO34-AM34 -> 20241.875 | CO34: =AY34*118% -> 89355.5 | CP34: =-Q34*118% -> -63236.2 | CQ34: =-BZ34*118% -> 0 | CR34: =-CA34*118% -> 0 | CS34: =SUM(CO34:CR34) -> 26119.3 | CT34: Telangana - HO | CU34: Telangana - HO | CV34: =MID(G34,3,10) -> AAMCB5608A | CW34: =MID(AR34,3,10) -> AAACD5406E | CX34: 0 | CY34: 0 | CZ34: 0 | DA34: 0 | DB34: 0
B35: ="Q" & IF(ROUNDUP(MONTH(D35)/3,0)-1=0,4,ROUNDUP(MONTH(D35)/3,0)-1) -> Q1 | C35: =TEXT(AN35,"mmm-yy") -> May-26 | D35: 46164 | E35: SH05262207 | F35: BLACK GOLD RECYCLING PRIVATE LIMITED | G35: 27AAMCB5608A1ZX | H35: 25/PUN/INV0305 | I35: 46164 | J35: 26-27/PUR/002494 | K35: 46164 | L35: MH | M35: DD01H9940 | N35: PET Bottle Scrap Baled - Clear | O35: 8873 | P35: 45 | Q35: =O35*P35 -> 399285 | R35: 0 | S35: =O35-R35 -> 8873 | T35: 0 | U35: 0 | V35: 0 | W35: 0 | X35: 0 | Y35: 0 | Z35: 0 | AA35: 0 | AB35: =Y35+AA35+Z35 -> 0 | AC35: 0 | AD35: =IFERROR((Q35+AB35)/S35,0) -> 45 | AE35: 0 | AF35: 0 | AG35: 0 | AH35: 0 | AI35: 0 | AJ35: 0 | AK35: 0 | AL35: 0 | AM35: =Q35+AB35+AL35+AK35+AJ35+T35+AE35 -> 399285 | AN35: 46164 | AO35: 36/REW/27IN00012 | AP35: 832139000052985017 | AQ35: DALMIA POLYPRO INDUSTRIES PRIVATE LIMITED (27) | AR35: 27AAACD5406E1Z3 | AS35: Koregaon Bhima, Maharashtra 412216 | AT35: Dindori | AU35: Maharashtra | AW35: 8873 | AX35: 58 | AY35: =AW35*AX35 -> 514634 | AZ35: =AW35=O35 -> TRUE | BA35: 0 | BB35: =AW35-BA35 -> 8873 | BC35: 0 | BD35: Regular | BE35: 0 | BF35: 0 | BG35: 0 | BH35: 0 | BI35: 0 | BJ35: 0 | BK35: 0 | BL35: 0 | BM35: 0 | BN35: =AY35*$BM$3 -> -12865.85 | BO35: =AY35+BL35+BM35+BN35+BC35+BG35 -> 501768.15 | BP35: =BO35-AM35 -> 102483.15 | BQ35: =IF(BP35>=0,"Positive Margin","Negative Margin") -> Positive Margin | BR35: CN Provision | BS35: =AY35-Y35-Q35-AA35-T35+BC35 -> 115349 | BT35: =IF(BS35<0, "Negative Margin at Inception", "Positive Margin at Inception") -> Positive Margin at Inception | BU35: =IFERROR(BP35/BO35,"0") -> 0.20424403 | BV35: =IF(BU35<1%,"Less Than 1%",IF(BU35>2%,"More than 2%",IF(BU35>=1%,"1% - 2%"))) -> More than 2% | BW35: =BM35+BN35 -> -12865.85 | BX35: =AL35+AK35 -> 0 | BY35: =BW35-BX35 -> -12865.85 | BZ35: =BM35 -> 0 | CA35: =AK35 -> 0 | CB35: =BZ35-CA35 -> 0 | CC35: Marketplace (Rewerse) | CD35: 0 | CE35: =TEXT(AN35,"mmm-yy") -> May-26 | CF35: =AM35-AL35-AA35 -> 399285 | CG35: =BO35-BN35 -> 514634 | CH35: =INT((D35- IF(MONTH(D35) >= 4, DATE(YEAR(D35), 4, 1), DATE(YEAR(D35)-1, 4, 1))) / 7) + 1 -> 8 | CI35: Plastic | CJ35: Plastic | CK35: =_xlfn.XLOOKUP(AR35,receivables!B:B,receivables!D:D) -> Neelesh Dixit | CL35: =AY35-Q35 -> 115349 | CM35: =CL35-Y35+Z35 -> 115349 | CN35: =BO35-AM35 -> 102483.15 | CO35: =AY35*118% -> 607268.12 | CP35: =-Q35*118% -> -471156.3 | CQ35: =-BZ35*118% -> 0 | CR35: =-CA35*118% -> 0 | CS35: =SUM(CO35:CR35) -> 136111.82 | CT35: Telangana - HO | CU35: Telangana - HO | CV35: =MID(G35,3,10) -> AAMCB5608A | CW35: =MID(AR35,3,10) -> AAACD5406E | CX35: 0 | CY35: 0 | CZ35: 0 | DA35: 0 | DB35: 0
B36: ="Q" & IF(ROUNDUP(MONTH(D36)/3,0)-1=0,4,ROUNDUP(MONTH(D36)/3,0)-1) -> Q1 | C36: =TEXT(AN36,"mmm-yy") -> May-26 | D36: 46164 | E36: SH05262207 | F36: BLACK GOLD RECYCLING PRIVATE LIMITED | G36: 27AAMCB5608A1ZX | H36: 25/PUN/INV0305 | I36: 46164 | J36: 26-27/PUR/002494 | K36: 46164 | L36: MH | M36: DD01H9940 | N36: PET Bottle Scrap Baled - Green | O36: 345 | P36: 40 | Q36: =O36*P36 -> 13800 | R36: 0 | S36: =O36-R36 -> 345 | T36: 0 | U36: 0 | V36: 0 | W36: 0 | X36: 0 | Y36: 0 | Z36: 0 | AA36: 0 | AB36: =Y36+AA36+Z36 -> 0 | AC36: 0 | AD36: =IFERROR((Q36+AB36)/S36,0) -> 40 | AE36: 0 | AF36: 0 | AG36: 0 | AH36: 0 | AI36: 0 | AJ36: 0 | AK36: 0 | AL36: 0 | AM36: =Q36+AB36+AL36+AK36+AJ36+T36+AE36 -> 13800 | AN36: 46164 | AO36: 36/REW/27IN00012 | AP36: 832139000052985017 | AQ36: DALMIA POLYPRO INDUSTRIES PRIVATE LIMITED (27) | AR36: 27AAACD5406E1Z3 | AS36: Koregaon Bhima, Maharashtra 412216 | AT36: Dindori | AU36: Maharashtra | AW36: 345 | AX36: 48 | AY36: =AW36*AX36 -> 16560 | AZ36: =AW36=O36 -> TRUE | BA36: 0 | BB36: =AW36-BA36 -> 345 | BC36: 0 | BD36: Regular | BE36: 0 | BF36: 0 | BG36: 0 | BH36: 0 | BI36: 0 | BJ36: 0 | BK36: 0 | BL36: 0 | BM36: 0 | BN36: =AY36*$BM$3 -> -414 | BO36: =AY36+BL36+BM36+BN36+BC36+BG36 -> 16146 | BP36: =BO36-AM36 -> 2346 | BQ36: =IF(BP36>=0,"Positive Margin","Negative Margin") -> Positive Margin | BR36: CN Provision | BS36: =AY36-Y36-Q36-AA36-T36+BC36 -> 2760 | BT36: =IF(BS36<0, "Negative Margin at Inception", "Positive Margin at Inception") -> Positive Margin at Inception | BU36: =IFERROR(BP36/BO36,"0") -> 0.14529915 | BV36: =IF(BU36<1%,"Less Than 1%",IF(BU36>2%,"More than 2%",IF(BU36>=1%,"1% - 2%"))) -> More than 2% | BW36: =BM36+BN36 -> -414 | BX36: =AL36+AK36 -> 0 | BY36: =BW36-BX36 -> -414 | BZ36: =BM36 -> 0 | CA36: =AK36 -> 0 | CB36: =BZ36-CA36 -> 0 | CC36: Marketplace (Rewerse) | CD36: 0 | CE36: =TEXT(AN36,"mmm-yy") -> May-26 | CF36: =AM36-AL36-AA36 -> 13800 | CG36: =BO36-BN36 -> 16560 | CH36: =INT((D36- IF(MONTH(D36) >= 4, DATE(YEAR(D36), 4, 1), DATE(YEAR(D36)-1, 4, 1))) / 7) + 1 -> 8 | CI36: Plastic | CJ36: Plastic | CK36: =_xlfn.XLOOKUP(AR36,receivables!B:B,receivables!D:D) -> Neelesh Dixit | CL36: =AY36-Q36 -> 2760 | CM36: =CL36-Y36+Z36 -> 2760 | CN36: =BO36-AM36 -> 2346 | CO36: =AY36*118% -> 19540.8 | CP36: =-Q36*118% -> -16284 | CQ36: =-BZ36*118% -> 0 | CR36: =-CA36*118% -> 0 | CS36: =SUM(CO36:CR36) -> 3256.8 | CT36: Telangana - HO | CU36: Telangana - HO | CV36: =MID(G36,3,10) -> AAMCB5608A | CW36: =MID(AR36,3,10) -> AAACD5406E | CX36: 0 | CY36: 0 | CZ36: 0 | DA36: 0 | DB36: 0
B37: ="Q" & IF(ROUNDUP(MONTH(D37)/3,0)-1=0,4,ROUNDUP(MONTH(D37)/3,0)-1) -> Q1 | C37: =TEXT(AN37,"mmm-yy") -> May-26 | D37: 46164 | E37: SH05262207 | F37: BLACK GOLD RECYCLING PRIVATE LIMITED | G37: 27AAMCB5608A1ZX | H37: 25/PUN/INV0305 | I37: 46164 | J37: 26-27/PUR/002494 | K37: 46164 | L37: MH | M37: DD01H9940 | N37: PET Liquor Bottle Scrap Baled | O37: 317 | P37: 45 | Q37: =O37*P37 -> 14265 | R37: 0 | S37: =O37-R37 -> 317 | T37: 0 | U37: 0 | V37: 0 | W37: 0 | X37: 0 | Y37: 0 | Z37: 0 | AA37: 0 | AB37: =Y37+AA37+Z37 -> 0 | AC37: 0 | AD37: =IFERROR((Q37+AB37)/S37,0) -> 45 | AE37: 0 | AF37: 0 | AG37: 0 | AH37: 0 | AI37: 0 | AJ37: 0 | AK37: 0 | AL37: 0 | AM37: =Q37+AB37+AL37+AK37+AJ37+T37+AE37 -> 14265 | AN37: 46164 | AO37: 36/REW/27IN00012 | AP37: 832139000052985017 | AQ37: DALMIA POLYPRO INDUSTRIES PRIVATE LIMITED (27) | AR37: 27AAACD5406E1Z3 | AS37: Koregaon Bhima, Maharashtra 412216 | AT37: Dindori | AU37: Maharashtra | AW37: 317 | AX37: 63 | AY37: =AW37*AX37 -> 19971 | AZ37: =AW37=O37 -> TRUE | BA37: 0 | BB37: =AW37-BA37 -> 317 | BC37: 0 | BD37: Regular | BE37: 0 | BF37: 0 | BG37: 0 | BH37: 0 | BI37: 0 | BJ37: 0 | BK37: 0 | BL37: 0 | BM37: 0 | BN37: =AY37*$BM$3 -> -499.275 | BO37: =AY37+BL37+BM37+BN37+BC37+BG37 -> 19471.725 | BP37: =BO37-AM37 -> 5206.725 | BQ37: =IF(BP37>=0,"Positive Margin","Negative Margin") -> Positive Margin | BR37: CN Provision | BS37: =AY37-Y37-Q37-AA37-T37+BC37 -> 5706 | BT37: =IF(BS37<0, "Negative Margin at Inception", "Positive Margin at Inception") -> Positive Margin at Inception | BU37: =IFERROR(BP37/BO37,"0") -> 0.26739927 | BV37: =IF(BU37<1%,"Less Than 1%",IF(BU37>2%,"More than 2%",IF(BU37>=1%,"1% - 2%"))) -> More than 2% | BW37: =BM37+BN37 -> -499.275 | BX37: =AL37+AK37 -> 0 | BY37: =BW37-BX37 -> -499.275 | BZ37: =BM37 -> 0 | CA37: =AK37 -> 0 | CB37: =BZ37-CA37 -> 0 | CC37: Marketplace (Rewerse) | CD37: 0 | CE37: =TEXT(AN37,"mmm-yy") -> May-26 | CF37: =AM37-AL37-AA37 -> 14265 | CG37: =BO37-BN37 -> 19971 | CH37: =INT((D37- IF(MONTH(D37) >= 4, DATE(YEAR(D37), 4, 1), DATE(YEAR(D37)-1, 4, 1))) / 7) + 1 -> 8 | CI37: Plastic | CJ37: Plastic | CK37: =_xlfn.XLOOKUP(AR37,receivables!B:B,receivables!D:D) -> Neelesh Dixit | CL37: =AY37-Q37 -> 5706 | CM37: =CL37-Y37+Z37 -> 5706 | CN37: =BO37-AM37 -> 5206.725 | CO37: =AY37*118% -> 23565.78 | CP37: =-Q37*118% -> -16832.7 | CQ37: =-BZ37*118% -> 0 | CR37: =-CA37*118% -> 0 | CS37: =SUM(CO37:CR37) -> 6733.08 | CT37: Telangana - HO | CU37: Telangana - HO | CV37: =MID(G37,3,10) -> AAMCB5608A | CW37: =MID(AR37,3,10) -> AAACD5406E | CX37: 0 | CY37: 0 | CZ37: 0 | DA37: 0 | DB37: 0
B38: ="Q" & IF(ROUNDUP(MONTH(D38)/3,0)-1=0,4,ROUNDUP(MONTH(D38)/3,0)-1) -> Q1 | C38: =TEXT(AN38,"mmm-yy") -> May-26 | D38: 46164 | E38: SH05262208 | F38: BLACK GOLD RECYCLING PRIVATE LIMITED | G38: 27AAMCB5608A1ZX | H38: 25/PUN/INV0306 | I38: 46164 | J38: 26-27/PUR/002495 | K38: 46164 | L38: MH | M38: MH41AU5461 | N38: PET Bottle Scrap Baled - Clear | O38: 8600 | P38: 45 | Q38: =O38*P38 -> 387000 | R38: 0 | S38: =O38-R38 -> 8600 | T38: 0 | U38: 0 | V38: 0 | W38: 0 | X38: 0 | Y38: 0 | Z38: 0 | AA38: 0 | AB38: =Y38+AA38+Z38 -> 0 | AC38: 0 | AD38: =IFERROR((Q38+AB38)/S38,0) -> 45 | AE38: 0 | AF38: 0 | AG38: 0 | AH38: 0 | AI38: 0 | AJ38: 0 | AK38: 0 | AL38: 0 | AM38: =Q38+AB38+AL38+AK38+AJ38+T38+AE38 -> 387000 | AN38: 46164 | AO38: 36/REW/27IN00013 | AP38: 832139000052985017 | AQ38: DALMIA POLYPRO INDUSTRIES PRIVATE LIMITED (27) | AR38: 27AAACD5406E1Z3 | AS38: Koregaon Bhima, Maharashtra 412216 | AT38: Dindori | AU38: Maharashtra | AW38: 8600 | AX38: 58 | AY38: =AW38*AX38 -> 498800 | AZ38: =AW38=O38 -> TRUE | BA38: 0 | BB38: =AW38-BA38 -> 8600 | BC38: 0 | BD38: Regular | BE38: 0 | BF38: 0 | BG38: 0 | BH38: 0 | BI38: 0 | BJ38: 0 | BK38: 0 | BL38: 0 | BM38: 0 | BN38: =AY38*$BM$3 -> -12470 | BO38: =AY38+BL38+BM38+BN38+BC38+BG38 -> 486330 | BP38: =BO38-AM38 -> 99330 | BQ38: =IF(BP38>=0,"Positive Margin","Negative Margin") -> Positive Margin | BR38: CN Provision | BS38: =AY38-Y38-Q38-AA38-T38+BC38 -> 111800 | BT38: =IF(BS38<0, "Negative Margin at Inception", "Positive Margin at Inception") -> Positive Margin at Inception | BU38: =IFERROR(BP38/BO38,"0") -> 0.20424403 | BV38: =IF(BU38<1%,"Less Than 1%",IF(BU38>2%,"More than 2%",IF(BU38>=1%,"1% - 2%"))) -> More than 2% | BW38: =BM38+BN38 -> -12470 | BX38: =AL38+AK38 -> 0 | BY38: =BW38-BX38 -> -12470 | BZ38: =BM38 -> 0 | CA38: =AK38 -> 0 | CB38: =BZ38-CA38 -> 0 | CC38: Marketplace (Rewerse) | CD38: 0 | CE38: =TEXT(AN38,"mmm-yy") -> May-26 | CF38: =AM38-AL38-AA38 -> 387000 | CG38: =BO38-BN38 -> 498800 | CH38: =INT((D38- IF(MONTH(D38) >= 4, DATE(YEAR(D38), 4, 1), DATE(YEAR(D38)-1, 4, 1))) / 7) + 1 -> 8 | CI38: Plastic | CJ38: Plastic | CK38: =_xlfn.XLOOKUP(AR38,receivables!B:B,receivables!D:D) -> Neelesh Dixit | CL38: =AY38-Q38 -> 111800 | CM38: =CL38-Y38+Z38 -> 111800 | CN38: =BO38-AM38 -> 99330 | CO38: =AY38*118% -> 588584 | CP38: =-Q38*118% -> -456660 | CQ38: =-BZ38*118% -> 0 | CR38: =-CA38*118% -> 0 | CS38: =SUM(CO38:CR38) -> 131924 | CT38: Telangana - HO | CU38: Telangana - HO | CV38: =MID(G38,3,10) -> AAMCB5608A | CW38: =MID(AR38,3,10) -> AAACD5406E | CX38: 0 | CY38: 0 | CZ38: 0 | DA38: 0 | DB38: 0
B39: ="Q" & IF(ROUNDUP(MONTH(D39)/3,0)-1=0,4,ROUNDUP(MONTH(D39)/3,0)-1) -> Q1 | C39: =TEXT(AN39,"mmm-yy") -> May-26 | D39: 46164 | E39: SH05262208 | F39: BLACK GOLD RECYCLING PRIVATE LIMITED | G39: 27AAMCB5608A1ZX | H39: 25/PUN/INV0306 | I39: 46164 | J39: 26-27/PUR/002495 | K39: 46164 | L39: MH | M39: MH41AU5461 | N39: PET Bottle Scrap Baled - Green | O39: 350 | P39: 40 | Q39: =O39*P39 -> 14000 | R39: 0 | S39: =O39-R39 -> 350 | T39: 0 | U39: 0 | V39: 0 | W39: 0 | X39: 0 | Y39: 0 | Z39: 0 | AA39: 0 | AB39: =Y39+AA39+Z39 -> 0 | AC39: 0 | AD39: =IFERROR((Q39+AB39)/S39,0) -> 40 | AE39: 0 | AF39: 0 | AG39: 0 | AH39: 0 | AI39: 0 | AJ39: 0 | AK39: 0 | AL39: 0 | AM39: =Q39+AB39+AL39+AK39+AJ39+T39+AE39 -> 14000 | AN39: 46164 | AO39: 36/REW/27IN00013 | AP39: 832139000052985017 | AQ39: DALMIA POLYPRO INDUSTRIES PRIVATE LIMITED (27) | AR39: 27AAACD5406E1Z3 | AS39: Koregaon Bhima, Maharashtra 412216 | AT39: Dindori | AU39: Maharashtra | AW39: 350 | AX39: 48 | AY39: =AW39*AX39 -> 16800 | AZ39: =AW39=O39 -> TRUE | BA39: 0 | BB39: =AW39-BA39 -> 350 | BC39: 0 | BD39: Regular | BE39: 0 | BF39: 0 | BG39: 0 | BH39: 0 | BI39: 0 | BJ39: 0 | BK39: 0 | BL39: 0 | BM39: 0 | BN39: =AY39*$BM$3 -> -420 | BO39: =AY39+BL39+BM39+BN39+BC39+BG39 -> 16380 | BP39: =BO39-AM39 -> 2380 | BQ39: =IF(BP39>=0,"Positive Margin","Negative Margin") -> Positive Margin | BR39: CN Provision | BS39: =AY39-Y39-Q39-AA39-T39+BC39 -> 2800 | BT39: =IF(BS39<0, "Negative Margin at Inception", "Positive Margin at Inception") -> Positive Margin at Inception | BU39: =IFERROR(BP39/BO39,"0") -> 0.14529915 | BV39: =IF(BU39<1%,"Less Than 1%",IF(BU39>2%,"More than 2%",IF(BU39>=1%,"1% - 2%"))) -> More than 2% | BW39: =BM39+BN39 -> -420 | BX39: =AL39+AK39 -> 0 | BY39: =BW39-BX39 -> -420 | BZ39: =BM39 -> 0 | CA39: =AK39 -> 0 | CB39: =BZ39-CA39 -> 0 | CC39: Marketplace (Rewerse) | CD39: 0 | CE39: =TEXT(AN39,"mmm-yy") -> May-26 | CF39: =AM39-AL39-AA39 -> 14000 | CG39: =BO39-BN39 -> 16800 | CH39: =INT((D39- IF(MONTH(D39) >= 4, DATE(YEAR(D39), 4, 1), DATE(YEAR(D39)-1, 4, 1))) / 7) + 1 -> 8 | CI39: Plastic | CJ39: Plastic | CK39: =_xlfn.XLOOKUP(AR39,receivables!B:B,receivables!D:D) -> Neelesh Dixit | CL39: =AY39-Q39 -> 2800 | CM39: =CL39-Y39+Z39 -> 2800 | CN39: =BO39-AM39 -> 2380 | CO39: =AY39*118% -> 19824 | CP39: =-Q39*118% -> -16520 | CQ39: =-BZ39*118% -> 0 | CR39: =-CA39*118% -> 0 | CS39: =SUM(CO39:CR39) -> 3304 | CT39: Telangana - HO | CU39: Telangana - HO | CV39: =MID(G39,3,10) -> AAMCB5608A | CW39: =MID(AR39,3,10) -> AAACD5406E | CX39: 0 | CY39: 0 | CZ39: 0 | DA39: 0 | DB39: 0
B40: ="Q" & IF(ROUNDUP(MONTH(D40)/3,0)-1=0,4,ROUNDUP(MONTH(D40)/3,0)-1) -> Q1 | C40: =TEXT(AN40,"mmm-yy") -> May-26 | D40: 46164 | E40: SH05262208 | F40: BLACK GOLD RECYCLING PRIVATE LIMITED | G40: 27AAMCB5608A1ZX | H40: 25/PUN/INV0306 | I40: 46164 | J40: 26-27/PUR/002495 | K40: 46164 | L40: MH | M40: MH41AU5461 | N40: PET Liquor Bottle Scrap Baled | O40: 325 | P40: 45 | Q40: =O40*P40 -> 14625 | R40: 0 | S40: =O40-R40 -> 325 | T40: 0 | U40: 0 | V40: 0 | W40: 0 | X40: 0 | Y40: 0 | Z40: 0 | AA40: 0 | AB40: =Y40+AA40+Z40 -> 0 | AC40: 0 | AD40: =IFERROR((Q40+AB40)/S40,0) -> 45 | AE40: 0 | AF40: 0 | AG40: 0 | AH40: 0 | AI40: 0 | AJ40: 0 | AK40: 0 | AL40: 0 | AM40: =Q40+AB40+AL40+AK40+AJ40+T40+AE40 -> 14625 | AN40: 46164 | AO40: 36/REW/27IN00013 | AP40: 832139000052985017 | AQ40: DALMIA POLYPRO INDUSTRIES PRIVATE LIMITED (27) | AR40: 27AAACD5406E1Z3 | AS40: Koregaon Bhima, Maharashtra 412216 | AT40: Dindori | AU40: Maharashtra | AW40: 325 | AX40: 63 | AY40: =AW40*AX40 -> 20475 | AZ40: =AW40=O40 -> TRUE | BA40: 0 | BB40: =AW40-BA40 -> 325 | BC40: 0 | BD40: Regular | BE40: 0 | BF40: 0 | BG40: 0 | BH40: 0 | BI40: 0 | BJ40: 0 | BK40: 0 | BL40: 0 | BM40: 0 | BN40: =AY40*$BM$3 -> -511.875 | BO40: =AY40+BL40+BM40+BN40+BC40+BG40 -> 19963.125 | BP40: =BO40-AM40 -> 5338.125 | BQ40: =IF(BP40>=0,"Positive Margin","Negative Margin") -> Positive Margin | BR40: CN Provision | BS40: =AY40-Y40-Q40-AA40-T40+BC40 -> 5850 | BT40: =IF(BS40<0, "Negative Margin at Inception", "Positive Margin at Inception") -> Positive Margin at Inception | BU40: =IFERROR(BP40/BO40,"0") -> 0.26739927 | BV40: =IF(BU40<1%,"Less Than 1%",IF(BU40>2%,"More than 2%",IF(BU40>=1%,"1% - 2%"))) -> More than 2% | BW40: =BM40+BN40 -> -511.875 | BX40: =AL40+AK40 -> 0 | BY40: =BW40-BX40 -> -511.875 | BZ40: =BM40 -> 0 | CA40: =AK40 -> 0 | CB40: =BZ40-CA40 -> 0 | CC40: Marketplace (Rewerse) | CD40: 0 | CE40: =TEXT(AN40,"mmm-yy") -> May-26 | CF40: =AM40-AL40-AA40 -> 14625 | CG40: =BO40-BN40 -> 20475 | CH40: =INT((D40- IF(MONTH(D40) >= 4, DATE(YEAR(D40), 4, 1), DATE(YEAR(D40)-1, 4, 1))) / 7) + 1 -> 8 | CI40: Plastic | CJ40: Plastic | CK40: =_xlfn.XLOOKUP(AR40,receivables!B:B,receivables!D:D) -> Neelesh Dixit | CL40: =AY40-Q40 -> 5850 | CM40: =CL40-Y40+Z40 -> 5850 | CN40: =BO40-AM40 -> 5338.125 | CO40: =AY40*118% -> 24160.5 | CP40: =-Q40*118% -> -17257.5 | CQ40: =-BZ40*118% -> 0 | CR40: =-CA40*118% -> 0 | CS40: =SUM(CO40:CR40) -> 6903 | CT40: Telangana - HO | CU40: Telangana - HO | CV40: =MID(G40,3,10) -> AAMCB5608A | CW40: =MID(AR40,3,10) -> AAACD5406E | CX40: 0 | CY40: 0 | CZ40: 0 | DA40: 0 | DB40: 0
B41: ="Q" & IF(ROUNDUP(MONTH(D41)/3,0)-1=0,4,ROUNDUP(MONTH(D41)/3,0)-1) -> Q1 | C41: =TEXT(AN41,"mmm-yy") -> May-26 | D41: 46165 | E41: SH05262309 | F41: BLACK GOLD RECYCLING PRIVATE LIMITED | G41: 27AAMCB5608A1ZX | H41: 25/PUN/INV0307 | I41: 46165 | J41: 26-27/PUR/002499 | K41: 46165 | L41: MH | M41: MH43BP9096 | N41: PET Bottle Scrap Baled - Clear | O41: 7915 | P41: 45 | Q41: =O41*P41 -> 356175 | R41: 0 | S41: =O41-R41 -> 7915 | T41: 0 | U41: 0 | V41: 0 | W41: 0 | X41: 0 | Y41: 0 | Z41: 0 | AA41: 0 | AB41: =Y41+AA41+Z41 -> 0 | AC41: 0 | AD41: =IFERROR((Q41+AB41)/S41,0) -> 45 | AE41: 0 | AF41: 0 | AG41: 0 | AH41: 0 | AI41: 0 | AJ41: 0 | AK41: 0 | AL41: 0 | AM41: =Q41+AB41+AL41+AK41+AJ41+T41+AE41 -> 356175 | AN41: 46165 | AO41: 36/REW/27IN00014 | AP41: 832139000052985017 | AQ41: DALMIA POLYPRO INDUSTRIES PRIVATE LIMITED (27) | AR41: 27AAACD5406E1Z3 | AS41: Koregaon Bhima,Maharashtra,412216 | AT41: Dindori | AU41: Maharashtra | AW41: 7915 | AX41: 58 | AY41: =AW41*AX41 -> 459070 | AZ41: =AW41=O41 -> TRUE | BA41: 0 | BB41: =AW41-BA41 -> 7915 | BC41: 0 | BD41: Regular | BE41: 0 | BF41: 0 | BG41: 0 | BH41: 0 | BI41: 0 | BJ41: 0 | BK41: 0 | BL41: 0 | BM41: 0 | BN41: =AY41*$BM$3 -> -11476.75 | BO41: =AY41+BL41+BM41+BN41+BC41+BG41 -> 447593.25 | BP41: =BO41-AM41 -> 91418.25 | BQ41: =IF(BP41>=0,"Positive Margin","Negative Margin") -> Positive Margin | BR41: CN Provision | BS41: =AY41-Y41-Q41-AA41-T41+BC41 -> 102895 | BT41: =IF(BS41<0, "Negative Margin at Inception", "Positive Margin at Inception") -> Positive Margin at Inception | BU41: =IFERROR(BP41/BO41,"0") -> 0.20424403 | BV41: =IF(BU41<1%,"Less Than 1%",IF(BU41>2%,"More than 2%",IF(BU41>=1%,"1% - 2%"))) -> More than 2% | BW41: =BM41+BN41 -> -11476.75 | BX41: =AL41+AK41 -> 0 | BY41: =BW41-BX41 -> -11476.75 | BZ41: =BM41 -> 0 | CA41: =AK41 -> 0 | CB41: =BZ41-CA41 -> 0 | CC41: Marketplace (Rewerse) | CD41: 0 | CE41: =TEXT(AN41,"mmm-yy") -> May-26 | CF41: =AM41-AL41-AA41 -> 356175 | CG41: =BO41-BN41 -> 459070 | CH41: =INT((D41- IF(MONTH(D41) >= 4, DATE(YEAR(D41), 4, 1), DATE(YEAR(D41)-1, 4, 1))) / 7) + 1 -> 8 | CI41: Plastic | CJ41: Plastic | CK41: =_xlfn.XLOOKUP(AR41,receivables!B:B,receivables!D:D) -> Neelesh Dixit | CL41: =AY41-Q41 -> 102895 | CM41: =CL41-Y41+Z41 -> 102895 | CN41: =BO41-AM41 -> 91418.25 | CO41: =AY41*118% -> 541702.6 | CP41: =-Q41*118% -> -420286.5 | CQ41: =-BZ41*118% -> 0 | CR41: =-CA41*118% -> 0 | CS41: =SUM(CO41:CR41) -> 121416.1 | CT41: Telangana - HO | CU41: Telangana - HO | CV41: =MID(G41,3,10) -> AAMCB5608A | CW41: =MID(AR41,3,10) -> AAACD5406E | CX41: 0 | CY41: 0 | CZ41: 0 | DA41: 0 | DB41: 0
B42: ="Q" & IF(ROUNDUP(MONTH(D42)/3,0)-1=0,4,ROUNDUP(MONTH(D42)/3,0)-1) -> Q1 | C42: =TEXT(AN42,"mmm-yy") -> May-26 | D42: 46165 | E42: SH05262309 | F42: BLACK GOLD RECYCLING PRIVATE LIMITED | G42: 27AAMCB5608A1ZX | H42: 25/PUN/INV0307 | I42: 46165 | J42: 26-27/PUR/002499 | K42: 46165 | L42: MH | M42: MH43BP9096 | N42: PET Liquor Bottle Scrap Baled | O42: 305 | P42: 45 | Q42: =O42*P42 -> 13725 | R42: 0 | S42: =O42-R42 -> 305 | T42: 0 | U42: 0 | V42: 0 | W42: 0 | X42: 0 | Y42: 0 | Z42: 0 | AA42: 0 | AB42: =Y42+AA42+Z42 -> 0 | AC42: 0 | AD42: =IFERROR((Q42+AB42)/S42,0) -> 45 | AE42: 0 | AF42: 0 | AG42: 0 | AH42: 0 | AI42: 0 | AJ42: 0 | AK42: 0 | AL42: 0 | AM42: =Q42+AB42+AL42+AK42+AJ42+T42+AE42 -> 13725 | AN42: 46165 | AO42: 36/REW/27IN00014 | AP42: 832139000052985017 | AQ42: DALMIA POLYPRO INDUSTRIES PRIVATE LIMITED (27) | AR42: 27AAACD5406E1Z3 | AS42: Koregaon Bhima,Maharashtra,412216 | AT42: Dindori | AU42: Maharashtra | AW42: 305 | AX42: 63 | AY42: =AW42*AX42 -> 19215 | AZ42: =AW42=O42 -> TRUE | BA42: 0 | BB42: =AW42-BA42 -> 305 | BC42: 0 | BD42: Regular | BE42: 0 | BF42: 0 | BG42: 0 | BH42: 0 | BI42: 0 | BJ42: 0 | BK42: 0 | BL42: 0 | BM42: 0 | BN42: =AY42*$BM$3 -> -480.375 | BO42: =AY42+BL42+BM42+BN42+BC42+BG42 -> 18734.625 | BP42: =BO42-AM42 -> 5009.625 | BQ42: =IF(BP42>=0,"Positive Margin","Negative Margin") -> Positive Margin | BR42: CN Provision | BS42: =AY42-Y42-Q42-AA42-T42+BC42 -> 5490 | BT42: =IF(BS42<0, "Negative Margin at Inception", "Positive Margin at Inception") -> Positive Margin at Inception | BU42: =IFERROR(BP42/BO42,"0") -> 0.26739927 | BV42: =IF(BU42<1%,"Less Than 1%",IF(BU42>2%,"More than 2%",IF(BU42>=1%,"1% - 2%"))) -> More than 2% | BW42: =BM42+BN42 -> -480.375 | BX42: =AL42+AK42 -> 0 | BY42: =BW42-BX42 -> -480.375 | BZ42: =BM42 -> 0 | CA42: =AK42 -> 0 | CB42: =BZ42-CA42 -> 0 | CC42: Marketplace (Rewerse) | CD42: 0 | CE42: =TEXT(AN42,"mmm-yy") -> May-26 | CF42: =AM42-AL42-AA42 -> 13725 | CG42: =BO42-BN42 -> 19215 | CH42: =INT((D42- IF(MONTH(D42) >= 4, DATE(YEAR(D42), 4, 1), DATE(YEAR(D42)-1, 4, 1))) / 7) + 1 -> 8 | CI42: Plastic | CJ42: Plastic | CK42: =_xlfn.XLOOKUP(AR42,receivables!B:B,receivables!D:D) -> Neelesh Dixit | CL42: =AY42-Q42 -> 5490 | CM42: =CL42-Y42+Z42 -> 5490 | CN42: =BO42-AM42 -> 5009.625 | CO42: =AY42*118% -> 22673.7 | CP42: =-Q42*118% -> -16195.5 | CQ42: =-BZ42*118% -> 0 | CR42: =-CA42*118% -> 0 | CS42: =SUM(CO42:CR42) -> 6478.2 | CT42: Telangana - HO | CU42: Telangana - HO | CV42: =MID(G42,3,10) -> AAMCB5608A | CW42: =MID(AR42,3,10) -> AAACD5406E | CX42: 0 | CY42: 0 | CZ42: 0 | DA42: 0 | DB42: 0
B43: ="Q" & IF(ROUNDUP(MONTH(D43)/3,0)-1=0,4,ROUNDUP(MONTH(D43)/3,0)-1) -> Q1 | C43: =TEXT(AN43,"mmm-yy") -> May-26 | D43: 46166 | E43: SH05262401 | F43: BLACK GOLD RECYCLING PRIVATE LIMITED | G43: 27AAMCB5608A1ZX | H43: 25/PUN/INV0309 | I43: 46166 | J43: 26-27/PUR/002500 | K43: 46166 | L43: MH | M43: MH15KS3637 | N43: PET Bottle Scrap Baled - Clear | O43: 9530 | P43: 44 | Q43: =O43*P43 -> 419320 | R43: 0 | S43: =O43-R43 -> 9530 | T43: 0 | U43: 0 | V43: 0 | W43: 0 | X43: 0 | Y43: 0 | Z43: 0 | AA43: 0 | AB43: =Y43+AA43+Z43 -> 0 | AC43: 0 | AD43: =IFERROR((Q43+AB43)/S43,0) -> 44 | AE43: 0 | AF43: 0 | AG43: 0 | AH43: 0 | AI43: 0 | AJ43: 0 | AK43: 0 | AL43: 0 | AM43: =Q43+AB43+AL43+AK43+AJ43+T43+AE43 -> 419320 | AN43: 46166 | AO43: 36/REW/27IN00015 | AP43: 832139000052985017 | AQ43: DALMIA POLYPRO INDUSTRIES PRIVATE LIMITED (27) | AR43: 27AAACD5406E1Z3 | AS43: Koregaon Bhima, Maharashtra 412216 | AT43: Dindori | AU43: Maharashtra | AW43: 9530 | AX43: 58 | AY43: =AW43*AX43 -> 552740 | AZ43: =AW43=O43 -> TRUE | BA43: 0 | BB43: =AW43-BA43 -> 9530 | BC43: 0 | BD43: Regular | BE43: 0 | BF43: 0 | BG43: 0 | BH43: 0 | BI43: 0 | BJ43: 0 | BK43: 0 | BL43: 0 | BM43: 0 | BN43: =AY43*$BM$3 -> -13818.5 | BO43: =AY43+BL43+BM43+BN43+BC43+BG43 -> 538921.5 | BP43: =BO43-AM43 -> 119601.5 | BQ43: =IF(BP43>=0,"Positive Margin","Negative Margin") -> Positive Margin | BR43: CN Provision | BS43: =AY43-Y43-Q43-AA43-T43+BC43 -> 133420 | BT43: =IF(BS43<0, "Negative Margin at Inception", "Positive Margin at Inception") -> Positive Margin at Inception | BU43: =IFERROR(BP43/BO43,"0") -> 0.2219275 | BV43: =IF(BU43<1%,"Less Than 1%",IF(BU43>2%,"More than 2%",IF(BU43>=1%,"1% - 2%"))) -> More than 2% | BW43: =BM43+BN43 -> -13818.5 | BX43: =AL43+AK43 -> 0 | BY43: =BW43-BX43 -> -13818.5 | BZ43: =BM43 -> 0 | CA43: =AK43 -> 0 | CB43: =BZ43-CA43 -> 0 | CC43: Marketplace (Rewerse) | CD43: 0 | CE43: =TEXT(AN43,"mmm-yy") -> May-26 | CF43: =AM43-AL43-AA43 -> 419320 | CG43: =BO43-BN43 -> 552740 | CH43: =INT((D43- IF(MONTH(D43) >= 4, DATE(YEAR(D43), 4, 1), DATE(YEAR(D43)-1, 4, 1))) / 7) + 1 -> 8 | CI43: Plastic | CJ43: Plastic | CK43: =_xlfn.XLOOKUP(AR43,receivables!B:B,receivables!D:D) -> Neelesh Dixit | CL43: =AY43-Q43 -> 133420 | CM43: =CL43-Y43+Z43 -> 133420 | CN43: =BO43-AM43 -> 119601.5 | CO43: =AY43*118% -> 652233.2 | CP43: =-Q43*118% -> -494797.6 | CQ43: =-BZ43*118% -> 0 | CR43: =-CA43*118% -> 0 | CS43: =SUM(CO43:CR43) -> 157435.6 | CT43: Telangana - HO | CU43: Telangana - HO | CV43: =MID(G43,3,10) -> AAMCB5608A | CW43: =MID(AR43,3,10) -> AAACD5406E | CX43: 0 | CY43: 0 | CZ43: 0 | DA43: 0 | DB43: 0
... B63: ="Q" & IF(ROUNDUP(MONTH(D63)/3,0)-1=0,4,ROUNDUP(MONTH(D63)/3,0)-1) -> Q1 | C63: =TEXT(AN63,"mmm-yy") -> Jun-26 | D63: 46186 | E63: SH06261402 | F63: BLACK GOLD RECYCLING PRIVATE LIMITED | G63: 27AAMCB5608A1ZX | H63: 25/PUN/INV0318 | I63: 46186 | J63: 26-27/PUR/003647 | K63: 46187 | L63: MH | M63: DD01AC9274 | N63: PET Liquor Bottle Scrap Baled | O63: 848 | P63: 49 | Q63: =O63*P63 -> 41552 | R63: 0 | S63: =O63-R63 -> 848 | T63: 0 | U63: 0 | V63: 0 | W63: 0 | X63: 0 | Y63: 0 | Z63: 0 | AA63: 0 | AB63: =Y63+AA63+Z63 -> 0 | AC63: 0 | AD63: =IFERROR((Q63+AB63)/S63,0) -> 49 | AE63: 0 | AF63: 0 | AG63: 0 | AH63: 0 | AI63: 0 | AJ63: 0 | AK63: 0 | AL63: 0 | AM63: =Q63+AB63+AL63+AK63+AJ63+T63+AE63 -> 41552 | AN63: 46187 | AO63: 36/REW/27IN00021 | AP63: 832139000052985017 | AQ63: DALMIA POLYPRO INDUSTRIES PRIVATE LIMITED (27) | AR63: 27AAACD5406E1Z3 | AS63: Koregaon Bhima, Maharashtra 412216 | AT63: Dindori | AU63: Maharashtra | AW63: 848 | AX63: 62 | AY63: =AW63*AX63 -> 52576 | AZ63: =AW63=O63 -> TRUE | BA63: 0 | BB63: =AW63-BA63 -> 848 | BC63: 0 | BD63: Regular | BE63: 0 | BF63: 0 | BG63: 0 | BH63: 0 | BI63: 0 | BJ63: 0 | BK63: 0 | BL63: 0 | BM63: 0 | BN63: =AY63*$BM$3 -> -1314.4 | BO63: =AY63+BL63+BM63+BN63+BC63+BG63 -> 51261.6 | BP63: =BO63-AM63 -> 9709.6 | BQ63: =IF(BP63>=0,"Positive Margin","Negative Margin") -> Positive Margin | BR63: CN Provision | BS63: =AY63-Y63-Q63-AA63-T63+BC63 -> 11024 | BT63: =IF(BS63<0, "Negative Margin at Inception", "Positive Margin at Inception") -> Positive Margin at Inception | BU63: =IFERROR(BP63/BO63,"0") -> 0.18941274 | BV63: =IF(BU63<1%,"Less Than 1%",IF(BU63>2%,"More than 2%",IF(BU63>=1%,"1% - 2%"))) -> More than 2% | BW63: =BM63+BN63 -> -1314.4 | BX63: =AL63+AK63 -> 0 | BY63: =BW63-BX63 -> -1314.4 | BZ63: =BM63 -> 0 | CA63: =AK63 -> 0 | CB63: =BZ63-CA63 -> 0 | CC63: Marketplace (Rewerse) | CD63: 0 | CE63: =TEXT(AN63,"mmm-yy") -> Jun-26 | CF63: =AM63-AL63-AA63 -> 41552 | CG63: =BO63-BN63 -> 52576 | CH63: =INT((D63- IF(MONTH(D63) >= 4, DATE(YEAR(D63), 4, 1), DATE(YEAR(D63)-1, 4, 1))) / 7) + 1 -> 11 | CI63: Plastic | CJ63: Plastic | CK63: =_xlfn.XLOOKUP(AR63,receivables!B:B,receivables!D:D) -> Neelesh Dixit | CL63: =AY63-Q63 -> 11024 | CM63: =CL63-Y63+Z63 -> 11024 | CN63: =BO63-AM63 -> 9709.6 | CO63: =AY63*118% -> 62039.68 | CP63: =-Q63*118% -> -49031.36 | CQ63: =-BZ63*118% -> 0 | CR63: =-CA63*118% -> 0 | CS63: =SUM(CO63:CR63) -> 13008.32 | CT63: Telangana - HO | CU63: Telangana - HO | CV63: =MID(G63,3,10) -> AAMCB5608A | CW63: =MID(AR63,3,10) -> AAACD5406E | CX63: 0 | CY63: 0 | CZ63: 0 | DA63: 0 | DB63: 0
B64: ="Q" & IF(ROUNDUP(MONTH(D64)/3,0)-1=0,4,ROUNDUP(MONTH(D64)/3,0)-1) -> Q1 | C64: =TEXT(AN64,"mmm-yy") -> Jun-26 | D64: 46188 | E64: SH06261504 | F64: BLACK GOLD RECYCLING PRIVATE LIMITED | G64: 27AAMCB5608A1ZX | H64: 25/PUN/INV0321 | I64: 46188 | J64: 26-27/PUR/003716 | K64: 46188 | L64: MH | M64: DN09R9152 | N64: PET Bottle Scrap Baled - Clear | O64: 8155 | P64: 44 | Q64: =O64*P64 -> 358820 | R64: 0 | S64: =O64-R64 -> 8155 | T64: 0 | U64: 0 | V64: 0 | W64: 0 | X64: 0 | Y64: 0 | Z64: 0 | AA64: 0 | AB64: =Y64+AA64+Z64 -> 0 | AC64: 0 | AD64: =IFERROR((Q64+AB64)/S64,0) -> 44 | AE64: 0 | AF64: 0 | AG64: 0 | AH64: 0 | AI64: 0 | AJ64: 0 | AK64: 0 | AL64: 0 | AM64: =Q64+AB64+AL64+AK64+AJ64+T64+AE64 -> 358820 | AN64: 46188 | AO64: 36/REW/27IN00023 | AP64: 832139000058476217 | AQ64: NATIONAL FIBRES PRIVATE LIMITED | AR64: 26AAICN2675D1ZG | AS64: Koregaon Bhima,Maharashtra,412216 | AT64: Silvassa | AU64: Dadra and Nagar Haveli and Daman and Diu | AV64: 182458834092 | AW64: 8155 | AX64: 57 | AY64: =AW64*AX64 -> 464835 | AZ64: =AW64=O64 -> TRUE | BA64: 0 | BB64: =AW64-BA64 -> 8155 | BC64: 0 | BD64: Regular | BE64: 0 | BF64: 0 | BG64: 0 | BH64: 0 | BI64: 0 | BJ64: 0 | BK64: 0 | BL64: 0 | BM64: 0 | BN64: =AY64*$BM$3 -> -11620.875 | BO64: =AY64+BL64+BM64+BN64+BC64+BG64 -> 453214.12 | BP64: =BO64-AM64 -> 94394.125 | BQ64: =IF(BP64>=0,"Positive Margin","Negative Margin") -> Positive Margin | BR64: CN Provision | BS64: =AY64-Y64-Q64-AA64-T64+BC64 -> 106015 | BT64: =IF(BS64<0, "Negative Margin at Inception", "Positive Margin at Inception") -> Positive Margin at Inception | BU64: =IFERROR(BP64/BO64,"0") -> 0.2082771 | BV64: =IF(BU64<1%,"Less Than 1%",IF(BU64>2%,"More than 2%",IF(BU64>=1%,"1% - 2%"))) -> More than 2% | BW64: =BM64+BN64 -> -11620.875 | BX64: =AL64+AK64 -> 0 | BY64: =BW64-BX64 -> -11620.875 | BZ64: =BM64 -> 0 | CA64: =AK64 -> 0 | CB64: =BZ64-CA64 -> 0 | CC64: Marketplace (Rewerse) | CD64: 0 | CE64: =TEXT(AN64,"mmm-yy") -> Jun-26 | CF64: =AM64-AL64-AA64 -> 358820 | CG64: =BO64-BN64 -> 464835 | CH64: =INT((D64- IF(MONTH(D64) >= 4, DATE(YEAR(D64), 4, 1), DATE(YEAR(D64)-1, 4, 1))) / 7) + 1 -> 11 | CI64: Plastic | CJ64: Plastic | CK64: =_xlfn.XLOOKUP(AR64,receivables!B:B,receivables!D:D) -> 0 | CL64: =AY64-Q64 -> 106015 | CM64: =CL64-Y64+Z64 -> 106015 | CN64: =BO64-AM64 -> 94394.125 | CO64: =AY64*118% -> 548505.3 | CP64: =-Q64*118% -> -423407.6 | CQ64: =-BZ64*118% -> 0 | CR64: =-CA64*118% -> 0 | CS64: =SUM(CO64:CR64) -> 125097.7 | CT64: Telangana - HO | CU64: Telangana - HO | CV64: =MID(G64,3,10) -> AAMCB5608A | CW64: =MID(AR64,3,10) -> AAICN2675D | CX64: 0 | CY64: 0 | CZ64: 0 | DA64: 0 | DB64: 0
B65: ="Q" & IF(ROUNDUP(MONTH(D65)/3,0)-1=0,4,ROUNDUP(MONTH(D65)/3,0)-1) -> Q1 | C65: =TEXT(AN65,"mmm-yy") -> Jun-26 | D65: 46188 | E65: SH06261504 | F65: BLACK GOLD RECYCLING PRIVATE LIMITED | G65: 27AAMCB5608A1ZX | H65: 25/PUN/INV0321 | I65: 46188 | J65: 26-27/PUR/003716 | K65: 46188 | L65: MH | M65: DN09R9152 | N65: PET Bottle Scrap Baled - Green | O65: 340 | P65: 39 | Q65: =O65*P65 -> 13260 | R65: 0 | S65: =O65-R65 -> 340 | T65: 0 | U65: 0 | V65: 0 | W65: 0 | X65: 0 | Y65: 0 | Z65: 0 | AA65: 0 | AB65: =Y65+AA65+Z65 -> 0 | AC65: 0 | AD65: =IFERROR((Q65+AB65)/S65,0) -> 39 | AE65: 0 | AF65: 0 | AG65: 0 | AH65: 0 | AI65: 0 | AJ65: 0 | AK65: 0 | AL65: 0 | AM65: =Q65+AB65+AL65+AK65+AJ65+T65+AE65 -> 13260 | AN65: 46188 | AO65: 36/REW/27IN00023 | AP65: 832139000058476217 | AQ65: NATIONAL FIBRES PRIVATE LIMITED | AR65: 26AAICN2675D1ZG | AS65: Koregaon Bhima,Maharashtra,412216 | AT65: Silvassa | AU65: Dadra and Nagar Haveli and Daman and Diu | AV65: 182458834092 | AW65: 340 | AX65: 47 | AY65: =AW65*AX65 -> 15980 | AZ65: =AW65=O65 -> TRUE | BA65: 0 | BB65: =AW65-BA65 -> 340 | BC65: 0 | BD65: Regular | BE65: 0 | BF65: 0 | BG65: 0 | BH65: 0 | BI65: 0 | BJ65: 0 | BK65: 0 | BL65: 0 | BM65: 0 | BN65: =AY65*$BM$3 -> -399.5 | BO65: =AY65+BL65+BM65+BN65+BC65+BG65 -> 15580.5 | BP65: =BO65-AM65 -> 2320.5 | BQ65: =IF(BP65>=0,"Positive Margin","Negative Margin") -> Positive Margin | BR65: CN Provision | BS65: =AY65-Y65-Q65-AA65-T65+BC65 -> 2720 | BT65: =IF(BS65<0, "Negative Margin at Inception", "Positive Margin at Inception") -> Positive Margin at Inception | BU65: =IFERROR(BP65/BO65,"0") -> 0.14893617 | BV65: =IF(BU65<1%,"Less Than 1%",IF(BU65>2%,"More than 2%",IF(BU65>=1%,"1% - 2%"))) -> More than 2% | BW65: =BM65+BN65 -> -399.5 | BX65: =AL65+AK65 -> 0 | BY65: =BW65-BX65 -> -399.5 | BZ65: =BM65 -> 0 | CA65: =AK65 -> 0 | CB65: =BZ65-CA65 -> 0 | CC65: Marketplace (Rewerse) | CD65: 0 | CE65: =TEXT(AN65,"mmm-yy") -> Jun-26 | CF65: =AM65-AL65-AA65 -> 13260 | CG65: =BO65-BN65 -> 15980 | CH65: =INT((D65- IF(MONTH(D65) >= 4, DATE(YEAR(D65), 4, 1), DATE(YEAR(D65)-1, 4, 1))) / 7) + 1 -> 11 | CI65: Plastic | CJ65: Plastic | CK65: =_xlfn.XLOOKUP(AR65,receivables!B:B,receivables!D:D) -> 0 | CL65: =AY65-Q65 -> 2720 | CM65: =CL65-Y65+Z65 -> 2720 | CN65: =BO65-AM65 -> 2320.5 | CO65: =AY65*118% -> 18856.4 | CP65: =-Q65*118% -> -15646.8 | CQ65: =-BZ65*118% -> 0 | CR65: =-CA65*118% -> 0 | CS65: =SUM(CO65:CR65) -> 3209.6 | CT65: Telangana - HO | CU65: Telangana - HO | CV65: =MID(G65,3,10) -> AAMCB5608A | CW65: =MID(AR65,3,10) -> AAICN2675D | CX65: 0 | CY65: 0 | CZ65: 0 | DA65: 0 | DB65: 0
B66: ="Q" & IF(ROUNDUP(MONTH(D66)/3,0)-1=0,4,ROUNDUP(MONTH(D66)/3,0)-1) -> Q1 | C66: =TEXT(AN66,"mmm-yy") -> Jun-26 | D66: 46188 | E66: SH06261504 | F66: BLACK GOLD RECYCLING PRIVATE LIMITED | G66: 27AAMCB5608A1ZX | H66: 25/PUN/INV0321 | I66: 46188 | J66: 26-27/PUR/003716 | K66: 46188 | L66: MH | M66: DN09R9152 | N66: PET Liquor Bottle Scrap Baled | O66: 445 | P66: 44 | Q66: =O66*P66 -> 19580 | R66: 0 | S66: =O66-R66 -> 445 | T66: 0 | U66: 0 | V66: 0 | W66: 0 | X66: 0 | Y66: 0 | Z66: 0 | AA66: 0 | AB66: =Y66+AA66+Z66 -> 0 | AC66: 0 | AD66: =IFERROR((Q66+AB66)/S66,0) -> 44 | AE66: 0 | AF66: 0 | AG66: 0 | AH66: 0 | AI66: 0 | AJ66: 0 | AK66: 0 | AL66: 0 | AM66: =Q66+AB66+AL66+AK66+AJ66+T66+AE66 -> 19580 | AN66: 46188 | AO66: 36/REW/27IN00023 | AP66: 832139000058476217 | AQ66: NATIONAL FIBRES PRIVATE LIMITED | AR66: 26AAICN2675D1ZG | AS66: Koregaon Bhima,Maharashtra,412216 | AT66: Silvassa | AU66: Dadra and Nagar Haveli and Daman and Diu | AV66: 182458834092 | AW66: 445 | AX66: 62 | AY66: =AW66*AX66 -> 27590 | AZ66: =AW66=O66 -> TRUE | BA66: 0 | BB66: =AW66-BA66 -> 445 | BC66: 0 | BD66: Regular | BE66: 0 | BF66: 0 | BG66: 0 | BH66: 0 | BI66: 0 | BJ66: 0 | BK66: 0 | BL66: 0 | BM66: 0 | BN66: =AY66*$BM$3 -> -689.75 | BO66: =AY66+BL66+BM66+BN66+BC66+BG66 -> 26900.25 | BP66: =BO66-AM66 -> 7320.25 | BQ66: =IF(BP66>=0,"Positive Margin","Negative Margin") -> Positive Margin | BR66: CN Provision | BS66: =AY66-Y66-Q66-AA66-T66+BC66 -> 8010 | BT66: =IF(BS66<0, "Negative Margin at Inception", "Positive Margin at Inception") -> Positive Margin at Inception | BU66: =IFERROR(BP66/BO66,"0") -> 0.27212572 | BV66: =IF(BU66<1%,"Less Than 1%",IF(BU66>2%,"More than 2%",IF(BU66>=1%,"1% - 2%"))) -> More than 2% | BW66: =BM66+BN66 -> -689.75 | BX66: =AL66+AK66 -> 0 | BY66: =BW66-BX66 -> -689.75 | BZ66: =BM66 -> 0 | CA66: =AK66 -> 0 | CB66: =BZ66-CA66 -> 0 | CC66: Marketplace (Rewerse) | CD66: 0 | CE66: =TEXT(AN66,"mmm-yy") -> Jun-26 | CF66: =AM66-AL66-AA66 -> 19580 | CG66: =BO66-BN66 -> 27590 | CH66: =INT((D66- IF(MONTH(D66) >= 4, DATE(YEAR(D66), 4, 1), DATE(YEAR(D66)-1, 4, 1))) / 7) + 1 -> 11 | CI66: Plastic | CJ66: Plastic | CK66: =_xlfn.XLOOKUP(AR66,receivables!B:B,receivables!D:D) -> 0 | CL66: =AY66-Q66 -> 8010 | CM66: =CL66-Y66+Z66 -> 8010 | CN66: =BO66-AM66 -> 7320.25 | CO66: =AY66*118% -> 32556.2 | CP66: =-Q66*118% -> -23104.4 | CQ66: =-BZ66*118% -> 0 | CR66: =-CA66*118% -> 0 | CS66: =SUM(CO66:CR66) -> 9451.8 | CT66: Telangana - HO | CU66: Telangana - HO | CV66: =MID(G66,3,10) -> AAMCB5608A | CW66: =MID(AR66,3,10) -> AAICN2675D | CX66: 0 | CY66: 0 | CZ66: 0 | DA66: 0 | DB66: 0
B67: ="Q" & IF(ROUNDUP(MONTH(D67)/3,0)-1=0,4,ROUNDUP(MONTH(D67)/3,0)-1) -> Q1 | C67: =TEXT(AN67,"mmm-yy") -> Jun-26 | D67: 46188 | E67: SH06261502 | F67: BLACK GOLD RECYCLING PRIVATE LIMITED | G67: 27AAMCB5608A1ZX | H67: 25/PUN/INV0320 | I67: 46188 | J67: 26-27/PUR/003714 | K67: 46188 | L67: MH | M67: MH15JW5807 | N67: PET Bottle Scrap Baled - Clear | O67: 9225 | P67: 44 | Q67: =O67*P67 -> 405900 | R67: 0 | S67: =O67-R67 -> 9225 | T67: 0 | U67: 0 | V67: 0 | W67: 0 | X67: 0 | Y67: 0 | Z67: 0 | AA67: 0 | AB67: =Y67+AA67+Z67 -> 0 | AC67: 0 | AD67: =IFERROR((Q67+AB67)/S67,0) -> 44 | AE67: 0 | AF67: 0 | AG67: 0 | AH67: 0 | AI67: 0 | AJ67: 0 | AK67: 0 | AL67: 0 | AM67: =Q67+AB67+AL67+AK67+AJ67+T67+AE67 -> 405900 | AN67: 46188 | AO67: 36/REW/27IN00022 | AP67: 832139000052985017 | AQ67: DALMIA POLYPRO INDUSTRIES PRIVATE LIMITED (27) | AR67: 27AAACD5406E1Z3 | AS67: Koregaon Bhima, Maharashtra 412216 | AT67: Dindori | AU67: Maharashtra | AW67: 9225 | AX67: 57 | AY67: =AW67*AX67 -> 525825 | AZ67: =AW67=O67 -> TRUE | BA67: 0 | BB67: =AW67-BA67 -> 9225 | BC67: 0 | BD67: Regular | BE67: 0 | BF67: 0 | BG67: 0 | BH67: 0 | BI67: 0 | BJ67: 0 | BK67: 0 | BL67: 0 | BM67: 0 | BN67: =AY67*$BM$3 -> -13145.625 | BO67: =AY67+BL67+BM67+BN67+BC67+BG67 -> 512679.38 | BP67: =BO67-AM67 -> 106779.38 | BQ67: =IF(BP67>=0,"Positive Margin","Negative Margin") -> Positive Margin | BR67: CN Provision | BS67: =AY67-Y67-Q67-AA67-T67+BC67 -> 119925 | BT67: =IF(BS67<0, "Negative Margin at Inception", "Positive Margin at Inception") -> Positive Margin at Inception | BU67: =IFERROR(BP67/BO67,"0") -> 0.2082771 | BV67: =IF(BU67<1%,"Less Than 1%",IF(BU67>2%,"More than 2%",IF(BU67>=1%,"1% - 2%"))) -> More than 2% | BW67: =BM67+BN67 -> -13145.625 | BX67: =AL67+AK67 -> 0 | BY67: =BW67-BX67 -> -13145.625 | BZ67: =BM67 -> 0 | CA67: =AK67 -> 0 | CB67: =BZ67-CA67 -> 0 | CC67: Marketplace (Rewerse) | CD67: 0 | CE67: =TEXT(AN67,"mmm-yy") -> Jun-26 | CF67: =AM67-AL67-AA67 -> 405900 | CG67: =BO67-BN67 -> 525825 | CH67: =INT((D67- IF(MONTH(D67) >= 4, DATE(YEAR(D67), 4, 1), DATE(YEAR(D67)-1, 4, 1))) / 7) + 1 -> 11 | CI67: Plastic | CJ67: Plastic | CK67: =_xlfn.XLOOKUP(AR67,receivables!B:B,receivables!D:D) -> Neelesh Dixit | CL67: =AY67-Q67 -> 119925 | CM67: =CL67-Y67+Z67 -> 119925 | CN67: =BO67-AM67 -> 106779.38 | CO67: =AY67*118% -> 620473.5 | CP67: =-Q67*118% -> -478962 | CQ67: =-BZ67*118% -> 0 | CR67: =-CA67*118% -> 0 | CS67: =SUM(CO67:CR67) -> 141511.5 | CT67: Telangana - HO | CU67: Telangana - HO | CV67: =MID(G67,3,10) -> AAMCB5608A | CW67: =MID(AR67,3,10) -> AAACD5406E | CX67: 0 | CY67: 0 | CZ67: 0 | DA67: 0 | DB67: 0
B68: ="Q" & IF(ROUNDUP(MONTH(D68)/3,0)-1=0,4,ROUNDUP(MONTH(D68)/3,0)-1) -> Q1 | C68: =TEXT(AN68,"mmm-yy") -> Jun-26 | D68: 46188 | E68: SH06261502 | F68: BLACK GOLD RECYCLING PRIVATE LIMITED | G68: 27AAMCB5608A1ZX | H68: 25/PUN/INV0320 | I68: 46188 | J68: 26-27/PUR/003714 | K68: 46188 | L68: MH | M68: MH15JW5807 | N68: PET Bottle Scrap Baled - Green | O68: 660 | P68: 39 | Q68: =O68*P68 -> 25740 | R68: 0 | S68: =O68-R68 -> 660 | T68: 0 | U68: 0 | V68: 0 | W68: 0 | X68: 0 | Y68: 0 | Z68: 0 | AA68: 0 | AB68: =Y68+AA68+Z68 -> 0 | AC68: 0 | AD68: =IFERROR((Q68+AB68)/S68,0) -> 39 | AE68: 0 | AF68: 0 | AG68: 0 | AH68: 0 | AI68: 0 | AJ68: 0 | AK68: 0 | AL68: 0 | AM68: =Q68+AB68+AL68+AK68+AJ68+T68+AE68 -> 25740 | AN68: 46188 | AO68: 36/REW/27IN00022 | AP68: 832139000052985017 | AQ68: DALMIA POLYPRO INDUSTRIES PRIVATE LIMITED (27) | AR68: 27AAACD5406E1Z3 | AS68: Koregaon Bhima, Maharashtra 412216 | AT68: Dindori | AU68: Maharashtra | AW68: 660 | AX68: 47 | AY68: =AW68*AX68 -> 31020 | AZ68: =AW68=O68 -> TRUE | BA68: 0 | BB68: =AW68-BA68 -> 660 | BC68: 0 | BD68: Regular | BE68: 0 | BF68: 0 | BG68: 0 | BH68: 0 | BI68: 0 | BJ68: 0 | BK68: 0 | BL68: 0 | BM68: 0 | BN68: =AY68*$BM$3 -> -775.5 | BO68: =AY68+BL68+BM68+BN68+BC68+BG68 -> 30244.5 | BP68: =BO68-AM68 -> 4504.5 | BQ68: =IF(BP68>=0,"Positive Margin","Negative Margin") -> Positive Margin | BR68: CN Provision | BS68: =AY68-Y68-Q68-AA68-T68+BC68 -> 5280 | BT68: =IF(BS68<0, "Negative Margin at Inception", "Positive Margin at Inception") -> Positive Margin at Inception | BU68: =IFERROR(BP68/BO68,"0") -> 0.14893617 | BV68: =IF(BU68<1%,"Less Than 1%",IF(BU68>2%,"More than 2%",IF(BU68>=1%,"1% - 2%"))) -> More than 2% | BW68: =BM68+BN68 -> -775.5 | BX68: =AL68+AK68 -> 0 | BY68: =BW68-BX68 -> -775.5 | BZ68: =BM68 -> 0 | CA68: =AK68 -> 0 | CB68: =BZ68-CA68 -> 0 | CC68: Marketplace (Rewerse) | CD68: 0 | CE68: =TEXT(AN68,"mmm-yy") -> Jun-26 | CF68: =AM68-AL68-AA68 -> 25740 | CG68: =BO68-BN68 -> 31020 | CH68: =INT((D68- IF(MONTH(D68) >= 4, DATE(YEAR(D68), 4, 1), DATE(YEAR(D68)-1, 4, 1))) / 7) + 1 -> 11 | CI68: Plastic | CJ68: Plastic | CK68: =_xlfn.XLOOKUP(AR68,receivables!B:B,receivables!D:D) -> Neelesh Dixit | CL68: =AY68-Q68 -> 5280 | CM68: =CL68-Y68+Z68 -> 5280 | CN68: =BO68-AM68 -> 4504.5 | CO68: =AY68*118% -> 36603.6 | CP68: =-Q68*118% -> -30373.2 | CQ68: =-BZ68*118% -> 0 | CR68: =-CA68*118% -> 0 | CS68: =SUM(CO68:CR68) -> 6230.4 | CT68: Telangana - HO | CU68: Telangana - HO | CV68: =MID(G68,3,10) -> AAMCB5608A | CW68: =MID(AR68,3,10) -> AAACD5406E | CX68: 0 | CY68: 0 | CZ68: 0 | DA68: 0 | DB68: 0
B69: ="Q" & IF(ROUNDUP(MONTH(D69)/3,0)-1=0,4,ROUNDUP(MONTH(D69)/3,0)-1) -> Q1 | C69: =TEXT(AN69,"mmm-yy") -> Jun-26 | D69: 46188 | E69: SH06261502 | F69: BLACK GOLD RECYCLING PRIVATE LIMITED | G69: 27AAMCB5608A1ZX | H69: 25/PUN/INV0320 | I69: 46188 | J69: 26-27/PUR/003714 | K69: 46188 | L69: MH | M69: MH15JW5807 | N69: PET Liquor Bottle Scrap Baled | O69: 590 | P69: 44 | Q69: =O69*P69 -> 25960 | R69: 0 | S69: =O69-R69 -> 590 | T69: 0 | U69: 0 | V69: 0 | W69: 0 | X69: 0 | Y69: 0 | Z69: 0 | AA69: 0 | AB69: =Y69+AA69+Z69 -> 0 | AC69: 0 | AD69: =IFERROR((Q69+AB69)/S69,0) -> 44 | AE69: 0 | AF69: 0 | AG69: 0 | AH69: 0 | AI69: 0 | AJ69: 0 | AK69: 0 | AL69: 0 | AM69: =Q69+AB69+AL69+AK69+AJ69+T69+AE69 -> 25960 | AN69: 46188 | AO69: 36/REW/27IN00022 | AP69: 832139000052985017 | AQ69: DALMIA POLYPRO INDUSTRIES PRIVATE LIMITED (27) | AR69: 27AAACD5406E1Z3 | AS69: Koregaon Bhima, Maharashtra 412216 | AT69: Dindori | AU69: Maharashtra | AW69: 590 | AX69: 62 | AY69: =AW69*AX69 -> 36580 | AZ69: =AW69=O69 -> TRUE | BA69: 0 | BB69: =AW69-BA69 -> 590 | BC69: 0 | BD69: Regular | BE69: 0 | BF69: 0 | BG69: 0 | BH69: 0 | BI69: 0 | BJ69: 0 | BK69: 0 | BL69: 0 | BM69: 0 | BN69: =AY69*$BM$3 -> -914.5 | BO69: =AY69+BL69+BM69+BN69+BC69+BG69 -> 35665.5 | BP69: =BO69-AM69 -> 9705.5 | BQ69: =IF(BP69>=0,"Positive Margin","Negative Margin") -> Positive Margin | BR69: CN Provision | BS69: =AY69-Y69-Q69-AA69-T69+BC69 -> 10620 | BT69: =IF(BS69<0, "Negative Margin at Inception", "Positive Margin at Inception") -> Positive Margin at Inception | BU69: =IFERROR(BP69/BO69,"0") -> 0.27212572 | BV69: =IF(BU69<1%,"Less Than 1%",IF(BU69>2%,"More than 2%",IF(BU69>=1%,"1% - 2%"))) -> More than 2% | BW69: =BM69+BN69 -> -914.5 | BX69: =AL69+AK69 -> 0 | BY69: =BW69-BX69 -> -914.5 | BZ69: =BM69 -> 0 | CA69: =AK69 -> 0 | CB69: =BZ69-CA69 -> 0 | CC69: Marketplace (Rewerse) | CD69: 0 | CE69: =TEXT(AN69,"mmm-yy") -> Jun-26 | CF69: =AM69-AL69-AA69 -> 25960 | CG69: =BO69-BN69 -> 36580 | CH69: =INT((D69- IF(MONTH(D69) >= 4, DATE(YEAR(D69), 4, 1), DATE(YEAR(D69)-1, 4, 1))) / 7) + 1 -> 11 | CI69: Plastic | CJ69: Plastic | CK69: =_xlfn.XLOOKUP(AR69,receivables!B:B,receivables!D:D) -> Neelesh Dixit | CL69: =AY69-Q69 -> 10620 | CM69: =CL69-Y69+Z69 -> 10620 | CN69: =BO69-AM69 -> 9705.5 | CO69: =AY69*118% -> 43164.4 | CP69: =-Q69*118% -> -30632.8 | CQ69: =-BZ69*118% -> 0 | CR69: =-CA69*118% -> 0 | CS69: =SUM(CO69:CR69) -> 12531.6 | CT69: Telangana - HO | CU69: Telangana - HO | CV69: =MID(G69,3,10) -> AAMCB5608A | CW69: =MID(AR69,3,10) -> AAACD5406E | CX69: 0 | CY69: 0 | CZ69: 0 | DA69: 0 | DB69: 0
B70: ="Q" & IF(ROUNDUP(MONTH(D70)/3,0)-1=0,4,ROUNDUP(MONTH(D70)/3,0)-1) -> Q1 | C70: =TEXT(AN70,"mmm-yy") -> Jun-26 | D70: 46192 | E70: SH06261908 | F70: BLACK GOLD RECYCLING PRIVATE LIMITED | G70: 27AAMCB5608A1ZX | H70: 25/PUN/INV0322 | I70: 46192 | J70: 26-27/PUR/003992 | K70: 46192 | L70: MH | M70: DD01W9376 | N70: PET Bottle Scrap Baled - Clear | O70: 8564 | P70: 43 | Q70: =O70*P70 -> 368252 | R70: 0 | S70: =O70-R70 -> 8564 | T70: 0 | U70: 0 | V70: 0 | W70: 0 | X70: 0 | Y70: 0 | Z70: 0 | AA70: 0 | AB70: =Y70+AA70+Z70 -> 0 | AC70: 0 | AD70: =IFERROR((Q70+AB70)/S70,0) -> 43 | AE70: 0 | AF70: 0 | AG70: 0 | AH70: 0 | AI70: 0 | AJ70: 0 | AK70: 0 | AL70: 0 | AM70: =Q70+AB70+AL70+AK70+AJ70+T70+AE70 -> 368252 | AN70: 46192 | AO70: 36/REW/27IN00024 | AP70: 832139000058476217 | AQ70: NATIONAL FIBRES PRIVATE LIMITED | AR70: 26AAICN2675D1ZG | AS70: Koregaon Bhima,Maharashtra,412216 | AT70: Silvassa | AU70: Dadra and Nagar Haveli and Daman and Diu | AV70: 172462827580 | AW70: 8564 | AX70: 57 | AY70: =AW70*AX70 -> 488148 | AZ70: =AW70=O70 -> TRUE | BA70: 0 | BB70: =AW70-BA70 -> 8564 | BC70: 0 | BD70: Regular | BE70: 0 | BF70: 0 | BG70: 0 | BH70: 0 | BI70: 0 | BJ70: 0 | BK70: 0 | BL70: 0 | BM70: 0 | BN70: =AY70*$BM$3 -> -12203.7 | BO70: =AY70+BL70+BM70+BN70+BC70+BG70 -> 475944.3 | BP70: =BO70-AM70 -> 107692.3 | BQ70: =IF(BP70>=0,"Positive Margin","Negative Margin") -> Positive Margin | BR70: CN Provision | BS70: =AY70-Y70-Q70-AA70-T70+BC70 -> 119896 | BT70: =IF(BS70<0, "Negative Margin at Inception", "Positive Margin at Inception") -> Positive Margin at Inception | BU70: =IFERROR(BP70/BO70,"0") -> 0.22627081 | BV70: =IF(BU70<1%,"Less Than 1%",IF(BU70>2%,"More than 2%",IF(BU70>=1%,"1% - 2%"))) -> More than 2% | BW70: =BM70+BN70 -> -12203.7 | BX70: =AL70+AK70 -> 0 | BY70: =BW70-BX70 -> -12203.7 | BZ70: =BM70 -> 0 | CA70: =AK70 -> 0 | CB70: =BZ70-CA70 -> 0 | CC70: Marketplace (Rewerse) | CD70: 0 | CE70: =TEXT(AN70,"mmm-yy") -> Jun-26 | CF70: =AM70-AL70-AA70 -> 368252 | CG70: =BO70-BN70 -> 488148 | CH70: =INT((D70- IF(MONTH(D70) >= 4, DATE(YEAR(D70), 4, 1), DATE(YEAR(D70)-1, 4, 1))) / 7) + 1 -> 12 | CI70: Plastic | CJ70: Plastic | CK70: =_xlfn.XLOOKUP(AR70,receivables!B:B,receivables!D:D) -> 0 | CL70: =AY70-Q70 -> 119896 | CM70: =CL70-Y70+Z70 -> 119896 | CN70: =BO70-AM70 -> 107692.3 | CO70: =AY70*118% -> 576014.64 | CP70: =-Q70*118% -> -434537.36 | CQ70: =-BZ70*118% -> 0 | CR70: =-CA70*118% -> 0 | CS70: =SUM(CO70:CR70) -> 141477.28 | CT70: Telangana - HO | CU70: Telangana - HO | CV70: =MID(G70,3,10) -> AAMCB5608A | CW70: =MID(AR70,3,10) -> AAICN2675D | CX70: 0 | CY70: 0 | CZ70: 0 | DA70: 0 | DB70: 0
B71: ="Q" & IF(ROUNDUP(MONTH(D71)/3,0)-1=0,4,ROUNDUP(MONTH(D71)/3,0)-1) -> Q1 | C71: =TEXT(AN71,"mmm-yy") -> Jun-26 | D71: 46192 | E71: SH06261908 | F71: BLACK GOLD RECYCLING PRIVATE LIMITED | G71: 27AAMCB5608A1ZX | H71: 25/PUN/INV0322 | I71: 46192 | J71: 26-27/PUR/003992 | K71: 46192 | L71: MH | M71: DD01W9376 | N71: PET Bottle Scrap Baled - Green | O71: 859 | P71: 38 | Q71: =O71*P71 -> 32642 | R71: 0 | S71: =O71-R71 -> 859 | T71: 0 | U71: 0 | V71: 0 | W71: 0 | X71: 0 | Y71: 0 | Z71: 0 | AA71: 0 | AB71: =Y71+AA71+Z71 -> 0 | AC71: 0 | AD71: =IFERROR((Q71+AB71)/S71,0) -> 38 | AE71: 0 | AF71: 0 | AG71: 0 | AH71: 0 | AI71: 0 | AJ71: 0 | AK71: 0 | AL71: 0 | AM71: =Q71+AB71+AL71+AK71+AJ71+T71+AE71 -> 32642 | AN71: 46192 | AO71: 36/REW/27IN00024 | AP71: 832139000058476217 | AQ71: NATIONAL FIBRES PRIVATE LIMITED | AR71: 26AAICN2675D1ZG | AS71: Koregaon Bhima,Maharashtra,412216 | AT71: Silvassa | AU71: Dadra and Nagar Haveli and Daman and Diu | AV71: 172462827580 | AW71: 859 | AX71: 47 | AY71: =AW71*AX71 -> 40373 | AZ71: =AW71=O71 -> TRUE | BA71: 0 | BB71: =AW71-BA71 -> 859 | BC71: 0 | BD71: Regular | BE71: 0 | BF71: 0 | BG71: 0 | BH71: 0 | BI71: 0 | BJ71: 0 | BK71: 0 | BL71: 0 | BM71: 0 | BN71: =AY71*$BM$3 -> -1009.325 | BO71: =AY71+BL71+BM71+BN71+BC71+BG71 -> 39363.675 | BP71: =BO71-AM71 -> 6721.675 | BQ71: =IF(BP71>=0,"Positive Margin","Negative Margin") -> Positive Margin | BR71: CN Provision | BS71: =AY71-Y71-Q71-AA71-T71+BC71 -> 7731 | BT71: =IF(BS71<0, "Negative Margin at Inception", "Positive Margin at Inception") -> Positive Margin at Inception | BU71: =IFERROR(BP71/BO71,"0") -> 0.17075832 | BV71: =IF(BU71<1%,"Less Than 1%",IF(BU71>2%,"More than 2%",IF(BU71>=1%,"1% - 2%"))) -> More than 2% | BW71: =BM71+BN71 -> -1009.325 | BX71: =AL71+AK71 -> 0 | BY71: =BW71-BX71 -> -1009.325 | BZ71: =BM71 -> 0 | CA71: =AK71 -> 0 | CB71: =BZ71-CA71 -> 0 | CC71: Marketplace (Rewerse) | CD71: 0 | CE71: =TEXT(AN71,"mmm-yy") -> Jun-26 | CF71: =AM71-AL71-AA71 -> 32642 | CG71: =BO71-BN71 -> 40373 | CH71: =INT((D71- IF(MONTH(D71) >= 4, DATE(YEAR(D71), 4, 1), DATE(YEAR(D71)-1, 4, 1))) / 7) + 1 -> 12 | CI71: Plastic | CJ71: Plastic | CK71: =_xlfn.XLOOKUP(AR71,receivables!B:B,receivables!D:D) -> 0 | CL71: =AY71-Q71 -> 7731 | CM71: =CL71-Y71+Z71 -> 7731 | CN71: =BO71-AM71 -> 6721.675 | CO71: =AY71*118% -> 47640.14 | CP71: =-Q71*118% -> -38517.56 | CQ71: =-BZ71*118% -> 0 | CR71: =-CA71*118% -> 0 | CS71: =SUM(CO71:CR71) -> 9122.58 | CT71: Telangana - HO | CU71: Telangana - HO | CV71: =MID(G71,3,10) -> AAMCB5608A | CW71: =MID(AR71,3,10) -> AAICN2675D | CX71: 0 | CY71: 0 | CZ71: 0 | DA71: 0 | DB71: 0
B72: ="Q" & IF(ROUNDUP(MONTH(D72)/3,0)-1=0,4,ROUNDUP(MONTH(D72)/3,0)-1) -> Q1 | C72: =TEXT(AN72,"mmm-yy") -> Jun-26 | D72: 46192 | E72: SH06261908 | F72: BLACK GOLD RECYCLING PRIVATE LIMITED | G72: 27AAMCB5608A1ZX | H72: 25/PUN/INV0322 | I72: 46192 | J72: 26-27/PUR/003992 | K72: 46192 | L72: MH | M72: DD01W9376 | N72: PET Liquor Bottle Scrap Baled | O72: 752 | P72: 43 | Q72: =O72*P72 -> 32336 | R72: 0 | S72: =O72-R72 -> 752 | T72: 0 | U72: 0 | V72: 0 | W72: 0 | X72: 0 | Y72: 0 | Z72: 0 | AA72: 0 | AB72: =Y72+AA72+Z72 -> 0 | AC72: 0 | AD72: =IFERROR((Q72+AB72)/S72,0) -> 43 | AE72: 0 | AF72: 0 | AG72: 0 | AH72: 0 | AI72: 0 | AJ72: 0 | AK72: 0 | AL72: 0 | AM72: =Q72+AB72+AL72+AK72+AJ72+T72+AE72 -> 32336 | AN72: 46192 | AO72: 36/REW/27IN00024 | AP72: 832139000058476217 | AQ72: NATIONAL FIBRES PRIVATE LIMITED | AR72: 26AAICN2675D1ZG | AS72: Koregaon Bhima,Maharashtra,412216 | AT72: Silvassa | AU72: Dadra and Nagar Haveli and Daman and Diu | AV72: 172462827580 | AW72: 752 | AX72: 62 | AY72: =AW72*AX72 -> 46624 | AZ72: =AW72=O72 -> TRUE | BA72: 0 | BB72: =AW72-BA72 -> 752 | BC72: 0 | BD72: Regular | BE72: 0 | BF72: 0 | BG72: 0 | BH72: 0 | BI72: 0 | BJ72: 0 | BK72: 0 | BL72: 0 | BM72: 0 | BN72: =AY72*$BM$3 -> -1165.6 | BO72: =AY72+BL72+BM72+BN72+BC72+BG72 -> 45458.4 | BP72: =BO72-AM72 -> 13122.4 | BQ72: =IF(BP72>=0,"Positive Margin","Negative Margin") -> Positive Margin | BR72: CN Provision | BS72: =AY72-Y72-Q72-AA72-T72+BC72 -> 14288 | BT72: =IF(BS72<0, "Negative Margin at Inception", "Positive Margin at Inception") -> Positive Margin at Inception | BU72: =IFERROR(BP72/BO72,"0") -> 0.28866832 | BV72: =IF(BU72<1%,"Less Than 1%",IF(BU72>2%,"More than 2%",IF(BU72>=1%,"1% - 2%"))) -> More than 2% | BW72: =BM72+BN72 -> -1165.6 | BX72: =AL72+AK72 -> 0 | BY72: =BW72-BX72 -> -1165.6 | BZ72: =BM72 -> 0 | CA72: =AK72 -> 0 | CB72: =BZ72-CA72 -> 0 | CC72: Marketplace (Rewerse) | CD72: 0 | CE72: =TEXT(AN72,"mmm-yy") -> Jun-26 | CF72: =AM72-AL72-AA72 -> 32336 | CG72: =BO72-BN72 -> 46624 | CH72: =INT((D72- IF(MONTH(D72) >= 4, DATE(YEAR(D72), 4, 1), DATE(YEAR(D72)-1, 4, 1))) / 7) + 1 -> 12 | CI72: Plastic | CJ72: Plastic | CK72: =_xlfn.XLOOKUP(AR72,receivables!B:B,receivables!D:D) -> 0 | CL72: =AY72-Q72 -> 14288 | CM72: =CL72-Y72+Z72 -> 14288 | CN72: =BO72-AM72 -> 13122.4 | CO72: =AY72*118% -> 55016.32 | CP72: =-Q72*118% -> -38156.48 | CQ72: =-BZ72*118% -> 0 | CR72: =-CA72*118% -> 0 | CS72: =SUM(CO72:CR72) -> 16859.84 | CT72: Telangana - HO | CU72: Telangana - HO | CV72: =MID(G72,3,10) -> AAMCB5608A | CW72: =MID(AR72,3,10) -> AAICN2675D | CX72: 0 | CY72: 0 | CZ72: 0 | DA72: 0 | DB72: 0
B73: ="Q" & IF(ROUNDUP(MONTH(D73)/3,0)-1=0,4,ROUNDUP(MONTH(D73)/3,0)-1) -> Q1 | C73: =TEXT(AN73,"mmm-yy") -> Jun-26 | D73: 46194 | E73: SH06262101 | F73: BLACK GOLD RECYCLING PRIVATE LIMITED | G73: 27AAMCB5608A1ZX | H73: 25/PUN/INV0324 | I73: 46194 | J73: 26-27/PUR/004000 | K73: 46194 | L73: MH | M73: MH15JW5807 | N73: PET Bottle Scrap Baled - Clear | O73: 9158 | P73: 43 | Q73: =O73*P73 -> 393794 | R73: 0 | S73: =O73-R73 -> 9158 | T73: 0 | U73: 0 | V73: 0 | W73: 0 | X73: 0 | Y73: 0 | Z73: 0 | AA73: 0 | AB73: =Y73+AA73+Z73 -> 0 | AC73: 0 | AD73: =IFERROR((Q73+AB73)/S73,0) -> 43 | AE73: 0 | AF73: 0 | AG73: 0 | AH73: 0 | AI73: 0 | AJ73: 0 | AK73: 0 | AL73: 0 | AM73: =Q73+AB73+AL73+AK73+AJ73+T73+AE73 -> 393794 | AN73: 46194 | AO73: 36/REW/27IN00025 | AP73: 832139000052985017 | AQ73: DALMIA POLYPRO INDUSTRIES PRIVATE LIMITED (27) | AR73: 27AAACD5406E1Z3 | AS73: Koregaon Bhima, Maharashtra 412216 | AT73: Dindori | AU73: Maharashtra | AW73: 9158 | AX73: 55 | AY73: =AW73*AX73 -> 503690 | AZ73: =AW73=O73 -> TRUE | BA73: 0 | BB73: =AW73-BA73 -> 9158 | BC73: 0 | BD73: Regular | BE73: 0 | BF73: 0 | BG73: 0 | BH73: 0 | BI73: 0 | BJ73: 0 | BK73: 0 | BL73: 0 | BM73: 0 | BN73: =AY73*$BM$3 -> -12592.25 | BO73: =AY73+BL73+BM73+BN73+BC73+BG73 -> 491097.75 | BP73: =BO73-AM73 -> 97303.75 | BQ73: =IF(BP73>=0,"Positive Margin","Negative Margin") -> Positive Margin | BR73: CN Provision | BS73: =AY73-Y73-Q73-AA73-T73+BC73 -> 109896 | BT73: =IF(BS73<0, "Negative Margin at Inception", "Positive Margin at Inception") -> Positive Margin at Inception | BU73: =IFERROR(BP73/BO73,"0") -> 0.1981352 | BV73: =IF(BU73<1%,"Less Than 1%",IF(BU73>2%,"More than 2%",IF(BU73>=1%,"1% - 2%"))) -> More than 2% | BW73: =BM73+BN73 -> -12592.25 | BX73: =AL73+AK73 -> 0 | BY73: =BW73-BX73 -> -12592.25 | BZ73: =BM73 -> 0 | CA73: =AK73 -> 0 | CB73: =BZ73-CA73 -> 0 | CC73: Marketplace (Rewerse) | CD73: 0 | CE73: =TEXT(AN73,"mmm-yy") -> Jun-26 | CF73: =AM73-AL73-AA73 -> 393794 | CG73: =BO73-BN73 -> 503690 | CH73: =INT((D73- IF(MONTH(D73) >= 4, DATE(YEAR(D73), 4, 1), DATE(YEAR(D73)-1, 4, 1))) / 7) + 1 -> 12 | CI73: Plastic | CJ73: Plastic | CK73: =_xlfn.XLOOKUP(AR73,receivables!B:B,receivables!D:D) -> Neelesh Dixit | CL73: =AY73-Q73 -> 109896 | CM73: =CL73-Y73+Z73 -> 109896 | CN73: =BO73-AM73 -> 97303.75 | CO73: =AY73*118% -> 594354.2 | CP73: =-Q73*118% -> -464676.92 | CQ73: =-BZ73*118% -> 0 | CR73: =-CA73*118% -> 0 | CS73: =SUM(CO73:CR73) -> 129677.28 | CT73: Telangana - HO | CU73: Telangana - HO | CV73: =MID(G73,3,10) -> AAMCB5608A | CW73: =MID(AR73,3,10) -> AAACD5406E | CX73: 0 | CY73: 0 | CZ73: 0 | DA73: 0 | DB73: 0
B74: ="Q" & IF(ROUNDUP(MONTH(D74)/3,0)-1=0,4,ROUNDUP(MONTH(D74)/3,0)-1) -> Q1 | C74: =TEXT(AN74,"mmm-yy") -> Jun-26 | D74: 46194 | E74: SH06262101 | F74: BLACK GOLD RECYCLING PRIVATE LIMITED | G74: 27AAMCB5608A1ZX | H74: 25/PUN/INV0324 | I74: 46194 | J74: 26-27/PUR/004000 | K74: 46194 | L74: MH | M74: MH15JW5807 | N74: PET Bottle Scrap Baled - Green | O74: 556 | P74: 38 | Q74: =O74*P74 -> 21128 | R74: 0 | S74: =O74-R74 -> 556 | T74: 0 | U74: 0 | V74: 0 | W74: 0 | X74: 0 | Y74: 0 | Z74: 0 | AA74: 0 | AB74: =Y74+AA74+Z74 -> 0 | AC74: 0 | AD74: =IFERROR((Q74+AB74)/S74,0) -> 38 | AE74: 0 | AF74: 0 | AG74: 0 | AH74: 0 | AI74: 0 | AJ74: 0 | AK74: 0 | AL74: 0 | AM74: =Q74+AB74+AL74+AK74+AJ74+T74+AE74 -> 21128 | AN74: 46194 | AO74: 36/REW/27IN00025 | AP74: 832139000052985017 | AQ74: DALMIA POLYPRO INDUSTRIES PRIVATE LIMITED (27) | AR74: 27AAACD5406E1Z3 | AS74: Koregaon Bhima, Maharashtra 412216 | AT74: Dindori | AU74: Maharashtra | AW74: 556 | AX74: 45 | AY74: =AW74*AX74 -> 25020 | AZ74: =AW74=O74 -> TRUE | BA74: 0 | BB74: =AW74-BA74 -> 556 | BC74: 0 | BD74: Regular | BE74: 0 | BF74: 0 | BG74: 0 | BH74: 0 | BI74: 0 | BJ74: 0 | BK74: 0 | BL74: 0 | BM74: 0 | BN74: =AY74*$BM$3 -> -625.5 | BO74: =AY74+BL74+BM74+BN74+BC74+BG74 -> 24394.5 | BP74: =BO74-AM74 -> 3266.5 | BQ74: =IF(BP74>=0,"Positive Margin","Negative Margin") -> Positive Margin | BR74: CN Provision | BS74: =AY74-Y74-Q74-AA74-T74+BC74 -> 3892 | BT74: =IF(BS74<0, "Negative Margin at Inception", "Positive Margin at Inception") -> Positive Margin at Inception | BU74: =IFERROR(BP74/BO74,"0") -> 0.13390313 | BV74: =IF(BU74<1%,"Less Than 1%",IF(BU74>2%,"More than 2%",IF(BU74>=1%,"1% - 2%"))) -> More than 2% | BW74: =BM74+BN74 -> -625.5 | BX74: =AL74+AK74 -> 0 | BY74: =BW74-BX74 -> -625.5 | BZ74: =BM74 -> 0 | CA74: =AK74 -> 0 | CB74: =BZ74-CA74 -> 0 | CC74: Marketplace (Rewerse) | CD74: 0 | CE74: =TEXT(AN74,"mmm-yy") -> Jun-26 | CF74: =AM74-AL74-AA74 -> 21128 | CG74: =BO74-BN74 -> 25020 | CH74: =INT((D74- IF(MONTH(D74) >= 4, DATE(YEAR(D74), 4, 1), DATE(YEAR(D74)-1, 4, 1))) / 7) + 1 -> 12 | CI74: Plastic | CJ74: Plastic | CK74: =_xlfn.XLOOKUP(AR74,receivables!B:B,receivables!D:D) -> Neelesh Dixit | CL74: =AY74-Q74 -> 3892 | CM74: =CL74-Y74+Z74 -> 3892 | CN74: =BO74-AM74 -> 3266.5 | CO74: =AY74*118% -> 29523.6 | CP74: =-Q74*118% -> -24931.04 | CQ74: =-BZ74*118% -> 0 | CR74: =-CA74*118% -> 0 | CS74: =SUM(CO74:CR74) -> 4592.56 | CT74: Telangana - HO | CU74: Telangana - HO | CV74: =MID(G74,3,10) -> AAMCB5608A | CW74: =MID(AR74,3,10) -> AAACD5406E | CX74: 0 | CY74: 0 | CZ74: 0 | DA74: 0 | DB74: 0
B75: ="Q" & IF(ROUNDUP(MONTH(D75)/3,0)-1=0,4,ROUNDUP(MONTH(D75)/3,0)-1) -> Q1 | C75: =TEXT(AN75,"mmm-yy") -> Jun-26 | D75: 46194 | E75: SH06262101 | F75: BLACK GOLD RECYCLING PRIVATE LIMITED | G75: 27AAMCB5608A1ZX | H75: 25/PUN/INV0324 | I75: 46194 | J75: 26-27/PUR/004000 | K75: 46194 | L75: MH | M75: MH15JW5807 | N75: PET Liquor Bottle Scrap Baled | O75: 641 | P75: 43 | Q75: =O75*P75 -> 27563 | R75: 0 | S75: =O75-R75 -> 641 | T75: 0 | U75: 0 | V75: 0 | W75: 0 | X75: 0 | Y75: 0 | Z75: 0 | AA75: 0 | AB75: =Y75+AA75+Z75 -> 0 | AC75: 0 | AD75: =IFERROR((Q75+AB75)/S75,0) -> 43 | AE75: 0 | AF75: 0 | AG75: 0 | AH75: 0 | AI75: 0 | AJ75: 0 | AK75: 0 | AL75: 0 | AM75: =Q75+AB75+AL75+AK75+AJ75+T75+AE75 -> 27563 | AN75: 46194 | AO75: 36/REW/27IN00025 | AP75: 832139000052985017 | AQ75: DALMIA POLYPRO INDUSTRIES PRIVATE LIMITED (27) | AR75: 27AAACD5406E1Z3 | AS75: Koregaon Bhima, Maharashtra 412216 | AT75: Dindori | AU75: Maharashtra | AW75: 641 | AX75: 60 | AY75: =AW75*AX75 -> 38460 | AZ75: =AW75=O75 -> TRUE | BA75: 0 | BB75: =AW75-BA75 -> 641 | BC75: 0 | BD75: Regular | BE75: 0 | BF75: 0 | BG75: 0 | BH75: 0 | BI75: 0 | BJ75: 0 | BK75: 0 | BL75: 0 | BM75: 0 | BN75: =AY75*$BM$3 -> -961.5 | BO75: =AY75+BL75+BM75+BN75+BC75+BG75 -> 37498.5 | BP75: =BO75-AM75 -> 9935.5 | BQ75: =IF(BP75>=0,"Positive Margin","Negative Margin") -> Positive Margin | BR75: CN Provision | BS75: =AY75-Y75-Q75-AA75-T75+BC75 -> 10897 | BT75: =IF(BS75<0, "Negative Margin at Inception", "Positive Margin at Inception") -> Positive Margin at Inception | BU75: =IFERROR(BP75/BO75,"0") -> 0.26495726 | BV75: =IF(BU75<1%,"Less Than 1%",IF(BU75>2%,"More than 2%",IF(BU75>=1%,"1% - 2%"))) -> More than 2% | BW75: =BM75+BN75 -> -961.5 | BX75: =AL75+AK75 -> 0 | BY75: =BW75-BX75 -> -961.5 | BZ75: =BM75 -> 0 | CA75: =AK75 -> 0 | CB75: =BZ75-CA75 -> 0 | CC75: Marketplace (Rewerse) | CD75: 0 | CE75: =TEXT(AN75,"mmm-yy") -> Jun-26 | CF75: =AM75-AL75-AA75 -> 27563 | CG75: =BO75-BN75 -> 38460 | CH75: =INT((D75- IF(MONTH(D75) >= 4, DATE(YEAR(D75), 4, 1), DATE(YEAR(D75)-1, 4, 1))) / 7) + 1 -> 12 | CI75: Plastic | CJ75: Plastic | CK75: =_xlfn.XLOOKUP(AR75,receivables!B:B,receivables!D:D) -> Neelesh Dixit | CL75: =AY75-Q75 -> 10897 | CM75: =CL75-Y75+Z75 -> 10897 | CN75: =BO75-AM75 -> 9935.5 | CO75: =AY75*118% -> 45382.8 | CP75: =-Q75*118% -> -32524.34 | CQ75: =-BZ75*118% -> 0 | CR75: =-CA75*118% -> 0 | CS75: =SUM(CO75:CR75) -> 12858.46 | CT75: Telangana - HO | CU75: Telangana - HO | CV75: =MID(G75,3,10) -> AAMCB5608A | CW75: =MID(AR75,3,10) -> AAACD5406E | CX75: 0 | CY75: 0 | CZ75: 0 | DA75: 0 | DB75: 0
B76: ="Q" & IF(ROUNDUP(MONTH(D76)/3,0)-1=0,4,ROUNDUP(MONTH(D76)/3,0)-1) -> Q1 | C76: =TEXT(AN76,"mmm-yy") -> Jun-26 | D76: 46187 | E76: SH06261404 | F76: BLACK GOLD RECYCLING PRIVATE LIMITED | G76: 27AAMCB5608A1ZX | H76: 25/PUN/INV0319 | I76: 46187 | J76: 26-27/PUR/003669 | K76: 46188 | L76: MH | M76: KA569441 | N76: Used Beverage Cans scrap (UBC) | O76: 6560 | P76: 180 | Q76: =O76*P76 -> 1180800 | R76: 0 | S76: =O76-R76 -> 6560 | T76: 0 | U76: 0 | V76: 0 | W76: 0 | X76: 0 | Y76: 0 | Z76: 0 | AA76: 0 | AB76: =Y76+AA76+Z76 -> 0 | AC76: 0 | AD76: =IFERROR((Q76+AB76)/S76,0) -> 180 | AE76: 0 | AF76: 0 | AG76: 0 | AH76: 0 | AI76: 0 | AJ76: 0 | AK76: 0 | AL76: 0 | AM76: =Q76+AB76+AL76+AK76+AJ76+T76+AE76 -> 1180800 | AN76: 46188 | AO76: 27/MET/27IN00003 | AP76: 832139000076790009 | AQ76: VINAYAK METAL AND ALLOYS PRIVATE LIMITED | AR76: 36AAGCV9303A1ZK | AS76: Koregaon Bhima,Maharashtra,412216 | AT76: Mutpoor | AU76: Telangana | AW76: 6560 | AX76: 262 | AY76: =AW76*AX76 -> 1718720 | AZ76: =AW76=O76 -> TRUE | BA76: 0 | BB76: =AW76-BA76 -> 6560 | BC76: 0 | BD76: Regular | BE76: 0 | BF76: 0 | BG76: 0 | BH76: 0 | BI76: 0 | BJ76: 0 | BK76: 0 | BL76: 0 | BM76: 0 | BN76: =AY76*$BM$3 -> -42968 | BO76: =AY76+BL76+BM76+BN76+BC76+BG76 -> 1675752 | BP76: =BO76-AM76 -> 494952 | BQ76: =IF(BP76>=0,"Positive Margin","Negative Margin") -> Positive Margin | BR76: CN Provision | BS76: =AY76-Y76-Q76-AA76-T76+BC76 -> 537920 | BT76: =IF(BS76<0, "Negative Margin at Inception", "Positive Margin at Inception") -> Positive Margin at Inception | BU76: =IFERROR(BP76/BO76,"0") -> 0.29536113 | BV76: =IF(BU76<1%,"Less Than 1%",IF(BU76>2%,"More than 2%",IF(BU76>=1%,"1% - 2%"))) -> More than 2% | BW76: =BM76+BN76 -> -42968 | BX76: =AL76+AK76 -> 0 | BY76: =BW76-BX76 -> -42968 | BZ76: =BM76 -> 0 | CA76: =AK76 -> 0 | CB76: =BZ76-CA76 -> 0 | CC76: Marketplace (Rewerse) | CD76: 0 | CE76: =TEXT(AN76,"mmm-yy") -> Jun-26 | CF76: =AM76-AL76-AA76 -> 1180800 | CG76: =BO76-BN76 -> 1718720 | CH76: =INT((D76- IF(MONTH(D76) >= 4, DATE(YEAR(D76), 4, 1), DATE(YEAR(D76)-1, 4, 1))) / 7) + 1 -> 11 | CI76: Plastic | CJ76: Plastic | CK76: =_xlfn.XLOOKUP(AR76,receivables!B:B,receivables!D:D) -> 0 | CL76: =AY76-Q76 -> 537920 | CM76: =CL76-Y76+Z76 -> 537920 | CN76: =BO76-AM76 -> 494952 | CO76: =AY76*118% -> 2028089.6 | CP76: =-Q76*118% -> -1393344 | CQ76: =-BZ76*118% -> 0 | CR76: =-CA76*118% -> 0 | CS76: =SUM(CO76:CR76) -> 634745.6 | CT76: Telangana - HO | CU76: Telangana - HO | CV76: =MID(G76,3,10) -> AAMCB5608A | CW76: =MID(AR76,3,10) -> AAGCV9303A | CX76: 0 | CY76: 0 | CZ76: 0 | DA76: 0 | DB76: 0
B77: ="Q" & IF(ROUNDUP(MONTH(D77)/3,0)-1=0,4,ROUNDUP(MONTH(D77)/3,0)-1) -> Q1 | C77: =TEXT(AN77,"mmm-yy") -> Jun-26 | D77: 46187 | E77: SH06261404 | F77: BLACK GOLD RECYCLING PRIVATE LIMITED | G77: 27AAMCB5608A1ZX | H77: 25/PUN/INV0319 | I77: 46187 | J77: 26-27/PUR/003669 | K77: 46188 | L77: MH | M77: KA569441 | N77: Aluminum Scrap | O77: 830 | P77: 180 | Q77: =O77*P77 -> 149400 | R77: 0 | S77: =O77-R77 -> 830 | T77: 0 | U77: 0 | V77: 0 | W77: 0 | X77: 0 | Y77: 0 | Z77: 0 | AA77: 0 | AB77: =Y77+AA77+Z77 -> 0 | AC77: 0 | AD77: =IFERROR((Q77+AB77)/S77,0) -> 180 | AE77: 0 | AF77: 0 | AG77: 0 | AH77: 0 | AI77: 0 | AJ77: 0 | AK77: 0 | AL77: 0 | AM77: =Q77+AB77+AL77+AK77+AJ77+T77+AE77 -> 149400 | AN77: 46188 | AO77: 27/MET/27IN00003 | AP77: 832139000076790009 | AQ77: VINAYAK METAL AND ALLOYS PRIVATE LIMITED | AR77: 36AAGCV9303A1ZK | AS77: Koregaon Bhima,Maharashtra,412216 | AT77: Mutpoor | AU77: Telangana | AW77: 830 | AX77: 235 | AY77: =AW77*AX77 -> 195050 | AZ77: =AW77=O77 -> TRUE | BA77: 0 | BB77: =AW77-BA77 -> 830 | BC77: 0 | BD77: Regular | BE77: 0 | BF77: 0 | BG77: 0 | BH77: 0 | BI77: 0 | BJ77: 0 | BK77: 0 | BL77: 0 | BM77: 0 | BN77: =AY77*$BM$3 -> -4876.25 | BO77: =AY77+BL77+BM77+BN77+BC77+BG77 -> 190173.75 | BP77: =BO77-AM77 -> 40773.75 | BQ77: =IF(BP77>=0,"Positive Margin","Negative Margin") -> Positive Margin | BR77: CN Provision | BS77: =AY77-Y77-Q77-AA77-T77+BC77 -> 45650 | BT77: =IF(BS77<0, "Negative Margin at Inception", "Positive Margin at Inception") -> Positive Margin at Inception | BU77: =IFERROR(BP77/BO77,"0") -> 0.21440262 | BV77: =IF(BU77<1%,"Less Than 1%",IF(BU77>2%,"More than 2%",IF(BU77>=1%,"1% - 2%"))) -> More than 2% | BW77: =BM77+BN77 -> -4876.25 | BX77: =AL77+AK77 -> 0 | BY77: =BW77-BX77 -> -4876.25 | BZ77: =BM77 -> 0 | CA77: =AK77 -> 0 | CB77: =BZ77-CA77 -> 0 | CC77: Marketplace (Rewerse) | CD77: 0 | CE77: =TEXT(AN77,"mmm-yy") -> Jun-26 | CF77: =AM77-AL77-AA77 -> 149400 | CG77: =BO77-BN77 -> 195050 | CH77: =INT((D77- IF(MONTH(D77) >= 4, DATE(YEAR(D77), 4, 1), DATE(YEAR(D77)-1, 4, 1))) / 7) + 1 -> 11 | CI77: Plastic | CJ77: Plastic | CK77: =_xlfn.XLOOKUP(AR77,receivables!B:B,receivables!D:D) -> 0 | CL77: =AY77-Q77 -> 45650 | CM77: =CL77-Y77+Z77 -> 45650 | CN77: =BO77-AM77 -> 40773.75 | CO77: =AY77*118% -> 230159 | CP77: =-Q77*118% -> -176292 | CQ77: =-BZ77*118% -> 0 | CR77: =-CA77*118% -> 0 | CS77: =SUM(CO77:CR77) -> 53867 | CT77: Telangana - HO | CU77: Telangana - HO | CV77: =MID(G77,3,10) -> AAMCB5608A | CW77: =MID(AR77,3,10) -> AAGCV9303A | CX77: 0 | CY77: 0 | CZ77: 0 | DA77: 0 | DB77: 0
F79: Total | O79: =SUBTOTAL(9,O5:O78) -> 250350 | Q79: =SUBTOTAL(9,Q5:Q78) -> 11824275 | S79: =SUBTOTAL(9,S5:S78) -> 250350 | T79: =SUBTOTAL(9,T5:T78) -> 0 | Y79: =SUBTOTAL(9,Y5:Y78) -> 0 | Z79: =SUBTOTAL(9,Z5:Z78) -> 0 | AA79: =SUBTOTAL(9,AA5:AA78) -> 0 | AB79: =SUBTOTAL(9,AB5:AB78) -> 0 | AC79: =SUBTOTAL(9,AC5:AC78) -> 0 | AD79: =SUBTOTAL(1,AD5:AD78) -> 45.643836 | AE79: =SUBTOTAL(9,AE5:AE78) -> 0 | AJ79: =SUBTOTAL(9,AJ5:AJ78) -> 0 | AK79: =SUBTOTAL(9,AK5:AK78) -> 0 | AL79: =SUBTOTAL(9,AL5:AL78) -> 0 | AM79: =SUBTOTAL(9,AM5:AM78) -> 11824275 | AW79: =SUBTOTAL(9,AW5:AW78) -> 250350 | AX79: =SUBTOTAL(101,AX5:AX78) -> 59.013699 | AY79: =SUBTOTAL(9,AY5:AY78) -> 15310125 | BA79: =SUBTOTAL(9,BA5:BA78) -> 0 | BB79: =SUBTOTAL(9,BB5:BB78) -> 250350 | BC79: =SUBTOTAL(9,BC5:BC78) -> 0 | BG79: =SUBTOTAL(9,BG5:BG78) -> 0 | BL79: =SUBTOTAL(9,BL5:BL78) -> 0 | BM79: =SUBTOTAL(9,BM5:BM78) -> -46411.94 | BN79: =SUBTOTAL(9,BN5:BN78) -> -299279.88 | BO79: =SUBTOTAL(9,BO5:BO78) -> 14964433 | BP79: =SUBTOTAL(9,BP5:BP78) -> 3140158.2 | BS79: =SUBTOTAL(9,BS5:BS78) -> 3485850 | BW79: =SUBTOTAL(9,BW5:BW78) -> -345691.82 | BX79: =SUBTOTAL(9,BX5:BX78) -> 0 | BY79: =SUBTOTAL(9,BY5:BY78) -> -345691.82 | BZ79: =SUBTOTAL(9,BZ5:BZ78) -> -46411.94 | CA79: =SUBTOTAL(9,CA5:CA78) -> 0 | CB79: =SUBTOTAL(9,CB5:CB78) -> -46411.94 | CF79: =SUBTOTAL(9,CF5:CF78) -> 11824275 | CG79: =SUBTOTAL(9,CG5:CG78) -> 15263713 | CL79: =SUBTOTAL(9,CL5:CL78) -> 3485850 | CM79: =SUBTOTAL(9,CM5:CM78) -> 3485850 | CN79: =SUBTOTAL(9,CN5:CN78) -> 3140158.2 | CO79: =SUBTOTAL(9,CO5:CO78) -> 18065948 | CP79: =SUBTOTAL(9,CP5:CP78) -> -13952644 | CQ79: =SUBTOTAL(9,CQ5:CQ78) -> 54766.089 | CR79: =SUBTOTAL(9,CR5:CR78) -> 0 | CS79: =SUBTOTAL(9,CS5:CS78) -> 4168069.1
N80: =O79-AW79+'Recon Items'!R31 -> 0 | P80: =Q79+AK79+AJ79+AL79+T79+AE79 -> 11824275 | Q80: =Q79*18% -> 2128369.5 | R80: =Q80*25% -> 532092.38 | AA80: =AB79/AY79 -> 0 | AC80: =+AL79+AK79 -> 0 | AI80: Total DN in FY 2025-26 | AJ80: =AK79+AJ79+AE79 -> 0 | AM80: =AM79*18% -> 2128369.5 | BH80: Total CN in FY 2025-26 | BI80: =BL79+BM79+BC79+BM87 -> -46411.94 | BK80: =BI80/AY79 -> -0.003031454 | BN80: =BP79/BO79 -> 0.20984144 | BR80: =BS79/AY79 -> 0.22768266 | BX80: =BX79/BW79 -> 0 | CA80: =IFERROR(CA79/BZ79,0) -> 0 | CD80: With GST | CE80: =CF79*118% -> 13952644 | CF80: =CG79*118% -> 18011181
AI81: Total DN of FY 2024-25 | AJ81: =-'Last year''s'!#REF! -> #REF! | BH81: Total CN of FY 2024-25 | BI81: ='Last year''s'!L8 -> 105923.5
B82: Quarter | C82: Month | D82: Date | E82: Shipment ID | F82: Supplier Name | G82: GST Reg No. | H82: Vendor Invoice No. | I82: Vendor Invoice Date | J82: P V No. | K82: P V Date | L82: State (Origin) | M82: Vehicle No. | N82: Material | O82: Qty (Kg) | P82: Price/Kg | Q82: Purchase Price | R82: Return Qty | S82: Net Qty | T82: Basic Customs Duty | U82: Transporter Name | V82: LR NO/BILL NO | W82: J V No. | X82: JV Date | Y82: Logistics cost | Z82: Debit note on logistic cost | AA82: Logistics Provision | AB82: Total Logistics Cost | AC82: Operational Cost | AD82: Cost/Kg. | AE82: Divertion/Internal | AF82: Debit Note No. | AG82: Debit Note Date. | AH82: Debit Note No. 2 | AI82: Debit Note Date. 2 | AJ82: Full Debit Note | AK82: Actual Debit Note | AL82: Provision for DN | AM82: Total Cost | AN82: Inv. Date | AO82: Inv. No. | AP82: Customer ID | AQ82: Buyer Name | AR82: Buyer GST Number | AS82: Location (Origin) | AT82: Location (Destination) | AU82: State (Destination) | AV82: E-WayBill Number | AW82: Qty(Kg) | AX82: Rate/Kg | AY82: Amount | AZ82: Qty Check | BA82: Return Qty | BB82: Net Qty | BC82: Divertion/Internal | BD82: Return Type | BE82: Date : DN to Buyer | BF82: DN to Buyer | BG82: Amount | BH82: Credit Note No:1 | BI82: CN Date. No:1 | BJ82: Credit Note No:2 | BK82: CN Date. No:2 | BL82: Full Credit Notes | BM82: Actual Credit Note | BN82: Provision for CN | BO82: Net Revenue | BP82: Margin | BQ82: Reamrks - Margin | BR82: Remarks | BS82: LMI @ Inception | BT82: Remarks @ Inception | BU82: Margin (%) | BV82: Margin Bucket | BW82: Total CN(Inc.Provisions) | BX82: Total DN(Inc.Provisions) | BY82: Check | BZ82: Actaul CN | CA82: Actual DN | CB82: Check | CC82: Material-Short Form | CD82: Supplier Type | CE82: Month | CF82: Cost | CG82: Revenue | CH82: Week No: | CI82: Category (Material) | CJ82: Broad Category | CK82: POC Name | CL82: Gross Margin | CM82: Recykal Margin | CN82: Net Margin | CO82: Sales | CP82: Purchases | CQ82: Credit Note | CR82: Debit Note | CS82: Margin | CT82: Bill Branch | CU82: Inv Branch | CV82: Vendor PAN No | CW82: Customer PAN No | CX82: GST TDS Applicability | CY82: Cash Discount(Provision) | CZ82: Cash Discount | DA82: Cash Discount. No | DB82: CD Date
B83: Q1 | C83: =TEXT(AN83,"mmm-yy") -> Apr-26 | D83: 46142 | E83: Supporting Service charges-Apr-26 (Variable) | F83: BLACK GOLD RECYCLING PRIVATE LIMITED | G83: 27AAMCB5608A1ZX | H83: 0 | I83: 0 | J83: 0 | K83: 0 | L83: MH | N83: Supporting Service charges-Apr-26 (Variable) | O83: 1 | P83: 0 | Q83: 0 | R83: 0 | S83: 1 | T83: 0 | U83: 0 | V83: 0 | W83: 0 | X83: 0 | Y83: 0 | Z83: 0 | AA83: 0 | AB83: 0 | AC83: =1581099*Summary!D5/123 -> 857135.62 | AD83: 0 | AE83: 0 | AF83: 0 | AG83: 0 | AH83: 0 | AI83: 0 | AJ83: 0 | AK83: 0 | AL83: 0 | AM83: 0 | AN83: 46142 | AO83: 0 | AP83: 0 | AQ83: 0 | AR83: 0 | AS83: 0 | AT83: 0 | AU83: 0 | AV83: 1 | AW83: 0 | AX83: 0 | AY83: TRUE | AZ83: 0 | BA83: 1 | BB83: 0 | BC83: Regular | BD83: 0 | BE83: 0 | BF83: 0 | BG83: 0 | BH83: 0 | BI83: 0 | BJ83: 0 | BK83: 0 | BL83: 0 | BM83: 0 | BN83: 0 | BO83: 0 | BP83: Positive Margin | BQ83: Supporting Service charges-Apr-26 | BR83: 0 | BS83: Positive Margin at Inception | BT83: 0 | BU83: More than 2% | BV83: 0 | BW83: 0 | BX83: 0 | BY83: 0 | BZ83: 0 | CA83: 0 | CB83: Marketplace Purchases (Rewerse) | CC83: 0 | CD83: Apr-25 | CE83: 0 | CF83: 0 | CG83: 4 | CH83: Cloud X | CI83: Cloud X | CJ83: Swapnil | CK83: 0 | CL83: 0 | CM83: 0 | CN83: 0 | CO83: 0 | CP83: 0 | CQ83: 0 | CR83: 0 | CS83: Telangana - HO | CT83: Telangana - HO | CU83: AAMCB5608A | CW83: =MID(AR83,3,10) | CX83: 0 | CY83: 0 | CZ83: 0 | DA83: 0 | DB83: 0
B84: Q1 | C84: =TEXT(AN84,"mmm-yy") -> May-26 | D84: 46173 | E84: Supporting Service charges-May-26 (Variable) | F84: BLACK GOLD RECYCLING PRIVATE LIMITED | G84: 27AAMCB5608A1ZX | H84: 0 | I84: 0 | J84: 0 | K84: 0 | L84: MH | N84: Supporting Service charges-May-26 (Variable) | O84: 1 | P84: 0 | Q84: 0 | R84: 0 | S84: 1 | T84: 0 | U84: 0 | V84: 0 | W84: 0 | X84: 0 | Y84: 0 | Z84: 0 | AA84: 0 | AB84: 0 | AC84: =1581099*Summary!E5/123 -> 1348111.9 | AD84: 0 | AE84: 0 | AF84: 0 | AG84: 0 | AH84: 0 | AI84: 0 | AJ84: 0 | AK84: 0 | AL84: 0 | AM84: 0 | AN84: 46173 | AO84: 0 | AP84: 0 | AQ84: 0 | AR84: 0 | AS84: 0 | AT84: 0 | AU84: 0 | AV84: 1 | AW84: 0 | AX84: 0 | AY84: TRUE | AZ84: 0 | BA84: 1 | BB84: 0 | BC84: Regular | BD84: 0 | BE84: 0 | BF84: 0 | BG84: 0 | BH84: 0 | BI84: 0 | BJ84: 0 | BK84: 0 | BL84: 0 | BM84: 0 | BN84: 0 | BO84: 0 | BP84: Positive Margin | BQ84: Supporting Service charges-May-26 (Variable) | BR84: 0 | BS84: Positive Margin at Inception | BT84: 0 | BU84: More than 2% | BV84: 0 | BW84: 0 | BX84: 0 | BY84: 0 | BZ84: 0 | CA84: 0 | CB84: Marketplace Purchases (Rewerse) | CC84: 0 | CD84: Apr-25 | CE84: 0 | CF84: 0 | CG84: 4 | CH84: Cloud X | CI84: Cloud X | CJ84: Swapnil | CK84: 0 | CL84: 0 | CM84: 0 | CN84: 0 | CO84: 0 | CP84: 0 | CQ84: 0 | CR84: 0 | CS84: Telangana - HO | CT84: Telangana - HO | CU84: AAMCB5608A | CW84: =MID(AR84,3,10) | CX84: 0 | CY84: 0 | CZ84: 0 | DA84: 0 | DB84: 0
B85: Q1 | C85: =TEXT(AN85,"mmm-yy") -> Jun-26 | D85: 46203 | E85: Supporting Service charges-Junne-26 (Variable) | F85: BLACK GOLD RECYCLING PRIVATE LIMITED | G85: 27AAMCB5608A1ZX | H85: 0 | I85: 0 | J85: 0 | K85: 0 | L85: MH | N85: Supporting Service charges-June-26 (Variable) | O85: 1 | P85: 0 | Q85: 0 | R85: 0 | S85: 1 | T85: 0 | U85: 0 | V85: 0 | W85: 0 | X85: 0 | Y85: 0 | Z85: 0 | AA85: 0 | AB85: 0 | AC85: =1581099*Summary!F5/123+100000 -> 1112867.4 | AD85: 0 | AE85: 0 | AF85: 0 | AG85: 0 | AH85: 0 | AI85: 0 | AJ85: 0 | AK85: 0 | AL85: 0 | AM85: 0 | AN85: 46203 | AO85: 0 | AP85: 0 | AQ85: 0 | AR85: 0 | AS85: 0 | AT85: 0 | AU85: 0 | AV85: 1 | AW85: 0 | AX85: 0 | AY85: TRUE | AZ85: 0 | BA85: 1 | BB85: 0 | BC85: Regular | BD85: 0 | BE85: 0 | BF85: 0 | BG85: 0 | BH85: 0 | BI85: 0 | BJ85: 0 | BK85: 0 | BL85: 0 | BM85: 0 | BN85: 0 | BO85: 0 | BP85: Positive Margin | BQ85: Supporting Service charges-June-26 (Variable) | BR85: 0 | BS85: Positive Margin at Inception | BT85: 0 | BU85: More than 2% | BV85: 0 | BW85: 0 | BX85: 0 | BY85: 0 | BZ85: 0 | CA85: 0 | CB85: Marketplace Purchases (Rewerse) | CC85: 0 | CD85: Apr-25 | CE85: 0 | CF85: 0 | CG85: 4 | CH85: Cloud X | CI85: Cloud X | CJ85: Swapnil | CK85: 0 | CL85: 0 | CM85: 0 | CN85: 0 | CO85: 0 | CP85: 0 | CQ85: 0 | CR85: 0 | CS85: Telangana - HO | CT85: Telangana - HO | CU85: AAMCB5608A | CW85: =MID(AR85,3,10) | CX85: 0 | CY85: 0 | CZ85: 0 | DA85: 0 | DB85: 0
F87: Total | O87: =SUBTOTAL(9,O83:O86) -> 3 | Q87: =SUBTOTAL(9,Q83:Q86) -> 0 | R87: =SUBTOTAL(9,R83:R86) -> 0 | S87: =SUBTOTAL(9,S83:S86) -> 3 | T87: =SUBTOTAL(9,T83:T86) -> 0 | Y87: =SUBTOTAL(9,Y83:Y86) -> 0 | Z87: =SUBTOTAL(9,Z83:Z86) -> 0 | AA87: =SUBTOTAL(9,AA83:AA86) -> 0 | AB87: =SUBTOTAL(9,AB83:AB86) -> 0 | AC87: =SUBTOTAL(9,AC83:AC86) -> 3318114.9 | AD87: =SUBTOTAL(9,AD83:AD86) -> 0 | AE87: =SUBTOTAL(9,AE83:AE86) -> 0 | AF87: =SUBTOTAL(9,AF83:AF86) -> 0 | AG87: =SUBTOTAL(9,AG83:AG86) -> 0 | AJ87: =SUBTOTAL(9,AJ83:AJ86) -> 0 | AK87: =SUBTOTAL(9,AK83:AK86) -> 0 | AL87: =SUBTOTAL(9,AL83:AL86) -> 0 | AM87: =SUBTOTAL(9,AM83:AM86) -> 0 | AW87: =SUBTOTAL(9,AW83:AW86) -> 0 | AY87: =SUBTOTAL(9,AY83:AY86) -> 0 | BA87: =SUBTOTAL(9,BA83:BA86) -> 3 | BB87: =SUBTOTAL(9,BB83:BB86) -> 0 | BC87: =SUBTOTAL(9,BC83:BC86) -> 0 | BG87: =SUBTOTAL(9,BG83:BG86) -> 0 | BL87: =SUBTOTAL(9,BL83:BL86) -> 0 | BM87: =SUBTOTAL(9,BM83:BM86) -> 0 | BN87: =SUBTOTAL(9,BN83:BN86) -> 0 | BO87: =SUBTOTAL(9,BO83:BO86) -> 0 | BP87: =SUBTOTAL(9,BP83:BP86) -> 0 | BS87: =SUBTOTAL(9,BS83:BS86) -> 0 | BW87: =SUBTOTAL(9,BW83:BW86) -> 0 | BX87: =SUBTOTAL(9,BX83:BX86) -> 0 | BY87: =SUBTOTAL(9,BY83:BY86) -> 0 | BZ87: =SUBTOTAL(9,BZ83:BZ86) -> 0 | CA87: =SUBTOTAL(9,CA83:CA86) -> 0 | CB87: =SUBTOTAL(9,CB83:CB86) -> 0 | CF87: =SUBTOTAL(9,CF83:CF86) -> 0 | CG87: =SUBTOTAL(9,CG83:CG86) -> 12 | CL87: =SUBTOTAL(9,CL83:CL86) -> 0 | CM87: =SUBTOTAL(9,CM83:CM86) -> 0 | CN87: =SUBTOTAL(9,CN83:CN86) -> 0 | CO87: =SUBTOTAL(9,CO83:CO86) -> 0 | CP87: =SUBTOTAL(9,CP83:CP86) -> 0 | CQ87: =SUBTOTAL(9,CQ83:CQ86) -> 0 | CR87: =SUBTOTAL(9,CR83:CR86) -> 0 | CS87: =SUBTOTAL(9,CS83:CS86) -> 0
N89: Particulars | O89: Amount | AA89: Particulars | AC89: Amount | AX89: Particulars | AY89: Amount
N90: Net Purchase as per report | O90: =Q79+AJ79+AK79+AE79+Q87+AK87 -> 11824275 | AA90: Net Logistic Cost as per report | AC90: =Y79+Z79 -> 0 | AX90: Net Sales As per report | AY90: =+AY79+BL79+BM79+BC79+BG79+AY87+BM87+BL87+BG87+BC87 -> 15263713
N91: As per ZOHO | O91: 10645655 | P91: 46194 | AA91: As per ZOHO | AC91: 0 | AD91: =P91 -> 46194 | AX91: As per ZOHO | AY91: 13655265 | AZ91: =P91 -> 46194
N92: Variance | O92: =O91-O90 -> -1178619.7 | AA92: Variance | AC92: =-(AC91-AC90) -> 0 | AX92: Variance | AY92: =AY90-AY91 -> 1608448.4
N93: Provision for DN to Vendors(Fy 2025-26) | O93: 0 | AA93: Fy 2025-26 Logistic Provision Reversal | AC93: 0 | AX93: CN Provision in Zoho FY 25-26 | AY93: ='Last year''s'!L3 -> 411245
N94: JV for last year Bills | O94: 0 | AA94: FY 2025-26 Logistics | AC94: 0 | AX94: FY 2025-26 Credit notes | AY94: =-'Last year''s'!L8 -> -105923.5
N95: Debit note FY 25-26 | O95: ='Last year''s'!F6 -> -151580.3 | AA95: Provision for Logistics (Fy 2025-26) | AC95: 0 | AX95: Provision for CN from Customers(Fy 2025-26) | AY95: 0
N96: Paper | O96: =-'Recon Items'!C46 -> 0 | AA96: Paper | AC96: =-'Recon Items'!K56 -> 0 | AX96: Paper | AY96: ='Recon Items'!G46 -> 0
N97: Reconciliation | O97: ='Recon Items'!G18-'Recon Items'!C18-'Recon Items'!N18+'Recon Items'!C43 -> -1330200 | AA97: Reconciliation | AC97: ='Recon Items'!K42 -> 0 | AX97: Reconciliation | AY97: =-'Recon Items'!C29+'Recon Items'!G29+'Recon Items'!R24+'Recon Items'!H43 -> -1913770
N98: Variance | O98: =O92+O95-O97-O94-O93-O96 -> 0.02 | AA98: Variance | AC98: =SUM(AC92:AC97) -> 0 | AX98: Final Variance | AY98: =AY92+AY94+AY97+AY93-AY95-AY96 -> -0.09
BJ111: =SUM(BJ105:BJ110) -> 0
BJ112: =BJ104-BJ111 -> 0
AK118: =AK119-AK120 -> 0

Sheet Recon Items
J3: Qty Reco | M3: FY 2024-25 bills considered ths year | Q3: FY 2024-25
B4: Bills in report not in P&L | C4: Amount | F4: Bills in P&L not in report | G4: Amount | H4: Qty | J4: Qty Check | K4: =Details!AD91 -> 46194 | M4: Bills in report not in P&L | N4: Amount | O4: Qty | Q4: DN to Customer | R4: Amount
B5: SH06261404 | C5: 1330200
J6: As Per Report | K6: =-Details!AW79 -> -250350
J7: As per Zoho(till May) | K7: 171555
J8: As per Zoho (current month) | K8: 71405 | L8: =Details!O76+Details!O77 -> 7390
J9: Reco | K9: =R31+I42 -> 0
J10: Variance | K10: =SUM(K6:K9)-H18 -> -7390
J14: BCD not in Report | K14: Amount
B18: G.Total | C18: =SUM(C5:C17) -> 1330200 | F18: G.Total | G18: =SUBTOTAL(9,G5:G17) -> 0 | H18: =SUBTOTAL(9,H5:H17) -> 0 | K18: =SUM(K15:K17) -> 0 | M18: G.Total | N18: =SUM(N5:N17) -> 0 | O18: =SUM(O5:O17) -> 0
B21: Sales in report not in P&L | C21: Amount | F21: Sales in P&L not in report | G21: Amount | H21: Qty | J21: Bils in Report & P&L , Sale yet to be done
B22: SH06261404 | C22: 1913770
Q24: G.Total | R24: =SUM(R5:R23) -> 0
Q25: Offline orders & Divertions
Q26: SO Number | R26: Qty
B29: G.Total | C29: =SUM(C22:C28) -> 1913770 | F29: G.Total | G29: =SUBTOTAL(9,G22:G28) -> 0 | H29: 0 | J29: G.Total
B31: DRS | Q31: G.Total | R31: =SUM(R27:R30) -> 0
B32: Bills | C32: Amount | D32: DN | F32: Invoices | G32: Amount | H32: CN | I32: Qty | J32: Logistic Bill | K32: Amount
B42: G.Total | C42: =SUM(C33:C41) -> 0 | D42: =SUM(D33:D41) -> 0 | F42: G.Total | G42: =SUBTOTAL(9,G33:G41) -> 0 | H42: =SUBTOTAL(9,H33:H41) -> 0 | I42: =SUBTOTAL(9,I33:I41) -> 0 | J42: G.Total | K42: =SUBTOTAL(9,K33:K41) -> 0
C43: =C42-D42 -> 0 | H43: =G42+H42 -> 0
B46: Paper | C46: =C56-D56 -> 0 | G46: =G56-H56 -> 0
B47: Bills | C47: Amount | D47: DN | F47: Invoices | G47: Amount | H47: CN | I47: Qty | J47: Logistic Bill | K47: Amount
B56: G.Total | C56: =SUM(C48:C55) -> 0 | D56: =SUM(D48:D55) -> 0 | F56: G.Total | G56: =SUBTOTAL(9,G48:G55) -> 0 | H56: =SUBTOTAL(9,H48:H55) -> 0 | I56: =SUBTOTAL(9,I48:I55) -> 0 | J56: G.Total | K56: =SUBTOTAL(9,K48:K55) -> 0
AB696: -568957
AB701: =-AB697+AB698-AB699 -> 0

Sheet Supplier Metrics
D1: =D2-Summary!Q7 -> 0
D2: =SUBTOTAL(9,D4:D25) -> 11824275 | E2: =COUNTA(_xlfn.ANCHORARRAY(E4)) -> 1
B3: Supplier Name | C3: GST Reg No. | D3: Purchases | E3: Count Supplier Name
B4: =_xlfn.XLOOKUP(C4,Details!$G$5:$G$78,Details!$F$5:$F$78) -> BLACK GOLD RECYCLING PRIVATE LIMITED | C4: {=_xlfn.UNIQUE(_xlfn._TRO_TRAILING(Details!G5:G78))} -> 27AAMCB5608A1ZX | D4: =SUMIFS(Details!$AM$5:$AM$78,Details!$G$5:$G$78,'Supplier Metrics'!C4)-SUMIFS(Details!$AB$5:$AB$78,Details!$G$5:$G$78,'Supplier Metrics'!C4) -> 11824275 | E4: {=_xlfn.UNIQUE(MID(_xlfn._TRO_TRAILING(Details!G5:G78),3,10))} -> AAMCB5608A

Sheet Buyer Metrics
F2: =F3-Summary!P6-Details!BO87 -> -1836623.6 | G2: =G3-Summary!P12-Summary!P79-Details!BP87 -> 2811691.3 | H2: =H3-Summary!P13 -> 0.21271156 | I2: =I3-Details!BZ79 -> 0 | K2: =K3-Summary!P19 -> 0 | S2: Revenue | AD2: Qty
B3: =COUNTA(_xlfn.ANCHORARRAY(B5)) -> 3 | C3: =COUNTA(_xlfn.ANCHORARRAY(C5)) -> 3 | E3: =SUM(E$5:E5) -> 223845 | F3: =SUM(F$5:F83) -> 13098507 | G3: =SUM(G$5:G83) -> 2604432.4 | H3: =G3/F3 -> 0.19883429 | I3: =SUM(I$5:I83) -> -46411.94 | J3: =I3/F3 -> -0.0035432999 | K3: =SUM(K$5:K83) -> 25 | L3: =SUBTOTAL(1,L5:L83) -> 525898.93 | M3: =F3/E3 -> 58.515971 | N3: =SUM(N$5:N83) -> 0 | S3: =SUBTOTAL(9,S5:S5) -> 0 | T3: =SUBTOTAL(9,T5:T5) -> 0 | U3: =SUBTOTAL(9,U5:U5) -> 0 | V3: =SUBTOTAL(9,V5:V5) -> 0 | W3: =SUBTOTAL(9,W5:W5) -> 0 | X3: =SUBTOTAL(9,X5:X5) -> 0 | Y3: =SUBTOTAL(9,Y5:Y5) -> 0 | Z3: =SUBTOTAL(9,Z5:Z5) -> 0 | ... AB3: =SUBTOTAL(9,AB5:AB5) -> 0 | AD3: =SUBTOTAL(9,AD5:AD5) -> 0 | AE3: =SUBTOTAL(9,AE5:AE5) -> 0 | AF3: =SUBTOTAL(9,AF5:AF5) -> 0 | AG3: =SUBTOTAL(9,AG5:AG5) -> 0 | AH3: =SUBTOTAL(9,AH5:AH5) -> 0 | AI3: =SUBTOTAL(9,AI5:AI5) -> 0 | AJ3: =SUBTOTAL(9,AJ5:AJ5) -> 0 | AK3: =SUBTOTAL(9,AK5:AK5) -> 0 | ... AM3: =SUBTOTAL(9,AM5:AM5) -> 0
B4: Count Recyclers | C4: Customer ID | D4: Customer Name | E4: Qty | F4: Revenue | G4: Margin | H4: Margin(% | I4: Debit Notes | J4: DN to Sale(%) | K4: No of transactions | L4: Avg Tran Value | M4: Avg.Price/kg | N4: Receivables | Q4: Count Recyclers | R4: Name | S4: Apr-25 | T4: May-25 | U4: Jun-25 | V4: Jul-25 | W4: Aug-25 | X4: Sep-25 | Y4: Oct-25 | Z4: Nov-25 | AA4: Dec-25 | AB4: Jan-26 | AD4: Apr-25 | AE4: May-25 | AF4: Jun-25 | AG4: Jul-25 | AH4: Aug-25 | AI4: Sep-25 | AJ4: Oct-25 | AK4: Nov-25 | AL4: Dec-25 | AM4: Jan-26
B5: {=_xlfn.UNIQUE(MID(_xlfn._TRO_TRAILING(Details!AR5:AR78),3,10))} -> AAACD5406E | C5: {=_xlfn.UNIQUE(_xlfn._TRO_TRAILING(Details!AR5:AR78))} -> 27AAACD5406E1Z3 | D5: =(_xlfn.XLOOKUP(C5,Details!$AR$5:$AR$78,Details!$AQ$5:$AQ$78)) -> DALMIA POLYPRO INDUSTRIES PRIVATE LIMITED (27) | E5: =SUMIFS(Details!BB:BB,Details!AR:AR,'Buyer Metrics'!$C5) -> 223845 | F5: =SUMIFS(Details!BO:BO,Details!AR:AR,'Buyer Metrics'!$C5) -> 12042046 | G5: =SUMIFS(Details!BP:BP,Details!AR:AR,'Buyer Metrics'!$C5) -> 2372861.2 | H5: =G5/F5 -> 0.19704801 | I5: =SUMIFS(Details!BZ:BZ,Details!AR:AR,'Buyer Metrics'!C5) -> -46411.94 | J5: =-(I5/F5) -> 0.0038541573 | K5: {=COUNTA(_xlfn.UNIQUE(_xlfn._xlws.FILTER(Details!AO5:AO78,Details!AR5:AR78='Buyer Metrics'!$C5)))} -> 23 | L5: =F5/K5 -> 523567.23 | M5: =F5/E5 -> 53.79636 | N5: =IFERROR(_xlfn.XLOOKUP(C5,receivables!#REF!,receivables!#REF!),0) -> 0 | Q5: {=_xlfn.UNIQUE(Details!CW5:CW78)} -> AAACD5406E | R5: =_xlfn.XLOOKUP(Q5,Details!CW:CW,Details!AQ:AQ) -> DALMIA POLYPRO INDUSTRIES PRIVATE LIMITED (27) | S5: =SUMIFS(Details!$BO:$BO,Details!$CW:$CW,'Buyer Metrics'!$Q5,Details!$C:$C,'Buyer Metrics'!S$4) -> 0 | T5: =SUMIFS(Details!$BO:$BO,Details!$CW:$CW,'Buyer Metrics'!$Q5,Details!$C:$C,'Buyer Metrics'!T$4) -> 0 | U5: =SUMIFS(Details!$BO:$BO,Details!$CW:$CW,'Buyer Metrics'!$Q5,Details!$C:$C,'Buyer Metrics'!U$4) -> 0 | V5: =SUMIFS(Details!$BO:$BO,Details!$CW:$CW,'Buyer Metrics'!$Q5,Details!$C:$C,'Buyer Metrics'!V$4) -> 0 | W5: =SUMIFS(Details!$BO:$BO,Details!$CW:$CW,'Buyer Metrics'!$Q5,Details!$C:$C,'Buyer Metrics'!W$4) -> 0 | X5: =SUMIFS(Details!$BO:$BO,Details!$CW:$CW,'Buyer Metrics'!$Q5,Details!$C:$C,'Buyer Metrics'!X$4) -> 0 | Y5: =SUMIFS(Details!$BO:$BO,Details!$CW:$CW,'Buyer Metrics'!$Q5,Details!$C:$C,'Buyer Metrics'!Y$4) -> 0 | Z5: =SUMIFS(Details!$BO:$BO,Details!$CW:$CW,'Buyer Metrics'!$Q5,Details!$C:$C,'Buyer Metrics'!Z$4) -> 0 | ... AB5: =SUMIFS(Details!$BO:$BO,Details!$CW:$CW,'Buyer Metrics'!$Q5,Details!$C:$C,'Buyer Metrics'!AB$4) -> 0 | AD5: =SUMIFS(Details!$BB:$BB,Details!$CW:$CW,'Buyer Metrics'!$Q5,Details!$C:$C,'Buyer Metrics'!AD$4) -> 0 | AE5: =SUMIFS(Details!$BB:$BB,Details!$CW:$CW,'Buyer Metrics'!$Q5,Details!$C:$C,'Buyer Metrics'!AE$4) -> 0 | AF5: =SUMIFS(Details!$BB:$BB,Details!$CW:$CW,'Buyer Metrics'!$Q5,Details!$C:$C,'Buyer Metrics'!AF$4) -> 0 | AG5: =SUMIFS(Details!$BB:$BB,Details!$CW:$CW,'Buyer Metrics'!$Q5,Details!$C:$C,'Buyer Metrics'!AG$4) -> 0 | AH5: =SUMIFS(Details!$BB:$BB,Details!$CW:$CW,'Buyer Metrics'!$Q5,Details!$C:$C,'Buyer Metrics'!AH$4) -> 0 | AI5: =SUMIFS(Details!$BB:$BB,Details!$CW:$CW,'Buyer Metrics'!$Q5,Details!$C:$C,'Buyer Metrics'!AI$4) -> 0 | AJ5: =SUMIFS(Details!$BB:$BB,Details!$CW:$CW,'Buyer Metrics'!$Q5,Details!$C:$C,'Buyer Metrics'!AJ$4) -> 0 | AK5: =SUMIFS(Details!$BB:$BB,Details!$CW:$CW,'Buyer Metrics'!$Q5,Details!$C:$C,'Buyer Metrics'!AK$4) -> 0 | ... AM5: =SUMIFS(Details!$BB:$BB,Details!$CW:$CW,'Buyer Metrics'!$Q5,Details!$C:$C,'Buyer Metrics'!AM$4) -> 0
B6: AAICN2675D | C6: 26AAICN2675D1ZG | D6: =(_xlfn.XLOOKUP(C6,Details!$AR$5:$AR$78,Details!$AQ$5:$AQ$78)) -> NATIONAL FIBRES PRIVATE LIMITED | E6: =SUMIFS(Details!BB:BB,Details!AR:AR,'Buyer Metrics'!$C6) -> 19115 | F6: =SUMIFS(Details!BO:BO,Details!AR:AR,'Buyer Metrics'!$C6) -> 1056461.2 | G6: =SUMIFS(Details!BP:BP,Details!AR:AR,'Buyer Metrics'!$C6) -> 231571.25 | H6: =G6/F6 -> 0.21919521 | I6: =SUMIFS(Details!BZ:BZ,Details!AR:AR,'Buyer Metrics'!C6) -> 0 | J6: =-(I6/F6) -> 0 | K6: {=COUNTA(_xlfn.UNIQUE(_xlfn._xlws.FILTER(Details!AO6:AO79,Details!AR6:AR79='Buyer Metrics'!$C6)))} -> 2 | L6: =F6/K6 -> 528230.62 | M6: =F6/E6 -> 55.268703 | N6: =IFERROR(_xlfn.XLOOKUP(C6,receivables!#REF!,receivables!#REF!),0) -> 0 | Q6: AAICN2675D
B7: AAGCV9303A | C7: 36AAGCV9303A1ZK | Q7: AAGCV9303A
Q8: 0

Sheet Material Metrics
B2: Material | C2: Category A | D2: Category B
B3: {=_xlfn.UNIQUE(_xlfn._TRO_TRAILING(Details!N5:N78))} -> PET Bottle Scrap Baled - Clear | C3: PET
B4: PET Bottle Scrap Baled - Green
B5: PET Liquor Bottle Scrap Baled
B6: Used Beverage Cans scrap (UBC)
B7: Aluminum Scrap
C41: HDPE
C42: HDPE

Sheet receivables
D1: =Details!P91 -> 46194 | E1: =SUBTOTAL(9,E3:E136) -> #N/A | R1: =SUBTOTAL(9,R3:R1000) -> 13788511 | S1: =SUBTOTAL(9,S3:S1000) -> 24188963 | W1: =SUBTOTAL(9,W3:W1000) -> 5319.09 | AA1: =SUM(AA3:AA14) -> 5319.09 | AB1: =R1-AA1 -> 13783192 | AD1: Legacy | AE1: =R1-#REF!-SUM(AE3:AE16)-AE18 -> #REF!
B2: Customer ID | C2: Buyer Name | D2: POC Name | E2: Recivables | H2: POC Name | I2: Buyer Name | K2: date | L2: status | M2: entity | N2: age | O2: due_date | P2: transaction_number | Q2: customer_name | R2: balance | S2: amount | T2: payment_terms | U2: gst_no | V2: credit_limit | W2: unused_credits_receivable_amount | X2: contact.CF.Vertical Name | Y2: Check | Z2: customer_name | AA2: unused_credits_receivable_amount | AD2: Customer Name | AE2: Current O/s
B3: {=_xlfn.UNIQUE(_xlfn._TRO_TRAILING(Details!AR5:AR78))} -> 27AAACD5406E1Z3 | C3: =_xlfn.XLOOKUP(B3,Details!AR:AR,Details!AQ:AQ) -> DALMIA POLYPRO INDUSTRIES PRIVATE LIMITED (27) | D3: Neelesh Dixit | E3: =_xlfn.XLOOKUP(C3,I:I,H:H) -> #N/A | H3: Neelesh Dixit | I3: M/S KASHI VISHWANATH TEXTILE MILL PRIVATE LIMITED | K3: 45881 | L3: overdue | M3: invoice | N3: 295 | O3: 2025-08-30 | P3: 26/MPRE/INV0045 | Q3: DALMIA POLYPRO INDUSTRIES PRIVATE LIMITED(24) | R3: 10355.76 | S3: 541459.52 | T3: Immediate | U3: 24AAACD5406E1Z9 | V3: 643265 | W3: 0 | X3: Marketplace (Plastic Waste) | Y3: Marketplace Sales (ReWerse) | Z3: {=_xlfn.UNIQUE(Q3:Q1048576)} -> DALMIA POLYPRO INDUSTRIES PRIVATE LIMITED(24) | AA3: =_xlfn.XLOOKUP(Z3,Q:Q,W:W) -> 0 | AD3: VANSH POLYPACK LLP | AE3: =SUMIFS(R:R,Q:Q,AD3) -> 0
B4: 26AAICN2675D1ZG | H4: Neelesh Dixit | I4: NIRMAL FIBRES PRIVATE LIMITED | K4: 45925 | L4: overdue | M4: invoice | N4: 251 | O4: 2025-10-13 | P4: 26/MPRE/INV0120 | Q4: DALMIA POLYPRO INDUSTRIES PRIVATE LIMITED(24) | R4: 21068.94 | S4: 577766.94 | T4: Immediate | U4: 24AAACD5406E1Z9 | V4: 643265 | W4: 0 | X4: Marketplace (Plastic Waste) | Y4: Marketplace Sales (ReWerse) | Z4: EVER BLOOMING RECYCLING SOLUTIONS PRIVATE LIMITED | AA4: =_xlfn.XLOOKUP(Z4,Q:Q,W:W) -> 0 | AD4: INDIA POLYMERS | AE4: =SUMIFS(R:R,Q:Q,AD4) -> 0
B5: 36AAGCV9303A1ZK | H5: Neelesh Dixit | I5: SHRIMAN NARAYAN FIBER UDHOG PRIVATE LIMITED | K5: 45966 | L5: overdue | M5: invoice | N5: 222 | O5: 2025-11-11 | P5: 26/MPRE/INV0155 | Q5: EVER BLOOMING RECYCLING SOLUTIONS PRIVATE LIMITED | R5: 32971.24 | S5: 82971.24 | T5: Net 1 (Day) | U5: 36AAICE2880K1ZA | V5: 500000 | W5: 0 | X5: Marketplace (Plastic Waste) | Y5: Marketplace Sales (ReWerse) | Z5: HINDALCO INDUSTRIES LIMITED | AA5: =_xlfn.XLOOKUP(Z5,Q:Q,W:W) -> 0 | AD5: VERDE POLYSFY PRIVATE LIMITED | AE5: =SUMIFS(R:R,Q:Q,AD5) -> 0
H6: Ramesh G | I6: Sri Chakra Poly Plast India Private Limited | K6: 45997 | L6: overdue | M6: invoice | N6: 191 | O6: 2025-12-12 | P6: 26/MPRE/INV0225 | Q6: EVER BLOOMING RECYCLING SOLUTIONS PRIVATE LIMITED | R6: 53353.06 | S6: 53353.06 | T6: Net 1 (Day) | U6: 36AAICE2880K1ZA | V6: 500000 | W6: 0 | X6: Marketplace (Plastic Waste) | Y6: Marketplace Sales (ReWerse) | Z6: DALMIA POLYPRO INDUSTRIES PRIVATE LIMITED (27) | AA6: =_xlfn.XLOOKUP(Z6,Q:Q,W:W) -> 0 | AD6: HALIFAX GREENTECH LLP | AE6: =SUMIFS(R:R,Q:Q,AD6) -> 0
H7: Neelesh Dixit | I7: RPG Industrial Product Private Limited | K7: 45999 | L7: overdue | M7: invoice | N7: 189 | O7: 2025-12-14 | P7: 26/MPRE/INV0226 | Q7: EVER BLOOMING RECYCLING SOLUTIONS PRIVATE LIMITED | R7: 17484.78 | S7: 17484.78 | T7: Net 1 (Day) | U7: 36AAICE2880K1ZA | V7: 500000 | W7: 0 | X7: Marketplace (Plastic Waste) | Y7: Marketplace Sales (ReWerse) | Z7: Sunway Paper Products | AA7: =_xlfn.XLOOKUP(Z7,Q:Q,W:W) -> 0 | AD7: MLS INDUSTRIES | AE7: =SUMIFS(R:R,Q:Q,AD7) -> 0
H8: Gitika | I8: SANDBERRY FIBRETECH PRIVATE LIMITED | K8: 46018 | L8: overdue | M8: invoice | N8: 170 | O8: 2026-01-02 | P8: 26/MPRE/INV0256 | Q8: HINDALCO INDUSTRIES LIMITED | R8: 4515.29 | S8: 1634913.6 | T8: Net 5 (Days) | U8: 21AAACH1201R1ZZ | V8: 10000000 | W8: 0 | X8: Marketplace (Metal Waste) | Y8: Marketplace Sales (ReWerse) | Z8: NATIONAL FIBRES PRIVATE LIMITED | AA8: =_xlfn.XLOOKUP(Z8,Q:Q,W:W) -> 0 | AD8: EMINENT DEALERS PVT LTD | AE8: =SUMIFS(R:R,Q:Q,AD8) -> 0
H9: Pushpraj | I9: RSWM LIMITED | K9: 46043 | L9: overdue | M9: invoice | N9: 145 | O9: 2026-01-27 | P9: 26/MPRE/INV0272 | Q9: HINDALCO INDUSTRIES LIMITED | R9: 5968.64 | S9: 1579149.8 | T9: Net 5 (Days) | U9: 21AAACH1201R1ZZ | V9: 10000000 | W9: 0 | X9: Marketplace (Metal Waste) | Y9: Marketplace Sales (ReWerse) | Z9: VINAYAK METAL AND ALLOYS PRIVATE LIMITED | AA9: =_xlfn.XLOOKUP(Z9,Q:Q,W:W) -> 5319.09 | AD9: Nitika Polymer | AE9: =SUMIFS(R:R,Q:Q,AD9) -> 0
H10: Neelesh Dixit | I10: Ganesha Ecosphere Limited (Unit-2) | K10: 46047 | L10: overdue | M10: invoice | N10: 141 | O10: 2026-01-31 | P10: 26/MPRE/INV0275 | Q10: HINDALCO INDUSTRIES LIMITED | R10: 14451.18 | S10: 1555546.8 | T10: Net 5 (Days) | U10: 21AAACH1201R1ZZ | V10: 10000000 | W10: 0 | X10: Marketplace (Metal Waste) | Y10: Marketplace Sales (ReWerse) | Z10: 0 | AD10: PUSHPANJALI ENTERPRISES | AE10: =SUMIFS(R:R,Q:Q,AD10) -> 0
H11: Ramesh G | I11: Ganesha Ecotech Private Limited (Warangal) | K11: 46050 | L11: overdue | M11: invoice | N11: 115 | O11: 2026-02-26 | P11: 26/MPRE/INV0277 | Q11: DALMIA POLYPRO INDUSTRIES PRIVATE LIMITED (27) | R11: 7982.68 | S11: 356832 | T11: Net 30 (Days) | U11: 27AAACD5406E1Z3 | V11: 16056735 | W11: 0 | X11: Marketplace (Plastic Waste) | Y11: Marketplace Sales (ReWerse) | AD11: M/S SHLOK AND SANS | AE11: =SUMIFS(R:R,Q:Q,AD11) -> 0
H12: Pushpraj | I12: KANCHAN INDIA LIMITED | K12: 46065 | L12: overdue | M12: invoice | N12: 100 | O12: 2026-03-13 | P12: 26/MPRE/INV0283 | Q12: Sunway Paper Products | R12: 175175.46 | S12: 1094262.8 | T12: Net 30 (Days) | U12: 27CLBPP3625C1ZD | V12: 5000000 | W12: 0 | X12: Marketplace (Metal Waste) | Y12: Marketplace Sales (ReWerse) | AD12: A N Service Enterprises | AE12: =SUMIFS(R:R,Q:Q,AD12) -> 0
H13: Gitika | I13: AEC PLAST PRIVATE LIMITED | K13: 46099 | L13: overdue | M13: invoice | N13: 66 | O13: 2026-04-16 | P13: 26/MPRE/INV0303 | Q13: DALMIA POLYPRO INDUSTRIES PRIVATE LIMITED (27) | R13: 15817.57 | S13: 512217.35 | T13: Net 30 (Days) | U13: 27AAACD5406E1Z3 | V13: 16056735 | W13: 0 | X13: Marketplace (Plastic Waste) | Y13: Marketplace Sales (ReWerse) | AD13: SHREE SALASAR POLYFLEX (P) LTD. | AE13: =SUMIFS(R:R,Q:Q,AD13) -> 0
H14: Ramesh G | I14: SULOCHANA COTTON SPINNING MILLS (P)LTD | K14: 46118 | L14: overdue | M14: invoice | N14: 47 | O14: 2026-05-05 | P14: 36/REW/27IN00001 | Q14: DALMIA POLYPRO INDUSTRIES PRIVATE LIMITED (27) | R14: 19414.44 | S14: 532533 | T14: Net 30 (Days) | U14: 27AAACD5406E1Z3 | V14: 16056735 | W14: 0 | X14: Marketplace (Plastic Waste) | Y14: Marketplace Sales (ReWerse) | AD14: M/S PAL INDUSTRIES | AE14: =SUMIFS(R:R,Q:Q,AD14) -> 0
H15: Pushpraj | I15: Prism Infratech Management Private Limited | K15: 46134 | L15: overdue | M15: invoice | N15: 31 | O15: 2026-05-21 | P15: 36/REW/27IN00006 | Q15: DALMIA POLYPRO INDUSTRIES PRIVATE LIMITED (27) | R15: 604179.36 | S15: 610050.9 | T15: Net 30 (Days) | U15: 27AAACD5406E1Z3 | V15: 16056735 | W15: 0 | X15: Marketplace (Plastic Waste) | Y15: Marketplace Sales (ReWerse) | AD15: Jai Jeen Mata Trading Company | AE15: =SUMIFS(R:R,Q:Q,AD15) -> 0
H16: Ramesh G | I16: KUNDANA TECHNO TEX PRIVATE LIMITED | K16: 46137 | L16: overdue | M16: invoice | N16: 28 | O16: 2026-05-24 | P16: 36/REW/27IN00007 | Q16: DALMIA POLYPRO INDUSTRIES PRIVATE LIMITED (27) | R16: 595384.88 | S16: 604382.1 | T16: Net 30 (Days) | U16: 27AAACD5406E1Z3 | V16: 16056735 | W16: 0 | X16: Marketplace (Plastic Waste) | Y16: Marketplace Sales (ReWerse) | AD16: Maa Durga Industries | AE16: =SUMIFS(R:R,Q:Q,AD16) -> 0
H17: Gitika | I17: DODHIA SYNTHETICS LIMITED | K17: 46145 | L17: overdue | M17: invoice | N17: 20 | O17: 2026-06-01 | P17: 36/REW/27IN00008 | Q17: DALMIA POLYPRO INDUSTRIES PRIVATE LIMITED (27) | R17: 599528.76 | S17: 605206.4 | T17: Net 30 (Days) | U17: 27AAACD5406E1Z3 | V17: 16056735 | W17: 0 | X17: Marketplace (Plastic Waste) | Y17: Marketplace Sales (ReWerse)
H18: Shashank | I18: Nextgen Fibres Private Limited | K18: 46147 | L18: overdue | M18: invoice | N18: 18 | O18: 2026-06-03 | P18: 36/REW/27IN00009 | Q18: DALMIA POLYPRO INDUSTRIES PRIVATE LIMITED (27) | R18: 715835.1 | S18: 715835.1 | T18: Net 30 (Days) | U18: 27AAACD5406E1Z3 | V18: 16056735 | W18: 0 | X18: Marketplace (Plastic Waste) | Y18: Marketplace Sales (ReWerse) | AD18: DRS
H19: Neelesh Dixit | I19: Silver Ecotex LLP | K19: 46151 | L19: overdue | M19: invoice | N19: 14 | O19: 2026-06-07 | P19: 36/REW/27IN00010 | Q19: DALMIA POLYPRO INDUSTRIES PRIVATE LIMITED (27) | R19: 740503.2 | S19: 740503.2 | T19: Net 30 (Days) | U19: 27AAACD5406E1Z3 | V19: 16056735 | W19: 0 | X19: Marketplace (Plastic Waste) | Y19: Marketplace Sales (ReWerse)
H20: Neelesh Dixit | I20: RELIANCE INDUSTRIES LIMITED | K20: 46158 | L20: overdue | M20: invoice | N20: 7 | O20: 2026-06-14 | P20: 36/REW/27IN00011 | Q20: DALMIA POLYPRO INDUSTRIES PRIVATE LIMITED (27) | R20: 582560.7 | S20: 582560.7 | T20: Net 30 (Days) | U20: 27AAACD5406E1Z3 | V20: 16056735 | W20: 0 | X20: Marketplace (Plastic Waste) | Y20: Marketplace Sales (ReWerse)
H21: Gitika | I21: Alliance Fibres Limited | K21: 46164 | L21: overdue | M21: invoice | N21: 1 | O21: 2026-06-20 | P21: 36/REW/27IN00013 | Q21: DALMIA POLYPRO INDUSTRIES PRIVATE LIMITED (27) | R21: 645219.5 | S21: 645219.5 | T21: Net 30 (Days) | U21: 27AAACD5406E1Z3 | V21: 16056735 | W21: 0 | X21: Marketplace (Plastic Waste) | Y21: Marketplace Sales (ReWerse)
H22: Shashank | I22: GUNJAN INDUSTRIES | K22: 46164 | L22: overdue | M22: invoice | N22: 1 | O22: 2026-06-20 | P22: 36/REW/27IN00012 | Q22: DALMIA POLYPRO INDUSTRIES PRIVATE LIMITED (27) | R22: 663382.7 | S22: 663382.7 | T22: Net 30 (Days) | U22: 27AAACD5406E1Z3 | V22: 16056735 | W22: 0 | X22: Marketplace (Plastic Waste) | Y22: Marketplace Sales (ReWerse)
H23: Gitika | I23: BADRI COTSYN LIMITED | K23: 46165 | L23: sent | M23: invoice | O23: 2026-06-21 | P23: 36/REW/27IN00014 | Q23: DALMIA POLYPRO INDUSTRIES PRIVATE LIMITED (27) | R23: 575664.3 | S23: 575664.3 | T23: Net 30 (Days) | U23: 27AAACD5406E1Z3 | V23: 16056735 | W23: 0 | X23: Marketplace (Plastic Waste) | Y23: Marketplace Sales (ReWerse)
H24: Neelesh Dixit | I24: SHRI MAN NARAYAN POLYTAX PVT LTD | K24: 46166 | L24: sent | M24: invoice | O24: 2026-06-22 | P24: 36/REW/27IN00016 | Q24: DALMIA POLYPRO INDUSTRIES PRIVATE LIMITED (27) | R24: 645809.7 | S24: 645809.7 | T24: Net 30 (Days) | U24: 27AAACD5406E1Z3 | V24: 16056735 | W24: 0 | X24: Marketplace (Plastic Waste) | Y24: Marketplace Sales (ReWerse)
H25: Pushpraj | I25: MAHALAKSHMI SPINTEX PRIVATE LIMITED | K25: 46166 | L25: sent | M25: invoice | O25: 2026-06-22 | P25: 36/REW/27IN00015 | Q25: DALMIA POLYPRO INDUSTRIES PRIVATE LIMITED (27) | R25: 739119.2 | S25: 739119.2 | T25: Net 30 (Days) | U25: 27AAACD5406E1Z3 | V25: 16056735 | W25: 0 | X25: Marketplace (Plastic Waste) | Y25: Marketplace Sales (ReWerse)
H26: Neelesh Dixit | I26: PASHUPATI EXCRUSION PRIVATE LIMITED | K26: 46170 | L26: sent | M26: invoice | O26: 2026-06-26 | P26: 36/REW/27IN00017 | Q26: DALMIA POLYPRO INDUSTRIES PRIVATE LIMITED (27) | R26: 650726 | S26: 650726 | T26: Net 30 (Days) | U26: 27AAACD5406E1Z3 | V26: 16056735 | W26: 0 | X26: Marketplace (Plastic Waste) | Y26: Marketplace Sales (ReWerse)
H27: Shashank | I27: BHAGYAVARDHAN POLYFLAKES PRIVATE LIMITED | K27: 46172 | L27: sent | M27: invoice | O27: 2026-06-28 | P27: 36/REW/27IN00018 | Q27: DALMIA POLYPRO INDUSTRIES PRIVATE LIMITED (27) | R27: 731939.5 | S27: 731939.5 | T27: Net 30 (Days) | U27: 27AAACD5406E1Z3 | V27: 16056735 | W27: 0 | X27: Marketplace (Plastic Waste) | Y27: Marketplace Sales (ReWerse)
H28: Neelesh Dixit | I28: M/S ARIHANT INDUSTRIES | K28: 46175 | L28: sent | M28: invoice | O28: 2026-07-01 | P28: 36/REW/27IN00019 | Q28: DALMIA POLYPRO INDUSTRIES PRIVATE LIMITED (27) | R28: 742675.1 | S28: 742675.1 | T28: Net 30 (Days) | U28: 27AAACD5406E1Z3 | V28: 16056735 | W28: 0 | X28: Marketplace (Plastic Waste) | Y28: Marketplace Sales (ReWerse)
H29: Neelesh Dixit | I29: RUNGTA GREENTECH LIMITED | K29: 46179 | L29: sent | M29: invoice | O29: 2026-07-05 | P29: 36/REW/27IN00020 | Q29: DALMIA POLYPRO INDUSTRIES PRIVATE LIMITED (27) | R29: 729032.8 | S29: 729032.8 | T29: Net 30 (Days) | U29: 27AAACD5406E1Z3 | V29: 16056735 | W29: 0 | X29: Marketplace (Plastic Waste) | Y29: Marketplace Sales (ReWerse)
H30: Gitika | I30: TAPADIA POLYESTERS PRIVATE LIMITED | K30: 46187 | L30: sent | M30: invoice | O30: 2026-07-13 | P30: 36/REW/27IN00021 | Q30: DALMIA POLYPRO INDUSTRIES PRIVATE LIMITED (27) | R30: 709064.6 | S30: 709064.6 | T30: Net 30 (Days) | U30: 27AAACD5406E1Z3 | V30: 16056735 | W30: 0 | X30: Marketplace (Plastic Waste) | Y30: Marketplace Sales (ReWerse)
H31: Ramesh G | I31: KANNAPIRAN POLYMERS LIMITED | K31: 46188 | L31: sent | M31: invoice | O31: 2026-07-09 | P31: 36/REW/27IN00023 | Q31: NATIONAL FIBRES PRIVATE LIMITED | R31: 611915.9 | S31: 611915.9 | T31: Net 30 (Days) | U31: 26AAICN2675D1ZG | V31: 5000000 | W31: 0 | X31: Marketplace (Plastic Waste) | Y31: Marketplace Sales (ReWerse)
H32: Ramesh G | I32: Shree Renga Polymers | K32: 46188 | L32: sent | M32: invoice | O32: 2026-07-14 | P32: 36/REW/27IN00022 | Q32: DALMIA POLYPRO INDUSTRIES PRIVATE LIMITED (27) | R32: 714246.5 | S32: 714246.5 | T32: Net 30 (Days) | U32: 27AAACD5406E1Z3 | V32: 16056735 | W32: 0 | X32: Marketplace (Plastic Waste) | Y32: Marketplace Sales (ReWerse)
H33: Gitika | I33: EMINENT DEALERS PVT LTD | K33: 46192 | L33: sent | M33: invoice | O33: 2026-07-13 | P33: 36/REW/27IN00024 | Q33: NATIONAL FIBRES PRIVATE LIMITED | R33: 692244.1 | S33: 692244.1 | T33: Net 30 (Days) | U33: 26AAICN2675D1ZG | V33: 5000000 | W33: 0 | X33: Marketplace (Plastic Waste) | Y33: Marketplace Sales (ReWerse)
H34: Shashank | I34: Dalmia Polypro Industries Private Limited | K34: 46194 | L34: sent | M34: invoice | O34: 2026-07-20 | P34: 36/REW/27IN00025 | Q34: DALMIA POLYPRO INDUSTRIES PRIVATE LIMITED (27) | R34: 682645.6 | S34: 682645.6 | T34: Net 30 (Days) | U34: 27AAACD5406E1Z3 | V34: 16056735 | W34: 0 | X34: Marketplace (Plastic Waste) | Y34: Marketplace Sales (ReWerse)
H35: Shashank | I35: UMA PLASTIC | K35: 46188 | L35: overdue | M35: invoice | N35: 3 | O35: 2026-06-18 | P35: 27/MET/27IN00003 | Q35: VINAYAK METAL AND ALLOYS PRIVATE LIMITED | R35: 38274.6 | S35: 2258248.6 | T35: Net 1 (Day) | U35: 36AAGCV9303A1ZK | V35: 2300000 | W35: 5319.09 | X35: Marketplace (Metal Waste) | Y35: Marketplace Sales (Metal)
H36: Ramesh G | I36: MANJUSHREE TECHNOPACK LIMITED
H37: Gitika | I37: Amaani Polyflakes
H38: Ramesh G | I38: J B ECOTEX LIMITED
H39: Shashank | I39: GOPAL PLASTIC
H40: Gitika | I40: SAHEB FIBRE PRIVATE LIMITED
H41: Shashank | I41: GOKUL PLASTIC
H42: Ramesh G | I42: SHREE RENGA POLYESTER PRIVATE LIMITED
H43: Ramesh G | I43: RECRAFT PROCESSING PRIVATE LIMITED
H44: Neelesh Dixit | I44: Apex International
H45: Pankaj | I45: ELITE INDUSTRIES
H46: Shashank | I46: SAMRUDDHI INDUSTRIES
H47: Shashank | I47: SAARK INDUSTRIES
... H59: Neelesh Dixit | I59: JAINARAIN FABTECH LIMITED

Sheet Last year's
E2: Particulars | F2: Amount | K2: Particulars | L2: Amount
E3: Provision for Credit Notes from Aggregators as on 31st Mar-2026 | F3: 1687476 | K3: Marketplace DN, CN and Expense Provisions | 31-03-2026 | L3: 411245
E4: Accounted in this Year | F4: =F8 -> 1839056.3 | K4: Accounted in FY 26-27 | L4: =L8 -> 105923.5
E5: NO DN value | F5: 0 | K5: NO DN value | L5: 0
F6: =F3-F4-F5 -> -151580.3 | K6: Closing Provision | L6: =L3-L4-L5 -> 305321.5
B8: Debit note Pertaining to FY 2026-27 | F8: =SUBTOTAL(9,F10:F1048576) -> 1839056.3 | H8: Credit note Pertaining to FY 25-26 | L8: =SUBTOTAL(9,L10:L39) -> 105923.5 | N8: FY 24-25 Logistic Bills accounted Fy 26-27
B9: SO Number | C9: Debit Note Date | D9: Debit Note Number | E9: Vendor Name | F9: SubTotal | H9: SO Number | I9: Credit Note Date | J9: Credit Note Number | K9: Customer Name | L9: CN Amount | N9: Bill Date | O9: Bill Number | P9: PurchaseOrder | Q9: Vendor Name | R9: Amount
B10: SH122521013 | C10: 46162 | D10: Penalty Charges | E10: M/S HINDALCO INDUSTRIES LIMITED | F10: 5064.05 | H10: SH02261907 | I10: 46114 | J10: 36/REW/27CN00001 | K10: DALMIA POLYPRO INDUSTRIES PRIVATE LIMITED (27) | L10: 4788
B11: SH122526022 | C11: 46162 | D11: Penalty Charges | E11: M/S HINDALCO INDUSTRIES LIMITED | F11: 5118.02 | H11: SH02261906 | I11: 46114 | J11: 36/REW/27CN00002 | K11: DALMIA POLYPRO INDUSTRIES PRIVATE LIMITED (27) | L11: 6559.68
B12: 25/PUN/INV0292 | C12: 46162 | D12: Supporting Service charges | E12: BLACK GOLD RECYCLING PRIVATE LIMITED | F12: 1807874.2 | H12: SH022621012 | I12: 46114 | J12: 36/REW/27CN00003 | K12: DALMIA POLYPRO INDUSTRIES PRIVATE LIMITED (27) | L12: 10391.92
B13: 25/PUN/INV0294 | C13: 46162 | D13: Supporting Service charges | E13: BLACK GOLD RECYCLING PRIVATE LIMITED | F13: 21000 | H13: SH03262901 | I13: 46118 | J13: 36/REW/27CN00018 | K13: DALMIA POLYPRO INDUSTRIES PRIVATE LIMITED (27) | L13: 2035.67
H14: SH022625015 | I14: 46118 | J14: 36/REW/27CN00004 | K14: DALMIA POLYPRO INDUSTRIES PRIVATE LIMITED (27) | L14: 1585.76
H15: SH03260306 | I15: 46118 | J15: 36/REW/27CN00008 | K15: DALMIA POLYPRO INDUSTRIES PRIVATE LIMITED (27) | L15: 1899.92
H16: SH03260308 | I16: 46118 | J16: 36/REW/27CN00010 | K16: DALMIA POLYPRO INDUSTRIES PRIVATE LIMITED (27) | L16: 4598
H17: SH03261502 | I17: 46118 | J17: 36/REW/27CN00012 | K17: DALMIA POLYPRO INDUSTRIES PRIVATE LIMITED (27) | L17: 2156
H18: SH03262205 | I18: 46118 | J18: 36/REW/27CN00015 | K18: DALMIA POLYPRO INDUSTRIES PRIVATE LIMITED (27) | L18: 3074.89
H19: SH03262801 | I19: 46118 | J19: 36/REW/27CN00017 | K19: DALMIA POLYPRO INDUSTRIES PRIVATE LIMITED (27) | L19: 4185.09
H20: SH022628020 | I20: 46118 | J20: 36/REW/27CN00007 | K20: DALMIA POLYPRO INDUSTRIES PRIVATE LIMITED (27) | L20: 4231.92
H21: SH03261204 | I21: 46118 | J21: 36/REW/27CN00011 | K21: DALMIA POLYPRO INDUSTRIES PRIVATE LIMITED (27) | L21: 5061.76
H22: SH03261708 | I22: 46118 | J22: 36/REW/27CN00014 | K22: DALMIA POLYPRO INDUSTRIES PRIVATE LIMITED (27) | L22: 8675.49
H23: SH03262409 | I23: 46118 | J23: 36/REW/27CN00016 | K23: DALMIA POLYPRO INDUSTRIES PRIVATE LIMITED (27) | L23: 4769.74
H24: SH032607010 | I24: 46118 | J24: 36/REW/27CN00009 | K24: DALMIA POLYPRO INDUSTRIES PRIVATE LIMITED (27) | L24: 10677.92
H25: SH03261503 | I25: 46118 | J25: 36/REW/27CN00013 | K25: DALMIA POLYPRO INDUSTRIES PRIVATE LIMITED (27) | L25: 7651.6
... H31: SH03263106 | I31: 46181 | J31: 36/REW/27CN00025 | K31: DALMIA POLYPRO INDUSTRIES PRIVATE LIMITED (27) | L31: 2398.9
L43: =#REF!-#REF!-#REF! -> #REF!

Sheet Revenue - Reco
C4: Sales - Reconciliation | F4: Purchases - Reconciliation | I4: Logistic Cost- Reconciliation
C5: Particulars | D5: Amount | F5: Particulars | G5: Amount | I5: Particulars | J5: Amount
C6: Net Revenue as per MIS Report | D6: =Details!AY90 -> 15263713 | F6: Net Purchases as per MIS Report | G6: =Details!O90 -> 11824275 | I6: Net Logistic as per MIS Report | J6: =Details!AC90 -> 0
C7: Credit Notes issued in FY-25 pertaining to FY-24 | D7: =Details!AY94 -> -105923.5 | F7: Debit Notes issued in FY-25 pertaining to FY-24 | G7: =-Details!O95 -> 151580.3 | I7: Logistic Bills issued in FY-25 pertaining to FY-24 | J7: =Details!AC94 -> 0
F8: DN Provision in Zoho FY 24-25 | G8: =Details!O93 -> 0 | I8: Logistic Provision in Zoho FY 24-25 | J8: =Details!AC95 -> 0
C9: Reconciliation | D9: =Details!AY97 -> -1913770 | F9: JV for Last year Bills | G9: 0 | J9: =SUM(J6:J8) -> 0
C10: CN Provision in Zoho FY 24-25 | D10: =-Details!AY95 -> 0 | F10: Last year bills considered this year | G10: =-'Recon Items'!N18 -> 0 | I10: Logistic Cost as per P&L Report (Zoho Books) | J10: =Details!AC91 -> 0
D11: =SUM(D6:D10) -> 13244020 | F11: Final - Variance | G11: ='Recon Items'!G18 -> 0 | I11: Final - Variance | J11: =J9-J10 -> 0
C12: Revenue as per P&L Report (Zoho Books) | D12: =Details!AY91 -> 13655265 | G12: =SUM(G6:G11) -> 11975855
C13: Final - Variance | D13: =D11-D12 -> -411245.09 | F13: Cost as per P&L Report (Zoho Books) | G13: =Details!O91 -> 10645655
F14: Final - Variance | G14: =G12-G13-'Recon Items'!C18 -> -0.02
